{
  "type": "Feature",
  "properties": {
    "gn:admin1_code":"55",
    "gn:admin2_code":"LE",
    "gn:admin3_code":"24132",
    "gn:asciiname":"La Omanuela",
    "gn:country_code":"ES",
    "gn:dem":1046,
    "gn:feature_class":"P",
    "gn:feature_code":"PPL",
    "gn:name":"La Oma\u00f1uela",
    "gn:population":0,
    "gn:timezone":"Europe/Madrid",
    "iso:country":"ES",
    "wof:name":"La Omanuela",
    "wof:placetype":"locality"
},
  "geometry": {"coordinates":[-5.98935,42.77761],"type":"Point"}
}