{
  "type": "Feature",
  "properties": {
    "gn:admin1_code":"32",
    "gn:admin3_code":"31017",
    "gn:asciiname":"Olague",
    "gn:country_code":"ES",
    "gn:dem":553,
    "gn:feature_class":"P",
    "gn:feature_code":"PPL",
    "gn:name":"Olag\u00fce",
    "gn:population":0,
    "gn:timezone":"Europe/Madrid",
    "iso:country":"ES",
    "name:und_x_variant":[
        "Olag\u00fce"
    ],
    "wof:name":"Olague",
    "wof:placetype":"locality"
},
  "geometry": {"coordinates":[-1.6192,42.96343],"type":"Point"}
}