{
  "type": "Feature",
  "properties": {
    "gn:gn_country":"ES",
    "gn:gn_fcode":"PPL",
    "gn:gn_pop":0,
    "iso:country":"ES",
    "name:arg_x_preferred":[
        "Ars\u00e8guel"
    ],
    "name:ast_x_preferred":[
        "Ars\u00e8guel"
    ],
    "name:cat_x_preferred":[
        "Ars\u00e8guel"
    ],
    "name:ceb_x_preferred":[
        "Ars\u00e8guel"
    ],
    "name:deu_x_preferred":[
        "Ars\u00e8guel"
    ],
    "name:eng_x_preferred":[
        "Ars\u00e8guel"
    ],
    "name:eus_x_preferred":[
        "Ars\u00e8guel"
    ],
    "name:fin_x_preferred":[
        "Ars\u00e8guel"
    ],
    "name:fra_x_preferred":[
        "Ars\u00e8guel"
    ],
    "name:hun_x_preferred":[
        "Ars\u00e8guel"
    ],
    "name:hye_x_preferred":[
        "\u0531\u0580\u057d\u0565\u0563\u0565\u056c"
    ],
    "name:ita_x_preferred":[
        "Ars\u00e8guel"
    ],
    "name:msa_x_preferred":[
        "Ars\u00e8guel"
    ],
    "name:nld_x_preferred":[
        "Ars\u00e8guel"
    ],
    "name:oci_x_preferred":[
        "Ars\u00e8guel"
    ],
    "name:pol_x_preferred":[
        "Ars\u00e8guel"
    ],
    "name:por_x_preferred":[
        "Ars\u00e8guel"
    ],
    "name:ron_x_preferred":[
        "Ars\u00e8guel"
    ],
    "name:rus_x_preferred":[
        "\u0410\u0440\u0441\u0435\u0433\u0435\u043b\u044c"
    ],
    "name:spa_x_preferred":[
        "Arseguell"
    ],
    "name:sqi_x_preferred":[
        "Ars\u00e8guel"
    ],
    "name:swe_x_preferred":[
        "Ars\u00e8guel"
    ],
    "name:ukr_x_preferred":[
        "\u0410\u0440\u0441\u0435\u0433\u0430\u043b"
    ],
    "name:uzb_x_preferred":[
        "Ars\u00e8guel"
    ],
    "name:vie_x_preferred":[
        "Ars\u00e8guel"
    ],
    "name:war_x_preferred":[
        "Ars\u00e8guel"
    ],
    "name:zho_x_preferred":[
        "\u963f\u5c14\u585e\u683c\u5c14"
    ],
    "qs_pg:aaroncc":"ES",
    "qs_pg:gn_country":"ES",
    "qs_pg:gn_fcode":"PPL",
    "qs_pg:gn_pop":0,
    "qs_pg:name":"Ars\u00e8guel",
    "qs_pg:name_adm0":"Espa\u00f1a",
    "qs_pg:name_adm1":"Catalunya",
    "qs_pg:photos":46,
    "qs_pg:photos_1k":9,
    "qs_pg:photos_9k":1,
    "qs_pg:photos_9r":2,
    "qs_pg:photos_all":46,
    "qs_pg:photos_sr":2,
    "qs_pg:pop_sr":0,
    "qs_pg:qs_pg_placetype":"locality",
    "qs_pg:qs_pg_placetype_gp":"Town",
    "qs_pg:woe_adm0":23424950,
    "woe:adm0_id":23424950,
    "woe:name_adm0":"Espa\u00f1a",
    "woe:name_adm1":"Catalunya",
    "woe:placetype":"Town",
    "wof:name":"Ars\u00e8guel",
    "wof:placetype":"locality"
},
  "geometry": {"coordinates":[1.58418,42.34998],"type":"Point"}
}