{
  "type": "Feature",
  "properties": {
    "gn:admin1_code":"58",
    "gn:admin2_code":"PO",
    "gn:admin3_code":"36054",
    "gn:asciiname":"Barrantes",
    "gn:country_code":"ES",
    "gn:dem":229,
    "gn:feature_class":"P",
    "gn:feature_code":"PPLL",
    "gn:name":"Barrantes",
    "gn:population":0,
    "gn:timezone":"Europe/Madrid",
    "iso:country":"ES",
    "name:glg_x_historical":[
        "Barrantes"
    ],
    "name:glg_x_preferred":[
        "Barrantes"
    ],
    "wof:name":"Barrantes",
    "wof:placetype":"locality"
},
  "geometry": {"coordinates":[-8.76228,42.02404],"type":"Point"}
}