{
  "type": "Feature",
  "properties": {
    "gn:admin1_code":"34",
    "gn:admin2_code":"O",
    "gn:admin3_code":"33001",
    "gn:asciiname":"Abaniella",
    "gn:country_code":"ES",
    "gn:dem":702,
    "gn:feature_class":"P",
    "gn:feature_code":"PPL",
    "gn:name":"Abaniella",
    "gn:population":0,
    "gn:timezone":"Europe/Madrid",
    "iso:country":"ES",
    "wof:name":"Abaniella",
    "wof:placetype":"locality"
},
  "geometry": {"coordinates":[-6.61572,43.21979],"type":"Point"}
}