{
  "type": "Feature",
  "properties": {
    "gn:admin1_code":"27",
    "gn:admin2_code":"LO",
    "gn:admin3_code":"26123",
    "gn:asciiname":"El Redal",
    "gn:country_code":"ES",
    "gn:dem":534,
    "gn:feature_class":"P",
    "gn:feature_code":"PPL",
    "gn:name":"El Redal",
    "gn:population":187,
    "gn:timezone":"Europe/Madrid",
    "iso:country":"ES",
    "wof:name":"El Redal",
    "wof:placetype":"locality",
    "wof:population":187
},
  "geometry": {"coordinates":[-2.20204,42.33746],"type":"Point"}
}