{
  "type": "Feature",
  "properties": {
    "gn:admin1_code":"27",
    "gn:admin2_code":"LO",
    "gn:admin3_code":"26123",
    "gn:asciiname":"El Redal",
    "gn:country_code":"ES",
    "gn:dem":534,
    "gn:feature_class":"P",
    "gn:feature_code":"PPL",
    "gn:name":"El Redal",
    "gn:population":187,
    "gn:timezone":"Europe/Madrid",
    "iso:country":"ES",
    "name:arg_x_preferred":[
        "El Redal"
    ],
    "name:ast_x_preferred":[
        "El Redal"
    ],
    "name:cat_x_preferred":[
        "El Redal"
    ],
    "name:ceb_x_preferred":[
        "El Redal"
    ],
    "name:eus_x_preferred":[
        "El Redal"
    ],
    "name:fra_x_preferred":[
        "El Redal"
    ],
    "name:hun_x_preferred":[
        "El Redal"
    ],
    "name:hye_x_preferred":[
        "\u0537\u056c \u054c\u0565\u0564\u0561\u056c"
    ],
    "name:ita_x_preferred":[
        "El Redal"
    ],
    "name:kaz_x_preferred":[
        "\u042d\u043b\u044c-\u0420\u0435\u0434\u0430\u043b\u044c"
    ],
    "name:msa_x_preferred":[
        "El Redal"
    ],
    "name:nld_x_preferred":[
        "El Redal"
    ],
    "name:oci_x_preferred":[
        "El Redal"
    ],
    "name:pol_x_preferred":[
        "El Redal"
    ],
    "name:por_x_preferred":[
        "El Redal"
    ],
    "name:rus_x_preferred":[
        "\u042d\u043b\u044c-\u0420\u0435\u0434\u0430\u043b\u044c"
    ],
    "name:spa_x_preferred":[
        "El Redal"
    ],
    "name:swe_x_preferred":[
        "El Redal"
    ],
    "name:ukr_x_preferred":[
        "\u0415\u043b\u044c-\u0420\u0435\u0434\u0430\u043b\u044c"
    ],
    "name:uzb_x_preferred":[
        "El Redal"
    ],
    "name:vie_x_preferred":[
        "El Redal"
    ],
    "name:war_x_preferred":[
        "El Redal"
    ],
    "name:zho_x_preferred":[
        "\u57c3\u5c14\u96f7\u8fbe\u5c14"
    ],
    "wof:name":"El Redal",
    "wof:placetype":"locality",
    "wof:population":187
},
  "geometry": {"coordinates":[-2.20204,42.33746],"type":"Point"}
}