{
  "type": "Feature",
  "properties": {
    "gn:admin1_code":"57",
    "gn:admin2_code":"BA",
    "gn:admin3_code":"06158",
    "gn:asciiname":"Cabrahiga",
    "gn:cc2":"ES",
    "gn:country_code":"ES",
    "gn:dem":472,
    "gn:feature_class":"P",
    "gn:feature_code":"PPL",
    "gn:name":"Cabrahiga",
    "gn:population":0,
    "gn:timezone":"Europe/Madrid",
    "iso:country":"ES",
    "name:und_x_variant":[
        "Cortijo Cabrahiga",
        "Cabrahiga"
    ],
    "wof:name":"Cabrahiga",
    "wof:placetype":"locality"
},
  "geometry": {"coordinates":[-6.43333,38.43333],"type":"Point"}
}