{
  "type": "Feature",
  "properties": {
    "gn:admin1_code":"54",
    "gn:admin2_code":"CU",
    "gn:admin3_code":"16149",
    "gn:asciiname":"Molinos de Papel",
    "gn:cc2":"ES",
    "gn:country_code":"ES",
    "gn:dem":1196,
    "gn:feature_class":"P",
    "gn:feature_code":"PPL",
    "gn:name":"Molinos de Papel",
    "gn:population":0,
    "gn:timezone":"Europe/Madrid",
    "iso:country":"ES",
    "name:und_x_variant":[
        "Molino de Papel",
        "Molinos de Papel"
    ],
    "wof:name":"Molinos de Papel",
    "wof:placetype":"locality"
},
  "geometry": {"coordinates":[-2.06667,40.08333],"type":"Point"}
}