{
  "type": "Feature",
  "properties": {
    "gn:country":"ES",
    "gn:fcode":"PPLA3",
    "gn:population":238,
    "iso:country":"ES",
    "name:arg_x_preferred":[
        "San Morales"
    ],
    "name:ast_x_preferred":[
        "San Morales"
    ],
    "name:cat_x_preferred":[
        "San Morales"
    ],
    "name:ceb_x_preferred":[
        "San Morales"
    ],
    "name:deu_x_preferred":[
        "San Morales"
    ],
    "name:eng_x_preferred":[
        "San Morales"
    ],
    "name:eus_x_preferred":[
        "San Morales"
    ],
    "name:fra_x_preferred":[
        "San Morales"
    ],
    "name:hun_x_preferred":[
        "San Morales"
    ],
    "name:ina_x_preferred":[
        "San Morales"
    ],
    "name:ita_x_preferred":[
        "San Morales"
    ],
    "name:kaz_x_preferred":[
        "\u0421\u0430\u043d-\u041c\u043e\u0440\u0430\u043b\u0435\u0441"
    ],
    "name:msa_x_preferred":[
        "San Morales"
    ],
    "name:nan_x_preferred":[
        "San Morales"
    ],
    "name:nld_x_preferred":[
        "San Morales"
    ],
    "name:oci_x_preferred":[
        "San Morales"
    ],
    "name:pol_x_preferred":[
        "San Morales"
    ],
    "name:por_x_preferred":[
        "San Morales"
    ],
    "name:rus_x_preferred":[
        "\u0421\u0430\u043d-\u041c\u043e\u0440\u0430\u043b\u0435\u0441"
    ],
    "name:spa_x_preferred":[
        "San Morales"
    ],
    "name:swe_x_preferred":[
        "San Morales"
    ],
    "name:ukr_x_preferred":[
        "\u0421\u0430\u043d-\u041c\u043e\u0440\u0430\u043b\u0435\u0441"
    ],
    "name:vie_x_preferred":[
        "San Morales"
    ],
    "name:war_x_preferred":[
        "San Morales"
    ],
    "name:zho_x_preferred":[
        "\u5723\u83ab\u62c9\u83b1\u65af"
    ],
    "qs_pg:aaroncc":"ES",
    "qs_pg:gn_country":"ES",
    "qs_pg:gn_fcode":"PPLA3",
    "qs_pg:gn_pop":238,
    "qs_pg:name":"San Morales",
    "qs_pg:name_adm0":"Espa\u00f1a",
    "qs_pg:name_adm1":"Castilla y Le\u00f3n",
    "qs_pg:photos_9k":1,
    "qs_pg:photos_9r":1,
    "qs_pg:photos_all":1,
    "qs_pg:photos_sr":0,
    "qs_pg:pop_sr":2,
    "qs_pg:qs_pg_placetype":"locality",
    "qs_pg:qs_pg_placetype_gp":"Town",
    "qs_pg:woe_adm0":23424950,
    "woe:adm0_id":23424950,
    "woe:name_adm0":"Espa\u00f1a",
    "woe:name_adm1":"Castilla y Le\u00f3n",
    "woe:placetype":"Town",
    "wof:name":"San Morales",
    "wof:placetype":"locality",
    "wof:population":238
},
  "geometry": {"coordinates":[-5.50234,40.99358],"type":"Point"}
}