{
  "type": "Feature",
  "properties": {
    "gn:country":"ES",
    "gn:fcode":"PPLA3",
    "gn:population":216,
    "iso:country":"ES",
    "name:arg_x_preferred":[
        "Villamol"
    ],
    "name:cat_x_preferred":[
        "Villamol"
    ],
    "name:ceb_x_preferred":[
        "Villamol"
    ],
    "name:che_x_preferred":[
        "\u0412\u0438\u043b\u044c\u044f\u043c\u043e\u043b\u044c"
    ],
    "name:eng_x_preferred":[
        "Villamol"
    ],
    "name:epo_x_preferred":[
        "Villamol"
    ],
    "name:eus_x_preferred":[
        "Villamol"
    ],
    "name:fra_x_preferred":[
        "Villamol"
    ],
    "name:gle_x_preferred":[
        "Villamol"
    ],
    "name:glg_x_preferred":[
        "Villamol"
    ],
    "name:haw_x_preferred":[
        "Villamol"
    ],
    "name:hun_x_preferred":[
        "Villamol"
    ],
    "name:ido_x_preferred":[
        "Villamol"
    ],
    "name:ile_x_preferred":[
        "Villamol"
    ],
    "name:ina_x_preferred":[
        "Villamol"
    ],
    "name:ita_x_preferred":[
        "Villamol"
    ],
    "name:lld_x_preferred":[
        "Villamol"
    ],
    "name:ltz_x_preferred":[
        "Villamol"
    ],
    "name:msa_x_preferred":[
        "Villamol"
    ],
    "name:nan_x_preferred":[
        "Villamol"
    ],
    "name:nld_x_preferred":[
        "Villamol"
    ],
    "name:nob_x_preferred":[
        "Villamol"
    ],
    "name:oci_x_preferred":[
        "Villamol"
    ],
    "name:pol_x_preferred":[
        "Villamol"
    ],
    "name:por_x_preferred":[
        "Villamol"
    ],
    "name:rus_x_preferred":[
        "\u0412\u0438\u043b\u044c\u044f\u043c\u043e\u043b\u044c"
    ],
    "name:spa_x_preferred":[
        "Villamol"
    ],
    "name:swe_x_preferred":[
        "Villamol"
    ],
    "name:tat_x_preferred":[
        "\u0412\u0438\u043b\u044c\u044f\u043c\u043e\u043b\u044c"
    ],
    "name:tpi_x_preferred":[
        "Villamol"
    ],
    "name:ukr_x_preferred":[
        "\u0412\u0456\u043b\u044c\u044f\u043c\u043e\u043b\u044c"
    ],
    "name:vec_x_preferred":[
        "Villamol"
    ],
    "name:vie_x_preferred":[
        "Villamol"
    ],
    "name:war_x_preferred":[
        "Villamol"
    ],
    "name:zho_x_preferred":[
        "\u6bd4\u5229\u4e9a\u83ab\u5c14"
    ],
    "qs_pg:aaroncc":"ES",
    "qs_pg:gn_country":"ES",
    "qs_pg:gn_fcode":"PPLA3",
    "qs_pg:gn_pop":216,
    "qs_pg:name":"Villamol",
    "qs_pg:name_adm0":"Espa\u00f1a",
    "qs_pg:name_adm1":"Castilla y Le\u00f3n",
    "qs_pg:photos_9r":0,
    "qs_pg:photos_sr":0,
    "qs_pg:pop_sr":2,
    "qs_pg:qs_pg_placetype":"locality",
    "qs_pg:qs_pg_placetype_gp":"Town",
    "qs_pg:woe_adm0":23424950,
    "woe:adm0_id":23424950,
    "woe:name_adm0":"Espa\u00f1a",
    "woe:name_adm1":"Castilla y Le\u00f3n",
    "woe:placetype":"Town",
    "wof:name":"Villamol",
    "wof:placetype":"locality",
    "wof:population":216
},
  "geometry": {"coordinates":[-5.04832,42.42766],"type":"Point"}
}