{
  "type": "Feature",
  "properties": {
    "iso:country":"ES",
    "name:spa_x_preferred":[
        "La Colonia del Palau"
    ],
    "name:und_x_variant":[
        "El Palau"
    ],
    "name:unk_x_variant":[
        "La Colonia del Palau"
    ],
    "qs:gn_adm0_cc":"ES",
    "qs:gn_local":3110885,
    "qs:gn_nam_loc":"Sant Andreu de la Barca, Catalunya, ES",
    "qs:gn_namadm1":"56",
    "qs:local_max":448,
    "qs:local_sum":448,
    "qs:localhoods":1,
    "qs:name":"La Colonia del Palau",
    "qs:name_adm0":"Espa\u00f1a",
    "qs:name_adm1":"Catalunya",
    "qs:name_adm2":"Barcelona",
    "qs:name_lau":"Sant Andreu de la Barca",
    "qs:name_local":"Sant Andreu de la Barca",
    "qs:photo_max":88,
    "qs:photo_sum":448,
    "qs:placetype":"Suburb",
    "qs:quad_count":47,
    "qs:woe_adm0":23424950,
    "qs:woe_adm1":12578034,
    "qs:woe_adm2":12602124,
    "qs:woe_lau":12693572,
    "qs:woe_local":772628,
    "qs:woe_ver":"7.10.0",
    "wof:lang":[
        "spa"
    ],
    "wof:name":"La Colonia del Palau",
    "wof:placetype":"neighbourhood"
},
  "geometry": {"coordinates":[1.967604,41.454598],"type":"Point"}
}