{
  "type": "Feature",
  "properties": {
    "gn:country":"ES",
    "gn:fcode":"PPL",
    "gn:population":123,
    "iso:country":"ES",
    "name:eng_x_preferred":[
        "Carbajal de Fuentes"
    ],
    "name:fra_x_preferred":[
        "Carbajal de Fuentes"
    ],
    "name:nld_x_preferred":[
        "Carbajal de Fuentes"
    ],
    "name:spa_x_preferred":[
        "Carbajal de Fuentes"
    ],
    "name:swe_x_preferred":[
        "Carbajal de Fuentes"
    ],
    "name:und_x_variant":[
        "Carbajal"
    ],
    "qs_pg:aaroncc":"ES",
    "qs_pg:gn_country":"ES",
    "qs_pg:gn_fcode":"PPL",
    "qs_pg:gn_pop":123,
    "qs_pg:name":"Carbajal de Fuentes",
    "qs_pg:name_adm0":"Espa\u00f1a",
    "qs_pg:name_adm1":"Castilla y Le\u00f3n",
    "qs_pg:photos_9r":0,
    "qs_pg:photos_sr":0,
    "qs_pg:pop_sr":1,
    "qs_pg:qs_pg_placetype":"locality",
    "qs_pg:qs_pg_placetype_gp":"Town",
    "qs_pg:woe_adm0":23424950,
    "woe:adm0_id":23424950,
    "woe:name_adm0":"Espa\u00f1a",
    "woe:name_adm1":"Castilla y Le\u00f3n",
    "woe:placetype":"Town",
    "wof:name":"Carbajal de Fuentes",
    "wof:placetype":"locality",
    "wof:population":123
},
  "geometry": {"coordinates":[-5.45806,42.18263],"type":"Point"}
}