{
  "type": "Feature",
  "properties": {
    "gn:admin1_code":"32",
    "gn:admin3_code":"31121",
    "gn:asciiname":"Arguinariz",
    "gn:country_code":"ES",
    "gn:dem":674,
    "gn:feature_class":"P",
    "gn:feature_code":"PPL",
    "gn:name":"Argui\u00f1\u00e1riz",
    "gn:population":0,
    "gn:timezone":"Europe/Madrid",
    "iso:country":"ES",
    "wof:name":"Arguinariz",
    "wof:placetype":"locality"
},
  "geometry": {"coordinates":[-1.86098,42.74298],"type":"Point"}
}