{
  "type": "Feature",
  "properties": {
    "gn:admin1_code":"55",
    "gn:admin2_code":"P",
    "gn:admin3_code":"34032",
    "gn:asciiname":"Cuillas del Valle",
    "gn:country_code":"ES",
    "gn:dem":750,
    "gn:feature_class":"P",
    "gn:feature_code":"PPL",
    "gn:name":"Cuillas del Valle",
    "gn:population":0,
    "gn:timezone":"Europe/Madrid",
    "iso:country":"ES",
    "wof:name":"Cuillas del Valle",
    "wof:placetype":"locality"
},
  "geometry": {"coordinates":[-4.00921,42.78915],"type":"Point"}
}