{
  "type": "Feature",
  "properties": {
    "gn:admin1_code":"31",
    "gn:admin2_code":"MU",
    "gn:admin3_code":"30006",
    "gn:asciiname":"Los Allozos",
    "gn:country_code":"ES",
    "gn:dem":566,
    "gn:feature_class":"P",
    "gn:feature_code":"PPL",
    "gn:name":"Los Allozos",
    "gn:population":0,
    "gn:timezone":"Europe/Madrid",
    "iso:country":"ES",
    "name:und_x_variant":[
        "Caser\u00edo Los Allozos",
        "Los Allozos"
    ],
    "wof:name":"Los Allozos",
    "wof:placetype":"locality"
},
  "geometry": {"coordinates":[-1.61053,37.77429],"type":"Point"}
}