{
  "type": "Feature",
  "properties": {
    "gn:admin1_code":"60",
    "gn:admin2_code":"V",
    "gn:admin3_code":"46099",
    "gn:asciiname":"Ral de Abajo",
    "gn:cc2":"ES",
    "gn:country_code":"ES",
    "gn:dem":377,
    "gn:feature_class":"P",
    "gn:feature_code":"PPL",
    "gn:name":"Ral de Abajo",
    "gn:population":0,
    "gn:timezone":"Europe/Madrid",
    "iso:country":"ES",
    "name:und_x_variant":[
        "Caser\u00edo Ral de Abajo",
        "Ral de Abajo"
    ],
    "wof:name":"Ral de Abajo",
    "wof:placetype":"locality"
},
  "geometry": {"coordinates":[-0.98333,39.26667],"type":"Point"}
}