{
  "type": "Feature",
  "properties": {
    "gn:admin1_code":"31",
    "gn:admin2_code":"MU",
    "gn:admin3_code":"30034",
    "gn:asciiname":"Cuesta Alta",
    "gn:country_code":"ES",
    "gn:dem":341,
    "gn:feature_class":"P",
    "gn:feature_code":"PPL",
    "gn:name":"Cuesta Alta",
    "gn:population":0,
    "gn:timezone":"Europe/Madrid",
    "iso:country":"ES",
    "name:und_x_variant":[
        "Caser\u00edo Cuesta Alta",
        "Cortijos de la Cuesta Alta",
        "Cuesta Alta"
    ],
    "wof:name":"Cuesta Alta",
    "wof:placetype":"locality"
},
  "geometry": {"coordinates":[-1.41451,38.16608],"type":"Point"}
}