{
  "type": "Feature",
  "properties": {
    "gn:gn_country":"ES",
    "gn:gn_fcode":"PPLA3",
    "gn:gn_pop":267,
    "gn:population":267,
    "iso:country":"ES",
    "name:ara_x_preferred":[
        "\u0633\u0627\u0644\u0641\u0627\u062a\u064a\u064a\u0631\u0627 \u062f\u064a \u0625\u0633\u0643\u0627"
    ],
    "name:arg_x_preferred":[
        "Salvatierra d'Esca"
    ],
    "name:cat_x_preferred":[
        "Salvatierra de Esca"
    ],
    "name:deu_x_preferred":[
        "Salvatierra de Esca"
    ],
    "name:eng_x_preferred":[
        "Salvatierra de Esca"
    ],
    "name:eus_x_preferred":[
        "Salbaterra Ezka"
    ],
    "name:fra_x_preferred":[
        "Salvatierra de Esca"
    ],
    "name:glg_x_preferred":[
        "Salvatierra de Esca"
    ],
    "name:hun_x_preferred":[
        "Salvatierra de Esca"
    ],
    "name:hye_x_preferred":[
        "\u054d\u0561\u056c\u057e\u0561\u057f\u056b\u0565\u057c\u0561 \u0564\u0565 \u0537\u057d\u056f\u0561"
    ],
    "name:ita_x_preferred":[
        "Salvatierra de Esca"
    ],
    "name:kaz_x_preferred":[
        "\u0421\u0430\u043b\u044c\u0432\u0430\u0442\u044c\u0435\u0440\u0440\u0430-\u0434\u0435-\u042d\u0441\u043a\u0430"
    ],
    "name:msa_x_preferred":[
        "Salvatierra de Esca"
    ],
    "name:nan_x_preferred":[
        "Salvatierra de Esca"
    ],
    "name:nld_x_preferred":[
        "Salvatierra de Esca"
    ],
    "name:oci_x_preferred":[
        "Salvatierra de Esca"
    ],
    "name:pol_x_preferred":[
        "Salvatierra de Esca"
    ],
    "name:por_x_preferred":[
        "Salvatierra de Esca"
    ],
    "name:rus_x_preferred":[
        "\u0421\u0430\u043b\u044c\u0432\u0430\u0442\u044c\u0435\u0440\u0440\u0430-\u0434\u0435-\u042d\u0441\u043a\u0430"
    ],
    "name:spa_x_preferred":[
        "Salvatierra de Esca"
    ],
    "name:swe_x_preferred":[
        "Salvatierra de Esca"
    ],
    "name:ukr_x_preferred":[
        "\u0421\u0430\u043b\u044c\u0432\u0430\u0442\u044c\u0454\u0440\u0440\u0430-\u0434\u0435-\u0415\u0441\u043a\u0430"
    ],
    "name:unk_x_variant":[
        "Salvatierra"
    ],
    "name:uzb_x_preferred":[
        "Salvatierra de Esca"
    ],
    "name:vie_x_preferred":[
        "Salvatierra de Esca"
    ],
    "name:war_x_preferred":[
        "Salvatierra de Esca"
    ],
    "name:zho_x_preferred":[
        "\u8428\u5c14\u74e6\u94c1\u62c9\u5fb7\u57c3\u65af\u5361"
    ],
    "qs_pg:aaroncc":"ES",
    "qs_pg:gn_country":"ES",
    "qs_pg:gn_fcode":"PPLA3",
    "qs_pg:gn_pop":267,
    "qs_pg:name":"Salvatierra de Esca",
    "qs_pg:name_adm0":"Espa\u00f1a",
    "qs_pg:name_adm1":"Arag\u00f3n",
    "qs_pg:photos_9k":1,
    "qs_pg:photos_9r":1,
    "qs_pg:photos_all":1,
    "qs_pg:photos_sr":0,
    "qs_pg:pop_sr":2,
    "qs_pg:qs_pg_placetype":"locality",
    "qs_pg:qs_pg_placetype_gp":"Town",
    "qs_pg:woe_adm0":23424950,
    "woe:adm0_id":23424950,
    "woe:name_adm0":"Espa\u00f1a",
    "woe:name_adm1":"Arag\u00f3n",
    "woe:placetype":"Town",
    "wof:name":"Salvatierra de Esca",
    "wof:placetype":"locality",
    "wof:population":267
},
  "geometry": {"coordinates":[-1.00475,42.67002],"type":"Point"}
}