{
  "type": "Feature",
  "properties": {
    "gn:admin1_code":"58",
    "gn:admin2_code":"C",
    "gn:admin3_code":"15080",
    "gn:asciiname":"Porta",
    "gn:cc2":"ES",
    "gn:country_code":"ES",
    "gn:dem":525,
    "gn:feature_class":"P",
    "gn:feature_code":"PPL",
    "gn:name":"Porta",
    "gn:population":0,
    "gn:timezone":"Europe/Madrid",
    "iso:country":"ES",
    "name:und_x_variant":[
        "San Pedro",
        "Porta"
    ],
    "wof:name":"Porta",
    "wof:placetype":"locality"
},
  "geometry": {"coordinates":[-8.01667,43.03333],"type":"Point"}
}