{
  "type": "Feature",
  "properties": {
    "gn:admin1_code":"58",
    "gn:admin2_code":"C",
    "gn:admin3_code":"15080",
    "gn:asciiname":"Porta",
    "gn:cc2":"ES",
    "gn:country_code":"ES",
    "gn:dem":525,
    "gn:feature_class":"P",
    "gn:feature_code":"PPL",
    "gn:name":"Porta",
    "gn:population":0,
    "gn:timezone":"Europe/Madrid",
    "iso:country":"ES",
    "name:bre_x_preferred":[
        "Porta"
    ],
    "name:cat_x_preferred":[
        "Porta"
    ],
    "name:ceb_x_preferred":[
        "Porta"
    ],
    "name:ces_x_preferred":[
        "Porta"
    ],
    "name:deu_x_preferred":[
        "Porta"
    ],
    "name:glg_x_preferred":[
        "Porta"
    ],
    "name:hun_x_preferred":[
        "Porta"
    ],
    "name:ita_x_preferred":[
        "Porta"
    ],
    "name:jpn_x_preferred":[
        "\u30dd\u30eb\u30bf"
    ],
    "name:kor_x_preferred":[
        "\ud3ec\ub974\ud0c0"
    ],
    "name:oci_x_preferred":[
        "P\u00f2rta"
    ],
    "name:pol_x_preferred":[
        "Porta"
    ],
    "name:por_x_preferred":[
        "Porta"
    ],
    "name:rus_x_preferred":[
        "\u041f\u043e\u0440\u0442\u0430"
    ],
    "name:slk_x_preferred":[
        "Porta"
    ],
    "name:spa_x_preferred":[
        "Porta"
    ],
    "name:swe_x_preferred":[
        "Porta"
    ],
    "name:ukr_x_preferred":[
        "\u041f\u043e\u0440\u0442\u0430"
    ],
    "name:und_x_variant":[
        "San Pedro",
        "Porta"
    ],
    "wof:name":"Porta",
    "wof:placetype":"locality"
},
  "geometry": {"coordinates":[-8.01667,43.03333],"type":"Point"}
}