{
  "type": "Feature",
  "properties": {
    "gn:admin1_code":"34",
    "gn:admin2_code":"O",
    "gn:admin3_code":"33036",
    "gn:asciiname":"Rotella",
    "gn:country_code":"ES",
    "gn:dem":246,
    "gn:feature_class":"P",
    "gn:feature_code":"PPL",
    "gn:name":"Rotella",
    "gn:population":0,
    "gn:timezone":"Europe/Madrid",
    "iso:country":"ES",
    "name:azb_x_preferred":[
        "\u0631\u0648\u062a\u0644\u0627"
    ],
    "name:bul_x_preferred":[
        "\u0420\u043e\u0442\u0435\u043b\u0430"
    ],
    "name:ceb_x_preferred":[
        "Rotella"
    ],
    "name:deu_x_preferred":[
        "Rotella"
    ],
    "name:epo_x_preferred":[
        "Rotella"
    ],
    "name:eus_x_preferred":[
        "Rotella"
    ],
    "name:fas_x_preferred":[
        "\u0631\u0648\u062a\u0644\u0627"
    ],
    "name:fra_x_preferred":[
        "Rotella"
    ],
    "name:hun_x_preferred":[
        "Rotella"
    ],
    "name:hye_x_preferred":[
        "\u054c\u0578\u057f\u0565\u056c\u0561"
    ],
    "name:ina_x_preferred":[
        "Rotella"
    ],
    "name:ita_x_preferred":[
        "Rotella"
    ],
    "name:jpn_x_preferred":[
        "\u30ed\u30c6\u30c3\u30e9"
    ],
    "name:kaz_x_preferred":[
        "\u0420\u043e\u0442\u0435\u043b\u043b\u0430"
    ],
    "name:lat_x_preferred":[
        "Rotella"
    ],
    "name:lmo_x_preferred":[
        "Rotella"
    ],
    "name:msa_x_preferred":[
        "Rotella"
    ],
    "name:nap_x_preferred":[
        "Rotella"
    ],
    "name:nld_x_preferred":[
        "Rotella"
    ],
    "name:pms_x_preferred":[
        "Rotella"
    ],
    "name:pol_x_preferred":[
        "Rotella"
    ],
    "name:por_x_preferred":[
        "Rotella"
    ],
    "name:ron_x_preferred":[
        "Rotella"
    ],
    "name:rus_x_preferred":[
        "\u0420\u043e\u0442\u0435\u043b\u043b\u0430"
    ],
    "name:spa_x_preferred":[
        "Rotella"
    ],
    "name:srp_x_preferred":[
        "\u0420\u043e\u0442\u0435\u043b\u0430"
    ],
    "name:tgl_x_preferred":[
        "Rotella"
    ],
    "name:ukr_x_preferred":[
        "\u0420\u043e\u0442\u0435\u043b\u043b\u0430"
    ],
    "name:uzb_x_preferred":[
        "Rotella"
    ],
    "name:vie_x_preferred":[
        "Rotella"
    ],
    "name:vol_x_preferred":[
        "Rotella"
    ],
    "name:war_x_preferred":[
        "Rotella"
    ],
    "name:zho_x_preferred":[
        "\u7f57\u6cf0\u62c9"
    ],
    "wof:name":"Rotella",
    "wof:placetype":"locality"
},
  "geometry": {"coordinates":[-4.89464,43.38474],"type":"Point"}
}