{
  "type": "Feature",
  "properties": {
    "gn:admin1_code":"34",
    "gn:admin2_code":"O",
    "gn:admin3_code":"33036",
    "gn:asciiname":"Rotella",
    "gn:country_code":"ES",
    "gn:dem":246,
    "gn:feature_class":"P",
    "gn:feature_code":"PPL",
    "gn:name":"Rotella",
    "gn:population":0,
    "gn:timezone":"Europe/Madrid",
    "iso:country":"ES",
    "wof:name":"Rotella",
    "wof:placetype":"locality"
},
  "geometry": {"coordinates":[-4.89464,43.38474],"type":"Point"}
}