{
  "type": "Feature",
  "properties": {
    "gn:admin1_code":"07",
    "gn:admin2_code":"PM",
    "gn:admin3_code":"07015",
    "gn:asciiname":"ses Truqueries",
    "gn:cc2":"ES",
    "gn:country_code":"ES",
    "gn:dem":28,
    "gn:feature_class":"P",
    "gn:feature_code":"PPL",
    "gn:name":"ses Truqueries",
    "gn:population":0,
    "gn:timezone":"Europe/Madrid",
    "iso:country":"ES",
    "wof:name":"ses Truqueries",
    "wof:placetype":"locality"
},
  "geometry": {"coordinates":[3.83333,40.01667],"type":"Point"}
}