{
  "type": "Feature",
  "properties": {
    "gn:admin1_code":"52",
    "gn:admin2_code":"HU",
    "gn:admin3_code":"22250",
    "gn:asciiname":"Cenarbe",
    "gn:country_code":"ES",
    "gn:dem":1180,
    "gn:feature_class":"P",
    "gn:feature_code":"PPL",
    "gn:name":"Cenarbe",
    "gn:population":0,
    "gn:timezone":"Europe/Madrid",
    "iso:country":"ES",
    "wof:name":"Cenarbe",
    "wof:placetype":"locality"
},
  "geometry": {"coordinates":[-0.51042,42.65528],"type":"Point"}
}