{
  "type": "Feature",
  "properties": {
    "gn:admin1_code":"CE",
    "gn:admin2_code":"CE",
    "gn:admin3_code":"51001",
    "gn:asciiname":"Las Cuevas",
    "gn:country_code":"ES",
    "gn:dem":67,
    "gn:feature_class":"P",
    "gn:feature_code":"PPLL",
    "gn:name":"Las Cuevas",
    "gn:population":0,
    "gn:timezone":"Europe/Madrid",
    "iso:country":"ES",
    "name:ceb_x_preferred":[
        "Las Cuevas"
    ],
    "name:deu_x_preferred":[
        "Las Cuevas"
    ],
    "name:nds_x_preferred":[
        "Las Cuevas"
    ],
    "name:spa_x_preferred":[
        "Las Cuevas"
    ],
    "name:swe_x_preferred":[
        "Las Cuevas"
    ],
    "wof:name":"Las Cuevas",
    "wof:placetype":"locality"
},
  "geometry": {"coordinates":[-5.28644,35.90152],"type":"Point"}
}