{
  "type": "Feature",
  "properties": {
    "gn:admin1_code":"58",
    "gn:admin2_code":"LU",
    "gn:admin3_code":"27058",
    "gn:asciiname":"Vilaesteva",
    "gn:country_code":"ES",
    "gn:dem":502,
    "gn:feature_class":"P",
    "gn:feature_code":"PPL",
    "gn:name":"Vilaesteva",
    "gn:population":0,
    "gn:timezone":"Europe/Madrid",
    "iso:country":"ES",
    "wof:name":"Vilaesteva",
    "wof:placetype":"locality"
},
  "geometry": {"coordinates":[-7.66245,42.66467],"type":"Point"}
}