{
  "type": "Feature",
  "properties": {
    "gn:admin1_code":"52",
    "gn:admin2_code":"HU",
    "gn:admin3_code":"22149",
    "gn:asciiname":"Jabarrillo",
    "gn:country_code":"ES",
    "gn:dem":614,
    "gn:feature_class":"P",
    "gn:feature_code":"PPL",
    "gn:name":"Jabarrillo",
    "gn:population":0,
    "gn:timezone":"Europe/Madrid",
    "iso:country":"ES",
    "name:und_x_variant":[
        "Javarrillo",
        "Jabarrillo"
    ],
    "wof:name":"Jabarrillo",
    "wof:placetype":"locality"
},
  "geometry": {"coordinates":[-0.64241,42.26957],"type":"Point"}
}