{
  "type": "Feature",
  "properties": {
    "gn:admin1_code":"51",
    "gn:admin2_code":"J",
    "gn:admin3_code":"23064",
    "gn:asciiname":"Navalcan",
    "gn:country_code":"ES",
    "gn:dem":1198,
    "gn:feature_class":"P",
    "gn:feature_code":"PPL",
    "gn:name":"Navalc\u00e1n",
    "gn:population":0,
    "gn:timezone":"Europe/Madrid",
    "iso:country":"ES",
    "name:und_x_variant":[
        "Caser\u00edo Navalc\u00e1n",
        "Navalc\u00e1n"
    ],
    "wof:name":"Navalcan",
    "wof:placetype":"locality"
},
  "geometry": {"coordinates":[-3.70589,37.53002],"type":"Point"}
}