{
  "type": "Feature",
  "properties": {
    "gn:admin1_code":"34",
    "gn:admin2_code":"O",
    "gn:admin3_code":"33011",
    "gn:asciiname":"Villar de Roguero",
    "gn:country_code":"ES",
    "gn:dem":1112,
    "gn:feature_class":"P",
    "gn:feature_code":"PPL",
    "gn:name":"Villar de Roguero",
    "gn:population":0,
    "gn:timezone":"Europe/Madrid",
    "iso:country":"ES",
    "wof:name":"Villar de Roguero",
    "wof:placetype":"locality"
},
  "geometry": {"coordinates":[-6.48764,43.03201],"type":"Point"}
}