{
  "type": "Feature",
  "properties": {
    "gn:admin1_code":"58",
    "gn:admin2_code":"LU",
    "gn:admin3_code":"27045",
    "gn:asciiname":"Cebrero",
    "gn:country_code":"ES",
    "gn:dem":1275,
    "gn:feature_class":"P",
    "gn:feature_code":"PPL",
    "gn:name":"Cebrero",
    "gn:population":0,
    "gn:timezone":"Europe/Madrid",
    "iso:country":"ES",
    "wof:name":"Cebrero",
    "wof:placetype":"locality"
},
  "geometry": {"coordinates":[-7.04304,42.7089],"type":"Point"}
}