{
  "type": "Feature",
  "properties": {
    "iso:country":"ES",
    "name:eng_x_preferred":[
        "Poligono Industrial Mi Malaga"
    ],
    "name:spa_x_preferred":[
        "Pol\u00edgono Industrial Mi M\u00e1laga"
    ],
    "wof:name":"Poligono Industrial Mi Malaga",
    "wof:placetype":"neighbourhood"
},
  "geometry": {"coordinates":[-4.47283943879502,36.66988203154099],"type":"Point"}
}