{
  "type": "Feature",
  "properties": {
    "gn:admin1_code":"51",
    "gn:admin2_code":"GR",
    "gn:admin3_code":"18013",
    "gn:asciiname":"Los Cortijillos",
    "gn:country_code":"ES",
    "gn:dem":375,
    "gn:feature_class":"P",
    "gn:feature_code":"PPL",
    "gn:name":"Los Cortijillos",
    "gn:population":0,
    "gn:timezone":"Europe/Madrid",
    "iso:country":"ES",
    "name:spa_x_preferred":[
        "Los Cortijillos"
    ],
    "name:und_x_variant":[
        "Caser\u00edo Los Cortijillos",
        "Los Cortijillos"
    ],
    "wof:name":"Los Cortijillos",
    "wof:placetype":"locality"
},
  "geometry": {"coordinates":[-4.12533,36.91231],"type":"Point"}
}