{
  "type": "Feature",
  "properties": {
    "gn:gn_country":"ES",
    "gn:gn_fcode":"PPLA3",
    "gn:gn_pop":379,
    "gn:population":379,
    "iso:country":"ES",
    "name:arg_x_preferred":[
        "Bobadilla del Campo"
    ],
    "name:cat_x_preferred":[
        "Bobadilla del Campo"
    ],
    "name:eng_x_preferred":[
        "Bobadilla del Campo"
    ],
    "name:eus_x_preferred":[
        "Bobadilla del Campo"
    ],
    "name:fas_x_preferred":[
        "\u0628\u0628\u0627\u062f\u06cc\u06cc\u0627 \u062f\u0644 \u06a9\u0627\u0645\u067e\u0648"
    ],
    "name:fra_x_preferred":[
        "Bobadilla del Campo"
    ],
    "name:hun_x_preferred":[
        "Bobadilla del Campo"
    ],
    "name:hye_x_preferred":[
        "\u0532\u0578\u0562\u0561\u0564\u056b\u056c\u0575\u0561 \u0564\u0565\u056c \u053f\u0561\u0574\u057a\u0578"
    ],
    "name:ina_x_preferred":[
        "Bobadilla del Campo"
    ],
    "name:ita_x_preferred":[
        "Bobadilla del Campo"
    ],
    "name:msa_x_preferred":[
        "Bobadilla del Campo"
    ],
    "name:nan_x_preferred":[
        "Bobadilla del Campo"
    ],
    "name:nld_x_preferred":[
        "Bobadilla del Campo"
    ],
    "name:oci_x_preferred":[
        "Bobadilla del Campo"
    ],
    "name:pol_x_preferred":[
        "Bobadilla del Campo"
    ],
    "name:por_x_preferred":[
        "Bobadilla del Campo"
    ],
    "name:rus_x_preferred":[
        "\u0411\u043e\u0431\u0430\u0434\u0438\u043b\u044c\u044f-\u0434\u0435\u043b\u044c-\u041a\u0430\u043c\u043f\u043e"
    ],
    "name:spa_x_preferred":[
        "Bobadilla del Campo"
    ],
    "name:swe_x_preferred":[
        "Bobadilla del Campo"
    ],
    "name:ukr_x_preferred":[
        "\u0411\u043e\u0431\u0430\u0434\u0456\u043b\u044c\u044f-\u0434\u0435\u043b\u044c-\u041a\u0430\u043c\u043f\u043e"
    ],
    "name:uzb_x_preferred":[
        "Bobadilla del Campo"
    ],
    "name:vie_x_preferred":[
        "Bobadilla del Campo"
    ],
    "name:war_x_preferred":[
        "Bobadilla del Campo"
    ],
    "name:zho_x_preferred":[
        "\u535a\u74e6\u8fea\u5229\u4e9a\u5fb7\u5c14\u574e\u6ce2"
    ],
    "qs_pg:aaroncc":"ES",
    "qs_pg:gn_country":"ES",
    "qs_pg:gn_fcode":"PPLA3",
    "qs_pg:gn_pop":379,
    "qs_pg:name":"Bobadilla del Campo",
    "qs_pg:name_adm0":"Espa\u00f1a",
    "qs_pg:name_adm1":"Castilla y Le\u00f3n",
    "qs_pg:photos_9r":0,
    "qs_pg:photos_sr":0,
    "qs_pg:pop_sr":2,
    "qs_pg:qs_pg_placetype":"locality",
    "qs_pg:qs_pg_placetype_gp":"Town",
    "qs_pg:woe_adm0":23424950,
    "woe:adm0_id":23424950,
    "woe:name_adm0":"Espa\u00f1a",
    "woe:name_adm1":"Castilla y Le\u00f3n",
    "woe:placetype":"Town",
    "wof:name":"Bobadilla del Campo",
    "wof:placetype":"locality",
    "wof:population":379
},
  "geometry": {"coordinates":[-5.02294,41.20432],"type":"Point"}
}