{
  "type": "Feature",
  "properties": {
    "gn:population":1498,
    "iso:country":"ES",
    "name:ara_x_preferred":[
        "\u0644\u0627\u063a\u0648\u0627\u0631\u062f\u064a\u0627"
    ],
    "name:arg_x_preferred":[
        "Laguardia"
    ],
    "name:ast_x_preferred":[
        "Laguardia"
    ],
    "name:azb_x_preferred":[
        "\u0644\u0627\u0642\u0648\u0627\u0631\u062f\u06cc\u0627"
    ],
    "name:bre_x_preferred":[
        "Guardia"
    ],
    "name:cat_x_preferred":[
        "Laguardia"
    ],
    "name:ceb_x_preferred":[
        "Laguardia"
    ],
    "name:deu_x_preferred":[
        "Laguardia"
    ],
    "name:eng_x_preferred":[
        "Laguardia"
    ],
    "name:eus_x_preferred":[
        "Guardia"
    ],
    "name:eus_x_variant":[
        "Biasteri"
    ],
    "name:fas_x_preferred":[
        "\u0644\u0627\u06af\u0648\u0627\u0631\u062f\u06cc\u0627"
    ],
    "name:fra_x_preferred":[
        "Laguardia"
    ],
    "name:glg_x_preferred":[
        "Laguardia"
    ],
    "name:heb_x_preferred":[
        "\u05dc\u05d2\u05d5\u05d5\u05d0\u05e8\u05d3\u05d9\u05d4"
    ],
    "name:hun_x_preferred":[
        "Laguardia"
    ],
    "name:hye_x_preferred":[
        "\u053c\u0561\u0563\u0578\u0582\u0561\u0580\u0564\u056b\u0561"
    ],
    "name:ita_x_preferred":[
        "Laguardia"
    ],
    "name:jpn_x_preferred":[
        "\u30e9\u30b0\u30a2\u30eb\u30c7\u30a3\u30a2"
    ],
    "name:lit_x_preferred":[
        "Lagvardija"
    ],
    "name:mkd_x_preferred":[
        "\u041b\u0430\u0433\u0432\u0430\u0440\u0434\u0438\u0458\u0430"
    ],
    "name:msa_x_preferred":[
        "Laguardia"
    ],
    "name:nld_x_preferred":[
        "Laguardia"
    ],
    "name:oci_x_preferred":[
        "Laguardia"
    ],
    "name:pam_x_preferred":[
        "Laguardia"
    ],
    "name:pol_x_preferred":[
        "Laguardia"
    ],
    "name:por_x_preferred":[
        "Laguardia"
    ],
    "name:rus_x_preferred":[
        "\u041b\u0430 \u0413\u0430\u0440\u0434\u0438\u0430"
    ],
    "name:sco_x_preferred":[
        "Laguardia"
    ],
    "name:spa_x_preferred":[
        "Laguardia"
    ],
    "name:swe_x_preferred":[
        "Laguardia"
    ],
    "name:tur_x_preferred":[
        "Laguardia"
    ],
    "name:ukr_x_preferred":[
        "\u041b\u0430\u0433\u0443\u0430\u0440\u0434\u0456\u044f"
    ],
    "name:vie_x_preferred":[
        "Laguardia"
    ],
    "name:war_x_preferred":[
        "Laguardia"
    ],
    "name:zho_x_preferred":[
        "\u62c9\u74dc\u5c14\u8fea\u4e9a"
    ],
    "qs:a0":"Espa\u00f1a",
    "qs:a1":"*Araba/\u00c1lava",
    "qs:a1r":"0Pa\u00eds Vasco",
    "qs:adm0":"Espa\u00f1a",
    "qs:la_lc":"*",
    "qs:level":"locality",
    "qs:loc":"Laguardia",
    "qs:loc_alt":"Laguardia",
    "qs:pop":0,
    "qs:type":"buffered point",
    "wd:wordcount":1165,
    "wof:name":"Laguardia",
    "wof:placetype":"locality",
    "wof:population":1498
},
  "geometry": {"coordinates":[-2.584773,42.553699],"type":"Point"}
}