{
  "type": "Feature",
  "properties": {
    "gn:gn_country":"ES",
    "gn:gn_fcode":"PPLA3",
    "gn:gn_pop":401,
    "gn:population":401,
    "iso:country":"ES",
    "name:arg_x_preferred":[
        "Pedrosillo de los Aires"
    ],
    "name:ast_x_preferred":[
        "Pedrosie\u1e37\u1e37u de los Aires"
    ],
    "name:baq_x_preferred":[
        "Pedrosillo de los Aires"
    ],
    "name:cat_x_preferred":[
        "Pedrosillo de los Aires"
    ],
    "name:chi_x_preferred":[
        "\u4f69\u5fb7\u7f57\u897f\u7565\u5fb7\u6d1b\u8d5b\u96f7\u65af"
    ],
    "name:dut_x_preferred":[
        "Pedrosillo de los Aires"
    ],
    "name:eng_x_preferred":[
        "Pedrosillo de los Aires"
    ],
    "name:fre_x_preferred":[
        "Pedrosillo de los Aires"
    ],
    "name:hun_x_preferred":[
        "Pedrosillo de los Aires"
    ],
    "name:ina_x_preferred":[
        "Pedrosillo de los Aires"
    ],
    "name:ita_x_preferred":[
        "Pedrosillo de los Aires"
    ],
    "name:kaz_x_preferred":[
        "\u041f\u0435\u0434\u0440\u043e\u0441\u0438\u043b\u044c\u043e-\u0434\u0435-\u043b\u043e\u0441-\u0410\u0439\u0440\u0435\u0441"
    ],
    "name:may_x_preferred":[
        "Pedrosillo de los Aires"
    ],
    "name:nan_x_preferred":[
        "Pedrosillo de los Aires"
    ],
    "name:oci_x_preferred":[
        "Pedrosillo de los Aires"
    ],
    "name:pol_x_preferred":[
        "Pedrosillo de los Aires"
    ],
    "name:por_x_preferred":[
        "Pedrosillo de los Aires"
    ],
    "name:rus_x_preferred":[
        "\u041f\u0435\u0434\u0440\u043e\u0441\u0438\u043b\u044c\u043e-\u0434\u0435-\u043b\u043e\u0441-\u0410\u0439\u0440\u0435\u0441"
    ],
    "name:spa_x_preferred":[
        "Pedrosillo de los Aires"
    ],
    "name:swe_x_preferred":[
        "Pedrosillo de los Aires"
    ],
    "name:ukr_x_preferred":[
        "\u041f\u0435\u0434\u0440\u043e\u0441\u0456\u043b\u044c\u0439\u043e-\u0434\u0435-\u043b\u043e\u0441-\u0410\u0439\u0440\u0435\u0441"
    ],
    "name:unk_x_variant":[
        "Pedrosillo de los Aires"
    ],
    "name:vie_x_preferred":[
        "Pedrosillo de los Aires"
    ],
    "name:war_x_preferred":[
        "Pedrosillo de los Aires"
    ],
    "qs_pg:aaroncc":"ES",
    "qs_pg:gn_country":"ES",
    "qs_pg:gn_fcode":"PPLA3",
    "qs_pg:gn_pop":401,
    "qs_pg:name":"Pedrosillo de Los Aires",
    "qs_pg:name_adm0":"Espa\u00f1a",
    "qs_pg:name_adm1":"Castilla y Le\u00f3n",
    "qs_pg:photos_9k":1,
    "qs_pg:photos_9r":1,
    "qs_pg:photos_all":1,
    "qs_pg:photos_sr":0,
    "qs_pg:pop_sr":2,
    "qs_pg:qs_pg_placetype":"locality",
    "qs_pg:qs_pg_placetype_gp":"Town",
    "qs_pg:woe_adm0":23424950,
    "woe:adm0_id":23424950,
    "woe:name_adm0":"Espa\u00f1a",
    "woe:name_adm1":"Castilla y Le\u00f3n",
    "woe:placetype":"Town",
    "wof:name":"Pedrosillo de Los Aires",
    "wof:placetype":"locality",
    "wof:population":401
},
  "geometry": {"coordinates":[-5.70511,40.71524],"type":"Point"}
}