{
  "type": "Feature",
  "properties": {
    "gn:admin1_code":"58",
    "gn:admin2_code":"C",
    "gn:admin3_code":"15045",
    "gn:asciiname":"Maronas",
    "gn:country_code":"ES",
    "gn:dem":322,
    "gn:feature_class":"P",
    "gn:feature_code":"PPL",
    "gn:name":"Maro\u00f1as",
    "gn:population":0,
    "gn:timezone":"Europe/Madrid",
    "iso:country":"ES",
    "wof:name":"Maronas",
    "wof:placetype":"locality"
},
  "geometry": {"coordinates":[-8.91161,42.9625],"type":"Point"}
}