{
  "type": "Feature",
  "properties": {
    "gn:admin1_code":"51",
    "gn:admin2_code":"MA",
    "gn:admin3_code":"29094",
    "gn:asciiname":"Cabrillas",
    "gn:country_code":"ES",
    "gn:dem":148,
    "gn:feature_class":"P",
    "gn:feature_code":"PPL",
    "gn:name":"Cabrillas",
    "gn:population":0,
    "gn:timezone":"Europe/Madrid",
    "iso:country":"ES",
    "name:arg_x_preferred":[
        "Cabrillas"
    ],
    "name:ast_x_preferred":[
        "Cabrillas"
    ],
    "name:cat_x_preferred":[
        "Cabrillas"
    ],
    "name:ceb_x_preferred":[
        "Cabrillas"
    ],
    "name:eus_x_preferred":[
        "Cabrillas"
    ],
    "name:fra_x_preferred":[
        "Cabrillas"
    ],
    "name:haw_x_preferred":[
        "Cabrillas"
    ],
    "name:hun_x_preferred":[
        "Cabrillas"
    ],
    "name:ina_x_preferred":[
        "Cabrillas"
    ],
    "name:ita_x_preferred":[
        "Cabrillas"
    ],
    "name:kaz_x_preferred":[
        "\u041a\u0430\u0431\u0440\u0438\u043b\u044c\u044f\u0441"
    ],
    "name:msa_x_preferred":[
        "Cabrillas"
    ],
    "name:oci_x_preferred":[
        "Cabrillas"
    ],
    "name:pol_x_preferred":[
        "Cabrillas"
    ],
    "name:por_x_preferred":[
        "Cabrillas"
    ],
    "name:rus_x_preferred":[
        "\u041a\u0430\u0431\u0440\u0438\u043b\u044c\u044f\u0441"
    ],
    "name:spa_x_preferred":[
        "Cabrillas"
    ],
    "name:swe_x_preferred":[
        "Cabrillas"
    ],
    "name:ukr_x_preferred":[
        "\u041a\u0430\u0431\u0440\u0456\u043b\u044c\u044f\u0441"
    ],
    "name:und_x_variant":[
        "Caser\u00edo Cabrillas"
    ],
    "name:uzb_x_preferred":[
        "Cabrillas"
    ],
    "name:vie_x_preferred":[
        "Cabrillas"
    ],
    "name:war_x_preferred":[
        "Cabrillas"
    ],
    "name:zho_x_preferred":[
        "\u5361\u592b\u91cc\u5229\u4e9a\u65af"
    ],
    "wof:name":"Cabrillas",
    "wof:placetype":"locality"
},
  "geometry": {"coordinates":[-4.15232,36.77802],"type":"Point"}
}