{
  "type": "Feature",
  "properties": {
    "gn:admin1_code":"51",
    "gn:admin2_code":"GR",
    "gn:admin3_code":"18147",
    "gn:asciiname":"Olias",
    "gn:country_code":"ES",
    "gn:dem":773,
    "gn:feature_class":"P",
    "gn:feature_code":"PPL",
    "gn:name":"Ol\u00edas",
    "gn:population":0,
    "gn:timezone":"Europe/Madrid",
    "iso:country":"ES",
    "name:und_x_variant":[
        "Oliar",
        "Ol\u00edas"
    ],
    "wof:name":"Olias",
    "wof:placetype":"locality"
},
  "geometry": {"coordinates":[-3.36813,36.82529],"type":"Point"}
}