{
  "type": "Feature",
  "properties": {
    "gn:admin1_code":"34",
    "gn:admin2_code":"O",
    "gn:admin3_code":"33073",
    "gn:asciiname":"La Oteda",
    "gn:country_code":"ES",
    "gn:dem":651,
    "gn:feature_class":"P",
    "gn:feature_code":"PPL",
    "gn:name":"La Oteda",
    "gn:population":0,
    "gn:timezone":"Europe/Madrid",
    "iso:country":"ES",
    "wof:name":"La Oteda",
    "wof:placetype":"locality"
},
  "geometry": {"coordinates":[-6.48333,43.36667],"type":"Point"}
}