{
  "type": "Feature",
  "properties": {
    "gn:admin1_code":"59",
    "gn:admin2_code":"SS",
    "gn:admin3_code":"20074",
    "gn:asciiname":"Basalgo",
    "gn:country_code":"ES",
    "gn:dem":305,
    "gn:feature_class":"P",
    "gn:feature_code":"PPL",
    "gn:name":"Basalgo",
    "gn:population":0,
    "gn:timezone":"Europe/Madrid",
    "iso:country":"ES",
    "name:eus_x_preferred":[
        "Basalgo"
    ],
    "wof:name":"Basalgo",
    "wof:placetype":"locality"
},
  "geometry": {"coordinates":[-2.43182,43.14252000000001],"type":"Point"}
}