{
  "type": "Feature",
  "properties": {
    "gn:admin1_code":"55",
    "gn:admin2_code":"BU",
    "gn:admin3_code":"09412",
    "gn:asciiname":"Bascunuelos",
    "gn:country_code":"ES",
    "gn:dem":612,
    "gn:feature_class":"P",
    "gn:feature_code":"PPL",
    "gn:name":"Bascu\u00f1uelos",
    "gn:population":0,
    "gn:timezone":"Europe/Madrid",
    "iso:country":"ES",
    "name:und_x_variant":[
        "Bascu\u00f1uelos"
    ],
    "wof:name":"Bascunuelos",
    "wof:placetype":"locality"
},
  "geometry": {"coordinates":[-3.33436,42.81151],"type":"Point"}
}