{
  "type": "Feature",
  "properties": {
    "gn:admin1_code":"34",
    "gn:admin2_code":"O",
    "gn:admin3_code":"33049",
    "gn:asciiname":"Torin",
    "gn:country_code":"ES",
    "gn:dem":219,
    "gn:feature_class":"P",
    "gn:feature_code":"PPL",
    "gn:name":"Tor\u00edn",
    "gn:population":0,
    "gn:timezone":"Europe/Madrid",
    "iso:country":"ES",
    "name:ceb_x_preferred":[
        "Torin"
    ],
    "name:srp_x_preferred":[
        "Torin"
    ],
    "name:swe_x_preferred":[
        "Torin"
    ],
    "wof:name":"Torin",
    "wof:placetype":"locality"
},
  "geometry": {"coordinates":[-5.30459,43.35371],"type":"Point"}
}