{
  "type": "Feature",
  "properties": {
    "iso:country":"ES",
    "qs:a0":"Espa\u00f1a",
    "qs:a1":"*M\u00e1laga",
    "qs:a1r":"0Andaluc\u00eda",
    "qs:adm0":"Espa\u00f1a",
    "qs:la_lc":"*",
    "qs:level":"locality",
    "qs:loc":"Casta\u00f1eta, La",
    "qs:loc_alt":"Castaneta, La",
    "qs:pop":0,
    "qs:type":"buffered point",
    "wof:name":"Casta\u00f1eta, La",
    "wof:placetype":"locality"
},
  "geometry": {"coordinates":[-4.549114,36.708862],"type":"Point"}
}