{
  "type": "Feature",
  "properties": {
    "gn:admin1_code":"58",
    "gn:admin2_code":"OR",
    "gn:admin3_code":"32029",
    "gn:asciiname":"Queixa",
    "gn:cc2":"ES",
    "gn:country_code":"ES",
    "gn:dem":1003,
    "gn:feature_class":"P",
    "gn:feature_code":"PPL",
    "gn:name":"Queixa",
    "gn:population":0,
    "gn:timezone":"Europe/Madrid",
    "iso:country":"ES",
    "name:und_x_variant":[
        "Santa Cruz",
        "Queija"
    ],
    "wof:name":"Queixa",
    "wof:placetype":"locality"
},
  "geometry": {"coordinates":[-7.41667,42.25],"type":"Point"}
}