{
  "type": "Feature",
  "properties": {
    "gn:gn_country":"ES",
    "gn:gn_fcode":"PPLA3",
    "gn:gn_pop":474,
    "gn:population":474,
    "iso:country":"ES",
    "name:ara_x_preferred":[
        "\u0628\u0627\u062a\u064a\u0631\u0646\u0627 \u062f\u064a\u0644 \u0645\u0627\u062f\u064a\u0631\u0627"
    ],
    "name:arg_x_preferred":[
        "Paterna del Madera"
    ],
    "name:cat_x_preferred":[
        "Paterna del Madera"
    ],
    "name:deu_x_preferred":[
        "Paterna del Madera"
    ],
    "name:eng_x_preferred":[
        "Paterna del Madera"
    ],
    "name:eus_x_preferred":[
        "Paterna del Madera"
    ],
    "name:fas_x_preferred":[
        "\u067e\u0627\u062a\u0631\u0646\u0627 \u062f\u0644 \u0645\u0627\u062f\u0631\u0627"
    ],
    "name:fra_x_preferred":[
        "Paterna del Madera"
    ],
    "name:hun_x_preferred":[
        "Paterna del Madera"
    ],
    "name:ina_x_preferred":[
        "Paterna del Madera"
    ],
    "name:ita_x_preferred":[
        "Paterna del Madera"
    ],
    "name:msa_x_preferred":[
        "Paterna del Madera"
    ],
    "name:nan_x_preferred":[
        "Paterna del Madera"
    ],
    "name:nld_x_preferred":[
        "Paterna del Madera"
    ],
    "name:oci_x_preferred":[
        "Paterna del Madera"
    ],
    "name:pol_x_preferred":[
        "Paterna del Madera"
    ],
    "name:por_x_preferred":[
        "Paterna del Madera"
    ],
    "name:ron_x_preferred":[
        "Paterna del Madera"
    ],
    "name:rus_x_preferred":[
        "\u041f\u0430\u0442\u0435\u0440\u043d\u0430-\u0434\u0435\u043b\u044c-\u041c\u0430\u0434\u0435\u0440\u0430"
    ],
    "name:spa_x_preferred":[
        "Paterna del Madera"
    ],
    "name:swe_x_preferred":[
        "Paterna del Madera"
    ],
    "name:ukr_x_preferred":[
        "\u041f\u0430\u0442\u0435\u0440\u043d\u0430-\u0434\u0435\u043b\u044c-\u041c\u0430\u0434\u0435\u0440\u0430"
    ],
    "name:vie_x_preferred":[
        "Paterna del Madera"
    ],
    "name:war_x_preferred":[
        "Paterna del Madera"
    ],
    "name:zho_x_preferred":[
        "\u5e15\u7279\u5c14\u7eb3\u5fb7\u5c14\u9a6c\u5fb7\u62c9"
    ],
    "qs_pg:aaroncc":"ES",
    "qs_pg:gn_country":"ES",
    "qs_pg:gn_fcode":"PPLA3",
    "qs_pg:gn_pop":474,
    "qs_pg:name":"Paterna del Madera",
    "qs_pg:name_adm0":"Espa\u00f1a",
    "qs_pg:name_adm1":"Castilla-La Mancha",
    "qs_pg:photos_9k":1,
    "qs_pg:photos_9r":1,
    "qs_pg:photos_all":1,
    "qs_pg:photos_sr":0,
    "qs_pg:pop_sr":2,
    "qs_pg:qs_pg_placetype":"locality",
    "qs_pg:qs_pg_placetype_gp":"Town",
    "qs_pg:woe_adm0":23424950,
    "woe:adm0_id":23424950,
    "woe:name_adm0":"Espa\u00f1a",
    "woe:name_adm1":"Castilla-La Mancha",
    "woe:placetype":"Town",
    "wof:name":"Paterna del Madera",
    "wof:placetype":"locality",
    "wof:population":474
},
  "geometry": {"coordinates":[-2.34421,38.59751],"type":"Point"}
}