{
  "type": "Feature",
  "properties": {
    "gn:admin1_code":"58",
    "gn:admin2_code":"LU",
    "gn:admin3_code":"27011",
    "gn:asciiname":"Barredo",
    "gn:country_code":"ES",
    "gn:dem":537,
    "gn:feature_class":"P",
    "gn:feature_code":"PPL",
    "gn:name":"Barredo",
    "gn:population":0,
    "gn:timezone":"Europe/Madrid",
    "iso:country":"ES",
    "name:und_x_variant":[
        "San Andr\u00e9s",
        "Barredo"
    ],
    "wof:name":"Barredo",
    "wof:placetype":"locality"
},
  "geometry": {"coordinates":[-7.41134,43.03435],"type":"Point"}
}