{
  "type": "Feature",
  "properties": {
    "gn:admin1_code":"39",
    "gn:admin2_code":"S",
    "gn:admin3_code":"39052",
    "gn:asciiname":"Quijano",
    "gn:country_code":"ES",
    "gn:dem":28,
    "gn:feature_class":"P",
    "gn:feature_code":"PPL",
    "gn:name":"Quijano",
    "gn:population":0,
    "gn:timezone":"Europe/Madrid",
    "iso:country":"ES",
    "wof:name":"Quijano",
    "wof:placetype":"locality"
},
  "geometry": {"coordinates":[-3.95593,43.36807],"type":"Point"}
}