{
  "type": "Feature",
  "properties": {
    "gn:gn_country":"ES",
    "gn:gn_fcode":"PPL",
    "gn:gn_pop":0,
    "iso:country":"ES",
    "name:alb_x_preferred":[
        "Vilalba Sasserra"
    ],
    "name:ara_x_preferred":[
        "\u0641\u064a\u0644\u0627\u0623\u0644\u0628\u0627 \u0633\u0627\u0633\u064a\u0631\u0627"
    ],
    "name:arg_x_preferred":[
        "Vilalba Sasserra"
    ],
    "name:arm_x_preferred":[
        "\u054e\u056b\u056c\u0561\u056c\u0562\u0561 \u054d\u0561\u057d\u0565\u057c\u0561"
    ],
    "name:baq_x_preferred":[
        "Vilalba Sasserra"
    ],
    "name:bre_x_preferred":[
        "Vilalba Sasserra"
    ],
    "name:cat_x_preferred":[
        "Vilalba Sasserra"
    ],
    "name:chi_x_preferred":[
        "\u6bd4\u62c9\u5c14\u74e6\u8428\u585e\u62c9"
    ],
    "name:dut_x_preferred":[
        "Vilalba Sasserra"
    ],
    "name:eng_x_preferred":[
        "Vilalba Sasserra"
    ],
    "name:fre_x_preferred":[
        "Vilalba Sasserra"
    ],
    "name:ger_x_preferred":[
        "Villalba Saserra"
    ],
    "name:hun_x_preferred":[
        "Vilalba Sasserra"
    ],
    "name:ita_x_preferred":[
        "Vilalba Sasserra"
    ],
    "name:kaz_x_preferred":[
        "\u0412\u0438\u043b\u0430\u043b\u044c\u0431\u0430-\u0421\u0430\u0441\u0441\u0435\u0440\u0440\u0430"
    ],
    "name:lat_x_preferred":[
        "Vilalba Sasserra"
    ],
    "name:oci_x_preferred":[
        "Vilalba Sasserra"
    ],
    "name:pol_x_preferred":[
        "Vilalba Sasserra"
    ],
    "name:por_x_preferred":[
        "Vilalba Sasserra"
    ],
    "name:rum_x_preferred":[
        "Vilalba Sasserra"
    ],
    "name:rus_x_preferred":[
        "\u0412\u0438\u043b\u0430\u043b\u044c\u0431\u0430-\u0421\u0430\u0441\u0441\u0435\u0440\u0440\u0430"
    ],
    "name:sco_x_preferred":[
        "Vilalba Sasserra"
    ],
    "name:spa_x_preferred":[
        "Villalba Saserra"
    ],
    "name:swe_x_preferred":[
        "Vilalba Sasserra"
    ],
    "name:ukr_x_preferred":[
        "\u0411\u0456\u043b\u0430\u043b\u0431\u0430-\u0421\u0430\u0441\u0435\u0440\u0440\u0430"
    ],
    "name:unk_x_variant":[
        "Villalba Saserra"
    ],
    "name:uzb_x_preferred":[
        "Vilalba Sasserra"
    ],
    "name:war_x_preferred":[
        "Vilalba Sasserra"
    ],
    "qs_pg:aaroncc":"ES",
    "qs_pg:gn_country":"ES",
    "qs_pg:gn_fcode":"PPL",
    "qs_pg:gn_pop":0,
    "qs_pg:name":"Vilalba Sasserra",
    "qs_pg:name_adm0":"Espa\u00f1a",
    "qs_pg:name_adm1":"Catalunya",
    "qs_pg:photos":90,
    "qs_pg:photos_1k":18,
    "qs_pg:photos_9k":1,
    "qs_pg:photos_9r":3,
    "qs_pg:photos_all":90,
    "qs_pg:photos_sr":3,
    "qs_pg:pop_sr":0,
    "qs_pg:qs_pg_placetype":"locality",
    "qs_pg:qs_pg_placetype_gp":"Town",
    "qs_pg:woe_adm0":23424950,
    "woe:adm0_id":23424950,
    "woe:name_adm0":"Espa\u00f1a",
    "woe:name_adm1":"Catalunya",
    "woe:placetype":"Town",
    "wof:name":"Vilalba Sasserra",
    "wof:placetype":"locality"
},
  "geometry": {"coordinates":[2.45,41.65],"type":"Point"}
}