{
  "type": "Feature",
  "properties": {
    "gn:admin1_code":"34",
    "gn:admin2_code":"O",
    "gn:admin3_code":"33011",
    "gn:asciiname":"San Damias",
    "gn:country_code":"ES",
    "gn:dem":702,
    "gn:feature_class":"P",
    "gn:feature_code":"PPL",
    "gn:name":"San Dam\u00edas",
    "gn:population":0,
    "gn:timezone":"Europe/Madrid",
    "iso:country":"ES",
    "wof:name":"San Damias",
    "wof:placetype":"locality"
},
  "geometry": {"coordinates":[-6.61298,43.14857],"type":"Point"}
}