{
  "type": "Feature",
  "properties": {
    "gn:admin1_code":"58",
    "gn:admin2_code":"C",
    "gn:admin3_code":"15056",
    "gn:asciiname":"Gonte",
    "gn:country_code":"ES",
    "gn:dem":238,
    "gn:feature_class":"P",
    "gn:feature_code":"PPL",
    "gn:name":"Gonte",
    "gn:population":0,
    "gn:timezone":"Europe/Madrid",
    "iso:country":"ES",
    "wof:name":"Gonte",
    "wof:placetype":"locality"
},
  "geometry": {"coordinates":[-8.76706,42.89899000000001],"type":"Point"}
}