{
  "type": "Feature",
  "properties": {
    "gn:admin1_code":"34",
    "gn:admin2_code":"O",
    "gn:admin3_code":"33076",
    "gn:asciiname":"Rali",
    "gn:country_code":"ES",
    "gn:dem":437,
    "gn:feature_class":"P",
    "gn:feature_code":"PPL",
    "gn:name":"Ral\u00ed",
    "gn:population":0,
    "gn:timezone":"Europe/Madrid",
    "iso:country":"ES",
    "wof:name":"Rali",
    "wof:placetype":"locality"
},
  "geometry": {"coordinates":[-5.44913,43.41415],"type":"Point"}
}