{
  "type": "Feature",
  "properties": {
    "gn:admin1_code":"34",
    "gn:admin2_code":"O",
    "gn:admin3_code":"33066",
    "gn:asciiname":"Atras",
    "gn:country_code":"ES",
    "gn:dem":419,
    "gn:feature_class":"P",
    "gn:feature_code":"PPL",
    "gn:name":"Atr\u00e1s",
    "gn:population":0,
    "gn:timezone":"Europe/Madrid",
    "iso:country":"ES",
    "wof:name":"Atras",
    "wof:placetype":"locality"
},
  "geometry": {"coordinates":[-5.61726,43.42871],"type":"Point"}
}