{
  "type": "Feature",
  "properties": {
    "gn:admin1_code":"58",
    "gn:admin2_code":"LU",
    "gn:admin3_code":"27037",
    "gn:asciiname":"Sebras",
    "gn:country_code":"ES",
    "gn:dem":855,
    "gn:feature_class":"P",
    "gn:feature_code":"PPL",
    "gn:name":"Sebr\u00e1s",
    "gn:population":0,
    "gn:timezone":"Europe/Madrid",
    "iso:country":"ES",
    "wof:name":"Sebras",
    "wof:placetype":"locality"
},
  "geometry": {"coordinates":[-7.11084,42.77036],"type":"Point"}
}