{
  "type": "Feature",
  "properties": {
    "gn:admin1_code":"56",
    "gn:admin2_code":"L",
    "gn:admin3_code":"25145",
    "gn:asciiname":"Nalec",
    "gn:country_code":"ES",
    "gn:dem":525,
    "gn:feature_class":"P",
    "gn:feature_code":"PPLA3",
    "gn:name":"Nalec",
    "gn:population":0,
    "gn:timezone":"Europe/Madrid",
    "iso:country":"ES",
    "name:arg_x_preferred":[
        "Nalec"
    ],
    "name:ast_x_preferred":[
        "Nalec"
    ],
    "name:cat_x_preferred":[
        "Nalec"
    ],
    "name:ceb_x_preferred":[
        "Nalec"
    ],
    "name:eus_x_preferred":[
        "Nalec"
    ],
    "name:fra_x_preferred":[
        "Nalec"
    ],
    "name:hun_x_preferred":[
        "Nalec"
    ],
    "name:hye_x_preferred":[
        "\u0546\u0561\u056c\u0565\u056f"
    ],
    "name:ita_x_preferred":[
        "Nalec"
    ],
    "name:msa_x_preferred":[
        "Nalec"
    ],
    "name:nld_x_preferred":[
        "Nalec"
    ],
    "name:oci_x_preferred":[
        "Nalec"
    ],
    "name:pol_x_preferred":[
        "Nalec"
    ],
    "name:por_x_preferred":[
        "Nalec"
    ],
    "name:ron_x_preferred":[
        "Nalec"
    ],
    "name:rus_x_preferred":[
        "\u041d\u0430\u043b\u0435\u043a"
    ],
    "name:spa_x_preferred":[
        "Nalech"
    ],
    "name:sqi_x_preferred":[
        "Nalec"
    ],
    "name:swe_x_preferred":[
        "Nalec"
    ],
    "name:und_x_variant":[
        "Nalech"
    ],
    "name:uzb_x_preferred":[
        "Nalec"
    ],
    "name:vie_x_preferred":[
        "Nalec"
    ],
    "name:war_x_preferred":[
        "Nalec"
    ],
    "name:zho_x_preferred":[
        "\u7eb3\u83b1\u514b"
    ],
    "wof:name":"Nalec",
    "wof:placetype":"locality"
},
  "geometry": {"coordinates":[1.11667,41.55],"type":"Point"}
}