{
  "type": "Feature",
  "properties": {
    "gn:admin1_code":"56",
    "gn:admin2_code":"L",
    "gn:admin3_code":"25145",
    "gn:asciiname":"Nalec",
    "gn:country_code":"ES",
    "gn:dem":525,
    "gn:feature_class":"P",
    "gn:feature_code":"PPLA3",
    "gn:name":"Nalec",
    "gn:population":0,
    "gn:timezone":"Europe/Madrid",
    "iso:country":"ES",
    "name:cat_x_preferred":[
        "Nalec"
    ],
    "name:spa_x_preferred":[
        "Nalech"
    ],
    "name:und_x_variant":[
        "Nalech"
    ],
    "wof:name":"Nalec",
    "wof:placetype":"locality"
},
  "geometry": {"coordinates":[1.11667,41.55],"type":"Point"}
}