{
  "type": "Feature",
  "properties": {
    "gn:admin1_code":"54",
    "gn:admin2_code":"GU",
    "gn:admin3_code":"19256",
    "gn:asciiname":"Tobes",
    "gn:country_code":"ES",
    "gn:dem":1035,
    "gn:feature_class":"P",
    "gn:feature_code":"PPL",
    "gn:name":"Tobes",
    "gn:population":0,
    "gn:timezone":"Europe/Madrid",
    "iso:country":"ES",
    "name:ast_x_preferred":[
        "Tobes"
    ],
    "name:deu_x_preferred":[
        "Tobes"
    ],
    "name:spa_x_preferred":[
        "Tobes"
    ],
    "wof:name":"Tobes",
    "wof:placetype":"locality"
},
  "geometry": {"coordinates":[-2.66071,41.19286],"type":"Point"}
}