{
  "type": "Feature",
  "properties": {
    "gn:admin1_code":"58",
    "gn:admin2_code":"OR",
    "gn:admin3_code":"32024",
    "gn:asciiname":"Rabal",
    "gn:cc2":"ES",
    "gn:country_code":"ES",
    "gn:dem":417,
    "gn:feature_class":"P",
    "gn:feature_code":"PPL",
    "gn:name":"Rabal",
    "gn:population":0,
    "gn:timezone":"Europe/Madrid",
    "iso:country":"ES",
    "name:und_x_variant":[
        "San Salvador"
    ],
    "wof:name":"Rabal",
    "wof:placetype":"locality"
},
  "geometry": {"coordinates":[-7.91887,42.20668],"type":"Point"}
}