{
  "type": "Feature",
  "properties": {
    "gn:admin1_code":"52",
    "gn:admin2_code":"HU",
    "gn:admin3_code":"22058",
    "gn:asciiname":"Otin",
    "gn:country_code":"ES",
    "gn:dem":1039,
    "gn:feature_class":"P",
    "gn:feature_code":"PPL",
    "gn:name":"Ot\u00edn",
    "gn:population":0,
    "gn:timezone":"Europe/Madrid",
    "iso:country":"ES",
    "name:und_x_variant":[
        "Ot\u00edn"
    ],
    "wof:name":"Otin",
    "wof:placetype":"locality"
},
  "geometry": {"coordinates":[-0.0743,42.31881],"type":"Point"}
}