{
  "type": "Feature",
  "properties": {
    "gn:admin1_code":"59",
    "gn:admin2_code":"BI",
    "gn:admin3_code":"48081",
    "gn:asciiname":"Aretxalde",
    "gn:country_code":"ES",
    "gn:dem":93,
    "gn:feature_class":"P",
    "gn:feature_code":"PPL",
    "gn:name":"Aretxalde",
    "gn:population":0,
    "gn:timezone":"Europe/Madrid",
    "iso:country":"ES",
    "name:eus_x_preferred":[
        "Aretxalde"
    ],
    "name:spa_x_preferred":[
        "Arechalde"
    ],
    "wof:name":"Aretxalde",
    "wof:placetype":"locality"
},
  "geometry": {"coordinates":[-2.83333,43.26667],"type":"Point"}
}