{
  "type": "Feature",
  "properties": {
    "gn:admin1_code":"51",
    "gn:admin2_code":"GR",
    "gn:admin3_code":"18088",
    "gn:asciiname":"El Navazuelo",
    "gn:country_code":"ES",
    "gn:dem":1096,
    "gn:feature_class":"P",
    "gn:feature_code":"PPL",
    "gn:name":"El Navazuelo",
    "gn:population":0,
    "gn:timezone":"Europe/Madrid",
    "iso:country":"ES",
    "name:und_x_variant":[
        "Caser\u00edo El Navazuelo",
        "Cortijada El Navazuelo",
        "El Navazuelo"
    ],
    "wof:name":"El Navazuelo",
    "wof:placetype":"locality"
},
  "geometry": {"coordinates":[-3.41922,37.5232],"type":"Point"}
}