{
  "type": "Feature",
  "properties": {
    "gn:gn_country":"ES",
    "gn:gn_fcode":"PPLA3",
    "gn:gn_pop":206,
    "gn:population":206,
    "iso:country":"ES",
    "name:ara_x_preferred":[
        "\u0627\u0644\u0643\u0648\u064a\u062f\u0627 \u062f\u064a \u0641\u064a\u0648"
    ],
    "name:arg_x_preferred":[
        "L'Alcudia de Veyo"
    ],
    "name:cat_x_preferred":[
        "l'Alc\u00fadia de Veo"
    ],
    "name:eng_x_preferred":[
        "Alcudia de Veo"
    ],
    "name:eus_x_preferred":[
        "L'Alc\u00fadia de Veo"
    ],
    "name:fas_x_preferred":[
        "\u0627\u0644\u06a9\u0648\u062f\u06cc\u0627 \u062f\u0648 \u0648\u06cc\u0648"
    ],
    "name:fra_x_preferred":[
        "Alcudia de Veo"
    ],
    "name:hun_x_preferred":[
        "Alc\u00fadia de Veo"
    ],
    "name:ita_x_preferred":[
        "Alcudia de Veo"
    ],
    "name:jpn_x_preferred":[
        "\u30a2\u30eb\u30af\u30c7\u30a3\u30a2\u30fb\u30c7\u30fb\u30d9\u30aa"
    ],
    "name:msa_x_preferred":[
        "Alcudia de Veo"
    ],
    "name:nan_x_preferred":[
        "Alcudia de Veo"
    ],
    "name:nld_x_preferred":[
        "Alcudia de Veo"
    ],
    "name:oci_x_preferred":[
        "Alcudia de Veo"
    ],
    "name:pol_x_preferred":[
        "Alcudia de Veo"
    ],
    "name:por_x_preferred":[
        "Alcudia de Veo"
    ],
    "name:rus_x_preferred":[
        "\u0410\u043b\u044c\u043a\u0443\u0434\u0438\u0430-\u0434\u0435-\u0412\u0435\u043e"
    ],
    "name:spa_x_preferred":[
        "Alcudia de Veo"
    ],
    "name:sqi_x_preferred":[
        "Alcudia de Veo"
    ],
    "name:swe_x_preferred":[
        "Alcudia de Veo"
    ],
    "name:ukr_x_preferred":[
        "\u0410\u043b\u044c\u043a\u0443\u0434\u0456\u044f-\u0434\u0435-\u0412\u0435\u043e"
    ],
    "name:uzb_x_preferred":[
        "Alcudia de Veo"
    ],
    "name:vie_x_preferred":[
        "Alcudia de Veo"
    ],
    "name:war_x_preferred":[
        "Alcudia de Veo"
    ],
    "name:zho_x_preferred":[
        "\u963f\u5c14\u5e93\u8fea\u4e9a\u5fb7\u97e6\u5965"
    ],
    "qs_pg:aaroncc":"ES",
    "qs_pg:gn_country":"ES",
    "qs_pg:gn_fcode":"PPLA3",
    "qs_pg:gn_pop":206,
    "qs_pg:name":"Alcudia de Veo",
    "qs_pg:name_adm0":"Espa\u00f1a",
    "qs_pg:name_adm1":"Comunitat Valenciana",
    "qs_pg:photos":136,
    "qs_pg:photos_1k":28,
    "qs_pg:photos_9k":1,
    "qs_pg:photos_9r":3,
    "qs_pg:photos_all":136,
    "qs_pg:photos_sr":3,
    "qs_pg:pop_sr":2,
    "qs_pg:qs_pg_placetype":"locality",
    "qs_pg:qs_pg_placetype_gp":"Town",
    "qs_pg:woe_adm0":23424950,
    "woe:adm0_id":23424950,
    "woe:name_adm0":"Espa\u00f1a",
    "woe:name_adm1":"Comunitat Valenciana",
    "woe:placetype":"Town",
    "wof:name":"Alcudia de Veo",
    "wof:placetype":"locality",
    "wof:population":206
},
  "geometry": {"coordinates":[-0.35,39.91667],"type":"Point"}
}