{
  "type": "Feature",
  "properties": {
    "gn:admin1_code":"58",
    "gn:admin2_code":"LU",
    "gn:admin3_code":"27001",
    "gn:asciiname":"Abeledo",
    "gn:cc2":"ES",
    "gn:country_code":"ES",
    "gn:dem":594,
    "gn:feature_class":"P",
    "gn:feature_code":"PPL",
    "gn:name":"Abeledo",
    "gn:population":0,
    "gn:timezone":"Europe/Madrid",
    "iso:country":"ES",
    "name:und_x_variant":[
        "Santa Mar\u00eda",
        "Abeledo"
    ],
    "wof:name":"Abeledo",
    "wof:placetype":"locality"
},
  "geometry": {"coordinates":[-7.46667,43.31667],"type":"Point"}
}