{
  "type": "Feature",
  "properties": {
    "gn:gn_country":"ES",
    "gn:gn_fcode":"PPLA3",
    "gn:gn_pop":152,
    "gn:population":152,
    "iso:country":"ES",
    "name:arg_x_preferred":[
        "Villalbarba"
    ],
    "name:ast_x_preferred":[
        "Villalbarba"
    ],
    "name:cat_x_preferred":[
        "Villalbarba"
    ],
    "name:ceb_x_preferred":[
        "Villalbarba"
    ],
    "name:eng_x_preferred":[
        "Villalbarba"
    ],
    "name:eus_x_preferred":[
        "Villalbarba"
    ],
    "name:fas_x_preferred":[
        "\u0628\u06cc\u06cc\u0627\u0644\u0628\u0627\u0631\u0628\u0627"
    ],
    "name:fra_x_preferred":[
        "Villalbarba"
    ],
    "name:hun_x_preferred":[
        "Villalbarba"
    ],
    "name:hye_x_preferred":[
        "\u054e\u056b\u056c\u0575\u0561\u056c\u0562\u0561\u0580\u0562\u0561"
    ],
    "name:ina_x_preferred":[
        "Villalbarba"
    ],
    "name:ita_x_preferred":[
        "Villalbarba"
    ],
    "name:msa_x_preferred":[
        "Villalbarba"
    ],
    "name:nan_x_preferred":[
        "Villalbarba"
    ],
    "name:nld_x_preferred":[
        "Villalbarba"
    ],
    "name:oci_x_preferred":[
        "Villalbarba"
    ],
    "name:pol_x_preferred":[
        "Villalbarba"
    ],
    "name:por_x_preferred":[
        "Villalbarba"
    ],
    "name:rus_x_preferred":[
        "\u0412\u0438\u043b\u044c\u044f\u043b\u044c\u0431\u0430\u0440\u0431\u0430"
    ],
    "name:spa_x_preferred":[
        "Villalbarba"
    ],
    "name:swe_x_preferred":[
        "Villalbarba"
    ],
    "name:ukr_x_preferred":[
        "\u0412\u0456\u043b\u044c\u044f\u043b\u044c\u0431\u0430\u0440\u0431\u0430"
    ],
    "name:unk_x_variant":[
        "Villarbarba"
    ],
    "name:vie_x_preferred":[
        "Villalbarba"
    ],
    "name:war_x_preferred":[
        "Villalbarba"
    ],
    "name:zho_x_preferred":[
        "\u6bd4\u5229\u4e9a\u5c14\u74e6\u5c14\u74e6"
    ],
    "qs_pg:aaroncc":"ES",
    "qs_pg:gn_country":"ES",
    "qs_pg:gn_fcode":"PPLA3",
    "qs_pg:gn_pop":152,
    "qs_pg:name":"Villalbarba",
    "qs_pg:name_adm0":"Espa\u00f1a",
    "qs_pg:name_adm1":"Castilla y Le\u00f3n",
    "qs_pg:photos_9r":0,
    "qs_pg:photos_sr":0,
    "qs_pg:pop_sr":1,
    "qs_pg:qs_pg_placetype":"locality",
    "qs_pg:qs_pg_placetype_gp":"Town",
    "qs_pg:woe_adm0":23424950,
    "woe:adm0_id":23424950,
    "woe:name_adm0":"Espa\u00f1a",
    "woe:name_adm1":"Castilla y Le\u00f3n",
    "woe:placetype":"Town",
    "wof:name":"Villalbarba",
    "wof:placetype":"locality",
    "wof:population":152
},
  "geometry": {"coordinates":[-5.21281,41.60389],"type":"Point"}
}