{
  "type": "Feature",
  "properties": {
    "gn:gn_country":"ES",
    "gn:gn_fcode":"PPL",
    "gn:gn_pop":414,
    "gn:population":414,
    "iso:country":"ES",
    "name:alb_x_preferred":[
        "Vilallonga de Ter"
    ],
    "name:ara_x_preferred":[
        "\u0641\u064a\u0644\u0627\u064a\u0648\u0646\u063a\u0627 \u062f\u064a \u062a\u064a\u0631"
    ],
    "name:arg_x_preferred":[
        "Vilallonga de Ter"
    ],
    "name:arm_x_preferred":[
        "\u054e\u056b\u056c\u0561\u056c\u0575\u0578\u0576\u0563\u0561 \u0564\u0565 \u054f\u0565\u0580"
    ],
    "name:baq_x_preferred":[
        "Vilallonga de Ter"
    ],
    "name:cat_x_preferred":[
        "Vilallonga de Ter"
    ],
    "name:chi_x_preferred":[
        "\u6bd4\u62c9\u5229\u7fc1\u52a0\u5fb7\u7279\u5c14"
    ],
    "name:dut_x_preferred":[
        "Vilallonga de Ter"
    ],
    "name:eng_x_preferred":[
        "Vilallonga de Ter"
    ],
    "name:fre_x_preferred":[
        "Vilallonga de Ter"
    ],
    "name:ger_x_preferred":[
        "Vilallonga de Ter"
    ],
    "name:hun_x_preferred":[
        "Vilallonga de Ter"
    ],
    "name:ita_x_preferred":[
        "Vilallonga de Ter"
    ],
    "name:kaz_x_preferred":[
        "\u0412\u0438\u043b\u0430\u043b\u044c\u043e\u043d\u0433\u0430-\u0434\u0435-\u0422\u0435\u0440"
    ],
    "name:lat_x_preferred":[
        "Vilallonga de Ter"
    ],
    "name:oci_x_preferred":[
        "Vilallonga de Ter"
    ],
    "name:pol_x_preferred":[
        "Vilallonga de Ter"
    ],
    "name:por_x_preferred":[
        "Vilallonga de Ter"
    ],
    "name:rus_x_preferred":[
        "\u0412\u0438\u043b\u0430\u043b\u044c\u043e\u043d\u0433\u0430-\u0434\u0435-\u0422\u0435\u0440"
    ],
    "name:spa_x_preferred":[
        "Vilallonga de Ter"
    ],
    "name:swe_x_preferred":[
        "Vilallonga de Ter"
    ],
    "name:uzb_x_preferred":[
        "Vilallonga de Ter"
    ],
    "name:war_x_preferred":[
        "Vilallonga de Ter"
    ],
    "qs_pg:aaroncc":"ES",
    "qs_pg:gn_country":"ES",
    "qs_pg:gn_fcode":"PPL",
    "qs_pg:gn_pop":414,
    "qs_pg:name":"Vilallonga de Ter",
    "qs_pg:name_adm0":"Espa\u00f1a",
    "qs_pg:name_adm1":"Catalunya",
    "qs_pg:photos":50,
    "qs_pg:photos_1k":10,
    "qs_pg:photos_9k":1,
    "qs_pg:photos_9r":2,
    "qs_pg:photos_all":50,
    "qs_pg:photos_sr":2,
    "qs_pg:pop_sr":2,
    "qs_pg:qs_pg_placetype":"locality",
    "qs_pg:qs_pg_placetype_gp":"Town",
    "qs_pg:woe_adm0":23424950,
    "woe:adm0_id":23424950,
    "woe:name_adm0":"Espa\u00f1a",
    "woe:name_adm1":"Catalunya",
    "woe:placetype":"Town",
    "wof:name":"Vilallonga de Ter",
    "wof:placetype":"locality",
    "wof:population":414
},
  "geometry": {"coordinates":[2.31652,42.32998],"type":"Point"}
}