{
  "type": "Feature",
  "properties": {
    "gn:admin1_code":"51",
    "gn:admin2_code":"J",
    "gn:admin3_code":"23048",
    "gn:asciiname":"Bardazoso",
    "gn:country_code":"ES",
    "gn:dem":894,
    "gn:feature_class":"P",
    "gn:feature_code":"PPL",
    "gn:name":"Bardazoso",
    "gn:population":0,
    "gn:timezone":"Europe/Madrid",
    "iso:country":"ES",
    "name:und_x_variant":[
        "Caser\u00edo Bardazoso",
        "Bardazoso"
    ],
    "wof:name":"Bardazoso",
    "wof:placetype":"locality"
},
  "geometry": {"coordinates":[-2.91916,38.10354],"type":"Point"}
}