{
  "type": "Feature",
  "properties": {
    "gn:admin1_code":"34",
    "gn:admin2_code":"O",
    "gn:admin3_code":"33011",
    "gn:asciiname":"Aguera de Castanedo",
    "gn:country_code":"ES",
    "gn:dem":462,
    "gn:feature_class":"P",
    "gn:feature_code":"PPL",
    "gn:name":"Ag\u00fcera de Casta\u00f1edo",
    "gn:population":0,
    "gn:timezone":"Europe/Madrid",
    "iso:country":"ES",
    "name:und_x_variant":[
        "Ag\u00fcera de Casta\u00f1edo"
    ],
    "wof:name":"Aguera de Castanedo",
    "wof:placetype":"locality"
},
  "geometry": {"coordinates":[-6.58632,43.106],"type":"Point"}
}