{
  "type": "Feature",
  "properties": {
    "gn:admin1_code":"58",
    "gn:admin2_code":"LU",
    "gn:admin3_code":"27049",
    "gn:asciiname":"Rio",
    "gn:cc2":"ES",
    "gn:country_code":"ES",
    "gn:dem":626,
    "gn:feature_class":"P",
    "gn:feature_code":"PPL",
    "gn:name":"R\u00edo",
    "gn:population":0,
    "gn:timezone":"Europe/Madrid",
    "iso:country":"ES",
    "name:und_x_variant":[
        "San Mamed",
        "R\u00edo"
    ],
    "wof:name":"Rio",
    "wof:placetype":"locality"
},
  "geometry": {"coordinates":[-7.73333,42.83333],"type":"Point"}
}