{
  "type": "Feature",
  "properties": {
    "gn:admin1_code":"39",
    "gn:admin2_code":"S",
    "gn:admin3_code":"39056",
    "gn:asciiname":"Aes",
    "gn:country_code":"ES",
    "gn:dem":102,
    "gn:feature_class":"P",
    "gn:feature_code":"PPL",
    "gn:name":"A\u00e9s",
    "gn:population":0,
    "gn:timezone":"Europe/Madrid",
    "iso:country":"ES",
    "name:und_x_variant":[
        "A\u00e9s"
    ],
    "wof:name":"Aes",
    "wof:placetype":"locality"
},
  "geometry": {"coordinates":[-3.95667,43.28292],"type":"Point"}
}