{
  "type": "Feature",
  "properties": {
    "gn:admin1_code":"55",
    "gn:admin2_code":"AV",
    "gn:admin3_code":"05113",
    "gn:asciiname":"Navalmoro",
    "gn:cc2":"ES",
    "gn:country_code":"ES",
    "gn:dem":1032,
    "gn:feature_class":"P",
    "gn:feature_code":"PPL",
    "gn:name":"Navalmoro",
    "gn:population":0,
    "gn:timezone":"Europe/Madrid",
    "iso:country":"ES",
    "name:und_x_variant":[
        "Barrio Navalmoro",
        "Navalmoro"
    ],
    "wof:name":"Navalmoro",
    "wof:placetype":"locality"
},
  "geometry": {"coordinates":[-5.51667,40.33333],"type":"Point"}
}