{
  "type": "Feature",
  "properties": {
    "gn:admin1_code":"58",
    "gn:admin2_code":"LU",
    "gn:admin3_code":"27050.0",
    "gn:asciiname":"Margaride",
    "gn:country_code":"ES",
    "gn:dem":297,
    "gn:feature_class":"P",
    "gn:feature_code":"PPL",
    "gn:name":"Margaride",
    "gn:population":0,
    "gn:timezone":"Europe/Madrid",
    "iso:country":"ES",
    "wof:name":"Margaride",
    "wof:placetype":"locality"
},
  "geometry": {"coordinates":[-7.33921,42.48185],"type":"Point"}
}