{
  "type": "Feature",
  "properties": {
    "gn:admin1_code":"55",
    "gn:admin2_code":"P",
    "gn:admin3_code":"34190",
    "gn:asciiname":"Valles de Valdavia",
    "gn:country_code":"ES",
    "gn:dem":956,
    "gn:feature_class":"P",
    "gn:feature_code":"PPL",
    "gn:name":"Valles de Valdavia",
    "gn:population":0,
    "gn:timezone":"Europe/Madrid",
    "iso:country":"ES",
    "wof:name":"Valles de Valdavia",
    "wof:placetype":"locality"
},
  "geometry": {"coordinates":[-4.63814,42.58135],"type":"Point"}
}