{
  "type": "Feature",
  "properties": {
    "gn:admin1_code":"56",
    "gn:admin2_code":"GI",
    "gn:admin3_code":"17135",
    "gn:asciiname":"els Cellers",
    "gn:country_code":"ES",
    "gn:dem":49,
    "gn:feature_class":"P",
    "gn:feature_code":"PPL",
    "gn:name":"els Cellers",
    "gn:population":0,
    "gn:timezone":"Europe/Madrid",
    "iso:country":"ES",
    "name:cat_x_preferred":[
        "els Cellers"
    ],
    "wof:name":"els Cellers",
    "wof:placetype":"locality"
},
  "geometry": {"coordinates":[2.93,42.31865],"type":"Point"}
}