{
  "type": "Feature",
  "properties": {
    "gn:gn_country":"ES",
    "gn:gn_fcode":"PPLA3",
    "gn:gn_pop":71,
    "gn:population":71,
    "iso:country":"ES",
    "name:azb_x_preferred":[
        "\u0628\u06cc\u06cc\u0627\u0626\u0644\u0633 \u062f \u0628\u0627\u0644\u062f\u0627\u0628\u06cc\u0627"
    ],
    "name:cat_x_preferred":[
        "Villaeles de Valdavia"
    ],
    "name:eng_x_preferred":[
        "Villaeles de Valdavia"
    ],
    "name:eus_x_preferred":[
        "Villaeles de Valdavia"
    ],
    "name:fas_x_preferred":[
        "\u0628\u06cc\u06cc\u0627\u0626\u0644\u0633 \u062f \u0628\u0627\u0644\u062f\u0627\u0628\u06cc\u0627"
    ],
    "name:fra_x_preferred":[
        "Villaeles de Valdavia"
    ],
    "name:glg_x_preferred":[
        "Villaeles de Valdavia"
    ],
    "name:hun_x_preferred":[
        "Villaeles de Valdavia"
    ],
    "name:ina_x_preferred":[
        "Villaeles de Valdavia"
    ],
    "name:ita_x_preferred":[
        "Villaeles de Valdavia"
    ],
    "name:msa_x_preferred":[
        "Villaeles de Valdavia"
    ],
    "name:nan_x_preferred":[
        "Villaeles de Valdavia"
    ],
    "name:nld_x_preferred":[
        "Villaeles de Valdavia"
    ],
    "name:oci_x_preferred":[
        "Villaeles de Valdavia"
    ],
    "name:pol_x_preferred":[
        "Villaeles de Valdavia"
    ],
    "name:por_x_preferred":[
        "Villaeles de Valdavia"
    ],
    "name:rus_x_preferred":[
        "\u0412\u0438\u043b\u044c\u044f\u044d\u043b\u0435\u0441-\u0434\u0435-\u0412\u0430\u043b\u044c\u0434\u0430\u0432\u0438\u0430"
    ],
    "name:spa_x_preferred":[
        "Villaeles de Valdavia"
    ],
    "name:swe_x_preferred":[
        "Villaeles de Valdavia"
    ],
    "name:ukr_x_preferred":[
        "\u0412\u0456\u043b\u044c\u044f\u0435\u043b\u0435\u0441-\u0434\u0435-\u0412\u0430\u043b\u044c\u0434\u0430\u0432\u0456\u044f"
    ],
    "name:uzb_x_preferred":[
        "Villaeles de Valdavia"
    ],
    "name:vie_x_preferred":[
        "Villaeles de Valdavia"
    ],
    "name:war_x_preferred":[
        "Villaeles de Valdavia"
    ],
    "name:zho_x_preferred":[
        "\u6bd4\u5229\u827e\u83b1\u65af\u5fb7\u74e6\u5c14\u8fbe\u7ef4\u4e9a"
    ],
    "qs_pg:aaroncc":"ES",
    "qs_pg:gn_country":"ES",
    "qs_pg:gn_fcode":"PPLA3",
    "qs_pg:gn_pop":71,
    "qs_pg:name":"Villaeles de Valdavia",
    "qs_pg:name_adm0":"Espa\u00f1a",
    "qs_pg:name_adm1":"Castilla y Le\u00f3n",
    "qs_pg:photos_9k":1,
    "qs_pg:photos_9r":1,
    "qs_pg:photos_all":1,
    "qs_pg:photos_sr":0,
    "qs_pg:pop_sr":1,
    "qs_pg:qs_pg_placetype":"locality",
    "qs_pg:qs_pg_placetype_gp":"Town",
    "qs_pg:woe_adm0":23424950,
    "woe:adm0_id":23424950,
    "woe:name_adm0":"Espa\u00f1a",
    "woe:name_adm1":"Castilla y Le\u00f3n",
    "woe:placetype":"Town",
    "wof:name":"Villaeles de Valdavia",
    "wof:placetype":"locality",
    "wof:population":71
},
  "geometry": {"coordinates":[-4.58318,42.56556],"type":"Point"}
}