{
  "type": "Feature",
  "properties": {
    "gn:admin1_code":"52",
    "gn:admin2_code":"TE",
    "gn:admin3_code":"44017",
    "gn:asciiname":"La Canadilla",
    "gn:country_code":"ES",
    "gn:dem":1227,
    "gn:feature_class":"P",
    "gn:feature_code":"PPL",
    "gn:name":"La Ca\u00f1adilla",
    "gn:population":0,
    "gn:timezone":"Europe/Madrid",
    "iso:country":"ES",
    "name:und_x_variant":[
        "La Ca\u00f1adilla"
    ],
    "wof:name":"La Canadilla",
    "wof:placetype":"locality"
},
  "geometry": {"coordinates":[-0.62199,40.73951],"type":"Point"}
}