{
  "type": "Feature",
  "properties": {
    "gn:admin1_code":"39",
    "gn:admin2_code":"S",
    "gn:admin3_code":"39039",
    "gn:asciiname":"Sel de la Carrera",
    "gn:country_code":"ES",
    "gn:dem":575,
    "gn:feature_class":"P",
    "gn:feature_code":"PPL",
    "gn:name":"Sel de la Carrera",
    "gn:population":0,
    "gn:timezone":"Europe/Madrid",
    "iso:country":"ES",
    "wof:name":"Sel de la Carrera",
    "wof:placetype":"locality"
},
  "geometry": {"coordinates":[-3.92658,43.14473],"type":"Point"}
}