{
  "type": "Feature",
  "properties": {
    "gn:gn_country":"ES",
    "gn:gn_fcode":"PPLA3",
    "gn:gn_pop":249,
    "gn:population":249,
    "iso:country":"ES",
    "name:ara_x_preferred":[
        "\u062a\u0648\u0628\u064a\u062f"
    ],
    "name:arg_x_preferred":[
        "Tobet"
    ],
    "name:cat_x_preferred":[
        "Tobed"
    ],
    "name:ceb_x_preferred":[
        "Tobed"
    ],
    "name:deu_x_preferred":[
        "Tobed"
    ],
    "name:eng_x_preferred":[
        "Tobed"
    ],
    "name:eus_x_preferred":[
        "Tobed"
    ],
    "name:fra_x_preferred":[
        "Tobed"
    ],
    "name:hun_x_preferred":[
        "Tobed"
    ],
    "name:ita_x_preferred":[
        "Tobed"
    ],
    "name:kaz_x_preferred":[
        "\u0422\u043e\u0431\u0435\u0434"
    ],
    "name:msa_x_preferred":[
        "Tobed"
    ],
    "name:nan_x_preferred":[
        "Tobed"
    ],
    "name:nld_x_preferred":[
        "Tobed"
    ],
    "name:oci_x_preferred":[
        "Tobed"
    ],
    "name:pol_x_preferred":[
        "Tobed"
    ],
    "name:por_x_preferred":[
        "Tobed"
    ],
    "name:rus_x_preferred":[
        "\u0422\u043e\u0431\u0435\u0434"
    ],
    "name:spa_x_preferred":[
        "Tobed"
    ],
    "name:swe_x_preferred":[
        "Tobed"
    ],
    "name:ukr_x_preferred":[
        "\u0422\u043e\u0431\u0435\u0434"
    ],
    "name:uzb_x_preferred":[
        "Tobed"
    ],
    "name:vie_x_preferred":[
        "Tobed"
    ],
    "name:war_x_preferred":[
        "Tobed"
    ],
    "name:zho_x_preferred":[
        "\u6258\u97e6\u5fb7"
    ],
    "qs_pg:aaroncc":"ES",
    "qs_pg:gn_country":"ES",
    "qs_pg:gn_fcode":"PPLA3",
    "qs_pg:gn_pop":249,
    "qs_pg:name":"Tobed",
    "qs_pg:name_adm0":"Espa\u00f1a",
    "qs_pg:name_adm1":"Arag\u00f3n",
    "qs_pg:photos_9r":0,
    "qs_pg:photos_sr":0,
    "qs_pg:pop_sr":2,
    "qs_pg:qs_pg_placetype":"locality",
    "qs_pg:qs_pg_placetype_gp":"Town",
    "qs_pg:woe_adm0":23424950,
    "woe:adm0_id":23424950,
    "woe:name_adm0":"Espa\u00f1a",
    "woe:name_adm1":"Arag\u00f3n",
    "woe:placetype":"Town",
    "wof:name":"Tobed",
    "wof:placetype":"locality",
    "wof:population":249
},
  "geometry": {"coordinates":[-1.39975,41.33866],"type":"Point"}
}