{
  "type": "Feature",
  "properties": {
    "gn:admin1_code":"59",
    "gn:admin2_code":"VI",
    "gn:admin3_code":"01010",
    "gn:asciiname":"Menoyo",
    "gn:country_code":"ES",
    "gn:dem":462,
    "gn:feature_class":"P",
    "gn:feature_code":"PPL",
    "gn:name":"Menoio",
    "gn:population":0,
    "gn:timezone":"Europe/Madrid",
    "iso:country":"ES",
    "name:eus_x_preferred":[
        "Menoio"
    ],
    "name:fra_x_preferred":[
        "Menoio"
    ],
    "name:spa_x_preferred":[
        "Menoyo"
    ],
    "wof:name":"Menoyo",
    "wof:placetype":"locality"
},
  "geometry": {"coordinates":[-3.07257,43.06889],"type":"Point"}
}