{
  "type": "Feature",
  "properties": {
    "gn:admin1_code":"56",
    "gn:admin2_code":"B",
    "gn:admin3_code":"08902",
    "gn:asciiname":"Vilanova de la Roca",
    "gn:country_code":"ES",
    "gn:dem":96,
    "gn:feature_class":"P",
    "gn:feature_code":"PPL",
    "gn:name":"Vilanova de la Roca",
    "gn:population":0,
    "gn:timezone":"Europe/Madrid",
    "iso:country":"ES",
    "name:cat_x_preferred":[
        "Vilanova de la Roca"
    ],
    "name:eng_x_preferred":[
        "Vilanova de la Roca"
    ],
    "name:eus_x_preferred":[
        "Vilanova de la Roca"
    ],
    "name:oci_x_preferred":[
        "Vilanova de la Roca"
    ],
    "name:spa_x_preferred":[
        "Vilanova Del Valles"
    ],
    "name:spa_x_variant":[
        "Vilanova de la Roca"
    ],
    "wof:name":"Vilanova de la Roca",
    "wof:placetype":"locality"
},
  "geometry": {"coordinates":[2.28583,41.55336],"type":"Point"}
}