{
  "type": "Feature",
  "properties": {
    "gn:admin1_code":"55",
    "gn:admin2_code":"BU",
    "gn:admin3_code":"09427",
    "gn:asciiname":"Villalibado",
    "gn:country_code":"ES",
    "gn:dem":864,
    "gn:feature_class":"P",
    "gn:feature_code":"PPL",
    "gn:name":"Villalibado",
    "gn:population":0,
    "gn:timezone":"Europe/Madrid",
    "iso:country":"ES",
    "wof:name":"Villalibado",
    "wof:placetype":"locality"
},
  "geometry": {"coordinates":[-3.97568,42.52538],"type":"Point"}
}