{
  "type": "Feature",
  "properties": {
    "gn:admin1_code":"34",
    "gn:admin2_code":"O",
    "gn:admin3_code":"33073",
    "gn:asciiname":"Calabazos",
    "gn:country_code":"ES",
    "gn:dem":442,
    "gn:feature_class":"P",
    "gn:feature_code":"PPL",
    "gn:name":"Calabazos",
    "gn:population":0,
    "gn:timezone":"Europe/Madrid",
    "iso:country":"ES",
    "wof:name":"Calabazos",
    "wof:placetype":"locality"
},
  "geometry": {"coordinates":[-6.31402,43.31483],"type":"Point"}
}