{
  "type": "Feature",
  "properties": {
    "gn:admin1_code":"55",
    "gn:admin2_code":"BU",
    "gn:admin3_code":"09448",
    "gn:asciiname":"Villafuertes",
    "gn:country_code":"ES",
    "gn:dem":839,
    "gn:feature_class":"P",
    "gn:feature_code":"PPL",
    "gn:name":"Villafuertes",
    "gn:population":0,
    "gn:timezone":"Europe/Madrid",
    "iso:country":"ES",
    "wof:name":"Villafuertes",
    "wof:placetype":"locality"
},
  "geometry": {"coordinates":[-3.80147,42.17658],"type":"Point"}
}