{
  "type": "Feature",
  "properties": {
    "gn:admin1_code":"58",
    "gn:admin2_code":"LU",
    "gn:admin3_code":"27050",
    "gn:asciiname":"Oporto",
    "gn:country_code":"ES",
    "gn:dem":574,
    "gn:feature_class":"P",
    "gn:feature_code":"PPL",
    "gn:name":"Oporto",
    "gn:population":0,
    "gn:timezone":"Europe/Madrid",
    "iso:country":"ES",
    "wof:name":"Oporto",
    "wof:placetype":"locality"
},
  "geometry": {"coordinates":[-7.09648,42.37248],"type":"Point"}
}