{
  "type": "Feature",
  "properties": {
    "gn:admin1_code":"58",
    "gn:admin2_code":"C",
    "gn:admin3_code":"15077",
    "gn:asciiname":"Ser",
    "gn:country_code":"ES",
    "gn:dem":391,
    "gn:feature_class":"P",
    "gn:feature_code":"PPL",
    "gn:name":"Ser",
    "gn:population":0,
    "gn:timezone":"Europe/Madrid",
    "iso:country":"ES",
    "wof:name":"Ser",
    "wof:placetype":"locality"
},
  "geometry": {"coordinates":[-8.78386,43.01102],"type":"Point"}
}