{
  "type": "Feature",
  "properties": {
    "gn:admin1_code":"51",
    "gn:admin2_code":"GR",
    "gn:admin3_code":"18105",
    "gn:asciiname":"Barcinas",
    "gn:country_code":"ES",
    "gn:dem":795,
    "gn:feature_class":"P",
    "gn:feature_code":"PPL",
    "gn:name":"Barcinas",
    "gn:population":0,
    "gn:timezone":"Europe/Madrid",
    "iso:country":"ES",
    "name:und_x_variant":[
        "Caser\u00edo Barcinas",
        "Barcinas"
    ],
    "wof:name":"Barcinas",
    "wof:placetype":"locality"
},
  "geometry": {"coordinates":[-3.54938,37.35989],"type":"Point"}
}