{
  "type": "Feature",
  "properties": {
    "gn:admin1_code":"34",
    "gn:admin2_code":"O",
    "gn:admin3_code":"33073",
    "gn:asciiname":"Conto",
    "gn:country_code":"ES",
    "gn:dem":300,
    "gn:feature_class":"P",
    "gn:feature_code":"PPL",
    "gn:name":"Conto",
    "gn:population":0,
    "gn:timezone":"Europe/Madrid",
    "iso:country":"ES",
    "wof:name":"Conto",
    "wof:placetype":"locality"
},
  "geometry": {"coordinates":[-6.57684,43.4085],"type":"Point"}
}