{
  "type": "Feature",
  "properties": {
    "gn:gn_country":"ES",
    "gn:gn_fcode":"PPLA3",
    "gn:gn_pop":119,
    "gn:population":119,
    "iso:country":"ES",
    "name:ara_x_preferred":[
        "\u0643\u0648\u0628\u0648 \u062f\u064a \u0628\u0648\u0631\u064a\u0628\u0627"
    ],
    "name:arg_x_preferred":[
        "Cubo de Bureba"
    ],
    "name:cat_x_preferred":[
        "Cubo de Bureba"
    ],
    "name:eng_x_preferred":[
        "Cubo de Bureba"
    ],
    "name:eus_x_preferred":[
        "Cubo de Bureba"
    ],
    "name:fas_x_preferred":[
        "\u06a9\u0648\u0628\u0648 \u062f \u0628\u0648\u0631\u0628\u0627"
    ],
    "name:fra_x_preferred":[
        "Cubo de Bureba"
    ],
    "name:glg_x_preferred":[
        "Cubo de Bureba"
    ],
    "name:haw_x_preferred":[
        "Cubo de Bureba"
    ],
    "name:hun_x_preferred":[
        "Cubo de Bureba"
    ],
    "name:ina_x_preferred":[
        "Cubo de Bureba"
    ],
    "name:ita_x_preferred":[
        "Cubo de Bureba"
    ],
    "name:lad_x_preferred":[
        "Cubo de Bureba"
    ],
    "name:msa_x_preferred":[
        "Cubo de Bureba"
    ],
    "name:nan_x_preferred":[
        "Cubo de Bureba"
    ],
    "name:nld_x_preferred":[
        "Cubo de Bureba"
    ],
    "name:oci_x_preferred":[
        "Cubo de Bureba"
    ],
    "name:pol_x_preferred":[
        "Cubo de Bureba"
    ],
    "name:por_x_preferred":[
        "Cubo de Bureba"
    ],
    "name:rus_x_preferred":[
        "\u041a\u0443\u0431\u043e-\u0434\u0435-\u0411\u0443\u0440\u0435\u0431\u0430"
    ],
    "name:spa_x_preferred":[
        "Cubo de Bureba"
    ],
    "name:swe_x_preferred":[
        "Cubo de Bureba"
    ],
    "name:ukr_x_preferred":[
        "\u041a\u0443\u0431\u043e-\u0434\u0435-\u0411\u0443\u0440\u0435\u0431\u0430"
    ],
    "name:unk_x_variant":[
        "Cubo"
    ],
    "name:vie_x_preferred":[
        "Cubo de Bureba"
    ],
    "name:war_x_preferred":[
        "Cubo de Bureba"
    ],
    "name:zho_x_preferred":[
        "\u5e93\u6c83\u5fb7\u6b66\u96f7\u74e6"
    ],
    "qs_pg:aaroncc":"ES",
    "qs_pg:gn_country":"ES",
    "qs_pg:gn_fcode":"PPLA3",
    "qs_pg:gn_pop":119,
    "qs_pg:name":"Cubo de Bureba",
    "qs_pg:name_adm0":"Espa\u00f1a",
    "qs_pg:name_adm1":"Castilla y Le\u00f3n",
    "qs_pg:photos_9k":1,
    "qs_pg:photos_9r":1,
    "qs_pg:photos_all":1,
    "qs_pg:photos_sr":0,
    "qs_pg:pop_sr":1,
    "qs_pg:qs_pg_placetype":"locality",
    "qs_pg:qs_pg_placetype_gp":"Town",
    "qs_pg:woe_adm0":23424950,
    "woe:adm0_id":23424950,
    "woe:name_adm0":"Espa\u00f1a",
    "woe:name_adm1":"Castilla y Le\u00f3n",
    "woe:placetype":"Town",
    "wof:name":"Cubo de Bureba",
    "wof:placetype":"locality",
    "wof:population":119
},
  "geometry": {"coordinates":[-3.20626,42.64011],"type":"Point"}
}