{
  "type": "Feature",
  "properties": {
    "gn:country":"ES",
    "gn:fcode":"PPLA3",
    "gn:population":684,
    "iso:country":"ES",
    "name:ara_x_preferred":[
        "\u0645\u0627\u0626\u064a\u0648\u060c \u0622\u0628\u0644\u0629"
    ],
    "name:ara_x_variant":[
        "\u0645\u0627\u0626\u064a\u0648"
    ],
    "name:ast_x_preferred":[
        "Maello"
    ],
    "name:azb_x_preferred":[
        "\u0645\u0627\u0626\u06cc\u0648"
    ],
    "name:cat_x_preferred":[
        "Maello"
    ],
    "name:ceb_x_preferred":[
        "Maello"
    ],
    "name:eng_x_preferred":[
        "Maello"
    ],
    "name:eus_x_preferred":[
        "Maello"
    ],
    "name:fas_x_preferred":[
        "\u0645\u0627\u0626\u06cc\u0648"
    ],
    "name:fra_x_preferred":[
        "Maello"
    ],
    "name:hun_x_preferred":[
        "Maello"
    ],
    "name:ina_x_preferred":[
        "Maello"
    ],
    "name:ita_x_preferred":[
        "Maello"
    ],
    "name:kaz_x_preferred":[
        "\u041c\u0430\u044d\u043b\u044c\u043e"
    ],
    "name:lit_x_preferred":[
        "Maelja"
    ],
    "name:mkd_x_preferred":[
        "\u041c\u0430\u0435\u0459\u043e"
    ],
    "name:msa_x_preferred":[
        "Maello"
    ],
    "name:nld_x_preferred":[
        "Maello"
    ],
    "name:oci_x_preferred":[
        "Maello"
    ],
    "name:pol_x_preferred":[
        "Maello"
    ],
    "name:por_x_preferred":[
        "Maello"
    ],
    "name:rup_x_preferred":[
        "Maello"
    ],
    "name:rus_x_preferred":[
        "\u041c\u0430\u044d\u043b\u044c\u043e"
    ],
    "name:spa_x_preferred":[
        "Maello"
    ],
    "name:swe_x_preferred":[
        "Maello"
    ],
    "name:ukr_x_preferred":[
        "\u041c\u0430\u0435\u043b\u044c\u0439\u043e"
    ],
    "name:uzb_x_preferred":[
        "Maello"
    ],
    "name:vie_x_preferred":[
        "Maello"
    ],
    "name:war_x_preferred":[
        "Maello"
    ],
    "name:zho_x_preferred":[
        "\u8fc8\u7565"
    ],
    "qs_pg:aaroncc":"ES",
    "qs_pg:gn_country":"ES",
    "qs_pg:gn_fcode":"PPLA3",
    "qs_pg:gn_pop":684,
    "qs_pg:name":"Maello",
    "qs_pg:name_adm0":"Espa\u00f1a",
    "qs_pg:name_adm1":"Castilla y Le\u00f3n",
    "qs_pg:photos_9k":1,
    "qs_pg:photos_9r":1,
    "qs_pg:photos_all":1,
    "qs_pg:photos_sr":0,
    "qs_pg:pop_sr":2,
    "qs_pg:qs_pg_placetype":"locality",
    "qs_pg:qs_pg_placetype_gp":"Town",
    "qs_pg:woe_adm0":23424950,
    "woe:adm0_id":23424950,
    "woe:name_adm0":"Espa\u00f1a",
    "woe:name_adm1":"Castilla y Le\u00f3n",
    "woe:placetype":"Town",
    "wof:name":"Maello",
    "wof:placetype":"locality",
    "wof:population":684
},
  "geometry": {"coordinates":[-4.51186,40.80929],"type":"Point"}
}