{
  "type": "Feature",
  "properties": {
    "gn:admin1_code":"58",
    "gn:admin2_code":"OR",
    "gn:admin3_code":"32049",
    "gn:asciiname":"A Medorra",
    "gn:country_code":"ES",
    "gn:dem":857,
    "gn:feature_class":"P",
    "gn:feature_code":"PPL",
    "gn:name":"A Medorra",
    "gn:population":0,
    "gn:timezone":"Europe/Madrid",
    "iso:country":"ES",
    "wof:name":"A Medorra",
    "wof:placetype":"locality"
},
  "geometry": {"coordinates":[-7.46667,42.31667],"type":"Point"}
}