{
  "type": "Feature",
  "properties": {
    "gn:country":"ES",
    "gn:fcode":"PPLA3",
    "gn:population":91,
    "iso:country":"ES",
    "name:ara_x_preferred":[
        "\u0628\u0648\u0628\u064a\u0631\u0643\u0627"
    ],
    "name:arg_x_preferred":[
        "Bubierca"
    ],
    "name:azb_x_preferred":[
        "\u0628\u0648\u0628\u06cc\u0631\u06a9\u0627"
    ],
    "name:cat_x_preferred":[
        "Bubierca"
    ],
    "name:ceb_x_preferred":[
        "Bubierca"
    ],
    "name:deu_x_preferred":[
        "Bubierca"
    ],
    "name:eng_x_preferred":[
        "Bubierca"
    ],
    "name:eus_x_preferred":[
        "Bubierca"
    ],
    "name:fas_x_preferred":[
        "\u0628\u0648\u0628\u06cc\u0631\u06a9\u0627"
    ],
    "name:fra_x_preferred":[
        "Bubierca"
    ],
    "name:glg_x_preferred":[
        "Bubierca"
    ],
    "name:hak_x_preferred":[
        "Bubierca"
    ],
    "name:hun_x_preferred":[
        "Bubierca"
    ],
    "name:ita_x_preferred":[
        "Bubierca"
    ],
    "name:kaz_x_preferred":[
        "\u0411\u0443\u0431\u044c\u0435\u0440\u043a\u0430"
    ],
    "name:lat_x_preferred":[
        "Bubierca"
    ],
    "name:msa_x_preferred":[
        "Bubierca"
    ],
    "name:nan_x_preferred":[
        "Bubierca"
    ],
    "name:nld_x_preferred":[
        "Bubierca"
    ],
    "name:oci_x_preferred":[
        "Bubierca"
    ],
    "name:pol_x_preferred":[
        "Bubierca"
    ],
    "name:por_x_preferred":[
        "Bubierca"
    ],
    "name:rus_x_preferred":[
        "\u0411\u0443\u0431\u044c\u0435\u0440\u043a\u0430"
    ],
    "name:spa_x_preferred":[
        "Bubierca"
    ],
    "name:swe_x_preferred":[
        "Bubierca"
    ],
    "name:ukr_x_preferred":[
        "\u0411\u0443\u0431'\u0454\u0440\u043a\u0430"
    ],
    "name:uzb_x_preferred":[
        "Bubierca"
    ],
    "name:vie_x_preferred":[
        "Bubierca"
    ],
    "name:war_x_preferred":[
        "Bubierca"
    ],
    "name:zho_x_preferred":[
        "\u5e03\u7ef4\u8036\u5c14\u5361"
    ],
    "qs_pg:aaroncc":"ES",
    "qs_pg:gn_country":"ES",
    "qs_pg:gn_fcode":"PPLA3",
    "qs_pg:gn_pop":91,
    "qs_pg:name":"Bubierca",
    "qs_pg:name_adm0":"Espa\u00f1a",
    "qs_pg:name_adm1":"Arag\u00f3n",
    "qs_pg:photos_9r":0,
    "qs_pg:photos_sr":0,
    "qs_pg:pop_sr":1,
    "qs_pg:qs_pg_placetype":"locality",
    "qs_pg:qs_pg_placetype_gp":"Town",
    "qs_pg:woe_adm0":23424950,
    "woe:adm0_id":23424950,
    "woe:name_adm0":"Espa\u00f1a",
    "woe:name_adm1":"Arag\u00f3n",
    "woe:placetype":"Town",
    "wof:name":"Bubierca",
    "wof:placetype":"locality",
    "wof:population":91
},
  "geometry": {"coordinates":[-1.85386,41.31482],"type":"Point"}
}