{
  "type": "Feature",
  "properties": {
    "gn:admin1_code":"58",
    "gn:admin2_code":"OR",
    "gn:admin3_code":"32017",
    "gn:asciiname":"Trigal",
    "gn:country_code":"ES",
    "gn:dem":680,
    "gn:feature_class":"P",
    "gn:feature_code":"PPL",
    "gn:name":"Trigal",
    "gn:population":0,
    "gn:timezone":"Europe/Madrid",
    "iso:country":"ES",
    "wof:name":"Trigal",
    "wof:placetype":"locality"
},
  "geometry": {"coordinates":[-6.84515,42.38509000000001],"type":"Point"}
}