{
  "type": "Feature",
  "properties": {
    "gn:admin1_code":"59",
    "gn:admin2_code":"SS",
    "gn:admin3_code":"20056",
    "gn:asciiname":"Astigarribia",
    "gn:country_code":"ES",
    "gn:dem":20,
    "gn:feature_class":"P",
    "gn:feature_code":"PPL",
    "gn:name":"Astigarribia",
    "gn:population":0,
    "gn:timezone":"Europe/Madrid",
    "iso:country":"ES",
    "name:eus_x_preferred":[
        "Astigarribia"
    ],
    "wof:name":"Astigarribia",
    "wof:placetype":"locality"
},
  "geometry": {"coordinates":[-2.37589,43.27843],"type":"Point"}
}