{
  "type": "Feature",
  "properties": {
    "gn:admin1_code":"55",
    "gn:admin2_code":"P",
    "gn:admin3_code":"34037",
    "gn:asciiname":"Polvorosa",
    "gn:country_code":"ES",
    "gn:dem":906,
    "gn:feature_class":"P",
    "gn:feature_code":"PPL",
    "gn:name":"Polvorosa",
    "gn:population":0,
    "gn:timezone":"Europe/Madrid",
    "iso:country":"ES",
    "wof:name":"Polvorosa",
    "wof:placetype":"locality"
},
  "geometry": {"coordinates":[-4.59947,42.6116],"type":"Point"}
}