{
  "type": "Feature",
  "properties": {
    "gn:admin1_code":"58",
    "gn:admin2_code":"LU",
    "gn:admin3_code":"27034",
    "gn:asciiname":"Lajo",
    "gn:country_code":"ES",
    "gn:dem":731,
    "gn:feature_class":"P",
    "gn:feature_code":"PPL",
    "gn:name":"Lajo",
    "gn:population":0,
    "gn:timezone":"Europe/Madrid",
    "iso:country":"ES",
    "wof:name":"Lajo",
    "wof:placetype":"locality"
},
  "geometry": {"coordinates":[-6.86667,42.96667],"type":"Point"}
}