{
  "type": "Feature",
  "properties": {
    "gn:admin1_code":"58",
    "gn:admin2_code":"LU",
    "gn:admin3_code":"27034",
    "gn:asciiname":"Lajo",
    "gn:country_code":"ES",
    "gn:dem":731,
    "gn:feature_class":"P",
    "gn:feature_code":"PPL",
    "gn:name":"Lajo",
    "gn:population":0,
    "gn:timezone":"Europe/Madrid",
    "iso:country":"ES",
    "name:cat_x_preferred":[
        "L'Atgi\u00e8r"
    ],
    "name:ceb_x_preferred":[
        "Lajo"
    ],
    "name:deu_x_preferred":[
        "Lajo"
    ],
    "name:eus_x_preferred":[
        "Lajo"
    ],
    "name:fra_x_preferred":[
        "Lajo"
    ],
    "name:hun_x_preferred":[
        "Lajo"
    ],
    "name:ita_x_preferred":[
        "Lajo"
    ],
    "name:kaz_x_preferred":[
        "\u041b\u0430\u0436\u043e"
    ],
    "name:lat_x_preferred":[
        "Lajo"
    ],
    "name:lmo_x_preferred":[
        "Lajo"
    ],
    "name:msa_x_preferred":[
        "Lajo"
    ],
    "name:nld_x_preferred":[
        "Lajo"
    ],
    "name:oci_x_preferred":[
        "L'Atgi\u00e8r"
    ],
    "name:pms_x_preferred":[
        "Lajo"
    ],
    "name:pol_x_preferred":[
        "Lajo"
    ],
    "name:por_x_preferred":[
        "Lajo"
    ],
    "name:ron_x_preferred":[
        "Lajo"
    ],
    "name:slk_x_preferred":[
        "Lajo"
    ],
    "name:spa_x_preferred":[
        "Lajo"
    ],
    "name:swe_x_preferred":[
        "Lajo"
    ],
    "name:ukr_x_preferred":[
        "\u041b\u0430\u0436\u043e"
    ],
    "name:urd_x_preferred":[
        "\u0644\u0627\u062c\u0648"
    ],
    "name:vie_x_preferred":[
        "Lajo"
    ],
    "name:vol_x_preferred":[
        "Lajo"
    ],
    "name:war_x_preferred":[
        "Lajo"
    ],
    "wof:name":"Lajo",
    "wof:placetype":"locality"
},
  "geometry": {"coordinates":[-6.86667,42.96667],"type":"Point"}
}