{
  "type": "Feature",
  "properties": {
    "gn:admin1_code":"55",
    "gn:admin2_code":"AV",
    "gn:admin3_code":"05027",
    "gn:asciiname":"Rivilla de Barajas",
    "gn:country_code":"ES",
    "gn:dem":949,
    "gn:feature_class":"P",
    "gn:feature_code":"PPL",
    "gn:name":"Rivilla de Barajas",
    "gn:population":0,
    "gn:timezone":"Europe/Madrid",
    "iso:country":"ES",
    "name:und_x_variant":[
        "Barrio Rivilla",
        "Rivilla",
        "Rivilla de Barajas"
    ],
    "wof:name":"Rivilla de Barajas",
    "wof:placetype":"locality"
},
  "geometry": {"coordinates":[-4.76256,40.79986],"type":"Point"}
}