{
  "type": "Feature",
  "properties": {
    "gn:admin1_code":"58",
    "gn:admin2_code":"LU",
    "gn:admin3_code":"27050",
    "gn:asciiname":"Casa do Vello",
    "gn:country_code":"ES",
    "gn:dem":467,
    "gn:feature_class":"P",
    "gn:feature_code":"PPL",
    "gn:name":"Casa do Vello",
    "gn:population":0,
    "gn:timezone":"Europe/Madrid",
    "iso:country":"ES",
    "wof:name":"Casa do Vello",
    "wof:placetype":"locality"
},
  "geometry": {"coordinates":[-7.16999,42.52676],"type":"Point"}
}