{
  "type": "Feature",
  "properties": {
    "gn:country":"ES",
    "gn:fcode":"PPL",
    "gn:population":0,
    "iso:country":"ES",
    "name:arg_x_preferred":[
        "Covarrubias"
    ],
    "name:cat_x_preferred":[
        "Covarrubias"
    ],
    "name:ceb_x_preferred":[
        "Covarrubias"
    ],
    "name:deu_x_preferred":[
        "Covarrubias"
    ],
    "name:fra_x_preferred":[
        "Covarrubias"
    ],
    "name:pol_x_preferred":[
        "Covarrubias"
    ],
    "name:spa_x_preferred":[
        "Covarrubias"
    ],
    "name:swe_x_preferred":[
        "Covarrubias"
    ],
    "name:vie_x_preferred":[
        "Covarrubias"
    ],
    "qs_pg:aaroncc":"ES",
    "qs_pg:gn_country":"ES",
    "qs_pg:gn_fcode":"PPL",
    "qs_pg:gn_pop":0,
    "qs_pg:name":"Covarrubias",
    "qs_pg:name_adm0":"Espa\u00f1a",
    "qs_pg:name_adm1":"Castilla y Le\u00f3n",
    "qs_pg:photos_9r":0,
    "qs_pg:photos_sr":0,
    "qs_pg:pop_sr":0,
    "qs_pg:qs_pg_placetype":"locality",
    "qs_pg:qs_pg_placetype_gp":"Town",
    "qs_pg:woe_adm0":23424950,
    "woe:adm0_id":23424950,
    "woe:name_adm0":"Espa\u00f1a",
    "woe:name_adm1":"Castilla y Le\u00f3n",
    "woe:placetype":"Town",
    "wof:name":"Covarrubias",
    "wof:placetype":"locality"
},
  "geometry": {"coordinates":[-2.5701,41.4478],"type":"Point"}
}