{
  "type": "Feature",
  "properties": {
    "gn:admin1_code":"34",
    "gn:admin2_code":"O",
    "gn:admin3_code":"33056",
    "gn:asciiname":"Bones",
    "gn:country_code":"ES",
    "gn:dem":91,
    "gn:feature_class":"P",
    "gn:feature_code":"PPL",
    "gn:name":"Bones",
    "gn:population":0,
    "gn:timezone":"Europe/Madrid",
    "iso:country":"ES",
    "wof:name":"Bones",
    "wof:placetype":"locality"
},
  "geometry": {"coordinates":[-5.12169,43.46108],"type":"Point"}
}