{
  "type": "Feature",
  "properties": {
    "gn:admin1_code":"34",
    "gn:admin2_code":"O",
    "gn:admin3_code":"33002",
    "gn:asciiname":"Casomera",
    "gn:country_code":"ES",
    "gn:dem":636,
    "gn:feature_class":"P",
    "gn:feature_code":"PPL",
    "gn:name":"Casomera",
    "gn:population":0,
    "gn:timezone":"Europe/Madrid",
    "iso:country":"ES",
    "name:ast_x_preferred":[
        "Casomera"
    ],
    "name:deu_x_preferred":[
        "Casomera"
    ],
    "name:spa_x_preferred":[
        "Casomera"
    ],
    "wof:name":"Casomera",
    "wof:placetype":"locality"
},
  "geometry": {"coordinates":[-5.57811,43.08096],"type":"Point"}
}