{
  "type": "Feature",
  "properties": {
    "gn:admin1_code":"34",
    "gn:admin2_code":"O",
    "gn:admin3_code":"33073",
    "gn:asciiname":"La Prohida",
    "gn:country_code":"ES",
    "gn:dem":429,
    "gn:feature_class":"P",
    "gn:feature_code":"PPL",
    "gn:name":"La Prohida",
    "gn:population":0,
    "gn:timezone":"Europe/Madrid",
    "iso:country":"ES",
    "wof:name":"La Prohida",
    "wof:placetype":"locality"
},
  "geometry": {"coordinates":[-6.45146,43.29517],"type":"Point"}
}