{
  "type": "Feature",
  "properties": {
    "gn:admin1_code":"60",
    "gn:admin2_code":"A",
    "gn:admin3_code":"03089",
    "gn:asciiname":"Derramador",
    "gn:country_code":"ES",
    "gn:dem":529,
    "gn:feature_class":"P",
    "gn:feature_code":"PPL",
    "gn:name":"Derramador",
    "gn:population":0,
    "gn:timezone":"Europe/Madrid",
    "iso:country":"ES",
    "name:und_x_variant":[
        "Caser\u00edo Derramador",
        "Derramador"
    ],
    "wof:name":"Derramador",
    "wof:placetype":"locality"
},
  "geometry": {"coordinates":[-0.94214,38.43184],"type":"Point"}
}