{
  "type": "Feature",
  "properties": {
    "gn:country":"ES",
    "gn:fcode":"PPLA3",
    "gn:population":246,
    "iso:country":"ES",
    "name:ara_x_preferred":[
        "\u0628\u0648\u0631\u062a\u064a\u0644 \u062f\u064a \u0645\u0648\u0631\u064a\u0644\u0627"
    ],
    "name:arg_x_preferred":[
        "Lo Portiel"
    ],
    "name:cat_x_preferred":[
        "Portell de Morella"
    ],
    "name:eng_x_preferred":[
        "Portell de Morella"
    ],
    "name:eus_x_preferred":[
        "Portell de Morella"
    ],
    "name:fra_x_preferred":[
        "Portell de Morella"
    ],
    "name:hun_x_preferred":[
        "Portell de Morella"
    ],
    "name:ita_x_preferred":[
        "Portell de Morella"
    ],
    "name:msa_x_preferred":[
        "Portell de Morella"
    ],
    "name:nan_x_preferred":[
        "Portell de Morella"
    ],
    "name:nld_x_preferred":[
        "Portell de Morella"
    ],
    "name:oci_x_preferred":[
        "Portell de Morella"
    ],
    "name:pol_x_preferred":[
        "Portell de Morella"
    ],
    "name:por_x_preferred":[
        "Portell de Morella"
    ],
    "name:rus_x_preferred":[
        "\u041f\u043e\u0440\u0442\u0435\u043b\u044c-\u0434\u0435-\u041c\u043e\u0440\u0435\u043b\u044c\u044f"
    ],
    "name:spa_x_preferred":[
        "Portell de Morella"
    ],
    "name:swe_x_preferred":[
        "Portell de Morella"
    ],
    "name:ukr_x_preferred":[
        "\u041f\u043e\u0440\u0442\u0435\u043b\u044c-\u0434\u0435-\u041c\u043e\u0440\u0435\u043b\u044c\u044f"
    ],
    "name:uzb_x_preferred":[
        "Portell de Morella"
    ],
    "name:vie_x_preferred":[
        "Portell de Morella"
    ],
    "name:war_x_preferred":[
        "Portell de Morella"
    ],
    "name:zho_x_preferred":[
        "\u6ce2\u5c14\u7279\u5229\u5fb7\u83ab\u96f7\u5229\u4e9a"
    ],
    "qs_pg:aaroncc":"ES",
    "qs_pg:gn_country":"ES",
    "qs_pg:gn_fcode":"PPLA3",
    "qs_pg:gn_pop":246,
    "qs_pg:name":"Portell de Morella",
    "qs_pg:name_adm0":"Espa\u00f1a",
    "qs_pg:name_adm1":"Comunitat Valenciana",
    "qs_pg:photos":15,
    "qs_pg:photos_1k":3,
    "qs_pg:photos_9k":1,
    "qs_pg:photos_9r":1,
    "qs_pg:photos_all":15,
    "qs_pg:photos_sr":1,
    "qs_pg:pop_sr":2,
    "qs_pg:qs_pg_placetype":"locality",
    "qs_pg:qs_pg_placetype_gp":"Town",
    "qs_pg:woe_adm0":23424950,
    "woe:adm0_id":23424950,
    "woe:name_adm0":"Espa\u00f1a",
    "woe:name_adm1":"Comunitat Valenciana",
    "woe:placetype":"Town",
    "wof:name":"Portell de Morella",
    "wof:placetype":"locality",
    "wof:population":246
},
  "geometry": {"coordinates":[-0.26249,40.53267],"type":"Point"}
}