{
  "type": "Feature",
  "properties": {
    "gn:admin1_code":"58",
    "gn:admin2_code":"LU",
    "gn:admin3_code":"27045",
    "gn:asciiname":"Santin",
    "gn:country_code":"ES",
    "gn:dem":981,
    "gn:feature_class":"P",
    "gn:feature_code":"PPL",
    "gn:name":"Sant\u00edn",
    "gn:population":0,
    "gn:timezone":"Europe/Madrid",
    "iso:country":"ES",
    "wof:name":"Santin",
    "wof:placetype":"locality"
},
  "geometry": {"coordinates":[-7.05716,42.65605],"type":"Point"}
}