{
  "type": "Feature",
  "properties": {
    "gn:admin1_code":"56",
    "gn:admin2_code":"GI",
    "gn:admin3_code":"17044",
    "gn:asciiname":"Serina",
    "gn:cc2":"ES",
    "gn:country_code":"ES",
    "gn:dem":125,
    "gn:feature_class":"P",
    "gn:feature_code":"PPL",
    "gn:name":"Seri\u00f1\u00e1",
    "gn:population":0,
    "gn:timezone":"Europe/Madrid",
    "iso:country":"ES",
    "name:und_x_variant":[
        "Caser\u00edo de Seri\u00f1\u00e1",
        "Caser\u00edo Seri\u00f1a",
        "Seri\u00f1\u00e1"
    ],
    "wof:name":"Serina",
    "wof:placetype":"locality"
},
  "geometry": {"coordinates":[2.88333,41.86667],"type":"Point"}
}