{
  "type": "Feature",
  "properties": {
    "gn:admin1_code":"56",
    "gn:admin2_code":"L",
    "gn:admin3_code":"25209",
    "gn:asciiname":"Sorre",
    "gn:country_code":"ES",
    "gn:dem":1075,
    "gn:feature_class":"P",
    "gn:feature_code":"PPL",
    "gn:name":"Sorr\u00e9",
    "gn:population":0,
    "gn:timezone":"Europe/Madrid",
    "iso:country":"ES",
    "name:fra_x_preferred":[
        "Sorre"
    ],
    "name:und_x_variant":[
        "Sorr\u00e9"
    ],
    "wof:name":"Sorre",
    "wof:placetype":"locality"
},
  "geometry": {"coordinates":[1.09807,42.45251],"type":"Point"}
}