{
  "type": "Feature",
  "properties": {
    "gn:admin1_code":"51",
    "gn:admin2_code":"H",
    "gn:admin3_code":"21025",
    "gn:asciiname":"Valconejo",
    "gn:cc2":"ES",
    "gn:country_code":"ES",
    "gn:dem":572,
    "gn:feature_class":"P",
    "gn:feature_code":"PPL",
    "gn:name":"Valconejo",
    "gn:population":0,
    "gn:timezone":"Europe/Madrid",
    "iso:country":"ES",
    "name:und_x_variant":[
        "Caser\u00edo Valconejo",
        "Valconejo"
    ],
    "wof:name":"Valconejo",
    "wof:placetype":"locality"
},
  "geometry": {"coordinates":[-6.85,37.91667],"type":"Point"}
}