{
  "type": "Feature",
  "properties": {
    "gn:admin1_code":"58",
    "gn:admin2_code":"OR",
    "gn:admin3_code":"32070",
    "gn:asciiname":"Argas",
    "gn:country_code":"ES",
    "gn:dem":825,
    "gn:feature_class":"P",
    "gn:feature_code":"PPL",
    "gn:name":"Argas",
    "gn:population":0,
    "gn:timezone":"Europe/Madrid",
    "iso:country":"ES",
    "name:ceb_x_preferred":[
        "Argas"
    ],
    "name:deu_x_preferred":[
        "Argas"
    ],
    "name:fas_x_preferred":[
        "\u0622\u0631\u06af\u0627\u0633"
    ],
    "name:fra_x_preferred":[
        "Argas"
    ],
    "name:ind_x_preferred":[
        "Caplak unggas"
    ],
    "name:nav_x_preferred":[
        "Naa\u02bcah\u00f3\u00f3hai biya\u02bc"
    ],
    "name:por_x_preferred":[
        "Argas"
    ],
    "name:rus_x_preferred":[
        "\u0410\u0440\u0433\u0430\u0441"
    ],
    "name:swe_x_preferred":[
        "Argas"
    ],
    "name:tur_x_preferred":[
        "Argas"
    ],
    "name:und_x_variant":[
        "San Silvestre",
        "Argas"
    ],
    "name:war_x_preferred":[
        "Argas"
    ],
    "wof:name":"Argas",
    "wof:placetype":"locality"
},
  "geometry": {"coordinates":[-7.33754,42.3785],"type":"Point"}
}