{
  "type": "Feature",
  "properties": {
    "iso:country":"ES",
    "wof:name":"Miribilla",
    "wof:placetype":"neighbourhood"
},
  "geometry": {"coordinates":[-2.9275227687123,43.25057751681587],"type":"Point"}
}