{
  "type": "Feature",
  "properties": {
    "gn:admin1_code":"54",
    "gn:admin2_code":"TO",
    "gn:admin3_code":"45102",
    "gn:asciiname":"Higares",
    "gn:country_code":"ES",
    "gn:dem":512,
    "gn:feature_class":"P",
    "gn:feature_code":"PPL",
    "gn:name":"Higares",
    "gn:population":0,
    "gn:timezone":"Europe/Madrid",
    "iso:country":"ES",
    "name:und_x_variant":[
        "Dehesa Higares",
        "Higares"
    ],
    "wof:name":"Higares",
    "wof:placetype":"locality"
},
  "geometry": {"coordinates":[-3.92973,39.91322],"type":"Point"}
}