{
  "type": "Feature",
  "properties": {
    "gn:admin1_code":"58",
    "gn:admin2_code":"LU",
    "gn:admin3_code":"27020",
    "gn:asciiname":"Rocha",
    "gn:cc2":"ES",
    "gn:country_code":"ES",
    "gn:dem":564,
    "gn:feature_class":"P",
    "gn:feature_code":"PPL",
    "gn:name":"Rocha",
    "gn:population":0,
    "gn:timezone":"Europe/Madrid",
    "iso:country":"ES",
    "name:ceb_x_preferred":[
        "Rocha"
    ],
    "name:deu_x_preferred":[
        "Rocha"
    ],
    "name:fin_x_preferred":[
        "Rocha"
    ],
    "name:fra_x_preferred":[
        "Rocha"
    ],
    "name:heb_x_preferred":[
        "\u05e8\u05d5\u05e9\u05d4"
    ],
    "name:hsb_x_preferred":[
        "Rocha"
    ],
    "name:ita_x_preferred":[
        "Rocha"
    ],
    "name:nld_x_preferred":[
        "Rocha"
    ],
    "name:pol_x_preferred":[
        "Rocha"
    ],
    "name:por_x_preferred":[
        "Rocha"
    ],
    "name:rus_x_preferred":[
        "\u0420\u043e\u0447\u0430"
    ],
    "name:slk_x_preferred":[
        "Rocha"
    ],
    "name:spa_x_preferred":[
        "Rocha"
    ],
    "name:swe_x_preferred":[
        "Rocha"
    ],
    "name:und_x_variant":[
        "San Cosme",
        "Rocha"
    ],
    "wof:name":"Rocha",
    "wof:placetype":"locality"
},
  "geometry": {"coordinates":[-7.85,43.05],"type":"Point"}
}