{
  "type": "Feature",
  "properties": {
    "gn:admin1_code":"58",
    "gn:admin2_code":"LU",
    "gn:admin3_code":"27020",
    "gn:asciiname":"Rocha",
    "gn:cc2":"ES",
    "gn:country_code":"ES",
    "gn:dem":564,
    "gn:feature_class":"P",
    "gn:feature_code":"PPL",
    "gn:name":"Rocha",
    "gn:population":0,
    "gn:timezone":"Europe/Madrid",
    "iso:country":"ES",
    "name:und_x_variant":[
        "San Cosme",
        "Rocha"
    ],
    "wof:name":"Rocha",
    "wof:placetype":"locality"
},
  "geometry": {"coordinates":[-7.85,43.05],"type":"Point"}
}