{
  "type": "Feature",
  "properties": {
    "iso:country":"ES",
    "wof:name":"Las Avenidas",
    "wof:placetype":"neighbourhood"
},
  "geometry": {"coordinates":[-5.98524549711022,37.41078423885702],"type":"Point"}
}