{
  "type": "Feature",
  "properties": {
    "gn:admin1_code":"55",
    "gn:admin2_code":"LE",
    "gn:admin3_code":"24079",
    "gn:asciiname":"Mellanzos",
    "gn:country_code":"ES",
    "gn:dem":905,
    "gn:feature_class":"P",
    "gn:feature_code":"PPL",
    "gn:name":"Mellanzos",
    "gn:population":0,
    "gn:timezone":"Europe/Madrid",
    "iso:country":"ES",
    "wof:name":"Mellanzos",
    "wof:placetype":"locality"
},
  "geometry": {"coordinates":[-5.32914,42.59421],"type":"Point"}
}