{
  "type": "Feature",
  "properties": {
    "gn:gn_country":"ES",
    "gn:gn_fcode":"PPLA3",
    "gn:gn_pop":205,
    "gn:population":205,
    "iso:country":"ES",
    "name:arg_x_preferred":[
        "Bercianos del Real Camino"
    ],
    "name:cat_x_preferred":[
        "Bercianos del Real Camino"
    ],
    "name:deu_x_preferred":[
        "Bercianos del Real Camino"
    ],
    "name:eng_x_preferred":[
        "Bercianos del Real Camino"
    ],
    "name:eus_x_preferred":[
        "Bercianos del Real Camino"
    ],
    "name:fas_x_preferred":[
        "\u0628\u0631\u062e\u0627\u0646\u0648\u0633 \u062f\u0644 \u0631\u06cc\u0627\u0644 \u06a9\u0645\u06cc\u0646\u0648"
    ],
    "name:fra_x_preferred":[
        "Bercianos del Real Camino"
    ],
    "name:glg_x_preferred":[
        "Bercianos del Real Camino"
    ],
    "name:haw_x_preferred":[
        "Bercianos del Real Camino"
    ],
    "name:hun_x_preferred":[
        "Bercianos del Real Camino"
    ],
    "name:ido_x_preferred":[
        "Bercianos del Real Camino"
    ],
    "name:ina_x_preferred":[
        "Bercianos del Real Camino"
    ],
    "name:ita_x_preferred":[
        "Bercianos del Real Camino"
    ],
    "name:msa_x_preferred":[
        "Bercianos del Real Camino"
    ],
    "name:nan_x_preferred":[
        "Bercianos del Real Camino"
    ],
    "name:nld_x_preferred":[
        "Bercianos del Real Camino"
    ],
    "name:oci_x_preferred":[
        "Bercianos del Real Camino"
    ],
    "name:pol_x_preferred":[
        "Bercianos del Real Camino"
    ],
    "name:por_x_preferred":[
        "Bercianos del Real Camino"
    ],
    "name:rup_x_preferred":[
        "Bercianos del Real Camino"
    ],
    "name:rus_x_preferred":[
        "\u0411\u0435\u0440\u0441\u0438\u0430\u043d\u043e\u0441-\u0434\u0435\u043b\u044c-\u0420\u0435\u0430\u043b\u044c-\u041a\u0430\u043c\u0438\u043d\u043e"
    ],
    "name:spa_x_preferred":[
        "Bercianos del Real Camino"
    ],
    "name:swe_x_preferred":[
        "Bercianos del Real Camino"
    ],
    "name:tpi_x_preferred":[
        "Bercianos del Real Camino"
    ],
    "name:ukr_x_preferred":[
        "\u0411\u0435\u0440\u0441\u0456\u0430\u043d\u043e\u0441-\u0434\u0435\u043b\u044c-\u0420\u0435\u0430\u043b\u044c-\u041a\u0430\u043c\u0456\u043d\u043e"
    ],
    "name:vie_x_preferred":[
        "Bercianos del Real Camino"
    ],
    "name:war_x_preferred":[
        "Bercianos del Real Camino"
    ],
    "name:zho_x_preferred":[
        "\u8d1d\u5c14\u897f\u4e9a\u8bfa\u65af\u5fb7\u5c14\u96f7\u4e9a\u5c14\u5361\u7c73\u8bfa"
    ],
    "qs_pg:aaroncc":"ES",
    "qs_pg:gn_country":"ES",
    "qs_pg:gn_fcode":"PPLA3",
    "qs_pg:gn_pop":205,
    "qs_pg:name":"Bercianos del Real Camino",
    "qs_pg:name_adm0":"Espa\u00f1a",
    "qs_pg:name_adm1":"Castilla y Le\u00f3n",
    "qs_pg:photos":153,
    "qs_pg:photos_1k":31,
    "qs_pg:photos_9k":1,
    "qs_pg:photos_9r":4,
    "qs_pg:photos_all":153,
    "qs_pg:photos_sr":4,
    "qs_pg:pop_sr":2,
    "qs_pg:qs_pg_placetype":"locality",
    "qs_pg:qs_pg_placetype_gp":"Town",
    "qs_pg:woe_adm0":23424950,
    "woe:adm0_id":23424950,
    "woe:name_adm0":"Espa\u00f1a",
    "woe:name_adm1":"Castilla y Le\u00f3n",
    "woe:placetype":"Town",
    "wof:name":"Bercianos del Real Camino",
    "wof:placetype":"locality",
    "wof:population":205
},
  "geometry": {"coordinates":[-5.14462,42.38732],"type":"Point"}
}