{
  "type": "Feature",
  "properties": {
    "gn:admin1_code":"51",
    "gn:admin2_code":"J",
    "gn:admin3_code":"23050",
    "gn:asciiname":"Galapagar",
    "gn:country_code":"ES",
    "gn:dem":486,
    "gn:feature_class":"P",
    "gn:feature_code":"PPL",
    "gn:name":"Galapagar",
    "gn:population":0,
    "gn:timezone":"Europe/Madrid",
    "iso:country":"ES",
    "name:ara_x_preferred":[
        "\u062c\u0627\u0644\u0627\u0628\u0627\u062c\u0627\u0631"
    ],
    "name:cat_x_preferred":[
        "Galapagar"
    ],
    "name:ceb_x_preferred":[
        "Galapagar"
    ],
    "name:epo_x_preferred":[
        "Galapagar"
    ],
    "name:eus_x_preferred":[
        "Galapagar"
    ],
    "name:fra_x_preferred":[
        "Galapagar"
    ],
    "name:glg_x_preferred":[
        "Galapagar"
    ],
    "name:hun_x_preferred":[
        "Galapagar"
    ],
    "name:hye_x_preferred":[
        "\u0533\u0561\u056c\u0561\u057a\u0561\u0563\u0561\u0580"
    ],
    "name:ita_x_preferred":[
        "Galapagar"
    ],
    "name:ltz_x_preferred":[
        "Galapagar"
    ],
    "name:mlg_x_preferred":[
        "Galapagar"
    ],
    "name:msa_x_preferred":[
        "Galapagar"
    ],
    "name:nld_x_preferred":[
        "Galapagar"
    ],
    "name:oci_x_preferred":[
        "Galapagar"
    ],
    "name:pol_x_preferred":[
        "Galapagar"
    ],
    "name:por_x_preferred":[
        "Galapagar"
    ],
    "name:rus_x_preferred":[
        "\u0413\u0430\u043b\u0430\u043f\u0430\u0433\u0430\u0440"
    ],
    "name:spa_x_preferred":[
        "Galapagar"
    ],
    "name:sqi_x_preferred":[
        "Galapagar"
    ],
    "name:srp_x_preferred":[
        "\u0413\u0430\u043b\u0430\u043f\u0430\u0433\u0430\u0440"
    ],
    "name:swe_x_preferred":[
        "Galapagar"
    ],
    "name:tur_x_preferred":[
        "Galapagar"
    ],
    "name:ukr_x_preferred":[
        "\u0413\u0430\u043b\u0430\u043f\u0430\u0433\u0430\u0440"
    ],
    "name:und_x_variant":[
        "Caser\u00edos Galapagar"
    ],
    "name:uzb_x_preferred":[
        "Galapagar"
    ],
    "name:vie_x_preferred":[
        "Galapagar"
    ],
    "name:war_x_preferred":[
        "Galapagar"
    ],
    "name:zho_x_preferred":[
        "\u52a0\u62c9\u5e15\u52a0\u5c14"
    ],
    "wof:name":"Galapagar",
    "wof:placetype":"locality"
},
  "geometry": {"coordinates":[-3.68523,37.85677],"type":"Point"}
}