{
  "type": "Feature",
  "properties": {
    "gn:admin1_code":"51",
    "gn:admin2_code":"J",
    "gn:admin3_code":"23050",
    "gn:asciiname":"Galapagar",
    "gn:country_code":"ES",
    "gn:dem":486,
    "gn:feature_class":"P",
    "gn:feature_code":"PPL",
    "gn:name":"Galapagar",
    "gn:population":0,
    "gn:timezone":"Europe/Madrid",
    "iso:country":"ES",
    "name:und_x_variant":[
        "Caser\u00edos Galapagar",
        "Galapagar"
    ],
    "wof:name":"Galapagar",
    "wof:placetype":"locality"
},
  "geometry": {"coordinates":[-3.68523,37.85677],"type":"Point"}
}