{
  "type": "Feature",
  "properties": {
    "gn:admin1_code":"55",
    "gn:admin2_code":"LE",
    "gn:admin3_code":"24076",
    "gn:asciiname":"Fontanos de Torio",
    "gn:country_code":"ES",
    "gn:dem":1079,
    "gn:feature_class":"P",
    "gn:feature_code":"PPL",
    "gn:name":"Fontanos de Tor\u00edo",
    "gn:population":0,
    "gn:timezone":"Europe/Madrid",
    "iso:country":"ES",
    "name:und_x_variant":[
        "Fontanos de Tor\u00edo"
    ],
    "wof:name":"Fontanos de Torio",
    "wof:placetype":"locality"
},
  "geometry": {"coordinates":[-5.53994,42.75509],"type":"Point"}
}