{
  "type": "Feature",
  "properties": {
    "gn:gn_country":"ES",
    "gn:gn_fcode":"PPLA3",
    "gn:gn_pop":130,
    "gn:population":130,
    "iso:country":"ES",
    "name:ara_x_preferred":[
        "\u0633\u064a\u0631\u0641\u064a\u0631\u0627 \u062f\u064a \u0628\u0648\u064a\u062a\u0631\u0627\u062c\u0648"
    ],
    "name:cat_x_preferred":[
        "Cervera de Buitrago"
    ],
    "name:eng_x_preferred":[
        "Cervera de Buitrago"
    ],
    "name:eus_x_preferred":[
        "Cervera de Buitrago"
    ],
    "name:fra_x_preferred":[
        "Cervera de Buitrago"
    ],
    "name:hun_x_preferred":[
        "Cervera de Buitrago"
    ],
    "name:hye_x_preferred":[
        "\u054d\u0565\u0580\u057e\u0565\u0580\u0561 \u0564\u0565 \u0532\u0578\u0582\u056b\u057f\u0580\u0561\u0563\u0578"
    ],
    "name:ita_x_preferred":[
        "Cervera de Buitrago"
    ],
    "name:ltz_x_preferred":[
        "Cervera de Buitrago"
    ],
    "name:msa_x_preferred":[
        "Cervera de Buitrago"
    ],
    "name:nan_x_preferred":[
        "Cervera de Buitrago"
    ],
    "name:nld_x_preferred":[
        "Cervera de Buitrago"
    ],
    "name:oci_x_preferred":[
        "Cervera de Buitrago"
    ],
    "name:pol_x_preferred":[
        "Cervera de Buitrago"
    ],
    "name:por_x_preferred":[
        "Cervera de Buitrago"
    ],
    "name:rus_x_preferred":[
        "\u0421\u0435\u0440\u0432\u0435\u0440\u0430-\u0434\u0435-\u0411\u0443\u0439\u0442\u0440\u0430\u0433\u043e"
    ],
    "name:spa_x_preferred":[
        "Cervera de Buitrago"
    ],
    "name:swe_x_preferred":[
        "Cervera de Buitrago"
    ],
    "name:ukr_x_preferred":[
        "\u0421\u0435\u0440\u0432\u0435\u0440\u0430-\u0434\u0435-\u0411\u0443\u0457\u0442\u0440\u0430\u0433\u043e"
    ],
    "name:uzb_x_preferred":[
        "Cervera de Buitrago"
    ],
    "name:vie_x_preferred":[
        "Cervera de Buitrago"
    ],
    "name:war_x_preferred":[
        "Cervera de Buitrago"
    ],
    "name:zho_x_preferred":[
        "\u585e\u5c14\u97e6\u62c9\u5fb7\u7ef4\u7279\u62c9\u6208"
    ],
    "qs_pg:aaroncc":"ES",
    "qs_pg:gn_country":"ES",
    "qs_pg:gn_fcode":"PPLA3",
    "qs_pg:gn_pop":130,
    "qs_pg:name":"Cervera de Buitrago",
    "qs_pg:name_adm0":"Espa\u00f1a",
    "qs_pg:name_adm1":"Comunidad de Madrid",
    "qs_pg:photos":120,
    "qs_pg:photos_1k":24,
    "qs_pg:photos_9k":1,
    "qs_pg:photos_9r":3,
    "qs_pg:photos_all":120,
    "qs_pg:photos_sr":3,
    "qs_pg:pop_sr":1,
    "qs_pg:qs_pg_placetype":"locality",
    "qs_pg:qs_pg_placetype_gp":"Town",
    "qs_pg:woe_adm0":23424950,
    "woe:adm0_id":23424950,
    "woe:name_adm0":"Espa\u00f1a",
    "woe:name_adm1":"Comunidad de Madrid",
    "woe:placetype":"Town",
    "wof:name":"Cervera de Buitrago",
    "wof:placetype":"locality",
    "wof:population":130
},
  "geometry": {"coordinates":[-3.52702,40.91988],"type":"Point"}
}