{
  "type": "Feature",
  "properties": {
    "gn:admin1_code":"58",
    "gn:admin2_code":"LU",
    "gn:admin3_code":"27048",
    "gn:asciiname":"San Mamed",
    "gn:country_code":"ES",
    "gn:dem":166,
    "gn:feature_class":"P",
    "gn:feature_code":"PPL",
    "gn:name":"San Mamed",
    "gn:population":0,
    "gn:timezone":"Europe/Madrid",
    "iso:country":"ES",
    "wof:name":"San Mamed",
    "wof:placetype":"locality"
},
  "geometry": {"coordinates":[-7.17665,43.35609],"type":"Point"}
}