{
  "type": "Feature",
  "properties": {
    "gn:admin1_code":"29",
    "gn:admin2_code":"M",
    "gn:admin3_code":"28131",
    "gn:asciiname":"San Lorenzo de El Escorial",
    "gn:country_code":"ES",
    "gn:dem":1049,
    "gn:feature_class":"P",
    "gn:feature_code":"PPLA3",
    "gn:name":"San Lorenzo de El Escorial",
    "gn:population":17889,
    "gn:timezone":"Europe/Madrid",
    "iso:country":"ES",
    "name:ara_x_preferred":[
        "\u0633\u0627\u0646 \u0644\u0648\u0631\u0646\u0632\u0648 \u062f\u064a \u0634 \u0627\u0644\u0625\u0633\u0643\u0648\u0631\u064a\u0627\u0644"
    ],
    "name:ara_x_variant":[
        "\u0633\u0627\u0646 \u0644\u0648\u0631\u0646\u0632\u0648 \u062f\u064a \u0627\u0644\u0625\u0633\u0643\u0648\u0631\u064a\u0627\u0644"
    ],
    "name:azb_x_preferred":[
        "\u0633\u0646 \u0644\u0648\u0631\u0646\u0632\u0648 \u062f \u0627\u0644 \u0627\u0633\u06a9\u0648\u0631\u06cc\u0627\u0644"
    ],
    "name:deu_x_preferred":[
        "El Escorial"
    ],
    "name:eng_x_preferred":[
        "El Escorial"
    ],
    "name:epo_x_preferred":[
        "Eskorialo"
    ],
    "name:fas_x_preferred":[
        "\u0633\u0646 \u0644\u0648\u0631\u0646\u0632\u0648 \u062f \u0627\u0644 \u0627\u0633\u06a9\u0648\u0631\u06cc\u0627\u0644"
    ],
    "name:fra_x_preferred":[
        "El Escorial"
    ],
    "name:hye_x_preferred":[
        "\u054d\u0561\u0576 \u053c\u0578\u0580\u0565\u0576\u057d\u0578 \u0564\u0565 \u0537\u056c \u0537\u057d\u056f\u0578\u0580\u056b\u0561\u056c"
    ],
    "name:ita_x_preferred":[
        "El Escorial"
    ],
    "name:kor_x_preferred":[
        "\uc0b0\ub85c\ub80c\uc18c\ub370\uc5d8\uc5d0\uc2a4\ucf54\ub9ac\uc54c"
    ],
    "name:por_x_preferred":[
        "El Escorial"
    ],
    "name:rus_x_preferred":[
        "\u0421\u0430\u043d-\u041b\u043e\u0440\u0435\u043d\u0441\u043e-\u0434\u0435-\u042d\u043b\u044c-\u042d\u0441\u043a\u043e\u0440\u0438\u0430\u043b\u044c"
    ],
    "name:spa_x_preferred":[
        "El Escorial"
    ],
    "name:ukr_x_preferred":[
        "\u0421\u0430\u043d-\u041b\u043e\u0440\u0435\u043d\u0441\u043e-\u0434\u0435-\u0415\u043b\u044c-\u0415\u0441\u043a\u043e\u0440\u0456\u0430\u043b\u044c"
    ],
    "name:und_x_variant":[
        "El Escorial",
        "San Lorenzo",
        "San Lorenzo del Escorial"
    ],
    "name:zho_x_preferred":[
        "\u5723\u6d1b\u4f26\u7d22\u5fb7\u57c3\u83b1\u65af\u79d1\u91cc\u4e9a\u5c14"
    ],
    "wof:name":"San Lorenzo de El Escorial",
    "wof:placetype":"locality",
    "wof:population":17889
},
  "geometry": {"coordinates":[-4.14738,40.59144000000001],"type":"Point"}
}