{
  "type": "Feature",
  "properties": {
    "gn:admin1_code":"34",
    "gn:admin2_code":"O",
    "gn:admin3_code":"33026",
    "gn:asciiname":"Villagarcia",
    "gn:country_code":"ES",
    "gn:dem":322,
    "gn:feature_class":"P",
    "gn:feature_code":"PPL",
    "gn:name":"Villagarc\u00eda",
    "gn:population":0,
    "gn:timezone":"Europe/Madrid",
    "iso:country":"ES",
    "name:und_x_variant":[
        "Villagarc\u00eda"
    ],
    "wof:name":"Villagarcia",
    "wof:placetype":"locality"
},
  "geometry": {"coordinates":[-6.10296,43.33304],"type":"Point"}
}