{
  "type": "Feature",
  "properties": {
    "gn:country":"ES",
    "gn:fcode":"PPLA3",
    "gn:population":0,
    "iso:country":"ES",
    "name:ara_x_preferred":[
        "\u0633\u0627\u0646 \u0645\u0627\u0631\u062a\u0646 \u062f\u064a \u062a\u0648\u0633"
    ],
    "name:arg_x_preferred":[
        "Sant Mart\u00ed de Tous"
    ],
    "name:cat_x_preferred":[
        "Sant Mart\u00ed de Tous"
    ],
    "name:deu_x_preferred":[
        "Sant Mart\u00ed de Tous"
    ],
    "name:eng_x_preferred":[
        "Sant Mart\u00ed de Tous"
    ],
    "name:eus_x_preferred":[
        "Sant Mart\u00ed de Tous"
    ],
    "name:fas_x_preferred":[
        "\u0633\u0646\u062a \u0645\u0627\u0631\u062a\u06cc\u0646 \u062f\u0647 \u062a\u0648\u0633"
    ],
    "name:fra_x_preferred":[
        "Sant Mart\u00ed de Tous"
    ],
    "name:hun_x_preferred":[
        "Sant Mart\u00ed de Tous"
    ],
    "name:hye_x_preferred":[
        "\u054d\u0561\u0576 \u0544\u0561\u0580\u057f\u056b\u0576 \u0564\u0565 \u054f\u0578\u0578\u0582\u057d"
    ],
    "name:ita_x_preferred":[
        "Sant Mart\u00ed de Tous"
    ],
    "name:kaz_x_preferred":[
        "\u0421\u0430\u043d-\u041c\u0430\u0440\u0442\u0438-\u0434\u0435-\u0422\u043e\u0443\u0441"
    ],
    "name:lat_x_preferred":[
        "Sant Mart\u00ed de Tous"
    ],
    "name:msa_x_preferred":[
        "Sant Mart\u00ed de Tous"
    ],
    "name:nld_x_preferred":[
        "Sant Mart\u00ed de Tous"
    ],
    "name:oci_x_preferred":[
        "Sant Mart\u00ed de Tous"
    ],
    "name:pol_x_preferred":[
        "Sant Mart\u00ed de Tous"
    ],
    "name:por_x_preferred":[
        "Sant Mart\u00ed de Tous"
    ],
    "name:rus_x_preferred":[
        "\u0421\u0430\u043d-\u041c\u0430\u0440\u0442\u0438-\u0434\u0435-\u0422\u043e\u0443\u0441"
    ],
    "name:sco_x_preferred":[
        "Sant Mart\u00ed de Tous"
    ],
    "name:spa_x_preferred":[
        "San Mart\u00edn de Tous"
    ],
    "name:sqi_x_preferred":[
        "Sant Mart\u00ed de Tous"
    ],
    "name:swe_x_preferred":[
        "Sant Mart\u00ed de Tous"
    ],
    "name:ukr_x_preferred":[
        "\u0421\u0430\u043d-\u041c\u0430\u0440\u0442\u0456-\u0434\u0430-\u0422\u043e\u0443\u0441"
    ],
    "name:uzb_x_preferred":[
        "San Mart\u00edn de Tous"
    ],
    "name:war_x_preferred":[
        "Sant Mart\u00ed de Tous"
    ],
    "name:zho_x_preferred":[
        "\u6851\u7279\u9a6c\u5c14\u8482\u5fb7\u6258\u65af"
    ],
    "qs_pg:aaroncc":"ES",
    "qs_pg:gn_country":"ES",
    "qs_pg:gn_fcode":"PPLA3",
    "qs_pg:gn_pop":0,
    "qs_pg:name":"Sant Mart\u00ed de Tous",
    "qs_pg:name_adm0":"Espa\u00f1a",
    "qs_pg:name_adm1":"Catalunya",
    "qs_pg:photos":231,
    "qs_pg:photos_1k":47,
    "qs_pg:photos_9k":1,
    "qs_pg:photos_9r":4,
    "qs_pg:photos_all":231,
    "qs_pg:photos_sr":4,
    "qs_pg:pop_sr":0,
    "qs_pg:qs_pg_placetype":"locality",
    "qs_pg:qs_pg_placetype_gp":"Town",
    "qs_pg:woe_adm0":23424950,
    "woe:adm0_id":23424950,
    "woe:name_adm0":"Espa\u00f1a",
    "woe:name_adm1":"Catalunya",
    "woe:placetype":"Town",
    "wof:name":"Sant Mart\u00ed de Tous",
    "wof:placetype":"locality"
},
  "geometry": {"coordinates":[1.51667,41.55],"type":"Point"}
}