{
  "type": "Feature",
  "properties": {
    "iso:country":"ES",
    "name:eng_x_preferred":[
        "El Censul II"
    ],
    "name:spa_x_preferred":[
        "El C\u00f3nsul II"
    ],
    "wof:name":"El Censul II",
    "wof:placetype":"neighbourhood"
},
  "geometry": {"coordinates":[-4.47893342074306,36.72207097672573],"type":"Point"}
}