{
  "type": "Feature",
  "properties": {
    "gn:admin1_code":"55",
    "gn:admin2_code":"SO",
    "gn:admin3_code":"42152",
    "gn:asciiname":"La Perera",
    "gn:country_code":"ES",
    "gn:dem":1083,
    "gn:feature_class":"P",
    "gn:feature_code":"PPL",
    "gn:name":"La Perera",
    "gn:population":0,
    "gn:timezone":"Europe/Madrid",
    "iso:country":"ES",
    "wof:name":"La Perera",
    "wof:placetype":"locality"
},
  "geometry": {"coordinates":[-3.03184,41.40761],"type":"Point"}
}