{
  "type": "Feature",
  "properties": {
    "gn:admin1_code":"58",
    "gn:admin2_code":"OR",
    "gn:admin3_code":"32058",
    "gn:asciiname":"Tibianes",
    "gn:country_code":"ES",
    "gn:dem":280,
    "gn:feature_class":"P",
    "gn:feature_code":"PPL",
    "gn:name":"Tibianes",
    "gn:population":0,
    "gn:timezone":"Europe/Madrid",
    "iso:country":"ES",
    "wof:name":"Tibianes",
    "wof:placetype":"locality"
},
  "geometry": {"coordinates":[-7.82178,42.35034],"type":"Point"}
}