{
  "type": "Feature",
  "properties": {
    "gn:admin1_code":"55",
    "gn:admin2_code":"LE",
    "gn:admin3_code":"33043",
    "gn:asciiname":"Bobia de Arriba",
    "gn:country_code":"ES",
    "gn:dem":423,
    "gn:feature_class":"P",
    "gn:feature_code":"PPL",
    "gn:name":"Bobia de Arriba",
    "gn:population":0,
    "gn:timezone":"Europe/Madrid",
    "iso:country":"ES",
    "wof:name":"Bobia de Arriba",
    "wof:placetype":"locality"
},
  "geometry": {"coordinates":[-4.9896,43.32555],"type":"Point"}
}