{
  "type": "Feature",
  "properties": {
    "gn:admin1_code":"60",
    "gn:admin2_code":"V",
    "gn:admin3_code":"46263",
    "gn:asciiname":"Hoz de Arriba",
    "gn:cc2":"ES",
    "gn:country_code":"ES",
    "gn:dem":691,
    "gn:feature_class":"P",
    "gn:feature_code":"PPL",
    "gn:name":"Hoz de Arriba",
    "gn:population":0,
    "gn:timezone":"Europe/Madrid",
    "iso:country":"ES",
    "name:und_x_variant":[
        "Caser\u00edo Hoz de Arriba",
        "Hoz de Arriba"
    ],
    "wof:name":"Hoz de Arriba",
    "wof:placetype":"locality"
},
  "geometry": {"coordinates":[-1.11667,39.08333],"type":"Point"}
}