{
  "type": "Feature",
  "properties": {
    "gn:admin1_code":"32",
    "gn:admin3_code":"31049",
    "gn:asciiname":"Ihaben",
    "gn:country_code":"ES",
    "gn:dem":553,
    "gn:feature_class":"P",
    "gn:feature_code":"PPL",
    "gn:name":"Ihaben",
    "gn:population":0,
    "gn:timezone":"Europe/Madrid",
    "iso:country":"ES",
    "name:eus_x_preferred":[
        "Ihaben"
    ],
    "name:spa_x_preferred":[
        "Yaben"
    ],
    "name:und_x_variant":[
        "Yaben"
    ],
    "wof:name":"Ihaben",
    "wof:placetype":"locality"
},
  "geometry": {"coordinates":[-1.80725,42.98732],"type":"Point"}
}