{
  "type": "Feature",
  "properties": {
    "gn:gn_country":"ES",
    "gn:gn_fcode":"PPL",
    "gn:gn_pop":0,
    "iso:country":"ES",
    "name:alb_x_preferred":[
        "Castellbell i el Vilar"
    ],
    "name:ara_x_preferred":[
        "\u0643\u0627\u0633\u062a\u064a\u0644\u0628\u064a\u0644 \u064a \u0641\u0627\u064a\u0644\u0627\u0631"
    ],
    "name:arg_x_preferred":[
        "Castellbell i el Vilar"
    ],
    "name:baq_x_preferred":[
        "Castellbell i el Vilar"
    ],
    "name:cat_x_preferred":[
        "Castellbell i el Vilar"
    ],
    "name:chi_x_preferred":[
        "\u5361\u65af\u7279\u5229\u97e6\u5217\u5c14\u7ef4\u62c9\u5c14"
    ],
    "name:dut_x_preferred":[
        "Castellbell i el Vilar"
    ],
    "name:eng_x_preferred":[
        "Castellbell i el Vilar"
    ],
    "name:fre_x_preferred":[
        "Castellbell i el Vilar"
    ],
    "name:ger_x_preferred":[
        "Castellbell i el Vilar"
    ],
    "name:heb_x_preferred":[
        "\u05e7\u05e1\u05d8\u05dc\u05d9\u05d1\u05dc \u05d0\u05d9 \u05d0\u05dc \u05d5\u05d9\u05dc\u05e8"
    ],
    "name:hun_x_preferred":[
        "Castellbell i el Vilar"
    ],
    "name:ita_x_preferred":[
        "Castellbell i el Vilar"
    ],
    "name:lat_x_preferred":[
        "Castellbell i el Vilar"
    ],
    "name:may_x_preferred":[
        "Castellbell i el Vilar"
    ],
    "name:oci_x_preferred":[
        "Castellbell i el Vilar"
    ],
    "name:per_x_preferred":[
        "\u06a9\u0627\u0633\u062a\u06cc\u0628\u06cc \u0627\u06cc \u0627\u0644 \u0628\u06cc\u0644\u0627\u0631"
    ],
    "name:pol_x_preferred":[
        "Castellbell i el Vilar"
    ],
    "name:por_x_preferred":[
        "Castellbell i el Vilar"
    ],
    "name:rum_x_preferred":[
        "Castellbell i el Vilar"
    ],
    "name:rus_x_preferred":[
        "\u041a\u0430\u0441\u0442\u0435\u043b\u044c\u0431\u0435\u043b\u044c-\u0438-\u044d\u043b\u044c-\u0412\u0438\u043b\u0430\u0440"
    ],
    "name:sco_x_preferred":[
        "Castellbell i el Vilar"
    ],
    "name:spa_x_preferred":[
        "Castellbell y Vilar"
    ],
    "name:swe_x_preferred":[
        "Castellbell i el Vilar"
    ],
    "name:ukr_x_preferred":[
        "\u041a\u0430\u0441\u0442\u0435\u043b\u044c\u0431\u0435\u043b\u044c-\u0456-\u0430\u043b-\u0411\u0456\u043b\u0430"
    ],
    "name:vie_x_preferred":[
        "Castellbell i el Vilar"
    ],
    "name:war_x_preferred":[
        "Castellbell i el Vilar"
    ],
    "qs_pg:aaroncc":"ES",
    "qs_pg:gn_country":"ES",
    "qs_pg:gn_fcode":"PPL",
    "qs_pg:gn_pop":0,
    "qs_pg:name":"Castellbell i el Vilar",
    "qs_pg:name_adm0":"Espa\u00f1a",
    "qs_pg:name_adm1":"Catalunya",
    "qs_pg:photos":333,
    "qs_pg:photos_1k":67,
    "qs_pg:photos_9k":1,
    "qs_pg:photos_9r":5,
    "qs_pg:photos_all":333,
    "qs_pg:photos_sr":5,
    "qs_pg:pop_sr":0,
    "qs_pg:qs_pg_placetype":"locality",
    "qs_pg:qs_pg_placetype_gp":"Town",
    "qs_pg:woe_adm0":23424950,
    "woe:adm0_id":23424950,
    "woe:name_adm0":"Espa\u00f1a",
    "woe:name_adm1":"Catalunya",
    "woe:placetype":"Town",
    "wof:name":"Castellbell i el Vilar",
    "wof:placetype":"locality"
},
  "geometry": {"coordinates":[1.86394,41.63395],"type":"Point"}
}