{
  "type": "Feature",
  "properties": {
    "gn:admin1_code":"55",
    "gn:admin2_code":"LE",
    "gn:admin3_code":"24098",
    "gn:asciiname":"Villalfeide",
    "gn:country_code":"ES",
    "gn:dem":1053,
    "gn:feature_class":"P",
    "gn:feature_code":"PPL",
    "gn:name":"Villalfeide",
    "gn:population":0,
    "gn:timezone":"Europe/Madrid",
    "iso:country":"ES",
    "wof:name":"Villalfeide",
    "wof:placetype":"locality"
},
  "geometry": {"coordinates":[-5.51599,42.87918],"type":"Point"}
}