{
  "type": "Feature",
  "properties": {
    "gn:admin1_code":"58",
    "gn:admin2_code":"LU",
    "gn:admin3_code":"27061",
    "gn:asciiname":"Cima de Vila",
    "gn:country_code":"ES",
    "gn:dem":226,
    "gn:feature_class":"P",
    "gn:feature_code":"PPL",
    "gn:name":"Cima de Vila",
    "gn:population":0,
    "gn:timezone":"Europe/Madrid",
    "iso:country":"ES",
    "wof:name":"Cima de Vila",
    "wof:placetype":"locality"
},
  "geometry": {"coordinates":[-7.19954,43.43748],"type":"Point"}
}