{
  "type": "Feature",
  "properties": {
    "iso:country":"ES",
    "name:eng_x_preferred":[
        "Las Torres"
    ],
    "name:spa_x_preferred":[
        "Las Torres"
    ],
    "wof:name":"Las Torres",
    "wof:placetype":"neighbourhood"
},
  "geometry": {"coordinates":[-4.44966514124614,36.71616565451445],"type":"Point"}
}