{
  "type": "Feature",
  "properties": {
    "gn:admin1_code":"54",
    "gn:admin2_code":"CR",
    "gn:admin3_code":"13901",
    "gn:asciiname":"Navalrincon",
    "gn:country_code":"ES",
    "gn:dem":614,
    "gn:feature_class":"P",
    "gn:feature_code":"PPL",
    "gn:name":"Navalrinc\u00f3n",
    "gn:population":0,
    "gn:timezone":"Europe/Madrid",
    "iso:country":"ES",
    "name:und_x_variant":[
        "Navalrrinc\u00f3n",
        "Navalrinc\u00f3n"
    ],
    "wof:name":"Navalrincon",
    "wof:placetype":"locality"
},
  "geometry": {"coordinates":[-4.35279,39.22513],"type":"Point"}
}