{
  "type": "Feature",
  "properties": {
    "gn:admin1_code":"56",
    "gn:admin2_code":"GI",
    "gn:admin3_code":"17013",
    "gn:asciiname":"Fornells",
    "gn:country_code":"ES",
    "gn:dem":43,
    "gn:feature_class":"P",
    "gn:feature_code":"PPL",
    "gn:name":"Fornells",
    "gn:population":0,
    "gn:timezone":"Europe/Madrid",
    "iso:country":"ES",
    "name:cat_x_preferred":[
        "Fornells"
    ],
    "wof:name":"Fornells",
    "wof:placetype":"locality"
},
  "geometry": {"coordinates":[3.21384,41.94021],"type":"Point"}
}