{
  "type": "Feature",
  "properties": {
    "gn:admin1_code":"34",
    "gn:admin2_code":"O",
    "gn:admin3_code":"33068",
    "gn:asciiname":"La Falguera",
    "gn:country_code":"ES",
    "gn:dem":1204,
    "gn:feature_class":"P",
    "gn:feature_code":"PPL",
    "gn:name":"La Falguera",
    "gn:population":0,
    "gn:timezone":"Europe/Madrid",
    "iso:country":"ES",
    "wof:name":"La Falguera",
    "wof:placetype":"locality"
},
  "geometry": {"coordinates":[-6.22124,43.11636],"type":"Point"}
}