{
  "type": "Feature",
  "properties": {
    "gn:admin1_code":"58",
    "gn:admin2_code":"C",
    "gn:admin3_code":"15045",
    "gn:asciiname":"Ninan",
    "gn:country_code":"ES",
    "gn:dem":293,
    "gn:feature_class":"P",
    "gn:feature_code":"PPL",
    "gn:name":"Ni\u00f1\u00e1n",
    "gn:population":0,
    "gn:timezone":"Europe/Madrid",
    "iso:country":"ES",
    "name:tat_x_preferred":[
        "\u041d\u0438\u043d\u0430\u043d"
    ],
    "wof:name":"Ninan",
    "wof:placetype":"locality"
},
  "geometry": {"coordinates":[-8.9746,42.9925],"type":"Point"}
}