{
  "type": "Feature",
  "properties": {
    "gn:gn_country":"ES",
    "gn:gn_fcode":"PPLA3",
    "gn:gn_pop":349,
    "gn:population":349,
    "iso:country":"ES",
    "name:baq_x_preferred":[
        "Nieva"
    ],
    "name:cat_x_preferred":[
        "Nieva"
    ],
    "name:chi_x_preferred":[
        "\u6d85\u74e6"
    ],
    "name:dut_x_preferred":[
        "Nieva"
    ],
    "name:eng_x_preferred":[
        "Nieva"
    ],
    "name:fre_x_preferred":[
        "Nieva"
    ],
    "name:hun_x_preferred":[
        "Nieva"
    ],
    "name:ina_x_preferred":[
        "Nieva"
    ],
    "name:ita_x_preferred":[
        "Nieva"
    ],
    "name:may_x_preferred":[
        "Nieva"
    ],
    "name:nan_x_preferred":[
        "Nieva"
    ],
    "name:oci_x_preferred":[
        "Nieva"
    ],
    "name:pol_x_preferred":[
        "Nieva"
    ],
    "name:por_x_preferred":[
        "Nieva"
    ],
    "name:rus_x_preferred":[
        "\u041d\u044c\u0435\u0432\u0430"
    ],
    "name:spa_x_preferred":[
        "Nieva"
    ],
    "name:swe_x_preferred":[
        "Nieva"
    ],
    "name:ukr_x_preferred":[
        "\u041d\u044c\u0454\u0432\u0430"
    ],
    "name:war_x_preferred":[
        "Nieva"
    ],
    "qs_pg:aaroncc":"ES",
    "qs_pg:gn_country":"ES",
    "qs_pg:gn_fcode":"PPLA3",
    "qs_pg:gn_pop":349,
    "qs_pg:name":"Nieva",
    "qs_pg:name_adm0":"Espa\u00f1a",
    "qs_pg:name_adm1":"Castilla y Le\u00f3n",
    "qs_pg:photos_9k":1,
    "qs_pg:photos_9r":1,
    "qs_pg:photos_all":1,
    "qs_pg:photos_sr":0,
    "qs_pg:pop_sr":2,
    "qs_pg:qs_pg_placetype":"locality",
    "qs_pg:qs_pg_placetype_gp":"Town",
    "qs_pg:woe_adm0":23424950,
    "woe:adm0_id":23424950,
    "woe:name_adm0":"Espa\u00f1a",
    "woe:name_adm1":"Castilla y Le\u00f3n",
    "woe:placetype":"Town",
    "wof:name":"Nieva",
    "wof:placetype":"locality",
    "wof:population":349
},
  "geometry": {"coordinates":[-4.42501,41.08191],"type":"Point"}
}