{
  "type": "Feature",
  "properties": {
    "gn:admin1_code":"32",
    "gn:admin3_code":"31050",
    "gn:asciiname":"Zozaia",
    "gn:country_code":"ES",
    "gn:dem":303,
    "gn:feature_class":"P",
    "gn:feature_code":"PPL",
    "gn:name":"Zozaia",
    "gn:population":0,
    "gn:timezone":"Europe/Madrid",
    "iso:country":"ES",
    "name:eus_x_preferred":[
        "Zozaia"
    ],
    "name:spa_x_preferred":[
        "Zozaya de Oronoz"
    ],
    "name:und_x_variant":[
        "Zozaya de Oronoz"
    ],
    "wof:name":"Zozaia",
    "wof:placetype":"locality"
},
  "geometry": {"coordinates":[-1.5989,43.12353],"type":"Point"}
}