{
  "type": "Feature",
  "properties": {
    "gn:gn_country":"ES",
    "gn:gn_fcode":"PPLA3",
    "gn:gn_pop":142,
    "gn:population":142,
    "iso:country":"ES",
    "name:ara_x_preferred":[
        "\u0641\u064a\u0627\u0646\u0648\u064a\u0641\u0627 \u062f\u064a \u063a\u0648\u0645\u064a\u062b"
    ],
    "name:baq_x_preferred":[
        "Villanueva de G\u00f3mez"
    ],
    "name:cat_x_preferred":[
        "Villanueva de G\u00f3mez"
    ],
    "name:chi_x_preferred":[
        "\u6208\u9ea6\u65af\u65b0\u9547"
    ],
    "name:dut_x_preferred":[
        "Villanueva de G\u00f3mez"
    ],
    "name:eng_x_preferred":[
        "Villanueva de G\u00f3mez"
    ],
    "name:fre_x_preferred":[
        "Villanueva de G\u00f3mez"
    ],
    "name:ger_x_preferred":[
        "Villanueva de G\u00f3mez"
    ],
    "name:hun_x_preferred":[
        "Villanueva de G\u00f3mez"
    ],
    "name:ina_x_preferred":[
        "Villanueva de G\u00f3mez"
    ],
    "name:ita_x_preferred":[
        "Villanueva de G\u00f3mez"
    ],
    "name:jpn_x_preferred":[
        "\u30d3\u30b8\u30e3\u30cc\u30a8\u30d0\u30fb\u30c7\u30fb\u30b4\u30e1\u30b9"
    ],
    "name:kaz_x_preferred":[
        "\u0412\u0438\u043b\u044c\u044f\u043d\u0443\u044d\u0432\u0430-\u0434\u0435-\u0413\u043e\u043c\u0435\u0441"
    ],
    "name:mac_x_preferred":[
        "\u0412\u0438\u043b\u0458\u0430\u043d\u0443\u0435\u0432\u0430 \u0434\u0435 \u0413\u043e\u043c\u0435\u0437"
    ],
    "name:may_x_preferred":[
        "Villanueva de G\u00f3mez"
    ],
    "name:oci_x_preferred":[
        "Villanueva de G\u00f3mez"
    ],
    "name:per_x_preferred":[
        "\u0628\u06cc\u06cc\u0627\u0646\u0648\u0626\u0628\u0627 \u062f \u06af\u0645\u0633"
    ],
    "name:pol_x_preferred":[
        "Villanueva de G\u00f3mez"
    ],
    "name:por_x_preferred":[
        "Villanueva de G\u00f3mez"
    ],
    "name:rus_x_preferred":[
        "\u0412\u0438\u043b\u044c\u044f\u043d\u0443\u044d\u0432\u0430-\u0434\u0435-\u0413\u043e\u043c\u0435\u0441"
    ],
    "name:spa_x_preferred":[
        "Villanueva de G\u00f3mez"
    ],
    "name:swe_x_preferred":[
        "Villanueva de G\u00f3mez"
    ],
    "name:ukr_x_preferred":[
        "\u0412\u0456\u043b\u044c\u044f\u043d\u0443\u0435\u0432\u0430-\u0434\u0435-\u0413\u043e\u043c\u0435\u0441"
    ],
    "name:unk_x_variant":[
        "Villanueva"
    ],
    "name:uzb_x_preferred":[
        "Villanueva de G\u00f3mez"
    ],
    "name:vie_x_preferred":[
        "Villanueva de G\u00f3mez"
    ],
    "name:war_x_preferred":[
        "Villanueva de G\u00f3mez"
    ],
    "qs_pg:aaroncc":"ES",
    "qs_pg:gn_country":"ES",
    "qs_pg:gn_fcode":"PPLA3",
    "qs_pg:gn_pop":142,
    "qs_pg:name":"Villanueva de G\u00f3mez",
    "qs_pg:name_adm0":"Espa\u00f1a",
    "qs_pg:name_adm1":"Castilla y Le\u00f3n",
    "qs_pg:photos_9r":0,
    "qs_pg:photos_sr":0,
    "qs_pg:pop_sr":1,
    "qs_pg:qs_pg_placetype":"locality",
    "qs_pg:qs_pg_placetype_gp":"Town",
    "qs_pg:woe_adm0":23424950,
    "woe:adm0_id":23424950,
    "woe:name_adm0":"Espa\u00f1a",
    "woe:name_adm1":"Castilla y Le\u00f3n",
    "woe:placetype":"Town",
    "wof:name":"Villanueva de G\u00f3mez",
    "wof:placetype":"locality",
    "wof:population":142
},
  "geometry": {"coordinates":[-4.7165,40.88269],"type":"Point"}
}