{
  "type": "Feature",
  "properties": {
    "gn:admin1_code":"58",
    "gn:admin2_code":"LU",
    "gn:admin3_code":"27006",
    "gn:asciiname":"Donin",
    "gn:country_code":"ES",
    "gn:dem":745,
    "gn:feature_class":"P",
    "gn:feature_code":"PPL",
    "gn:name":"Don\u00edn",
    "gn:population":0,
    "gn:timezone":"Europe/Madrid",
    "iso:country":"ES",
    "wof:name":"Donin",
    "wof:placetype":"locality"
},
  "geometry": {"coordinates":[-7.12477,42.93026],"type":"Point"}
}