{
  "type": "Feature",
  "properties": {
    "gn:admin1_code":"58",
    "gn:admin2_code":"LU",
    "gn:admin3_code":"27053",
    "gn:asciiname":"Lamas",
    "gn:country_code":"ES",
    "gn:dem":312,
    "gn:feature_class":"P",
    "gn:feature_code":"PPL",
    "gn:name":"Lamas",
    "gn:population":0,
    "gn:timezone":"Europe/Madrid",
    "iso:country":"ES",
    "wof:name":"Lamas",
    "wof:placetype":"locality"
},
  "geometry": {"coordinates":[-7.19864,43.18614],"type":"Point"}
}