{
  "type": "Feature",
  "properties": {
    "gn:admin1_code":"58",
    "gn:admin2_code":"LU",
    "gn:admin3_code":"27053",
    "gn:asciiname":"Lamas",
    "gn:country_code":"ES",
    "gn:dem":312,
    "gn:feature_class":"P",
    "gn:feature_code":"PPL",
    "gn:name":"Lamas",
    "gn:population":0,
    "gn:timezone":"Europe/Madrid",
    "iso:country":"ES",
    "name:ceb_x_preferred":[
        "Lamas"
    ],
    "name:deu_x_preferred":[
        "Lamas"
    ],
    "name:fra_x_preferred":[
        "Lamas"
    ],
    "name:glg_x_preferred":[
        "Lamas"
    ],
    "name:ita_x_preferred":[
        "Lamas"
    ],
    "name:nds_x_preferred":[
        "Lamas"
    ],
    "name:nld_x_preferred":[
        "Lamas"
    ],
    "name:pol_x_preferred":[
        "Lamas"
    ],
    "name:por_x_preferred":[
        "Lamas"
    ],
    "name:rus_x_preferred":[
        "\u041b\u0430\u043c\u0430\u0441"
    ],
    "name:rus_x_variant":[
        "\u041b\u0430\u043c\u0430\u0448"
    ],
    "name:spa_x_preferred":[
        "Lamas"
    ],
    "name:swe_x_preferred":[
        "Lamas"
    ],
    "name:tur_x_preferred":[
        "Lamas"
    ],
    "name:ukr_x_preferred":[
        "\u041b\u0430\u043c\u0430\u0448"
    ],
    "name:urd_x_preferred":[
        "\u0644\u0627\u0645\u0627\u0633"
    ],
    "name:vie_x_preferred":[
        "Lamas"
    ],
    "wof:name":"Lamas",
    "wof:placetype":"locality"
},
  "geometry": {"coordinates":[-7.19864,43.18614],"type":"Point"}
}