{
  "type": "Feature",
  "properties": {
    "gn:admin1_code":"29",
    "gn:admin2_code":"M",
    "gn:admin3_code":"28128",
    "gn:asciiname":"Rozas de Puerto Real",
    "gn:country_code":"ES",
    "gn:dem":870,
    "gn:feature_class":"P",
    "gn:feature_code":"PPLA3",
    "gn:name":"Rozas de Puerto Real",
    "gn:population":0,
    "gn:timezone":"Europe/Madrid",
    "iso:country":"ES",
    "name:ara_x_preferred":[
        "\u0631\u0648\u0632\u0627\u0633 \u062f\u064a \u0628\u0648\u064a\u0631\u062a\u0648 \u0631\u064a\u0627\u0644"
    ],
    "name:hye_x_preferred":[
        "\u054c\u0578\u057d\u0561\u057d \u0564\u0565 \u054a\u0578\u0582\u0565\u0580\u057f\u0578 \u054c\u0565\u0561\u056c"
    ],
    "wof:name":"Rozas de Puerto Real",
    "wof:placetype":"locality"
},
  "geometry": {"coordinates":[-4.48333,40.31667],"type":"Point"}
}