{
  "type": "Feature",
  "properties": {
    "gn:admin1_code":"29",
    "gn:admin2_code":"M",
    "gn:admin3_code":"28128",
    "gn:asciiname":"Rozas de Puerto Real",
    "gn:country_code":"ES",
    "gn:dem":870,
    "gn:feature_class":"P",
    "gn:feature_code":"PPLA3",
    "gn:name":"Rozas de Puerto Real",
    "gn:population":0,
    "gn:timezone":"Europe/Madrid",
    "iso:country":"ES",
    "wof:name":"Rozas de Puerto Real",
    "wof:placetype":"locality"
},
  "geometry": {"coordinates":[-4.48333,40.31667],"type":"Point"}
}