{
  "type": "Feature",
  "properties": {
    "gn:admin1_code":"59",
    "gn:admin2_code":"VI",
    "gn:admin3_code":"01054",
    "gn:asciiname":"Abornicano",
    "gn:country_code":"ES",
    "gn:dem":588,
    "gn:feature_class":"P",
    "gn:feature_code":"PPL",
    "gn:name":"Abornikano",
    "gn:population":0,
    "gn:timezone":"Europe/Madrid",
    "iso:country":"ES",
    "name:eus_x_preferred":[
        "Abornikano"
    ],
    "name:spa_x_preferred":[
        "Aborn\u00edcano"
    ],
    "wof:name":"Abornicano",
    "wof:placetype":"locality"
},
  "geometry": {"coordinates":[-2.88942,42.92886],"type":"Point"}
}