{
  "type": "Feature",
  "properties": {
    "gn:admin1_code":"58",
    "gn:admin2_code":"C",
    "gn:admin3_code":"15010",
    "gn:asciiname":"Arceo",
    "gn:cc2":"ES",
    "gn:country_code":"ES",
    "gn:dem":342,
    "gn:feature_class":"P",
    "gn:feature_code":"PPL",
    "gn:name":"Arceo",
    "gn:population":0,
    "gn:timezone":"Europe/Madrid",
    "iso:country":"ES",
    "name:und_x_variant":[
        "San Vicente",
        "Arceo"
    ],
    "wof:name":"Arceo",
    "wof:placetype":"locality"
},
  "geometry": {"coordinates":[-8.16667,43.03333],"type":"Point"}
}