{
  "type": "Feature",
  "properties": {
    "gn:admin1_code":"34",
    "gn:admin2_code":"O",
    "gn:admin3_code":"33001",
    "gn:asciiname":"Lomes",
    "gn:country_code":"ES",
    "gn:dem":442,
    "gn:feature_class":"P",
    "gn:feature_code":"PPL",
    "gn:name":"Lomes",
    "gn:population":0,
    "gn:timezone":"Europe/Madrid",
    "iso:country":"ES",
    "name:ast_x_preferred":[
        "\u1e36\u1e37omes"
    ],
    "name:cat_x_preferred":[
        "Lomes"
    ],
    "name:deu_x_preferred":[
        "Lomes"
    ],
    "name:spa_x_preferred":[
        "Lomes"
    ],
    "wof:name":"Lomes",
    "wof:placetype":"locality"
},
  "geometry": {"coordinates":[-6.57096,43.21466],"type":"Point"}
}