{
  "type": "Feature",
  "properties": {
    "gn:admin1_code":"60",
    "gn:admin2_code":"A",
    "gn:admin3_code":"03056",
    "gn:asciiname":"Alcudia",
    "gn:country_code":"ES",
    "gn:dem":373,
    "gn:feature_class":"P",
    "gn:feature_code":"PPL",
    "gn:name":"Alcudia",
    "gn:population":0,
    "gn:timezone":"Europe/Madrid",
    "iso:country":"ES",
    "wof:name":"Alcudia",
    "wof:placetype":"locality"
},
  "geometry": {"coordinates":[-0.42943,38.75907],"type":"Point"}
}