{
  "type": "Feature",
  "properties": {
    "iso:country":"ES",
    "name:eng_x_preferred":[
        "Ind. San Alberto II"
    ],
    "name:spa_x_preferred":[
        "Ind. San Alberto II"
    ],
    "wof:name":"Ind. San Alberto II",
    "wof:placetype":"neighbourhood"
},
  "geometry": {"coordinates":[-4.4527264373421,36.73189688519252],"type":"Point"}
}