{
  "type": "Feature",
  "properties": {
    "gn:admin1_code":"55",
    "gn:admin2_code":"BU",
    "gn:admin3_code":"09109",
    "gn:asciiname":"Torre",
    "gn:country_code":"ES",
    "gn:dem":589,
    "gn:feature_class":"P",
    "gn:feature_code":"PPL",
    "gn:name":"Torre",
    "gn:population":0,
    "gn:timezone":"Europe/Madrid",
    "iso:country":"ES",
    "wof:name":"Torre",
    "wof:placetype":"locality"
},
  "geometry": {"coordinates":[-2.67345,42.69392],"type":"Point"}
}