{
  "type": "Feature",
  "properties": {
    "gn:admin1_code":"56",
    "gn:admin2_code":"B",
    "gn:admin3_code":"08114",
    "gn:asciiname":"Ca'n Bros",
    "gn:country_code":"ES",
    "gn:dem":59,
    "gn:feature_class":"P",
    "gn:feature_code":"PPL",
    "gn:name":"Ca\u2019n Bros",
    "gn:population":0,
    "gn:timezone":"Europe/Madrid",
    "iso:country":"ES",
    "name:und_x_variant":[
        "Barrio Ca\u2019n Bros",
        "Ca\u2019n Bros"
    ],
    "wof:name":"Ca'n Bros",
    "wof:placetype":"locality"
},
  "geometry": {"coordinates":[1.92181,41.4969],"type":"Point"}
}