{
  "type": "Feature",
  "properties": {
    "gn:admin1_code":"39",
    "gn:admin2_code":"S",
    "gn:admin3_code":"39027",
    "gn:asciiname":"Horna",
    "gn:country_code":"ES",
    "gn:dem":858,
    "gn:feature_class":"P",
    "gn:feature_code":"PPL",
    "gn:name":"Horna",
    "gn:population":0,
    "gn:timezone":"Europe/Madrid",
    "iso:country":"ES",
    "name:ces_x_preferred":[
        "Horna"
    ],
    "name:dan_x_preferred":[
        "Horna"
    ],
    "name:deu_x_preferred":[
        "Horna"
    ],
    "name:fin_x_preferred":[
        "Horna"
    ],
    "name:fra_x_preferred":[
        "Horna"
    ],
    "name:ita_x_preferred":[
        "Horna"
    ],
    "name:pol_x_preferred":[
        "Horna"
    ],
    "name:rus_x_preferred":[
        "Horna"
    ],
    "name:swe_x_preferred":[
        "Horna"
    ],
    "name:tur_x_preferred":[
        "Horna"
    ],
    "wof:name":"Horna",
    "wof:placetype":"locality"
},
  "geometry": {"coordinates":[-4.09295,42.97974],"type":"Point"}
}