{
  "type": "Feature",
  "properties": {
    "gn:gn_country":"ES",
    "gn:gn_fcode":"PPLA3",
    "gn:gn_pop":2194,
    "gn:population":2194,
    "iso:country":"ES",
    "name:ara_x_preferred":[
        "\u0641\u064a\u0644\u0627\u0628\u0644\u0627\u0631\u064a\u0643\u0633"
    ],
    "name:arg_x_preferred":[
        "Vilablareix"
    ],
    "name:ast_x_preferred":[
        "Vilablareix"
    ],
    "name:cat_x_preferred":[
        "Vilablareix"
    ],
    "name:ceb_x_preferred":[
        "Vilablareix"
    ],
    "name:deu_x_preferred":[
        "Vilablareix"
    ],
    "name:eng_x_preferred":[
        "Vilablareix"
    ],
    "name:eus_x_preferred":[
        "Vilablareix"
    ],
    "name:fra_x_preferred":[
        "Vilablareix"
    ],
    "name:hun_x_preferred":[
        "Vilablareix"
    ],
    "name:hye_x_preferred":[
        "\u054e\u056b\u056c\u0561\u0562\u056c\u0561\u0580\u0565\u0577"
    ],
    "name:ita_x_preferred":[
        "Vilablareix"
    ],
    "name:kaz_x_preferred":[
        "\u0412\u0438\u043b\u0430\u0431\u043b\u0430\u0440\u0435\u0448"
    ],
    "name:lat_x_preferred":[
        "Vilablareix"
    ],
    "name:msa_x_preferred":[
        "Vilablareix"
    ],
    "name:nld_x_preferred":[
        "Vilablareix"
    ],
    "name:oci_x_preferred":[
        "Vilablareix"
    ],
    "name:pol_x_preferred":[
        "Vilablareix"
    ],
    "name:por_x_preferred":[
        "Vilablareix"
    ],
    "name:rus_x_preferred":[
        "\u0412\u0438\u043b\u0430\u0431\u043b\u0430\u0440\u0435\u0448"
    ],
    "name:spa_x_preferred":[
        "Vilablareix"
    ],
    "name:sqi_x_preferred":[
        "Vilablareix"
    ],
    "name:swe_x_preferred":[
        "Vilablareix"
    ],
    "name:tah_x_preferred":[
        "Vilablareix"
    ],
    "name:uzb_x_preferred":[
        "Vilablareix"
    ],
    "name:war_x_preferred":[
        "Vilablareix"
    ],
    "name:zho_x_preferred":[
        "\u6bd4\u62c9\u592b\u62c9\u96f7\u65af"
    ],
    "qs_pg:aaroncc":"ES",
    "qs_pg:gn_country":"ES",
    "qs_pg:gn_fcode":"PPLA3",
    "qs_pg:gn_pop":2194,
    "qs_pg:name":"Vilablareix",
    "qs_pg:name_adm0":"Espa\u00f1a",
    "qs_pg:name_adm1":"Catalunya",
    "qs_pg:photos":373,
    "qs_pg:photos_1k":76,
    "qs_pg:photos_9k":2,
    "qs_pg:photos_9r":5,
    "qs_pg:photos_all":373,
    "qs_pg:photos_sr":6,
    "qs_pg:pop_sr":4,
    "qs_pg:qs_pg_placetype":"locality",
    "qs_pg:qs_pg_placetype_gp":"Town",
    "qs_pg:woe_adm0":23424950,
    "woe:adm0_id":23424950,
    "woe:name_adm0":"Espa\u00f1a",
    "woe:name_adm1":"Catalunya",
    "woe:placetype":"Town",
    "wof:name":"Vilablareix",
    "wof:placetype":"locality",
    "wof:population":2194
},
  "geometry": {"coordinates":[2.77377,41.95746],"type":"Point"}
}