{
  "type": "Feature",
  "properties": {
    "gn:admin1_code":"34",
    "gn:admin2_code":"O",
    "gn:admin3_code":"33016",
    "gn:asciiname":"Castrillon",
    "gn:country_code":"ES",
    "gn:dem":113,
    "gn:feature_class":"P",
    "gn:feature_code":"PPLA3",
    "gn:name":"Castrill\u00f3n",
    "gn:population":0,
    "gn:timezone":"Europe/Madrid",
    "iso:country":"ES",
    "name:ara_x_preferred":[
        "\u0643\u0627\u0633\u062a\u0631\u064a\u0648\u0646"
    ],
    "name:arg_x_preferred":[
        "Castrill\u00f3n"
    ],
    "name:ast_x_preferred":[
        "Castrill\u00f3n"
    ],
    "name:azb_x_preferred":[
        "\u06a9\u0627\u0633\u062a\u0631\u06cc\u06cc\u0646"
    ],
    "name:cat_x_preferred":[
        "Castrill\u00f3n"
    ],
    "name:cym_x_preferred":[
        "Castrill\u00f3n"
    ],
    "name:deu_x_preferred":[
        "Castrill\u00f3n"
    ],
    "name:eus_x_preferred":[
        "Castrill\u00f3n"
    ],
    "name:fas_x_preferred":[
        "\u06a9\u0627\u0633\u062a\u0631\u06cc\u06cc\u0646"
    ],
    "name:fra_x_preferred":[
        "Castrill\u00f3n"
    ],
    "name:glg_x_preferred":[
        "Castrill\u00f3n"
    ],
    "name:hun_x_preferred":[
        "Castrill\u00f3n"
    ],
    "name:ina_x_preferred":[
        "Castrill\u00f3n"
    ],
    "name:ita_x_preferred":[
        "Castrill\u00f3n"
    ],
    "name:msa_x_preferred":[
        "Castrill\u00f3n"
    ],
    "name:nld_x_preferred":[
        "Castrill\u00f3n"
    ],
    "name:oci_x_preferred":[
        "Castrill\u00f3n"
    ],
    "name:pam_x_preferred":[
        "Castrill\u00f3n"
    ],
    "name:pol_x_preferred":[
        "Castrill\u00f3n"
    ],
    "name:por_x_preferred":[
        "Castrill\u00f3n"
    ],
    "name:rus_x_preferred":[
        "\u041a\u0430\u0441\u0442\u0440\u0438\u043b\u044c\u043e\u043d"
    ],
    "name:spa_x_preferred":[
        "Castrill\u00f3n"
    ],
    "name:sqi_x_preferred":[
        "Castrill\u00f3n"
    ],
    "name:srp_x_preferred":[
        "\u041a\u0430\u0441\u0442\u0440\u0438\u0459\u043e\u043d"
    ],
    "name:tur_x_preferred":[
        "Castrill\u00f3n"
    ],
    "name:ukr_x_preferred":[
        "\u041a\u0430\u0441\u0442\u0440\u0456\u043b\u044c\u0439\u043e\u043d"
    ],
    "name:uzb_x_preferred":[
        "Castrill\u00f3n"
    ],
    "name:vie_x_preferred":[
        "Castrill\u00f3n"
    ],
    "name:war_x_preferred":[
        "Castrill\u00f3n"
    ],
    "name:zho_x_preferred":[
        "\u5361\u65af\u7279\u91cc\u5229\u7fc1"
    ],
    "wof:name":"Castrillon",
    "wof:placetype":"locality"
},
  "geometry": {"coordinates":[-5.99381,43.54793],"type":"Point"}
}