{
  "type": "Feature",
  "properties": {
    "gn:gn_country":"ES",
    "gn:gn_fcode":"ADM3",
    "gn:gn_pop":95,
    "gn:population":94,
    "iso:country":"ES",
    "name:alb_x_preferred":[
        "Cab\u00f3"
    ],
    "name:arg_x_preferred":[
        "Cab\u00f3"
    ],
    "name:arm_x_preferred":[
        "\u053f\u0561\u0562\u0578"
    ],
    "name:baq_x_preferred":[
        "Cab\u00f3"
    ],
    "name:cat_x_preferred":[
        "Cab\u00f3"
    ],
    "name:chi_x_preferred":[
        "\u5361\u6c83"
    ],
    "name:dut_x_preferred":[
        "Cab\u00f3"
    ],
    "name:eng_x_preferred":[
        "Cab\u00f3"
    ],
    "name:fre_x_preferred":[
        "Cab\u00f3"
    ],
    "name:ger_x_preferred":[
        "Cab\u00f3"
    ],
    "name:gre_x_preferred":[
        "\u039a\u03b1\u03bc\u03c0\u03cc"
    ],
    "name:hun_x_preferred":[
        "Cab\u00f3"
    ],
    "name:ita_x_preferred":[
        "Cab\u00f3"
    ],
    "name:may_x_preferred":[
        "Cab\u00f3"
    ],
    "name:oci_x_preferred":[
        "Cab\u00f3"
    ],
    "name:pol_x_preferred":[
        "Cab\u00f3"
    ],
    "name:por_x_preferred":[
        "Cab\u00f3"
    ],
    "name:rum_x_preferred":[
        "Cab\u00f3"
    ],
    "name:rus_x_preferred":[
        "\u041a\u0430\u0431\u043e"
    ],
    "name:spa_x_preferred":[
        "Cab\u00f3"
    ],
    "name:swe_x_preferred":[
        "Cab\u00f3"
    ],
    "name:ukr_x_preferred":[
        "\u041a\u0430\u0431\u043e"
    ],
    "name:uzb_x_preferred":[
        "Cab\u00f3"
    ],
    "name:vie_x_preferred":[
        "Cab\u00f3"
    ],
    "name:war_x_preferred":[
        "Cab\u00f3"
    ],
    "qs_pg:aaroncc":"ES",
    "qs_pg:gn_country":"ES",
    "qs_pg:gn_fcode":"ADM3",
    "qs_pg:gn_pop":95,
    "qs_pg:name":"Cab\u00f3",
    "qs_pg:name_adm0":"Espa\u00f1a",
    "qs_pg:name_adm1":"Catalunya",
    "qs_pg:photos":36,
    "qs_pg:photos_1k":7,
    "qs_pg:photos_9k":1,
    "qs_pg:photos_9r":2,
    "qs_pg:photos_all":36,
    "qs_pg:photos_sr":2,
    "qs_pg:pop_sr":1,
    "qs_pg:qs_pg_placetype":"locality",
    "qs_pg:qs_pg_placetype_gp":"Town",
    "qs_pg:woe_adm0":23424950,
    "woe:adm0_id":23424950,
    "woe:name_adm0":"Espa\u00f1a",
    "woe:name_adm1":"Catalunya",
    "woe:placetype":"Town",
    "wof:name":"Cab\u00f3",
    "wof:placetype":"locality",
    "wof:population":94
},
  "geometry": {"coordinates":[1.24244,42.23595],"type":"Point"}
}