{
  "type": "Feature",
  "properties": {
    "gn:admin1_code":"54",
    "gn:admin2_code":"GU",
    "gn:admin3_code":"19211",
    "gn:asciiname":"Tabladillo",
    "gn:country_code":"ES",
    "gn:dem":938,
    "gn:feature_class":"P",
    "gn:feature_code":"PPL",
    "gn:name":"Tabladillo",
    "gn:population":0,
    "gn:timezone":"Europe/Madrid",
    "iso:country":"ES",
    "wof:name":"Tabladillo",
    "wof:placetype":"locality"
},
  "geometry": {"coordinates":[-2.67063,40.53119],"type":"Point"}
}