{
  "type": "Feature",
  "properties": {
    "gn:admin1_code":"32",
    "gn:admin3_code":"31237",
    "gn:asciiname":"Zabalceta",
    "gn:country_code":"ES",
    "gn:dem":543,
    "gn:feature_class":"P",
    "gn:feature_code":"PPL",
    "gn:name":"Zabalceta",
    "gn:population":0,
    "gn:timezone":"Europe/Madrid",
    "iso:country":"ES",
    "wof:name":"Zabalceta",
    "wof:placetype":"locality"
},
  "geometry": {"coordinates":[-1.50848,42.73242],"type":"Point"}
}