{
  "type": "Feature",
  "properties": {
    "gn:admin1_code":"51",
    "gn:admin2_code":"H",
    "gn:admin3_code":"21063",
    "gn:asciiname":"El Campillo",
    "gn:country_code":"ES",
    "gn:dem":103,
    "gn:feature_class":"P",
    "gn:feature_code":"PPL",
    "gn:name":"El Campillo",
    "gn:population":0,
    "gn:timezone":"Europe/Madrid",
    "iso:country":"ES",
    "name:und_x_variant":[
        "Casas El Campillo",
        "El Campillo"
    ],
    "wof:name":"El Campillo",
    "wof:placetype":"locality"
},
  "geometry": {"coordinates":[-7.0559,37.43493],"type":"Point"}
}