{
  "type": "Feature",
  "properties": {
    "gn:admin1_code":"39",
    "gn:admin2_code":"S",
    "gn:admin3_code":"39015",
    "gn:asciiname":"Barcena",
    "gn:country_code":"ES",
    "gn:dem":584,
    "gn:feature_class":"P",
    "gn:feature_code":"PPL",
    "gn:name":"B\u00e1rcena",
    "gn:population":0,
    "gn:timezone":"Europe/Madrid",
    "iso:country":"ES",
    "wof:name":"Barcena",
    "wof:placetype":"locality"
},
  "geometry": {"coordinates":[-4.71251,43.13484],"type":"Point"}
}