{
  "type": "Feature",
  "properties": {
    "gn:gn_country":"ES",
    "gn:gn_fcode":"PPLA3",
    "gn:gn_pop":354,
    "gn:population":354,
    "iso:country":"ES",
    "name:ara_x_preferred":[
        "\u0641\u064a\u0644\u0627\u0631 \u062f\u064a \u0647\u0648\u0645\u0648"
    ],
    "name:arg_x_preferred":[
        "Villar del Humo"
    ],
    "name:cat_x_preferred":[
        "Villar del Humo"
    ],
    "name:eng_x_preferred":[
        "Villar del Humo"
    ],
    "name:eus_x_preferred":[
        "Villar del Humo"
    ],
    "name:fra_x_preferred":[
        "Villar del Humo"
    ],
    "name:hun_x_preferred":[
        "Villar del Humo"
    ],
    "name:ita_x_preferred":[
        "Villar del Humo"
    ],
    "name:kaz_x_preferred":[
        "\u0412\u0438\u043b\u044c\u044f\u0440-\u0434\u0435\u043b\u044c-\u0423\u043c\u043e"
    ],
    "name:msa_x_preferred":[
        "Villar del Humo"
    ],
    "name:nan_x_preferred":[
        "Villar del Humo"
    ],
    "name:nld_x_preferred":[
        "Villar del Humo"
    ],
    "name:oci_x_preferred":[
        "Villar del Humo"
    ],
    "name:pol_x_preferred":[
        "Villar del Humo"
    ],
    "name:por_x_preferred":[
        "Villar del Humo"
    ],
    "name:rus_x_preferred":[
        "\u0412\u0438\u043b\u044c\u044f\u0440-\u0434\u0435\u043b\u044c-\u0423\u043c\u043e"
    ],
    "name:spa_x_preferred":[
        "Villar del Humo"
    ],
    "name:swe_x_preferred":[
        "Villar del Humo"
    ],
    "name:ukr_x_preferred":[
        "\u0412\u0456\u043b\u044c\u044f\u0440-\u0434\u0435\u043b\u044c-\u0423\u043c\u043e"
    ],
    "name:vie_x_preferred":[
        "Villar del Humo"
    ],
    "name:war_x_preferred":[
        "Villar del Humo"
    ],
    "name:zho_x_preferred":[
        "\u4e4c\u83ab\u6751"
    ],
    "qs_pg:aaroncc":"ES",
    "qs_pg:gn_country":"ES",
    "qs_pg:gn_fcode":"PPLA3",
    "qs_pg:gn_pop":354,
    "qs_pg:name":"Villar del Humo",
    "qs_pg:name_adm0":"Espa\u00f1a",
    "qs_pg:name_adm1":"Castilla-La Mancha",
    "qs_pg:photos_9k":1,
    "qs_pg:photos_9r":1,
    "qs_pg:photos_all":2,
    "qs_pg:photos_sr":0,
    "qs_pg:pop_sr":2,
    "qs_pg:qs_pg_placetype":"locality",
    "qs_pg:qs_pg_placetype_gp":"Town",
    "qs_pg:woe_adm0":23424950,
    "woe:adm0_id":23424950,
    "woe:name_adm0":"Espa\u00f1a",
    "woe:name_adm1":"Castilla-La Mancha",
    "woe:placetype":"Town",
    "wof:name":"Villar del Humo",
    "wof:placetype":"locality",
    "wof:population":354
},
  "geometry": {"coordinates":[-1.63333,39.86667],"type":"Point"}
}