{
  "type": "Feature",
  "properties": {
    "gn:admin1_code":"34",
    "gn:admin2_code":"O",
    "gn:admin3_code":"33025",
    "gn:asciiname":"Balbin",
    "gn:country_code":"ES",
    "gn:dem":52,
    "gn:feature_class":"P",
    "gn:feature_code":"PPL",
    "gn:name":"Balb\u00edn",
    "gn:population":0,
    "gn:timezone":"Europe/Madrid",
    "iso:country":"ES",
    "name:und_x_variant":[
        "Balb\u00edn"
    ],
    "wof:name":"Balbin",
    "wof:placetype":"locality"
},
  "geometry": {"coordinates":[-5.81691,43.61411],"type":"Point"}
}