{
  "type": "Feature",
  "properties": {
    "iso:country":"ES",
    "name:eng_x_preferred":[
        "Los Guindos"
    ],
    "name:spa_x_preferred":[
        "Los Guindos"
    ],
    "wof:name":"Los Guindos",
    "wof:placetype":"neighbourhood"
},
  "geometry": {"coordinates":[-4.44668967588184,36.68920180585199],"type":"Point"}
}