{
  "type": "Feature",
  "properties": {
    "gn:admin1_code":"54",
    "gn:admin2_code":"AB",
    "gn:admin3_code":"02055",
    "gn:asciiname":"Canadas",
    "gn:country_code":"ES",
    "gn:dem":1478,
    "gn:feature_class":"P",
    "gn:feature_code":"PPL",
    "gn:name":"Ca\u00f1adas",
    "gn:population":0,
    "gn:timezone":"Europe/Madrid",
    "iso:country":"ES",
    "name:und_x_variant":[
        "Ca\u00f1adas de Abajo",
        "Ca\u00f1adas"
    ],
    "wof:name":"Canadas",
    "wof:placetype":"locality"
},
  "geometry": {"coordinates":[-2.41453,38.08787],"type":"Point"}
}