{
  "type": "Feature",
  "properties": {
    "gn:admin1_code":"59",
    "gn:admin2_code":"SS",
    "gn:admin3_code":"20059",
    "gn:asciiname":"Zubia",
    "gn:country_code":"ES",
    "gn:dem":423,
    "gn:feature_class":"P",
    "gn:feature_code":"PPL",
    "gn:name":"Zubia",
    "gn:population":0,
    "gn:timezone":"Europe/Madrid",
    "iso:country":"ES",
    "name:eus_x_preferred":[
        "Zubia"
    ],
    "wof:name":"Zubia",
    "wof:placetype":"locality"
},
  "geometry": {"coordinates":[-2.44744,42.99349],"type":"Point"}
}