{
  "type": "Feature",
  "properties": {
    "gn:admin1_code":"55",
    "gn:admin2_code":"LE",
    "gn:admin3_code":"24037",
    "gn:asciiname":"Lavandera",
    "gn:country_code":"ES",
    "gn:dem":1204,
    "gn:feature_class":"P",
    "gn:feature_code":"PPL",
    "gn:name":"Lavandera",
    "gn:population":0,
    "gn:timezone":"Europe/Madrid",
    "iso:country":"ES",
    "wof:name":"Lavandera",
    "wof:placetype":"locality"
},
  "geometry": {"coordinates":[-5.51399,42.9499],"type":"Point"}
}