{
  "type": "Feature",
  "properties": {
    "gn:admin1_code":"54",
    "gn:admin2_code":"CU",
    "gn:admin3_code":"16905",
    "gn:asciiname":"Villar del Saz de Arcas",
    "gn:country_code":"ES",
    "gn:dem":1214,
    "gn:feature_class":"P",
    "gn:feature_code":"PPL",
    "gn:name":"Villar del Saz de Arcas",
    "gn:population":0,
    "gn:timezone":"Europe/Madrid",
    "iso:country":"ES",
    "wof:name":"Villar del Saz de Arcas",
    "wof:placetype":"locality"
},
  "geometry": {"coordinates":[-2.06667,39.95],"type":"Point"}
}