{
  "type": "Feature",
  "properties": {
    "gn:admin1_code":"34",
    "gn:admin2_code":"O",
    "gn:admin3_code":"33061",
    "gn:asciiname":"Bousono",
    "gn:country_code":"ES",
    "gn:dem":552,
    "gn:feature_class":"P",
    "gn:feature_code":"PPL",
    "gn:name":"Bouso\u00f1o",
    "gn:population":0,
    "gn:timezone":"Europe/Madrid",
    "iso:country":"ES",
    "name:und_x_variant":[
        "Bouso\u00f1o"
    ],
    "wof:name":"Bousono",
    "wof:placetype":"locality"
},
  "geometry": {"coordinates":[-6.89962,43.3039],"type":"Point"}
}