{
  "type": "Feature",
  "properties": {
    "gn:gn_country":"ES",
    "gn:gn_fcode":"PPL",
    "gn:gn_pop":106,
    "gn:population":106,
    "iso:country":"ES",
    "name:aze_x_preferred":[
        "Axuy"
    ],
    "name:ceb_x_preferred":[
        "Ajuy"
    ],
    "name:deu_x_preferred":[
        "Ajuy"
    ],
    "name:eng_x_preferred":[
        "Ajuy"
    ],
    "name:nld_x_preferred":[
        "Ajuy"
    ],
    "name:rus_x_preferred":[
        "\u0410\u0445\u0443\u0438"
    ],
    "name:rus_x_variant":[
        "\u0410\u0445\u0443\u0439"
    ],
    "name:spa_x_preferred":[
        "Ajuy"
    ],
    "name:swe_x_preferred":[
        "Ajuy"
    ],
    "name:ukr_x_preferred":[
        "\u0410\u0445\u0443\u0439"
    ],
    "qs_pg:aaroncc":"ES",
    "qs_pg:gn_country":"ES",
    "qs_pg:gn_fcode":"PPL",
    "qs_pg:gn_pop":106,
    "qs_pg:name":"Ajui",
    "qs_pg:name_adm0":"Espa\u00f1a",
    "qs_pg:name_adm1":"Islas Canarias",
    "qs_pg:photos":520,
    "qs_pg:photos_1k":105,
    "qs_pg:photos_9k":2,
    "qs_pg:photos_9r":5,
    "qs_pg:photos_all":520,
    "qs_pg:photos_sr":7,
    "qs_pg:pop_sr":1,
    "qs_pg:qs_pg_placetype":"locality",
    "qs_pg:qs_pg_placetype_gp":"Town",
    "qs_pg:woe_adm0":23424950,
    "woe:adm0_id":23424950,
    "woe:name_adm0":"Espa\u00f1a",
    "woe:name_adm1":"Islas Canarias",
    "woe:placetype":"Town",
    "wof:name":"Ajui",
    "wof:placetype":"locality",
    "wof:population":106
},
  "geometry": {"coordinates":[-14.15382,28.3994],"type":"Point"}
}