{
  "type": "Feature",
  "properties": {
    "gn:admin1_code":"34",
    "gn:admin2_code":"O",
    "gn:admin3_code":"33076",
    "gn:asciiname":"Sopenas",
    "gn:country_code":"ES",
    "gn:dem":188,
    "gn:feature_class":"P",
    "gn:feature_code":"PPL",
    "gn:name":"Sope\u00f1as",
    "gn:population":0,
    "gn:timezone":"Europe/Madrid",
    "iso:country":"ES",
    "name:und_x_variant":[
        "Sope\u00f1as"
    ],
    "wof:name":"Sopenas",
    "wof:placetype":"locality"
},
  "geometry": {"coordinates":[-5.53333,43.45],"type":"Point"}
}