{
  "type": "Feature",
  "properties": {
    "gn:gn_country":"ES",
    "gn:gn_fcode":"PPLA3",
    "gn:gn_pop":368,
    "gn:population":368,
    "iso:country":"ES",
    "name:alb_x_preferred":[
        "Herguijuela"
    ],
    "name:ara_x_preferred":[
        "\u0647\u064a\u0631\u062c\u0648\u0627\u064a\u062e\u0648\u064a\u0644\u0627"
    ],
    "name:baq_x_preferred":[
        "Herguijuela"
    ],
    "name:cat_x_preferred":[
        "Herguijuela"
    ],
    "name:chi_x_preferred":[
        "\u57c3\u5c14\u5409\u80e1\u57c3\u62c9"
    ],
    "name:dut_x_preferred":[
        "Herguijuela"
    ],
    "name:eng_x_preferred":[
        "Herguijuela"
    ],
    "name:epo_x_preferred":[
        "Herguijuela"
    ],
    "name:ext_x_preferred":[
        "Erguijuela"
    ],
    "name:fre_x_preferred":[
        "Herguijuela"
    ],
    "name:ger_x_preferred":[
        "Herguijuela"
    ],
    "name:hun_x_preferred":[
        "Herguijuela"
    ],
    "name:ina_x_preferred":[
        "Herguijuela"
    ],
    "name:ita_x_preferred":[
        "Herguijuela"
    ],
    "name:may_x_preferred":[
        "Herguijuela"
    ],
    "name:nan_x_preferred":[
        "Herguijuela"
    ],
    "name:oci_x_preferred":[
        "Herguijuela"
    ],
    "name:pol_x_preferred":[
        "Herguijuela"
    ],
    "name:por_x_preferred":[
        "Herguijuela"
    ],
    "name:rum_x_preferred":[
        "Herguijuela"
    ],
    "name:rus_x_preferred":[
        "\u042d\u0440\u0433\u0438\u0445\u0443\u044d\u043b\u0430"
    ],
    "name:spa_x_preferred":[
        "Herguijuela"
    ],
    "name:swe_x_preferred":[
        "Herguijuela"
    ],
    "name:ukr_x_preferred":[
        "\u0415\u0440\u0433\u0456\u0445\u0443\u0435\u043b\u0430"
    ],
    "name:uzb_x_preferred":[
        "Herguijuela"
    ],
    "name:vie_x_preferred":[
        "Herguijuela"
    ],
    "name:war_x_preferred":[
        "Herguijuela"
    ],
    "qs_pg:aaroncc":"ES",
    "qs_pg:gn_country":"ES",
    "qs_pg:gn_fcode":"PPLA3",
    "qs_pg:gn_pop":368,
    "qs_pg:name":"Herguijuela",
    "qs_pg:name_adm0":"Espa\u00f1a",
    "qs_pg:name_adm1":"Extremadura",
    "qs_pg:photos":32,
    "qs_pg:photos_1k":6,
    "qs_pg:photos_9k":1,
    "qs_pg:photos_9r":2,
    "qs_pg:photos_all":32,
    "qs_pg:photos_sr":2,
    "qs_pg:pop_sr":2,
    "qs_pg:qs_pg_placetype":"locality",
    "qs_pg:qs_pg_placetype_gp":"Town",
    "qs_pg:woe_adm0":23424950,
    "woe:adm0_id":23424950,
    "woe:name_adm0":"Espa\u00f1a",
    "woe:name_adm1":"Extremadura",
    "woe:placetype":"Town",
    "wof:name":"Herguijuela",
    "wof:placetype":"locality",
    "wof:population":368
},
  "geometry": {"coordinates":[-5.76001,39.37452],"type":"Point"}
}