{
  "type": "Feature",
  "properties": {
    "gn:admin1_code":"55",
    "gn:admin2_code":"BU",
    "gn:admin3_code":"09001",
    "gn:asciiname":"Barcena de Bureba",
    "gn:country_code":"ES",
    "gn:dem":762,
    "gn:feature_class":"P",
    "gn:feature_code":"PPL",
    "gn:name":"B\u00e1rcena de Bureba",
    "gn:population":0,
    "gn:timezone":"Europe/Madrid",
    "iso:country":"ES",
    "wof:name":"Barcena de Bureba",
    "wof:placetype":"locality"
},
  "geometry": {"coordinates":[-3.55373,42.61741],"type":"Point"}
}