{
  "type": "Feature",
  "properties": {
    "gn:admin1_code":"55",
    "gn:admin2_code":"ZA",
    "gn:admin3_code":"49032",
    "gn:asciiname":"Olleros de Tera",
    "gn:country_code":"ES",
    "gn:dem":751,
    "gn:feature_class":"P",
    "gn:feature_code":"PPL",
    "gn:name":"Olleros de Tera",
    "gn:population":0,
    "gn:timezone":"Europe/Madrid",
    "iso:country":"ES",
    "name:und_x_variant":[
        "Olleros",
        "Olleros de Tera"
    ],
    "wof:name":"Olleros de Tera",
    "wof:placetype":"locality"
},
  "geometry": {"coordinates":[-6.10165,41.9837],"type":"Point"}
}