{
  "type": "Feature",
  "properties": {
    "gn:admin1_code":"58",
    "gn:admin2_code":"PO",
    "gn:admin3_code":"36051",
    "gn:asciiname":"Adina",
    "gn:cc2":"ES",
    "gn:country_code":"ES",
    "gn:dem":81,
    "gn:feature_class":"P",
    "gn:feature_code":"PPL",
    "gn:name":"Adina",
    "gn:population":0,
    "gn:timezone":"Europe/Madrid",
    "iso:country":"ES",
    "name:deu_x_preferred":[
        "Adina"
    ],
    "name:glg_x_preferred":[
        "Adina"
    ],
    "name:hun_x_preferred":[
        "Adina"
    ],
    "name:ita_x_preferred":[
        "Adina"
    ],
    "name:pol_x_preferred":[
        "Adina"
    ],
    "name:slk_x_preferred":[
        "Adina"
    ],
    "name:und_x_variant":[
        "Santa Mar\u00eda"
    ],
    "wof:name":"Adina",
    "wof:placetype":"locality"
},
  "geometry": {"coordinates":[-8.83258,42.41056],"type":"Point"}
}