{
  "type": "Feature",
  "properties": {
    "gn:admin1_code":"55",
    "gn:admin2_code":"SG",
    "gn:admin3_code":"40170",
    "gn:asciiname":"Barahona de Fresno",
    "gn:country_code":"ES",
    "gn:dem":1023,
    "gn:feature_class":"P",
    "gn:feature_code":"PPL",
    "gn:name":"Barahona de Fresno",
    "gn:population":0,
    "gn:timezone":"Europe/Madrid",
    "iso:country":"ES",
    "name:und_x_variant":[
        "Barahona del Fresno",
        "Barahona",
        "Barahona de Fresno"
    ],
    "wof:name":"Barahona de Fresno",
    "wof:placetype":"locality"
},
  "geometry": {"coordinates":[-3.56961,41.35356],"type":"Point"}
}