{
  "type": "Feature",
  "properties": {
    "gn:admin1_code":"55",
    "gn:admin2_code":"BU",
    "gn:admin3_code":"09012",
    "gn:asciiname":"Quintanilla de Santa Gadea",
    "gn:country_code":"ES",
    "gn:dem":914,
    "gn:feature_class":"P",
    "gn:feature_code":"PPL",
    "gn:name":"Quintanilla de Santa Gadea",
    "gn:population":0,
    "gn:timezone":"Europe/Madrid",
    "iso:country":"ES",
    "wof:name":"Quintanilla de Santa Gadea",
    "wof:placetype":"locality"
},
  "geometry": {"coordinates":[-3.96177,42.96413],"type":"Point"}
}