{
  "type": "Feature",
  "properties": {
    "gn:admin1_code":"39",
    "gn:admin2_code":"S",
    "gn:admin3_code":"39067",
    "gn:asciiname":"Lastras",
    "gn:country_code":"ES",
    "gn:dem":132,
    "gn:feature_class":"P",
    "gn:feature_code":"PPL",
    "gn:name":"Lastras",
    "gn:population":0,
    "gn:timezone":"Europe/Madrid",
    "iso:country":"ES",
    "wof:name":"Lastras",
    "wof:placetype":"locality"
},
  "geometry": {"coordinates":[-3.53868,43.28109],"type":"Point"}
}