{
  "type": "Feature",
  "properties": {
    "gn:admin1_code":"58",
    "gn:admin2_code":"LU",
    "gn:admin3_code":"27026",
    "gn:asciiname":"Carracedo",
    "gn:country_code":"ES",
    "gn:dem":427,
    "gn:feature_class":"P",
    "gn:feature_code":"PPL",
    "gn:name":"Carracedo",
    "gn:population":0,
    "gn:timezone":"Europe/Madrid",
    "iso:country":"ES",
    "wof:name":"Carracedo",
    "wof:placetype":"locality"
},
  "geometry": {"coordinates":[-7.37344,42.86857],"type":"Point"}
}