{
  "type": "Feature",
  "properties": {
    "gn:admin1_code":"34",
    "gn:admin2_code":"O",
    "gn:admin3_code":"33059",
    "gn:asciiname":"Branalonga",
    "gn:country_code":"ES",
    "gn:dem":551,
    "gn:feature_class":"P",
    "gn:feature_code":"PPL",
    "gn:name":"Bra\u00f1alonga",
    "gn:population":0,
    "gn:timezone":"Europe/Madrid",
    "iso:country":"ES",
    "name:und_x_variant":[
        "Bra\u00f1alonga"
    ],
    "wof:name":"Branalonga",
    "wof:placetype":"locality"
},
  "geometry": {"coordinates":[-6.34843,43.39643],"type":"Point"}
}