{
  "type": "Feature",
  "properties": {
    "gn:admin1_code":"34",
    "gn:admin2_code":"O",
    "gn:admin3_code":"33059",
    "gn:asciiname":"Colniella",
    "gn:country_code":"ES",
    "gn:dem":527,
    "gn:feature_class":"P",
    "gn:feature_code":"PPL",
    "gn:name":"Colniella",
    "gn:population":0,
    "gn:timezone":"Europe/Madrid",
    "iso:country":"ES",
    "name:und_x_variant":[
        "Coroniella",
        "Colniella"
    ],
    "wof:name":"Colniella",
    "wof:placetype":"locality"
},
  "geometry": {"coordinates":[-6.3226,43.44394000000001],"type":"Point"}
}