{
  "type": "Feature",
  "properties": {
    "gn:admin1_code":"54",
    "gn:admin2_code":"CU",
    "gn:admin3_code":"16126",
    "gn:asciiname":"El Canaveral",
    "gn:cc2":"ES",
    "gn:country_code":"ES",
    "gn:dem":842,
    "gn:feature_class":"P",
    "gn:feature_code":"PPL",
    "gn:name":"El Ca\u00f1averal",
    "gn:population":0,
    "gn:timezone":"Europe/Madrid",
    "iso:country":"ES",
    "name:und_x_variant":[
        "Caser\u00edo El Ca\u00f1averal",
        "El Ca\u00f1averal"
    ],
    "wof:name":"El Canaveral",
    "wof:placetype":"locality"
},
  "geometry": {"coordinates":[-1.53333,39.61667],"type":"Point"}
}