{
  "type": "Feature",
  "properties": {
    "gn:admin1_code":"34",
    "gn:admin2_code":"O",
    "gn:admin3_code":"33035",
    "gn:asciiname":"Posada",
    "gn:country_code":"ES",
    "gn:dem":173,
    "gn:feature_class":"P",
    "gn:feature_code":"PPL",
    "gn:name":"Posada",
    "gn:population":0,
    "gn:timezone":"Europe/Madrid",
    "iso:country":"ES",
    "wof:name":"Posada",
    "wof:placetype":"locality"
},
  "geometry": {"coordinates":[-5.85497,43.43955],"type":"Point"}
}