{
  "type": "Feature",
  "properties": {
    "gn:admin1_code":"58",
    "gn:admin2_code":"OR",
    "gn:admin3_code":"32084",
    "gn:asciiname":"Bangueses de Arriba",
    "gn:country_code":"ES",
    "gn:dem":808,
    "gn:feature_class":"P",
    "gn:feature_code":"PPL",
    "gn:name":"Bangueses de Arriba",
    "gn:population":0,
    "gn:timezone":"Europe/Madrid",
    "iso:country":"ES",
    "wof:name":"Bangueses de Arriba",
    "wof:placetype":"locality"
},
  "geometry": {"coordinates":[-8.05139,42.10092],"type":"Point"}
}