{
  "type": "Feature",
  "properties": {
    "gn:gn_country":"ES",
    "gn:gn_fcode":"PPLA3",
    "gn:gn_pop":343,
    "gn:population":343,
    "iso:country":"ES",
    "name:ara_x_preferred":[
        "\u0623\u0648\u0631\u064a\u0627 \u062f\u064a \u062e\u0627\u0644\u0648\u0646"
    ],
    "name:arg_x_preferred":[
        "Urreya de Xal\u00f3n"
    ],
    "name:baq_x_preferred":[
        "Urrea de Jal\u00f3n"
    ],
    "name:cat_x_preferred":[
        "Urrea de Jal\u00f3n"
    ],
    "name:chi_x_preferred":[
        "\u4e4c\u96f7\u4e9a\u5fb7\u54c8\u9686"
    ],
    "name:dut_x_preferred":[
        "Urrea de Jal\u00f3n"
    ],
    "name:eng_x_preferred":[
        "Urrea de Jal\u00f3n"
    ],
    "name:fre_x_preferred":[
        "Urrea de Jal\u00f3n"
    ],
    "name:hun_x_preferred":[
        "Urrea de Jal\u00f3n"
    ],
    "name:ita_x_preferred":[
        "Urrea de Jal\u00f3n"
    ],
    "name:kaz_x_preferred":[
        "\u0423\u0440\u0440\u0435\u0430-\u0434\u0435-\u0425\u0430\u043b\u043e\u043d"
    ],
    "name:may_x_preferred":[
        "Urrea de Jal\u00f3n"
    ],
    "name:nan_x_preferred":[
        "Urrea de Jal\u00f3n"
    ],
    "name:oci_x_preferred":[
        "Urrea de Jal\u00f3n"
    ],
    "name:pol_x_preferred":[
        "Urrea de Jal\u00f3n"
    ],
    "name:por_x_preferred":[
        "Urrea de Jal\u00f3n"
    ],
    "name:rus_x_preferred":[
        "\u0423\u0440\u0440\u0435\u0430-\u0434\u0435-\u0425\u0430\u043b\u043e\u043d"
    ],
    "name:spa_x_preferred":[
        "Urrea de Jal\u00f3n"
    ],
    "name:ukr_x_preferred":[
        "\u0423\u0440\u0440\u0435\u0430-\u0434\u0435-\u0425\u0430\u043b\u043e\u043d"
    ],
    "name:uzb_x_preferred":[
        "Urrea de Jal\u00f3n"
    ],
    "name:vie_x_preferred":[
        "Urrea de Jal\u00f3n"
    ],
    "name:war_x_preferred":[
        "Urrea de Jal\u00f3n"
    ],
    "qs_pg:aaroncc":"ES",
    "qs_pg:gn_country":"ES",
    "qs_pg:gn_fcode":"PPLA3",
    "qs_pg:gn_pop":343,
    "qs_pg:name":"Urrea de Jal\u00f3n",
    "qs_pg:name_adm0":"Espa\u00f1a",
    "qs_pg:name_adm1":"Arag\u00f3n",
    "qs_pg:photos":9,
    "qs_pg:photos_1k":2,
    "qs_pg:photos_9k":1,
    "qs_pg:photos_9r":1,
    "qs_pg:photos_all":9,
    "qs_pg:photos_sr":1,
    "qs_pg:pop_sr":2,
    "qs_pg:qs_pg_placetype":"locality",
    "qs_pg:qs_pg_placetype_gp":"Town",
    "qs_pg:woe_adm0":23424950,
    "woe:adm0_id":23424950,
    "woe:name_adm0":"Espa\u00f1a",
    "woe:name_adm1":"Arag\u00f3n",
    "woe:placetype":"Town",
    "wof:name":"Urrea de Jal\u00f3n",
    "wof:placetype":"locality",
    "wof:population":343
},
  "geometry": {"coordinates":[-1.2342,41.66715],"type":"Point"}
}