{
  "type": "Feature",
  "properties": {
    "gn:admin1_code":"34",
    "gn:admin2_code":"O",
    "gn:admin3_code":"33026",
    "gn:asciiname":"Nalio",
    "gn:country_code":"ES",
    "gn:dem":170,
    "gn:feature_class":"P",
    "gn:feature_code":"PPL",
    "gn:name":"Nali\u00f3",
    "gn:population":0,
    "gn:timezone":"Europe/Madrid",
    "iso:country":"ES",
    "name:und_x_variant":[
        "Nali\u00f3"
    ],
    "wof:name":"Nalio",
    "wof:placetype":"locality"
},
  "geometry": {"coordinates":[-6.00526,43.3768],"type":"Point"}
}