{
  "type": "Feature",
  "properties": {
    "gn:admin1_code":"55",
    "gn:admin2_code":"P",
    "gn:admin3_code":"34225",
    "gn:asciiname":"Calabazanos",
    "gn:country_code":"ES",
    "gn:dem":724,
    "gn:feature_class":"P",
    "gn:feature_code":"PPL",
    "gn:name":"Calabazanos",
    "gn:population":0,
    "gn:timezone":"Europe/Madrid",
    "iso:country":"ES",
    "wof:name":"Calabazanos",
    "wof:placetype":"locality"
},
  "geometry": {"coordinates":[-4.50455,41.94349],"type":"Point"}
}