{
  "type": "Feature",
  "properties": {
    "gn:admin1_code":"58",
    "gn:admin2_code":"LU",
    "gn:admin3_code":"27058",
    "gn:asciiname":"Licin",
    "gn:country_code":"ES",
    "gn:dem":565,
    "gn:feature_class":"P",
    "gn:feature_code":"PPL",
    "gn:name":"Lic\u00edn",
    "gn:population":0,
    "gn:timezone":"Europe/Madrid",
    "iso:country":"ES",
    "name:und_x_variant":[
        "Lic\u00edn"
    ],
    "wof:name":"Licin",
    "wof:placetype":"locality"
},
  "geometry": {"coordinates":[-7.64208,42.5716],"type":"Point"}
}