{
  "type": "Feature",
  "properties": {
    "iso:country":"ES",
    "name:cat_x_preferred":[
        "Arneva"
    ],
    "name:eng_x_preferred":[
        "Arneva"
    ],
    "name:spa_x_colloquial":[
        "Caserio Arneva"
    ],
    "name:spa_x_preferred":[
        "Arneva"
    ],
    "name:spa_x_variant":[
        "Caser\u00edo Arneva"
    ],
    "name:unk_x_variant":[
        "Caser\u00edo Arneva"
    ],
    "qs:a0":"Espa\u00f1a",
    "qs:a1":"*Alicante",
    "qs:a1r":"0Comunidad Valenciana",
    "qs:adm0":"Espa\u00f1a",
    "qs:la_lc":"*",
    "qs:level":"locality",
    "qs:loc":"Arneva",
    "qs:loc_alt":"Arneva",
    "qs:pop":0,
    "qs:type":"buffered point",
    "wof:lang":[
        "spa"
    ],
    "wof:name":"Arneva",
    "wof:placetype":"locality"
},
  "geometry": {"coordinates":[-0.941106,38.055213],"type":"Point"}
}