{
  "type": "Feature",
  "properties": {
    "gn:country":"ES",
    "gn:fcode":"PPLA3",
    "gn:population":87,
    "iso:country":"ES",
    "name:arg_x_preferred":[
        "Brincones"
    ],
    "name:ast_x_preferred":[
        "Brincones"
    ],
    "name:cat_x_preferred":[
        "Brincones"
    ],
    "name:ceb_x_preferred":[
        "Brincones"
    ],
    "name:che_x_preferred":[
        "\u0411\u0440\u0438\u043d\u043a\u043e\u043d\u0435\u0441"
    ],
    "name:deu_x_preferred":[
        "Brincones"
    ],
    "name:eng_x_preferred":[
        "Brincones"
    ],
    "name:epo_x_preferred":[
        "Brincones"
    ],
    "name:eus_x_preferred":[
        "Brincones"
    ],
    "name:fra_x_preferred":[
        "Brincones"
    ],
    "name:gle_x_preferred":[
        "Brincones"
    ],
    "name:haw_x_preferred":[
        "Brincones"
    ],
    "name:hun_x_preferred":[
        "Brincones"
    ],
    "name:ile_x_preferred":[
        "Brincones"
    ],
    "name:ina_x_preferred":[
        "Brincones"
    ],
    "name:ita_x_preferred":[
        "Brincones"
    ],
    "name:kaz_x_preferred":[
        "\u0411\u0440\u0438\u043d\u043a\u043e\u043d\u0435\u0441"
    ],
    "name:lld_x_preferred":[
        "Brincones"
    ],
    "name:ltz_x_preferred":[
        "Brincones"
    ],
    "name:msa_x_preferred":[
        "Brincones"
    ],
    "name:nan_x_preferred":[
        "Brincones"
    ],
    "name:nld_x_preferred":[
        "Brincones"
    ],
    "name:nob_x_preferred":[
        "Brincones"
    ],
    "name:oci_x_preferred":[
        "Brincones"
    ],
    "name:pol_x_preferred":[
        "Brincones"
    ],
    "name:por_x_preferred":[
        "Brincones"
    ],
    "name:rup_x_preferred":[
        "Brincones"
    ],
    "name:rus_x_preferred":[
        "\u0411\u0440\u0438\u043d\u043a\u043e\u043d\u0435\u0441"
    ],
    "name:spa_x_preferred":[
        "Brincones"
    ],
    "name:swe_x_preferred":[
        "Brincones"
    ],
    "name:tat_x_preferred":[
        "\u0411\u0440\u0438\u043d\u043a\u043e\u043d\u0435\u0441"
    ],
    "name:ukr_x_preferred":[
        "\u0411\u0440\u0456\u043d\u043a\u043e\u043d\u0435\u0441"
    ],
    "name:ukr_x_variant":[
        "\u0411\u0440\u0438\u043d\u043a\u043e\u043d\u0435\u0441"
    ],
    "name:uzb_x_preferred":[
        "Brincones"
    ],
    "name:vec_x_preferred":[
        "Brincones"
    ],
    "name:vie_x_preferred":[
        "Brincones"
    ],
    "name:war_x_preferred":[
        "Brincones"
    ],
    "name:zho_x_preferred":[
        "\u5e03\u6797\u79d1\u5185\u65af"
    ],
    "qs_pg:aaroncc":"ES",
    "qs_pg:gn_country":"ES",
    "qs_pg:gn_fcode":"PPLA3",
    "qs_pg:gn_pop":87,
    "qs_pg:name":"Brincones",
    "qs_pg:name_adm0":"Espa\u00f1a",
    "qs_pg:name_adm1":"Castilla y Le\u00f3n",
    "qs_pg:photos_9r":0,
    "qs_pg:photos_sr":0,
    "qs_pg:pop_sr":1,
    "qs_pg:qs_pg_placetype":"locality",
    "qs_pg:qs_pg_placetype_gp":"Town",
    "qs_pg:woe_adm0":23424950,
    "woe:adm0_id":23424950,
    "woe:name_adm0":"Espa\u00f1a",
    "woe:name_adm1":"Castilla y Le\u00f3n",
    "woe:placetype":"Town",
    "wof:name":"Brincones",
    "wof:placetype":"locality",
    "wof:population":87
},
  "geometry": {"coordinates":[-6.34865,41.1134],"type":"Point"}
}