{
  "type": "Feature",
  "properties": {
    "gn:gn_country":"ES",
    "gn:gn_fcode":"PPL",
    "gn:gn_pop":820,
    "gn:population":820,
    "iso:country":"ES",
    "name:arg_x_preferred":[
        "Am\u00e9scua la Baixa"
    ],
    "name:ast_x_preferred":[
        "Ameskoabarrena"
    ],
    "name:bre_x_preferred":[
        "Ameskoabarren"
    ],
    "name:bul_x_preferred":[
        "\u0417\u0443\u0434\u0430\u0438\u0440\u0435"
    ],
    "name:cat_x_preferred":[
        "Ameskoabarren"
    ],
    "name:ceb_x_preferred":[
        "Zudaire"
    ],
    "name:eng_x_preferred":[
        "Am\u00e9scoa Baja"
    ],
    "name:epo_x_preferred":[
        "Am\u00e9scoa Baja"
    ],
    "name:eus_x_preferred":[
        "Ameskoabarrena"
    ],
    "name:fra_x_preferred":[
        "Am\u00e9scoa Baja"
    ],
    "name:hun_x_preferred":[
        "Am\u00e9scoa Baja"
    ],
    "name:ita_x_preferred":[
        "Am\u00e9scoa Baja"
    ],
    "name:jpn_x_preferred":[
        "\u30a2\u30e1\u30b9\u30b3\u30a2\u30fb\u30d0\u30cf"
    ],
    "name:msa_x_preferred":[
        "Am\u00e9scoa Baja"
    ],
    "name:nan_x_preferred":[
        "Am\u00e9scoa Baja"
    ],
    "name:nld_x_preferred":[
        "Am\u00e9scoa Baja"
    ],
    "name:oci_x_preferred":[
        "Ameskoabarren"
    ],
    "name:pol_x_preferred":[
        "Am\u00e9scoa Baja"
    ],
    "name:por_x_preferred":[
        "Am\u00e9scoa Baja"
    ],
    "name:rup_x_preferred":[
        "Am\u00e9scoa Baja"
    ],
    "name:rus_x_preferred":[
        "\u0410\u043c\u0435\u0441\u043a\u043e\u0430-\u0411\u0430\u0445\u0430"
    ],
    "name:sco_x_preferred":[
        "Am\u00e9scoa Baja"
    ],
    "name:spa_x_preferred":[
        "Am\u00e9scoa Baja"
    ],
    "name:swe_x_preferred":[
        "Zudaire"
    ],
    "name:ukr_x_preferred":[
        "\u0410\u043c\u0435\u0441\u043a\u043e\u0430-\u0411\u0430\u0445\u0430"
    ],
    "name:unk_x_variant":[
        "Amezcoa Baja"
    ],
    "name:uzb_x_preferred":[
        "Am\u00e9scoa Baja"
    ],
    "name:vie_x_preferred":[
        "Am\u00e9scoa Baja"
    ],
    "name:war_x_preferred":[
        "Am\u00e9scoa Baja"
    ],
    "name:zho_x_preferred":[
        "\u963f\u6885\u65af\u79d1\u963f\u74e6\u54c8"
    ],
    "qs_pg:aaroncc":"ES",
    "qs_pg:gn_country":"ES",
    "qs_pg:gn_fcode":"PPL",
    "qs_pg:gn_pop":820,
    "qs_pg:name":"Zudaire",
    "qs_pg:name_adm0":"Espa\u00f1a",
    "qs_pg:name_adm1":"Comunidad Foral de Navarra",
    "qs_pg:photos_9k":1,
    "qs_pg:photos_9r":1,
    "qs_pg:photos_all":1,
    "qs_pg:photos_sr":0,
    "qs_pg:pop_sr":2,
    "qs_pg:qs_pg_placetype":"locality",
    "qs_pg:qs_pg_placetype_gp":"Town",
    "qs_pg:woe_adm0":23424950,
    "woe:adm0_id":23424950,
    "woe:name_adm0":"Espa\u00f1a",
    "woe:name_adm1":"Comunidad Foral de Navarra",
    "woe:placetype":"Town",
    "wof:name":"Zudaire",
    "wof:placetype":"locality",
    "wof:population":820
},
  "geometry": {"coordinates":[-2.13363,42.77295],"type":"Point"}
}