{
  "type": "Feature",
  "properties": {
    "gn:admin1_code":"58",
    "gn:admin2_code":"C",
    "gn:admin3_code":"15091",
    "gn:asciiname":"Goimil",
    "gn:cc2":"ES",
    "gn:country_code":"ES",
    "gn:dem":57,
    "gn:feature_class":"P",
    "gn:feature_code":"PPL",
    "gn:name":"Goimil",
    "gn:population":0,
    "gn:timezone":"Europe/Madrid",
    "iso:country":"ES",
    "name:und_x_variant":[
        "San Crist\u00f3bal"
    ],
    "wof:name":"Goimil",
    "wof:placetype":"locality"
},
  "geometry": {"coordinates":[-8.15,43.31667],"type":"Point"}
}