{
  "type": "Feature",
  "properties": {
    "gn:admin1_code":"54",
    "gn:admin2_code":"CU",
    "gn:admin3_code":"16909",
    "gn:asciiname":"Ribatajada",
    "gn:country_code":"ES",
    "gn:dem":939,
    "gn:feature_class":"P",
    "gn:feature_code":"PPL",
    "gn:name":"Ribatajada",
    "gn:population":0,
    "gn:timezone":"Europe/Madrid",
    "iso:country":"ES",
    "name:ceb_x_preferred":[
        "Ribatajada"
    ],
    "name:epo_x_preferred":[
        "Ribatajada"
    ],
    "name:spa_x_preferred":[
        "Ribatajada"
    ],
    "name:swe_x_preferred":[
        "Ribatajada"
    ],
    "name:und_x_variant":[
        "Ribatejada",
        "Ribatajada"
    ],
    "wof:name":"Ribatajada",
    "wof:placetype":"locality"
},
  "geometry": {"coordinates":[-2.17397,40.33771],"type":"Point"}
}