{
  "type": "Feature",
  "properties": {
    "gn:admin1_code":"54",
    "gn:admin2_code":"AB",
    "gn:admin3_code":"02051",
    "gn:asciiname":"Casa de Jaime",
    "gn:country_code":"ES",
    "gn:dem":791,
    "gn:feature_class":"P",
    "gn:feature_code":"PPL",
    "gn:name":"Casa de Jaime",
    "gn:population":0,
    "gn:timezone":"Europe/Madrid",
    "iso:country":"ES",
    "name:und_x_variant":[
        "Casas de Jaime",
        "Casa de Jaime"
    ],
    "wof:name":"Casa de Jaime",
    "wof:placetype":"locality"
},
  "geometry": {"coordinates":[-1.32312,38.71697],"type":"Point"}
}