{
  "type": "Feature",
  "properties": {
    "gn:gn_country":"ES",
    "gn:gn_fcode":"PPLA3",
    "gn:gn_pop":194,
    "gn:population":194,
    "iso:country":"ES",
    "name:ara_x_preferred":[
        "\u0633\u064a\u063a\u0648\u0631\u0627 \u062f\u064a \u062a\u0648\u0631\u0648"
    ],
    "name:cat_x_preferred":[
        "Segura de Toro"
    ],
    "name:deu_x_preferred":[
        "Segura de Toro"
    ],
    "name:eng_x_preferred":[
        "Segura de Toro"
    ],
    "name:epo_x_preferred":[
        "Segura de Toro"
    ],
    "name:eus_x_preferred":[
        "Segura de Toro"
    ],
    "name:ext_x_preferred":[
        "Segura e Toru"
    ],
    "name:fra_x_preferred":[
        "Segura de Toro"
    ],
    "name:hun_x_preferred":[
        "Segura de Toro"
    ],
    "name:ina_x_preferred":[
        "Segura de Toro"
    ],
    "name:ita_x_preferred":[
        "Segura de Toro"
    ],
    "name:msa_x_preferred":[
        "Segura de Toro"
    ],
    "name:nan_x_preferred":[
        "Segura de Toro"
    ],
    "name:nld_x_preferred":[
        "Segura de Toro"
    ],
    "name:oci_x_preferred":[
        "Segura de Toro"
    ],
    "name:pol_x_preferred":[
        "Segura de Toro"
    ],
    "name:por_x_preferred":[
        "Segura de Toro"
    ],
    "name:ron_x_preferred":[
        "Segura de Toro"
    ],
    "name:rus_x_preferred":[
        "\u0421\u0435\u0433\u0443\u0440\u0430-\u0434\u0435-\u0422\u043e\u0440\u043e"
    ],
    "name:spa_x_preferred":[
        "Segura de Toro"
    ],
    "name:swe_x_preferred":[
        "Segura de Toro"
    ],
    "name:ukr_x_preferred":[
        "\u0421\u0435\u0433\u0443\u0440\u0430-\u0434\u0435-\u0422\u043e\u0440\u043e"
    ],
    "name:uzb_x_preferred":[
        "Segura de Toro"
    ],
    "name:vie_x_preferred":[
        "Segura de Toro"
    ],
    "name:war_x_preferred":[
        "Segura de Toro"
    ],
    "name:zho_x_preferred":[
        "\u585e\u53e4\u62c9\u5fb7\u6258\u7f57"
    ],
    "qs_pg:aaroncc":"ES",
    "qs_pg:gn_country":"ES",
    "qs_pg:gn_fcode":"PPLA3",
    "qs_pg:gn_pop":194,
    "qs_pg:name":"Segura de Toro",
    "qs_pg:name_adm0":"Espa\u00f1a",
    "qs_pg:name_adm1":"Extremadura",
    "qs_pg:photos":68,
    "qs_pg:photos_1k":14,
    "qs_pg:photos_9k":1,
    "qs_pg:photos_9r":2,
    "qs_pg:photos_all":68,
    "qs_pg:photos_sr":2,
    "qs_pg:pop_sr":1,
    "qs_pg:qs_pg_placetype":"locality",
    "qs_pg:qs_pg_placetype_gp":"Town",
    "qs_pg:woe_adm0":23424950,
    "woe:adm0_id":23424950,
    "woe:name_adm0":"Espa\u00f1a",
    "woe:name_adm1":"Extremadura",
    "woe:placetype":"Town",
    "wof:name":"Segura de Toro",
    "wof:placetype":"locality",
    "wof:population":194
},
  "geometry": {"coordinates":[-5.94836,40.22427],"type":"Point"}
}