{
  "type": "Feature",
  "properties": {
    "gn:admin1_code":"55",
    "gn:admin2_code":"LE",
    "gn:admin3_code":"24177",
    "gn:asciiname":"Arintero",
    "gn:country_code":"ES",
    "gn:dem":1329,
    "gn:feature_class":"P",
    "gn:feature_code":"PPL",
    "gn:name":"Arintero",
    "gn:population":0,
    "gn:timezone":"Europe/Madrid",
    "iso:country":"ES",
    "wof:name":"Arintero",
    "wof:placetype":"locality"
},
  "geometry": {"coordinates":[-5.36307,42.94732],"type":"Point"}
}