{
  "type": "Feature",
  "properties": {
    "gn:gn_country":"ES",
    "gn:gn_fcode":"PPLA3",
    "gn:gn_pop":117,
    "gn:population":117,
    "iso:country":"ES",
    "name:cat_x_preferred":[
        "Villah\u00e1n"
    ],
    "name:eng_x_preferred":[
        "Villah\u00e1n"
    ],
    "name:eus_x_preferred":[
        "Villah\u00e1n"
    ],
    "name:fas_x_preferred":[
        "\u0628\u06cc\u06cc\u0627\u0647\u0627\u0646"
    ],
    "name:fra_x_preferred":[
        "Villah\u00e1n"
    ],
    "name:glg_x_preferred":[
        "Villah\u00e1n"
    ],
    "name:hun_x_preferred":[
        "Villah\u00e1n"
    ],
    "name:hye_x_preferred":[
        "\u054e\u056b\u056c\u0575\u0561\u0561\u0576"
    ],
    "name:ina_x_preferred":[
        "Villah\u00e1n"
    ],
    "name:ita_x_preferred":[
        "Villah\u00e1n"
    ],
    "name:msa_x_preferred":[
        "Villah\u00e1n"
    ],
    "name:nan_x_preferred":[
        "Villah\u00e1n"
    ],
    "name:nld_x_preferred":[
        "Villah\u00e1n"
    ],
    "name:oci_x_preferred":[
        "Villah\u00e1n"
    ],
    "name:pol_x_preferred":[
        "Villah\u00e1n"
    ],
    "name:por_x_preferred":[
        "Villah\u00e1n"
    ],
    "name:rus_x_preferred":[
        "\u0412\u0438\u043b\u044c\u044f\u0430\u043d"
    ],
    "name:spa_x_preferred":[
        "Villah\u00e1n"
    ],
    "name:swe_x_preferred":[
        "Villah\u00e1n"
    ],
    "name:ukr_x_preferred":[
        "\u0412\u0456\u043b\u044c\u044f\u0430\u043d"
    ],
    "name:unk_x_variant":[
        "Villah\u00e1n de Palenzuela"
    ],
    "name:uzb_x_preferred":[
        "Villah\u00e1n"
    ],
    "name:vie_x_preferred":[
        "Villah\u00e1n"
    ],
    "name:war_x_preferred":[
        "Villah\u00e1n"
    ],
    "name:zho_x_preferred":[
        "\u6bd4\u5229\u4e9a\u5b89"
    ],
    "qs_pg:aaroncc":"ES",
    "qs_pg:gn_country":"ES",
    "qs_pg:gn_fcode":"PPLA3",
    "qs_pg:gn_pop":117,
    "qs_pg:name":"Villah\u00e1n",
    "qs_pg:name_adm0":"Espa\u00f1a",
    "qs_pg:name_adm1":"Castilla y Le\u00f3n",
    "qs_pg:photos_9r":0,
    "qs_pg:photos_sr":0,
    "qs_pg:pop_sr":1,
    "qs_pg:qs_pg_placetype":"locality",
    "qs_pg:qs_pg_placetype_gp":"Town",
    "qs_pg:woe_adm0":23424950,
    "woe:adm0_id":23424950,
    "woe:name_adm0":"Espa\u00f1a",
    "woe:name_adm1":"Castilla y Le\u00f3n",
    "woe:placetype":"Town",
    "wof:name":"Villah\u00e1n",
    "wof:placetype":"locality",
    "wof:population":117
},
  "geometry": {"coordinates":[-4.13104,42.0503],"type":"Point"}
}