{
  "type": "Feature",
  "properties": {
    "gn:admin1_code":"34",
    "gn:admin2_code":"O",
    "gn:admin3_code":"33011",
    "gn:asciiname":"Arbas",
    "gn:country_code":"ES",
    "gn:dem":789,
    "gn:feature_class":"P",
    "gn:feature_code":"PPL",
    "gn:name":"Arb\u00e1s",
    "gn:population":0,
    "gn:timezone":"Europe/Madrid",
    "iso:country":"ES",
    "name:arg_x_preferred":[
        "Arbast"
    ],
    "name:bug_x_preferred":[
        "Arbas"
    ],
    "name:cat_x_preferred":[
        "Arbast"
    ],
    "name:ceb_x_preferred":[
        "Arbas"
    ],
    "name:deu_x_preferred":[
        "Arbas"
    ],
    "name:eus_x_preferred":[
        "Arbast"
    ],
    "name:fra_x_preferred":[
        "Arbas"
    ],
    "name:ita_x_preferred":[
        "Arbas"
    ],
    "name:lat_x_preferred":[
        "Arbas"
    ],
    "name:mlg_x_preferred":[
        "Arbas"
    ],
    "name:msa_x_preferred":[
        "Arbas"
    ],
    "name:nld_x_preferred":[
        "Arbas"
    ],
    "name:oci_x_preferred":[
        "Arbast"
    ],
    "name:pol_x_preferred":[
        "Arbas"
    ],
    "name:ron_x_preferred":[
        "Arbas"
    ],
    "name:rus_x_preferred":[
        "\u0410\u0440\u0431\u0430\u0441"
    ],
    "name:slk_x_preferred":[
        "Arbas"
    ],
    "name:spa_x_preferred":[
        "Arbas"
    ],
    "name:srp_x_preferred":[
        "\u0410\u0440\u0431\u0430"
    ],
    "name:swe_x_preferred":[
        "Arbas"
    ],
    "name:ukr_x_preferred":[
        "\u0410\u0440\u0431\u0430\u0441"
    ],
    "name:und_x_variant":[
        "Arb\u00e1s"
    ],
    "name:vie_x_preferred":[
        "Arbas"
    ],
    "name:vol_x_preferred":[
        "Arbas"
    ],
    "name:war_x_preferred":[
        "Arbas"
    ],
    "name:zho_x_preferred":[
        "\u963f\u5c14\u5df4"
    ],
    "wof:name":"Arbas",
    "wof:placetype":"locality"
},
  "geometry": {"coordinates":[-6.4692,43.03338],"type":"Point"}
}