{
  "type": "Feature",
  "properties": {
    "gn:admin1_code":"34",
    "gn:admin2_code":"O",
    "gn:admin3_code":"33011",
    "gn:asciiname":"Arbas",
    "gn:country_code":"ES",
    "gn:dem":789,
    "gn:feature_class":"P",
    "gn:feature_code":"PPL",
    "gn:name":"Arb\u00e1s",
    "gn:population":0,
    "gn:timezone":"Europe/Madrid",
    "iso:country":"ES",
    "name:und_x_variant":[
        "Arb\u00e1s"
    ],
    "wof:name":"Arbas",
    "wof:placetype":"locality"
},
  "geometry": {"coordinates":[-6.4692,43.03338],"type":"Point"}
}