{
  "type": "Feature",
  "properties": {
    "gn:admin1_code":"39",
    "gn:admin2_code":"S",
    "gn:admin3_code":"39095",
    "gn:asciiname":"Portillo",
    "gn:country_code":"ES",
    "gn:dem":131,
    "gn:feature_class":"P",
    "gn:feature_code":"PPL",
    "gn:name":"Portillo",
    "gn:population":0,
    "gn:timezone":"Europe/Madrid",
    "iso:country":"ES",
    "name:ceb_x_preferred":[
        "Portillo"
    ],
    "name:deu_x_preferred":[
        "Portillo"
    ],
    "name:fin_x_preferred":[
        "Portillo"
    ],
    "name:fra_x_preferred":[
        "Portillo"
    ],
    "name:ita_x_preferred":[
        "Portillo"
    ],
    "name:nds_x_preferred":[
        "Portillo"
    ],
    "name:nld_x_preferred":[
        "Portillo"
    ],
    "name:rus_x_preferred":[
        "\u041f\u043e\u0440\u0442\u0438\u043b\u044c\u043e"
    ],
    "name:spa_x_preferred":[
        "Portillo"
    ],
    "name:swe_x_preferred":[
        "Portillo"
    ],
    "name:ukr_x_preferred":[
        "\u041f\u043e\u0440\u0442\u0456\u043b\u044c\u0439\u043e"
    ],
    "wof:name":"Portillo",
    "wof:placetype":"locality"
},
  "geometry": {"coordinates":[-4.441,43.3489],"type":"Point"}
}