{
  "type": "Feature",
  "properties": {
    "gn:admin1_code":"55",
    "gn:admin2_code":"ZA",
    "gn:admin3_code":"49017",
    "gn:asciiname":"Lagarejos de la Carballeda",
    "gn:country_code":"ES",
    "gn:dem":975,
    "gn:feature_class":"P",
    "gn:feature_code":"PPL",
    "gn:name":"Lagarejos de la Carballeda",
    "gn:population":0,
    "gn:timezone":"Europe/Madrid",
    "iso:country":"ES",
    "wof:name":"Lagarejos de la Carballeda",
    "wof:placetype":"locality"
},
  "geometry": {"coordinates":[-6.44494,42.05327],"type":"Point"}
}