{
  "type": "Feature",
  "properties": {
    "gn:admin1_code":"58",
    "gn:admin2_code":"OR",
    "gn:admin3_code":"32041",
    "gn:asciiname":"Parada del Monte",
    "gn:country_code":"ES",
    "gn:dem":730,
    "gn:feature_class":"P",
    "gn:feature_code":"PPL",
    "gn:name":"Parada del Monte",
    "gn:population":0,
    "gn:timezone":"Europe/Madrid",
    "iso:country":"ES",
    "name:und_x_variant":[
        "Parada de Monte",
        "Parada del Monte"
    ],
    "wof:name":"Parada del Monte",
    "wof:placetype":"locality"
},
  "geometry": {"coordinates":[-8.03813,42.0115],"type":"Point"}
}