{
  "type": "Feature",
  "properties": {
    "gn:admin1_code":"34",
    "gn:admin2_code":"O",
    "gn:admin3_code":"33012",
    "gn:asciiname":"Colladin",
    "gn:country_code":"ES",
    "gn:dem":217,
    "gn:feature_class":"P",
    "gn:feature_code":"PPL",
    "gn:name":"Collad\u00edn",
    "gn:population":0,
    "gn:timezone":"Europe/Madrid",
    "iso:country":"ES",
    "wof:name":"Colladin",
    "wof:placetype":"locality"
},
  "geometry": {"coordinates":[-5.112,43.38909],"type":"Point"}
}