{
  "type": "Feature",
  "properties": {
    "iso:country":"ES",
    "name:eng_x_preferred":[
        "Ciudad Jardin"
    ],
    "name:spa_x_preferred":[
        "Ciudad Jard\u00edn"
    ],
    "wof:name":"Ciudad Jardin",
    "wof:placetype":"neighbourhood"
},
  "geometry": {"coordinates":[-4.42192750979719,36.74801461357278],"type":"Point"}
}