{
  "type": "Feature",
  "properties": {
    "gn:admin1_code":"34",
    "gn:admin2_code":"O",
    "gn:admin3_code":"33036",
    "gn:asciiname":"Mediavilla",
    "gn:country_code":"ES",
    "gn:dem":56,
    "gn:feature_class":"P",
    "gn:feature_code":"PPL",
    "gn:name":"Mediavilla",
    "gn:population":0,
    "gn:timezone":"Europe/Madrid",
    "iso:country":"ES",
    "wof:name":"Mediavilla",
    "wof:placetype":"locality"
},
  "geometry": {"coordinates":[-4.89411,43.39944000000001],"type":"Point"}
}