{
  "type": "Feature",
  "properties": {
    "iso:country":"ES",
    "name:eng_x_preferred":[
        "Campanillas"
    ],
    "name:spa_x_preferred":[
        "Campanillas"
    ],
    "wof:name":"Campanillas",
    "wof:placetype":"neighbourhood"
},
  "geometry": {"coordinates":[-4.5436497924166,36.72622163052376],"type":"Point"}
}