{
  "type": "Feature",
  "properties": {
    "gn:admin1_code":"54",
    "gn:admin2_code":"AB",
    "gn:admin3_code":"02042",
    "gn:asciiname":"Almazaran",
    "gn:country_code":"ES",
    "gn:dem":516,
    "gn:feature_class":"P",
    "gn:feature_code":"PPL",
    "gn:name":"Almazar\u00e1n",
    "gn:population":0,
    "gn:timezone":"Europe/Madrid",
    "iso:country":"ES",
    "name:und_x_variant":[
        "Caser\u00edo Almazar\u00e1n",
        "Almazar\u00e1n"
    ],
    "wof:name":"Almazaran",
    "wof:placetype":"locality"
},
  "geometry": {"coordinates":[-2.10681,38.40478],"type":"Point"}
}