{
  "type": "Feature",
  "properties": {
    "gn:admin1_code":"55",
    "gn:admin2_code":"LE",
    "gn:admin3_code":"24165",
    "gn:asciiname":"San Tirso",
    "gn:country_code":"ES",
    "gn:dem":803,
    "gn:feature_class":"P",
    "gn:feature_code":"PPL",
    "gn:name":"San Tirso",
    "gn:population":0,
    "gn:timezone":"Europe/Madrid",
    "iso:country":"ES",
    "name:ast_x_preferred":[
        "San Tisu"
    ],
    "name:deu_x_preferred":[
        "San Tirso"
    ],
    "name:sco_x_preferred":[
        "San Tirso"
    ],
    "name:spa_x_preferred":[
        "San Tirso"
    ],
    "wof:name":"San Tirso",
    "wof:placetype":"locality"
},
  "geometry": {"coordinates":[-6.91591,42.52144000000001],"type":"Point"}
}