{
  "type": "Feature",
  "properties": {
    "gn:admin1_code":"58",
    "gn:admin2_code":"LU",
    "gn:admin3_code":"27065",
    "gn:asciiname":"Oleiros",
    "gn:cc2":"ES",
    "gn:country_code":"ES",
    "gn:dem":497,
    "gn:feature_class":"P",
    "gn:feature_code":"PPL",
    "gn:name":"Oleiros",
    "gn:population":0,
    "gn:timezone":"Europe/Madrid",
    "iso:country":"ES",
    "name:bre_x_preferred":[
        "Oleiros"
    ],
    "name:ceb_x_preferred":[
        "Oleiros"
    ],
    "name:fra_x_preferred":[
        "Oleiros"
    ],
    "name:glg_x_preferred":[
        "Oleiros"
    ],
    "name:ita_x_preferred":[
        "Oleiros"
    ],
    "name:jpn_x_preferred":[
        "\u30aa\u30ec\u30a4\u30ed\u30b9"
    ],
    "name:lmo_x_preferred":[
        "Oleiros"
    ],
    "name:mlg_x_preferred":[
        "Oleiros"
    ],
    "name:nld_x_preferred":[
        "Oleiros"
    ],
    "name:por_x_preferred":[
        "Oleiros"
    ],
    "name:rus_x_preferred":[
        "\u041e\u043b\u0435\u0439\u0440\u0443\u0448"
    ],
    "name:scn_x_preferred":[
        "Oleiros"
    ],
    "name:spa_x_preferred":[
        "Oleiros"
    ],
    "name:swe_x_preferred":[
        "Oleiros"
    ],
    "name:ukr_x_preferred":[
        "\u041e\u043b\u0435\u0439\u0440\u0443\u0448"
    ],
    "name:und_x_variant":[
        "San Mamed",
        "Oleiros"
    ],
    "wof:name":"Oleiros",
    "wof:placetype":"locality"
},
  "geometry": {"coordinates":[-7.62978,43.2551],"type":"Point"}
}