{
  "type": "Feature",
  "properties": {
    "gn:admin1_code":"31",
    "gn:admin2_code":"MU",
    "gn:admin3_code":"30016",
    "gn:asciiname":"Los Castillejos",
    "gn:cc2":"ES",
    "gn:country_code":"ES",
    "gn:dem":106,
    "gn:feature_class":"P",
    "gn:feature_code":"PPL",
    "gn:name":"Los Castillejos",
    "gn:population":0,
    "gn:timezone":"Europe/Madrid",
    "iso:country":"ES",
    "name:und_x_variant":[
        "Caser\u00edo Los Castillejos",
        "Los Castillejos"
    ],
    "wof:name":"Los Castillejos",
    "wof:placetype":"locality"
},
  "geometry": {"coordinates":[-1.08333,37.66667],"type":"Point"}
}