{
  "type": "Feature",
  "properties": {
    "gn:admin1_code":"60",
    "gn:admin2_code":"V",
    "gn:admin3_code":"46213",
    "gn:asciiname":"Ponton",
    "gn:country_code":"ES",
    "gn:dem":662,
    "gn:feature_class":"P",
    "gn:feature_code":"PPL",
    "gn:name":"Pont\u00f3n",
    "gn:population":0,
    "gn:timezone":"Europe/Madrid",
    "iso:country":"ES",
    "name:deu_x_preferred":[
        "Ponton"
    ],
    "name:fra_x_preferred":[
        "Ponton"
    ],
    "name:heb_x_preferred":[
        "\u05e4\u05d5\u05e0\u05d8\u05d5\u05df"
    ],
    "name:pol_x_preferred":[
        "Ponton"
    ],
    "name:swe_x_preferred":[
        "Ponton"
    ],
    "wof:name":"Ponton",
    "wof:placetype":"locality"
},
  "geometry": {"coordinates":[-1.11667,39.48333],"type":"Point"}
}