{
  "type": "Feature",
  "properties": {
    "gn:admin1_code":"58",
    "gn:admin2_code":"LU",
    "gn:admin3_code":"27040",
    "gn:asciiname":"Maceda",
    "gn:country_code":"ES",
    "gn:dem":452,
    "gn:feature_class":"P",
    "gn:feature_code":"PPL",
    "gn:name":"Maceda",
    "gn:population":0,
    "gn:timezone":"Europe/Madrid",
    "iso:country":"ES",
    "name:ceb_x_preferred":[
        "Maceda"
    ],
    "name:deu_x_preferred":[
        "Maceda"
    ],
    "name:glg_x_preferred":[
        "Maceda"
    ],
    "name:nld_x_preferred":[
        "Maceda"
    ],
    "name:pol_x_preferred":[
        "Maceda"
    ],
    "name:por_x_preferred":[
        "Maceda"
    ],
    "name:rus_x_preferred":[
        "\u041c\u0430\u0441\u0435\u0434\u0430"
    ],
    "name:spa_x_preferred":[
        "Maceda"
    ],
    "name:ukr_x_preferred":[
        "\u041c\u0430\u0441\u0435\u0434\u0430"
    ],
    "name:war_x_preferred":[
        "Maceda"
    ],
    "wof:name":"Maceda",
    "wof:placetype":"locality"
},
  "geometry": {"coordinates":[-7.88333,42.91667],"type":"Point"}
}