{
  "type": "Feature",
  "properties": {
    "gn:country":"ES",
    "gn:fcode":"PPL",
    "gn:population":0,
    "iso:country":"ES",
    "name:cat_x_preferred":[
        "Arr\u00f2s"
    ],
    "name:deu_x_preferred":[
        "Arr\u00f2s"
    ],
    "name:eng_x_preferred":[
        "Arr\u00f2s"
    ],
    "name:fra_x_preferred":[
        "Arr\u00f2s"
    ],
    "name:glg_x_preferred":[
        "Arr\u00f2s"
    ],
    "name:oci_x_preferred":[
        "Arr\u00f2s"
    ],
    "name:spa_x_preferred":[
        "Arr\u00f3s"
    ],
    "name:zho_x_preferred":[
        "\u8d1d\u5c3c\u7a46\u65af\u83b1\u59c6"
    ],
    "qs_pg:aaroncc":"ES",
    "qs_pg:gn_country":"ES",
    "qs_pg:gn_fcode":"PPL",
    "qs_pg:gn_pop":0,
    "qs_pg:name":"Arr\u00f3s",
    "qs_pg:name_adm0":"Espa\u00f1a",
    "qs_pg:name_adm1":"Catalunya",
    "qs_pg:photos":138,
    "qs_pg:photos_1k":28,
    "qs_pg:photos_9k":1,
    "qs_pg:photos_9r":3,
    "qs_pg:photos_all":138,
    "qs_pg:photos_sr":3,
    "qs_pg:pop_sr":0,
    "qs_pg:qs_pg_placetype":"locality",
    "qs_pg:qs_pg_placetype_gp":"Town",
    "qs_pg:woe_adm0":23424950,
    "woe:adm0_id":23424950,
    "woe:name_adm0":"Espa\u00f1a",
    "woe:name_adm1":"Catalunya",
    "woe:placetype":"Town",
    "wof:name":"Arr\u00f3s",
    "wof:placetype":"locality"
},
  "geometry": {"coordinates":[0.76183,42.73812],"type":"Point"}
}