{
  "type": "Feature",
  "properties": {
    "gn:admin1_code":"55",
    "gn:admin2_code":"P",
    "gn:admin3_code":"34049",
    "gn:asciiname":"Recueva",
    "gn:country_code":"ES",
    "gn:dem":1040,
    "gn:feature_class":"P",
    "gn:feature_code":"PPL",
    "gn:name":"Recueva",
    "gn:population":0,
    "gn:timezone":"Europe/Madrid",
    "iso:country":"ES",
    "wof:name":"Recueva",
    "wof:placetype":"locality"
},
  "geometry": {"coordinates":[-4.6593,42.7829],"type":"Point"}
}