{
  "type": "Feature",
  "properties": {
    "iso:country":"ES",
    "name:spa_x_variant":[
        "Pinoflores"
    ],
    "wof:name":"Pino Flores",
    "wof:placetype":"neighbourhood"
},
  "geometry": {"coordinates":[-5.97252824370223,37.40806853720814],"type":"Point"}
}