{
  "type": "Feature",
  "properties": {
    "gn:admin1_code":"59",
    "gn:admin2_code":"VI",
    "gn:admin3_code":"01003",
    "gn:asciiname":"Barajuen",
    "gn:country_code":"ES",
    "gn:dem":479,
    "gn:feature_class":"P",
    "gn:feature_code":"PPL",
    "gn:name":"Barajuen",
    "gn:population":0,
    "gn:timezone":"Europe/Madrid",
    "iso:country":"ES",
    "wof:name":"Barajuen",
    "wof:placetype":"locality"
},
  "geometry": {"coordinates":[-2.55875,43.04705],"type":"Point"}
}