{
  "type": "Feature",
  "properties": {
    "gn:country":"ES",
    "gn:fcode":"PPLA3",
    "gn:population":229,
    "iso:country":"ES",
    "name:arg_x_preferred":[
        "Elgorriaga"
    ],
    "name:ast_x_preferred":[
        "Elgorriaga"
    ],
    "name:bre_x_preferred":[
        "Elgorriaga"
    ],
    "name:cat_x_preferred":[
        "Elgorriaga"
    ],
    "name:ceb_x_preferred":[
        "Elgorriaga"
    ],
    "name:eng_x_preferred":[
        "Elgorriaga"
    ],
    "name:eus_x_preferred":[
        "Elgorriaga"
    ],
    "name:fra_x_preferred":[
        "Elgorriaga"
    ],
    "name:hun_x_preferred":[
        "Elgorriaga"
    ],
    "name:ita_x_preferred":[
        "Elgorriaga"
    ],
    "name:jpn_x_preferred":[
        "\u30a8\u30eb\u30b4\u30ea\u30a2\u30ac"
    ],
    "name:msa_x_preferred":[
        "Elgorriaga"
    ],
    "name:nan_x_preferred":[
        "Elgorriaga"
    ],
    "name:nld_x_preferred":[
        "Elgorriaga"
    ],
    "name:oci_x_preferred":[
        "Elgorriaga"
    ],
    "name:pol_x_preferred":[
        "Elgorriaga"
    ],
    "name:por_x_preferred":[
        "Elgorriaga"
    ],
    "name:rup_x_preferred":[
        "Elgorriaga"
    ],
    "name:rus_x_preferred":[
        "\u042d\u043b\u044c\u0433\u043e\u0440\u0440\u0438\u0430\u0433\u0430"
    ],
    "name:spa_x_preferred":[
        "Elgorriaga"
    ],
    "name:swe_x_preferred":[
        "Elgorriaga"
    ],
    "name:ukr_x_preferred":[
        "\u0415\u043b\u044c\u0433\u043e\u0440\u0440\u0456\u0430\u0433\u0430"
    ],
    "name:uzb_x_preferred":[
        "Elgorriaga"
    ],
    "name:vie_x_preferred":[
        "Elgorriaga"
    ],
    "name:war_x_preferred":[
        "Elgorriaga"
    ],
    "name:zho_x_preferred":[
        "\u57c3\u5c14\u6208\u91cc\u4e9a\u52a0"
    ],
    "qs_pg:aaroncc":"ES",
    "qs_pg:gn_country":"ES",
    "qs_pg:gn_fcode":"PPLA3",
    "qs_pg:gn_pop":229,
    "qs_pg:name":"Elgorriaga",
    "qs_pg:name_adm0":"Espa\u00f1a",
    "qs_pg:name_adm1":"Comunidad Foral de Navarra",
    "qs_pg:photos_9k":1,
    "qs_pg:photos_9r":1,
    "qs_pg:photos_all":3,
    "qs_pg:photos_sr":0,
    "qs_pg:pop_sr":2,
    "qs_pg:qs_pg_placetype":"locality",
    "qs_pg:qs_pg_placetype_gp":"Town",
    "qs_pg:woe_adm0":23424950,
    "woe:adm0_id":23424950,
    "woe:name_adm0":"Espa\u00f1a",
    "woe:name_adm1":"Comunidad Foral de Navarra",
    "woe:placetype":"Town",
    "wof:name":"Elgorriaga",
    "wof:placetype":"locality",
    "wof:population":229
},
  "geometry": {"coordinates":[-1.68658,43.13858],"type":"Point"}
}