{
  "type": "Feature",
  "properties": {
    "gn:gn_country":"ES",
    "gn:gn_fcode":"ADM3",
    "gn:gn_pop":3462,
    "gn:population":3621,
    "iso:country":"ES",
    "name:alb_x_preferred":[
        "Ol\u00e8rdola"
    ],
    "name:ara_x_preferred":[
        "\u0623\u0648\u0644\u064a\u0631\u062f\u0648\u0644\u0627"
    ],
    "name:arg_x_preferred":[
        "Ol\u00e8rdola"
    ],
    "name:arm_x_preferred":[
        "\u0555\u056c\u0565\u0580\u0564\u0578\u056c\u0561"
    ],
    "name:baq_x_preferred":[
        "Ol\u00e8rdola"
    ],
    "name:cat_x_preferred":[
        "Ol\u00e8rdola"
    ],
    "name:chi_x_preferred":[
        "\u5965\u83b1\u5c14\u591a\u62c9"
    ],
    "name:dut_x_preferred":[
        "Ol\u00e8rdola"
    ],
    "name:eng_x_preferred":[
        "Ol\u00e8rdola"
    ],
    "name:fas_x_preferred":[
        "\u0627\u0644\u0631\u062f\u0644\u0627"
    ],
    "name:fre_x_preferred":[
        "Ol\u00e8rdola"
    ],
    "name:ger_x_preferred":[
        "Ol\u00e8rdola"
    ],
    "name:hun_x_preferred":[
        "Ol\u00e8rdola"
    ],
    "name:hye_x_preferred":[
        "\u0555\u056c\u0565\u0580\u0564\u0578\u056c\u0561"
    ],
    "name:ita_x_preferred":[
        "Ol\u00e8rdola"
    ],
    "name:kaz_x_preferred":[
        "\u041e\u043b\u0435\u0440\u0434\u043e\u043b\u0430"
    ],
    "name:lat_x_preferred":[
        "Ol\u00e8rdola"
    ],
    "name:may_x_preferred":[
        "Ol\u00e8rdola"
    ],
    "name:oci_x_preferred":[
        "Ol\u00e8rdola"
    ],
    "name:per_x_preferred":[
        "\u0627\u0644\u0631\u062f\u0644\u0627"
    ],
    "name:pol_x_preferred":[
        "Ol\u00e8rdola"
    ],
    "name:por_x_preferred":[
        "Ol\u00e8rdola"
    ],
    "name:rum_x_preferred":[
        "Ol\u00e8rdola"
    ],
    "name:rus_x_preferred":[
        "\u041e\u043b\u0435\u0440\u0434\u043e\u043b\u0430"
    ],
    "name:sco_x_preferred":[
        "Ol\u00e8rdola"
    ],
    "name:spa_x_preferred":[
        "Ol\u00e9rdola"
    ],
    "name:swe_x_preferred":[
        "Ol\u00e8rdola"
    ],
    "name:ukr_x_preferred":[
        "\u0423\u043b\u0435\u0440\u0434\u0443\u043b\u0430"
    ],
    "name:unk_x_variant":[
        "Ol\u00e9rdola"
    ],
    "name:uzb_x_preferred":[
        "Ol\u00e8rdola"
    ],
    "name:vie_x_preferred":[
        "Ol\u00e8rdola"
    ],
    "name:war_x_preferred":[
        "Ol\u00e8rdola"
    ],
    "name:zho_x_preferred":[
        "\u5965\u83b1\u5c14\u591a\u62c9"
    ],
    "qs_pg:aaroncc":"ES",
    "qs_pg:gn_country":"ES",
    "qs_pg:gn_fcode":"ADM3",
    "qs_pg:gn_pop":3462,
    "qs_pg:name":"Ol\u00e8rdola",
    "qs_pg:name_adm0":"Espa\u00f1a",
    "qs_pg:name_adm1":"Catalunya",
    "qs_pg:photos":464,
    "qs_pg:photos_1k":94,
    "qs_pg:photos_9k":2,
    "qs_pg:photos_9r":5,
    "qs_pg:photos_all":464,
    "qs_pg:photos_sr":7,
    "qs_pg:pop_sr":4,
    "qs_pg:qs_pg_placetype":"locality",
    "qs_pg:qs_pg_placetype_gp":"Town",
    "qs_pg:woe_adm0":23424950,
    "woe:adm0_id":23424950,
    "woe:name_adm0":"Espa\u00f1a",
    "woe:name_adm1":"Catalunya",
    "woe:placetype":"Town",
    "wof:name":"Ol\u00e8rdola",
    "wof:placetype":"locality",
    "wof:population":3621
},
  "geometry": {"coordinates":[1.71667,41.31667],"type":"Point"}
}