{
  "type": "Feature",
  "properties": {
    "gn:gn_country":"ES",
    "gn:gn_fcode":"PPL",
    "gn:gn_pop":22538,
    "gn:population":22538,
    "iso:country":"ES",
    "qs_pg:aaroncc":"ES",
    "qs_pg:gn_country":"ES",
    "qs_pg:gn_fcode":"PPL",
    "qs_pg:gn_pop":22538,
    "qs_pg:name":"Segundo Ensanche",
    "qs_pg:photos_9r":0,
    "qs_pg:photos_sr":0,
    "qs_pg:pop_sr":7,
    "qs_pg:qs_pg_placetype":"locality",
    "wof:name":"Segundo Ensanche",
    "wof:placetype":"locality",
    "wof:population":22538
},
  "geometry": {"coordinates":[-1.64295,42.8139],"type":"Point"}
}