{
  "type": "Feature",
  "properties": {
    "gn:country":"ES",
    "gn:fcode":"PPLA3",
    "gn:population":153,
    "iso:country":"ES",
    "name:ara_x_preferred":[
        "\u062a\u0627\u0641\u064a\u0631\u062a\u064a\u062a"
    ],
    "name:arg_x_preferred":[
        "Tavertet"
    ],
    "name:ast_x_preferred":[
        "Tavertet"
    ],
    "name:azb_x_preferred":[
        "\u062a\u0627\u0628\u0631\u062a\u062a"
    ],
    "name:cat_x_preferred":[
        "Tavertet"
    ],
    "name:ceb_x_preferred":[
        "Tavertet"
    ],
    "name:che_x_preferred":[
        "\u0422\u0430\u0432\u0435\u0440\u0442\u0435\u0442"
    ],
    "name:deu_x_preferred":[
        "Tavertet"
    ],
    "name:diq_x_preferred":[
        "Tavertet"
    ],
    "name:eng_x_preferred":[
        "Tavertet"
    ],
    "name:eus_x_preferred":[
        "Tavertet"
    ],
    "name:fas_x_preferred":[
        "\u062a\u0627\u0628\u0631\u062a\u062a"
    ],
    "name:fra_x_preferred":[
        "Tavertet"
    ],
    "name:gle_x_preferred":[
        "Tavertet"
    ],
    "name:glg_x_preferred":[
        "Tavertet"
    ],
    "name:hun_x_preferred":[
        "Tavertet"
    ],
    "name:hye_x_preferred":[
        "\u054f\u0561\u057e\u0565\u0580\u057f\u0565\u057f"
    ],
    "name:ile_x_preferred":[
        "Tavertet"
    ],
    "name:ita_x_preferred":[
        "Tavertet"
    ],
    "name:lat_x_preferred":[
        "Tavertet"
    ],
    "name:lld_x_preferred":[
        "Tavertet"
    ],
    "name:msa_x_preferred":[
        "Tavertet"
    ],
    "name:nld_x_preferred":[
        "Tavertet"
    ],
    "name:oci_x_preferred":[
        "Tavertet"
    ],
    "name:pol_x_preferred":[
        "Tavertet"
    ],
    "name:por_x_preferred":[
        "Tavertet"
    ],
    "name:rus_x_preferred":[
        "\u0422\u0430\u0432\u0435\u0440\u0442\u0435\u0442"
    ],
    "name:spa_x_preferred":[
        "Tavertet"
    ],
    "name:sqi_x_preferred":[
        "Tavertet"
    ],
    "name:swe_x_preferred":[
        "Tavertet"
    ],
    "name:tat_x_preferred":[
        "\u0422\u0430\u0432\u0435\u0440\u0442\u0435\u0442"
    ],
    "name:uzb_x_preferred":[
        "Tavertet"
    ],
    "name:vec_x_preferred":[
        "Tavertet"
    ],
    "name:war_x_preferred":[
        "Tavertet"
    ],
    "name:zho_x_preferred":[
        "\u5854\u97e6\u5c14\u7279\u7279"
    ],
    "qs_pg:aaroncc":"ES",
    "qs_pg:gn_country":"ES",
    "qs_pg:gn_fcode":"PPLA3",
    "qs_pg:gn_pop":153,
    "qs_pg:name":"Tavertet",
    "qs_pg:name_adm0":"Espa\u00f1a",
    "qs_pg:name_adm1":"Catalunya",
    "qs_pg:photos":973,
    "qs_pg:photos_1k":197,
    "qs_pg:photos_9k":4,
    "qs_pg:photos_9r":6,
    "qs_pg:photos_all":973,
    "qs_pg:photos_sr":10,
    "qs_pg:pop_sr":1,
    "qs_pg:qs_pg_placetype":"locality",
    "qs_pg:qs_pg_placetype_gp":"Town",
    "qs_pg:woe_adm0":23424950,
    "woe:adm0_id":23424950,
    "woe:name_adm0":"Espa\u00f1a",
    "woe:name_adm1":"Catalunya",
    "woe:placetype":"Town",
    "wof:name":"Tavertet",
    "wof:placetype":"locality",
    "wof:population":153
},
  "geometry": {"coordinates":[2.4186,41.99572],"type":"Point"}
}