{
  "type": "Feature",
  "properties": {
    "gn:admin1_code":"51",
    "gn:admin2_code":"AL",
    "gn:admin3_code":"04086",
    "gn:asciiname":"La Huelga",
    "gn:country_code":"ES",
    "gn:dem":175,
    "gn:feature_class":"P",
    "gn:feature_code":"PPL",
    "gn:name":"La Huelga",
    "gn:population":0,
    "gn:timezone":"Europe/Madrid",
    "iso:country":"ES",
    "wof:name":"La Huelga",
    "wof:placetype":"locality"
},
  "geometry": {"coordinates":[-2.01264,37.11487],"type":"Point"}
}