{
  "type": "Feature",
  "properties": {
    "gn:gn_country":"ES",
    "gn:gn_fcode":"PPL",
    "gn:gn_pop":0,
    "iso:country":"ES",
    "name:deu_x_preferred":[
        "Isla Plana"
    ],
    "name:eng_x_preferred":[
        "Isla Plana"
    ],
    "name:glg_x_preferred":[
        "Illa Plana"
    ],
    "name:spa_x_preferred":[
        "Isla Plana"
    ],
    "name:swe_x_preferred":[
        "Isla Plana"
    ],
    "name:unk_x_variant":[
        "Caser\u00edo Isla Plana"
    ],
    "qs_pg:aaroncc":"ES",
    "qs_pg:gn_country":"ES",
    "qs_pg:gn_fcode":"PPL",
    "qs_pg:gn_pop":0,
    "qs_pg:name":"Isla Plana",
    "qs_pg:name_adm0":"Espa\u00f1a",
    "qs_pg:name_adm1":"Regi\u00f3n de Murcia",
    "qs_pg:photos":174,
    "qs_pg:photos_1k":35,
    "qs_pg:photos_9k":1,
    "qs_pg:photos_9r":4,
    "qs_pg:photos_all":174,
    "qs_pg:photos_sr":4,
    "qs_pg:pop_sr":0,
    "qs_pg:qs_pg_placetype":"locality",
    "qs_pg:qs_pg_placetype_gp":"Town",
    "qs_pg:woe_adm0":23424950,
    "woe:adm0_id":23424950,
    "woe:name_adm0":"Espa\u00f1a",
    "woe:name_adm1":"Regi\u00f3n de Murcia",
    "woe:placetype":"Town",
    "wof:name":"Isla Plana",
    "wof:placetype":"locality"
},
  "geometry": {"coordinates":[-1.20858,37.57465],"type":"Point"}
}