{
  "type": "Feature",
  "properties": {
    "gn:admin1_code":"58",
    "gn:admin2_code":"C",
    "gn:admin3_code":"15047",
    "gn:asciiname":"Cumbraos",
    "gn:cc2":"ES",
    "gn:country_code":"ES",
    "gn:dem":473,
    "gn:feature_class":"P",
    "gn:feature_code":"PPL",
    "gn:name":"Cumbraos",
    "gn:population":0,
    "gn:timezone":"Europe/Madrid",
    "iso:country":"ES",
    "name:und_x_variant":[
        "Santa Mar\u00eda",
        "Cumbraos"
    ],
    "wof:name":"Cumbraos",
    "wof:placetype":"locality"
},
  "geometry": {"coordinates":[-8.16667,43.08333],"type":"Point"}
}