{
  "type": "Feature",
  "properties": {
    "gn:admin1_code":"57",
    "gn:admin2_code":"BA",
    "gn:admin3_code":"06016",
    "gn:asciiname":"Monterroso",
    "gn:country_code":"ES",
    "gn:dem":458,
    "gn:feature_class":"P",
    "gn:feature_code":"PPL",
    "gn:name":"Monterroso",
    "gn:population":0,
    "gn:timezone":"Europe/Madrid",
    "iso:country":"ES",
    "name:und_x_variant":[
        "Cortijo Monterroso",
        "Monterroso"
    ],
    "wof:name":"Monterroso",
    "wof:placetype":"locality"
},
  "geometry": {"coordinates":[-6.92842,38.54413],"type":"Point"}
}