{
  "type": "Feature",
  "properties": {
    "gn:admin1_code":"57",
    "gn:admin2_code":"BA",
    "gn:admin3_code":"06016",
    "gn:asciiname":"Monterroso",
    "gn:country_code":"ES",
    "gn:dem":458,
    "gn:feature_class":"P",
    "gn:feature_code":"PPL",
    "gn:name":"Monterroso",
    "gn:population":0,
    "gn:timezone":"Europe/Madrid",
    "iso:country":"ES",
    "name:arg_x_preferred":[
        "Monterroso"
    ],
    "name:ast_x_preferred":[
        "Monterroso"
    ],
    "name:cat_x_preferred":[
        "Monterroso"
    ],
    "name:ceb_x_preferred":[
        "Monterroso"
    ],
    "name:eus_x_preferred":[
        "Monterroso"
    ],
    "name:fra_x_preferred":[
        "Monterroso"
    ],
    "name:glg_x_preferred":[
        "Monterroso"
    ],
    "name:hun_x_preferred":[
        "Monterroso"
    ],
    "name:hye_x_preferred":[
        "\u0544\u0578\u0576\u057f\u0565\u057c\u0578\u057d\u0578"
    ],
    "name:ita_x_preferred":[
        "Monterroso"
    ],
    "name:jpn_x_preferred":[
        "\u30e2\u30f3\u30c6\u30ed\u30fc\u30bd"
    ],
    "name:kaz_x_preferred":[
        "\u041c\u043e\u043d\u0442\u0435\u0440\u0440\u043e\u0441\u043e"
    ],
    "name:msa_x_preferred":[
        "Monterroso"
    ],
    "name:nld_x_preferred":[
        "Monterroso"
    ],
    "name:oci_x_preferred":[
        "Monterroso"
    ],
    "name:pol_x_preferred":[
        "Monterroso"
    ],
    "name:por_x_preferred":[
        "Monterroso"
    ],
    "name:rus_x_preferred":[
        "\u041c\u043e\u043d\u0442\u0435\u0440\u0440\u043e\u0441\u043e"
    ],
    "name:spa_x_preferred":[
        "Monterroso"
    ],
    "name:swe_x_preferred":[
        "Monterroso"
    ],
    "name:tur_x_preferred":[
        "Monterroso"
    ],
    "name:ukr_x_preferred":[
        "\u041c\u043e\u043d\u0442\u0435\u0440\u0440\u043e\u0441\u043e"
    ],
    "name:und_x_variant":[
        "Cortijo Monterroso"
    ],
    "name:uzb_x_preferred":[
        "Monterroso"
    ],
    "name:vie_x_preferred":[
        "Monterroso"
    ],
    "name:war_x_preferred":[
        "Monterroso"
    ],
    "name:zho_x_preferred":[
        "\u8499\u7279\u7f57\u7d22"
    ],
    "wof:name":"Monterroso",
    "wof:placetype":"locality"
},
  "geometry": {"coordinates":[-6.92842,38.54413],"type":"Point"}
}