{
  "type": "Feature",
  "properties": {
    "gn:admin1_code":"52",
    "gn:admin2_code":"HU",
    "gn:admin3_code":"22199",
    "gn:asciiname":"Fenillosa",
    "gn:country_code":"ES",
    "gn:dem":1069,
    "gn:feature_class":"P",
    "gn:feature_code":"PPL",
    "gn:name":"Fenillosa",
    "gn:population":0,
    "gn:timezone":"Europe/Madrid",
    "iso:country":"ES",
    "wof:name":"Fenillosa",
    "wof:placetype":"locality"
},
  "geometry": {"coordinates":[-0.22591,42.43473],"type":"Point"}
}