{
  "type": "Feature",
  "properties": {
    "gn:admin1_code":"58",
    "gn:admin2_code":"OR",
    "gn:admin3_code":"32092",
    "gn:asciiname":"Chaguazoso",
    "gn:country_code":"ES",
    "gn:dem":1290,
    "gn:feature_class":"P",
    "gn:feature_code":"PPL",
    "gn:name":"Chaguazoso",
    "gn:population":0,
    "gn:timezone":"Europe/Madrid",
    "iso:country":"ES",
    "wof:name":"Chaguazoso",
    "wof:placetype":"locality"
},
  "geometry": {"coordinates":[-7.21637,42.19251],"type":"Point"}
}