{
  "type": "Feature",
  "properties": {
    "gn:admin1_code":"56",
    "gn:admin2_code":"GI",
    "gn:admin3_code":"17161",
    "gn:asciiname":"Sant Miquel de Pineda",
    "gn:country_code":"ES",
    "gn:dem":504,
    "gn:feature_class":"P",
    "gn:feature_code":"PPL",
    "gn:name":"Sant Miquel de Pineda",
    "gn:population":0,
    "gn:timezone":"Europe/Madrid",
    "iso:country":"ES",
    "name:cat_x_preferred":[
        "Sant Miquel de Pineda"
    ],
    "wof:name":"Sant Miquel de Pineda",
    "wof:placetype":"locality"
},
  "geometry": {"coordinates":[2.4939,42.09746],"type":"Point"}
}