{
  "type": "Feature",
  "properties": {
    "gn:admin1_code":"59",
    "gn:admin2_code":"SS",
    "gn:admin3_code":"20034",
    "gn:asciiname":"Maulanda",
    "gn:country_code":"ES",
    "gn:dem":362,
    "gn:feature_class":"P",
    "gn:feature_code":"PPL",
    "gn:name":"Marulanda",
    "gn:population":0,
    "gn:timezone":"Europe/Madrid",
    "iso:country":"ES",
    "name:eus_x_preferred":[
        "Marulanda"
    ],
    "name:spa_x_preferred":[
        "Maulanda"
    ],
    "wof:name":"Maulanda",
    "wof:placetype":"locality"
},
  "geometry": {"coordinates":[-2.56665,42.99514],"type":"Point"}
}