{
  "type": "Feature",
  "properties": {
    "gn:admin1_code":"59",
    "gn:admin2_code":"SS",
    "gn:admin3_code":"20034",
    "gn:asciiname":"Erana",
    "gn:country_code":"ES",
    "gn:dem":435,
    "gn:feature_class":"P",
    "gn:feature_code":"PPL",
    "gn:name":"Era\u00f1a",
    "gn:population":0,
    "gn:timezone":"Europe/Madrid",
    "iso:country":"ES",
    "name:eus_x_preferred":[
        "Era\u00f1a"
    ],
    "wof:name":"Erana",
    "wof:placetype":"locality"
},
  "geometry": {"coordinates":[-2.51645,43.01024],"type":"Point"}
}