{
  "type": "Feature",
  "properties": {
    "gn:admin1_code":"51",
    "gn:admin2_code":"SE",
    "gn:admin3_code":"41020",
    "gn:asciiname":"La Harinosa",
    "gn:country_code":"ES",
    "gn:dem":125,
    "gn:feature_class":"P",
    "gn:feature_code":"PPL",
    "gn:name":"La Harinosa",
    "gn:population":0,
    "gn:timezone":"Europe/Madrid",
    "iso:country":"ES",
    "name:und_x_variant":[
        "Caser\u00edo La Harinosa",
        "La Harinosa"
    ],
    "wof:name":"La Harinosa",
    "wof:placetype":"locality"
},
  "geometry": {"coordinates":[-5.83084,36.95364],"type":"Point"}
}