{
  "type": "Feature",
  "properties": {
    "gn:admin1_code":"58",
    "gn:admin2_code":"C",
    "gn:admin3_code":"15061",
    "gn:asciiname":"Cuina",
    "gn:cc2":"ES",
    "gn:country_code":"ES",
    "gn:dem":77,
    "gn:feature_class":"P",
    "gn:feature_code":"PPL",
    "gn:name":"Cui\u00f1a",
    "gn:population":0,
    "gn:timezone":"Europe/Madrid",
    "iso:country":"ES",
    "name:und_x_variant":[
        "Santiago",
        "Cui\u00f1a"
    ],
    "wof:name":"Cuina",
    "wof:placetype":"locality"
},
  "geometry": {"coordinates":[-7.83333,43.66667],"type":"Point"}
}