{
  "type": "Feature",
  "properties": {
    "gn:admin1_code":"55",
    "gn:admin2_code":"AV",
    "gn:admin3_code":"05128",
    "gn:asciiname":"Zorita de los Molinos",
    "gn:country_code":"ES",
    "gn:dem":926,
    "gn:feature_class":"P",
    "gn:feature_code":"PPL",
    "gn:name":"Zorita de los Molinos",
    "gn:population":0,
    "gn:timezone":"Europe/Madrid",
    "iso:country":"ES",
    "wof:name":"Zorita de los Molinos",
    "wof:placetype":"locality"
},
  "geometry": {"coordinates":[-4.69898,40.76918],"type":"Point"}
}