{
  "type": "Feature",
  "properties": {
    "gn:gn_country":"ES",
    "gn:gn_fcode":"ADM3",
    "gn:gn_pop":192,
    "gn:population":219,
    "iso:country":"ES",
    "name:arg_x_preferred":[
        "Blecua-Torres"
    ],
    "name:baq_x_preferred":[
        "Blecua y Torres"
    ],
    "name:cat_x_preferred":[
        "Blecua y Torres"
    ],
    "name:chi_x_preferred":[
        "\u5e03\u83b1\u5938\u4f0a\u6258\u96f7\u65af"
    ],
    "name:dut_x_preferred":[
        "Blecua y Torres"
    ],
    "name:eng_x_preferred":[
        "Blecua y Torres"
    ],
    "name:fre_x_preferred":[
        "Blecua y Torres"
    ],
    "name:hak_x_preferred":[
        "Blecua y Torres"
    ],
    "name:hun_x_preferred":[
        "Blecua y Torres"
    ],
    "name:ita_x_preferred":[
        "Blecua y Torres"
    ],
    "name:may_x_preferred":[
        "Blecua y Torres"
    ],
    "name:nan_x_preferred":[
        "Blecua y Torres"
    ],
    "name:oci_x_preferred":[
        "Blecua y Torres"
    ],
    "name:pol_x_preferred":[
        "Blecua y Torres"
    ],
    "name:por_x_preferred":[
        "Blecua y Torres"
    ],
    "name:rus_x_preferred":[
        "\u0411\u043b\u0435\u043a\u0443\u0430-\u0438-\u0422\u043e\u0440\u0440\u0435\u0441"
    ],
    "name:spa_x_preferred":[
        "Blecua y Torres"
    ],
    "name:swe_x_preferred":[
        "Blecua y Torres"
    ],
    "name:ukr_x_preferred":[
        "\u0411\u043b\u0435\u043a\u0443\u0430-\u0456-\u0422\u043e\u0440\u0440\u0435\u0441"
    ],
    "name:uzb_x_preferred":[
        "Blecua y Torres"
    ],
    "name:vie_x_preferred":[
        "Blecua y Torres"
    ],
    "name:war_x_preferred":[
        "Blecua y Torres"
    ],
    "qs_pg:aaroncc":"ES",
    "qs_pg:gn_country":"ES",
    "qs_pg:gn_fcode":"ADM3",
    "qs_pg:gn_pop":192,
    "qs_pg:name":"Blecua y Torres",
    "qs_pg:name_adm0":"Espa\u00f1a",
    "qs_pg:name_adm1":"Arag\u00f3n",
    "qs_pg:photos_9r":0,
    "qs_pg:photos_sr":0,
    "qs_pg:pop_sr":1,
    "qs_pg:qs_pg_placetype":"locality",
    "qs_pg:qs_pg_placetype_gp":"Town",
    "qs_pg:woe_adm0":23424950,
    "woe:adm0_id":23424950,
    "woe:name_adm0":"Espa\u00f1a",
    "woe:name_adm1":"Arag\u00f3n",
    "woe:placetype":"Town",
    "wof:name":"Blecua y Torres",
    "wof:placetype":"locality",
    "wof:population":219
},
  "geometry": {"coordinates":[-0.19123,42.07091],"type":"Point"}
}