{
  "type": "Feature",
  "properties": {
    "gn:gn_country":"ES",
    "gn:gn_fcode":"PPL",
    "gn:gn_pop":0,
    "iso:country":"ES",
    "name:arg_x_preferred":[
        "Bembibre"
    ],
    "name:ast_x_preferred":[
        "Bembibre"
    ],
    "name:cat_x_preferred":[
        "Bembibre"
    ],
    "name:ceb_x_preferred":[
        "Bembibre"
    ],
    "name:epo_x_preferred":[
        "Bembibro"
    ],
    "name:eus_x_preferred":[
        "Bembibre"
    ],
    "name:fra_x_preferred":[
        "Bembibre"
    ],
    "name:glg_x_preferred":[
        "Bembibre"
    ],
    "name:haw_x_preferred":[
        "Bembibre"
    ],
    "name:hun_x_preferred":[
        "Bembibre"
    ],
    "name:ido_x_preferred":[
        "Bembibre"
    ],
    "name:ina_x_preferred":[
        "Bembibre"
    ],
    "name:ita_x_preferred":[
        "Bembibre"
    ],
    "name:jpn_x_preferred":[
        "\u30d9\u30f3\u30d3\u30d6\u30ec"
    ],
    "name:msa_x_preferred":[
        "Bembibre"
    ],
    "name:nld_x_preferred":[
        "Bembibre"
    ],
    "name:oci_x_preferred":[
        "Bembibre"
    ],
    "name:pol_x_preferred":[
        "Bembibre"
    ],
    "name:por_x_preferred":[
        "Bembibre"
    ],
    "name:rus_x_preferred":[
        "\u0411\u0435\u043c\u0431\u0438\u0431\u0440\u0435"
    ],
    "name:spa_x_preferred":[
        "Bembibre"
    ],
    "name:swe_x_preferred":[
        "Bembibre"
    ],
    "name:tpi_x_preferred":[
        "Bembibre"
    ],
    "name:ukr_x_preferred":[
        "\u0411\u0435\u043c\u0431\u0456\u0431\u0440\u0435"
    ],
    "name:vie_x_preferred":[
        "Bembibre"
    ],
    "name:war_x_preferred":[
        "Bembibre"
    ],
    "name:zho_x_preferred":[
        "\u672c\u7ef4\u592b\u96f7"
    ],
    "qs_pg:aaroncc":"ES",
    "qs_pg:gn_country":"ES",
    "qs_pg:gn_fcode":"PPL",
    "qs_pg:gn_pop":0,
    "qs_pg:name":"Bembibre",
    "qs_pg:name_adm0":"Espa\u00f1a",
    "qs_pg:name_adm1":"Galicia",
    "qs_pg:photos_9r":0,
    "qs_pg:photos_sr":0,
    "qs_pg:pop_sr":0,
    "qs_pg:qs_pg_placetype":"locality",
    "qs_pg:qs_pg_placetype_gp":"Town",
    "qs_pg:woe_adm0":23424950,
    "woe:adm0_id":23424950,
    "woe:name_adm0":"Espa\u00f1a",
    "woe:name_adm1":"Galicia",
    "woe:placetype":"Town",
    "wof:name":"Bembibre",
    "wof:placetype":"locality"
},
  "geometry": {"coordinates":[-8.66358,43.02487],"type":"Point"}
}