{
  "type": "Feature",
  "properties": {
    "gn:admin1_code":"55",
    "gn:admin2_code":"SA",
    "gn:admin3_code":"37013",
    "gn:asciiname":"Valbuena",
    "gn:country_code":"ES",
    "gn:dem":869,
    "gn:feature_class":"P",
    "gn:feature_code":"PPL",
    "gn:name":"Valbuena",
    "gn:population":0,
    "gn:timezone":"Europe/Madrid",
    "iso:country":"ES",
    "wof:name":"Valbuena",
    "wof:placetype":"locality"
},
  "geometry": {"coordinates":[-5.86207,40.38034],"type":"Point"}
}