{
  "type": "Feature",
  "properties": {
    "gn:admin1_code":"59",
    "gn:admin2_code":"BI",
    "gn:admin3_code":"48080",
    "gn:asciiname":"Escontrilla Alta",
    "gn:country_code":"ES",
    "gn:dem":34,
    "gn:feature_class":"P",
    "gn:feature_code":"PPL",
    "gn:name":"Escontrilla Alta",
    "gn:population":0,
    "gn:timezone":"Europe/Madrid",
    "iso:country":"ES",
    "wof:name":"Escontrilla Alta",
    "wof:placetype":"locality"
},
  "geometry": {"coordinates":[-3.03744,43.3042],"type":"Point"}
}