{
  "type": "Feature",
  "properties": {
    "gn:admin1_code":"58",
    "gn:admin2_code":"LU",
    "gn:admin3_code":"27065",
    "gn:asciiname":"Roman",
    "gn:cc2":"ES",
    "gn:country_code":"ES",
    "gn:dem":447,
    "gn:feature_class":"P",
    "gn:feature_code":"PPL",
    "gn:name":"Rom\u00e1n",
    "gn:population":0,
    "gn:timezone":"Europe/Madrid",
    "iso:country":"ES",
    "name:afr_x_preferred":[
        "Roman"
    ],
    "name:azb_x_preferred":[
        "\u0631\u0648\u0645\u0627\u0646 \u060c"
    ],
    "name:bre_x_preferred":[
        "Roman"
    ],
    "name:ceb_x_preferred":[
        "Roman"
    ],
    "name:ces_x_preferred":[
        "Roman"
    ],
    "name:deu_x_preferred":[
        "Roman"
    ],
    "name:ell_x_preferred":[
        "\u03a1\u03c9\u03bc\u03b1\u03af\u03bf\u03b9"
    ],
    "name:epo_x_preferred":[
        "Roman"
    ],
    "name:est_x_preferred":[
        "Roman"
    ],
    "name:fin_x_preferred":[
        "Roman"
    ],
    "name:fra_x_preferred":[
        "Roman"
    ],
    "name:heb_x_preferred":[
        "\u05e8\u05d5\u05de\u05df"
    ],
    "name:ita_x_preferred":[
        "Roman"
    ],
    "name:jpn_x_preferred":[
        "\u30ed\u30de\u30f3"
    ],
    "name:kur_x_preferred":[
        "Roman"
    ],
    "name:ltz_x_preferred":[
        "Roman"
    ],
    "name:nld_x_preferred":[
        "Roman"
    ],
    "name:pms_x_preferred":[
        "Roman"
    ],
    "name:pol_x_preferred":[
        "Roman"
    ],
    "name:por_x_preferred":[
        "Roman"
    ],
    "name:ron_x_preferred":[
        "Roman"
    ],
    "name:slk_x_preferred":[
        "Roman"
    ],
    "name:slv_x_preferred":[
        "Roman"
    ],
    "name:spa_x_preferred":[
        "Roman"
    ],
    "name:srp_x_preferred":[
        "\u0420\u0438\u043c\u0459\u0430\u043d\u0438"
    ],
    "name:swe_x_preferred":[
        "Roman"
    ],
    "name:und_x_variant":[
        "Santa Eulalia",
        "Rom\u00e1n"
    ],
    "name:wln_x_preferred":[
        "Roman"
    ],
    "name:zho_x_preferred":[
        "\u7f57\u9a6c\u4eba"
    ],
    "wof:name":"Roman",
    "wof:placetype":"locality"
},
  "geometry": {"coordinates":[-7.58828,43.3017],"type":"Point"}
}