{
  "type": "Feature",
  "properties": {
    "gn:admin1_code":"58",
    "gn:admin2_code":"LU",
    "gn:admin3_code":"27065",
    "gn:asciiname":"Roman",
    "gn:cc2":"ES",
    "gn:country_code":"ES",
    "gn:dem":447,
    "gn:feature_class":"P",
    "gn:feature_code":"PPL",
    "gn:name":"Rom\u00e1n",
    "gn:population":0,
    "gn:timezone":"Europe/Madrid",
    "iso:country":"ES",
    "name:und_x_variant":[
        "Santa Eulalia",
        "Rom\u00e1n"
    ],
    "wof:name":"Roman",
    "wof:placetype":"locality"
},
  "geometry": {"coordinates":[-7.58828,43.3017],"type":"Point"}
}