{
  "type": "Feature",
  "properties": {
    "gn:admin1_code":"55",
    "gn:admin2_code":"AV",
    "gn:admin3_code":"05236",
    "gn:asciiname":"Serrania",
    "gn:country_code":"ES",
    "gn:dem":1213,
    "gn:feature_class":"P",
    "gn:feature_code":"PPL",
    "gn:name":"Serran\u00eda",
    "gn:population":0,
    "gn:timezone":"Europe/Madrid",
    "iso:country":"ES",
    "name:bpy_x_preferred":[
        "\u09b8\u09c7\u09b0\u09b0\u09be\u09a8\u09bf\u09af\u09bc\u09be"
    ],
    "name:ceb_x_preferred":[
        "Serrania"
    ],
    "name:epo_x_preferred":[
        "Serrania"
    ],
    "name:eus_x_preferred":[
        "Serrania"
    ],
    "name:fra_x_preferred":[
        "Serrania"
    ],
    "name:ita_x_preferred":[
        "Serrania"
    ],
    "name:kat_x_preferred":[
        "\u10e1\u10d4\u10e0\u10d0\u10dc\u10d8\u10d0"
    ],
    "name:kaz_x_preferred":[
        "\u0421\u0435\u0440\u0440\u0430\u043d\u0438\u044f"
    ],
    "name:mlg_x_preferred":[
        "Serrania"
    ],
    "name:nld_x_preferred":[
        "Serrania"
    ],
    "name:nor_x_preferred":[
        "Serrania"
    ],
    "name:pol_x_preferred":[
        "Serrania"
    ],
    "name:por_x_preferred":[
        "Serrania"
    ],
    "name:ron_x_preferred":[
        "Serrania"
    ],
    "name:rus_x_preferred":[
        "\u0421\u0435\u0440\u0440\u0430\u043d\u0438\u044f"
    ],
    "name:swe_x_preferred":[
        "Serrania"
    ],
    "name:und_x_variant":[
        "Serran\u00eda"
    ],
    "name:vie_x_preferred":[
        "Serrania"
    ],
    "name:vol_x_preferred":[
        "Serrania"
    ],
    "name:war_x_preferred":[
        "Serrania"
    ],
    "name:zho_x_preferred":[
        "\u585e\u62c9\u5c3c\u4e9a"
    ],
    "wof:name":"Serrania",
    "wof:placetype":"locality"
},
  "geometry": {"coordinates":[-5.59034,40.34883],"type":"Point"}
}