{
  "type": "Feature",
  "properties": {
    "gn:admin1_code":"55",
    "gn:admin2_code":"AV",
    "gn:admin3_code":"05236",
    "gn:asciiname":"Serrania",
    "gn:country_code":"ES",
    "gn:dem":1213,
    "gn:feature_class":"P",
    "gn:feature_code":"PPL",
    "gn:name":"Serran\u00eda",
    "gn:population":0,
    "gn:timezone":"Europe/Madrid",
    "iso:country":"ES",
    "name:und_x_variant":[
        "Serran\u00eda"
    ],
    "wof:name":"Serrania",
    "wof:placetype":"locality"
},
  "geometry": {"coordinates":[-5.59034,40.34883],"type":"Point"}
}