{
  "type": "Feature",
  "properties": {
    "gn:admin1_code":"54",
    "gn:admin2_code":"TO",
    "gn:admin3_code":"45162",
    "gn:asciiname":"Minas de Santa Quiteria",
    "gn:country_code":"ES",
    "gn:dem":472,
    "gn:feature_class":"P",
    "gn:feature_code":"PPL",
    "gn:name":"Minas de Santa Quiteria",
    "gn:population":0,
    "gn:timezone":"Europe/Madrid",
    "iso:country":"ES",
    "name:und_x_variant":[
        "Mina Santa Quiteria",
        "Minas de Santa Quiteria"
    ],
    "wof:name":"Minas de Santa Quiteria",
    "wof:placetype":"locality"
},
  "geometry": {"coordinates":[-4.97939,39.46049],"type":"Point"}
}