{
  "type": "Feature",
  "properties": {
    "gn:admin1_code":"52",
    "gn:admin2_code":"HU",
    "gn:admin3_code":"22199",
    "gn:asciiname":"Asun",
    "gn:country_code":"ES",
    "gn:dem":1277,
    "gn:feature_class":"P",
    "gn:feature_code":"PPL",
    "gn:name":"As\u00fan",
    "gn:population":0,
    "gn:timezone":"Europe/Madrid",
    "iso:country":"ES",
    "wof:name":"Asun",
    "wof:placetype":"locality"
},
  "geometry": {"coordinates":[-0.38577,42.61898],"type":"Point"}
}