{
  "type": "Feature",
  "properties": {
    "gn:admin1_code":"59",
    "gn:admin2_code":"VI",
    "gn:admin3_code":"01004",
    "gn:asciiname":"Retes de Tudela",
    "gn:country_code":"ES",
    "gn:dem":399,
    "gn:feature_class":"P",
    "gn:feature_code":"PPL",
    "gn:name":"Erretes Tudela / Retes de Tudela",
    "gn:population":0,
    "gn:timezone":"Europe/Madrid",
    "iso:country":"ES",
    "name:eus_x_preferred":[
        "Erretes Tudela"
    ],
    "name:spa_x_preferred":[
        "Retes de Tudela"
    ],
    "wof:name":"Retes de Tudela",
    "wof:placetype":"locality"
},
  "geometry": {"coordinates":[-3.16841,43.11458],"type":"Point"}
}