{
  "type": "Feature",
  "properties": {
    "gn:admin1_code":"54",
    "gn:admin2_code":"CU",
    "gn:admin3_code":"16239",
    "gn:asciiname":"Los Perales",
    "gn:country_code":"ES",
    "gn:dem":1343,
    "gn:feature_class":"P",
    "gn:feature_code":"PPL",
    "gn:name":"Los Perales",
    "gn:population":0,
    "gn:timezone":"Europe/Madrid",
    "iso:country":"ES",
    "name:und_x_variant":[
        "Barrio Los Perales",
        "Los Perales"
    ],
    "wof:name":"Los Perales",
    "wof:placetype":"locality"
},
  "geometry": {"coordinates":[-1.9247,40.42663],"type":"Point"}
}