{
  "type": "Feature",
  "properties": {
    "gn:admin1_code":"53",
    "gn:admin2_code":"TF",
    "gn:admin3_code":"38001",
    "gn:asciiname":"Tijoco de Abajo",
    "gn:country_code":"ES",
    "gn:dem":535,
    "gn:feature_class":"P",
    "gn:feature_code":"PPL",
    "gn:name":"Tijoco de Abajo",
    "gn:population":0,
    "gn:timezone":"Atlantic/Canary",
    "iso:country":"ES",
    "wof:name":"Tijoco de Abajo",
    "wof:placetype":"locality"
},
  "geometry": {"coordinates":[-16.75,28.15],"type":"Point"}
}