{
  "type": "Feature",
  "properties": {
    "gn:admin1_code":"55",
    "gn:admin2_code":"SO",
    "gn:admin3_code":"42027",
    "gn:asciiname":"Torrearevalo",
    "gn:country_code":"ES",
    "gn:dem":1280,
    "gn:feature_class":"P",
    "gn:feature_code":"PPL",
    "gn:name":"Torrear\u00e9valo",
    "gn:population":0,
    "gn:timezone":"Europe/Madrid",
    "iso:country":"ES",
    "name:und_x_variant":[
        "Torrear\u00e9valo"
    ],
    "wof:name":"Torrearevalo",
    "wof:placetype":"locality"
},
  "geometry": {"coordinates":[-2.38863,41.95928],"type":"Point"}
}