{
  "type": "Feature",
  "properties": {
    "gn:admin1_code":"55",
    "gn:admin2_code":"AV",
    "gn:admin3_code":"05037",
    "gn:asciiname":"Navamojada",
    "gn:country_code":"ES",
    "gn:dem":1093,
    "gn:feature_class":"P",
    "gn:feature_code":"PPL",
    "gn:name":"Navamojada",
    "gn:population":0,
    "gn:timezone":"Europe/Madrid",
    "iso:country":"ES",
    "wof:name":"Navamojada",
    "wof:placetype":"locality"
},
  "geometry": {"coordinates":[-5.46146,40.32147],"type":"Point"}
}