{
  "type": "Feature",
  "properties": {
    "gn:admin1_code":"58",
    "gn:admin2_code":"C",
    "gn:admin3_code":"15035",
    "gn:asciiname":"Sillobre",
    "gn:cc2":"ES",
    "gn:country_code":"ES",
    "gn:dem":328,
    "gn:feature_class":"P",
    "gn:feature_code":"PPL",
    "gn:name":"Sillobre",
    "gn:population":0,
    "gn:timezone":"Europe/Madrid",
    "iso:country":"ES",
    "name:und_x_variant":[
        "Santa Marina",
        "Sillobre"
    ],
    "wof:name":"Sillobre",
    "wof:placetype":"locality"
},
  "geometry": {"coordinates":[-8.13333,43.48333],"type":"Point"}
}