{
  "type": "Feature",
  "properties": {
    "gn:admin1_code":"56",
    "gn:admin2_code":"GI",
    "gn:admin3_code":"17051",
    "gn:asciiname":"Mare de Deu de Vida",
    "gn:country_code":"ES",
    "gn:dem":188,
    "gn:feature_class":"P",
    "gn:feature_code":"PPLL",
    "gn:name":"Mare de D\u00e9u de Vida",
    "gn:population":0,
    "gn:timezone":"Europe/Madrid",
    "iso:country":"ES",
    "name:cat_x_preferred":[
        "Mare de D\u00e9u de Vida"
    ],
    "wof:name":"Mare de Deu de Vida",
    "wof:placetype":"locality"
},
  "geometry": {"coordinates":[2.83829,42.26686],"type":"Point"}
}