{
  "type": "Feature",
  "properties": {
    "gn:admin1_code":"31",
    "gn:admin2_code":"MU",
    "gn:admin3_code":"30038",
    "gn:asciiname":"Las Torres de Cotillas",
    "gn:country_code":"ES",
    "gn:dem":87,
    "gn:feature_class":"P",
    "gn:feature_code":"PPLA3",
    "gn:name":"Las Torres de Cotillas",
    "gn:population":21062,
    "gn:timezone":"Europe/Madrid",
    "iso:country":"ES",
    "name:ara_x_preferred":[
        "\u0644\u0627\u0633 \u062a\u0648\u0631\u064a\u0633 \u062f\u064a \u0643\u0648\u062a\u064a\u0627\u0633"
    ],
    "name:azb_x_preferred":[
        "\u0644\u0627\u0633 \u062a\u0631\u0633 \u062f \u06a9\u062a\u06cc\u06cc\u0627\u0633"
    ],
    "name:fas_x_preferred":[
        "\u0644\u0627\u0633 \u062a\u0631\u0633 \u062f \u06a9\u062a\u06cc\u06cc\u0627\u0633"
    ],
    "name:srp_x_preferred":[
        "\u041b\u0430\u0441 \u0422\u043e\u0440\u0435\u0441 \u0434\u0435 \u041a\u043e\u0442\u0438\u0459\u0430\u0441"
    ],
    "name:und_x_variant":[
        "La Torres de Cotillas",
        "Las Torres de Cotillas"
    ],
    "name:urd_x_preferred":[
        "\u0644\u0627\u0633 \u0679\u0648\u0631\u06cc\u0633 \u062f\u06d2 \u06a9\u0648\u0679\u06cc\u0644\u0627\u0633"
    ],
    "wof:name":"Las Torres de Cotillas",
    "wof:placetype":"locality",
    "wof:population":21062
},
  "geometry": {"coordinates":[-1.24188,38.02822000000001],"type":"Point"}
}