{
  "type": "Feature",
  "properties": {
    "gn:admin1_code":"31",
    "gn:admin2_code":"MU",
    "gn:admin3_code":"30038",
    "gn:asciiname":"Las Torres de Cotillas",
    "gn:country_code":"ES",
    "gn:dem":87,
    "gn:feature_class":"P",
    "gn:feature_code":"PPLA3",
    "gn:name":"Las Torres de Cotillas",
    "gn:population":21062,
    "gn:timezone":"Europe/Madrid",
    "iso:country":"ES",
    "name:und_x_variant":[
        "La Torres de Cotillas",
        "Las Torres de Cotillas"
    ],
    "wof:name":"Las Torres de Cotillas",
    "wof:placetype":"locality",
    "wof:population":21062
},
  "geometry": {"coordinates":[-1.24188,38.02822000000001],"type":"Point"}
}