{
  "type": "Feature",
  "properties": {
    "gn:admin1_code":"39",
    "gn:admin2_code":"S",
    "gn:admin3_code":"39056",
    "gn:asciiname":"Las Presillas",
    "gn:country_code":"ES",
    "gn:dem":54,
    "gn:feature_class":"P",
    "gn:feature_code":"PPL",
    "gn:name":"Las Presillas",
    "gn:population":0,
    "gn:timezone":"Europe/Madrid",
    "iso:country":"ES",
    "wof:name":"Las Presillas",
    "wof:placetype":"locality"
},
  "geometry": {"coordinates":[-3.9864,43.33017],"type":"Point"}
}