{
  "type": "Feature",
  "properties": {
    "gn:admin1_code":"58",
    "gn:admin2_code":"LU",
    "gn:admin3_code":"27023",
    "gn:asciiname":"Gomelle",
    "gn:country_code":"ES",
    "gn:dem":604,
    "gn:feature_class":"P",
    "gn:feature_code":"PPL",
    "gn:name":"Gomelle",
    "gn:population":0,
    "gn:timezone":"Europe/Madrid",
    "iso:country":"ES",
    "wof:name":"Gomelle",
    "wof:placetype":"locality"
},
  "geometry": {"coordinates":[-7.66956,42.94162],"type":"Point"}
}