{
  "type": "Feature",
  "properties": {
    "gn:admin1_code":"52",
    "gn:admin2_code":"TE",
    "gn:admin3_code":"44216",
    "gn:asciiname":"Concud",
    "gn:country_code":"ES",
    "gn:dem":936,
    "gn:feature_class":"P",
    "gn:feature_code":"PPL",
    "gn:name":"Concud",
    "gn:population":0,
    "gn:timezone":"Europe/Madrid",
    "iso:country":"ES",
    "name:und_x_variant":[
        "Barrio de Concud",
        "Concud"
    ],
    "wof:name":"Concud",
    "wof:placetype":"locality"
},
  "geometry": {"coordinates":[-1.14755,40.37956],"type":"Point"}
}