{
  "type": "Feature",
  "properties": {
    "gn:gn_country":"ES",
    "gn:gn_fcode":"PPL",
    "gn:gn_pop":0,
    "iso:country":"ES",
    "name:dut_x_preferred":[
        "Los Abrigos"
    ],
    "name:eng_x_preferred":[
        "Los Abrigos"
    ],
    "name:fre_x_preferred":[
        "Los Abrigos"
    ],
    "name:spa_x_preferred":[
        "Los Abrigos"
    ],
    "name:unk_x_variant":[
        "Los Abrigos"
    ],
    "qs_pg:aaroncc":"ES",
    "qs_pg:gn_country":"ES",
    "qs_pg:gn_fcode":"PPL",
    "qs_pg:gn_pop":0,
    "qs_pg:name":"El Abrigo",
    "qs_pg:name_adm0":"Espa\u00f1a",
    "qs_pg:name_adm1":"Islas Canarias",
    "qs_pg:photos":413,
    "qs_pg:photos_1k":84,
    "qs_pg:photos_9k":2,
    "qs_pg:photos_9r":5,
    "qs_pg:photos_all":413,
    "qs_pg:photos_sr":6,
    "qs_pg:pop_sr":0,
    "qs_pg:qs_pg_placetype":"locality",
    "qs_pg:qs_pg_placetype_gp":"Town",
    "qs_pg:woe_adm0":23424950,
    "woe:adm0_id":23424950,
    "woe:name_adm0":"Espa\u00f1a",
    "woe:name_adm1":"Islas Canarias",
    "woe:placetype":"Town",
    "wof:name":"El Abrigo",
    "wof:placetype":"locality"
},
  "geometry": {"coordinates":[-16.59407,28.02905],"type":"Point"}
}