{
  "type": "Feature",
  "properties": {
    "gn:admin1_code":"32",
    "gn:admin3_code":"31158",
    "gn:asciiname":"Villanueva de Longuida",
    "gn:country_code":"ES",
    "gn:dem":501,
    "gn:feature_class":"P",
    "gn:feature_code":"PPL",
    "gn:name":"Villanueva de L\u00f3nguida",
    "gn:population":0,
    "gn:timezone":"Europe/Madrid",
    "iso:country":"ES",
    "wof:name":"Villanueva de Longuida",
    "wof:placetype":"locality"
},
  "geometry": {"coordinates":[-1.36007,42.75596],"type":"Point"}
}