{
  "type": "Feature",
  "properties": {
    "gn:admin1_code":"54",
    "gn:admin2_code":"GU",
    "gn:admin3_code":"19210",
    "gn:asciiname":"Rienda",
    "gn:country_code":"ES",
    "gn:dem":1015,
    "gn:feature_class":"P",
    "gn:feature_code":"PPL",
    "gn:name":"Rienda",
    "gn:population":0,
    "gn:timezone":"Europe/Madrid",
    "iso:country":"ES",
    "wof:name":"Rienda",
    "wof:placetype":"locality"
},
  "geometry": {"coordinates":[-2.71649,41.2277],"type":"Point"}
}