{
  "type": "Feature",
  "properties": {
    "gn:admin1_code":"51",
    "gn:admin2_code":"MA",
    "gn:admin3_code":"29082",
    "gn:asciiname":"Rincon de la Victoria",
    "gn:country_code":"ES",
    "gn:dem":11,
    "gn:feature_class":"P",
    "gn:feature_code":"PPLA3",
    "gn:name":"Rinc\u00f3n de la Victoria",
    "gn:population":38666,
    "gn:timezone":"Europe/Madrid",
    "iso:country":"ES",
    "name:ara_x_preferred":[
        "\u0631\u064a\u0646\u0643\u0648\u0646 \u062f\u064a \u0644\u0627 \u0641\u064a\u0643\u062a\u0648\u0631\u064a\u0627"
    ],
    "name:kaz_x_preferred":[
        "\u0420\u0438\u043d\u043a\u043e\u043d-\u0434\u0435-\u043b\u0430-\u0412\u0438\u043a\u0442\u043e\u0440\u0438\u0430"
    ],
    "name:lat_x_preferred":[
        "Bezmiliana"
    ],
    "name:rus_x_preferred":[
        "\u0420\u0438\u043d\u043a\u043e\u043d-\u0434\u0435-\u043b\u0430-\u0412\u0438\u043a\u0442\u043e\u0440\u0438\u044f"
    ],
    "name:rus_x_variant":[
        "\u0420\u0438\u043d\u043a\u043e\u043d-\u0434\u0435-\u043b\u0430-\u0412\u0438\u043a\u0442\u043e\u0440\u0438\u0430"
    ],
    "name:ukr_x_preferred":[
        "\u0420\u0456\u043d\u043a\u043e\u043d-\u0434\u0435-\u043b\u0430-\u0412\u0456\u043a\u0442\u043e\u0440\u0456\u044f"
    ],
    "name:zho_x_preferred":[
        "\u6797\u5b54\u5fb7\u62c9\u7ef4\u514b\u6258\u91cc\u4e9a"
    ],
    "wof:name":"Rincon de la Victoria",
    "wof:placetype":"locality",
    "wof:population":38666
},
  "geometry": {"coordinates":[-4.27583,36.71715],"type":"Point"}
}