{
  "type": "Feature",
  "properties": {
    "gn:admin1_code":"53",
    "gn:admin2_code":"TF",
    "gn:admin3_code":"38019",
    "gn:asciiname":"Alcala",
    "gn:country_code":"ES",
    "gn:dem":15,
    "gn:feature_class":"P",
    "gn:feature_code":"PPL",
    "gn:name":"Alcal\u00e1",
    "gn:population":0,
    "gn:timezone":"Atlantic/Canary",
    "iso:country":"ES",
    "wof:name":"Alcala",
    "wof:placetype":"locality"
},
  "geometry": {"coordinates":[-16.82779,28.20201],"type":"Point"}
}