{
  "type": "Feature",
  "properties": {
    "gn:admin1_code":"58",
    "gn:admin2_code":"C",
    "gn:admin3_code":"15092",
    "gn:asciiname":"Padreiro de Abajo",
    "gn:country_code":"ES",
    "gn:dem":314,
    "gn:feature_class":"P",
    "gn:feature_code":"PPL",
    "gn:name":"Padreiro de Abajo",
    "gn:population":0,
    "gn:timezone":"Europe/Madrid",
    "iso:country":"ES",
    "wof:name":"Padreiro de Abajo",
    "wof:placetype":"locality"
},
  "geometry": {"coordinates":[-9.03792,43.04545],"type":"Point"}
}