{
  "type": "Feature",
  "properties": {
    "gn:admin1_code":"55",
    "gn:admin2_code":"LE",
    "gn:admin3_code":"24198",
    "gn:asciiname":"Villasinde",
    "gn:country_code":"ES",
    "gn:dem":895,
    "gn:feature_class":"P",
    "gn:feature_code":"PPL",
    "gn:name":"Villasinde",
    "gn:population":0,
    "gn:timezone":"Europe/Madrid",
    "iso:country":"ES",
    "wof:name":"Villasinde",
    "wof:placetype":"locality"
},
  "geometry": {"coordinates":[-6.95431,42.64816],"type":"Point"}
}