{
  "type": "Feature",
  "properties": {
    "gn:admin1_code":"51",
    "gn:admin2_code":"SE",
    "gn:admin3_code":"41068",
    "gn:asciiname":"Navarredonda",
    "gn:country_code":"ES",
    "gn:dem":599,
    "gn:feature_class":"P",
    "gn:feature_code":"PPL",
    "gn:name":"Navarredonda",
    "gn:population":0,
    "gn:timezone":"Europe/Madrid",
    "iso:country":"ES",
    "wof:name":"Navarredonda",
    "wof:placetype":"locality"
},
  "geometry": {"coordinates":[-5.08333,37.15],"type":"Point"}
}