{
  "type": "Feature",
  "properties": {
    "gn:admin1_code":"52",
    "gn:admin2_code":"HU",
    "gn:admin3_code":"22908",
    "gn:asciiname":"Costean",
    "gn:country_code":"ES",
    "gn:dem":437,
    "gn:feature_class":"P",
    "gn:feature_code":"PPL",
    "gn:name":"Coste\u00e1n",
    "gn:population":0,
    "gn:timezone":"Europe/Madrid",
    "iso:country":"ES",
    "name:und_x_variant":[
        "Caser\u00edo Coste\u00e1n",
        "Coste\u00e1n"
    ],
    "wof:name":"Costean",
    "wof:placetype":"locality"
},
  "geometry": {"coordinates":[0.17631,42.08624],"type":"Point"}
}