{
  "type": "Feature",
  "properties": {
    "gn:admin1_code":"58",
    "gn:admin2_code":"LU",
    "gn:admin3_code":"27011",
    "gn:asciiname":"Couso",
    "gn:country_code":"ES",
    "gn:dem":839,
    "gn:feature_class":"P",
    "gn:feature_code":"PPL",
    "gn:name":"Couso",
    "gn:population":0,
    "gn:timezone":"Europe/Madrid",
    "iso:country":"ES",
    "wof:name":"Couso",
    "wof:placetype":"locality"
},
  "geometry": {"coordinates":[-7.25,42.96667],"type":"Point"}
}