{
  "type": "Feature",
  "properties": {
    "gn:admin1_code":"51",
    "gn:admin2_code":"J",
    "gn:admin3_code":"23904",
    "gn:asciiname":"Vites",
    "gn:country_code":"ES",
    "gn:dem":1077,
    "gn:feature_class":"P",
    "gn:feature_code":"PPL",
    "gn:name":"Vites",
    "gn:population":0,
    "gn:timezone":"Europe/Madrid",
    "iso:country":"ES",
    "name:und_x_variant":[
        "Caser\u00edo Vites",
        "Vites"
    ],
    "wof:name":"Vites",
    "wof:placetype":"locality"
},
  "geometry": {"coordinates":[-2.4773,38.16389],"type":"Point"}
}