{
  "type": "Feature",
  "properties": {
    "iso:country":"ES",
    "name:eng_x_preferred":[
        "Nuevo San Andres 2"
    ],
    "name:spa_x_preferred":[
        "Nuevo San Andr\u00e9s 2"
    ],
    "wof:name":"Nuevo San Andres 2",
    "wof:placetype":"neighbourhood"
},
  "geometry": {"coordinates":[-4.45718963538855,36.69849284306328],"type":"Point"}
}