{
  "type": "Feature",
  "properties": {
    "gn:country":"ES",
    "gn:fcode":"PPLA3",
    "gn:population":106,
    "iso:country":"ES",
    "name:arg_x_preferred":[
        "Bonansa"
    ],
    "name:ast_x_preferred":[
        "Bonansa"
    ],
    "name:cat_x_preferred":[
        "Bonansa"
    ],
    "name:ceb_x_preferred":[
        "Bonansa"
    ],
    "name:deu_x_preferred":[
        "Bonansa"
    ],
    "name:eng_x_preferred":[
        "Bonansa"
    ],
    "name:eus_x_preferred":[
        "Bonansa"
    ],
    "name:fra_x_preferred":[
        "Bonansa"
    ],
    "name:hak_x_preferred":[
        "Bonansa"
    ],
    "name:hun_x_preferred":[
        "Bonansa"
    ],
    "name:ita_x_preferred":[
        "Bonansa"
    ],
    "name:msa_x_preferred":[
        "Bonansa"
    ],
    "name:nan_x_preferred":[
        "Bonansa"
    ],
    "name:nld_x_preferred":[
        "Bonansa"
    ],
    "name:oci_x_preferred":[
        "Bonansa"
    ],
    "name:pol_x_preferred":[
        "Bonansa"
    ],
    "name:por_x_preferred":[
        "Bonansa"
    ],
    "name:rus_x_preferred":[
        "\u0411\u043e\u043d\u0430\u043d\u0441\u0430"
    ],
    "name:spa_x_preferred":[
        "Bonansa"
    ],
    "name:swe_x_preferred":[
        "Bonansa"
    ],
    "name:ukr_x_preferred":[
        "\u0411\u043e\u043d\u0430\u043d\u0441\u0430"
    ],
    "name:uzb_x_preferred":[
        "Bonansa"
    ],
    "name:vie_x_preferred":[
        "Bonansa"
    ],
    "name:war_x_preferred":[
        "Bonansa"
    ],
    "name:zho_x_preferred":[
        "\u535a\u5357\u8428"
    ],
    "qs_pg:aaroncc":"ES",
    "qs_pg:gn_country":"ES",
    "qs_pg:gn_fcode":"PPLA3",
    "qs_pg:gn_pop":106,
    "qs_pg:name":"Bonansa",
    "qs_pg:name_adm0":"Espa\u00f1a",
    "qs_pg:name_adm1":"Arag\u00f3n",
    "qs_pg:photos":30,
    "qs_pg:photos_1k":6,
    "qs_pg:photos_9k":1,
    "qs_pg:photos_9r":2,
    "qs_pg:photos_all":30,
    "qs_pg:photos_sr":2,
    "qs_pg:pop_sr":1,
    "qs_pg:qs_pg_placetype":"locality",
    "qs_pg:qs_pg_placetype_gp":"Town",
    "qs_pg:woe_adm0":23424950,
    "woe:adm0_id":23424950,
    "woe:name_adm0":"Espa\u00f1a",
    "woe:name_adm1":"Arag\u00f3n",
    "woe:placetype":"Town",
    "wof:name":"Bonansa",
    "wof:placetype":"locality",
    "wof:population":106
},
  "geometry": {"coordinates":[0.66692,42.42691],"type":"Point"}
}