{
  "type": "Feature",
  "properties": {
    "gn:gn_country":"ES",
    "gn:gn_fcode":"ADM3",
    "gn:gn_pop":853,
    "gn:population":848,
    "iso:country":"ES",
    "name:ara_x_preferred":[
        "\u0645\u064a\u0631\u0627\u064a\u0646\u062f\u0627\u062f \u062f\u064a \u0645\u0648\u0646\u062a\u0627\u064a\u062c\u0627"
    ],
    "name:arg_x_preferred":[
        "Merindad de Montija"
    ],
    "name:cat_x_preferred":[
        "Merindad de Montija"
    ],
    "name:eng_x_preferred":[
        "Merindad de Montija"
    ],
    "name:eus_x_preferred":[
        "Merindad de Montija"
    ],
    "name:fas_x_preferred":[
        "\u0645\u0631\u06cc\u0646\u062f\u0627\u062f \u062f \u0645\u0646\u062a\u06cc\u062e\u0627"
    ],
    "name:fra_x_preferred":[
        "Merindad de Montija"
    ],
    "name:glg_x_preferred":[
        "Merindad de Montija"
    ],
    "name:haw_x_preferred":[
        "Merindad de Montija"
    ],
    "name:hun_x_preferred":[
        "Merindad de Montija"
    ],
    "name:ina_x_preferred":[
        "Merindad de Montija"
    ],
    "name:ita_x_preferred":[
        "Merindad de Montija"
    ],
    "name:lad_x_preferred":[
        "Merindad de Montija"
    ],
    "name:msa_x_preferred":[
        "Merindad de Montija"
    ],
    "name:nan_x_preferred":[
        "Merindad de Montija"
    ],
    "name:nld_x_preferred":[
        "Merindad de Montija"
    ],
    "name:oci_x_preferred":[
        "Merindad de Montija"
    ],
    "name:pol_x_preferred":[
        "Merindad de Montija"
    ],
    "name:por_x_preferred":[
        "Merindad de Montija"
    ],
    "name:rus_x_preferred":[
        "\u041c\u0435\u0440\u0438\u043d\u0434\u0430\u0434-\u0434\u0435-\u041c\u043e\u043d\u0442\u0438\u0445\u0430"
    ],
    "name:spa_x_preferred":[
        "Merindad de Montija"
    ],
    "name:swe_x_preferred":[
        "Merindad de Montija"
    ],
    "name:ukr_x_preferred":[
        "\u041c\u0435\u0440\u0456\u043d\u0434\u0430\u0434-\u0434\u0435-\u041c\u043e\u043d\u0442\u0456\u0445\u0430"
    ],
    "name:uzb_x_preferred":[
        "Merindad de Montija"
    ],
    "name:vie_x_preferred":[
        "Merindad de Montija"
    ],
    "name:war_x_preferred":[
        "Merindad de Montija"
    ],
    "name:zho_x_preferred":[
        "\u6885\u6797\u8fbe\u5fb7\u8499\u8482\u54c8"
    ],
    "qs_pg:aaroncc":"ES",
    "qs_pg:gn_country":"ES",
    "qs_pg:gn_fcode":"ADM3",
    "qs_pg:gn_pop":853,
    "qs_pg:name":"Merindad de Montija",
    "qs_pg:name_adm0":"Espa\u00f1a",
    "qs_pg:name_adm1":"Castilla y Le\u00f3n",
    "qs_pg:photos_9r":0,
    "qs_pg:photos_sr":0,
    "qs_pg:pop_sr":2,
    "qs_pg:qs_pg_placetype":"locality",
    "qs_pg:qs_pg_placetype_gp":"Town",
    "qs_pg:woe_adm0":23424950,
    "woe:adm0_id":23424950,
    "woe:name_adm0":"Espa\u00f1a",
    "woe:name_adm1":"Castilla y Le\u00f3n",
    "woe:placetype":"Town",
    "wof:name":"Merindad de Montija",
    "wof:placetype":"locality",
    "wof:population":848
},
  "geometry": {"coordinates":[-3.48217,43.06106],"type":"Point"}
}