{
  "type": "Feature",
  "properties": {
    "gn:admin1_code":"56",
    "gn:admin2_code":"B",
    "gn:admin3_code":"08145",
    "gn:asciiname":"Viladellops",
    "gn:country_code":"ES",
    "gn:dem":182,
    "gn:feature_class":"P",
    "gn:feature_code":"PPL",
    "gn:name":"Viladellops",
    "gn:population":0,
    "gn:timezone":"Europe/Madrid",
    "iso:country":"ES",
    "wof:name":"Viladellops",
    "wof:placetype":"locality"
},
  "geometry": {"coordinates":[1.73743,41.30599],"type":"Point"}
}