{
  "type": "Feature",
  "properties": {
    "gn:admin1_code":"57",
    "gn:admin2_code":"CC",
    "gn:admin3_code":"10081",
    "gn:asciiname":"Torre de Paniagua",
    "gn:country_code":"ES",
    "gn:dem":398,
    "gn:feature_class":"P",
    "gn:feature_code":"PPL",
    "gn:name":"Torre de Paniagua",
    "gn:population":0,
    "gn:timezone":"Europe/Madrid",
    "iso:country":"ES",
    "name:und_x_variant":[
        "Caser\u00edo Torre de Paniagua",
        "Torre de Paniagua"
    ],
    "wof:name":"Torre de Paniagua",
    "wof:placetype":"locality"
},
  "geometry": {"coordinates":[-5.9437,40.00147],"type":"Point"}
}