{
  "type": "Feature",
  "properties": {
    "gn:admin1_code":"58",
    "gn:admin2_code":"LU",
    "gn:admin3_code":"27048",
    "gn:asciiname":"Aldeguer",
    "gn:country_code":"ES",
    "gn:dem":211,
    "gn:feature_class":"P",
    "gn:feature_code":"PPL",
    "gn:name":"Aldeguer",
    "gn:population":0,
    "gn:timezone":"Europe/Madrid",
    "iso:country":"ES",
    "wof:name":"Aldeguer",
    "wof:placetype":"locality"
},
  "geometry": {"coordinates":[-7.17701,43.32615],"type":"Point"}
}