{
  "type": "Feature",
  "properties": {
    "gn:admin1_code":"53",
    "gn:admin2_code":"TF",
    "gn:admin3_code":"38012",
    "gn:asciiname":"Zarza",
    "gn:country_code":"ES",
    "gn:dem":750,
    "gn:feature_class":"P",
    "gn:feature_code":"PPL",
    "gn:name":"Zarza",
    "gn:population":0,
    "gn:timezone":"Atlantic/Canary",
    "iso:country":"ES",
    "name:ceb_x_preferred":[
        "Zarza"
    ],
    "name:deu_x_preferred":[
        "Zarza"
    ],
    "name:fra_x_preferred":[
        "Zarza"
    ],
    "name:ron_x_preferred":[
        "Zarza"
    ],
    "name:rus_x_preferred":[
        "\u0421\u0430\u0440\u0441\u0430"
    ],
    "name:sco_x_preferred":[
        "Zarza"
    ],
    "name:spa_x_preferred":[
        "Zarza"
    ],
    "name:swe_x_preferred":[
        "Zarza"
    ],
    "wof:name":"Zarza",
    "wof:placetype":"locality"
},
  "geometry": {"coordinates":[-16.4644,28.23561],"type":"Point"}
}