{
  "type": "Feature",
  "properties": {
    "gn:admin1_code":"60",
    "gn:admin2_code":"V",
    "gn:admin3_code":"46161.0",
    "gn:asciiname":"Marines del llano",
    "gn:country_code":"ES",
    "gn:dem":218,
    "gn:feature_class":"P",
    "gn:feature_code":"PPL",
    "gn:name":"Marines del llano",
    "gn:population":0,
    "gn:timezone":"Europe/Madrid",
    "iso:country":"ES",
    "wof:name":"Marines del llano",
    "wof:placetype":"locality"
},
  "geometry": {"coordinates":[-0.56123,39.67534000000001],"type":"Point"}
}