{
  "type": "Feature",
  "properties": {
    "gn:admin1_code":"55",
    "gn:admin2_code":"P",
    "gn:admin3_code":"34192",
    "gn:asciiname":"Robladillo de Ucieza",
    "gn:country_code":"ES",
    "gn:dem":839,
    "gn:feature_class":"P",
    "gn:feature_code":"PPL",
    "gn:name":"Robladillo de Ucieza",
    "gn:population":0,
    "gn:timezone":"Europe/Madrid",
    "iso:country":"ES",
    "wof:name":"Robladillo de Ucieza",
    "wof:placetype":"locality"
},
  "geometry": {"coordinates":[-4.57546,42.39888],"type":"Point"}
}