{
  "type": "Feature",
  "properties": {
    "gn:population":1152,
    "iso:country":"ES",
    "name:ara_x_preferred":[
        "\u0645\u0648\u0645\u0628\u064a\u0644\u062a\u0631\u0627\u0646"
    ],
    "name:ast_x_preferred":[
        "Mombeltr\u00e1n"
    ],
    "name:azb_x_preferred":[
        "\u0645\u0645\u0628\u0644\u062a\u0631\u0627\u0646"
    ],
    "name:cat_x_preferred":[
        "Mombeltr\u00e1n"
    ],
    "name:ceb_x_preferred":[
        "Mombeltr\u00e1n"
    ],
    "name:dan_x_preferred":[
        "Mombeltr\u00e1n"
    ],
    "name:deu_x_preferred":[
        "Mombeltr\u00e1n"
    ],
    "name:eng_x_preferred":[
        "Mombeltr\u00e1n"
    ],
    "name:eus_x_preferred":[
        "Mombeltr\u00e1n"
    ],
    "name:fas_x_preferred":[
        "\u0645\u0645\u0628\u0644\u062a\u0631\u0627\u0646"
    ],
    "name:fra_x_preferred":[
        "Mombeltr\u00e1n"
    ],
    "name:hun_x_preferred":[
        "Mombeltr\u00e1n"
    ],
    "name:ina_x_preferred":[
        "Mombeltr\u00e1n"
    ],
    "name:ita_x_preferred":[
        "Mombeltr\u00e1n"
    ],
    "name:kaz_x_preferred":[
        "\u041c\u043e\u043c\u0431\u0435\u043b\u044c\u0442\u0440\u0430\u043d"
    ],
    "name:mkd_x_preferred":[
        "\u041c\u043e\u043c\u0431\u0435\u043b\u0442\u0440\u0430\u043d"
    ],
    "name:msa_x_preferred":[
        "Mombeltr\u00e1n"
    ],
    "name:nld_x_preferred":[
        "Mombeltr\u00e1n"
    ],
    "name:oci_x_preferred":[
        "Mombeltr\u00e1n"
    ],
    "name:pol_x_preferred":[
        "Mombeltr\u00e1n"
    ],
    "name:por_x_preferred":[
        "Mombeltr\u00e1n"
    ],
    "name:rus_x_preferred":[
        "\u041c\u043e\u043c\u0431\u0435\u043b\u044c\u0442\u0440\u0430\u043d"
    ],
    "name:spa_x_colloquial":[
        "Mombeltran"
    ],
    "name:spa_x_preferred":[
        "Mombeltr\u00e1n"
    ],
    "name:swe_x_preferred":[
        "Mombeltr\u00e1n"
    ],
    "name:ukr_x_preferred":[
        "\u041c\u043e\u043c\u0431\u0435\u043b\u044c\u0442\u0440\u0430\u043d"
    ],
    "name:uzb_x_preferred":[
        "Mombeltr\u00e1n"
    ],
    "name:vie_x_preferred":[
        "Mombeltr\u00e1n"
    ],
    "name:war_x_preferred":[
        "Mombeltr\u00e1n"
    ],
    "name:zho_x_preferred":[
        "\u8499\u97e6\u5c14\u7279\u5170"
    ],
    "qs:a0":"Espa\u00f1a",
    "qs:a1":"*Avila",
    "qs:a1r":"0Castilla y Le\u00f3n",
    "qs:adm0":"Espa\u00f1a",
    "qs:la_lc":"*",
    "qs:level":"locality",
    "qs:loc":"Mombeltr\u00e1n",
    "qs:loc_alt":"Mombeltran",
    "qs:pop":0,
    "qs:type":"buffered point",
    "wd:wordcount":45,
    "wof:lang":[
        "spa"
    ],
    "wof:name":"Mombeltr\u00e1n",
    "wof:placetype":"locality",
    "wof:population":1152
},
  "geometry": {"coordinates":[-5.017915,40.260124],"type":"Point"}
}