{
  "type": "Feature",
  "properties": {
    "gn:admin1_code":"55",
    "gn:admin2_code":"BU",
    "gn:admin3_code":"09215",
    "gn:asciiname":"Hornillayuso",
    "gn:country_code":"ES",
    "gn:dem":635,
    "gn:feature_class":"P",
    "gn:feature_code":"PPL",
    "gn:name":"Hornillayuso",
    "gn:population":0,
    "gn:timezone":"Europe/Madrid",
    "iso:country":"ES",
    "wof:name":"Hornillayuso",
    "wof:placetype":"locality"
},
  "geometry": {"coordinates":[-3.59596,43.01607],"type":"Point"}
}