{
  "type": "Feature",
  "properties": {
    "gn:admin1_code":"56",
    "gn:admin2_code":"L",
    "gn:admin3_code":"25169",
    "gn:asciiname":"l' Albi",
    "gn:country_code":"ES",
    "gn:dem":524,
    "gn:feature_class":"P",
    "gn:feature_code":"PPL",
    "gn:name":"l' Albi",
    "gn:population":0,
    "gn:timezone":"Europe/Madrid",
    "iso:country":"ES",
    "name:cat_x_preferred":[
        "l' Albi"
    ],
    "name:spa_x_preferred":[
        "Albi"
    ],
    "name:und_x_variant":[
        "Alb\u00ed"
    ],
    "wof:name":"l' Albi",
    "wof:placetype":"locality"
},
  "geometry": {"coordinates":[0.93333,41.41667],"type":"Point"}
}