{
  "type": "Feature",
  "properties": {
    "gn:admin1_code":"56",
    "gn:admin2_code":"L",
    "gn:admin3_code":"25169",
    "gn:asciiname":"l' Albi",
    "gn:country_code":"ES",
    "gn:dem":524,
    "gn:feature_class":"P",
    "gn:feature_code":"PPL",
    "gn:name":"l' Albi",
    "gn:population":0,
    "gn:timezone":"Europe/Madrid",
    "iso:country":"ES",
    "name:arg_x_preferred":[
        "L'Albi"
    ],
    "name:cat_x_preferred":[
        "l' Albi"
    ],
    "name:cat_x_variant":[
        "L'Albi"
    ],
    "name:ceb_x_preferred":[
        "L'Albi"
    ],
    "name:eus_x_preferred":[
        "L'Albi"
    ],
    "name:fra_x_preferred":[
        "L'Albi"
    ],
    "name:hun_x_preferred":[
        "L\u2019Albi"
    ],
    "name:hye_x_preferred":[
        "\u053c\u0561 \u0531\u056c\u0562\u056b"
    ],
    "name:ita_x_preferred":[
        "L'Albi"
    ],
    "name:msa_x_preferred":[
        "L'Albi"
    ],
    "name:oci_x_preferred":[
        "L'Albi"
    ],
    "name:pol_x_preferred":[
        "L\u2019Albi"
    ],
    "name:por_x_preferred":[
        "L'Albi"
    ],
    "name:ron_x_preferred":[
        "L'Albi"
    ],
    "name:rus_x_preferred":[
        "\u041b\u0430-\u0410\u043b\u044c\u0431\u0438"
    ],
    "name:spa_x_preferred":[
        "Albi"
    ],
    "name:spa_x_variant":[
        "Alb\u00ed"
    ],
    "name:sqi_x_preferred":[
        "L'Albi"
    ],
    "name:swe_x_preferred":[
        "L'Albi"
    ],
    "name:uzb_x_preferred":[
        "Albi"
    ],
    "name:vie_x_preferred":[
        "L'Albi"
    ],
    "name:war_x_preferred":[
        "L'Albi"
    ],
    "name:zho_x_preferred":[
        "\u62c9\u5c14\u7ef4"
    ],
    "wof:name":"l' Albi",
    "wof:placetype":"locality"
},
  "geometry": {"coordinates":[0.93333,41.41667],"type":"Point"}
}