{
  "type": "Feature",
  "properties": {
    "gn:country":"ES",
    "gn:fcode":"PPL",
    "gn:population":108,
    "iso:country":"ES",
    "name:ara_x_preferred":[
        "\u0644\u0648\u0633 \u064a\u0627\u0646\u0648\u0633 \u062f\u064a \u062a\u0648\u0631\u0645\u064a\u0633"
    ],
    "name:azb_x_preferred":[
        "\u0644\u0633 \u06cc\u0627\u0646\u0648\u0633 \u062f\u062a\u0648\u0631\u0645\u0633"
    ],
    "name:cat_x_preferred":[
        "Los Llanos de Tormes"
    ],
    "name:deu_x_preferred":[
        "Los Llanos de Tormes"
    ],
    "name:eng_x_preferred":[
        "Los Llanos de Tormes"
    ],
    "name:eus_x_preferred":[
        "Los Llanos de Tormes"
    ],
    "name:fas_x_preferred":[
        "\u0644\u0633 \u06cc\u0627\u0646\u0648\u0633 \u062f\u062a\u0648\u0631\u0645\u0633"
    ],
    "name:fra_x_preferred":[
        "Los Llanos de Tormes"
    ],
    "name:hun_x_preferred":[
        "Los Llanos de Tormes"
    ],
    "name:ina_x_preferred":[
        "Los Llanos de Tormes"
    ],
    "name:ita_x_preferred":[
        "Los Llanos de Tormes"
    ],
    "name:kaz_x_preferred":[
        "\u041b\u043e\u0441-\u041b\u044c\u044f\u043d\u043e\u0441-\u0434\u0435-\u0422\u043e\u0440\u043c\u0435\u0441"
    ],
    "name:mkd_x_preferred":[
        "\u041b\u043e\u0441 \u0409\u0430\u043d\u043e\u0441 \u0434\u0435 \u0422\u043e\u0440\u043c\u0435\u0441"
    ],
    "name:msa_x_preferred":[
        "Los Llanos de Tormes"
    ],
    "name:nld_x_preferred":[
        "Los Llanos de Tormes"
    ],
    "name:oci_x_preferred":[
        "Los Llanos de Tormes"
    ],
    "name:pol_x_preferred":[
        "Los Llanos de Tormes"
    ],
    "name:por_x_preferred":[
        "Los Llanos de Tormes"
    ],
    "name:rus_x_preferred":[
        "\u041b\u043e\u0441-\u041b\u044c\u044f\u043d\u043e\u0441-\u0434\u0435-\u0422\u043e\u0440\u043c\u0435\u0441"
    ],
    "name:spa_x_preferred":[
        "Los Llanos de Tormes"
    ],
    "name:swe_x_preferred":[
        "Los Llanos de Tormes"
    ],
    "name:ukr_x_preferred":[
        "\u041b\u043e\u0441-\u041b\u044c\u044f\u043d\u043e\u0441-\u0434\u0435-\u0422\u043e\u0440\u043c\u0435\u0441"
    ],
    "name:uzb_x_preferred":[
        "Los Llanos de Tormes"
    ],
    "name:vie_x_preferred":[
        "Los Llanos de Tormes"
    ],
    "name:war_x_preferred":[
        "Los Llanos de Tormes"
    ],
    "name:zho_x_preferred":[
        "\u6d1b\u65af\u5229\u4e9a\u8bfa\u65af\u5fb7\u6258\u5c14\u6885\u65af"
    ],
    "qs_pg:aaroncc":"ES",
    "qs_pg:gn_country":"ES",
    "qs_pg:gn_fcode":"PPL",
    "qs_pg:gn_pop":108,
    "qs_pg:name":"Los Llanos de Tormes",
    "qs_pg:name_adm0":"Espa\u00f1a",
    "qs_pg:name_adm1":"Castilla y Le\u00f3n",
    "qs_pg:photos_9k":1,
    "qs_pg:photos_9r":1,
    "qs_pg:photos_all":1,
    "qs_pg:photos_sr":0,
    "qs_pg:pop_sr":1,
    "qs_pg:qs_pg_placetype":"locality",
    "qs_pg:qs_pg_placetype_gp":"Town",
    "qs_pg:woe_adm0":23424950,
    "woe:adm0_id":23424950,
    "woe:name_adm0":"Espa\u00f1a",
    "woe:name_adm1":"Castilla y Le\u00f3n",
    "woe:placetype":"Town",
    "wof:name":"Los Llanos de Tormes",
    "wof:placetype":"locality",
    "wof:population":108
},
  "geometry": {"coordinates":[-5.50016,40.32773],"type":"Point"}
}