{
  "type": "Feature",
  "properties": {
    "gn:admin1_code":"39",
    "gn:admin2_code":"S",
    "gn:admin3_code":"39094",
    "gn:asciiname":"Moroso",
    "gn:country_code":"ES",
    "gn:dem":1040,
    "gn:feature_class":"P",
    "gn:feature_code":"PPL",
    "gn:name":"Moroso",
    "gn:population":0,
    "gn:timezone":"Europe/Madrid",
    "iso:country":"ES",
    "wof:name":"Moroso",
    "wof:placetype":"locality"
},
  "geometry": {"coordinates":[-4.1074,42.85431],"type":"Point"}
}