{
  "type": "Feature",
  "properties": {
    "gn:admin1_code":"60",
    "gn:admin2_code":"CS",
    "gn:admin3_code":"12124",
    "gn:asciiname":"Les Ramblelles",
    "gn:country_code":"ES",
    "gn:dem":329,
    "gn:feature_class":"P",
    "gn:feature_code":"PPL",
    "gn:name":"Les Ramblelles",
    "gn:population":0,
    "gn:timezone":"Europe/Madrid",
    "iso:country":"ES",
    "name:und_x_variant":[
        "Caser\u00edo Les Ramblelles",
        "Les Ramblelles"
    ],
    "wof:name":"Les Ramblelles",
    "wof:placetype":"locality"
},
  "geometry": {"coordinates":[-0.04416,40.19242],"type":"Point"}
}