{
  "type": "Feature",
  "properties": {
    "gn:admin1_code":"55",
    "gn:admin2_code":"BU",
    "gn:admin3_code":"09219",
    "gn:asciiname":"Suzana",
    "gn:country_code":"ES",
    "gn:dem":480,
    "gn:feature_class":"P",
    "gn:feature_code":"PPL",
    "gn:name":"Suzana",
    "gn:population":0,
    "gn:timezone":"Europe/Madrid",
    "iso:country":"ES",
    "name:bre_x_preferred":[
        "Suzana"
    ],
    "name:hrv_x_preferred":[
        "Suzana"
    ],
    "name:slv_x_preferred":[
        "Suzana"
    ],
    "wof:name":"Suzana",
    "wof:placetype":"locality"
},
  "geometry": {"coordinates":[-2.99003,42.70933],"type":"Point"}
}