{
  "type": "Feature",
  "properties": {
    "gn:admin1_code":"51",
    "gn:admin2_code":"CO",
    "gn:admin3_code":"14057",
    "gn:asciiname":"Los Algarbes",
    "gn:country_code":"ES",
    "gn:dem":220,
    "gn:feature_class":"P",
    "gn:feature_code":"PPL",
    "gn:name":"Los Algarbes",
    "gn:population":0,
    "gn:timezone":"Europe/Madrid",
    "iso:country":"ES",
    "wof:name":"Los Algarbes",
    "wof:placetype":"locality"
},
  "geometry": {"coordinates":[-4.966,37.6078],"type":"Point"}
}