{
  "type": "Feature",
  "properties": {
    "gn:gn_country":"ES",
    "gn:gn_fcode":"PPLA3",
    "gn:gn_pop":0,
    "iso:country":"ES",
    "name:alb_x_preferred":[
        "Sant Pere de Vilamajor"
    ],
    "name:ara_x_preferred":[
        "\u0633\u0627\u0646 \u0628\u064a\u062f\u0631\u0648 \u062f\u064a \u0641\u064a\u0644\u0627\u0645\u0627\u062e\u0648\u0631"
    ],
    "name:arg_x_preferred":[
        "Sant Pere de Vilamajor"
    ],
    "name:baq_x_preferred":[
        "Sant Pere de Vilamajor"
    ],
    "name:cat_x_preferred":[
        "Sant Pere de Vilamajor"
    ],
    "name:chi_x_preferred":[
        "\u6851\u7279\u4f69\u96f7\u5fb7\u7ef4\u62c9\u9a6c\u970d\u5c14"
    ],
    "name:dut_x_preferred":[
        "Sant Pere de Vilamajor"
    ],
    "name:eng_x_preferred":[
        "Sant Pere de Vilamajor"
    ],
    "name:fre_x_preferred":[
        "Sant Pere de Vilamajor"
    ],
    "name:ger_x_preferred":[
        "San Pedro de Vilamajor"
    ],
    "name:glg_x_preferred":[
        "Sant Pere de Vilamajor"
    ],
    "name:hun_x_preferred":[
        "Sant Pere de Vilamajor"
    ],
    "name:ita_x_preferred":[
        "Sant Pere de Vilamajor"
    ],
    "name:lat_x_preferred":[
        "Sant Pere de Vilamajor"
    ],
    "name:oci_x_preferred":[
        "Sant Pere de Vilamajor"
    ],
    "name:pol_x_preferred":[
        "Sant Pere de Vilamajor"
    ],
    "name:por_x_preferred":[
        "Sant Pere de Vilamajor"
    ],
    "name:sco_x_preferred":[
        "Sant Pere de Vilamajor"
    ],
    "name:spa_x_preferred":[
        "San Pedro de Vilamajor"
    ],
    "name:swe_x_preferred":[
        "Sant Pere de Vilamajor"
    ],
    "name:ukr_x_preferred":[
        "\u0421\u0430\u043d-\u041f\u0435\u0440\u0430-\u0434\u0430-\u0411\u0456\u043b\u0430\u043c\u0430\u0436\u043e"
    ],
    "name:unk_x_variant":[
        "San Pedro de Vilamajor"
    ],
    "name:war_x_preferred":[
        "Sant Pere de Vilamajor"
    ],
    "qs_pg:aaroncc":"ES",
    "qs_pg:gn_country":"ES",
    "qs_pg:gn_fcode":"PPLA3",
    "qs_pg:gn_pop":0,
    "qs_pg:name":"Sant Pere de Vilamajor",
    "qs_pg:name_adm0":"Espa\u00f1a",
    "qs_pg:name_adm1":"Catalunya",
    "qs_pg:photos":272,
    "qs_pg:photos_1k":55,
    "qs_pg:photos_9k":1,
    "qs_pg:photos_9r":4,
    "qs_pg:photos_all":272,
    "qs_pg:photos_sr":5,
    "qs_pg:pop_sr":0,
    "qs_pg:qs_pg_placetype":"locality",
    "qs_pg:qs_pg_placetype_gp":"Town",
    "qs_pg:woe_adm0":23424950,
    "woe:adm0_id":23424950,
    "woe:name_adm0":"Espa\u00f1a",
    "woe:name_adm1":"Catalunya",
    "woe:placetype":"Town",
    "wof:name":"Sant Pere de Vilamajor",
    "wof:placetype":"locality"
},
  "geometry": {"coordinates":[2.38333,41.68333],"type":"Point"}
}