{
  "type": "Feature",
  "properties": {
    "gn:admin1_code":"34",
    "gn:admin2_code":"O",
    "gn:admin3_code":"33044",
    "gn:asciiname":"Prados",
    "gn:cc2":"ES",
    "gn:country_code":"ES",
    "gn:dem":188,
    "gn:feature_class":"P",
    "gn:feature_code":"PPL",
    "gn:name":"Prados",
    "gn:population":0,
    "gn:timezone":"Europe/Madrid",
    "iso:country":"ES",
    "name:und_x_variant":[
        "San Juli\u00e1n",
        "San Juli\u00e1n de los Prados",
        "Prados"
    ],
    "wof:name":"Prados",
    "wof:placetype":"locality"
},
  "geometry": {"coordinates":[-5.81667,43.36667],"type":"Point"}
}