{
  "type": "Feature",
  "properties": {
    "gn:admin1_code":"54",
    "gn:admin2_code":"AB",
    "gn:admin3_code":"02060",
    "gn:asciiname":"Fontanar de las Vinas",
    "gn:country_code":"ES",
    "gn:dem":1010,
    "gn:feature_class":"P",
    "gn:feature_code":"PPL",
    "gn:name":"Fontanar de las Vi\u00f1as",
    "gn:population":0,
    "gn:timezone":"Europe/Madrid",
    "iso:country":"ES",
    "name:und_x_variant":[
        "Fontanar de las Vi\u00f1as"
    ],
    "wof:name":"Fontanar de las Vinas",
    "wof:placetype":"locality"
},
  "geometry": {"coordinates":[-2.01959,38.67725],"type":"Point"}
}