{
  "type": "Feature",
  "properties": {
    "gn:admin1_code":"57",
    "gn:admin2_code":"CC",
    "gn:admin3_code":"10203",
    "gn:asciiname":"La Borrega",
    "gn:country_code":"ES",
    "gn:dem":461,
    "gn:feature_class":"P",
    "gn:feature_code":"PPL",
    "gn:name":"La Borrega",
    "gn:population":0,
    "gn:timezone":"Europe/Madrid",
    "iso:country":"ES",
    "wof:name":"La Borrega",
    "wof:placetype":"locality"
},
  "geometry": {"coordinates":[-7.21667,39.31667],"type":"Point"}
}