{
  "type": "Feature",
  "properties": {
    "gn:gn_country":"ES",
    "gn:gn_fcode":"PPLA3",
    "gn:gn_pop":0,
    "iso:country":"ES",
    "name:ara_x_preferred":[
        "\u0633\u0648\u0646\u062f\u0627\u064a\u0643\u0627"
    ],
    "name:arg_x_preferred":[
        "Sondika"
    ],
    "name:baq_x_preferred":[
        "Sondika"
    ],
    "name:bul_x_preferred":[
        "\u0421\u043e\u043d\u0434\u0438\u043a\u0430"
    ],
    "name:cat_x_preferred":[
        "Sondika"
    ],
    "name:chi_x_preferred":[
        "\u677e\u8fea\u5361"
    ],
    "name:dut_x_preferred":[
        "Sondika"
    ],
    "name:eng_x_preferred":[
        "Sondika"
    ],
    "name:fre_x_preferred":[
        "Sondika"
    ],
    "name:glg_x_preferred":[
        "Sondika"
    ],
    "name:hun_x_preferred":[
        "Sondika"
    ],
    "name:ita_x_preferred":[
        "Sondika"
    ],
    "name:jpn_x_preferred":[
        "\u30bd\u30f3\u30c7\u30a3\u30ab"
    ],
    "name:lat_x_preferred":[
        "Sondica"
    ],
    "name:lit_x_preferred":[
        "Sondika"
    ],
    "name:may_x_preferred":[
        "Sondika"
    ],
    "name:oci_x_preferred":[
        "Sondika"
    ],
    "name:pol_x_preferred":[
        "Sondika"
    ],
    "name:por_x_preferred":[
        "Sondica"
    ],
    "name:rus_x_preferred":[
        "\u0421\u043e\u043d\u0434\u0438\u043a\u0430"
    ],
    "name:sco_x_preferred":[
        "Sondika"
    ],
    "name:spa_x_preferred":[
        "Sondica"
    ],
    "name:swe_x_preferred":[
        "Sondika"
    ],
    "name:ukr_x_preferred":[
        "\u0421\u043e\u043d\u0434\u0456\u043a\u0430"
    ],
    "name:uzb_x_preferred":[
        "Sondica"
    ],
    "name:war_x_preferred":[
        "Sondika"
    ],
    "qs_pg:aaroncc":"ES",
    "qs_pg:gn_country":"ES",
    "qs_pg:gn_fcode":"PPLA3",
    "qs_pg:gn_pop":0,
    "qs_pg:name":"Sondika",
    "qs_pg:name_adm0":"Espa\u00f1a",
    "qs_pg:name_adm1":"Euskadi",
    "qs_pg:photos":158,
    "qs_pg:photos_1k":32,
    "qs_pg:photos_9k":1,
    "qs_pg:photos_9r":4,
    "qs_pg:photos_all":158,
    "qs_pg:photos_sr":4,
    "qs_pg:pop_sr":0,
    "qs_pg:qs_pg_placetype":"locality",
    "qs_pg:qs_pg_placetype_gp":"Town",
    "qs_pg:woe_adm0":23424950,
    "woe:adm0_id":23424950,
    "woe:name_adm0":"Espa\u00f1a",
    "woe:name_adm1":"Euskadi",
    "woe:placetype":"Town",
    "wof:name":"Sondika",
    "wof:placetype":"locality"
},
  "geometry": {"coordinates":[-2.92442,43.3002],"type":"Point"}
}