{
  "type": "Feature",
  "properties": {
    "gn:admin1_code":"34",
    "gn:admin2_code":"O",
    "gn:admin3_code":"33043",
    "gn:asciiname":"Robellada",
    "gn:country_code":"ES",
    "gn:dem":307,
    "gn:feature_class":"P",
    "gn:feature_code":"PPL",
    "gn:name":"Robellada",
    "gn:population":0,
    "gn:timezone":"Europe/Madrid",
    "iso:country":"ES",
    "wof:name":"Robellada",
    "wof:placetype":"locality"
},
  "geometry": {"coordinates":[-4.92368,43.34322],"type":"Point"}
}