{
  "type": "Feature",
  "properties": {
    "iso:country":"ES",
    "wof:name":"Distrito Sur",
    "wof:placetype":"neighbourhood"
},
  "geometry": {"coordinates":[-4.77800246318562,37.86852282336879],"type":"Point"}
}