{
  "type": "Feature",
  "properties": {
    "gn:admin1_code":"55",
    "gn:admin2_code":"BU",
    "gn:admin3_code":"09410",
    "gn:asciiname":"Artieta",
    "gn:country_code":"ES",
    "gn:dem":466,
    "gn:feature_class":"P",
    "gn:feature_code":"PPL",
    "gn:name":"Artieta",
    "gn:population":0,
    "gn:timezone":"Europe/Madrid",
    "iso:country":"ES",
    "wof:name":"Artieta",
    "wof:placetype":"locality"
},
  "geometry": {"coordinates":[-3.18792,43.1164],"type":"Point"}
}