{
  "type": "Feature",
  "properties": {
    "gn:gn_country":"ES",
    "gn:gn_fcode":"PPL",
    "gn:gn_pop":0,
    "iso:country":"ES",
    "qs_pg:aaroncc":"ES",
    "qs_pg:gn_country":"ES",
    "qs_pg:gn_fcode":"PPL",
    "qs_pg:gn_pop":0,
    "qs_pg:name":"Ba\u00f1os de Panticosa",
    "qs_pg:name_adm0":"Espa\u00f1a",
    "qs_pg:name_adm1":"Arag\u00f3n",
    "qs_pg:photos":324,
    "qs_pg:photos_1k":66,
    "qs_pg:photos_9k":1,
    "qs_pg:photos_9r":5,
    "qs_pg:photos_all":324,
    "qs_pg:photos_sr":5,
    "qs_pg:pop_sr":0,
    "qs_pg:qs_pg_placetype":"locality",
    "qs_pg:qs_pg_placetype_gp":"Town",
    "qs_pg:woe_adm0":23424950,
    "woe:adm0_id":23424950,
    "woe:name_adm0":"Espa\u00f1a",
    "woe:name_adm1":"Arag\u00f3n",
    "woe:placetype":"Town",
    "wof:name":"Ba\u00f1os de Panticosa",
    "wof:placetype":"locality"
},
  "geometry": {"coordinates":[-0.23415,42.7605],"type":"Point"}
}