{
  "type": "Feature",
  "properties": {
    "gn:admin1_code":"56",
    "gn:admin2_code":"GI",
    "gn:admin3_code":"17218",
    "gn:asciiname":"Olles",
    "gn:country_code":"ES",
    "gn:dem":152,
    "gn:feature_class":"P",
    "gn:feature_code":"PPL",
    "gn:name":"Oll\u00e9s",
    "gn:population":0,
    "gn:timezone":"Europe/Madrid",
    "iso:country":"ES",
    "wof:name":"Olles",
    "wof:placetype":"locality"
},
  "geometry": {"coordinates":[2.83305,42.15364],"type":"Point"}
}