{
  "type": "Feature",
  "properties": {
    "gn:admin1_code":"56",
    "gn:admin2_code":"GI",
    "gn:admin3_code":"17093",
    "gn:asciiname":"els Hostalets",
    "gn:cc2":"ES",
    "gn:country_code":"ES",
    "gn:dem":41,
    "gn:feature_class":"P",
    "gn:feature_code":"PPL",
    "gn:name":"els Hostalets",
    "gn:population":0,
    "gn:timezone":"Europe/Madrid",
    "iso:country":"ES",
    "name:cat_x_preferred":[
        "els Hostalets"
    ],
    "name:cat_x_variant":[
        "els Hostalets de Llers"
    ],
    "wof:name":"els Hostalets",
    "wof:placetype":"locality"
},
  "geometry": {"coordinates":[2.94468,42.2915],"type":"Point"}
}