{
  "type": "Feature",
  "properties": {
    "gn:admin1_code":"34",
    "gn:admin2_code":"O",
    "gn:admin3_code":"33017",
    "gn:asciiname":"Silvallana",
    "gn:country_code":"ES",
    "gn:dem":98,
    "gn:feature_class":"P",
    "gn:feature_code":"PPL",
    "gn:name":"Silvallana",
    "gn:population":0,
    "gn:timezone":"Europe/Madrid",
    "iso:country":"ES",
    "wof:name":"Silvallana",
    "wof:placetype":"locality"
},
  "geometry": {"coordinates":[-7.01425,43.49916],"type":"Point"}
}