{
  "type": "Feature",
  "properties": {
    "gn:admin1_code":"59",
    "gn:admin2_code":"BI",
    "gn:admin3_code":"48067",
    "gn:asciiname":"Ajuria",
    "gn:country_code":"ES",
    "gn:dem":272,
    "gn:feature_class":"P",
    "gn:feature_code":"PPL",
    "gn:name":"Aiuria",
    "gn:population":0,
    "gn:timezone":"Europe/Madrid",
    "iso:country":"ES",
    "name:eus_x_preferred":[
        "Aiuria"
    ],
    "name:spa_x_preferred":[
        "Ajurias"
    ],
    "wof:name":"Ajuria",
    "wof:placetype":"locality"
},
  "geometry": {"coordinates":[-2.65,43.25],"type":"Point"}
}