{
  "type": "Feature",
  "properties": {
    "gn:gn_country":"ES",
    "gn:gn_fcode":"PPLA3",
    "gn:gn_pop":415,
    "gn:population":415,
    "iso:country":"ES",
    "name:arg_x_preferred":[
        "San Esteban de la Sierra"
    ],
    "name:ast_x_preferred":[
        "San Esteban"
    ],
    "name:baq_x_preferred":[
        "San Esteban de la Sierra"
    ],
    "name:cat_x_preferred":[
        "San Esteban de la Sierra"
    ],
    "name:chi_x_preferred":[
        "\u5723\u57c3\u65af\u7279\u4e07\u5fb7\u62c9\u8c22\u62c9"
    ],
    "name:dut_x_preferred":[
        "San Esteban de la Sierra"
    ],
    "name:eng_x_preferred":[
        "San Esteban de la Sierra"
    ],
    "name:fre_x_preferred":[
        "San Esteban de la Sierra"
    ],
    "name:ger_x_preferred":[
        "San Esteban de la Sierra"
    ],
    "name:hun_x_preferred":[
        "San Esteban de la Sierra"
    ],
    "name:ina_x_preferred":[
        "San Esteban de la Sierra"
    ],
    "name:ita_x_preferred":[
        "San Esteban de la Sierra"
    ],
    "name:kaz_x_preferred":[
        "\u0421\u0430\u043d-\u042d\u0441\u0442\u0435\u0431\u0430\u043d-\u0434\u0435-\u043b\u0430-\u0421\u044c\u0435\u0440\u0440\u0430"
    ],
    "name:may_x_preferred":[
        "San Esteban de la Sierra"
    ],
    "name:nan_x_preferred":[
        "San Esteban de la Sierra"
    ],
    "name:oci_x_preferred":[
        "San Esteban de la Sierra"
    ],
    "name:pol_x_preferred":[
        "San Esteban de la Sierra"
    ],
    "name:por_x_preferred":[
        "San Esteban de la Sierra"
    ],
    "name:rus_x_preferred":[
        "\u0421\u0430\u043d-\u042d\u0441\u0442\u0435\u0431\u0430\u043d-\u0434\u0435-\u043b\u0430-\u0421\u044c\u0435\u0440\u0440\u0430"
    ],
    "name:spa_x_preferred":[
        "San Esteban de la Sierra"
    ],
    "name:swe_x_preferred":[
        "San Esteban de la Sierra"
    ],
    "name:ukr_x_preferred":[
        "\u0421\u0430\u043d-\u0415\u0441\u0442\u0435\u0431\u0430\u043d-\u0434\u0435-\u043b\u0430-\u0421\u044c\u0454\u0440\u0440\u0430"
    ],
    "name:uzb_x_preferred":[
        "San Esteban de la Sierra"
    ],
    "name:vie_x_preferred":[
        "San Esteban de la Sierra"
    ],
    "name:war_x_preferred":[
        "San Esteban de la Sierra"
    ],
    "qs_pg:aaroncc":"ES",
    "qs_pg:gn_country":"ES",
    "qs_pg:gn_fcode":"PPLA3",
    "qs_pg:gn_pop":415,
    "qs_pg:name":"San Esteban de la Sierra",
    "qs_pg:name_adm0":"Espa\u00f1a",
    "qs_pg:name_adm1":"Castilla y Le\u00f3n",
    "qs_pg:photos":13,
    "qs_pg:photos_1k":3,
    "qs_pg:photos_9k":1,
    "qs_pg:photos_9r":1,
    "qs_pg:photos_all":13,
    "qs_pg:photos_sr":1,
    "qs_pg:pop_sr":2,
    "qs_pg:qs_pg_placetype":"locality",
    "qs_pg:qs_pg_placetype_gp":"Town",
    "qs_pg:woe_adm0":23424950,
    "woe:adm0_id":23424950,
    "woe:name_adm0":"Espa\u00f1a",
    "woe:name_adm1":"Castilla y Le\u00f3n",
    "woe:placetype":"Town",
    "wof:name":"San Esteban de la Sierra",
    "wof:placetype":"locality",
    "wof:population":415
},
  "geometry": {"coordinates":[-5.90619,40.5068],"type":"Point"}
}