{
  "type": "Feature",
  "properties": {
    "gn:country":"ES",
    "gn:fcode":"PPLA3",
    "gn:population":62,
    "iso:country":"ES",
    "name:arg_x_preferred":[
        "Pobladura de Valderaduey"
    ],
    "name:cat_x_preferred":[
        "Pobladura de Valderaduey"
    ],
    "name:eng_x_preferred":[
        "Pobladura de Valderaduey"
    ],
    "name:eus_x_preferred":[
        "Pobladura de Valderaduey"
    ],
    "name:fra_x_preferred":[
        "Pobladura de Valderaduey"
    ],
    "name:haw_x_preferred":[
        "Pobladura de Valderaduey"
    ],
    "name:hun_x_preferred":[
        "Pobladura de Valderaduey"
    ],
    "name:ile_x_preferred":[
        "Pobladura de Valderaduey"
    ],
    "name:ina_x_preferred":[
        "Pobladura de Valderaduey"
    ],
    "name:ita_x_preferred":[
        "Pobladura de Valderaduey"
    ],
    "name:msa_x_preferred":[
        "Pobladura de Valderaduey"
    ],
    "name:nan_x_preferred":[
        "Pobladura de Valderaduey"
    ],
    "name:nld_x_preferred":[
        "Pobladura de Valderaduey"
    ],
    "name:oci_x_preferred":[
        "Pobladura de Valderaduey"
    ],
    "name:pol_x_preferred":[
        "Pobladura de Valderaduey"
    ],
    "name:por_x_preferred":[
        "Pobladura de Valderaduey"
    ],
    "name:rus_x_preferred":[
        "\u041f\u043e\u0431\u043b\u0430\u0434\u0443\u0440\u0430-\u0434\u0435-\u0412\u0430\u043b\u044c\u0434\u0435\u0440\u0430\u0434\u0443\u044d\u0439"
    ],
    "name:spa_x_preferred":[
        "Pobladura de Valderaduey"
    ],
    "name:swe_x_preferred":[
        "Pobladura de Valderaduey"
    ],
    "name:ukr_x_preferred":[
        "\u041f\u043e\u0431\u043b\u0430\u0434\u0443\u0440\u0430-\u0434\u0435-\u0412\u0430\u043b\u044c\u0434\u0435\u0440\u0430\u0434\u0443\u0435\u0439"
    ],
    "name:uzb_x_preferred":[
        "Pobladura de Valderaduey"
    ],
    "name:vie_x_preferred":[
        "Pobladura de Valderaduey"
    ],
    "name:war_x_preferred":[
        "Pobladura de Valderaduey"
    ],
    "name:zho_x_preferred":[
        "\u6ce2\u592b\u62c9\u675c\u62c9\u5fb7\u74e6\u5c14\u5fb7\u62c9\u675c\u57c3"
    ],
    "qs_pg:aaroncc":"ES",
    "qs_pg:gn_country":"ES",
    "qs_pg:gn_fcode":"PPLA3",
    "qs_pg:gn_pop":62,
    "qs_pg:name":"Pobladura de Valderaduey",
    "qs_pg:name_adm0":"Espa\u00f1a",
    "qs_pg:name_adm1":"Castilla y Le\u00f3n",
    "qs_pg:photos_9k":1,
    "qs_pg:photos_9r":1,
    "qs_pg:photos_all":1,
    "qs_pg:photos_sr":0,
    "qs_pg:pop_sr":1,
    "qs_pg:qs_pg_placetype":"locality",
    "qs_pg:qs_pg_placetype_gp":"Town",
    "qs_pg:woe_adm0":23424950,
    "woe:adm0_id":23424950,
    "woe:name_adm0":"Espa\u00f1a",
    "woe:name_adm1":"Castilla y Le\u00f3n",
    "woe:placetype":"Town",
    "wof:name":"Pobladura de Valderaduey",
    "wof:placetype":"locality",
    "wof:population":62
},
  "geometry": {"coordinates":[-5.54189,41.70009],"type":"Point"}
}