{
  "type": "Feature",
  "properties": {
    "gn:admin1_code":"55",
    "gn:admin2_code":"SO",
    "gn:admin3_code":"42019",
    "gn:asciiname":"Portelarbol",
    "gn:country_code":"ES",
    "gn:dem":1165,
    "gn:feature_class":"P",
    "gn:feature_code":"PPL",
    "gn:name":"Portel\u00e1rbol",
    "gn:population":0,
    "gn:timezone":"Europe/Madrid",
    "iso:country":"ES",
    "name:und_x_variant":[
        "Portel\u00e1rbol"
    ],
    "wof:name":"Portelarbol",
    "wof:placetype":"locality"
},
  "geometry": {"coordinates":[-2.41277,41.89841],"type":"Point"}
}