{
  "type": "Feature",
  "properties": {
    "iso:country":"ES",
    "qs_pg:aaroncc":"ES",
    "qs_pg:name":"Aeropuerto Reina Sofia",
    "qs_pg:name_adm0":"Espa\u00f1a",
    "qs_pg:name_adm1":"Islas Canarias",
    "qs_pg:photos":226,
    "qs_pg:photos_1k":46,
    "qs_pg:photos_9k":1,
    "qs_pg:photos_9r":4,
    "qs_pg:photos_all":226,
    "qs_pg:photos_sr":4,
    "qs_pg:pop_sr":0,
    "qs_pg:qs_pg_placetype":"locality",
    "qs_pg:qs_pg_placetype_gp":"Town",
    "qs_pg:woe_adm0":23424950,
    "woe:adm0_id":23424950,
    "woe:name_adm0":"Espa\u00f1a",
    "woe:name_adm1":"Islas Canarias",
    "woe:placetype":"Town",
    "wof:name":"Aeropuerto Reina Sofia",
    "wof:placetype":"locality"
},
  "geometry": {"coordinates":[-16.575279,28.046606],"type":"Point"}
}