{
  "type": "Feature",
  "properties": {
    "gn:gn_country":"ES",
    "gn:gn_fcode":"PPLA3",
    "gn:gn_pop":125,
    "gn:population":125,
    "iso:country":"ES",
    "name:arg_x_preferred":[
        "Villanueva de San Mancio"
    ],
    "name:cat_x_preferred":[
        "Villanueva de San Mancio"
    ],
    "name:deu_x_preferred":[
        "Villanueva de San Mancio"
    ],
    "name:eng_x_preferred":[
        "Villanueva de San Mancio"
    ],
    "name:eus_x_preferred":[
        "Villanueva de San Mancio"
    ],
    "name:fas_x_preferred":[
        "\u0628\u06cc\u06cc\u0627\u0646\u0648\u0626\u0628\u0627 \u062f \u0633\u0627\u0646 \u0645\u0627\u0646\u0633\u06cc\u0648"
    ],
    "name:fra_x_preferred":[
        "Villanueva de San Mancio"
    ],
    "name:hun_x_preferred":[
        "Villanueva de San Mancio"
    ],
    "name:hye_x_preferred":[
        "\u054e\u056b\u056c\u0575\u0561\u0576\u0578\u0582\u0587\u0561 \u0564\u0565 \u054d\u0561\u0576 \u0544\u0561\u0576\u057d\u056b\u0578"
    ],
    "name:ina_x_preferred":[
        "Villanueva de San Mancio"
    ],
    "name:ita_x_preferred":[
        "Villanueva de San Mancio"
    ],
    "name:jpn_x_preferred":[
        "\u30d3\u30b8\u30e3\u30cc\u30a8\u30d0\u30fb\u30c7\u30fb\u30b5\u30f3\u30fb\u30de\u30f3\u30b7\u30aa"
    ],
    "name:msa_x_preferred":[
        "Villanueva de San Mancio"
    ],
    "name:nan_x_preferred":[
        "Villanueva de San Mancio"
    ],
    "name:nld_x_preferred":[
        "Villanueva de San Mancio"
    ],
    "name:oci_x_preferred":[
        "Villanueva de San Mancio"
    ],
    "name:pol_x_preferred":[
        "Villanueva de San Mancio"
    ],
    "name:por_x_preferred":[
        "Villanueva de San Mancio"
    ],
    "name:rus_x_preferred":[
        "\u0412\u0438\u043b\u044c\u044f\u043d\u0443\u044d\u0432\u0430-\u0434\u0435-\u0421\u0430\u043d-\u041c\u0430\u043d\u0441\u0438\u043e"
    ],
    "name:spa_x_preferred":[
        "Villanueva de San Mancio"
    ],
    "name:swe_x_preferred":[
        "Villanueva de San Mancio"
    ],
    "name:ukr_x_preferred":[
        "\u0412\u0456\u043b\u044c\u044f\u043d\u0443\u0435\u0432\u0430-\u0434\u0435-\u0421\u0430\u043d-\u041c\u0430\u043d\u0441\u0456\u043e"
    ],
    "name:vie_x_preferred":[
        "Villanueva de San Mancio"
    ],
    "name:war_x_preferred":[
        "Villanueva de San Mancio"
    ],
    "name:zho_x_preferred":[
        "\u5723\u66fc\u897f\u5965\u65b0\u9547"
    ],
    "qs_pg:aaroncc":"ES",
    "qs_pg:gn_country":"ES",
    "qs_pg:gn_fcode":"PPLA3",
    "qs_pg:gn_pop":125,
    "qs_pg:name":"Villanueva de San Mancio",
    "qs_pg:name_adm0":"Espa\u00f1a",
    "qs_pg:name_adm1":"Castilla y Le\u00f3n",
    "qs_pg:photos_9k":1,
    "qs_pg:photos_9r":1,
    "qs_pg:photos_all":7,
    "qs_pg:photos_sr":0,
    "qs_pg:pop_sr":1,
    "qs_pg:qs_pg_placetype":"locality",
    "qs_pg:qs_pg_placetype_gp":"Town",
    "qs_pg:woe_adm0":23424950,
    "woe:adm0_id":23424950,
    "woe:name_adm0":"Espa\u00f1a",
    "woe:name_adm1":"Castilla y Le\u00f3n",
    "woe:placetype":"Town",
    "wof:name":"Villanueva de San Mancio",
    "wof:placetype":"locality",
    "wof:population":125
},
  "geometry": {"coordinates":[-5.012,41.92842],"type":"Point"}
}