{
  "type": "Feature",
  "properties": {
    "gn:admin1_code":"52",
    "gn:admin2_code":"HU",
    "gn:admin3_code":"22189",
    "gn:asciiname":"Hospital",
    "gn:country_code":"ES",
    "gn:dem":678,
    "gn:feature_class":"P",
    "gn:feature_code":"PPL",
    "gn:name":"Hospital",
    "gn:population":0,
    "gn:timezone":"Europe/Madrid",
    "iso:country":"ES",
    "wof:name":"Hospital",
    "wof:placetype":"locality"
},
  "geometry": {"coordinates":[0.16093,42.54723],"type":"Point"}
}