{
  "type": "Feature",
  "properties": {
    "gn:admin1_code":"34",
    "gn:admin2_code":"O",
    "gn:admin3_code":"33045",
    "gn:asciiname":"Collia",
    "gn:country_code":"ES",
    "gn:dem":157,
    "gn:feature_class":"P",
    "gn:feature_code":"PPL",
    "gn:name":"Coll\u00eda",
    "gn:population":0,
    "gn:timezone":"Europe/Madrid",
    "iso:country":"ES",
    "name:ast_x_preferred":[
        "Santitom\u00e1s"
    ],
    "name:spa_x_preferred":[
        "Coll\u00eda"
    ],
    "wof:name":"Collia",
    "wof:placetype":"locality"
},
  "geometry": {"coordinates":[-5.19018,43.40916],"type":"Point"}
}