{
  "type": "Feature",
  "properties": {
    "gn:country":"ES",
    "gn:fcode":"PPLA3",
    "gn:population":190,
    "iso:country":"ES",
    "name:arg_x_preferred":[
        "Bermellar"
    ],
    "name:ast_x_preferred":[
        "Bermellar"
    ],
    "name:cat_x_preferred":[
        "Bermellar"
    ],
    "name:ceb_x_preferred":[
        "Bermellar"
    ],
    "name:deu_x_preferred":[
        "Bermellar"
    ],
    "name:eng_x_preferred":[
        "Bermellar"
    ],
    "name:eus_x_preferred":[
        "Bermellar"
    ],
    "name:fra_x_preferred":[
        "Bermellar"
    ],
    "name:haw_x_preferred":[
        "Bermellar"
    ],
    "name:hun_x_preferred":[
        "Bermellar"
    ],
    "name:ina_x_preferred":[
        "Bermellar"
    ],
    "name:ita_x_preferred":[
        "Bermellar"
    ],
    "name:kaz_x_preferred":[
        "\u0411\u0435\u0440\u043c\u0435\u043b\u044c\u044f\u0440"
    ],
    "name:msa_x_preferred":[
        "Bermellar"
    ],
    "name:nan_x_preferred":[
        "Bermellar"
    ],
    "name:nld_x_preferred":[
        "Bermellar"
    ],
    "name:oci_x_preferred":[
        "Bermellar"
    ],
    "name:pol_x_preferred":[
        "Bermellar"
    ],
    "name:por_x_preferred":[
        "Bermellar"
    ],
    "name:rup_x_preferred":[
        "Bermellar"
    ],
    "name:rus_x_preferred":[
        "\u0411\u0435\u0440\u043c\u0435\u043b\u044c\u044f\u0440"
    ],
    "name:spa_x_preferred":[
        "Bermellar"
    ],
    "name:swe_x_preferred":[
        "Bermellar"
    ],
    "name:ukr_x_preferred":[
        "\u0411\u0435\u0440\u043c\u0435\u043b\u044c\u044f\u0440"
    ],
    "name:uzb_x_preferred":[
        "Bermellar"
    ],
    "name:vie_x_preferred":[
        "Bermellar"
    ],
    "name:war_x_preferred":[
        "Bermellar"
    ],
    "name:zho_x_preferred":[
        "\u8d1d\u5c14\u6885\u5229\u4e9a\u5c14"
    ],
    "qs_pg:aaroncc":"ES",
    "qs_pg:gn_country":"ES",
    "qs_pg:gn_fcode":"PPLA3",
    "qs_pg:gn_pop":190,
    "qs_pg:name":"Bermellar",
    "qs_pg:name_adm0":"Espa\u00f1a",
    "qs_pg:name_adm1":"Castilla y Le\u00f3n",
    "qs_pg:photos_9k":1,
    "qs_pg:photos_9r":1,
    "qs_pg:photos_all":1,
    "qs_pg:photos_sr":0,
    "qs_pg:pop_sr":1,
    "qs_pg:qs_pg_placetype":"locality",
    "qs_pg:qs_pg_placetype_gp":"Town",
    "qs_pg:woe_adm0":23424950,
    "woe:adm0_id":23424950,
    "woe:name_adm0":"Espa\u00f1a",
    "woe:name_adm1":"Castilla y Le\u00f3n",
    "woe:placetype":"Town",
    "wof:name":"Bermellar",
    "wof:placetype":"locality",
    "wof:population":190
},
  "geometry": {"coordinates":[-6.67014,40.99918],"type":"Point"}
}