{
  "type": "Feature",
  "properties": {
    "gn:admin1_code":"58",
    "gn:admin2_code":"LU",
    "gn:admin3_code":"27051",
    "gn:asciiname":"Villaguiz",
    "gn:country_code":"ES",
    "gn:dem":36,
    "gn:feature_class":"P",
    "gn:feature_code":"PPL",
    "gn:name":"Villag\u00fciz",
    "gn:population":0,
    "gn:timezone":"Europe/Madrid",
    "iso:country":"ES",
    "wof:name":"Villaguiz",
    "wof:placetype":"locality"
},
  "geometry": {"coordinates":[-7.11804,43.54222],"type":"Point"}
}