{
  "type": "Feature",
  "properties": {
    "gn:admin1_code":"34",
    "gn:admin2_code":"O",
    "gn:admin3_code":"33041",
    "gn:asciiname":"Vigo",
    "gn:country_code":"ES",
    "gn:dem":49,
    "gn:feature_class":"P",
    "gn:feature_code":"PPL",
    "gn:name":"Vigo",
    "gn:population":0,
    "gn:timezone":"Europe/Madrid",
    "iso:country":"ES",
    "name:rus_x_preferred":[
        "\u0412\u0438\u0433\u043e"
    ],
    "wof:name":"Vigo",
    "wof:placetype":"locality"
},
  "geometry": {"coordinates":[-6.62824,43.5639],"type":"Point"}
}