{
  "type": "Feature",
  "properties": {
    "gn:admin1_code":"58",
    "gn:admin2_code":"C",
    "gn:admin3_code":"15073",
    "gn:asciiname":"Martin",
    "gn:country_code":"ES",
    "gn:dem":55,
    "gn:feature_class":"P",
    "gn:feature_code":"PPL",
    "gn:name":"Mart\u00edn",
    "gn:population":0,
    "gn:timezone":"Europe/Madrid",
    "iso:country":"ES",
    "wof:name":"Martin",
    "wof:placetype":"locality"
},
  "geometry": {"coordinates":[-8.99008,42.54556],"type":"Point"}
}