{
  "type": "Feature",
  "properties": {
    "gn:admin1_code":"53",
    "gn:admin2_code":"TF",
    "gn:admin3_code":"38038",
    "gn:asciiname":"Igueste",
    "gn:country_code":"ES",
    "gn:dem":107,
    "gn:feature_class":"P",
    "gn:feature_code":"PPL",
    "gn:name":"Igueste",
    "gn:population":0,
    "gn:timezone":"Atlantic/Canary",
    "iso:country":"ES",
    "name:und_x_variant":[
        "Valle de Igueste",
        "Igueste de Candelaria",
        "Valle Igueste",
        "Igueste"
    ],
    "wof:name":"Igueste",
    "wof:placetype":"locality"
},
  "geometry": {"coordinates":[-16.15751,28.52384],"type":"Point"}
}