{
  "type": "Feature",
  "properties": {
    "gn:admin1_code":"55",
    "gn:admin2_code":"BU",
    "gn:admin3_code":"09410",
    "gn:asciiname":"Campillo de Mena",
    "gn:country_code":"ES",
    "gn:dem":470,
    "gn:feature_class":"P",
    "gn:feature_code":"PPL",
    "gn:name":"Campillo de Mena",
    "gn:population":0,
    "gn:timezone":"Europe/Madrid",
    "iso:country":"ES",
    "wof:name":"Campillo de Mena",
    "wof:placetype":"locality"
},
  "geometry": {"coordinates":[-3.35864,43.11746],"type":"Point"}
}