{
  "type": "Feature",
  "properties": {
    "gn:admin1_code":"58",
    "gn:admin2_code":"OR",
    "gn:admin3_code":"32050",
    "gn:asciiname":"Villaza",
    "gn:country_code":"ES",
    "gn:dem":379,
    "gn:feature_class":"P",
    "gn:feature_code":"PPL",
    "gn:name":"Villaza",
    "gn:population":0,
    "gn:timezone":"Europe/Madrid",
    "iso:country":"ES",
    "wof:name":"Villaza",
    "wof:placetype":"locality"
},
  "geometry": {"coordinates":[-7.48993,41.9314],"type":"Point"}
}