{
  "type": "Feature",
  "properties": {
    "gn:admin1_code":"55",
    "gn:admin2_code":"LE",
    "gn:admin3_code":"24101",
    "gn:asciiname":"Montrondo",
    "gn:country_code":"ES",
    "gn:dem":1289,
    "gn:feature_class":"P",
    "gn:feature_code":"PPL",
    "gn:name":"Montrondo",
    "gn:population":0,
    "gn:timezone":"Europe/Madrid",
    "iso:country":"ES",
    "wof:name":"Montrondo",
    "wof:placetype":"locality"
},
  "geometry": {"coordinates":[-6.21194,42.84978],"type":"Point"}
}