{
  "type": "Feature",
  "properties": {
    "gn:admin1_code":"59",
    "gn:admin2_code":"BI",
    "gn:admin3_code":"48036",
    "gn:asciiname":"Ordana",
    "gn:country_code":"ES",
    "gn:dem":201,
    "gn:feature_class":"P",
    "gn:feature_code":"PPL",
    "gn:name":"Orda\u00f1a",
    "gn:population":0,
    "gn:timezone":"Europe/Madrid",
    "iso:country":"ES",
    "wof:name":"Ordana",
    "wof:placetype":"locality"
},
  "geometry": {"coordinates":[-2.83735,43.21191],"type":"Point"}
}