{
  "type": "Feature",
  "properties": {
    "gn:admin1_code":"34",
    "gn:admin2_code":"O",
    "gn:admin3_code":"33066",
    "gn:asciiname":"Ferrera",
    "gn:country_code":"ES",
    "gn:dem":207,
    "gn:feature_class":"P",
    "gn:feature_code":"PPL",
    "gn:name":"Ferrera",
    "gn:population":0,
    "gn:timezone":"Europe/Madrid",
    "iso:country":"ES",
    "name:als_x_preferred":[
        "Ferrera"
    ],
    "name:ceb_x_preferred":[
        "Ferrera"
    ],
    "name:deu_x_preferred":[
        "Ferrera"
    ],
    "name:epo_x_preferred":[
        "Ferrera"
    ],
    "name:eus_x_preferred":[
        "Ferrera"
    ],
    "name:fra_x_preferred":[
        "Ferrera"
    ],
    "name:ind_x_preferred":[
        "Ferrera"
    ],
    "name:ita_x_preferred":[
        "Ferrera"
    ],
    "name:lmo_x_preferred":[
        "Ferrera"
    ],
    "name:msa_x_preferred":[
        "Ferrera"
    ],
    "name:nld_x_preferred":[
        "Ferrera"
    ],
    "name:nno_x_preferred":[
        "Ferrera"
    ],
    "name:roh_x_preferred":[
        "Farera"
    ],
    "name:spa_x_preferred":[
        "Ferrera"
    ],
    "name:sqi_x_preferred":[
        "Ferrera"
    ],
    "name:swe_x_preferred":[
        "Ferrera"
    ],
    "name:war_x_preferred":[
        "Ferrera"
    ],
    "name:zho_x_preferred":[
        "\u8cbb\u96f7\u62c9"
    ],
    "wof:name":"Ferrera",
    "wof:placetype":"locality"
},
  "geometry": {"coordinates":[-5.68752,43.39716],"type":"Point"}
}