{
  "type": "Feature",
  "properties": {
    "gn:admin1_code":"34",
    "gn:admin2_code":"O",
    "gn:admin3_code":"33032",
    "gn:asciiname":"Portillas",
    "gn:country_code":"ES",
    "gn:dem":426,
    "gn:feature_class":"P",
    "gn:feature_code":"PPL",
    "gn:name":"Portillas",
    "gn:population":0,
    "gn:timezone":"Europe/Madrid",
    "iso:country":"ES",
    "wof:name":"Portillas",
    "wof:placetype":"locality"
},
  "geometry": {"coordinates":[-5.5508,43.25434],"type":"Point"}
}