{
  "type": "Feature",
  "properties": {
    "gn:admin1_code":"58",
    "gn:admin2_code":"C",
    "gn:admin3_code":"15071",
    "gn:asciiname":"Esparrelle",
    "gn:cc2":"ES",
    "gn:country_code":"ES",
    "gn:dem":124,
    "gn:feature_class":"P",
    "gn:feature_code":"PPL",
    "gn:name":"Esparrelle",
    "gn:population":0,
    "gn:timezone":"Europe/Madrid",
    "iso:country":"ES",
    "name:und_x_variant":[
        "Esparelle",
        "Esparrelle"
    ],
    "wof:name":"Esparrelle",
    "wof:placetype":"locality"
},
  "geometry": {"coordinates":[-9.01667,42.65],"type":"Point"}
}