{
  "type": "Feature",
  "properties": {
    "gn:admin1_code":"58",
    "gn:admin2_code":"C",
    "gn:admin3_code":"15056",
    "gn:asciiname":"Covas",
    "gn:country_code":"ES",
    "gn:dem":171,
    "gn:feature_class":"P",
    "gn:feature_code":"PPL",
    "gn:name":"Covas",
    "gn:population":0,
    "gn:timezone":"Europe/Madrid",
    "iso:country":"ES",
    "wof:name":"Covas",
    "wof:placetype":"locality"
},
  "geometry": {"coordinates":[-8.7479,42.91819],"type":"Point"}
}