{
  "type": "Feature",
  "properties": {
    "gn:admin1_code":"58",
    "gn:admin2_code":"C",
    "gn:admin3_code":"15042",
    "gn:asciiname":"Cambono",
    "gn:cc2":"ES",
    "gn:country_code":"ES",
    "gn:dem":225,
    "gn:feature_class":"P",
    "gn:feature_code":"PPL",
    "gn:name":"Cambo\u00f1o",
    "gn:population":0,
    "gn:timezone":"Europe/Madrid",
    "iso:country":"ES",
    "name:und_x_variant":[
        "San Juan",
        "Cambo\u00f1o"
    ],
    "wof:name":"Cambono",
    "wof:placetype":"locality"
},
  "geometry": {"coordinates":[-8.91667,42.75],"type":"Point"}
}