{
  "type": "Feature",
  "properties": {
    "gn:admin1_code":"58",
    "gn:admin2_code":"C",
    "gn:admin3_code":"15009",
    "gn:asciiname":"Piadela",
    "gn:country_code":"ES",
    "gn:dem":56,
    "gn:feature_class":"P",
    "gn:feature_code":"PPL",
    "gn:name":"Piadela",
    "gn:population":0,
    "gn:timezone":"Europe/Madrid",
    "iso:country":"ES",
    "wof:name":"Piadela",
    "wof:placetype":"locality"
},
  "geometry": {"coordinates":[-8.25047,43.26752000000001],"type":"Point"}
}