{
  "type": "Feature",
  "properties": {
    "gn:admin1_code":"34",
    "gn:admin2_code":"O",
    "gn:admin3_code":"33031",
    "gn:asciiname":"Barros",
    "gn:country_code":"ES",
    "gn:dem":201,
    "gn:feature_class":"P",
    "gn:feature_code":"PPL",
    "gn:name":"Barros",
    "gn:population":0,
    "gn:timezone":"Europe/Madrid",
    "iso:country":"ES",
    "wof:name":"Barros",
    "wof:placetype":"locality"
},
  "geometry": {"coordinates":[-5.70669,43.31968],"type":"Point"}
}