{
  "type": "Feature",
  "properties": {
    "gn:gn_country":"ES",
    "gn:gn_fcode":"PPLA3",
    "gn:gn_pop":359,
    "gn:population":359,
    "iso:country":"ES",
    "name:cat_x_preferred":[
        "Bustillo de la Vega"
    ],
    "name:eng_x_preferred":[
        "Bustillo de la Vega"
    ],
    "name:eus_x_preferred":[
        "Bustillo de la Vega"
    ],
    "name:fas_x_preferred":[
        "\u0628\u0648\u0633\u062a\u06cc\u06cc\u0648 \u062f \u0644\u0627 \u0628\u06af\u0627"
    ],
    "name:fra_x_preferred":[
        "Bustillo de la Vega"
    ],
    "name:glg_x_preferred":[
        "Bustillo de la Vega"
    ],
    "name:hun_x_preferred":[
        "Bustillo de la Vega"
    ],
    "name:hye_x_preferred":[
        "\u0532\u0578\u0582\u057d\u057f\u056b\u056c\u0575\u0578 \u0564\u0565 \u056c\u0561 \u054e\u0565\u0563\u0561"
    ],
    "name:ina_x_preferred":[
        "Bustillo de la Vega"
    ],
    "name:ita_x_preferred":[
        "Bustillo de la Vega"
    ],
    "name:msa_x_preferred":[
        "Bustillo de la Vega"
    ],
    "name:nan_x_preferred":[
        "Bustillo de la Vega"
    ],
    "name:nld_x_preferred":[
        "Bustillo de la Vega"
    ],
    "name:oci_x_preferred":[
        "Bustillo de la Vega"
    ],
    "name:pol_x_preferred":[
        "Bustillo de la Vega"
    ],
    "name:por_x_preferred":[
        "Bustillo de la Vega"
    ],
    "name:rus_x_preferred":[
        "\u0411\u0443\u0441\u0442\u0438\u043b\u044c\u043e-\u0434\u0435-\u043b\u0430-\u0412\u0435\u0433\u0430"
    ],
    "name:spa_x_preferred":[
        "Bustillo de la Vega"
    ],
    "name:swe_x_preferred":[
        "Bustillo de la Vega"
    ],
    "name:ukr_x_preferred":[
        "\u0411\u0443\u0441\u0442\u0456\u043b\u044c\u0439\u043e-\u0434\u0435-\u043b\u0430-\u0412\u0435\u0433\u0430"
    ],
    "name:uzb_x_preferred":[
        "Bustillo de la Vega"
    ],
    "name:vie_x_preferred":[
        "Bustillo de la Vega"
    ],
    "name:war_x_preferred":[
        "Bustillo de la Vega"
    ],
    "name:zho_x_preferred":[
        "\u5e03\u65af\u8482\u7565\u5fb7\u62c9\u97e6\u52a0"
    ],
    "qs_pg:aaroncc":"ES",
    "qs_pg:gn_country":"ES",
    "qs_pg:gn_fcode":"PPLA3",
    "qs_pg:gn_pop":359,
    "qs_pg:name":"Bustillo de la Vega",
    "qs_pg:name_adm0":"Espa\u00f1a",
    "qs_pg:name_adm1":"Castilla y Le\u00f3n",
    "qs_pg:photos_9r":0,
    "qs_pg:photos_sr":0,
    "qs_pg:pop_sr":2,
    "qs_pg:qs_pg_placetype":"locality",
    "qs_pg:qs_pg_placetype_gp":"Town",
    "qs_pg:woe_adm0":23424950,
    "woe:adm0_id":23424950,
    "woe:name_adm0":"Espa\u00f1a",
    "woe:name_adm1":"Castilla y Le\u00f3n",
    "woe:placetype":"Town",
    "wof:name":"Bustillo de la Vega",
    "wof:placetype":"locality",
    "wof:population":359
},
  "geometry": {"coordinates":[-4.74115,42.45605],"type":"Point"}
}