{
  "type": "Feature",
  "properties": {
    "gn:gn_country":"ES",
    "gn:gn_fcode":"PPL",
    "gn:gn_pop":348,
    "gn:population":348,
    "iso:country":"ES",
    "name:arg_x_preferred":[
        "Horcajo Medianero"
    ],
    "name:ast_x_preferred":[
        "Forcayu Medianeru"
    ],
    "name:cat_x_preferred":[
        "Horcajo Medianero"
    ],
    "name:ceb_x_preferred":[
        "Horcajo Medianero"
    ],
    "name:eng_x_preferred":[
        "Horcajo Medianero"
    ],
    "name:eus_x_preferred":[
        "Horcajo Medianero"
    ],
    "name:fra_x_preferred":[
        "Horcajo Medianero"
    ],
    "name:haw_x_preferred":[
        "Horcajo Medianero"
    ],
    "name:hun_x_preferred":[
        "Horcajo Medianero"
    ],
    "name:ina_x_preferred":[
        "Horcajo Medianero"
    ],
    "name:ita_x_preferred":[
        "Horcajo Medianero"
    ],
    "name:kaz_x_preferred":[
        "\u041e\u0440\u043a\u0430\u0445\u043e-\u041c\u0435\u0434\u0438\u0430\u043d\u0435\u0440\u043e"
    ],
    "name:msa_x_preferred":[
        "Horcajo Medianero"
    ],
    "name:nan_x_preferred":[
        "Horcajo Medianero"
    ],
    "name:nld_x_preferred":[
        "Horcajo Medianero"
    ],
    "name:oci_x_preferred":[
        "Horcajo Medianero"
    ],
    "name:pol_x_preferred":[
        "Horcajo Medianero"
    ],
    "name:por_x_preferred":[
        "Horcajo Medianero"
    ],
    "name:rus_x_preferred":[
        "\u041e\u0440\u043a\u0430\u0445\u043e-\u041c\u0435\u0434\u0438\u0430\u043d\u0435\u0440\u043e"
    ],
    "name:spa_x_preferred":[
        "Horcajo Medianero"
    ],
    "name:swe_x_preferred":[
        "Horcajo Medianero"
    ],
    "name:ukr_x_preferred":[
        "\u041e\u0440\u043a\u0430\u0445\u043e-\u041c\u0435\u0434\u0456\u0430\u043d\u0435\u0440\u043e"
    ],
    "name:vie_x_preferred":[
        "Horcajo Medianero"
    ],
    "name:war_x_preferred":[
        "Horcajo Medianero"
    ],
    "name:zho_x_preferred":[
        "\u5965\u5c14\u5361\u970d\u6885\u8fea\u4e9a\u5185\u7f57"
    ],
    "qs_pg:aaroncc":"ES",
    "qs_pg:gn_country":"ES",
    "qs_pg:gn_fcode":"PPL",
    "qs_pg:gn_pop":348,
    "qs_pg:name":"Horcajo-Medianero",
    "qs_pg:name_adm0":"Espa\u00f1a",
    "qs_pg:name_adm1":"Castilla y Le\u00f3n",
    "qs_pg:photos_9r":0,
    "qs_pg:photos_sr":0,
    "qs_pg:pop_sr":2,
    "qs_pg:qs_pg_placetype":"locality",
    "qs_pg:qs_pg_placetype_gp":"Town",
    "qs_pg:woe_adm0":23424950,
    "woe:adm0_id":23424950,
    "woe:name_adm0":"Espa\u00f1a",
    "woe:name_adm1":"Castilla y Le\u00f3n",
    "woe:placetype":"Town",
    "wof:name":"Horcajo-Medianero",
    "wof:placetype":"locality",
    "wof:population":348
},
  "geometry": {"coordinates":[-5.40584,40.63976],"type":"Point"}
}