{
  "type": "Feature",
  "properties": {
    "gn:admin1_code":"60",
    "gn:admin2_code":"A",
    "gn:admin3_code":"03062",
    "gn:asciiname":"Los Palacios",
    "gn:country_code":"ES",
    "gn:dem":5,
    "gn:feature_class":"P",
    "gn:feature_code":"PPL",
    "gn:name":"Los Palacios",
    "gn:population":0,
    "gn:timezone":"Europe/Madrid",
    "iso:country":"ES",
    "name:deu_x_preferred":[
        "Los Palacios"
    ],
    "name:fra_x_preferred":[
        "Los Palacios"
    ],
    "name:ita_x_preferred":[
        "Los Palacios"
    ],
    "name:kat_x_preferred":[
        "\u10da\u10dd\u10e1-\u10de\u10d0\u10da\u10d0\u10e1\u10d8\u10dd\u10e1\u10d8"
    ],
    "name:nld_x_preferred":[
        "Los Palacios"
    ],
    "name:por_x_preferred":[
        "Los Palacios"
    ],
    "name:rus_x_preferred":[
        "\u041b\u043e\u0441-\u041f\u0430\u043b\u0430\u0441\u044c\u043e\u0441"
    ],
    "name:spa_x_preferred":[
        "Los Palacios"
    ],
    "name:vie_x_preferred":[
        "Los Palacios"
    ],
    "name:zho_x_preferred":[
        "\u6d1b\u65af\u5e15\u62c9\u897f\u5965\u65af"
    ],
    "wof:name":"Los Palacios",
    "wof:placetype":"locality"
},
  "geometry": {"coordinates":[-0.72514,38.10599000000001],"type":"Point"}
}