{
  "type": "Feature",
  "properties": {
    "gn:admin1_code":"60",
    "gn:admin2_code":"A",
    "gn:admin3_code":"03062",
    "gn:asciiname":"Los Palacios",
    "gn:country_code":"ES",
    "gn:dem":5,
    "gn:feature_class":"P",
    "gn:feature_code":"PPL",
    "gn:name":"Los Palacios",
    "gn:population":0,
    "gn:timezone":"Europe/Madrid",
    "iso:country":"ES",
    "wof:name":"Los Palacios",
    "wof:placetype":"locality"
},
  "geometry": {"coordinates":[-0.72514,38.10599000000001],"type":"Point"}
}