{
  "type": "Feature",
  "properties": {
    "gn:gn_country":"ES",
    "gn:gn_fcode":"PPL",
    "gn:gn_pop":110,
    "gn:population":110,
    "iso:country":"ES",
    "name:ara_x_preferred":[
        "\u0641\u064a\u0644\u0627\u0646\u064a\u0648\u0641\u0627 \u062f\u064a \u062c\u0648\u0627\u062f\u0627\u0645\u064a\u062e\u0648\u062f"
    ],
    "name:arg_x_preferred":[
        "Villanueva de Guadamejud"
    ],
    "name:cat_x_preferred":[
        "Villanueva de Guadamejud"
    ],
    "name:eng_x_preferred":[
        "Villanueva de Guadamejud"
    ],
    "name:eus_x_preferred":[
        "Villanueva de Guadamejud"
    ],
    "name:fra_x_preferred":[
        "Villanueva de Guadamejud"
    ],
    "name:hun_x_preferred":[
        "Villanueva de Guadamejud"
    ],
    "name:ita_x_preferred":[
        "Villanueva de Guadamejud"
    ],
    "name:jpn_x_preferred":[
        "\u30d3\u30b8\u30e3\u30cc\u30a8\u30d0\u30fb\u30c7\u30fb\u30b0\u30a2\u30c0\u30e1\u30d5\u30c9"
    ],
    "name:kaz_x_preferred":[
        "\u0412\u0438\u043b\u044c\u044f\u043d\u0443\u044d\u0432\u0430-\u0434\u0435-\u0413\u0432\u0430\u0434\u0430\u043c\u0435\u0445\u0443\u0434"
    ],
    "name:msa_x_preferred":[
        "Villanueva de Guadamejud"
    ],
    "name:nan_x_preferred":[
        "Villanueva de Guadamejud"
    ],
    "name:nld_x_preferred":[
        "Villanueva de Guadamejud"
    ],
    "name:oci_x_preferred":[
        "Villanueva de Guadamejud"
    ],
    "name:pol_x_preferred":[
        "Villanueva de Guadamejud"
    ],
    "name:por_x_preferred":[
        "Villanueva de Guadamejud"
    ],
    "name:rus_x_preferred":[
        "\u0412\u0438\u043b\u044c\u044f\u043d\u0443\u044d\u0432\u0430-\u0434\u0435-\u0413\u0432\u0430\u0434\u0430\u043c\u0435\u0445\u0443\u0434"
    ],
    "name:spa_x_preferred":[
        "Villanueva de Guadamejud"
    ],
    "name:swe_x_preferred":[
        "Villanueva de Guadamejud"
    ],
    "name:ukr_x_preferred":[
        "\u0412\u0456\u043b\u044c\u044f\u043d\u0443\u0435\u0432\u0430-\u0434\u0435-\u0413\u0443\u0430\u0434\u0430\u043c\u0435\u0445\u0443\u0434"
    ],
    "name:vie_x_preferred":[
        "Villanueva de Guadamejud"
    ],
    "name:war_x_preferred":[
        "Villanueva de Guadamejud"
    ],
    "name:zho_x_preferred":[
        "\u74dc\u8fbe\u6885\u80e1\u5fb7\u65b0\u9547"
    ],
    "qs_pg:aaroncc":"ES",
    "qs_pg:gn_country":"ES",
    "qs_pg:gn_fcode":"PPL",
    "qs_pg:gn_pop":110,
    "qs_pg:name":"Villanueva de Guadamajud",
    "qs_pg:photos_9r":0,
    "qs_pg:photos_sr":0,
    "qs_pg:pop_sr":1,
    "qs_pg:qs_pg_placetype":"locality",
    "wof:name":"Villanueva de Guadamajud",
    "wof:placetype":"locality",
    "wof:population":110
},
  "geometry": {"coordinates":[-2.5053,40.22475],"type":"Point"}
}