{
  "type": "Feature",
  "properties": {
    "gn:admin1_code":"55",
    "gn:admin2_code":"ZA",
    "gn:admin3_code":"49071",
    "gn:asciiname":"Ceadea",
    "gn:country_code":"ES",
    "gn:dem":831,
    "gn:feature_class":"P",
    "gn:feature_code":"PPL",
    "gn:name":"Ceadea",
    "gn:population":0,
    "gn:timezone":"Europe/Madrid",
    "iso:country":"ES",
    "wof:name":"Ceadea",
    "wof:placetype":"locality"
},
  "geometry": {"coordinates":[-6.25246,41.68306],"type":"Point"}
}