{
  "type": "Feature",
  "properties": {
    "gn:admin1_code":"53",
    "gn:admin2_code":"GC",
    "gn:admin3_code":"35024",
    "gn:asciiname":"Isla de Alegranza",
    "gn:country_code":"ES",
    "gn:dem":67,
    "gn:feature_class":"P",
    "gn:feature_code":"PPL",
    "gn:name":"Isla de Alegranza",
    "gn:population":0,
    "gn:timezone":"Atlantic/Canary",
    "iso:country":"ES",
    "wof:name":"Isla de Alegranza",
    "wof:placetype":"locality"
},
  "geometry": {"coordinates":[-13.50992,29.40102000000001],"type":"Point"}
}