{
  "type": "Feature",
  "properties": {
    "gn:admin1_code":"58",
    "gn:admin2_code":"C",
    "gn:admin3_code":"15042",
    "gn:asciiname":"Fruime",
    "gn:country_code":"ES",
    "gn:dem":209,
    "gn:feature_class":"P",
    "gn:feature_code":"PPL",
    "gn:name":"Fruime",
    "gn:population":0,
    "gn:timezone":"Europe/Madrid",
    "iso:country":"ES",
    "wof:name":"Fruime",
    "wof:placetype":"locality"
},
  "geometry": {"coordinates":[-8.82275,42.72924],"type":"Point"}
}