{
  "type": "Feature",
  "properties": {
    "gn:admin1_code":"55",
    "gn:admin2_code":"LE",
    "gn:admin3_code":"24088",
    "gn:asciiname":"Villamor de Laguna",
    "gn:country_code":"ES",
    "gn:dem":767,
    "gn:feature_class":"P",
    "gn:feature_code":"PPL",
    "gn:name":"Villamor de Laguna",
    "gn:population":0,
    "gn:timezone":"Europe/Madrid",
    "iso:country":"ES",
    "name:und_x_variant":[
        "Villamorico",
        "Villamor de Laguna"
    ],
    "wof:name":"Villamor de Laguna",
    "wof:placetype":"locality"
},
  "geometry": {"coordinates":[-5.67736,42.19186],"type":"Point"}
}