{
  "type": "Feature",
  "properties": {
    "gn:gn_country":"ES",
    "gn:gn_fcode":"PPLA3",
    "gn:gn_pop":858,
    "gn:population":858,
    "iso:country":"ES",
    "name:ara_x_preferred":[
        "\u0627\u0644\u0641\u0648\u0646\u062f\u064a\u063a\u0648\u064a\u0644\u0627"
    ],
    "name:arg_x_preferred":[
        "Alfandaguella"
    ],
    "name:cat_x_preferred":[
        "Fondeguilla"
    ],
    "name:eng_x_preferred":[
        "Alfondeguilla"
    ],
    "name:eus_x_preferred":[
        "Fondeguilla"
    ],
    "name:fas_x_preferred":[
        "\u0627\u0644\u0641\u0627\u0646\u062f\u06af\u0648\u06cc\u0644\u0627"
    ],
    "name:fra_x_preferred":[
        "Alfondeguilla"
    ],
    "name:hun_x_preferred":[
        "Alfondeguilla"
    ],
    "name:ita_x_preferred":[
        "Alfondeguilla"
    ],
    "name:msa_x_preferred":[
        "Alfondeguilla"
    ],
    "name:nan_x_preferred":[
        "Alfondeguilla"
    ],
    "name:nld_x_preferred":[
        "Alfondeguilla"
    ],
    "name:oci_x_preferred":[
        "Alfondeguilla"
    ],
    "name:pol_x_preferred":[
        "Alfondeguilla"
    ],
    "name:por_x_preferred":[
        "Alfondeguilla"
    ],
    "name:rup_x_preferred":[
        "Alfondeguilla"
    ],
    "name:rus_x_preferred":[
        "\u0410\u043b\u044c\u0444\u043e\u043d\u0434\u0435\u0433\u0438\u043b\u044c\u044f"
    ],
    "name:spa_x_preferred":[
        "Alfondeguilla"
    ],
    "name:swe_x_preferred":[
        "Alfondeguilla"
    ],
    "name:ukr_x_preferred":[
        "\u0410\u043b\u044c\u0444\u043e\u043d\u0434\u0435\u0433\u0456\u043b\u044c\u044f"
    ],
    "name:uzb_x_preferred":[
        "Alfondeguilla"
    ],
    "name:vie_x_preferred":[
        "Alfondeguilla"
    ],
    "name:war_x_preferred":[
        "Alfondeguilla"
    ],
    "name:zho_x_preferred":[
        "\u963f\u5c14\u4e30\u5fb7\u5409\u5229\u4e9a"
    ],
    "qs_pg:aaroncc":"ES",
    "qs_pg:gn_country":"ES",
    "qs_pg:gn_fcode":"PPLA3",
    "qs_pg:gn_pop":858,
    "qs_pg:name":"Alfondeguilla",
    "qs_pg:name_adm0":"Espa\u00f1a",
    "qs_pg:name_adm1":"Comunitat Valenciana",
    "qs_pg:photos":173,
    "qs_pg:photos_1k":35,
    "qs_pg:photos_9k":1,
    "qs_pg:photos_9r":4,
    "qs_pg:photos_all":173,
    "qs_pg:photos_sr":4,
    "qs_pg:pop_sr":2,
    "qs_pg:qs_pg_placetype":"locality",
    "qs_pg:qs_pg_placetype_gp":"Town",
    "qs_pg:woe_adm0":23424950,
    "woe:adm0_id":23424950,
    "woe:name_adm0":"Espa\u00f1a",
    "woe:name_adm1":"Comunitat Valenciana",
    "woe:placetype":"Town",
    "wof:name":"Alfondeguilla",
    "wof:placetype":"locality",
    "wof:population":858
},
  "geometry": {"coordinates":[-0.26667,39.83333],"type":"Point"}
}