{
  "type": "Feature",
  "properties": {
    "gn:admin1_code":"27",
    "gn:admin2_code":"LO",
    "gn:admin3_code":"26140",
    "gn:asciiname":"Santurde",
    "gn:country_code":"ES",
    "gn:dem":713,
    "gn:feature_class":"P",
    "gn:feature_code":"PPL",
    "gn:name":"Santurde",
    "gn:population":0,
    "gn:timezone":"Europe/Madrid",
    "iso:country":"ES",
    "wof:name":"Santurde",
    "wof:placetype":"locality"
},
  "geometry": {"coordinates":[-2.9804,42.38994],"type":"Point"}
}