{
  "type": "Feature",
  "properties": {
    "gn:admin1_code":"60",
    "gn:admin2_code":"V",
    "gn:admin3_code":"46254",
    "gn:asciiname":"Jaraguas",
    "gn:country_code":"ES",
    "gn:dem":806,
    "gn:feature_class":"P",
    "gn:feature_code":"PPL",
    "gn:name":"Jaraguas",
    "gn:population":0,
    "gn:timezone":"Europe/Madrid",
    "iso:country":"ES",
    "wof:name":"Jaraguas",
    "wof:placetype":"locality"
},
  "geometry": {"coordinates":[-1.36667,39.53333],"type":"Point"}
}