{
  "type": "Feature",
  "properties": {
    "gn:admin1_code":"59",
    "gn:admin2_code":"BI",
    "gn:admin3_code":"48086",
    "gn:asciiname":"El Llano",
    "gn:country_code":"ES",
    "gn:dem":191,
    "gn:feature_class":"P",
    "gn:feature_code":"PPL",
    "gn:name":"Llano",
    "gn:population":0,
    "gn:timezone":"Europe/Madrid",
    "iso:country":"ES",
    "name:ceb_x_preferred":[
        "El Llano"
    ],
    "name:deu_x_preferred":[
        "El Llano"
    ],
    "name:fra_x_preferred":[
        "El Llano"
    ],
    "name:ita_x_preferred":[
        "El Llano"
    ],
    "name:spa_x_preferred":[
        "El Llano"
    ],
    "name:swe_x_preferred":[
        "El Llano"
    ],
    "wof:name":"El Llano",
    "wof:placetype":"locality"
},
  "geometry": {"coordinates":[-3.15552,43.28415],"type":"Point"}
}