{
  "type": "Feature",
  "properties": {
    "gn:admin1_code":"58",
    "gn:admin2_code":"C",
    "gn:admin3_code":"15069",
    "gn:asciiname":"Erines",
    "gn:cc2":"ES",
    "gn:country_code":"ES",
    "gn:dem":149,
    "gn:feature_class":"P",
    "gn:feature_code":"PPL",
    "gn:name":"Erines",
    "gn:population":0,
    "gn:timezone":"Europe/Madrid",
    "iso:country":"ES",
    "name:und_x_variant":[
        "San Esteban",
        "Eirines",
        "Erines"
    ],
    "wof:name":"Erines",
    "wof:placetype":"locality"
},
  "geometry": {"coordinates":[-8.13333,43.41667],"type":"Point"}
}