{
  "type": "Feature",
  "properties": {
    "iso:country":"ES",
    "qs:a0":"Espa\u00f1a",
    "qs:a1":"*Asturias",
    "qs:a1r":"0Principado de Asturias",
    "qs:adm0":"Espa\u00f1a",
    "qs:la_lc":"*",
    "qs:level":"locality",
    "qs:loc":"Rioturbio",
    "qs:loc_alt":"Rioturbio",
    "qs:pop":0,
    "qs:type":"buffered point",
    "wof:name":"Rioturbio",
    "wof:placetype":"locality"
},
  "geometry": {"coordinates":[-5.737403,43.265204],"type":"Point"}
}