{
  "type": "Feature",
  "properties": {
    "gn:admin1_code":"55",
    "gn:admin2_code":"LE",
    "gn:admin3_code":"24063",
    "gn:asciiname":"Vega de Monasterio",
    "gn:country_code":"ES",
    "gn:dem":878,
    "gn:feature_class":"P",
    "gn:feature_code":"PPL",
    "gn:name":"Vega de Monasterio",
    "gn:population":0,
    "gn:timezone":"Europe/Madrid",
    "iso:country":"ES",
    "wof:name":"Vega de Monasterio",
    "wof:placetype":"locality"
},
  "geometry": {"coordinates":[-5.18282,42.6714],"type":"Point"}
}