{
  "type": "Feature",
  "properties": {
    "gn:admin1_code":"58",
    "gn:admin2_code":"C",
    "gn:admin3_code":"15057",
    "gn:asciiname":"Obre",
    "gn:cc2":"ES",
    "gn:country_code":"ES",
    "gn:dem":126,
    "gn:feature_class":"P",
    "gn:feature_code":"PPL",
    "gn:name":"Obre",
    "gn:population":0,
    "gn:timezone":"Europe/Madrid",
    "iso:country":"ES",
    "name:bos_x_preferred":[
        "Obre"
    ],
    "name:ceb_x_preferred":[
        "Obre"
    ],
    "name:fra_x_preferred":[
        "Obre"
    ],
    "name:hrv_x_preferred":[
        "Obre"
    ],
    "name:srp_x_preferred":[
        "\u041e\u0431\u0440\u0435"
    ],
    "name:swe_x_preferred":[
        "Obre"
    ],
    "name:und_x_variant":[
        "Santa Marina"
    ],
    "wof:name":"Obre",
    "wof:placetype":"locality"
},
  "geometry": {"coordinates":[-8.91667,42.78333],"type":"Point"}
}