{
  "type": "Feature",
  "properties": {
    "gn:admin1_code":"53",
    "gn:admin2_code":"GC",
    "gn:admin3_code":"35016",
    "gn:asciiname":"Kamwala",
    "gn:country_code":"ES",
    "gn:dem":-9999,
    "gn:feature_class":"P",
    "gn:feature_code":"PPL",
    "gn:name":"Kamwala",
    "gn:population":0,
    "gn:timezone":"Atlantic/Canary",
    "iso:country":"ES",
    "wof:name":"Kamwala",
    "wof:placetype":"locality"
},
  "geometry": {"coordinates":[-15.45226,28.29651],"type":"Point"}
}