{
  "type": "Feature",
  "properties": {
    "gn:admin1_code":"34",
    "gn:admin2_code":"O",
    "gn:admin3_code":"33073",
    "gn:asciiname":"El Fondal",
    "gn:country_code":"ES",
    "gn:dem":703,
    "gn:feature_class":"P",
    "gn:feature_code":"PPL",
    "gn:name":"El Fondal",
    "gn:population":0,
    "gn:timezone":"Europe/Madrid",
    "iso:country":"ES",
    "wof:name":"El Fondal",
    "wof:placetype":"locality"
},
  "geometry": {"coordinates":[-6.43577,43.4015],"type":"Point"}
}