{
  "type": "Feature",
  "properties": {
    "gn:admin1_code":"54",
    "gn:admin2_code":"AB",
    "gn:admin3_code":"02039",
    "gn:asciiname":"Los Morabios",
    "gn:country_code":"ES",
    "gn:dem":990,
    "gn:feature_class":"P",
    "gn:feature_code":"PPL",
    "gn:name":"Los Morabios",
    "gn:population":0,
    "gn:timezone":"Europe/Madrid",
    "iso:country":"ES",
    "name:und_x_variant":[
        "Caser\u00edo Los Morabios",
        "Casa del Morabio",
        "Los Morabios"
    ],
    "wof:name":"Los Morabios",
    "wof:placetype":"locality"
},
  "geometry": {"coordinates":[-1.49317,38.9971],"type":"Point"}
}