{
  "type": "Feature",
  "properties": {
    "gn:admin1_code":"58",
    "gn:admin2_code":"LU",
    "gn:admin3_code":"27050",
    "gn:asciiname":"Los Curras",
    "gn:country_code":"ES",
    "gn:dem":582,
    "gn:feature_class":"P",
    "gn:feature_code":"PPL",
    "gn:name":"Los Curr\u00e1s",
    "gn:population":0,
    "gn:timezone":"Europe/Madrid",
    "iso:country":"ES",
    "name:und_x_variant":[
        "Las Curras",
        "Los Curr\u00e1s"
    ],
    "wof:name":"Los Curras",
    "wof:placetype":"locality"
},
  "geometry": {"coordinates":[-7.23222,42.34343],"type":"Point"}
}