{
  "type": "Feature",
  "properties": {
    "gn:admin1_code":"56",
    "gn:admin2_code":"B",
    "gn:admin3_code":"08156",
    "gn:asciiname":"Palausolita",
    "gn:country_code":"ES",
    "gn:dem":137,
    "gn:feature_class":"P",
    "gn:feature_code":"PPL",
    "gn:name":"Palausolit\u00e0",
    "gn:population":0,
    "gn:timezone":"Europe/Madrid",
    "iso:country":"ES",
    "wof:name":"Palausolita",
    "wof:placetype":"locality"
},
  "geometry": {"coordinates":[2.16667,41.58333],"type":"Point"}
}