{
  "type": "Feature",
  "properties": {
    "gn:admin1_code":"60",
    "gn:admin2_code":"V",
    "gn:admin3_code":"46202",
    "gn:asciiname":"Torre de Baba",
    "gn:cc2":"ES",
    "gn:country_code":"ES",
    "gn:dem":101,
    "gn:feature_class":"P",
    "gn:feature_code":"PPL",
    "gn:name":"Torre de Baba",
    "gn:population":0,
    "gn:timezone":"Europe/Madrid",
    "iso:country":"ES",
    "name:und_x_variant":[
        "Caser\u00edo Torre Baba",
        "Torre de Baba"
    ],
    "wof:name":"Torre de Baba",
    "wof:placetype":"locality"
},
  "geometry": {"coordinates":[-0.53333,39.58333],"type":"Point"}
}