{
  "type": "Feature",
  "properties": {
    "gn:admin1_code":"51",
    "gn:admin2_code":"GR",
    "gn:admin3_code":"18085",
    "gn:asciiname":"Las Vinas",
    "gn:country_code":"ES",
    "gn:dem":1179,
    "gn:feature_class":"P",
    "gn:feature_code":"PPL",
    "gn:name":"Las Vi\u00f1as",
    "gn:population":0,
    "gn:timezone":"Europe/Madrid",
    "iso:country":"ES",
    "name:und_x_variant":[
        "Cortijada Las Vi\u00f1as",
        "Las Vi\u00f1as"
    ],
    "wof:name":"Las Vinas",
    "wof:placetype":"locality"
},
  "geometry": {"coordinates":[-3.01123,37.40231],"type":"Point"}
}