{
  "type": "Feature",
  "properties": {
    "gn:admin1_code":"57",
    "gn:admin2_code":"BA",
    "gn:admin3_code":"06015",
    "gn:asciiname":"Morantes",
    "gn:country_code":"ES",
    "gn:dem":224,
    "gn:feature_class":"P",
    "gn:feature_code":"PPL",
    "gn:name":"Morantes",
    "gn:population":0,
    "gn:timezone":"Europe/Madrid",
    "iso:country":"ES",
    "name:und_x_variant":[
        "Cortijo Morantes",
        "Morante",
        "Cortijo Viejo de Morantes",
        "Morantes"
    ],
    "wof:name":"Morantes",
    "wof:placetype":"locality"
},
  "geometry": {"coordinates":[-6.67008,39.04953],"type":"Point"}
}