{
  "type": "Feature",
  "properties": {
    "gn:admin1_code":"32",
    "gn:admin3_code":"31241",
    "gn:asciiname":"Adoain",
    "gn:country_code":"ES",
    "gn:dem":757,
    "gn:feature_class":"P",
    "gn:feature_code":"PPL",
    "gn:name":"Adoa\u00edn",
    "gn:population":0,
    "gn:timezone":"Europe/Madrid",
    "iso:country":"ES",
    "name:und_x_variant":[
        "Adoa\u00edn"
    ],
    "wof:name":"Adoain",
    "wof:placetype":"locality"
},
  "geometry": {"coordinates":[-1.17239,42.7906],"type":"Point"}
}