{
  "type": "Feature",
  "properties": {
    "gn:admin1_code":"52",
    "gn:admin2_code":"HU",
    "gn:admin3_code":"22158",
    "gn:asciiname":"Selgua",
    "gn:country_code":"ES",
    "gn:dem":297,
    "gn:feature_class":"P",
    "gn:feature_code":"PPL",
    "gn:name":"Selgua",
    "gn:population":0,
    "gn:timezone":"Europe/Madrid",
    "iso:country":"ES",
    "wof:name":"Selgua",
    "wof:placetype":"locality"
},
  "geometry": {"coordinates":[0.11999,41.92929],"type":"Point"}
}