{
  "type": "Feature",
  "properties": {
    "gn:admin1_code":"34",
    "gn:admin2_code":"O",
    "gn:admin3_code":"33059",
    "gn:asciiname":"Barca",
    "gn:country_code":"ES",
    "gn:dem":81,
    "gn:feature_class":"P",
    "gn:feature_code":"PPL",
    "gn:name":"Barca",
    "gn:population":0,
    "gn:timezone":"Europe/Madrid",
    "iso:country":"ES",
    "name:und_x_variant":[
        "Santiago",
        "Barca"
    ],
    "wof:name":"Barca",
    "wof:placetype":"locality"
},
  "geometry": {"coordinates":[-6.15428,43.38495],"type":"Point"}
}