{
  "type": "Feature",
  "properties": {
    "gn:country":"ES",
    "gn:fcode":"PPLA3",
    "gn:population":61,
    "iso:country":"ES",
    "name:arg_x_preferred":[
        "Irueste"
    ],
    "name:ast_x_preferred":[
        "Irueste"
    ],
    "name:bul_x_preferred":[
        "\u0418\u0440\u0443\u0435\u0441\u0442\u0435"
    ],
    "name:cat_x_preferred":[
        "Irueste"
    ],
    "name:ceb_x_preferred":[
        "Irueste"
    ],
    "name:che_x_preferred":[
        "\u0418\u0440\u0443\u044d\u0441\u0442\u0435"
    ],
    "name:eng_x_preferred":[
        "Irueste"
    ],
    "name:epo_x_preferred":[
        "Irueste"
    ],
    "name:eus_x_preferred":[
        "Irueste"
    ],
    "name:fra_x_preferred":[
        "Irueste"
    ],
    "name:gle_x_preferred":[
        "Irueste"
    ],
    "name:hun_x_preferred":[
        "Irueste"
    ],
    "name:ile_x_preferred":[
        "Irueste"
    ],
    "name:ina_x_preferred":[
        "Irueste"
    ],
    "name:ita_x_preferred":[
        "Irueste"
    ],
    "name:kaz_x_preferred":[
        "\u0418\u0440\u0443\u044d\u0441\u0442\u0435"
    ],
    "name:lld_x_preferred":[
        "Irueste"
    ],
    "name:ltz_x_preferred":[
        "Irueste"
    ],
    "name:msa_x_preferred":[
        "Irueste"
    ],
    "name:nan_x_preferred":[
        "Irueste"
    ],
    "name:nld_x_preferred":[
        "Irueste"
    ],
    "name:nob_x_preferred":[
        "Irueste"
    ],
    "name:oci_x_preferred":[
        "Irueste"
    ],
    "name:pol_x_preferred":[
        "Irueste"
    ],
    "name:por_x_preferred":[
        "Irueste"
    ],
    "name:rus_x_preferred":[
        "\u0418\u0440\u0443\u044d\u0441\u0442\u0435"
    ],
    "name:spa_x_preferred":[
        "Irueste"
    ],
    "name:swe_x_preferred":[
        "Irueste"
    ],
    "name:tat_x_preferred":[
        "\u0418\u0440\u0443\u044d\u0441\u0442\u0435"
    ],
    "name:ukr_x_preferred":[
        "\u0406\u0440\u0443\u0435\u0441\u0442\u0435"
    ],
    "name:vec_x_preferred":[
        "Irueste"
    ],
    "name:vie_x_preferred":[
        "Irueste"
    ],
    "name:war_x_preferred":[
        "Irueste"
    ],
    "name:zho_x_preferred":[
        "\u4f0a\u9c81\u57c3\u65af\u7279"
    ],
    "qs_pg:aaroncc":"ES",
    "qs_pg:gn_country":"ES",
    "qs_pg:gn_fcode":"PPLA3",
    "qs_pg:gn_pop":61,
    "qs_pg:name":"Irueste",
    "qs_pg:name_adm0":"Espa\u00f1a",
    "qs_pg:name_adm1":"Castilla-La Mancha",
    "qs_pg:photos_9k":1,
    "qs_pg:photos_9r":1,
    "qs_pg:photos_all":1,
    "qs_pg:photos_sr":0,
    "qs_pg:pop_sr":1,
    "qs_pg:qs_pg_placetype":"locality",
    "qs_pg:qs_pg_placetype_gp":"Town",
    "qs_pg:woe_adm0":23424950,
    "woe:adm0_id":23424950,
    "woe:name_adm0":"Espa\u00f1a",
    "woe:name_adm1":"Castilla-La Mancha",
    "woe:placetype":"Town",
    "wof:name":"Irueste",
    "wof:placetype":"locality",
    "wof:population":61
},
  "geometry": {"coordinates":[-2.89072,40.61206],"type":"Point"}
}