{
  "type": "Feature",
  "properties": {
    "gn:admin1_code":"39",
    "gn:admin2_code":"S",
    "gn:admin3_code":"39015",
    "gn:asciiname":"Trevino",
    "gn:country_code":"ES",
    "gn:dem":739,
    "gn:feature_class":"P",
    "gn:feature_code":"PPL",
    "gn:name":"Trevi\u00f1o",
    "gn:population":0,
    "gn:timezone":"Europe/Madrid",
    "iso:country":"ES",
    "name:deu_x_preferred":[
        "Trevino"
    ],
    "name:fra_x_preferred":[
        "Trevino"
    ],
    "name:ita_x_preferred":[
        "Trevino"
    ],
    "name:nld_x_preferred":[
        "Trevino"
    ],
    "name:rus_x_preferred":[
        "\u0422\u0440\u0435\u0432\u0438\u043d\u043e"
    ],
    "name:spa_x_preferred":[
        "Trevino"
    ],
    "name:und_x_variant":[
        "Trevi\u00f1o"
    ],
    "wof:name":"Trevino",
    "wof:placetype":"locality"
},
  "geometry": {"coordinates":[-4.72682,43.12167],"type":"Point"}
}