{
  "type": "Feature",
  "properties": {
    "gn:gn_country":"ES",
    "gn:gn_fcode":"PPLA3",
    "gn:gn_pop":207,
    "gn:population":207,
    "iso:country":"ES",
    "name:arg_x_preferred":[
        "Izagre"
    ],
    "name:baq_x_preferred":[
        "Izagre"
    ],
    "name:cat_x_preferred":[
        "Izagre"
    ],
    "name:chi_x_preferred":[
        "\u4f0a\u8428\u683c\u96f7"
    ],
    "name:dut_x_preferred":[
        "Izagre"
    ],
    "name:eng_x_preferred":[
        "Izagre"
    ],
    "name:fre_x_preferred":[
        "Izagre"
    ],
    "name:ger_x_preferred":[
        "Izagre"
    ],
    "name:glg_x_preferred":[
        "Izagre"
    ],
    "name:haw_x_preferred":[
        "Izagre"
    ],
    "name:hun_x_preferred":[
        "Izagre"
    ],
    "name:ido_x_preferred":[
        "Izagre"
    ],
    "name:ina_x_preferred":[
        "Izagre"
    ],
    "name:ita_x_preferred":[
        "Izagre"
    ],
    "name:may_x_preferred":[
        "Izagre"
    ],
    "name:nan_x_preferred":[
        "Izagre"
    ],
    "name:oci_x_preferred":[
        "Izagre"
    ],
    "name:per_x_preferred":[
        "\u0627\u06cc\u0633\u0627\u06af\u0631\u0647"
    ],
    "name:pol_x_preferred":[
        "Izagre"
    ],
    "name:por_x_preferred":[
        "Izagre"
    ],
    "name:rus_x_preferred":[
        "\u0418\u0441\u0430\u0433\u0440\u0435"
    ],
    "name:spa_x_preferred":[
        "Izagre"
    ],
    "name:swe_x_preferred":[
        "Izagre"
    ],
    "name:tpi_x_preferred":[
        "Izagre"
    ],
    "name:ukr_x_preferred":[
        "\u0406\u0441\u0430\u0433\u0440\u0435"
    ],
    "name:vie_x_preferred":[
        "Izagre"
    ],
    "name:war_x_preferred":[
        "Izagre"
    ],
    "qs_pg:aaroncc":"ES",
    "qs_pg:gn_country":"ES",
    "qs_pg:gn_fcode":"PPLA3",
    "qs_pg:gn_pop":207,
    "qs_pg:name":"Izagre",
    "qs_pg:name_adm0":"Espa\u00f1a",
    "qs_pg:name_adm1":"Castilla y Le\u00f3n",
    "qs_pg:photos_9k":1,
    "qs_pg:photos_9r":1,
    "qs_pg:photos_all":1,
    "qs_pg:photos_sr":0,
    "qs_pg:pop_sr":2,
    "qs_pg:qs_pg_placetype":"locality",
    "qs_pg:qs_pg_placetype_gp":"Town",
    "qs_pg:woe_adm0":23424950,
    "woe:adm0_id":23424950,
    "woe:name_adm0":"Espa\u00f1a",
    "woe:name_adm1":"Castilla y Le\u00f3n",
    "woe:placetype":"Town",
    "wof:name":"Izagre",
    "wof:placetype":"locality",
    "wof:population":207
},
  "geometry": {"coordinates":[-5.25727,42.2241],"type":"Point"}
}