{
  "type": "Feature",
  "properties": {
    "gn:admin1_code":"51",
    "gn:admin2_code":"AL",
    "gn:admin3_code":"04098",
    "gn:asciiname":"La Ermita del Piar",
    "gn:country_code":"ES",
    "gn:dem":696,
    "gn:feature_class":"P",
    "gn:feature_code":"PPL",
    "gn:name":"La Ermita del Piar",
    "gn:population":0,
    "gn:timezone":"Europe/Madrid",
    "iso:country":"ES",
    "name:und_x_variant":[
        "El Piar de Abajo",
        "Caser\u00edo La Ermita del Piar",
        "La Ermita del Piar"
    ],
    "wof:name":"La Ermita del Piar",
    "wof:placetype":"locality"
},
  "geometry": {"coordinates":[-2.02319,37.66539],"type":"Point"}
}