{
  "type": "Feature",
  "properties": {
    "gn:admin1_code":"55",
    "gn:admin2_code":"LE",
    "gn:admin3_code":"24092",
    "gn:asciiname":"Villaviciosa de la Ribera",
    "gn:country_code":"ES",
    "gn:dem":929,
    "gn:feature_class":"P",
    "gn:feature_code":"PPL",
    "gn:name":"Villaviciosa de la Ribera",
    "gn:population":0,
    "gn:timezone":"Europe/Madrid",
    "iso:country":"ES",
    "wof:name":"Villaviciosa de la Ribera",
    "wof:placetype":"locality"
},
  "geometry": {"coordinates":[-5.85379,42.66303],"type":"Point"}
}