{
  "type": "Feature",
  "properties": {
    "gn:gn_country":"ES",
    "gn:gn_fcode":"PPLA3",
    "gn:gn_pop":61,
    "gn:population":61,
    "iso:country":"ES",
    "name:azb_x_preferred":[
        "\u0628\u06cc\u06cc\u0627\u0645\u0648\u0626\u0631\u0627 \u062f \u0644\u0627 \u06a9\u0648\u0626\u0633\u0627"
    ],
    "name:cat_x_preferred":[
        "Villamuera de la Cueza"
    ],
    "name:eng_x_preferred":[
        "Villamuera de la Cueza"
    ],
    "name:eus_x_preferred":[
        "Villamuera de la Cueza"
    ],
    "name:fas_x_preferred":[
        "\u0628\u06cc\u06cc\u0627\u0645\u0648\u0626\u0631\u0627 \u062f \u0644\u0627 \u06a9\u0648\u0626\u0633\u0627"
    ],
    "name:fra_x_preferred":[
        "Villamuera de la Cueza"
    ],
    "name:glg_x_preferred":[
        "Villamuera de la Cueza"
    ],
    "name:hun_x_preferred":[
        "Villamuera de la Cueza"
    ],
    "name:hye_x_preferred":[
        "\u054e\u056b\u056c\u0575\u0561\u0574\u0578\u0582\u0565\u0580\u0561 \u0564\u0565 \u056c\u0561 \u053f\u0578\u0582\u0565\u057d\u0561"
    ],
    "name:ina_x_preferred":[
        "Villamuera de la Cueza"
    ],
    "name:ita_x_preferred":[
        "Villamuera de la Cueza"
    ],
    "name:msa_x_preferred":[
        "Villamuera de la Cueza"
    ],
    "name:nan_x_preferred":[
        "Villamuera de la Cueza"
    ],
    "name:nld_x_preferred":[
        "Villamuera de la Cueza"
    ],
    "name:oci_x_preferred":[
        "Villamuera de la Cueza"
    ],
    "name:pol_x_preferred":[
        "Villamuera de la Cueza"
    ],
    "name:por_x_preferred":[
        "Villamuera de la Cueza"
    ],
    "name:rus_x_preferred":[
        "\u0412\u0438\u043b\u044c\u044f\u043c\u0443\u044d\u0440\u0430-\u0434\u0435-\u043b\u0430-\u041a\u0443\u044d\u0441\u0430"
    ],
    "name:spa_x_preferred":[
        "Villamuera de la Cueza"
    ],
    "name:swe_x_preferred":[
        "Villamuera de la Cueza"
    ],
    "name:ukr_x_preferred":[
        "\u0412\u0456\u043b\u044c\u044f\u043c\u0443\u0435\u0440\u0430-\u0434\u0435-\u043b\u0430-\u041a\u0443\u0435\u0441\u0430"
    ],
    "name:uzb_x_preferred":[
        "Villamuera de la Cueza"
    ],
    "name:vie_x_preferred":[
        "Villamuera de la Cueza"
    ],
    "name:war_x_preferred":[
        "Villamuera de la Cueza"
    ],
    "name:zho_x_preferred":[
        "\u6bd4\u5229\u4e9a\u7a46\u57c3\u62c9\u5fb7\u62c9\u5e93\u57c3\u8428"
    ],
    "qs_pg:aaroncc":"ES",
    "qs_pg:gn_country":"ES",
    "qs_pg:gn_fcode":"PPLA3",
    "qs_pg:gn_pop":61,
    "qs_pg:name":"Villamuera de la Cueza",
    "qs_pg:name_adm0":"Espa\u00f1a",
    "qs_pg:name_adm1":"Castilla y Le\u00f3n",
    "qs_pg:photos_9k":1,
    "qs_pg:photos_9r":1,
    "qs_pg:photos_all":2,
    "qs_pg:photos_sr":0,
    "qs_pg:pop_sr":1,
    "qs_pg:qs_pg_placetype":"locality",
    "qs_pg:qs_pg_placetype_gp":"Town",
    "qs_pg:woe_adm0":23424950,
    "woe:adm0_id":23424950,
    "woe:name_adm0":"Espa\u00f1a",
    "woe:name_adm1":"Castilla y Le\u00f3n",
    "woe:placetype":"Town",
    "wof:name":"Villamuera de la Cueza",
    "wof:placetype":"locality",
    "wof:population":61
},
  "geometry": {"coordinates":[-4.6886,42.25843],"type":"Point"}
}