{
  "type": "Feature",
  "properties": {
    "gn:country":"ES",
    "gn:fcode":"PPLA3",
    "gn:population":87,
    "iso:country":"ES",
    "name:ara_x_preferred":[
        "\u0643\u0627\u062a\u0634\u0648\u0631\u0627\u064a\u0644\u0627"
    ],
    "name:ast_x_preferred":[
        "Cachorrilla"
    ],
    "name:cat_x_preferred":[
        "Cachorrilla"
    ],
    "name:ceb_x_preferred":[
        "Cachorrilla"
    ],
    "name:eng_x_preferred":[
        "Cachorrilla"
    ],
    "name:epo_x_preferred":[
        "Cachorrilla"
    ],
    "name:eus_x_preferred":[
        "Cachorrilla"
    ],
    "name:ext_x_preferred":[
        "Cachorrilla"
    ],
    "name:fra_x_preferred":[
        "Cachorrilla"
    ],
    "name:hun_x_preferred":[
        "Cachorrilla"
    ],
    "name:ina_x_preferred":[
        "Cachorrilla"
    ],
    "name:ita_x_preferred":[
        "Cachorrilla"
    ],
    "name:msa_x_preferred":[
        "Cachorrilla"
    ],
    "name:nan_x_preferred":[
        "Cachorrilla"
    ],
    "name:nld_x_preferred":[
        "Cachorrilla"
    ],
    "name:oci_x_preferred":[
        "Cachorrilla"
    ],
    "name:pol_x_preferred":[
        "Cachorrilla"
    ],
    "name:por_x_preferred":[
        "Cachorrilla"
    ],
    "name:ron_x_preferred":[
        "Cachorrilla"
    ],
    "name:rus_x_preferred":[
        "\u041a\u0430\u0447\u043e\u0440\u0440\u0438\u043b\u044c\u044f"
    ],
    "name:spa_x_preferred":[
        "Cachorrilla"
    ],
    "name:swe_x_preferred":[
        "Cachorrilla"
    ],
    "name:ukr_x_preferred":[
        "\u041a\u0430\u0447\u043e\u0440\u0440\u0456\u043b\u044c\u044f"
    ],
    "name:uzb_x_preferred":[
        "Cachorrilla"
    ],
    "name:vie_x_preferred":[
        "Cachorrilla"
    ],
    "name:war_x_preferred":[
        "Cachorrilla"
    ],
    "name:zho_x_preferred":[
        "\u5361\u4e54\u91cc\u5229\u4e9a"
    ],
    "qs_pg:aaroncc":"ES",
    "qs_pg:gn_country":"ES",
    "qs_pg:gn_fcode":"PPLA3",
    "qs_pg:gn_pop":87,
    "qs_pg:name":"Cachorrilla",
    "qs_pg:name_adm0":"Espa\u00f1a",
    "qs_pg:name_adm1":"Extremadura",
    "qs_pg:photos_9r":0,
    "qs_pg:photos_sr":0,
    "qs_pg:pop_sr":1,
    "qs_pg:qs_pg_placetype":"locality",
    "qs_pg:qs_pg_placetype_gp":"Town",
    "qs_pg:woe_adm0":23424950,
    "woe:adm0_id":23424950,
    "woe:name_adm0":"Espa\u00f1a",
    "woe:name_adm1":"Extremadura",
    "woe:placetype":"Town",
    "wof:name":"Cachorrilla",
    "wof:placetype":"locality",
    "wof:population":87
},
  "geometry": {"coordinates":[-6.66909,39.91557],"type":"Point"}
}