{
  "type": "Feature",
  "properties": {
    "gn:country":"ES",
    "gn:fcode":"PPLA3",
    "gn:population":517,
    "iso:country":"ES",
    "name:arg_x_preferred":[
        "Machac\u00f3n"
    ],
    "name:ast_x_preferred":[
        "Machac\u00f3n"
    ],
    "name:cat_x_preferred":[
        "Machac\u00f3n"
    ],
    "name:ceb_x_preferred":[
        "Machac\u00f3n"
    ],
    "name:eng_x_preferred":[
        "Machac\u00f3n"
    ],
    "name:eus_x_preferred":[
        "Machac\u00f3n"
    ],
    "name:fra_x_preferred":[
        "Machac\u00f3n"
    ],
    "name:haw_x_preferred":[
        "Machac\u00f3n"
    ],
    "name:hun_x_preferred":[
        "Machac\u00f3n"
    ],
    "name:ina_x_preferred":[
        "Machac\u00f3n"
    ],
    "name:ita_x_preferred":[
        "Machac\u00f3n"
    ],
    "name:kaz_x_preferred":[
        "\u041c\u0430\u0447\u0430\u043a\u043e\u043d"
    ],
    "name:lit_x_preferred":[
        "Ma\u010dakonas"
    ],
    "name:msa_x_preferred":[
        "Machac\u00f3n"
    ],
    "name:nan_x_preferred":[
        "Machac\u00f3n"
    ],
    "name:nld_x_preferred":[
        "Machac\u00f3n"
    ],
    "name:oci_x_preferred":[
        "Machac\u00f3n"
    ],
    "name:pol_x_preferred":[
        "Machac\u00f3n"
    ],
    "name:por_x_preferred":[
        "Machac\u00f3n"
    ],
    "name:rus_x_preferred":[
        "\u041c\u0430\u0447\u0430\u043a\u043e\u043d"
    ],
    "name:spa_x_preferred":[
        "Machac\u00f3n"
    ],
    "name:swe_x_preferred":[
        "Machac\u00f3n"
    ],
    "name:ukr_x_preferred":[
        "\u041c\u0430\u0447\u0430\u043a\u043e\u043d"
    ],
    "name:vie_x_preferred":[
        "Machac\u00f3n"
    ],
    "name:war_x_preferred":[
        "Machac\u00f3n"
    ],
    "name:zho_x_preferred":[
        "\u9a6c\u67e5\u5b54"
    ],
    "qs_pg:aaroncc":"ES",
    "qs_pg:gn_country":"ES",
    "qs_pg:gn_fcode":"PPLA3",
    "qs_pg:gn_pop":517,
    "qs_pg:name":"Machac\u00f3n",
    "qs_pg:name_adm0":"Espa\u00f1a",
    "qs_pg:name_adm1":"Castilla y Le\u00f3n",
    "qs_pg:photos_9r":0,
    "qs_pg:photos_sr":0,
    "qs_pg:pop_sr":2,
    "qs_pg:qs_pg_placetype":"locality",
    "qs_pg:qs_pg_placetype_gp":"Town",
    "qs_pg:woe_adm0":23424950,
    "woe:adm0_id":23424950,
    "woe:name_adm0":"Espa\u00f1a",
    "woe:name_adm1":"Castilla y Le\u00f3n",
    "woe:placetype":"Town",
    "wof:name":"Machac\u00f3n",
    "wof:placetype":"locality",
    "wof:population":517
},
  "geometry": {"coordinates":[-5.5243,40.92623],"type":"Point"}
}