{
  "type": "Feature",
  "properties": {
    "gn:country":"ES",
    "gn:fcode":"PPLL",
    "gn:population":0,
    "iso:country":"ES",
    "name:cat_x_preferred":[
        "Can Picafort"
    ],
    "name:deu_x_preferred":[
        "Can Picafort"
    ],
    "name:eng_x_preferred":[
        "Can Picafort"
    ],
    "name:eng_x_variant":[
        "Ca'n Picafort"
    ],
    "name:fra_x_preferred":[
        "Can Picafort"
    ],
    "name:nld_x_preferred":[
        "Can Picafort"
    ],
    "name:spa_x_preferred":[
        "Can Picafort"
    ],
    "name:spa_x_variant":[
        "Ca'n Picafort"
    ],
    "qs_pg:aaroncc":"ES",
    "qs_pg:gn_country":"ES",
    "qs_pg:gn_fcode":"PPLL",
    "qs_pg:gn_pop":0,
    "qs_pg:name":"Ca'n Picafort",
    "qs_pg:name_adm0":"Espa\u00f1a",
    "qs_pg:name_adm1":"Illes Balears",
    "qs_pg:photos":1701,
    "qs_pg:photos_1k":345,
    "qs_pg:photos_9k":8,
    "qs_pg:photos_9r":8,
    "qs_pg:photos_all":1701,
    "qs_pg:photos_sr":14,
    "qs_pg:pop_sr":0,
    "qs_pg:qs_pg_placetype":"locality",
    "qs_pg:qs_pg_placetype_gp":"Town",
    "qs_pg:woe_adm0":23424950,
    "woe:adm0_id":23424950,
    "woe:name_adm0":"Espa\u00f1a",
    "woe:name_adm1":"Illes Balears",
    "woe:placetype":"Town",
    "wof:name":"Ca'n Picafort",
    "wof:placetype":"locality"
},
  "geometry": {"coordinates":[3.15307,39.76385],"type":"Point"}
}