{
  "type": "Feature",
  "properties": {
    "gn:admin1_code":"55",
    "gn:admin2_code":"BU",
    "gn:admin3_code":"09054",
    "gn:asciiname":"Villanueva-Soportilla",
    "gn:country_code":"ES",
    "gn:dem":531,
    "gn:feature_class":"P",
    "gn:feature_code":"PPL",
    "gn:name":"Villanueva-Soportilla",
    "gn:population":0,
    "gn:timezone":"Europe/Madrid",
    "iso:country":"ES",
    "wof:name":"Villanueva-Soportilla",
    "wof:placetype":"locality"
},
  "geometry": {"coordinates":[-3.07448,42.74601],"type":"Point"}
}