{
  "type": "Feature",
  "properties": {
    "gn:admin1_code":"55",
    "gn:admin2_code":"BU",
    "gn:admin3_code":"09209",
    "gn:asciiname":"Villate",
    "gn:country_code":"ES",
    "gn:dem":646,
    "gn:feature_class":"P",
    "gn:feature_code":"PPL",
    "gn:name":"Villate",
    "gn:population":0,
    "gn:timezone":"Europe/Madrid",
    "iso:country":"ES",
    "name:arg_x_preferred":[
        "Vilata"
    ],
    "name:bug_x_preferred":[
        "Villate"
    ],
    "name:cat_x_preferred":[
        "Vilata"
    ],
    "name:ceb_x_preferred":[
        "Villate"
    ],
    "name:deu_x_preferred":[
        "Villate"
    ],
    "name:eus_x_preferred":[
        "Villate"
    ],
    "name:fra_x_preferred":[
        "Villate"
    ],
    "name:hun_x_preferred":[
        "Villate"
    ],
    "name:ind_x_preferred":[
        "Villate"
    ],
    "name:ita_x_preferred":[
        "Villate"
    ],
    "name:lat_x_preferred":[
        "Villate"
    ],
    "name:msa_x_preferred":[
        "Villate"
    ],
    "name:nld_x_preferred":[
        "Villate"
    ],
    "name:oci_x_preferred":[
        "Vilata"
    ],
    "name:pms_x_preferred":[
        "Villate"
    ],
    "name:pol_x_preferred":[
        "Villate"
    ],
    "name:por_x_preferred":[
        "Villate"
    ],
    "name:ron_x_preferred":[
        "Villate"
    ],
    "name:rus_x_preferred":[
        "\u0412\u0438\u043b\u043b\u0430\u0442"
    ],
    "name:slk_x_preferred":[
        "Villate"
    ],
    "name:spa_x_preferred":[
        "Villate"
    ],
    "name:swe_x_preferred":[
        "Villate"
    ],
    "name:ukr_x_preferred":[
        "\u0412\u0456\u043b\u043b\u0430\u0442"
    ],
    "name:vie_x_preferred":[
        "Villate"
    ],
    "name:vol_x_preferred":[
        "Villate"
    ],
    "name:war_x_preferred":[
        "Villate"
    ],
    "name:zho_x_preferred":[
        "\u7ef4\u62c9\u7279"
    ],
    "wof:name":"Villate",
    "wof:placetype":"locality"
},
  "geometry": {"coordinates":[-3.38107,42.96341],"type":"Point"}
}