{
  "type": "Feature",
  "properties": {
    "gn:admin1_code":"32",
    "gn:admin3_code":"31186",
    "gn:asciiname":"Latasa",
    "gn:country_code":"ES",
    "gn:dem":511,
    "gn:feature_class":"P",
    "gn:feature_code":"PPL",
    "gn:name":"Latasa",
    "gn:population":0,
    "gn:timezone":"Europe/Madrid",
    "iso:country":"ES",
    "wof:name":"Latasa",
    "wof:placetype":"locality"
},
  "geometry": {"coordinates":[-1.65,42.95],"type":"Point"}
}