{
  "type": "Feature",
  "properties": {
    "gn:admin1_code":"34",
    "gn:admin2_code":"O",
    "gn:admin3_code":"33072",
    "gn:asciiname":"Barrio",
    "gn:country_code":"ES",
    "gn:dem":756,
    "gn:feature_class":"P",
    "gn:feature_code":"PPL",
    "gn:name":"Barrio",
    "gn:population":0,
    "gn:timezone":"Europe/Madrid",
    "iso:country":"ES",
    "name:deu_x_preferred":[
        "Barrio"
    ],
    "name:hun_x_preferred":[
        "Barrio"
    ],
    "name:ilo_x_preferred":[
        "Barrio"
    ],
    "name:ind_x_preferred":[
        "Barrio"
    ],
    "name:ita_x_preferred":[
        "Barrio"
    ],
    "name:lat_x_preferred":[
        "Barrium"
    ],
    "name:scn_x_preferred":[
        "Barrio"
    ],
    "name:spa_x_preferred":[
        "Barrio"
    ],
    "name:swe_x_preferred":[
        "Barrio"
    ],
    "name:tur_x_preferred":[
        "Barrio"
    ],
    "wof:name":"Barrio",
    "wof:placetype":"locality"
},
  "geometry": {"coordinates":[-6.0997,43.11655],"type":"Point"}
}