{
  "type": "Feature",
  "properties": {
    "gn:admin1_code":"57",
    "gn:admin2_code":"BA",
    "gn:admin3_code":"06059",
    "gn:asciiname":"Granja de Torrehermosa",
    "gn:country_code":"ES",
    "gn:dem":565,
    "gn:feature_class":"P",
    "gn:feature_code":"PPLA3",
    "gn:name":"Granja de Torrehermosa",
    "gn:population":2475,
    "gn:timezone":"Europe/Madrid",
    "iso:country":"ES",
    "name:ara_x_preferred":[
        "\u063a\u0631\u0627\u0646\u062c\u0627 \u062f\u064a \u062a\u0648\u0631\u064a\u0647\u064a\u0631\u0645\u0648\u0633\u0627"
    ],
    "name:mkd_x_preferred":[
        "\u0413\u0440\u0430\u043d\u0445\u0430 \u0434\u0435 \u0422\u043e\u0440\u0435\u0435\u0440\u043c\u043e\u0441\u0430"
    ],
    "name:rus_x_preferred":[
        "\u0413\u0440\u0430\u043d\u0445\u0430-\u0434\u0435-\u0422\u043e\u0440\u0440\u0435\u044d\u0440\u043c\u043e\u0441\u0430"
    ],
    "name:ukr_x_preferred":[
        "\u0413\u0440\u0430\u043d\u0445\u0430-\u0434\u0435-\u0422\u043e\u0440\u0440\u0435\u0435\u0440\u043c\u043e\u0441\u0430"
    ],
    "name:zho_x_preferred":[
        "\u683c\u5170\u54c8\u5fb7\u6258\u96f7\u57c3\u5c14\u83ab\u8428"
    ],
    "wof:name":"Granja de Torrehermosa",
    "wof:placetype":"locality",
    "wof:population":2475
},
  "geometry": {"coordinates":[-5.58333,38.31667],"type":"Point"}
}