{
  "type": "Feature",
  "properties": {
    "gn:admin1_code":"39",
    "gn:admin2_code":"S",
    "gn:admin3_code":"39096.0",
    "gn:asciiname":"Soberado",
    "gn:country_code":"ES",
    "gn:dem":556,
    "gn:feature_class":"P",
    "gn:feature_code":"PPL",
    "gn:name":"Soberado",
    "gn:population":0,
    "gn:timezone":"Europe/Madrid",
    "iso:country":"ES",
    "wof:name":"Soberado",
    "wof:placetype":"locality"
},
  "geometry": {"coordinates":[-4.63112,43.08309000000001],"type":"Point"}
}