{
  "type": "Feature",
  "properties": {
    "gn:admin1_code":"34",
    "gn:admin2_code":"O",
    "gn:admin3_code":"33034",
    "gn:asciiname":"Villar de Carcedo",
    "gn:country_code":"ES",
    "gn:dem":296,
    "gn:feature_class":"P",
    "gn:feature_code":"PPL",
    "gn:name":"Villar de Carcedo",
    "gn:population":0,
    "gn:timezone":"Europe/Madrid",
    "iso:country":"ES",
    "wof:name":"Villar de Carcedo",
    "wof:placetype":"locality"
},
  "geometry": {"coordinates":[-6.41266,43.49243],"type":"Point"}
}