{
  "type": "Feature",
  "properties": {
    "gn:admin1_code":"34",
    "gn:admin2_code":"O",
    "gn:admin3_code":"33048",
    "gn:asciiname":"Seran",
    "gn:country_code":"ES",
    "gn:dem":475,
    "gn:feature_class":"P",
    "gn:feature_code":"PPL",
    "gn:name":"Ser\u00e1n",
    "gn:population":0,
    "gn:timezone":"Europe/Madrid",
    "iso:country":"ES",
    "wof:name":"Seran",
    "wof:placetype":"locality"
},
  "geometry": {"coordinates":[-6.85,43.26667],"type":"Point"}
}