{
  "type": "Feature",
  "properties": {
    "gn:admin1_code":"34",
    "gn:admin2_code":"O",
    "gn:admin3_code":"33054",
    "gn:asciiname":"Alcedo",
    "gn:country_code":"ES",
    "gn:dem":273,
    "gn:feature_class":"P",
    "gn:feature_code":"PPL",
    "gn:name":"Alcedo",
    "gn:population":0,
    "gn:timezone":"Europe/Madrid",
    "iso:country":"ES",
    "name:ara_x_preferred":[
        "\u0627\u0644\u0633\u064a\u062f\u0648"
    ],
    "name:bre_x_preferred":[
        "Alcedo"
    ],
    "name:cat_x_preferred":[
        "Alcedo"
    ],
    "name:ceb_x_preferred":[
        "Alcedo"
    ],
    "name:ces_x_preferred":[
        "Alcedo"
    ],
    "name:deu_x_preferred":[
        "Alcedo"
    ],
    "name:epo_x_preferred":[
        "Alcedo"
    ],
    "name:est_x_preferred":[
        "J\u00e4\u00e4lind"
    ],
    "name:eus_x_preferred":[
        "Alcedo"
    ],
    "name:fra_x_preferred":[
        "Alcedo"
    ],
    "name:hun_x_preferred":[
        "Alcedo"
    ],
    "name:hye_x_preferred":[
        "\u0531\u056c\u056f\u0565\u0564\u0578"
    ],
    "name:ido_x_preferred":[
        "Alcedo"
    ],
    "name:ita_x_preferred":[
        "Alcedo"
    ],
    "name:jpn_x_preferred":[
        "\u30ab\u30ef\u30bb\u30df\u5c5e"
    ],
    "name:kat_x_preferred":[
        "\u10d0\u10da\u10d9\u10e3\u10dc\u10d8"
    ],
    "name:kaz_x_preferred":[
        "\u0417\u044b\u043c\u044b\u0440\u0430\u043d\u0434\u0430\u0440 \u0442\u0443\u044b\u0441\u044b"
    ],
    "name:kbd_x_preferred":[
        "\u041f\u0441\u044b\u043a\u044a\u0443\u0430\u0440\u0433\u044a\u0445\u044d\u0440"
    ],
    "name:lav_x_preferred":[
        "Zivju dzen\u012b\u0161i"
    ],
    "name:lit_x_preferred":[
        "Tul\u017eiai"
    ],
    "name:nld_x_preferred":[
        "Alcedo"
    ],
    "name:nor_x_preferred":[
        "Alcedo"
    ],
    "name:pol_x_preferred":[
        "Alcedo"
    ],
    "name:por_x_preferred":[
        "Alcedo"
    ],
    "name:ron_x_preferred":[
        "Alcedo"
    ],
    "name:rus_x_preferred":[
        "\u0417\u0438\u043c\u043e\u0440\u043e\u0434\u043a\u0438"
    ],
    "name:spa_x_preferred":[
        "Alcedo"
    ],
    "name:swe_x_preferred":[
        "Alcedo"
    ],
    "name:war_x_preferred":[
        "Alcedo"
    ],
    "name:zho_x_preferred":[
        "\u7fe0\u9e1f\u5c5e"
    ],
    "wof:name":"Alcedo",
    "wof:placetype":"locality"
},
  "geometry": {"coordinates":[-5.98307,43.43579],"type":"Point"}
}