{
  "type": "Feature",
  "properties": {
    "gn:admin1_code":"34",
    "gn:admin2_code":"O",
    "gn:admin3_code":"33054",
    "gn:asciiname":"Alcedo",
    "gn:country_code":"ES",
    "gn:dem":273,
    "gn:feature_class":"P",
    "gn:feature_code":"PPL",
    "gn:name":"Alcedo",
    "gn:population":0,
    "gn:timezone":"Europe/Madrid",
    "iso:country":"ES",
    "wof:name":"Alcedo",
    "wof:placetype":"locality"
},
  "geometry": {"coordinates":[-5.98307,43.43579],"type":"Point"}
}