{
  "type": "Feature",
  "properties": {
    "gn:country":"ES",
    "gn:fcode":"PPL",
    "gn:population":315,
    "iso:country":"ES",
    "name:ara_x_preferred":[
        "\u0625\u0644 \u062c\u0648\u0631\u062f\u0648"
    ],
    "name:arz_x_preferred":[
        "\u0627\u0644 \u062c\u0648\u0631\u062f\u0648"
    ],
    "name:ast_x_preferred":[
        "El Gordo"
    ],
    "name:cat_x_preferred":[
        "El Gordo"
    ],
    "name:ceb_x_preferred":[
        "El Gordo"
    ],
    "name:che_x_preferred":[
        "\u042d\u043b\u044c-\u0413\u043e\u0440\u0434\u043e"
    ],
    "name:eng_x_preferred":[
        "El Gordo"
    ],
    "name:epo_x_preferred":[
        "El Gordo"
    ],
    "name:eus_x_preferred":[
        "El Gordo"
    ],
    "name:fas_x_preferred":[
        "\u0627\u0644 \u06af\u0648\u0631\u062f\u0648"
    ],
    "name:fra_x_preferred":[
        "El Gordo"
    ],
    "name:gle_x_preferred":[
        "El Gordo"
    ],
    "name:hun_x_preferred":[
        "El Gordo"
    ],
    "name:ina_x_preferred":[
        "El Gordo"
    ],
    "name:ita_x_preferred":[
        "El Gordo"
    ],
    "name:kat_x_preferred":[
        "\u10d4\u10da-\u10d2\u10dd\u10e0\u10d3\u10dd"
    ],
    "name:lld_x_preferred":[
        "El Gordo"
    ],
    "name:ltz_x_preferred":[
        "El Gordo"
    ],
    "name:msa_x_preferred":[
        "El Gordo"
    ],
    "name:nld_x_preferred":[
        "El Gordo"
    ],
    "name:nob_x_preferred":[
        "El Gordo"
    ],
    "name:oci_x_preferred":[
        "El Gordo"
    ],
    "name:pol_x_preferred":[
        "El Gordo"
    ],
    "name:por_x_preferred":[
        "El Gordo"
    ],
    "name:ron_x_preferred":[
        "El Gordo"
    ],
    "name:rus_x_preferred":[
        "\u042d\u043b\u044c-\u0413\u043e\u0440\u0434\u043e"
    ],
    "name:spa_x_preferred":[
        "El Gordo"
    ],
    "name:swe_x_preferred":[
        "El Gordo"
    ],
    "name:swe_x_variant":[
        "EL Gordo"
    ],
    "name:tat_x_preferred":[
        "\u042d\u043b\u044c-\u0413\u043e\u0440\u0434\u043e"
    ],
    "name:ukr_x_preferred":[
        "\u0415\u043b\u044c-\u0413\u043e\u0440\u0434\u043e"
    ],
    "name:vec_x_preferred":[
        "El Gordo"
    ],
    "name:vie_x_preferred":[
        "El Gordo"
    ],
    "name:war_x_preferred":[
        "El Gordo"
    ],
    "name:zho_x_preferred":[
        "\u57c3\u5c14\u6208\u5c14\u591a"
    ],
    "qs_pg:aaroncc":"ES",
    "qs_pg:gn_country":"ES",
    "qs_pg:gn_fcode":"PPL",
    "qs_pg:gn_pop":315,
    "qs_pg:name":"El Gordo",
    "qs_pg:name_adm0":"Espa\u00f1a",
    "qs_pg:name_adm1":"Extremadura",
    "qs_pg:photos_9k":1,
    "qs_pg:photos_9r":1,
    "qs_pg:photos_all":1,
    "qs_pg:photos_sr":0,
    "qs_pg:pop_sr":2,
    "qs_pg:qs_pg_placetype":"locality",
    "qs_pg:qs_pg_placetype_gp":"Town",
    "qs_pg:woe_adm0":23424950,
    "woe:adm0_id":23424950,
    "woe:name_adm0":"Espa\u00f1a",
    "woe:name_adm1":"Extremadura",
    "woe:placetype":"Town",
    "wof:name":"El Gordo",
    "wof:placetype":"locality",
    "wof:population":315
},
  "geometry": {"coordinates":[-5.34343,39.8656],"type":"Point"}
}