{
  "type": "Feature",
  "properties": {
    "gn:admin1_code":"54",
    "gn:admin2_code":"AB",
    "gn:admin3_code":"02003",
    "gn:asciiname":"Casa Grande",
    "gn:country_code":"ES",
    "gn:dem":683,
    "gn:feature_class":"P",
    "gn:feature_code":"PPL",
    "gn:name":"Casa Grande",
    "gn:population":0,
    "gn:timezone":"Europe/Madrid",
    "iso:country":"ES",
    "wof:name":"Casa Grande",
    "wof:placetype":"locality"
},
  "geometry": {"coordinates":[-1.96776,39.03867],"type":"Point"}
}