{
  "type": "Feature",
  "properties": {
    "gn:admin1_code":"51",
    "gn:admin2_code":"J",
    "gn:admin3_code":"23009",
    "gn:asciiname":"Jarafe",
    "gn:country_code":"ES",
    "gn:dem":434,
    "gn:feature_class":"P",
    "gn:feature_code":"PPL",
    "gn:name":"Jarafe",
    "gn:population":0,
    "gn:timezone":"Europe/Madrid",
    "iso:country":"ES",
    "name:und_x_variant":[
        "Caser\u00edo Jarafe",
        "Jarafe"
    ],
    "wof:name":"Jarafe",
    "wof:placetype":"locality"
},
  "geometry": {"coordinates":[-3.56122,37.88963],"type":"Point"}
}