{
  "type": "Feature",
  "properties": {
    "iso:country":"ES",
    "wof:name":"L'Illa Perduda",
    "wof:placetype":"neighbourhood"
},
  "geometry": {"coordinates":[-0.34195065555578,39.46989209781481],"type":"Point"}
}