{
  "type": "Feature",
  "properties": {
    "gn:admin1_code":"51",
    "gn:admin2_code":"AL",
    "gn:admin3_code":"4032.0",
    "gn:asciiname":"Gafares",
    "gn:country_code":"ES",
    "gn:dem":203,
    "gn:feature_class":"P",
    "gn:feature_code":"PPL",
    "gn:name":"Gafares",
    "gn:population":37,
    "gn:timezone":"Europe/Madrid",
    "iso:country":"ES",
    "name:eng_x_preferred":[
        "Los Alamillos"
    ],
    "name:spa_x_preferred":[
        "Los Alamillos"
    ],
    "wof:name":"Gafares",
    "wof:placetype":"locality",
    "wof:population":37
},
  "geometry": {"coordinates":[-1.99361,37.01611],"type":"Point"}
}