{
  "type": "Feature",
  "properties": {
    "gn:admin1_code":"57",
    "gn:admin2_code":"BA",
    "gn:admin3_code":"06022",
    "gn:asciiname":"Sierra Gorda",
    "gn:country_code":"ES",
    "gn:dem":560,
    "gn:feature_class":"P",
    "gn:feature_code":"PPL",
    "gn:name":"Sierra Gorda",
    "gn:population":0,
    "gn:timezone":"Europe/Madrid",
    "iso:country":"ES",
    "name:deu_x_preferred":[
        "Sierra Gorda"
    ],
    "name:fra_x_preferred":[
        "Sierra Gorda"
    ],
    "name:hrv_x_preferred":[
        "Sierra Gorda"
    ],
    "name:kor_x_preferred":[
        "\uc2dc\uc5d0\ub77c\uace0\ub974\ub2e4"
    ],
    "name:por_x_preferred":[
        "Sierra Gorda"
    ],
    "name:spa_x_preferred":[
        "Sierra Gorda"
    ],
    "name:und_x_variant":[
        "Cortijo Sierra Gorda"
    ],
    "name:vie_x_preferred":[
        "Sierra Gorda"
    ],
    "wof:name":"Sierra Gorda",
    "wof:placetype":"locality"
},
  "geometry": {"coordinates":[-6.53784,38.42669],"type":"Point"}
}