{
  "type": "Feature",
  "properties": {
    "gn:admin1_code":"57",
    "gn:admin2_code":"BA",
    "gn:admin3_code":"06022",
    "gn:asciiname":"Sierra Gorda",
    "gn:country_code":"ES",
    "gn:dem":560,
    "gn:feature_class":"P",
    "gn:feature_code":"PPL",
    "gn:name":"Sierra Gorda",
    "gn:population":0,
    "gn:timezone":"Europe/Madrid",
    "iso:country":"ES",
    "name:und_x_variant":[
        "Cortijo Sierra Gorda",
        "Sierra Gorda"
    ],
    "wof:name":"Sierra Gorda",
    "wof:placetype":"locality"
},
  "geometry": {"coordinates":[-6.53784,38.42669],"type":"Point"}
}