{
  "type": "Feature",
  "properties": {
    "gn:admin1_code":"51",
    "gn:admin2_code":"J",
    "gn:admin3_code":"23009",
    "gn:asciiname":"Garciez-Jimena",
    "gn:country_code":"ES",
    "gn:dem":310,
    "gn:feature_class":"P",
    "gn:feature_code":"PPL",
    "gn:name":"Garc\u00edez-Jimena",
    "gn:population":0,
    "gn:timezone":"Europe/Madrid",
    "iso:country":"ES",
    "name:und_x_variant":[
        "Estaci\u00f3n Garciez-Jimena",
        "Garc\u00edez-Jimena"
    ],
    "wof:name":"Garciez-Jimena",
    "wof:placetype":"locality"
},
  "geometry": {"coordinates":[-3.46243,37.92637],"type":"Point"}
}