{
  "type": "Feature",
  "properties": {
    "gn:admin1_code":"32",
    "gn:admin3_code":"31049",
    "gn:asciiname":"Garzaron",
    "gn:cc2":"ES",
    "gn:country_code":"ES",
    "gn:dem":583,
    "gn:feature_class":"P",
    "gn:feature_code":"PPL",
    "gn:name":"Garzar\u00f3n",
    "gn:population":0,
    "gn:timezone":"Europe/Madrid",
    "iso:country":"ES",
    "name:und_x_variant":[
        "Carzar\u00f3n"
    ],
    "wof:name":"Garzaron",
    "wof:placetype":"locality"
},
  "geometry": {"coordinates":[-1.77472,42.9985],"type":"Point"}
}