{
  "type": "Feature",
  "properties": {
    "gn:admin1_code":"31",
    "gn:admin2_code":"MU",
    "gn:admin3_code":"30030",
    "gn:asciiname":"Los Banos",
    "gn:country_code":"ES",
    "gn:dem":287,
    "gn:feature_class":"P",
    "gn:feature_code":"PPL",
    "gn:name":"Los Ba\u00f1os",
    "gn:population":0,
    "gn:timezone":"Europe/Madrid",
    "iso:country":"ES",
    "name:ceb_x_preferred":[
        "Los Ba\u00f1os"
    ],
    "name:deu_x_preferred":[
        "Los Ba\u00f1os"
    ],
    "name:eng_x_preferred":[
        "Banos y Mendigo"
    ],
    "name:fra_x_preferred":[
        "Los Banos"
    ],
    "name:spa_x_preferred":[
        "Los Ba\u00f1os"
    ],
    "name:swe_x_preferred":[
        "Los Ba\u00f1os"
    ],
    "name:und_x_variant":[
        "Caser\u00edo Los Ba\u00f1os",
        "Casa Los Ba\u00f1os"
    ],
    "wof:name":"Los Banos",
    "wof:placetype":"locality"
},
  "geometry": {"coordinates":[-1.13184,37.86845],"type":"Point"}
}