{
  "type": "Feature",
  "properties": {
    "gn:admin1_code":"60",
    "gn:admin2_code":"CS",
    "gn:admin3_code":"12902",
    "gn:asciiname":"Masia de Mollet",
    "gn:country_code":"ES",
    "gn:dem":509,
    "gn:feature_class":"P",
    "gn:feature_code":"PPL",
    "gn:name":"Mas\u00eda de Mollet",
    "gn:population":0,
    "gn:timezone":"Europe/Madrid",
    "iso:country":"ES",
    "name:und_x_variant":[
        "Mas de Mollet",
        "Mas\u00eda de Mollet"
    ],
    "wof:name":"Masia de Mollet",
    "wof:placetype":"locality"
},
  "geometry": {"coordinates":[-0.08074,40.07867],"type":"Point"}
}