{
  "type": "Feature",
  "properties": {
    "gn:admin1_code":"34",
    "gn:admin2_code":"O",
    "gn:admin3_code":"33072",
    "gn:asciiname":"San Salvador",
    "gn:country_code":"ES",
    "gn:dem":575,
    "gn:feature_class":"P",
    "gn:feature_code":"PPL",
    "gn:name":"San Salvador",
    "gn:population":0,
    "gn:timezone":"Europe/Madrid",
    "iso:country":"ES",
    "wof:name":"San Salvador",
    "wof:placetype":"locality"
},
  "geometry": {"coordinates":[-6.07369,43.1343],"type":"Point"}
}