{
  "type": "Feature",
  "properties": {
    "gn:admin1_code":"55",
    "gn:admin2_code":"ZA",
    "gn:admin3_code":"49206",
    "gn:asciiname":"San Pedro de la Vina",
    "gn:country_code":"ES",
    "gn:dem":751,
    "gn:feature_class":"P",
    "gn:feature_code":"PPL",
    "gn:name":"San Pedro de la Vi\u00f1a",
    "gn:population":0,
    "gn:timezone":"Europe/Madrid",
    "iso:country":"ES",
    "name:und_x_variant":[
        "San Pedro de la Vi\u00f1a"
    ],
    "wof:name":"San Pedro de la Vina",
    "wof:placetype":"locality"
},
  "geometry": {"coordinates":[-6.01906,42.09937],"type":"Point"}
}