{
  "type": "Feature",
  "properties": {
    "gn:admin1_code":"39",
    "gn:admin2_code":"S",
    "gn:admin3_code":"39054",
    "gn:asciiname":"Posadillo",
    "gn:country_code":"ES",
    "gn:dem":36,
    "gn:feature_class":"P",
    "gn:feature_code":"PPL",
    "gn:name":"Posadillo",
    "gn:population":0,
    "gn:timezone":"Europe/Madrid",
    "iso:country":"ES",
    "wof:name":"Posadillo",
    "wof:placetype":"locality"
},
  "geometry": {"coordinates":[-4.01752,43.37605],"type":"Point"}
}