{
  "type": "Feature",
  "properties": {
    "gn:country":"ES",
    "gn:fcode":"PPLL",
    "gn:population":24846,
    "iso:country":"ES",
    "qs_pg:aaroncc":"ES",
    "qs_pg:gn_country":"ES",
    "qs_pg:gn_fcode":"PPLL",
    "qs_pg:gn_pop":24846,
    "qs_pg:name":"Iturrama",
    "qs_pg:photos_9r":0,
    "qs_pg:photos_sr":0,
    "qs_pg:pop_sr":7,
    "qs_pg:qs_pg_placetype":"locality",
    "wof:name":"Iturrama",
    "wof:placetype":"locality",
    "wof:population":24846
},
  "geometry": {"coordinates":[-1.65825,42.80847],"type":"Point"}
}