{
  "type": "Feature",
  "properties": {
    "gn:admin1_code":"34",
    "gn:admin2_code":"O",
    "gn:admin3_code":"33028",
    "gn:asciiname":"Luina",
    "gn:country_code":"ES",
    "gn:dem":704,
    "gn:feature_class":"P",
    "gn:feature_code":"PPL",
    "gn:name":"Lui\u00f1a",
    "gn:population":0,
    "gn:timezone":"Europe/Madrid",
    "iso:country":"ES",
    "name:und_x_variant":[
        "San Mart\u00edn",
        "San Mart\u00edn de Lui\u00f1a",
        "Lui\u00f1a"
    ],
    "wof:name":"Luina",
    "wof:placetype":"locality"
},
  "geometry": {"coordinates":[-6.76578,42.91896],"type":"Point"}
}