{
  "type": "Feature",
  "properties": {
    "gn:admin1_code":"51",
    "gn:admin2_code":"GR",
    "gn:admin3_code":"18013",
    "gn:asciiname":"Los Banos",
    "gn:country_code":"ES",
    "gn:dem":781,
    "gn:feature_class":"P",
    "gn:feature_code":"PPL",
    "gn:name":"Los Ba\u00f1os",
    "gn:population":0,
    "gn:timezone":"Europe/Madrid",
    "iso:country":"ES",
    "name:ceb_x_preferred":[
        "Los Ba\u00f1os"
    ],
    "name:deu_x_preferred":[
        "Los Ba\u00f1os"
    ],
    "name:fra_x_preferred":[
        "Los Banos"
    ],
    "name:spa_x_preferred":[
        "Los Ba\u00f1os"
    ],
    "name:swe_x_preferred":[
        "Los Ba\u00f1os"
    ],
    "wof:name":"Los Banos",
    "wof:placetype":"locality"
},
  "geometry": {"coordinates":[-3.98357,37.02045],"type":"Point"}
}