{
  "type": "Feature",
  "properties": {
    "gn:country":"ES",
    "gn:fcode":"PPL",
    "gn:population":174,
    "iso:country":"ES",
    "name:arg_x_preferred":[
        "Vilam\u00f2s"
    ],
    "name:ast_x_preferred":[
        "Vilam\u00f2s"
    ],
    "name:cat_x_preferred":[
        "Vilam\u00f2s"
    ],
    "name:ceb_x_preferred":[
        "Vilam\u00f3s"
    ],
    "name:che_x_preferred":[
        "\u0412\u0438\u043b\u0430\u043c\u043e\u0441"
    ],
    "name:deu_x_preferred":[
        "Vilam\u00f2s"
    ],
    "name:eng_x_preferred":[
        "Vilam\u00f2s"
    ],
    "name:eus_x_preferred":[
        "Vilam\u00f2s"
    ],
    "name:fra_x_preferred":[
        "Vilam\u00f2s"
    ],
    "name:gle_x_preferred":[
        "Vilam\u00f2s"
    ],
    "name:glg_x_preferred":[
        "Vilam\u00f2s"
    ],
    "name:hun_x_preferred":[
        "Vilam\u00f2s"
    ],
    "name:hye_x_preferred":[
        "\u054e\u056b\u056c\u0561\u0574\u0578\u057d"
    ],
    "name:ile_x_preferred":[
        "Vilam\u00f2s"
    ],
    "name:ita_x_preferred":[
        "Vilam\u00f2s"
    ],
    "name:lld_x_preferred":[
        "Vilam\u00f2s"
    ],
    "name:lmo_x_preferred":[
        "Vilam\u00f2s"
    ],
    "name:msa_x_preferred":[
        "Vilam\u00f2s"
    ],
    "name:nld_x_preferred":[
        "Vilam\u00f2s"
    ],
    "name:oci_x_preferred":[
        "Vilam\u00f2s"
    ],
    "name:pol_x_preferred":[
        "Vilam\u00f2s"
    ],
    "name:por_x_preferred":[
        "Vilam\u00f2s"
    ],
    "name:ron_x_preferred":[
        "Vilam\u00f2s"
    ],
    "name:rus_x_preferred":[
        "\u0412\u0438\u043b\u0430\u043c\u043e\u0441"
    ],
    "name:spa_x_preferred":[
        "Vilam\u00f3s"
    ],
    "name:sqi_x_preferred":[
        "Vilam\u00f2s"
    ],
    "name:swe_x_preferred":[
        "Vilam\u00f3s"
    ],
    "name:swe_x_variant":[
        "Vilam\u00f2s"
    ],
    "name:tat_x_preferred":[
        "\u0412\u0438\u043b\u0430\u043c\u043e\u0441"
    ],
    "name:ukr_x_preferred":[
        "\u0411\u0456\u043b\u0430\u043c\u043e\u0441"
    ],
    "name:vec_x_preferred":[
        "Vilam\u00f2s"
    ],
    "name:vie_x_preferred":[
        "Vilam\u00f2s"
    ],
    "name:war_x_preferred":[
        "Vilam\u00f2s"
    ],
    "name:zho_x_preferred":[
        "\u6bd4\u62c9\u83ab\u65af"
    ],
    "qs_pg:aaroncc":"ES",
    "qs_pg:gn_country":"ES",
    "qs_pg:gn_fcode":"PPL",
    "qs_pg:gn_pop":174,
    "qs_pg:name":"Vilam\u00f3s",
    "qs_pg:photos_9r":0,
    "qs_pg:photos_sr":0,
    "qs_pg:pop_sr":1,
    "qs_pg:qs_pg_placetype":"locality",
    "wof:name":"Vilam\u00f3s",
    "wof:placetype":"locality",
    "wof:population":174
},
  "geometry": {"coordinates":[0.72689,42.7475],"type":"Point"}
}