{
  "type": "Feature",
  "properties": {
    "gn:admin1_code":"34",
    "gn:admin2_code":"O",
    "gn:admin3_code":"33025",
    "gn:asciiname":"Llodero",
    "gn:country_code":"ES",
    "gn:dem":25,
    "gn:feature_class":"P",
    "gn:feature_code":"PPL",
    "gn:name":"Llodero",
    "gn:population":0,
    "gn:timezone":"Europe/Madrid",
    "iso:country":"ES",
    "name:und_x_variant":[
        "Lloreda",
        "Llodero"
    ],
    "wof:name":"Llodero",
    "wof:placetype":"locality"
},
  "geometry": {"coordinates":[-5.91882,43.59895],"type":"Point"}
}