{
  "type": "Feature",
  "properties": {
    "iso:country":"ES",
    "name:ara_x_preferred":[
        "\u0641\u064a\u0627\u0646\u0627 \u062f\u064a\u0644 \u0628\u0648\u064a\u0648"
    ],
    "name:cat_x_preferred":[
        "Viana do Bolo"
    ],
    "name:ceb_x_preferred":[
        "Viana do Bolo"
    ],
    "name:deu_x_preferred":[
        "Viana do Bolo"
    ],
    "name:eng_x_preferred":[
        "Viana do Bolo"
    ],
    "name:eus_x_preferred":[
        "Viana do Bolo"
    ],
    "name:fra_x_preferred":[
        "Viana do Bolo"
    ],
    "name:glg_x_preferred":[
        "Viana do Bolo"
    ],
    "name:hun_x_preferred":[
        "Viana do Bolo"
    ],
    "name:ita_x_preferred":[
        "Viana do Bolo"
    ],
    "name:jpn_x_preferred":[
        "\u30d3\u30a2\u30ca\u30fb\u30c9\u30fb\u30dc\u30fc\u30ed"
    ],
    "name:lit_x_preferred":[
        "Vjana de Bolas"
    ],
    "name:lmo_x_preferred":[
        "Viana do Bolo"
    ],
    "name:msa_x_preferred":[
        "Viana do Bolo"
    ],
    "name:nan_x_preferred":[
        "Viana do Bolo"
    ],
    "name:nld_x_preferred":[
        "Viana do Bolo"
    ],
    "name:oci_x_preferred":[
        "Viana do Bolo"
    ],
    "name:pol_x_preferred":[
        "Viana do Bolo"
    ],
    "name:por_x_preferred":[
        "Viana do Bolo"
    ],
    "name:rus_x_preferred":[
        "\u0412\u044c\u044f\u043d\u0430-\u0434\u0435\u043b\u044c-\u0411\u043e\u043b\u044c\u043e"
    ],
    "name:spa_x_preferred":[
        "Viana do Bolo",
        "Viana del Bollo"
    ],
    "name:spa_x_variant":[
        "Viana del Bollo"
    ],
    "name:swe_x_preferred":[
        "Viana do Bolo"
    ],
    "name:tur_x_preferred":[
        "Viana do Bolo"
    ],
    "name:ukr_x_preferred":[
        "\u0412\u0456\u0430\u043d\u0430-\u0434\u043e-\u0411\u043e\u043b\u043e"
    ],
    "name:uzb_x_preferred":[
        "Viana do Bolo"
    ],
    "name:vie_x_preferred":[
        "Viana do Bolo"
    ],
    "name:war_x_preferred":[
        "Viana do Bolo"
    ],
    "name:zho_min_nan_x_preferred":[
        "Viana do Bolo"
    ],
    "name:zho_x_preferred":[
        "\u6bd4\u4e9a\u7eb3\u591a\u6c83\u6d1b"
    ],
    "qs:a0":"Espa\u00f1a",
    "qs:a1":"*Ourense",
    "qs:a1r":"0Galicia",
    "qs:adm0":"Espa\u00f1a",
    "qs:la_lc":"*",
    "qs:level":"locality",
    "qs:loc":"Viana do Bolo",
    "qs:loc_alt":"Viana do Bolo",
    "qs:pop":0,
    "qs:type":"buffered point",
    "wd:wordcount":59,
    "wof:lang":[
        "spa"
    ],
    "wof:name":"Viana do Bolo",
    "wof:placetype":"locality"
},
  "geometry": {"coordinates":[-7.11256,42.178161],"type":"Point"}
}