{
  "type": "Feature",
  "properties": {
    "gn:admin1_code":"58",
    "gn:admin2_code":"LU",
    "gn:admin3_code":"27035",
    "gn:asciiname":"Ouviano",
    "gn:country_code":"ES",
    "gn:dem":424,
    "gn:feature_class":"P",
    "gn:feature_code":"PPL",
    "gn:name":"Ouvia\u00f1o",
    "gn:population":0,
    "gn:timezone":"Europe/Madrid",
    "iso:country":"ES",
    "name:und_x_variant":[
        "Santiago",
        "Ouvia\u00f1o"
    ],
    "wof:name":"Ouviano",
    "wof:placetype":"locality"
},
  "geometry": {"coordinates":[-6.91404,43.10168],"type":"Point"}
}