{
  "type": "Feature",
  "properties": {
    "gn:admin1_code":"55",
    "gn:admin2_code":"AV",
    "gn:admin3_code":"05019",
    "gn:asciiname":"La Alamedilla del Berrocal",
    "gn:country_code":"ES",
    "gn:dem":1204,
    "gn:feature_class":"P",
    "gn:feature_code":"PPL",
    "gn:name":"La Alamedilla del Berrocal",
    "gn:population":0,
    "gn:timezone":"Europe/Madrid",
    "iso:country":"ES",
    "name:und_x_variant":[
        "Alamedilla del Berrocal",
        "La Alamedilla del Berrocal"
    ],
    "wof:name":"La Alamedilla del Berrocal",
    "wof:placetype":"locality"
},
  "geometry": {"coordinates":[-4.76638,40.70773],"type":"Point"}
}