{
  "type": "Feature",
  "properties": {
    "gn:gn_country":"ES",
    "gn:gn_fcode":"ADM3",
    "gn:gn_pop":680,
    "gn:population":654,
    "iso:country":"ES",
    "name:ara_x_preferred":[
        "\u0628\u0648\u064a\u0646\u062a\u064a\u062f\u064a\u0641\u0627"
    ],
    "name:bul_x_preferred":[
        "\u041f\u043e\u043d\u0442\u0435\u0434\u0435\u0432\u0430"
    ],
    "name:cat_x_preferred":[
        "Pontedeva"
    ],
    "name:eng_x_preferred":[
        "Pontedeva"
    ],
    "name:eus_x_preferred":[
        "Pontedeva"
    ],
    "name:fra_x_preferred":[
        "Pontedeva"
    ],
    "name:glg_x_preferred":[
        "Pontedeva"
    ],
    "name:hun_x_preferred":[
        "Pontedeva"
    ],
    "name:ita_x_preferred":[
        "Pontedeva"
    ],
    "name:jpn_x_preferred":[
        "\u30dd\u30f3\u30c6\u30c7\u30fc\u30d0"
    ],
    "name:kaz_x_preferred":[
        "\u041f\u0443\u044d\u043d\u0442\u0435\u0434\u0435\u0432\u0430"
    ],
    "name:lmo_x_preferred":[
        "Pontedeva"
    ],
    "name:msa_x_preferred":[
        "Pontedeva"
    ],
    "name:nan_x_preferred":[
        "Pontedeva"
    ],
    "name:nld_x_preferred":[
        "Pontedeva"
    ],
    "name:oci_x_preferred":[
        "Pontedeva"
    ],
    "name:pol_x_preferred":[
        "Pontedeva"
    ],
    "name:por_x_preferred":[
        "Pontedeva"
    ],
    "name:rus_x_preferred":[
        "\u041f\u0443\u044d\u043d\u0442\u0435\u0434\u0435\u0432\u0430"
    ],
    "name:spa_x_preferred":[
        "Puentedeva"
    ],
    "name:swe_x_preferred":[
        "Pontedeva"
    ],
    "name:tur_x_preferred":[
        "Pontedeva"
    ],
    "name:ukr_x_preferred":[
        "\u041f\u043e\u043d\u0442\u0435\u0434\u0435\u0432\u0430"
    ],
    "name:uzb_x_preferred":[
        "Pontedeva"
    ],
    "name:vie_x_preferred":[
        "Pontedeva"
    ],
    "name:war_x_preferred":[
        "Pontedeva"
    ],
    "name:zho_x_preferred":[
        "\u84ec\u7279\u5fb7\u74e6"
    ],
    "qs_pg:aaroncc":"ES",
    "qs_pg:gn_country":"ES",
    "qs_pg:gn_fcode":"ADM3",
    "qs_pg:gn_pop":680,
    "qs_pg:name":"Pontedeva",
    "qs_pg:name_adm0":"Espa\u00f1a",
    "qs_pg:name_adm1":"Galicia",
    "qs_pg:photos_9k":1,
    "qs_pg:photos_9r":3,
    "qs_pg:photos_all":103,
    "qs_pg:photos_sr":0,
    "qs_pg:pop_sr":2,
    "qs_pg:qs_pg_placetype":"locality",
    "qs_pg:qs_pg_placetype_gp":"Town",
    "qs_pg:woe_adm0":23424950,
    "woe:adm0_id":23424950,
    "woe:name_adm0":"Espa\u00f1a",
    "woe:name_adm1":"Galicia",
    "woe:placetype":"Town",
    "wof:name":"Pontedeva",
    "wof:placetype":"locality",
    "wof:population":654
},
  "geometry": {"coordinates":[-8.1381,42.16921],"type":"Point"}
}