{
  "type": "Feature",
  "properties": {
    "gn:admin1_code":"34",
    "gn:admin2_code":"O",
    "gn:admin3_code":"33076",
    "gn:asciiname":"Trias",
    "gn:country_code":"ES",
    "gn:dem":143,
    "gn:feature_class":"P",
    "gn:feature_code":"PPL",
    "gn:name":"Tr\u00edas",
    "gn:population":0,
    "gn:timezone":"Europe/Madrid",
    "iso:country":"ES",
    "name:und_x_variant":[
        "Tr\u00edas"
    ],
    "wof:name":"Trias",
    "wof:placetype":"locality"
},
  "geometry": {"coordinates":[-5.52628,43.45203],"type":"Point"}
}