{
  "type": "Feature",
  "properties": {
    "gn:country":"ES",
    "gn:fcode":"PPLA3",
    "gn:population":61,
    "iso:country":"ES",
    "name:arg_x_preferred":[
        "Piedra Millera"
    ],
    "name:ast_x_preferred":[
        "Piedramillera"
    ],
    "name:bre_x_preferred":[
        "Piedramillera"
    ],
    "name:bul_x_preferred":[
        "\u041f\u0438\u0435\u0434\u0440\u0430\u043c\u0438\u043b\u0435\u0440\u0430"
    ],
    "name:cat_x_preferred":[
        "Piedramillera"
    ],
    "name:ceb_x_preferred":[
        "Piedramillera"
    ],
    "name:deu_x_preferred":[
        "Piedramillera"
    ],
    "name:eng_x_preferred":[
        "Piedramillera"
    ],
    "name:eus_x_preferred":[
        "Piedramillera"
    ],
    "name:fra_x_preferred":[
        "Piedramillera"
    ],
    "name:hun_x_preferred":[
        "Piedramillera"
    ],
    "name:ita_x_preferred":[
        "Piedramillera"
    ],
    "name:jpn_x_preferred":[
        "\u30d4\u30a8\u30c9\u30e9\u30df\u30ea\u30a7\u30e9"
    ],
    "name:msa_x_preferred":[
        "Piedramillera"
    ],
    "name:nan_x_preferred":[
        "Piedramillera"
    ],
    "name:nld_x_preferred":[
        "Piedramillera"
    ],
    "name:oci_x_preferred":[
        "Piedramillera"
    ],
    "name:pol_x_preferred":[
        "Piedramillera"
    ],
    "name:por_x_preferred":[
        "Piedramillera"
    ],
    "name:rus_x_preferred":[
        "\u041f\u044c\u0435\u0434\u0440\u0430\u043c\u0438\u043b\u044c\u0435\u0440\u0430"
    ],
    "name:sco_x_preferred":[
        "Piedramillera"
    ],
    "name:spa_x_preferred":[
        "Piedramillera"
    ],
    "name:swe_x_preferred":[
        "Piedramillera"
    ],
    "name:ukr_x_preferred":[
        "\u041f'\u0454\u0434\u0440\u0430\u043c\u0456\u043b\u044c\u0454\u0440\u0430"
    ],
    "name:uzb_x_preferred":[
        "Piedramillera"
    ],
    "name:vie_x_preferred":[
        "Piedramillera"
    ],
    "name:war_x_preferred":[
        "Piedramillera"
    ],
    "name:zho_x_preferred":[
        "\u5f7c\u5fb7\u62c9\u7c73\u5217\u62c9"
    ],
    "qs_pg:aaroncc":"ES",
    "qs_pg:gn_country":"ES",
    "qs_pg:gn_fcode":"PPLA3",
    "qs_pg:gn_pop":61,
    "qs_pg:name":"Piedramillera",
    "qs_pg:name_adm0":"Espa\u00f1a",
    "qs_pg:name_adm1":"Comunidad Foral de Navarra",
    "qs_pg:photos_9r":0,
    "qs_pg:photos_sr":0,
    "qs_pg:pop_sr":1,
    "qs_pg:qs_pg_placetype":"locality",
    "qs_pg:qs_pg_placetype_gp":"Town",
    "qs_pg:woe_adm0":23424950,
    "woe:adm0_id":23424950,
    "woe:name_adm0":"Espa\u00f1a",
    "woe:name_adm1":"Comunidad Foral de Navarra",
    "woe:placetype":"Town",
    "wof:name":"Piedramillera",
    "wof:placetype":"locality",
    "wof:population":61
},
  "geometry": {"coordinates":[-2.20416,42.632],"type":"Point"}
}