{
  "type": "Feature",
  "properties": {
    "gn:gn_country":"ES",
    "gn:gn_fcode":"PPLA3",
    "gn:gn_pop":166,
    "gn:population":166,
    "iso:country":"ES",
    "name:ara_x_preferred":[
        "\u0641\u0627\u0644\u0628\u0627\u0644\u0645\u0627\u0633"
    ],
    "name:arg_x_preferred":[
        "Val Palmas"
    ],
    "name:cat_x_preferred":[
        "Valpalmas"
    ],
    "name:eng_x_preferred":[
        "Valpalmas"
    ],
    "name:eus_x_preferred":[
        "Valpalmas"
    ],
    "name:fra_x_preferred":[
        "Valpalmas"
    ],
    "name:hun_x_preferred":[
        "Valpalmas"
    ],
    "name:ita_x_preferred":[
        "Valpalmas"
    ],
    "name:kaz_x_preferred":[
        "\u0412\u0430\u043b\u044c\u043f\u0430\u043b\u044c\u043c\u0430\u0441"
    ],
    "name:msa_x_preferred":[
        "Valpalmas"
    ],
    "name:nan_x_preferred":[
        "Valpalmas"
    ],
    "name:nld_x_preferred":[
        "Valpalmas"
    ],
    "name:oci_x_preferred":[
        "Valpalmas"
    ],
    "name:pol_x_preferred":[
        "Valpalmas"
    ],
    "name:por_x_preferred":[
        "Valpalmas"
    ],
    "name:rus_x_preferred":[
        "\u0412\u0430\u043b\u044c\u043f\u0430\u043b\u044c\u043c\u0430\u0441"
    ],
    "name:spa_x_preferred":[
        "Valpalmas"
    ],
    "name:swe_x_preferred":[
        "Valpalmas"
    ],
    "name:ukr_x_preferred":[
        "\u0412\u0430\u043b\u044c\u043f\u0430\u043b\u044c\u043c\u0430\u0441"
    ],
    "name:uzb_x_preferred":[
        "Valpalmas"
    ],
    "name:vie_x_preferred":[
        "Valpalmas"
    ],
    "name:war_x_preferred":[
        "Valpalmas"
    ],
    "name:zho_x_preferred":[
        "\u5df4\u5c14\u5e15\u5c14\u9a6c\u65af"
    ],
    "qs_pg:aaroncc":"ES",
    "qs_pg:gn_country":"ES",
    "qs_pg:gn_fcode":"PPLA3",
    "qs_pg:gn_pop":166,
    "qs_pg:name":"Valpalmas",
    "qs_pg:name_adm0":"Espa\u00f1a",
    "qs_pg:name_adm1":"Arag\u00f3n",
    "qs_pg:photos_9k":1,
    "qs_pg:photos_9r":1,
    "qs_pg:photos_all":1,
    "qs_pg:photos_sr":0,
    "qs_pg:pop_sr":1,
    "qs_pg:qs_pg_placetype":"locality",
    "qs_pg:qs_pg_placetype_gp":"Town",
    "qs_pg:woe_adm0":23424950,
    "woe:adm0_id":23424950,
    "woe:name_adm0":"Espa\u00f1a",
    "woe:name_adm1":"Arag\u00f3n",
    "woe:placetype":"Town",
    "wof:name":"Valpalmas",
    "wof:placetype":"locality",
    "wof:population":166
},
  "geometry": {"coordinates":[-0.85481,42.15821],"type":"Point"}
}