{
  "type": "Feature",
  "properties": {
    "gn:admin1_code":"51",
    "gn:admin2_code":"CO",
    "gn:admin3_code":"14017",
    "gn:asciiname":"La Fuencubierta",
    "gn:country_code":"ES",
    "gn:dem":173,
    "gn:feature_class":"P",
    "gn:feature_code":"PPL",
    "gn:name":"La Fuencubierta",
    "gn:population":0,
    "gn:timezone":"Europe/Madrid",
    "iso:country":"ES",
    "wof:name":"La Fuencubierta",
    "wof:placetype":"locality"
},
  "geometry": {"coordinates":[-4.98892,37.70884],"type":"Point"}
}