{
  "type": "Feature",
  "properties": {
    "gn:gn_country":"ES",
    "gn:gn_fcode":"PPLA3",
    "gn:gn_pop":105,
    "gn:population":105,
    "iso:country":"ES",
    "name:ast_x_preferred":[
        "Villovieco"
    ],
    "name:azb_x_preferred":[
        "\u0628\u06cc\u06cc\u0628\u06cc\u06a9\u0648"
    ],
    "name:cat_x_preferred":[
        "Villovieco"
    ],
    "name:ceb_x_preferred":[
        "Villovieco"
    ],
    "name:eng_x_preferred":[
        "Villovieco"
    ],
    "name:eus_x_preferred":[
        "Villovieco"
    ],
    "name:fas_x_preferred":[
        "\u0628\u06cc\u06cc\u0628\u06cc\u06a9\u0648"
    ],
    "name:fra_x_preferred":[
        "Villovieco"
    ],
    "name:glg_x_preferred":[
        "Villovieco"
    ],
    "name:hun_x_preferred":[
        "Villovieco"
    ],
    "name:hye_x_preferred":[
        "\u054e\u056b\u056c\u0575\u0578\u057d\u057e\u056b\u0565\u056f\u0578"
    ],
    "name:ile_x_preferred":[
        "Villovieco"
    ],
    "name:ina_x_preferred":[
        "Villovieco"
    ],
    "name:ita_x_preferred":[
        "Villovieco"
    ],
    "name:msa_x_preferred":[
        "Villovieco"
    ],
    "name:nan_x_preferred":[
        "Villovieco"
    ],
    "name:nld_x_preferred":[
        "Villovieco"
    ],
    "name:oci_x_preferred":[
        "Villovieco"
    ],
    "name:pol_x_preferred":[
        "Villovieco"
    ],
    "name:por_x_preferred":[
        "Villovieco"
    ],
    "name:rus_x_preferred":[
        "\u0412\u0438\u043b\u044c\u043e\u0432\u044c\u0435\u043a\u043e"
    ],
    "name:spa_x_preferred":[
        "Villovieco"
    ],
    "name:swe_x_preferred":[
        "Villovieco"
    ],
    "name:ukr_x_preferred":[
        "\u0412\u0456\u043b\u044c\u0439\u043e\u0432'\u0454\u043a\u043e"
    ],
    "name:uzb_x_preferred":[
        "Villovieco"
    ],
    "name:vie_x_preferred":[
        "Villovieco"
    ],
    "name:war_x_preferred":[
        "Villovieco"
    ],
    "name:zho_x_preferred":[
        "\u6bd4\u7565\u7ef4\u8036\u79d1"
    ],
    "qs_pg:aaroncc":"ES",
    "qs_pg:gn_country":"ES",
    "qs_pg:gn_fcode":"PPLA3",
    "qs_pg:gn_pop":105,
    "qs_pg:name":"Villovieco",
    "qs_pg:name_adm0":"Espa\u00f1a",
    "qs_pg:name_adm1":"Castilla y Le\u00f3n",
    "qs_pg:photos":32,
    "qs_pg:photos_1k":6,
    "qs_pg:photos_9k":1,
    "qs_pg:photos_9r":2,
    "qs_pg:photos_all":32,
    "qs_pg:photos_sr":2,
    "qs_pg:pop_sr":1,
    "qs_pg:qs_pg_placetype":"locality",
    "qs_pg:qs_pg_placetype_gp":"Town",
    "qs_pg:woe_adm0":23424950,
    "woe:adm0_id":23424950,
    "woe:name_adm0":"Espa\u00f1a",
    "woe:name_adm1":"Castilla y Le\u00f3n",
    "woe:placetype":"Town",
    "wof:name":"Villovieco",
    "wof:placetype":"locality",
    "wof:population":105
},
  "geometry": {"coordinates":[-4.48122,42.29478],"type":"Point"}
}