{
  "type": "Feature",
  "properties": {
    "gn:gn_country":"ES",
    "gn:gn_fcode":"PPLX",
    "gn:gn_pop":0,
    "iso:country":"ES",
    "name:cat_x_preferred":[
        "Pe\u00f1agrande"
    ],
    "name:dut_x_preferred":[
        "Pe\u00f1agrande"
    ],
    "name:eng_x_preferred":[
        "Pe\u00f1agrande"
    ],
    "name:epo_x_preferred":[
        "Penjagrando"
    ],
    "name:fre_x_preferred":[
        "Pe\u00f1agrande"
    ],
    "name:ger_x_preferred":[
        "Pe\u00f1agrande"
    ],
    "name:por_x_preferred":[
        "Pe\u00f1agrande"
    ],
    "name:spa_x_preferred":[
        "Pe\u00f1a Grande"
    ],
    "name:unk_x_variant":[
        "Barrio Pe\u00f1a Grande"
    ],
    "qs_pg:aaroncc":"ES",
    "qs_pg:gn_country":"ES",
    "qs_pg:gn_fcode":"PPLX",
    "qs_pg:gn_pop":0,
    "qs_pg:name":"Pe\u00f1a Grande",
    "qs_pg:name_adm0":"Espa\u00f1a",
    "qs_pg:name_adm1":"Comunidad de Madrid",
    "qs_pg:photos":33,
    "qs_pg:photos_1k":7,
    "qs_pg:photos_9k":1,
    "qs_pg:photos_9r":2,
    "qs_pg:photos_all":33,
    "qs_pg:photos_sr":2,
    "qs_pg:pop_sr":0,
    "qs_pg:qs_pg_placetype":"locality_gp_neighbourhood_gn",
    "qs_pg:qs_pg_placetype_gp":"Town",
    "qs_pg:woe_adm0":23424950,
    "woe:adm0_id":23424950,
    "woe:name_adm0":"Espa\u00f1a",
    "woe:name_adm1":"Comunidad de Madrid",
    "woe:placetype":"Town",
    "wof:name":"Pe\u00f1a Grande",
    "wof:placetype":"locality"
},
  "geometry": {"coordinates":[-3.71667,40.48333],"type":"Point"}
}