{
  "type": "Feature",
  "properties": {
    "gn:admin1_code":"58",
    "gn:admin2_code":"PO",
    "gn:admin3_code":"36042",
    "gn:asciiname":"Arcos",
    "gn:cc2":"ES",
    "gn:country_code":"ES",
    "gn:dem":131,
    "gn:feature_class":"P",
    "gn:feature_code":"PPL",
    "gn:name":"Arcos",
    "gn:population":0,
    "gn:timezone":"Europe/Madrid",
    "iso:country":"ES",
    "name:und_x_variant":[
        "San Ver\u00edsimo",
        "Arcos"
    ],
    "wof:name":"Arcos",
    "wof:placetype":"locality"
},
  "geometry": {"coordinates":[-8.46667,42.18333],"type":"Point"}
}