{
  "type": "Feature",
  "properties": {
    "gn:gn_country":"ES",
    "gn:gn_fcode":"PPLA3",
    "gn:gn_pop":0,
    "iso:country":"ES",
    "name:arg_x_preferred":[
        "La Pobla de Massaluca"
    ],
    "name:cat_x_preferred":[
        "la Pobla de Massaluca"
    ],
    "name:eng_x_preferred":[
        "La Pobla de Massaluca"
    ],
    "name:eus_x_preferred":[
        "La Pobla de Massaluca"
    ],
    "name:fas_x_preferred":[
        "\u0644\u0627 \u067e\u0628\u0644\u0627 \u062f \u0645\u0627\u0633\u0633\u0627\u0644\u0648\u06a9\u0627"
    ],
    "name:fra_x_preferred":[
        "La Pobla de Massaluca"
    ],
    "name:glg_x_preferred":[
        "La Pobla de Massaluca"
    ],
    "name:hun_x_preferred":[
        "La Pobla de Massaluca"
    ],
    "name:hye_x_preferred":[
        "\u053c\u0561 \u054a\u0578\u0562\u056c\u0561 \u0564\u0565 \u0544\u0561\u057d\u0561\u056c\u0578\u0582\u056f\u0561"
    ],
    "name:ita_x_preferred":[
        "La Pobla de Massaluca"
    ],
    "name:lat_x_preferred":[
        "La Pobla de Massaluca"
    ],
    "name:nld_x_preferred":[
        "La Pobla de Massaluca"
    ],
    "name:oci_x_preferred":[
        "La Pobla de Massaluca"
    ],
    "name:pol_x_preferred":[
        "La Pobla de Massaluca"
    ],
    "name:por_x_preferred":[
        "La Pobla de Massaluca"
    ],
    "name:rus_x_preferred":[
        "\u041b\u0430-\u041f\u043e\u0431\u043b\u0430-\u0434\u0435-\u041c\u0430\u0441\u0441\u0430\u043b\u0443\u043a\u0430"
    ],
    "name:spa_x_preferred":[
        "Pobla de Masaluca"
    ],
    "name:sqi_x_preferred":[
        "La Pobla de Massaluca"
    ],
    "name:swe_x_preferred":[
        "La Pobla de Massaluca"
    ],
    "name:urd_x_preferred":[
        "\u0644\u0627 \u067e\u0648\u0628\u0644\u0627 \u062f\u06d2 \u0645\u0627\u0633\u0627\u0644\u06cc\u0648\u06a9\u0627"
    ],
    "name:uzb_x_preferred":[
        "La Pobla de Massaluca"
    ],
    "name:vie_x_preferred":[
        "La Pobla de Massaluca"
    ],
    "name:war_x_preferred":[
        "La Pobla de Massaluca"
    ],
    "name:zho_x_preferred":[
        "\u62c9\u6ce2\u592b\u62c9\u5fb7\u9a6c\u8428\u5362\u5361"
    ],
    "qs_pg:aaroncc":"ES",
    "qs_pg:gn_country":"ES",
    "qs_pg:gn_fcode":"PPLA3",
    "qs_pg:gn_pop":0,
    "qs_pg:name":"Pobla de Masaluca",
    "qs_pg:name_adm0":"Espa\u00f1a",
    "qs_pg:name_adm1":"Catalunya",
    "qs_pg:photos":32,
    "qs_pg:photos_1k":6,
    "qs_pg:photos_9k":1,
    "qs_pg:photos_9r":2,
    "qs_pg:photos_all":32,
    "qs_pg:photos_sr":2,
    "qs_pg:pop_sr":0,
    "qs_pg:qs_pg_placetype":"locality",
    "qs_pg:qs_pg_placetype_gp":"Town",
    "qs_pg:woe_adm0":23424950,
    "woe:adm0_id":23424950,
    "woe:name_adm0":"Espa\u00f1a",
    "woe:name_adm1":"Catalunya",
    "woe:placetype":"Town",
    "wof:name":"Pobla de Masaluca",
    "wof:placetype":"locality"
},
  "geometry": {"coordinates":[0.35,41.18333],"type":"Point"}
}