{
  "type": "Feature",
  "properties": {
    "gn:gn_country":"ES",
    "gn:gn_fcode":"PPL",
    "gn:gn_pop":14979,
    "gn:population":14979,
    "iso:country":"ES",
    "name:ara_x_preferred":[
        "\u0625\u0644\u064a\u0633\u0643\u0648\u0631\u064a\u0627\u0644"
    ],
    "name:ast_x_preferred":[
        "El Escorial"
    ],
    "name:azb_x_preferred":[
        "\u0627\u0644 \u0627\u0633\u06a9\u0648\u0631\u06cc\u0627\u0644"
    ],
    "name:bel_x_preferred":[
        "\u0413\u043e\u0440\u0430\u0434 \u042d\u043b\u044c-\u042d\u0441\u043a\u0430\u0440\u044b\u044f\u043b\u044c"
    ],
    "name:cat_x_preferred":[
        "El Escorial"
    ],
    "name:ceb_x_preferred":[
        "El Escorial"
    ],
    "name:deu_x_preferred":[
        "El Escorial"
    ],
    "name:ell_x_preferred":[
        "\u0395\u03bb \u0395\u03c3\u03ba\u03bf\u03c1\u03b9\u03ac\u03bb"
    ],
    "name:eng_x_preferred":[
        "El Escorial"
    ],
    "name:epo_x_preferred":[
        "El Escorial"
    ],
    "name:fas_x_preferred":[
        "\u0627\u0644 \u0627\u0633\u06a9\u0648\u0631\u06cc\u0627\u0644"
    ],
    "name:fra_x_preferred":[
        "L'Escurial"
    ],
    "name:glg_x_preferred":[
        "O Escorial"
    ],
    "name:hun_x_preferred":[
        "El Escorial"
    ],
    "name:hye_x_preferred":[
        "\u0537\u056c \u0537\u057d\u056f\u0578\u0580\u056b\u0561\u056c"
    ],
    "name:ita_x_preferred":[
        "El Escorial"
    ],
    "name:jpn_x_preferred":[
        "\u30a8\u30eb\u30fb\u30a8\u30b9\u30b3\u30ea\u30a2\u30eb"
    ],
    "name:kor_x_preferred":[
        "\uc5d8\uc5d0\uc2a4\ucf54\ub9ac\uc54c"
    ],
    "name:lad_x_preferred":[
        "El Escorial"
    ],
    "name:lit_x_preferred":[
        "El Eskorialis"
    ],
    "name:ltz_x_preferred":[
        "El Escorial"
    ],
    "name:msa_x_preferred":[
        "El Escorial"
    ],
    "name:nan_x_preferred":[
        "El Escorial"
    ],
    "name:nld_x_preferred":[
        "El Escorial"
    ],
    "name:oci_x_preferred":[
        "El Escorial"
    ],
    "name:pol_x_preferred":[
        "El Escorial"
    ],
    "name:por_x_preferred":[
        "El Escorial"
    ],
    "name:rus_x_preferred":[
        "\u042d\u043b\u044c-\u042d\u0441\u043a\u043e\u0440\u0438\u0430\u043b\u044c"
    ],
    "name:spa_x_preferred":[
        "El Escorial"
    ],
    "name:swe_x_preferred":[
        "El Escorial"
    ],
    "name:ukr_x_preferred":[
        "\u0415\u043b\u044c-\u0415\u0441\u043a\u043e\u0440\u0456\u0430\u043b\u044c"
    ],
    "name:unk_x_variant":[
        "Escorial"
    ],
    "name:uzb_x_preferred":[
        "El Escorial"
    ],
    "name:vie_x_preferred":[
        "El Escorial"
    ],
    "name:war_x_preferred":[
        "El Escorial"
    ],
    "name:zho_x_preferred":[
        "\u57c3\u5c14\u57c3\u65af\u79d1\u91cc\u4e9a\u5c14"
    ],
    "name:zho_x_variant":[
        "\u57c3\u83b1\u65af\u79d1\u91cc\u4e9a\u5c14"
    ],
    "qs_pg:aaroncc":"ES",
    "qs_pg:gn_country":"ES",
    "qs_pg:gn_fcode":"PPL",
    "qs_pg:gn_pop":14979,
    "qs_pg:name":"El Escorial",
    "qs_pg:photos_9r":0,
    "qs_pg:photos_sr":0,
    "qs_pg:pop_sr":6,
    "qs_pg:qs_pg_placetype":"locality",
    "wof:name":"El Escorial",
    "wof:placetype":"locality",
    "wof:population":14979
},
  "geometry": {"coordinates":[-4.12846,40.58254],"type":"Point"}
}