{
  "type": "Feature",
  "properties": {
    "gn:gn_country":"ES",
    "gn:gn_fcode":"PPLA3",
    "gn:gn_pop":94,
    "gn:population":94,
    "iso:country":"ES",
    "name:ara_x_preferred":[
        "\u062a\u0634\u0627\u0645\u0627\u0631\u062a\u064a\u0646\u060c \u0622\u0628\u0644\u0629"
    ],
    "name:ara_x_variant":[
        "\u062a\u0634\u0627\u0645\u0627\u0631\u062a\u064a\u0646"
    ],
    "name:ast_x_preferred":[
        "Chamart\u00edn"
    ],
    "name:cat_x_preferred":[
        "Chamart\u00edn"
    ],
    "name:eng_x_preferred":[
        "Chamart\u00edn"
    ],
    "name:eus_x_preferred":[
        "Chamart\u00edn"
    ],
    "name:fra_x_preferred":[
        "Chamart\u00edn"
    ],
    "name:hun_x_preferred":[
        "Chamart\u00edn"
    ],
    "name:hye_x_preferred":[
        "\u0549\u0561\u0574\u0561\u0580\u057f\u056b\u0576"
    ],
    "name:ina_x_preferred":[
        "Chamart\u00edn"
    ],
    "name:ita_x_preferred":[
        "Chamart\u00edn"
    ],
    "name:kaz_x_preferred":[
        "\u0427\u0430\u043c\u0430\u0440\u0442\u0438\u043d"
    ],
    "name:mkd_x_preferred":[
        "\u0427\u0430\u043c\u0430\u0440\u0442\u0438\u043d"
    ],
    "name:msa_x_preferred":[
        "Chamart\u00edn"
    ],
    "name:nld_x_preferred":[
        "Chamart\u00edn"
    ],
    "name:oci_x_preferred":[
        "Chamart\u00edn"
    ],
    "name:pol_x_preferred":[
        "Chamart\u00edn"
    ],
    "name:por_x_preferred":[
        "Chamart\u00edn"
    ],
    "name:rus_x_preferred":[
        "\u0427\u0430\u043c\u0430\u0440\u0442\u0438\u043d"
    ],
    "name:spa_x_preferred":[
        "Chamart\u00edn"
    ],
    "name:ukr_x_preferred":[
        "\u0427\u0430\u043c\u0430\u0440\u0442\u0456\u043d"
    ],
    "name:unk_x_variant":[
        "Chamartin de la Sierra"
    ],
    "name:uzb_x_preferred":[
        "Chamart\u00edn"
    ],
    "name:war_x_preferred":[
        "Chamart\u00edn"
    ],
    "name:zho_x_preferred":[
        "\u67e5\u9a6c\u5c14\u5ef7"
    ],
    "qs_pg:aaroncc":"ES",
    "qs_pg:gn_country":"ES",
    "qs_pg:gn_fcode":"PPLA3",
    "qs_pg:gn_pop":94,
    "qs_pg:name":"Chamart\u00edn",
    "qs_pg:name_adm0":"Espa\u00f1a",
    "qs_pg:name_adm1":"Castilla y Le\u00f3n",
    "qs_pg:photos_9r":0,
    "qs_pg:photos_sr":0,
    "qs_pg:pop_sr":1,
    "qs_pg:qs_pg_placetype":"locality",
    "qs_pg:qs_pg_placetype_gp":"Town",
    "qs_pg:woe_adm0":23424950,
    "woe:adm0_id":23424950,
    "woe:name_adm0":"Espa\u00f1a",
    "woe:name_adm1":"Castilla y Le\u00f3n",
    "woe:placetype":"Town",
    "wof:name":"Chamart\u00edn",
    "wof:placetype":"locality",
    "wof:population":94
},
  "geometry": {"coordinates":[-4.95769,40.70267],"type":"Point"}
}