{
  "type": "Feature",
  "properties": {
    "gn:admin1_code":"59",
    "gn:admin2_code":"VI",
    "gn:admin3_code":"01013",
    "gn:asciiname":"Mendixur / Mendijur",
    "gn:country_code":"ES",
    "gn:dem":564,
    "gn:feature_class":"P",
    "gn:feature_code":"PPL",
    "gn:name":"Mendixur / Mend\u00edjur",
    "gn:population":0,
    "gn:timezone":"Europe/Madrid",
    "iso:country":"ES",
    "name:eus_x_preferred":[
        "Mendixur"
    ],
    "name:spa_x_preferred":[
        "Mend\u00edjur"
    ],
    "name:und_x_variant":[
        "Mendijur"
    ],
    "wof:name":"Mendixur / Mendijur",
    "wof:placetype":"locality"
},
  "geometry": {"coordinates":[-2.53695,42.88685],"type":"Point"}
}