{
  "type": "Feature",
  "properties": {
    "gn:admin1_code":"55",
    "gn:admin2_code":"SO",
    "gn:admin3_code":"42158",
    "gn:asciiname":"Escobosa de Calatanazor",
    "gn:country_code":"ES",
    "gn:dem":1000,
    "gn:feature_class":"P",
    "gn:feature_code":"PPL",
    "gn:name":"Escobosa de Calata\u00f1azor",
    "gn:population":0,
    "gn:timezone":"Europe/Madrid",
    "iso:country":"ES",
    "wof:name":"Escobosa de Calatanazor",
    "wof:placetype":"locality"
},
  "geometry": {"coordinates":[-2.83314,41.60514000000001],"type":"Point"}
}