{
  "type": "Feature",
  "properties": {
    "gn:admin1_code":"54",
    "gn:admin2_code":"CU",
    "gn:admin3_code":"16909",
    "gn:asciiname":"Villaseca",
    "gn:country_code":"ES",
    "gn:dem":931,
    "gn:feature_class":"P",
    "gn:feature_code":"PPL",
    "gn:name":"Villaseca",
    "gn:population":0,
    "gn:timezone":"Europe/Madrid",
    "iso:country":"ES",
    "name:cat_x_preferred":[
        "Vila-seca"
    ],
    "name:eus_x_preferred":[
        "Vila-seca"
    ],
    "name:fra_x_preferred":[
        "Villaseca"
    ],
    "name:spa_x_preferred":[
        "Villaseca"
    ],
    "wof:name":"Villaseca",
    "wof:placetype":"locality"
},
  "geometry": {"coordinates":[-2.21299,40.31929],"type":"Point"}
}