{
  "type": "Feature",
  "properties": {
    "gn:country":"ES",
    "gn:fcode":"PPLA3",
    "gn:population":14,
    "iso:country":"ES",
    "name:arg_x_preferred":[
        "Zarzosa"
    ],
    "name:ast_x_preferred":[
        "Zarzosa"
    ],
    "name:bul_x_preferred":[
        "\u0417\u0430\u0440\u0437\u043e\u0441\u0430"
    ],
    "name:cat_x_preferred":[
        "Zarzosa"
    ],
    "name:ceb_x_preferred":[
        "Zarzosa"
    ],
    "name:deu_x_preferred":[
        "Zarzosa"
    ],
    "name:eng_x_preferred":[
        "Zarzosa"
    ],
    "name:eus_x_preferred":[
        "Zarzosa"
    ],
    "name:fra_x_preferred":[
        "Zarzosa"
    ],
    "name:hun_x_preferred":[
        "Zarzosa"
    ],
    "name:hye_x_preferred":[
        "\u054d\u0561\u0580\u057d\u0578\u057d\u0561"
    ],
    "name:ita_x_preferred":[
        "Zarzosa"
    ],
    "name:kaz_x_preferred":[
        "\u0421\u0430\u0440\u0441\u043e\u0441\u0430"
    ],
    "name:msa_x_preferred":[
        "Zarzosa"
    ],
    "name:nan_x_preferred":[
        "Zarzosa"
    ],
    "name:nld_x_preferred":[
        "Zarzosa"
    ],
    "name:oci_x_preferred":[
        "Zarzosa"
    ],
    "name:pol_x_preferred":[
        "Zarzosa"
    ],
    "name:por_x_preferred":[
        "Zarzosa"
    ],
    "name:rup_x_preferred":[
        "Zarzosa"
    ],
    "name:rus_x_preferred":[
        "\u0421\u0430\u0440\u0441\u043e\u0441\u0430"
    ],
    "name:spa_x_preferred":[
        "Zarzosa"
    ],
    "name:swe_x_preferred":[
        "Zarzosa"
    ],
    "name:ukr_x_preferred":[
        "\u0421\u0430\u0440\u0441\u043e\u0441\u0430"
    ],
    "name:uzb_x_preferred":[
        "Zarzosa"
    ],
    "name:vie_x_preferred":[
        "Zarzosa"
    ],
    "name:war_x_preferred":[
        "Zarzosa"
    ],
    "name:zho_x_preferred":[
        "\u8428\u5c14\u7d22\u8428"
    ],
    "qs_pg:aaroncc":"ES",
    "qs_pg:gn_country":"ES",
    "qs_pg:gn_fcode":"PPLA3",
    "qs_pg:gn_pop":14,
    "qs_pg:name":"Zarzosa",
    "qs_pg:name_adm0":"Espa\u00f1a",
    "qs_pg:name_adm1":"La Rioja",
    "qs_pg:photos_9k":1,
    "qs_pg:photos_9r":3,
    "qs_pg:photos_all":124,
    "qs_pg:photos_sr":0,
    "qs_pg:pop_sr":1,
    "qs_pg:qs_pg_placetype":"locality",
    "qs_pg:qs_pg_placetype_gp":"Town",
    "qs_pg:woe_adm0":23424950,
    "woe:adm0_id":23424950,
    "woe:name_adm0":"Espa\u00f1a",
    "woe:name_adm1":"La Rioja",
    "woe:placetype":"Town",
    "wof:name":"Zarzosa",
    "wof:placetype":"locality",
    "wof:population":14
},
  "geometry": {"coordinates":[-2.34297,42.18294],"type":"Point"}
}