{
  "type": "Feature",
  "properties": {
    "gn:country":"ES",
    "gn:fcode":"PPL",
    "gn:population":0,
    "iso:country":"ES",
    "name:ast_x_preferred":[
        "C\u00f3breces"
    ],
    "name:eng_x_preferred":[
        "C\u00f3breces"
    ],
    "name:eus_x_preferred":[
        "C\u00f3breces"
    ],
    "name:fra_x_preferred":[
        "C\u00f3breces"
    ],
    "name:ita_x_preferred":[
        "C\u00f3breces"
    ],
    "name:spa_x_preferred":[
        "C\u00f3breces"
    ],
    "qs_pg:aaroncc":"ES",
    "qs_pg:gn_country":"ES",
    "qs_pg:gn_fcode":"PPL",
    "qs_pg:gn_pop":0,
    "qs_pg:name":"C\u00f3breces",
    "qs_pg:name_adm0":"Espa\u00f1a",
    "qs_pg:name_adm1":"Cantabria",
    "qs_pg:photos":452,
    "qs_pg:photos_1k":92,
    "qs_pg:photos_9k":2,
    "qs_pg:photos_9r":5,
    "qs_pg:photos_all":452,
    "qs_pg:photos_sr":7,
    "qs_pg:pop_sr":0,
    "qs_pg:qs_pg_placetype":"locality",
    "qs_pg:qs_pg_placetype_gp":"Town",
    "qs_pg:woe_adm0":23424950,
    "woe:adm0_id":23424950,
    "woe:name_adm0":"Espa\u00f1a",
    "woe:name_adm1":"Cantabria",
    "woe:placetype":"Town",
    "wof:name":"C\u00f3breces",
    "wof:placetype":"locality"
},
  "geometry": {"coordinates":[-4.21361,43.38745],"type":"Point"}
}