{
  "type": "Feature",
  "properties": {
    "gn:admin1_code":"32",
    "gn:admin3_code":"31158",
    "gn:asciiname":"Ecay",
    "gn:country_code":"ES",
    "gn:dem":501,
    "gn:feature_class":"P",
    "gn:feature_code":"PPL",
    "gn:name":"Ecay",
    "gn:population":0,
    "gn:timezone":"Europe/Madrid",
    "iso:country":"ES",
    "name:eus_x_preferred":[
        "Ekai"
    ],
    "wof:name":"Ecay",
    "wof:placetype":"locality"
},
  "geometry": {"coordinates":[-1.38737,42.77411],"type":"Point"}
}