{
  "type": "Feature",
  "properties": {
    "gn:gn_country":"ES",
    "gn:gn_fcode":"PPLA3",
    "gn:gn_pop":321,
    "gn:population":321,
    "iso:country":"ES",
    "name:arg_x_preferred":[
        "Palacios de Sanabria"
    ],
    "name:cat_x_preferred":[
        "Palacios de Sanabria"
    ],
    "name:eng_x_preferred":[
        "Palacios de Sanabria"
    ],
    "name:eus_x_preferred":[
        "Palacios de Sanabria"
    ],
    "name:fra_x_preferred":[
        "Palacios de Sanabria"
    ],
    "name:glg_x_preferred":[
        "Palacios de Sanabria"
    ],
    "name:haw_x_preferred":[
        "Palacios de Sanabria"
    ],
    "name:hun_x_preferred":[
        "Palacios de Sanabria"
    ],
    "name:ile_x_preferred":[
        "Palacios de Sanabria"
    ],
    "name:ina_x_preferred":[
        "Palacios de Sanabria"
    ],
    "name:ita_x_preferred":[
        "Palacios de Sanabria"
    ],
    "name:msa_x_preferred":[
        "Palacios de Sanabria"
    ],
    "name:nan_x_preferred":[
        "Palacios de Sanabria"
    ],
    "name:nld_x_preferred":[
        "Palacios de Sanabria"
    ],
    "name:oci_x_preferred":[
        "Palacios de Sanabria"
    ],
    "name:pol_x_preferred":[
        "Palacios de Sanabria"
    ],
    "name:por_x_preferred":[
        "Palacios de Sanabria"
    ],
    "name:rus_x_preferred":[
        "\u041f\u0430\u043b\u0430\u0441\u0438\u043e\u0441-\u0434\u0435-\u0421\u0430\u043d\u0430\u0431\u0440\u0438\u0430"
    ],
    "name:spa_x_preferred":[
        "Palacios de Sanabria"
    ],
    "name:swe_x_preferred":[
        "Palacios de Sanabria"
    ],
    "name:ukr_x_preferred":[
        "\u041f\u0430\u043b\u0430\u0441\u0456\u043e\u0441-\u0434\u0435-\u0421\u0430\u043d\u0430\u0431\u0440\u0456\u044f"
    ],
    "name:vie_x_preferred":[
        "Palacios de Sanabria"
    ],
    "name:war_x_preferred":[
        "Palacios de Sanabria"
    ],
    "name:zho_x_preferred":[
        "\u5e15\u62c9\u897f\u5965\u65af\u5fb7\u8428\u7eb3\u592b\u91cc\u4e9a"
    ],
    "qs_pg:aaroncc":"ES",
    "qs_pg:gn_country":"ES",
    "qs_pg:gn_fcode":"PPLA3",
    "qs_pg:gn_pop":321,
    "qs_pg:name":"Palacios de Sanabria",
    "qs_pg:name_adm0":"Espa\u00f1a",
    "qs_pg:name_adm1":"Castilla y Le\u00f3n",
    "qs_pg:photos_9r":0,
    "qs_pg:photos_sr":0,
    "qs_pg:pop_sr":2,
    "qs_pg:qs_pg_placetype":"locality",
    "qs_pg:qs_pg_placetype_gp":"Town",
    "qs_pg:woe_adm0":23424950,
    "woe:adm0_id":23424950,
    "woe:name_adm0":"Espa\u00f1a",
    "woe:name_adm1":"Castilla y Le\u00f3n",
    "woe:placetype":"Town",
    "wof:name":"Palacios de Sanabria",
    "wof:placetype":"locality",
    "wof:population":321
},
  "geometry": {"coordinates":[-6.52362,42.05901],"type":"Point"}
}