{
  "type": "Feature",
  "properties": {
    "gn:admin1_code":"54",
    "gn:admin2_code":"GU",
    "gn:admin3_code":"19209",
    "gn:asciiname":"Pardos",
    "gn:country_code":"ES",
    "gn:dem":1185,
    "gn:feature_class":"P",
    "gn:feature_code":"PPLA3",
    "gn:name":"Pardos",
    "gn:population":0,
    "gn:timezone":"Europe/Madrid",
    "iso:country":"ES",
    "wof:name":"Pardos",
    "wof:placetype":"locality"
},
  "geometry": {"coordinates":[-1.92555,40.94818],"type":"Point"}
}