{
  "type": "Feature",
  "properties": {
    "gn:admin1_code":"54",
    "gn:admin2_code":"GU",
    "gn:admin3_code":"19209",
    "gn:asciiname":"Pardos",
    "gn:country_code":"ES",
    "gn:dem":1185,
    "gn:feature_class":"P",
    "gn:feature_code":"PPLA3",
    "gn:name":"Pardos",
    "gn:population":0,
    "gn:timezone":"Europe/Madrid",
    "iso:country":"ES",
    "name:arg_x_preferred":[
        "Pardos"
    ],
    "name:ast_x_preferred":[
        "Pardos"
    ],
    "name:cat_x_preferred":[
        "Pardos"
    ],
    "name:ceb_x_preferred":[
        "Pardos"
    ],
    "name:epo_x_preferred":[
        "Pardos"
    ],
    "name:eus_x_preferred":[
        "Pardos"
    ],
    "name:fra_x_preferred":[
        "Pardos"
    ],
    "name:hun_x_preferred":[
        "Pardos"
    ],
    "name:ina_x_preferred":[
        "Pardos"
    ],
    "name:ita_x_preferred":[
        "Pardos"
    ],
    "name:kaz_x_preferred":[
        "\u041f\u0430\u0440\u0434\u043e\u0441"
    ],
    "name:msa_x_preferred":[
        "Pardos"
    ],
    "name:nld_x_preferred":[
        "Pardos"
    ],
    "name:oci_x_preferred":[
        "Pardos"
    ],
    "name:pol_x_preferred":[
        "Pardos"
    ],
    "name:por_x_preferred":[
        "Pardos"
    ],
    "name:rus_x_preferred":[
        "\u041f\u0430\u0440\u0434\u043e\u0441"
    ],
    "name:spa_x_preferred":[
        "Pardos"
    ],
    "name:sqi_x_preferred":[
        "Pardos"
    ],
    "name:swe_x_preferred":[
        "Pardos"
    ],
    "name:ukr_x_preferred":[
        "\u041f\u0430\u0440\u0434\u043e\u0441"
    ],
    "name:war_x_preferred":[
        "Pardos"
    ],
    "name:zho_x_preferred":[
        "\u5e15\u5c14\u591a\u65af"
    ],
    "wof:name":"Pardos",
    "wof:placetype":"locality"
},
  "geometry": {"coordinates":[-1.92555,40.94818],"type":"Point"}
}