{
  "type": "Feature",
  "properties": {
    "gn:country":"ES",
    "gn:fcode":"PPLA3",
    "gn:population":431,
    "iso:country":"ES",
    "name:ara_x_preferred":[
        "\u062e\u064a\u0645\u064a\u0631\u0627 \u062f\u064a \u0644\u064a\u0628\u0627\u0631"
    ],
    "name:arg_x_preferred":[
        "Jimera de L\u00edbar"
    ],
    "name:cat_x_preferred":[
        "Jimera de L\u00edbar"
    ],
    "name:eng_x_preferred":[
        "Jimera de L\u00edbar"
    ],
    "name:eus_x_preferred":[
        "Jimera de L\u00edbar"
    ],
    "name:fra_x_preferred":[
        "Jimera de L\u00edbar"
    ],
    "name:hun_x_preferred":[
        "Jimera de L\u00edbar"
    ],
    "name:hye_x_preferred":[
        "\u053d\u056b\u0574\u0565\u0580\u0561 \u0564\u0565 \u053c\u056b\u0562\u0561\u0580"
    ],
    "name:ita_x_preferred":[
        "Jimera de L\u00edbar"
    ],
    "name:kaz_x_preferred":[
        "\u0425\u0438\u043c\u0435\u0440\u0430-\u0434\u0435-\u041b\u0438\u0431\u0430\u0440"
    ],
    "name:kon_x_preferred":[
        "Jimera de L\u00edbar"
    ],
    "name:msa_x_preferred":[
        "Jimera de L\u00edbar"
    ],
    "name:nan_x_preferred":[
        "Jimera de L\u00edbar"
    ],
    "name:nld_x_preferred":[
        "Jimera de L\u00edbar"
    ],
    "name:oci_x_preferred":[
        "Jimera de L\u00edbar"
    ],
    "name:pol_x_preferred":[
        "Jimera de L\u00edbar"
    ],
    "name:por_x_preferred":[
        "Jimera de L\u00edbar"
    ],
    "name:rus_x_preferred":[
        "\u0425\u0438\u043c\u0435\u0440\u0430-\u0434\u0435-\u041b\u0438\u0431\u0430\u0440"
    ],
    "name:spa_x_preferred":[
        "Jimera de L\u00edbar"
    ],
    "name:swe_x_preferred":[
        "Jimera de L\u00edbar"
    ],
    "name:ukr_x_preferred":[
        "\u0425\u0456\u043c\u0435\u0440\u0430-\u0434\u0435-\u041b\u0456\u0431\u0430\u0440"
    ],
    "name:uzb_x_preferred":[
        "Jimera de L\u00edbar"
    ],
    "name:vie_x_preferred":[
        "Jimera de L\u00edbar"
    ],
    "name:war_x_preferred":[
        "Jimera de L\u00edbar"
    ],
    "name:zho_x_preferred":[
        "\u5e0c\u6885\u62c9\u5fb7\u5229\u74e6\u5c14"
    ],
    "qs_pg:aaroncc":"ES",
    "qs_pg:gn_country":"ES",
    "qs_pg:gn_fcode":"PPLA3",
    "qs_pg:gn_pop":431,
    "qs_pg:name":"Jimera de L\u00edbar",
    "qs_pg:name_adm0":"Espa\u00f1a",
    "qs_pg:name_adm1":"Andaluc\u00eda",
    "qs_pg:photos":113,
    "qs_pg:photos_1k":23,
    "qs_pg:photos_9k":1,
    "qs_pg:photos_9r":3,
    "qs_pg:photos_all":113,
    "qs_pg:photos_sr":3,
    "qs_pg:pop_sr":2,
    "qs_pg:qs_pg_placetype":"locality",
    "qs_pg:qs_pg_placetype_gp":"Town",
    "qs_pg:woe_adm0":23424950,
    "woe:adm0_id":23424950,
    "woe:name_adm0":"Espa\u00f1a",
    "woe:name_adm1":"Andaluc\u00eda",
    "woe:placetype":"Town",
    "wof:name":"Jimera de L\u00edbar",
    "wof:placetype":"locality",
    "wof:population":431
},
  "geometry": {"coordinates":[-5.27412,36.65119],"type":"Point"}
}