{
  "type": "Feature",
  "properties": {
    "gn:admin1_code":"51",
    "gn:admin2_code":"J",
    "gn:admin3_code":"23050",
    "gn:asciiname":"Brujuelo",
    "gn:country_code":"ES",
    "gn:dem":438,
    "gn:feature_class":"P",
    "gn:feature_code":"PPL",
    "gn:name":"Brujuelo",
    "gn:population":0,
    "gn:timezone":"Europe/Madrid",
    "iso:country":"ES",
    "name:und_x_variant":[
        "Caser\u00edo Brujuelo",
        "Brujuelo"
    ],
    "wof:name":"Brujuelo",
    "wof:placetype":"locality"
},
  "geometry": {"coordinates":[-3.66875,37.8788],"type":"Point"}
}