{
  "type": "Feature",
  "properties": {
    "gn:admin1_code":"55",
    "gn:admin2_code":"LE",
    "gn:admin3_code":"24170",
    "gn:asciiname":"San Andres de las Puentes",
    "gn:country_code":"ES",
    "gn:dem":786,
    "gn:feature_class":"P",
    "gn:feature_code":"PPL",
    "gn:name":"San Andr\u00e9s de las Puentes",
    "gn:population":0,
    "gn:timezone":"Europe/Madrid",
    "iso:country":"ES",
    "wof:name":"San Andres de las Puentes",
    "wof:placetype":"locality"
},
  "geometry": {"coordinates":[-6.37676,42.57363],"type":"Point"}
}