{
  "type": "Feature",
  "properties": {
    "gn:admin1_code":"55",
    "gn:admin2_code":"BU",
    "gn:admin3_code":"09074",
    "gn:asciiname":"San Medel",
    "gn:country_code":"ES",
    "gn:dem":897,
    "gn:feature_class":"P",
    "gn:feature_code":"PPL",
    "gn:name":"San Medel",
    "gn:population":0,
    "gn:timezone":"Europe/Madrid",
    "iso:country":"ES",
    "wof:name":"San Medel",
    "wof:placetype":"locality"
},
  "geometry": {"coordinates":[-3.59665,42.33317],"type":"Point"}
}