{
  "type": "Feature",
  "properties": {
    "gn:admin1_code":"27",
    "gn:admin2_code":"LO",
    "gn:admin3_code":"26126",
    "gn:asciiname":"Olivan",
    "gn:country_code":"ES",
    "gn:dem":859,
    "gn:feature_class":"P",
    "gn:feature_code":"PPL",
    "gn:name":"Oliv\u00e1n",
    "gn:population":0,
    "gn:timezone":"Europe/Madrid",
    "iso:country":"ES",
    "wof:name":"Olivan",
    "wof:placetype":"locality"
},
  "geometry": {"coordinates":[-2.30842,42.23495],"type":"Point"}
}