{
  "type": "Feature",
  "properties": {
    "gn:admin1_code":"58",
    "gn:admin2_code":"LU",
    "gn:admin3_code":"27010",
    "gn:asciiname":"Bendia",
    "gn:cc2":"ES",
    "gn:country_code":"ES",
    "gn:dem":420,
    "gn:feature_class":"P",
    "gn:feature_code":"PPL",
    "gn:name":"Bend\u00eda",
    "gn:population":0,
    "gn:timezone":"Europe/Madrid",
    "iso:country":"ES",
    "name:und_x_variant":[
        "San Andr\u00e9s",
        "Bend\u00eda"
    ],
    "wof:name":"Bendia",
    "wof:placetype":"locality"
},
  "geometry": {"coordinates":[-7.46667,43.16667],"type":"Point"}
}