{
  "type": "Feature",
  "properties": {
    "iso:country":"ES",
    "qs_pg:aaroncc":"ES",
    "qs_pg:name":"Rub\u00e1rcena",
    "qs_pg:name_adm0":"Espa\u00f1a",
    "qs_pg:name_adm1":"Cantabria",
    "qs_pg:photos":9,
    "qs_pg:photos_1k":2,
    "qs_pg:photos_9k":1,
    "qs_pg:photos_9r":1,
    "qs_pg:photos_all":9,
    "qs_pg:photos_sr":1,
    "qs_pg:pop_sr":0,
    "qs_pg:qs_pg_placetype":"locality",
    "qs_pg:qs_pg_placetype_gp":"Town",
    "qs_pg:woe_adm0":23424950,
    "woe:adm0_id":23424950,
    "woe:name_adm0":"Espa\u00f1a",
    "woe:name_adm1":"Cantabria",
    "woe:placetype":"Town",
    "wof:name":"Rub\u00e1rcena",
    "wof:placetype":"locality"
},
  "geometry": {"coordinates":[-4.300578,43.383561],"type":"Point"}
}