{
  "type": "Feature",
  "properties": {
    "gn:admin1_code":"34",
    "gn:admin2_code":"O",
    "gn:admin3_code":"33017",
    "gn:asciiname":"Moldes",
    "gn:country_code":"ES",
    "gn:dem":53,
    "gn:feature_class":"P",
    "gn:feature_code":"PPL",
    "gn:name":"Moldes",
    "gn:population":0,
    "gn:timezone":"Europe/Madrid",
    "iso:country":"ES",
    "name:spa_x_preferred":[
        "Moldes"
    ],
    "name:und_x_variant":[
        "San Juan",
        "Moldes"
    ],
    "wof:name":"Moldes",
    "wof:placetype":"locality"
},
  "geometry": {"coordinates":[-7.02017,43.51804],"type":"Point"}
}