{
  "type": "Feature",
  "properties": {
    "gn:admin1_code":"52",
    "gn:admin2_code":"HU",
    "gn:admin3_code":"22066",
    "gn:asciiname":"Morcat",
    "gn:country_code":"ES",
    "gn:dem":1088,
    "gn:feature_class":"P",
    "gn:feature_code":"PPL",
    "gn:name":"Morcat",
    "gn:population":0,
    "gn:timezone":"Europe/Madrid",
    "iso:country":"ES",
    "wof:name":"Morcat",
    "wof:placetype":"locality"
},
  "geometry": {"coordinates":[0.02495,42.39859000000001],"type":"Point"}
}