{
  "type": "Feature",
  "properties": {
    "gn:admin1_code":"51",
    "gn:admin2_code":"AL",
    "gn:admin3_code":"04064",
    "gn:asciiname":"La Marina de la Torre",
    "gn:cc2":"ES",
    "gn:country_code":"ES",
    "gn:dem":9,
    "gn:feature_class":"P",
    "gn:feature_code":"PPL",
    "gn:name":"La Marina de la Torre",
    "gn:population":0,
    "gn:timezone":"Europe/Madrid",
    "iso:country":"ES",
    "name:und_x_variant":[
        "Cortijada La Marina de la Torre"
    ],
    "wof:name":"La Marina de la Torre",
    "wof:placetype":"locality"
},
  "geometry": {"coordinates":[-1.82622,37.16018],"type":"Point"}
}