{
  "type": "Feature",
  "properties": {
    "gn:admin1_code":"51",
    "gn:admin2_code":"J",
    "gn:admin3_code":"23017",
    "gn:asciiname":"El Chantre",
    "gn:country_code":"ES",
    "gn:dem":831,
    "gn:feature_class":"P",
    "gn:feature_code":"PPL",
    "gn:name":"El Chantre",
    "gn:population":0,
    "gn:timezone":"Europe/Madrid",
    "iso:country":"ES",
    "name:und_x_variant":[
        "Cortijada El Chantre",
        "El Chantre"
    ],
    "wof:name":"El Chantre",
    "wof:placetype":"locality"
},
  "geometry": {"coordinates":[-3.22752,37.71588],"type":"Point"}
}