{
  "type": "Feature",
  "properties": {
    "gn:admin1_code":"55",
    "gn:admin2_code":"BU",
    "gn:admin3_code":"09045",
    "gn:asciiname":"Santa Cruz del Tozo",
    "gn:country_code":"ES",
    "gn:dem":951,
    "gn:feature_class":"P",
    "gn:feature_code":"PPL",
    "gn:name":"Santa Cruz del Tozo",
    "gn:population":0,
    "gn:timezone":"Europe/Madrid",
    "iso:country":"ES",
    "wof:name":"Santa Cruz del Tozo",
    "wof:placetype":"locality"
},
  "geometry": {"coordinates":[-3.88333,42.64713],"type":"Point"}
}