{
  "type": "Feature",
  "properties": {
    "gn:admin1_code":"55",
    "gn:admin2_code":"LE",
    "gn:admin3_code":"24037",
    "gn:asciiname":"Campo",
    "gn:country_code":"ES",
    "gn:dem":1227,
    "gn:feature_class":"P",
    "gn:feature_code":"PPL",
    "gn:name":"Campo",
    "gn:population":0,
    "gn:timezone":"Europe/Madrid",
    "iso:country":"ES",
    "wof:name":"Campo",
    "wof:placetype":"locality"
},
  "geometry": {"coordinates":[-5.5796,42.98928],"type":"Point"}
}