{
  "type": "Feature",
  "properties": {
    "gn:gn_country":"ES",
    "gn:gn_fcode":"PPL",
    "gn:gn_pop":296,
    "gn:population":296,
    "iso:country":"ES",
    "name:arg_x_preferred":[
        "Mald\u00e0"
    ],
    "name:cat_x_preferred":[
        "Mald\u00e0"
    ],
    "name:eng_x_preferred":[
        "Mald\u00e0"
    ],
    "name:eus_x_preferred":[
        "Mald\u00e0"
    ],
    "name:fra_x_preferred":[
        "Mald\u00e0"
    ],
    "name:hun_x_preferred":[
        "Mald\u00e0"
    ],
    "name:ita_x_preferred":[
        "Mald\u00e0"
    ],
    "name:jpn_x_preferred":[
        "\u30de\u30eb\u30c0\u30fc"
    ],
    "name:nld_x_preferred":[
        "Mald\u00e0"
    ],
    "name:oci_x_preferred":[
        "Mald\u00e0"
    ],
    "name:pol_x_preferred":[
        "Mald\u00e0"
    ],
    "name:por_x_preferred":[
        "Mald\u00e0"
    ],
    "name:ron_x_preferred":[
        "Mald\u00e0"
    ],
    "name:rus_x_preferred":[
        "\u041c\u0430\u043b\u044c\u0434\u0430"
    ],
    "name:spa_x_preferred":[
        "Mald\u00e1"
    ],
    "name:swe_x_preferred":[
        "Mald\u00e0"
    ],
    "name:uzb_x_preferred":[
        "Mald\u00e0"
    ],
    "name:vie_x_preferred":[
        "Mald\u00e0"
    ],
    "name:war_x_preferred":[
        "Mald\u00e0"
    ],
    "name:zho_x_preferred":[
        "\u9a6c\u5c14\u8fbe"
    ],
    "qs_pg:aaroncc":"ES",
    "qs_pg:gn_country":"ES",
    "qs_pg:gn_fcode":"PPL",
    "qs_pg:gn_pop":296,
    "qs_pg:name":"Mald\u00e0",
    "qs_pg:name_adm0":"Espa\u00f1a",
    "qs_pg:name_adm1":"Catalunya",
    "qs_pg:photos_9k":1,
    "qs_pg:photos_9r":4,
    "qs_pg:photos_all":186,
    "qs_pg:photos_sr":0,
    "qs_pg:pop_sr":2,
    "qs_pg:qs_pg_placetype":"locality",
    "qs_pg:qs_pg_placetype_gp":"Town",
    "qs_pg:woe_adm0":23424950,
    "woe:adm0_id":23424950,
    "woe:name_adm0":"Espa\u00f1a",
    "woe:name_adm1":"Catalunya",
    "woe:placetype":"Town",
    "wof:name":"Mald\u00e0",
    "wof:placetype":"locality",
    "wof:population":296
},
  "geometry": {"coordinates":[1.03333,41.55],"type":"Point"}
}