{
  "type": "Feature",
  "properties": {
    "gn:admin1_code":"51",
    "gn:admin2_code":"J",
    "gn:admin3_code":"23066",
    "gn:asciiname":"El Posito",
    "gn:country_code":"ES",
    "gn:dem":386,
    "gn:feature_class":"P",
    "gn:feature_code":"PPL",
    "gn:name":"El P\u00f3sito",
    "gn:population":0,
    "gn:timezone":"Europe/Madrid",
    "iso:country":"ES",
    "name:und_x_variant":[
        "Cortijada El P\u00f3sito",
        "Cortijo del P\u00f3sito",
        "El P\u00f3sito"
    ],
    "wof:name":"El Posito",
    "wof:placetype":"locality"
},
  "geometry": {"coordinates":[-3.22124,37.94299],"type":"Point"}
}