{
  "type": "Feature",
  "properties": {
    "gn:gn_country":"ES",
    "gn:gn_fcode":"PPLA3",
    "gn:gn_pop":591,
    "gn:population":591,
    "iso:country":"ES",
    "name:alb_x_preferred":[
        "Orist\u00e0"
    ],
    "name:ara_x_preferred":[
        "\u0623\u0648\u0631\u064a\u0633\u062a\u0627\u060c \u0628\u0631\u0634\u0644\u0648\u0646\u0629"
    ],
    "name:arg_x_preferred":[
        "Orist\u00e0"
    ],
    "name:arm_x_preferred":[
        "\u0555\u0580\u056b\u057d\u057f\u0561"
    ],
    "name:baq_x_preferred":[
        "Orist\u00e0"
    ],
    "name:cat_x_preferred":[
        "Orist\u00e0"
    ],
    "name:chi_x_preferred":[
        "\u5965\u91cc\u65af\u5854"
    ],
    "name:dut_x_preferred":[
        "Orist\u00e0"
    ],
    "name:eng_x_preferred":[
        "Orist\u00e0"
    ],
    "name:fre_x_preferred":[
        "Orist\u00e0"
    ],
    "name:ger_x_preferred":[
        "Orist\u00e0"
    ],
    "name:hun_x_preferred":[
        "Orist\u00e0"
    ],
    "name:ita_x_preferred":[
        "Orist\u00e0"
    ],
    "name:kaz_x_preferred":[
        "\u041e\u0440\u0438\u0441\u0442\u0430"
    ],
    "name:lat_x_preferred":[
        "Orist\u00e0"
    ],
    "name:oci_x_preferred":[
        "Orist\u00e0"
    ],
    "name:per_x_preferred":[
        "\u0627\u0631\u06cc\u0633\u062a\u0627"
    ],
    "name:pol_x_preferred":[
        "Orist\u00e0"
    ],
    "name:por_x_preferred":[
        "Orist\u00e0"
    ],
    "name:rum_x_preferred":[
        "Orist\u00e0"
    ],
    "name:rus_x_preferred":[
        "\u041e\u0440\u0438\u0441\u0442\u0430"
    ],
    "name:spa_x_preferred":[
        "Orist\u00e1"
    ],
    "name:swe_x_preferred":[
        "Orist\u00e0"
    ],
    "name:uzb_x_preferred":[
        "Orist\u00e0"
    ],
    "name:war_x_preferred":[
        "Orist\u00e0"
    ],
    "qs_pg:aaroncc":"ES",
    "qs_pg:gn_country":"ES",
    "qs_pg:gn_fcode":"PPLA3",
    "qs_pg:gn_pop":591,
    "qs_pg:name":"Orist\u00e0",
    "qs_pg:name_adm0":"Espa\u00f1a",
    "qs_pg:name_adm1":"Catalunya",
    "qs_pg:photos":75,
    "qs_pg:photos_1k":15,
    "qs_pg:photos_9k":1,
    "qs_pg:photos_9r":2,
    "qs_pg:photos_all":75,
    "qs_pg:photos_sr":2,
    "qs_pg:pop_sr":2,
    "qs_pg:qs_pg_placetype":"locality",
    "qs_pg:qs_pg_placetype_gp":"Town",
    "qs_pg:woe_adm0":23424950,
    "woe:adm0_id":23424950,
    "woe:name_adm0":"Espa\u00f1a",
    "woe:name_adm1":"Catalunya",
    "woe:placetype":"Town",
    "wof:name":"Orist\u00e0",
    "wof:placetype":"locality",
    "wof:population":591
},
  "geometry": {"coordinates":[2.06667,41.93333],"type":"Point"}
}