{
  "type": "Feature",
  "properties": {
    "gn:admin1_code":"31",
    "gn:admin2_code":"MU",
    "gn:admin3_code":"30024",
    "gn:asciiname":"Campico de los Lopez",
    "gn:country_code":"ES",
    "gn:dem":683,
    "gn:feature_class":"P",
    "gn:feature_code":"PPL",
    "gn:name":"Campico de los L\u00f3pez",
    "gn:population":0,
    "gn:timezone":"Europe/Madrid",
    "iso:country":"ES",
    "name:und_x_variant":[
        "Campico L\u00f3pez",
        "Campico de Lopez",
        "Campico de los L\u00f3pez"
    ],
    "wof:name":"Campico de los Lopez",
    "wof:placetype":"locality"
},
  "geometry": {"coordinates":[-1.57814,37.58818],"type":"Point"}
}