{
  "type": "Feature",
  "properties": {
    "gn:admin1_code":"58",
    "gn:admin2_code":"LU",
    "gn:admin3_code":"27062",
    "gn:asciiname":"Meizaran",
    "gn:country_code":"ES",
    "gn:dem":947,
    "gn:feature_class":"P",
    "gn:feature_code":"PPL",
    "gn:name":"Meizar\u00e1n",
    "gn:population":0,
    "gn:timezone":"Europe/Madrid",
    "iso:country":"ES",
    "wof:name":"Meizaran",
    "wof:placetype":"locality"
},
  "geometry": {"coordinates":[-7.176,42.7666],"type":"Point"}
}