{
  "type": "Feature",
  "properties": {
    "gn:admin1_code":"51",
    "gn:admin2_code":"MA",
    "gn:admin3_code":"29051.0",
    "gn:asciiname":"Atalaya Isdabe",
    "gn:country_code":"ES",
    "gn:dem":15,
    "gn:feature_class":"P",
    "gn:feature_code":"PPL",
    "gn:name":"Atalaya Isdabe",
    "gn:population":0,
    "gn:timezone":"Europe/Madrid",
    "iso:country":"ES",
    "wof:name":"Atalaya Isdabe",
    "wof:placetype":"locality"
},
  "geometry": {"coordinates":[-5.0153,36.46468],"type":"Point"}
}