{
  "type": "Feature",
  "properties": {
    "gn:admin1_code":"56",
    "gn:admin2_code":"T",
    "gn:admin3_code":"43013",
    "gn:asciiname":"Las Tres Cales",
    "gn:country_code":"ES",
    "gn:dem":44,
    "gn:feature_class":"P",
    "gn:feature_code":"PPL",
    "gn:name":"Las Tres Cales",
    "gn:population":0,
    "gn:timezone":"Europe/Madrid",
    "iso:country":"ES",
    "wof:name":"Las Tres Cales",
    "wof:placetype":"locality"
},
  "geometry": {"coordinates":[0.80938,40.91158],"type":"Point"}
}