{
  "type": "Feature",
  "properties": {
    "gn:gn_country":"ES",
    "gn:gn_fcode":"PPLA3",
    "gn:gn_pop":60,
    "gn:population":60,
    "iso:country":"ES",
    "name:arm_x_preferred":[
        "\u054e\u0561\u056c\u0564\u0565\u057c\u0561\u0562\u0561\u0576\u0578"
    ],
    "name:baq_x_preferred":[
        "Valderr\u00e1bano"
    ],
    "name:cat_x_preferred":[
        "Valderr\u00e1bano"
    ],
    "name:chi_x_preferred":[
        "\u5df4\u5c14\u5fb7\u62c9\u74e6\u8bfa"
    ],
    "name:dut_x_preferred":[
        "Valderr\u00e1bano"
    ],
    "name:eng_x_preferred":[
        "Valderr\u00e1bano"
    ],
    "name:fre_x_preferred":[
        "Valderr\u00e1bano"
    ],
    "name:glg_x_preferred":[
        "Valderr\u00e1bano"
    ],
    "name:hun_x_preferred":[
        "Valderr\u00e1bano"
    ],
    "name:ina_x_preferred":[
        "Valderr\u00e1bano"
    ],
    "name:ita_x_preferred":[
        "Valderr\u00e1bano"
    ],
    "name:may_x_preferred":[
        "Valderr\u00e1bano"
    ],
    "name:nan_x_preferred":[
        "Valderr\u00e1bano"
    ],
    "name:oci_x_preferred":[
        "Valderr\u00e1bano"
    ],
    "name:per_x_preferred":[
        "\u0628\u0627\u0644\u062f\u0631\u0627\u0628\u0627\u0646\u0648"
    ],
    "name:pol_x_preferred":[
        "Valderr\u00e1bano"
    ],
    "name:por_x_preferred":[
        "Valderr\u00e1bano"
    ],
    "name:rus_x_preferred":[
        "\u0412\u0430\u043b\u044c\u0434\u0435\u0440\u0440\u0430\u0431\u0430\u043d\u043e"
    ],
    "name:spa_x_preferred":[
        "Valderr\u00e1bano"
    ],
    "name:swe_x_preferred":[
        "Valderr\u00e1bano"
    ],
    "name:ukr_x_preferred":[
        "\u0412\u0430\u043b\u044c\u0434\u0435\u0440\u0440\u0430\u0431\u0430\u043d\u043e"
    ],
    "name:uzb_x_preferred":[
        "Valderr\u00e1bano"
    ],
    "name:vie_x_preferred":[
        "Valderr\u00e1bano"
    ],
    "name:war_x_preferred":[
        "Valderr\u00e1bano"
    ],
    "qs_pg:aaroncc":"ES",
    "qs_pg:gn_country":"ES",
    "qs_pg:gn_fcode":"PPLA3",
    "qs_pg:gn_pop":60,
    "qs_pg:name":"Valderr\u00e1bano",
    "qs_pg:name_adm0":"Espa\u00f1a",
    "qs_pg:name_adm1":"Castilla y Le\u00f3n",
    "qs_pg:photos_9r":0,
    "qs_pg:photos_sr":0,
    "qs_pg:pop_sr":1,
    "qs_pg:qs_pg_placetype":"locality",
    "qs_pg:qs_pg_placetype_gp":"Town",
    "qs_pg:woe_adm0":23424950,
    "woe:adm0_id":23424950,
    "woe:name_adm0":"Espa\u00f1a",
    "woe:name_adm1":"Castilla y Le\u00f3n",
    "woe:placetype":"Town",
    "wof:name":"Valderr\u00e1bano",
    "wof:placetype":"locality",
    "wof:population":60
},
  "geometry": {"coordinates":[-4.65584,42.60674],"type":"Point"}
}