{
  "type": "Feature",
  "properties": {
    "gn:admin1_code":"53",
    "gn:admin2_code":"TF",
    "gn:admin3_code":"38027",
    "gn:asciiname":"Los Barros",
    "gn:country_code":"ES",
    "gn:dem":628,
    "gn:feature_class":"P",
    "gn:feature_code":"PPL",
    "gn:name":"Los Barros",
    "gn:population":0,
    "gn:timezone":"Atlantic/Canary",
    "iso:country":"ES",
    "wof:name":"Los Barros",
    "wof:placetype":"locality"
},
  "geometry": {"coordinates":[-17.883,28.65773],"type":"Point"}
}