{
  "type": "Feature",
  "properties": {
    "gn:gn_country":"ES",
    "gn:gn_fcode":"PPL",
    "gn:gn_pop":0,
    "iso:country":"ES",
    "name:cat_x_preferred":[
        "Riu Cadagua"
    ],
    "name:ceb_x_preferred":[
        "Cadagua"
    ],
    "name:chv_x_preferred":[
        "\u041a\u0430\u0434\u0430\u0433\u0443\u0430"
    ],
    "name:deu_x_preferred":[
        "Cadagua"
    ],
    "name:ell_x_preferred":[
        "\u039a\u03b1\u03b4\u03ac\u03b3\u03bf\u03c5\u03b1"
    ],
    "name:eus_x_preferred":[
        "Cadagua"
    ],
    "name:fra_x_preferred":[
        "Kadagua"
    ],
    "name:glg_x_preferred":[
        "R\u00edo Cadagua"
    ],
    "name:nld_x_preferred":[
        "Cadagua"
    ],
    "name:nno_x_preferred":[
        "Cadagua"
    ],
    "name:oci_x_preferred":[
        "Cadagua"
    ],
    "name:rus_x_preferred":[
        "\u041a\u0430\u0434\u0430\u0433\u0443\u0430"
    ],
    "name:spa_x_preferred":[
        "R\u00edo Cadagua"
    ],
    "name:swe_x_preferred":[
        "Cadagua"
    ],
    "name:unk_x_variant":[
        "Cadagufa"
    ],
    "name:zho_x_preferred":[
        "\u5361\u9054\u74dc\u6cb3"
    ],
    "qs_pg:aaroncc":"ES",
    "qs_pg:gn_country":"ES",
    "qs_pg:gn_fcode":"PPL",
    "qs_pg:gn_pop":0,
    "qs_pg:name":"Cadagua",
    "qs_pg:name_adm0":"Espa\u00f1a",
    "qs_pg:name_adm1":"Castilla y Le\u00f3n",
    "qs_pg:photos":57,
    "qs_pg:photos_1k":12,
    "qs_pg:photos_9k":1,
    "qs_pg:photos_9r":2,
    "qs_pg:photos_all":57,
    "qs_pg:photos_sr":2,
    "qs_pg:pop_sr":0,
    "qs_pg:qs_pg_placetype":"locality",
    "qs_pg:qs_pg_placetype_gp":"Town",
    "qs_pg:woe_adm0":23424950,
    "woe:adm0_id":23424950,
    "woe:name_adm0":"Espa\u00f1a",
    "woe:name_adm1":"Castilla y Le\u00f3n",
    "woe:placetype":"Town",
    "wof:name":"Cadagua",
    "wof:placetype":"locality"
},
  "geometry": {"coordinates":[-3.35011,43.07311],"type":"Point"}
}