{
  "type": "Feature",
  "properties": {
    "gn:country":"ES",
    "gn:fcode":"PPL",
    "gn:population":743,
    "iso:country":"ES",
    "name:arg_x_preferred":[
        "Erro"
    ],
    "name:bre_x_preferred":[
        "Erroibar"
    ],
    "name:bul_x_preferred":[
        "\u0415\u0440\u043e\u0438\u0431\u0430\u0440"
    ],
    "name:cat_x_preferred":[
        "Erroibar"
    ],
    "name:ceb_x_preferred":[
        "Erroibar"
    ],
    "name:deu_x_preferred":[
        "Erro"
    ],
    "name:eng_x_preferred":[
        "Erro"
    ],
    "name:eus_x_preferred":[
        "Erroibar"
    ],
    "name:fra_x_preferred":[
        "Erro"
    ],
    "name:glg_x_preferred":[
        "Erro"
    ],
    "name:hun_x_preferred":[
        "Erro"
    ],
    "name:ita_x_preferred":[
        "Erro"
    ],
    "name:jpn_x_preferred":[
        "\u30a8\u30ed"
    ],
    "name:msa_x_preferred":[
        "Erro"
    ],
    "name:nan_x_preferred":[
        "Erro"
    ],
    "name:nld_x_preferred":[
        "Erro"
    ],
    "name:oci_x_preferred":[
        "Erroibar"
    ],
    "name:pol_x_preferred":[
        "Erro"
    ],
    "name:por_x_preferred":[
        "Erro"
    ],
    "name:rup_x_preferred":[
        "Erro"
    ],
    "name:rus_x_preferred":[
        "\u042d\u0440\u0440\u043e"
    ],
    "name:spa_x_preferred":[
        "Erro"
    ],
    "name:swe_x_preferred":[
        "Erroibar"
    ],
    "name:ukr_x_preferred":[
        "\u0415\u0440\u0440\u043e"
    ],
    "name:uzb_x_preferred":[
        "Erro"
    ],
    "name:vie_x_preferred":[
        "Erro"
    ],
    "name:war_x_preferred":[
        "Erro"
    ],
    "name:zho_x_preferred":[
        "\u57c3\u7f57"
    ],
    "qs_pg:aaroncc":"ES",
    "qs_pg:gn_country":"ES",
    "qs_pg:gn_fcode":"PPL",
    "qs_pg:gn_pop":743,
    "qs_pg:name":"Erro",
    "qs_pg:name_adm0":"Espa\u00f1a",
    "qs_pg:name_adm1":"Comunidad Foral de Navarra",
    "qs_pg:photos":120,
    "qs_pg:photos_1k":24,
    "qs_pg:photos_9k":1,
    "qs_pg:photos_9r":3,
    "qs_pg:photos_all":120,
    "qs_pg:photos_sr":3,
    "qs_pg:pop_sr":2,
    "qs_pg:qs_pg_placetype":"locality",
    "qs_pg:qs_pg_placetype_gp":"Town",
    "qs_pg:woe_adm0":23424950,
    "woe:adm0_id":23424950,
    "woe:name_adm0":"Espa\u00f1a",
    "woe:name_adm1":"Comunidad Foral de Navarra",
    "woe:placetype":"Town",
    "wof:name":"Erro",
    "wof:placetype":"locality",
    "wof:population":743
},
  "geometry": {"coordinates":[-1.45,42.95],"type":"Point"}
}