{
  "type": "Feature",
  "properties": {
    "gn:admin1_code":"51",
    "gn:admin2_code":"GR",
    "gn:admin3_code":"18023",
    "gn:asciiname":"La Jamula",
    "gn:country_code":"ES",
    "gn:dem":1034,
    "gn:feature_class":"P",
    "gn:feature_code":"PPL",
    "gn:name":"La J\u00e1mula",
    "gn:population":0,
    "gn:timezone":"Europe/Madrid",
    "iso:country":"ES",
    "name:und_x_variant":[
        "Cortijos de la Jamula",
        "Caser\u00edo La J\u00e1mula",
        "La J\u00e1mula"
    ],
    "wof:name":"La Jamula",
    "wof:placetype":"locality"
},
  "geometry": {"coordinates":[-2.59419,37.49064],"type":"Point"}
}