{
  "type": "Feature",
  "properties": {
    "gn:country":"ES",
    "gn:fcode":"PPLA3",
    "gn:population":0,
    "iso:country":"ES",
    "name:ara_x_preferred":[
        "\u0623\u0644\u0627\u062e\u0627\u0631"
    ],
    "name:ast_x_preferred":[
        "Al\u00e1jar"
    ],
    "name:azb_x_preferred":[
        "\u0627\u0644\u0639\u062c\u0627\u0631"
    ],
    "name:bul_x_preferred":[
        "\u0410\u043b\u0430\u0445\u0430\u0440"
    ],
    "name:cat_x_preferred":[
        "Al\u00e1jar"
    ],
    "name:ceb_x_preferred":[
        "Al\u00e1jar"
    ],
    "name:deu_x_preferred":[
        "Al\u00e1jar"
    ],
    "name:eng_x_preferred":[
        "Al\u00e1jar"
    ],
    "name:epo_x_preferred":[
        "Al\u00e1jar"
    ],
    "name:eus_x_preferred":[
        "Al\u00e1jar"
    ],
    "name:fas_x_preferred":[
        "\u0627\u0644\u0639\u062c\u0627\u0631"
    ],
    "name:fra_x_preferred":[
        "Al\u00e1jar"
    ],
    "name:hat_x_preferred":[
        "Al\u00e1jar"
    ],
    "name:heb_x_preferred":[
        "\u05d0\u05dc\u05d7\u05d0\u05e8"
    ],
    "name:hun_x_preferred":[
        "Al\u00e1jar"
    ],
    "name:hye_x_preferred":[
        "\u0531\u056c\u0561\u056d\u0561\u0580"
    ],
    "name:ita_x_preferred":[
        "Al\u00e1jar"
    ],
    "name:jpn_x_preferred":[
        "\u30a2\u30e9\u30cf\u30eb"
    ],
    "name:kaz_x_preferred":[
        "\u0410\u043b\u0430\u0445\u0430\u0440"
    ],
    "name:lad_x_preferred":[
        "Al\u00e1jar"
    ],
    "name:msa_x_preferred":[
        "Al\u00e1jar"
    ],
    "name:nan_x_preferred":[
        "Al\u00e1jar"
    ],
    "name:nld_x_preferred":[
        "Al\u00e1jar"
    ],
    "name:oci_x_preferred":[
        "Al\u00e1jar"
    ],
    "name:pol_x_preferred":[
        "Al\u00e1jar"
    ],
    "name:por_x_preferred":[
        "Al\u00e1jar"
    ],
    "name:rus_x_preferred":[
        "\u0410\u043b\u0430\u0445\u0430\u0440"
    ],
    "name:spa_x_preferred":[
        "Al\u00e1jar"
    ],
    "name:swe_x_preferred":[
        "Al\u00e1jar"
    ],
    "name:tur_x_preferred":[
        "Al\u00e1jar"
    ],
    "name:ukr_x_preferred":[
        "\u0410\u043b\u0430\u0445\u0430\u0440"
    ],
    "name:uzb_x_preferred":[
        "Al\u00e1jar"
    ],
    "name:vie_x_preferred":[
        "Al\u00e1jar"
    ],
    "name:war_x_preferred":[
        "Al\u00e1jar"
    ],
    "name:zho_x_preferred":[
        "\u963f\u62c9\u54c8\u5c14"
    ],
    "qs_pg:aaroncc":"ES",
    "qs_pg:gn_country":"ES",
    "qs_pg:gn_fcode":"PPLA3",
    "qs_pg:gn_pop":0,
    "qs_pg:name":"Al\u00e1jar",
    "qs_pg:name_adm0":"Espa\u00f1a",
    "qs_pg:name_adm1":"Andaluc\u00eda",
    "qs_pg:photos":544,
    "qs_pg:photos_1k":110,
    "qs_pg:photos_9k":2,
    "qs_pg:photos_9r":5,
    "qs_pg:photos_all":544,
    "qs_pg:photos_sr":7,
    "qs_pg:pop_sr":0,
    "qs_pg:qs_pg_placetype":"locality",
    "qs_pg:qs_pg_placetype_gp":"Town",
    "qs_pg:woe_adm0":23424950,
    "woe:adm0_id":23424950,
    "woe:name_adm0":"Espa\u00f1a",
    "woe:name_adm1":"Andaluc\u00eda",
    "woe:placetype":"Town",
    "wof:name":"Al\u00e1jar",
    "wof:placetype":"locality"
},
  "geometry": {"coordinates":[-6.66536,37.87408],"type":"Point"}
}