{
  "type": "Feature",
  "properties": {
    "gn:country":"ES",
    "gn:fcode":"PPLA3",
    "gn:population":68,
    "iso:country":"ES",
    "name:arg_x_preferred":[
        "Aria"
    ],
    "name:bre_x_preferred":[
        "Aria"
    ],
    "name:cat_x_preferred":[
        "Aria"
    ],
    "name:ceb_x_preferred":[
        "Aria"
    ],
    "name:che_x_preferred":[
        "\u0410\u0440\u0438\u044f"
    ],
    "name:deu_x_preferred":[
        "Aria"
    ],
    "name:eng_x_preferred":[
        "Aria"
    ],
    "name:eus_x_preferred":[
        "Aria"
    ],
    "name:fra_x_preferred":[
        "Aria"
    ],
    "name:gle_x_preferred":[
        "Aria"
    ],
    "name:hun_x_preferred":[
        "Aria"
    ],
    "name:ina_x_preferred":[
        "Aria"
    ],
    "name:ita_x_preferred":[
        "Aria"
    ],
    "name:jpn_x_preferred":[
        "\u30a2\u30ea\u30a2"
    ],
    "name:kat_x_preferred":[
        "\u10d0\u10e0\u10d8\u10d0"
    ],
    "name:lld_x_preferred":[
        "Aria"
    ],
    "name:msa_x_preferred":[
        "Aria"
    ],
    "name:nan_x_preferred":[
        "Aria"
    ],
    "name:nld_x_preferred":[
        "Aria"
    ],
    "name:nob_x_preferred":[
        "Aria"
    ],
    "name:oci_x_preferred":[
        "Aria"
    ],
    "name:pol_x_preferred":[
        "Aria"
    ],
    "name:por_x_preferred":[
        "Aria"
    ],
    "name:rus_x_preferred":[
        "\u0410\u0440\u0438\u0430"
    ],
    "name:spa_x_preferred":[
        "Aria"
    ],
    "name:swe_x_preferred":[
        "Aria"
    ],
    "name:tat_x_preferred":[
        "\u0410\u0440\u0438\u044f"
    ],
    "name:ukr_x_preferred":[
        "\u0410\u0440\u0456\u044f"
    ],
    "name:vec_x_preferred":[
        "Aria"
    ],
    "name:vie_x_preferred":[
        "Aria"
    ],
    "name:war_x_preferred":[
        "Aria"
    ],
    "name:zho_x_preferred":[
        "\u963f\u91cc\u4e9a"
    ],
    "qs_pg:aaroncc":"ES",
    "qs_pg:gn_country":"ES",
    "qs_pg:gn_fcode":"PPLA3",
    "qs_pg:gn_pop":68,
    "qs_pg:name":"Aria",
    "qs_pg:name_adm0":"Espa\u00f1a",
    "qs_pg:name_adm1":"Comunidad Foral de Navarra",
    "qs_pg:photos_9k":1,
    "qs_pg:photos_9r":1,
    "qs_pg:photos_all":1,
    "qs_pg:photos_sr":0,
    "qs_pg:pop_sr":1,
    "qs_pg:qs_pg_placetype":"locality",
    "qs_pg:qs_pg_placetype_gp":"Town",
    "qs_pg:woe_adm0":23424950,
    "woe:adm0_id":23424950,
    "woe:name_adm0":"Espa\u00f1a",
    "woe:name_adm1":"Comunidad Foral de Navarra",
    "woe:placetype":"Town",
    "wof:name":"Aria",
    "wof:placetype":"locality",
    "wof:population":68
},
  "geometry": {"coordinates":[-1.26584,42.95283],"type":"Point"}
}