{
  "type": "Feature",
  "properties": {
    "gn:admin1_code":"34",
    "gn:admin2_code":"O",
    "gn:admin3_code":"33032",
    "gn:asciiname":"Pumarada",
    "gn:country_code":"ES",
    "gn:dem":656,
    "gn:feature_class":"P",
    "gn:feature_code":"PPL",
    "gn:name":"Pumarada",
    "gn:population":0,
    "gn:timezone":"Europe/Madrid",
    "iso:country":"ES",
    "name:und_x_variant":[
        "Pomarada",
        "Pumarada"
    ],
    "wof:name":"Pumarada",
    "wof:placetype":"locality"
},
  "geometry": {"coordinates":[-5.5481,43.2163],"type":"Point"}
}