{
  "type": "Feature",
  "properties": {
    "gn:admin1_code":"55",
    "gn:admin2_code":"ZA",
    "gn:admin3_code":"49152",
    "gn:asciiname":"Arcillo",
    "gn:country_code":"ES",
    "gn:dem":727,
    "gn:feature_class":"P",
    "gn:feature_code":"PPL",
    "gn:name":"Arcillo",
    "gn:population":0,
    "gn:timezone":"Europe/Madrid",
    "iso:country":"ES",
    "wof:name":"Arcillo",
    "wof:placetype":"locality"
},
  "geometry": {"coordinates":[-5.94531,41.41862],"type":"Point"}
}