{
  "type": "Feature",
  "properties": {
    "gn:admin1_code":"55",
    "gn:admin2_code":"BU",
    "gn:admin3_code":"09109",
    "gn:asciiname":"Moraza",
    "gn:country_code":"ES",
    "gn:dem":729,
    "gn:feature_class":"P",
    "gn:feature_code":"PPL",
    "gn:name":"Moraza",
    "gn:population":0,
    "gn:timezone":"Europe/Madrid",
    "iso:country":"ES",
    "wof:name":"Moraza",
    "wof:placetype":"locality"
},
  "geometry": {"coordinates":[-2.72172,42.6743],"type":"Point"}
}