{
  "type": "Feature",
  "properties": {
    "gn:country":"ES",
    "gn:fcode":"PPLA3",
    "gn:population":294,
    "iso:country":"ES",
    "name:arg_x_preferred":[
        "Coomonte"
    ],
    "name:ast_x_preferred":[
        "Coomonte"
    ],
    "name:cat_x_preferred":[
        "Coomonte"
    ],
    "name:ceb_x_preferred":[
        "Coomonte"
    ],
    "name:eng_x_preferred":[
        "Coomonte"
    ],
    "name:eus_x_preferred":[
        "Coomonte"
    ],
    "name:fra_x_preferred":[
        "Coomonte"
    ],
    "name:haw_x_preferred":[
        "Coomonte"
    ],
    "name:hun_x_preferred":[
        "Coomonte"
    ],
    "name:hye_x_preferred":[
        "\u053f\u0578\u0578\u0574\u0578\u0576\u057f\u0565"
    ],
    "name:ile_x_preferred":[
        "Coomonte"
    ],
    "name:ina_x_preferred":[
        "Coomonte"
    ],
    "name:ita_x_preferred":[
        "Coomonte"
    ],
    "name:msa_x_preferred":[
        "Coomonte"
    ],
    "name:nan_x_preferred":[
        "Coomonte"
    ],
    "name:nld_x_preferred":[
        "Coomonte"
    ],
    "name:oci_x_preferred":[
        "Coomonte"
    ],
    "name:pol_x_preferred":[
        "Coomonte"
    ],
    "name:por_x_preferred":[
        "Coomonte"
    ],
    "name:rus_x_preferred":[
        "\u041a\u043e\u043e\u043c\u043e\u043d\u0442\u0435"
    ],
    "name:spa_x_preferred":[
        "Coomonte"
    ],
    "name:swe_x_preferred":[
        "Coomonte"
    ],
    "name:ukr_x_preferred":[
        "\u041a\u043e\u043e\u043c\u043e\u043d\u0442\u0435"
    ],
    "name:uzb_x_preferred":[
        "Coomonte"
    ],
    "name:vie_x_preferred":[
        "Coomonte"
    ],
    "name:war_x_preferred":[
        "Coomonte"
    ],
    "name:zho_x_preferred":[
        "\u79d1\u5965\u8499\u7279"
    ],
    "qs_pg:aaroncc":"ES",
    "qs_pg:gn_country":"ES",
    "qs_pg:gn_fcode":"PPLA3",
    "qs_pg:gn_pop":294,
    "qs_pg:name":"Coomonte",
    "qs_pg:name_adm0":"Espa\u00f1a",
    "qs_pg:name_adm1":"Castilla y Le\u00f3n",
    "qs_pg:photos_9r":0,
    "qs_pg:photos_sr":0,
    "qs_pg:pop_sr":2,
    "qs_pg:qs_pg_placetype":"locality",
    "qs_pg:qs_pg_placetype_gp":"Town",
    "qs_pg:woe_adm0":23424950,
    "woe:adm0_id":23424950,
    "woe:name_adm0":"Espa\u00f1a",
    "woe:name_adm1":"Castilla y Le\u00f3n",
    "woe:placetype":"Town",
    "wof:name":"Coomonte",
    "wof:placetype":"locality",
    "wof:population":294
},
  "geometry": {"coordinates":[-5.81316,42.11546],"type":"Point"}
}