{
  "type": "Feature",
  "properties": {
    "gn:admin1_code":"55",
    "gn:admin2_code":"ZA",
    "gn:admin3_code":"49117",
    "gn:asciiname":"Abraveses de Tera",
    "gn:country_code":"ES",
    "gn:dem":718,
    "gn:feature_class":"P",
    "gn:feature_code":"PPL",
    "gn:name":"Abraveses de Tera",
    "gn:population":0,
    "gn:timezone":"Europe/Madrid",
    "iso:country":"ES",
    "wof:name":"Abraveses de Tera",
    "wof:placetype":"locality"
},
  "geometry": {"coordinates":[-5.8951,41.99296],"type":"Point"}
}