{
  "type": "Feature",
  "properties": {
    "gn:admin1_code":"55",
    "gn:admin2_code":"LE",
    "gn:admin3_code":"24169",
    "gn:asciiname":"Santa Marina del Sil",
    "gn:country_code":"ES",
    "gn:dem":665,
    "gn:feature_class":"P",
    "gn:feature_code":"PPL",
    "gn:name":"Santa Marina del Sil",
    "gn:population":0,
    "gn:timezone":"Europe/Madrid",
    "iso:country":"ES",
    "name:spa_x_preferred":[
        "Santa Marina del Sil"
    ],
    "wof:name":"Santa Marina del Sil",
    "wof:placetype":"locality"
},
  "geometry": {"coordinates":[-6.50096,42.66501],"type":"Point"}
}