{
  "type": "Feature",
  "properties": {
    "gn:country":"ES",
    "gn:fcode":"PPLA3",
    "gn:population":98,
    "iso:country":"ES",
    "name:arg_x_preferred":[
        "Do\u00f1inos de Ledesma"
    ],
    "name:cat_x_preferred":[
        "Do\u00f1inos de Ledesma"
    ],
    "name:che_x_preferred":[
        "\u0414\u043e\u043d\u044c\u0438\u043d\u043e\u0441-\u0434\u0435-\u041b\u0435\u0434\u0435\u0441\u043c\u0430"
    ],
    "name:eng_x_preferred":[
        "Do\u00f1inos de Ledesma"
    ],
    "name:eus_x_preferred":[
        "Do\u00f1inos de Ledesma"
    ],
    "name:fra_x_preferred":[
        "Do\u00f1inos de Ledesma"
    ],
    "name:haw_x_preferred":[
        "Do\u00f1inos de Ledesma"
    ],
    "name:hun_x_preferred":[
        "Do\u00f1inos de Ledesma"
    ],
    "name:ina_x_preferred":[
        "Do\u00f1inos de Ledesma"
    ],
    "name:ita_x_preferred":[
        "Do\u00f1inos de Ledesma"
    ],
    "name:kaz_x_preferred":[
        "\u0414\u043e\u043d\u044c\u0438\u043d\u043e\u0441-\u0434\u0435-\u041b\u0435\u0434\u0435\u0441\u043c\u0430"
    ],
    "name:msa_x_preferred":[
        "Do\u00f1inos de Ledesma"
    ],
    "name:nan_x_preferred":[
        "Do\u00f1inos de Ledesma"
    ],
    "name:nld_x_preferred":[
        "Do\u00f1inos de Ledesma"
    ],
    "name:oci_x_preferred":[
        "Do\u00f1inos de Ledesma"
    ],
    "name:pol_x_preferred":[
        "Do\u00f1inos de Ledesma"
    ],
    "name:por_x_preferred":[
        "Do\u00f1inos de Ledesma"
    ],
    "name:rup_x_preferred":[
        "Do\u00f1inos de Ledesma"
    ],
    "name:rus_x_preferred":[
        "\u0414\u043e\u043d\u044c\u0438\u043d\u043e\u0441-\u0434\u0435-\u041b\u0435\u0434\u0435\u0441\u043c\u0430"
    ],
    "name:spa_x_preferred":[
        "Do\u00f1inos de Ledesma"
    ],
    "name:swe_x_preferred":[
        "Do\u00f1inos de Ledesma"
    ],
    "name:tat_x_preferred":[
        "\u0414\u043e\u043d\u044c\u0438\u043d\u043e\u0441-\u0434\u0435-\u041b\u0435\u0434\u0435\u0441\u043c\u0430"
    ],
    "name:ukr_x_preferred":[
        "\u0414\u043e\u043d\u044c\u0457\u043d\u043e\u0441-\u0434\u0435-\u041b\u0435\u0434\u0435\u0441\u043c\u0430"
    ],
    "name:vie_x_preferred":[
        "Do\u00f1inos de Ledesma"
    ],
    "name:war_x_preferred":[
        "Do\u00f1inos de Ledesma"
    ],
    "name:zho_x_preferred":[
        "\u591a\u5c3c\u4f0a\u8bfa\u65af\u5fb7\u83b1\u5fb7\u65af\u9a6c"
    ],
    "qs_pg:aaroncc":"ES",
    "qs_pg:gn_country":"ES",
    "qs_pg:gn_fcode":"PPLA3",
    "qs_pg:gn_pop":98,
    "qs_pg:name":"Do\u00f1inos de Ledesma",
    "qs_pg:name_adm0":"Espa\u00f1a",
    "qs_pg:name_adm1":"Castilla y Le\u00f3n",
    "qs_pg:photos_9r":0,
    "qs_pg:photos_sr":0,
    "qs_pg:pop_sr":1,
    "qs_pg:qs_pg_placetype":"locality",
    "qs_pg:qs_pg_placetype_gp":"Town",
    "qs_pg:woe_adm0":23424950,
    "woe:adm0_id":23424950,
    "woe:name_adm0":"Espa\u00f1a",
    "woe:name_adm1":"Castilla y Le\u00f3n",
    "woe:placetype":"Town",
    "wof:name":"Do\u00f1inos de Ledesma",
    "wof:placetype":"locality",
    "wof:population":98
},
  "geometry": {"coordinates":[-6.03412,41.01251],"type":"Point"}
}