{
  "type": "Feature",
  "properties": {
    "gn:admin1_code":"53",
    "gn:admin2_code":"TF",
    "gn:admin3_code":"38023",
    "gn:asciiname":"La Cuesta",
    "gn:country_code":"ES",
    "gn:dem":321,
    "gn:feature_class":"P",
    "gn:feature_code":"PPL",
    "gn:name":"La Cuesta",
    "gn:population":0,
    "gn:timezone":"Atlantic/Canary",
    "iso:country":"ES",
    "wof:name":"La Cuesta",
    "wof:placetype":"locality"
},
  "geometry": {"coordinates":[-16.28622,28.46798],"type":"Point"}
}