{
  "type": "Feature",
  "properties": {
    "gn:admin1_code":"54",
    "gn:admin2_code":"AB",
    "gn:admin3_code":"02072",
    "gn:asciiname":"Los Olmos",
    "gn:country_code":"ES",
    "gn:dem":657,
    "gn:feature_class":"P",
    "gn:feature_code":"PPL",
    "gn:name":"Los Olmos",
    "gn:population":0,
    "gn:timezone":"Europe/Madrid",
    "iso:country":"ES",
    "wof:name":"Los Olmos",
    "wof:placetype":"locality"
},
  "geometry": {"coordinates":[-1.90061,38.31195],"type":"Point"}
}