{
  "type": "Feature",
  "properties": {
    "gn:country":"ES",
    "gn:fcode":"PPL",
    "gn:population":0,
    "iso:country":"ES",
    "name:arg_x_preferred":[
        "Rocafort de Queralt"
    ],
    "name:azb_x_preferred":[
        "\u0631\u06a9\u0627\u0641\u0631\u062a \u062f \u06a9\u0631\u0627\u0644\u062a"
    ],
    "name:cat_x_preferred":[
        "Rocafort de Queralt"
    ],
    "name:eng_x_preferred":[
        "Rocafort de Queralt"
    ],
    "name:eus_x_preferred":[
        "Rocafort de Queralt"
    ],
    "name:fas_x_preferred":[
        "\u0631\u06a9\u0627\u0641\u0631\u062a \u062f \u06a9\u0631\u0627\u0644\u062a"
    ],
    "name:fra_x_preferred":[
        "Rocafort de Queralt"
    ],
    "name:glg_x_preferred":[
        "Rocafort de Queralt"
    ],
    "name:hun_x_preferred":[
        "Rocafort de Queralt"
    ],
    "name:hye_x_preferred":[
        "\u054c\u0578\u056f\u0561\u0586\u0578\u0580\u057f \u0564\u0565 \u053f\u0565\u0580\u0561\u056c\u057f"
    ],
    "name:ita_x_preferred":[
        "Rocafort de Queralt"
    ],
    "name:lat_x_preferred":[
        "Rocafort de Queralt"
    ],
    "name:msa_x_preferred":[
        "Rocafort de Queralt"
    ],
    "name:nld_x_preferred":[
        "Rocafort de Queralt"
    ],
    "name:oci_x_preferred":[
        "Rocafort de Queralt"
    ],
    "name:pol_x_preferred":[
        "Rocafort de Queralt"
    ],
    "name:por_x_preferred":[
        "Rocafort de Queralt"
    ],
    "name:rus_x_preferred":[
        "\u0420\u043e\u043a\u0430\u0444\u043e\u0440\u0442-\u0434\u0435-\u041a\u0435\u0440\u0430\u043b\u044c\u0442"
    ],
    "name:spa_x_preferred":[
        "Rocafort de Queralt"
    ],
    "name:sqi_x_preferred":[
        "Rocafort de Queralt"
    ],
    "name:swe_x_preferred":[
        "Rocafort de Queralt"
    ],
    "name:uzb_x_preferred":[
        "Rocafort de Queralt"
    ],
    "name:vie_x_preferred":[
        "Rocafort de Queralt"
    ],
    "name:war_x_preferred":[
        "Rocafort de Queralt"
    ],
    "name:zho_x_preferred":[
        "\u7f57\u5361\u798f\u5c14\u7279\u5fb7\u514b\u62c9\u5c14\u7279"
    ],
    "qs_pg:aaroncc":"ES",
    "qs_pg:gn_country":"ES",
    "qs_pg:gn_fcode":"PPL",
    "qs_pg:gn_pop":0,
    "qs_pg:name":"Rocafort de Queralt",
    "qs_pg:name_adm0":"Espa\u00f1a",
    "qs_pg:name_adm1":"Catalunya",
    "qs_pg:photos":60,
    "qs_pg:photos_1k":12,
    "qs_pg:photos_9k":1,
    "qs_pg:photos_9r":2,
    "qs_pg:photos_all":60,
    "qs_pg:photos_sr":2,
    "qs_pg:pop_sr":0,
    "qs_pg:qs_pg_placetype":"locality",
    "qs_pg:qs_pg_placetype_gp":"Town",
    "qs_pg:woe_adm0":23424950,
    "woe:adm0_id":23424950,
    "woe:name_adm0":"Espa\u00f1a",
    "woe:name_adm1":"Catalunya",
    "woe:placetype":"Town",
    "wof:name":"Rocafort de Queralt",
    "wof:placetype":"locality"
},
  "geometry": {"coordinates":[1.28333,41.46667],"type":"Point"}
}