{
  "type": "Feature",
  "properties": {
    "gn:admin1_code":"27",
    "gn:admin2_code":"LO",
    "gn:admin3_code":"26004",
    "gn:asciiname":"Larriba",
    "gn:country_code":"ES",
    "gn:dem":1227,
    "gn:feature_class":"P",
    "gn:feature_code":"PPL",
    "gn:name":"Larriba",
    "gn:population":0,
    "gn:timezone":"Europe/Madrid",
    "iso:country":"ES",
    "wof:name":"Larriba",
    "wof:placetype":"locality"
},
  "geometry": {"coordinates":[-2.37181,42.17377000000001],"type":"Point"}
}