{
  "type": "Feature",
  "properties": {
    "gn:gn_country":"ES",
    "gn:gn_fcode":"PPLA3",
    "gn:gn_pop":216,
    "gn:population":216,
    "iso:country":"ES",
    "name:arg_x_preferred":[
        "Pedrosillo de Alba"
    ],
    "name:cat_x_preferred":[
        "Pedrosillo de Alba"
    ],
    "name:eng_x_preferred":[
        "Pedrosillo de Alba"
    ],
    "name:eus_x_preferred":[
        "Pedrosillo de Alba"
    ],
    "name:fra_x_preferred":[
        "Pedrosillo de Alba"
    ],
    "name:hun_x_preferred":[
        "Pedrosillo de Alba"
    ],
    "name:ina_x_preferred":[
        "Pedrosillo de Alba"
    ],
    "name:ita_x_preferred":[
        "Pedrosillo de Alba"
    ],
    "name:kaz_x_preferred":[
        "\u041f\u0435\u0434\u0440\u043e\u0441\u0438\u043b\u044c\u043e-\u0434\u0435-\u0410\u043b\u044c\u0431\u0430"
    ],
    "name:msa_x_preferred":[
        "Pedrosillo de Alba"
    ],
    "name:nan_x_preferred":[
        "Pedrosillo de Alba"
    ],
    "name:nld_x_preferred":[
        "Pedrosillo de Alba"
    ],
    "name:oci_x_preferred":[
        "Pedrosillo de Alba"
    ],
    "name:pol_x_preferred":[
        "Pedrosillo de Alba"
    ],
    "name:por_x_preferred":[
        "Pedrosillo de Alba"
    ],
    "name:rus_x_preferred":[
        "\u041f\u0435\u0434\u0440\u043e\u0441\u0438\u043b\u044c\u043e-\u0434\u0435-\u0410\u043b\u044c\u0431\u0430"
    ],
    "name:spa_x_preferred":[
        "Pedrosillo de Alba"
    ],
    "name:swe_x_preferred":[
        "Pedrosillo de Alba"
    ],
    "name:ukr_x_preferred":[
        "\u041f\u0435\u0434\u0440\u043e\u0441\u0456\u043b\u044c\u0439\u043e-\u0434\u0435-\u0410\u043b\u044c\u0431\u0430"
    ],
    "name:vie_x_preferred":[
        "Pedrosillo de Alba"
    ],
    "name:war_x_preferred":[
        "Pedrosillo de Alba"
    ],
    "name:zho_x_preferred":[
        "\u4f69\u5fb7\u7f57\u897f\u7565\u5fb7\u4e9a\u5c14\u74e6"
    ],
    "qs_pg:aaroncc":"ES",
    "qs_pg:gn_country":"ES",
    "qs_pg:gn_fcode":"PPLA3",
    "qs_pg:gn_pop":216,
    "qs_pg:name":"Pedrosillo de Alba",
    "qs_pg:name_adm0":"Espa\u00f1a",
    "qs_pg:name_adm1":"Castilla y Le\u00f3n",
    "qs_pg:photos_9r":0,
    "qs_pg:photos_sr":0,
    "qs_pg:pop_sr":2,
    "qs_pg:qs_pg_placetype":"locality",
    "qs_pg:qs_pg_placetype_gp":"Town",
    "qs_pg:woe_adm0":23424950,
    "woe:adm0_id":23424950,
    "woe:name_adm0":"Espa\u00f1a",
    "woe:name_adm1":"Castilla y Le\u00f3n",
    "woe:placetype":"Town",
    "wof:name":"Pedrosillo de Alba",
    "wof:placetype":"locality",
    "wof:population":216
},
  "geometry": {"coordinates":[-5.39506,40.82277],"type":"Point"}
}