{
  "type": "Feature",
  "properties": {
    "gn:admin1_code":"60",
    "gn:admin2_code":"A",
    "gn:admin3_code":"03018",
    "gn:asciiname":"Bernia",
    "gn:cc2":"ES",
    "gn:country_code":"ES",
    "gn:dem":497,
    "gn:feature_class":"P",
    "gn:feature_code":"PPL",
    "gn:name":"Bernia",
    "gn:population":0,
    "gn:timezone":"Europe/Madrid",
    "iso:country":"ES",
    "name:und_x_variant":[
        "Caser\u00edo Bernia",
        "Bernia"
    ],
    "wof:name":"Bernia",
    "wof:placetype":"locality"
},
  "geometry": {"coordinates":[-0.05,38.65],"type":"Point"}
}