{
  "type": "Feature",
  "properties": {
    "gn:admin1_code":"31",
    "gn:admin2_code":"MU",
    "gn:admin3_code":"30037",
    "gn:asciiname":"Molino de las Animas",
    "gn:country_code":"ES",
    "gn:dem":37,
    "gn:feature_class":"P",
    "gn:feature_code":"PPL",
    "gn:name":"Molino de las \u00c1nimas",
    "gn:population":0,
    "gn:timezone":"Europe/Madrid",
    "iso:country":"ES",
    "name:und_x_variant":[
        "Caser\u00edo Molino de las Animas",
        "Molino de las \u00c1nimas"
    ],
    "wof:name":"Molino de las Animas",
    "wof:placetype":"locality"
},
  "geometry": {"coordinates":[-0.91588,37.77365],"type":"Point"}
}