{
  "type": "Feature",
  "properties": {
    "gn:gn_country":"ES",
    "gn:gn_fcode":"PPLA3",
    "gn:gn_pop":564,
    "gn:population":564,
    "iso:country":"ES",
    "name:arg_x_preferred":[
        "Vilaplana"
    ],
    "name:ast_x_preferred":[
        "Vilaplana"
    ],
    "name:azb_x_preferred":[
        "\u0628\u06cc\u0644\u0627\u067e\u0644\u0627\u0646\u0627"
    ],
    "name:cat_x_preferred":[
        "Vilaplana"
    ],
    "name:ceb_x_preferred":[
        "Vilaplana"
    ],
    "name:deu_x_preferred":[
        "Vilaplana"
    ],
    "name:eng_x_preferred":[
        "Vilaplana"
    ],
    "name:eus_x_preferred":[
        "Vilaplana"
    ],
    "name:fas_x_preferred":[
        "\u0628\u06cc\u0644\u0627\u067e\u0644\u0627\u0646\u0627"
    ],
    "name:fra_x_preferred":[
        "Vilaplana"
    ],
    "name:glg_x_preferred":[
        "Vilaplana"
    ],
    "name:heb_x_preferred":[
        "\u05d5\u05d9\u05dc\u05e4\u05dc\u05e0\u05d4"
    ],
    "name:hun_x_preferred":[
        "Vilaplana"
    ],
    "name:hye_x_preferred":[
        "\u054e\u056b\u056c\u0561\u057a\u056c\u0561\u0576\u0561"
    ],
    "name:ita_x_preferred":[
        "Vilaplana"
    ],
    "name:lat_x_preferred":[
        "Vilaplana"
    ],
    "name:msa_x_preferred":[
        "Vilaplana"
    ],
    "name:nld_x_preferred":[
        "Vilaplana"
    ],
    "name:oci_x_preferred":[
        "Vilaplana"
    ],
    "name:pol_x_preferred":[
        "Vilaplana"
    ],
    "name:por_x_preferred":[
        "Vilaplana"
    ],
    "name:rus_x_preferred":[
        "\u0412\u0438\u043b\u0430\u043f\u043b\u0430\u043d\u0430"
    ],
    "name:spa_x_preferred":[
        "Vilaplana"
    ],
    "name:sqi_x_preferred":[
        "Vilaplana"
    ],
    "name:swe_x_preferred":[
        "Vilaplana"
    ],
    "name:ukr_x_preferred":[
        "\u0411\u0456\u043b\u0430\u043f\u043b\u0430\u043d\u0430"
    ],
    "name:uzb_x_preferred":[
        "Vilaplana"
    ],
    "name:vie_x_preferred":[
        "Vilaplana"
    ],
    "name:war_x_preferred":[
        "Vilaplana"
    ],
    "name:zho_x_preferred":[
        "\u6bd4\u62c9\u666e\u62c9\u7eb3"
    ],
    "qs_pg:aaroncc":"ES",
    "qs_pg:gn_country":"ES",
    "qs_pg:gn_fcode":"PPLA3",
    "qs_pg:gn_pop":564,
    "qs_pg:name":"Vilaplana",
    "qs_pg:name_adm0":"Espa\u00f1a",
    "qs_pg:name_adm1":"Catalunya",
    "qs_pg:photos":171,
    "qs_pg:photos_1k":35,
    "qs_pg:photos_9k":1,
    "qs_pg:photos_9r":4,
    "qs_pg:photos_all":171,
    "qs_pg:photos_sr":4,
    "qs_pg:pop_sr":2,
    "qs_pg:qs_pg_placetype":"locality",
    "qs_pg:qs_pg_placetype_gp":"Town",
    "qs_pg:woe_adm0":23424950,
    "woe:adm0_id":23424950,
    "woe:name_adm0":"Espa\u00f1a",
    "woe:name_adm1":"Catalunya",
    "woe:placetype":"Town",
    "wof:name":"Vilaplana",
    "wof:placetype":"locality",
    "wof:population":564
},
  "geometry": {"coordinates":[1.03325,41.228],"type":"Point"}
}