{
  "type": "Feature",
  "properties": {
    "gn:admin1_code":"58",
    "gn:admin2_code":"LU",
    "gn:admin3_code":"27035",
    "gn:asciiname":"Cancio",
    "gn:country_code":"ES",
    "gn:dem":420,
    "gn:feature_class":"P",
    "gn:feature_code":"PPL",
    "gn:name":"Cancio",
    "gn:population":0,
    "gn:timezone":"Europe/Madrid",
    "iso:country":"ES",
    "name:ita_x_preferred":[
        "Canzio"
    ],
    "name:pol_x_preferred":[
        "Kancjusz"
    ],
    "name:spa_x_preferred":[
        "Cancio"
    ],
    "wof:name":"Cancio",
    "wof:placetype":"locality"
},
  "geometry": {"coordinates":[-6.88333,43.11667],"type":"Point"}
}