{
  "type": "Feature",
  "properties": {
    "gn:gn_country":"ES",
    "gn:gn_fcode":"PPLA3",
    "gn:gn_pop":111,
    "gn:population":111,
    "iso:country":"ES",
    "name:arg_x_preferred":[
        "Zarapicos"
    ],
    "name:baq_x_preferred":[
        "Zarapicos"
    ],
    "name:cat_x_preferred":[
        "Zarapicos"
    ],
    "name:chi_x_preferred":[
        "\u8428\u62c9\u76ae\u79d1\u65af"
    ],
    "name:dut_x_preferred":[
        "Zarapicos"
    ],
    "name:eng_x_preferred":[
        "Zarapicos"
    ],
    "name:fre_x_preferred":[
        "Zarapicos"
    ],
    "name:ger_x_preferred":[
        "Zarapicos"
    ],
    "name:hun_x_preferred":[
        "Zarapicos"
    ],
    "name:ina_x_preferred":[
        "Zarapicos"
    ],
    "name:ita_x_preferred":[
        "Zarapicos"
    ],
    "name:kaz_x_preferred":[
        "\u0421\u0430\u0440\u0430\u043f\u0438\u043a\u043e\u0441"
    ],
    "name:may_x_preferred":[
        "Zarapicos"
    ],
    "name:nan_x_preferred":[
        "Zarapicos"
    ],
    "name:oci_x_preferred":[
        "Zarapicos"
    ],
    "name:pol_x_preferred":[
        "Zarapicos"
    ],
    "name:por_x_preferred":[
        "Zarapicos"
    ],
    "name:rus_x_preferred":[
        "\u0421\u0430\u0440\u0430\u043f\u0438\u043a\u043e\u0441"
    ],
    "name:spa_x_preferred":[
        "Zarapicos"
    ],
    "name:swe_x_preferred":[
        "Zarapicos"
    ],
    "name:ukr_x_preferred":[
        "\u0421\u0430\u0440\u0430\u043f\u0456\u043a\u043e\u0441"
    ],
    "name:vie_x_preferred":[
        "Zarapicos"
    ],
    "name:war_x_preferred":[
        "Zarapicos"
    ],
    "qs_pg:aaroncc":"ES",
    "qs_pg:gn_country":"ES",
    "qs_pg:gn_fcode":"PPLA3",
    "qs_pg:gn_pop":111,
    "qs_pg:name":"Zarapicos",
    "qs_pg:name_adm0":"Espa\u00f1a",
    "qs_pg:name_adm1":"Castilla y Le\u00f3n",
    "qs_pg:photos_9r":0,
    "qs_pg:photos_sr":0,
    "qs_pg:pop_sr":1,
    "qs_pg:qs_pg_placetype":"locality",
    "qs_pg:qs_pg_placetype_gp":"Town",
    "qs_pg:woe_adm0":23424950,
    "woe:adm0_id":23424950,
    "woe:name_adm0":"Espa\u00f1a",
    "woe:name_adm1":"Castilla y Le\u00f3n",
    "woe:placetype":"Town",
    "wof:name":"Zarapicos",
    "wof:placetype":"locality",
    "wof:population":111
},
  "geometry": {"coordinates":[-5.84526,41.0383],"type":"Point"}
}