{
  "type": "Feature",
  "properties": {
    "gn:admin1_code":"58",
    "gn:admin2_code":"LU",
    "gn:admin3_code":"27004",
    "gn:asciiname":"Surriba",
    "gn:country_code":"ES",
    "gn:dem":571,
    "gn:feature_class":"P",
    "gn:feature_code":"PPL",
    "gn:name":"Surriba",
    "gn:population":0,
    "gn:timezone":"Europe/Madrid",
    "iso:country":"ES",
    "wof:name":"Surriba",
    "wof:placetype":"locality"
},
  "geometry": {"coordinates":[-7.14371,42.99299],"type":"Point"}
}