{
  "type": "Feature",
  "properties": {
    "gn:admin1_code":"55",
    "gn:admin2_code":"LE",
    "gn:admin3_code":"24164",
    "gn:asciiname":"Pobladura",
    "gn:country_code":"ES",
    "gn:dem":1153,
    "gn:feature_class":"P",
    "gn:feature_code":"PPL",
    "gn:name":"Pobladura",
    "gn:population":0,
    "gn:timezone":"Europe/Madrid",
    "iso:country":"ES",
    "name:glg_x_preferred":[
        "Pobladura"
    ],
    "name:spa_x_preferred":[
        "Pobladura"
    ],
    "wof:name":"Pobladura",
    "wof:placetype":"locality"
},
  "geometry": {"coordinates":[-5.92926,42.91878],"type":"Point"}
}