{
  "type": "Feature",
  "properties": {
    "gn:admin1_code":"58",
    "gn:admin2_code":"OR",
    "gn:admin3_code":"32076",
    "gn:asciiname":"Cea",
    "gn:country_code":"ES",
    "gn:dem":518,
    "gn:feature_class":"P",
    "gn:feature_code":"PPL",
    "gn:name":"Cea",
    "gn:population":2960,
    "gn:timezone":"Europe/Madrid",
    "iso:country":"ES",
    "name:glg_x_preferred":[
        "Cea"
    ],
    "name:hun_x_preferred":[
        "Cea"
    ],
    "name:nld_x_preferred":[
        "Cea"
    ],
    "name:spa_x_preferred":[
        "Cea"
    ],
    "name:und_x_variant":[
        "San Crist\u00f3bal de Cea",
        "San Crist\u00f3bal",
        "Cea"
    ],
    "wof:name":"Cea",
    "wof:placetype":"locality",
    "wof:population":2960
},
  "geometry": {"coordinates":[-7.98739,42.4749],"type":"Point"}
}