{
  "type": "Feature",
  "properties": {
    "gn:admin1_code":"55",
    "gn:admin2_code":"SO",
    "gn:admin3_code":"42127",
    "gn:asciiname":"Rejas de Ucero",
    "gn:country_code":"ES",
    "gn:dem":995,
    "gn:feature_class":"P",
    "gn:feature_code":"PPL",
    "gn:name":"Rejas de Ucero",
    "gn:population":0,
    "gn:timezone":"Europe/Madrid",
    "iso:country":"ES",
    "wof:name":"Rejas de Ucero",
    "wof:placetype":"locality"
},
  "geometry": {"coordinates":[-3.10567,41.70705],"type":"Point"}
}