{
  "type": "Feature",
  "properties": {
    "gn:admin1_code":"59",
    "gn:admin2_code":"SS",
    "gn:admin3_code":"20060",
    "gn:asciiname":"Oreja",
    "gn:country_code":"ES",
    "gn:dem":414,
    "gn:feature_class":"P",
    "gn:feature_code":"PPLA3",
    "gn:name":"Orexa",
    "gn:population":0,
    "gn:timezone":"Europe/Madrid",
    "iso:country":"ES",
    "name:eus_x_preferred":[
        "Orexa"
    ],
    "name:spa_x_preferred":[
        "Oreja"
    ],
    "wof:name":"Oreja",
    "wof:placetype":"locality"
},
  "geometry": {"coordinates":[-2.01119,43.09382],"type":"Point"}
}