{
  "type": "Feature",
  "properties": {
    "gn:admin1_code":"34",
    "gn:admin2_code":"O",
    "gn:admin3_code":"33034",
    "gn:asciiname":"Calella",
    "gn:country_code":"ES",
    "gn:dem":83,
    "gn:feature_class":"P",
    "gn:feature_code":"PPL",
    "gn:name":"Calella",
    "gn:population":0,
    "gn:timezone":"Europe/Madrid",
    "iso:country":"ES",
    "name:ara_x_preferred":[
        "\u0643\u0644\u064a\u0644\u0629"
    ],
    "name:arg_x_preferred":[
        "Calella"
    ],
    "name:azb_x_preferred":[
        "\u06a9\u0627\u0644\u06cc\u0627"
    ],
    "name:cat_x_preferred":[
        "Calella"
    ],
    "name:ceb_x_preferred":[
        "Calella"
    ],
    "name:ces_x_preferred":[
        "Calella"
    ],
    "name:dan_x_preferred":[
        "Calella"
    ],
    "name:deu_x_preferred":[
        "Calella"
    ],
    "name:eus_x_preferred":[
        "Calella"
    ],
    "name:fas_x_preferred":[
        "\u06a9\u0627\u0644\u06cc\u0627"
    ],
    "name:fra_x_preferred":[
        "Calella"
    ],
    "name:glg_x_preferred":[
        "Calella"
    ],
    "name:hun_x_preferred":[
        "Calella"
    ],
    "name:hye_x_preferred":[
        "\u053f\u0561\u056c\u0565\u056c\u0575\u0561"
    ],
    "name:ita_x_preferred":[
        "Calella"
    ],
    "name:kaz_x_preferred":[
        "\u041a\u0430\u043b\u0435\u043b\u044c\u044f"
    ],
    "name:kor_x_preferred":[
        "\uce7c\ub808\uc57c"
    ],
    "name:lat_x_preferred":[
        "Calella"
    ],
    "name:mkd_x_preferred":[
        "\u041a\u0430\u043b\u0435\u043b\u0458\u0430"
    ],
    "name:msa_x_preferred":[
        "Calella"
    ],
    "name:nld_x_preferred":[
        "Calella"
    ],
    "name:nor_x_preferred":[
        "Calella"
    ],
    "name:oci_x_preferred":[
        "Calella"
    ],
    "name:pol_x_preferred":[
        "Calella"
    ],
    "name:por_x_preferred":[
        "Calella"
    ],
    "name:ron_x_preferred":[
        "Calella"
    ],
    "name:rus_x_preferred":[
        "\u041a\u0430\u043b\u0435\u043b\u044c\u044f"
    ],
    "name:spa_x_preferred":[
        "Calella"
    ],
    "name:sqi_x_preferred":[
        "Calella"
    ],
    "name:swe_x_preferred":[
        "Calella"
    ],
    "name:uzb_x_preferred":[
        "Calella"
    ],
    "name:vie_x_preferred":[
        "Calella"
    ],
    "name:war_x_preferred":[
        "Calella"
    ],
    "name:zho_x_preferred":[
        "\u5361\u83b1\u5229\u4e9a"
    ],
    "wof:name":"Calella",
    "wof:placetype":"locality"
},
  "geometry": {"coordinates":[-6.56667,43.55],"type":"Point"}
}