{
  "type": "Feature",
  "properties": {
    "gn:admin1_code":"51",
    "gn:admin2_code":"J",
    "gn:admin3_code":"23064",
    "gn:asciiname":"La Umbria",
    "gn:country_code":"ES",
    "gn:dem":1095,
    "gn:feature_class":"P",
    "gn:feature_code":"PPL",
    "gn:name":"La Umbr\u00eda",
    "gn:population":0,
    "gn:timezone":"Europe/Madrid",
    "iso:country":"ES",
    "name:und_x_variant":[
        "Caser\u00edo La Umbr\u00eda",
        "La Umbr\u00eda"
    ],
    "wof:name":"La Umbria",
    "wof:placetype":"locality"
},
  "geometry": {"coordinates":[-3.55743,37.58258],"type":"Point"}
}