{
  "type": "Feature",
  "properties": {
    "gn:gn_country":"ES",
    "gn:gn_fcode":"PPL",
    "gn:gn_pop":0,
    "iso:country":"ES",
    "name:arm_x_preferred":[
        "\u054e\u056b\u057e\u0561\u0580 \u0564\u0565\u056c \u054d\u056b\u0564"
    ],
    "name:baq_x_preferred":[
        "Vivar"
    ],
    "name:cat_x_preferred":[
        "Vivar del Cid"
    ],
    "name:dut_x_preferred":[
        "Vivar"
    ],
    "name:eng_x_preferred":[
        "Vivar del Cid"
    ],
    "name:glg_x_preferred":[
        "Vivar del Cid"
    ],
    "name:slv_x_preferred":[
        "Vivar del Cid"
    ],
    "name:spa_x_preferred":[
        "Vivar del Cid"
    ],
    "name:tgl_x_preferred":[
        "Vivar del Cid"
    ],
    "qs_pg:aaroncc":"ES",
    "qs_pg:gn_country":"ES",
    "qs_pg:gn_fcode":"PPL",
    "qs_pg:gn_pop":0,
    "qs_pg:name":"Vivar del Cid",
    "qs_pg:name_adm0":"Espa\u00f1a",
    "qs_pg:name_adm1":"Castilla y Le\u00f3n",
    "qs_pg:photos_9k":1,
    "qs_pg:photos_9r":1,
    "qs_pg:photos_all":1,
    "qs_pg:photos_sr":0,
    "qs_pg:pop_sr":0,
    "qs_pg:qs_pg_placetype":"locality",
    "qs_pg:qs_pg_placetype_gp":"Town",
    "qs_pg:woe_adm0":23424950,
    "woe:adm0_id":23424950,
    "woe:name_adm0":"Espa\u00f1a",
    "woe:name_adm1":"Castilla y Le\u00f3n",
    "woe:placetype":"Town",
    "wof:name":"Vivar del Cid",
    "wof:placetype":"locality"
},
  "geometry": {"coordinates":[-3.68008,42.42308],"type":"Point"}
}