{
  "type": "Feature",
  "properties": {
    "gn:admin1_code":"55",
    "gn:admin2_code":"AV",
    "gn:admin3_code":"05075",
    "gn:asciiname":"Fresnedilla",
    "gn:country_code":"ES",
    "gn:dem":619,
    "gn:feature_class":"P",
    "gn:feature_code":"PPLA3",
    "gn:name":"Fresnedilla",
    "gn:population":99,
    "gn:timezone":"Europe/Madrid",
    "iso:country":"ES",
    "name:ara_x_preferred":[
        "\u0641\u0631\u064a\u0633\u0646\u064a\u062f\u064a\u0627"
    ],
    "name:ast_x_preferred":[
        "Fresnedilla"
    ],
    "name:cat_x_preferred":[
        "Fresnedilla"
    ],
    "name:ceb_x_preferred":[
        "Fresnedilla"
    ],
    "name:eus_x_preferred":[
        "Fresnedilla"
    ],
    "name:fas_x_preferred":[
        "\u0641\u0631\u0633\u0646\u062f\u06cc\u06cc\u0627"
    ],
    "name:fra_x_preferred":[
        "Fresnedilla"
    ],
    "name:hun_x_preferred":[
        "Fresnedilla"
    ],
    "name:hye_x_preferred":[
        "\u0556\u0580\u0565\u057d\u0576\u0565\u0564\u056b\u056c\u0575\u0561"
    ],
    "name:ina_x_preferred":[
        "Fresnedilla"
    ],
    "name:ita_x_preferred":[
        "Fresnedilla"
    ],
    "name:kaz_x_preferred":[
        "\u0424\u0440\u0435\u0441\u043d\u0435\u0434\u0438\u043b\u044c\u044f"
    ],
    "name:mkd_x_preferred":[
        "\u0424\u0440\u0435\u0441\u043d\u0435\u0434\u0438\u043b\u0430"
    ],
    "name:msa_x_preferred":[
        "Fresnedilla"
    ],
    "name:nld_x_preferred":[
        "Fresnedilla"
    ],
    "name:oci_x_preferred":[
        "Fresnedilla"
    ],
    "name:pol_x_preferred":[
        "Fresnedilla"
    ],
    "name:por_x_preferred":[
        "Fresnedilla"
    ],
    "name:rus_x_preferred":[
        "\u0424\u0440\u0435\u0441\u043d\u0435\u0434\u0438\u043b\u044c\u044f"
    ],
    "name:spa_x_preferred":[
        "Fresnedilla"
    ],
    "name:swe_x_preferred":[
        "Fresnedilla"
    ],
    "name:ukr_x_preferred":[
        "\u0424\u0440\u0435\u0441\u043d\u0435\u0434\u0456\u043b\u044c\u044f"
    ],
    "name:und_x_variant":[
        "Fresnedillas"
    ],
    "name:uzb_x_preferred":[
        "Fresnedilla"
    ],
    "name:vie_x_preferred":[
        "Fresnedilla"
    ],
    "name:war_x_preferred":[
        "Fresnedilla"
    ],
    "name:zho_x_preferred":[
        "\u592b\u96f7\u65af\u5185\u8fea\u5229\u4e9a"
    ],
    "wof:name":"Fresnedilla",
    "wof:placetype":"locality",
    "wof:population":99
},
  "geometry": {"coordinates":[-4.62201,40.23233],"type":"Point"}
}