{
  "type": "Feature",
  "properties": {
    "gn:admin1_code":"60",
    "gn:admin2_code":"A",
    "gn:admin3_code":"03066",
    "gn:asciiname":"La Jaud",
    "gn:country_code":"ES",
    "gn:dem":327,
    "gn:feature_class":"P",
    "gn:feature_code":"PPL",
    "gn:name":"La Jaud",
    "gn:population":0,
    "gn:timezone":"Europe/Madrid",
    "iso:country":"ES",
    "name:und_x_variant":[
        "Caser\u00edo La Jaud",
        "La Jaud"
    ],
    "wof:name":"La Jaud",
    "wof:placetype":"locality"
},
  "geometry": {"coordinates":[-0.80785,38.4441],"type":"Point"}
}