{
  "type": "Feature",
  "properties": {
    "gn:country":"ES",
    "iso:country":"ES",
    "name:bul_x_preferred":[
        "\u0418\u0437\u0432\u043e\u0440\u044a\u0442"
    ],
    "name:cat_x_preferred":[
        "El manantial"
    ],
    "name:epo_x_preferred":[
        "El manantial"
    ],
    "name:fra_x_preferred":[
        "El manantial"
    ],
    "name:hat_x_preferred":[
        "El Manantial"
    ],
    "name:hun_x_preferred":[
        "Az \u0151sforr\u00e1s"
    ],
    "name:mkd_x_preferred":[
        "\u0418\u0437\u0432\u043e\u0440"
    ],
    "name:por_x_preferred":[
        "El manantial"
    ],
    "name:ron_x_preferred":[
        "Taina din ad\u00e2ncuri"
    ],
    "name:sqi_x_preferred":[
        "El manantial"
    ],
    "name:srp_x_preferred":[
        "\u0418\u0437\u0432\u043e\u0440"
    ],
    "name:tgl_x_preferred":[
        "El Manantial"
    ],
    "qs_pg:aaroncc":"ES",
    "qs_pg:gn_country":"ES",
    "qs_pg:name":"El Manantial",
    "qs_pg:name_adm0":"Espa\u00f1a",
    "qs_pg:name_adm1":"Andaluc\u00eda",
    "qs_pg:photos":14,
    "qs_pg:photos_1k":3,
    "qs_pg:photos_9k":1,
    "qs_pg:photos_9r":1,
    "qs_pg:photos_all":14,
    "qs_pg:photos_sr":1,
    "qs_pg:pop_sr":0,
    "qs_pg:qs_pg_placetype":"locality",
    "qs_pg:qs_pg_placetype_gp":"Town",
    "qs_pg:woe_adm0":23424950,
    "woe:adm0_id":23424950,
    "woe:name_adm0":"Espa\u00f1a",
    "woe:name_adm1":"Andaluc\u00eda",
    "woe:placetype":"Town",
    "wof:name":"El Manantial",
    "wof:placetype":"locality"
},
  "geometry": {"coordinates":[-6.2813555,36.6076555],"type":"Point"}
}