{
  "type": "Feature",
  "properties": {
    "gn:admin1_code":"32",
    "gn:admin3_code":"31020",
    "gn:asciiname":"Arribe",
    "gn:country_code":"ES",
    "gn:dem":221,
    "gn:feature_class":"P",
    "gn:feature_code":"PPL",
    "gn:name":"Arribe",
    "gn:population":0,
    "gn:timezone":"Europe/Madrid",
    "iso:country":"ES",
    "name:eus_x_preferred":[
        "Arribe"
    ],
    "name:spa_x_preferred":[
        "Arriba"
    ],
    "name:und_x_variant":[
        "Arriba"
    ],
    "wof:name":"Arribe",
    "wof:placetype":"locality"
},
  "geometry": {"coordinates":[-1.98509,43.03753],"type":"Point"}
}