{
  "type": "Feature",
  "properties": {
    "gn:country":"ES",
    "gn:fcode":"PPLA3",
    "gn:population":222,
    "iso:country":"ES",
    "name:arg_x_preferred":[
        "Mayalde"
    ],
    "name:ast_x_preferred":[
        "Mayalde"
    ],
    "name:cat_x_preferred":[
        "Mayalde"
    ],
    "name:ceb_x_preferred":[
        "Mayalde"
    ],
    "name:eng_x_preferred":[
        "Mayalde"
    ],
    "name:eus_x_preferred":[
        "Mayalde"
    ],
    "name:fra_x_preferred":[
        "Mayalde"
    ],
    "name:glg_x_preferred":[
        "Mayalde"
    ],
    "name:haw_x_preferred":[
        "Mayalde"
    ],
    "name:hun_x_preferred":[
        "Mayalde"
    ],
    "name:ile_x_preferred":[
        "Mayalde"
    ],
    "name:ina_x_preferred":[
        "Mayalde"
    ],
    "name:ita_x_preferred":[
        "Mayalde"
    ],
    "name:msa_x_preferred":[
        "Mayalde"
    ],
    "name:nan_x_preferred":[
        "Mayalde"
    ],
    "name:nld_x_preferred":[
        "Mayalde"
    ],
    "name:oci_x_preferred":[
        "Mayalde"
    ],
    "name:pol_x_preferred":[
        "Mayalde"
    ],
    "name:por_x_preferred":[
        "Mayalde"
    ],
    "name:rus_x_preferred":[
        "\u041c\u0430\u0439\u044f\u043b\u044c\u0434\u0435"
    ],
    "name:spa_x_preferred":[
        "Mayalde"
    ],
    "name:swe_x_preferred":[
        "Mayalde"
    ],
    "name:ukr_x_preferred":[
        "\u041c\u0430\u044f\u043b\u044c\u0434\u0435"
    ],
    "name:uzb_x_preferred":[
        "Mayalde"
    ],
    "name:vie_x_preferred":[
        "Mayalde"
    ],
    "name:war_x_preferred":[
        "Mayalde"
    ],
    "name:zho_x_preferred":[
        "\u8fc8\u963f\u5c14\u5fb7"
    ],
    "qs_pg:aaroncc":"ES",
    "qs_pg:gn_country":"ES",
    "qs_pg:gn_fcode":"PPLA3",
    "qs_pg:gn_pop":222,
    "qs_pg:name":"Mayalde",
    "qs_pg:name_adm0":"Espa\u00f1a",
    "qs_pg:name_adm1":"Castilla y Le\u00f3n",
    "qs_pg:photos_9r":0,
    "qs_pg:photos_sr":0,
    "qs_pg:pop_sr":2,
    "qs_pg:qs_pg_placetype":"locality",
    "qs_pg:qs_pg_placetype_gp":"Town",
    "qs_pg:woe_adm0":23424950,
    "woe:adm0_id":23424950,
    "woe:name_adm0":"Espa\u00f1a",
    "woe:name_adm1":"Castilla y Le\u00f3n",
    "woe:placetype":"Town",
    "wof:name":"Mayalde",
    "wof:placetype":"locality",
    "wof:population":222
},
  "geometry": {"coordinates":[-5.79767,41.2508],"type":"Point"}
}