{
  "type": "Feature",
  "properties": {
    "gn:admin1_code":"51",
    "gn:admin2_code":"J",
    "gn:admin3_code":"23904",
    "gn:asciiname":"Los Centenares",
    "gn:cc2":"ES",
    "gn:country_code":"ES",
    "gn:dem":1229,
    "gn:feature_class":"P",
    "gn:feature_code":"PPL",
    "gn:name":"Los Centenares",
    "gn:population":0,
    "gn:timezone":"Europe/Madrid",
    "iso:country":"ES",
    "name:und_x_variant":[
        "Caser\u00edo Los Centenares",
        "Los Centenares"
    ],
    "wof:name":"Los Centenares",
    "wof:placetype":"locality"
},
  "geometry": {"coordinates":[-2.73333,38.08333],"type":"Point"}
}