{
  "type": "Feature",
  "properties": {
    "gn:admin1_code":"39",
    "gn:admin2_code":"S",
    "gn:admin3_code":"39094",
    "gn:asciiname":"Rebollar de Ebro",
    "gn:country_code":"ES",
    "gn:dem":718,
    "gn:feature_class":"P",
    "gn:feature_code":"PPL",
    "gn:name":"Rebollar de Ebro",
    "gn:population":0,
    "gn:timezone":"Europe/Madrid",
    "iso:country":"ES",
    "name:und_x_variant":[
        "Rebollar",
        "Rebollar de Ebro"
    ],
    "wof:name":"Rebollar de Ebro",
    "wof:placetype":"locality"
},
  "geometry": {"coordinates":[-3.95436,42.79403],"type":"Point"}
}