{
  "type": "Feature",
  "properties": {
    "gn:admin1_code":"51",
    "gn:admin2_code":"J",
    "gn:admin3_code":"23081",
    "gn:asciiname":"Cabeza Gorda",
    "gn:country_code":"ES",
    "gn:dem":1364,
    "gn:feature_class":"P",
    "gn:feature_code":"PPL",
    "gn:name":"Cabeza Gorda",
    "gn:population":0,
    "gn:timezone":"Europe/Madrid",
    "iso:country":"ES",
    "name:und_x_variant":[
        "Cortijada Cabeza Gorda",
        "Casa de Cabeza Gorda",
        "Cabeza Gorda"
    ],
    "wof:name":"Cabeza Gorda",
    "wof:placetype":"locality"
},
  "geometry": {"coordinates":[-2.6231,38.18156],"type":"Point"}
}