{
  "type": "Feature",
  "properties": {
    "gn:country":"ES",
    "gn:fcode":"ADM3",
    "gn:population":160,
    "iso:country":"ES",
    "name:arg_x_preferred":[
        "Granyanella"
    ],
    "name:ast_x_preferred":[
        "Granyanella"
    ],
    "name:bul_x_preferred":[
        "\u0413\u0440\u0430\u043d\u044f\u043d\u0435\u043b\u0430"
    ],
    "name:cat_x_preferred":[
        "Granyanella"
    ],
    "name:ceb_x_preferred":[
        "Granyanella"
    ],
    "name:che_x_preferred":[
        "\u0413\u0440\u0430\u043d\u044c\u044f\u043d\u0435\u043b\u044c\u044f"
    ],
    "name:diq_x_preferred":[
        "Granyanella"
    ],
    "name:eng_x_preferred":[
        "Granyanella"
    ],
    "name:eus_x_preferred":[
        "Granyanella"
    ],
    "name:fas_x_preferred":[
        "\u06af\u0631\u0627\u0646\u06cc\u0627\u0646\u0644\u0627"
    ],
    "name:fra_x_preferred":[
        "Granyanella"
    ],
    "name:gle_x_preferred":[
        "Granyanella"
    ],
    "name:hun_x_preferred":[
        "Granyanella"
    ],
    "name:hye_x_preferred":[
        "\u0533\u0580\u0561\u0576\u056b\u0561\u0576\u0565\u056c\u0575\u0561"
    ],
    "name:ile_x_preferred":[
        "Granyanella"
    ],
    "name:ita_x_preferred":[
        "Granyanella"
    ],
    "name:lld_x_preferred":[
        "Granyanella"
    ],
    "name:lmo_x_preferred":[
        "Granyanella"
    ],
    "name:msa_x_preferred":[
        "Granyanella"
    ],
    "name:nld_x_preferred":[
        "Granyanella"
    ],
    "name:oci_x_preferred":[
        "Granyanella"
    ],
    "name:pol_x_preferred":[
        "Granyanella"
    ],
    "name:por_x_preferred":[
        "Granyanella"
    ],
    "name:ron_x_preferred":[
        "Granyanella"
    ],
    "name:rus_x_preferred":[
        "\u0413\u0440\u0430\u043d\u044c\u044f\u043d\u0435\u043b\u044c\u044f"
    ],
    "name:spa_x_preferred":[
        "Gra\u00f1anella"
    ],
    "name:sqi_x_preferred":[
        "Granyanella"
    ],
    "name:swe_x_preferred":[
        "Granyanella"
    ],
    "name:tat_x_preferred":[
        "\u0413\u0440\u0430\u043d\u044c\u044f\u043d\u0435\u043b\u044c\u044f"
    ],
    "name:uzb_x_preferred":[
        "Gra\u00f1anella"
    ],
    "name:vec_x_preferred":[
        "Granyanella"
    ],
    "name:vie_x_preferred":[
        "Granyanella"
    ],
    "name:war_x_preferred":[
        "Granyanella"
    ],
    "name:zho_x_preferred":[
        "\u683c\u62c9\u5c3c\u4e9a\u5185\u5229\u4e9a"
    ],
    "qs_pg:aaroncc":"ES",
    "qs_pg:gn_country":"ES",
    "qs_pg:gn_fcode":"ADM3",
    "qs_pg:gn_pop":160,
    "qs_pg:name":"Granyanella",
    "qs_pg:name_adm0":"Espa\u00f1a",
    "qs_pg:name_adm1":"Catalunya",
    "qs_pg:photos":38,
    "qs_pg:photos_1k":8,
    "qs_pg:photos_9k":1,
    "qs_pg:photos_9r":2,
    "qs_pg:photos_all":38,
    "qs_pg:photos_sr":2,
    "qs_pg:pop_sr":1,
    "qs_pg:qs_pg_placetype":"locality",
    "qs_pg:qs_pg_placetype_gp":"Town",
    "qs_pg:woe_adm0":23424950,
    "woe:adm0_id":23424950,
    "woe:name_adm0":"Espa\u00f1a",
    "woe:name_adm1":"Catalunya",
    "woe:placetype":"Town",
    "wof:name":"Granyanella",
    "wof:placetype":"locality",
    "wof:population":143
},
  "geometry": {"coordinates":[1.21482,41.6559],"type":"Point"}
}