{
  "type": "Feature",
  "properties": {
    "gn:admin1_code":"39",
    "gn:admin2_code":"S",
    "gn:admin3_code":"39087",
    "gn:asciiname":"Ramera",
    "gn:country_code":"ES",
    "gn:dem":6,
    "gn:feature_class":"P",
    "gn:feature_code":"PPL",
    "gn:name":"Ramera",
    "gn:population":0,
    "gn:timezone":"Europe/Madrid",
    "iso:country":"ES",
    "wof:name":"Ramera",
    "wof:placetype":"locality"
},
  "geometry": {"coordinates":[-4.03832,43.37776],"type":"Point"}
}