{
  "type": "Feature",
  "properties": {
    "gn:admin1_code":"58",
    "gn:admin2_code":"OR",
    "gn:admin3_code":"32029",
    "gn:asciiname":"Celeiros",
    "gn:country_code":"ES",
    "gn:dem":1005,
    "gn:feature_class":"P",
    "gn:feature_code":"PPL",
    "gn:name":"Celeiros",
    "gn:population":0,
    "gn:timezone":"Europe/Madrid",
    "iso:country":"ES",
    "name:und_x_variant":[
        "San Mart\u00edn",
        "Celeiros"
    ],
    "wof:name":"Celeiros",
    "wof:placetype":"locality"
},
  "geometry": {"coordinates":[-7.37611,42.26288],"type":"Point"}
}