{
  "type": "Feature",
  "properties": {
    "gn:admin1_code":"55",
    "gn:admin2_code":"BU",
    "gn:admin3_code":"09172",
    "gn:asciiname":"Quintanilla-Pedro Abarca",
    "gn:country_code":"ES",
    "gn:dem":944,
    "gn:feature_class":"P",
    "gn:feature_code":"PPL",
    "gn:name":"Quintanilla-Pedro Abarca",
    "gn:population":0,
    "gn:timezone":"Europe/Madrid",
    "iso:country":"ES",
    "wof:name":"Quintanilla-Pedro Abarca",
    "wof:placetype":"locality"
},
  "geometry": {"coordinates":[-3.81346,42.56528],"type":"Point"}
}