{
  "type": "Feature",
  "properties": {
    "gn:admin1_code":"55",
    "gn:admin2_code":"ZA",
    "gn:admin3_code":"49219.0",
    "gn:asciiname":"Villaveza",
    "gn:country_code":"ES",
    "gn:dem":645,
    "gn:feature_class":"P",
    "gn:feature_code":"PPLL",
    "gn:name":"Villaveza",
    "gn:population":0,
    "gn:timezone":"Europe/Madrid",
    "iso:country":"ES",
    "wof:name":"Villaveza",
    "wof:placetype":"locality"
},
  "geometry": {"coordinates":[-5.35727,41.50447],"type":"Point"}
}