{
  "type": "Feature",
  "properties": {
    "gn:admin1_code":"58",
    "gn:admin2_code":"OR",
    "gn:admin3_code":"32040",
    "gn:asciiname":"Ourega",
    "gn:country_code":"ES",
    "gn:dem":452,
    "gn:feature_class":"P",
    "gn:feature_code":"PPL",
    "gn:name":"Ourega",
    "gn:population":0,
    "gn:timezone":"Europe/Madrid",
    "iso:country":"ES",
    "wof:name":"Ourega",
    "wof:placetype":"locality"
},
  "geometry": {"coordinates":[-8.16319,42.36584000000001],"type":"Point"}
}