{
  "type": "Feature",
  "properties": {
    "gn:admin1_code":"59",
    "gn:admin2_code":"VI",
    "gn:admin3_code":"1046.0",
    "gn:asciiname":"Castillo-Sopena",
    "gn:country_code":"ES",
    "gn:dem":628,
    "gn:feature_class":"P",
    "gn:feature_code":"PPL",
    "gn:name":"Castillo-Sope\u00f1a",
    "gn:population":0,
    "gn:timezone":"Europe/Madrid",
    "iso:country":"ES",
    "wof:name":"Castillo-Sopena",
    "wof:placetype":"locality"
},
  "geometry": {"coordinates":[-2.92146,42.78872],"type":"Point"}
}