{
  "type": "Feature",
  "properties": {
    "gn:admin1_code":"54",
    "gn:admin2_code":"CU",
    "gn:admin3_code":"16902",
    "gn:asciiname":"Olmedilla de Arcas",
    "gn:country_code":"ES",
    "gn:dem":939,
    "gn:feature_class":"P",
    "gn:feature_code":"PPL",
    "gn:name":"Olmedilla de Arcas",
    "gn:population":0,
    "gn:timezone":"Europe/Madrid",
    "iso:country":"ES",
    "wof:name":"Olmedilla de Arcas",
    "wof:placetype":"locality"
},
  "geometry": {"coordinates":[-2.15,39.98333],"type":"Point"}
}