{
  "type": "Feature",
  "properties": {
    "gn:admin1_code":"59",
    "gn:admin2_code":"BI",
    "gn:admin3_code":"48085",
    "gn:asciiname":"Bareno",
    "gn:country_code":"ES",
    "gn:dem":13,
    "gn:feature_class":"P",
    "gn:feature_code":"PPL",
    "gn:name":"Bare\u00f1o",
    "gn:population":0,
    "gn:timezone":"Europe/Madrid",
    "iso:country":"ES",
    "wof:name":"Bareno",
    "wof:placetype":"locality"
},
  "geometry": {"coordinates":[-2.99197,43.39027],"type":"Point"}
}