{
  "type": "Feature",
  "properties": {
    "gn:admin1_code":"55",
    "gn:admin2_code":"AV",
    "gn:admin3_code":"05065",
    "gn:asciiname":"Pascualgrande",
    "gn:country_code":"ES",
    "gn:dem":903,
    "gn:feature_class":"P",
    "gn:feature_code":"PPL",
    "gn:name":"Pascualgrande",
    "gn:population":0,
    "gn:timezone":"Europe/Madrid",
    "iso:country":"ES",
    "wof:name":"Pascualgrande",
    "wof:placetype":"locality"
},
  "geometry": {"coordinates":[-4.96398,40.88916],"type":"Point"}
}