{
  "type": "Feature",
  "properties": {
    "gn:admin1_code":"39",
    "gn:admin2_code":"S",
    "gn:asciiname":"Valnera",
    "gn:country_code":"ES",
    "gn:dem":370,
    "gn:feature_class":"P",
    "gn:feature_code":"PPL",
    "gn:name":"Valnera",
    "gn:population":0,
    "gn:timezone":"Europe/Madrid",
    "iso:country":"ES",
    "wof:name":"Valnera",
    "wof:placetype":"locality"
},
  "geometry": {"coordinates":[-3.43457,43.18937],"type":"Point"}
}