{
  "type": "Feature",
  "properties": {
    "gn:admin1_code":"58",
    "gn:admin2_code":"PO",
    "gn:admin3_code":"36019",
    "gn:asciiname":"Estacas",
    "gn:country_code":"ES",
    "gn:dem":425,
    "gn:feature_class":"P",
    "gn:feature_code":"PPL",
    "gn:name":"Estacas",
    "gn:population":0,
    "gn:timezone":"Europe/Madrid",
    "iso:country":"ES",
    "wof:name":"Estacas",
    "wof:placetype":"locality"
},
  "geometry": {"coordinates":[-8.417,42.33973],"type":"Point"}
}