{
  "type": "Feature",
  "properties": {
    "gn:admin1_code":"55",
    "gn:admin2_code":"SA",
    "gn:admin3_code":"37135",
    "gn:asciiname":"La Estacion",
    "gn:cc2":"ES",
    "gn:country_code":"ES",
    "gn:dem":781,
    "gn:feature_class":"P",
    "gn:feature_code":"PPL",
    "gn:name":"La Estaci\u00f3n",
    "gn:population":0,
    "gn:timezone":"Europe/Madrid",
    "iso:country":"ES",
    "name:und_x_variant":[
        "Barrio la Estaci\u00f3n",
        "La Estaci\u00f3n"
    ],
    "wof:name":"La Estacion",
    "wof:placetype":"locality"
},
  "geometry": {"coordinates":[-6.25,40.78333],"type":"Point"}
}