{
  "type": "Feature",
  "properties": {
    "gn:admin1_code":"51",
    "gn:admin2_code":"H",
    "gn:admin3_code":"21076",
    "gn:asciiname":"Madre del Agua",
    "gn:country_code":"ES",
    "gn:dem":153,
    "gn:feature_class":"P",
    "gn:feature_code":"PPL",
    "gn:name":"Madre del Agua",
    "gn:population":0,
    "gn:timezone":"Europe/Madrid",
    "iso:country":"ES",
    "name:und_x_variant":[
        "Casas Madre del Agua",
        "Madre del Agua"
    ],
    "wof:name":"Madre del Agua",
    "wof:placetype":"locality"
},
  "geometry": {"coordinates":[-7.172,37.43145],"type":"Point"}
}