{
  "type": "Feature",
  "properties": {
    "gn:admin1_code":"55",
    "gn:admin2_code":"SO",
    "gn:admin3_code":"42068",
    "gn:asciiname":"Bordeje",
    "gn:country_code":"ES",
    "gn:dem":953,
    "gn:feature_class":"P",
    "gn:feature_code":"PPL",
    "gn:name":"Bordej\u00e9",
    "gn:population":0,
    "gn:timezone":"Europe/Madrid",
    "iso:country":"ES",
    "name:und_x_variant":[
        "Bordej\u00e9"
    ],
    "wof:name":"Bordeje",
    "wof:placetype":"locality"
},
  "geometry": {"coordinates":[-2.50512,41.44912],"type":"Point"}
}