{
  "type": "Feature",
  "properties": {
    "gn:country":"ES",
    "gn:fcode":"PPLA3",
    "gn:population":259,
    "iso:country":"ES",
    "name:arg_x_preferred":[
        "Melgar de Arriba"
    ],
    "name:azb_x_preferred":[
        "\u0645\u0644\u0642\u0627\u0631 \u062f \u0622\u0631\u06cc\u0628\u0627"
    ],
    "name:cat_x_preferred":[
        "Melgar de Arriba"
    ],
    "name:eng_x_preferred":[
        "Melgar de Arriba"
    ],
    "name:eus_x_preferred":[
        "Melgar de Arriba"
    ],
    "name:fas_x_preferred":[
        "\u0645\u0644\u06af\u0627\u0631 \u062f \u0622\u0631\u06cc\u0628\u0627"
    ],
    "name:fra_x_preferred":[
        "Melgar de Arriba"
    ],
    "name:hun_x_preferred":[
        "Melgar de Arriba"
    ],
    "name:hye_x_preferred":[
        "\u0544\u0565\u056c\u0563\u0561\u0580 \u0564\u0565 \u0531\u057c\u056b\u0562\u0561"
    ],
    "name:ina_x_preferred":[
        "Melgar de Arriba"
    ],
    "name:ita_x_preferred":[
        "Melgar de Arriba"
    ],
    "name:msa_x_preferred":[
        "Melgar de Arriba"
    ],
    "name:nan_x_preferred":[
        "Melgar de Arriba"
    ],
    "name:nld_x_preferred":[
        "Melgar de Arriba"
    ],
    "name:oci_x_preferred":[
        "Melgar de Arriba"
    ],
    "name:pol_x_preferred":[
        "Melgar de Arriba"
    ],
    "name:por_x_preferred":[
        "Melgar de Arriba"
    ],
    "name:rus_x_preferred":[
        "\u041c\u0435\u043b\u044c\u0433\u0430\u0440-\u0434\u0435-\u0410\u0440\u0440\u0438\u0431\u0430"
    ],
    "name:spa_x_preferred":[
        "Melgar de Arriba"
    ],
    "name:swe_x_preferred":[
        "Melgar de Arriba"
    ],
    "name:ukr_x_preferred":[
        "\u041c\u0435\u043b\u044c\u0433\u0430\u0440-\u0434\u0435-\u0410\u0440\u0440\u0456\u0431\u0430"
    ],
    "name:vie_x_preferred":[
        "Melgar de Arriba"
    ],
    "name:war_x_preferred":[
        "Melgar de Arriba"
    ],
    "name:zho_x_preferred":[
        "\u6885\u5c14\u52a0\u5c14\u5fb7\u4e9a\u91cc\u74e6"
    ],
    "qs_pg:aaroncc":"ES",
    "qs_pg:gn_country":"ES",
    "qs_pg:gn_fcode":"PPLA3",
    "qs_pg:gn_pop":259,
    "qs_pg:name":"Melgar de Arriba",
    "qs_pg:name_adm0":"Espa\u00f1a",
    "qs_pg:name_adm1":"Castilla y Le\u00f3n",
    "qs_pg:photos":15,
    "qs_pg:photos_1k":3,
    "qs_pg:photos_9k":1,
    "qs_pg:photos_9r":1,
    "qs_pg:photos_all":15,
    "qs_pg:photos_sr":1,
    "qs_pg:pop_sr":2,
    "qs_pg:qs_pg_placetype":"locality",
    "qs_pg:qs_pg_placetype_gp":"Town",
    "qs_pg:woe_adm0":23424950,
    "woe:adm0_id":23424950,
    "woe:name_adm0":"Espa\u00f1a",
    "woe:name_adm1":"Castilla y Le\u00f3n",
    "woe:placetype":"Town",
    "wof:name":"Melgar de Arriba",
    "wof:placetype":"locality",
    "wof:population":259
},
  "geometry": {"coordinates":[-5.09712,42.26806],"type":"Point"}
}