{
  "type": "Feature",
  "properties": {
    "gn:admin1_code":"55",
    "gn:admin2_code":"LE",
    "gn:admin3_code":"24228",
    "gn:asciiname":"San Pelayo",
    "gn:country_code":"ES",
    "gn:dem":811,
    "gn:feature_class":"P",
    "gn:feature_code":"PPL",
    "gn:name":"San Pelayo",
    "gn:population":0,
    "gn:timezone":"Europe/Madrid",
    "iso:country":"ES",
    "wof:name":"San Pelayo",
    "wof:placetype":"locality"
},
  "geometry": {"coordinates":[-5.86946,42.41045],"type":"Point"}
}