{
  "type": "Feature",
  "properties": {
    "gn:admin1_code":"58",
    "gn:admin2_code":"LU",
    "gn:admin3_code":"27031",
    "gn:asciiname":"Tor",
    "gn:cc2":"ES",
    "gn:country_code":"ES",
    "gn:dem":325,
    "gn:feature_class":"P",
    "gn:feature_code":"PPL",
    "gn:name":"Tor",
    "gn:population":0,
    "gn:timezone":"Europe/Madrid",
    "iso:country":"ES",
    "name:aze_x_preferred":[
        "Tor"
    ],
    "name:bel_x_preferred":[
        "\u0422\u043e\u0440"
    ],
    "name:bre_x_preferred":[
        "Tor"
    ],
    "name:bul_x_preferred":[
        "\u0422\u043e\u0440"
    ],
    "name:cat_x_preferred":[
        "Tor"
    ],
    "name:ceb_x_preferred":[
        "Tor"
    ],
    "name:ces_x_preferred":[
        "Tor"
    ],
    "name:deu_x_preferred":[
        "Tor"
    ],
    "name:eus_x_preferred":[
        "Tor"
    ],
    "name:fin_x_preferred":[
        "Tor"
    ],
    "name:fra_x_preferred":[
        "Tor"
    ],
    "name:hun_x_preferred":[
        "Tor"
    ],
    "name:hye_x_preferred":[
        "\u054f\u0578\u0580"
    ],
    "name:kaz_x_preferred":[
        "\u0422\u043e\u0440"
    ],
    "name:kor_x_preferred":[
        "\ud1a0\ub974"
    ],
    "name:kur_x_preferred":[
        "Tor"
    ],
    "name:lav_x_preferred":[
        "Tor"
    ],
    "name:mkd_x_preferred":[
        "\u0422\u043e\u0440"
    ],
    "name:nld_x_preferred":[
        "Tor"
    ],
    "name:nor_x_preferred":[
        "Tor"
    ],
    "name:pol_x_preferred":[
        "Tor"
    ],
    "name:por_x_preferred":[
        "Tor"
    ],
    "name:ron_x_preferred":[
        "Tor"
    ],
    "name:rus_x_preferred":[
        "\u0422\u043e\u0440"
    ],
    "name:sah_x_preferred":[
        "Tor"
    ],
    "name:slk_x_preferred":[
        "Tor"
    ],
    "name:spa_x_preferred":[
        "Tor"
    ],
    "name:srp_x_preferred":[
        "\u0422\u043e\u0440"
    ],
    "name:swe_x_preferred":[
        "Tor"
    ],
    "name:tur_x_preferred":[
        "Tor"
    ],
    "name:ukr_x_preferred":[
        "\u0422\u043e\u0440"
    ],
    "name:und_x_variant":[
        "San Juli\u00e1n"
    ],
    "name:zho_x_preferred":[
        "Tor"
    ],
    "wof:name":"Tor",
    "wof:placetype":"locality"
},
  "geometry": {"coordinates":[-7.56667,42.55],"type":"Point"}
}