{
  "type": "Feature",
  "properties": {
    "gn:admin1_code":"55",
    "gn:admin2_code":"P",
    "gn:admin3_code":"34004",
    "gn:asciiname":"Quintanas de Hormiguera",
    "gn:country_code":"ES",
    "gn:dem":949,
    "gn:feature_class":"P",
    "gn:feature_code":"PPL",
    "gn:name":"Quintanas de Hormiguera",
    "gn:population":0,
    "gn:timezone":"Europe/Madrid",
    "iso:country":"ES",
    "wof:name":"Quintanas de Hormiguera",
    "wof:placetype":"locality"
},
  "geometry": {"coordinates":[-4.15187,42.86205],"type":"Point"}
}