{
  "type": "Feature",
  "properties": {
    "gn:admin1_code":"39",
    "gn:admin2_code":"S",
    "gn:admin3_code":"39078",
    "gn:asciiname":"La Penilla",
    "gn:country_code":"ES",
    "gn:dem":79,
    "gn:feature_class":"P",
    "gn:feature_code":"PPL",
    "gn:name":"La Penilla",
    "gn:population":0,
    "gn:timezone":"Europe/Madrid",
    "iso:country":"ES",
    "name:und_x_variant":[
        "Penilla",
        "La Penilla"
    ],
    "wof:name":"La Penilla",
    "wof:placetype":"locality"
},
  "geometry": {"coordinates":[-3.94653,43.28556],"type":"Point"}
}