{
  "type": "Feature",
  "properties": {
    "gn:admin1_code":"55",
    "gn:admin2_code":"ZA",
    "gn:admin3_code":"49256",
    "gn:asciiname":"Mozar",
    "gn:country_code":"ES",
    "gn:dem":708,
    "gn:feature_class":"P",
    "gn:feature_code":"PPL",
    "gn:name":"M\u00f3zar",
    "gn:population":0,
    "gn:timezone":"Europe/Madrid",
    "iso:country":"ES",
    "wof:name":"Mozar",
    "wof:placetype":"locality"
},
  "geometry": {"coordinates":[-5.77577,41.95325],"type":"Point"}
}