{
  "type": "Feature",
  "properties": {
    "iso:country":"ES",
    "name:eng_x_preferred":[
        "Miraflores"
    ],
    "name:spa_x_preferred":[
        "Miraflores"
    ],
    "wof:name":"Miraflores",
    "wof:placetype":"neighbourhood"
},
  "geometry": {"coordinates":[-4.34961418038142,36.72553480194062],"type":"Point"}
}