{
  "type": "Feature",
  "properties": {
    "gn:admin1_code":"31",
    "gn:admin2_code":"MU",
    "gn:admin3_code":"30016",
    "gn:asciiname":"Los Navarros",
    "gn:country_code":"ES",
    "gn:dem":62,
    "gn:feature_class":"P",
    "gn:feature_code":"PPL",
    "gn:name":"Los Navarros",
    "gn:population":0,
    "gn:timezone":"Europe/Madrid",
    "iso:country":"ES",
    "name:und_x_variant":[
        "Caser\u00edo Los Navarros",
        "Los Navarros"
    ],
    "wof:name":"Los Navarros",
    "wof:placetype":"locality"
},
  "geometry": {"coordinates":[-1.04289,37.68312],"type":"Point"}
}