{
  "type": "Feature",
  "properties": {
    "gn:admin1_code":"39",
    "gn:admin2_code":"S",
    "gn:admin3_code":"39054",
    "gn:asciiname":"Rumoroso",
    "gn:country_code":"ES",
    "gn:dem":22,
    "gn:feature_class":"P",
    "gn:feature_code":"PPL",
    "gn:name":"Rumoroso",
    "gn:population":0,
    "gn:timezone":"Europe/Madrid",
    "iso:country":"ES",
    "wof:name":"Rumoroso",
    "wof:placetype":"locality"
},
  "geometry": {"coordinates":[-3.99745,43.38615],"type":"Point"}
}