{
  "type": "Feature",
  "properties": {
    "gn:gn_country":"ES",
    "gn:gn_fcode":"PPLA3",
    "gn:gn_pop":123,
    "gn:population":123,
    "iso:country":"ES",
    "name:arg_x_preferred":[
        "Desollo"
    ],
    "name:ast_x_preferred":[
        "Desojo"
    ],
    "name:bre_x_preferred":[
        "Desoio"
    ],
    "name:cat_x_preferred":[
        "Desojo"
    ],
    "name:ceb_x_preferred":[
        "Desojo"
    ],
    "name:eng_x_preferred":[
        "Desojo"
    ],
    "name:eus_x_preferred":[
        "Desoio"
    ],
    "name:fra_x_preferred":[
        "Desojo"
    ],
    "name:hun_x_preferred":[
        "Desojo"
    ],
    "name:ita_x_preferred":[
        "Desojo"
    ],
    "name:jpn_x_preferred":[
        "\u30c7\u30bd\u30db"
    ],
    "name:msa_x_preferred":[
        "Desojo"
    ],
    "name:nan_x_preferred":[
        "Desojo"
    ],
    "name:nld_x_preferred":[
        "Desojo"
    ],
    "name:oci_x_preferred":[
        "Desoio"
    ],
    "name:pol_x_preferred":[
        "Desojo"
    ],
    "name:por_x_preferred":[
        "Desojo"
    ],
    "name:rup_x_preferred":[
        "Desojo"
    ],
    "name:rus_x_preferred":[
        "\u0414\u0435\u0441\u043e\u0445\u043e"
    ],
    "name:sco_x_preferred":[
        "Desojo"
    ],
    "name:spa_x_preferred":[
        "Desojo"
    ],
    "name:swe_x_preferred":[
        "Desojo"
    ],
    "name:ukr_x_preferred":[
        "\u0414\u0435\u0441\u043e\u0445\u043e"
    ],
    "name:uzb_x_preferred":[
        "Desojo"
    ],
    "name:vie_x_preferred":[
        "Desojo"
    ],
    "name:war_x_preferred":[
        "Desojo"
    ],
    "name:zho_x_preferred":[
        "\u5fb7\u7d22\u970d"
    ],
    "qs_pg:aaroncc":"ES",
    "qs_pg:gn_country":"ES",
    "qs_pg:gn_fcode":"PPLA3",
    "qs_pg:gn_pop":123,
    "qs_pg:name":"Desojo",
    "qs_pg:name_adm0":"Espa\u00f1a",
    "qs_pg:name_adm1":"Comunidad Foral de Navarra",
    "qs_pg:photos_9r":0,
    "qs_pg:photos_sr":0,
    "qs_pg:pop_sr":1,
    "qs_pg:qs_pg_placetype":"locality",
    "qs_pg:qs_pg_placetype_gp":"Town",
    "qs_pg:woe_adm0":23424950,
    "woe:adm0_id":23424950,
    "woe:name_adm0":"Espa\u00f1a",
    "woe:name_adm1":"Comunidad Foral de Navarra",
    "woe:placetype":"Town",
    "wof:name":"Desojo",
    "wof:placetype":"locality",
    "wof:population":123
},
  "geometry": {"coordinates":[-2.27438,42.5879],"type":"Point"}
}