{
  "type": "Feature",
  "properties": {
    "gn:admin1_code":"55",
    "gn:admin2_code":"LE",
    "gn:admin3_code":"24132",
    "gn:asciiname":"Robledo de Omana",
    "gn:country_code":"ES",
    "gn:dem":1248,
    "gn:feature_class":"P",
    "gn:feature_code":"PPL",
    "gn:name":"Robledo de Oma\u00f1a",
    "gn:population":0,
    "gn:timezone":"Europe/Madrid",
    "iso:country":"ES",
    "name:und_x_variant":[
        "Robledo de Oma\u00f1a"
    ],
    "wof:name":"Robledo de Omana",
    "wof:placetype":"locality"
},
  "geometry": {"coordinates":[-5.99295,42.81149],"type":"Point"}
}