{
  "type": "Feature",
  "properties": {
    "gn:admin1_code":"55",
    "gn:admin2_code":"ZA",
    "gn:admin3_code":"49179",
    "gn:asciiname":"Triufe",
    "gn:country_code":"ES",
    "gn:dem":965,
    "gn:feature_class":"P",
    "gn:feature_code":"PPL",
    "gn:name":"Triuf\u00e9",
    "gn:population":0,
    "gn:timezone":"Europe/Madrid",
    "iso:country":"ES",
    "name:und_x_variant":[
        "Triuf\u00e9"
    ],
    "wof:name":"Triufe",
    "wof:placetype":"locality"
},
  "geometry": {"coordinates":[-6.59377,42.06178],"type":"Point"}
}