{
  "type": "Feature",
  "properties": {
    "gn:admin1_code":"34",
    "gn:admin2_code":"O",
    "gn:admin3_code":"33052",
    "gn:asciiname":"Santullano",
    "gn:cc2":"ES",
    "gn:country_code":"ES",
    "gn:dem":410,
    "gn:feature_class":"P",
    "gn:feature_code":"PPL",
    "gn:name":"Santullano",
    "gn:population":0,
    "gn:timezone":"Europe/Madrid",
    "iso:country":"ES",
    "name:ast_x_preferred":[
        "Santullano"
    ],
    "name:spa_x_preferred":[
        "Santullano"
    ],
    "name:und_x_variant":[
        "Santuallano",
        "Santullano"
    ],
    "wof:name":"Santullano",
    "wof:placetype":"locality"
},
  "geometry": {"coordinates":[-6.03333,43.21667],"type":"Point"}
}