{
  "type": "Feature",
  "properties": {
    "iso:country":"ES",
    "name:cat_x_preferred":[
        "Este"
    ],
    "name:ceb_x_preferred":[
        "Este"
    ],
    "name:deu_x_preferred":[
        "Este"
    ],
    "name:eus_x_preferred":[
        "Este"
    ],
    "name:fin_x_preferred":[
        "Este"
    ],
    "name:fra_x_preferred":[
        "Este"
    ],
    "name:hun_x_preferred":[
        "Este"
    ],
    "name:ita_x_preferred":[
        "Este"
    ],
    "name:lmo_x_preferred":[
        "Este"
    ],
    "name:nld_x_preferred":[
        "Este"
    ],
    "name:pol_x_preferred":[
        "Este"
    ],
    "name:por_x_preferred":[
        "Este"
    ],
    "name:ron_x_preferred":[
        "Este"
    ],
    "name:rus_x_preferred":[
        "\u042d\u0441\u0442\u0435"
    ],
    "name:spa_x_preferred":[
        "Este"
    ],
    "name:swe_x_preferred":[
        "Este"
    ],
    "name:ukr_x_preferred":[
        "\u0415\u0441\u0442\u0435"
    ],
    "wof:name":"Este",
    "wof:placetype":"neighbourhood"
},
  "geometry": {"coordinates":[-5.90779465397894,37.40143231456676],"type":"Point"}
}