{
  "type": "Feature",
  "properties": {
    "iso:country":"ES",
    "wof:name":"Este",
    "wof:placetype":"neighbourhood"
},
  "geometry": {"coordinates":[-5.90779465397894,37.40143231456676],"type":"Point"}
}