{
  "type": "Feature",
  "properties": {
    "gn:admin1_code":"34",
    "gn:admin2_code":"O",
    "gn:admin3_code":"33036",
    "gn:asciiname":"Soberron",
    "gn:country_code":"ES",
    "gn:dem":47,
    "gn:feature_class":"P",
    "gn:feature_code":"PPL",
    "gn:name":"Soberr\u00f3n",
    "gn:population":0,
    "gn:timezone":"Europe/Madrid",
    "iso:country":"ES",
    "name:und_x_variant":[
        "Soberr\u00f3n"
    ],
    "wof:name":"Soberron",
    "wof:placetype":"locality"
},
  "geometry": {"coordinates":[-4.75721,43.39875],"type":"Point"}
}