{
  "type": "Feature",
  "properties": {
    "gn:admin1_code":"52",
    "gn:admin2_code":"HU",
    "gn:admin3_code":"22199",
    "gn:asciiname":"Borres",
    "gn:country_code":"ES",
    "gn:dem":906,
    "gn:feature_class":"P",
    "gn:feature_code":"PPL",
    "gn:name":"Borr\u00e9s",
    "gn:population":0,
    "gn:timezone":"Europe/Madrid",
    "iso:country":"ES",
    "wof:name":"Borres",
    "wof:placetype":"locality"
},
  "geometry": {"coordinates":[-0.40512,42.55928],"type":"Point"}
}