{
  "type": "Feature",
  "properties": {
    "gn:admin1_code":"34",
    "gn:admin2_code":"O",
    "gn:admin3_code":"33069",
    "gn:asciiname":"La Corrada",
    "gn:country_code":"ES",
    "gn:dem":179,
    "gn:feature_class":"P",
    "gn:feature_code":"PPL",
    "gn:name":"La Corrada",
    "gn:population":0,
    "gn:timezone":"Europe/Madrid",
    "iso:country":"ES",
    "name:ast_x_preferred":[
        "La Corrada"
    ],
    "name:deu_x_preferred":[
        "Corrada"
    ],
    "name:spa_x_preferred":[
        "La Corrada"
    ],
    "name:und_x_variant":[
        "Corrada",
        "La Corrada"
    ],
    "wof:name":"La Corrada",
    "wof:placetype":"locality"
},
  "geometry": {"coordinates":[-6.04838,43.52407],"type":"Point"}
}