{
  "type": "Feature",
  "properties": {
    "gn:admin1_code":"54",
    "gn:admin2_code":"AB",
    "gn:admin3_code":"02003",
    "gn:asciiname":"Miralcampo",
    "gn:country_code":"ES",
    "gn:dem":685,
    "gn:feature_class":"P",
    "gn:feature_code":"PPL",
    "gn:name":"Miralcampo",
    "gn:population":0,
    "gn:timezone":"Europe/Madrid",
    "iso:country":"ES",
    "name:und_x_variant":[
        "Caser\u00edo Miralcampo",
        "Miralcampo"
    ],
    "wof:name":"Miralcampo",
    "wof:placetype":"locality"
},
  "geometry": {"coordinates":[-1.78229,39.08753],"type":"Point"}
}