{
  "type": "Feature",
  "properties": {
    "gn:admin1_code":"51",
    "gn:admin2_code":"H",
    "gn:admin3_code":"21072",
    "gn:asciiname":"El Castano",
    "gn:country_code":"ES",
    "gn:dem":203,
    "gn:feature_class":"P",
    "gn:feature_code":"PPL",
    "gn:name":"El Casta\u00f1o",
    "gn:population":0,
    "gn:timezone":"Europe/Madrid",
    "iso:country":"ES",
    "name:und_x_variant":[
        "Caser\u00edo El Casta\u00f1o",
        "El Casta\u00f1o"
    ],
    "wof:name":"El Castano",
    "wof:placetype":"locality"
},
  "geometry": {"coordinates":[-6.7189,37.50986],"type":"Point"}
}