{
  "type": "Feature",
  "properties": {
    "gn:admin1_code":"51",
    "gn:admin2_code":"GR",
    "gn:admin3_code":"18087",
    "gn:asciiname":"Los Carballos",
    "gn:country_code":"ES",
    "gn:dem":699,
    "gn:feature_class":"P",
    "gn:feature_code":"PPL",
    "gn:name":"Los Carballos",
    "gn:population":0,
    "gn:timezone":"Europe/Madrid",
    "iso:country":"ES",
    "name:und_x_variant":[
        "Barrio Los Carballos",
        "Los Carballos"
    ],
    "wof:name":"Los Carballos",
    "wof:placetype":"locality"
},
  "geometry": {"coordinates":[-3.58485,37.1435],"type":"Point"}
}