{
  "type": "Feature",
  "properties": {
    "gn:admin1_code":"55",
    "gn:admin2_code":"SG",
    "gn:admin3_code":"40188",
    "gn:asciiname":"Chavida",
    "gn:country_code":"ES",
    "gn:dem":1149,
    "gn:feature_class":"P",
    "gn:feature_code":"PPL",
    "gn:name":"Chavida",
    "gn:population":0,
    "gn:timezone":"Europe/Madrid",
    "iso:country":"ES",
    "name:und_x_variant":[
        "Charida",
        "Chavida"
    ],
    "wof:name":"Chavida",
    "wof:placetype":"locality"
},
  "geometry": {"coordinates":[-3.88344,41.07862],"type":"Point"}
}