{
  "type": "Feature",
  "properties": {
    "gn:country":"ES",
    "gn:fcode":"PPL",
    "gn:population":0,
    "iso:country":"ES",
    "name:eus_x_preferred":[
        "Goiuri"
    ],
    "name:spa_x_preferred":[
        "G\u00fajuli"
    ],
    "qs_pg:aaroncc":"ES",
    "qs_pg:gn_country":"ES",
    "qs_pg:gn_fcode":"PPL",
    "qs_pg:gn_pop":0,
    "qs_pg:name":"Gujuli",
    "qs_pg:name_adm0":"Espa\u00f1a",
    "qs_pg:name_adm1":"Euskadi",
    "qs_pg:photos":93,
    "qs_pg:photos_1k":19,
    "qs_pg:photos_9k":1,
    "qs_pg:photos_9r":3,
    "qs_pg:photos_all":93,
    "qs_pg:photos_sr":3,
    "qs_pg:pop_sr":0,
    "qs_pg:qs_pg_placetype":"locality",
    "qs_pg:qs_pg_placetype_gp":"Town",
    "qs_pg:woe_adm0":23424950,
    "woe:adm0_id":23424950,
    "woe:name_adm0":"Espa\u00f1a",
    "woe:name_adm1":"Euskadi",
    "woe:placetype":"Town",
    "wof:name":"Gujuli",
    "wof:placetype":"locality"
},
  "geometry": {"coordinates":[-2.91886,42.97752],"type":"Point"}
}