{
  "type": "Feature",
  "properties": {
    "gn:admin1_code":"31",
    "gn:admin2_code":"MU",
    "gn:admin3_code":"30003",
    "gn:asciiname":"Los Arejos",
    "gn:country_code":"ES",
    "gn:dem":305,
    "gn:feature_class":"P",
    "gn:feature_code":"PPL",
    "gn:name":"Los Arejos",
    "gn:population":0,
    "gn:timezone":"Europe/Madrid",
    "iso:country":"ES",
    "name:und_x_variant":[
        "Caser\u00edo Los Arejos",
        "Los Arejos"
    ],
    "wof:name":"Los Arejos",
    "wof:placetype":"locality"
},
  "geometry": {"coordinates":[-1.67352,37.46314],"type":"Point"}
}