{
  "type": "Feature",
  "properties": {
    "gn:admin1_code":"58",
    "gn:admin2_code":"LU",
    "gn:admin3_code":"27012",
    "gn:asciiname":"Lamas",
    "gn:country_code":"ES",
    "gn:dem":738,
    "gn:feature_class":"P",
    "gn:feature_code":"PPL",
    "gn:name":"Lamas",
    "gn:population":0,
    "gn:timezone":"Europe/Madrid",
    "iso:country":"ES",
    "name:und_x_variant":[
        "San Juli\u00e1n",
        "Lamas"
    ],
    "wof:name":"Lamas",
    "wof:placetype":"locality"
},
  "geometry": {"coordinates":[-7.03167,42.83061],"type":"Point"}
}