{
  "type": "Feature",
  "properties": {
    "gn:country":"ES",
    "gn:fcode":"PPLA3",
    "gn:population":171,
    "iso:country":"ES",
    "name:ara_x_preferred":[
        "\u0623\u062a\u064a\u0627\u060c \u0633\u0631\u0642\u0633\u0637\u0629"
    ],
    "name:ara_x_variant":[
        "\u0623\u062a\u064a\u0627"
    ],
    "name:arg_x_preferred":[
        "Atea"
    ],
    "name:arz_x_preferred":[
        "\u0627\u062a\u064a\u0627"
    ],
    "name:cat_x_preferred":[
        "Atea"
    ],
    "name:ceb_x_preferred":[
        "Atea"
    ],
    "name:ces_x_preferred":[
        "Atea"
    ],
    "name:che_x_preferred":[
        "\u0410\u0442\u0435\u0430"
    ],
    "name:deu_x_preferred":[
        "Atea"
    ],
    "name:eng_x_preferred":[
        "Atea"
    ],
    "name:epo_x_preferred":[
        "Atea"
    ],
    "name:eus_x_preferred":[
        "Atea"
    ],
    "name:fas_x_preferred":[
        "\u0622\u062a\u06cc\u0627"
    ],
    "name:fra_x_preferred":[
        "Atea"
    ],
    "name:gle_x_preferred":[
        "Atea"
    ],
    "name:hrv_x_preferred":[
        "Atea"
    ],
    "name:hun_x_preferred":[
        "Atea"
    ],
    "name:ile_x_preferred":[
        "Atea"
    ],
    "name:ina_x_preferred":[
        "Atea"
    ],
    "name:ita_x_preferred":[
        "Atea"
    ],
    "name:kat_x_preferred":[
        "\u10d0\u10e2\u10d4\u10d0"
    ],
    "name:kaz_x_preferred":[
        "\u0410\u0442\u0435\u0430"
    ],
    "name:lld_x_preferred":[
        "Atea"
    ],
    "name:ltz_x_preferred":[
        "Atea"
    ],
    "name:msa_x_preferred":[
        "Atea"
    ],
    "name:nan_x_preferred":[
        "Atea"
    ],
    "name:nld_x_preferred":[
        "Atea"
    ],
    "name:nob_x_preferred":[
        "Atea"
    ],
    "name:oci_x_preferred":[
        "Atea"
    ],
    "name:pol_x_preferred":[
        "Atea"
    ],
    "name:por_x_preferred":[
        "Atea"
    ],
    "name:rus_x_preferred":[
        "\u0410\u0442\u0435\u0430"
    ],
    "name:slk_x_preferred":[
        "Atea"
    ],
    "name:spa_x_preferred":[
        "Atea"
    ],
    "name:swe_x_preferred":[
        "Atea"
    ],
    "name:tat_x_preferred":[
        "\u0410\u0442\u0435\u0430"
    ],
    "name:ukr_x_preferred":[
        "\u0410\u0442\u0435\u0430"
    ],
    "name:uzb_x_preferred":[
        "Atea"
    ],
    "name:vec_x_preferred":[
        "Atea"
    ],
    "name:vie_x_preferred":[
        "Atea"
    ],
    "name:war_x_preferred":[
        "Atea"
    ],
    "name:zho_x_preferred":[
        "\u963f\u7279\u4e9a"
    ],
    "qs_pg:aaroncc":"ES",
    "qs_pg:gn_country":"ES",
    "qs_pg:gn_fcode":"PPLA3",
    "qs_pg:gn_pop":171,
    "qs_pg:name":"Atea",
    "qs_pg:name_adm0":"Espa\u00f1a",
    "qs_pg:name_adm1":"Arag\u00f3n",
    "qs_pg:photos_9r":0,
    "qs_pg:photos_sr":0,
    "qs_pg:pop_sr":1,
    "qs_pg:qs_pg_placetype":"locality",
    "qs_pg:qs_pg_placetype_gp":"Town",
    "qs_pg:woe_adm0":23424950,
    "woe:adm0_id":23424950,
    "woe:name_adm0":"Espa\u00f1a",
    "woe:name_adm1":"Arag\u00f3n",
    "woe:placetype":"Town",
    "wof:name":"Atea",
    "wof:placetype":"locality",
    "wof:population":171
},
  "geometry": {"coordinates":[-1.55533,41.16059],"type":"Point"}
}