{
  "type": "Feature",
  "properties": {
    "gn:gn_country":"ES",
    "gn:gn_fcode":"PPL",
    "gn:gn_pop":86,
    "gn:population":86,
    "iso:country":"ES",
    "name:alb_x_preferred":[
        "Sobremunt"
    ],
    "name:ara_x_preferred":[
        "\u0633\u0648\u0628\u0631\u064a\u0645\u0648\u0646\u062a"
    ],
    "name:arg_x_preferred":[
        "Sobremunt"
    ],
    "name:arm_x_preferred":[
        "\u054d\u0578\u0562\u0580\u0565\u0574\u0578\u0582\u0576\u057f"
    ],
    "name:baq_x_preferred":[
        "Sobremunt"
    ],
    "name:bul_x_preferred":[
        "\u0421\u043e\u0431\u0440\u0435\u043c\u0443\u043d\u0442"
    ],
    "name:cat_x_preferred":[
        "Sobremunt"
    ],
    "name:chi_x_preferred":[
        "\u7d22\u592b\u96f7\u8499\u7279"
    ],
    "name:dut_x_preferred":[
        "Sobremunt"
    ],
    "name:eng_x_preferred":[
        "Sobremunt"
    ],
    "name:fre_x_preferred":[
        "Sobremunt"
    ],
    "name:ger_x_preferred":[
        "Sobremunt"
    ],
    "name:hun_x_preferred":[
        "Sobremunt"
    ],
    "name:ita_x_preferred":[
        "Sobremunt"
    ],
    "name:lat_x_preferred":[
        "Sobremunt"
    ],
    "name:oci_x_preferred":[
        "Sobremunt"
    ],
    "name:per_x_preferred":[
        "\u0633\u0628\u0631\u0645\u0648\u0646\u062a"
    ],
    "name:pol_x_preferred":[
        "Sobremunt"
    ],
    "name:por_x_preferred":[
        "Sobremunt"
    ],
    "name:rus_x_preferred":[
        "\u0421\u043e\u0431\u0440\u0435\u043c\u0443\u043d"
    ],
    "name:spa_x_preferred":[
        "Sobremunt"
    ],
    "name:swe_x_preferred":[
        "Sobremunt"
    ],
    "name:uzb_x_preferred":[
        "Sobremunt"
    ],
    "name:war_x_preferred":[
        "Sobremunt"
    ],
    "qs_pg:aaroncc":"ES",
    "qs_pg:gn_country":"ES",
    "qs_pg:gn_fcode":"PPL",
    "qs_pg:gn_pop":86,
    "qs_pg:name":"Sobremunt",
    "qs_pg:name_adm0":"Espa\u00f1a",
    "qs_pg:name_adm1":"Catalunya",
    "qs_pg:photos_9r":0,
    "qs_pg:photos_sr":0,
    "qs_pg:pop_sr":1,
    "qs_pg:qs_pg_placetype":"locality",
    "qs_pg:qs_pg_placetype_gp":"Town",
    "qs_pg:woe_adm0":23424950,
    "woe:adm0_id":23424950,
    "woe:name_adm0":"Espa\u00f1a",
    "woe:name_adm1":"Catalunya",
    "woe:placetype":"Town",
    "wof:name":"Sobremunt",
    "wof:placetype":"locality",
    "wof:population":86
},
  "geometry": {"coordinates":[2.16502,42.03597],"type":"Point"}
}