{
  "type": "Feature",
  "properties": {
    "gn:admin1_code":"58",
    "gn:admin2_code":"LU",
    "gn:admin3_code":"27028",
    "gn:asciiname":"Muja",
    "gn:cc2":"ES",
    "gn:country_code":"ES",
    "gn:dem":493,
    "gn:feature_class":"P",
    "gn:feature_code":"PPL",
    "gn:name":"Muja",
    "gn:population":0,
    "gn:timezone":"Europe/Madrid",
    "iso:country":"ES",
    "name:ceb_x_preferred":[
        "Muja"
    ],
    "name:swe_x_preferred":[
        "Muja"
    ],
    "name:und_x_variant":[
        "Santa Mar\u00eda",
        "Muja"
    ],
    "wof:name":"Muja",
    "wof:placetype":"locality"
},
  "geometry": {"coordinates":[-7.51667,43.05],"type":"Point"}
}