{
  "type": "Feature",
  "properties": {
    "gn:admin1_code":"55",
    "gn:admin2_code":"LE",
    "gn:admin3_code":"24114",
    "gn:asciiname":"Vega de Gordon",
    "gn:country_code":"ES",
    "gn:dem":1096,
    "gn:feature_class":"P",
    "gn:feature_code":"PPL",
    "gn:name":"Vega de Gord\u00f3n",
    "gn:population":0,
    "gn:timezone":"Europe/Madrid",
    "iso:country":"ES",
    "name:und_x_variant":[
        "Vega de Gord\u00f3n"
    ],
    "wof:name":"Vega de Gordon",
    "wof:placetype":"locality"
},
  "geometry": {"coordinates":[-5.66161,42.87072],"type":"Point"}
}