{
  "type": "Feature",
  "properties": {
    "gn:country":"ES",
    "gn:fcode":"PPL",
    "gn:population":0,
    "iso:country":"ES",
    "name:cat_x_preferred":[
        "El Toro"
    ],
    "name:ceb_x_preferred":[
        "El Toro"
    ],
    "name:deu_x_preferred":[
        "El Toro"
    ],
    "name:eng_x_preferred":[
        "El Toro"
    ],
    "name:nld_x_preferred":[
        "El Toro"
    ],
    "name:pol_x_preferred":[
        "El Toro"
    ],
    "name:spa_x_preferred":[
        "El Toro"
    ],
    "name:swe_x_preferred":[
        "El Toro"
    ],
    "qs_pg:aaroncc":"ES",
    "qs_pg:gn_country":"ES",
    "qs_pg:gn_fcode":"PPL",
    "qs_pg:gn_pop":0,
    "qs_pg:name":"El Toro",
    "qs_pg:name_adm0":"Espa\u00f1a",
    "qs_pg:name_adm1":"Illes Balears",
    "qs_pg:photos":1016,
    "qs_pg:photos_1k":206,
    "qs_pg:photos_9k":5,
    "qs_pg:photos_9r":7,
    "qs_pg:photos_all":1016,
    "qs_pg:photos_sr":11,
    "qs_pg:pop_sr":0,
    "qs_pg:qs_pg_placetype":"locality",
    "qs_pg:qs_pg_placetype_gp":"Town",
    "qs_pg:woe_adm0":23424950,
    "woe:adm0_id":23424950,
    "woe:name_adm0":"Espa\u00f1a",
    "woe:name_adm1":"Illes Balears",
    "woe:placetype":"Town",
    "wof:name":"El Toro",
    "wof:placetype":"locality",
    "wof:population":2321
},
  "geometry": {"coordinates":[2.48222,39.48477],"type":"Point"}
}