{
  "type": "Feature",
  "properties": {
    "gn:admin1_code":"58",
    "gn:admin2_code":"C",
    "gn:admin3_code":"15070",
    "gn:asciiname":"Deveso",
    "gn:cc2":"ES",
    "gn:country_code":"ES",
    "gn:dem":401,
    "gn:feature_class":"P",
    "gn:feature_code":"PPL",
    "gn:name":"Deveso",
    "gn:population":0,
    "gn:timezone":"Europe/Madrid",
    "iso:country":"ES",
    "name:und_x_variant":[
        "Santa Mar\u00eda",
        "Deveso"
    ],
    "wof:name":"Deveso",
    "wof:placetype":"locality"
},
  "geometry": {"coordinates":[-7.85,43.55],"type":"Point"}
}