{
  "type": "Feature",
  "properties": {
    "gn:admin1_code":"59",
    "gn:admin2_code":"VI",
    "gn:admin3_code":"01010",
    "gn:asciiname":"Ozeka",
    "gn:country_code":"ES",
    "gn:dem":426,
    "gn:feature_class":"P",
    "gn:feature_code":"PPL",
    "gn:name":"Ozeka",
    "gn:population":0,
    "gn:timezone":"Europe/Madrid",
    "iso:country":"ES",
    "wof:name":"Ozeka",
    "wof:placetype":"locality"
},
  "geometry": {"coordinates":[-3.08952,43.07162],"type":"Point"}
}