{
  "type": "Feature",
  "properties": {
    "gn:admin1_code":"55",
    "gn:admin2_code":"P",
    "gn:admin3_code":"34055",
    "gn:asciiname":"Quintanilla de la Cueza",
    "gn:country_code":"ES",
    "gn:dem":850,
    "gn:feature_class":"P",
    "gn:feature_code":"PPL",
    "gn:name":"Quintanilla de la Cueza",
    "gn:population":0,
    "gn:timezone":"Europe/Madrid",
    "iso:country":"ES",
    "wof:name":"Quintanilla de la Cueza",
    "wof:placetype":"locality"
},
  "geometry": {"coordinates":[-4.7941,42.29917],"type":"Point"}
}