{
  "type": "Feature",
  "properties": {
    "gn:admin1_code":"58",
    "gn:admin2_code":"LU",
    "gn:admin3_code":"27048",
    "gn:asciiname":"Rio de Campos",
    "gn:country_code":"ES",
    "gn:dem":795,
    "gn:feature_class":"P",
    "gn:feature_code":"PPL",
    "gn:name":"R\u00edo de Campos",
    "gn:population":0,
    "gn:timezone":"Europe/Madrid",
    "iso:country":"ES",
    "wof:name":"Rio de Campos",
    "wof:placetype":"locality"
},
  "geometry": {"coordinates":[-7.13334,43.28218],"type":"Point"}
}