{
  "type": "Feature",
  "properties": {
    "gn:admin1_code":"51",
    "gn:admin2_code":"CA",
    "gn:admin3_code":"11008",
    "gn:asciiname":"Guadarranque",
    "gn:country_code":"ES",
    "gn:dem":7,
    "gn:feature_class":"P",
    "gn:feature_code":"PPL",
    "gn:name":"Guadarranque",
    "gn:population":0,
    "gn:timezone":"Europe/Madrid",
    "iso:country":"ES",
    "name:ceb_x_preferred":[
        "R\u00edo Guadarranque"
    ],
    "name:zho_x_preferred":[
        "\u74dc\u9054\u862d\u514b\u6cb3"
    ],
    "wof:name":"Guadarranque",
    "wof:placetype":"locality"
},
  "geometry": {"coordinates":[-5.42812,36.17577],"type":"Point"}
}