{
  "type": "Feature",
  "properties": {
    "gn:admin1_code":"39",
    "gn:admin2_code":"S",
    "gn:admin3_code":"39083",
    "gn:asciiname":"Incedo",
    "gn:country_code":"ES",
    "gn:dem":315,
    "gn:feature_class":"P",
    "gn:feature_code":"PPL",
    "gn:name":"Incedo",
    "gn:population":0,
    "gn:timezone":"Europe/Madrid",
    "iso:country":"ES",
    "wof:name":"Incedo",
    "wof:placetype":"locality"
},
  "geometry": {"coordinates":[-3.47892,43.21411],"type":"Point"}
}