{
  "type": "Feature",
  "properties": {
    "gn:admin1_code":"55",
    "gn:admin2_code":"LE",
    "gn:admin3_code":"24103",
    "gn:asciiname":"Arnado",
    "gn:country_code":"ES",
    "gn:dem":661,
    "gn:feature_class":"P",
    "gn:feature_code":"PPL",
    "gn:name":"Arnado",
    "gn:population":0,
    "gn:timezone":"Europe/Madrid",
    "iso:country":"ES",
    "wof:name":"Arnado",
    "wof:placetype":"locality"
},
  "geometry": {"coordinates":[-7.01348,42.53658],"type":"Point"}
}