{
  "type": "Feature",
  "properties": {
    "gn:admin1_code":"58",
    "gn:admin2_code":"C",
    "gn:admin3_code":"15017",
    "gn:asciiname":"Andeiro",
    "gn:cc2":"ES",
    "gn:country_code":"ES",
    "gn:dem":89,
    "gn:feature_class":"P",
    "gn:feature_code":"PPL",
    "gn:name":"Andeiro",
    "gn:population":0,
    "gn:timezone":"Europe/Madrid",
    "iso:country":"ES",
    "name:und_x_variant":[
        "San Mart\u00edn",
        "Andeiro"
    ],
    "wof:name":"Andeiro",
    "wof:placetype":"locality"
},
  "geometry": {"coordinates":[-8.33333,43.25],"type":"Point"}
}