{
  "type": "Feature",
  "properties": {
    "gn:admin1_code":"54",
    "gn:admin2_code":"AB",
    "gn:admin3_code":"02037",
    "gn:asciiname":"Agramon",
    "gn:country_code":"ES",
    "gn:dem":408,
    "gn:feature_class":"P",
    "gn:feature_code":"PPL",
    "gn:name":"Agram\u00f3n",
    "gn:population":0,
    "gn:timezone":"Europe/Madrid",
    "iso:country":"ES",
    "name:und_x_variant":[
        "Agram\u00f3n"
    ],
    "wof:name":"Agramon",
    "wof:placetype":"locality"
},
  "geometry": {"coordinates":[-1.63747,38.42188],"type":"Point"}
}