{
  "type": "Feature",
  "properties": {
    "gn:gn_country":"ES",
    "gn:gn_fcode":"PPLA3",
    "gn:gn_pop":101,
    "gn:population":101,
    "iso:country":"ES",
    "name:ara_x_preferred":[
        "\u0646\u0627\u0631\u0628\u0648\u0646\u064a\u062a\u0627"
    ],
    "name:arg_x_preferred":[
        "Narboneta"
    ],
    "name:cat_x_preferred":[
        "Narboneta"
    ],
    "name:eng_x_preferred":[
        "Narboneta"
    ],
    "name:eus_x_preferred":[
        "Narboneta"
    ],
    "name:fra_x_preferred":[
        "Narboneta"
    ],
    "name:glg_x_preferred":[
        "Narboneta"
    ],
    "name:hun_x_preferred":[
        "Narboneta"
    ],
    "name:ita_x_preferred":[
        "Narboneta"
    ],
    "name:kaz_x_preferred":[
        "\u041d\u0430\u0440\u0431\u043e\u043d\u0435\u0442\u0430"
    ],
    "name:msa_x_preferred":[
        "Narboneta"
    ],
    "name:nan_x_preferred":[
        "Narboneta"
    ],
    "name:nld_x_preferred":[
        "Narboneta"
    ],
    "name:oci_x_preferred":[
        "Narboneta"
    ],
    "name:pol_x_preferred":[
        "Narboneta"
    ],
    "name:por_x_preferred":[
        "Narboneta"
    ],
    "name:rus_x_preferred":[
        "\u041d\u0430\u0440\u0431\u043e\u043d\u0435\u0442\u0430"
    ],
    "name:spa_x_preferred":[
        "Narboneta"
    ],
    "name:swe_x_preferred":[
        "Narboneta"
    ],
    "name:ukr_x_preferred":[
        "\u041d\u0430\u0440\u0431\u043e\u043d\u0435\u0442\u0430"
    ],
    "name:vie_x_preferred":[
        "Narboneta"
    ],
    "name:war_x_preferred":[
        "Narboneta"
    ],
    "name:zho_x_preferred":[
        "\u7eb3\u5c14\u6c83\u5185\u5854"
    ],
    "qs_pg:aaroncc":"ES",
    "qs_pg:gn_country":"ES",
    "qs_pg:gn_fcode":"PPLA3",
    "qs_pg:gn_pop":101,
    "qs_pg:name":"Narboneta",
    "qs_pg:name_adm0":"Espa\u00f1a",
    "qs_pg:name_adm1":"Castilla-La Mancha",
    "qs_pg:photos_9r":0,
    "qs_pg:photos_sr":0,
    "qs_pg:pop_sr":1,
    "qs_pg:qs_pg_placetype":"locality",
    "qs_pg:qs_pg_placetype_gp":"Town",
    "qs_pg:woe_adm0":23424950,
    "woe:adm0_id":23424950,
    "woe:name_adm0":"Espa\u00f1a",
    "woe:name_adm1":"Castilla-La Mancha",
    "woe:placetype":"Town",
    "wof:name":"Narboneta",
    "wof:placetype":"locality",
    "wof:population":101
},
  "geometry": {"coordinates":[-1.46667,39.75],"type":"Point"}
}