{
  "type": "Feature",
  "properties": {
    "gn:admin1_code":"58",
    "gn:admin2_code":"C",
    "gn:admin3_code":"15052",
    "gn:asciiname":"Cibran",
    "gn:country_code":"ES",
    "gn:dem":140,
    "gn:feature_class":"P",
    "gn:feature_code":"PPL",
    "gn:name":"Cibr\u00e1n",
    "gn:population":0,
    "gn:timezone":"Europe/Madrid",
    "iso:country":"ES",
    "name:und_x_variant":[
        "Cibri\u00e1n",
        "Cibr\u00e1n"
    ],
    "wof:name":"Cibran",
    "wof:placetype":"locality"
},
  "geometry": {"coordinates":[-9.13263,43.05124],"type":"Point"}
}