{
  "type": "Feature",
  "properties": {
    "gn:gn_country":"ES",
    "gn:gn_fcode":"PPLA3",
    "gn:gn_pop":8,
    "gn:population":8,
    "iso:country":"ES",
    "name:ara_x_preferred":[
        "\u0627\u064a\u0644\u0627\u0646 \u062f\u064a \u0641\u0627\u0643\u0627\u0633"
    ],
    "name:arg_x_preferred":[
        "Ill\u00e1n de Vacas"
    ],
    "name:azb_x_preferred":[
        "\u0627\u06cc\u06cc\u0627\u0646 \u062f \u0628\u0627\u06a9\u0627\u0633"
    ],
    "name:cat_x_preferred":[
        "Ill\u00e1n de Vacas"
    ],
    "name:eng_x_preferred":[
        "Ill\u00e1n de Vacas"
    ],
    "name:epo_x_preferred":[
        "Ill\u00e1n de Vacas"
    ],
    "name:est_x_preferred":[
        "Ill\u00e1n de Vacas"
    ],
    "name:eus_x_preferred":[
        "Ill\u00e1n de Vacas"
    ],
    "name:fas_x_preferred":[
        "\u0627\u06cc\u06cc\u0627\u0646 \u062f \u0628\u0627\u06a9\u0627\u0633"
    ],
    "name:fra_x_preferred":[
        "Ill\u00e1n de Vacas"
    ],
    "name:glg_x_preferred":[
        "Ill\u00e1n de Vacas"
    ],
    "name:hun_x_preferred":[
        "Ill\u00e1n de Vacas"
    ],
    "name:hye_x_preferred":[
        "\u053b\u056c\u0575\u0561\u0576 \u0564\u0565 \u054e\u0561\u056f\u0561\u057d"
    ],
    "name:ina_x_preferred":[
        "Ill\u00e1n de Vacas"
    ],
    "name:ita_x_preferred":[
        "Ill\u00e1n de Vacas"
    ],
    "name:jpn_x_preferred":[
        "\u30a4\u30ea\u30e3\u30f3\u30fb\u30c7\u30fb\u30d0\u30ab\u30b9"
    ],
    "name:kaz_x_preferred":[
        "\u0418\u043b\u044c\u044f\u043d-\u0434\u0435-\u0412\u0430\u043a\u0430\u0441"
    ],
    "name:msa_x_preferred":[
        "Ill\u00e1n de Vacas"
    ],
    "name:nan_x_preferred":[
        "Ill\u00e1n de Vacas"
    ],
    "name:nld_x_preferred":[
        "Ill\u00e1n de Vacas"
    ],
    "name:oci_x_preferred":[
        "Ill\u00e1n de Vacas"
    ],
    "name:pol_x_preferred":[
        "Ill\u00e1n de Vacas"
    ],
    "name:por_x_preferred":[
        "Ill\u00e1n de Vacas"
    ],
    "name:ron_x_preferred":[
        "Ill\u00e1n de Vacas"
    ],
    "name:rus_x_preferred":[
        "\u0418\u043b\u044c\u044f\u043d-\u0434\u0435-\u0412\u0430\u043a\u0430\u0441"
    ],
    "name:spa_x_preferred":[
        "Ill\u00e1n de Vacas"
    ],
    "name:sqi_x_preferred":[
        "Ill\u00e1n de Vacas"
    ],
    "name:swe_x_preferred":[
        "Ill\u00e1n de Vacas"
    ],
    "name:ukr_x_preferred":[
        "\u0406\u043b\u044c\u044f\u043d-\u0434\u0435-\u0412\u0430\u043a\u0430\u0441"
    ],
    "name:vie_x_preferred":[
        "Ill\u00e1n de Vacas"
    ],
    "name:war_x_preferred":[
        "Ill\u00e1n de Vacas"
    ],
    "name:zho_x_preferred":[
        "\u4f0a\u826f\u5fb7\u74e6\u5361\u65af"
    ],
    "qs_pg:aaroncc":"ES",
    "qs_pg:gn_country":"ES",
    "qs_pg:gn_fcode":"PPLA3",
    "qs_pg:gn_pop":8,
    "qs_pg:name":"Ill\u00e1n de Vacas",
    "qs_pg:name_adm0":"Espa\u00f1a",
    "qs_pg:name_adm1":"Castilla-La Mancha",
    "qs_pg:photos_9r":0,
    "qs_pg:photos_sr":0,
    "qs_pg:pop_sr":1,
    "qs_pg:qs_pg_placetype":"locality",
    "qs_pg:qs_pg_placetype_gp":"Town",
    "qs_pg:woe_adm0":23424950,
    "woe:adm0_id":23424950,
    "woe:name_adm0":"Espa\u00f1a",
    "woe:name_adm1":"Castilla-La Mancha",
    "woe:placetype":"Town",
    "wof:name":"Ill\u00e1n de Vacas",
    "wof:placetype":"locality",
    "wof:population":8
},
  "geometry": {"coordinates":[-4.55743,39.97079],"type":"Point"}
}