{
  "type": "Feature",
  "properties": {
    "gn:admin1_code":"34",
    "gn:admin2_code":"O",
    "gn:admin3_code":"33032",
    "gn:asciiname":"Entralgo",
    "gn:country_code":"ES",
    "gn:dem":312,
    "gn:feature_class":"P",
    "gn:feature_code":"PPL",
    "gn:name":"Entralgo",
    "gn:population":0,
    "gn:timezone":"Europe/Madrid",
    "iso:country":"ES",
    "wof:name":"Entralgo",
    "wof:placetype":"locality"
},
  "geometry": {"coordinates":[-5.55567,43.2333],"type":"Point"}
}