{
  "type": "Feature",
  "properties": {
    "gn:country":"ES",
    "gn:fcode":"PPLA3",
    "gn:population":108,
    "iso:country":"ES",
    "name:azb_x_preferred":[
        "\u0633\u0627\u0646 \u0631\u0645\u0627\u0646 \u062f \u0644\u0627 \u06a9\u0648\u0628\u0627"
    ],
    "name:cat_x_preferred":[
        "San Rom\u00e1n de la Cuba"
    ],
    "name:deu_x_preferred":[
        "San Rom\u00e1n de la Cuba"
    ],
    "name:eng_x_preferred":[
        "San Rom\u00e1n de la Cuba"
    ],
    "name:eus_x_preferred":[
        "San Rom\u00e1n de la Cuba"
    ],
    "name:fas_x_preferred":[
        "\u0633\u0627\u0646 \u0631\u0645\u0627\u0646 \u062f \u0644\u0627 \u06a9\u0648\u0628\u0627"
    ],
    "name:fra_x_preferred":[
        "San Rom\u00e1n de la Cuba"
    ],
    "name:glg_x_preferred":[
        "San Rom\u00e1n de la Cuba"
    ],
    "name:hun_x_preferred":[
        "San Rom\u00e1n de la Cuba"
    ],
    "name:hye_x_preferred":[
        "\u054d\u0561\u0576 \u054c\u0578\u0574\u0561\u0576 \u0564\u0565 \u056c\u0561 \u053f\u0578\u0582\u0562\u0561"
    ],
    "name:ina_x_preferred":[
        "San Rom\u00e1n de la Cuba"
    ],
    "name:ita_x_preferred":[
        "San Rom\u00e1n de la Cuba"
    ],
    "name:msa_x_preferred":[
        "San Rom\u00e1n de la Cuba"
    ],
    "name:nan_x_preferred":[
        "San Rom\u00e1n de la Cuba"
    ],
    "name:nld_x_preferred":[
        "San Rom\u00e1n de la Cuba"
    ],
    "name:oci_x_preferred":[
        "San Rom\u00e1n de la Cuba"
    ],
    "name:pol_x_preferred":[
        "San Rom\u00e1n de la Cuba"
    ],
    "name:por_x_preferred":[
        "San Rom\u00e1n de la Cuba"
    ],
    "name:rus_x_preferred":[
        "\u0421\u0430\u043d-\u0420\u043e\u043c\u0430\u043d-\u0434\u0435-\u043b\u0430-\u041a\u0443\u0431\u0430"
    ],
    "name:spa_x_preferred":[
        "San Rom\u00e1n de la Cuba"
    ],
    "name:swe_x_preferred":[
        "San Rom\u00e1n de la Cuba"
    ],
    "name:ukr_x_preferred":[
        "\u0421\u0430\u043d-\u0420\u043e\u043c\u0430\u043d-\u0434\u0435-\u043b\u0430-\u041a\u0443\u0431\u0430"
    ],
    "name:uzb_x_preferred":[
        "San Rom\u00e1n de la Cuba"
    ],
    "name:vie_x_preferred":[
        "San Rom\u00e1n de la Cuba"
    ],
    "name:war_x_preferred":[
        "San Rom\u00e1n de la Cuba"
    ],
    "name:zho_x_preferred":[
        "\u5723\u7f57\u66fc\u5fb7\u62c9\u5e93\u74e6"
    ],
    "qs_pg:aaroncc":"ES",
    "qs_pg:gn_country":"ES",
    "qs_pg:gn_fcode":"PPLA3",
    "qs_pg:gn_pop":108,
    "qs_pg:name":"San Rom\u00e1n de la Cuba",
    "qs_pg:name_adm0":"Espa\u00f1a",
    "qs_pg:name_adm1":"Castilla y Le\u00f3n",
    "qs_pg:photos_9r":0,
    "qs_pg:photos_sr":0,
    "qs_pg:pop_sr":1,
    "qs_pg:qs_pg_placetype":"locality",
    "qs_pg:qs_pg_placetype_gp":"Town",
    "qs_pg:woe_adm0":23424950,
    "woe:adm0_id":23424950,
    "woe:name_adm0":"Espa\u00f1a",
    "woe:name_adm1":"Castilla y Le\u00f3n",
    "woe:placetype":"Town",
    "wof:name":"San Rom\u00e1n de la Cuba",
    "wof:placetype":"locality",
    "wof:population":108
},
  "geometry": {"coordinates":[-4.85724,42.26257],"type":"Point"}
}