{
  "type": "Feature",
  "properties": {
    "gn:admin1_code":"56",
    "gn:admin2_code":"GI",
    "gn:admin3_code":"17099",
    "gn:admin4_code":"17082.0",
    "gn:asciiname":"Girult",
    "gn:country_code":"ES",
    "gn:dem":1569,
    "gn:feature_class":"P",
    "gn:feature_code":"PPL",
    "gn:name":"Girult",
    "gn:population":0,
    "gn:timezone":"Europe/Madrid",
    "iso:country":"ES",
    "wof:name":"Girult",
    "wof:placetype":"locality"
},
  "geometry": {"coordinates":[1.77712,42.44879],"type":"Point"}
}