{
  "type": "Feature",
  "properties": {
    "gn:admin1_code":"34",
    "gn:admin2_code":"O",
    "gn:admin3_code":"33061",
    "gn:asciiname":"Arrunada",
    "gn:country_code":"ES",
    "gn:dem":554,
    "gn:feature_class":"P",
    "gn:feature_code":"PPL",
    "gn:name":"Arru\u00f1ada",
    "gn:population":0,
    "gn:timezone":"Europe/Madrid",
    "iso:country":"ES",
    "wof:name":"Arrunada",
    "wof:placetype":"locality"
},
  "geometry": {"coordinates":[-6.9294,43.32084],"type":"Point"}
}