{
  "type": "Feature",
  "properties": {
    "gn:admin1_code":"51",
    "gn:admin2_code":"CO",
    "gn:admin3_code":"14030",
    "gn:asciiname":"Fuente Palmera",
    "gn:country_code":"ES",
    "gn:dem":162,
    "gn:feature_class":"P",
    "gn:feature_code":"PPLA3",
    "gn:name":"Fuente Palmera",
    "gn:population":10788,
    "gn:timezone":"Europe/Madrid",
    "iso:country":"ES",
    "wof:name":"Fuente Palmera",
    "wof:placetype":"locality",
    "wof:population":10788
},
  "geometry": {"coordinates":[-5.09965,37.70494],"type":"Point"}
}