{
  "type": "Feature",
  "properties": {
    "gn:admin1_code":"34",
    "gn:admin2_code":"O",
    "gn:admin3_code":"33059",
    "gn:asciiname":"Oves",
    "gn:country_code":"ES",
    "gn:dem":635,
    "gn:feature_class":"P",
    "gn:feature_code":"PPL",
    "gn:name":"Ov\u00e9s",
    "gn:population":0,
    "gn:timezone":"Europe/Madrid",
    "iso:country":"ES",
    "name:und_x_variant":[
        "Ov\u00e9s"
    ],
    "wof:name":"Oves",
    "wof:placetype":"locality"
},
  "geometry": {"coordinates":[-6.33638,43.40849],"type":"Point"}
}