{
  "type": "Feature",
  "properties": {
    "gn:admin1_code":"58",
    "gn:admin2_code":"LU",
    "gn:admin3_code":"27012",
    "gn:asciiname":"Quindos",
    "gn:country_code":"ES",
    "gn:dem":844,
    "gn:feature_class":"P",
    "gn:feature_code":"PPL",
    "gn:name":"Quind\u00f3s",
    "gn:population":0,
    "gn:timezone":"Europe/Madrid",
    "iso:country":"ES",
    "wof:name":"Quindos",
    "wof:placetype":"locality"
},
  "geometry": {"coordinates":[-6.99228,42.86656],"type":"Point"}
}