{
  "type": "Feature",
  "properties": {
    "gn:gn_country":"ES",
    "gn:gn_fcode":"PPLA3",
    "gn:gn_pop":183,
    "gn:population":183,
    "iso:country":"ES",
    "name:ara_x_preferred":[
        "\u0628\u0627\u0631\u0627\u0643\u0627\u0633\u060c \u0643\u0627\u0633\u062a\u064a\u0644\u0648\u0646"
    ],
    "name:arg_x_preferred":[
        "Barracas"
    ],
    "name:baq_x_preferred":[
        "Barracas"
    ],
    "name:cat_x_preferred":[
        "Barraques"
    ],
    "name:dut_x_preferred":[
        "Barracas"
    ],
    "name:eng_x_preferred":[
        "Barracas"
    ],
    "name:fre_x_preferred":[
        "Barracas"
    ],
    "name:hun_x_preferred":[
        "Barracas"
    ],
    "name:ita_x_preferred":[
        "Barracas"
    ],
    "name:may_x_preferred":[
        "Barracas"
    ],
    "name:nan_x_preferred":[
        "Barracas"
    ],
    "name:oci_x_preferred":[
        "Barracas"
    ],
    "name:pam_x_preferred":[
        "Barracas"
    ],
    "name:pol_x_preferred":[
        "Barracas"
    ],
    "name:por_x_preferred":[
        "Barracas"
    ],
    "name:rus_x_preferred":[
        "\u0411\u0430\u0440\u0440\u0430\u043a\u0430\u0441"
    ],
    "name:spa_x_preferred":[
        "Barracas"
    ],
    "name:swe_x_preferred":[
        "Barracas"
    ],
    "name:ukr_x_preferred":[
        "\u0411\u0430\u0440\u0440\u0430\u043a\u0430\u0441"
    ],
    "name:uzb_x_preferred":[
        "Barracas"
    ],
    "name:vie_x_preferred":[
        "Barracas"
    ],
    "name:war_x_preferred":[
        "Barracas"
    ],
    "qs_pg:aaroncc":"ES",
    "qs_pg:gn_country":"ES",
    "qs_pg:gn_fcode":"PPLA3",
    "qs_pg:gn_pop":183,
    "qs_pg:name":"Barracas",
    "qs_pg:name_adm0":"Espa\u00f1a",
    "qs_pg:name_adm1":"Comunitat Valenciana",
    "qs_pg:photos":73,
    "qs_pg:photos_1k":15,
    "qs_pg:photos_9k":1,
    "qs_pg:photos_9r":2,
    "qs_pg:photos_all":73,
    "qs_pg:photos_sr":2,
    "qs_pg:pop_sr":1,
    "qs_pg:qs_pg_placetype":"locality",
    "qs_pg:qs_pg_placetype_gp":"Town",
    "qs_pg:woe_adm0":23424950,
    "woe:adm0_id":23424950,
    "woe:name_adm0":"Espa\u00f1a",
    "woe:name_adm1":"Comunitat Valenciana",
    "woe:placetype":"Town",
    "wof:name":"Barracas",
    "wof:placetype":"locality",
    "wof:population":183
},
  "geometry": {"coordinates":[-0.68333,40.01667],"type":"Point"}
}