{
  "type": "Feature",
  "properties": {
    "gn:country":"ES",
    "gn:fcode":"PPLA3",
    "gn:population":30,
    "iso:country":"ES",
    "name:ara_x_preferred":[
        "\u063a\u0627\u0644\u0628\u0627\u0631\u0648\u0633"
    ],
    "name:arg_x_preferred":[
        "Galbarros"
    ],
    "name:ast_x_preferred":[
        "Galbarros"
    ],
    "name:bul_x_preferred":[
        "\u0413\u0430\u043b\u0431\u0430\u0440\u043e\u0441"
    ],
    "name:cat_x_preferred":[
        "Galbarros"
    ],
    "name:ceb_x_preferred":[
        "Galbarros"
    ],
    "name:deu_x_preferred":[
        "Galbarros"
    ],
    "name:eng_x_preferred":[
        "Galbarros"
    ],
    "name:eus_x_preferred":[
        "Galbarros"
    ],
    "name:fas_x_preferred":[
        "\u06af\u0627\u0644\u0628\u0627\u0631\u0633"
    ],
    "name:fra_x_preferred":[
        "Galbarros"
    ],
    "name:glg_x_preferred":[
        "Galbarros"
    ],
    "name:haw_x_preferred":[
        "Galbarros"
    ],
    "name:hun_x_preferred":[
        "Galbarros"
    ],
    "name:ina_x_preferred":[
        "Galbarros"
    ],
    "name:ita_x_preferred":[
        "Galbarros"
    ],
    "name:lad_x_preferred":[
        "Galbarros"
    ],
    "name:msa_x_preferred":[
        "Galbarros"
    ],
    "name:nan_x_preferred":[
        "Galbarros"
    ],
    "name:nld_x_preferred":[
        "Galbarros"
    ],
    "name:oci_x_preferred":[
        "Galbarros"
    ],
    "name:pol_x_preferred":[
        "Galbarros"
    ],
    "name:por_x_preferred":[
        "Galbarros"
    ],
    "name:rus_x_preferred":[
        "\u0413\u0430\u043b\u044c\u0431\u0430\u0440\u0440\u043e\u0441"
    ],
    "name:spa_x_preferred":[
        "Galbarros"
    ],
    "name:swe_x_preferred":[
        "Galbarros"
    ],
    "name:tpi_x_preferred":[
        "Galbarros"
    ],
    "name:ukr_x_preferred":[
        "\u0413\u0430\u043b\u044c\u0431\u0430\u0440\u0440\u043e\u0441"
    ],
    "name:vie_x_preferred":[
        "Galbarros"
    ],
    "name:war_x_preferred":[
        "Galbarros"
    ],
    "name:zho_x_preferred":[
        "\u52a0\u5c14\u74e6\u7f57\u65af"
    ],
    "qs_pg:aaroncc":"ES",
    "qs_pg:gn_country":"ES",
    "qs_pg:gn_fcode":"PPLA3",
    "qs_pg:gn_pop":30,
    "qs_pg:name":"Galbarros",
    "qs_pg:name_adm0":"Espa\u00f1a",
    "qs_pg:name_adm1":"Castilla y Le\u00f3n",
    "qs_pg:photos_9r":0,
    "qs_pg:photos_sr":0,
    "qs_pg:pop_sr":1,
    "qs_pg:qs_pg_placetype":"locality",
    "qs_pg:qs_pg_placetype_gp":"Town",
    "qs_pg:woe_adm0":23424950,
    "woe:adm0_id":23424950,
    "woe:name_adm0":"Espa\u00f1a",
    "woe:name_adm1":"Castilla y Le\u00f3n",
    "woe:placetype":"Town",
    "wof:name":"Galbarros",
    "wof:placetype":"locality",
    "wof:population":30
},
  "geometry": {"coordinates":[-3.43827,42.52729],"type":"Point"}
}