{
  "type": "Feature",
  "properties": {
    "gn:admin1_code":"55",
    "gn:admin2_code":"VA",
    "gn:admin3_code":"47195",
    "gn:asciiname":"Penalba de Duero",
    "gn:country_code":"ES",
    "gn:dem":712,
    "gn:feature_class":"P",
    "gn:feature_code":"PPL",
    "gn:name":"Pe\u00f1alba de Duero",
    "gn:population":0,
    "gn:timezone":"Europe/Madrid",
    "iso:country":"ES",
    "wof:name":"Penalba de Duero",
    "wof:placetype":"locality"
},
  "geometry": {"coordinates":[-4.48831,41.61355],"type":"Point"}
}