{
  "type": "Feature",
  "properties": {
    "gn:country":"ES",
    "gn:fcode":"ADM3",
    "gn:population":24,
    "iso:country":"ES",
    "name:ara_x_preferred":[
        "\u0623\u0646\u063a\u0648\u0646"
    ],
    "name:arg_x_preferred":[
        "Ang\u00f3n"
    ],
    "name:arz_x_preferred":[
        "\u0627\u0646\u062c\u0648\u0646"
    ],
    "name:ast_x_preferred":[
        "Ang\u00f3n"
    ],
    "name:cat_x_preferred":[
        "Ang\u00f3n"
    ],
    "name:ceb_x_preferred":[
        "Ang\u00f3n"
    ],
    "name:che_x_preferred":[
        "\u0410\u043d\u0433\u043e\u043d"
    ],
    "name:deu_x_preferred":[
        "Ang\u00f3n"
    ],
    "name:eng_x_preferred":[
        "Ang\u00f3n"
    ],
    "name:epo_x_preferred":[
        "Ang\u00f3n"
    ],
    "name:eus_x_preferred":[
        "Ang\u00f3n"
    ],
    "name:fra_x_preferred":[
        "Ang\u00f3n"
    ],
    "name:gle_x_preferred":[
        "Ang\u00f3n"
    ],
    "name:hun_x_preferred":[
        "Ang\u00f3n"
    ],
    "name:ile_x_preferred":[
        "Ang\u00f3n"
    ],
    "name:ina_x_preferred":[
        "Ang\u00f3n"
    ],
    "name:ita_x_preferred":[
        "Ang\u00f3n"
    ],
    "name:kaz_x_preferred":[
        "\u0410\u043d\u0433\u043e\u043d"
    ],
    "name:lld_x_preferred":[
        "Ang\u00f3n"
    ],
    "name:ltz_x_preferred":[
        "Ang\u00f3n"
    ],
    "name:msa_x_preferred":[
        "Ang\u00f3n"
    ],
    "name:nan_x_preferred":[
        "Ang\u00f3n"
    ],
    "name:nld_x_preferred":[
        "Ang\u00f3n"
    ],
    "name:nob_x_preferred":[
        "Ang\u00f3n"
    ],
    "name:oci_x_preferred":[
        "Ang\u00f3n"
    ],
    "name:pam_x_preferred":[
        "Ang\u00f3n"
    ],
    "name:pol_x_preferred":[
        "Ang\u00f3n"
    ],
    "name:por_x_preferred":[
        "Ang\u00f3n"
    ],
    "name:rus_x_preferred":[
        "\u0410\u043d\u0433\u043e\u043d"
    ],
    "name:spa_x_preferred":[
        "Ang\u00f3n"
    ],
    "name:swe_x_preferred":[
        "Ang\u00f3n"
    ],
    "name:tat_x_preferred":[
        "\u0410\u043d\u0433\u043e\u043d"
    ],
    "name:ukr_x_preferred":[
        "\u0410\u043d\u0433\u043e\u043d"
    ],
    "name:vec_x_preferred":[
        "Ang\u00f3n"
    ],
    "name:vie_x_preferred":[
        "Ang\u00f3n"
    ],
    "name:war_x_preferred":[
        "Ang\u00f3n"
    ],
    "name:zho_x_preferred":[
        "\u5b89\u8d21"
    ],
    "qs_pg:aaroncc":"ES",
    "qs_pg:gn_country":"ES",
    "qs_pg:gn_fcode":"ADM3",
    "qs_pg:gn_pop":24,
    "qs_pg:name":"Ang\u00f3n",
    "qs_pg:name_adm0":"Espa\u00f1a",
    "qs_pg:name_adm1":"Castilla-La Mancha",
    "qs_pg:photos_9r":0,
    "qs_pg:photos_sr":0,
    "qs_pg:pop_sr":1,
    "qs_pg:qs_pg_placetype":"locality",
    "qs_pg:qs_pg_placetype_gp":"Town",
    "qs_pg:woe_adm0":23424950,
    "woe:adm0_id":23424950,
    "woe:name_adm0":"Espa\u00f1a",
    "woe:name_adm1":"Castilla-La Mancha",
    "woe:placetype":"Town",
    "wof:name":"Ang\u00f3n",
    "wof:placetype":"locality",
    "wof:population":17
},
  "geometry": {"coordinates":[-2.86195,41.07126],"type":"Point"}
}