{
  "type": "Feature",
  "properties": {
    "gn:admin1_code":"58",
    "gn:admin2_code":"C",
    "gn:admin3_code":"15002",
    "gn:asciiname":"Oca",
    "gn:country_code":"ES",
    "gn:dem":228,
    "gn:feature_class":"P",
    "gn:feature_code":"PPL",
    "gn:name":"Oca",
    "gn:population":0,
    "gn:timezone":"Europe/Madrid",
    "iso:country":"ES",
    "wof:name":"Oca",
    "wof:placetype":"locality"
},
  "geometry": {"coordinates":[-8.67643,42.92752],"type":"Point"}
}