{
  "type": "Feature",
  "properties": {
    "gn:admin1_code":"32",
    "gn:admin3_code":"31086.0",
    "gn:asciiname":"Sarriguren",
    "gn:country_code":"ES",
    "gn:dem":460,
    "gn:elevation":"510.0",
    "gn:feature_class":"P",
    "gn:feature_code":"PPLA3",
    "gn:name":"Sarriguren",
    "gn:population":14779,
    "gn:timezone":"Europe/Madrid",
    "iso:country":"ES",
    "wof:name":"Sarriguren",
    "wof:placetype":"locality",
    "wof:population":14779
},
  "geometry": {"coordinates":[-1.59815,42.81292],"type":"Point"}
}