{
  "type": "Feature",
  "properties": {
    "gn:gn_country":"ES",
    "gn:gn_fcode":"PPLA3",
    "gn:gn_pop":222,
    "gn:population":222,
    "iso:country":"ES",
    "name:arg_x_preferred":[
        "Escariche"
    ],
    "name:baq_x_preferred":[
        "Escariche"
    ],
    "name:cat_x_preferred":[
        "Escariche"
    ],
    "name:chi_x_preferred":[
        "\u57c3\u65af\u5361\u91cc\u5207"
    ],
    "name:dut_x_preferred":[
        "Escariche"
    ],
    "name:eng_x_preferred":[
        "Escariche"
    ],
    "name:fre_x_preferred":[
        "Escariche"
    ],
    "name:hun_x_preferred":[
        "Escariche"
    ],
    "name:ina_x_preferred":[
        "Escariche"
    ],
    "name:ita_x_preferred":[
        "Escariche"
    ],
    "name:kaz_x_preferred":[
        "\u042d\u0441\u043a\u0430\u0440\u0438\u0447\u0435"
    ],
    "name:may_x_preferred":[
        "Escariche"
    ],
    "name:nan_x_preferred":[
        "Escariche"
    ],
    "name:oci_x_preferred":[
        "Escariche"
    ],
    "name:pol_x_preferred":[
        "Escariche"
    ],
    "name:por_x_preferred":[
        "Escariche"
    ],
    "name:rus_x_preferred":[
        "\u042d\u0441\u043a\u0430\u0440\u0438\u0447\u0435"
    ],
    "name:spa_x_preferred":[
        "Escariche"
    ],
    "name:swe_x_preferred":[
        "Escariche"
    ],
    "name:ukr_x_preferred":[
        "\u0415\u0441\u043a\u0430\u0440\u0456\u0447\u0435"
    ],
    "name:vie_x_preferred":[
        "Escariche"
    ],
    "name:war_x_preferred":[
        "Escariche"
    ],
    "qs_pg:aaroncc":"ES",
    "qs_pg:gn_country":"ES",
    "qs_pg:gn_fcode":"PPLA3",
    "qs_pg:gn_pop":222,
    "qs_pg:name":"Escariche",
    "qs_pg:name_adm0":"Espa\u00f1a",
    "qs_pg:name_adm1":"Castilla-La Mancha",
    "qs_pg:photos_9k":1,
    "qs_pg:photos_9r":1,
    "qs_pg:photos_all":1,
    "qs_pg:photos_sr":0,
    "qs_pg:pop_sr":2,
    "qs_pg:qs_pg_placetype":"locality",
    "qs_pg:qs_pg_placetype_gp":"Town",
    "qs_pg:woe_adm0":23424950,
    "woe:adm0_id":23424950,
    "woe:name_adm0":"Espa\u00f1a",
    "woe:name_adm1":"Castilla-La Mancha",
    "woe:placetype":"Town",
    "wof:name":"Escariche",
    "wof:placetype":"locality",
    "wof:population":222
},
  "geometry": {"coordinates":[-3.0531,40.40553],"type":"Point"}
}