{
  "type": "Feature",
  "properties": {
    "gn:country":"ES",
    "gn:fcode":"PPLA3",
    "gn:population":117,
    "iso:country":"ES",
    "name:arg_x_preferred":[
        "Alfantega"
    ],
    "name:ast_x_preferred":[
        "Alf\u00e1ntega"
    ],
    "name:cat_x_preferred":[
        "Alf\u00e1ntega"
    ],
    "name:ceb_x_preferred":[
        "Alf\u00e1ntega"
    ],
    "name:deu_x_preferred":[
        "Alf\u00e1ntega"
    ],
    "name:eng_x_preferred":[
        "Alf\u00e1ntega"
    ],
    "name:eus_x_preferred":[
        "Alfantega"
    ],
    "name:fas_x_preferred":[
        "\u0627\u0644\u0641\u0627\u0646\u062a\u06af\u0627"
    ],
    "name:fra_x_preferred":[
        "Alf\u00e1ntega"
    ],
    "name:hak_x_preferred":[
        "Alf\u00e1ntega"
    ],
    "name:hun_x_preferred":[
        "Alf\u00e1ntega"
    ],
    "name:ita_x_preferred":[
        "Alf\u00e1ntega"
    ],
    "name:msa_x_preferred":[
        "Alf\u00e1ntega"
    ],
    "name:nan_x_preferred":[
        "Alf\u00e1ntega"
    ],
    "name:nld_x_preferred":[
        "Alf\u00e1ntega"
    ],
    "name:oci_x_preferred":[
        "Alf\u00e1ntega"
    ],
    "name:pol_x_preferred":[
        "Alf\u00e1ntega"
    ],
    "name:por_x_preferred":[
        "Alf\u00e1ntega"
    ],
    "name:rus_x_preferred":[
        "\u0410\u043b\u044c\u0444\u0430\u043d\u0442\u0435\u0433\u0430"
    ],
    "name:spa_x_preferred":[
        "Alf\u00e1ntega"
    ],
    "name:swe_x_preferred":[
        "Alf\u00e1ntega"
    ],
    "name:ukr_x_preferred":[
        "\u0410\u043b\u044c\u0444\u0430\u043d\u0442\u0435\u0433\u0430"
    ],
    "name:vie_x_preferred":[
        "Alf\u00e1ntega"
    ],
    "name:war_x_preferred":[
        "Alf\u00e1ntega"
    ],
    "name:zho_x_preferred":[
        "\u963f\u5c14\u51e1\u7279\u52a0"
    ],
    "qs_pg:aaroncc":"ES",
    "qs_pg:gn_country":"ES",
    "qs_pg:gn_fcode":"PPLA3",
    "qs_pg:gn_pop":117,
    "qs_pg:name":"Alf\u00e1ntega",
    "qs_pg:name_adm0":"Espa\u00f1a",
    "qs_pg:name_adm1":"Arag\u00f3n",
    "qs_pg:photos_9r":0,
    "qs_pg:photos_sr":0,
    "qs_pg:pop_sr":1,
    "qs_pg:qs_pg_placetype":"locality",
    "qs_pg:qs_pg_placetype_gp":"Town",
    "qs_pg:woe_adm0":23424950,
    "woe:adm0_id":23424950,
    "woe:name_adm0":"Espa\u00f1a",
    "woe:name_adm1":"Arag\u00f3n",
    "woe:placetype":"Town",
    "wof:name":"Alf\u00e1ntega",
    "wof:placetype":"locality",
    "wof:population":117
},
  "geometry": {"coordinates":[0.14823,41.82832],"type":"Point"}
}