{
  "type": "Feature",
  "properties": {
    "gn:admin1_code":"51",
    "gn:admin2_code":"J",
    "gn:admin3_code":"23092",
    "gn:asciiname":"Canavera",
    "gn:country_code":"ES",
    "gn:dem":462,
    "gn:feature_class":"P",
    "gn:feature_code":"PPL",
    "gn:name":"Ca\u00f1avera",
    "gn:population":0,
    "gn:timezone":"Europe/Madrid",
    "iso:country":"ES",
    "name:und_x_variant":[
        "Caser\u00edo Ca\u00f1avera",
        "Casa de la Ca\u00f1avera",
        "Ca\u00f1avera"
    ],
    "wof:name":"Canavera",
    "wof:placetype":"locality"
},
  "geometry": {"coordinates":[-3.37717,38.1072],"type":"Point"}
}