{
  "type": "Feature",
  "properties": {
    "gn:admin1_code":"31",
    "gn:admin2_code":"MU",
    "gn:admin3_code":"30037",
    "gn:asciiname":"Las Carrionas",
    "gn:country_code":"ES",
    "gn:dem":39,
    "gn:feature_class":"P",
    "gn:feature_code":"PPL",
    "gn:name":"Las Carrionas",
    "gn:population":0,
    "gn:timezone":"Europe/Madrid",
    "iso:country":"ES",
    "name:und_x_variant":[
        "Casas Las Carrionas",
        "Caser\u00edo Las Carrionas",
        "Las Carrionas"
    ],
    "wof:name":"Las Carrionas",
    "wof:placetype":"locality"
},
  "geometry": {"coordinates":[-0.94328,37.75917000000001],"type":"Point"}
}