{
  "type": "Feature",
  "properties": {
    "gn:admin1_code":"39",
    "gn:admin2_code":"S",
    "gn:admin3_code":"39044",
    "gn:asciiname":"Gornazo",
    "gn:cc2":"ES",
    "gn:country_code":"ES",
    "gn:dem":39,
    "gn:feature_class":"P",
    "gn:feature_code":"PPL",
    "gn:name":"Gornazo",
    "gn:population":0,
    "gn:timezone":"Europe/Madrid",
    "iso:country":"ES",
    "name:und_x_variant":[
        "Cornazo",
        "Gornazo"
    ],
    "wof:name":"Gornazo",
    "wof:placetype":"locality"
},
  "geometry": {"coordinates":[-3.98332,43.41309],"type":"Point"}
}