{
  "type": "Feature",
  "properties": {
    "gn:admin1_code":"58",
    "gn:admin2_code":"C",
    "gn:admin3_code":"15071",
    "gn:asciiname":"Vilar",
    "gn:country_code":"ES",
    "gn:dem":55,
    "gn:feature_class":"P",
    "gn:feature_code":"PPL",
    "gn:name":"Vilar",
    "gn:population":0,
    "gn:timezone":"Europe/Madrid",
    "iso:country":"ES",
    "name:bre_x_preferred":[
        "Vilar"
    ],
    "name:cat_x_preferred":[
        "Vilar"
    ],
    "name:ceb_x_preferred":[
        "Vilar"
    ],
    "name:deu_x_preferred":[
        "Vilar"
    ],
    "name:fra_x_preferred":[
        "Vilar"
    ],
    "name:glg_x_preferred":[
        "Vilar"
    ],
    "name:ita_x_preferred":[
        "Vilar"
    ],
    "name:jpn_x_preferred":[
        "\u30f4\u30a3\u30e9\u30fc\u30eb"
    ],
    "name:nld_x_preferred":[
        "Vilar"
    ],
    "name:por_x_preferred":[
        "Vilar"
    ],
    "name:rus_x_preferred":[
        "\u0412\u0438\u043b\u0430\u0440"
    ],
    "name:spa_x_preferred":[
        "Vilar"
    ],
    "name:swe_x_preferred":[
        "Vilar"
    ],
    "name:tur_x_preferred":[
        "Vilar"
    ],
    "wof:name":"Vilar",
    "wof:placetype":"locality"
},
  "geometry": {"coordinates":[-9.00913,42.70627],"type":"Point"}
}