{
  "type": "Feature",
  "properties": {
    "gn:admin1_code":"58",
    "gn:admin2_code":"C",
    "gn:admin3_code":"15071",
    "gn:asciiname":"Vilar",
    "gn:country_code":"ES",
    "gn:dem":55,
    "gn:feature_class":"P",
    "gn:feature_code":"PPL",
    "gn:name":"Vilar",
    "gn:population":0,
    "gn:timezone":"Europe/Madrid",
    "iso:country":"ES",
    "wof:name":"Vilar",
    "wof:placetype":"locality"
},
  "geometry": {"coordinates":[-9.00913,42.70627],"type":"Point"}
}