{
  "type": "Feature",
  "properties": {
    "gn:gn_country":"ES",
    "gn:gn_fcode":"PPLA3",
    "gn:gn_pop":835,
    "gn:population":835,
    "iso:country":"ES",
    "name:arg_x_preferred":[
        "Palomeque"
    ],
    "name:arm_x_preferred":[
        "\u054a\u0561\u056c\u0578\u0574\u0565\u056f\u0565"
    ],
    "name:baq_x_preferred":[
        "Palomeque"
    ],
    "name:cat_x_preferred":[
        "Palomeque"
    ],
    "name:chi_x_preferred":[
        "\u5e15\u6d1b\u6885\u514b"
    ],
    "name:dut_x_preferred":[
        "Palomeque"
    ],
    "name:eng_x_preferred":[
        "Palomeque"
    ],
    "name:epo_x_preferred":[
        "Palomeque"
    ],
    "name:fre_x_preferred":[
        "Palomeque"
    ],
    "name:hun_x_preferred":[
        "Palomeque"
    ],
    "name:ina_x_preferred":[
        "Palomeque"
    ],
    "name:ita_x_preferred":[
        "Palomeque"
    ],
    "name:kaz_x_preferred":[
        "\u041f\u0430\u043b\u043e\u043c\u0435\u043a\u0435"
    ],
    "name:may_x_preferred":[
        "Palomeque"
    ],
    "name:nan_x_preferred":[
        "Palomeque"
    ],
    "name:oci_x_preferred":[
        "Palomeque"
    ],
    "name:per_x_preferred":[
        "\u067e\u0627\u0644\u0645\u06a9\u0647"
    ],
    "name:pol_x_preferred":[
        "Palomeque"
    ],
    "name:por_x_preferred":[
        "Palomeque"
    ],
    "name:rum_x_preferred":[
        "Palomeque"
    ],
    "name:rus_x_preferred":[
        "\u041f\u0430\u043b\u043e\u043c\u0435\u043a\u0435"
    ],
    "name:spa_x_preferred":[
        "Palomeque"
    ],
    "name:swe_x_preferred":[
        "Palomeque"
    ],
    "name:ukr_x_preferred":[
        "\u041f\u0430\u043b\u043e\u043c\u0435\u043a\u0435"
    ],
    "name:vie_x_preferred":[
        "Palomeque"
    ],
    "name:war_x_preferred":[
        "Palomeque"
    ],
    "qs_pg:aaroncc":"ES",
    "qs_pg:gn_country":"ES",
    "qs_pg:gn_fcode":"PPLA3",
    "qs_pg:gn_pop":835,
    "qs_pg:name":"Palomeque",
    "qs_pg:name_adm0":"Espa\u00f1a",
    "qs_pg:name_adm1":"Castilla-La Mancha",
    "qs_pg:photos_9r":0,
    "qs_pg:photos_sr":0,
    "qs_pg:pop_sr":2,
    "qs_pg:qs_pg_placetype":"locality",
    "qs_pg:qs_pg_placetype_gp":"Town",
    "qs_pg:woe_adm0":23424950,
    "woe:adm0_id":23424950,
    "woe:name_adm0":"Espa\u00f1a",
    "woe:name_adm1":"Castilla-La Mancha",
    "woe:placetype":"Town",
    "wof:name":"Palomeque",
    "wof:placetype":"locality",
    "wof:population":835
},
  "geometry": {"coordinates":[-3.96403,40.11966],"type":"Point"}
}