{
  "type": "Feature",
  "properties": {
    "gn:country":"ES",
    "gn:fcode":"PPLA3",
    "gn:population":42,
    "iso:country":"ES",
    "name:ara_x_preferred":[
        "\u062a\u0648\u0631\u064a\u0644\u0627\u0628\u0627\u062e\u0627"
    ],
    "name:arg_x_preferred":[
        "Torre la Palla"
    ],
    "name:cat_x_preferred":[
        "Torrelapaja"
    ],
    "name:ceb_x_preferred":[
        "Torrelapaja"
    ],
    "name:eng_x_preferred":[
        "Torrelapaja"
    ],
    "name:eus_x_preferred":[
        "Torrelapaja"
    ],
    "name:fra_x_preferred":[
        "Torrelapaja"
    ],
    "name:hun_x_preferred":[
        "Torrelapaja"
    ],
    "name:ita_x_preferred":[
        "Torrelapaja"
    ],
    "name:kaz_x_preferred":[
        "\u0422\u043e\u0440\u0440\u0435\u043b\u0430\u043f\u0430\u0445\u0430"
    ],
    "name:msa_x_preferred":[
        "Torrelapaja"
    ],
    "name:nan_x_preferred":[
        "Torrelapaja"
    ],
    "name:nld_x_preferred":[
        "Torrelapaja"
    ],
    "name:oci_x_preferred":[
        "Torrelapaja"
    ],
    "name:pol_x_preferred":[
        "Torrelapaja"
    ],
    "name:por_x_preferred":[
        "Torrelapaja"
    ],
    "name:rus_x_preferred":[
        "\u0422\u043e\u0440\u0440\u0435\u043b\u0430\u043f\u0430\u0445\u0430"
    ],
    "name:spa_x_preferred":[
        "Torrelapaja"
    ],
    "name:swe_x_preferred":[
        "Torrelapaja"
    ],
    "name:ukr_x_preferred":[
        "\u0422\u043e\u0440\u0440\u0435\u043b\u0430\u043f\u0430\u0445\u0430"
    ],
    "name:uzb_x_preferred":[
        "Torrelapaja"
    ],
    "name:vie_x_preferred":[
        "Torrelapaja"
    ],
    "name:war_x_preferred":[
        "Torrelapaja"
    ],
    "name:zho_x_preferred":[
        "\u6258\u96f7\u62c9\u5e15\u54c8"
    ],
    "qs_pg:aaroncc":"ES",
    "qs_pg:gn_country":"ES",
    "qs_pg:gn_fcode":"PPLA3",
    "qs_pg:gn_pop":42,
    "qs_pg:name":"Torrelapaja",
    "qs_pg:name_adm0":"Espa\u00f1a",
    "qs_pg:name_adm1":"Arag\u00f3n",
    "qs_pg:photos_9k":1,
    "qs_pg:photos_9r":1,
    "qs_pg:photos_all":1,
    "qs_pg:photos_sr":0,
    "qs_pg:pop_sr":1,
    "qs_pg:qs_pg_placetype":"locality",
    "qs_pg:qs_pg_placetype_gp":"Town",
    "qs_pg:woe_adm0":23424950,
    "woe:adm0_id":23424950,
    "woe:name_adm0":"Espa\u00f1a",
    "woe:name_adm1":"Arag\u00f3n",
    "woe:placetype":"Town",
    "wof:name":"Torrelapaja",
    "wof:placetype":"locality",
    "wof:population":42
},
  "geometry": {"coordinates":[-1.95181,41.58133],"type":"Point"}
}