{
  "type": "Feature",
  "properties": {
    "gn:gn_country":"ES",
    "gn:gn_fcode":"PPLA3",
    "gn:gn_pop":414,
    "gn:population":414,
    "iso:country":"ES",
    "name:arg_x_preferred":[
        "Val Chunquera"
    ],
    "name:baq_x_preferred":[
        "Valjunquera"
    ],
    "name:cat_x_preferred":[
        "Valljunquera"
    ],
    "name:chi_x_preferred":[
        "\u5df4\u5c14\u6d2a\u514b\u62c9"
    ],
    "name:dut_x_preferred":[
        "Valjunquera"
    ],
    "name:eng_x_preferred":[
        "Valjunquera"
    ],
    "name:fre_x_preferred":[
        "Valjunquera"
    ],
    "name:ger_x_preferred":[
        "Valjunquera"
    ],
    "name:hun_x_preferred":[
        "Valjunquera"
    ],
    "name:ita_x_preferred":[
        "Valjunquera"
    ],
    "name:kaz_x_preferred":[
        "\u0412\u0430\u043b\u044c\u0445\u0443\u043d\u043a\u0435\u0440\u0430"
    ],
    "name:may_x_preferred":[
        "Valjunquera"
    ],
    "name:nan_x_preferred":[
        "Valjunquera"
    ],
    "name:oci_x_preferred":[
        "Valljunquera"
    ],
    "name:pol_x_preferred":[
        "Valjunquera"
    ],
    "name:por_x_preferred":[
        "Valjunquera"
    ],
    "name:rus_x_preferred":[
        "\u0412\u0430\u043b\u044c\u0445\u0443\u043d\u043a\u0435\u0440\u0430"
    ],
    "name:spa_x_preferred":[
        "Valjunquera"
    ],
    "name:swe_x_preferred":[
        "Valjunquera"
    ],
    "name:ukr_x_preferred":[
        "\u0412\u0430\u043b\u044c\u0445\u0443\u043d\u043a\u0435\u0440\u0430"
    ],
    "name:unk_x_variant":[
        "Valljunquera"
    ],
    "name:uzb_x_preferred":[
        "Valjunquera"
    ],
    "name:vie_x_preferred":[
        "Valjunquera"
    ],
    "name:war_x_preferred":[
        "Valjunquera"
    ],
    "qs_pg:aaroncc":"ES",
    "qs_pg:gn_country":"ES",
    "qs_pg:gn_fcode":"PPLA3",
    "qs_pg:gn_pop":414,
    "qs_pg:name":"Valjunquera",
    "qs_pg:name_adm0":"Espa\u00f1a",
    "qs_pg:name_adm1":"Arag\u00f3n",
    "qs_pg:photos_9k":1,
    "qs_pg:photos_9r":1,
    "qs_pg:photos_all":2,
    "qs_pg:photos_sr":0,
    "qs_pg:pop_sr":2,
    "qs_pg:qs_pg_placetype":"locality",
    "qs_pg:qs_pg_placetype_gp":"Town",
    "qs_pg:woe_adm0":23424950,
    "woe:adm0_id":23424950,
    "woe:name_adm0":"Espa\u00f1a",
    "woe:name_adm1":"Arag\u00f3n",
    "woe:placetype":"Town",
    "wof:name":"Valjunquera",
    "wof:placetype":"locality",
    "wof:population":414
},
  "geometry": {"coordinates":[0.02575,40.9525],"type":"Point"}
}