{
  "type": "Feature",
  "properties": {
    "gn:admin1_code":"34",
    "gn:admin2_code":"O",
    "gn:admin3_code":"33047",
    "gn:asciiname":"Hontamio",
    "gn:country_code":"ES",
    "gn:dem":125,
    "gn:feature_class":"P",
    "gn:feature_code":"PPL",
    "gn:name":"Hontami\u00f3",
    "gn:population":0,
    "gn:timezone":"Europe/Madrid",
    "iso:country":"ES",
    "name:und_x_variant":[
        "Hontami\u00f3"
    ],
    "wof:name":"Hontamio",
    "wof:placetype":"locality"
},
  "geometry": {"coordinates":[-4.58333,43.31667],"type":"Point"}
}