{
  "type": "Feature",
  "properties": {
    "gn:admin1_code":"55",
    "gn:admin2_code":"LE",
    "gn:admin3_code":"24101",
    "gn:asciiname":"Lazado",
    "gn:country_code":"ES",
    "gn:dem":1283,
    "gn:feature_class":"P",
    "gn:feature_code":"PPL",
    "gn:name":"Lazado",
    "gn:population":0,
    "gn:timezone":"Europe/Madrid",
    "iso:country":"ES",
    "wof:name":"Lazado",
    "wof:placetype":"locality"
},
  "geometry": {"coordinates":[-6.16425,42.8565],"type":"Point"}
}