{
  "type": "Feature",
  "properties": {
    "gn:admin1_code":"53",
    "gn:admin2_code":"TF",
    "gn:admin3_code":"38038",
    "gn:asciiname":"Maria Jimenez",
    "gn:country_code":"ES",
    "gn:dem":151,
    "gn:feature_class":"P",
    "gn:feature_code":"PPL",
    "gn:name":"Mar\u00eda Jim\u00e9nez",
    "gn:population":0,
    "gn:timezone":"Atlantic/Canary",
    "iso:country":"ES",
    "name:und_x_variant":[
        "Mar\u00eda Jim\u00e9nez"
    ],
    "wof:name":"Maria Jimenez",
    "wof:placetype":"locality"
},
  "geometry": {"coordinates":[-16.23167,28.51043],"type":"Point"}
}