{
  "type": "Feature",
  "properties": {
    "gn:admin1_code":"51",
    "gn:admin2_code":"H",
    "gn:admin3_code":"21001",
    "gn:asciiname":"El Cabezuelo",
    "gn:country_code":"ES",
    "gn:dem":545,
    "gn:feature_class":"P",
    "gn:feature_code":"PPL",
    "gn:name":"El Cabezuelo",
    "gn:population":0,
    "gn:timezone":"Europe/Madrid",
    "iso:country":"ES",
    "wof:name":"El Cabezuelo",
    "wof:placetype":"locality"
},
  "geometry": {"coordinates":[-6.68139,37.86854],"type":"Point"}
}