{
  "type": "Feature",
  "properties": {
    "gn:country":"ES",
    "gn:fcode":"PPLA3",
    "gn:population":316,
    "iso:country":"ES",
    "name:ara_x_preferred":[
        "\u0628\u0648\u062e\u064a\u0631\u0627"
    ],
    "name:arg_x_preferred":[
        "Pujerra"
    ],
    "name:ast_x_preferred":[
        "Pujerra"
    ],
    "name:cat_x_preferred":[
        "Pujerra"
    ],
    "name:ceb_x_preferred":[
        "Pujerra"
    ],
    "name:eng_x_preferred":[
        "Pujerra"
    ],
    "name:epo_x_preferred":[
        "Pujerra"
    ],
    "name:eus_x_preferred":[
        "Pujerra"
    ],
    "name:fra_x_preferred":[
        "Pujerra"
    ],
    "name:hat_x_preferred":[
        "Pujerra"
    ],
    "name:hun_x_preferred":[
        "Pujerra"
    ],
    "name:hye_x_preferred":[
        "\u054a\u0578\u0582\u056d\u0565\u057c\u0561"
    ],
    "name:ita_x_preferred":[
        "Pujerra"
    ],
    "name:kaz_x_preferred":[
        "\u041f\u0443\u0445\u0435\u0440\u0440\u0430"
    ],
    "name:kon_x_preferred":[
        "Pujerra"
    ],
    "name:msa_x_preferred":[
        "Pujerra"
    ],
    "name:nan_x_preferred":[
        "Pujerra"
    ],
    "name:nld_x_preferred":[
        "Pujerra"
    ],
    "name:oci_x_preferred":[
        "Pujerra"
    ],
    "name:pol_x_preferred":[
        "Pujerra"
    ],
    "name:por_x_preferred":[
        "Pujerra"
    ],
    "name:rus_x_preferred":[
        "\u041f\u0443\u0445\u0435\u0440\u0440\u0430"
    ],
    "name:spa_x_preferred":[
        "Pujerra"
    ],
    "name:swe_x_preferred":[
        "Pujerra"
    ],
    "name:ukr_x_preferred":[
        "\u041f\u0443\u0445\u0435\u0440\u0440\u0430"
    ],
    "name:uzb_x_preferred":[
        "Pujerra"
    ],
    "name:vie_x_preferred":[
        "Pujerra"
    ],
    "name:war_x_preferred":[
        "Pujerra"
    ],
    "name:zho_x_preferred":[
        "\u666e\u8d6b\u62c9"
    ],
    "qs_pg:aaroncc":"ES",
    "qs_pg:gn_country":"ES",
    "qs_pg:gn_fcode":"PPLA3",
    "qs_pg:gn_pop":316,
    "qs_pg:name":"Pujerra",
    "qs_pg:name_adm0":"Espa\u00f1a",
    "qs_pg:name_adm1":"Andaluc\u00eda",
    "qs_pg:photos_9r":0,
    "qs_pg:photos_sr":0,
    "qs_pg:pop_sr":2,
    "qs_pg:qs_pg_placetype":"locality",
    "qs_pg:qs_pg_placetype_gp":"Town",
    "qs_pg:woe_adm0":23424950,
    "woe:adm0_id":23424950,
    "woe:name_adm0":"Espa\u00f1a",
    "woe:name_adm1":"Andaluc\u00eda",
    "woe:placetype":"Town",
    "wof:name":"Pujerra",
    "wof:placetype":"locality",
    "wof:population":316
},
  "geometry": {"coordinates":[-5.14979,36.61274],"type":"Point"}
}