{
  "type": "Feature",
  "properties": {
    "gn:admin1_code":"34",
    "gn:admin2_code":"O",
    "gn:admin3_code":"33062",
    "gn:asciiname":"Ferreira",
    "gn:country_code":"ES",
    "gn:dem":608,
    "gn:feature_class":"P",
    "gn:feature_code":"PPL",
    "gn:name":"Ferreira",
    "gn:population":0,
    "gn:timezone":"Europe/Madrid",
    "iso:country":"ES",
    "name:cat_x_preferred":[
        "Ferreira"
    ],
    "name:ceb_x_preferred":[
        "Ferreira"
    ],
    "name:ces_x_preferred":[
        "Ferreira"
    ],
    "name:deu_x_preferred":[
        "Ferreira"
    ],
    "name:fin_x_preferred":[
        "Ferreira"
    ],
    "name:fra_x_preferred":[
        "Ferreira"
    ],
    "name:glg_x_preferred":[
        "Ferreira"
    ],
    "name:heb_x_preferred":[
        "\u05e4\u05e8\u05d9\u05d9\u05e8\u05d4"
    ],
    "name:hye_x_preferred":[
        "\u0556\u0565\u057c\u0565\u056b\u0580\u0561"
    ],
    "name:ita_x_preferred":[
        "Ferreira"
    ],
    "name:jpn_x_preferred":[
        "\u30d5\u30a7\u30ec\u30a4\u30e9"
    ],
    "name:lav_x_preferred":[
        "Ferreira"
    ],
    "name:lit_x_preferred":[
        "Ferreira"
    ],
    "name:nld_x_preferred":[
        "Ferreira"
    ],
    "name:pol_x_preferred":[
        "Ferreira"
    ],
    "name:por_x_preferred":[
        "Ferreira"
    ],
    "name:rus_x_preferred":[
        "\u0424\u0435\u0440\u0440\u0435\u0439\u0440\u0430"
    ],
    "name:spa_x_preferred":[
        "Ferreira"
    ],
    "name:swe_x_preferred":[
        "Ferreira"
    ],
    "name:ukr_x_preferred":[
        "\u0424\u0435\u0440\u0440\u0435\u0439\u0440\u0430"
    ],
    "wof:name":"Ferreira",
    "wof:placetype":"locality"
},
  "geometry": {"coordinates":[-6.98333,43.23333],"type":"Point"}
}