{
  "type": "Feature",
  "properties": {
    "gn:gn_country":"ES",
    "gn:gn_fcode":"PPLA3",
    "gn:gn_pop":315,
    "gn:population":315,
    "iso:country":"ES",
    "name:ara_x_preferred":[
        "\u0641\u064a\u0644\u0627\u0646\u063a\u0648\u0645\u064a\u0632"
    ],
    "name:arg_x_preferred":[
        "Villang\u00f3mez"
    ],
    "name:ast_x_preferred":[
        "Villang\u00f3mez"
    ],
    "name:azb_x_preferred":[
        "\u0628\u06cc\u06cc\u0627\u0646\u0642\u0645\u0633"
    ],
    "name:cat_x_preferred":[
        "Villang\u00f3mez"
    ],
    "name:ceb_x_preferred":[
        "Villang\u00f3mez"
    ],
    "name:eng_x_preferred":[
        "Villang\u00f3mez"
    ],
    "name:epo_x_preferred":[
        "Villang\u00f3mez"
    ],
    "name:eus_x_preferred":[
        "Villang\u00f3mez"
    ],
    "name:fas_x_preferred":[
        "\u0628\u06cc\u06cc\u0627\u0646\u06af\u0645\u0633"
    ],
    "name:fra_x_preferred":[
        "Villang\u00f3mez"
    ],
    "name:glg_x_preferred":[
        "Villang\u00f3mez"
    ],
    "name:haw_x_preferred":[
        "Villang\u00f3mez"
    ],
    "name:hun_x_preferred":[
        "Villang\u00f3mez"
    ],
    "name:ina_x_preferred":[
        "Villang\u00f3mez"
    ],
    "name:ita_x_preferred":[
        "Villang\u00f3mez"
    ],
    "name:msa_x_preferred":[
        "Villang\u00f3mez"
    ],
    "name:nan_x_preferred":[
        "Villang\u00f3mez"
    ],
    "name:nld_x_preferred":[
        "Villang\u00f3mez"
    ],
    "name:oci_x_preferred":[
        "Villang\u00f3mez"
    ],
    "name:pol_x_preferred":[
        "Villang\u00f3mez"
    ],
    "name:por_x_preferred":[
        "Villang\u00f3mez"
    ],
    "name:rus_x_preferred":[
        "\u0412\u0438\u043b\u044c\u044f\u043d\u0433\u043e\u043c\u0435\u0441"
    ],
    "name:spa_x_preferred":[
        "Villang\u00f3mez"
    ],
    "name:swe_x_preferred":[
        "Villang\u00f3mez"
    ],
    "name:ukr_x_preferred":[
        "\u0412\u0456\u043b\u044c\u044f\u043d\u0433\u043e\u043c\u0435\u0441"
    ],
    "name:vie_x_preferred":[
        "Villang\u00f3mez"
    ],
    "name:war_x_preferred":[
        "Villang\u00f3mez"
    ],
    "name:zho_x_preferred":[
        "\u6bd4\u826f\u6208\u6885\u65af"
    ],
    "qs_pg:aaroncc":"ES",
    "qs_pg:gn_country":"ES",
    "qs_pg:gn_fcode":"PPLA3",
    "qs_pg:gn_pop":315,
    "qs_pg:name":"Villang\u00f3mez",
    "qs_pg:name_adm0":"Espa\u00f1a",
    "qs_pg:name_adm1":"Castilla y Le\u00f3n",
    "qs_pg:photos_9r":0,
    "qs_pg:photos_sr":0,
    "qs_pg:pop_sr":2,
    "qs_pg:qs_pg_placetype":"locality",
    "qs_pg:qs_pg_placetype_gp":"Town",
    "qs_pg:woe_adm0":23424950,
    "woe:adm0_id":23424950,
    "woe:name_adm0":"Espa\u00f1a",
    "woe:name_adm1":"Castilla y Le\u00f3n",
    "woe:placetype":"Town",
    "wof:name":"Villang\u00f3mez",
    "wof:placetype":"locality",
    "wof:population":315
},
  "geometry": {"coordinates":[-3.77419,42.17961],"type":"Point"}
}