{
  "type": "Feature",
  "properties": {
    "gn:admin1_code":"34",
    "gn:admin2_code":"O",
    "gn:admin3_code":"33072",
    "gn:asciiname":"Santianes",
    "gn:country_code":"ES",
    "gn:dem":516,
    "gn:feature_class":"P",
    "gn:feature_code":"PPL",
    "gn:name":"Santianes",
    "gn:population":0,
    "gn:timezone":"Europe/Madrid",
    "iso:country":"ES",
    "name:ast_x_preferred":[
        "Santianes"
    ],
    "name:spa_x_preferred":[
        "Santianes"
    ],
    "wof:name":"Santianes",
    "wof:placetype":"locality"
},
  "geometry": {"coordinates":[-6.1236,43.17725],"type":"Point"}
}