{
  "type": "Feature",
  "properties": {
    "gn:admin1_code":"27",
    "gn:admin2_code":"LO",
    "gn:admin3_code":"26108",
    "gn:asciiname":"Los Molinos de Ocon",
    "gn:country_code":"ES",
    "gn:dem":644,
    "gn:feature_class":"P",
    "gn:feature_code":"PPL",
    "gn:name":"Los Molinos de Oc\u00f3n",
    "gn:population":0,
    "gn:timezone":"Europe/Madrid",
    "iso:country":"ES",
    "name:und_x_variant":[
        "Los Molinos",
        "Los Molinos de Oc\u00f3n"
    ],
    "wof:name":"Los Molinos de Ocon",
    "wof:placetype":"locality"
},
  "geometry": {"coordinates":[-2.20902,42.31418],"type":"Point"}
}