{
  "type": "Feature",
  "properties": {
    "gn:country":"ES",
    "gn:fcode":"PPLA3",
    "gn:population":82,
    "iso:country":"ES",
    "name:ast_x_preferred":[
        "Triollo"
    ],
    "name:azb_x_preferred":[
        "\u062a\u0631\u06cc\u06cc\u0648"
    ],
    "name:bul_x_preferred":[
        "\u0422\u0440\u0438\u043e\u043b\u043e"
    ],
    "name:cat_x_preferred":[
        "Triollo"
    ],
    "name:ceb_x_preferred":[
        "Triollo"
    ],
    "name:deu_x_preferred":[
        "Triollo"
    ],
    "name:eng_x_preferred":[
        "Triollo"
    ],
    "name:eus_x_preferred":[
        "Triollo"
    ],
    "name:fas_x_preferred":[
        "\u062a\u0631\u06cc\u06cc\u0648"
    ],
    "name:fra_x_preferred":[
        "Triollo"
    ],
    "name:glg_x_preferred":[
        "Triollo"
    ],
    "name:hun_x_preferred":[
        "Triollo"
    ],
    "name:ina_x_preferred":[
        "Triollo"
    ],
    "name:ita_x_preferred":[
        "Triollo"
    ],
    "name:msa_x_preferred":[
        "Triollo"
    ],
    "name:nan_x_preferred":[
        "Triollo"
    ],
    "name:nld_x_preferred":[
        "Triollo"
    ],
    "name:oci_x_preferred":[
        "Triollo"
    ],
    "name:pol_x_preferred":[
        "Triollo"
    ],
    "name:por_x_preferred":[
        "Triollo"
    ],
    "name:rus_x_preferred":[
        "\u0422\u0440\u0438\u043e\u043b\u044c\u043e"
    ],
    "name:spa_x_preferred":[
        "Triollo"
    ],
    "name:swe_x_preferred":[
        "Triollo"
    ],
    "name:ukr_x_preferred":[
        "\u0422\u0440\u0456\u043e\u043b\u044c\u0439\u043e"
    ],
    "name:uzb_x_preferred":[
        "Triollo"
    ],
    "name:vie_x_preferred":[
        "Triollo"
    ],
    "name:war_x_preferred":[
        "Triollo"
    ],
    "name:zho_x_preferred":[
        "\u7279\u91cc\u5965\u7565"
    ],
    "qs_pg:aaroncc":"ES",
    "qs_pg:gn_country":"ES",
    "qs_pg:gn_fcode":"PPLA3",
    "qs_pg:gn_pop":82,
    "qs_pg:name":"Triollo",
    "qs_pg:name_adm0":"Espa\u00f1a",
    "qs_pg:name_adm1":"Castilla y Le\u00f3n",
    "qs_pg:photos":189,
    "qs_pg:photos_1k":38,
    "qs_pg:photos_9k":1,
    "qs_pg:photos_9r":4,
    "qs_pg:photos_all":189,
    "qs_pg:photos_sr":4,
    "qs_pg:pop_sr":1,
    "qs_pg:qs_pg_placetype":"locality",
    "qs_pg:qs_pg_placetype_gp":"Town",
    "qs_pg:woe_adm0":23424950,
    "woe:adm0_id":23424950,
    "woe:name_adm0":"Espa\u00f1a",
    "woe:name_adm1":"Castilla y Le\u00f3n",
    "woe:placetype":"Town",
    "wof:name":"Triollo",
    "wof:placetype":"locality",
    "wof:population":82
},
  "geometry": {"coordinates":[-4.6813,42.92456],"type":"Point"}
}