{
  "type": "Feature",
  "properties": {
    "iso:country":"ES",
    "wof:name":"Distrito Sureste",
    "wof:placetype":"neighbourhood"
},
  "geometry": {"coordinates":[-4.76046025775398,37.88198272552576],"type":"Point"}
}