{
  "type": "Feature",
  "properties": {
    "gn:country":"ES",
    "gn:fcode":"PPLA3",
    "gn:population":836,
    "iso:country":"ES",
    "name:ara_x_preferred":[
        "\u0633\u0627\u0646\u062a\u0627 \u0645\u0627\u062c\u062f\u0627\u0644\u064a\u0646\u0627 \u062f\u064a \u0628\u0648\u0644\u0628\u064a\u0633"
    ],
    "name:arg_x_preferred":[
        "Santa Malena de Polpiz"
    ],
    "name:cat_x_preferred":[
        "Santa Magdalena de Polp\u00eds"
    ],
    "name:deu_x_preferred":[
        "Santa Magdalena de Pulpis"
    ],
    "name:eng_x_preferred":[
        "Santa Magdalena de Polp\u00eds"
    ],
    "name:eus_x_preferred":[
        "Santa Magdalena de Polp\u00eds"
    ],
    "name:fra_x_preferred":[
        "Santa Magdalena de Pulpis"
    ],
    "name:hun_x_preferred":[
        "Santa Magdalena de Pulpis"
    ],
    "name:ita_x_preferred":[
        "Santa Magdalena de Pulpis"
    ],
    "name:msa_x_preferred":[
        "Santa Magdalena de Polp\u00eds"
    ],
    "name:nan_x_preferred":[
        "Santa Magdalena de Polp\u00eds"
    ],
    "name:nld_x_preferred":[
        "Santa Magdalena de Polp\u00eds"
    ],
    "name:oci_x_preferred":[
        "Santa Magdalena de Pulpis"
    ],
    "name:pol_x_preferred":[
        "Santa Magdalena de Pulpis"
    ],
    "name:por_x_preferred":[
        "Santa Magdalena de Pulpis"
    ],
    "name:rus_x_preferred":[
        "\u0421\u0430\u043d\u0442\u0430-\u041c\u0430\u0433\u0434\u0430\u043b\u0435\u043d\u0430-\u0434\u0435-\u041f\u0443\u043b\u044c\u043f\u0438\u0441"
    ],
    "name:spa_x_preferred":[
        "Santa Magdalena de Pulpis"
    ],
    "name:sqi_x_preferred":[
        "Santa Magdalena de Polp\u00eds"
    ],
    "name:swe_x_preferred":[
        "Santa Magdalena de Pulpis"
    ],
    "name:ukr_x_preferred":[
        "\u0421\u0430\u043d\u0442\u0430-\u041c\u0430\u0433\u0434\u0430\u043b\u0435\u043d\u0430-\u0434\u0435-\u041f\u0443\u043b\u044c\u043f\u0456\u0441"
    ],
    "name:uzb_x_preferred":[
        "Santa Magdalena de Pulpis"
    ],
    "name:vie_x_preferred":[
        "Santa Magdalena de Pulpis"
    ],
    "name:war_x_preferred":[
        "Santa Magdalena de Pulpis"
    ],
    "name:zho_x_preferred":[
        "\u5723\u9a6c\u683c\u8fbe\u83b1\u7eb3\u5fb7\u666e\u5c14\u76ae\u65af"
    ],
    "qs_pg:aaroncc":"ES",
    "qs_pg:gn_country":"ES",
    "qs_pg:gn_fcode":"PPLA3",
    "qs_pg:gn_pop":836,
    "qs_pg:name":"Santa Magdalena de Pulpis",
    "qs_pg:name_adm0":"Espa\u00f1a",
    "qs_pg:name_adm1":"Comunitat Valenciana",
    "qs_pg:photos":84,
    "qs_pg:photos_1k":17,
    "qs_pg:photos_9k":1,
    "qs_pg:photos_9r":3,
    "qs_pg:photos_all":84,
    "qs_pg:photos_sr":3,
    "qs_pg:pop_sr":2,
    "qs_pg:qs_pg_placetype":"locality",
    "qs_pg:qs_pg_placetype_gp":"Town",
    "qs_pg:woe_adm0":23424950,
    "woe:adm0_id":23424950,
    "woe:name_adm0":"Espa\u00f1a",
    "woe:name_adm1":"Comunitat Valenciana",
    "woe:placetype":"Town",
    "wof:name":"Santa Magdalena de Pulpis",
    "wof:placetype":"locality",
    "wof:population":836
},
  "geometry": {"coordinates":[0.30258,40.35625],"type":"Point"}
}