{
  "type": "Feature",
  "properties": {
    "gn:admin1_code":"51",
    "gn:admin2_code":"AL",
    "gn:admin3_code":"04050",
    "gn:asciiname":"Aulago",
    "gn:country_code":"ES",
    "gn:dem":1000,
    "gn:feature_class":"P",
    "gn:feature_code":"PPL",
    "gn:name":"Aulago",
    "gn:population":0,
    "gn:timezone":"Europe/Madrid",
    "iso:country":"ES",
    "wof:name":"Aulago",
    "wof:placetype":"locality"
},
  "geometry": {"coordinates":[-2.62588,37.1605],"type":"Point"}
}