{
  "type": "Feature",
  "properties": {
    "gn:admin1_code":"51",
    "gn:admin2_code":"GR",
    "gn:admin3_code":"18023",
    "gn:asciiname":"Cortijo Nuevo",
    "gn:country_code":"ES",
    "gn:dem":1374,
    "gn:feature_class":"P",
    "gn:feature_code":"PPL",
    "gn:name":"Cortijo Nuevo",
    "gn:population":0,
    "gn:timezone":"Europe/Madrid",
    "iso:country":"ES",
    "name:und_x_variant":[
        "Caser\u00edo Cortijo Nuevo",
        "Cortijo Nuevo"
    ],
    "wof:name":"Cortijo Nuevo",
    "wof:placetype":"locality"
},
  "geometry": {"coordinates":[-2.78794,37.34756],"type":"Point"}
}