{
  "type": "Feature",
  "properties": {
    "gn:gn_country":"ES",
    "gn:gn_fcode":"PPL",
    "gn:gn_pop":0,
    "iso:country":"ES",
    "name:arg_x_preferred":[
        "Fontibre"
    ],
    "name:cat_x_preferred":[
        "Fontibre"
    ],
    "name:eng_x_preferred":[
        "Fontibre"
    ],
    "name:epo_x_preferred":[
        "Fontibre"
    ],
    "name:eus_x_preferred":[
        "Fontibre"
    ],
    "name:glg_x_preferred":[
        "Fontibre"
    ],
    "name:jpn_x_preferred":[
        "\u30d5\u30a9\u30f3\u30c6\u30a3\u30d6\u30ec"
    ],
    "name:nld_x_preferred":[
        "Fontibre"
    ],
    "name:spa_x_preferred":[
        "Fontibre"
    ],
    "qs_pg:aaroncc":"ES",
    "qs_pg:gn_country":"ES",
    "qs_pg:gn_fcode":"PPL",
    "qs_pg:gn_pop":0,
    "qs_pg:name":"Fontibre",
    "qs_pg:name_adm0":"Espa\u00f1a",
    "qs_pg:name_adm1":"Cantabria",
    "qs_pg:photos":195,
    "qs_pg:photos_1k":40,
    "qs_pg:photos_9k":1,
    "qs_pg:photos_9r":4,
    "qs_pg:photos_all":195,
    "qs_pg:photos_sr":4,
    "qs_pg:pop_sr":0,
    "qs_pg:qs_pg_placetype":"locality",
    "qs_pg:qs_pg_placetype_gp":"Town",
    "qs_pg:woe_adm0":23424950,
    "woe:adm0_id":23424950,
    "woe:name_adm0":"Espa\u00f1a",
    "woe:name_adm1":"Cantabria",
    "woe:placetype":"Town",
    "wof:name":"Fontibre",
    "wof:placetype":"locality"
},
  "geometry": {"coordinates":[-4.18647,43.01714],"type":"Point"}
}