{
  "type": "Feature",
  "properties": {
    "gn:admin1_code":"34",
    "gn:admin2_code":"O",
    "gn:admin3_code":"33068",
    "gn:asciiname":"Coto de Buenamadre",
    "gn:country_code":"ES",
    "gn:dem":981,
    "gn:feature_class":"P",
    "gn:feature_code":"PPL",
    "gn:name":"Coto de Buenamadre",
    "gn:population":0,
    "gn:timezone":"Europe/Madrid",
    "iso:country":"ES",
    "wof:name":"Coto de Buenamadre",
    "wof:placetype":"locality"
},
  "geometry": {"coordinates":[-6.23686,43.08016],"type":"Point"}
}