{
  "type": "Feature",
  "properties": {
    "gn:gn_country":"ES",
    "gn:gn_fcode":"PPLA3",
    "gn:gn_pop":900,
    "gn:population":900,
    "iso:country":"ES",
    "name:ara_x_preferred":[
        "\u0633\u0627\u0646\u062a\u0627\u064a\u0628\u0627\u0646\u064a\u064a\u0632 \u0625\u0644 \u0628\u0627\u062e\u0648"
    ],
    "name:baq_x_preferred":[
        "Santib\u00e1\u00f1ez el Bajo"
    ],
    "name:cat_x_preferred":[
        "Santib\u00e1\u00f1ez el Bajo"
    ],
    "name:chi_x_preferred":[
        "\u6851\u8482\u74e6\u6d85\u585e\u5c14\u74e6\u970d"
    ],
    "name:dut_x_preferred":[
        "Santib\u00e1\u00f1ez el Bajo"
    ],
    "name:eng_x_preferred":[
        "Santib\u00e1\u00f1ez el Bajo"
    ],
    "name:epo_x_preferred":[
        "Santib\u00e1\u00f1ez el Bajo"
    ],
    "name:ext_x_preferred":[
        "Santiba\u00f1i el Baju"
    ],
    "name:fre_x_preferred":[
        "Santib\u00e1\u00f1ez el Bajo"
    ],
    "name:hun_x_preferred":[
        "Santib\u00e1\u00f1ez el Bajo"
    ],
    "name:ina_x_preferred":[
        "Santib\u00e1\u00f1ez el Bajo"
    ],
    "name:ita_x_preferred":[
        "Santib\u00e1\u00f1ez el Bajo"
    ],
    "name:may_x_preferred":[
        "Santib\u00e1\u00f1ez el Bajo"
    ],
    "name:nan_x_preferred":[
        "Santib\u00e1\u00f1ez el Bajo"
    ],
    "name:oci_x_preferred":[
        "Santib\u00e1\u00f1ez el Bajo"
    ],
    "name:pol_x_preferred":[
        "Santib\u00e1\u00f1ez el Bajo"
    ],
    "name:por_x_preferred":[
        "Santib\u00e1\u00f1ez el Bajo"
    ],
    "name:rum_x_preferred":[
        "Santib\u00e1\u00f1ez el Bajo"
    ],
    "name:rus_x_preferred":[
        "\u0421\u0430\u043d\u0442\u0438\u0431\u0430\u043d\u044c\u0435\u0441-\u044d\u043b\u044c-\u0411\u0430\u0445\u043e"
    ],
    "name:spa_x_preferred":[
        "Santib\u00e1\u00f1ez el Bajo"
    ],
    "name:swe_x_preferred":[
        "Santib\u00e1\u00f1ez el Bajo"
    ],
    "name:ukr_x_preferred":[
        "\u0421\u0430\u043d\u0442\u0456\u0431\u0430\u043d\u044c\u0454\u0441-\u0435\u043b\u044c-\u0411\u0430\u0445\u043e"
    ],
    "name:vie_x_preferred":[
        "Santib\u00e1\u00f1ez el Bajo"
    ],
    "name:war_x_preferred":[
        "Santib\u00e1\u00f1ez el Bajo"
    ],
    "qs_pg:aaroncc":"ES",
    "qs_pg:gn_country":"ES",
    "qs_pg:gn_fcode":"PPLA3",
    "qs_pg:gn_pop":900,
    "qs_pg:name":"Santib\u00e1\u00f1ez el Bajo",
    "qs_pg:name_adm0":"Espa\u00f1a",
    "qs_pg:name_adm1":"Extremadura",
    "qs_pg:photos_9r":0,
    "qs_pg:photos_sr":0,
    "qs_pg:pop_sr":2,
    "qs_pg:qs_pg_placetype":"locality",
    "qs_pg:qs_pg_placetype_gp":"Town",
    "qs_pg:woe_adm0":23424950,
    "woe:adm0_id":23424950,
    "woe:name_adm0":"Espa\u00f1a",
    "woe:name_adm1":"Extremadura",
    "woe:placetype":"Town",
    "wof:name":"Santib\u00e1\u00f1ez el Bajo",
    "wof:placetype":"locality",
    "wof:population":900
},
  "geometry": {"coordinates":[-6.22441,40.17637],"type":"Point"}
}