{
  "type": "Feature",
  "properties": {
    "gn:gn_country":"ES",
    "gn:gn_fcode":"ADM3",
    "gn:gn_pop":341,
    "gn:population":325,
    "iso:country":"ES",
    "name:baq_x_preferred":[
        "Santo Tom\u00e9 del Puerto"
    ],
    "name:cat_x_preferred":[
        "Santo Tom\u00e9 del Puerto"
    ],
    "name:chi_x_preferred":[
        "\u6851\u6258\u6258\u6885\u5fb7\u5c14\u666e\u57c3\u5c14\u6258"
    ],
    "name:dut_x_preferred":[
        "Santo Tom\u00e9 del Puerto"
    ],
    "name:eng_x_preferred":[
        "Santo Tom\u00e9 del Puerto"
    ],
    "name:fre_x_preferred":[
        "Santo Tom\u00e9 del Puerto"
    ],
    "name:hun_x_preferred":[
        "Santo Tom\u00e9 del Puerto"
    ],
    "name:ina_x_preferred":[
        "Santo Tom\u00e9 del Puerto"
    ],
    "name:ita_x_preferred":[
        "Santo Tom\u00e9 del Puerto"
    ],
    "name:may_x_preferred":[
        "Santo Tom\u00e9 del Puerto"
    ],
    "name:nan_x_preferred":[
        "Santo Tom\u00e9 del Puerto"
    ],
    "name:oci_x_preferred":[
        "Santo Tom\u00e9 del Puerto"
    ],
    "name:pol_x_preferred":[
        "Santo Tom\u00e9 del Puerto"
    ],
    "name:por_x_preferred":[
        "Santo Tom\u00e9 del Puerto"
    ],
    "name:rus_x_preferred":[
        "\u0421\u0430\u043d\u0442\u043e-\u0422\u043e\u043c\u0435-\u0434\u0435\u043b\u044c-\u041f\u0443\u044d\u0440\u0442\u043e"
    ],
    "name:spa_x_preferred":[
        "Santo Tom\u00e9 del Puerto"
    ],
    "name:swe_x_preferred":[
        "Santo Tom\u00e9 del Puerto"
    ],
    "name:ukr_x_preferred":[
        "\u0421\u0430\u043d\u0442\u043e-\u0422\u043e\u043c\u0435-\u0434\u0435\u043b\u044c-\u041f\u0443\u0435\u0440\u0442\u043e"
    ],
    "name:uzb_x_preferred":[
        "Santo Tom\u00e9 del Puerto"
    ],
    "name:vie_x_preferred":[
        "Santo Tom\u00e9 del Puerto"
    ],
    "name:war_x_preferred":[
        "Santo Tom\u00e9 del Puerto"
    ],
    "qs_pg:aaroncc":"ES",
    "qs_pg:gn_country":"ES",
    "qs_pg:gn_fcode":"ADM3",
    "qs_pg:gn_pop":341,
    "qs_pg:name":"Santo Tom\u00e9 del Puerto",
    "qs_pg:name_adm0":"Espa\u00f1a",
    "qs_pg:name_adm1":"Castilla y Le\u00f3n",
    "qs_pg:photos":23,
    "qs_pg:photos_1k":5,
    "qs_pg:photos_9k":1,
    "qs_pg:photos_9r":1,
    "qs_pg:photos_all":23,
    "qs_pg:photos_sr":1,
    "qs_pg:pop_sr":2,
    "qs_pg:qs_pg_placetype":"locality",
    "qs_pg:qs_pg_placetype_gp":"Town",
    "qs_pg:woe_adm0":23424950,
    "woe:adm0_id":23424950,
    "woe:name_adm0":"Espa\u00f1a",
    "woe:name_adm1":"Castilla y Le\u00f3n",
    "woe:placetype":"Town",
    "wof:name":"Santo Tom\u00e9 del Puerto",
    "wof:placetype":"locality",
    "wof:population":325
},
  "geometry": {"coordinates":[-3.57782,41.18722],"type":"Point"}
}