{
  "type": "Feature",
  "properties": {
    "gn:gn_country":"ES",
    "gn:gn_fcode":"PPLA3",
    "gn:gn_pop":288,
    "gn:population":288,
    "iso:country":"ES",
    "name:ara_x_preferred":[
        "\u0623\u0628\u0627\u062f\u064a\u0627"
    ],
    "name:ast_x_preferred":[
        "Abad\u00eda"
    ],
    "name:cat_x_preferred":[
        "Abad\u00eda"
    ],
    "name:ceb_x_preferred":[
        "Abad\u00eda"
    ],
    "name:deu_x_preferred":[
        "Abad\u00eda"
    ],
    "name:eng_x_preferred":[
        "Abad\u00eda"
    ],
    "name:epo_x_preferred":[
        "Abad\u00eda"
    ],
    "name:eus_x_preferred":[
        "Abad\u00eda"
    ],
    "name:fra_x_preferred":[
        "Abad\u00eda"
    ],
    "name:glg_x_preferred":[
        "Abad\u00eda"
    ],
    "name:hun_x_preferred":[
        "Abad\u00eda"
    ],
    "name:hye_x_preferred":[
        "\u0531\u0562\u0561\u0564\u056b\u0561"
    ],
    "name:ina_x_preferred":[
        "Abad\u00eda"
    ],
    "name:ita_x_preferred":[
        "Abad\u00eda"
    ],
    "name:msa_x_preferred":[
        "Abad\u00eda"
    ],
    "name:nan_x_preferred":[
        "Abad\u00eda"
    ],
    "name:nld_x_preferred":[
        "Abad\u00eda"
    ],
    "name:oci_x_preferred":[
        "Abad\u00eda"
    ],
    "name:pol_x_preferred":[
        "Abad\u00eda"
    ],
    "name:por_x_preferred":[
        "Abadia"
    ],
    "name:ron_x_preferred":[
        "Abad\u00eda"
    ],
    "name:rus_x_preferred":[
        "\u0410\u0431\u0430\u0434\u0438\u0430"
    ],
    "name:spa_x_preferred":[
        "Abad\u00eda"
    ],
    "name:swe_x_preferred":[
        "Abad\u00eda"
    ],
    "name:tpi_x_preferred":[
        "Abad\u00eda"
    ],
    "name:ukr_x_preferred":[
        "\u0410\u0431\u0430\u0434\u0456\u044f"
    ],
    "name:uzb_x_preferred":[
        "Abad\u00eda"
    ],
    "name:vie_x_preferred":[
        "Abad\u00eda"
    ],
    "name:war_x_preferred":[
        "Abad\u00eda"
    ],
    "name:zho_x_preferred":[
        "\u963f\u74e6\u8fea\u4e9a"
    ],
    "qs_pg:aaroncc":"ES",
    "qs_pg:gn_country":"ES",
    "qs_pg:gn_fcode":"PPLA3",
    "qs_pg:gn_pop":288,
    "qs_pg:name":"Abad\u00eda",
    "qs_pg:name_adm0":"Espa\u00f1a",
    "qs_pg:name_adm1":"Extremadura",
    "qs_pg:photos":135,
    "qs_pg:photos_1k":27,
    "qs_pg:photos_9k":1,
    "qs_pg:photos_9r":3,
    "qs_pg:photos_all":135,
    "qs_pg:photos_sr":3,
    "qs_pg:pop_sr":2,
    "qs_pg:qs_pg_placetype":"locality",
    "qs_pg:qs_pg_placetype_gp":"Town",
    "qs_pg:woe_adm0":23424950,
    "woe:adm0_id":23424950,
    "woe:name_adm0":"Espa\u00f1a",
    "woe:name_adm1":"Extremadura",
    "woe:placetype":"Town",
    "wof:name":"Abad\u00eda",
    "wof:placetype":"locality",
    "wof:population":288
},
  "geometry": {"coordinates":[-5.97828,40.25922],"type":"Point"}
}