{
  "type": "Feature",
  "properties": {
    "gn:country":"ES",
    "gn:fcode":"PPL",
    "gn:population":43,
    "iso:country":"ES",
    "name:ara_x_preferred":[
        "\u0644\u0627 \u0628\u0627\u0631\u0627 \u062f\u064a \u0644\u0627\u0633 \u0641\u064a\u062c\u0627\u0633"
    ],
    "name:arg_x_preferred":[
        "La Parra de las Vegas"
    ],
    "name:cat_x_preferred":[
        "La Parra de las Vegas"
    ],
    "name:eng_x_preferred":[
        "La Parra de las Vegas"
    ],
    "name:eus_x_preferred":[
        "La Parra de las Vegas"
    ],
    "name:fra_x_preferred":[
        "La Parra de las Vegas"
    ],
    "name:glg_x_preferred":[
        "La Parra de las Vegas"
    ],
    "name:hun_x_preferred":[
        "La Parra de las Vegas"
    ],
    "name:ita_x_preferred":[
        "La Parra de las Vegas"
    ],
    "name:kaz_x_preferred":[
        "\u041b\u0430-\u041f\u0430\u0440\u0440\u0430-\u0434\u0435-\u043b\u0430\u0441-\u0412\u0435\u0433\u0430\u0441"
    ],
    "name:msa_x_preferred":[
        "La Parra de las Vegas"
    ],
    "name:nan_x_preferred":[
        "La Parra de las Vegas"
    ],
    "name:nld_x_preferred":[
        "La Parra de las Vegas"
    ],
    "name:nob_x_preferred":[
        "La Parra de las Vegas"
    ],
    "name:oci_x_preferred":[
        "La Parra de las Vegas"
    ],
    "name:pol_x_preferred":[
        "La Parra de las Vegas"
    ],
    "name:por_x_preferred":[
        "La Parra de las Vegas"
    ],
    "name:rus_x_preferred":[
        "\u041b\u0430-\u041f\u0430\u0440\u0440\u0430-\u0434\u0435-\u043b\u0430\u0441-\u0412\u0435\u0433\u0430\u0441"
    ],
    "name:spa_x_preferred":[
        "La Parra de las Vegas"
    ],
    "name:ukr_x_preferred":[
        "\u041b\u0430-\u041f\u0430\u0440\u0440\u0430-\u0434\u0435-\u043b\u0430\u0441-\u0412\u0435\u0433\u0430\u0441"
    ],
    "name:vie_x_preferred":[
        "La Parra de las Vegas"
    ],
    "name:war_x_preferred":[
        "La Parra de las Vegas"
    ],
    "name:zho_x_preferred":[
        "\u62c9\u5e15\u62c9\u5fb7\u62c9\u65af\u97e6\u52a0\u65af"
    ],
    "qs_pg:aaroncc":"ES",
    "qs_pg:gn_country":"ES",
    "qs_pg:gn_fcode":"PPL",
    "qs_pg:gn_pop":43,
    "qs_pg:name":"La Parra de Las Vegas",
    "qs_pg:name_adm0":"Espa\u00f1a",
    "qs_pg:name_adm1":"Castilla-La Mancha",
    "qs_pg:photos_9r":0,
    "qs_pg:photos_sr":0,
    "qs_pg:pop_sr":1,
    "qs_pg:qs_pg_placetype":"locality",
    "qs_pg:qs_pg_placetype_gp":"Town",
    "qs_pg:woe_adm0":23424950,
    "woe:adm0_id":23424950,
    "woe:name_adm0":"Espa\u00f1a",
    "woe:name_adm1":"Castilla-La Mancha",
    "woe:placetype":"Town",
    "wof:name":"La Parra de Las Vegas",
    "wof:placetype":"locality",
    "wof:population":43
},
  "geometry": {"coordinates":[-2.20443,39.86882],"type":"Point"}
}