{
  "type": "Feature",
  "properties": {
    "gn:admin1_code":"56",
    "gn:admin2_code":"GI",
    "gn:admin3_code":"17198",
    "gn:asciiname":"Sant Tomas de Fluvia",
    "gn:country_code":"ES",
    "gn:dem":33,
    "gn:feature_class":"P",
    "gn:feature_code":"PPL",
    "gn:name":"Sant Tom\u00e0s de Fluvi\u00e0",
    "gn:population":0,
    "gn:timezone":"Europe/Madrid",
    "iso:country":"ES",
    "name:cat_x_preferred":[
        "Sant Tom\u00e0s de Fluvi\u00e0"
    ],
    "wof:name":"Sant Tomas de Fluvia",
    "wof:placetype":"locality"
},
  "geometry": {"coordinates":[3.00927,42.18207],"type":"Point"}
}