{
  "type": "Feature",
  "properties": {
    "gn:admin1_code":"51",
    "gn:admin2_code":"GR",
    "gn:admin3_code":"18061",
    "gn:asciiname":"Cortijada Santa Catalina",
    "gn:country_code":"ES",
    "gn:dem":786,
    "gn:feature_class":"P",
    "gn:feature_code":"PPL",
    "gn:name":"Cortijada Santa Catalina",
    "gn:population":0,
    "gn:timezone":"Europe/Madrid",
    "iso:country":"ES",
    "name:und_x_variant":[
        "Cortijo de Santa Catalina",
        "Cortijada Santa Catalina"
    ],
    "wof:name":"Cortijada Santa Catalina",
    "wof:placetype":"locality"
},
  "geometry": {"coordinates":[-3.76415,37.12918],"type":"Point"}
}