{
  "type": "Feature",
  "properties": {
    "gn:country":"ES",
    "gn:fcode":"PPL",
    "gn:population":0,
    "iso:country":"ES",
    "name:arg_x_preferred":[
        "A Pontenova"
    ],
    "name:ast_x_preferred":[
        "A Pontenova"
    ],
    "name:cat_x_preferred":[
        "A Pontenova"
    ],
    "name:eus_x_preferred":[
        "A Pontenova"
    ],
    "name:fra_x_preferred":[
        "A Pontenova"
    ],
    "name:glg_x_preferred":[
        "A Pontenova"
    ],
    "name:hun_x_preferred":[
        "A Pontenova"
    ],
    "name:hye_x_preferred":[
        "\u054a\u0578\u0582\u0565\u0576\u057f\u0565 \u0546\u0578\u0582\u0565\u057e\u0578"
    ],
    "name:ita_x_preferred":[
        "A Pontenova"
    ],
    "name:jpn_x_preferred":[
        "\u30a2\u30fb\u30dd\u30f3\u30c6\u30ce\u30fc\u30d0"
    ],
    "name:kaz_x_preferred":[
        "\u041f\u0443\u044d\u043d\u0442\u0435-\u041d\u0443\u044d\u0432\u043e"
    ],
    "name:msa_x_preferred":[
        "A Pontenova"
    ],
    "name:nld_x_preferred":[
        "A Pontenova"
    ],
    "name:oci_x_preferred":[
        "A Pontenova"
    ],
    "name:pol_x_preferred":[
        "Puente Nuevo"
    ],
    "name:por_x_preferred":[
        "A Pontenova"
    ],
    "name:rus_x_preferred":[
        "\u041f\u0443\u044d\u043d\u0442\u0435-\u041d\u0443\u044d\u0432\u043e"
    ],
    "name:spa_x_preferred":[
        "Puente Nuevo"
    ],
    "name:tur_x_preferred":[
        "A Pontenova"
    ],
    "name:ukr_x_preferred":[
        "\u0410-\u041f\u043e\u043d\u0442\u0435\u043d\u043e\u0432\u0430"
    ],
    "name:uzb_x_preferred":[
        "A Pontenova"
    ],
    "name:vie_x_preferred":[
        "A Pontenova"
    ],
    "name:war_x_preferred":[
        "A Pontenova"
    ],
    "name:zho_x_preferred":[
        "\u963f\u84ec\u7279\u8bfa\u74e6"
    ],
    "qs_pg:aaroncc":"ES",
    "qs_pg:gn_country":"ES",
    "qs_pg:gn_fcode":"PPL",
    "qs_pg:gn_pop":0,
    "qs_pg:name":"A Pontenova",
    "qs_pg:name_adm0":"Espa\u00f1a",
    "qs_pg:name_adm1":"Galicia",
    "qs_pg:photos":32,
    "qs_pg:photos_1k":6,
    "qs_pg:photos_9k":1,
    "qs_pg:photos_9r":2,
    "qs_pg:photos_all":32,
    "qs_pg:photos_sr":2,
    "qs_pg:pop_sr":0,
    "qs_pg:qs_pg_placetype":"locality",
    "qs_pg:qs_pg_placetype_gp":"Town",
    "qs_pg:woe_adm0":23424950,
    "woe:adm0_id":23424950,
    "woe:name_adm0":"Espa\u00f1a",
    "woe:name_adm1":"Galicia",
    "woe:placetype":"Town",
    "wof:name":"A Pontenova",
    "wof:placetype":"locality"
},
  "geometry": {"coordinates":[-7.23333,42.38333],"type":"Point"}
}