{
  "type": "Feature",
  "properties": {
    "gn:admin1_code":"07",
    "gn:admin2_code":"PM",
    "gn:admin3_code":"07040",
    "gn:asciiname":"Creu Vermella",
    "gn:country_code":"ES",
    "gn:dem":23,
    "gn:feature_class":"P",
    "gn:feature_code":"PPL",
    "gn:name":"Creu Vermella",
    "gn:population":0,
    "gn:timezone":"Europe/Madrid",
    "iso:country":"ES",
    "wof:name":"Creu Vermella",
    "wof:placetype":"locality"
},
  "geometry": {"coordinates":[2.71531,39.57973],"type":"Point"}
}