{
  "type": "Feature",
  "properties": {
    "gn:country":"ES",
    "gn:fcode":"PPLA3",
    "gn:population":1129,
    "iso:country":"ES",
    "name:arg_x_preferred":[
        "Villaman\u00edn"
    ],
    "name:azb_x_preferred":[
        "\u0648\u06cc\u06cc\u0627\u0645\u0627\u0646\u06cc\u0646"
    ],
    "name:cat_x_preferred":[
        "Villaman\u00edn"
    ],
    "name:ceb_x_preferred":[
        "Villaman\u00edn"
    ],
    "name:eng_x_preferred":[
        "Villaman\u00edn"
    ],
    "name:eus_x_preferred":[
        "Villaman\u00edn"
    ],
    "name:fas_x_preferred":[
        "\u0648\u06cc\u06cc\u0627\u0645\u0627\u0646\u06cc\u0646"
    ],
    "name:fra_x_preferred":[
        "Villaman\u00edn"
    ],
    "name:glg_x_preferred":[
        "Villaman\u00edn"
    ],
    "name:haw_x_preferred":[
        "Villaman\u00edn"
    ],
    "name:hun_x_preferred":[
        "Villaman\u00edn"
    ],
    "name:hye_x_preferred":[
        "\u054e\u056b\u056c\u0575\u0561\u0574\u0561\u0576\u056b\u0576"
    ],
    "name:ido_x_preferred":[
        "Villaman\u00edn"
    ],
    "name:ina_x_preferred":[
        "Villaman\u00edn"
    ],
    "name:ita_x_preferred":[
        "Villaman\u00edn"
    ],
    "name:jpn_x_preferred":[
        "\u30d3\u30b8\u30e3\u30de\u30cb\u30f3"
    ],
    "name:kaz_x_preferred":[
        "\u0412\u0438\u043b\u044c\u044f\u043c\u0430\u043d\u0438\u043d"
    ],
    "name:lit_x_preferred":[
        "Viljamaninas"
    ],
    "name:msa_x_preferred":[
        "Villaman\u00edn"
    ],
    "name:nan_x_preferred":[
        "Villaman\u00edn"
    ],
    "name:nld_x_preferred":[
        "Villaman\u00edn"
    ],
    "name:oci_x_preferred":[
        "Villaman\u00edn"
    ],
    "name:pol_x_preferred":[
        "Villaman\u00edn"
    ],
    "name:por_x_preferred":[
        "Villaman\u00edn"
    ],
    "name:rus_x_preferred":[
        "\u0412\u0438\u043b\u044c\u044f\u043c\u0430\u043d\u0438\u043d"
    ],
    "name:spa_x_preferred":[
        "Villaman\u00edn"
    ],
    "name:swe_x_preferred":[
        "Villaman\u00edn"
    ],
    "name:tpi_x_preferred":[
        "Villaman\u00edn"
    ],
    "name:ukr_x_preferred":[
        "\u0412\u0456\u043b\u044c\u044f\u043c\u0430\u043d\u0456\u043d"
    ],
    "name:vie_x_preferred":[
        "Villaman\u00edn"
    ],
    "name:war_x_preferred":[
        "Villaman\u00edn"
    ],
    "name:zho_x_preferred":[
        "\u6bd4\u5229\u4e9a\u9a6c\u5b81"
    ],
    "qs_pg:aaroncc":"ES",
    "qs_pg:gn_country":"ES",
    "qs_pg:gn_fcode":"PPLA3",
    "qs_pg:gn_pop":1129,
    "qs_pg:name":"Villaman\u00edn",
    "qs_pg:name_adm0":"Espa\u00f1a",
    "qs_pg:name_adm1":"Castilla y Le\u00f3n",
    "qs_pg:photos":119,
    "qs_pg:photos_1k":24,
    "qs_pg:photos_9k":1,
    "qs_pg:photos_9r":3,
    "qs_pg:photos_all":119,
    "qs_pg:photos_sr":3,
    "qs_pg:pop_sr":3,
    "qs_pg:qs_pg_placetype":"locality",
    "qs_pg:qs_pg_placetype_gp":"Town",
    "qs_pg:woe_adm0":23424950,
    "woe:adm0_id":23424950,
    "woe:name_adm0":"Espa\u00f1a",
    "woe:name_adm1":"Castilla y Le\u00f3n",
    "woe:placetype":"Town",
    "wof:name":"Villaman\u00edn",
    "wof:placetype":"locality",
    "wof:population":1129
},
  "geometry": {"coordinates":[-5.65,42.93333],"type":"Point"}
}