{
  "type": "Feature",
  "properties": {
    "gn:admin1_code":"58",
    "gn:admin2_code":"LU",
    "gn:admin3_code":"27054",
    "gn:asciiname":"Lourido",
    "gn:country_code":"ES",
    "gn:dem":366,
    "gn:feature_class":"P",
    "gn:feature_code":"PPL",
    "gn:name":"Lourido",
    "gn:population":0,
    "gn:timezone":"Europe/Madrid",
    "iso:country":"ES",
    "wof:name":"Lourido",
    "wof:placetype":"locality"
},
  "geometry": {"coordinates":[-7.21584,43.27387],"type":"Point"}
}