{
  "type": "Feature",
  "properties": {
    "gn:admin1_code":"55",
    "gn:admin2_code":"P",
    "gn:admin3_code":"34236",
    "gn:asciiname":"Villotilla",
    "gn:country_code":"ES",
    "gn:dem":840,
    "gn:feature_class":"P",
    "gn:feature_code":"PPL",
    "gn:name":"Villotilla",
    "gn:population":0,
    "gn:timezone":"Europe/Madrid",
    "iso:country":"ES",
    "wof:name":"Villotilla",
    "wof:placetype":"locality"
},
  "geometry": {"coordinates":[-4.67934,42.35946],"type":"Point"}
}