{
  "type": "Feature",
  "properties": {
    "gn:admin1_code":"55",
    "gn:admin2_code":"LE",
    "gn:admin3_code":"24011",
    "gn:asciiname":"Mosteiros",
    "gn:country_code":"ES",
    "gn:dem":962,
    "gn:feature_class":"P",
    "gn:feature_code":"PPL",
    "gn:name":"Mosteiros",
    "gn:population":0,
    "gn:timezone":"Europe/Madrid",
    "iso:country":"ES",
    "name:ceb_x_preferred":[
        "Mosteiros"
    ],
    "name:deu_x_preferred":[
        "Mosteiros"
    ],
    "name:fas_x_preferred":[
        "\u0645\u0648\u0633\u062a\u0626\u06cc\u0631\u0648\u0633"
    ],
    "name:fra_x_preferred":[
        "Mosteiros"
    ],
    "name:heb_x_preferred":[
        "\u05de\u05d5\u05d8\u05dc\u05d4 \u05e1\u05d8\u05e8\u05d5\u05dd"
    ],
    "name:hun_x_preferred":[
        "Mosteiros"
    ],
    "name:nds_x_preferred":[
        "Mosteiros"
    ],
    "name:nld_x_preferred":[
        "Mosteiros"
    ],
    "name:por_x_preferred":[
        "Mosteiros"
    ],
    "name:rus_x_preferred":[
        "\u041c\u043e\u0448\u0442\u0435\u0439\u0440\u0443\u0448"
    ],
    "name:swe_x_preferred":[
        "Mosteiros"
    ],
    "wof:name":"Mosteiros",
    "wof:placetype":"locality"
},
  "geometry": {"coordinates":[-6.95063,42.59566],"type":"Point"}
}