{
  "type": "Feature",
  "properties": {
    "gn:admin1_code":"55",
    "gn:admin2_code":"LE",
    "gn:admin3_code":"24011",
    "gn:asciiname":"Mosteiros",
    "gn:country_code":"ES",
    "gn:dem":962,
    "gn:feature_class":"P",
    "gn:feature_code":"PPL",
    "gn:name":"Mosteiros",
    "gn:population":0,
    "gn:timezone":"Europe/Madrid",
    "iso:country":"ES",
    "wof:name":"Mosteiros",
    "wof:placetype":"locality"
},
  "geometry": {"coordinates":[-6.95063,42.59566],"type":"Point"}
}