{
  "type": "Feature",
  "properties": {
    "gn:admin1_code":"55",
    "gn:admin2_code":"SG",
    "gn:admin3_code":"40162",
    "gn:asciiname":"Pradenilla",
    "gn:country_code":"ES",
    "gn:dem":1121,
    "gn:feature_class":"P",
    "gn:feature_code":"PPL",
    "gn:name":"Pradenilla",
    "gn:population":0,
    "gn:timezone":"Europe/Madrid",
    "iso:country":"ES",
    "wof:name":"Pradenilla",
    "wof:placetype":"locality"
},
  "geometry": {"coordinates":[-3.68349,41.16213],"type":"Point"}
}