{
  "type": "Feature",
  "properties": {
    "gn:country":"ES",
    "gn:fcode":"PPLA3",
    "gn:population":278,
    "iso:country":"ES",
    "name:ara_x_preferred":[
        "\u0623\u0644\u0648\u0633\u062a\u0627\u0646\u062a\u064a"
    ],
    "name:arg_x_preferred":[
        "Alustante"
    ],
    "name:arz_x_preferred":[
        "\u0627\u0644\u0648\u0633\u062a\u0627\u0646\u062a\u0649"
    ],
    "name:ast_x_preferred":[
        "Alustante"
    ],
    "name:cat_x_preferred":[
        "Alustante"
    ],
    "name:ceb_x_preferred":[
        "Alustante"
    ],
    "name:che_x_preferred":[
        "\u0410\u043b\u0443\u0441\u0442\u0430\u043d\u0442\u0435"
    ],
    "name:eng_x_preferred":[
        "Alustante"
    ],
    "name:epo_x_preferred":[
        "Alustante"
    ],
    "name:eus_x_preferred":[
        "Alustante"
    ],
    "name:fas_x_preferred":[
        "\u0627\u0644\u0648\u0633\u062a\u0627\u0646\u062a"
    ],
    "name:fra_x_preferred":[
        "Alustante"
    ],
    "name:gle_x_preferred":[
        "Alustante"
    ],
    "name:hun_x_preferred":[
        "Alustante"
    ],
    "name:hye_x_preferred":[
        "\u0531\u056c\u0578\u0582\u057d\u057f\u0561\u0576\u057f\u0565"
    ],
    "name:ile_x_preferred":[
        "Alustante"
    ],
    "name:ina_x_preferred":[
        "Alustante"
    ],
    "name:ita_x_preferred":[
        "Alustante"
    ],
    "name:kaz_x_preferred":[
        "\u0410\u043b\u0443\u0441\u0442\u0430\u043d\u0442\u0435"
    ],
    "name:lld_x_preferred":[
        "Alustante"
    ],
    "name:ltz_x_preferred":[
        "Alustante"
    ],
    "name:msa_x_preferred":[
        "Alustante"
    ],
    "name:nan_x_preferred":[
        "Alustante"
    ],
    "name:nld_x_preferred":[
        "Alustante"
    ],
    "name:nob_x_preferred":[
        "Alustante"
    ],
    "name:oci_x_preferred":[
        "Alustante"
    ],
    "name:pam_x_preferred":[
        "Alustante"
    ],
    "name:pol_x_preferred":[
        "Alustante"
    ],
    "name:por_x_preferred":[
        "Alustante"
    ],
    "name:rus_x_preferred":[
        "\u0410\u043b\u0443\u0441\u0442\u0430\u043d\u0442\u0435"
    ],
    "name:spa_x_preferred":[
        "Alustante"
    ],
    "name:sqi_x_preferred":[
        "Alustante"
    ],
    "name:swe_x_preferred":[
        "Alustante"
    ],
    "name:tat_x_preferred":[
        "\u0410\u043b\u0443\u0441\u0442\u0430\u043d\u0442\u0435"
    ],
    "name:ukr_x_preferred":[
        "\u0410\u043b\u0443\u0441\u0442\u0430\u043d\u0442\u0435"
    ],
    "name:vec_x_preferred":[
        "Alustante"
    ],
    "name:vie_x_preferred":[
        "Alustante"
    ],
    "name:war_x_preferred":[
        "Alustante"
    ],
    "name:zho_x_preferred":[
        "\u963f\u5362\u65af\u5766\u7279"
    ],
    "qs_pg:aaroncc":"ES",
    "qs_pg:gn_country":"ES",
    "qs_pg:gn_fcode":"PPLA3",
    "qs_pg:gn_pop":278,
    "qs_pg:name":"Alustante",
    "qs_pg:photos_9r":0,
    "qs_pg:photos_sr":0,
    "qs_pg:pop_sr":2,
    "qs_pg:qs_pg_placetype":"locality",
    "wof:name":"Alustante",
    "wof:placetype":"locality",
    "wof:population":278
},
  "geometry": {"coordinates":[-1.6591,40.61442],"type":"Point"}
}