{
  "type": "Feature",
  "properties": {
    "iso:country":"ES",
    "name:und_x_variant":[
        "San Tirso de Oseiro"
    ],
    "qs:a0":"Espa\u00f1a",
    "qs:a1":"*A Coru\u00f1a",
    "qs:a1r":"0Galicia",
    "qs:adm0":"Espa\u00f1a",
    "qs:la_lc":"*",
    "qs:level":"locality",
    "qs:loc":"Oseiro",
    "qs:loc_alt":"Oseiro",
    "qs:pop":0,
    "qs:type":"buffered point",
    "wof:name":"Oseiro",
    "wof:placetype":"locality"
},
  "geometry": {"coordinates":[-8.433452,43.365401],"type":"Point"}
}