{
  "type": "Feature",
  "properties": {
    "gn:admin1_code":"51",
    "gn:admin2_code":"SE",
    "gn:admin3_code":"41038",
    "gn:asciiname":"Matachica",
    "gn:country_code":"ES",
    "gn:dem":62,
    "gn:feature_class":"P",
    "gn:feature_code":"PPLL",
    "gn:name":"Matachica",
    "gn:population":0,
    "gn:timezone":"Europe/Madrid",
    "iso:country":"ES",
    "wof:name":"Matachica",
    "wof:placetype":"locality"
},
  "geometry": {"coordinates":[-5.88424,37.27694],"type":"Point"}
}