{
  "type": "Feature",
  "properties": {
    "gn:admin1_code":"58",
    "gn:admin2_code":"OR",
    "gn:admin3_code":"32013",
    "gn:asciiname":"Cardelle",
    "gn:country_code":"ES",
    "gn:dem":336,
    "gn:feature_class":"P",
    "gn:feature_code":"PPL",
    "gn:name":"Cardelle",
    "gn:population":0,
    "gn:timezone":"Europe/Madrid",
    "iso:country":"ES",
    "wof:name":"Cardelle",
    "wof:placetype":"locality"
},
  "geometry": {"coordinates":[-8.23109,42.42607],"type":"Point"}
}