{
  "type": "Feature",
  "properties": {
    "gn:admin1_code":"34",
    "gn:admin2_code":"O",
    "gn:admin3_code":"33073",
    "gn:asciiname":"Vega del Rey",
    "gn:country_code":"ES",
    "gn:dem":593,
    "gn:feature_class":"P",
    "gn:feature_code":"PPL",
    "gn:name":"Vega del Rey",
    "gn:population":0,
    "gn:timezone":"Europe/Madrid",
    "iso:country":"ES",
    "name:und_x_variant":[
        "Vega de Rey",
        "Vega del Rey"
    ],
    "wof:name":"Vega del Rey",
    "wof:placetype":"locality"
},
  "geometry": {"coordinates":[-6.50192,43.33389],"type":"Point"}
}