{
  "type": "Feature",
  "properties": {
    "gn:admin1_code":"54",
    "gn:admin2_code":"GU",
    "gn:admin3_code":"19277",
    "gn:asciiname":"Otilla",
    "gn:country_code":"ES",
    "gn:dem":1183,
    "gn:feature_class":"P",
    "gn:feature_code":"PPL",
    "gn:name":"Otilla",
    "gn:population":0,
    "gn:timezone":"Europe/Madrid",
    "iso:country":"ES",
    "wof:name":"Otilla",
    "wof:placetype":"locality"
},
  "geometry": {"coordinates":[-1.78365,40.73922],"type":"Point"}
}