{
  "type": "Feature",
  "properties": {
    "gn:admin1_code":"51",
    "gn:admin2_code":"SE",
    "gn:admin3_code":"41091",
    "gn:asciiname":"Torreblanca de los Canos",
    "gn:country_code":"ES",
    "gn:dem":35,
    "gn:feature_class":"P",
    "gn:feature_code":"PPL",
    "gn:name":"Torreblanca de los Ca\u00f1os",
    "gn:population":0,
    "gn:timezone":"Europe/Madrid",
    "iso:country":"ES",
    "name:spa_x_preferred":[
        "Torreblanca de los Ca\u00f1os"
    ],
    "wof:name":"Torreblanca de los Canos",
    "wof:placetype":"locality"
},
  "geometry": {"coordinates":[-5.90491,37.38524],"type":"Point"}
}