{
  "type": "Feature",
  "properties": {
    "gn:country":"ES",
    "gn:fcode":"PPLA3",
    "gn:population":146,
    "iso:country":"ES",
    "name:ast_x_preferred":[
        "Villodrigo"
    ],
    "name:azb_x_preferred":[
        "\u0628\u06cc\u06cc\u062f\u0631\u06cc\u0642\u0648"
    ],
    "name:cat_x_preferred":[
        "Villodrigo"
    ],
    "name:ceb_x_preferred":[
        "Villodrigo"
    ],
    "name:eng_x_preferred":[
        "Villodrigo"
    ],
    "name:eus_x_preferred":[
        "Villodrigo"
    ],
    "name:fas_x_preferred":[
        "\u0628\u06cc\u06cc\u062f\u0631\u06cc\u06af\u0648"
    ],
    "name:fra_x_preferred":[
        "Villodrigo"
    ],
    "name:glg_x_preferred":[
        "Villodrigo"
    ],
    "name:hun_x_preferred":[
        "Villodrigo"
    ],
    "name:ile_x_preferred":[
        "Villodrigo"
    ],
    "name:ina_x_preferred":[
        "Villodrigo"
    ],
    "name:ita_x_preferred":[
        "Villodrigo"
    ],
    "name:msa_x_preferred":[
        "Villodrigo"
    ],
    "name:nan_x_preferred":[
        "Villodrigo"
    ],
    "name:nld_x_preferred":[
        "Villodrigo"
    ],
    "name:oci_x_preferred":[
        "Villodrigo"
    ],
    "name:pol_x_preferred":[
        "Villodrigo"
    ],
    "name:por_x_preferred":[
        "Villodrigo"
    ],
    "name:rus_x_preferred":[
        "\u0412\u0438\u043b\u044c\u043e\u0434\u0440\u0438\u0433\u043e"
    ],
    "name:spa_x_preferred":[
        "Villodrigo"
    ],
    "name:swe_x_preferred":[
        "Villodrigo"
    ],
    "name:ukr_x_preferred":[
        "\u0412\u0456\u043b\u044c\u0439\u043e\u0434\u0440\u0456\u0433\u043e"
    ],
    "name:und_x_variant":[
        "Villadrigo"
    ],
    "name:uzb_x_preferred":[
        "Villodrigo"
    ],
    "name:vie_x_preferred":[
        "Villodrigo"
    ],
    "name:war_x_preferred":[
        "Villodrigo"
    ],
    "name:zho_x_preferred":[
        "\u6bd4\u7565\u5fb7\u91cc\u6208"
    ],
    "qs_pg:aaroncc":"ES",
    "qs_pg:gn_country":"ES",
    "qs_pg:gn_fcode":"PPLA3",
    "qs_pg:gn_pop":146,
    "qs_pg:name":"Villodrigo",
    "qs_pg:name_adm0":"Espa\u00f1a",
    "qs_pg:name_adm1":"Castilla y Le\u00f3n",
    "qs_pg:photos_9k":1,
    "qs_pg:photos_9r":1,
    "qs_pg:photos_all":1,
    "qs_pg:photos_sr":0,
    "qs_pg:pop_sr":1,
    "qs_pg:qs_pg_placetype":"locality",
    "qs_pg:qs_pg_placetype_gp":"Town",
    "qs_pg:woe_adm0":23424950,
    "woe:adm0_id":23424950,
    "woe:name_adm0":"Espa\u00f1a",
    "woe:name_adm1":"Castilla y Le\u00f3n",
    "woe:placetype":"Town",
    "wof:name":"Villodrigo",
    "wof:placetype":"locality",
    "wof:population":146
},
  "geometry": {"coordinates":[-4.09527,42.14436],"type":"Point"}
}