{
  "type": "Feature",
  "properties": {
    "gn:admin1_code":"52",
    "gn:admin2_code":"HU",
    "gn:admin3_code":"22059",
    "gn:asciiname":"Aso de Sobremonte",
    "gn:country_code":"ES",
    "gn:dem":1271,
    "gn:feature_class":"P",
    "gn:feature_code":"PPL",
    "gn:name":"Aso de Sobremonte",
    "gn:population":0,
    "gn:timezone":"Europe/Madrid",
    "iso:country":"ES",
    "wof:name":"Aso de Sobremonte",
    "wof:placetype":"locality"
},
  "geometry": {"coordinates":[-0.36384,42.63251],"type":"Point"}
}