{
  "type": "Feature",
  "properties": {
    "gn:admin1_code":"58",
    "gn:admin2_code":"OR",
    "gn:admin3_code":"32043",
    "gn:asciiname":"Francos",
    "gn:country_code":"ES",
    "gn:dem":564,
    "gn:feature_class":"P",
    "gn:feature_code":"PPL",
    "gn:name":"Francos",
    "gn:population":0,
    "gn:timezone":"Europe/Madrid",
    "iso:country":"ES",
    "wof:name":"Francos",
    "wof:placetype":"locality"
},
  "geometry": {"coordinates":[-7.6449,42.27901],"type":"Point"}
}