{
  "type": "Feature",
  "properties": {
    "gn:admin1_code":"58",
    "gn:admin2_code":"LU",
    "gn:admin3_code":"27048",
    "gn:asciiname":"Cova",
    "gn:country_code":"ES",
    "gn:dem":218,
    "gn:feature_class":"P",
    "gn:feature_code":"PPL",
    "gn:name":"Cova",
    "gn:population":0,
    "gn:timezone":"Europe/Madrid",
    "iso:country":"ES",
    "wof:name":"Cova",
    "wof:placetype":"locality"
},
  "geometry": {"coordinates":[-7.18828,43.37446],"type":"Point"}
}