{
  "type": "Feature",
  "properties": {
    "gn:admin1_code":"54",
    "gn:admin2_code":"GU",
    "gn:admin3_code":"19033",
    "gn:asciiname":"Tobillos",
    "gn:country_code":"ES",
    "gn:dem":1220,
    "gn:feature_class":"P",
    "gn:feature_code":"PPL",
    "gn:name":"Tobillos",
    "gn:population":0,
    "gn:timezone":"Europe/Madrid",
    "iso:country":"ES",
    "wof:name":"Tobillos",
    "wof:placetype":"locality"
},
  "geometry": {"coordinates":[-2.15139,40.98858],"type":"Point"}
}