{
  "type": "Feature",
  "properties": {
    "gn:admin1_code":"58",
    "gn:admin2_code":"LU",
    "gn:admin3_code":"27040",
    "gn:asciiname":"Laya",
    "gn:country_code":"ES",
    "gn:dem":500,
    "gn:feature_class":"P",
    "gn:feature_code":"PPL",
    "gn:name":"Laya",
    "gn:population":0,
    "gn:timezone":"Europe/Madrid",
    "iso:country":"ES",
    "wof:name":"Laya",
    "wof:placetype":"locality"
},
  "geometry": {"coordinates":[-7.87784,42.90323],"type":"Point"}
}