{
  "type": "Feature",
  "properties": {
    "gn:admin1_code":"58",
    "gn:admin2_code":"LU",
    "gn:admin3_code":"27040",
    "gn:asciiname":"Laya",
    "gn:country_code":"ES",
    "gn:dem":500,
    "gn:feature_class":"P",
    "gn:feature_code":"PPL",
    "gn:name":"Laya",
    "gn:population":0,
    "gn:timezone":"Europe/Madrid",
    "iso:country":"ES",
    "name:ceb_x_preferred":[
        "Laya"
    ],
    "name:deu_x_preferred":[
        "Laya"
    ],
    "name:pol_x_preferred":[
        "Laya"
    ],
    "name:que_x_preferred":[
        "Laya"
    ],
    "name:rus_x_preferred":[
        "\u041b\u0430\u0439\u044f"
    ],
    "name:swe_x_preferred":[
        "Laya"
    ],
    "wof:name":"Laya",
    "wof:placetype":"locality"
},
  "geometry": {"coordinates":[-7.87784,42.90323],"type":"Point"}
}