{
  "type": "Feature",
  "properties": {
    "gn:admin1_code":"57",
    "gn:admin2_code":"BA",
    "gn:admin3_code":"06136",
    "gn:asciiname":"Los Matorrales",
    "gn:cc2":"ES",
    "gn:country_code":"ES",
    "gn:dem":578,
    "gn:feature_class":"P",
    "gn:feature_code":"PPL",
    "gn:name":"Los Matorrales",
    "gn:population":0,
    "gn:timezone":"Europe/Madrid",
    "iso:country":"ES",
    "name:und_x_variant":[
        "Cortijos Los Matorrales",
        "Matorrales",
        "Los Matorrales"
    ],
    "wof:name":"Los Matorrales",
    "wof:placetype":"locality"
},
  "geometry": {"coordinates":[-6.15,38.33333],"type":"Point"}
}