{
  "type": "Feature",
  "properties": {
    "gn:admin1_code":"55",
    "gn:admin2_code":"BU",
    "gn:admin3_code":"09214",
    "gn:asciiname":"El Ribero",
    "gn:country_code":"ES",
    "gn:dem":671,
    "gn:feature_class":"P",
    "gn:feature_code":"PPL",
    "gn:name":"El Ribero",
    "gn:population":0,
    "gn:timezone":"Europe/Madrid",
    "iso:country":"ES",
    "wof:name":"El Ribero",
    "wof:placetype":"locality"
},
  "geometry": {"coordinates":[-3.48352,43.03834000000001],"type":"Point"}
}