{
  "type": "Feature",
  "properties": {
    "gn:admin1_code":"55",
    "gn:admin2_code":"AV",
    "gn:admin3_code":"05112",
    "gn:asciiname":"El Barquillo",
    "gn:country_code":"ES",
    "gn:dem":983,
    "gn:feature_class":"P",
    "gn:feature_code":"PPL",
    "gn:name":"El Barquillo",
    "gn:population":0,
    "gn:timezone":"Europe/Madrid",
    "iso:country":"ES",
    "wof:name":"El Barquillo",
    "wof:placetype":"locality"
},
  "geometry": {"coordinates":[-5.50652,40.41879],"type":"Point"}
}