{
  "type": "Feature",
  "properties": {
    "gn:admin1_code":"55",
    "gn:admin2_code":"LE",
    "gn:admin3_code":"24230",
    "gn:asciiname":"Zambrocinos",
    "gn:country_code":"ES",
    "gn:dem":789,
    "gn:feature_class":"P",
    "gn:feature_code":"PPL",
    "gn:name":"Zambrocinos",
    "gn:population":0,
    "gn:timezone":"Europe/Madrid",
    "iso:country":"ES",
    "wof:name":"Zambrocinos",
    "wof:placetype":"locality"
},
  "geometry": {"coordinates":[-5.73905,42.29571],"type":"Point"}
}