{
  "type": "Feature",
  "properties": {
    "gn:admin1_code":"55",
    "gn:admin2_code":"LE",
    "gn:admin3_code":"24102",
    "gn:asciiname":"Cabanillas de San Justo",
    "gn:country_code":"ES",
    "gn:dem":855,
    "gn:feature_class":"P",
    "gn:feature_code":"PPL",
    "gn:name":"Cabanillas de San Justo",
    "gn:population":0,
    "gn:timezone":"Europe/Madrid",
    "iso:country":"ES",
    "wof:name":"Cabanillas de San Justo",
    "wof:placetype":"locality"
},
  "geometry": {"coordinates":[-6.34949,42.69313],"type":"Point"}
}