{
  "type": "Feature",
  "properties": {
    "gn:gn_country":"ES",
    "gn:gn_fcode":"PPL",
    "gn:gn_pop":0,
    "iso:country":"ES",
    "name:ast_x_preferred":[
        "Tarna"
    ],
    "name:spa_x_preferred":[
        "Tarna"
    ],
    "qs_pg:aaroncc":"ES",
    "qs_pg:gn_country":"ES",
    "qs_pg:gn_fcode":"PPL",
    "qs_pg:gn_pop":0,
    "qs_pg:name":"Tarna",
    "qs_pg:name_adm0":"Espa\u00f1a",
    "qs_pg:name_adm1":"Principado de Asturias",
    "qs_pg:photos":629,
    "qs_pg:photos_1k":127,
    "qs_pg:photos_9k":3,
    "qs_pg:photos_9r":5,
    "qs_pg:photos_all":629,
    "qs_pg:photos_sr":8,
    "qs_pg:pop_sr":0,
    "qs_pg:qs_pg_placetype":"locality",
    "qs_pg:qs_pg_placetype_gp":"Town",
    "qs_pg:woe_adm0":23424950,
    "woe:adm0_id":23424950,
    "woe:name_adm0":"Espa\u00f1a",
    "woe:name_adm1":"Principado de Asturias",
    "woe:placetype":"Town",
    "wof:name":"Tarna",
    "wof:placetype":"locality"
},
  "geometry": {"coordinates":[-5.22678,43.11038],"type":"Point"}
}