{
  "type": "Feature",
  "properties": {
    "gn:admin1_code":"58",
    "gn:admin2_code":"PO",
    "gn:admin3_code":"36017",
    "gn:asciiname":"Somoza",
    "gn:country_code":"ES",
    "gn:dem":307,
    "gn:feature_class":"P",
    "gn:feature_code":"PPL",
    "gn:name":"Somoza",
    "gn:population":0,
    "gn:timezone":"Europe/Madrid",
    "iso:country":"ES",
    "wof:name":"Somoza",
    "wof:placetype":"locality"
},
  "geometry": {"coordinates":[-8.48333,42.66667],"type":"Point"}
}