{
  "type": "Feature",
  "properties": {
    "gn:admin1_code":"51",
    "gn:admin2_code":"GR",
    "gn:admin3_code":"18192",
    "gn:asciiname":"El Almendral",
    "gn:country_code":"ES",
    "gn:dem":900,
    "gn:feature_class":"P",
    "gn:feature_code":"PPL",
    "gn:name":"El Almendral",
    "gn:population":0,
    "gn:timezone":"Europe/Madrid",
    "iso:country":"ES",
    "wof:name":"El Almendral",
    "wof:placetype":"locality"
},
  "geometry": {"coordinates":[-4.12782,36.98558],"type":"Point"}
}