{
  "type": "Feature",
  "properties": {
    "gn:gn_country":"ES",
    "gn:gn_fcode":"PPLA3",
    "gn:gn_pop":277,
    "gn:population":277,
    "iso:country":"ES",
    "name:arg_x_preferred":[
        "Matade\u00f3n de los Oteros"
    ],
    "name:cat_x_preferred":[
        "Matade\u00f3n de los Oteros"
    ],
    "name:deu_x_preferred":[
        "Matade\u00f3n de los Oteros"
    ],
    "name:eng_x_preferred":[
        "Matade\u00f3n de los Oteros"
    ],
    "name:eus_x_preferred":[
        "Matade\u00f3n de los Oteros"
    ],
    "name:fra_x_preferred":[
        "Matade\u00f3n de los Oteros"
    ],
    "name:glg_x_preferred":[
        "Matade\u00f3n de los Oteros"
    ],
    "name:haw_x_preferred":[
        "Matade\u00f3n de los Oteros"
    ],
    "name:hun_x_preferred":[
        "Matade\u00f3n de los Oteros"
    ],
    "name:ido_x_preferred":[
        "Matade\u00f3n de los Oteros"
    ],
    "name:ina_x_preferred":[
        "Matade\u00f3n de los Oteros"
    ],
    "name:ita_x_preferred":[
        "Matade\u00f3n de los Oteros"
    ],
    "name:msa_x_preferred":[
        "Matade\u00f3n de los Oteros"
    ],
    "name:nan_x_preferred":[
        "Matade\u00f3n de los Oteros"
    ],
    "name:nld_x_preferred":[
        "Matade\u00f3n de los Oteros"
    ],
    "name:oci_x_preferred":[
        "Matade\u00f3n de los Oteros"
    ],
    "name:pol_x_preferred":[
        "Matade\u00f3n de los Oteros"
    ],
    "name:por_x_preferred":[
        "Matade\u00f3n de los Oteros"
    ],
    "name:rus_x_preferred":[
        "\u041c\u0430\u0442\u0430\u0434\u0435\u043e\u043d-\u0434\u0435-\u043b\u043e\u0441-\u041e\u0442\u0435\u0440\u043e\u0441"
    ],
    "name:spa_x_preferred":[
        "Matade\u00f3n de los Oteros"
    ],
    "name:swe_x_preferred":[
        "Matade\u00f3n de los Oteros"
    ],
    "name:tpi_x_preferred":[
        "Matade\u00f3n de los Oteros"
    ],
    "name:ukr_x_preferred":[
        "\u041c\u0430\u0442\u0430\u0434\u0435\u043e\u043d-\u0434\u0435-\u043b\u043e\u0441-\u041e\u0442\u0435\u0440\u043e\u0441"
    ],
    "name:unk_x_variant":[
        "Matadeon"
    ],
    "name:vie_x_preferred":[
        "Matade\u00f3n de los Oteros"
    ],
    "name:war_x_preferred":[
        "Matade\u00f3n de los Oteros"
    ],
    "name:zho_x_preferred":[
        "\u9a6c\u5854\u5fb7\u7fc1\u5fb7\u6d1b\u7d22\u7279\u7f57\u65af"
    ],
    "qs_pg:aaroncc":"ES",
    "qs_pg:gn_country":"ES",
    "qs_pg:gn_fcode":"PPLA3",
    "qs_pg:gn_pop":277,
    "qs_pg:name":"Matade\u00f3n de Los Oteros",
    "qs_pg:name_adm0":"Espa\u00f1a",
    "qs_pg:name_adm1":"Castilla y Le\u00f3n",
    "qs_pg:photos":14,
    "qs_pg:photos_1k":3,
    "qs_pg:photos_9k":1,
    "qs_pg:photos_9r":1,
    "qs_pg:photos_all":14,
    "qs_pg:photos_sr":1,
    "qs_pg:pop_sr":2,
    "qs_pg:qs_pg_placetype":"locality",
    "qs_pg:qs_pg_placetype_gp":"Town",
    "qs_pg:woe_adm0":23424950,
    "woe:adm0_id":23424950,
    "woe:name_adm0":"Espa\u00f1a",
    "woe:name_adm1":"Castilla y Le\u00f3n",
    "woe:placetype":"Town",
    "wof:name":"Matade\u00f3n de Los Oteros",
    "wof:placetype":"locality",
    "wof:population":277
},
  "geometry": {"coordinates":[-5.36887,42.33776],"type":"Point"}
}