{
  "type": "Feature",
  "properties": {
    "gn:admin1_code":"34",
    "gn:admin2_code":"O",
    "gn:admin3_code":"33028",
    "gn:asciiname":"Alguerdo",
    "gn:country_code":"ES",
    "gn:dem":544,
    "gn:feature_class":"P",
    "gn:feature_code":"PPL",
    "gn:name":"Alguerdo",
    "gn:population":0,
    "gn:timezone":"Europe/Madrid",
    "iso:country":"ES",
    "wof:name":"Alguerdo",
    "wof:placetype":"locality"
},
  "geometry": {"coordinates":[-6.77605,42.98768],"type":"Point"}
}