{
  "type": "Feature",
  "properties": {
    "gn:country":"ES",
    "gn:fcode":"PPL",
    "gn:population":120,
    "iso:country":"ES",
    "name:arg_x_preferred":[
        "La Toba"
    ],
    "name:ast_x_preferred":[
        "La Toba"
    ],
    "name:cat_x_preferred":[
        "La Toba"
    ],
    "name:ceb_x_preferred":[
        "La Toba"
    ],
    "name:eng_x_preferred":[
        "La Toba"
    ],
    "name:epo_x_preferred":[
        "La Toba"
    ],
    "name:eus_x_preferred":[
        "La Toba"
    ],
    "name:fra_x_preferred":[
        "La Toba"
    ],
    "name:hun_x_preferred":[
        "La Toba"
    ],
    "name:ina_x_preferred":[
        "La Toba"
    ],
    "name:ita_x_preferred":[
        "La Toba"
    ],
    "name:kaz_x_preferred":[
        "\u041b\u0430-\u0422\u043e\u0431\u0430"
    ],
    "name:msa_x_preferred":[
        "La Toba"
    ],
    "name:nan_x_preferred":[
        "La Toba"
    ],
    "name:nld_x_preferred":[
        "La Toba"
    ],
    "name:oci_x_preferred":[
        "La Toba"
    ],
    "name:pol_x_preferred":[
        "La Toba"
    ],
    "name:por_x_preferred":[
        "La Toba"
    ],
    "name:rus_x_preferred":[
        "\u041b\u0430-\u0422\u043e\u0431\u0430"
    ],
    "name:spa_x_preferred":[
        "La Toba"
    ],
    "name:swe_x_preferred":[
        "La Toba"
    ],
    "name:ukr_x_preferred":[
        "\u041b\u0430-\u0422\u043e\u0431\u0430"
    ],
    "name:vie_x_preferred":[
        "La Toba"
    ],
    "name:war_x_preferred":[
        "La Toba"
    ],
    "name:zho_x_preferred":[
        "\u62c9\u6258\u74e6"
    ],
    "qs_pg:aaroncc":"ES",
    "qs_pg:gn_country":"ES",
    "qs_pg:gn_fcode":"PPL",
    "qs_pg:gn_pop":120,
    "qs_pg:name":"La Toba",
    "qs_pg:name_adm0":"Espa\u00f1a",
    "qs_pg:name_adm1":"Castilla-La Mancha",
    "qs_pg:photos":566,
    "qs_pg:photos_1k":115,
    "qs_pg:photos_9k":3,
    "qs_pg:photos_9r":5,
    "qs_pg:photos_all":566,
    "qs_pg:photos_sr":8,
    "qs_pg:pop_sr":1,
    "qs_pg:qs_pg_placetype":"locality",
    "qs_pg:qs_pg_placetype_gp":"Town",
    "qs_pg:woe_adm0":23424950,
    "woe:adm0_id":23424950,
    "woe:name_adm0":"Espa\u00f1a",
    "woe:name_adm1":"Castilla-La Mancha",
    "woe:placetype":"Town",
    "wof:name":"La Toba",
    "wof:placetype":"locality",
    "wof:population":120
},
  "geometry": {"coordinates":[-2.98012,41.00482],"type":"Point"}
}