{
  "type": "Feature",
  "properties": {
    "gn:gn_country":"ES",
    "gn:gn_fcode":"PPL",
    "gn:gn_pop":2433,
    "gn:population":2433,
    "iso:country":"ES",
    "name:unk_x_variant":[
        "Almudevar"
    ],
    "qs_pg:aaroncc":"ES",
    "qs_pg:gn_country":"ES",
    "qs_pg:gn_fcode":"PPL",
    "qs_pg:gn_pop":2433,
    "qs_pg:name":"Almud\u00e9bar",
    "qs_pg:photos_9r":0,
    "qs_pg:photos_sr":0,
    "qs_pg:pop_sr":4,
    "qs_pg:qs_pg_placetype":"locality",
    "wof:name":"Almud\u00e9bar",
    "wof:placetype":"locality",
    "wof:population":2433
},
  "geometry": {"coordinates":[-0.58141,42.04255],"type":"Point"}
}