{
  "type": "Feature",
  "properties": {
    "gn:admin1_code":"55",
    "gn:admin2_code":"SA",
    "gn:admin3_code":"37170.0",
    "gn:asciiname":"Muchachos",
    "gn:country_code":"ES",
    "gn:dem":791,
    "gn:feature_class":"P",
    "gn:feature_code":"PPL",
    "gn:name":"Muchachos",
    "gn:population":0,
    "gn:timezone":"Europe/Madrid",
    "iso:country":"ES",
    "wof:name":"Muchachos",
    "wof:placetype":"locality"
},
  "geometry": {"coordinates":[-5.97266,41.05262000000001],"type":"Point"}
}