{
  "type": "Feature",
  "properties": {
    "gn:country":"ES",
    "gn:fcode":"PPLA3",
    "gn:population":300,
    "iso:country":"ES",
    "name:arg_x_preferred":[
        "Lizo\u00e1in"
    ],
    "name:ast_x_preferred":[
        "Lizo\u00e1in-Arriasgoiti"
    ],
    "name:cat_x_preferred":[
        "Lintzoain"
    ],
    "name:ceb_x_preferred":[
        "Lizo\u00e1in-Arriasgoiti"
    ],
    "name:deu_x_preferred":[
        "Lizo\u00e1in"
    ],
    "name:eng_x_preferred":[
        "Lizo\u00e1in"
    ],
    "name:eus_x_preferred":[
        "Lizoainibar-Arriasgoiti"
    ],
    "name:fra_x_preferred":[
        "Lizo\u00e1in-Arriasgoiti"
    ],
    "name:hun_x_preferred":[
        "Lizo\u00e1in"
    ],
    "name:ita_x_preferred":[
        "Lizo\u00e1in"
    ],
    "name:jpn_x_preferred":[
        "\u30ea\u30bd\u30a2\u30a4\u30f3"
    ],
    "name:msa_x_preferred":[
        "Lizo\u00e1in"
    ],
    "name:nan_x_preferred":[
        "Lizo\u00e1in"
    ],
    "name:nld_x_preferred":[
        "Lizo\u00e1in-Arriasgoiti"
    ],
    "name:oci_x_preferred":[
        "Lizoainibar-Arriasgoiti"
    ],
    "name:pol_x_preferred":[
        "Lizo\u00e1in-Arriasgoiti"
    ],
    "name:por_x_preferred":[
        "Lizo\u00e1in-Arriasgoiti"
    ],
    "name:rus_x_preferred":[
        "\u041b\u0438\u0441\u043e\u0430\u0439\u043d"
    ],
    "name:spa_x_preferred":[
        "Lizo\u00e1in-Arriasgoiti"
    ],
    "name:swe_x_preferred":[
        "Lizo\u00e1in-Arriasgoiti"
    ],
    "name:ukr_x_preferred":[
        "\u041b\u0456\u0441\u043e\u0430\u0439\u043d"
    ],
    "name:uzb_x_preferred":[
        "Lizo\u00e1in"
    ],
    "name:vie_x_preferred":[
        "Lizo\u00e1in"
    ],
    "name:war_x_preferred":[
        "Lizo\u00e1in"
    ],
    "name:zho_x_preferred":[
        "\u5229\u7d22\u963f\u56e0-\u963f\u91cc\u4e9a\u65af\u6208\u4f0a\u8482"
    ],
    "qs_pg:aaroncc":"ES",
    "qs_pg:gn_country":"ES",
    "qs_pg:gn_fcode":"PPLA3",
    "qs_pg:gn_pop":300,
    "qs_pg:name":"Lizo\u00e1in",
    "qs_pg:name_adm0":"Espa\u00f1a",
    "qs_pg:name_adm1":"Comunidad Foral de Navarra",
    "qs_pg:photos_9k":1,
    "qs_pg:photos_9r":1,
    "qs_pg:photos_all":1,
    "qs_pg:photos_sr":0,
    "qs_pg:pop_sr":2,
    "qs_pg:qs_pg_placetype":"locality",
    "qs_pg:qs_pg_placetype_gp":"Town",
    "qs_pg:woe_adm0":23424950,
    "woe:adm0_id":23424950,
    "woe:name_adm0":"Espa\u00f1a",
    "woe:name_adm1":"Comunidad Foral de Navarra",
    "woe:placetype":"Town",
    "wof:name":"Lizo\u00e1in",
    "wof:placetype":"locality",
    "wof:population":300
},
  "geometry": {"coordinates":[-1.46753,42.79868],"type":"Point"}
}