{
  "type": "Feature",
  "properties": {
    "gn:admin1_code":"55",
    "gn:admin2_code":"LE",
    "gn:admin3_code":"24092",
    "gn:asciiname":"San Roman de los Caballeros",
    "gn:country_code":"ES",
    "gn:dem":915,
    "gn:feature_class":"P",
    "gn:feature_code":"PPL",
    "gn:name":"San Rom\u00e1n de los Caballeros",
    "gn:population":0,
    "gn:timezone":"Europe/Madrid",
    "iso:country":"ES",
    "name:und_x_variant":[
        "San Rom\u00e1n de los Caballeros"
    ],
    "wof:name":"San Roman de los Caballeros",
    "wof:placetype":"locality"
},
  "geometry": {"coordinates":[-5.84055,42.64823],"type":"Point"}
}