{
  "type": "Feature",
  "properties": {
    "gn:admin1_code":"34",
    "gn:admin2_code":"O",
    "gn:admin3_code":"33073",
    "gn:asciiname":"Llaneces de la Barca",
    "gn:country_code":"ES",
    "gn:dem":581,
    "gn:feature_class":"P",
    "gn:feature_code":"PPL",
    "gn:name":"Llaneces de la Barca",
    "gn:population":0,
    "gn:timezone":"Europe/Madrid",
    "iso:country":"ES",
    "wof:name":"Llaneces de la Barca",
    "wof:placetype":"locality"
},
  "geometry": {"coordinates":[-6.35392,43.30213],"type":"Point"}
}