{
  "type": "Feature",
  "properties": {
    "gn:admin1_code":"58",
    "gn:admin2_code":"C",
    "gn:admin3_code":"15056",
    "gn:asciiname":"Aro",
    "gn:country_code":"ES",
    "gn:dem":269,
    "gn:feature_class":"P",
    "gn:feature_code":"PPL",
    "gn:name":"Aro",
    "gn:population":0,
    "gn:timezone":"Europe/Madrid",
    "iso:country":"ES",
    "wof:name":"Aro",
    "wof:placetype":"locality"
},
  "geometry": {"coordinates":[-8.78954,42.90318],"type":"Point"}
}