{
  "type": "Feature",
  "properties": {
    "gn:admin1_code":"58",
    "gn:admin2_code":"C",
    "gn:admin3_code":"15056",
    "gn:asciiname":"Aro",
    "gn:country_code":"ES",
    "gn:dem":269,
    "gn:feature_class":"P",
    "gn:feature_code":"PPL",
    "gn:name":"Aro",
    "gn:population":0,
    "gn:timezone":"Europe/Madrid",
    "iso:country":"ES",
    "name:ceb_x_preferred":[
        "Aro"
    ],
    "name:epo_x_preferred":[
        "Aro"
    ],
    "name:eus_x_preferred":[
        "Aro"
    ],
    "name:fin_x_preferred":[
        "Aro"
    ],
    "name:fra_x_preferred":[
        "Aro"
    ],
    "name:glg_x_preferred":[
        "Aro"
    ],
    "name:hye_x_preferred":[
        "\u0531\u0580\u0578"
    ],
    "name:ind_x_preferred":[
        "Aro"
    ],
    "name:nld_x_preferred":[
        "Aro"
    ],
    "name:pol_x_preferred":[
        "Aro"
    ],
    "name:por_x_preferred":[
        "Aro"
    ],
    "name:ron_x_preferred":[
        "ARO"
    ],
    "name:rus_x_preferred":[
        "\u0410\u0440\u043e"
    ],
    "name:spa_x_preferred":[
        "Aro"
    ],
    "name:srp_x_preferred":[
        "\u0410\u0440\u043e"
    ],
    "name:swe_x_preferred":[
        "Aro"
    ],
    "name:ukr_x_preferred":[
        "\u0410\u0440\u043e"
    ],
    "wof:name":"Aro",
    "wof:placetype":"locality"
},
  "geometry": {"coordinates":[-8.78954,42.90318],"type":"Point"}
}