{
  "type": "Feature",
  "properties": {
    "gn:gn_country":"ES",
    "gn:gn_fcode":"PPLA3",
    "gn:gn_pop":247,
    "gn:population":247,
    "iso:country":"ES",
    "name:arg_x_historical":[
        "Biarche"
    ],
    "name:arg_x_preferred":[
        "Biarche"
    ],
    "name:baq_x_preferred":[
        "Bierge"
    ],
    "name:cat_x_preferred":[
        "Bierge"
    ],
    "name:chi_x_preferred":[
        "\u522b\u5c14\u8d6b"
    ],
    "name:dut_x_preferred":[
        "Bierge"
    ],
    "name:eng_x_preferred":[
        "Bierge"
    ],
    "name:fre_x_preferred":[
        "Bierge"
    ],
    "name:ger_x_preferred":[
        "Bierge"
    ],
    "name:hak_x_preferred":[
        "Bierge"
    ],
    "name:hun_x_preferred":[
        "Bierge"
    ],
    "name:ita_x_preferred":[
        "Bierge"
    ],
    "name:may_x_preferred":[
        "Bierge"
    ],
    "name:nan_x_preferred":[
        "Bierge"
    ],
    "name:oci_x_preferred":[
        "Bierge"
    ],
    "name:pol_x_preferred":[
        "Bierge"
    ],
    "name:por_x_preferred":[
        "Bierge"
    ],
    "name:rus_x_preferred":[
        "\u0411\u044c\u0435\u0440\u0445\u0435"
    ],
    "name:spa_x_preferred":[
        "Bierge"
    ],
    "name:swe_x_preferred":[
        "Bierge"
    ],
    "name:ukr_x_preferred":[
        "\u0411'\u0454\u0440\u0445\u0435"
    ],
    "name:uzb_x_preferred":[
        "Bierge"
    ],
    "name:vie_x_preferred":[
        "Bierge"
    ],
    "name:war_x_preferred":[
        "Bierge"
    ],
    "qs_pg:aaroncc":"ES",
    "qs_pg:gn_country":"ES",
    "qs_pg:gn_fcode":"PPLA3",
    "qs_pg:gn_pop":247,
    "qs_pg:name":"Bierge",
    "qs_pg:name_adm0":"Espa\u00f1a",
    "qs_pg:name_adm1":"Arag\u00f3n",
    "qs_pg:photos":247,
    "qs_pg:photos_1k":50,
    "qs_pg:photos_9k":1,
    "qs_pg:photos_9r":4,
    "qs_pg:photos_all":247,
    "qs_pg:photos_sr":4,
    "qs_pg:pop_sr":2,
    "qs_pg:qs_pg_placetype":"locality",
    "qs_pg:qs_pg_placetype_gp":"Town",
    "qs_pg:woe_adm0":23424950,
    "woe:adm0_id":23424950,
    "woe:name_adm0":"Espa\u00f1a",
    "woe:name_adm1":"Arag\u00f3n",
    "woe:placetype":"Town",
    "wof:name":"Bierge",
    "wof:placetype":"locality",
    "wof:population":247
},
  "geometry": {"coordinates":[-0.08326,42.16216],"type":"Point"}
}