{
  "type": "Feature",
  "properties": {
    "gn:country":"ES",
    "gn:fcode":"PPL",
    "gn:population":126,
    "iso:country":"ES",
    "name:cat_x_preferred":[
        "la Sorollera"
    ],
    "name:spa_x_preferred":[
        "Cerollera"
    ],
    "qs_pg:aaroncc":"ES",
    "qs_pg:gn_country":"ES",
    "qs_pg:gn_fcode":"PPL",
    "qs_pg:gn_pop":126,
    "qs_pg:name":"Cerollera",
    "qs_pg:photos_9r":0,
    "qs_pg:photos_sr":0,
    "qs_pg:pop_sr":1,
    "qs_pg:qs_pg_placetype":"locality",
    "wof:name":"Cerollera",
    "wof:placetype":"locality",
    "wof:population":126
},
  "geometry": {"coordinates":[-0.056,40.84033],"type":"Point"}
}