{
  "type": "Feature",
  "properties": {
    "gn:admin1_code":"60",
    "gn:admin2_code":"V",
    "gn:admin3_code":"46029",
    "gn:asciiname":"Reig",
    "gn:cc2":"ES",
    "gn:country_code":"ES",
    "gn:dem":22,
    "gn:feature_class":"P",
    "gn:feature_code":"PPL",
    "gn:name":"Reig",
    "gn:population":0,
    "gn:timezone":"Europe/Madrid",
    "iso:country":"ES",
    "name:und_x_variant":[
        "Caser\u00edo Reig",
        "Reig"
    ],
    "wof:name":"Reig",
    "wof:placetype":"locality"
},
  "geometry": {"coordinates":[-0.45,39.21667],"type":"Point"}
}