{
  "type": "Feature",
  "properties": {
    "iso:country":"ES",
    "name:eng_x_preferred":[
        "Hacienda Los Montes"
    ],
    "name:spa_x_preferred":[
        "Hacienda Los Montes"
    ],
    "wof:name":"Hacienda Los Montes",
    "wof:placetype":"neighbourhood"
},
  "geometry": {"coordinates":[-4.41643434297079,36.74764781813364],"type":"Point"}
}