{
  "type": "Feature",
  "properties": {
    "gn:admin1_code":"55",
    "gn:admin2_code":"LE",
    "gn:admin3_code":"24209",
    "gn:asciiname":"Veguellina",
    "gn:country_code":"ES",
    "gn:dem":656,
    "gn:feature_class":"P",
    "gn:feature_code":"PPL",
    "gn:name":"Veguellina",
    "gn:population":0,
    "gn:timezone":"Europe/Madrid",
    "iso:country":"ES",
    "wof:name":"Veguellina",
    "wof:placetype":"locality"
},
  "geometry": {"coordinates":[-6.7822,42.70347],"type":"Point"}
}