{
  "type": "Feature",
  "properties": {
    "gn:admin1_code":"55",
    "gn:admin2_code":"SO",
    "gn:admin3_code":"42022",
    "gn:asciiname":"Castejon del Campo",
    "gn:country_code":"ES",
    "gn:dem":1043,
    "gn:feature_class":"P",
    "gn:feature_code":"PPL",
    "gn:name":"Castej\u00f3n del Campo",
    "gn:population":0,
    "gn:timezone":"Europe/Madrid",
    "iso:country":"ES",
    "name:und_x_variant":[
        "Castej\u00f3n del Campo"
    ],
    "wof:name":"Castejon del Campo",
    "wof:placetype":"locality"
},
  "geometry": {"coordinates":[-2.14486,41.69102],"type":"Point"}
}