{
  "type": "Feature",
  "properties": {
    "gn:admin1_code":"34",
    "gn:admin2_code":"O",
    "gn:admin3_code":"33063",
    "gn:asciiname":"Eilale",
    "gn:country_code":"ES",
    "gn:dem":82,
    "gn:feature_class":"P",
    "gn:feature_code":"PPL",
    "gn:name":"Eilale",
    "gn:population":0,
    "gn:timezone":"Europe/Madrid",
    "iso:country":"ES",
    "wof:name":"Eilale",
    "wof:placetype":"locality"
},
  "geometry": {"coordinates":[-7.15072,43.40037],"type":"Point"}
}