{
  "type": "Feature",
  "properties": {
    "gn:admin1_code":"58",
    "gn:admin2_code":"LU",
    "gn:admin3_code":"27019",
    "gn:asciiname":"Ferreiravella",
    "gn:country_code":"ES",
    "gn:dem":147,
    "gn:feature_class":"P",
    "gn:feature_code":"PPL",
    "gn:name":"Ferreiravella",
    "gn:population":0,
    "gn:timezone":"Europe/Madrid",
    "iso:country":"ES",
    "wof:name":"Ferreiravella",
    "wof:placetype":"locality"
},
  "geometry": {"coordinates":[-7.31583,43.55408],"type":"Point"}
}