{
  "type": "Feature",
  "properties": {
    "iso:country":"ES",
    "name:eng_x_preferred":[
        "San Isidro"
    ],
    "name:spa_x_preferred":[
        "San Isidro"
    ],
    "wof:name":"San Isidro",
    "wof:placetype":"neighbourhood"
},
  "geometry": {"coordinates":[-4.36420540476404,36.72741515161696],"type":"Point"}
}