{
  "type": "Feature",
  "properties": {
    "iso:country":"ES",
    "name:eng_x_preferred":[
        "Colinas del Limonar"
    ],
    "name:spa_x_preferred":[
        "Colinas del Limonar"
    ],
    "wof:name":"Colinas del Limonar",
    "wof:placetype":"neighbourhood"
},
  "geometry": {"coordinates":[-4.39995484249159,36.73641385879134],"type":"Point"}
}