{
  "type": "Feature",
  "properties": {
    "gn:country":"ES",
    "gn:fcode":"PPLA3",
    "gn:population":191,
    "iso:country":"ES",
    "name:arg_x_preferred":[
        "Guadramiro"
    ],
    "name:ast_x_preferred":[
        "Guadramiru"
    ],
    "name:cat_x_preferred":[
        "Guadramiro"
    ],
    "name:eng_x_preferred":[
        "Guadramiro"
    ],
    "name:eus_x_preferred":[
        "Guadramiro"
    ],
    "name:fra_x_preferred":[
        "Guadramiro"
    ],
    "name:haw_x_preferred":[
        "Guadramiro"
    ],
    "name:hun_x_preferred":[
        "Guadramiro"
    ],
    "name:ina_x_preferred":[
        "Guadramiro"
    ],
    "name:ita_x_preferred":[
        "Guadramiro"
    ],
    "name:kaz_x_preferred":[
        "\u0413\u0432\u0430\u0434\u0440\u0430\u043c\u0438\u0440\u043e"
    ],
    "name:nan_x_preferred":[
        "Guadramiro"
    ],
    "name:nld_x_preferred":[
        "Guadramiro"
    ],
    "name:oci_x_preferred":[
        "Guadramiro"
    ],
    "name:pol_x_preferred":[
        "Guadramiro"
    ],
    "name:por_x_preferred":[
        "Guadramiro"
    ],
    "name:rus_x_preferred":[
        "\u0413\u0432\u0430\u0434\u0440\u0430\u043c\u0438\u0440\u043e"
    ],
    "name:spa_x_preferred":[
        "Guadramiro"
    ],
    "name:sqi_x_preferred":[
        "Guadramiro"
    ],
    "name:ukr_x_preferred":[
        "\u0413\u0443\u0430\u0434\u0440\u0430\u043c\u0456\u0440\u043e"
    ],
    "name:uzb_x_preferred":[
        "Guadramiro"
    ],
    "name:war_x_preferred":[
        "Guadramiro"
    ],
    "name:zho_x_preferred":[
        "\u74dc\u5fb7\u62c9\u7c73\u7f57"
    ],
    "qs_pg:aaroncc":"ES",
    "qs_pg:gn_country":"ES",
    "qs_pg:gn_fcode":"PPLA3",
    "qs_pg:gn_pop":191,
    "qs_pg:name":"Guadramiro",
    "qs_pg:name_adm0":"Espa\u00f1a",
    "qs_pg:name_adm1":"Castilla y Le\u00f3n",
    "qs_pg:photos_9r":0,
    "qs_pg:photos_sr":0,
    "qs_pg:pop_sr":1,
    "qs_pg:qs_pg_placetype":"locality",
    "qs_pg:qs_pg_placetype_gp":"Town",
    "qs_pg:woe_adm0":23424950,
    "woe:adm0_id":23424950,
    "woe:name_adm0":"Espa\u00f1a",
    "woe:name_adm1":"Castilla y Le\u00f3n",
    "woe:placetype":"Town",
    "wof:name":"Guadramiro",
    "wof:placetype":"locality",
    "wof:population":191
},
  "geometry": {"coordinates":[-6.49369,41.01703],"type":"Point"}
}