{
  "type": "Feature",
  "properties": {
    "gn:gn_country":"ES",
    "gn:gn_fcode":"PPL",
    "gn:gn_pop":381,
    "gn:population":381,
    "iso:country":"ES",
    "name:arg_x_preferred":[
        "Rionegro del Puente"
    ],
    "name:cat_x_preferred":[
        "Rionegro del Puente"
    ],
    "name:ceb_x_preferred":[
        "R\u00edonegro del Puente"
    ],
    "name:eng_x_preferred":[
        "Rionegro del Puente"
    ],
    "name:eus_x_preferred":[
        "Rionegro del Puente"
    ],
    "name:fra_x_preferred":[
        "Rionegro del Puente"
    ],
    "name:haw_x_preferred":[
        "Rionegro del Puente"
    ],
    "name:hun_x_preferred":[
        "Rionegro del Puente"
    ],
    "name:ile_x_preferred":[
        "Rionegro del Puente"
    ],
    "name:ina_x_preferred":[
        "Rionegro del Puente"
    ],
    "name:ita_x_preferred":[
        "Rionegro del Puente"
    ],
    "name:msa_x_preferred":[
        "Rionegro del Puente"
    ],
    "name:nan_x_preferred":[
        "Rionegro del Puente"
    ],
    "name:nld_x_preferred":[
        "Rionegro del Puente"
    ],
    "name:nob_x_preferred":[
        "Rionegro del Puente"
    ],
    "name:oci_x_preferred":[
        "Rionegro del Puente"
    ],
    "name:pol_x_preferred":[
        "Rionegro del Puente"
    ],
    "name:por_x_preferred":[
        "Rionegro del Puente"
    ],
    "name:rus_x_preferred":[
        "\u0420\u0438\u043e\u043d\u0435\u0433\u0440\u043e-\u0434\u0435\u043b\u044c-\u041f\u0443\u044d\u043d\u0442\u0435"
    ],
    "name:spa_x_preferred":[
        "Rionegro del Puente"
    ],
    "name:swe_x_preferred":[
        "R\u00edonegro del Puente"
    ],
    "name:ukr_x_preferred":[
        "\u0420\u0456\u043e\u043d\u0435\u0433\u0440\u043e-\u0434\u0435\u043b\u044c-\u041f\u0443\u0435\u043d\u0442\u0435"
    ],
    "name:unk_x_variant":[
        "R\u00edonegro del Puente"
    ],
    "name:vie_x_preferred":[
        "Rionegro del Puente"
    ],
    "name:war_x_preferred":[
        "Rionegro del Puente"
    ],
    "name:zho_x_preferred":[
        "\u91cc\u5965\u5185\u683c\u7f57\u5fb7\u5c14\u84ec\u7279"
    ],
    "qs_pg:aaroncc":"ES",
    "qs_pg:gn_country":"ES",
    "qs_pg:gn_fcode":"PPL",
    "qs_pg:gn_pop":381,
    "qs_pg:name":"Rionegro del Puente",
    "qs_pg:name_adm0":"Espa\u00f1a",
    "qs_pg:name_adm1":"Castilla y Le\u00f3n",
    "qs_pg:photos":15,
    "qs_pg:photos_1k":3,
    "qs_pg:photos_9k":1,
    "qs_pg:photos_9r":1,
    "qs_pg:photos_all":15,
    "qs_pg:photos_sr":1,
    "qs_pg:pop_sr":2,
    "qs_pg:qs_pg_placetype":"locality",
    "qs_pg:qs_pg_placetype_gp":"Town",
    "qs_pg:woe_adm0":23424950,
    "woe:adm0_id":23424950,
    "woe:name_adm0":"Espa\u00f1a",
    "woe:name_adm1":"Castilla y Le\u00f3n",
    "woe:placetype":"Town",
    "wof:name":"Rionegro del Puente",
    "wof:placetype":"locality",
    "wof:population":381
},
  "geometry": {"coordinates":[-6.22789,42.00489],"type":"Point"}
}