{
  "type": "Feature",
  "properties": {
    "gn:admin1_code":"34",
    "gn:admin2_code":"O",
    "gn:admin3_code":"33038",
    "gn:asciiname":"Corras de la Puente",
    "gn:country_code":"ES",
    "gn:dem":247,
    "gn:feature_class":"P",
    "gn:feature_code":"PPL",
    "gn:name":"Corras de la Puente",
    "gn:population":0,
    "gn:timezone":"Europe/Madrid",
    "iso:country":"ES",
    "wof:name":"Corras de la Puente",
    "wof:placetype":"locality"
},
  "geometry": {"coordinates":[-5.86854,43.25948],"type":"Point"}
}