{
  "type": "Feature",
  "properties": {
    "gn:gn_country":"ES",
    "gn:gn_fcode":"PPL",
    "gn:gn_pop":0,
    "iso:country":"ES",
    "name:cat_x_preferred":[
        "Arroyo"
    ],
    "name:ceb_x_preferred":[
        "Arroyo"
    ],
    "name:deu_x_preferred":[
        "Arroyo"
    ],
    "name:fra_x_preferred":[
        "Arroyo"
    ],
    "name:heb_x_preferred":[
        "\u05d0\u05e8\u05d5\u05d9\u05d5"
    ],
    "name:ita_x_preferred":[
        "Arroyo"
    ],
    "name:jpn_x_preferred":[
        "\u30a2\u30ed\u30e8"
    ],
    "name:kor_x_preferred":[
        "\uc544\ub85c\uc694"
    ],
    "name:nld_x_preferred":[
        "Arroyo"
    ],
    "name:pol_x_preferred":[
        "Arroyo"
    ],
    "name:por_x_preferred":[
        "Arroyo"
    ],
    "name:rus_x_preferred":[
        "\u0410\u0440\u0440\u043e\u0439\u043e"
    ],
    "name:slk_x_preferred":[
        "Arroyo"
    ],
    "name:slv_x_preferred":[
        "Arroyo"
    ],
    "name:spa_x_preferred":[
        "Arroyo"
    ],
    "name:swe_x_preferred":[
        "Arroyo"
    ],
    "qs_pg:aaroncc":"ES",
    "qs_pg:gn_country":"ES",
    "qs_pg:gn_fcode":"PPL",
    "qs_pg:gn_pop":0,
    "qs_pg:name":"Arroyo",
    "qs_pg:name_adm0":"Espa\u00f1a",
    "qs_pg:name_adm1":"Cantabria",
    "qs_pg:photos":20,
    "qs_pg:photos_1k":4,
    "qs_pg:photos_9k":1,
    "qs_pg:photos_9r":1,
    "qs_pg:photos_all":20,
    "qs_pg:photos_sr":1,
    "qs_pg:pop_sr":0,
    "qs_pg:qs_pg_placetype":"locality",
    "qs_pg:qs_pg_placetype_gp":"Town",
    "qs_pg:woe_adm0":23424950,
    "woe:adm0_id":23424950,
    "woe:name_adm0":"Espa\u00f1a",
    "woe:name_adm1":"Cantabria",
    "woe:placetype":"Town",
    "wof:name":"Arroyo",
    "wof:placetype":"locality"
},
  "geometry": {"coordinates":[-4.0542,42.97286],"type":"Point"}
}