{
  "type": "Feature",
  "properties": {
    "gn:admin1_code":"55",
    "gn:admin2_code":"SG",
    "gn:admin3_code":"40063",
    "gn:asciiname":"Lovingos",
    "gn:country_code":"ES",
    "gn:dem":854,
    "gn:feature_class":"P",
    "gn:feature_code":"PPL",
    "gn:name":"Lovingos",
    "gn:population":0,
    "gn:timezone":"Europe/Madrid",
    "iso:country":"ES",
    "wof:name":"Lovingos",
    "wof:placetype":"locality"
},
  "geometry": {"coordinates":[-4.22294,41.40672],"type":"Point"}
}