{
  "type": "Feature",
  "properties": {
    "gn:country":"ES",
    "gn:fcode":"PPLA3",
    "gn:population":1538,
    "iso:country":"ES",
    "name:arg_x_preferred":[
        "Fuentes de O\u00f1oro"
    ],
    "name:cat_x_preferred":[
        "Fuentes de O\u00f1oro"
    ],
    "name:deu_x_preferred":[
        "Fuentes de O\u00f1oro"
    ],
    "name:eng_x_preferred":[
        "Fuentes de O\u00f1oro"
    ],
    "name:eus_x_preferred":[
        "Fuentes de O\u00f1oro"
    ],
    "name:fra_x_preferred":[
        "Fuentes de O\u00f1oro"
    ],
    "name:glg_x_preferred":[
        "Fuentes de O\u00f1oro"
    ],
    "name:haw_x_preferred":[
        "Fuentes de O\u00f1oro"
    ],
    "name:hun_x_preferred":[
        "Fuentes de O\u00f1oro"
    ],
    "name:ina_x_preferred":[
        "Fuentes de O\u00f1oro"
    ],
    "name:ita_x_preferred":[
        "Fuentes de O\u00f1oro"
    ],
    "name:jpn_x_preferred":[
        "\u30d5\u30a8\u30f3\u30c6\u30b9\u30fb\u30c7\u30fb\u30aa\u30cb\u30e7\u30ed\u306e\u6226\u3044"
    ],
    "name:kaz_x_preferred":[
        "\u0424\u0443\u044d\u043d\u0442\u0435\u0441-\u0434\u0435-\u041e\u043d\u044c\u043e\u0440\u043e"
    ],
    "name:msa_x_preferred":[
        "Fuentes de O\u00f1oro"
    ],
    "name:nan_x_preferred":[
        "Fuentes de O\u00f1oro"
    ],
    "name:nld_x_preferred":[
        "Fuentes de O\u00f1oro"
    ],
    "name:oci_x_preferred":[
        "Fuentes de O\u00f1oro"
    ],
    "name:pol_x_preferred":[
        "Fuentes de O\u00f1oro"
    ],
    "name:por_x_preferred":[
        "Fontes de Onor"
    ],
    "name:rus_x_preferred":[
        "\u0424\u0443\u044d\u043d\u0442\u0435\u0441-\u0434\u0435-\u041e\u043d\u044c\u043e\u0440\u043e"
    ],
    "name:spa_x_preferred":[
        "Fuentes de O\u00f1oro"
    ],
    "name:swe_x_preferred":[
        "Fuentes de O\u00f1oro"
    ],
    "name:ukr_x_preferred":[
        "\u0424\u0443\u0435\u043d\u0442\u0435\u0441-\u0434\u0435-\u041e\u043d\u044c\u0439\u043e\u0440\u043e"
    ],
    "name:vie_x_preferred":[
        "Fuentes de O\u00f1oro"
    ],
    "name:war_x_preferred":[
        "Fuentes de O\u00f1oro"
    ],
    "name:zho_x_preferred":[
        "\u4e30\u7279\u65af\u5fb7\u5965\u5c3c\u5965\u7f57"
    ],
    "qs_pg:aaroncc":"ES",
    "qs_pg:gn_country":"ES",
    "qs_pg:gn_fcode":"PPLA3",
    "qs_pg:gn_pop":1538,
    "qs_pg:name":"Fuentes de O\u00f1oro",
    "qs_pg:name_adm0":"Espa\u00f1a",
    "qs_pg:name_adm1":"Castilla y Le\u00f3n",
    "qs_pg:photos":14,
    "qs_pg:photos_1k":3,
    "qs_pg:photos_9k":1,
    "qs_pg:photos_9r":1,
    "qs_pg:photos_all":14,
    "qs_pg:photos_sr":1,
    "qs_pg:pop_sr":3,
    "qs_pg:qs_pg_placetype":"locality",
    "qs_pg:qs_pg_placetype_gp":"Town",
    "qs_pg:woe_adm0":23424950,
    "woe:adm0_id":23424950,
    "woe:name_adm0":"Espa\u00f1a",
    "woe:name_adm1":"Castilla y Le\u00f3n",
    "woe:placetype":"Town",
    "wof:name":"Fuentes de O\u00f1oro",
    "wof:placetype":"locality",
    "wof:population":1538
},
  "geometry": {"coordinates":[-6.81144,40.59102],"type":"Point"}
}