{
  "type": "Feature",
  "properties": {
    "iso:country":"ES",
    "name:eng_x_preferred":[
        "Poligono Haza Angosta"
    ],
    "name:spa_x_preferred":[
        "Pol\u00edgono Haza Angosta"
    ],
    "wof:name":"Poligono Haza Angosta",
    "wof:placetype":"neighbourhood"
},
  "geometry": {"coordinates":[-4.46728905148084,36.68390197071295],"type":"Point"}
}