{
  "type": "Feature",
  "properties": {
    "gn:admin1_code":"58",
    "gn:admin2_code":"C",
    "gn:admin3_code":"15092",
    "gn:asciiname":"Berdoyas",
    "gn:country_code":"ES",
    "gn:dem":234,
    "gn:feature_class":"P",
    "gn:feature_code":"PPL",
    "gn:name":"Berdoyas",
    "gn:population":0,
    "gn:timezone":"Europe/Madrid",
    "iso:country":"ES",
    "wof:name":"Berdoyas",
    "wof:placetype":"locality"
},
  "geometry": {"coordinates":[-9.08503,43.05703],"type":"Point"}
}