{
  "type": "Feature",
  "properties": {
    "gn:admin1_code":"59",
    "gn:admin2_code":"BI",
    "gn:admin3_code":"48080",
    "gn:asciiname":"Galindo-Salcedillo",
    "gn:country_code":"ES",
    "gn:dem":0,
    "gn:feature_class":"P",
    "gn:feature_code":"PPL",
    "gn:name":"Galindo-Salcedillo",
    "gn:population":0,
    "gn:timezone":"Europe/Madrid",
    "iso:country":"ES",
    "wof:name":"Galindo-Salcedillo",
    "wof:placetype":"locality"
},
  "geometry": {"coordinates":[-2.99532,43.30488],"type":"Point"}
}