{
  "type": "Feature",
  "properties": {
    "gn:admin1_code":"34",
    "gn:admin2_code":"O",
    "gn:admin3_code":"33018",
    "gn:asciiname":"Villar",
    "gn:country_code":"ES",
    "gn:dem":133,
    "gn:feature_class":"P",
    "gn:feature_code":"PPL",
    "gn:name":"Villar",
    "gn:population":0,
    "gn:timezone":"Europe/Madrid",
    "iso:country":"ES",
    "name:arg_x_preferred":[
        "Villar"
    ],
    "name:ast_x_preferred":[
        "Villar"
    ],
    "name:ceb_x_preferred":[
        "Villar"
    ],
    "name:deu_x_preferred":[
        "Villar"
    ],
    "name:fra_x_preferred":[
        "Villar"
    ],
    "name:ita_x_preferred":[
        "Villar"
    ],
    "name:jpn_x_preferred":[
        "\u30d3\u30b8\u30e3\u30fc\u30eb"
    ],
    "name:nld_x_preferred":[
        "Villar"
    ],
    "name:por_x_preferred":[
        "Villar"
    ],
    "name:rus_x_preferred":[
        "\u0412\u0438\u043b\u044c\u044f\u0440"
    ],
    "name:sco_x_preferred":[
        "Villar"
    ],
    "name:spa_x_preferred":[
        "Villar"
    ],
    "name:srp_x_preferred":[
        "Vilar"
    ],
    "name:swe_x_preferred":[
        "Villar"
    ],
    "wof:name":"Villar",
    "wof:placetype":"locality"
},
  "geometry": {"coordinates":[-6.74347,43.48999],"type":"Point"}
}