{
  "type": "Feature",
  "properties": {
    "gn:admin1_code":"34",
    "gn:admin2_code":"O",
    "gn:admin3_code":"33018",
    "gn:asciiname":"Villar",
    "gn:country_code":"ES",
    "gn:dem":133,
    "gn:feature_class":"P",
    "gn:feature_code":"PPL",
    "gn:name":"Villar",
    "gn:population":0,
    "gn:timezone":"Europe/Madrid",
    "iso:country":"ES",
    "wof:name":"Villar",
    "wof:placetype":"locality"
},
  "geometry": {"coordinates":[-6.74347,43.48999],"type":"Point"}
}