{
  "type": "Feature",
  "properties": {
    "gn:admin1_code":"55",
    "gn:admin2_code":"AV",
    "gn:admin3_code":"05046",
    "gn:asciiname":"Canales",
    "gn:country_code":"ES",
    "gn:dem":857,
    "gn:feature_class":"P",
    "gn:feature_code":"PPLA3",
    "gn:name":"Canales",
    "gn:population":54,
    "gn:timezone":"Europe/Madrid",
    "iso:country":"ES",
    "name:ara_x_preferred":[
        "\u0643\u0627\u0646\u0627\u0644\u064a\u0633"
    ],
    "name:cat_x_preferred":[
        "Canales"
    ],
    "name:eus_x_preferred":[
        "Canales"
    ],
    "name:fas_x_preferred":[
        "\u06a9\u0627\u0646\u0627\u0644\u0633"
    ],
    "name:fra_x_preferred":[
        "Canales"
    ],
    "name:hun_x_preferred":[
        "Canales"
    ],
    "name:ina_x_preferred":[
        "Canales"
    ],
    "name:ita_x_preferred":[
        "Canales"
    ],
    "name:kaz_x_preferred":[
        "\u041a\u0430\u043d\u0430\u043b\u0435\u0441"
    ],
    "name:mkd_x_preferred":[
        "\u041a\u0430\u043d\u0430\u043b\u0435\u0441"
    ],
    "name:msa_x_preferred":[
        "Canales"
    ],
    "name:nld_x_preferred":[
        "Canales"
    ],
    "name:oci_x_preferred":[
        "Canales"
    ],
    "name:pol_x_preferred":[
        "Canales"
    ],
    "name:por_x_preferred":[
        "Canales"
    ],
    "name:rus_x_preferred":[
        "\u041a\u0430\u043d\u0430\u043b\u0435\u0441"
    ],
    "name:spa_x_preferred":[
        "Canales"
    ],
    "name:ukr_x_preferred":[
        "\u041a\u0430\u043d\u0430\u043b\u0435\u0441"
    ],
    "name:uzb_x_preferred":[
        "Canales"
    ],
    "name:vie_x_preferred":[
        "Canales"
    ],
    "name:war_x_preferred":[
        "Canales"
    ],
    "name:zho_x_preferred":[
        "\u5361\u7eb3\u83b1\u65af"
    ],
    "wof:name":"Canales",
    "wof:placetype":"locality",
    "wof:population":54
},
  "geometry": {"coordinates":[-4.90163,41.00331],"type":"Point"}
}