{
  "type": "Feature",
  "properties": {
    "gn:admin1_code":"55",
    "gn:admin2_code":"AV",
    "gn:admin3_code":"05046",
    "gn:asciiname":"Canales",
    "gn:country_code":"ES",
    "gn:dem":857,
    "gn:feature_class":"P",
    "gn:feature_code":"PPLA3",
    "gn:name":"Canales",
    "gn:population":54,
    "gn:timezone":"Europe/Madrid",
    "iso:country":"ES",
    "wof:name":"Canales",
    "wof:placetype":"locality",
    "wof:population":54
},
  "geometry": {"coordinates":[-4.90163,41.00331],"type":"Point"}
}