{
  "type": "Feature",
  "properties": {
    "gn:admin1_code":"56",
    "gn:admin2_code":"GI",
    "gn:admin3_code":"17210",
    "gn:asciiname":"Saldet",
    "gn:country_code":"ES",
    "gn:dem":8,
    "gn:feature_class":"P",
    "gn:feature_code":"PPL",
    "gn:name":"Saldet",
    "gn:population":0,
    "gn:timezone":"Europe/Madrid",
    "iso:country":"ES",
    "name:cat_x_preferred":[
        "Saldet"
    ],
    "wof:name":"Saldet",
    "wof:placetype":"locality"
},
  "geometry": {"coordinates":[3.06276,42.17091],"type":"Point"}
}