{
  "type": "Feature",
  "properties": {
    "gn:admin1_code":"56",
    "gn:admin2_code":"GI",
    "gn:admin3_code":"17210",
    "gn:asciiname":"els Masos de Ventallo",
    "gn:country_code":"ES",
    "gn:dem":35,
    "gn:feature_class":"P",
    "gn:feature_code":"PPL",
    "gn:name":"els Masos de Ventall\u00f3",
    "gn:population":0,
    "gn:timezone":"Europe/Madrid",
    "iso:country":"ES",
    "name:cat_x_preferred":[
        "els Masos de Ventall\u00f3"
    ],
    "wof:name":"els Masos de Ventallo",
    "wof:placetype":"locality"
},
  "geometry": {"coordinates":[3.02158,42.14974],"type":"Point"}
}