{
  "type": "Feature",
  "properties": {
    "gn:admin1_code":"59",
    "gn:admin2_code":"SS",
    "gn:admin3_code":"20023",
    "gn:asciiname":"Berrobi",
    "gn:country_code":"ES",
    "gn:dem":155,
    "gn:feature_class":"P",
    "gn:feature_code":"PPLA3",
    "gn:name":"Berrobi",
    "gn:population":575,
    "gn:timezone":"Europe/Madrid",
    "iso:country":"ES",
    "name:ara_x_preferred":[
        "\u0628\u064a\u0631\u0648\u0628\u064a"
    ],
    "name:arg_x_preferred":[
        "Berrobi"
    ],
    "name:ast_x_preferred":[
        "Berrobi"
    ],
    "name:bre_x_preferred":[
        "Berrobi"
    ],
    "name:cat_x_preferred":[
        "Berrobi"
    ],
    "name:ceb_x_preferred":[
        "Berrobi"
    ],
    "name:eng_x_preferred":[
        "Berrobi"
    ],
    "name:eus_x_preferred":[
        "Berrobi"
    ],
    "name:fra_x_preferred":[
        "Berrobi"
    ],
    "name:glg_x_preferred":[
        "Berrobi"
    ],
    "name:hun_x_preferred":[
        "Berrobi"
    ],
    "name:ita_x_preferred":[
        "Berrobi"
    ],
    "name:msa_x_preferred":[
        "Berrobi"
    ],
    "name:nld_x_preferred":[
        "Berrobi"
    ],
    "name:oci_x_preferred":[
        "Berrobi"
    ],
    "name:pol_x_preferred":[
        "Berrobi"
    ],
    "name:por_x_preferred":[
        "Berrobi"
    ],
    "name:rus_x_preferred":[
        "\u0411\u0435\u0440\u0440\u043e\u0431\u0438"
    ],
    "name:sco_x_preferred":[
        "Berrobi"
    ],
    "name:spa_x_preferred":[
        "Berrobi"
    ],
    "name:swe_x_preferred":[
        "Berrobi"
    ],
    "name:ukr_x_preferred":[
        "\u0411\u0435\u0440\u0440\u043e\u0431\u0456"
    ],
    "name:uzb_x_preferred":[
        "Berrobi"
    ],
    "name:vie_x_preferred":[
        "Berrobi"
    ],
    "name:war_x_preferred":[
        "Berrobi"
    ],
    "name:zho_x_preferred":[
        "\u8d1d\u7f57\u7ef4"
    ],
    "wof:name":"Berrobi",
    "wof:placetype":"locality",
    "wof:population":575
},
  "geometry": {"coordinates":[-2.02623,43.14518],"type":"Point"}
}