{
  "type": "Feature",
  "properties": {
    "gn:admin1_code":"59",
    "gn:admin2_code":"SS",
    "gn:admin3_code":"20023",
    "gn:asciiname":"Berrobi",
    "gn:country_code":"ES",
    "gn:dem":155,
    "gn:feature_class":"P",
    "gn:feature_code":"PPLA3",
    "gn:name":"Berrobi",
    "gn:population":575,
    "gn:timezone":"Europe/Madrid",
    "iso:country":"ES",
    "name:ast_x_preferred":[
        "Berrobi"
    ],
    "name:eng_x_preferred":[
        "Berrobi"
    ],
    "name:eus_x_preferred":[
        "Berrobi"
    ],
    "name:ita_x_preferred":[
        "Berrobi"
    ],
    "name:nld_x_preferred":[
        "Berrobi"
    ],
    "name:por_x_preferred":[
        "Berrobi"
    ],
    "name:spa_x_preferred":[
        "Berrobi"
    ],
    "wof:name":"Berrobi",
    "wof:placetype":"locality",
    "wof:population":575
},
  "geometry": {"coordinates":[-2.02623,43.14518],"type":"Point"}
}