{
  "type": "Feature",
  "properties": {
    "gn:admin1_code":"55",
    "gn:admin2_code":"LE",
    "gn:admin3_code":"24109",
    "gn:asciiname":"Cuevas del Sil",
    "gn:country_code":"ES",
    "gn:dem":893,
    "gn:feature_class":"P",
    "gn:feature_code":"PPL",
    "gn:name":"Cuevas del Sil",
    "gn:population":0,
    "gn:timezone":"Europe/Madrid",
    "iso:country":"ES",
    "wof:name":"Cuevas del Sil",
    "wof:placetype":"locality"
},
  "geometry": {"coordinates":[-6.39176,42.89336],"type":"Point"}
}