{
  "type": "Feature",
  "properties": {
    "gn:admin1_code":"55",
    "gn:admin2_code":"SA",
    "gn:admin3_code":"37192",
    "gn:asciiname":"Aldeagallega",
    "gn:country_code":"ES",
    "gn:dem":843,
    "gn:feature_class":"P",
    "gn:feature_code":"PPL",
    "gn:name":"Aldeagallega",
    "gn:population":0,
    "gn:timezone":"Europe/Madrid",
    "iso:country":"ES",
    "wof:name":"Aldeagallega",
    "wof:placetype":"locality"
},
  "geometry": {"coordinates":[-5.72097,40.87804000000001],"type":"Point"}
}