{
  "type": "Feature",
  "properties": {
    "gn:gn_country":"ES",
    "gn:gn_fcode":"PPLA3",
    "gn:gn_pop":247,
    "gn:population":247,
    "iso:country":"ES",
    "name:arg_x_preferred":[
        "Muelas de los Caballeros"
    ],
    "name:baq_x_preferred":[
        "Muelas de los Caballeros"
    ],
    "name:cat_x_preferred":[
        "Muelas de los Caballeros"
    ],
    "name:chi_x_preferred":[
        "\u7a46\u57c3\u62c9\u65af\u5fb7\u6d1b\u65af\u5361\u74e6\u5217\u7f57\u65af"
    ],
    "name:dut_x_preferred":[
        "Muelas de los Caballeros"
    ],
    "name:eng_x_preferred":[
        "Muelas de los Caballeros"
    ],
    "name:fre_x_preferred":[
        "Muelas de los Caballeros"
    ],
    "name:haw_x_preferred":[
        "Muelas de los Caballeros"
    ],
    "name:hun_x_preferred":[
        "Muelas de los Caballeros"
    ],
    "name:ile_x_preferred":[
        "Muelas de los Caballeros"
    ],
    "name:ina_x_preferred":[
        "Muelas de los Caballeros"
    ],
    "name:ita_x_preferred":[
        "Muelas de los Caballeros"
    ],
    "name:may_x_preferred":[
        "Muelas de los Caballeros"
    ],
    "name:nan_x_preferred":[
        "Muelas de los Caballeros"
    ],
    "name:oci_x_preferred":[
        "Muelas de los Caballeros"
    ],
    "name:por_x_preferred":[
        "Muelas de los Caballeros"
    ],
    "name:rus_x_preferred":[
        "\u041c\u0443\u044d\u043b\u0430\u0441-\u0434\u0435-\u043b\u043e\u0441-\u041a\u0430\u0431\u0430\u043b\u044c\u0435\u0440\u043e\u0441"
    ],
    "name:spa_x_preferred":[
        "Muelas de los Caballeros"
    ],
    "name:swe_x_preferred":[
        "Muelas de los Caballeros"
    ],
    "name:ukr_x_preferred":[
        "\u041c\u0443\u0435\u043b\u0430\u0441-\u0434\u0435-\u043b\u043e\u0441-\u041a\u0430\u0431\u0430\u043b\u044c\u0454\u0440\u043e\u0441"
    ],
    "name:unk_x_variant":[
        "Muelas de los Caballeros"
    ],
    "name:vie_x_preferred":[
        "Muelas de los Caballeros"
    ],
    "name:war_x_preferred":[
        "Muelas de los Caballeros"
    ],
    "qs_pg:aaroncc":"ES",
    "qs_pg:gn_country":"ES",
    "qs_pg:gn_fcode":"PPLA3",
    "qs_pg:gn_pop":247,
    "qs_pg:name":"Muelas de Los Caballeros",
    "qs_pg:name_adm0":"Espa\u00f1a",
    "qs_pg:name_adm1":"Castilla y Le\u00f3n",
    "qs_pg:photos":3,
    "qs_pg:photos_1k":1,
    "qs_pg:photos_9k":1,
    "qs_pg:photos_9r":1,
    "qs_pg:photos_all":3,
    "qs_pg:photos_sr":1,
    "qs_pg:pop_sr":2,
    "qs_pg:qs_pg_placetype":"locality",
    "qs_pg:qs_pg_placetype_gp":"Town",
    "qs_pg:woe_adm0":23424950,
    "woe:adm0_id":23424950,
    "woe:name_adm0":"Espa\u00f1a",
    "woe:name_adm1":"Castilla y Le\u00f3n",
    "woe:placetype":"Town",
    "wof:name":"Muelas de Los Caballeros",
    "wof:placetype":"locality",
    "wof:population":247
},
  "geometry": {"coordinates":[-6.33719,42.12843],"type":"Point"}
}