{
  "type": "Feature",
  "properties": {
    "gn:country":"ES",
    "gn:fcode":"PPLA3",
    "gn:population":80,
    "iso:country":"ES",
    "name:ara_x_preferred":[
        "\u0641\u064a\u0627\u0646\u0648\u064a\u0641\u0627 \u062f\u064a \u062e\u064a\u0644\u0648\u0643\u0627"
    ],
    "name:arg_x_preferred":[
        "Villanueva de Xiloca"
    ],
    "name:cat_x_preferred":[
        "Villanueva de Jiloca"
    ],
    "name:eng_x_preferred":[
        "Villanueva de Jiloca"
    ],
    "name:eus_x_preferred":[
        "Villanueva de Jiloca"
    ],
    "name:fra_x_preferred":[
        "Villanueva de Jiloca"
    ],
    "name:hun_x_preferred":[
        "Villanueva de Jiloca"
    ],
    "name:hye_x_preferred":[
        "\u054e\u056b\u056c\u0575\u0561\u0576\u0578\u0582\u0587\u0561 \u0564\u0565 \u053d\u056b\u056c\u0578\u056f\u0561"
    ],
    "name:ita_x_preferred":[
        "Villanueva de Jiloca"
    ],
    "name:jpn_x_preferred":[
        "\u30d3\u30b8\u30e3\u30cc\u30a8\u30d0\u30fb\u30c7\u30fb\u30d2\u30ed\u30ab"
    ],
    "name:kaz_x_preferred":[
        "\u0412\u0438\u043b\u044c\u044f\u043d\u0443\u044d\u0432\u0430-\u0434\u0435-\u0425\u0438\u043b\u043e\u043a\u0430"
    ],
    "name:msa_x_preferred":[
        "Villanueva de Jiloca"
    ],
    "name:nan_x_preferred":[
        "Villanueva de Jiloca"
    ],
    "name:nld_x_preferred":[
        "Villanueva de Jiloca"
    ],
    "name:oci_x_preferred":[
        "Villanueva de Jiloca"
    ],
    "name:pol_x_preferred":[
        "Villanueva de Jiloca"
    ],
    "name:por_x_preferred":[
        "Villanueva de Jiloca"
    ],
    "name:rus_x_preferred":[
        "\u0412\u0438\u043b\u044c\u044f\u043d\u0443\u044d\u0432\u0430-\u0434\u0435-\u0425\u0438\u043b\u043e\u043a\u0430"
    ],
    "name:spa_x_preferred":[
        "Villanueva de Jiloca"
    ],
    "name:ukr_x_preferred":[
        "\u0412\u0456\u043b\u044c\u044f\u043d\u0443\u0435\u0432\u0430-\u0434\u0435-\u0425\u0456\u043b\u043e\u043a\u0430"
    ],
    "name:und_x_variant":[
        "Villanueva"
    ],
    "name:uzb_x_preferred":[
        "Villanueva de Jiloca"
    ],
    "name:vie_x_preferred":[
        "Villanueva de Jiloca"
    ],
    "name:war_x_preferred":[
        "Villanueva de Jiloca"
    ],
    "name:zho_x_preferred":[
        "\u5e0c\u6d1b\u5361\u65b0\u9547"
    ],
    "qs_pg:aaroncc":"ES",
    "qs_pg:gn_country":"ES",
    "qs_pg:gn_fcode":"PPLA3",
    "qs_pg:gn_pop":80,
    "qs_pg:name":"Villanueva de Jiloca",
    "qs_pg:name_adm0":"Espa\u00f1a",
    "qs_pg:name_adm1":"Arag\u00f3n",
    "qs_pg:photos_9r":0,
    "qs_pg:photos_sr":0,
    "qs_pg:pop_sr":1,
    "qs_pg:qs_pg_placetype":"locality",
    "qs_pg:qs_pg_placetype_gp":"Town",
    "qs_pg:woe_adm0":23424950,
    "woe:adm0_id":23424950,
    "woe:name_adm0":"Espa\u00f1a",
    "woe:name_adm1":"Arag\u00f3n",
    "woe:placetype":"Town",
    "wof:name":"Villanueva de Jiloca",
    "wof:placetype":"locality",
    "wof:population":80
},
  "geometry": {"coordinates":[-1.3896,41.07625],"type":"Point"}
}