{
  "type": "Feature",
  "properties": {
    "gn:admin1_code":"32",
    "gn:admin3_code":"31026",
    "gn:asciiname":"Aras",
    "gn:country_code":"ES",
    "gn:dem":638,
    "gn:feature_class":"P",
    "gn:feature_code":"PPLA3",
    "gn:name":"Aras",
    "gn:population":221,
    "gn:timezone":"Europe/Madrid",
    "iso:country":"ES",
    "name:und_x_variant":[
        "Tres Aras",
        "Aras"
    ],
    "wof:name":"Aras",
    "wof:placetype":"locality",
    "wof:population":221
},
  "geometry": {"coordinates":[-2.356,42.56172],"type":"Point"}
}