{
  "type": "Feature",
  "properties": {
    "gn:admin1_code":"32",
    "gn:admin3_code":"31026",
    "gn:asciiname":"Aras",
    "gn:country_code":"ES",
    "gn:dem":638,
    "gn:feature_class":"P",
    "gn:feature_code":"PPLA3",
    "gn:name":"Aras",
    "gn:population":221,
    "gn:timezone":"Europe/Madrid",
    "iso:country":"ES",
    "name:arg_x_preferred":[
        "Aras"
    ],
    "name:ast_x_preferred":[
        "Ares"
    ],
    "name:bre_x_preferred":[
        "Aras"
    ],
    "name:cat_x_preferred":[
        "Aras"
    ],
    "name:ceb_x_preferred":[
        "Aras"
    ],
    "name:eus_x_preferred":[
        "Aras"
    ],
    "name:fra_x_preferred":[
        "Aras"
    ],
    "name:hun_x_preferred":[
        "Aras"
    ],
    "name:ita_x_preferred":[
        "Aras"
    ],
    "name:msa_x_preferred":[
        "Aras"
    ],
    "name:nld_x_preferred":[
        "Aras"
    ],
    "name:oci_x_preferred":[
        "Aras"
    ],
    "name:pol_x_preferred":[
        "Aras"
    ],
    "name:por_x_preferred":[
        "Aras"
    ],
    "name:rus_x_preferred":[
        "\u0410\u0440\u0430\u0441"
    ],
    "name:sco_x_preferred":[
        "Aras"
    ],
    "name:spa_x_preferred":[
        "Aras"
    ],
    "name:swe_x_preferred":[
        "Aras"
    ],
    "name:ukr_x_preferred":[
        "\u0410\u0440\u0430\u0441"
    ],
    "name:und_x_variant":[
        "Tres Aras",
        "Aras"
    ],
    "name:uzb_x_preferred":[
        "Aras"
    ],
    "name:vie_x_preferred":[
        "Aras"
    ],
    "name:war_x_preferred":[
        "Aras"
    ],
    "name:zho_x_preferred":[
        "\u963f\u62c9\u65af"
    ],
    "wof:name":"Aras",
    "wof:placetype":"locality",
    "wof:population":221
},
  "geometry": {"coordinates":[-2.356,42.56172],"type":"Point"}
}