{
  "type": "Feature",
  "properties": {
    "gn:admin1_code":"55",
    "gn:admin2_code":"SO",
    "gn:admin3_code":"42178",
    "gn:asciiname":"Fuentecantales",
    "gn:country_code":"ES",
    "gn:dem":1062,
    "gn:feature_class":"P",
    "gn:feature_code":"PPL",
    "gn:name":"Fuentecantales",
    "gn:population":0,
    "gn:timezone":"Europe/Madrid",
    "iso:country":"ES",
    "wof:name":"Fuentecantales",
    "wof:placetype":"locality"
},
  "geometry": {"coordinates":[-2.98932,41.71812],"type":"Point"}
}