{
  "type": "Feature",
  "properties": {
    "gn:admin1_code":"53",
    "gn:admin2_code":"GC",
    "gn:admin3_code":"35014",
    "gn:asciiname":"Toston",
    "gn:cc2":"ES",
    "gn:country_code":"ES",
    "gn:dem":14,
    "gn:feature_class":"P",
    "gn:feature_code":"PPL",
    "gn:name":"Tost\u00f3n",
    "gn:population":0,
    "gn:timezone":"Atlantic/Canary",
    "iso:country":"ES",
    "name:und_x_variant":[
        "Cotillo",
        "Puerto del Cotillo",
        "Puerto del Tost\u00f3n"
    ],
    "wof:name":"Toston",
    "wof:placetype":"locality"
},
  "geometry": {"coordinates":[-14.00997,28.68389],"type":"Point"}
}