{
  "type": "Feature",
  "properties": {
    "gn:admin1_code":"58",
    "gn:admin2_code":"LU",
    "gn:admin3_code":"27007",
    "gn:asciiname":"Saavedra",
    "gn:cc2":"ES",
    "gn:country_code":"ES",
    "gn:dem":432,
    "gn:feature_class":"P",
    "gn:feature_code":"PPL",
    "gn:name":"Saavedra",
    "gn:population":0,
    "gn:timezone":"Europe/Madrid",
    "iso:country":"ES",
    "name:und_x_variant":[
        "Santa Mar\u00eda",
        "Saavedra"
    ],
    "wof:name":"Saavedra",
    "wof:placetype":"locality"
},
  "geometry": {"coordinates":[-7.63333,43.15],"type":"Point"}
}