{
  "type": "Feature",
  "properties": {
    "gn:admin1_code":"58",
    "gn:admin2_code":"LU",
    "gn:admin3_code":"27007",
    "gn:asciiname":"Saavedra",
    "gn:cc2":"ES",
    "gn:country_code":"ES",
    "gn:dem":432,
    "gn:feature_class":"P",
    "gn:feature_code":"PPL",
    "gn:name":"Saavedra",
    "gn:population":0,
    "gn:timezone":"Europe/Madrid",
    "iso:country":"ES",
    "name:ast_x_preferred":[
        "Saavedra"
    ],
    "name:ceb_x_preferred":[
        "Saavedra"
    ],
    "name:ces_x_preferred":[
        "Saavedra"
    ],
    "name:deu_x_preferred":[
        "Saavedra"
    ],
    "name:fra_x_preferred":[
        "Saavedra"
    ],
    "name:glg_x_preferred":[
        "Saavedra"
    ],
    "name:ita_x_preferred":[
        "Saavedra"
    ],
    "name:jpn_x_preferred":[
        "\u30b5\u30a2\u30d9\u30c9\u30e9"
    ],
    "name:nds_x_preferred":[
        "Saavedra"
    ],
    "name:nld_x_preferred":[
        "Saavedra"
    ],
    "name:por_x_preferred":[
        "Saavedra"
    ],
    "name:ron_x_preferred":[
        "Saavedra"
    ],
    "name:rus_x_preferred":[
        "\u0421\u0430\u0430\u0432\u0435\u0434\u0440\u0430"
    ],
    "name:spa_x_preferred":[
        "Saavedra"
    ],
    "name:swe_x_preferred":[
        "Saavedra"
    ],
    "name:ukr_x_preferred":[
        "\u0421\u0430\u0430\u0432\u0435\u0434\u0440\u0430"
    ],
    "name:und_x_variant":[
        "Santa Mar\u00eda",
        "Saavedra"
    ],
    "wof:name":"Saavedra",
    "wof:placetype":"locality"
},
  "geometry": {"coordinates":[-7.63333,43.15],"type":"Point"}
}