{
  "type": "Feature",
  "properties": {
    "gn:gn_country":"ES",
    "gn:gn_fcode":"PPLA3",
    "gn:gn_pop":39,
    "gn:population":39,
    "iso:country":"ES",
    "name:arg_x_preferred":[
        "Robres del Castillo"
    ],
    "name:cat_x_preferred":[
        "Robres del Castillo"
    ],
    "name:deu_x_preferred":[
        "Robres del Castillo"
    ],
    "name:eng_x_preferred":[
        "Robres del Castillo"
    ],
    "name:eus_x_preferred":[
        "Robres del Castillo"
    ],
    "name:fra_x_preferred":[
        "Robres del Castillo"
    ],
    "name:hun_x_preferred":[
        "Robres del Castillo"
    ],
    "name:hye_x_preferred":[
        "\u054c\u0578\u0562\u0580\u0565\u057d \u0564\u0565\u056c \u053f\u0561\u057d\u057f\u056b\u056c\u056b\u0578"
    ],
    "name:ita_x_preferred":[
        "Robres del Castillo"
    ],
    "name:kaz_x_preferred":[
        "\u0420\u043e\u0431\u0440\u0435\u0441-\u0434\u0435\u043b\u044c-\u041a\u0430\u0441\u0442\u0438\u043b\u044c\u043e"
    ],
    "name:msa_x_preferred":[
        "Robres del Castillo"
    ],
    "name:nan_x_preferred":[
        "Robres del Castillo"
    ],
    "name:nld_x_preferred":[
        "Robres del Castillo"
    ],
    "name:oci_x_preferred":[
        "Robres del Castillo"
    ],
    "name:pol_x_preferred":[
        "Robres del Castillo"
    ],
    "name:por_x_preferred":[
        "Robres del Castillo"
    ],
    "name:rup_x_preferred":[
        "Robres del Castillo"
    ],
    "name:rus_x_preferred":[
        "\u0420\u043e\u0431\u0440\u0435\u0441-\u0434\u0435\u043b\u044c-\u041a\u0430\u0441\u0442\u0438\u043b\u044c\u043e"
    ],
    "name:spa_x_preferred":[
        "Robres del Castillo"
    ],
    "name:swe_x_preferred":[
        "Robres del Castillo"
    ],
    "name:ukr_x_preferred":[
        "\u0420\u043e\u0431\u0440\u0435\u0441-\u0434\u0435\u043b\u044c-\u041a\u0430\u0441\u0442\u0456\u043b\u044c\u0439\u043e"
    ],
    "name:uzb_x_preferred":[
        "Robres del Castillo"
    ],
    "name:vie_x_preferred":[
        "Robres del Castillo"
    ],
    "name:war_x_preferred":[
        "Robres del Castillo"
    ],
    "name:zho_x_preferred":[
        "\u7f57\u592b\u96f7\u65af\u5fb7\u5c14\u5361\u65af\u8482\u7565"
    ],
    "qs_pg:aaroncc":"ES",
    "qs_pg:gn_country":"ES",
    "qs_pg:gn_fcode":"PPLA3",
    "qs_pg:gn_pop":39,
    "qs_pg:name":"Robres del Castillo",
    "qs_pg:name_adm0":"Espa\u00f1a",
    "qs_pg:name_adm1":"La Rioja",
    "qs_pg:photos_9k":1,
    "qs_pg:photos_9r":1,
    "qs_pg:photos_all":3,
    "qs_pg:photos_sr":0,
    "qs_pg:pop_sr":1,
    "qs_pg:qs_pg_placetype":"locality",
    "qs_pg:qs_pg_placetype_gp":"Town",
    "qs_pg:woe_adm0":23424950,
    "woe:adm0_id":23424950,
    "woe:name_adm0":"Espa\u00f1a",
    "woe:name_adm1":"La Rioja",
    "woe:placetype":"Town",
    "wof:name":"Robres del Castillo",
    "wof:placetype":"locality",
    "wof:population":39
},
  "geometry": {"coordinates":[-2.29245,42.27593],"type":"Point"}
}