{
  "type": "Feature",
  "properties": {
    "gn:admin1_code":"39",
    "gn:admin2_code":"S",
    "gn:admin3_code":"39045",
    "gn:asciiname":"La Toba",
    "gn:country_code":"ES",
    "gn:dem":352,
    "gn:feature_class":"P",
    "gn:feature_code":"PPL",
    "gn:name":"La Toba",
    "gn:population":0,
    "gn:timezone":"Europe/Madrid",
    "iso:country":"ES",
    "wof:name":"La Toba",
    "wof:placetype":"locality"
},
  "geometry": {"coordinates":[-3.72881,43.25656],"type":"Point"}
}