{
  "type": "Feature",
  "properties": {
    "gn:admin1_code":"39",
    "gn:admin2_code":"S",
    "gn:admin3_code":"39045",
    "gn:asciiname":"La Toba",
    "gn:country_code":"ES",
    "gn:dem":352,
    "gn:feature_class":"P",
    "gn:feature_code":"PPL",
    "gn:name":"La Toba",
    "gn:population":0,
    "gn:timezone":"Europe/Madrid",
    "iso:country":"ES",
    "name:arg_x_preferred":[
        "La Toba"
    ],
    "name:cat_x_preferred":[
        "La Toba"
    ],
    "name:ceb_x_preferred":[
        "La Toba"
    ],
    "name:epo_x_preferred":[
        "La Toba"
    ],
    "name:eus_x_preferred":[
        "La Toba"
    ],
    "name:fra_x_preferred":[
        "La Toba"
    ],
    "name:hun_x_preferred":[
        "La Toba"
    ],
    "name:ina_x_preferred":[
        "La Toba"
    ],
    "name:ita_x_preferred":[
        "La Toba"
    ],
    "name:kaz_x_preferred":[
        "\u041b\u0430-\u0422\u043e\u0431\u0430"
    ],
    "name:msa_x_preferred":[
        "La Toba"
    ],
    "name:nld_x_preferred":[
        "La Toba"
    ],
    "name:oci_x_preferred":[
        "La Toba"
    ],
    "name:pol_x_preferred":[
        "La Toba"
    ],
    "name:por_x_preferred":[
        "La Toba"
    ],
    "name:rus_x_preferred":[
        "\u041b\u0430-\u0422\u043e\u0431\u0430"
    ],
    "name:spa_x_preferred":[
        "La Toba"
    ],
    "name:swe_x_preferred":[
        "La Toba"
    ],
    "name:ukr_x_preferred":[
        "\u041b\u0430-\u0422\u043e\u0431\u0430"
    ],
    "name:vie_x_preferred":[
        "La Toba"
    ],
    "name:war_x_preferred":[
        "La Toba"
    ],
    "name:zho_x_preferred":[
        "\u62c9\u6258\u74e6"
    ],
    "wof:name":"La Toba",
    "wof:placetype":"locality"
},
  "geometry": {"coordinates":[-3.72881,43.25656],"type":"Point"}
}