{
  "type": "Feature",
  "properties": {
    "iso:country":"ES",
    "name:ast_x_preferred":[
        "El Pino"
    ],
    "name:ceb_x_preferred":[
        "El Pino"
    ],
    "name:deu_x_preferred":[
        "El Pino"
    ],
    "name:glg_x_preferred":[
        "O Pino"
    ],
    "name:spa_x_preferred":[
        "El Pino"
    ],
    "name:srp_x_preferred":[
        "\u0415\u043b \u041f\u0438\u043d\u043e"
    ],
    "name:swe_x_preferred":[
        "El Pino"
    ],
    "qs_pg:aaroncc":"ES",
    "qs_pg:name":"El Pino",
    "qs_pg:name_adm0":"Espa\u00f1a",
    "qs_pg:name_adm1":"Galicia",
    "qs_pg:photos":327,
    "qs_pg:photos_1k":66,
    "qs_pg:photos_9k":1,
    "qs_pg:photos_9r":5,
    "qs_pg:photos_all":327,
    "qs_pg:photos_sr":5,
    "qs_pg:pop_sr":0,
    "qs_pg:qs_pg_placetype":"locality",
    "qs_pg:qs_pg_placetype_gp":"Town",
    "qs_pg:woe_adm0":23424950,
    "woe:adm0_id":23424950,
    "woe:name_adm0":"Espa\u00f1a",
    "woe:name_adm1":"Galicia",
    "woe:placetype":"Town",
    "wof:name":"El Pino",
    "wof:placetype":"locality"
},
  "geometry": {"coordinates":[-8.362441,42.908545],"type":"Point"}
}