{
  "type": "Feature",
  "properties": {
    "gn:admin1_code":"60",
    "gn:admin2_code":"V",
    "gn:admin3_code":"46170",
    "gn:asciiname":"Venta del Potro",
    "gn:country_code":"ES",
    "gn:dem":412,
    "gn:feature_class":"P",
    "gn:feature_code":"PPL",
    "gn:name":"Venta del Potro",
    "gn:population":0,
    "gn:timezone":"Europe/Madrid",
    "iso:country":"ES",
    "name:und_x_variant":[
        "Casas Venta del Potro",
        "Venta del Porto y Casas de Marco",
        "Venta del Potro"
    ],
    "wof:name":"Venta del Potro",
    "wof:placetype":"locality"
},
  "geometry": {"coordinates":[-0.82167,38.85169000000001],"type":"Point"}
}