{
  "type": "Feature",
  "properties": {
    "gn:admin1_code":"54",
    "gn:admin2_code":"AB",
    "gn:admin3_code":"02034",
    "gn:asciiname":"Molar de Arriba",
    "gn:cc2":"ES",
    "gn:country_code":"ES",
    "gn:dem":621,
    "gn:feature_class":"P",
    "gn:feature_code":"PPL",
    "gn:name":"Molar de Arriba",
    "gn:population":0,
    "gn:timezone":"Europe/Madrid",
    "iso:country":"ES",
    "name:und_x_variant":[
        "Caser\u00edo Molar de Arriba",
        "Molar de Arriba"
    ],
    "wof:name":"Molar de Arriba",
    "wof:placetype":"locality"
},
  "geometry": {"coordinates":[-1.55,39.23333],"type":"Point"}
}