{
  "type": "Feature",
  "properties": {
    "gn:gn_country":"ES",
    "gn:gn_fcode":"PPLA3",
    "gn:gn_pop":106,
    "gn:population":106,
    "iso:country":"ES",
    "name:ara_x_preferred":[
        "\u062b\u064a\u0628\u064a\u062f\u0627 \u0644\u0627 \u0645\u0648\u0631\u0627"
    ],
    "name:cat_x_preferred":[
        "Cepeda la Mora"
    ],
    "name:deu_x_preferred":[
        "Cepeda la Mora"
    ],
    "name:eng_x_preferred":[
        "Cepeda la Mora"
    ],
    "name:eus_x_preferred":[
        "Cepeda la Mora"
    ],
    "name:fas_x_preferred":[
        "\u0633\u067e\u062f\u0627 \u0644\u0627 \u0645\u0631\u0627"
    ],
    "name:fra_x_preferred":[
        "Cepeda de la Mora"
    ],
    "name:hun_x_preferred":[
        "Cepeda la Mora"
    ],
    "name:hye_x_preferred":[
        "\u054d\u0565\u057a\u0565\u0564\u0561 \u056c\u0561 \u0544\u0578\u0580\u0561"
    ],
    "name:ina_x_preferred":[
        "Cepeda la Mora"
    ],
    "name:ita_x_preferred":[
        "Cepeda la Mora"
    ],
    "name:kaz_x_preferred":[
        "\u0421\u0435\u043f\u0435\u0434\u0430-\u043b\u0430-\u041c\u043e\u0440\u0430"
    ],
    "name:mkd_x_preferred":[
        "\u041a\u0435\u043f\u0435\u0434\u0430 \u043b\u0430 \u041c\u043e\u0440\u0430"
    ],
    "name:msa_x_preferred":[
        "Cepeda la Mora"
    ],
    "name:nld_x_preferred":[
        "Cepeda la Mora"
    ],
    "name:oci_x_preferred":[
        "Cepeda la Mora"
    ],
    "name:pol_x_preferred":[
        "Cepeda de la Mora"
    ],
    "name:por_x_preferred":[
        "Cepeda la Mora"
    ],
    "name:rus_x_preferred":[
        "\u0421\u0435\u043f\u0435\u0434\u0430-\u043b\u0430-\u041c\u043e\u0440\u0430"
    ],
    "name:spa_x_preferred":[
        "Cepeda la Mora"
    ],
    "name:swe_x_preferred":[
        "Cepeda de la Mora"
    ],
    "name:ukr_x_preferred":[
        "\u0421\u0435\u043f\u0435\u0434\u0430-\u043b\u0430-\u041c\u043e\u0440\u0430"
    ],
    "name:uzb_x_preferred":[
        "Cepeda la Mora"
    ],
    "name:vie_x_preferred":[
        "Cepeda la Mora"
    ],
    "name:war_x_preferred":[
        "Cepeda la Mora"
    ],
    "name:zho_x_preferred":[
        "\u585e\u4f69\u8fbe\u62c9\u83ab\u62c9"
    ],
    "qs_pg:aaroncc":"ES",
    "qs_pg:gn_country":"ES",
    "qs_pg:gn_fcode":"PPLA3",
    "qs_pg:gn_pop":106,
    "qs_pg:name":"Cepeda la Mora",
    "qs_pg:name_adm0":"Espa\u00f1a",
    "qs_pg:name_adm1":"Castilla y Le\u00f3n",
    "qs_pg:photos_9r":0,
    "qs_pg:photos_sr":0,
    "qs_pg:pop_sr":1,
    "qs_pg:qs_pg_placetype":"locality",
    "qs_pg:qs_pg_placetype_gp":"Town",
    "qs_pg:woe_adm0":23424950,
    "woe:adm0_id":23424950,
    "woe:name_adm0":"Espa\u00f1a",
    "woe:name_adm1":"Castilla y Le\u00f3n",
    "woe:placetype":"Town",
    "wof:name":"Cepeda la Mora",
    "wof:placetype":"locality",
    "wof:population":106
},
  "geometry": {"coordinates":[-5.04833,40.4578],"type":"Point"}
}