{
  "type": "Feature",
  "properties": {
    "gn:admin1_code":"34",
    "gn:admin2_code":"O",
    "gn:admin3_code":"33024",
    "gn:asciiname":"Penaferruz",
    "gn:country_code":"ES",
    "gn:dem":148,
    "gn:feature_class":"P",
    "gn:feature_code":"PPL",
    "gn:name":"Pe\u00f1aferruz",
    "gn:population":0,
    "gn:timezone":"Europe/Madrid",
    "iso:country":"ES",
    "name:und_x_variant":[
        "Pe\u00f1aferruz"
    ],
    "wof:name":"Penaferruz",
    "wof:placetype":"locality"
},
  "geometry": {"coordinates":[-5.73459,43.45558],"type":"Point"}
}