{
  "type": "Feature",
  "properties": {
    "gn:gn_country":"ES",
    "gn:gn_fcode":"PPLA3",
    "gn:gn_pop":1088,
    "gn:population":1088,
    "iso:country":"ES",
    "name:ara_x_preferred":[
        "\u0628\u064a\u062a\u064a\u0646\u060c \u0623\u0648\u0631\u064a\u0646\u0633\u064a"
    ],
    "name:baq_x_preferred":[
        "Pet\u00edn"
    ],
    "name:cat_x_preferred":[
        "Pet\u00edn"
    ],
    "name:chi_x_preferred":[
        "\u4f69\u5ef7"
    ],
    "name:dut_x_preferred":[
        "Pet\u00edn"
    ],
    "name:eng_x_preferred":[
        "Pet\u00edn"
    ],
    "name:fre_x_preferred":[
        "Pet\u00edn"
    ],
    "name:glg_x_preferred":[
        "Pet\u00edn"
    ],
    "name:hun_x_preferred":[
        "Pet\u00edn"
    ],
    "name:ita_x_preferred":[
        "Pet\u00edn"
    ],
    "name:jpn_x_preferred":[
        "\u30da\u30c6\u30a3\u30f3"
    ],
    "name:lmo_x_preferred":[
        "Pet\u00edn"
    ],
    "name:may_x_preferred":[
        "Pet\u00edn"
    ],
    "name:nan_x_preferred":[
        "Pet\u00edn"
    ],
    "name:oci_x_preferred":[
        "Pet\u00edn"
    ],
    "name:pol_x_preferred":[
        "Pet\u00edn"
    ],
    "name:por_x_preferred":[
        "Pet\u00edn"
    ],
    "name:rus_x_preferred":[
        "\u041f\u0435\u0442\u0438\u043d"
    ],
    "name:spa_x_preferred":[
        "Pet\u00edn"
    ],
    "name:swe_x_preferred":[
        "Pet\u00edn"
    ],
    "name:tur_x_preferred":[
        "Pet\u00edn"
    ],
    "name:ukr_x_preferred":[
        "\u041f\u0435\u0442\u0456\u043d"
    ],
    "name:uzb_x_preferred":[
        "Pet\u00edn"
    ],
    "name:vie_x_preferred":[
        "Pet\u00edn"
    ],
    "name:war_x_preferred":[
        "Pet\u00edn"
    ],
    "qs_pg:aaroncc":"ES",
    "qs_pg:gn_country":"ES",
    "qs_pg:gn_fcode":"PPLA3",
    "qs_pg:gn_pop":1088,
    "qs_pg:name":"Pet\u00edn",
    "qs_pg:name_adm0":"Espa\u00f1a",
    "qs_pg:name_adm1":"Galicia",
    "qs_pg:photos":147,
    "qs_pg:photos_1k":30,
    "qs_pg:photos_9k":1,
    "qs_pg:photos_9r":3,
    "qs_pg:photos_all":147,
    "qs_pg:photos_sr":3,
    "qs_pg:pop_sr":3,
    "qs_pg:qs_pg_placetype":"locality",
    "qs_pg:qs_pg_placetype_gp":"Town",
    "qs_pg:woe_adm0":23424950,
    "woe:adm0_id":23424950,
    "woe:name_adm0":"Espa\u00f1a",
    "woe:name_adm1":"Galicia",
    "woe:placetype":"Town",
    "wof:name":"Pet\u00edn",
    "wof:placetype":"locality",
    "wof:population":1088
},
  "geometry": {"coordinates":[-7.12899,42.38192],"type":"Point"}
}