{
  "type": "Feature",
  "properties": {
    "gn:admin1_code":"58",
    "gn:admin2_code":"LU",
    "gn:admin3_code":"27015",
    "gn:asciiname":"Justas",
    "gn:country_code":"ES",
    "gn:dem":398,
    "gn:feature_class":"P",
    "gn:feature_code":"PPL",
    "gn:name":"Just\u00e1s",
    "gn:population":0,
    "gn:timezone":"Europe/Madrid",
    "iso:country":"ES",
    "wof:name":"Justas",
    "wof:placetype":"locality"
},
  "geometry": {"coordinates":[-7.48333,43.18333],"type":"Point"}
}