{
  "type": "Feature",
  "properties": {
    "gn:country":"ES",
    "gn:fcode":"PPLA3",
    "gn:population":73,
    "iso:country":"ES",
    "name:arg_x_preferred":[
        "Mantiel"
    ],
    "name:ast_x_preferred":[
        "Mantiel"
    ],
    "name:bul_x_preferred":[
        "\u041c\u0430\u043d\u0442\u0438\u0435\u043b"
    ],
    "name:cat_x_preferred":[
        "Mantiel"
    ],
    "name:ceb_x_preferred":[
        "Mantiel"
    ],
    "name:eng_x_preferred":[
        "Mantiel"
    ],
    "name:epo_x_preferred":[
        "Mantiel"
    ],
    "name:eus_x_preferred":[
        "Mantiel"
    ],
    "name:fra_x_preferred":[
        "Mantiel"
    ],
    "name:hun_x_preferred":[
        "Mantiel"
    ],
    "name:ina_x_preferred":[
        "Mantiel"
    ],
    "name:ita_x_preferred":[
        "Mantiel"
    ],
    "name:kaz_x_preferred":[
        "\u041c\u0430\u043d\u0442\u044c\u0435\u043b\u044c"
    ],
    "name:msa_x_preferred":[
        "Mantiel"
    ],
    "name:nan_x_preferred":[
        "Mantiel"
    ],
    "name:nld_x_preferred":[
        "Mantiel"
    ],
    "name:oci_x_preferred":[
        "Mantiel"
    ],
    "name:pam_x_preferred":[
        "Mantiel"
    ],
    "name:pol_x_preferred":[
        "Mantiel"
    ],
    "name:por_x_preferred":[
        "Mantiel"
    ],
    "name:rus_x_preferred":[
        "\u041c\u0430\u043d\u0442\u044c\u0435\u043b\u044c"
    ],
    "name:spa_x_preferred":[
        "Mantiel"
    ],
    "name:swe_x_preferred":[
        "Mantiel"
    ],
    "name:ukr_x_preferred":[
        "\u041c\u0430\u043d\u0442\u044c\u0454\u043b\u044c"
    ],
    "name:vie_x_preferred":[
        "Mantiel"
    ],
    "name:war_x_preferred":[
        "Mantiel"
    ],
    "name:zho_x_preferred":[
        "\u66fc\u94c1\u5c14"
    ],
    "qs_pg:aaroncc":"ES",
    "qs_pg:gn_country":"ES",
    "qs_pg:gn_fcode":"PPLA3",
    "qs_pg:gn_pop":73,
    "qs_pg:name":"Mantiel",
    "qs_pg:name_adm0":"Espa\u00f1a",
    "qs_pg:name_adm1":"Castilla-La Mancha",
    "qs_pg:photos_9r":0,
    "qs_pg:photos_sr":0,
    "qs_pg:pop_sr":1,
    "qs_pg:qs_pg_placetype":"locality",
    "qs_pg:qs_pg_placetype_gp":"Town",
    "qs_pg:woe_adm0":23424950,
    "woe:adm0_id":23424950,
    "woe:name_adm0":"Espa\u00f1a",
    "woe:name_adm1":"Castilla-La Mancha",
    "woe:placetype":"Town",
    "wof:name":"Mantiel",
    "wof:placetype":"locality",
    "wof:population":73
},
  "geometry": {"coordinates":[-2.66324,40.61892],"type":"Point"}
}