{
  "type": "Feature",
  "properties": {
    "gn:country":"ES",
    "gn:fcode":"PPLA3",
    "gn:population":138,
    "iso:country":"ES",
    "name:arg_x_preferred":[
        "Chasa"
    ],
    "name:ast_x_preferred":[
        "Jasa"
    ],
    "name:cat_x_preferred":[
        "Jasa"
    ],
    "name:ceb_x_preferred":[
        "Jasa"
    ],
    "name:che_x_preferred":[
        "\u0425\u0430\u0441\u0430"
    ],
    "name:deu_x_preferred":[
        "Jasa"
    ],
    "name:diq_x_preferred":[
        "Jasa"
    ],
    "name:eng_x_preferred":[
        "Jasa"
    ],
    "name:epo_x_preferred":[
        "Jasa"
    ],
    "name:eus_x_preferred":[
        "Jasa"
    ],
    "name:fra_x_preferred":[
        "Jasa"
    ],
    "name:gle_x_preferred":[
        "Jasa"
    ],
    "name:glg_x_preferred":[
        "Jasa"
    ],
    "name:hak_x_preferred":[
        "Jasa"
    ],
    "name:hun_x_preferred":[
        "Jasa"
    ],
    "name:ile_x_preferred":[
        "Jasa"
    ],
    "name:ina_x_preferred":[
        "Jasa"
    ],
    "name:ind_x_preferred":[
        "Jasa"
    ],
    "name:ita_x_preferred":[
        "Jasa"
    ],
    "name:kat_x_preferred":[
        "\u10ee\u10d0\u10e1\u10d0"
    ],
    "name:lld_x_preferred":[
        "Jasa"
    ],
    "name:msa_x_preferred":[
        "Jasa"
    ],
    "name:nan_x_preferred":[
        "Jasa"
    ],
    "name:nld_x_preferred":[
        "Jasa"
    ],
    "name:nob_x_preferred":[
        "Jasa"
    ],
    "name:oci_x_preferred":[
        "Jasa"
    ],
    "name:pol_x_preferred":[
        "Jasa"
    ],
    "name:por_x_preferred":[
        "Jasa"
    ],
    "name:rus_x_preferred":[
        "\u0425\u0430\u0441\u0430"
    ],
    "name:spa_x_preferred":[
        "Jasa"
    ],
    "name:swe_x_preferred":[
        "Jasa"
    ],
    "name:tat_x_preferred":[
        "\u0425\u0430\u0441\u0430"
    ],
    "name:ukr_x_preferred":[
        "\u0425\u0430\u0441\u0430"
    ],
    "name:urd_x_preferred":[
        "\u062c\u0633\u0627"
    ],
    "name:uzb_x_preferred":[
        "Jasa"
    ],
    "name:vec_x_preferred":[
        "Jasa"
    ],
    "name:vie_x_preferred":[
        "Jasa"
    ],
    "name:war_x_preferred":[
        "Jasa"
    ],
    "name:zho_x_preferred":[
        "\u54c8\u8428"
    ],
    "qs_pg:aaroncc":"ES",
    "qs_pg:gn_country":"ES",
    "qs_pg:gn_fcode":"PPLA3",
    "qs_pg:gn_pop":138,
    "qs_pg:name":"Jasa",
    "qs_pg:name_adm0":"Espa\u00f1a",
    "qs_pg:name_adm1":"Arag\u00f3n",
    "qs_pg:photos":18,
    "qs_pg:photos_1k":4,
    "qs_pg:photos_9k":1,
    "qs_pg:photos_9r":1,
    "qs_pg:photos_all":18,
    "qs_pg:photos_sr":1,
    "qs_pg:pop_sr":1,
    "qs_pg:qs_pg_placetype":"locality",
    "qs_pg:qs_pg_placetype_gp":"Town",
    "qs_pg:woe_adm0":23424950,
    "woe:adm0_id":23424950,
    "woe:name_adm0":"Espa\u00f1a",
    "woe:name_adm1":"Arag\u00f3n",
    "woe:placetype":"Town",
    "wof:name":"Jasa",
    "wof:placetype":"locality",
    "wof:population":138
},
  "geometry": {"coordinates":[-0.66605,42.6948],"type":"Point"}
}