{
  "type": "Feature",
  "properties": {
    "gn:admin1_code":"59",
    "gn:admin2_code":"SS",
    "gn:admin3_code":"20019",
    "gn:asciiname":"Erausquin-zar",
    "gn:country_code":"ES",
    "gn:dem":342,
    "gn:feature_class":"P",
    "gn:feature_code":"PPL",
    "gn:name":"Erauskin",
    "gn:population":0,
    "gn:timezone":"Europe/Madrid",
    "iso:country":"ES",
    "name:und_x_variant":[
        "Erausquin",
        "Erausquin-zar"
    ],
    "wof:name":"Erausquin-zar",
    "wof:placetype":"locality"
},
  "geometry": {"coordinates":[-2.19591,43.05695],"type":"Point"}
}