{
  "type": "Feature",
  "properties": {
    "gn:admin1_code":"52",
    "gn:admin2_code":"HU",
    "gn:admin3_code":"22199",
    "gn:asciiname":"San Roman de Basa",
    "gn:country_code":"ES",
    "gn:dem":981,
    "gn:feature_class":"P",
    "gn:feature_code":"PPL",
    "gn:name":"San Rom\u00e1n de Basa",
    "gn:population":0,
    "gn:timezone":"Europe/Madrid",
    "iso:country":"ES",
    "wof:name":"San Roman de Basa",
    "wof:placetype":"locality"
},
  "geometry": {"coordinates":[-0.30974,42.51164],"type":"Point"}
}