{
  "type": "Feature",
  "properties": {
    "gn:admin1_code":"54",
    "gn:admin2_code":"CU",
    "gn:admin3_code":"16112",
    "gn:asciiname":"La Langa",
    "gn:country_code":"ES",
    "gn:dem":954,
    "gn:feature_class":"P",
    "gn:feature_code":"PPL",
    "gn:name":"La Langa",
    "gn:population":0,
    "gn:timezone":"Europe/Madrid",
    "iso:country":"ES",
    "name:und_x_variant":[
        "Langa",
        "La Langa"
    ],
    "wof:name":"La Langa",
    "wof:placetype":"locality"
},
  "geometry": {"coordinates":[-2.65983,40.08996],"type":"Point"}
}