{
  "type": "Feature",
  "properties": {
    "gn:admin1_code":"34",
    "gn:admin2_code":"O",
    "gn:admin3_code":"33057",
    "gn:asciiname":"Palombar",
    "gn:country_code":"ES",
    "gn:dem":126,
    "gn:feature_class":"P",
    "gn:feature_code":"PPLL",
    "gn:name":"Palombar",
    "gn:population":0,
    "gn:timezone":"Europe/Madrid",
    "iso:country":"ES",
    "wof:name":"Palombar",
    "wof:placetype":"locality"
},
  "geometry": {"coordinates":[-5.91049,43.30809],"type":"Point"}
}