{
  "type": "Feature",
  "properties": {
    "gn:gn_country":"ES",
    "gn:gn_fcode":"PPL",
    "gn:gn_pop":0,
    "iso:country":"ES",
    "name:arg_x_preferred":[
        "Granyena de Segarra"
    ],
    "name:cat_x_preferred":[
        "Granyena de Segarra"
    ],
    "name:deu_x_preferred":[
        "Granyena de Segarra"
    ],
    "name:eng_x_preferred":[
        "Granyena de Segarra"
    ],
    "name:eus_x_preferred":[
        "Granyena de Segarra"
    ],
    "name:fra_x_preferred":[
        "Granyena de Segarra"
    ],
    "name:hun_x_preferred":[
        "Granyena de Segarra"
    ],
    "name:hye_x_preferred":[
        "\u0533\u0580\u0561\u0576\u056b\u0565\u0576\u0561 \u0564\u0565 \u054d\u0565\u0563\u0561\u057c\u0561"
    ],
    "name:ita_x_preferred":[
        "Granyena de Segarra"
    ],
    "name:nld_x_preferred":[
        "Granyena de Segarra"
    ],
    "name:oci_x_preferred":[
        "Granyena de Segarra"
    ],
    "name:pol_x_preferred":[
        "Granyena de Segarra"
    ],
    "name:por_x_preferred":[
        "Granyena de Segarra"
    ],
    "name:ron_x_preferred":[
        "Granyena de Segarra"
    ],
    "name:rus_x_preferred":[
        "\u0413\u0440\u0430\u043d\u044c\u0435\u043d\u0430-\u0434\u0435-\u0421\u0435\u0433\u0430\u0440\u0440\u0430"
    ],
    "name:spa_x_preferred":[
        "Gra\u00f1ena de Cervera"
    ],
    "name:sqi_x_preferred":[
        "Granyena de Segarra"
    ],
    "name:swe_x_preferred":[
        "Granyena de Segarra"
    ],
    "name:unk_x_variant":[
        "Gra\u00f1ena de Cervera"
    ],
    "name:uzb_x_preferred":[
        "Gra\u00f1ena de Segarra"
    ],
    "name:vie_x_preferred":[
        "Granyena de Segarra"
    ],
    "name:war_x_preferred":[
        "Granyena de Segarra"
    ],
    "name:zho_x_preferred":[
        "\u683c\u62c9\u6d85\u7eb3\u5fb7\u585e\u52a0\u62c9"
    ],
    "qs_pg:aaroncc":"ES",
    "qs_pg:gn_country":"ES",
    "qs_pg:gn_fcode":"PPL",
    "qs_pg:gn_pop":0,
    "qs_pg:name":"Granyena de Segarra",
    "qs_pg:name_adm0":"Espa\u00f1a",
    "qs_pg:name_adm1":"Catalunya",
    "qs_pg:photos":22,
    "qs_pg:photos_1k":4,
    "qs_pg:photos_9k":1,
    "qs_pg:photos_9r":1,
    "qs_pg:photos_all":22,
    "qs_pg:photos_sr":1,
    "qs_pg:pop_sr":0,
    "qs_pg:qs_pg_placetype":"locality",
    "qs_pg:qs_pg_placetype_gp":"Town",
    "qs_pg:woe_adm0":23424950,
    "woe:adm0_id":23424950,
    "woe:name_adm0":"Espa\u00f1a",
    "woe:name_adm1":"Catalunya",
    "woe:placetype":"Town",
    "wof:name":"Granyena de Segarra",
    "wof:placetype":"locality"
},
  "geometry": {"coordinates":[1.25,41.61667],"type":"Point"}
}