{
  "type": "Feature",
  "properties": {
    "iso:country":"ES",
    "name:arg_x_preferred":[
        "Vila-rodona"
    ],
    "name:ast_x_preferred":[
        "Vila-rodona"
    ],
    "name:azb_x_preferred":[
        "\u0628\u06cc\u0644\u0627-\u0631\u062f\u0646\u0627"
    ],
    "name:cat_x_preferred":[
        "Vila-rodona"
    ],
    "name:ceb_x_preferred":[
        "Vila-rodona"
    ],
    "name:deu_x_preferred":[
        "Vila-rodona"
    ],
    "name:eng_x_preferred":[
        "Vila-rodona"
    ],
    "name:eus_x_preferred":[
        "Vila-rodona"
    ],
    "name:fas_x_preferred":[
        "\u0628\u06cc\u0644\u0627-\u0631\u062f\u0646\u0627"
    ],
    "name:fra_x_preferred":[
        "Vila-rodona"
    ],
    "name:fra_x_variant":[
        "Vila-Rodona"
    ],
    "name:glg_x_preferred":[
        "Vila-rodona"
    ],
    "name:hun_x_preferred":[
        "Vila-rodona"
    ],
    "name:hye_x_preferred":[
        "\u054e\u056b\u056c\u0561 \u054c\u0578\u0564\u0578\u0576\u0561"
    ],
    "name:ita_x_preferred":[
        "Vila-rodona"
    ],
    "name:jpn_x_preferred":[
        "\u30d3\u30e9\uff1d\u30eb\u30c9\u30fc\u30ca"
    ],
    "name:lat_x_preferred":[
        "Vila-rodona"
    ],
    "name:msa_x_preferred":[
        "Vila-rodona"
    ],
    "name:nld_x_preferred":[
        "Vila-rodona"
    ],
    "name:oci_x_preferred":[
        "Vila-rodona"
    ],
    "name:pol_x_preferred":[
        "Vila-rodona"
    ],
    "name:por_x_preferred":[
        "Vila-rodona"
    ],
    "name:rus_x_preferred":[
        "\u0412\u0438\u043b\u0430-\u0420\u043e\u0434\u043e\u043d\u0430"
    ],
    "name:spa_x_preferred":[
        "Vilarrodona"
    ],
    "name:sqi_x_preferred":[
        "Vila-rodona"
    ],
    "name:swe_x_preferred":[
        "Vila-rodona"
    ],
    "name:ukr_x_preferred":[
        "\u0411\u0456\u043b\u0430-\u0440\u0443\u0434\u043e\u043d\u0430"
    ],
    "name:unk_x_variant":[
        "Villarodona"
    ],
    "name:uzb_x_preferred":[
        "Vila-rodona"
    ],
    "name:vie_x_preferred":[
        "Vila-rodona"
    ],
    "name:war_x_preferred":[
        "Vila-rodona"
    ],
    "name:zho_x_preferred":[
        "\u6bd4\u62c9-\u7f57\u591a\u7eb3"
    ],
    "qs:a0":"Espa\u00f1a",
    "qs:a1":"*Tarragona",
    "qs:a1r":"0Catalu\u00f1a",
    "qs:adm0":"Espa\u00f1a",
    "qs:la_lc":"*",
    "qs:level":"locality",
    "qs:loc":"Vila-rodona",
    "qs:loc_alt":"Vila-rodona",
    "qs:pop":0,
    "qs:type":"buffered point",
    "wd:wordcount":45,
    "wof:name":"Vila-rodona",
    "wof:placetype":"locality"
},
  "geometry": {"coordinates":[1.358527,41.311425],"type":"Point"}
}