{
  "type": "Feature",
  "properties": {
    "gn:admin1_code":"58",
    "gn:admin2_code":"LU",
    "gn:admin3_code":"27014",
    "gn:asciiname":"Fonteita",
    "gn:cc2":"ES",
    "gn:country_code":"ES",
    "gn:dem":492,
    "gn:feature_class":"P",
    "gn:feature_code":"PPL",
    "gn:name":"Fonteita",
    "gn:population":0,
    "gn:timezone":"Europe/Madrid",
    "iso:country":"ES",
    "name:und_x_variant":[
        "Santiago",
        "Fonteita"
    ],
    "wof:name":"Fonteita",
    "wof:placetype":"locality"
},
  "geometry": {"coordinates":[-7.36667,42.95],"type":"Point"}
}