{
  "type": "Feature",
  "properties": {
    "gn:admin1_code":"52",
    "gn:admin2_code":"HU",
    "gn:admin3_code":"22109",
    "gn:asciiname":"Lardies",
    "gn:country_code":"ES",
    "gn:dem":898,
    "gn:feature_class":"P",
    "gn:feature_code":"PPL",
    "gn:name":"Lardi\u00e9s",
    "gn:population":0,
    "gn:timezone":"Europe/Madrid",
    "iso:country":"ES",
    "name:und_x_variant":[
        "Lardi\u00e9s"
    ],
    "wof:name":"Lardies",
    "wof:placetype":"locality"
},
  "geometry": {"coordinates":[-0.13276,42.49833],"type":"Point"}
}