{
  "type": "Feature",
  "properties": {
    "gn:admin1_code":"57",
    "gn:admin2_code":"CC",
    "gn:admin3_code":"10205",
    "gn:asciiname":"La Granja",
    "gn:country_code":"ES",
    "gn:dem":414,
    "gn:feature_class":"P",
    "gn:feature_code":"PPL",
    "gn:name":"La Granja",
    "gn:population":0,
    "gn:timezone":"Europe/Madrid",
    "iso:country":"ES",
    "name:ceb_x_preferred":[
        "La Granja"
    ],
    "name:deu_x_preferred":[
        "La Granja"
    ],
    "name:eus_x_preferred":[
        "La Granja"
    ],
    "name:fra_x_preferred":[
        "La Granja"
    ],
    "name:glg_x_preferred":[
        "La Granja"
    ],
    "name:hun_x_preferred":[
        "La Granja"
    ],
    "name:msa_x_preferred":[
        "La Granja"
    ],
    "name:nld_x_preferred":[
        "La Granja"
    ],
    "name:oci_x_preferred":[
        "La Granja"
    ],
    "name:pol_x_preferred":[
        "La Granja"
    ],
    "name:por_x_preferred":[
        "La Granja"
    ],
    "name:ron_x_preferred":[
        "La Granja"
    ],
    "name:rus_x_preferred":[
        "\u041b\u0430-\u0413\u0440\u0430\u043d\u0445\u0430"
    ],
    "name:spa_x_preferred":[
        "La granja"
    ],
    "name:swe_x_preferred":[
        "La Granja"
    ],
    "name:ukr_x_preferred":[
        "\u041b\u0430 \u0413\u0440\u0430\u043d\u0445\u0430"
    ],
    "name:und_x_variant":[
        "Caser\u00edo de la Granja",
        "Colonia la Granja",
        "La Granja"
    ],
    "name:vie_x_preferred":[
        "La Granja"
    ],
    "name:war_x_preferred":[
        "La Granja"
    ],
    "wof:name":"La Granja",
    "wof:placetype":"locality"
},
  "geometry": {"coordinates":[-6.88673,40.15566],"type":"Point"}
}