{
  "type": "Feature",
  "properties": {
    "gn:admin1_code":"55",
    "gn:admin2_code":"SO",
    "gn:admin3_code":"42043",
    "gn:asciiname":"Osma",
    "gn:country_code":"ES",
    "gn:dem":900,
    "gn:feature_class":"P",
    "gn:feature_code":"PPL",
    "gn:name":"Osma",
    "gn:population":0,
    "gn:timezone":"Europe/Madrid",
    "iso:country":"ES",
    "wof:name":"Osma",
    "wof:placetype":"locality"
},
  "geometry": {"coordinates":[-3.08234,41.58377],"type":"Point"}
}