{
  "type": "Feature",
  "properties": {
    "gn:gn_country":"ES",
    "gn:gn_fcode":"PPLA3",
    "gn:gn_pop":243,
    "gn:population":243,
    "iso:country":"ES",
    "name:arg_x_preferred":[
        "Bailo"
    ],
    "name:baq_x_preferred":[
        "Bailo"
    ],
    "name:cat_x_preferred":[
        "Bailo"
    ],
    "name:chi_x_preferred":[
        "\u62dc\u6d1b"
    ],
    "name:dut_x_preferred":[
        "Bailo"
    ],
    "name:eng_x_preferred":[
        "Bailo"
    ],
    "name:fre_x_preferred":[
        "Bailo"
    ],
    "name:ger_x_preferred":[
        "Bailo"
    ],
    "name:glg_x_preferred":[
        "Bailo"
    ],
    "name:hak_x_preferred":[
        "Bailo"
    ],
    "name:hun_x_preferred":[
        "Bailo"
    ],
    "name:ind_x_preferred":[
        "Bailo"
    ],
    "name:ita_x_preferred":[
        "Bailo"
    ],
    "name:may_x_preferred":[
        "Bailo"
    ],
    "name:nan_x_preferred":[
        "Bailo"
    ],
    "name:oci_x_preferred":[
        "Bailo"
    ],
    "name:pol_x_preferred":[
        "Bailo"
    ],
    "name:por_x_preferred":[
        "Bailo"
    ],
    "name:rum_x_preferred":[
        "Bailo"
    ],
    "name:rus_x_preferred":[
        "\u0411\u0430\u0439\u043b\u043e"
    ],
    "name:spa_x_preferred":[
        "Bailo"
    ],
    "name:swe_x_preferred":[
        "Bailo"
    ],
    "name:ukr_x_preferred":[
        "\u0411\u0430\u0439\u043b\u043e"
    ],
    "name:uzb_x_preferred":[
        "Bailo"
    ],
    "name:vie_x_preferred":[
        "Bailo"
    ],
    "name:war_x_preferred":[
        "Bailo"
    ],
    "name:zho_x_preferred":[
        "\u62dc\u6d1b"
    ],
    "qs_pg:aaroncc":"ES",
    "qs_pg:gn_country":"ES",
    "qs_pg:gn_fcode":"PPLA3",
    "qs_pg:gn_pop":243,
    "qs_pg:name":"Bailo",
    "qs_pg:name_adm0":"Espa\u00f1a",
    "qs_pg:name_adm1":"Arag\u00f3n",
    "qs_pg:photos_9r":0,
    "qs_pg:photos_sr":0,
    "qs_pg:pop_sr":2,
    "qs_pg:qs_pg_placetype":"locality",
    "qs_pg:qs_pg_placetype_gp":"Town",
    "qs_pg:woe_adm0":23424950,
    "woe:adm0_id":23424950,
    "woe:name_adm0":"Espa\u00f1a",
    "woe:name_adm1":"Arag\u00f3n",
    "woe:placetype":"Town",
    "wof:name":"Bailo",
    "wof:placetype":"locality",
    "wof:population":243
},
  "geometry": {"coordinates":[-0.81136,42.50906],"type":"Point"}
}