{
  "type": "Feature",
  "properties": {
    "gn:admin1_code":"56",
    "gn:admin2_code":"GI",
    "gn:admin3_code":"17031",
    "gn:asciiname":"Vilademires",
    "gn:country_code":"ES",
    "gn:dem":177,
    "gn:feature_class":"P",
    "gn:feature_code":"PPL",
    "gn:name":"Vilademires",
    "gn:population":0,
    "gn:timezone":"Europe/Madrid",
    "iso:country":"ES",
    "name:cat_x_preferred":[
        "Vilademires"
    ],
    "wof:name":"Vilademires",
    "wof:placetype":"locality"
},
  "geometry": {"coordinates":[2.794,42.22931],"type":"Point"}
}