{
  "type": "Feature",
  "properties": {
    "gn:gn_country":"ES",
    "gn:gn_fcode":"PPLA3",
    "gn:gn_pop":365,
    "gn:population":365,
    "iso:country":"ES",
    "name:ara_x_preferred":[
        "\u0623\u0648\u064a\u0648\u0643\u0627\u0633\u064a\u0631\u0648"
    ],
    "name:baq_x_preferred":[
        "Hoyocasero"
    ],
    "name:cat_x_preferred":[
        "Hoyocasero"
    ],
    "name:chi_x_preferred":[
        "\u5965\u7ea6\u5361\u585e\u7f57"
    ],
    "name:dut_x_preferred":[
        "Hoyocasero"
    ],
    "name:eng_x_preferred":[
        "Hoyocasero"
    ],
    "name:fre_x_preferred":[
        "Hoyocasero"
    ],
    "name:hun_x_preferred":[
        "Hoyocasero"
    ],
    "name:ina_x_preferred":[
        "Hoyocasero"
    ],
    "name:ita_x_preferred":[
        "Hoyocasero"
    ],
    "name:kaz_x_preferred":[
        "\u041e\u0439\u043e\u043a\u0430\u0441\u0435\u0440\u043e"
    ],
    "name:mac_x_preferred":[
        "\u0425\u043e\u0458\u043e\u043a\u0430\u0441\u0435\u0440\u043e"
    ],
    "name:may_x_preferred":[
        "Hoyocasero"
    ],
    "name:oci_x_preferred":[
        "Hoyocasero"
    ],
    "name:per_x_preferred":[
        "\u0647\u06cc\u06a9\u0627\u0633\u0631\u0648"
    ],
    "name:pol_x_preferred":[
        "Hoyocasero"
    ],
    "name:por_x_preferred":[
        "Hoyocasero"
    ],
    "name:rus_x_preferred":[
        "\u041e\u0439\u043e\u043a\u0430\u0441\u0435\u0440\u043e"
    ],
    "name:spa_x_preferred":[
        "Hoyocasero"
    ],
    "name:swe_x_preferred":[
        "Hoyocasero"
    ],
    "name:ukr_x_preferred":[
        "\u041e\u0439\u043e\u043a\u0430\u0441\u0435\u0440\u043e"
    ],
    "name:uzb_x_preferred":[
        "Hoyocasero"
    ],
    "name:vie_x_preferred":[
        "Hoyocasero"
    ],
    "name:war_x_preferred":[
        "Hoyocasero"
    ],
    "qs_pg:aaroncc":"ES",
    "qs_pg:gn_country":"ES",
    "qs_pg:gn_fcode":"PPLA3",
    "qs_pg:gn_pop":365,
    "qs_pg:name":"Hoyocasero",
    "qs_pg:name_adm0":"Espa\u00f1a",
    "qs_pg:name_adm1":"Castilla y Le\u00f3n",
    "qs_pg:photos":42,
    "qs_pg:photos_1k":9,
    "qs_pg:photos_9k":1,
    "qs_pg:photos_9r":2,
    "qs_pg:photos_all":42,
    "qs_pg:photos_sr":2,
    "qs_pg:pop_sr":2,
    "qs_pg:qs_pg_placetype":"locality",
    "qs_pg:qs_pg_placetype_gp":"Town",
    "qs_pg:woe_adm0":23424950,
    "woe:adm0_id":23424950,
    "woe:name_adm0":"Espa\u00f1a",
    "woe:name_adm1":"Castilla y Le\u00f3n",
    "woe:placetype":"Town",
    "wof:name":"Hoyocasero",
    "wof:placetype":"locality",
    "wof:population":365
},
  "geometry": {"coordinates":[-4.97455,40.3989],"type":"Point"}
}