{
  "type": "Feature",
  "properties": {
    "gn:admin1_code":"58",
    "gn:admin2_code":"C",
    "gn:admin3_code":"15062",
    "gn:asciiname":"Famelga",
    "gn:country_code":"ES",
    "gn:dem":128,
    "gn:feature_class":"P",
    "gn:feature_code":"PPL",
    "gn:name":"Famelga",
    "gn:population":0,
    "gn:timezone":"Europe/Madrid",
    "iso:country":"ES",
    "name:und_x_variant":[
        "Lafamelga",
        "Famelga"
    ],
    "wof:name":"Famelga",
    "wof:placetype":"locality"
},
  "geometry": {"coordinates":[-8.9358,42.88358],"type":"Point"}
}