{
  "type": "Feature",
  "properties": {
    "gn:admin1_code":"58",
    "gn:admin2_code":"LU",
    "gn:admin3_code":"27018",
    "gn:asciiname":"Sancedo",
    "gn:country_code":"ES",
    "gn:dem":690,
    "gn:feature_class":"P",
    "gn:feature_code":"PPL",
    "gn:name":"Sancedo",
    "gn:population":0,
    "gn:timezone":"Europe/Madrid",
    "iso:country":"ES",
    "wof:name":"Sancedo",
    "wof:placetype":"locality"
},
  "geometry": {"coordinates":[-7.01576,43.0644],"type":"Point"}
}