{
  "type": "Feature",
  "properties": {
    "gn:admin1_code":"58",
    "gn:admin2_code":"LU",
    "gn:admin3_code":"27018",
    "gn:asciiname":"Sancedo",
    "gn:country_code":"ES",
    "gn:dem":690,
    "gn:feature_class":"P",
    "gn:feature_code":"PPL",
    "gn:name":"Sancedo",
    "gn:population":0,
    "gn:timezone":"Europe/Madrid",
    "iso:country":"ES",
    "name:arg_x_preferred":[
        "Sancedo"
    ],
    "name:cat_x_preferred":[
        "Sancedo"
    ],
    "name:ceb_x_preferred":[
        "Sancedo"
    ],
    "name:eus_x_preferred":[
        "Sancedo"
    ],
    "name:fra_x_preferred":[
        "Sancedo"
    ],
    "name:glg_x_preferred":[
        "Sancedo"
    ],
    "name:haw_x_preferred":[
        "Sancedo"
    ],
    "name:hun_x_preferred":[
        "Sancedo"
    ],
    "name:ido_x_preferred":[
        "Sancedo"
    ],
    "name:ina_x_preferred":[
        "Sancedo"
    ],
    "name:ita_x_preferred":[
        "Sancedo"
    ],
    "name:jpn_x_preferred":[
        "\u30b5\u30f3\u30bb\u30fc\u30c9"
    ],
    "name:msa_x_preferred":[
        "Sancedo"
    ],
    "name:oci_x_preferred":[
        "Sancedo"
    ],
    "name:pol_x_preferred":[
        "Sancedo"
    ],
    "name:por_x_preferred":[
        "Sancedo"
    ],
    "name:rus_x_preferred":[
        "\u0421\u0430\u043d\u0441\u0435\u0434\u043e"
    ],
    "name:spa_x_preferred":[
        "Sancedo"
    ],
    "name:swe_x_preferred":[
        "Sancedo"
    ],
    "name:tpi_x_preferred":[
        "Sancedo"
    ],
    "name:ukr_x_preferred":[
        "\u0421\u0430\u043d\u0441\u0435\u0434\u043e"
    ],
    "name:vie_x_preferred":[
        "Sancedo"
    ],
    "name:war_x_preferred":[
        "Sancedo"
    ],
    "name:zho_x_preferred":[
        "\u6851\u585e\u591a"
    ],
    "wof:name":"Sancedo",
    "wof:placetype":"locality"
},
  "geometry": {"coordinates":[-7.01576,43.0644],"type":"Point"}
}