{
  "type": "Feature",
  "properties": {
    "gn:admin1_code":"34",
    "gn:admin2_code":"O",
    "gn:admin3_code":"33072",
    "gn:asciiname":"Villa de Sub",
    "gn:country_code":"ES",
    "gn:dem":1016,
    "gn:feature_class":"P",
    "gn:feature_code":"PPL",
    "gn:name":"Villa de Sub",
    "gn:population":0,
    "gn:timezone":"Europe/Madrid",
    "iso:country":"ES",
    "wof:name":"Villa de Sub",
    "wof:placetype":"locality"
},
  "geometry": {"coordinates":[-6.03936,43.10549],"type":"Point"}
}