{
  "type": "Feature",
  "properties": {
    "gn:admin1_code":"52",
    "gn:admin2_code":"HU",
    "gn:admin3_code":"22150",
    "gn:asciiname":"Barluenga",
    "gn:country_code":"ES",
    "gn:dem":677,
    "gn:feature_class":"P",
    "gn:feature_code":"PPL",
    "gn:name":"Barluenga",
    "gn:population":0,
    "gn:timezone":"Europe/Madrid",
    "iso:country":"ES",
    "wof:name":"Barluenga",
    "wof:placetype":"locality"
},
  "geometry": {"coordinates":[-0.33944,42.20023],"type":"Point"}
}