{
  "type": "Feature",
  "properties": {
    "gn:admin1_code":"51",
    "gn:admin2_code":"CO",
    "gn:admin3_code":"14029",
    "gn:asciiname":"Los Panchez",
    "gn:country_code":"ES",
    "gn:dem":720,
    "gn:feature_class":"P",
    "gn:feature_code":"PPL",
    "gn:name":"Los P\u00e1nchez",
    "gn:population":0,
    "gn:timezone":"Europe/Madrid",
    "iso:country":"ES",
    "name:und_x_variant":[
        "Los P\u00e1nchez"
    ],
    "wof:name":"Los Panchez",
    "wof:placetype":"locality"
},
  "geometry": {"coordinates":[-5.33333,38.18333],"type":"Point"}
}