{
  "type": "Feature",
  "properties": {
    "gn:admin1_code":"51",
    "gn:admin2_code":"GR",
    "gn:admin3_code":"18053",
    "gn:asciiname":"Cuevas de las Cucharetas",
    "gn:country_code":"ES",
    "gn:dem":678,
    "gn:feature_class":"P",
    "gn:feature_code":"PPL",
    "gn:name":"Cuevas de las Cucharetas",
    "gn:population":0,
    "gn:timezone":"Europe/Madrid",
    "iso:country":"ES",
    "name:und_x_variant":[
        "Caser\u00edo Cuevas de las Cucharetas",
        "Cucharetas",
        "Cuevas de las Cucharetas"
    ],
    "wof:name":"Cuevas de las Cucharetas",
    "wof:placetype":"locality"
},
  "geometry": {"coordinates":[-2.78425,37.6304],"type":"Point"}
}