{
  "type": "Feature",
  "properties": {
    "gn:country":"ES",
    "gn:fcode":"PPLA3",
    "gn:population":80,
    "iso:country":"ES",
    "name:ara_x_preferred":[
        "\u062c\u0631\u0627\u0646\u064a\u0631\u0627"
    ],
    "name:arg_x_preferred":[
        "Granera"
    ],
    "name:ast_x_preferred":[
        "Granera"
    ],
    "name:bul_x_preferred":[
        "\u0413\u0440\u0430\u043d\u0435\u0440\u0430"
    ],
    "name:cat_x_preferred":[
        "Granera"
    ],
    "name:ceb_x_preferred":[
        "Granera"
    ],
    "name:che_x_preferred":[
        "\u0413\u0440\u0430\u043d\u0435\u0440\u0430"
    ],
    "name:deu_x_preferred":[
        "Granera"
    ],
    "name:diq_x_preferred":[
        "Granera"
    ],
    "name:eng_x_preferred":[
        "Granera"
    ],
    "name:eus_x_preferred":[
        "Granera"
    ],
    "name:fas_x_preferred":[
        "\u06af\u0631\u0627\u0646\u0631\u0627"
    ],
    "name:fra_x_preferred":[
        "Granera"
    ],
    "name:gle_x_preferred":[
        "Granera"
    ],
    "name:hun_x_preferred":[
        "Granera"
    ],
    "name:hye_x_preferred":[
        "\u0533\u0580\u0561\u0576\u0565\u0580\u0561"
    ],
    "name:ile_x_preferred":[
        "Granera"
    ],
    "name:ita_x_preferred":[
        "Granera"
    ],
    "name:kaz_x_preferred":[
        "\u0413\u0440\u0430\u043d\u0435\u0440\u0430"
    ],
    "name:lat_x_preferred":[
        "Granera"
    ],
    "name:lld_x_preferred":[
        "Granera"
    ],
    "name:msa_x_preferred":[
        "Granera"
    ],
    "name:nld_x_preferred":[
        "Granera"
    ],
    "name:oci_x_preferred":[
        "Granera"
    ],
    "name:pol_x_preferred":[
        "Granera"
    ],
    "name:por_x_preferred":[
        "Granera"
    ],
    "name:ron_x_preferred":[
        "Granera"
    ],
    "name:rus_x_preferred":[
        "\u0413\u0440\u0430\u043d\u0435\u0440\u0430"
    ],
    "name:sco_x_preferred":[
        "Granera"
    ],
    "name:spa_x_preferred":[
        "Granera"
    ],
    "name:sqi_x_preferred":[
        "Granera"
    ],
    "name:swe_x_preferred":[
        "Granera"
    ],
    "name:tat_x_preferred":[
        "\u0413\u0440\u0430\u043d\u0435\u0440\u0430"
    ],
    "name:ukr_x_preferred":[
        "\u0490\u0440\u0430\u043d\u0435\u0440\u0430"
    ],
    "name:uzb_x_preferred":[
        "Granera"
    ],
    "name:vec_x_preferred":[
        "Granera"
    ],
    "name:war_x_preferred":[
        "Granera"
    ],
    "name:zho_x_preferred":[
        "\u683c\u62c9\u5185\u62c9"
    ],
    "qs_pg:aaroncc":"ES",
    "qs_pg:gn_country":"ES",
    "qs_pg:gn_fcode":"PPLA3",
    "qs_pg:gn_pop":80,
    "qs_pg:name":"Granera",
    "qs_pg:name_adm0":"Espa\u00f1a",
    "qs_pg:name_adm1":"Catalunya",
    "qs_pg:photos":38,
    "qs_pg:photos_1k":8,
    "qs_pg:photos_9k":1,
    "qs_pg:photos_9r":2,
    "qs_pg:photos_all":38,
    "qs_pg:photos_sr":2,
    "qs_pg:pop_sr":1,
    "qs_pg:qs_pg_placetype":"locality",
    "qs_pg:qs_pg_placetype_gp":"Town",
    "qs_pg:woe_adm0":23424950,
    "woe:adm0_id":23424950,
    "woe:name_adm0":"Espa\u00f1a",
    "woe:name_adm1":"Catalunya",
    "woe:placetype":"Town",
    "wof:name":"Granera",
    "wof:placetype":"locality",
    "wof:population":80
},
  "geometry": {"coordinates":[2.05924,41.72741],"type":"Point"}
}