{
  "type": "Feature",
  "properties": {
    "gn:gn_country":"ES",
    "gn:gn_fcode":"PPL",
    "gn:gn_pop":7648,
    "gn:population":7648,
    "iso:country":"ES",
    "name:arg_x_preferred":[
        "L'Olleria"
    ],
    "name:cat_x_preferred":[
        "L'Olleria"
    ],
    "name:deu_x_preferred":[
        "L'Olleria"
    ],
    "name:eng_x_preferred":[
        "L'Olleria"
    ],
    "name:eus_x_preferred":[
        "L'Olleria"
    ],
    "name:fas_x_preferred":[
        "\u0644\u0627 \u0641\u0646\u062a \u062f \u0627\u0646 \u06a9\u0627\u0631\u0633"
    ],
    "name:fra_x_preferred":[
        "L'Olleria"
    ],
    "name:hun_x_preferred":[
        "L\u2019Olleria"
    ],
    "name:ita_x_preferred":[
        "L'Olleria"
    ],
    "name:lit_x_preferred":[
        "L'Oljerija"
    ],
    "name:msa_x_preferred":[
        "L'Olleria"
    ],
    "name:nan_x_preferred":[
        "L'Olleria"
    ],
    "name:nld_x_preferred":[
        "L'Olleria"
    ],
    "name:oci_x_preferred":[
        "Olleria"
    ],
    "name:pol_x_preferred":[
        "L'Olleria"
    ],
    "name:por_x_preferred":[
        "L'Olleria"
    ],
    "name:rus_x_preferred":[
        "\u041e\u043b\u044c\u0435\u0440\u0438\u0430"
    ],
    "name:spa_x_preferred":[
        "Oller\u00eda"
    ],
    "name:sqi_x_preferred":[
        "L'Olleria"
    ],
    "name:swe_x_preferred":[
        "L'Olleria"
    ],
    "name:ukr_x_preferred":[
        "\u041b'\u041e\u043b\u044c\u0454\u0440\u0456\u044f"
    ],
    "name:war_x_preferred":[
        "L'Olleria"
    ],
    "name:zho_x_preferred":[
        "\u6d1b\u5217\u91cc\u4e9a"
    ],
    "qs_pg:aaroncc":"ES",
    "qs_pg:gn_country":"ES",
    "qs_pg:gn_fcode":"PPL",
    "qs_pg:gn_pop":7648,
    "qs_pg:name":"Oller\u00eda",
    "qs_pg:name_adm0":"Espa\u00f1a",
    "qs_pg:name_adm1":"Comunitat Valenciana",
    "qs_pg:photos":70,
    "qs_pg:photos_1k":14,
    "qs_pg:photos_9k":1,
    "qs_pg:photos_9r":2,
    "qs_pg:photos_all":70,
    "qs_pg:photos_sr":2,
    "qs_pg:pop_sr":5,
    "qs_pg:qs_pg_placetype":"locality",
    "qs_pg:qs_pg_placetype_gp":"Town",
    "qs_pg:woe_adm0":23424950,
    "woe:adm0_id":23424950,
    "woe:name_adm0":"Espa\u00f1a",
    "woe:name_adm1":"Comunitat Valenciana",
    "woe:placetype":"Town",
    "wof:name":"Oller\u00eda",
    "wof:placetype":"locality",
    "wof:population":7648
},
  "geometry": {"coordinates":[-0.55,38.91667],"type":"Point"}
}