{
  "type": "Feature",
  "properties": {
    "gn:admin1_code":"59",
    "gn:admin2_code":"BI",
    "gn:admin3_code":"48042",
    "gn:asciiname":"Allende",
    "gn:country_code":"ES",
    "gn:dem":109,
    "gn:feature_class":"P",
    "gn:feature_code":"PPL",
    "gn:name":"Allende",
    "gn:population":0,
    "gn:timezone":"Europe/Madrid",
    "iso:country":"ES",
    "wof:name":"Allende",
    "wof:placetype":"locality"
},
  "geometry": {"coordinates":[-3.10191,43.16582],"type":"Point"}
}