{
  "type": "Feature",
  "properties": {
    "gn:admin1_code":"53",
    "gn:admin2_code":"TF",
    "gn:admin3_code":"38003",
    "gn:asciiname":"Quise",
    "gn:country_code":"ES",
    "gn:dem":478,
    "gn:feature_class":"P",
    "gn:feature_code":"PPL",
    "gn:name":"Quise",
    "gn:population":0,
    "gn:timezone":"Atlantic/Canary",
    "iso:country":"ES",
    "wof:name":"Quise",
    "wof:placetype":"locality"
},
  "geometry": {"coordinates":[-17.25694,28.04627],"type":"Point"}
}