{
  "type": "Feature",
  "properties": {
    "gn:gn_country":"ES",
    "gn:gn_fcode":"PPLA3",
    "gn:gn_pop":661,
    "gn:population":661,
    "iso:country":"ES",
    "name:ara_x_preferred":[
        "\u0643\u0627\u0633\u0627\u0633 \u062f\u064a\u0644 \u0643\u0627\u0633\u062a\u0627\u0646\u064a\u0627\u0631"
    ],
    "name:cat_x_preferred":[
        "Casas del Casta\u00f1ar"
    ],
    "name:eng_x_preferred":[
        "Casas del Casta\u00f1ar"
    ],
    "name:epo_x_preferred":[
        "Casas del Casta\u00f1ar"
    ],
    "name:eus_x_preferred":[
        "Casas del Casta\u00f1ar"
    ],
    "name:fra_x_preferred":[
        "Casas del Casta\u00f1ar"
    ],
    "name:hun_x_preferred":[
        "Casas del Casta\u00f1ar"
    ],
    "name:ina_x_preferred":[
        "Casas del Casta\u00f1ar"
    ],
    "name:ita_x_preferred":[
        "Casas del Casta\u00f1ar"
    ],
    "name:msa_x_preferred":[
        "Casas del Casta\u00f1ar"
    ],
    "name:nan_x_preferred":[
        "Casas del Casta\u00f1ar"
    ],
    "name:nld_x_preferred":[
        "Casas del Casta\u00f1ar"
    ],
    "name:oci_x_preferred":[
        "Casas del Casta\u00f1ar"
    ],
    "name:pol_x_preferred":[
        "Casas del Casta\u00f1ar"
    ],
    "name:por_x_preferred":[
        "Casas del Casta\u00f1ar"
    ],
    "name:ron_x_preferred":[
        "Casas del Casta\u00f1ar"
    ],
    "name:rus_x_preferred":[
        "\u041a\u0430\u0441\u0430\u0441-\u0434\u0435\u043b\u044c-\u041a\u0430\u0441\u0442\u0430\u043d\u044c\u044f\u0440"
    ],
    "name:sco_x_preferred":[
        "Casas del Casta\u00f1ar"
    ],
    "name:spa_x_preferred":[
        "Casas del Casta\u00f1ar"
    ],
    "name:swe_x_preferred":[
        "Casas del Casta\u00f1ar"
    ],
    "name:ukr_x_preferred":[
        "\u041a\u0430\u0441\u0430\u0441-\u0434\u0435\u043b\u044c-\u041a\u0430\u0441\u0442\u0430\u043d\u044c\u044f\u0440"
    ],
    "name:uzb_x_preferred":[
        "Casas del Casta\u00f1ar"
    ],
    "name:vie_x_preferred":[
        "Casas del Casta\u00f1ar"
    ],
    "name:war_x_preferred":[
        "Casas del Casta\u00f1ar"
    ],
    "name:zho_x_preferred":[
        "\u5361\u8428\u65af\u5fb7\u5c14\u5361\u65af\u5854\u5c3c\u4e9a\u5c14"
    ],
    "qs_pg:aaroncc":"ES",
    "qs_pg:gn_country":"ES",
    "qs_pg:gn_fcode":"PPLA3",
    "qs_pg:gn_pop":661,
    "qs_pg:name":"Casas del Casta\u00f1ar",
    "qs_pg:name_adm0":"Espa\u00f1a",
    "qs_pg:name_adm1":"Extremadura",
    "qs_pg:photos":127,
    "qs_pg:photos_1k":26,
    "qs_pg:photos_9k":1,
    "qs_pg:photos_9r":3,
    "qs_pg:photos_all":127,
    "qs_pg:photos_sr":3,
    "qs_pg:pop_sr":2,
    "qs_pg:qs_pg_placetype":"locality",
    "qs_pg:qs_pg_placetype_gp":"Town",
    "qs_pg:woe_adm0":23424950,
    "woe:adm0_id":23424950,
    "woe:name_adm0":"Espa\u00f1a",
    "woe:name_adm1":"Extremadura",
    "woe:placetype":"Town",
    "wof:name":"Casas del Casta\u00f1ar",
    "wof:placetype":"locality",
    "wof:population":661
},
  "geometry": {"coordinates":[-5.90509,40.10785],"type":"Point"}
}