{
  "type": "Feature",
  "properties": {
    "gn:admin1_code":"52",
    "gn:admin2_code":"HU",
    "gn:admin3_code":"22173",
    "gn:asciiname":"Yeste",
    "gn:country_code":"ES",
    "gn:dem":563,
    "gn:feature_class":"P",
    "gn:feature_code":"PPL",
    "gn:name":"Yeste",
    "gn:population":0,
    "gn:timezone":"Europe/Madrid",
    "iso:country":"ES",
    "wof:name":"Yeste",
    "wof:placetype":"locality"
},
  "geometry": {"coordinates":[-0.68333,42.38333],"type":"Point"}
}