{
  "type": "Feature",
  "properties": {
    "gn:country":"ES",
    "gn:fcode":"PPL",
    "gn:population":403,
    "iso:country":"ES",
    "name:ara_x_preferred":[
        "\u0646\u0627\u0641\u0627\u0644\u0648\u0646\u063a\u064a\u0627"
    ],
    "name:ast_x_preferred":[
        "Navalonguilla"
    ],
    "name:azb_x_preferred":[
        "\u0646\u0627\u0628\u0627\u0644\u0646\u0642\u06cc\u06cc\u0627"
    ],
    "name:cat_x_preferred":[
        "Navalonguilla"
    ],
    "name:ceb_x_preferred":[
        "Navalonguilla"
    ],
    "name:eng_x_preferred":[
        "Navalonguilla"
    ],
    "name:eus_x_preferred":[
        "Navalonguilla"
    ],
    "name:fas_x_preferred":[
        "\u0646\u0627\u0628\u0627\u0644\u0646\u06af\u06cc\u06cc\u0627"
    ],
    "name:fra_x_preferred":[
        "Navalonguilla"
    ],
    "name:hun_x_preferred":[
        "Navalonguilla"
    ],
    "name:ina_x_preferred":[
        "Navalonguilla"
    ],
    "name:ita_x_preferred":[
        "Navalonguilla"
    ],
    "name:kaz_x_preferred":[
        "\u041d\u0430\u0432\u0430\u043b\u043e\u043d\u0433\u0438\u043b\u044c\u044f"
    ],
    "name:mkd_x_preferred":[
        "\u041d\u0430\u0432\u0430\u043b\u043e\u043d\u0433\u0443\u0438\u043b\u0430"
    ],
    "name:msa_x_preferred":[
        "Navalonguilla"
    ],
    "name:nld_x_preferred":[
        "Navalonguilla"
    ],
    "name:oci_x_preferred":[
        "Navalonguilla"
    ],
    "name:pol_x_preferred":[
        "Navalonguilla"
    ],
    "name:por_x_preferred":[
        "Navalonguilla"
    ],
    "name:rus_x_preferred":[
        "\u041d\u0430\u0432\u0430\u043b\u043e\u043d\u0433\u0438\u043b\u044c\u044f"
    ],
    "name:spa_x_preferred":[
        "Navalonguilla"
    ],
    "name:srd_x_preferred":[
        "Navalonguilla"
    ],
    "name:swe_x_preferred":[
        "Navalonguilla"
    ],
    "name:ukr_x_preferred":[
        "\u041d\u0430\u0432\u0430\u043b\u043e\u043d\u0433\u0456\u043b\u044c\u044f"
    ],
    "name:uzb_x_preferred":[
        "Navalonguilla"
    ],
    "name:vie_x_preferred":[
        "Navalonguilla"
    ],
    "name:war_x_preferred":[
        "Navalonguilla"
    ],
    "name:zho_x_preferred":[
        "\u7eb3\u74e6\u9686\u5409\u5229\u4e9a"
    ],
    "qs_pg:aaroncc":"ES",
    "qs_pg:gn_country":"ES",
    "qs_pg:gn_fcode":"PPL",
    "qs_pg:gn_pop":403,
    "qs_pg:name":"Navalonguilla",
    "qs_pg:name_adm0":"Espa\u00f1a",
    "qs_pg:name_adm1":"Castilla y Le\u00f3n",
    "qs_pg:photos":395,
    "qs_pg:photos_1k":80,
    "qs_pg:photos_9k":2,
    "qs_pg:photos_9r":5,
    "qs_pg:photos_all":395,
    "qs_pg:photos_sr":6,
    "qs_pg:pop_sr":2,
    "qs_pg:qs_pg_placetype":"locality",
    "qs_pg:qs_pg_placetype_gp":"Town",
    "qs_pg:woe_adm0":23424950,
    "woe:adm0_id":23424950,
    "woe:name_adm0":"Espa\u00f1a",
    "woe:name_adm1":"Castilla y Le\u00f3n",
    "woe:placetype":"Town",
    "wof:name":"Navalonguilla",
    "wof:placetype":"locality",
    "wof:population":403
},
  "geometry": {"coordinates":[-5.50042,40.27835],"type":"Point"}
}