{
  "type": "Feature",
  "properties": {
    "gn:admin1_code":"59",
    "gn:admin2_code":"SS",
    "gn:admin3_code":"20003",
    "gn:asciiname":"Aizarnazabal",
    "gn:country_code":"ES",
    "gn:dem":58,
    "gn:feature_class":"P",
    "gn:feature_code":"PPLA3",
    "gn:name":"Aizarnazabal",
    "gn:population":602,
    "gn:timezone":"Europe/Madrid",
    "iso:country":"ES",
    "name:ara_x_preferred":[
        "\u0623\u064a\u062b\u0627\u0631\u0646\u0627\u062b\u0627\u0628\u0627\u0644"
    ],
    "name:arg_x_preferred":[
        "Aizarnazabal"
    ],
    "name:ast_x_preferred":[
        "Aizarnazabal"
    ],
    "name:bre_x_preferred":[
        "Aizarnazabal"
    ],
    "name:cat_x_preferred":[
        "Aizarnazabal"
    ],
    "name:ceb_x_preferred":[
        "Aizarnazabal"
    ],
    "name:est_x_preferred":[
        "Aizarnazabal"
    ],
    "name:eus_x_preferred":[
        "Aizarnazabal"
    ],
    "name:fra_x_preferred":[
        "Aizarnazabal"
    ],
    "name:glg_x_preferred":[
        "Aizarnazabal"
    ],
    "name:hun_x_preferred":[
        "Aizarnazabal"
    ],
    "name:ita_x_preferred":[
        "Aizarnazabal"
    ],
    "name:msa_x_preferred":[
        "Aizarnazabal"
    ],
    "name:nld_x_preferred":[
        "Aizarnazabal"
    ],
    "name:oci_x_preferred":[
        "Aizarnazabal"
    ],
    "name:pol_x_preferred":[
        "Aizarnazabal"
    ],
    "name:por_x_preferred":[
        "Aizarnazabal"
    ],
    "name:rus_x_preferred":[
        "\u0410\u0439\u0441\u0430\u0440\u043d\u0430\u0441\u0430\u0431\u0430\u043b\u044c"
    ],
    "name:sco_x_preferred":[
        "Aizarnazabal"
    ],
    "name:spa_x_preferred":[
        "Aizarnaz\u00e1bal"
    ],
    "name:swe_x_preferred":[
        "Aizarnazabal"
    ],
    "name:ukr_x_preferred":[
        "\u0410\u0439\u0441\u0430\u0440\u043d\u0430\u0441\u0430\u0431\u0430\u043b\u044c"
    ],
    "name:uzb_x_preferred":[
        "Aizarnazabal"
    ],
    "name:vie_x_preferred":[
        "Aizarnazabal"
    ],
    "name:war_x_preferred":[
        "Aizarnazabal"
    ],
    "name:zho_x_preferred":[
        "\u827e\u8428\u5c14\u7eb3\u8428\u74e6\u5c14"
    ],
    "wof:name":"Aizarnazabal",
    "wof:placetype":"locality",
    "wof:population":602
},
  "geometry": {"coordinates":[-2.23607,43.25591],"type":"Point"}
}