{
  "type": "Feature",
  "properties": {
    "gn:admin1_code":"59",
    "gn:admin2_code":"SS",
    "gn:admin3_code":"20003",
    "gn:asciiname":"Aizarnazabal",
    "gn:country_code":"ES",
    "gn:dem":58,
    "gn:feature_class":"P",
    "gn:feature_code":"PPLA3",
    "gn:name":"Aizarnazabal",
    "gn:population":602,
    "gn:timezone":"Europe/Madrid",
    "iso:country":"ES",
    "name:eus_x_preferred":[
        "Aizarnazabal"
    ],
    "name:spa_x_preferred":[
        "Aizarnaz\u00e1bal"
    ],
    "wof:name":"Aizarnazabal",
    "wof:placetype":"locality",
    "wof:population":602
},
  "geometry": {"coordinates":[-2.23607,43.25591],"type":"Point"}
}