{
  "type": "Feature",
  "properties": {
    "gn:admin1_code":"32",
    "gn:admin3_code":"31049",
    "gn:asciiname":"Udabe",
    "gn:cc2":"ES",
    "gn:country_code":"ES",
    "gn:dem":586,
    "gn:feature_class":"P",
    "gn:feature_code":"PPL",
    "gn:name":"Udabe",
    "gn:population":0,
    "gn:timezone":"Europe/Madrid",
    "iso:country":"ES",
    "name:eus_x_preferred":[
        "Udabe"
    ],
    "name:spa_x_preferred":[
        "Udave"
    ],
    "name:und_x_variant":[
        "Udave"
    ],
    "wof:name":"Udabe",
    "wof:placetype":"locality"
},
  "geometry": {"coordinates":[-1.8257,42.9742],"type":"Point"}
}