{
  "type": "Feature",
  "properties": {
    "gn:gn_country":"ES",
    "gn:gn_fcode":"PPLA3",
    "gn:gn_pop":128,
    "gn:population":128,
    "iso:country":"ES",
    "name:ara_x_preferred":[
        "\u0623\u0644\u0628\u0648\u0631\u062e\u064a"
    ],
    "name:arg_x_preferred":[
        "Alborche"
    ],
    "name:baq_x_preferred":[
        "Alborge"
    ],
    "name:cat_x_preferred":[
        "Alborge"
    ],
    "name:chi_x_preferred":[
        "\u963f\u5c14\u6c83\u5c14\u8d6b"
    ],
    "name:dut_x_preferred":[
        "Alborge"
    ],
    "name:eng_x_preferred":[
        "Alborge"
    ],
    "name:fre_x_preferred":[
        "Alborge"
    ],
    "name:hun_x_preferred":[
        "Alborge"
    ],
    "name:ita_x_preferred":[
        "Alborge"
    ],
    "name:kaz_x_preferred":[
        "\u0410\u043b\u044c\u0431\u043e\u0440\u0445\u0435"
    ],
    "name:may_x_preferred":[
        "Alborge"
    ],
    "name:nan_x_preferred":[
        "Alborge"
    ],
    "name:oci_x_preferred":[
        "Alborge"
    ],
    "name:pol_x_preferred":[
        "Alborge"
    ],
    "name:por_x_preferred":[
        "Alborge"
    ],
    "name:rus_x_preferred":[
        "\u0410\u043b\u044c\u0431\u043e\u0440\u0445\u0435"
    ],
    "name:spa_x_preferred":[
        "Alborge"
    ],
    "name:swe_x_preferred":[
        "Alborge"
    ],
    "name:ukr_x_preferred":[
        "\u0410\u043b\u044c\u0431\u043e\u0440\u0445\u0435"
    ],
    "name:uzb_x_preferred":[
        "Alborge"
    ],
    "name:vie_x_preferred":[
        "Alborge"
    ],
    "name:war_x_preferred":[
        "Alborge"
    ],
    "qs_pg:aaroncc":"ES",
    "qs_pg:gn_country":"ES",
    "qs_pg:gn_fcode":"PPLA3",
    "qs_pg:gn_pop":128,
    "qs_pg:name":"Alborge",
    "qs_pg:name_adm0":"Espa\u00f1a",
    "qs_pg:name_adm1":"Arag\u00f3n",
    "qs_pg:photos":439,
    "qs_pg:photos_1k":89,
    "qs_pg:photos_9k":2,
    "qs_pg:photos_9r":5,
    "qs_pg:photos_all":439,
    "qs_pg:photos_sr":6,
    "qs_pg:pop_sr":1,
    "qs_pg:qs_pg_placetype":"locality",
    "qs_pg:qs_pg_placetype_gp":"Town",
    "qs_pg:woe_adm0":23424950,
    "woe:adm0_id":23424950,
    "woe:name_adm0":"Espa\u00f1a",
    "woe:name_adm1":"Arag\u00f3n",
    "woe:placetype":"Town",
    "wof:name":"Alborge",
    "wof:placetype":"locality",
    "wof:population":128
},
  "geometry": {"coordinates":[-0.35675,41.33367],"type":"Point"}
}