{
  "type": "Feature",
  "properties": {
    "gn:admin1_code":"58",
    "gn:admin2_code":"OR",
    "gn:admin3_code":"32016",
    "gn:asciiname":"Lobas",
    "gn:country_code":"ES",
    "gn:dem":921,
    "gn:feature_class":"P",
    "gn:feature_code":"PPL",
    "gn:name":"Lob\u00e1s",
    "gn:population":0,
    "gn:timezone":"Europe/Madrid",
    "iso:country":"ES",
    "wof:name":"Lobas",
    "wof:placetype":"locality"
},
  "geometry": {"coordinates":[-7.8435,41.97825],"type":"Point"}
}