{
  "type": "Feature",
  "properties": {
    "gn:admin1_code":"58",
    "gn:admin2_code":"OR",
    "gn:admin3_code":"32086",
    "gn:asciiname":"Servainza",
    "gn:country_code":"ES",
    "gn:dem":1153,
    "gn:feature_class":"P",
    "gn:feature_code":"PPL",
    "gn:name":"Servainza",
    "gn:population":0,
    "gn:timezone":"Europe/Madrid",
    "iso:country":"ES",
    "wof:name":"Servainza",
    "wof:placetype":"locality"
},
  "geometry": {"coordinates":[-7.19167,42.20499],"type":"Point"}
}