{
  "type": "Feature",
  "properties": {
    "iso:country":"ES",
    "name:ara_x_preferred":[
        "\u0641\u064a\u0627\u0631\u064a\u0627\u0644 \u062f\u064a \u0623\u0644\u0627\u0641\u0627"
    ],
    "name:arg_x_preferred":[
        "Legutio"
    ],
    "name:ast_x_preferred":[
        "Legutio"
    ],
    "name:azb_x_preferred":[
        "\u0644\u0642\u0648\u062a\u06cc\u0627\u0646\u0648"
    ],
    "name:bre_x_preferred":[
        "Legutio"
    ],
    "name:bul_x_preferred":[
        "\u041b\u0435\u0433\u0443\u0442\u0438\u043e"
    ],
    "name:cat_x_preferred":[
        "Legutio"
    ],
    "name:ceb_x_preferred":[
        "Legutio"
    ],
    "name:eng_x_preferred":[
        "Legutio"
    ],
    "name:eus_x_preferred":[
        "Legutio"
    ],
    "name:eus_x_variant":[
        "Bilerle",
        "Legutiano"
    ],
    "name:fas_x_preferred":[
        "\u0644\u06af\u0648\u062a\u06cc\u0627\u0646\u0648"
    ],
    "name:fra_x_preferred":[
        "Legutio"
    ],
    "name:glg_x_preferred":[
        "Legutio"
    ],
    "name:hun_x_preferred":[
        "Legutio"
    ],
    "name:ita_x_preferred":[
        "Legutio"
    ],
    "name:jpn_x_preferred":[
        "\u30ec\u30b0\u30c6\u30a3\u30a2\u30fc\u30ce"
    ],
    "name:mkd_x_preferred":[
        "\u041b\u0435\u0433\u0443\u0442\u0438\u0430\u043d\u043e"
    ],
    "name:msa_x_preferred":[
        "Legutio"
    ],
    "name:nan_x_preferred":[
        "Legutiano"
    ],
    "name:nld_x_preferred":[
        "Legutio"
    ],
    "name:oci_x_preferred":[
        "Legutio"
    ],
    "name:pol_x_preferred":[
        "Legutiano"
    ],
    "name:por_x_preferred":[
        "Legutio"
    ],
    "name:rus_x_preferred":[
        "\u0412\u0438\u043b\u044c\u044f\u0440\u0440\u0435\u0430\u043b\u044c-\u0434\u0435-\u0410\u043b\u0430\u0432\u0430"
    ],
    "name:sco_x_preferred":[
        "Legutio"
    ],
    "name:spa_x_preferred":[
        "Legutiano",
        "Villarreal de \u00c1lava"
    ],
    "name:spa_x_variant":[
        "Villarreal",
        "Villarreal de Alava"
    ],
    "name:swe_x_preferred":[
        "Legutio"
    ],
    "name:tur_x_preferred":[
        "Legutio"
    ],
    "name:ukr_x_preferred":[
        "\u041b\u0435\u0433\u0443\u0442\u0456\u0430\u043d\u043e"
    ],
    "name:uzb_x_preferred":[
        "Legutio"
    ],
    "name:vie_x_preferred":[
        "Legutio"
    ],
    "name:vie_x_variant":[
        "Legutiano"
    ],
    "name:war_x_preferred":[
        "Legutio"
    ],
    "name:war_x_variant":[
        "Legutiano"
    ],
    "name:zho_min_nan_x_preferred":[
        "Legutiano"
    ],
    "name:zho_x_preferred":[
        "\u83b1\u53e4\u8482\u4e9a\u8bfa"
    ],
    "qs:a0":"Espa\u00f1a",
    "qs:a1":"*Araba/\u00c1lava",
    "qs:a1r":"0Pa\u00eds Vasco",
    "qs:adm0":"Espa\u00f1a",
    "qs:la_lc":"*",
    "qs:level":"locality",
    "qs:loc":"Legutiano",
    "qs:loc_alt":"Legutiano",
    "qs:pop":0,
    "qs:type":"buffered point",
    "wd:wordcount":51,
    "wof:lang":[
        "spa"
    ],
    "wof:name":"Legutiano",
    "wof:placetype":"locality"
},
  "geometry": {"coordinates":[-2.642626,42.979847],"type":"Point"}
}