{
  "type": "Feature",
  "properties": {
    "gn:admin1_code":"31",
    "gn:admin2_code":"MU",
    "gn:admin3_code":"30021",
    "gn:asciiname":"Los Guerreros",
    "gn:country_code":"ES",
    "gn:dem":154,
    "gn:feature_class":"P",
    "gn:feature_code":"PPL",
    "gn:name":"Los Guerreros",
    "gn:population":0,
    "gn:timezone":"Europe/Madrid",
    "iso:country":"ES",
    "name:deu_x_preferred":[
        "Los Guerreros"
    ],
    "name:fra_x_preferred":[
        "Los Guerreros"
    ],
    "name:ita_x_preferred":[
        "Los Guerreros"
    ],
    "name:kor_x_preferred":[
        "\ub85c\uc2a4 \uac8c\ub808\ub85c\uc988"
    ],
    "name:por_x_preferred":[
        "Los Guerreros"
    ],
    "name:spa_x_preferred":[
        "Los Guerreros"
    ],
    "name:tha_x_preferred":[
        "\u0e42\u0e25\u0e2a\u0e40\u0e01\u0e23\u0e4c\u0e40\u0e23\u0e42\u0e23\u0e2a\u0e4c"
    ],
    "name:und_x_variant":[
        "Caser\u00edo Los Guerreros",
        "Los Guerreros"
    ],
    "wof:name":"Los Guerreros",
    "wof:placetype":"locality"
},
  "geometry": {"coordinates":[-1.22277,37.73365],"type":"Point"}
}