{
  "type": "Feature",
  "properties": {
    "gn:admin1_code":"31",
    "gn:admin2_code":"MU",
    "gn:admin3_code":"30021",
    "gn:asciiname":"Los Guerreros",
    "gn:country_code":"ES",
    "gn:dem":154,
    "gn:feature_class":"P",
    "gn:feature_code":"PPL",
    "gn:name":"Los Guerreros",
    "gn:population":0,
    "gn:timezone":"Europe/Madrid",
    "iso:country":"ES",
    "name:und_x_variant":[
        "Caser\u00edo Los Guerreros",
        "Los Guerreros"
    ],
    "wof:name":"Los Guerreros",
    "wof:placetype":"locality"
},
  "geometry": {"coordinates":[-1.22277,37.73365],"type":"Point"}
}