{
  "type": "Feature",
  "properties": {
    "gn:admin1_code":"60",
    "gn:admin2_code":"CS",
    "gn:admin3_code":"12108",
    "gn:asciiname":"Benitandus",
    "gn:country_code":"ES",
    "gn:dem":337,
    "gn:feature_class":"P",
    "gn:feature_code":"PPL",
    "gn:name":"Benitand\u00fas",
    "gn:population":0,
    "gn:timezone":"Europe/Madrid",
    "iso:country":"ES",
    "name:und_x_variant":[
        "Benitand\u00fas"
    ],
    "wof:name":"Benitandus",
    "wof:placetype":"locality"
},
  "geometry": {"coordinates":[-0.33333,39.95],"type":"Point"}
}