{
  "type": "Feature",
  "properties": {
    "gn:admin1_code":"55",
    "gn:admin2_code":"LE",
    "gn:admin3_code":"24182",
    "gn:asciiname":"Tejados",
    "gn:country_code":"ES",
    "gn:dem":847,
    "gn:feature_class":"P",
    "gn:feature_code":"PPL",
    "gn:name":"Tejados",
    "gn:population":0,
    "gn:timezone":"Europe/Madrid",
    "iso:country":"ES",
    "wof:name":"Tejados",
    "wof:placetype":"locality"
},
  "geometry": {"coordinates":[-6.03861,42.36831],"type":"Point"}
}