{
  "type": "Feature",
  "properties": {
    "gn:country":"ES",
    "gn:fcode":"PPLA3",
    "gn:population":214,
    "iso:country":"ES",
    "name:ast_x_preferred":[
        "Vertavillo"
    ],
    "name:azb_x_preferred":[
        "\u0628\u0631\u062a\u0627\u0628\u06cc\u06cc\u0648"
    ],
    "name:cat_x_preferred":[
        "Vertavillo"
    ],
    "name:ceb_x_preferred":[
        "Vertavillo"
    ],
    "name:che_x_preferred":[
        "\u0412\u0435\u0440\u0442\u0430\u0432\u0438\u043b\u044c\u043e"
    ],
    "name:eng_x_preferred":[
        "Vertavillo"
    ],
    "name:epo_x_preferred":[
        "Vertavillo"
    ],
    "name:eus_x_preferred":[
        "Vertavillo"
    ],
    "name:fas_x_preferred":[
        "\u0628\u0631\u062a\u0627\u0628\u06cc\u06cc\u0648"
    ],
    "name:fra_x_preferred":[
        "Vertavillo"
    ],
    "name:gle_x_preferred":[
        "Vertavillo"
    ],
    "name:glg_x_preferred":[
        "Vertavillo"
    ],
    "name:hun_x_preferred":[
        "Vertavillo"
    ],
    "name:ile_x_preferred":[
        "Vertavillo"
    ],
    "name:ina_x_preferred":[
        "Vertavillo"
    ],
    "name:ita_x_preferred":[
        "Vertavillo"
    ],
    "name:lld_x_preferred":[
        "Vertavillo"
    ],
    "name:ltz_x_preferred":[
        "Vertavillo"
    ],
    "name:msa_x_preferred":[
        "Vertavillo"
    ],
    "name:nan_x_preferred":[
        "Vertavillo"
    ],
    "name:nld_x_preferred":[
        "Vertavillo"
    ],
    "name:nob_x_preferred":[
        "Vertavillo"
    ],
    "name:oci_x_preferred":[
        "Vertavillo"
    ],
    "name:pol_x_preferred":[
        "Vertavillo"
    ],
    "name:por_x_preferred":[
        "Vertavillo"
    ],
    "name:rus_x_preferred":[
        "\u0412\u0435\u0440\u0442\u0430\u0432\u0438\u043b\u044c\u043e"
    ],
    "name:spa_x_preferred":[
        "Vertavillo"
    ],
    "name:swe_x_preferred":[
        "Vertavillo"
    ],
    "name:tat_x_preferred":[
        "\u0412\u0435\u0440\u0442\u0430\u0432\u0438\u043b\u044c\u043e"
    ],
    "name:ukr_x_preferred":[
        "\u0412\u0435\u0440\u0442\u0430\u0432\u0456\u043b\u044c\u0439\u043e"
    ],
    "name:uzb_x_preferred":[
        "Vertavillo"
    ],
    "name:vec_x_preferred":[
        "Vertavillo"
    ],
    "name:vie_x_preferred":[
        "Vertavillo"
    ],
    "name:war_x_preferred":[
        "Vertavillo"
    ],
    "name:zho_x_preferred":[
        "\u8d1d\u5c14\u5854\u7ef4\u7565"
    ],
    "qs_pg:aaroncc":"ES",
    "qs_pg:gn_country":"ES",
    "qs_pg:gn_fcode":"PPLA3",
    "qs_pg:gn_pop":214,
    "qs_pg:name":"Vertavillo",
    "qs_pg:name_adm0":"Espa\u00f1a",
    "qs_pg:name_adm1":"Castilla y Le\u00f3n",
    "qs_pg:photos":87,
    "qs_pg:photos_1k":18,
    "qs_pg:photos_9k":1,
    "qs_pg:photos_9r":3,
    "qs_pg:photos_all":87,
    "qs_pg:photos_sr":3,
    "qs_pg:pop_sr":2,
    "qs_pg:qs_pg_placetype":"locality",
    "qs_pg:qs_pg_placetype_gp":"Town",
    "qs_pg:woe_adm0":23424950,
    "woe:adm0_id":23424950,
    "woe:name_adm0":"Espa\u00f1a",
    "woe:name_adm1":"Castilla y Le\u00f3n",
    "woe:placetype":"Town",
    "wof:name":"Vertavillo",
    "wof:placetype":"locality",
    "wof:population":214
},
  "geometry": {"coordinates":[-4.32707,41.83281],"type":"Point"}
}