{
  "type": "Feature",
  "properties": {
    "gn:admin1_code":"34",
    "gn:admin2_code":"O",
    "gn:admin3_code":"33023",
    "gn:asciiname":"Penadecabras",
    "gn:country_code":"ES",
    "gn:dem":424,
    "gn:feature_class":"P",
    "gn:feature_code":"PPL",
    "gn:name":"Penadecabras",
    "gn:population":0,
    "gn:timezone":"Europe/Madrid",
    "iso:country":"ES",
    "wof:name":"Penadecabras",
    "wof:placetype":"locality"
},
  "geometry": {"coordinates":[-6.84711,43.46227],"type":"Point"}
}