{
  "type": "Feature",
  "properties": {
    "gn:admin1_code":"58",
    "gn:admin2_code":"LU",
    "gn:admin3_code":"27057",
    "gn:asciiname":"Cesar",
    "gn:country_code":"ES",
    "gn:dem":588,
    "gn:feature_class":"P",
    "gn:feature_code":"PPL",
    "gn:name":"C\u00e9sar",
    "gn:population":0,
    "gn:timezone":"Europe/Madrid",
    "iso:country":"ES",
    "name:und_x_variant":[
        "C\u00e9sar"
    ],
    "wof:name":"Cesar",
    "wof:placetype":"locality"
},
  "geometry": {"coordinates":[-7.41467,42.74793],"type":"Point"}
}