{
  "type": "Feature",
  "properties": {
    "gn:gn_country":"ES",
    "gn:gn_fcode":"PPLA3",
    "gn:gn_pop":176,
    "gn:population":176,
    "iso:country":"ES",
    "name:alb_x_preferred":[
        "Rab\u00f3s"
    ],
    "name:ara_x_preferred":[
        "\u0631\u0627\u0628\u0648\u0633"
    ],
    "name:arg_x_preferred":[
        "Rab\u00f3s"
    ],
    "name:arm_x_preferred":[
        "\u054c\u0561\u0562\u0578\u057d"
    ],
    "name:baq_x_preferred":[
        "Rab\u00f3s"
    ],
    "name:cat_x_preferred":[
        "Rab\u00f3s"
    ],
    "name:chi_x_preferred":[
        "\u62c9\u6c83\u65af"
    ],
    "name:dut_x_preferred":[
        "Rab\u00f3s"
    ],
    "name:eng_x_preferred":[
        "Rab\u00f3s"
    ],
    "name:fre_x_preferred":[
        "Rab\u00f3s"
    ],
    "name:ger_x_preferred":[
        "Rab\u00f3s"
    ],
    "name:hun_x_preferred":[
        "Rab\u00f3s"
    ],
    "name:ita_x_preferred":[
        "Rab\u00f3s"
    ],
    "name:kaz_x_preferred":[
        "\u0420\u0430\u0431\u043e\u0441"
    ],
    "name:lat_x_preferred":[
        "Rab\u00f3s"
    ],
    "name:may_x_preferred":[
        "Rab\u00f3s"
    ],
    "name:oci_x_preferred":[
        "Rab\u00f3s"
    ],
    "name:pam_x_preferred":[
        "Rab\u00f3s"
    ],
    "name:pol_x_preferred":[
        "Rab\u00f3s"
    ],
    "name:por_x_preferred":[
        "Rab\u00f3s"
    ],
    "name:rum_x_preferred":[
        "Rab\u00f3s"
    ],
    "name:rus_x_preferred":[
        "\u0420\u0430\u0431\u043e\u0441"
    ],
    "name:spa_x_preferred":[
        "Rab\u00f3s"
    ],
    "name:swe_x_preferred":[
        "Rab\u00f3s"
    ],
    "name:tah_x_preferred":[
        "Rab\u00f3s"
    ],
    "name:ukr_x_preferred":[
        "\u0420\u0430\u0431\u043e\u0441"
    ],
    "name:uzb_x_preferred":[
        "Rab\u00f3s"
    ],
    "name:vie_x_preferred":[
        "Rab\u00f3s"
    ],
    "name:war_x_preferred":[
        "Rab\u00f3s"
    ],
    "qs_pg:aaroncc":"ES",
    "qs_pg:gn_country":"ES",
    "qs_pg:gn_fcode":"PPLA3",
    "qs_pg:gn_pop":176,
    "qs_pg:name":"Rab\u00f3s",
    "qs_pg:name_adm0":"Espa\u00f1a",
    "qs_pg:name_adm1":"Catalunya",
    "qs_pg:photos":31,
    "qs_pg:photos_1k":6,
    "qs_pg:photos_9k":1,
    "qs_pg:photos_9r":2,
    "qs_pg:photos_all":31,
    "qs_pg:photos_sr":2,
    "qs_pg:pop_sr":1,
    "qs_pg:qs_pg_placetype":"locality",
    "qs_pg:qs_pg_placetype_gp":"Town",
    "qs_pg:woe_adm0":23424950,
    "woe:adm0_id":23424950,
    "woe:name_adm0":"Espa\u00f1a",
    "woe:name_adm1":"Catalunya",
    "woe:placetype":"Town",
    "wof:name":"Rab\u00f3s",
    "wof:placetype":"locality",
    "wof:population":176
},
  "geometry": {"coordinates":[3.02828,42.3789],"type":"Point"}
}