{
  "type": "Feature",
  "properties": {
    "gn:gn_country":"ES",
    "gn:gn_fcode":"PPLA3",
    "gn:gn_pop":213,
    "gn:population":213,
    "iso:country":"ES",
    "name:ara_x_preferred":[
        "\u0633\u0627\u0646\u062a\u0627 \u0643\u0631\u0648\u062b \u062f\u064a \u063a\u0631\u064a\u0648"
    ],
    "name:arg_x_preferred":[
        "Santa Cruz de Griu"
    ],
    "name:baq_x_preferred":[
        "Santa Cruz de Grio"
    ],
    "name:cat_x_preferred":[
        "Santa Cruz de Gr\u00edo"
    ],
    "name:chi_x_preferred":[
        "\u5723\u514b\u9c81\u65af\u5fb7\u683c\u91cc\u5965"
    ],
    "name:dut_x_preferred":[
        "Santa Cruz de Gr\u00edo"
    ],
    "name:eng_x_preferred":[
        "Santa Cruz de Gr\u00edo"
    ],
    "name:fre_x_preferred":[
        "Santa Cruz de Gr\u00edo"
    ],
    "name:ger_x_preferred":[
        "Santa Cruz de Gr\u00edo"
    ],
    "name:hun_x_preferred":[
        "Santa Cruz de Gr\u00edo"
    ],
    "name:ita_x_preferred":[
        "Santa Cruz de Gr\u00edo"
    ],
    "name:kaz_x_preferred":[
        "\u0421\u0430\u043d\u0442\u0430-\u041a\u0440\u0443\u0441-\u0434\u0435-\u0413\u0440\u0438\u043e"
    ],
    "name:may_x_preferred":[
        "Santa Cruz de Gr\u00edo"
    ],
    "name:nan_x_preferred":[
        "Santa Cruz de Gr\u00edo"
    ],
    "name:oci_x_preferred":[
        "Santa Cruz de Gr\u00edo"
    ],
    "name:pol_x_preferred":[
        "Santa Cruz de Gr\u00edo"
    ],
    "name:por_x_preferred":[
        "Santa Cruz de Gr\u00edo"
    ],
    "name:rus_x_preferred":[
        "\u0421\u0430\u043d\u0442\u0430-\u041a\u0440\u0443\u0441-\u0434\u0435-\u0413\u0440\u0438\u043e"
    ],
    "name:sco_x_preferred":[
        "Santa Cruz de Gr\u00edo"
    ],
    "name:spa_x_preferred":[
        "Santa Cruz de Gr\u00edo"
    ],
    "name:swe_x_preferred":[
        "Santa Cruz de Gr\u00edo"
    ],
    "name:ukr_x_preferred":[
        "\u0421\u0430\u043d\u0442\u0430-\u041a\u0440\u0443\u0441-\u0434\u0435-\u0413\u0440\u0456\u043e"
    ],
    "name:uzb_x_preferred":[
        "Santa Cruz de Gr\u00edo"
    ],
    "name:vie_x_preferred":[
        "Santa Cruz de Gr\u00edo"
    ],
    "name:war_x_preferred":[
        "Santa Cruz de Gr\u00edo"
    ],
    "qs_pg:aaroncc":"ES",
    "qs_pg:gn_country":"ES",
    "qs_pg:gn_fcode":"PPLA3",
    "qs_pg:gn_pop":213,
    "qs_pg:name":"Santa Cruz de Gr\u00edo",
    "qs_pg:name_adm0":"Espa\u00f1a",
    "qs_pg:name_adm1":"Arag\u00f3n",
    "qs_pg:photos_9r":0,
    "qs_pg:photos_sr":0,
    "qs_pg:pop_sr":2,
    "qs_pg:qs_pg_placetype":"locality",
    "qs_pg:qs_pg_placetype_gp":"Town",
    "qs_pg:woe_adm0":23424950,
    "woe:adm0_id":23424950,
    "woe:name_adm0":"Espa\u00f1a",
    "woe:name_adm1":"Arag\u00f3n",
    "woe:placetype":"Town",
    "wof:name":"Santa Cruz de Gr\u00edo",
    "wof:placetype":"locality",
    "wof:population":213
},
  "geometry": {"coordinates":[-1.43008,41.3705],"type":"Point"}
}