{
  "type": "Feature",
  "properties": {
    "gn:country":"ES",
    "gn:fcode":"PPLA3",
    "gn:population":54,
    "iso:country":"ES",
    "name:arg_x_preferred":[
        "Gascue\u00f1a de Bornova"
    ],
    "name:cat_x_preferred":[
        "Gascue\u00f1a de Bornova"
    ],
    "name:che_x_preferred":[
        "\u0413\u0430\u0441\u043a\u0443\u044d\u043d\u044c\u044f-\u0434\u0435-\u0411\u043e\u0440\u043d\u043e\u0432\u0430"
    ],
    "name:deu_x_preferred":[
        "Gascue\u00f1a de Bornova"
    ],
    "name:eng_x_preferred":[
        "Gascue\u00f1a de Bornova"
    ],
    "name:eus_x_preferred":[
        "Gascue\u00f1a de Bornova"
    ],
    "name:fra_x_preferred":[
        "Gascue\u00f1a de Bornova"
    ],
    "name:hun_x_preferred":[
        "Gascue\u00f1a de Bornova"
    ],
    "name:ina_x_preferred":[
        "Gascue\u00f1a de Bornova"
    ],
    "name:ita_x_preferred":[
        "Gascue\u00f1a de Bornova"
    ],
    "name:kaz_x_preferred":[
        "\u0413\u0430\u0441\u043a\u0443\u044d\u043d\u0438\u044f-\u0434\u0435-\u0411\u043e\u0440\u043d\u043e\u0432\u0430"
    ],
    "name:msa_x_preferred":[
        "Gascue\u00f1a de Bornova"
    ],
    "name:nan_x_preferred":[
        "Gascue\u00f1a de Bornova"
    ],
    "name:nld_x_preferred":[
        "Gascue\u00f1a de Bornova"
    ],
    "name:oci_x_preferred":[
        "Gascue\u00f1a de Bornova"
    ],
    "name:pol_x_preferred":[
        "Gascue\u00f1a de Bornova"
    ],
    "name:por_x_preferred":[
        "Gascue\u00f1a de Bornova"
    ],
    "name:rus_x_preferred":[
        "\u0413\u0430\u0441\u043a\u0443\u044d\u043d\u0438\u044f-\u0434\u0435-\u0411\u043e\u0440\u043d\u043e\u0432\u0430"
    ],
    "name:spa_x_preferred":[
        "Gascue\u00f1a de Bornova"
    ],
    "name:swe_x_preferred":[
        "Gascue\u00f1a de Bornova"
    ],
    "name:tat_x_preferred":[
        "\u0413\u0430\u0441\u043a\u0443\u044d\u043d\u044c\u044f-\u0434\u0435-\u0411\u043e\u0440\u043d\u043e\u0432\u0430"
    ],
    "name:ukr_x_preferred":[
        "\u0413\u0430\u0441\u043a\u0443\u0435\u043d\u044c\u044f-\u0434\u0435-\u0411\u043e\u0440\u043d\u043e\u0432\u0430"
    ],
    "name:vie_x_preferred":[
        "Gascue\u00f1a de Bornova"
    ],
    "name:war_x_preferred":[
        "Gascue\u00f1a de Bornova"
    ],
    "name:zho_x_preferred":[
        "\u52a0\u65af\u5e93\u57c3\u5c3c\u4e9a\u5fb7\u6c83\u5c14\u8bfa\u74e6"
    ],
    "qs_pg:aaroncc":"ES",
    "qs_pg:gn_country":"ES",
    "qs_pg:gn_fcode":"PPLA3",
    "qs_pg:gn_pop":54,
    "qs_pg:name":"Gascue\u00f1a de Bornova",
    "qs_pg:name_adm0":"Espa\u00f1a",
    "qs_pg:name_adm1":"Castilla-La Mancha",
    "qs_pg:photos_9k":1,
    "qs_pg:photos_9r":1,
    "qs_pg:photos_all":1,
    "qs_pg:photos_sr":0,
    "qs_pg:pop_sr":1,
    "qs_pg:qs_pg_placetype":"locality",
    "qs_pg:qs_pg_placetype_gp":"Town",
    "qs_pg:woe_adm0":23424950,
    "woe:adm0_id":23424950,
    "woe:name_adm0":"Espa\u00f1a",
    "woe:name_adm1":"Castilla-La Mancha",
    "woe:placetype":"Town",
    "wof:name":"Gascue\u00f1a de Bornova",
    "wof:placetype":"locality",
    "wof:population":54
},
  "geometry": {"coordinates":[-3.01924,41.14243],"type":"Point"}
}