{
  "type": "Feature",
  "properties": {
    "gn:admin1_code":"58",
    "gn:admin2_code":"OR",
    "gn:admin3_code":"32052",
    "gn:asciiname":"Carballeira",
    "gn:country_code":"ES",
    "gn:dem":338,
    "gn:feature_class":"P",
    "gn:feature_code":"PPL",
    "gn:name":"Carballeira",
    "gn:population":0,
    "gn:timezone":"Europe/Madrid",
    "iso:country":"ES",
    "wof:name":"Carballeira",
    "wof:placetype":"locality"
},
  "geometry": {"coordinates":[-7.76398,42.41684],"type":"Point"}
}