{
  "type": "Feature",
  "properties": {
    "gn:admin1_code":"52",
    "gn:admin2_code":"Z",
    "gn:admin3_code":"50297",
    "gn:asciiname":"El Castellar",
    "gn:country_code":"ES",
    "gn:dem":322,
    "gn:feature_class":"P",
    "gn:feature_code":"PPL",
    "gn:name":"El Castellar",
    "gn:population":0,
    "gn:timezone":"Europe/Madrid",
    "iso:country":"ES",
    "name:arg_x_preferred":[
        "Lo Castellar"
    ],
    "name:cat_x_preferred":[
        "El Castellar"
    ],
    "name:deu_x_preferred":[
        "El Castellar"
    ],
    "name:eus_x_preferred":[
        "El Castellar"
    ],
    "name:fas_x_preferred":[
        "\u0627\u0644 \u06a9\u0627\u0633\u062a\u06cc\u0627\u0631"
    ],
    "name:fra_x_preferred":[
        "El Castellar"
    ],
    "name:hun_x_preferred":[
        "El Castellar"
    ],
    "name:hye_x_preferred":[
        "\u0537\u056c \u053f\u0561\u057d\u057f\u0565\u056c\u0575\u0561\u0580"
    ],
    "name:ita_x_preferred":[
        "El Castellar"
    ],
    "name:kaz_x_preferred":[
        "\u042d\u043b\u044c-\u041a\u0430\u0441\u0442\u0435\u043b\u044c\u044f\u0440"
    ],
    "name:msa_x_preferred":[
        "El Castellar"
    ],
    "name:nld_x_preferred":[
        "El Castellar"
    ],
    "name:oci_x_preferred":[
        "El Castellar"
    ],
    "name:pol_x_preferred":[
        "El Castellar"
    ],
    "name:por_x_preferred":[
        "El Castellar"
    ],
    "name:rus_x_preferred":[
        "\u042d\u043b\u044c-\u041a\u0430\u0441\u0442\u0435\u043b\u044c\u044f\u0440"
    ],
    "name:spa_x_preferred":[
        "El Castellar"
    ],
    "name:ukr_x_preferred":[
        "\u0415\u043b\u044c-\u041a\u0430\u0441\u0442\u0435\u043b\u044c\u044f\u0440"
    ],
    "name:und_x_variant":[
        "Castellar",
        "Ermita del Castellar"
    ],
    "name:uzb_x_preferred":[
        "El Castellar"
    ],
    "name:vie_x_preferred":[
        "El Castellar"
    ],
    "name:war_x_preferred":[
        "El Castellar"
    ],
    "name:zho_x_preferred":[
        "\u57c3\u5c14\u5361\u65af\u7279\u5229\u4e9a\u5c14"
    ],
    "wof:name":"El Castellar",
    "wof:placetype":"locality"
},
  "geometry": {"coordinates":[-1.05496,41.78175],"type":"Point"}
}