{
  "type": "Feature",
  "properties": {
    "gn:admin1_code":"52",
    "gn:admin2_code":"Z",
    "gn:admin3_code":"50297",
    "gn:asciiname":"El Castellar",
    "gn:country_code":"ES",
    "gn:dem":322,
    "gn:feature_class":"P",
    "gn:feature_code":"PPL",
    "gn:name":"El Castellar",
    "gn:population":0,
    "gn:timezone":"Europe/Madrid",
    "iso:country":"ES",
    "name:und_x_variant":[
        "Castellar",
        "Ermita del Castellar",
        "El Castellar"
    ],
    "wof:name":"El Castellar",
    "wof:placetype":"locality"
},
  "geometry": {"coordinates":[-1.05496,41.78175],"type":"Point"}
}