{
  "type": "Feature",
  "properties": {
    "gn:country":"ES",
    "gn:fcode":"PPLA3",
    "gn:population":43,
    "iso:country":"ES",
    "name:arg_x_preferred":[
        "Azuelo"
    ],
    "name:ast_x_preferred":[
        "Azuelo"
    ],
    "name:bre_x_preferred":[
        "Azuelo"
    ],
    "name:bul_x_preferred":[
        "\u0410\u0437\u0443\u0435\u043b\u043e"
    ],
    "name:cat_x_preferred":[
        "Azuelo"
    ],
    "name:ceb_x_preferred":[
        "Azuelo"
    ],
    "name:eng_x_preferred":[
        "Azuelo"
    ],
    "name:eus_x_preferred":[
        "Azuelo"
    ],
    "name:fra_x_preferred":[
        "Azuelo"
    ],
    "name:hun_x_preferred":[
        "Azuelo"
    ],
    "name:ita_x_preferred":[
        "Azuelo"
    ],
    "name:jpn_x_preferred":[
        "\u30a2\u30b9\u30a8\u30ed"
    ],
    "name:msa_x_preferred":[
        "Azuelo"
    ],
    "name:nan_x_preferred":[
        "Azuelo"
    ],
    "name:nld_x_preferred":[
        "Azuelo"
    ],
    "name:oci_x_preferred":[
        "Azuelo"
    ],
    "name:pol_x_preferred":[
        "Azuelo"
    ],
    "name:por_x_preferred":[
        "Azuelo"
    ],
    "name:rup_x_preferred":[
        "Azuelo"
    ],
    "name:rus_x_preferred":[
        "\u0410\u0441\u0443\u044d\u043b\u043e"
    ],
    "name:spa_x_preferred":[
        "Azuelo"
    ],
    "name:swe_x_preferred":[
        "Azuelo"
    ],
    "name:ukr_x_preferred":[
        "\u0410\u0441\u0443\u0435\u043b\u043e"
    ],
    "name:uzb_x_preferred":[
        "Azuelo"
    ],
    "name:vie_x_preferred":[
        "Azuelo"
    ],
    "name:war_x_preferred":[
        "Azuelo"
    ],
    "name:zho_x_preferred":[
        "\u963f\u82cf\u57c3\u6d1b"
    ],
    "qs_pg:aaroncc":"ES",
    "qs_pg:gn_country":"ES",
    "qs_pg:gn_fcode":"PPLA3",
    "qs_pg:gn_pop":43,
    "qs_pg:name":"Azuelo",
    "qs_pg:name_adm0":"Espa\u00f1a",
    "qs_pg:name_adm1":"Comunidad Foral de Navarra",
    "qs_pg:photos_9r":0,
    "qs_pg:photos_sr":0,
    "qs_pg:pop_sr":1,
    "qs_pg:qs_pg_placetype":"locality",
    "qs_pg:qs_pg_placetype_gp":"Town",
    "qs_pg:woe_adm0":23424950,
    "woe:adm0_id":23424950,
    "woe:name_adm0":"Espa\u00f1a",
    "woe:name_adm1":"Comunidad Foral de Navarra",
    "woe:placetype":"Town",
    "wof:name":"Azuelo",
    "wof:placetype":"locality",
    "wof:population":43
},
  "geometry": {"coordinates":[-2.34987,42.60844],"type":"Point"}
}