{
  "type": "Feature",
  "properties": {
    "gn:gn_country":"ES",
    "gn:gn_fcode":"ADM3",
    "gn:gn_pop":370,
    "gn:population":370,
    "iso:country":"ES",
    "name:arg_x_preferred":[
        "Soriguera"
    ],
    "name:ast_x_preferred":[
        "Soriguera"
    ],
    "name:bul_x_preferred":[
        "\u0421\u043e\u0440\u0438\u0433\u0443\u0435\u0440\u0430"
    ],
    "name:cat_x_preferred":[
        "Soriguera"
    ],
    "name:ceb_x_preferred":[
        "Soriguera"
    ],
    "name:deu_x_preferred":[
        "Soriguera"
    ],
    "name:eng_x_preferred":[
        "Soriguera"
    ],
    "name:eus_x_preferred":[
        "Soriguera"
    ],
    "name:fra_x_preferred":[
        "Soriguera"
    ],
    "name:hun_x_preferred":[
        "Soriguera"
    ],
    "name:ita_x_preferred":[
        "Soriguera"
    ],
    "name:msa_x_preferred":[
        "Soriguera"
    ],
    "name:nld_x_preferred":[
        "Soriguera"
    ],
    "name:oci_x_preferred":[
        "Soriguera"
    ],
    "name:pol_x_preferred":[
        "Soriguera"
    ],
    "name:por_x_preferred":[
        "Soriguera"
    ],
    "name:ron_x_preferred":[
        "Soriguera"
    ],
    "name:rus_x_preferred":[
        "\u0421\u043e\u0440\u0438\u0433\u0435\u0440\u0430"
    ],
    "name:spa_x_preferred":[
        "Soriguera"
    ],
    "name:sqi_x_preferred":[
        "Soriguera"
    ],
    "name:swe_x_preferred":[
        "Soriguera"
    ],
    "name:uzb_x_preferred":[
        "Soriguera"
    ],
    "name:vie_x_preferred":[
        "Soriguera"
    ],
    "name:war_x_preferred":[
        "Soriguera"
    ],
    "name:zho_x_preferred":[
        "\u7d22\u91cc\u683c\u62c9"
    ],
    "qs_pg:aaroncc":"ES",
    "qs_pg:gn_country":"ES",
    "qs_pg:gn_fcode":"ADM3",
    "qs_pg:gn_pop":370,
    "qs_pg:name":"Soriguera",
    "qs_pg:name_adm0":"Espa\u00f1a",
    "qs_pg:name_adm1":"Catalunya",
    "qs_pg:photos":41,
    "qs_pg:photos_1k":8,
    "qs_pg:photos_9k":1,
    "qs_pg:photos_9r":2,
    "qs_pg:photos_all":41,
    "qs_pg:photos_sr":2,
    "qs_pg:pop_sr":2,
    "qs_pg:qs_pg_placetype":"locality",
    "qs_pg:qs_pg_placetype_gp":"Town",
    "qs_pg:woe_adm0":23424950,
    "woe:adm0_id":23424950,
    "woe:name_adm0":"Espa\u00f1a",
    "woe:name_adm1":"Catalunya",
    "woe:placetype":"Town",
    "wof:name":"Soriguera",
    "wof:placetype":"locality",
    "wof:population":370
},
  "geometry": {"coordinates":[1.13003,42.38247],"type":"Point"}
}