{
  "type": "Feature",
  "properties": {
    "gn:admin1_code":"58",
    "gn:admin2_code":"C",
    "gn:admin3_code":"15020",
    "gn:asciiname":"Minarzo",
    "gn:country_code":"ES",
    "gn:dem":48,
    "gn:feature_class":"P",
    "gn:feature_code":"PPL",
    "gn:name":"Mi\u00f1arzo",
    "gn:population":0,
    "gn:timezone":"Europe/Madrid",
    "iso:country":"ES",
    "name:und_x_variant":[
        "Mi\u00f1arzos",
        "Mi\u00f1arzo"
    ],
    "wof:name":"Minarzo",
    "wof:placetype":"locality"
},
  "geometry": {"coordinates":[-9.13254,42.7989],"type":"Point"}
}