{
  "type": "Feature",
  "properties": {
    "gn:admin1_code":"55",
    "gn:admin2_code":"SG",
    "gn:admin3_code":"40193",
    "gn:asciiname":"San Miguel de Neguera",
    "gn:country_code":"ES",
    "gn:dem":895,
    "gn:feature_class":"P",
    "gn:feature_code":"PPL",
    "gn:name":"San Miguel de Neguera",
    "gn:population":0,
    "gn:timezone":"Europe/Madrid",
    "iso:country":"ES",
    "name:und_x_variant":[
        "San Miguel de Noguera",
        "San Miguel de Neguera"
    ],
    "wof:name":"San Miguel de Neguera",
    "wof:placetype":"locality"
},
  "geometry": {"coordinates":[-3.84357,41.2805],"type":"Point"}
}