{
  "type": "Feature",
  "properties": {
    "gn:gn_country":"ES",
    "gn:gn_fcode":"PPLA3",
    "gn:gn_pop":184,
    "gn:population":184,
    "iso:country":"ES",
    "name:arg_x_preferred":[
        "Pe\u00f1acaballera"
    ],
    "name:baq_x_preferred":[
        "Pe\u00f1acaballera"
    ],
    "name:cat_x_preferred":[
        "Pe\u00f1acaballera"
    ],
    "name:chi_x_preferred":[
        "\u4f69\u5c3c\u4e9a\u5361\u74e6\u5217\u62c9"
    ],
    "name:dut_x_preferred":[
        "Pe\u00f1acaballera"
    ],
    "name:eng_x_preferred":[
        "Pe\u00f1acaballera"
    ],
    "name:fre_x_preferred":[
        "Pe\u00f1acaballera"
    ],
    "name:ger_x_preferred":[
        "Pe\u00f1acaballera"
    ],
    "name:hun_x_preferred":[
        "Pe\u00f1acaballera"
    ],
    "name:ina_x_preferred":[
        "Pe\u00f1acaballera"
    ],
    "name:ita_x_preferred":[
        "Pe\u00f1acaballera"
    ],
    "name:kaz_x_preferred":[
        "\u041f\u0435\u043d\u044c\u044f\u043a\u0430\u0431\u0430\u043b\u044c\u0435\u0440\u0430"
    ],
    "name:may_x_preferred":[
        "Pe\u00f1acaballera"
    ],
    "name:nan_x_preferred":[
        "Pe\u00f1acaballera"
    ],
    "name:oci_x_preferred":[
        "Pe\u00f1acaballera"
    ],
    "name:pol_x_preferred":[
        "Pe\u00f1acaballera"
    ],
    "name:por_x_preferred":[
        "Pe\u00f1acaballera"
    ],
    "name:rus_x_preferred":[
        "\u041f\u0435\u043d\u044c\u044f\u043a\u0430\u0431\u0430\u043b\u044c\u0435\u0440\u0430"
    ],
    "name:spa_x_preferred":[
        "Pe\u00f1acaballera"
    ],
    "name:swe_x_preferred":[
        "Pe\u00f1acaballera"
    ],
    "name:ukr_x_preferred":[
        "\u041f\u0435\u043d\u044c\u044f\u043a\u0430\u0431\u0430\u043b\u044c\u0454\u0440\u0430"
    ],
    "name:vie_x_preferred":[
        "Pe\u00f1acaballera"
    ],
    "name:war_x_preferred":[
        "Pe\u00f1acaballera"
    ],
    "qs_pg:aaroncc":"ES",
    "qs_pg:gn_country":"ES",
    "qs_pg:gn_fcode":"PPLA3",
    "qs_pg:gn_pop":184,
    "qs_pg:name":"Pe\u00f1acaballera",
    "qs_pg:name_adm0":"Espa\u00f1a",
    "qs_pg:name_adm1":"Castilla y Le\u00f3n",
    "qs_pg:photos_9k":1,
    "qs_pg:photos_9r":1,
    "qs_pg:photos_all":1,
    "qs_pg:photos_sr":0,
    "qs_pg:pop_sr":1,
    "qs_pg:qs_pg_placetype":"locality",
    "qs_pg:qs_pg_placetype_gp":"Town",
    "qs_pg:woe_adm0":23424950,
    "woe:adm0_id":23424950,
    "woe:name_adm0":"Espa\u00f1a",
    "woe:name_adm1":"Castilla y Le\u00f3n",
    "woe:placetype":"Town",
    "wof:name":"Pe\u00f1acaballera",
    "wof:placetype":"locality",
    "wof:population":184
},
  "geometry": {"coordinates":[-5.86121,40.34353],"type":"Point"}
}