{
  "type": "Feature",
  "properties": {
    "gn:admin1_code":"58",
    "gn:admin2_code":"LU",
    "gn:admin3_code":"27024",
    "gn:asciiname":"Hospital",
    "gn:country_code":"ES",
    "gn:dem":696,
    "gn:feature_class":"P",
    "gn:feature_code":"PPL",
    "gn:name":"Hospital",
    "gn:population":0,
    "gn:timezone":"Europe/Madrid",
    "iso:country":"ES",
    "wof:name":"Hospital",
    "wof:placetype":"locality"
},
  "geometry": {"coordinates":[-7.3424,42.65574],"type":"Point"}
}