{
  "type": "Feature",
  "properties": {
    "gn:admin1_code":"58",
    "gn:admin2_code":"LU",
    "gn:admin3_code":"27004",
    "gn:asciiname":"Gasalla",
    "gn:country_code":"ES",
    "gn:dem":907,
    "gn:feature_class":"P",
    "gn:feature_code":"PPL",
    "gn:name":"Gasalla",
    "gn:population":0,
    "gn:timezone":"Europe/Madrid",
    "iso:country":"ES",
    "wof:name":"Gasalla",
    "wof:placetype":"locality"
},
  "geometry": {"coordinates":[-7.14579,42.94975],"type":"Point"}
}