{
  "type": "Feature",
  "properties": {
    "gn:admin1_code":"34",
    "gn:admin2_code":"O",
    "gn:admin3_code":"33007",
    "gn:asciiname":"Villar de Serandinas",
    "gn:country_code":"ES",
    "gn:dem":191,
    "gn:feature_class":"P",
    "gn:feature_code":"PPL",
    "gn:name":"Villar de Serandinas",
    "gn:population":0,
    "gn:timezone":"Europe/Madrid",
    "iso:country":"ES",
    "wof:name":"Villar de Serandinas",
    "wof:placetype":"locality"
},
  "geometry": {"coordinates":[-6.74581,43.45025],"type":"Point"}
}