{
  "type": "Feature",
  "properties": {
    "gn:gn_country":"ES",
    "gn:gn_fcode":"PPLA3",
    "gn:gn_pop":372,
    "gn:population":372,
    "iso:country":"ES",
    "name:ara_x_preferred":[
        "\u0643\u0627\u0628\u064a\u0632\u0627\u0631\u0627\u062f\u0648\u0633\u060c \u0633\u064a\u0648\u062f\u0627\u062f \u0631\u064a\u0627\u0644"
    ],
    "name:arg_x_preferred":[
        "Cabezarados"
    ],
    "name:cat_x_preferred":[
        "Cabezarados"
    ],
    "name:eng_x_preferred":[
        "Cabezarados"
    ],
    "name:epo_x_preferred":[
        "Cabezarados"
    ],
    "name:eus_x_preferred":[
        "Cabezarados"
    ],
    "name:fra_x_preferred":[
        "Cabezarados"
    ],
    "name:hun_x_preferred":[
        "Cabezarados"
    ],
    "name:ita_x_preferred":[
        "Cabezarados"
    ],
    "name:kaz_x_preferred":[
        "\u041a\u0430\u0431\u0435\u0441\u0430\u0440\u0430\u0434\u043e\u0441"
    ],
    "name:msa_x_preferred":[
        "Cabezarados"
    ],
    "name:nan_x_preferred":[
        "Cabezarados"
    ],
    "name:nld_x_preferred":[
        "Cabezarados"
    ],
    "name:oci_x_preferred":[
        "Cabezarados"
    ],
    "name:pol_x_preferred":[
        "Cabezarados"
    ],
    "name:por_x_preferred":[
        "Cabezarados"
    ],
    "name:ron_x_preferred":[
        "Cabezarados"
    ],
    "name:rus_x_preferred":[
        "\u041a\u0430\u0431\u0435\u0441\u0430\u0440\u0430\u0434\u043e\u0441"
    ],
    "name:sco_x_preferred":[
        "Cabezarados"
    ],
    "name:spa_x_preferred":[
        "Cabezarados"
    ],
    "name:swe_x_preferred":[
        "Cabezarados"
    ],
    "name:ukr_x_preferred":[
        "\u041a\u0430\u0431\u0435\u0441\u0430\u0440\u0430\u0434\u043e\u0441"
    ],
    "name:vie_x_preferred":[
        "Cabezarados"
    ],
    "name:war_x_preferred":[
        "Cabezarados"
    ],
    "name:zho_x_preferred":[
        "\u5361\u97e6\u8428\u62c9\u591a\u65af"
    ],
    "qs_pg:aaroncc":"ES",
    "qs_pg:gn_country":"ES",
    "qs_pg:gn_fcode":"PPLA3",
    "qs_pg:gn_pop":372,
    "qs_pg:name":"Cabezarados",
    "qs_pg:photos_9r":0,
    "qs_pg:photos_sr":0,
    "qs_pg:pop_sr":2,
    "qs_pg:qs_pg_placetype":"locality",
    "wof:name":"Cabezarados",
    "wof:placetype":"locality",
    "wof:population":372
},
  "geometry": {"coordinates":[-4.2983,38.84469],"type":"Point"}
}