{
  "type": "Feature",
  "properties": {
    "gn:gn_country":"ES",
    "gn:gn_fcode":"PPLA3",
    "gn:gn_pop":223,
    "gn:population":223,
    "iso:country":"ES",
    "name:ara_x_preferred":[
        "\u0633\u0627\u0646 \u0641\u064a\u062b\u064a\u0646\u062a\u064a \u062f\u064a \u0623\u0631\u064a\u0641\u0627\u0644\u0648"
    ],
    "name:baq_x_preferred":[
        "San Vicente de Ar\u00e9valo"
    ],
    "name:cat_x_preferred":[
        "San Vicente de Ar\u00e9valo"
    ],
    "name:chi_x_preferred":[
        "\u5723\u6bd4\u68ee\u7279\u5fb7\u4e9a\u96f7\u74e6\u6d1b"
    ],
    "name:dut_x_preferred":[
        "San Vicente de Ar\u00e9valo"
    ],
    "name:eng_x_preferred":[
        "San Vicente de Ar\u00e9valo"
    ],
    "name:fre_x_preferred":[
        "San Vicente de Ar\u00e9valo"
    ],
    "name:hun_x_preferred":[
        "San Vicente de Ar\u00e9valo"
    ],
    "name:ina_x_preferred":[
        "San Vicente de Ar\u00e9valo"
    ],
    "name:ita_x_preferred":[
        "San Vicente de Ar\u00e9valo"
    ],
    "name:kaz_x_preferred":[
        "\u0421\u0430\u043d-\u0412\u0438\u0441\u0435\u043d\u0442\u0435-\u0434\u0435-\u0410\u0440\u0435\u0432\u0430\u043b\u043e"
    ],
    "name:mac_x_preferred":[
        "\u0421\u0430\u043d \u0412\u0438\u0441\u0435\u043d\u0442\u0435 \u0434\u0435 \u0410\u0440\u0435\u0432\u0430\u043b\u043e"
    ],
    "name:may_x_preferred":[
        "San Vicente de Ar\u00e9valo"
    ],
    "name:oci_x_preferred":[
        "San Vicente de Ar\u00e9valo"
    ],
    "name:per_x_preferred":[
        "\u0633\u0627\u0646 \u0628\u06cc\u0633\u0646\u062a\u0647 \u062f \u0622\u0631\u0628\u0627\u0644\u0648"
    ],
    "name:pol_x_preferred":[
        "San Vicente de Ar\u00e9valo"
    ],
    "name:por_x_preferred":[
        "San Vicente de Ar\u00e9valo"
    ],
    "name:rus_x_preferred":[
        "\u0421\u0430\u043d-\u0412\u0438\u0441\u0435\u043d\u0442\u0435-\u0434\u0435-\u0410\u0440\u0435\u0432\u0430\u043b\u043e"
    ],
    "name:spa_x_preferred":[
        "San Vicente de Ar\u00e9valo"
    ],
    "name:swe_x_preferred":[
        "San Vicente de Ar\u00e9valo"
    ],
    "name:ukr_x_preferred":[
        "\u0421\u0430\u043d-\u0412\u0456\u0441\u0435\u043d\u0442\u0435-\u0434\u0435-\u0410\u0440\u0435\u0432\u0430\u043b\u043e"
    ],
    "name:uzb_x_preferred":[
        "San Vicente de Ar\u00e9valo"
    ],
    "name:vie_x_preferred":[
        "San Vicente de Ar\u00e9valo"
    ],
    "name:war_x_preferred":[
        "San Vicente de Ar\u00e9valo"
    ],
    "qs_pg:aaroncc":"ES",
    "qs_pg:gn_country":"ES",
    "qs_pg:gn_fcode":"PPLA3",
    "qs_pg:gn_pop":223,
    "qs_pg:name":"San Vicente de Ar\u00e9valo",
    "qs_pg:name_adm0":"Espa\u00f1a",
    "qs_pg:name_adm1":"Castilla y Le\u00f3n",
    "qs_pg:photos_9r":0,
    "qs_pg:photos_sr":0,
    "qs_pg:pop_sr":2,
    "qs_pg:qs_pg_placetype":"locality",
    "qs_pg:qs_pg_placetype_gp":"Town",
    "qs_pg:woe_adm0":23424950,
    "woe:adm0_id":23424950,
    "woe:name_adm0":"Espa\u00f1a",
    "woe:name_adm1":"Castilla y Le\u00f3n",
    "woe:placetype":"Town",
    "wof:name":"San Vicente de Ar\u00e9valo",
    "wof:placetype":"locality",
    "wof:population":223
},
  "geometry": {"coordinates":[-4.80194,40.96773],"type":"Point"}
}