{
  "type": "Feature",
  "properties": {
    "gn:admin1_code":"59",
    "gn:admin2_code":"VI",
    "gn:admin3_code":"01053",
    "gn:asciiname":"Mezquia",
    "gn:country_code":"ES",
    "gn:dem":606,
    "gn:feature_class":"P",
    "gn:feature_code":"PPL",
    "gn:name":"Mezkia",
    "gn:population":0,
    "gn:timezone":"Europe/Madrid",
    "iso:country":"ES",
    "name:eus_x_preferred":[
        "Mezkia"
    ],
    "name:spa_x_preferred":[
        "Mezquia"
    ],
    "name:spa_x_variant":[
        "Mezqu\u00eda"
    ],
    "wof:name":"Mezquia",
    "wof:placetype":"locality"
},
  "geometry": {"coordinates":[-2.35365,42.86376],"type":"Point"}
}