{
  "type": "Feature",
  "properties": {
    "gn:admin1_code":"58",
    "gn:admin2_code":"C",
    "gn:admin3_code":"15093",
    "gn:asciiname":"Baizana",
    "gn:country_code":"ES",
    "gn:dem":237,
    "gn:feature_class":"P",
    "gn:feature_code":"PPL",
    "gn:name":"Baizana",
    "gn:population":0,
    "gn:timezone":"Europe/Madrid",
    "iso:country":"ES",
    "name:und_x_variant":[
        "Beizana",
        "Baizana"
    ],
    "wof:name":"Baizana",
    "wof:placetype":"locality"
},
  "geometry": {"coordinates":[-8.94153,43.09692],"type":"Point"}
}