{
  "type": "Feature",
  "properties": {
    "gn:admin1_code":"55",
    "gn:admin2_code":"AV",
    "gn:admin3_code":"05055",
    "gn:asciiname":"Casillas",
    "gn:country_code":"ES",
    "gn:dem":1048,
    "gn:feature_class":"P",
    "gn:feature_code":"PPLA3",
    "gn:name":"Casillas",
    "gn:population":838,
    "gn:timezone":"Europe/Madrid",
    "iso:country":"ES",
    "name:ast_x_preferred":[
        "Casillas"
    ],
    "name:cat_x_preferred":[
        "Casillas"
    ],
    "name:ceb_x_preferred":[
        "Casillas"
    ],
    "name:deu_x_preferred":[
        "Casillas"
    ],
    "name:eus_x_preferred":[
        "Casillas"
    ],
    "name:fra_x_preferred":[
        "Casillas"
    ],
    "name:ita_x_preferred":[
        "Casillas"
    ],
    "name:pol_x_preferred":[
        "Casillas"
    ],
    "name:por_x_preferred":[
        "Casillas"
    ],
    "name:rus_x_preferred":[
        "\u041a\u0430\u0441\u0438\u043b\u044c\u044f\u0441"
    ],
    "name:spa_x_preferred":[
        "Casillas"
    ],
    "name:swe_x_preferred":[
        "Casillas"
    ],
    "wof:name":"Casillas",
    "wof:placetype":"locality",
    "wof:population":838
},
  "geometry": {"coordinates":[-4.57182,40.3261],"type":"Point"}
}