{
  "type": "Feature",
  "properties": {
    "gn:country":"ES",
    "gn:fcode":"PPLA3",
    "gn:population":129,
    "iso:country":"ES",
    "name:arg_x_preferred":[
        "Fresnedoso"
    ],
    "name:ast_x_preferred":[
        "Fresnedoso"
    ],
    "name:cat_x_preferred":[
        "Fresnedoso"
    ],
    "name:ceb_x_preferred":[
        "Fresnedoso"
    ],
    "name:eng_x_preferred":[
        "Fresnedoso"
    ],
    "name:eus_x_preferred":[
        "Fresnedoso"
    ],
    "name:fra_x_preferred":[
        "Fresnedoso"
    ],
    "name:haw_x_preferred":[
        "Fresnedoso"
    ],
    "name:hun_x_preferred":[
        "Fresnedoso"
    ],
    "name:ina_x_preferred":[
        "Fresnedoso"
    ],
    "name:ita_x_preferred":[
        "Fresnedoso"
    ],
    "name:kaz_x_preferred":[
        "\u0424\u0440\u0435\u0441\u043d\u0435\u0434\u043e\u0441\u043e"
    ],
    "name:msa_x_preferred":[
        "Fresnedoso"
    ],
    "name:nan_x_preferred":[
        "Fresnedoso"
    ],
    "name:nld_x_preferred":[
        "Fresnedoso"
    ],
    "name:oci_x_preferred":[
        "Fresnedoso"
    ],
    "name:pol_x_preferred":[
        "Fresnedoso"
    ],
    "name:por_x_preferred":[
        "Fresnedoso"
    ],
    "name:rus_x_preferred":[
        "\u0424\u0440\u0435\u0441\u043d\u0435\u0434\u043e\u0441\u043e"
    ],
    "name:spa_x_preferred":[
        "Fresnedoso"
    ],
    "name:swe_x_preferred":[
        "Fresnedoso"
    ],
    "name:ukr_x_preferred":[
        "\u0424\u0440\u0435\u0441\u043d\u0435\u0434\u043e\u0441\u043e"
    ],
    "name:vie_x_preferred":[
        "Fresnedoso"
    ],
    "name:war_x_preferred":[
        "Fresnedoso"
    ],
    "name:zho_x_preferred":[
        "\u5f17\u96f7\u65af\u5185\u591a\u7d22"
    ],
    "qs_pg:aaroncc":"ES",
    "qs_pg:gn_country":"ES",
    "qs_pg:gn_fcode":"PPLA3",
    "qs_pg:gn_pop":129,
    "qs_pg:name":"Fresnedoso",
    "qs_pg:name_adm0":"Espa\u00f1a",
    "qs_pg:name_adm1":"Castilla y Le\u00f3n",
    "qs_pg:photos_9r":0,
    "qs_pg:photos_sr":0,
    "qs_pg:pop_sr":1,
    "qs_pg:qs_pg_placetype":"locality",
    "qs_pg:qs_pg_placetype_gp":"Town",
    "qs_pg:woe_adm0":23424950,
    "woe:adm0_id":23424950,
    "woe:name_adm0":"Espa\u00f1a",
    "woe:name_adm1":"Castilla y Le\u00f3n",
    "woe:placetype":"Town",
    "wof:name":"Fresnedoso",
    "wof:placetype":"locality",
    "wof:population":129
},
  "geometry": {"coordinates":[-5.7097,40.43618],"type":"Point"}
}