{
  "type": "Feature",
  "properties": {
    "gn:admin1_code":"55",
    "gn:admin2_code":"ZA",
    "gn:admin3_code":"49220",
    "gn:asciiname":"Paladinos del Valle",
    "gn:country_code":"ES",
    "gn:dem":722,
    "gn:feature_class":"P",
    "gn:feature_code":"PPL",
    "gn:name":"Paladinos del Valle",
    "gn:population":0,
    "gn:timezone":"Europe/Madrid",
    "iso:country":"ES",
    "wof:name":"Paladinos del Valle",
    "wof:placetype":"locality"
},
  "geometry": {"coordinates":[-5.72854,42.08098],"type":"Point"}
}