{
  "type": "Feature",
  "properties": {
    "gn:admin1_code":"34",
    "gn:admin2_code":"O",
    "gn:admin3_code":"33002",
    "gn:asciiname":"Villanueva",
    "gn:country_code":"ES",
    "gn:dem":361,
    "gn:feature_class":"P",
    "gn:feature_code":"PPL",
    "gn:name":"Villanueva",
    "gn:population":0,
    "gn:timezone":"Europe/Madrid",
    "iso:country":"ES",
    "wof:name":"Villanueva",
    "wof:placetype":"locality"
},
  "geometry": {"coordinates":[-5.74787,43.16999000000001],"type":"Point"}
}