{
  "type": "Feature",
  "properties": {
    "gn:admin1_code":"32",
    "gn:admin3_code":"31126",
    "gn:asciiname":"Zarrantz",
    "gn:country_code":"ES",
    "gn:dem":649,
    "gn:feature_class":"P",
    "gn:feature_code":"PPL",
    "gn:name":"Zarrantz",
    "gn:population":0,
    "gn:timezone":"Europe/Madrid",
    "iso:country":"ES",
    "name:eus_x_preferred":[
        "Zarrantz"
    ],
    "name:spa_x_preferred":[
        "Zarranz"
    ],
    "wof:name":"Zarrantz",
    "wof:placetype":"locality"
},
  "geometry": {"coordinates":[-1.78391,42.94505],"type":"Point"}
}