{
  "type": "Feature",
  "properties": {
    "gn:gn_country":"ES",
    "gn:gn_fcode":"PPL",
    "gn:gn_pop":404,
    "gn:population":404,
    "iso:country":"ES",
    "name:arg_x_preferred":[
        "El Pego"
    ],
    "name:baq_x_preferred":[
        "El Pego"
    ],
    "name:cat_x_preferred":[
        "El Pego"
    ],
    "name:chi_x_preferred":[
        "\u57c3\u5c14\u4f69\u6208"
    ],
    "name:dut_x_preferred":[
        "El Pego"
    ],
    "name:eng_x_preferred":[
        "El Pego"
    ],
    "name:fre_x_preferred":[
        "El Pego"
    ],
    "name:haw_x_preferred":[
        "El Pego"
    ],
    "name:hun_x_preferred":[
        "El Pego"
    ],
    "name:ile_x_preferred":[
        "El Pego"
    ],
    "name:ina_x_preferred":[
        "El Pego"
    ],
    "name:ita_x_preferred":[
        "El Pego"
    ],
    "name:may_x_preferred":[
        "El Pego"
    ],
    "name:nan_x_preferred":[
        "El Pego"
    ],
    "name:oci_x_preferred":[
        "El Pego"
    ],
    "name:pol_x_preferred":[
        "El Pego"
    ],
    "name:por_x_preferred":[
        "El Pego"
    ],
    "name:rus_x_preferred":[
        "\u042d\u043b\u044c-\u041f\u0435\u0433\u043e"
    ],
    "name:spa_x_preferred":[
        "El Pego"
    ],
    "name:swe_x_preferred":[
        "El Pego"
    ],
    "name:ukr_x_preferred":[
        "\u0415\u043b\u044c-\u041f\u0435\u0433\u043e"
    ],
    "name:unk_x_variant":[
        "El Pego"
    ],
    "name:vie_x_preferred":[
        "El Pego"
    ],
    "name:war_x_preferred":[
        "El Pego"
    ],
    "qs_pg:aaroncc":"ES",
    "qs_pg:gn_country":"ES",
    "qs_pg:gn_fcode":"PPL",
    "qs_pg:gn_pop":404,
    "qs_pg:name":"El Pegollo",
    "qs_pg:name_adm0":"Espa\u00f1a",
    "qs_pg:name_adm1":"Castilla y Le\u00f3n",
    "qs_pg:photos_9r":0,
    "qs_pg:photos_sr":0,
    "qs_pg:pop_sr":2,
    "qs_pg:qs_pg_placetype":"locality",
    "qs_pg:qs_pg_placetype_gp":"Town",
    "qs_pg:woe_adm0":23424950,
    "woe:adm0_id":23424950,
    "woe:name_adm0":"Espa\u00f1a",
    "woe:name_adm1":"Castilla y Le\u00f3n",
    "woe:placetype":"Town",
    "wof:name":"El Pegollo",
    "wof:placetype":"locality",
    "wof:population":404
},
  "geometry": {"coordinates":[-5.46712,41.334],"type":"Point"}
}