{
  "type": "Feature",
  "properties": {
    "gn:admin1_code":"58",
    "gn:admin2_code":"LU",
    "gn:admin3_code":"27057",
    "gn:asciiname":"Chorente",
    "gn:cc2":"ES",
    "gn:country_code":"ES",
    "gn:dem":601,
    "gn:feature_class":"P",
    "gn:feature_code":"PPL",
    "gn:name":"Chorente",
    "gn:population":0,
    "gn:timezone":"Europe/Madrid",
    "iso:country":"ES",
    "name:und_x_variant":[
        "San Juli\u00e1n",
        "Chorente"
    ],
    "wof:name":"Chorente",
    "wof:placetype":"locality"
},
  "geometry": {"coordinates":[-7.45,42.71667],"type":"Point"}
}