{
  "type": "Feature",
  "properties": {
    "gn:gn_country":"ES",
    "gn:gn_fcode":"ADM3",
    "gn:gn_pop":8587,
    "gn:population":9701,
    "iso:country":"ES",
    "name:ara_x_preferred":[
        "\u0641\u064a\u063a\u0627\u0633 \u062f\u064a\u0644 \u062e\u064a\u0646\u064a\u0644"
    ],
    "name:arm_x_preferred":[
        "\u054e\u0565\u0563\u0561\u057d \u0564\u0565\u056c \u053d\u0565\u0576\u056b\u056c"
    ],
    "name:baq_x_preferred":[
        "Vegas del Genil"
    ],
    "name:cat_x_preferred":[
        "Vegas del Genil"
    ],
    "name:chi_x_preferred":[
        "\u8d1d\u52a0\u65af\u5fb7\u5c14\u8d6b\u5c3c\u5c14"
    ],
    "name:dut_x_preferred":[
        "Vegas del Genil"
    ],
    "name:eng_x_preferred":[
        "Vegas del Genil"
    ],
    "name:epo_x_preferred":[
        "Vegas del Genil"
    ],
    "name:fre_x_preferred":[
        "Vegas del Genil"
    ],
    "name:hat_x_preferred":[
        "Vegas del Genil"
    ],
    "name:hun_x_preferred":[
        "Vegas del Genil"
    ],
    "name:ita_x_preferred":[
        "Vegas del Genil"
    ],
    "name:kaz_x_preferred":[
        "\u0412\u0435\u0433\u0430\u0441-\u0434\u0435\u043b\u044c-\u0425\u0435\u043d\u0438\u043b\u044c"
    ],
    "name:lit_x_preferred":[
        "Vegas del Chenilas"
    ],
    "name:may_x_preferred":[
        "Vegas del Genil"
    ],
    "name:nan_x_preferred":[
        "Vegas del Genil"
    ],
    "name:oci_x_preferred":[
        "Vegas del Genil"
    ],
    "name:pol_x_preferred":[
        "Vegas del Genil"
    ],
    "name:por_x_preferred":[
        "Vegas del Genil"
    ],
    "name:rus_x_preferred":[
        "\u0412\u0435\u0433\u0430\u0441-\u0434\u0435\u043b\u044c-\u0425\u0435\u043d\u0438\u043b\u044c"
    ],
    "name:sco_x_preferred":[
        "Vegas del Genil"
    ],
    "name:spa_x_preferred":[
        "Vegas del Genil"
    ],
    "name:swe_x_preferred":[
        "Vegas del Genil"
    ],
    "name:tur_x_preferred":[
        "Vegas del Genil"
    ],
    "name:ukr_x_preferred":[
        "\u0412\u0435\u0433\u0430\u0441-\u0434\u0435\u043b\u044c-\u0425\u0435\u043d\u0456\u043b\u044c"
    ],
    "name:uzb_x_preferred":[
        "Vegas del Genil"
    ],
    "name:vie_x_preferred":[
        "Vegas del Genil"
    ],
    "name:war_x_preferred":[
        "Vegas del Genil"
    ],
    "qs_pg:aaroncc":"ES",
    "qs_pg:gn_country":"ES",
    "qs_pg:gn_fcode":"ADM3",
    "qs_pg:gn_pop":8587,
    "qs_pg:name":"Vegas del Genil",
    "qs_pg:name_adm0":"Espa\u00f1a",
    "qs_pg:name_adm1":"Andaluc\u00eda",
    "qs_pg:photos":16,
    "qs_pg:photos_1k":3,
    "qs_pg:photos_9k":1,
    "qs_pg:photos_9r":1,
    "qs_pg:photos_all":16,
    "qs_pg:photos_sr":1,
    "qs_pg:pop_sr":5,
    "qs_pg:qs_pg_placetype":"locality",
    "qs_pg:qs_pg_placetype_gp":"Town",
    "qs_pg:woe_adm0":23424950,
    "woe:adm0_id":23424950,
    "woe:name_adm0":"Espa\u00f1a",
    "woe:name_adm1":"Andaluc\u00eda",
    "woe:placetype":"Town",
    "wof:name":"Vegas del Genil",
    "wof:placetype":"locality",
    "wof:population":9701
},
  "geometry": {"coordinates":[-3.68933,37.16966],"type":"Point"}
}