{
  "type": "Feature",
  "properties": {
    "gn:admin1_code":"55",
    "gn:admin2_code":"BU",
    "gn:admin3_code":"09906",
    "gn:asciiname":"Villalbilla-Sobresierra",
    "gn:country_code":"ES",
    "gn:dem":902,
    "gn:feature_class":"P",
    "gn:feature_code":"PPL",
    "gn:name":"Villalbilla-Sobresierra",
    "gn:population":0,
    "gn:timezone":"Europe/Madrid",
    "iso:country":"ES",
    "wof:name":"Villalbilla-Sobresierra",
    "wof:placetype":"locality"
},
  "geometry": {"coordinates":[-3.66119,42.52968],"type":"Point"}
}