{
  "type": "Feature",
  "properties": {
    "gn:admin1_code":"59",
    "gn:admin2_code":"BI",
    "gn:admin3_code":"48055",
    "gn:asciiname":"Arraibi",
    "gn:country_code":"ES",
    "gn:dem":72,
    "gn:feature_class":"P",
    "gn:feature_code":"PPL",
    "gn:name":"Arraibi",
    "gn:population":0,
    "gn:timezone":"Europe/Madrid",
    "iso:country":"ES",
    "wof:name":"Arraibi",
    "wof:placetype":"locality"
},
  "geometry": {"coordinates":[-2.77542,43.2058],"type":"Point"}
}