{
  "type": "Feature",
  "properties": {
    "gn:country":"ES",
    "gn:fcode":"PPLA3",
    "gn:population":120,
    "iso:country":"ES",
    "name:arg_x_preferred":[
        "Ibieca"
    ],
    "name:ast_x_preferred":[
        "Ibieca"
    ],
    "name:cat_x_preferred":[
        "Ibieca"
    ],
    "name:ceb_x_preferred":[
        "Ibieca"
    ],
    "name:eng_x_preferred":[
        "Ibieca"
    ],
    "name:eus_x_preferred":[
        "Ibieca"
    ],
    "name:fra_x_preferred":[
        "Ibieca"
    ],
    "name:hak_x_preferred":[
        "Ibieca"
    ],
    "name:hun_x_preferred":[
        "Ibieca"
    ],
    "name:ita_x_preferred":[
        "Ibieca"
    ],
    "name:msa_x_preferred":[
        "Ibieca"
    ],
    "name:nan_x_preferred":[
        "Ibieca"
    ],
    "name:nld_x_preferred":[
        "Ibieca"
    ],
    "name:oci_x_preferred":[
        "Ibieca"
    ],
    "name:pol_x_preferred":[
        "Ibieca"
    ],
    "name:por_x_preferred":[
        "Ibieca"
    ],
    "name:rus_x_preferred":[
        "\u0418\u0431\u044c\u0435\u043a\u0430"
    ],
    "name:spa_x_preferred":[
        "Ibieca"
    ],
    "name:swe_x_preferred":[
        "Ibieca"
    ],
    "name:ukr_x_preferred":[
        "\u0406\u0431'\u0454\u043a\u0430"
    ],
    "name:uzb_x_preferred":[
        "Ibieca"
    ],
    "name:vie_x_preferred":[
        "Ibieca"
    ],
    "name:war_x_preferred":[
        "Ibieca"
    ],
    "name:zho_x_preferred":[
        "\u4f0a\u7ef4\u8036\u5361"
    ],
    "qs_pg:aaroncc":"ES",
    "qs_pg:gn_country":"ES",
    "qs_pg:gn_fcode":"PPLA3",
    "qs_pg:gn_pop":120,
    "qs_pg:name":"Ibieca",
    "qs_pg:name_adm0":"Espa\u00f1a",
    "qs_pg:name_adm1":"Arag\u00f3n",
    "qs_pg:photos_9k":1,
    "qs_pg:photos_9r":1,
    "qs_pg:photos_all":1,
    "qs_pg:photos_sr":0,
    "qs_pg:pop_sr":1,
    "qs_pg:qs_pg_placetype":"locality",
    "qs_pg:qs_pg_placetype_gp":"Town",
    "qs_pg:woe_adm0":23424950,
    "woe:adm0_id":23424950,
    "woe:name_adm0":"Espa\u00f1a",
    "woe:name_adm1":"Arag\u00f3n",
    "woe:placetype":"Town",
    "wof:name":"Ibieca",
    "wof:placetype":"locality",
    "wof:population":120
},
  "geometry": {"coordinates":[-0.20856,42.16079],"type":"Point"}
}