{
  "type": "Feature",
  "properties": {
    "gn:admin1_code":"51",
    "gn:admin2_code":"GR",
    "gn:admin3_code":"18162",
    "gn:asciiname":"Castillo de Banos",
    "gn:country_code":"ES",
    "gn:dem":4,
    "gn:feature_class":"P",
    "gn:feature_code":"PPL",
    "gn:name":"Castillo de Ba\u00f1os",
    "gn:population":0,
    "gn:timezone":"Europe/Madrid",
    "iso:country":"ES",
    "name:und_x_variant":[
        "Castillo Ba\u00f1os",
        "Caser\u00edo Castillo de Ba\u00f1os",
        "Castillo de Ba\u00f1os"
    ],
    "wof:name":"Castillo de Banos",
    "wof:placetype":"locality"
},
  "geometry": {"coordinates":[-3.29953,36.74081],"type":"Point"}
}