{
  "type": "Feature",
  "properties": {
    "gn:admin1_code":"34",
    "gn:admin2_code":"O",
    "gn:admin3_code":"33017",
    "gn:asciiname":"Santalla",
    "gn:country_code":"ES",
    "gn:dem":141,
    "gn:feature_class":"P",
    "gn:feature_code":"PPL",
    "gn:name":"Santalla",
    "gn:population":0,
    "gn:timezone":"Europe/Madrid",
    "iso:country":"ES",
    "wof:name":"Santalla",
    "wof:placetype":"locality"
},
  "geometry": {"coordinates":[-6.99102,43.46299000000001],"type":"Point"}
}