{
  "type": "Feature",
  "properties": {
    "iso:country":"ES",
    "wof:name":"San Rafael de la Albaida",
    "wof:placetype":"neighbourhood"
},
  "geometry": {"coordinates":[-4.80817015342713,37.89743922696646],"type":"Point"}
}