{
  "type": "Feature",
  "properties": {
    "gn:admin1_code":"56",
    "gn:admin2_code":"GI",
    "gn:admin3_code":"17117",
    "gn:asciiname":"Calella de Palafrugell",
    "gn:country_code":"ES",
    "gn:dem":29,
    "gn:feature_class":"P",
    "gn:feature_code":"PPL",
    "gn:name":"Calella de Palafrugell",
    "gn:population":747,
    "gn:timezone":"Europe/Madrid",
    "iso:country":"ES",
    "name:rus_x_preferred":[
        "\u041a\u0430\u043b\u0435\u0439\u044f \u0434\u0435 \u041f\u0430\u043b\u0430\u0444\u0440\u0443\u0436\u0435\u043b\u044c"
    ],
    "name:spa_x_preferred":[
        "Calella de Palafrugell"
    ],
    "name:spa_x_variant":[
        "Calella"
    ],
    "wof:name":"Calella de Palafrugell",
    "wof:placetype":"locality",
    "wof:population":747
},
  "geometry": {"coordinates":[3.18659,41.89199],"type":"Point"}
}