{
  "type": "Feature",
  "properties": {
    "gn:admin1_code":"54",
    "gn:admin2_code":"CR",
    "gn:admin3_code":"13015",
    "gn:asciiname":"Veredas",
    "gn:country_code":"ES",
    "gn:dem":778,
    "gn:feature_class":"P",
    "gn:feature_code":"PPL",
    "gn:name":"Veredas",
    "gn:population":0,
    "gn:timezone":"Europe/Madrid",
    "iso:country":"ES",
    "name:fra_x_preferred":[
        "Veredas"
    ],
    "name:por_x_preferred":[
        "Veredas"
    ],
    "wof:name":"Veredas",
    "wof:placetype":"locality"
},
  "geometry": {"coordinates":[-4.34418,38.66025],"type":"Point"}
}