{
  "type": "Feature",
  "properties": {
    "gn:admin1_code":"58",
    "gn:admin2_code":"OR",
    "gn:admin3_code":"32083",
    "gn:asciiname":"Castromarigo",
    "gn:country_code":"ES",
    "gn:dem":889,
    "gn:feature_class":"P",
    "gn:feature_code":"PPL",
    "gn:name":"Castromarigo",
    "gn:population":0,
    "gn:timezone":"Europe/Madrid",
    "iso:country":"ES",
    "wof:name":"Castromarigo",
    "wof:placetype":"locality"
},
  "geometry": {"coordinates":[-7.03257,42.27266],"type":"Point"}
}