{
  "type": "Feature",
  "properties": {
    "gn:admin1_code":"55",
    "gn:admin2_code":"LE",
    "gn:admin3_code":"24901",
    "gn:asciiname":"Velilla de la Tercia",
    "gn:country_code":"ES",
    "gn:dem":1185,
    "gn:feature_class":"P",
    "gn:feature_code":"PPL",
    "gn:name":"Velilla de la Tercia",
    "gn:population":0,
    "gn:timezone":"Europe/Madrid",
    "iso:country":"ES",
    "wof:name":"Velilla de la Tercia",
    "wof:placetype":"locality"
},
  "geometry": {"coordinates":[-5.63699,42.94748],"type":"Point"}
}