{
  "type": "Feature",
  "properties": {
    "gn:admin1_code":"59",
    "gn:admin2_code":"VI",
    "gn:admin3_code":"01044",
    "gn:asciiname":"Loza",
    "gn:country_code":"ES",
    "gn:dem":799,
    "gn:feature_class":"P",
    "gn:feature_code":"PPL",
    "gn:name":"Loza",
    "gn:population":0,
    "gn:timezone":"Europe/Madrid",
    "iso:country":"ES",
    "name:eus_x_preferred":[
        "Lotza"
    ],
    "name:fra_x_preferred":[
        "Loza"
    ],
    "name:spa_x_preferred":[
        "Loza"
    ],
    "wof:name":"Loza",
    "wof:placetype":"locality"
},
  "geometry": {"coordinates":[-2.68307,42.6433],"type":"Point"}
}