{
  "type": "Feature",
  "properties": {
    "gn:admin1_code":"57",
    "gn:admin2_code":"CC",
    "gn:admin3_code":"10148",
    "gn:asciiname":"Coto Navacebrera y Navahermosa",
    "gn:country_code":"ES",
    "gn:dem":400,
    "gn:feature_class":"P",
    "gn:feature_code":"PPL",
    "gn:name":"Coto Navacebrera y Navahermosa",
    "gn:population":0,
    "gn:timezone":"Europe/Madrid",
    "iso:country":"ES",
    "name:und_x_variant":[
        "Caser\u00edo Coto Navacebrera y Navahermes",
        "Caser\u00edo Coto Navacebrera y Navahermosa",
        "Coto Navacebrera y Navahermosa"
    ],
    "wof:name":"Coto Navacebrera y Navahermosa",
    "wof:placetype":"locality"
},
  "geometry": {"coordinates":[-6.0045,40.07358],"type":"Point"}
}