{
  "type": "Feature",
  "properties": {
    "gn:admin1_code":"31",
    "gn:admin2_code":"MU",
    "gn:admin3_code":"30024",
    "gn:asciiname":"Barranco de los Hilarios",
    "gn:country_code":"ES",
    "gn:dem":593,
    "gn:feature_class":"P",
    "gn:feature_code":"PPL",
    "gn:name":"Barranco de los Hilarios",
    "gn:population":0,
    "gn:timezone":"Europe/Madrid",
    "iso:country":"ES",
    "name:und_x_variant":[
        "Caser\u00edo Barranco de los Hilarios",
        "Barranco de los Hilarios"
    ],
    "wof:name":"Barranco de los Hilarios",
    "wof:placetype":"locality"
},
  "geometry": {"coordinates":[-1.82938,37.61927],"type":"Point"}
}