{
  "type": "Feature",
  "properties": {
    "gn:admin1_code":"59",
    "gn:admin2_code":"BI",
    "gn:admin3_code":"48023",
    "gn:asciiname":"Esparta",
    "gn:country_code":"ES",
    "gn:dem":171,
    "gn:feature_class":"P",
    "gn:feature_code":"PPL",
    "gn:name":"Esparta",
    "gn:population":0,
    "gn:timezone":"Europe/Madrid",
    "iso:country":"ES",
    "name:ceb_x_preferred":[
        "Esparta"
    ],
    "name:fra_x_preferred":[
        "Esparta"
    ],
    "name:ita_x_preferred":[
        "Esparta"
    ],
    "name:nld_x_preferred":[
        "Esparta"
    ],
    "name:pol_x_preferred":[
        "Esparta"
    ],
    "name:por_x_preferred":[
        "Esparta"
    ],
    "name:spa_x_preferred":[
        "Esparta"
    ],
    "name:zho_x_preferred":[
        "\u57c3\u65af\u5e15\u723e\u5854"
    ],
    "wof:name":"Esparta",
    "wof:placetype":"locality"
},
  "geometry": {"coordinates":[-2.78544,43.1303],"type":"Point"}
}