{
  "type": "Feature",
  "properties": {
    "gn:gn_country":"ES",
    "gn:gn_fcode":"PPLA3",
    "gn:gn_pop":294,
    "gn:population":294,
    "iso:country":"ES",
    "name:ara_x_preferred":[
        "\u0643\u064a\u0631\u0641\u064a\u0631\u0627 \u062f\u064a\u0644 \u064a\u0627\u0646\u0648"
    ],
    "name:arg_x_preferred":[
        "Cervera del Llano"
    ],
    "name:ast_x_preferred":[
        "Cervera del Llano"
    ],
    "name:cat_x_preferred":[
        "Cervera del Llano"
    ],
    "name:ceb_x_preferred":[
        "Cervera del Llano"
    ],
    "name:deu_x_preferred":[
        "Cervera del Llano"
    ],
    "name:eng_x_preferred":[
        "Cervera del Llano"
    ],
    "name:epo_x_preferred":[
        "Cervera del Llano"
    ],
    "name:eus_x_preferred":[
        "Cervera del Llano"
    ],
    "name:fra_x_preferred":[
        "Cervera del Llano"
    ],
    "name:hun_x_preferred":[
        "Cervera del Llano"
    ],
    "name:ita_x_preferred":[
        "Cervera del Llano"
    ],
    "name:kaz_x_preferred":[
        "\u0421\u0435\u0440\u0432\u0435\u0440\u0430-\u0434\u0435\u043b\u044c-\u041b\u044c\u044f\u043d\u043e"
    ],
    "name:msa_x_preferred":[
        "Cervera del Llano"
    ],
    "name:nan_x_preferred":[
        "Cervera del Llano"
    ],
    "name:nld_x_preferred":[
        "Cervera del Llano"
    ],
    "name:oci_x_preferred":[
        "Cervera del Llano"
    ],
    "name:pol_x_preferred":[
        "Cervera del Llano"
    ],
    "name:por_x_preferred":[
        "Cervera del Llano"
    ],
    "name:rus_x_preferred":[
        "\u0421\u0435\u0440\u0432\u0435\u0440\u0430-\u0434\u0435\u043b\u044c-\u041b\u044c\u044f\u043d\u043e"
    ],
    "name:spa_x_preferred":[
        "Cervera del Llano"
    ],
    "name:swe_x_preferred":[
        "Cervera del Llano"
    ],
    "name:ukr_x_preferred":[
        "\u0421\u0435\u0440\u0432\u0435\u0440\u0430-\u0434\u0435\u043b\u044c-\u041b\u044c\u044f\u043d\u043e"
    ],
    "name:vie_x_preferred":[
        "Cervera del Llano"
    ],
    "name:war_x_preferred":[
        "Cervera del Llano"
    ],
    "name:zho_x_preferred":[
        "\u585e\u5c14\u97e6\u62c9\u5fb7\u5229\u62c9\u8bfa"
    ],
    "qs_pg:aaroncc":"ES",
    "qs_pg:gn_country":"ES",
    "qs_pg:gn_fcode":"PPLA3",
    "qs_pg:gn_pop":294,
    "qs_pg:name":"Cervera del Llano",
    "qs_pg:name_adm0":"Espa\u00f1a",
    "qs_pg:name_adm1":"Castilla-La Mancha",
    "qs_pg:photos":11,
    "qs_pg:photos_1k":2,
    "qs_pg:photos_9k":1,
    "qs_pg:photos_9r":1,
    "qs_pg:photos_all":11,
    "qs_pg:photos_sr":1,
    "qs_pg:pop_sr":2,
    "qs_pg:qs_pg_placetype":"locality",
    "qs_pg:qs_pg_placetype_gp":"Town",
    "qs_pg:woe_adm0":23424950,
    "woe:adm0_id":23424950,
    "woe:name_adm0":"Espa\u00f1a",
    "woe:name_adm1":"Castilla-La Mancha",
    "woe:placetype":"Town",
    "wof:name":"Cervera del Llano",
    "wof:placetype":"locality",
    "wof:population":294
},
  "geometry": {"coordinates":[-2.42019,39.78312],"type":"Point"}
}