{
  "type": "Feature",
  "properties": {
    "gn:admin1_code":"55",
    "gn:admin2_code":"P",
    "gn:admin3_code":"34151",
    "gn:asciiname":"Fontecha",
    "gn:country_code":"ES",
    "gn:dem":1090,
    "gn:feature_class":"P",
    "gn:feature_code":"PPL",
    "gn:name":"Fontecha",
    "gn:population":22,
    "gn:timezone":"Europe/Madrid",
    "iso:country":"ES",
    "name:eng_x_preferred":[
        "Fontecha De La Pe\u00f1a"
    ],
    "name:eus_x_preferred":[
        "Fontecha"
    ],
    "name:fra_x_preferred":[
        "Fontecha"
    ],
    "name:spa_x_preferred":[
        "Fontecha"
    ],
    "wof:name":"Fontecha",
    "wof:placetype":"locality",
    "wof:population":22
},
  "geometry": {"coordinates":[-4.72197,42.74384000000001],"type":"Point"}
}