{
  "type": "Feature",
  "properties": {
    "gn:gn_country":"ES",
    "gn:gn_fcode":"PPLA3",
    "gn:gn_pop":136,
    "gn:population":136,
    "iso:country":"ES",
    "name:arg_x_preferred":[
        "Bobadilla"
    ],
    "name:arm_x_preferred":[
        "\u0532\u0578\u0562\u0561\u0564\u056b\u056c\u056b\u0561"
    ],
    "name:baq_x_preferred":[
        "Bobadilla"
    ],
    "name:cat_x_preferred":[
        "Bobadilla"
    ],
    "name:chi_x_preferred":[
        "\u535a\u74e6\u8fea\u5229\u4e9a"
    ],
    "name:dut_x_preferred":[
        "Bobadilla"
    ],
    "name:eng_x_preferred":[
        "Bobadilla"
    ],
    "name:fre_x_preferred":[
        "Bobadilla"
    ],
    "name:glg_x_preferred":[
        "Bobadilla"
    ],
    "name:hun_x_preferred":[
        "Bobadilla"
    ],
    "name:ita_x_preferred":[
        "Bobadilla"
    ],
    "name:jpn_x_preferred":[
        "\u30dc\u30d0\u30c7\u30a3\u30fc\u30ea\u30e3"
    ],
    "name:kaz_x_preferred":[
        "\u0411\u043e\u0431\u0430\u0434\u0438\u043b\u044c\u044f"
    ],
    "name:may_x_preferred":[
        "Bobadilla"
    ],
    "name:nan_x_preferred":[
        "Bobadilla"
    ],
    "name:oci_x_preferred":[
        "Bobadilla"
    ],
    "name:pol_x_preferred":[
        "Bobadilla"
    ],
    "name:por_x_preferred":[
        "Bobadilla"
    ],
    "name:rum_x_preferred":[
        "Bobadilla"
    ],
    "name:rus_x_preferred":[
        "\u0411\u043e\u0431\u0430\u0434\u0438\u043b\u044c\u044f"
    ],
    "name:spa_x_preferred":[
        "Bobadilla"
    ],
    "name:swe_x_preferred":[
        "Bobadilla"
    ],
    "name:ukr_x_preferred":[
        "\u0411\u043e\u0431\u0430\u0434\u0456\u043b\u044c\u044f"
    ],
    "name:uzb_x_preferred":[
        "Bobadilla"
    ],
    "name:vie_x_preferred":[
        "Bobadilla"
    ],
    "name:war_x_preferred":[
        "Bobadilla"
    ],
    "qs_pg:aaroncc":"ES",
    "qs_pg:gn_country":"ES",
    "qs_pg:gn_fcode":"PPLA3",
    "qs_pg:gn_pop":136,
    "qs_pg:name":"Bobadilla",
    "qs_pg:name_adm0":"Espa\u00f1a",
    "qs_pg:name_adm1":"La Rioja",
    "qs_pg:photos_9k":1,
    "qs_pg:photos_9r":1,
    "qs_pg:photos_all":1,
    "qs_pg:photos_sr":0,
    "qs_pg:pop_sr":1,
    "qs_pg:qs_pg_placetype":"locality",
    "qs_pg:qs_pg_placetype_gp":"Town",
    "qs_pg:woe_adm0":23424950,
    "woe:adm0_id":23424950,
    "woe:name_adm0":"Espa\u00f1a",
    "woe:name_adm1":"La Rioja",
    "woe:placetype":"Town",
    "wof:name":"Bobadilla",
    "wof:placetype":"locality",
    "wof:population":136
},
  "geometry": {"coordinates":[-2.75992,42.31873],"type":"Point"}
}