{
  "type": "Feature",
  "properties": {
    "gn:admin1_code":"51",
    "gn:admin2_code":"CA",
    "gn:admin3_code":"11022",
    "gn:asciiname":"La Atunara",
    "gn:country_code":"ES",
    "gn:dem":6,
    "gn:feature_class":"P",
    "gn:feature_code":"PPL",
    "gn:name":"La Atunara",
    "gn:population":0,
    "gn:timezone":"Europe/Madrid",
    "iso:country":"ES",
    "name:spa_x_preferred":[
        "La Atunara"
    ],
    "name:und_x_variant":[
        "Tunara",
        "La Tunara"
    ],
    "wof:name":"La Atunara",
    "wof:placetype":"locality"
},
  "geometry": {"coordinates":[-5.33858,36.16913],"type":"Point"}
}