{
  "type": "Feature",
  "properties": {
    "gn:admin1_code":"55",
    "gn:admin2_code":"SG",
    "gn:admin3_code":"40083",
    "gn:asciiname":"Los Valles de Fuentiduena",
    "gn:country_code":"ES",
    "gn:dem":872,
    "gn:feature_class":"P",
    "gn:feature_code":"PPL",
    "gn:name":"Los Valles de Fuentidue\u00f1a",
    "gn:population":0,
    "gn:timezone":"Europe/Madrid",
    "iso:country":"ES",
    "name:und_x_variant":[
        "Valles de Fuentidue\u00f1a",
        "Los Valles de Fuentidue\u00f1a"
    ],
    "wof:name":"Los Valles de Fuentiduena",
    "wof:placetype":"locality"
},
  "geometry": {"coordinates":[-3.99806,41.42097],"type":"Point"}
}