{
  "type": "Feature",
  "properties": {
    "gn:admin1_code":"54",
    "gn:admin2_code":"AB",
    "gn:admin3_code":"02040",
    "gn:asciiname":"Fontanar de Arriba",
    "gn:country_code":"ES",
    "gn:dem":959,
    "gn:feature_class":"P",
    "gn:feature_code":"PPL",
    "gn:name":"Fontanar de Arriba",
    "gn:population":0,
    "gn:timezone":"Europe/Madrid",
    "iso:country":"ES",
    "name:und_x_variant":[
        "Caser\u00edo Fontanar de Arriba",
        "Fontanar de Arriba"
    ],
    "wof:name":"Fontanar de Arriba",
    "wof:placetype":"locality"
},
  "geometry": {"coordinates":[-1.58238,38.95325],"type":"Point"}
}