{
  "type": "Feature",
  "properties": {
    "gn:admin1_code":"58",
    "gn:admin2_code":"OR",
    "gn:admin3_code":"32089",
    "gn:asciiname":"Seiro",
    "gn:country_code":"ES",
    "gn:dem":686,
    "gn:feature_class":"P",
    "gn:feature_code":"PPL",
    "gn:name":"Seir\u00f3",
    "gn:population":0,
    "gn:timezone":"Europe/Madrid",
    "iso:country":"ES",
    "wof:name":"Seiro",
    "wof:placetype":"locality"
},
  "geometry": {"coordinates":[-7.62829,42.18414],"type":"Point"}
}