{
  "type": "Feature",
  "properties": {
    "gn:admin1_code":"39",
    "gn:admin2_code":"S",
    "gn:admin3_code":"39012",
    "gn:asciiname":"Ontoria",
    "gn:country_code":"ES",
    "gn:dem":121,
    "gn:feature_class":"P",
    "gn:feature_code":"PPL",
    "gn:name":"Ontoria",
    "gn:population":0,
    "gn:timezone":"Europe/Madrid",
    "iso:country":"ES",
    "wof:name":"Ontoria",
    "wof:placetype":"locality"
},
  "geometry": {"coordinates":[-4.2142,43.30785],"type":"Point"}
}