{
  "type": "Feature",
  "properties": {
    "gn:admin1_code":"55",
    "gn:admin2_code":"LE",
    "gn:admin3_code":"24056",
    "gn:asciiname":"Quintana de la Pena",
    "gn:country_code":"ES",
    "gn:dem":1166,
    "gn:feature_class":"P",
    "gn:feature_code":"PPL",
    "gn:name":"Quintana de la Pe\u00f1a",
    "gn:population":0,
    "gn:timezone":"Europe/Madrid",
    "iso:country":"ES",
    "name:und_x_variant":[
        "Quintana de la Pe\u00f1a"
    ],
    "wof:name":"Quintana de la Pena",
    "wof:placetype":"locality"
},
  "geometry": {"coordinates":[-5.07701,42.79087],"type":"Point"}
}