{
  "type": "Feature",
  "properties": {
    "gn:admin1_code":"58",
    "gn:admin2_code":"LU",
    "gn:admin3_code":"27037",
    "gn:asciiname":"Ferreiras",
    "gn:country_code":"ES",
    "gn:dem":1029,
    "gn:feature_class":"P",
    "gn:feature_code":"PPL",
    "gn:name":"Ferreiras",
    "gn:population":0,
    "gn:timezone":"Europe/Madrid",
    "iso:country":"ES",
    "name:ceb_x_preferred":[
        "Ferreiras"
    ],
    "name:deu_x_preferred":[
        "Ferreiras"
    ],
    "name:kaz_x_preferred":[
        "\u0424\u0435\u0440\u0440\u0435\u0439\u0440\u0430\u0448"
    ],
    "name:nld_x_preferred":[
        "Ferreiras"
    ],
    "name:por_x_preferred":[
        "Ferreiras"
    ],
    "name:rus_x_preferred":[
        "\u0424\u0435\u0440\u0440\u0435\u0439\u0440\u0430\u0448"
    ],
    "name:spa_x_preferred":[
        "Ferreiras"
    ],
    "name:swe_x_preferred":[
        "Ferreiras"
    ],
    "wof:name":"Ferreiras",
    "wof:placetype":"locality"
},
  "geometry": {"coordinates":[-7.04288,42.74394],"type":"Point"}
}