{
  "type": "Feature",
  "properties": {
    "gn:admin1_code":"54",
    "gn:admin2_code":"GU",
    "gn:admin3_code":"19257",
    "gn:asciiname":"La Cabrera",
    "gn:country_code":"ES",
    "gn:dem":963,
    "gn:feature_class":"P",
    "gn:feature_code":"PPL",
    "gn:name":"La Cabrera",
    "gn:population":0,
    "gn:timezone":"Europe/Madrid",
    "iso:country":"ES",
    "name:ara_x_preferred":[
        "\u0644\u0627 \u0643\u0627\u0628\u0631\u064a\u0631\u0627"
    ],
    "name:cat_x_preferred":[
        "La Cabrera"
    ],
    "name:ceb_x_preferred":[
        "La Cabrera"
    ],
    "name:diq_x_preferred":[
        "La Cabrera"
    ],
    "name:hun_x_preferred":[
        "La Cabrera"
    ],
    "name:hye_x_preferred":[
        "\u053c\u0561 \u053f\u0561\u0562\u0580\u0565\u0580\u0561"
    ],
    "name:ita_x_preferred":[
        "La Cabrera"
    ],
    "name:jpn_x_preferred":[
        "\u30e9\u30fb\u30ab\u30d6\u30ec\u30fc\u30e9"
    ],
    "name:ltz_x_preferred":[
        "La Cabrera"
    ],
    "name:msa_x_preferred":[
        "La Cabrera"
    ],
    "name:nld_x_preferred":[
        "La Cabrera"
    ],
    "name:pol_x_preferred":[
        "La Cabrera"
    ],
    "name:por_x_preferred":[
        "La Cabrera"
    ],
    "name:rus_x_preferred":[
        "\u041b\u0430-\u041a\u0430\u0431\u0440\u0435\u0440\u0430"
    ],
    "name:spa_x_preferred":[
        "La Cabrera"
    ],
    "name:ukr_x_preferred":[
        "\u041b\u0430-\u041a\u0430\u0431\u0440\u0435\u0440\u0430"
    ],
    "name:urd_x_preferred":[
        "\u0644\u0627 \u06a9\u0627\u0628\u0631\u06cc\u0631\u0627"
    ],
    "name:uzb_x_preferred":[
        "La Cabrera"
    ],
    "name:war_x_preferred":[
        "La Cabrera"
    ],
    "wof:name":"La Cabrera",
    "wof:placetype":"locality"
},
  "geometry": {"coordinates":[-2.67766,41.00842],"type":"Point"}
}