{
  "type": "Feature",
  "properties": {
    "gn:admin1_code":"54",
    "gn:admin2_code":"GU",
    "gn:admin3_code":"19257",
    "gn:asciiname":"La Cabrera",
    "gn:country_code":"ES",
    "gn:dem":963,
    "gn:feature_class":"P",
    "gn:feature_code":"PPL",
    "gn:name":"La Cabrera",
    "gn:population":0,
    "gn:timezone":"Europe/Madrid",
    "iso:country":"ES",
    "wof:name":"La Cabrera",
    "wof:placetype":"locality"
},
  "geometry": {"coordinates":[-2.67766,41.00842],"type":"Point"}
}