{
  "type": "Feature",
  "properties": {
    "gn:admin1_code":"52",
    "gn:admin2_code":"TE",
    "gn:admin3_code":"44010",
    "gn:asciiname":"Albentosa",
    "gn:country_code":"ES",
    "gn:dem":976,
    "gn:feature_class":"P",
    "gn:feature_code":"PPLA3",
    "gn:name":"Albentosa",
    "gn:population":0,
    "gn:timezone":"Europe/Madrid",
    "iso:country":"ES",
    "name:und_x_variant":[
        "Estaci\u00f3n de Rubielos de Mora",
        "Estaci\u00f3n Rubielos de Mora"
    ],
    "wof:name":"Albentosa",
    "wof:placetype":"locality"
},
  "geometry": {"coordinates":[-0.76928,40.10342],"type":"Point"}
}