{
  "type": "Feature",
  "properties": {
    "gn:admin1_code":"52",
    "gn:admin2_code":"TE",
    "gn:admin3_code":"44010",
    "gn:asciiname":"Albentosa",
    "gn:country_code":"ES",
    "gn:dem":976,
    "gn:feature_class":"P",
    "gn:feature_code":"PPLA3",
    "gn:name":"Albentosa",
    "gn:population":0,
    "gn:timezone":"Europe/Madrid",
    "iso:country":"ES",
    "name:arg_x_preferred":[
        "Albentosa"
    ],
    "name:ast_x_preferred":[
        "Albentosa"
    ],
    "name:azb_x_preferred":[
        "\u0622\u0644\u0628\u0646\u062a\u0633\u0627"
    ],
    "name:cat_x_preferred":[
        "Alventosa"
    ],
    "name:ceb_x_preferred":[
        "Albentosa"
    ],
    "name:eus_x_preferred":[
        "Albentosa"
    ],
    "name:fas_x_preferred":[
        "\u0622\u0644\u0628\u0646\u062a\u0633\u0627"
    ],
    "name:fra_x_preferred":[
        "Albentosa"
    ],
    "name:hun_x_preferred":[
        "Albentosa"
    ],
    "name:hye_x_preferred":[
        "\u0531\u056c\u0562\u0565\u0576\u057f\u0578\u057d\u0561"
    ],
    "name:ita_x_preferred":[
        "Albentosa"
    ],
    "name:kaz_x_preferred":[
        "\u0410\u043b\u044c\u0431\u0435\u043d\u0442\u043e\u0441\u0430"
    ],
    "name:msa_x_preferred":[
        "Albentosa"
    ],
    "name:nld_x_preferred":[
        "Albentosa"
    ],
    "name:oci_x_preferred":[
        "Albentosa"
    ],
    "name:pol_x_preferred":[
        "Albentosa"
    ],
    "name:por_x_preferred":[
        "Albentosa"
    ],
    "name:rus_x_preferred":[
        "\u0410\u043b\u044c\u0431\u0435\u043d\u0442\u043e\u0441\u0430"
    ],
    "name:spa_x_preferred":[
        "Albentosa"
    ],
    "name:swe_x_preferred":[
        "Albentosa"
    ],
    "name:ukr_x_preferred":[
        "\u0410\u043b\u044c\u0431\u0435\u043d\u0442\u043e\u0441\u0430"
    ],
    "name:und_x_variant":[
        "Estaci\u00f3n de Rubielos de Mora",
        "Estaci\u00f3n Rubielos de Mora"
    ],
    "name:uzb_x_preferred":[
        "Albentosa"
    ],
    "name:vie_x_preferred":[
        "Albentosa"
    ],
    "name:war_x_preferred":[
        "Albentosa"
    ],
    "name:zho_x_preferred":[
        "\u963f\u5c14\u6587\u6258\u8428"
    ],
    "wof:name":"Albentosa",
    "wof:placetype":"locality"
},
  "geometry": {"coordinates":[-0.76928,40.10342],"type":"Point"}
}