{
  "type": "Feature",
  "properties": {
    "gn:admin1_code":"56",
    "gn:admin2_code":"GI",
    "gn:admin3_code":"17158",
    "gn:asciiname":"Ullastre",
    "gn:country_code":"ES",
    "gn:dem":93,
    "gn:feature_class":"P",
    "gn:feature_code":"PPL",
    "gn:name":"Ullastre",
    "gn:population":0,
    "gn:timezone":"Europe/Madrid",
    "iso:country":"ES",
    "name:cat_x_preferred":[
        "Ullastre"
    ],
    "wof:name":"Ullastre",
    "wof:placetype":"locality"
},
  "geometry": {"coordinates":[2.97219,42.36397],"type":"Point"}
}