{
  "type": "Feature",
  "properties": {
    "gn:admin1_code":"51",
    "gn:admin2_code":"GR",
    "gn:admin3_code":"18105",
    "gn:asciiname":"El Frage",
    "gn:country_code":"ES",
    "gn:dem":873,
    "gn:feature_class":"P",
    "gn:feature_code":"PPL",
    "gn:name":"El Frage",
    "gn:population":0,
    "gn:timezone":"Europe/Madrid",
    "iso:country":"ES",
    "name:und_x_variant":[
        "Caser\u00edo El Frage",
        "El Frage"
    ],
    "wof:name":"El Frage",
    "wof:placetype":"locality"
},
  "geometry": {"coordinates":[-3.59069,37.38981],"type":"Point"}
}