{
  "type": "Feature",
  "properties": {
    "gn:admin1_code":"51",
    "gn:admin2_code":"J",
    "gn:admin3_code":"23076",
    "gn:asciiname":"Venta Nueva",
    "gn:country_code":"ES",
    "gn:dem":740,
    "gn:feature_class":"P",
    "gn:feature_code":"PPL",
    "gn:name":"Venta Nueva",
    "gn:population":0,
    "gn:timezone":"Europe/Madrid",
    "iso:country":"ES",
    "wof:name":"Venta Nueva",
    "wof:placetype":"locality"
},
  "geometry": {"coordinates":[-3.57012,38.31469],"type":"Point"}
}