{
  "type": "Feature",
  "properties": {
    "gn:gn_country":"ES",
    "gn:gn_fcode":"PPLA3",
    "gn:gn_pop":372,
    "gn:population":372,
    "iso:country":"ES",
    "name:arg_x_preferred":[
        "Wamba"
    ],
    "name:ast_x_preferred":[
        "Wamba"
    ],
    "name:cat_x_preferred":[
        "Wamba"
    ],
    "name:deu_x_preferred":[
        "Santa Mar\u00eda de Wamba"
    ],
    "name:eng_x_preferred":[
        "Wamba"
    ],
    "name:eus_x_preferred":[
        "Wamba"
    ],
    "name:fra_x_preferred":[
        "Wamba"
    ],
    "name:hun_x_preferred":[
        "Wamba"
    ],
    "name:ina_x_preferred":[
        "Wamba"
    ],
    "name:ita_x_preferred":[
        "Wamba"
    ],
    "name:msa_x_preferred":[
        "Wamba"
    ],
    "name:nan_x_preferred":[
        "Wamba"
    ],
    "name:nld_x_preferred":[
        "Wamba"
    ],
    "name:oci_x_preferred":[
        "Wamba"
    ],
    "name:pol_x_preferred":[
        "Wamba"
    ],
    "name:por_x_preferred":[
        "Wamba"
    ],
    "name:rus_x_preferred":[
        "\u0412\u0430\u043c\u0431\u0430"
    ],
    "name:spa_x_preferred":[
        "Wamba"
    ],
    "name:ukr_x_preferred":[
        "\u0412\u0430\u043c\u0431\u0430"
    ],
    "name:vie_x_preferred":[
        "Wamba"
    ],
    "name:war_x_preferred":[
        "Wamba"
    ],
    "qs_pg:aaroncc":"ES",
    "qs_pg:gn_country":"ES",
    "qs_pg:gn_fcode":"PPLA3",
    "qs_pg:gn_pop":372,
    "qs_pg:name":"Wamba",
    "qs_pg:name_adm0":"Espa\u00f1a",
    "qs_pg:name_adm1":"Castilla y Le\u00f3n",
    "qs_pg:photos":197,
    "qs_pg:photos_1k":40,
    "qs_pg:photos_9k":1,
    "qs_pg:photos_9r":4,
    "qs_pg:photos_all":197,
    "qs_pg:photos_sr":4,
    "qs_pg:pop_sr":2,
    "qs_pg:qs_pg_placetype":"locality",
    "qs_pg:qs_pg_placetype_gp":"Town",
    "qs_pg:woe_adm0":23424950,
    "woe:adm0_id":23424950,
    "woe:name_adm0":"Espa\u00f1a",
    "woe:name_adm1":"Castilla y Le\u00f3n",
    "woe:placetype":"Town",
    "wof:name":"Wamba",
    "wof:placetype":"locality",
    "wof:population":372
},
  "geometry": {"coordinates":[-4.91748,41.67525],"type":"Point"}
}