{
  "type": "Feature",
  "properties": {
    "gn:gn_country":"ES",
    "gn:gn_fcode":"PPLA3",
    "gn:gn_pop":472,
    "gn:population":472,
    "iso:country":"ES",
    "name:arg_x_preferred":[
        "Mart\u00edn"
    ],
    "name:baq_x_preferred":[
        "Mart\u00edn del R\u00edo"
    ],
    "name:cat_x_preferred":[
        "Mart\u00edn del R\u00edo"
    ],
    "name:chi_x_preferred":[
        "\u6ee8\u6cb3\u9a6c\u4e01"
    ],
    "name:dut_x_preferred":[
        "Mart\u00edn del R\u00edo"
    ],
    "name:eng_x_preferred":[
        "Mart\u00edn del R\u00edo"
    ],
    "name:fre_x_preferred":[
        "Mart\u00edn del R\u00edo"
    ],
    "name:hun_x_preferred":[
        "Mart\u00edn del R\u00edo"
    ],
    "name:ita_x_preferred":[
        "Mart\u00edn del R\u00edo"
    ],
    "name:kaz_x_preferred":[
        "\u041c\u0430\u0440\u0442\u0438\u043d-\u0434\u0435\u043b\u044c-\u0420\u0438\u043e"
    ],
    "name:may_x_preferred":[
        "Mart\u00edn del R\u00edo"
    ],
    "name:nan_x_preferred":[
        "Mart\u00edn del R\u00edo"
    ],
    "name:oci_x_preferred":[
        "Mart\u00edn del R\u00edo"
    ],
    "name:per_x_preferred":[
        "\u0645\u0627\u0631\u062a\u06cc\u0646 \u062f\u0644 \u0631\u06cc\u0648"
    ],
    "name:pol_x_preferred":[
        "Mart\u00edn del R\u00edo"
    ],
    "name:por_x_preferred":[
        "Mart\u00edn del R\u00edo"
    ],
    "name:rus_x_preferred":[
        "\u041c\u0430\u0440\u0442\u0438\u043d-\u0434\u0435\u043b\u044c-\u0420\u0438\u043e"
    ],
    "name:spa_x_preferred":[
        "Mart\u00edn del R\u00edo"
    ],
    "name:swe_x_preferred":[
        "Mart\u00edn del R\u00edo"
    ],
    "name:ukr_x_preferred":[
        "\u041c\u0430\u0440\u0442\u0456\u043d-\u0434\u0435\u043b\u044c-\u0420\u0456\u043e"
    ],
    "name:urd_x_preferred":[
        "\u0645\u0627\u0631\u0679\u0646 \u062f\u0644 \u0631\u06cc\u0648"
    ],
    "name:uzb_x_preferred":[
        "Mart\u00edn del R\u00edo"
    ],
    "name:vie_x_preferred":[
        "Mart\u00edn del R\u00edo"
    ],
    "name:war_x_preferred":[
        "Mart\u00edn del R\u00edo"
    ],
    "qs_pg:aaroncc":"ES",
    "qs_pg:gn_country":"ES",
    "qs_pg:gn_fcode":"PPLA3",
    "qs_pg:gn_pop":472,
    "qs_pg:name":"Mart\u00edn del R\u00edo",
    "qs_pg:name_adm0":"Espa\u00f1a",
    "qs_pg:name_adm1":"Arag\u00f3n",
    "qs_pg:photos":48,
    "qs_pg:photos_1k":10,
    "qs_pg:photos_9k":1,
    "qs_pg:photos_9r":2,
    "qs_pg:photos_all":48,
    "qs_pg:photos_sr":2,
    "qs_pg:pop_sr":2,
    "qs_pg:qs_pg_placetype":"locality",
    "qs_pg:qs_pg_placetype_gp":"Town",
    "qs_pg:woe_adm0":23424950,
    "woe:adm0_id":23424950,
    "woe:name_adm0":"Espa\u00f1a",
    "woe:name_adm1":"Arag\u00f3n",
    "woe:placetype":"Town",
    "wof:name":"Mart\u00edn del R\u00edo",
    "wof:placetype":"locality",
    "wof:population":472
},
  "geometry": {"coordinates":[-0.89549,40.84459],"type":"Point"}
}