{
  "type": "Feature",
  "properties": {
    "gn:admin1_code":"54",
    "gn:admin2_code":"TO",
    "gn:admin3_code":"45119",
    "gn:asciiname":"Ontalba",
    "gn:country_code":"ES",
    "gn:dem":560,
    "gn:feature_class":"P",
    "gn:feature_code":"PPL",
    "gn:name":"Ontalba",
    "gn:population":0,
    "gn:timezone":"Europe/Madrid",
    "iso:country":"ES",
    "name:und_x_variant":[
        "Dehesa Ontalba",
        "Casa Ontalba",
        "Ontalba"
    ],
    "wof:name":"Ontalba",
    "wof:placetype":"locality"
},
  "geometry": {"coordinates":[-3.81006,40.08162],"type":"Point"}
}