{
  "type": "Feature",
  "properties": {
    "gn:admin1_code":"52",
    "gn:admin2_code":"HU",
    "gn:admin3_code":"22130",
    "gn:asciiname":"Martillue",
    "gn:country_code":"ES",
    "gn:dem":856,
    "gn:feature_class":"P",
    "gn:feature_code":"PPL",
    "gn:name":"Martillu\u00e9",
    "gn:population":0,
    "gn:timezone":"Europe/Madrid",
    "iso:country":"ES",
    "wof:name":"Martillue",
    "wof:placetype":"locality"
},
  "geometry": {"coordinates":[-0.4352,42.54692],"type":"Point"}
}