{
  "type": "Feature",
  "properties": {
    "gn:admin1_code":"55",
    "gn:admin2_code":"SO",
    "gn:admin3_code":"42071",
    "gn:asciiname":"Almarail",
    "gn:country_code":"ES",
    "gn:dem":983,
    "gn:feature_class":"P",
    "gn:feature_code":"PPL",
    "gn:name":"Almarail",
    "gn:population":0,
    "gn:timezone":"Europe/Madrid",
    "iso:country":"ES",
    "wof:name":"Almarail",
    "wof:placetype":"locality"
},
  "geometry": {"coordinates":[-2.38021,41.58097],"type":"Point"}
}