{
  "type": "Feature",
  "properties": {
    "gn:admin1_code":"55",
    "gn:admin2_code":"SG",
    "gn:admin3_code":"40170",
    "gn:asciiname":"El Negredo",
    "gn:country_code":"ES",
    "gn:dem":1104,
    "gn:feature_class":"P",
    "gn:feature_code":"PPL",
    "gn:name":"El Negredo",
    "gn:population":0,
    "gn:timezone":"Europe/Madrid",
    "iso:country":"ES",
    "name:und_x_variant":[
        "Negredo",
        "El Negredo"
    ],
    "wof:name":"El Negredo",
    "wof:placetype":"locality"
},
  "geometry": {"coordinates":[-3.31436,41.3268],"type":"Point"}
}