{
  "type": "Feature",
  "properties": {
    "gn:admin1_code":"53",
    "gn:admin2_code":"TF",
    "gn:admin3_code":"38020",
    "gn:asciiname":"Vista Ramos",
    "gn:country_code":"ES",
    "gn:dem":389,
    "gn:feature_class":"P",
    "gn:feature_code":"PPL",
    "gn:name":"Vista Ramos",
    "gn:population":0,
    "gn:timezone":"Atlantic/Canary",
    "iso:country":"ES",
    "wof:name":"Vista Ramos",
    "wof:placetype":"locality"
},
  "geometry": {"coordinates":[-16.41849,28.32148],"type":"Point"}
}