{
  "type": "Feature",
  "properties": {
    "gn:admin1_code":"55",
    "gn:admin2_code":"SA",
    "gn:admin3_code":"37041",
    "gn:asciiname":"Corral de Garcinigo",
    "gn:country_code":"ES",
    "gn:dem":943,
    "gn:feature_class":"P",
    "gn:feature_code":"PPL",
    "gn:name":"Corral de Garc\u00ed\u00f1igo",
    "gn:population":0,
    "gn:timezone":"Europe/Madrid",
    "iso:country":"ES",
    "name:und_x_variant":[
        "Corral de Garc\u00ed\u00f1igo"
    ],
    "wof:name":"Corral de Garcinigo",
    "wof:placetype":"locality"
},
  "geometry": {"coordinates":[-5.93505,40.65192],"type":"Point"}
}