{
  "type": "Feature",
  "properties": {
    "gn:admin1_code":"54",
    "gn:admin2_code":"AB",
    "gn:admin3_code":"02022",
    "gn:asciiname":"El Puerto",
    "gn:country_code":"ES",
    "gn:dem":1238,
    "gn:feature_class":"P",
    "gn:feature_code":"PPL",
    "gn:name":"El Puerto",
    "gn:population":0,
    "gn:timezone":"Europe/Madrid",
    "iso:country":"ES",
    "name:ast_x_preferred":[
        "El Puertu"
    ],
    "name:ceb_x_preferred":[
        "El Puerto"
    ],
    "name:deu_x_preferred":[
        "El Puerto"
    ],
    "name:spa_x_preferred":[
        "El Puerto"
    ],
    "name:srp_x_preferred":[
        "\u0415\u043b \u041f\u0443\u0435\u0440\u0442\u043e"
    ],
    "name:swe_x_preferred":[
        "El Puerto"
    ],
    "name:und_x_variant":[
        "Caser\u00edo El Puerto",
        "El Puerto"
    ],
    "wof:name":"El Puerto",
    "wof:placetype":"locality"
},
  "geometry": {"coordinates":[-2.15929,38.6797],"type":"Point"}
}