{
  "type": "Feature",
  "properties": {
    "iso:country":"ES",
    "qs_pg:aaroncc":"ES",
    "qs_pg:name":"Bahia",
    "qs_pg:name_adm0":"Espa\u00f1a",
    "qs_pg:name_adm1":"Regi\u00f3n de Murcia",
    "qs_pg:photos":239,
    "qs_pg:photos_1k":48,
    "qs_pg:photos_9k":1,
    "qs_pg:photos_9r":4,
    "qs_pg:photos_all":239,
    "qs_pg:photos_sr":4,
    "qs_pg:pop_sr":0,
    "qs_pg:qs_pg_placetype":"locality",
    "qs_pg:qs_pg_placetype_gp":"Town",
    "qs_pg:woe_adm0":23424950,
    "woe:adm0_id":23424950,
    "woe:name_adm0":"Espa\u00f1a",
    "woe:name_adm1":"Regi\u00f3n de Murcia",
    "woe:placetype":"Town",
    "wof:name":"Bahia",
    "wof:placetype":"locality"
},
  "geometry": {"coordinates":[-1.272354,37.559743],"type":"Point"}
}