{
  "type": "Feature",
  "properties": {
    "iso:country":"ES",
    "name:spa_x_preferred":[
        "Grupo Teniente Ortiz de Z\u00e1rate"
    ],
    "wof:name":"Grupo Teniente Ortiz de Zarate",
    "wof:placetype":"neighbourhood"
},
  "geometry": {"coordinates":[-0.87315952494272,41.66667257466848],"type":"Point"}
}