{
  "type": "Feature",
  "properties": {
    "gn:country":"ES",
    "gn:fcode":"PPL",
    "gn:population":159,
    "iso:country":"ES",
    "name:arg_x_preferred":[
        "\u00dacar"
    ],
    "name:ast_x_preferred":[
        "Ukar"
    ],
    "name:bre_x_preferred":[
        "Ukar"
    ],
    "name:cat_x_preferred":[
        "Ukar"
    ],
    "name:ceb_x_preferred":[
        "\u00dacar"
    ],
    "name:eng_x_preferred":[
        "\u00dacar"
    ],
    "name:eus_x_preferred":[
        "Ukar"
    ],
    "name:fra_x_preferred":[
        "\u00dacar"
    ],
    "name:hun_x_preferred":[
        "\u00dacar"
    ],
    "name:ita_x_preferred":[
        "Ucar"
    ],
    "name:jpn_x_preferred":[
        "\u30a6\u30ab\u30eb"
    ],
    "name:msa_x_preferred":[
        "\u00dacar"
    ],
    "name:nan_x_preferred":[
        "\u00dacar"
    ],
    "name:nld_x_preferred":[
        "Ucar"
    ],
    "name:oci_x_preferred":[
        "Ukar"
    ],
    "name:pol_x_preferred":[
        "Ucar"
    ],
    "name:por_x_preferred":[
        "\u00dacar"
    ],
    "name:rus_x_preferred":[
        "\u0423\u043a\u0430\u0440"
    ],
    "name:spa_x_preferred":[
        "\u00dacar"
    ],
    "name:swe_x_preferred":[
        "\u00dacar"
    ],
    "name:ukr_x_preferred":[
        "\u0423\u043a\u0430\u0440"
    ],
    "name:uzb_x_preferred":[
        "\u00dacar"
    ],
    "name:vie_x_preferred":[
        "\u00dacar"
    ],
    "name:war_x_preferred":[
        "\u00dacar"
    ],
    "name:zho_x_preferred":[
        "\u4e4c\u5361\u5c14"
    ],
    "qs_pg:aaroncc":"ES",
    "qs_pg:gn_country":"ES",
    "qs_pg:gn_fcode":"PPL",
    "qs_pg:gn_pop":159,
    "qs_pg:name":"Ucar",
    "qs_pg:name_adm0":"Espa\u00f1a",
    "qs_pg:name_adm1":"Comunidad Foral de Navarra",
    "qs_pg:photos_9r":0,
    "qs_pg:photos_sr":0,
    "qs_pg:pop_sr":1,
    "qs_pg:qs_pg_placetype":"locality",
    "qs_pg:qs_pg_placetype_gp":"Town",
    "qs_pg:woe_adm0":23424950,
    "woe:adm0_id":23424950,
    "woe:name_adm0":"Espa\u00f1a",
    "woe:name_adm1":"Comunidad Foral de Navarra",
    "woe:placetype":"Town",
    "wof:name":"Ucar",
    "wof:placetype":"locality",
    "wof:population":159
},
  "geometry": {"coordinates":[-1.70237,42.65694],"type":"Point"}
}