{
  "type": "Feature",
  "properties": {
    "gn:admin1_code":"58",
    "gn:admin2_code":"LU",
    "gn:admin3_code":"27012",
    "gn:asciiname":"San Martin de las Canadas",
    "gn:country_code":"ES",
    "gn:dem":516,
    "gn:feature_class":"P",
    "gn:feature_code":"PPL",
    "gn:name":"San Mart\u00edn de las Ca\u00f1adas",
    "gn:population":0,
    "gn:timezone":"Europe/Madrid",
    "iso:country":"ES",
    "wof:name":"San Martin de las Canadas",
    "wof:placetype":"locality"
},
  "geometry": {"coordinates":[-7.06437,42.82283],"type":"Point"}
}