{
  "type": "Feature",
  "properties": {
    "gn:admin1_code":"52",
    "gn:admin2_code":"TE",
    "gn:admin3_code":"44127",
    "gn:asciiname":"Arroyofrio",
    "gn:country_code":"ES",
    "gn:dem":1486,
    "gn:feature_class":"P",
    "gn:feature_code":"PPL",
    "gn:name":"Arroyofr\u00edo",
    "gn:population":0,
    "gn:timezone":"Europe/Madrid",
    "iso:country":"ES",
    "name:und_x_variant":[
        "Arroyofr\u00edo"
    ],
    "wof:name":"Arroyofrio",
    "wof:placetype":"locality"
},
  "geometry": {"coordinates":[-1.48274,40.23325],"type":"Point"}
}