{
  "type": "Feature",
  "properties": {
    "gn:admin1_code":"55",
    "gn:admin2_code":"SO",
    "gn:admin3_code":"42043",
    "gn:asciiname":"Valdelubiel",
    "gn:country_code":"ES",
    "gn:dem":947,
    "gn:feature_class":"P",
    "gn:feature_code":"PPL",
    "gn:name":"Valdelubiel",
    "gn:population":0,
    "gn:timezone":"Europe/Madrid",
    "iso:country":"ES",
    "name:und_x_variant":[
        "Valdeluviel",
        "Valdelubiel"
    ],
    "wof:name":"Valdelubiel",
    "wof:placetype":"locality"
},
  "geometry": {"coordinates":[-3.05,41.63987],"type":"Point"}
}