{
  "type": "Feature",
  "properties": {
    "gn:admin1_code":"55",
    "gn:admin2_code":"AV",
    "gn:admin3_code":"05225",
    "gn:asciiname":"Valdemolinos",
    "gn:country_code":"ES",
    "gn:dem":1059,
    "gn:feature_class":"P",
    "gn:feature_code":"PPL",
    "gn:name":"Valdemolinos",
    "gn:population":0,
    "gn:timezone":"Europe/Madrid",
    "iso:country":"ES",
    "wof:name":"Valdemolinos",
    "wof:placetype":"locality"
},
  "geometry": {"coordinates":[-5.41679,40.51548],"type":"Point"}
}