{
  "type": "Feature",
  "properties": {
    "gn:country":"ES",
    "gn:fcode":"PPLA3",
    "gn:population":96,
    "iso:country":"ES",
    "name:arg_x_preferred":[
        "Torre d'Arcas"
    ],
    "name:cat_x_preferred":[
        "Torredarques"
    ],
    "name:che_x_preferred":[
        "\u0422\u043e\u0440\u0440\u0435-\u0434\u0435-\u0410\u0440\u043a\u0430\u0441"
    ],
    "name:deu_x_preferred":[
        "Torre de Arcas"
    ],
    "name:eng_x_preferred":[
        "Torre de Arcas"
    ],
    "name:eus_x_preferred":[
        "Torre de Arcas"
    ],
    "name:fra_x_preferred":[
        "Torre de Arcas"
    ],
    "name:hun_x_preferred":[
        "Torre de Arcas"
    ],
    "name:ita_x_preferred":[
        "Torre de Arcas"
    ],
    "name:kaz_x_preferred":[
        "\u0422\u043e\u0440\u0440\u0435-\u0434\u0435-\u0410\u0440\u043a\u0430\u0441"
    ],
    "name:msa_x_preferred":[
        "Torre de Arcas"
    ],
    "name:nan_x_preferred":[
        "Torre de Arcas"
    ],
    "name:nld_x_preferred":[
        "Torre de Arcas"
    ],
    "name:oci_x_preferred":[
        "Torredarques"
    ],
    "name:pol_x_preferred":[
        "Torre de Arcas"
    ],
    "name:por_x_preferred":[
        "Torre de Arcas"
    ],
    "name:rus_x_preferred":[
        "\u0422\u043e\u0440\u0440\u0435-\u0434\u0435-\u0410\u0440\u043a\u0430\u0441"
    ],
    "name:spa_x_preferred":[
        "Torre de Arcas"
    ],
    "name:swe_x_preferred":[
        "Torre de Arcas"
    ],
    "name:tat_x_preferred":[
        "\u0422\u043e\u0440\u0440\u0435-\u0434\u0435-\u0410\u0440\u043a\u0430\u0441"
    ],
    "name:ukr_x_preferred":[
        "\u0422\u043e\u0440\u0440\u0435-\u0434\u0435-\u0410\u0440\u043a\u0430\u0441"
    ],
    "name:uzb_x_preferred":[
        "Torre de Arcas"
    ],
    "name:vie_x_preferred":[
        "Torre de Arcas"
    ],
    "name:war_x_preferred":[
        "Torre de Arcas"
    ],
    "name:zho_x_preferred":[
        "\u6258\u96f7\u5fb7\u4e9a\u5c14\u5361\u65af"
    ],
    "qs_pg:aaroncc":"ES",
    "qs_pg:gn_country":"ES",
    "qs_pg:gn_fcode":"PPLA3",
    "qs_pg:gn_pop":96,
    "qs_pg:name":"Torre de Arcas",
    "qs_pg:name_adm0":"Espa\u00f1a",
    "qs_pg:name_adm1":"Arag\u00f3n",
    "qs_pg:photos":22,
    "qs_pg:photos_1k":4,
    "qs_pg:photos_9k":1,
    "qs_pg:photos_9r":1,
    "qs_pg:photos_all":22,
    "qs_pg:photos_sr":1,
    "qs_pg:pop_sr":1,
    "qs_pg:qs_pg_placetype":"locality",
    "qs_pg:qs_pg_placetype_gp":"Town",
    "qs_pg:woe_adm0":23424950,
    "woe:adm0_id":23424950,
    "woe:name_adm0":"Espa\u00f1a",
    "woe:name_adm1":"Arag\u00f3n",
    "woe:placetype":"Town",
    "wof:name":"Torre de Arcas",
    "wof:placetype":"locality",
    "wof:population":96
},
  "geometry": {"coordinates":[-0.06892,40.75137],"type":"Point"}
}