{
  "type": "Feature",
  "properties": {
    "gn:admin1_code":"59",
    "gn:admin2_code":"SS",
    "gn:admin3_code":"20074",
    "gn:asciiname":"Aranzeta",
    "gn:country_code":"ES",
    "gn:dem":364,
    "gn:feature_class":"P",
    "gn:feature_code":"PPLL",
    "gn:name":"Arantzeta",
    "gn:population":0,
    "gn:timezone":"Europe/Madrid",
    "iso:country":"ES",
    "name:eus_x_preferred":[
        "Aranzeta"
    ],
    "wof:name":"Aranzeta",
    "wof:placetype":"locality"
},
  "geometry": {"coordinates":[-2.47184,43.14458],"type":"Point"}
}