{
  "type": "Feature",
  "properties": {
    "gn:admin1_code":"55",
    "gn:admin2_code":"BU",
    "gn:admin3_code":"09297",
    "gn:asciiname":"Villarmentero",
    "gn:country_code":"ES",
    "gn:dem":832,
    "gn:feature_class":"P",
    "gn:feature_code":"PPL",
    "gn:name":"Villarmentero",
    "gn:population":0,
    "gn:timezone":"Europe/Madrid",
    "iso:country":"ES",
    "wof:name":"Villarmentero",
    "wof:placetype":"locality"
},
  "geometry": {"coordinates":[-3.82341,42.37364],"type":"Point"}
}