{
  "type": "Feature",
  "properties": {
    "gn:admin1_code":"58",
    "gn:admin2_code":"OR",
    "gn:admin3_code":"32071",
    "gn:asciiname":"As Ferreiras",
    "gn:country_code":"ES",
    "gn:dem":877,
    "gn:feature_class":"P",
    "gn:feature_code":"PPL",
    "gn:name":"As Ferreiras",
    "gn:population":0,
    "gn:timezone":"Europe/Madrid",
    "iso:country":"ES",
    "wof:name":"As Ferreiras",
    "wof:placetype":"locality"
},
  "geometry": {"coordinates":[-7.2908,41.98476],"type":"Point"}
}