{
  "type": "Feature",
  "properties": {
    "gn:gn_country":"ES",
    "gn:gn_fcode":"PPLA3",
    "gn:gn_pop":163,
    "gn:population":163,
    "iso:country":"ES",
    "name:arg_x_preferred":[
        "Fonzaleche"
    ],
    "name:arm_x_preferred":[
        "\u0556\u0578\u0576\u057d\u0561\u056c\u0565\u0579\u0565"
    ],
    "name:baq_x_preferred":[
        "Fonzaleche"
    ],
    "name:cat_x_preferred":[
        "Fonzaleche"
    ],
    "name:chi_x_preferred":[
        "\u4e30\u8428\u83b1\u5207"
    ],
    "name:dut_x_preferred":[
        "Fonzaleche"
    ],
    "name:eng_x_preferred":[
        "Fonzaleche"
    ],
    "name:fre_x_preferred":[
        "Fonzaleche"
    ],
    "name:glg_x_preferred":[
        "Fonzaleche"
    ],
    "name:hun_x_preferred":[
        "Fonzaleche"
    ],
    "name:ita_x_preferred":[
        "Fonzaleche"
    ],
    "name:kaz_x_preferred":[
        "\u0424\u043e\u043d\u0441\u0430\u043b\u0435\u0447\u0435"
    ],
    "name:may_x_preferred":[
        "Fonzaleche"
    ],
    "name:nan_x_preferred":[
        "Fonzaleche"
    ],
    "name:oci_x_preferred":[
        "Fonzaleche"
    ],
    "name:pol_x_preferred":[
        "Fonzaleche"
    ],
    "name:por_x_preferred":[
        "Fonzaleche"
    ],
    "name:rup_x_preferred":[
        "Fonzaleche"
    ],
    "name:rus_x_preferred":[
        "\u0424\u043e\u043d\u0441\u0430\u043b\u0435\u0447\u0435"
    ],
    "name:spa_x_preferred":[
        "Fonzaleche"
    ],
    "name:swe_x_preferred":[
        "Fonzaleche"
    ],
    "name:ukr_x_preferred":[
        "\u0424\u043e\u043d\u0441\u0430\u043b\u0435\u0447\u0435"
    ],
    "name:uzb_x_preferred":[
        "Fonzaleche"
    ],
    "name:vie_x_preferred":[
        "Fonzaleche"
    ],
    "name:war_x_preferred":[
        "Fonzaleche"
    ],
    "qs_pg:aaroncc":"ES",
    "qs_pg:gn_country":"ES",
    "qs_pg:gn_fcode":"PPLA3",
    "qs_pg:gn_pop":163,
    "qs_pg:name":"Fonzaleche",
    "qs_pg:name_adm0":"Espa\u00f1a",
    "qs_pg:name_adm1":"La Rioja",
    "qs_pg:photos_9r":0,
    "qs_pg:photos_sr":0,
    "qs_pg:pop_sr":1,
    "qs_pg:qs_pg_placetype":"locality",
    "qs_pg:qs_pg_placetype_gp":"Town",
    "qs_pg:woe_adm0":23424950,
    "woe:adm0_id":23424950,
    "woe:name_adm0":"Espa\u00f1a",
    "woe:name_adm1":"La Rioja",
    "woe:placetype":"Town",
    "wof:name":"Fonzaleche",
    "wof:placetype":"locality",
    "wof:population":163
},
  "geometry": {"coordinates":[-3.01218,42.58114],"type":"Point"}
}