{
  "type": "Feature",
  "properties": {
    "gn:admin1_code":"55",
    "gn:admin2_code":"BU",
    "gn:admin3_code":"09125",
    "gn:asciiname":"Vilviestre de Muno",
    "gn:country_code":"ES",
    "gn:dem":832,
    "gn:feature_class":"P",
    "gn:feature_code":"PPL",
    "gn:name":"Vilviestre de Mu\u00f1\u00f3",
    "gn:population":0,
    "gn:timezone":"Europe/Madrid",
    "iso:country":"ES",
    "wof:name":"Vilviestre de Muno",
    "wof:placetype":"locality"
},
  "geometry": {"coordinates":[-3.93362,42.29077],"type":"Point"}
}