{
  "type": "Feature",
  "properties": {
    "gn:admin1_code":"60",
    "gn:admin2_code":"A",
    "gn:admin3_code":"03019",
    "gn:asciiname":"Ofra",
    "gn:cc2":"ES",
    "gn:country_code":"ES",
    "gn:dem":298,
    "gn:feature_class":"P",
    "gn:feature_code":"PPL",
    "gn:name":"Ofra",
    "gn:population":0,
    "gn:timezone":"Europe/Madrid",
    "iso:country":"ES",
    "name:ara_x_preferred":[
        "\u0639\u0648\u0641\u0631\u0627"
    ],
    "name:ces_x_preferred":[
        "Ofra"
    ],
    "name:deu_x_preferred":[
        "Ofra"
    ],
    "name:heb_x_preferred":[
        "\u05e2\u05e4\u05e8\u05d4"
    ],
    "name:nld_x_preferred":[
        "Ofra"
    ],
    "name:nno_x_preferred":[
        "Ofra"
    ],
    "name:pol_x_preferred":[
        "Ofra"
    ],
    "name:rus_x_preferred":[
        "\u041e\u0444\u0440\u0430"
    ],
    "name:und_x_variant":[
        "Caser\u00edo Ofra",
        "Ofra"
    ],
    "wof:name":"Ofra",
    "wof:placetype":"locality"
},
  "geometry": {"coordinates":[-0.81667,38.31667],"type":"Point"}
}