{
  "type": "Feature",
  "properties": {
    "gn:admin1_code":"57",
    "gn:admin2_code":"CC",
    "gn:admin3_code":"10195",
    "gn:asciiname":"La Cumbre",
    "gn:country_code":"ES",
    "gn:dem":482,
    "gn:feature_class":"P",
    "gn:feature_code":"PPL",
    "gn:name":"La Cumbre",
    "gn:population":1027,
    "gn:timezone":"Europe/Madrid",
    "iso:country":"ES",
    "wof:name":"La Cumbre",
    "wof:placetype":"locality",
    "wof:population":1027
},
  "geometry": {"coordinates":[-5.97635,39.4046],"type":"Point"}
}