{
  "type": "Feature",
  "properties": {
    "gn:admin1_code":"57",
    "gn:admin2_code":"CC",
    "gn:admin3_code":"10195",
    "gn:asciiname":"La Cumbre",
    "gn:country_code":"ES",
    "gn:dem":482,
    "gn:feature_class":"P",
    "gn:feature_code":"PPL",
    "gn:name":"La Cumbre",
    "gn:population":1027,
    "gn:timezone":"Europe/Madrid",
    "iso:country":"ES",
    "name:ara_x_preferred":[
        "\u0644\u0627 \u0643\u0648\u0645\u0628\u0631\u064a"
    ],
    "name:cat_x_preferred":[
        "La Cumbre"
    ],
    "name:ceb_x_preferred":[
        "La Cumbre"
    ],
    "name:epo_x_preferred":[
        "La Cumbre"
    ],
    "name:eus_x_preferred":[
        "La Cumbre"
    ],
    "name:fra_x_preferred":[
        "La Cumbre"
    ],
    "name:hun_x_preferred":[
        "La Cumbre"
    ],
    "name:hye_x_preferred":[
        "\u053c\u0561 \u053f\u0578\u0582\u0574\u0562\u0580\u0565"
    ],
    "name:ina_x_preferred":[
        "La Cumbre"
    ],
    "name:ita_x_preferred":[
        "La Cumbre"
    ],
    "name:msa_x_preferred":[
        "La Cumbre"
    ],
    "name:nld_x_preferred":[
        "La Cumbre"
    ],
    "name:oci_x_preferred":[
        "La Cumbre"
    ],
    "name:pol_x_preferred":[
        "La Cumbre"
    ],
    "name:por_x_preferred":[
        "La Cumbre"
    ],
    "name:ron_x_preferred":[
        "La Cumbre"
    ],
    "name:rus_x_preferred":[
        "\u041b\u0430-\u041a\u0443\u043c\u0431\u0440\u0435"
    ],
    "name:spa_x_preferred":[
        "La Cumbre"
    ],
    "name:ukr_x_preferred":[
        "\u041b\u0430-\u041a\u0443\u043c\u0431\u0440\u0435"
    ],
    "name:uzb_x_preferred":[
        "La Cumbre"
    ],
    "name:vie_x_preferred":[
        "La Cumbre"
    ],
    "name:war_x_preferred":[
        "La Cumbre"
    ],
    "name:zho_x_preferred":[
        "\u62c9\u6606\u592b\u96f7"
    ],
    "wof:name":"La Cumbre",
    "wof:placetype":"locality",
    "wof:population":1027
},
  "geometry": {"coordinates":[-5.97635,39.4046],"type":"Point"}
}