{
  "type": "Feature",
  "properties": {
    "iso:country":"ES",
    "wof:name":"Masustegi",
    "wof:placetype":"neighbourhood"
},
  "geometry": {"coordinates":[-2.95636189455083,43.2552660378775],"type":"Point"}
}