{
  "type": "Feature",
  "properties": {
    "gn:gn_country":"ES",
    "gn:gn_fcode":"PPL",
    "gn:gn_pop":93,
    "gn:population":93,
    "iso:country":"ES",
    "name:cat_x_preferred":[
        "L'Hostalnou de Bianya"
    ],
    "name:eng_x_preferred":[
        "L'Hostalnou de Bianya"
    ],
    "name:tah_x_preferred":[
        "L'Hostalnou de Bianya"
    ],
    "qs_pg:aaroncc":"ES",
    "qs_pg:gn_country":"ES",
    "qs_pg:gn_fcode":"PPL",
    "qs_pg:gn_pop":93,
    "qs_pg:name":"L'Hostalnou de Bianya",
    "qs_pg:name_adm0":"Espa\u00f1a",
    "qs_pg:name_adm1":"Catalunya",
    "qs_pg:photos_9r":0,
    "qs_pg:photos_sr":0,
    "qs_pg:pop_sr":1,
    "qs_pg:qs_pg_placetype":"locality",
    "qs_pg:qs_pg_placetype_gp":"Town",
    "qs_pg:woe_adm0":23424950,
    "woe:adm0_id":23424950,
    "woe:name_adm0":"Espa\u00f1a",
    "woe:name_adm1":"Catalunya",
    "woe:placetype":"Town",
    "wof:name":"L'Hostalnou de Bianya",
    "wof:placetype":"locality",
    "wof:population":93
},
  "geometry": {"coordinates":[2.45407,42.2118],"type":"Point"}
}