{
  "type": "Feature",
  "properties": {
    "gn:admin1_code":"55",
    "gn:admin2_code":"LE",
    "gn:admin3_code":"24162",
    "gn:asciiname":"Santovenia de Valdoncina",
    "gn:country_code":"ES",
    "gn:dem":836,
    "gn:feature_class":"P",
    "gn:feature_code":"PPL",
    "gn:name":"Santovenia de Valdoncina",
    "gn:population":0,
    "gn:timezone":"Europe/Madrid",
    "iso:country":"ES",
    "wof:name":"Santovenia de Valdoncina",
    "wof:placetype":"locality"
},
  "geometry": {"coordinates":[-5.62306,42.54299],"type":"Point"}
}