{
  "type": "Feature",
  "properties": {
    "gn:admin1_code":"32",
    "gn:admin3_code":"31136",
    "gn:asciiname":"Beorburu",
    "gn:country_code":"ES",
    "gn:dem":730,
    "gn:feature_class":"P",
    "gn:feature_code":"PPL",
    "gn:name":"Beorburu",
    "gn:population":0,
    "gn:timezone":"Europe/Madrid",
    "iso:country":"ES",
    "wof:name":"Beorburu",
    "wof:placetype":"locality"
},
  "geometry": {"coordinates":[-1.73249,42.91539],"type":"Point"}
}