{
  "type": "Feature",
  "properties": {
    "gn:admin1_code":"34",
    "gn:admin2_code":"O",
    "gn:admin3_code":"33037",
    "gn:asciiname":"San Justo",
    "gn:country_code":"ES",
    "gn:dem":840,
    "gn:feature_class":"P",
    "gn:feature_code":"PPL",
    "gn:name":"San Justo",
    "gn:population":0,
    "gn:timezone":"Europe/Madrid",
    "iso:country":"ES",
    "name:ara_x_preferred":[
        "\u0633\u0627\u0646 \u062c\u0648\u0633\u062a\u0648"
    ],
    "name:ben_x_preferred":[
        "\u09b8\u09be\u09a8 \u099c\u09c1\u09b8\u09cd\u09a4\u09cb"
    ],
    "name:cat_x_preferred":[
        "Sant Just"
    ],
    "name:ceb_x_preferred":[
        "San Justo"
    ],
    "name:deu_x_preferred":[
        "San Justo"
    ],
    "name:ell_x_preferred":[
        "\u03a3\u03b1\u03bd \u03a7\u03bf\u03cd\u03c3\u03c4\u03bf"
    ],
    "name:eus_x_preferred":[
        "San Justo"
    ],
    "name:fas_x_preferred":[
        "\u0633\u0646 \u062c\u0627\u0633\u062a\u0648"
    ],
    "name:fra_x_preferred":[
        "San Justo"
    ],
    "name:heb_x_preferred":[
        "\u05e1\u05df \u05d7\u05d5\u05e1\u05d8\u05d5"
    ],
    "name:hin_x_preferred":[
        "\u0938\u0948\u0928 \u091c\u0938\u094d\u091f\u094b"
    ],
    "name:hun_x_preferred":[
        "San Justo"
    ],
    "name:ind_x_preferred":[
        "San Justo"
    ],
    "name:ita_x_preferred":[
        "San Justo"
    ],
    "name:kor_x_preferred":[
        "\uc0b0 \ud6c4\uc2a4\ud1a0"
    ],
    "name:nld_x_preferred":[
        "San Justo"
    ],
    "name:pol_x_preferred":[
        "San Justo"
    ],
    "name:sco_x_preferred":[
        "San Justo"
    ],
    "name:spa_x_preferred":[
        "San Justo"
    ],
    "name:swe_x_preferred":[
        "San Justo"
    ],
    "name:tur_x_preferred":[
        "San Justo"
    ],
    "name:ukr_x_preferred":[
        "\u0421\u0430\u043d-\u0425\u0443\u0441\u0442\u043e"
    ],
    "name:urd_x_preferred":[
        "\u0633\u0627\u0646 \u062c\u0648\u0633\u0679\u0648"
    ],
    "name:vie_x_preferred":[
        "San Justo"
    ],
    "wof:name":"San Justo",
    "wof:placetype":"locality"
},
  "geometry": {"coordinates":[-5.69793,43.2286],"type":"Point"}
}