{
  "type": "Feature",
  "properties": {
    "gn:admin1_code":"34",
    "gn:admin2_code":"O",
    "gn:admin3_code":"33037",
    "gn:asciiname":"San Justo",
    "gn:country_code":"ES",
    "gn:dem":840,
    "gn:feature_class":"P",
    "gn:feature_code":"PPL",
    "gn:name":"San Justo",
    "gn:population":0,
    "gn:timezone":"Europe/Madrid",
    "iso:country":"ES",
    "name:cat_x_preferred":[
        "Sant Just"
    ],
    "name:ceb_x_preferred":[
        "San Justo"
    ],
    "name:deu_x_preferred":[
        "San Justo"
    ],
    "name:eus_x_preferred":[
        "San Justo"
    ],
    "name:fra_x_preferred":[
        "San Justo"
    ],
    "name:ita_x_preferred":[
        "San Justo"
    ],
    "name:nld_x_preferred":[
        "San Justo"
    ],
    "name:pol_x_preferred":[
        "San Justo"
    ],
    "name:sco_x_preferred":[
        "San Justo"
    ],
    "name:spa_x_preferred":[
        "San Justo"
    ],
    "name:swe_x_preferred":[
        "San Justo"
    ],
    "name:ukr_x_preferred":[
        "\u0421\u0430\u043d-\u0425\u0443\u0441\u0442\u043e"
    ],
    "wof:name":"San Justo",
    "wof:placetype":"locality"
},
  "geometry": {"coordinates":[-5.69793,43.2286],"type":"Point"}
}