{
  "type": "Feature",
  "properties": {
    "gn:country":"ES",
    "gn:fcode":"PPLA3",
    "gn:population":861,
    "iso:country":"ES",
    "name:arg_x_preferred":[
        "Arganza"
    ],
    "name:ast_x_preferred":[
        "Arganza"
    ],
    "name:cat_x_preferred":[
        "Arganza"
    ],
    "name:ceb_x_preferred":[
        "Arganza"
    ],
    "name:eng_x_preferred":[
        "Arganza"
    ],
    "name:eus_x_preferred":[
        "Arganza"
    ],
    "name:fra_x_preferred":[
        "Arganza"
    ],
    "name:glg_x_preferred":[
        "Arganza"
    ],
    "name:haw_x_preferred":[
        "Arganza"
    ],
    "name:hun_x_preferred":[
        "Arganza"
    ],
    "name:ido_x_preferred":[
        "Arganza"
    ],
    "name:ina_x_preferred":[
        "Arganza"
    ],
    "name:ita_x_preferred":[
        "Arganza"
    ],
    "name:lat_x_preferred":[
        "Arganda"
    ],
    "name:msa_x_preferred":[
        "Arganza"
    ],
    "name:nld_x_preferred":[
        "Arganza"
    ],
    "name:oci_x_preferred":[
        "Arganza"
    ],
    "name:pol_x_preferred":[
        "Arganza"
    ],
    "name:por_x_preferred":[
        "Arganza"
    ],
    "name:rup_x_preferred":[
        "Arganza"
    ],
    "name:rus_x_preferred":[
        "\u0410\u0440\u0433\u0430\u043d\u0441\u0430"
    ],
    "name:spa_x_preferred":[
        "Arganza"
    ],
    "name:swe_x_preferred":[
        "Arganza"
    ],
    "name:tpi_x_preferred":[
        "Arganza"
    ],
    "name:ukr_x_preferred":[
        "\u0410\u0440\u0433\u0430\u043d\u0441\u0430"
    ],
    "name:vie_x_preferred":[
        "Arganza"
    ],
    "name:war_x_preferred":[
        "Arganza"
    ],
    "name:zho_x_preferred":[
        "\u963f\u5c14\u7518\u8428"
    ],
    "qs_pg:aaroncc":"ES",
    "qs_pg:gn_country":"ES",
    "qs_pg:gn_fcode":"PPLA3",
    "qs_pg:gn_pop":861,
    "qs_pg:name":"Arganza",
    "qs_pg:name_adm0":"Espa\u00f1a",
    "qs_pg:name_adm1":"Castilla y Le\u00f3n",
    "qs_pg:photos":29,
    "qs_pg:photos_1k":6,
    "qs_pg:photos_9k":1,
    "qs_pg:photos_9r":2,
    "qs_pg:photos_all":29,
    "qs_pg:photos_sr":2,
    "qs_pg:pop_sr":2,
    "qs_pg:qs_pg_placetype":"locality",
    "qs_pg:qs_pg_placetype_gp":"Town",
    "qs_pg:woe_adm0":23424950,
    "woe:adm0_id":23424950,
    "woe:name_adm0":"Espa\u00f1a",
    "woe:name_adm1":"Castilla y Le\u00f3n",
    "woe:placetype":"Town",
    "wof:name":"Arganza",
    "wof:placetype":"locality",
    "wof:population":861
},
  "geometry": {"coordinates":[-6.68627,42.64077],"type":"Point"}
}