{
  "type": "Feature",
  "properties": {
    "gn:gn_country":"ES",
    "gn:gn_fcode":"PPL",
    "gn:gn_pop":270,
    "gn:population":270,
    "iso:country":"ES",
    "name:arg_x_preferred":[
        "Oliola"
    ],
    "name:cat_x_preferred":[
        "Oliola"
    ],
    "name:eng_x_preferred":[
        "Oliola"
    ],
    "name:eus_x_preferred":[
        "Oliola"
    ],
    "name:fra_x_preferred":[
        "Oliola"
    ],
    "name:hun_x_preferred":[
        "Oliola"
    ],
    "name:hye_x_preferred":[
        "\u0555\u056c\u056b\u0578\u056c\u0561"
    ],
    "name:ita_x_preferred":[
        "Oliola"
    ],
    "name:nld_x_preferred":[
        "Oliola"
    ],
    "name:oci_x_preferred":[
        "Oliola"
    ],
    "name:pol_x_preferred":[
        "Oliola"
    ],
    "name:por_x_preferred":[
        "Oliola"
    ],
    "name:ron_x_preferred":[
        "Oliola"
    ],
    "name:rus_x_preferred":[
        "\u041e\u043b\u0438\u043e\u043b\u0430"
    ],
    "name:sco_x_preferred":[
        "Oliola"
    ],
    "name:spa_x_preferred":[
        "Oliola"
    ],
    "name:sqi_x_preferred":[
        "Oliola"
    ],
    "name:swe_x_preferred":[
        "Oliola"
    ],
    "name:uzb_x_preferred":[
        "Oliola"
    ],
    "name:vie_x_preferred":[
        "Oliola"
    ],
    "name:war_x_preferred":[
        "Oliola"
    ],
    "name:zho_x_preferred":[
        "\u5965\u5229\u5965\u62c9"
    ],
    "qs_pg:aaroncc":"ES",
    "qs_pg:gn_country":"ES",
    "qs_pg:gn_fcode":"PPL",
    "qs_pg:gn_pop":270,
    "qs_pg:name":"Oliola",
    "qs_pg:name_adm0":"Espa\u00f1a",
    "qs_pg:name_adm1":"Catalunya",
    "qs_pg:photos_9k":1,
    "qs_pg:photos_9r":1,
    "qs_pg:photos_all":1,
    "qs_pg:photos_sr":0,
    "qs_pg:pop_sr":2,
    "qs_pg:qs_pg_placetype":"locality",
    "qs_pg:qs_pg_placetype_gp":"Town",
    "qs_pg:woe_adm0":23424950,
    "woe:adm0_id":23424950,
    "woe:name_adm0":"Espa\u00f1a",
    "woe:name_adm1":"Catalunya",
    "woe:placetype":"Town",
    "wof:name":"Oliola",
    "wof:placetype":"locality",
    "wof:population":270
},
  "geometry": {"coordinates":[1.17631,41.87566],"type":"Point"}
}