{
  "type": "Feature",
  "properties": {
    "gn:admin1_code":"55",
    "gn:admin2_code":"SO",
    "gn:admin3_code":"42014",
    "gn:asciiname":"Valloria",
    "gn:country_code":"ES",
    "gn:dem":1205,
    "gn:feature_class":"P",
    "gn:feature_code":"PPL",
    "gn:name":"Vallor\u00eda",
    "gn:population":0,
    "gn:timezone":"Europe/Madrid",
    "iso:country":"ES",
    "name:und_x_variant":[
        "Vallor\u00eda"
    ],
    "wof:name":"Valloria",
    "wof:placetype":"locality"
},
  "geometry": {"coordinates":[-2.38569,42.00654],"type":"Point"}
}