{
  "type": "Feature",
  "properties": {
    "gn:country":"ES",
    "gn:fcode":"PPLA3",
    "gn:population":1206,
    "iso:country":"ES",
    "name:ara_x_preferred":[
        "\u0644\u064a\u062a\u0648\u0631"
    ],
    "name:arg_x_preferred":[
        "Letur"
    ],
    "name:ast_x_preferred":[
        "Letur"
    ],
    "name:azb_x_preferred":[
        "\u0644\u062a\u0648\u0631"
    ],
    "name:cat_x_preferred":[
        "Letur"
    ],
    "name:ceb_x_preferred":[
        "Letur"
    ],
    "name:eng_x_preferred":[
        "Letur"
    ],
    "name:eus_x_preferred":[
        "Letur"
    ],
    "name:fas_x_preferred":[
        "\u0644\u062a\u0648\u0631"
    ],
    "name:fra_x_preferred":[
        "Letur"
    ],
    "name:hun_x_preferred":[
        "Letur"
    ],
    "name:ina_x_preferred":[
        "Letur"
    ],
    "name:ita_x_preferred":[
        "Letur"
    ],
    "name:msa_x_preferred":[
        "Letur"
    ],
    "name:nan_x_preferred":[
        "Letur"
    ],
    "name:nld_x_preferred":[
        "Letur"
    ],
    "name:oci_x_preferred":[
        "Letur"
    ],
    "name:pol_x_preferred":[
        "Letur"
    ],
    "name:por_x_preferred":[
        "Letur"
    ],
    "name:ron_x_preferred":[
        "Letur"
    ],
    "name:rus_x_preferred":[
        "\u041b\u0435\u0442\u0443\u0440"
    ],
    "name:spa_x_preferred":[
        "Letur"
    ],
    "name:swe_x_preferred":[
        "Letur"
    ],
    "name:ukr_x_preferred":[
        "\u041b\u0435\u0442\u0443\u0440"
    ],
    "name:vie_x_preferred":[
        "Letur"
    ],
    "name:war_x_preferred":[
        "Letur"
    ],
    "name:zho_x_preferred":[
        "\u83b1\u56fe\u5c14"
    ],
    "qs_pg:aaroncc":"ES",
    "qs_pg:gn_country":"ES",
    "qs_pg:gn_fcode":"PPLA3",
    "qs_pg:gn_pop":1206,
    "qs_pg:name":"Letur",
    "qs_pg:name_adm0":"Espa\u00f1a",
    "qs_pg:name_adm1":"Castilla-La Mancha",
    "qs_pg:photos":386,
    "qs_pg:photos_1k":78,
    "qs_pg:photos_9k":2,
    "qs_pg:photos_9r":5,
    "qs_pg:photos_all":386,
    "qs_pg:photos_sr":6,
    "qs_pg:pop_sr":3,
    "qs_pg:qs_pg_placetype":"locality",
    "qs_pg:qs_pg_placetype_gp":"Town",
    "qs_pg:woe_adm0":23424950,
    "woe:adm0_id":23424950,
    "woe:name_adm0":"Espa\u00f1a",
    "woe:name_adm1":"Castilla-La Mancha",
    "woe:placetype":"Town",
    "wof:name":"Letur",
    "wof:placetype":"locality",
    "wof:population":1206
},
  "geometry": {"coordinates":[-2.10206,38.36626],"type":"Point"}
}