{
  "type": "Feature",
  "properties": {
    "gn:gn_country":"ES",
    "gn:gn_fcode":"PPL",
    "gn:gn_pop":0,
    "iso:country":"ES",
    "name:deu_x_preferred":[
        "Foncebad\u00f3n"
    ],
    "name:eng_x_preferred":[
        "Foncebad\u00f3n"
    ],
    "name:fra_x_preferred":[
        "Foncebad\u00f3n"
    ],
    "name:ita_x_preferred":[
        "Foncebad\u00f3n"
    ],
    "name:nld_x_preferred":[
        "Foncebad\u00f3n"
    ],
    "name:spa_x_preferred":[
        "Foncebad\u00f3n"
    ],
    "qs_pg:aaroncc":"ES",
    "qs_pg:gn_country":"ES",
    "qs_pg:gn_fcode":"PPL",
    "qs_pg:gn_pop":0,
    "qs_pg:name":"Foncebad\u00f3n",
    "qs_pg:name_adm0":"Espa\u00f1a",
    "qs_pg:name_adm1":"Castilla y Le\u00f3n",
    "qs_pg:photos":577,
    "qs_pg:photos_1k":117,
    "qs_pg:photos_9k":3,
    "qs_pg:photos_9r":5,
    "qs_pg:photos_all":577,
    "qs_pg:photos_sr":8,
    "qs_pg:pop_sr":0,
    "qs_pg:qs_pg_placetype":"locality",
    "qs_pg:qs_pg_placetype_gp":"Town",
    "qs_pg:woe_adm0":23424950,
    "woe:adm0_id":23424950,
    "woe:name_adm0":"Espa\u00f1a",
    "woe:name_adm1":"Castilla y Le\u00f3n",
    "woe:placetype":"Town",
    "wof:name":"Foncebad\u00f3n",
    "wof:placetype":"locality"
},
  "geometry": {"coordinates":[-6.34368,42.49117],"type":"Point"}
}