{
  "type": "Feature",
  "properties": {
    "gn:admin1_code":"58",
    "gn:admin2_code":"C",
    "gn:admin3_code":"15052",
    "gn:asciiname":"Fumineo",
    "gn:country_code":"ES",
    "gn:dem":116,
    "gn:feature_class":"P",
    "gn:feature_code":"PPL",
    "gn:name":"Fumi\u00f1eo",
    "gn:population":0,
    "gn:timezone":"Europe/Madrid",
    "iso:country":"ES",
    "name:und_x_variant":[
        "Fumi\u00f1eu",
        "Fumi\u00f1eo"
    ],
    "wof:name":"Fumineo",
    "wof:placetype":"locality"
},
  "geometry": {"coordinates":[-9.16445,43.06755],"type":"Point"}
}