{
  "type": "Feature",
  "properties": {
    "gn:admin1_code":"58",
    "gn:admin2_code":"LU",
    "gn:admin3_code":"27045",
    "gn:asciiname":"Branas de Sierra",
    "gn:country_code":"ES",
    "gn:dem":1144,
    "gn:feature_class":"P",
    "gn:feature_code":"PPL",
    "gn:name":"Bra\u00f1as de Sierra",
    "gn:population":0,
    "gn:timezone":"Europe/Madrid",
    "iso:country":"ES",
    "wof:name":"Branas de Sierra",
    "wof:placetype":"locality"
},
  "geometry": {"coordinates":[-7.02498,42.65287],"type":"Point"}
}