{
  "type": "Feature",
  "properties": {
    "gn:admin1_code":"59",
    "gn:admin2_code":"BI",
    "gn:admin3_code":"48096",
    "gn:asciiname":"Llantada",
    "gn:country_code":"ES",
    "gn:dem":102,
    "gn:feature_class":"P",
    "gn:feature_code":"PPL",
    "gn:name":"Llantada",
    "gn:population":0,
    "gn:timezone":"Europe/Madrid",
    "iso:country":"ES",
    "wof:name":"Llantada",
    "wof:placetype":"locality"
},
  "geometry": {"coordinates":[-3.13014,43.2071],"type":"Point"}
}