{
  "type": "Feature",
  "properties": {
    "gn:admin1_code":"39",
    "gn:admin2_code":"S",
    "gn:admin3_code":"39069",
    "gn:asciiname":"Llano",
    "gn:country_code":"ES",
    "gn:dem":102,
    "gn:feature_class":"P",
    "gn:feature_code":"PPL",
    "gn:name":"Llano",
    "gn:population":0,
    "gn:timezone":"Europe/Madrid",
    "iso:country":"ES",
    "name:ceb_x_preferred":[
        "Llano"
    ],
    "name:deu_x_preferred":[
        "Llano"
    ],
    "name:eus_x_preferred":[
        "Llano"
    ],
    "name:fra_x_preferred":[
        "Llano"
    ],
    "name:hun_x_preferred":[
        "Llano"
    ],
    "name:ita_x_preferred":[
        "Llano"
    ],
    "name:nld_x_preferred":[
        "Llano"
    ],
    "name:pol_x_preferred":[
        "Llano"
    ],
    "name:rus_x_preferred":[
        "\u041b\u043b\u0430\u043d\u043e"
    ],
    "name:spa_x_preferred":[
        "Llano"
    ],
    "name:swe_x_preferred":[
        "Llano"
    ],
    "wof:name":"Llano",
    "wof:placetype":"locality"
},
  "geometry": {"coordinates":[-4.05543,43.27632],"type":"Point"}
}