{
  "type": "Feature",
  "properties": {
    "gn:admin1_code":"55",
    "gn:admin2_code":"BU",
    "gn:admin3_code":"09427",
    "gn:asciiname":"Hormicedo",
    "gn:country_code":"ES",
    "gn:dem":897,
    "gn:feature_class":"P",
    "gn:feature_code":"PPL",
    "gn:name":"Hormicedo",
    "gn:population":0,
    "gn:timezone":"Europe/Madrid",
    "iso:country":"ES",
    "wof:name":"Hormicedo",
    "wof:placetype":"locality"
},
  "geometry": {"coordinates":[-3.9893,42.5909],"type":"Point"}
}