{
  "type": "Feature",
  "properties": {
    "gn:admin1_code":"58",
    "gn:admin2_code":"C",
    "gn:admin3_code":"15053",
    "gn:asciiname":"San Julian",
    "gn:country_code":"ES",
    "gn:dem":114,
    "gn:feature_class":"P",
    "gn:feature_code":"PPL",
    "gn:name":"San Juli\u00e1n",
    "gn:population":0,
    "gn:timezone":"Europe/Madrid",
    "iso:country":"ES",
    "wof:name":"San Julian",
    "wof:placetype":"locality"
},
  "geometry": {"coordinates":[-9.02761,42.8278],"type":"Point"}
}