{
  "type": "Feature",
  "properties": {
    "gn:admin1_code":"29",
    "gn:admin2_code":"M",
    "gn:admin3_code":"28087",
    "gn:asciiname":"Apeadero de Los Molinos-Guadarrama",
    "gn:cc2":"ES",
    "gn:country_code":"ES",
    "gn:dem":1049,
    "gn:feature_class":"P",
    "gn:feature_code":"PPL",
    "gn:name":"Apeadero de Los Molinos-Guadarrama",
    "gn:population":0,
    "gn:timezone":"Europe/Madrid",
    "iso:country":"ES",
    "name:und_x_variant":[
        "Colonia Apeadero"
    ],
    "wof:name":"Apeadero de Los Molinos-Guadarrama",
    "wof:placetype":"locality"
},
  "geometry": {"coordinates":[-4.07301,40.71526],"type":"Point"}
}