{
  "type": "Feature",
  "properties": {
    "gn:admin1_code":"51",
    "gn:admin2_code":"GR",
    "gn:admin3_code":"18135",
    "gn:asciiname":"Venta Valero",
    "gn:country_code":"ES",
    "gn:dem":971,
    "gn:feature_class":"P",
    "gn:feature_code":"PPL",
    "gn:name":"Venta Valero",
    "gn:population":0,
    "gn:timezone":"Europe/Madrid",
    "iso:country":"ES",
    "name:und_x_variant":[
        "Caser\u00edo Venta de Valero",
        "Venta de Varelo",
        "Venta Valero"
    ],
    "wof:name":"Venta Valero",
    "wof:placetype":"locality"
},
  "geometry": {"coordinates":[-4.01089,37.40711],"type":"Point"}
}