{
  "type": "Feature",
  "properties": {
    "gn:admin1_code":"56",
    "gn:admin2_code":"L",
    "gn:admin3_code":"25081",
    "gn:asciiname":"L' Espluga Calba",
    "gn:country_code":"ES",
    "gn:dem":433,
    "gn:feature_class":"P",
    "gn:feature_code":"PPL",
    "gn:name":"L' Espluga Calba",
    "gn:population":0,
    "gn:timezone":"Europe/Madrid",
    "iso:country":"ES",
    "name:arg_x_preferred":[
        "L'Espluga Calba"
    ],
    "name:cat_x_preferred":[
        "l' Espluga Calba"
    ],
    "name:cat_x_variant":[
        "L'Espluga Calba"
    ],
    "name:ceb_x_preferred":[
        "L'Espluga Calba"
    ],
    "name:deu_x_preferred":[
        "L\u2019Espluga Calba"
    ],
    "name:eus_x_preferred":[
        "L'Espluga Calba"
    ],
    "name:fra_x_preferred":[
        "L'Espluga Calba"
    ],
    "name:hun_x_preferred":[
        "L\u2019Espluga Calba"
    ],
    "name:hye_x_preferred":[
        "\u0537\u057d\u057a\u056c\u0578\u0582\u0563\u0561 \u053f\u0561\u056c\u057e\u0561"
    ],
    "name:ita_x_preferred":[
        "L'Espluga Calba"
    ],
    "name:msa_x_preferred":[
        "L'Espluga Calba"
    ],
    "name:oci_x_preferred":[
        "L'Espluga Calba"
    ],
    "name:pol_x_preferred":[
        "L\u2019Espluga Calba"
    ],
    "name:por_x_preferred":[
        "L'Espluga Calba"
    ],
    "name:ron_x_preferred":[
        "Espluga Calba"
    ],
    "name:rus_x_preferred":[
        "\u042d\u0441\u043f\u043b\u0443\u0433\u0430-\u041a\u0430\u043b\u044c\u0432\u0430"
    ],
    "name:spa_x_preferred":[
        "Espluga Calva"
    ],
    "name:sqi_x_preferred":[
        "L'Espluga Calba"
    ],
    "name:swe_x_preferred":[
        "L'Espluga Calba"
    ],
    "name:und_x_variant":[
        "Espluga Calva"
    ],
    "name:uzb_x_preferred":[
        "Espluga Calva"
    ],
    "name:vie_x_preferred":[
        "L'Espluga Calba"
    ],
    "name:war_x_preferred":[
        "L'Espluga Calba"
    ],
    "name:zho_x_preferred":[
        "\u83b1\u65af\u666e\u5362\u52a0\u5361\u5c14\u74e6"
    ],
    "wof:name":"L' Espluga Calba",
    "wof:placetype":"locality"
},
  "geometry": {"coordinates":[1.00489,41.49628],"type":"Point"}
}