{
  "type": "Feature",
  "properties": {
    "gn:admin1_code":"56",
    "gn:admin2_code":"L",
    "gn:admin3_code":"25081",
    "gn:asciiname":"L' Espluga Calba",
    "gn:country_code":"ES",
    "gn:dem":433,
    "gn:feature_class":"P",
    "gn:feature_code":"PPL",
    "gn:name":"L' Espluga Calba",
    "gn:population":0,
    "gn:timezone":"Europe/Madrid",
    "iso:country":"ES",
    "name:cat_x_preferred":[
        "l' Espluga Calba"
    ],
    "name:spa_x_preferred":[
        "Espluga Calva"
    ],
    "name:und_x_variant":[
        "Espluga Calva"
    ],
    "wof:name":"L' Espluga Calba",
    "wof:placetype":"locality"
},
  "geometry": {"coordinates":[1.00489,41.49628],"type":"Point"}
}