{
  "type": "Feature",
  "properties": {
    "gn:population":924,
    "iso:country":"ES",
    "name:ara_x_preferred":[
        "\u0646\u064a\u063a\u0648\u064a\u0644\u0627\u0633"
    ],
    "name:ast_x_preferred":[
        "Nig\u00fcelas"
    ],
    "name:cat_x_preferred":[
        "Nig\u00fcelas"
    ],
    "name:ceb_x_preferred":[
        "Nig\u00fcelas"
    ],
    "name:deu_x_preferred":[
        "Nig\u00fcelas"
    ],
    "name:diq_x_preferred":[
        "Nig\u00fcelas"
    ],
    "name:eng_x_preferred":[
        "Nig\u00fcelas"
    ],
    "name:epo_x_preferred":[
        "Nig\u00fcelas"
    ],
    "name:eus_x_preferred":[
        "Nig\u00fcelas"
    ],
    "name:fra_x_preferred":[
        "Nig\u00fcelas"
    ],
    "name:hat_x_preferred":[
        "Nig\u00fcelas"
    ],
    "name:hun_x_preferred":[
        "Nig\u00fcelas"
    ],
    "name:hye_x_preferred":[
        "\u0546\u056b\u0563\u0578\u0582\u0565\u056c\u0561\u057d"
    ],
    "name:ita_x_preferred":[
        "Nig\u00fcelas"
    ],
    "name:kaz_x_preferred":[
        "\u041d\u0438\u0433\u0443\u044d\u043b\u0430\u0441"
    ],
    "name:msa_x_preferred":[
        "Nig\u00fcelas"
    ],
    "name:nan_x_preferred":[
        "Nig\u00fcelas"
    ],
    "name:nld_x_preferred":[
        "Nig\u00fcelas"
    ],
    "name:oci_x_preferred":[
        "Nig\u00fcelas"
    ],
    "name:pol_x_preferred":[
        "Nig\u00fcelas"
    ],
    "name:por_x_preferred":[
        "Nig\u00fcelas"
    ],
    "name:rus_x_preferred":[
        "\u041d\u0438\u0433\u0443\u044d\u043b\u0430\u0441"
    ],
    "name:spa_x_colloquial":[
        "Nigueelas",
        "Niguelas"
    ],
    "name:spa_x_preferred":[
        "Nig\u00fcelas"
    ],
    "name:swe_x_preferred":[
        "Nig\u00fcelas"
    ],
    "name:tur_x_preferred":[
        "Nig\u00fcelas"
    ],
    "name:ukr_x_preferred":[
        "\u041d\u0456\u0433\u0443\u0435\u043b\u0430\u0441"
    ],
    "name:uzb_x_preferred":[
        "Nig\u00fcelas"
    ],
    "name:vie_x_preferred":[
        "Nig\u00fcelas"
    ],
    "name:war_x_preferred":[
        "Nig\u00fcelas"
    ],
    "name:zho_x_preferred":[
        "\u5c3c\u683c\u62c9\u65af"
    ],
    "qs:a0":"Espa\u00f1a",
    "qs:a1":"*Granada",
    "qs:a1r":"0Andaluc\u00eda",
    "qs:adm0":"Espa\u00f1a",
    "qs:la_lc":"*",
    "qs:level":"locality",
    "qs:loc":"Nig\u00fcelas",
    "qs:loc_alt":"Niguelas",
    "qs:pop":0,
    "qs:type":"buffered point",
    "wd:wordcount":77,
    "wof:lang":[
        "spa"
    ],
    "wof:name":"Nig\u00fcelas",
    "wof:placetype":"locality",
    "wof:population":924
},
  "geometry": {"coordinates":[-3.538769,36.977993],"type":"Point"}
}