{
  "type": "Feature",
  "properties": {
    "gn:admin1_code":"55",
    "gn:admin2_code":"BU",
    "gn:admin3_code":"09209",
    "gn:asciiname":"Villanueva la Lastra",
    "gn:country_code":"ES",
    "gn:dem":587,
    "gn:feature_class":"P",
    "gn:feature_code":"PPL",
    "gn:name":"Villanueva la Lastra",
    "gn:population":0,
    "gn:timezone":"Europe/Madrid",
    "iso:country":"ES",
    "wof:name":"Villanueva la Lastra",
    "wof:placetype":"locality"
},
  "geometry": {"coordinates":[-3.50842,42.93582],"type":"Point"}
}