{
  "type": "Feature",
  "properties": {
    "gn:country":"ES",
    "gn:fcode":"PPLA3",
    "gn:population":1976,
    "iso:country":"ES",
    "name:arg_x_preferred":[
        "Chozas de Abajo"
    ],
    "name:cat_x_preferred":[
        "Chozas de Abajo"
    ],
    "name:deu_x_preferred":[
        "Chozas de Abajo"
    ],
    "name:eng_x_preferred":[
        "Chozas de Abajo"
    ],
    "name:eus_x_preferred":[
        "Chozas de Abajo"
    ],
    "name:fra_x_preferred":[
        "Chozas de Abajo"
    ],
    "name:glg_x_preferred":[
        "Chozas de Abajo"
    ],
    "name:haw_x_preferred":[
        "Chozas de Abajo"
    ],
    "name:hun_x_preferred":[
        "Chozas de Abajo"
    ],
    "name:ido_x_preferred":[
        "Chozas de Abajo"
    ],
    "name:ina_x_preferred":[
        "Chozas de Abajo"
    ],
    "name:ita_x_preferred":[
        "Chozas de Abajo"
    ],
    "name:lit_x_preferred":[
        "\u010cosas de Abachas"
    ],
    "name:msa_x_preferred":[
        "Chozas de Abajo"
    ],
    "name:nan_x_preferred":[
        "Chozas de Abajo"
    ],
    "name:nld_x_preferred":[
        "Chozas de Abajo"
    ],
    "name:oci_x_preferred":[
        "Chozas de Abajo"
    ],
    "name:pol_x_preferred":[
        "Chozas de Abajo"
    ],
    "name:por_x_preferred":[
        "Chozas de Abajo"
    ],
    "name:rup_x_preferred":[
        "Chozas de Abajo"
    ],
    "name:rus_x_preferred":[
        "\u0427\u043e\u0441\u0430\u0441-\u0434\u0435-\u0410\u0431\u0430\u0445\u043e"
    ],
    "name:spa_x_preferred":[
        "Chozas de Abajo"
    ],
    "name:swe_x_preferred":[
        "Chozas de Abajo"
    ],
    "name:tpi_x_preferred":[
        "Chozas de Abajo"
    ],
    "name:ukr_x_preferred":[
        "\u0427\u043e\u0441\u0430\u0441-\u0434\u0435-\u0410\u0431\u0430\u0445\u043e"
    ],
    "name:vie_x_preferred":[
        "Chozas de Abajo"
    ],
    "name:war_x_preferred":[
        "Chozas de Abajo"
    ],
    "name:zho_x_preferred":[
        "\u4e54\u8428\u65af\u5fb7\u4e9a\u74e6\u970d"
    ],
    "qs_pg:aaroncc":"ES",
    "qs_pg:gn_country":"ES",
    "qs_pg:gn_fcode":"PPLA3",
    "qs_pg:gn_pop":1976,
    "qs_pg:name":"Chozas de Abajo",
    "qs_pg:name_adm0":"Espa\u00f1a",
    "qs_pg:name_adm1":"Castilla y Le\u00f3n",
    "qs_pg:photos":228,
    "qs_pg:photos_1k":46,
    "qs_pg:photos_9k":1,
    "qs_pg:photos_9r":4,
    "qs_pg:photos_all":228,
    "qs_pg:photos_sr":4,
    "qs_pg:pop_sr":3,
    "qs_pg:qs_pg_placetype":"locality",
    "qs_pg:qs_pg_placetype_gp":"Town",
    "qs_pg:woe_adm0":23424950,
    "woe:adm0_id":23424950,
    "woe:name_adm0":"Espa\u00f1a",
    "woe:name_adm1":"Castilla y Le\u00f3n",
    "woe:placetype":"Town",
    "wof:name":"Chozas de Abajo",
    "wof:placetype":"locality",
    "wof:population":1976
},
  "geometry": {"coordinates":[-5.68656,42.50657],"type":"Point"}
}