{
  "type": "Feature",
  "properties": {
    "gn:admin1_code":"56",
    "gn:admin2_code":"L",
    "gn:admin3_code":"25043",
    "gn:asciiname":"Candet",
    "gn:country_code":"ES",
    "gn:dem":1164,
    "gn:feature_class":"P",
    "gn:feature_code":"PPL",
    "gn:name":"Candet",
    "gn:population":0,
    "gn:timezone":"Europe/Madrid",
    "iso:country":"ES",
    "wof:name":"Candet",
    "wof:placetype":"locality"
},
  "geometry": {"coordinates":[0.78466,42.49761],"type":"Point"}
}