{
  "type": "Feature",
  "properties": {
    "gn:gn_country":"ES",
    "gn:gn_fcode":"ADM3",
    "gn:gn_pop":4339,
    "gn:population":3924,
    "iso:country":"ES",
    "name:ara_x_preferred":[
        "\u062a\u0648\u0631\u062f\u0648\u064a\u0627"
    ],
    "name:baq_x_preferred":[
        "Tordoia"
    ],
    "name:bre_x_preferred":[
        "Tordoia"
    ],
    "name:bul_x_preferred":[
        "\u0422\u043e\u0440\u0434\u043e\u0438\u0430"
    ],
    "name:cat_x_preferred":[
        "Tordoia"
    ],
    "name:chi_x_preferred":[
        "\u6258\u5c14\u591a\u4e9a"
    ],
    "name:dut_x_preferred":[
        "Tordoia"
    ],
    "name:eng_x_preferred":[
        "Tordoia"
    ],
    "name:fre_x_preferred":[
        "Tordoia"
    ],
    "name:ger_x_preferred":[
        "Tordoia"
    ],
    "name:glg_x_preferred":[
        "Tordoia"
    ],
    "name:hun_x_preferred":[
        "Tordoia"
    ],
    "name:ita_x_preferred":[
        "Tordoia"
    ],
    "name:jpn_x_preferred":[
        "\u30c8\u30eb\u30c9\u30a4\u30a2"
    ],
    "name:lit_x_preferred":[
        "Tordoja"
    ],
    "name:lmo_x_preferred":[
        "Tordoia"
    ],
    "name:mac_x_preferred":[
        "\u0422\u043e\u0440\u0434\u043e\u0438\u0458\u0430"
    ],
    "name:may_x_preferred":[
        "Tordoia"
    ],
    "name:nan_x_preferred":[
        "Tordoia"
    ],
    "name:oci_x_preferred":[
        "Tordoia"
    ],
    "name:pol_x_preferred":[
        "Tordoia"
    ],
    "name:por_x_preferred":[
        "Tordoia"
    ],
    "name:rus_x_preferred":[
        "\u0422\u043e\u0440\u0434\u043e\u0439\u044f"
    ],
    "name:spa_x_preferred":[
        "Tordoia"
    ],
    "name:swe_x_preferred":[
        "Tordoia"
    ],
    "name:tur_x_preferred":[
        "Tordoia"
    ],
    "name:ukr_x_preferred":[
        "\u0422\u043e\u0440\u0434\u043e\u0439\u044f"
    ],
    "name:uzb_x_preferred":[
        "Tordoia"
    ],
    "name:vie_x_preferred":[
        "Tordoia"
    ],
    "name:war_x_preferred":[
        "Tordoia"
    ],
    "qs_pg:aaroncc":"ES",
    "qs_pg:gn_country":"ES",
    "qs_pg:gn_fcode":"ADM3",
    "qs_pg:gn_pop":4339,
    "qs_pg:name":"Tordoia",
    "qs_pg:name_adm0":"Espa\u00f1a",
    "qs_pg:name_adm1":"Galicia",
    "qs_pg:photos":54,
    "qs_pg:photos_1k":11,
    "qs_pg:photos_9k":1,
    "qs_pg:photos_9r":2,
    "qs_pg:photos_all":54,
    "qs_pg:photos_sr":2,
    "qs_pg:pop_sr":4,
    "qs_pg:qs_pg_placetype":"locality",
    "qs_pg:qs_pg_placetype_gp":"Town",
    "qs_pg:woe_adm0":23424950,
    "woe:adm0_id":23424950,
    "woe:name_adm0":"Espa\u00f1a",
    "woe:name_adm1":"Galicia",
    "woe:placetype":"Town",
    "wof:name":"Tordoia",
    "wof:placetype":"locality",
    "wof:population":3924
},
  "geometry": {"coordinates":[-8.54182,43.08618],"type":"Point"}
}