{
  "type": "Feature",
  "properties": {
    "gn:country":"ES",
    "gn:fcode":"PPLA3",
    "gn:population":44,
    "iso:country":"ES",
    "name:ara_x_preferred":[
        "\u0641\u0627\u0644\u0647\u064a\u0631\u0645\u0648\u0633\u0648 \u062f\u064a \u0644\u0627 \u0641\u0648\u064a\u0646\u062a\u064a"
    ],
    "name:arg_x_preferred":[
        "Valhermoso de la Fuente"
    ],
    "name:arz_x_preferred":[
        "\u0641\u0627\u0644\u0647\u064a\u0631\u0645\u0648\u0633\u0648 \u062f\u0649 \u0644\u0627 \u0641\u0648\u064a\u0646\u062a\u0649"
    ],
    "name:cat_x_preferred":[
        "Valhermoso de la Fuente"
    ],
    "name:eng_x_preferred":[
        "Valhermoso de la Fuente"
    ],
    "name:eus_x_preferred":[
        "Valhermoso de la Fuente"
    ],
    "name:fra_x_preferred":[
        "Valhermoso de la Fuente"
    ],
    "name:hun_x_preferred":[
        "Valhermoso de la Fuente"
    ],
    "name:ita_x_preferred":[
        "Valhermoso de la Fuente"
    ],
    "name:kaz_x_preferred":[
        "\u0412\u0430\u043b\u044c\u0445\u0435\u0440\u043c\u043e\u0441\u043e-\u0434\u0435-\u043b\u0430-\u0424\u0443\u044d\u043d\u0442\u0435"
    ],
    "name:msa_x_preferred":[
        "Valhermoso de la Fuente"
    ],
    "name:nan_x_preferred":[
        "Valhermoso de la Fuente"
    ],
    "name:nld_x_preferred":[
        "Valhermoso de la Fuente"
    ],
    "name:oci_x_preferred":[
        "Valhermoso de la Fuente"
    ],
    "name:pol_x_preferred":[
        "Valhermoso de la Fuente"
    ],
    "name:por_x_preferred":[
        "Valhermoso de la Fuente"
    ],
    "name:rus_x_preferred":[
        "\u0412\u0430\u043b\u044c\u0445\u0435\u0440\u043c\u043e\u0441\u043e-\u0434\u0435-\u043b\u0430-\u0424\u0443\u044d\u043d\u0442\u0435"
    ],
    "name:spa_x_preferred":[
        "Valhermoso de la Fuente"
    ],
    "name:swe_x_preferred":[
        "Valhermoso de la Fuente"
    ],
    "name:ukr_x_preferred":[
        "\u0412\u0430\u043b\u0435\u0440\u043c\u043e\u0441\u043e-\u0434\u0435-\u043b\u0430-\u0424\u0443\u0435\u043d\u0442\u0435"
    ],
    "name:und_x_variant":[
        "Valhermoso"
    ],
    "name:vie_x_preferred":[
        "Valhermoso de la Fuente"
    ],
    "name:war_x_preferred":[
        "Valhermoso de la Fuente"
    ],
    "name:zho_x_preferred":[
        "\u5df4\u5c14\u57c3\u5c14\u83ab\u7d22\u5fb7\u62c9\u4e30\u7279"
    ],
    "qs_pg:aaroncc":"ES",
    "qs_pg:gn_country":"ES",
    "qs_pg:gn_fcode":"PPLA3",
    "qs_pg:gn_pop":44,
    "qs_pg:name":"Valhermoso de la Fuente",
    "qs_pg:name_adm0":"Espa\u00f1a",
    "qs_pg:name_adm1":"Castilla-La Mancha",
    "qs_pg:photos_9k":1,
    "qs_pg:photos_9r":1,
    "qs_pg:photos_all":2,
    "qs_pg:photos_sr":0,
    "qs_pg:pop_sr":1,
    "qs_pg:qs_pg_placetype":"locality",
    "qs_pg:qs_pg_placetype_gp":"Town",
    "qs_pg:woe_adm0":23424950,
    "woe:adm0_id":23424950,
    "woe:name_adm0":"Espa\u00f1a",
    "woe:name_adm1":"Castilla-La Mancha",
    "woe:placetype":"Town",
    "wof:name":"Valhermoso de la Fuente",
    "wof:placetype":"locality",
    "wof:population":44
},
  "geometry": {"coordinates":[-2.01667,39.56667],"type":"Point"}
}