{
  "type": "Feature",
  "properties": {
    "gn:admin1_code":"52",
    "gn:admin2_code":"HU",
    "gn:admin3_code":"22125",
    "gn:asciiname":"Bunales",
    "gn:country_code":"ES",
    "gn:dem":390,
    "gn:feature_class":"P",
    "gn:feature_code":"PPL",
    "gn:name":"Bu\u00f1ales",
    "gn:population":0,
    "gn:timezone":"Europe/Madrid",
    "iso:country":"ES",
    "name:und_x_variant":[
        "Bu\u00f1ales"
    ],
    "wof:name":"Bunales",
    "wof:placetype":"locality"
},
  "geometry": {"coordinates":[-0.40682,42.04654],"type":"Point"}
}