{
  "type": "Feature",
  "properties": {
    "gn:admin1_code":"56",
    "gn:admin2_code":"L",
    "gn:admin3_code":"25227.0",
    "gn:asciiname":"La Plana de Mont-Ros",
    "gn:country_code":"ES",
    "gn:dem":895,
    "gn:feature_class":"P",
    "gn:feature_code":"PPL",
    "gn:name":"La Plana de Mont-Ros",
    "gn:population":0,
    "gn:timezone":"Europe/Madrid",
    "iso:country":"ES",
    "wof:name":"La Plana de Mont-Ros",
    "wof:placetype":"locality"
},
  "geometry": {"coordinates":[0.96508,42.38201],"type":"Point"}
}