{
  "type": "Feature",
  "properties": {
    "gn:admin1_code":"58",
    "gn:admin2_code":"C",
    "gn:admin3_code":"15071",
    "gn:asciiname":"Tarrio",
    "gn:country_code":"ES",
    "gn:dem":120,
    "gn:feature_class":"P",
    "gn:feature_code":"PPL",
    "gn:name":"Tarr\u00edo",
    "gn:population":0,
    "gn:timezone":"Europe/Madrid",
    "iso:country":"ES",
    "wof:name":"Tarrio",
    "wof:placetype":"locality"
},
  "geometry": {"coordinates":[-9.01081,42.69585],"type":"Point"}
}