{
  "type": "Feature",
  "properties": {
    "gn:admin1_code":"31",
    "gn:admin2_code":"MU",
    "gn:admin3_code":"30037",
    "gn:asciiname":"La Atalaya",
    "gn:country_code":"ES",
    "gn:dem":98,
    "gn:feature_class":"P",
    "gn:feature_code":"PPL",
    "gn:name":"La Atalaya",
    "gn:population":0,
    "gn:timezone":"Europe/Madrid",
    "iso:country":"ES",
    "name:und_x_variant":[
        "Caser\u00edo La Atalaya",
        "La Atalaya"
    ],
    "wof:name":"La Atalaya",
    "wof:placetype":"locality"
},
  "geometry": {"coordinates":[-1.06089,37.75442],"type":"Point"}
}