{
  "type": "Feature",
  "properties": {
    "gn:gn_country":"ES",
    "iso:country":"ES",
    "qs_pg:aaroncc":"ES",
    "qs_pg:gn_country":"ES",
    "qs_pg:name":"Charco de Rivero",
    "qs_pg:name_adm0":"Espa\u00f1a",
    "qs_pg:name_adm1":"Islas Canarias",
    "qs_pg:photos":51,
    "qs_pg:photos_1k":10,
    "qs_pg:photos_9k":1,
    "qs_pg:photos_9r":2,
    "qs_pg:photos_all":51,
    "qs_pg:photos_sr":2,
    "qs_pg:pop_sr":0,
    "qs_pg:qs_pg_placetype":"locality",
    "qs_pg:qs_pg_placetype_gp":"Town",
    "qs_pg:woe_adm0":23424950,
    "woe:adm0_id":23424950,
    "woe:name_adm0":"Espa\u00f1a",
    "woe:name_adm1":"Islas Canarias",
    "woe:placetype":"Town",
    "wof:name":"Charco de Rivero",
    "wof:placetype":"locality"
},
  "geometry": {"coordinates":[-16.396794,28.537688],"type":"Point"}
}