{
  "type": "Feature",
  "properties": {
    "gn:admin1_code":"55",
    "gn:admin2_code":"LE",
    "gn:admin3_code":"24144",
    "gn:asciiname":"Matilla de la Vega",
    "gn:country_code":"ES",
    "gn:dem":793,
    "gn:feature_class":"P",
    "gn:feature_code":"PPL",
    "gn:name":"Matilla de la Vega",
    "gn:population":0,
    "gn:timezone":"Europe/Madrid",
    "iso:country":"ES",
    "name:und_x_variant":[
        "Matilla",
        "Matilla de la Vega"
    ],
    "wof:name":"Matilla de la Vega",
    "wof:placetype":"locality"
},
  "geometry": {"coordinates":[-5.90276,42.37449],"type":"Point"}
}