{
  "type": "Feature",
  "properties": {
    "gn:admin1_code":"58",
    "gn:admin2_code":"PO",
    "gn:admin3_code":"36035",
    "gn:asciiname":"Panxon",
    "gn:country_code":"ES",
    "gn:dem":28,
    "gn:feature_class":"P",
    "gn:feature_code":"PPL",
    "gn:name":"Panx\u00f3n",
    "gn:population":0,
    "gn:timezone":"Europe/Madrid",
    "iso:country":"ES",
    "wof:name":"Panxon",
    "wof:placetype":"locality"
},
  "geometry": {"coordinates":[-8.83333,42.15],"type":"Point"}
}