{
  "type": "Feature",
  "properties": {
    "gn:gn_country":"ES",
    "gn:gn_fcode":"PPLA3",
    "gn:gn_pop":386,
    "gn:population":386,
    "iso:country":"ES",
    "name:ara_x_preferred":[
        "\u0625\u0633\u062a\u064a\u064a\u0646\u0634\u0633"
    ],
    "name:arg_x_preferred":[
        "Estellencs"
    ],
    "name:ast_x_preferred":[
        "Estellenchs"
    ],
    "name:cat_x_preferred":[
        "Estellencs"
    ],
    "name:ceb_x_preferred":[
        "Estellencs"
    ],
    "name:deu_x_preferred":[
        "Estellencs"
    ],
    "name:eng_x_preferred":[
        "Estellencs"
    ],
    "name:eus_x_preferred":[
        "Estellencs"
    ],
    "name:fas_x_preferred":[
        "\u0627\u0633\u062a\u06cc\u0646\u06a9\u0633"
    ],
    "name:fra_x_preferred":[
        "Estellencs"
    ],
    "name:glg_x_preferred":[
        "Estellencs"
    ],
    "name:hun_x_preferred":[
        "Estellencs"
    ],
    "name:ita_x_preferred":[
        "Estellencs"
    ],
    "name:jpn_x_preferred":[
        "\u30a8\u30b9\u30c6\u30ea\u30a7\u30f3\u30af\u30b9"
    ],
    "name:msa_x_preferred":[
        "Estellencs"
    ],
    "name:nld_x_preferred":[
        "Estellencs"
    ],
    "name:oci_x_preferred":[
        "Estellencs"
    ],
    "name:pam_x_preferred":[
        "Estellencs"
    ],
    "name:pol_x_preferred":[
        "Estellencs"
    ],
    "name:por_x_preferred":[
        "Estellencs"
    ],
    "name:ron_x_preferred":[
        "Estellencs"
    ],
    "name:spa_x_preferred":[
        "Estellencs"
    ],
    "name:spa_x_variant":[
        "Estellenchs"
    ],
    "name:sqi_x_preferred":[
        "Estellencs"
    ],
    "name:srd_x_preferred":[
        "Estellencs"
    ],
    "name:swe_x_preferred":[
        "Estellencs"
    ],
    "name:tur_x_preferred":[
        "Estellencs"
    ],
    "name:vie_x_preferred":[
        "Estellencs"
    ],
    "name:war_x_preferred":[
        "Estellencs"
    ],
    "name:zho_x_preferred":[
        "\u57c3\u65af\u7279\u8fde\u514b\u65af"
    ],
    "qs_pg:aaroncc":"ES",
    "qs_pg:gn_country":"ES",
    "qs_pg:gn_fcode":"PPLA3",
    "qs_pg:gn_pop":386,
    "qs_pg:name":"Estellencs",
    "qs_pg:photos_9r":0,
    "qs_pg:photos_sr":0,
    "qs_pg:pop_sr":2,
    "qs_pg:qs_pg_placetype":"locality",
    "wof:name":"Estellencs",
    "wof:placetype":"locality",
    "wof:population":386
},
  "geometry": {"coordinates":[2.4813,39.65338],"type":"Point"}
}