{
  "type": "Feature",
  "properties": {
    "gn:admin1_code":"56",
    "gn:admin2_code":"B",
    "gn:admin3_code":"08213",
    "gn:asciiname":"El Guix",
    "gn:country_code":"ES",
    "gn:dem":282,
    "gn:feature_class":"P",
    "gn:feature_code":"PPL",
    "gn:name":"El Guix",
    "gn:population":0,
    "gn:timezone":"Europe/Madrid",
    "iso:country":"ES",
    "wof:name":"El Guix",
    "wof:placetype":"locality"
},
  "geometry": {"coordinates":[1.85082,41.74011],"type":"Point"}
}