{
  "type": "Feature",
  "properties": {
    "gn:gn_country":"ES",
    "gn:gn_fcode":"PPLA3",
    "gn:gn_pop":422,
    "gn:population":422,
    "iso:country":"ES",
    "name:cat_x_preferred":[
        "Espirdo"
    ],
    "name:deu_x_preferred":[
        "Espirdo"
    ],
    "name:eng_x_preferred":[
        "Espirdo"
    ],
    "name:eus_x_preferred":[
        "Espirdo"
    ],
    "name:fra_x_preferred":[
        "Espirdo"
    ],
    "name:hun_x_preferred":[
        "Espirdo"
    ],
    "name:ina_x_preferred":[
        "Espirdo"
    ],
    "name:ita_x_preferred":[
        "Espirdo"
    ],
    "name:msa_x_preferred":[
        "Espirdo"
    ],
    "name:nan_x_preferred":[
        "Espirdo"
    ],
    "name:nld_x_preferred":[
        "Espirdo"
    ],
    "name:oci_x_preferred":[
        "Espirdo"
    ],
    "name:pol_x_preferred":[
        "Espirdo"
    ],
    "name:por_x_preferred":[
        "Espirdo"
    ],
    "name:rus_x_preferred":[
        "\u042d\u0441\u043f\u0438\u0440\u0434\u043e"
    ],
    "name:spa_x_preferred":[
        "Espirdo"
    ],
    "name:swe_x_preferred":[
        "Espirdo"
    ],
    "name:ukr_x_preferred":[
        "\u0415\u0441\u043f\u0456\u0440\u0434\u043e"
    ],
    "name:unk_x_variant":[
        "Espira Otero"
    ],
    "name:vie_x_preferred":[
        "Espirdo"
    ],
    "name:war_x_preferred":[
        "Espirdo"
    ],
    "name:zho_x_preferred":[
        "\u57c3\u65af\u76ae\u5c14\u591a"
    ],
    "qs_pg:aaroncc":"ES",
    "qs_pg:gn_country":"ES",
    "qs_pg:gn_fcode":"PPLA3",
    "qs_pg:gn_pop":422,
    "qs_pg:name":"Espirdo",
    "qs_pg:name_adm0":"Espa\u00f1a",
    "qs_pg:name_adm1":"Castilla y Le\u00f3n",
    "qs_pg:photos_9k":1,
    "qs_pg:photos_9r":1,
    "qs_pg:photos_all":1,
    "qs_pg:photos_sr":0,
    "qs_pg:pop_sr":2,
    "qs_pg:qs_pg_placetype":"locality",
    "qs_pg:qs_pg_placetype_gp":"Town",
    "qs_pg:woe_adm0":23424950,
    "woe:adm0_id":23424950,
    "woe:name_adm0":"Espa\u00f1a",
    "woe:name_adm1":"Castilla y Le\u00f3n",
    "woe:placetype":"Town",
    "wof:name":"Espirdo",
    "wof:placetype":"locality",
    "wof:population":422
},
  "geometry": {"coordinates":[-4.07331,40.99764],"type":"Point"}
}