{
  "type": "Feature",
  "properties": {
    "gn:country":"ES",
    "gn:fcode":"PPL",
    "gn:population":91,
    "iso:country":"ES",
    "name:ara_x_preferred":[
        "\u062a\u0648\u0631\u064a\u0628\u0627\u062f\u0631\u064a"
    ],
    "name:arg_x_preferred":[
        "Torrepadre"
    ],
    "name:ast_x_preferred":[
        "Torrepadre"
    ],
    "name:azb_x_preferred":[
        "\u062a\u0631\u067e\u0627\u062f\u0631\u0647"
    ],
    "name:bul_x_preferred":[
        "\u0422\u043e\u0440\u0435\u043f\u0430\u0434\u0440\u0435"
    ],
    "name:cat_x_preferred":[
        "Torrepadre"
    ],
    "name:ceb_x_preferred":[
        "Torrepadre"
    ],
    "name:eng_x_preferred":[
        "Torrepadre"
    ],
    "name:epo_x_preferred":[
        "Torrepadre"
    ],
    "name:eus_x_preferred":[
        "Torrepadre"
    ],
    "name:fas_x_preferred":[
        "\u062a\u0631\u067e\u0627\u062f\u0631\u0647"
    ],
    "name:fra_x_preferred":[
        "Torrepadre"
    ],
    "name:glg_x_preferred":[
        "Torrepadre"
    ],
    "name:haw_x_preferred":[
        "Torrepadre"
    ],
    "name:hun_x_preferred":[
        "Torrepadre"
    ],
    "name:ina_x_preferred":[
        "Torrepadre"
    ],
    "name:ita_x_preferred":[
        "Torrepadre"
    ],
    "name:msa_x_preferred":[
        "Torrepadre"
    ],
    "name:nan_x_preferred":[
        "Torrepadre"
    ],
    "name:nld_x_preferred":[
        "Torrepadre"
    ],
    "name:oci_x_preferred":[
        "Torrepadre"
    ],
    "name:pol_x_preferred":[
        "Torrepadre"
    ],
    "name:por_x_preferred":[
        "Torrepadre"
    ],
    "name:rus_x_preferred":[
        "\u0422\u043e\u0440\u0440\u0435\u043f\u0430\u0434\u0440\u0435"
    ],
    "name:spa_x_preferred":[
        "Torrepadre"
    ],
    "name:swe_x_preferred":[
        "Torrepadre"
    ],
    "name:ukr_x_preferred":[
        "\u0422\u043e\u0440\u0440\u0435\u043f\u0430\u0434\u0440\u0435"
    ],
    "name:vie_x_preferred":[
        "Torrepadre"
    ],
    "name:war_x_preferred":[
        "Torrepadre"
    ],
    "name:zho_x_preferred":[
        "\u6258\u96f7\u5e15\u5fb7\u96f7"
    ],
    "qs_pg:aaroncc":"ES",
    "qs_pg:gn_country":"ES",
    "qs_pg:gn_fcode":"PPL",
    "qs_pg:gn_pop":91,
    "qs_pg:name":"Torrepadre",
    "qs_pg:name_adm0":"Espa\u00f1a",
    "qs_pg:name_adm1":"Castilla y Le\u00f3n",
    "qs_pg:photos_9r":0,
    "qs_pg:photos_sr":0,
    "qs_pg:pop_sr":1,
    "qs_pg:qs_pg_placetype":"locality",
    "qs_pg:qs_pg_placetype_gp":"Town",
    "qs_pg:woe_adm0":23424950,
    "woe:adm0_id":23424950,
    "woe:name_adm0":"Espa\u00f1a",
    "woe:name_adm1":"Castilla y Le\u00f3n",
    "woe:placetype":"Town",
    "wof:name":"Torrepadre",
    "wof:placetype":"locality",
    "wof:population":91
},
  "geometry": {"coordinates":[-3.93701,42.04388],"type":"Point"}
}