{
  "type": "Feature",
  "properties": {
    "gn:admin1_code":"34",
    "gn:admin2_code":"O",
    "gn:admin3_code":"33031",
    "gn:asciiname":"La Felguera",
    "gn:country_code":"ES",
    "gn:dem":234,
    "gn:feature_class":"P",
    "gn:feature_code":"PPL",
    "gn:name":"La Felguera",
    "gn:population":0,
    "gn:timezone":"Europe/Madrid",
    "iso:country":"ES",
    "name:ast_x_preferred":[
        "La Felguera"
    ],
    "name:cat_x_preferred":[
        "La Felguera"
    ],
    "name:deu_x_preferred":[
        "La Felguera"
    ],
    "name:eus_x_preferred":[
        "La Felguera"
    ],
    "name:fra_x_preferred":[
        "La Felguera"
    ],
    "name:glg_x_preferred":[
        "La Felguera"
    ],
    "name:ita_x_preferred":[
        "La Felguera"
    ],
    "name:nld_x_preferred":[
        "La Felguera"
    ],
    "name:pol_x_preferred":[
        "La Felguera"
    ],
    "name:por_x_preferred":[
        "La Felguera"
    ],
    "name:spa_x_preferred":[
        "La Felguera"
    ],
    "name:swe_x_preferred":[
        "La Felguera"
    ],
    "name:urd_x_preferred":[
        "\u0644\u0627 \u0641\u06cc\u0644\u06af\u0648\u06cc\u0631\u0627"
    ],
    "wof:name":"La Felguera",
    "wof:placetype":"locality"
},
  "geometry": {"coordinates":[-5.67895,43.43126],"type":"Point"}
}