{
  "type": "Feature",
  "properties": {
    "gn:admin1_code":"53",
    "gn:admin2_code":"TF",
    "gn:admin3_code":"38015",
    "gn:asciiname":"Las Cruces",
    "gn:country_code":"ES",
    "gn:dem":103,
    "gn:feature_class":"P",
    "gn:feature_code":"PPL",
    "gn:name":"Las Cruces",
    "gn:population":0,
    "gn:timezone":"Atlantic/Canary",
    "iso:country":"ES",
    "wof:name":"Las Cruces",
    "wof:placetype":"locality"
},
  "geometry": {"coordinates":[-16.79053,28.36754],"type":"Point"}
}