{
  "type": "Feature",
  "properties": {
    "gn:admin1_code":"55",
    "gn:admin2_code":"BU",
    "gn:admin3_code":"09109",
    "gn:asciiname":"Ocilla",
    "gn:country_code":"ES",
    "gn:dem":625,
    "gn:feature_class":"P",
    "gn:feature_code":"PPL",
    "gn:name":"Ocilla",
    "gn:population":0,
    "gn:timezone":"Europe/Madrid",
    "iso:country":"ES",
    "name:eus_x_preferred":[
        "Ozilla"
    ],
    "wof:name":"Ocilla",
    "wof:placetype":"locality"
},
  "geometry": {"coordinates":[-2.78057,42.7634],"type":"Point"}
}