{
  "type": "Feature",
  "properties": {
    "gn:admin1_code":"54",
    "gn:admin2_code":"AB",
    "gn:admin3_code":"02086",
    "gn:asciiname":"Alcantarilla",
    "gn:country_code":"ES",
    "gn:dem":810,
    "gn:feature_class":"P",
    "gn:feature_code":"PPL",
    "gn:name":"Alcantarilla",
    "gn:population":0,
    "gn:timezone":"Europe/Madrid",
    "iso:country":"ES",
    "name:ara_x_preferred":[
        "\u0623\u0644\u0643\u0627\u0646\u062a\u064a\u0631\u064a\u0627"
    ],
    "name:arg_x_preferred":[
        "Alcantariella"
    ],
    "name:azb_x_preferred":[
        "\u0622\u0644\u06a9\u0627\u0646\u062a\u0627\u0631\u06cc\u06cc\u0627"
    ],
    "name:cat_x_preferred":[
        "Alcantarilla"
    ],
    "name:ceb_x_preferred":[
        "Alcantarilla"
    ],
    "name:deu_x_preferred":[
        "Alcantarilla"
    ],
    "name:eus_x_preferred":[
        "Alcantarilla"
    ],
    "name:fas_x_preferred":[
        "\u0622\u0644\u06a9\u0627\u0646\u062a\u0627\u0631\u06cc\u06cc\u0627"
    ],
    "name:fra_x_preferred":[
        "Alcantarilla"
    ],
    "name:glg_x_preferred":[
        "Alcantarilla"
    ],
    "name:hun_x_preferred":[
        "Alcantarilla"
    ],
    "name:ita_x_preferred":[
        "Alcantarilla"
    ],
    "name:mlg_x_preferred":[
        "Alcantarilla"
    ],
    "name:msa_x_preferred":[
        "Alcantarilla"
    ],
    "name:nld_x_preferred":[
        "Alcantarilla"
    ],
    "name:oci_x_preferred":[
        "Alcantarilla"
    ],
    "name:pol_x_preferred":[
        "Alcantarilla"
    ],
    "name:por_x_preferred":[
        "Alcantarilla"
    ],
    "name:rus_x_preferred":[
        "\u0410\u043b\u044c\u043a\u0430\u043d\u0442\u0430\u0440\u0438\u043b\u044c\u044f"
    ],
    "name:spa_x_preferred":[
        "Alcantarilla"
    ],
    "name:sqi_x_preferred":[
        "Alcantarilla"
    ],
    "name:srp_x_preferred":[
        "\u0410\u043b\u043a\u0430\u043d\u0442\u0430\u0440\u0438\u0459\u0430"
    ],
    "name:swe_x_preferred":[
        "Alcantarilla"
    ],
    "name:tur_x_preferred":[
        "Alcantarilla"
    ],
    "name:ukr_x_preferred":[
        "\u0410\u043b\u044c\u043a\u0430\u043d\u0442\u0430\u0440\u0456\u043b\u044c\u044f"
    ],
    "name:vie_x_preferred":[
        "Alcantarilla"
    ],
    "name:war_x_preferred":[
        "Alcantarilla"
    ],
    "name:zho_x_preferred":[
        "\u963f\u5c14\u574e\u5854\u91cc\u5229\u4e9a"
    ],
    "wof:name":"Alcantarilla",
    "wof:placetype":"locality"
},
  "geometry": {"coordinates":[-2.44534,38.30349],"type":"Point"}
}