{
  "type": "Feature",
  "properties": {
    "gn:admin1_code":"55",
    "gn:admin2_code":"ZA",
    "gn:admin3_code":"49077",
    "gn:asciiname":"Mogatar",
    "gn:country_code":"ES",
    "gn:dem":805,
    "gn:feature_class":"P",
    "gn:feature_code":"PPL",
    "gn:name":"Mog\u00e1tar",
    "gn:population":0,
    "gn:timezone":"Europe/Madrid",
    "iso:country":"ES",
    "name:und_x_variant":[
        "Mog\u00e1tar"
    ],
    "wof:name":"Mogatar",
    "wof:placetype":"locality"
},
  "geometry": {"coordinates":[-5.92238,41.35296],"type":"Point"}
}