{
  "type": "Feature",
  "properties": {
    "gn:gn_country":"ES",
    "gn:gn_fcode":"PPLA3",
    "gn:gn_pop":183,
    "gn:population":183,
    "iso:country":"ES",
    "name:alb_x_preferred":[
        "Estubeny"
    ],
    "name:arg_x_preferred":[
        "Estubeny"
    ],
    "name:baq_x_preferred":[
        "Estubeny"
    ],
    "name:cat_x_preferred":[
        "Estubeny"
    ],
    "name:chi_x_preferred":[
        "\u57c3\u65af\u56fe\u97e6\u5c3c"
    ],
    "name:dut_x_preferred":[
        "Estubeny"
    ],
    "name:eng_x_preferred":[
        "Estubeny"
    ],
    "name:fre_x_preferred":[
        "Estubeny"
    ],
    "name:hun_x_preferred":[
        "Estubeny"
    ],
    "name:ita_x_preferred":[
        "Estubeny"
    ],
    "name:may_x_preferred":[
        "Estubeny"
    ],
    "name:nan_x_preferred":[
        "Estubeny"
    ],
    "name:oci_x_preferred":[
        "Estubeny"
    ],
    "name:per_x_preferred":[
        "\u0641\u0627\u0648\u0631\u0627"
    ],
    "name:pol_x_preferred":[
        "Estubeny"
    ],
    "name:por_x_preferred":[
        "Estubeny"
    ],
    "name:rup_x_preferred":[
        "Estubeny"
    ],
    "name:rus_x_preferred":[
        "\u042d\u0441\u0442\u0443\u0431\u0435\u043d\u044c"
    ],
    "name:spa_x_preferred":[
        "Estubeny"
    ],
    "name:swe_x_preferred":[
        "Estubeny"
    ],
    "name:ukr_x_preferred":[
        "\u0415\u0441\u0442\u0443\u0431\u0435\u043d\u044c"
    ],
    "name:war_x_preferred":[
        "Estubeny"
    ],
    "qs_pg:aaroncc":"ES",
    "qs_pg:gn_country":"ES",
    "qs_pg:gn_fcode":"PPLA3",
    "qs_pg:gn_pop":183,
    "qs_pg:name":"Estubeny",
    "qs_pg:name_adm0":"Espa\u00f1a",
    "qs_pg:name_adm1":"Comunitat Valenciana",
    "qs_pg:photos_9r":0,
    "qs_pg:photos_sr":0,
    "qs_pg:pop_sr":1,
    "qs_pg:qs_pg_placetype":"locality",
    "qs_pg:qs_pg_placetype_gp":"Town",
    "qs_pg:woe_adm0":23424950,
    "woe:adm0_id":23424950,
    "woe:name_adm0":"Espa\u00f1a",
    "woe:name_adm1":"Comunitat Valenciana",
    "woe:placetype":"Town",
    "wof:name":"Estubeny",
    "wof:placetype":"locality",
    "wof:population":183
},
  "geometry": {"coordinates":[-0.62379,39.01792],"type":"Point"}
}