{
  "type": "Feature",
  "properties": {
    "gn:admin1_code":"51",
    "gn:admin2_code":"GR",
    "gn:admin3_code":"18087",
    "gn:asciiname":"Fargue",
    "gn:cc2":"ES",
    "gn:country_code":"ES",
    "gn:dem":949,
    "gn:feature_class":"P",
    "gn:feature_code":"PPL",
    "gn:name":"Fargue",
    "gn:population":0,
    "gn:timezone":"Europe/Madrid",
    "iso:country":"ES",
    "name:und_x_variant":[
        "Alquer\u00eda Fargue",
        "El Fargue"
    ],
    "wof:name":"Fargue",
    "wof:placetype":"locality"
},
  "geometry": {"coordinates":[-3.56223,37.20675],"type":"Point"}
}