{
  "type": "Feature",
  "properties": {
    "gn:admin1_code":"34",
    "gn:admin2_code":"O",
    "gn:admin3_code":"33037",
    "gn:asciiname":"El Campo",
    "gn:country_code":"ES",
    "gn:dem":498,
    "gn:feature_class":"P",
    "gn:feature_code":"PPL",
    "gn:name":"El Campo",
    "gn:population":0,
    "gn:timezone":"Europe/Madrid",
    "iso:country":"ES",
    "wof:name":"El Campo",
    "wof:placetype":"locality"
},
  "geometry": {"coordinates":[-5.71834,43.27355],"type":"Point"}
}