{
  "type": "Feature",
  "properties": {
    "gn:country":"ES",
    "gn:fcode":"PPL",
    "gn:population":134,
    "iso:country":"ES",
    "name:arg_x_preferred":[
        "T\u00edrvia"
    ],
    "name:ast_x_preferred":[
        "T\u00edrvia"
    ],
    "name:cat_x_preferred":[
        "T\u00edrvia"
    ],
    "name:ceb_x_preferred":[
        "T\u00edrvia"
    ],
    "name:deu_x_preferred":[
        "T\u00edrvia"
    ],
    "name:eng_x_preferred":[
        "T\u00edrvia"
    ],
    "name:eus_x_preferred":[
        "T\u00edrvia"
    ],
    "name:fra_x_preferred":[
        "Tirvia"
    ],
    "name:hun_x_preferred":[
        "T\u00edrvia"
    ],
    "name:hye_x_preferred":[
        "\u054f\u056b\u0580\u057e\u056b\u0561"
    ],
    "name:ita_x_preferred":[
        "T\u00edrvia"
    ],
    "name:msa_x_preferred":[
        "T\u00edrvia"
    ],
    "name:nld_x_preferred":[
        "T\u00edrvia"
    ],
    "name:oci_x_preferred":[
        "T\u00edrvia"
    ],
    "name:pol_x_preferred":[
        "T\u00edrvia"
    ],
    "name:por_x_preferred":[
        "T\u00edrvia"
    ],
    "name:ron_x_preferred":[
        "T\u00edrvia"
    ],
    "name:rus_x_preferred":[
        "\u0422\u0438\u0440\u0432\u0438\u044f"
    ],
    "name:spa_x_preferred":[
        "Tirvia"
    ],
    "name:sqi_x_preferred":[
        "T\u00edrvia"
    ],
    "name:swe_x_preferred":[
        "T\u00edrvia"
    ],
    "name:uzb_x_preferred":[
        "T\u00edrvia"
    ],
    "name:vie_x_preferred":[
        "T\u00edrvia"
    ],
    "name:war_x_preferred":[
        "T\u00edrvia"
    ],
    "name:zho_x_preferred":[
        "\u8482\u5c14\u7ef4\u4e9a"
    ],
    "qs_pg:aaroncc":"ES",
    "qs_pg:gn_country":"ES",
    "qs_pg:gn_fcode":"PPL",
    "qs_pg:gn_pop":134,
    "qs_pg:name":"T\u00edrvia",
    "qs_pg:name_adm0":"Espa\u00f1a",
    "qs_pg:name_adm1":"Catalunya",
    "qs_pg:photos":31,
    "qs_pg:photos_1k":6,
    "qs_pg:photos_9k":1,
    "qs_pg:photos_9r":2,
    "qs_pg:photos_all":31,
    "qs_pg:photos_sr":2,
    "qs_pg:pop_sr":1,
    "qs_pg:qs_pg_placetype":"locality",
    "qs_pg:qs_pg_placetype_gp":"Town",
    "qs_pg:woe_adm0":23424950,
    "woe:adm0_id":23424950,
    "woe:name_adm0":"Espa\u00f1a",
    "woe:name_adm1":"Catalunya",
    "woe:placetype":"Town",
    "wof:name":"T\u00edrvia",
    "wof:placetype":"locality",
    "wof:population":134
},
  "geometry": {"coordinates":[1.25,42.51667],"type":"Point"}
}