{
  "type": "Feature",
  "properties": {
    "gn:admin1_code":"58",
    "gn:admin2_code":"OR",
    "gn:admin3_code":"32082",
    "gn:asciiname":"Chamusinos",
    "gn:country_code":"ES",
    "gn:dem":680,
    "gn:feature_class":"P",
    "gn:feature_code":"PPL",
    "gn:name":"Chamusi\u00f1os",
    "gn:population":0,
    "gn:timezone":"Europe/Madrid",
    "iso:country":"ES",
    "wof:name":"Chamusinos",
    "wof:placetype":"locality"
},
  "geometry": {"coordinates":[-7.64898,42.01292],"type":"Point"}
}