{
  "type": "Feature",
  "properties": {
    "gn:admin1_code":"55",
    "gn:admin2_code":"SG",
    "gn:admin3_code":"40111",
    "gn:asciiname":"San Pedro de las Duenas",
    "gn:country_code":"ES",
    "gn:dem":930,
    "gn:feature_class":"P",
    "gn:feature_code":"PPL",
    "gn:name":"San Pedro de las Due\u00f1as",
    "gn:population":0,
    "gn:timezone":"Europe/Madrid",
    "iso:country":"ES",
    "name:und_x_variant":[
        "Caser\u00edo San Pedro de las Duenas",
        "Convento de San Pedro de las Due\u00f1as",
        "San Pedro de las Due\u00f1as"
    ],
    "wof:name":"San Pedro de las Duenas",
    "wof:placetype":"locality"
},
  "geometry": {"coordinates":[-4.31628,40.85672],"type":"Point"}
}