{
  "type": "Feature",
  "properties": {
    "gn:gn_country":"ES",
    "gn:gn_fcode":"PPLA3",
    "gn:gn_pop":59,
    "gn:population":59,
    "iso:country":"ES",
    "name:ara_x_preferred":[
        "\u063a\u0631\u064a\u0633\u064a\u0644"
    ],
    "name:arg_x_preferred":[
        "Grisel"
    ],
    "name:baq_x_preferred":[
        "Grisel"
    ],
    "name:bul_x_preferred":[
        "\u0413\u0440\u0438\u0441\u0435\u043b"
    ],
    "name:cat_x_preferred":[
        "Grisel"
    ],
    "name:chi_x_preferred":[
        "\u683c\u91cc\u585e\u5c14"
    ],
    "name:dut_x_preferred":[
        "Grisel"
    ],
    "name:eng_x_preferred":[
        "Grisel"
    ],
    "name:fre_x_preferred":[
        "Grisel"
    ],
    "name:hun_x_preferred":[
        "Grisel"
    ],
    "name:ita_x_preferred":[
        "Grisel"
    ],
    "name:kaz_x_preferred":[
        "\u0413\u0440\u0438\u0441\u0435\u043b\u044c"
    ],
    "name:may_x_preferred":[
        "Grisel"
    ],
    "name:nan_x_preferred":[
        "Grisel"
    ],
    "name:oci_x_preferred":[
        "Grisel"
    ],
    "name:pol_x_preferred":[
        "Grisel"
    ],
    "name:por_x_preferred":[
        "Grisel"
    ],
    "name:rus_x_preferred":[
        "\u0413\u0440\u0438\u0441\u0435\u043b\u044c"
    ],
    "name:spa_x_preferred":[
        "Grisel"
    ],
    "name:swe_x_preferred":[
        "Grisel"
    ],
    "name:ukr_x_preferred":[
        "\u0413\u0440\u0456\u0441\u0435\u043b\u044c"
    ],
    "name:uzb_x_preferred":[
        "Grisel"
    ],
    "name:vie_x_preferred":[
        "Grisel"
    ],
    "name:war_x_preferred":[
        "Grisel"
    ],
    "qs_pg:aaroncc":"ES",
    "qs_pg:gn_country":"ES",
    "qs_pg:gn_fcode":"PPLA3",
    "qs_pg:gn_pop":59,
    "qs_pg:name":"Grisel",
    "qs_pg:name_adm0":"Espa\u00f1a",
    "qs_pg:name_adm1":"Arag\u00f3n",
    "qs_pg:photos_9k":1,
    "qs_pg:photos_9r":4,
    "qs_pg:photos_all":185,
    "qs_pg:photos_sr":0,
    "qs_pg:pop_sr":1,
    "qs_pg:qs_pg_placetype":"locality",
    "qs_pg:qs_pg_placetype_gp":"Town",
    "qs_pg:woe_adm0":23424950,
    "woe:adm0_id":23424950,
    "woe:name_adm0":"Espa\u00f1a",
    "woe:name_adm1":"Arag\u00f3n",
    "woe:placetype":"Town",
    "wof:name":"Grisel",
    "wof:placetype":"locality",
    "wof:population":59
},
  "geometry": {"coordinates":[-1.72794,41.87109],"type":"Point"}
}