{
  "type": "Feature",
  "properties": {
    "gn:country":"ES",
    "gn:fcode":"PPL",
    "gn:population":0,
    "iso:country":"ES",
    "name:ast_x_preferred":[
        "El Puertu"
    ],
    "name:ceb_x_preferred":[
        "El Puerto"
    ],
    "name:deu_x_preferred":[
        "El Puerto"
    ],
    "name:spa_x_preferred":[
        "El Puerto"
    ],
    "name:srp_x_preferred":[
        "\u0415\u043b \u041f\u0443\u0435\u0440\u0442\u043e"
    ],
    "name:swe_x_preferred":[
        "El Puerto"
    ],
    "qs_pg:aaroncc":"ES",
    "qs_pg:gn_country":"ES",
    "qs_pg:gn_fcode":"PPL",
    "qs_pg:gn_pop":0,
    "qs_pg:name":"El Puerto",
    "qs_pg:name_adm0":"Espa\u00f1a",
    "qs_pg:name_adm1":"Comunitat Valenciana",
    "qs_pg:photos":845,
    "qs_pg:photos_1k":171,
    "qs_pg:photos_9k":4,
    "qs_pg:photos_9r":6,
    "qs_pg:photos_all":845,
    "qs_pg:photos_sr":9,
    "qs_pg:pop_sr":0,
    "qs_pg:qs_pg_placetype":"locality",
    "qs_pg:qs_pg_placetype_gp":"Town",
    "qs_pg:woe_adm0":23424950,
    "woe:adm0_id":23424950,
    "woe:name_adm0":"Espa\u00f1a",
    "woe:name_adm1":"Comunitat Valenciana",
    "woe:placetype":"Town",
    "wof:name":"El Puerto",
    "wof:placetype":"locality"
},
  "geometry": {"coordinates":[-0.07257,39.86683],"type":"Point"}
}