{
  "type": "Feature",
  "properties": {
    "gn:admin1_code":"39",
    "gn:admin2_code":"S",
    "gn:admin3_code":"39057",
    "gn:asciiname":"La Pared",
    "gn:country_code":"ES",
    "gn:dem":242,
    "gn:feature_class":"P",
    "gn:feature_code":"PPL",
    "gn:name":"La Pared",
    "gn:population":0,
    "gn:timezone":"Europe/Madrid",
    "iso:country":"ES",
    "wof:name":"La Pared",
    "wof:placetype":"locality"
},
  "geometry": {"coordinates":[-3.45064,43.23757],"type":"Point"}
}