{
  "type": "Feature",
  "properties": {
    "gn:country":"ES",
    "gn:fcode":"PPLX",
    "gn:population":149718,
    "iso:country":"ES",
    "name:deu_x_preferred":[
        "Madrid Centro"
    ],
    "name:eng_x_preferred":[
        "Madrid City Center"
    ],
    "name:fin_x_preferred":[
        "Madrid Centro"
    ],
    "name:fra_x_preferred":[
        "Madrid Centro"
    ],
    "name:ita_x_preferred":[
        "Madrid Centro"
    ],
    "name:nld_x_preferred":[
        "Madrid Centro"
    ],
    "name:nor_x_preferred":[
        "Madrid Centro"
    ],
    "name:pol_x_preferred":[
        "Madrid Centro"
    ],
    "name:spa_x_preferred":[
        "Madrid Centro"
    ],
    "name:swe_x_preferred":[
        "Madrid Centro"
    ],
    "qs_pg:aaroncc":"ES",
    "qs_pg:gn_country":"ES",
    "qs_pg:gn_fcode":"PPLX",
    "qs_pg:gn_pop":149718,
    "qs_pg:name":"City Center",
    "qs_pg:photos_9r":0,
    "qs_pg:photos_sr":0,
    "qs_pg:pop_sr":9,
    "qs_pg:qs_pg_placetype":"neighbourhood",
    "wof:name":"City Center",
    "wof:placetype":"neighbourhood",
    "wof:population":149718
},
  "geometry": {"coordinates":[-3.70275,40.41831],"type":"Point"}
}