{
  "type": "Feature",
  "properties": {
    "gn:admin1_code":"51",
    "gn:admin2_code":"AL",
    "gn:admin3_code":"04035",
    "gn:asciiname":"Burgallana",
    "gn:country_code":"ES",
    "gn:dem":77,
    "gn:feature_class":"P",
    "gn:feature_code":"PPL",
    "gn:name":"Burgallana",
    "gn:population":0,
    "gn:timezone":"Europe/Madrid",
    "iso:country":"ES",
    "name:und_x_variant":[
        "Barriada Burgallana",
        "Barriada de Burgallana",
        "Burgallana"
    ],
    "wof:name":"Burgallana",
    "wof:placetype":"locality"
},
  "geometry": {"coordinates":[-1.8686,37.29454000000001],"type":"Point"}
}