{
  "type": "Feature",
  "properties": {
    "gn:admin1_code":"55",
    "gn:admin2_code":"LE",
    "gn:admin3_code":"24157",
    "gn:asciiname":"Barrio de Urdiales",
    "gn:country_code":"ES",
    "gn:dem":810,
    "gn:feature_class":"P",
    "gn:feature_code":"PPL",
    "gn:name":"Barrio de Urdiales",
    "gn:population":0,
    "gn:timezone":"Europe/Madrid",
    "iso:country":"ES",
    "wof:name":"Barrio de Urdiales",
    "wof:placetype":"locality"
},
  "geometry": {"coordinates":[-5.77349,42.36869],"type":"Point"}
}