{
  "type": "Feature",
  "properties": {
    "gn:admin1_code":"53",
    "gn:admin2_code":"GC",
    "gn:admin3_code":"35015",
    "gn:asciiname":"El Cortijo de Tetui",
    "gn:country_code":"ES",
    "gn:dem":299,
    "gn:feature_class":"P",
    "gn:feature_code":"PPL",
    "gn:name":"El Cortijo de Tetu\u00ed",
    "gn:population":0,
    "gn:timezone":"Atlantic/Canary",
    "iso:country":"ES",
    "wof:name":"El Cortijo de Tetui",
    "wof:placetype":"locality"
},
  "geometry": {"coordinates":[-14.07755,28.35081],"type":"Point"}
}