{
  "type": "Feature",
  "properties": {
    "gn:admin1_code":"52",
    "gn:admin2_code":"HU",
    "gn:admin3_code":"22907",
    "gn:asciiname":"Olson",
    "gn:country_code":"ES",
    "gn:dem":598,
    "gn:feature_class":"P",
    "gn:feature_code":"PPL",
    "gn:name":"Ols\u00f3n",
    "gn:population":0,
    "gn:timezone":"Europe/Madrid",
    "iso:country":"ES",
    "name:ces_x_preferred":[
        "Olson"
    ],
    "name:deu_x_preferred":[
        "Olson"
    ],
    "name:fra_x_preferred":[
        "Olson"
    ],
    "name:ita_x_preferred":[
        "Olson"
    ],
    "name:pol_x_preferred":[
        "Olson"
    ],
    "name:rus_x_preferred":[
        "\u0423\u043b\u044c\u0441\u043e\u043d"
    ],
    "name:ukr_x_preferred":[
        "\u041e\u043b\u0441\u043e\u043d"
    ],
    "name:und_x_variant":[
        "Ols\u00f3n"
    ],
    "wof:name":"Olson",
    "wof:placetype":"locality"
},
  "geometry": {"coordinates":[0.12737,42.27324],"type":"Point"}
}