{
  "type": "Feature",
  "properties": {
    "gn:admin1_code":"57",
    "gn:admin2_code":"CC",
    "gn:admin3_code":"10136",
    "gn:asciiname":"Fresnedilla",
    "gn:country_code":"ES",
    "gn:dem":398,
    "gn:feature_class":"P",
    "gn:feature_code":"PPL",
    "gn:name":"Fresnedilla",
    "gn:population":0,
    "gn:timezone":"Europe/Madrid",
    "iso:country":"ES",
    "name:und_x_variant":[
        "Caser\u00edo Fresnedilla",
        "Caser\u00edo Dehesa Fresedilla",
        "Fresnedilla"
    ],
    "wof:name":"Fresnedilla",
    "wof:placetype":"locality"
},
  "geometry": {"coordinates":[-6.09275,40.16517],"type":"Point"}
}