{
  "type": "Feature",
  "properties": {
    "gn:admin1_code":"56",
    "gn:admin2_code":"T",
    "gn:admin3_code":"43029",
    "gn:asciiname":"Solivella",
    "gn:country_code":"ES",
    "gn:dem":490,
    "gn:feature_class":"P",
    "gn:feature_code":"PPL",
    "gn:name":"Solivella",
    "gn:population":0,
    "gn:timezone":"Europe/Madrid",
    "iso:country":"ES",
    "name:arg_x_preferred":[
        "Solivella"
    ],
    "name:ast_x_preferred":[
        "Solivella"
    ],
    "name:azb_x_preferred":[
        "\u0633\u0644\u06cc\u0628\u06cc\u0627"
    ],
    "name:cat_x_preferred":[
        "Solivella"
    ],
    "name:ceb_x_preferred":[
        "Solivella"
    ],
    "name:eus_x_preferred":[
        "Solivella"
    ],
    "name:fas_x_preferred":[
        "\u0633\u0644\u06cc\u0628\u06cc\u0627"
    ],
    "name:fra_x_preferred":[
        "Solivella"
    ],
    "name:glg_x_preferred":[
        "Solivella"
    ],
    "name:hun_x_preferred":[
        "Solivella"
    ],
    "name:hye_x_preferred":[
        "\u054d\u0578\u056c\u056b\u057e\u0565\u056c\u0575\u0561"
    ],
    "name:ita_x_preferred":[
        "Solivella"
    ],
    "name:lat_x_preferred":[
        "Solivella"
    ],
    "name:msa_x_preferred":[
        "Solivella"
    ],
    "name:oci_x_preferred":[
        "Solivella"
    ],
    "name:pol_x_preferred":[
        "Solivella"
    ],
    "name:por_x_preferred":[
        "Solivella"
    ],
    "name:rus_x_preferred":[
        "\u0421\u043e\u043b\u0438\u0432\u0435\u043b\u044c\u044f"
    ],
    "name:spa_x_preferred":[
        "Solivella"
    ],
    "name:sqi_x_preferred":[
        "Solivella"
    ],
    "name:swe_x_preferred":[
        "Solivella"
    ],
    "name:uzb_x_preferred":[
        "Solivella"
    ],
    "name:war_x_preferred":[
        "Solivella"
    ],
    "name:zho_x_preferred":[
        "\u7d22\u5229\u97e6\u5229\u4e9a"
    ],
    "wof:name":"Solivella",
    "wof:placetype":"locality"
},
  "geometry": {"coordinates":[1.17824,41.45505],"type":"Point"}
}