{
  "type": "Feature",
  "properties": {
    "gn:admin1_code":"56",
    "gn:admin2_code":"T",
    "gn:admin3_code":"43029",
    "gn:asciiname":"Solivella",
    "gn:country_code":"ES",
    "gn:dem":490,
    "gn:feature_class":"P",
    "gn:feature_code":"PPL",
    "gn:name":"Solivella",
    "gn:population":0,
    "gn:timezone":"Europe/Madrid",
    "iso:country":"ES",
    "wof:name":"Solivella",
    "wof:placetype":"locality"
},
  "geometry": {"coordinates":[1.17824,41.45505],"type":"Point"}
}