{
  "type": "Feature",
  "properties": {
    "gn:admin1_code":"51",
    "gn:admin2_code":"GR",
    "gn:admin3_code":"18135",
    "gn:asciiname":"Lomas de Marcos",
    "gn:country_code":"ES",
    "gn:dem":1015,
    "gn:feature_class":"P",
    "gn:feature_code":"PPL",
    "gn:name":"Lomas de Marcos",
    "gn:population":0,
    "gn:timezone":"Europe/Madrid",
    "iso:country":"ES",
    "name:und_x_variant":[
        "Casa Lomas de Marcos",
        "Lomas de Marcos"
    ],
    "wof:name":"Lomas de Marcos",
    "wof:placetype":"locality"
},
  "geometry": {"coordinates":[-4.06143,37.35679],"type":"Point"}
}