{
  "type": "Feature",
  "properties": {
    "iso:country":"ES",
    "name:ara_x_preferred":[
        "\u0628\u0627\u0644\u064a\u0627\u0631\u0627\u064a\u0646"
    ],
    "name:arg_x_preferred":[
        "Baliarrain"
    ],
    "name:ast_x_preferred":[
        "Baliarrain"
    ],
    "name:baq_x_preferred":[
        "Baliarrain"
    ],
    "name:bre_x_preferred":[
        "Baliarrain"
    ],
    "name:cat_x_preferred":[
        "Baliarrain"
    ],
    "name:chi_x_preferred":[
        "\u5df4\u5229\u4e9a\u8d56\u6069"
    ],
    "name:dut_x_preferred":[
        "Baliarrain"
    ],
    "name:eng_x_preferred":[
        "Baliarrain"
    ],
    "name:fre_x_preferred":[
        "Baliarrain"
    ],
    "name:glg_x_preferred":[
        "Baliarrain"
    ],
    "name:hun_x_preferred":[
        "Baliarrain"
    ],
    "name:ita_x_preferred":[
        "Baliarrain"
    ],
    "name:jpn_x_preferred":[
        "\u30d0\u30ea\u30a2\u30e9\u30a4\u30f3"
    ],
    "name:may_x_preferred":[
        "Baliarrain"
    ],
    "name:oci_x_preferred":[
        "Baliarrain"
    ],
    "name:pol_x_preferred":[
        "Baliarrain"
    ],
    "name:por_x_preferred":[
        "Baliarrain"
    ],
    "name:rup_x_preferred":[
        "Baliarrain"
    ],
    "name:rus_x_preferred":[
        "\u0411\u0430\u043b\u0438\u0430\u0440\u0440\u0430\u0439\u043d"
    ],
    "name:sco_x_preferred":[
        "Baliarrain"
    ],
    "name:spa_x_preferred":[
        "Baliarrain"
    ],
    "name:swe_x_preferred":[
        "Baliarrain"
    ],
    "name:ukr_x_preferred":[
        "\u0411\u0430\u043b\u0456\u0430\u0440\u0440\u0430\u0439\u043d"
    ],
    "name:uzb_x_preferred":[
        "Baliarrain"
    ],
    "name:vie_x_preferred":[
        "Baliarrain"
    ],
    "name:war_x_preferred":[
        "Baliarrain"
    ],
    "qs_pg:aaroncc":"ES",
    "qs_pg:name":"Baliarrain",
    "qs_pg:name_adm0":"Espa\u00f1a",
    "qs_pg:name_adm1":"Euskadi",
    "qs_pg:photos":16,
    "qs_pg:photos_1k":3,
    "qs_pg:photos_9k":1,
    "qs_pg:photos_9r":1,
    "qs_pg:photos_all":16,
    "qs_pg:photos_sr":1,
    "qs_pg:pop_sr":0,
    "qs_pg:qs_pg_placetype":"locality",
    "qs_pg:qs_pg_placetype_gp":"Town",
    "qs_pg:woe_adm0":23424950,
    "woe:adm0_id":23424950,
    "woe:name_adm0":"Espa\u00f1a",
    "woe:name_adm1":"Euskadi",
    "woe:placetype":"Town",
    "wof:name":"Baliarrain",
    "wof:placetype":"locality"
},
  "geometry": {"coordinates":[-2.1355,43.0714165],"type":"Point"}
}