{
  "type": "Feature",
  "properties": {
    "gn:country":"ES",
    "gn:fcode":"ADM3",
    "gn:population":7139,
    "iso:country":"ES",
    "name:arg_x_preferred":[
        "Aranguren"
    ],
    "name:bre_x_preferred":[
        "Aranguren"
    ],
    "name:cat_x_preferred":[
        "Aranguren"
    ],
    "name:ceb_x_preferred":[
        "Aranguren"
    ],
    "name:eng_x_preferred":[
        "Aranguren"
    ],
    "name:eus_x_preferred":[
        "Aranguren"
    ],
    "name:fra_x_preferred":[
        "Aranguren"
    ],
    "name:glg_x_preferred":[
        "Aranguren"
    ],
    "name:hun_x_preferred":[
        "Aranguren"
    ],
    "name:ita_x_preferred":[
        "Aranguren"
    ],
    "name:jpn_x_preferred":[
        "\u30a2\u30e9\u30f3\u30b0\u30ec\u30f3"
    ],
    "name:lit_x_preferred":[
        "Arangurenas"
    ],
    "name:msa_x_preferred":[
        "Aranguren"
    ],
    "name:nan_x_preferred":[
        "Aranguren"
    ],
    "name:nld_x_preferred":[
        "Aranguren"
    ],
    "name:oci_x_preferred":[
        "Aranguren"
    ],
    "name:pol_x_preferred":[
        "Aranguren"
    ],
    "name:por_x_preferred":[
        "Aranguren"
    ],
    "name:rup_x_preferred":[
        "Aranguren"
    ],
    "name:rus_x_preferred":[
        "\u0410\u0440\u0430\u043d\u0433\u0443\u0440\u0435\u043d"
    ],
    "name:sco_x_preferred":[
        "Aranguren"
    ],
    "name:spa_x_preferred":[
        "Aranguren"
    ],
    "name:sqi_x_preferred":[
        "Aranguren"
    ],
    "name:swe_x_preferred":[
        "Aranguren"
    ],
    "name:ukr_x_preferred":[
        "\u0410\u0440\u0430\u043d\u0433\u0443\u0440\u0435\u043d"
    ],
    "name:uzb_x_preferred":[
        "Aranguren"
    ],
    "name:vie_x_preferred":[
        "Aranguren"
    ],
    "name:war_x_preferred":[
        "Aranguren"
    ],
    "name:zho_x_preferred":[
        "\u963f\u5170\u53e4\u4f26"
    ],
    "qs_pg:aaroncc":"ES",
    "qs_pg:gn_country":"ES",
    "qs_pg:gn_fcode":"ADM3",
    "qs_pg:gn_pop":7139,
    "qs_pg:name":"Aranguren",
    "qs_pg:name_adm0":"Espa\u00f1a",
    "qs_pg:name_adm1":"Comunidad Foral de Navarra",
    "qs_pg:photos":580,
    "qs_pg:photos_1k":118,
    "qs_pg:photos_9k":3,
    "qs_pg:photos_9r":5,
    "qs_pg:photos_all":580,
    "qs_pg:photos_sr":8,
    "qs_pg:pop_sr":5,
    "qs_pg:qs_pg_placetype":"locality",
    "qs_pg:qs_pg_placetype_gp":"Town",
    "qs_pg:woe_adm0":23424950,
    "woe:adm0_id":23424950,
    "woe:name_adm0":"Espa\u00f1a",
    "woe:name_adm1":"Comunidad Foral de Navarra",
    "woe:placetype":"Town",
    "wof:name":"Aranguren",
    "wof:placetype":"locality",
    "wof:population":8092
},
  "geometry": {"coordinates":[-1.57726,42.77889],"type":"Point"}
}