{
  "type": "Feature",
  "properties": {
    "gn:admin1_code":"34",
    "gn:admin2_code":"O",
    "gn:admin3_code":"33040",
    "gn:asciiname":"Omedo",
    "gn:country_code":"ES",
    "gn:dem":305,
    "gn:feature_class":"P",
    "gn:feature_code":"PPL",
    "gn:name":"Omedo",
    "gn:population":0,
    "gn:timezone":"Europe/Madrid",
    "iso:country":"ES",
    "wof:name":"Omedo",
    "wof:placetype":"locality"
},
  "geometry": {"coordinates":[-5.49188,43.34965],"type":"Point"}
}