{
  "type": "Feature",
  "properties": {
    "gn:admin1_code":"51",
    "gn:admin2_code":"J",
    "gn:admin3_code":"23043",
    "gn:asciiname":"Hornos el Viejo",
    "gn:country_code":"ES",
    "gn:dem":763,
    "gn:feature_class":"P",
    "gn:feature_code":"PPL",
    "gn:name":"Hornos el Viejo",
    "gn:population":0,
    "gn:timezone":"Europe/Madrid",
    "iso:country":"ES",
    "name:und_x_variant":[
        "Cortijo de Hornos el Viejo",
        "Hornos el Viejo"
    ],
    "wof:name":"Hornos el Viejo",
    "wof:placetype":"locality"
},
  "geometry": {"coordinates":[-2.72791,38.1865],"type":"Point"}
}