{
  "type": "Feature",
  "properties": {
    "gn:country":"ES",
    "gn:fcode":"PPLA3",
    "gn:population":56,
    "iso:country":"ES",
    "name:arg_x_preferred":[
        "Villaverde de Montejo"
    ],
    "name:cat_x_preferred":[
        "Villaverde de Montejo"
    ],
    "name:che_x_preferred":[
        "\u0412\u0438\u043b\u044c\u044f\u0432\u0435\u0440\u0434\u0435-\u0434\u0435-\u041c\u043e\u043d\u0442\u0435\u0445\u043e"
    ],
    "name:deu_x_preferred":[
        "Villaverde de Montejo"
    ],
    "name:eng_x_preferred":[
        "Villaverde de Montejo"
    ],
    "name:eus_x_preferred":[
        "Villaverde de Montejo"
    ],
    "name:fra_x_preferred":[
        "Villaverde de Montejo"
    ],
    "name:hun_x_preferred":[
        "Villaverde de Montejo"
    ],
    "name:ina_x_preferred":[
        "Villaverde de Montejo"
    ],
    "name:ita_x_preferred":[
        "Villaverde de Montejo"
    ],
    "name:msa_x_preferred":[
        "Villaverde de Montejo"
    ],
    "name:nan_x_preferred":[
        "Villaverde de Montejo"
    ],
    "name:nld_x_preferred":[
        "Villaverde de Montejo"
    ],
    "name:oci_x_preferred":[
        "Villaverde de Montejo"
    ],
    "name:pol_x_preferred":[
        "Villaverde de Montejo"
    ],
    "name:por_x_preferred":[
        "Villaverde de Montejo"
    ],
    "name:rus_x_preferred":[
        "\u0412\u0438\u043b\u044c\u044f\u0432\u0435\u0440\u0434\u0435-\u0434\u0435-\u041c\u043e\u043d\u0442\u0435\u0445\u043e"
    ],
    "name:spa_x_preferred":[
        "Villaverde de Montejo"
    ],
    "name:swe_x_preferred":[
        "Villaverde de Montejo"
    ],
    "name:tat_x_preferred":[
        "\u0412\u0438\u043b\u044c\u044f\u0432\u0435\u0440\u0434\u0435-\u0434\u0435-\u041c\u043e\u043d\u0442\u0435\u0445\u043e"
    ],
    "name:ukr_x_preferred":[
        "\u0412\u0456\u043b\u044c\u044f\u0432\u0435\u0440\u0434\u0435-\u0434\u0435-\u041c\u043e\u043d\u0442\u0435\u0445\u043e"
    ],
    "name:vie_x_preferred":[
        "Villaverde de Montejo"
    ],
    "name:war_x_preferred":[
        "Villaverde de Montejo"
    ],
    "name:zho_x_preferred":[
        "\u6bd4\u5229\u4e9a\u97e6\u5c14\u5fb7\u5fb7\u8499\u7279\u970d"
    ],
    "qs_pg:aaroncc":"ES",
    "qs_pg:gn_country":"ES",
    "qs_pg:gn_fcode":"PPLA3",
    "qs_pg:gn_pop":56,
    "qs_pg:name":"Villaverde de Montejo",
    "qs_pg:name_adm0":"Espa\u00f1a",
    "qs_pg:name_adm1":"Castilla y Le\u00f3n",
    "qs_pg:photos_9r":0,
    "qs_pg:photos_sr":0,
    "qs_pg:pop_sr":1,
    "qs_pg:qs_pg_placetype":"locality",
    "qs_pg:qs_pg_placetype_gp":"Town",
    "qs_pg:woe_adm0":23424950,
    "woe:adm0_id":23424950,
    "woe:name_adm0":"Espa\u00f1a",
    "woe:name_adm1":"Castilla y Le\u00f3n",
    "woe:placetype":"Town",
    "wof:name":"Villaverde de Montejo",
    "wof:placetype":"locality",
    "wof:population":56
},
  "geometry": {"coordinates":[-3.65452,41.52225],"type":"Point"}
}