{
  "type": "Feature",
  "properties": {
    "gn:admin1_code":"55",
    "gn:admin2_code":"SG",
    "gn:admin3_code":"40024",
    "gn:asciiname":"Morcuera",
    "gn:country_code":"ES",
    "gn:dem":1066,
    "gn:feature_class":"P",
    "gn:feature_code":"PPL",
    "gn:name":"Morcuera",
    "gn:population":0,
    "gn:timezone":"Europe/Madrid",
    "iso:country":"ES",
    "wof:name":"Morcuera",
    "wof:placetype":"locality"
},
  "geometry": {"coordinates":[-3.21663,41.46468],"type":"Point"}
}