{
  "type": "Feature",
  "properties": {
    "gn:admin1_code":"55",
    "gn:admin2_code":"ZA",
    "gn:admin3_code":"49166",
    "gn:asciiname":"Castellanos",
    "gn:country_code":"ES",
    "gn:dem":957,
    "gn:feature_class":"P",
    "gn:feature_code":"PPL",
    "gn:name":"Castellanos",
    "gn:population":0,
    "gn:timezone":"Europe/Madrid",
    "iso:country":"ES",
    "name:cat_x_preferred":[
        "Castellanos"
    ],
    "name:ceb_x_preferred":[
        "Castellanos"
    ],
    "name:deu_x_preferred":[
        "Castellanos"
    ],
    "name:fra_x_preferred":[
        "Castellanos"
    ],
    "name:ita_x_preferred":[
        "Castellanos"
    ],
    "name:nld_x_preferred":[
        "Castellanos"
    ],
    "name:rus_x_preferred":[
        "\u041a\u0430\u0441\u0442\u0435\u043b\u044c\u044f\u043d\u043e\u0441"
    ],
    "name:spa_x_preferred":[
        "Castellanos"
    ],
    "name:swe_x_preferred":[
        "Castellanos"
    ],
    "name:ukr_x_preferred":[
        "\u041a\u0430\u0441\u0442\u0435\u043b\u044c\u044f\u043d\u043e\u0441"
    ],
    "wof:name":"Castellanos",
    "wof:placetype":"locality"
},
  "geometry": {"coordinates":[-6.61681,42.07382],"type":"Point"}
}