{
  "type": "Feature",
  "properties": {
    "gn:admin1_code":"55",
    "gn:admin2_code":"ZA",
    "gn:admin3_code":"49166",
    "gn:asciiname":"Castellanos",
    "gn:country_code":"ES",
    "gn:dem":957,
    "gn:feature_class":"P",
    "gn:feature_code":"PPL",
    "gn:name":"Castellanos",
    "gn:population":0,
    "gn:timezone":"Europe/Madrid",
    "iso:country":"ES",
    "wof:name":"Castellanos",
    "wof:placetype":"locality"
},
  "geometry": {"coordinates":[-6.61681,42.07382],"type":"Point"}
}