{
  "type": "Feature",
  "properties": {
    "gn:country":"ES",
    "gn:fcode":"PPLA3",
    "gn:population":9999,
    "iso:country":"ES",
    "name:ara_x_preferred":[
        "\u0645\u0648\u0631\u0648\u0633\u060c \u0644\u0627 \u0643\u0631\u0648\u0646\u064a\u0627"
    ],
    "name:ara_x_variant":[
        "\u0645\u0648\u0631\u0648\u0633"
    ],
    "name:bre_x_preferred":[
        "Muros"
    ],
    "name:cat_x_preferred":[
        "Muros"
    ],
    "name:ceb_x_preferred":[
        "Muros"
    ],
    "name:dan_x_preferred":[
        "Muros"
    ],
    "name:deu_x_preferred":[
        "Muros"
    ],
    "name:eng_x_preferred":[
        "Muros"
    ],
    "name:eus_x_preferred":[
        "Muros"
    ],
    "name:fin_x_preferred":[
        "Muros"
    ],
    "name:fra_x_preferred":[
        "Muros"
    ],
    "name:glg_x_preferred":[
        "Muros"
    ],
    "name:hun_x_preferred":[
        "Muros"
    ],
    "name:hye_x_preferred":[
        "\u0544\u0578\u0582\u0580\u0578\u057d"
    ],
    "name:ita_x_preferred":[
        "Muros"
    ],
    "name:jpn_x_preferred":[
        "\u30e0\u30fc\u30ed\u30b9"
    ],
    "name:lit_x_preferred":[
        "Murosas"
    ],
    "name:mkd_x_preferred":[
        "\u041c\u0443\u0441\u043e\u0441"
    ],
    "name:msa_x_preferred":[
        "Muros"
    ],
    "name:nan_x_preferred":[
        "Muros"
    ],
    "name:nld_x_preferred":[
        "Muros"
    ],
    "name:oci_x_preferred":[
        "Muros"
    ],
    "name:pol_x_preferred":[
        "Muros"
    ],
    "name:por_x_preferred":[
        "Muros"
    ],
    "name:rus_x_preferred":[
        "\u041c\u0443\u0440\u043e\u0441"
    ],
    "name:spa_x_preferred":[
        "Muros"
    ],
    "name:swe_x_preferred":[
        "Muros"
    ],
    "name:tur_x_preferred":[
        "Muros"
    ],
    "name:ukr_x_preferred":[
        "\u041c\u0443\u0440\u043e\u0441"
    ],
    "name:und_x_variant":[
        "Ebora"
    ],
    "name:uzb_x_preferred":[
        "Muros"
    ],
    "name:vie_x_preferred":[
        "Muros"
    ],
    "name:war_x_preferred":[
        "Muros"
    ],
    "name:zho_x_preferred":[
        "\u7a46\u7f57\u65af"
    ],
    "qs_pg:aaroncc":"ES",
    "qs_pg:gn_country":"ES",
    "qs_pg:gn_fcode":"PPLA3",
    "qs_pg:gn_pop":9999,
    "qs_pg:name":"Muros",
    "qs_pg:name_adm0":"Espa\u00f1a",
    "qs_pg:name_adm1":"Galicia",
    "qs_pg:photos":1213,
    "qs_pg:photos_1k":246,
    "qs_pg:photos_9k":5,
    "qs_pg:photos_9r":7,
    "qs_pg:photos_all":1213,
    "qs_pg:photos_sr":11,
    "qs_pg:pop_sr":5,
    "qs_pg:qs_pg_placetype":"locality",
    "qs_pg:qs_pg_placetype_gp":"Town",
    "qs_pg:woe_adm0":23424950,
    "woe:adm0_id":23424950,
    "woe:name_adm0":"Espa\u00f1a",
    "woe:name_adm1":"Galicia",
    "woe:placetype":"Town",
    "wof:name":"Muros",
    "wof:placetype":"locality",
    "wof:population":9999
},
  "geometry": {"coordinates":[-9.06032,42.77617],"type":"Point"}
}