{
  "type": "Feature",
  "properties": {
    "iso:country":"ES",
    "name:cat_x_preferred":[
        "Nostra Senyora de Jes\u00fas"
    ],
    "name:cat_x_variant":[
        "Jes\u00fas"
    ],
    "name:eng_x_preferred":[
        "Jes\u00fas"
    ],
    "name:nld_x_preferred":[
        "Jes\u00fas"
    ],
    "name:spa_x_preferred":[
        "Nuestra Se\u00f1ora de Jes\u00fas"
    ],
    "qs_pg:aaroncc":"ES",
    "qs_pg:name":"Jes\u00fas",
    "qs_pg:name_adm0":"Espa\u00f1a",
    "qs_pg:name_adm1":"Illes Balears",
    "qs_pg:photos":218,
    "qs_pg:photos_1k":44,
    "qs_pg:photos_9k":1,
    "qs_pg:photos_9r":4,
    "qs_pg:photos_all":218,
    "qs_pg:photos_sr":4,
    "qs_pg:pop_sr":0,
    "qs_pg:qs_pg_placetype":"locality",
    "qs_pg:qs_pg_placetype_gp":"Town",
    "qs_pg:woe_adm0":23424950,
    "woe:adm0_id":23424950,
    "woe:name_adm0":"Espa\u00f1a",
    "woe:name_adm1":"Illes Balears",
    "woe:placetype":"Town",
    "wof:name":"Jes\u00fas",
    "wof:placetype":"locality"
},
  "geometry": {"coordinates":[1.437149,38.9312545],"type":"Point"}
}