{
  "type": "Feature",
  "properties": {
    "gn:gn_country":"ES",
    "gn:gn_fcode":"PPL",
    "gn:gn_pop":600,
    "gn:population":600,
    "iso:country":"ES",
    "name:rus_x_preferred":[
        "\u041f\u0443\u044d\u0440\u0442\u043e \u0434\u0435 \u0421\u0430\u043d\u0442\u044c\u044f\u0433\u043e"
    ],
    "name:spa_x_preferred":[
        "Puerto Santiago"
    ],
    "name:unk_x_variant":[
        "Santiago"
    ],
    "qs_pg:aaroncc":"ES",
    "qs_pg:gn_country":"ES",
    "qs_pg:gn_fcode":"PPL",
    "qs_pg:gn_pop":600,
    "qs_pg:name":"Puerto de Santiago",
    "qs_pg:name_adm0":"Espa\u00f1a",
    "qs_pg:name_adm1":"Islas Canarias",
    "qs_pg:photos":1565,
    "qs_pg:photos_1k":317,
    "qs_pg:photos_9k":7,
    "qs_pg:photos_9r":8,
    "qs_pg:photos_all":1565,
    "qs_pg:photos_sr":13,
    "qs_pg:pop_sr":2,
    "qs_pg:qs_pg_placetype":"locality",
    "qs_pg:qs_pg_placetype_gp":"Town",
    "qs_pg:woe_adm0":23424950,
    "woe:adm0_id":23424950,
    "woe:name_adm0":"Espa\u00f1a",
    "woe:name_adm1":"Islas Canarias",
    "woe:placetype":"Town",
    "wof:name":"Puerto de Santiago",
    "wof:placetype":"locality",
    "wof:population":600
},
  "geometry": {"coordinates":[-16.84335,28.23666],"type":"Point"}
}