{
  "type": "Feature",
  "properties": {
    "gn:country":"ES",
    "gn:fcode":"PPLA3",
    "gn:population":505,
    "iso:country":"ES",
    "name:arg_x_preferred":[
        "Pozal de Gallinas"
    ],
    "name:azb_x_preferred":[
        "\u067e\u0633\u0627\u0644 \u062f \u0642\u0627\u06cc\u06cc\u0646\u0627\u0633"
    ],
    "name:cat_x_preferred":[
        "Pozal de Gallinas"
    ],
    "name:eng_x_preferred":[
        "Pozal de Gallinas"
    ],
    "name:eus_x_preferred":[
        "Pozal de Gallinas"
    ],
    "name:fas_x_preferred":[
        "\u067e\u0633\u0627\u0644 \u062f \u06af\u0627\u06cc\u06cc\u0646\u0627\u0633"
    ],
    "name:fra_x_preferred":[
        "Pozal de Gallinas"
    ],
    "name:hun_x_preferred":[
        "Pozal de Gallinas"
    ],
    "name:hye_x_preferred":[
        "\u054a\u0578\u057d\u0561\u056c \u0564\u0565 \u0533\u0561\u056c\u0575\u056b\u0576\u0561\u057d"
    ],
    "name:ina_x_preferred":[
        "Pozal de Gallinas"
    ],
    "name:ita_x_preferred":[
        "Pozal de Gallinas"
    ],
    "name:msa_x_preferred":[
        "Pozal de Gallinas"
    ],
    "name:nan_x_preferred":[
        "Pozal de Gallinas"
    ],
    "name:nld_x_preferred":[
        "Pozal de Gallinas"
    ],
    "name:oci_x_preferred":[
        "Pozal de Gallinas"
    ],
    "name:pol_x_preferred":[
        "Pozal de Gallinas"
    ],
    "name:por_x_preferred":[
        "Pozal de Gallinas"
    ],
    "name:rus_x_preferred":[
        "\u041f\u043e\u0441\u0430\u043b\u044c-\u0434\u0435-\u0413\u0430\u043b\u044c\u0438\u043d\u0430\u0441"
    ],
    "name:spa_x_preferred":[
        "Pozal de Gallinas"
    ],
    "name:swe_x_preferred":[
        "Pozal de Gallinas"
    ],
    "name:ukr_x_preferred":[
        "\u041f\u043e\u0441\u0430\u043b\u044c-\u0434\u0435-\u0413\u0430\u043b\u044c\u0457\u043d\u0430\u0441"
    ],
    "name:uzb_x_preferred":[
        "Pozal de Gallinas"
    ],
    "name:vie_x_preferred":[
        "Pozal de Gallinas"
    ],
    "name:war_x_preferred":[
        "Pozal de Gallinas"
    ],
    "name:zho_x_preferred":[
        "\u6ce2\u8428\u5c14\u5fb7\u52a0\u5229\u7eb3\u65af"
    ],
    "qs_pg:aaroncc":"ES",
    "qs_pg:gn_country":"ES",
    "qs_pg:gn_fcode":"PPLA3",
    "qs_pg:gn_pop":505,
    "qs_pg:name":"Pozal de Gallinas",
    "qs_pg:name_adm0":"Espa\u00f1a",
    "qs_pg:name_adm1":"Castilla y Le\u00f3n",
    "qs_pg:photos_9k":1,
    "qs_pg:photos_9r":1,
    "qs_pg:photos_all":2,
    "qs_pg:photos_sr":0,
    "qs_pg:pop_sr":2,
    "qs_pg:qs_pg_placetype":"locality",
    "qs_pg:qs_pg_placetype_gp":"Town",
    "qs_pg:woe_adm0":23424950,
    "woe:adm0_id":23424950,
    "woe:name_adm0":"Espa\u00f1a",
    "woe:name_adm1":"Castilla y Le\u00f3n",
    "woe:placetype":"Town",
    "wof:name":"Pozal de Gallinas",
    "wof:placetype":"locality",
    "wof:population":505
},
  "geometry": {"coordinates":[-4.83936,41.31831],"type":"Point"}
}