{
  "type": "Feature",
  "properties": {
    "gn:admin1_code":"55",
    "gn:admin2_code":"SA",
    "gn:admin3_code":"37102",
    "gn:asciiname":"Valdelamatanza",
    "gn:country_code":"ES",
    "gn:dem":648,
    "gn:feature_class":"P",
    "gn:feature_code":"PPL",
    "gn:name":"Valdelamatanza",
    "gn:population":0,
    "gn:timezone":"Europe/Madrid",
    "iso:country":"ES",
    "wof:name":"Valdelamatanza",
    "wof:placetype":"locality"
},
  "geometry": {"coordinates":[-5.92418,40.29013],"type":"Point"}
}