{
  "type": "Feature",
  "properties": {
    "gn:admin1_code":"55",
    "gn:admin2_code":"LE",
    "gn:admin3_code":"24227",
    "gn:asciiname":"San Justo de las Regueras",
    "gn:country_code":"ES",
    "gn:dem":786,
    "gn:feature_class":"P",
    "gn:feature_code":"PPL",
    "gn:name":"San Justo de las Regueras",
    "gn:population":0,
    "gn:timezone":"Europe/Madrid",
    "iso:country":"ES",
    "wof:name":"San Justo de las Regueras",
    "wof:placetype":"locality"
},
  "geometry": {"coordinates":[-5.48673,42.50188],"type":"Point"}
}