{
  "type": "Feature",
  "properties": {
    "gn:admin1_code":"51",
    "gn:admin2_code":"J",
    "gn:admin3_code":"23092",
    "gn:asciiname":"Miranda",
    "gn:cc2":"ES",
    "gn:country_code":"ES",
    "gn:dem":422,
    "gn:feature_class":"P",
    "gn:feature_code":"PPL",
    "gn:name":"Miranda",
    "gn:population":0,
    "gn:timezone":"Europe/Madrid",
    "iso:country":"ES",
    "name:und_x_variant":[
        "Caser\u00edo Miranda",
        "Miranda"
    ],
    "wof:name":"Miranda",
    "wof:placetype":"locality"
},
  "geometry": {"coordinates":[-3.38333,37.95],"type":"Point"}
}