{
  "type": "Feature",
  "properties": {
    "gn:admin1_code":"51",
    "gn:admin2_code":"J",
    "gn:admin3_code":"23084",
    "gn:asciiname":"Sorihuela del Guadalimar",
    "gn:country_code":"ES",
    "gn:dem":650,
    "gn:feature_class":"P",
    "gn:feature_code":"PPLA3",
    "gn:name":"Sorihuela del Guadalimar",
    "gn:population":1232,
    "gn:timezone":"Europe/Madrid",
    "iso:country":"ES",
    "wof:name":"Sorihuela del Guadalimar",
    "wof:placetype":"locality",
    "wof:population":1232
},
  "geometry": {"coordinates":[-3.0536,38.24062],"type":"Point"}
}