{
  "type": "Feature",
  "properties": {
    "gn:admin1_code":"51",
    "gn:admin2_code":"J",
    "gn:admin3_code":"23084",
    "gn:asciiname":"Sorihuela del Guadalimar",
    "gn:country_code":"ES",
    "gn:dem":650,
    "gn:feature_class":"P",
    "gn:feature_code":"PPLA3",
    "gn:name":"Sorihuela del Guadalimar",
    "gn:population":1232,
    "gn:timezone":"Europe/Madrid",
    "iso:country":"ES",
    "name:ara_x_preferred":[
        "\u0633\u0648\u0631\u064a\u0648\u064a\u0644\u0627 \u062f\u064a\u0644 \u063a\u0648\u0627\u062f\u0627\u0644\u064a\u0645\u0627\u0631"
    ],
    "name:azb_x_preferred":[
        "\u0633\u0631\u06cc\u0647\u0648\u0626\u0644\u0627 \u062f\u0644 \u0642\u0648\u0627\u062f\u0627\u0644\u06cc\u0645\u0627\u0631"
    ],
    "name:cat_x_preferred":[
        "Sorihuela del Guadalimar"
    ],
    "name:ceb_x_preferred":[
        "Sorihuela del Guadalimar"
    ],
    "name:eus_x_preferred":[
        "Sorihuela del Guadalimar"
    ],
    "name:fas_x_preferred":[
        "\u0633\u0631\u06cc\u0647\u0648\u0626\u0644\u0627 \u062f\u0644 \u06af\u0648\u0627\u062f\u0627\u0644\u06cc\u0645\u0627\u0631"
    ],
    "name:fra_x_preferred":[
        "Sorihuela del Guadalimar"
    ],
    "name:hat_x_preferred":[
        "Sorihuela del Guadalimar"
    ],
    "name:hun_x_preferred":[
        "Sorihuela del Guadalimar"
    ],
    "name:hye_x_preferred":[
        "\u054d\u0578\u0580\u056b\u0578\u0582\u0565\u056c\u0561 \u0564\u0565\u056c \u0533\u0578\u0582\u0561\u0564\u0561\u056c\u056b\u0574\u0561\u0580"
    ],
    "name:ita_x_preferred":[
        "Sorihuela del Guadalimar"
    ],
    "name:msa_x_preferred":[
        "Sorihuela del Guadalimar"
    ],
    "name:nld_x_preferred":[
        "Sorihuela del Guadalimar"
    ],
    "name:oci_x_preferred":[
        "Sorihuela del Guadalimar"
    ],
    "name:pol_x_preferred":[
        "Sorihuela del Guadalimar"
    ],
    "name:por_x_preferred":[
        "Sorihuela del Guadalimar"
    ],
    "name:ron_x_preferred":[
        "Sorihuela del Guadalimar"
    ],
    "name:rus_x_preferred":[
        "\u0421\u043e\u0440\u0438\u0443\u044d\u043b\u0430-\u0434\u0435\u043b\u044c-\u0413\u0443\u0430\u0434\u0430\u043b\u0438\u043c\u0430\u0440"
    ],
    "name:spa_x_preferred":[
        "Sorihuela del Guadalimar"
    ],
    "name:swe_x_preferred":[
        "Sorihuela del Guadalimar"
    ],
    "name:tur_x_preferred":[
        "Sorihuela del Guadalimar"
    ],
    "name:ukr_x_preferred":[
        "\u0421\u043e\u0440\u0456\u0443\u0435\u043b\u0430-\u0434\u0435\u043b\u044c-\u0413\u0443\u0430\u0434\u0430\u043b\u0456\u043c\u0430\u0440"
    ],
    "name:vie_x_preferred":[
        "Sorihuela del Guadalimar"
    ],
    "name:war_x_preferred":[
        "Sorihuela del Guadalimar"
    ],
    "name:zho_x_preferred":[
        "\u7d22\u91cc\u97e6\u62c9\u5fb7\u5c14\u74dc\u8fbe\u5229\u9a6c\u5c14"
    ],
    "wof:name":"Sorihuela del Guadalimar",
    "wof:placetype":"locality",
    "wof:population":1232
},
  "geometry": {"coordinates":[-3.0536,38.24062],"type":"Point"}
}