{
  "type": "Feature",
  "properties": {
    "gn:admin1_code":"58",
    "gn:admin2_code":"LU",
    "gn:admin3_code":"27012",
    "gn:asciiname":"Villameixide",
    "gn:country_code":"ES",
    "gn:dem":601,
    "gn:feature_class":"P",
    "gn:feature_code":"PPL",
    "gn:name":"Villameixide",
    "gn:population":0,
    "gn:timezone":"Europe/Madrid",
    "iso:country":"ES",
    "wof:name":"Villameixide",
    "wof:placetype":"locality"
},
  "geometry": {"coordinates":[-7.01667,42.93333],"type":"Point"}
}