{
  "type": "Feature",
  "properties": {
    "gn:admin1_code":"56",
    "gn:admin2_code":"GI",
    "gn:admin3_code":"17020",
    "gn:asciiname":"Estanyol",
    "gn:country_code":"ES",
    "gn:dem":181,
    "gn:feature_class":"P",
    "gn:feature_code":"PPL",
    "gn:name":"Estanyol",
    "gn:population":0,
    "gn:timezone":"Europe/Madrid",
    "iso:country":"ES",
    "wof:name":"Estanyol",
    "wof:placetype":"locality"
},
  "geometry": {"coordinates":[2.75,41.93333],"type":"Point"}
}