{
  "type": "Feature",
  "properties": {
    "gn:admin1_code":"59",
    "gn:admin2_code":"BI",
    "gn:admin3_code":"48002",
    "gn:asciiname":"Las Calizas",
    "gn:country_code":"ES",
    "gn:dem":296,
    "gn:feature_class":"P",
    "gn:feature_code":"PPL",
    "gn:name":"Las Calizas",
    "gn:population":0,
    "gn:timezone":"Europe/Madrid",
    "iso:country":"ES",
    "wof:name":"Las Calizas",
    "wof:placetype":"locality"
},
  "geometry": {"coordinates":[-3.07797,43.30045],"type":"Point"}
}