{
  "type": "Feature",
  "properties": {
    "gn:admin1_code":"58",
    "gn:admin2_code":"PO",
    "gn:admin3_code":"36013",
    "gn:asciiname":"Godones",
    "gn:cc2":"ES",
    "gn:country_code":"ES",
    "gn:dem":482,
    "gn:feature_class":"P",
    "gn:feature_code":"PPL",
    "gn:name":"Godones",
    "gn:population":0,
    "gn:timezone":"Europe/Madrid",
    "iso:country":"ES",
    "name:und_x_variant":[
        "Santa Mar\u00eda",
        "Godones"
    ],
    "wof:name":"Godones",
    "wof:placetype":"locality"
},
  "geometry": {"coordinates":[-8.31667,42.28333],"type":"Point"}
}