{
  "type": "Feature",
  "properties": {
    "gn:admin1_code":"58",
    "gn:admin2_code":"LU",
    "gn:admin3_code":"27055",
    "gn:asciiname":"Portela",
    "gn:country_code":"ES",
    "gn:dem":1181,
    "gn:feature_class":"P",
    "gn:feature_code":"PPL",
    "gn:name":"Portela",
    "gn:population":0,
    "gn:timezone":"Europe/Madrid",
    "iso:country":"ES",
    "name:ceb_x_preferred":[
        "Portela"
    ],
    "name:deu_x_preferred":[
        "Portela"
    ],
    "name:fra_x_preferred":[
        "Portela"
    ],
    "name:glg_x_preferred":[
        "Portela"
    ],
    "name:kaz_x_preferred":[
        "\u041f\u043e\u0440\u0442\u0435\u043b\u0430"
    ],
    "name:nld_x_preferred":[
        "Portela"
    ],
    "name:por_x_preferred":[
        "Portela"
    ],
    "name:rus_x_preferred":[
        "\u041f\u043e\u0440\u0442\u0435\u043b\u0430"
    ],
    "name:spa_x_preferred":[
        "Portela"
    ],
    "name:srp_x_preferred":[
        "Portela"
    ],
    "name:ukr_x_preferred":[
        "\u041f\u043e\u0440\u0442\u0435\u043b\u0430"
    ],
    "wof:name":"Portela",
    "wof:placetype":"locality"
},
  "geometry": {"coordinates":[-7.1937,42.68546],"type":"Point"}
}