{
  "type": "Feature",
  "properties": {
    "gn:country":"ES",
    "gn:fcode":"PPL",
    "gn:population":591,
    "iso:country":"ES",
    "name:ara_x_preferred":[
        "\u0628\u064a\u0646\u0627\u062a\u0627\u064a"
    ],
    "name:ast_x_preferred":[
        "Benatae"
    ],
    "name:azb_x_preferred":[
        "\u0628\u0646\u0627\u062a\u0627\u0626\u0647"
    ],
    "name:cat_x_preferred":[
        "Benatae"
    ],
    "name:epo_x_preferred":[
        "Benatae"
    ],
    "name:eus_x_preferred":[
        "Benatae"
    ],
    "name:fas_x_preferred":[
        "\u0628\u0646\u0627\u062a\u0627\u0626\u0647"
    ],
    "name:fra_x_preferred":[
        "Benatae"
    ],
    "name:hat_x_preferred":[
        "Benatae"
    ],
    "name:hun_x_preferred":[
        "Benatae"
    ],
    "name:hye_x_preferred":[
        "\u0532\u0565\u0576\u0561\u057f\u0561\u0565"
    ],
    "name:ita_x_preferred":[
        "Benatae"
    ],
    "name:msa_x_preferred":[
        "Benatae"
    ],
    "name:nld_x_preferred":[
        "Benatae"
    ],
    "name:oci_x_preferred":[
        "Benatae"
    ],
    "name:pol_x_preferred":[
        "Benatae"
    ],
    "name:por_x_preferred":[
        "Benatae"
    ],
    "name:ron_x_preferred":[
        "Benatae"
    ],
    "name:rus_x_preferred":[
        "\u0411\u0435\u043d\u0430\u0442\u0430\u044d"
    ],
    "name:spa_x_preferred":[
        "Benatae"
    ],
    "name:tur_x_preferred":[
        "Benatae"
    ],
    "name:ukr_x_preferred":[
        "\u0411\u0435\u043d\u0430\u0442\u0430\u0435"
    ],
    "name:und_x_variant":[
        "Caser\u00edo Benalae"
    ],
    "name:uzb_x_preferred":[
        "Benatae"
    ],
    "name:vie_x_preferred":[
        "Benatae"
    ],
    "name:war_x_preferred":[
        "Benatae"
    ],
    "name:zho_x_preferred":[
        "\u8d1d\u7eb3\u6cf0"
    ],
    "qs_pg:aaroncc":"ES",
    "qs_pg:gn_country":"ES",
    "qs_pg:gn_fcode":"PPL",
    "qs_pg:gn_pop":591,
    "qs_pg:name":"Benatae",
    "qs_pg:name_adm0":"Espa\u00f1a",
    "qs_pg:name_adm1":"Andaluc\u00eda",
    "qs_pg:photos_9r":0,
    "qs_pg:photos_sr":0,
    "qs_pg:pop_sr":2,
    "qs_pg:qs_pg_placetype":"locality",
    "qs_pg:qs_pg_placetype_gp":"Town",
    "qs_pg:woe_adm0":23424950,
    "woe:adm0_id":23424950,
    "woe:name_adm0":"Espa\u00f1a",
    "woe:name_adm1":"Andaluc\u00eda",
    "woe:placetype":"Town",
    "wof:name":"Benatae",
    "wof:placetype":"locality",
    "wof:population":591
},
  "geometry": {"coordinates":[-3.13505,38.18897],"type":"Point"}
}