{
  "type": "Feature",
  "properties": {
    "gn:admin1_code":"58",
    "gn:admin2_code":"OR",
    "gn:admin3_code":"32059",
    "gn:asciiname":"Bubal",
    "gn:cc2":"ES",
    "gn:country_code":"ES",
    "gn:dem":621,
    "gn:feature_class":"P",
    "gn:feature_code":"PPL",
    "gn:name":"B\u00fabal",
    "gn:population":0,
    "gn:timezone":"Europe/Madrid",
    "iso:country":"ES",
    "name:und_x_variant":[
        "El Salvador",
        "San Salvador",
        "B\u00fabal"
    ],
    "wof:name":"Bubal",
    "wof:placetype":"locality"
},
  "geometry": {"coordinates":[-7.76667,42.48333],"type":"Point"}
}