{
  "type": "Feature",
  "properties": {
    "gn:admin1_code":"55",
    "gn:admin2_code":"SO",
    "gn:admin3_code":"42163",
    "gn:asciiname":"San Felices",
    "gn:country_code":"ES",
    "gn:dem":940,
    "gn:feature_class":"P",
    "gn:feature_code":"PPLA3",
    "gn:name":"San Felices",
    "gn:population":0,
    "gn:timezone":"Europe/Madrid",
    "iso:country":"ES",
    "wof:name":"San Felices",
    "wof:placetype":"locality"
},
  "geometry": {"coordinates":[-2.02638,41.93708],"type":"Point"}
}