{
  "type": "Feature",
  "properties": {
    "gn:gn_country":"ES",
    "gn:gn_fcode":"PPLA3",
    "gn:gn_pop":280,
    "gn:population":280,
    "iso:country":"ES",
    "name:arg_x_preferred":[
        "Tirgo"
    ],
    "name:arm_x_preferred":[
        "\u054f\u056b\u0580\u0563\u0578"
    ],
    "name:baq_x_preferred":[
        "Tirgo"
    ],
    "name:cat_x_preferred":[
        "Tirgo"
    ],
    "name:chi_x_preferred":[
        "\u8482\u5c14\u6208"
    ],
    "name:dut_x_preferred":[
        "Tirgo"
    ],
    "name:eng_x_preferred":[
        "Tirgo"
    ],
    "name:fre_x_preferred":[
        "Tirgo"
    ],
    "name:ger_x_preferred":[
        "Tirgo"
    ],
    "name:hun_x_preferred":[
        "Tirgo"
    ],
    "name:hye_x_preferred":[
        "\u054f\u056b\u0580\u0563\u0578"
    ],
    "name:ita_x_preferred":[
        "Tirgo"
    ],
    "name:jpn_x_preferred":[
        "\u30c6\u30a3\u30eb\u30b4"
    ],
    "name:kaz_x_preferred":[
        "\u0422\u0438\u0440\u0433\u043e"
    ],
    "name:may_x_preferred":[
        "Tirgo"
    ],
    "name:nan_x_preferred":[
        "Tirgo"
    ],
    "name:oci_x_preferred":[
        "Tirgo"
    ],
    "name:pol_x_preferred":[
        "Tirgo"
    ],
    "name:por_x_preferred":[
        "Tirgo"
    ],
    "name:rup_x_preferred":[
        "Tirgo"
    ],
    "name:rus_x_preferred":[
        "\u0422\u0438\u0440\u0433\u043e"
    ],
    "name:spa_x_preferred":[
        "Tirgo"
    ],
    "name:swe_x_preferred":[
        "Tirgo"
    ],
    "name:ukr_x_preferred":[
        "\u0422\u0456\u0440\u0433\u043e"
    ],
    "name:uzb_x_preferred":[
        "Tirgo"
    ],
    "name:vie_x_preferred":[
        "Tirgo"
    ],
    "name:war_x_preferred":[
        "Tirgo"
    ],
    "name:zho_x_preferred":[
        "\u8482\u5c14\u6208"
    ],
    "qs_pg:aaroncc":"ES",
    "qs_pg:gn_country":"ES",
    "qs_pg:gn_fcode":"PPLA3",
    "qs_pg:gn_pop":280,
    "qs_pg:name":"Tirgo",
    "qs_pg:name_adm0":"Espa\u00f1a",
    "qs_pg:name_adm1":"La Rioja",
    "qs_pg:photos":28,
    "qs_pg:photos_1k":6,
    "qs_pg:photos_9k":1,
    "qs_pg:photos_9r":2,
    "qs_pg:photos_all":28,
    "qs_pg:photos_sr":2,
    "qs_pg:pop_sr":2,
    "qs_pg:qs_pg_placetype":"locality",
    "qs_pg:qs_pg_placetype_gp":"Town",
    "qs_pg:woe_adm0":23424950,
    "woe:adm0_id":23424950,
    "woe:name_adm0":"Espa\u00f1a",
    "woe:name_adm1":"La Rioja",
    "woe:placetype":"Town",
    "wof:name":"Tirgo",
    "wof:placetype":"locality",
    "wof:population":280
},
  "geometry": {"coordinates":[-2.9494,42.54587],"type":"Point"}
}