{
  "type": "Feature",
  "properties": {
    "gn:gn_country":"ES",
    "gn:gn_fcode":"PPLA3",
    "gn:gn_pop":171,
    "gn:population":171,
    "iso:country":"ES",
    "name:cat_x_preferred":[
        "Miguel\u00e1\u00f1ez"
    ],
    "name:eng_x_preferred":[
        "Miguel\u00e1\u00f1ez"
    ],
    "name:eus_x_preferred":[
        "Miguel\u00e1\u00f1ez"
    ],
    "name:fra_x_preferred":[
        "Miguel\u00e1\u00f1ez"
    ],
    "name:hun_x_preferred":[
        "Miguel\u00e1\u00f1ez"
    ],
    "name:ina_x_preferred":[
        "Miguel\u00e1\u00f1ez"
    ],
    "name:ita_x_preferred":[
        "Miguel\u00e1\u00f1ez"
    ],
    "name:msa_x_preferred":[
        "Miguel\u00e1\u00f1ez"
    ],
    "name:nan_x_preferred":[
        "Miguel\u00e1\u00f1ez"
    ],
    "name:nld_x_preferred":[
        "Miguel\u00e1\u00f1ez"
    ],
    "name:oci_x_preferred":[
        "Miguel\u00e1\u00f1ez"
    ],
    "name:pol_x_preferred":[
        "Miguel\u00e1\u00f1ez"
    ],
    "name:por_x_preferred":[
        "Miguel\u00e1\u00f1ez"
    ],
    "name:rus_x_preferred":[
        "\u041c\u0438\u0433\u0435\u043b\u0430\u043d\u044c\u0435\u0441"
    ],
    "name:spa_x_preferred":[
        "Miguel\u00e1\u00f1ez"
    ],
    "name:swe_x_preferred":[
        "Miguel\u00e1\u00f1ez"
    ],
    "name:ukr_x_preferred":[
        "\u041c\u0456\u0433\u0435\u043b\u0430\u043d\u044c\u0454\u0441"
    ],
    "name:vie_x_preferred":[
        "Miguel\u00e1\u00f1ez"
    ],
    "name:war_x_preferred":[
        "Miguel\u00e1\u00f1ez"
    ],
    "name:zho_x_preferred":[
        "\u7c73\u683c\u62c9\u6d85\u65af"
    ],
    "qs_pg:aaroncc":"ES",
    "qs_pg:gn_country":"ES",
    "qs_pg:gn_fcode":"PPLA3",
    "qs_pg:gn_pop":171,
    "qs_pg:name":"Miguel\u00e1\u00f1ez",
    "qs_pg:name_adm0":"Espa\u00f1a",
    "qs_pg:name_adm1":"Castilla y Le\u00f3n",
    "qs_pg:photos":7,
    "qs_pg:photos_1k":1,
    "qs_pg:photos_9k":1,
    "qs_pg:photos_9r":1,
    "qs_pg:photos_all":7,
    "qs_pg:photos_sr":1,
    "qs_pg:pop_sr":1,
    "qs_pg:qs_pg_placetype":"locality",
    "qs_pg:qs_pg_placetype_gp":"Town",
    "qs_pg:woe_adm0":23424950,
    "woe:adm0_id":23424950,
    "woe:name_adm0":"Espa\u00f1a",
    "woe:name_adm1":"Castilla y Le\u00f3n",
    "woe:placetype":"Town",
    "wof:name":"Miguel\u00e1\u00f1ez",
    "wof:placetype":"locality",
    "wof:population":171
},
  "geometry": {"coordinates":[-4.3641,41.12155],"type":"Point"}
}