{
  "type": "Feature",
  "properties": {
    "iso:country":"ES",
    "name:spa_x_preferred":[
        "Urbana Las Palmeras"
    ],
    "name:unk_x_variant":[
        "Urbana Las Palmeras"
    ],
    "qs:gn_adm0_cc":"ES",
    "qs:gn_local":2514256,
    "qs:gn_nam_loc":"M\u00e1laga, M\u00e1laga, M\u00e1laga, Andaluc\u00eda, ES",
    "qs:gn_namadm1":"51",
    "qs:local_max":12916,
    "qs:local_sum":43893,
    "qs:localhoods":40,
    "qs:name":"Urbana Las Palmeras",
    "qs:name_adm0":"Espa\u00f1a",
    "qs:name_adm1":"Andaluc\u00eda",
    "qs:name_adm2":"M\u00e1laga",
    "qs:name_lau":"M\u00e1laga",
    "qs:name_local":"M\u00e1laga",
    "qs:photo_max":154,
    "qs:photo_sum":339,
    "qs:placetype":"Suburb",
    "qs:quad_count":9,
    "qs:woe_adm0":23424950,
    "qs:woe_adm1":12578029,
    "qs:woe_adm2":12602102,
    "qs:woe_lau":12689256,
    "qs:woe_local":766356,
    "qs:woe_ver":"7.10.0",
    "wof:lang":[
        "spa"
    ],
    "wof:name":"Urbana Las Palmeras",
    "wof:placetype":"neighbourhood"
},
  "geometry": {"coordinates":[-4.400741,36.727277],"type":"Point"}
}