{
  "type": "Feature",
  "properties": {
    "gn:admin1_code":"58",
    "gn:admin2_code":"OR",
    "gn:admin3_code":"32052",
    "gn:asciiname":"Vinoas",
    "gn:country_code":"ES",
    "gn:dem":341,
    "gn:feature_class":"P",
    "gn:feature_code":"PPL",
    "gn:name":"Vi\u00f1o\u00e1s",
    "gn:population":0,
    "gn:timezone":"Europe/Madrid",
    "iso:country":"ES",
    "name:und_x_variant":[
        "Vi\u00f1o\u00e1s"
    ],
    "wof:name":"Vinoas",
    "wof:placetype":"locality"
},
  "geometry": {"coordinates":[-7.74118,42.42749],"type":"Point"}
}