{
  "type": "Feature",
  "properties": {
    "gn:admin1_code":"60",
    "gn:admin2_code":"V",
    "gn:admin3_code":"46106",
    "gn:asciiname":"Villar de Tejas",
    "gn:country_code":"ES",
    "gn:dem":906,
    "gn:feature_class":"P",
    "gn:feature_code":"PPL",
    "gn:name":"Villar de Tejas",
    "gn:population":0,
    "gn:timezone":"Europe/Madrid",
    "iso:country":"ES",
    "wof:name":"Villar de Tejas",
    "wof:placetype":"locality"
},
  "geometry": {"coordinates":[-1.08333,39.63333],"type":"Point"}
}