{
  "type": "Feature",
  "properties": {
    "gn:admin1_code":"53",
    "gn:admin2_code":"TF",
    "gn:admin3_code":"38032",
    "gn:asciiname":"San Isidro",
    "gn:country_code":"ES",
    "gn:dem":277,
    "gn:feature_class":"P",
    "gn:feature_code":"PPL",
    "gn:name":"San Isidro",
    "gn:population":0,
    "gn:timezone":"Atlantic/Canary",
    "iso:country":"ES",
    "wof:name":"San Isidro",
    "wof:placetype":"locality"
},
  "geometry": {"coordinates":[-16.31958,28.41575],"type":"Point"}
}