{
  "type": "Feature",
  "properties": {
    "gn:admin1_code":"31",
    "gn:admin2_code":"MU",
    "gn:admin3_code":"30024",
    "gn:asciiname":"Los Raspajos",
    "gn:country_code":"ES",
    "gn:dem":501,
    "gn:feature_class":"P",
    "gn:feature_code":"PPL",
    "gn:name":"Los Raspajos",
    "gn:population":0,
    "gn:timezone":"Europe/Madrid",
    "iso:country":"ES",
    "name:und_x_variant":[
        "Cortijo de los Raspajos",
        "Caser\u00edo Los Raspajos",
        "Los Raspajos"
    ],
    "wof:name":"Los Raspajos",
    "wof:placetype":"locality"
},
  "geometry": {"coordinates":[-1.73585,37.7655],"type":"Point"}
}