{
  "type": "Feature",
  "properties": {
    "gn:gn_country":"ES",
    "gn:gn_fcode":"PPL",
    "gn:gn_pop":12766,
    "gn:population":12766,
    "iso:country":"ES",
    "name:ara_x_preferred":[
        "\u0644\u0627 \u0628\u0648\u064a\u0628\u0644\u0627"
    ],
    "name:arg_x_preferred":[
        "Sa Pobla"
    ],
    "name:ast_x_preferred":[
        "Poblar"
    ],
    "name:cat_x_preferred":[
        "sa Pobla"
    ],
    "name:cat_x_variant":[
        "la Pobla"
    ],
    "name:ceb_x_preferred":[
        "Sa Pobla"
    ],
    "name:deu_x_preferred":[
        "sa Pobla"
    ],
    "name:deu_x_variant":[
        "Sa Pobla"
    ],
    "name:eng_x_preferred":[
        "sa Pobla"
    ],
    "name:eng_x_variant":[
        "Sa Pobla"
    ],
    "name:eus_x_preferred":[
        "Sa Pobla"
    ],
    "name:fra_x_preferred":[
        "Sa Pobla"
    ],
    "name:glg_x_preferred":[
        "Sa Pobla"
    ],
    "name:hun_x_preferred":[
        "Sa Pobla"
    ],
    "name:ita_x_preferred":[
        "sa Pobla"
    ],
    "name:ita_x_variant":[
        "Sa Pobla"
    ],
    "name:jpn_x_preferred":[
        "\u30b5\u30fb\u30dd\u30d6\u30e9"
    ],
    "name:lit_x_preferred":[
        "Sa Pablo"
    ],
    "name:msa_x_preferred":[
        "Sa Pobla"
    ],
    "name:nld_x_preferred":[
        "sa Pobla"
    ],
    "name:nld_x_variant":[
        "Sa Pobla"
    ],
    "name:oci_x_preferred":[
        "Sa Pobla"
    ],
    "name:pol_x_preferred":[
        "Sa Pobla"
    ],
    "name:por_x_preferred":[
        "sa Pobla"
    ],
    "name:por_x_variant":[
        "Sa Pobla"
    ],
    "name:rus_x_preferred":[
        "\u0421\u0430 \u041f\u043e\u0431\u043b\u0430"
    ],
    "name:spa_x_preferred":[
        "sa Pobla"
    ],
    "name:spa_x_variant":[
        "La Puebla"
    ],
    "name:sqi_x_preferred":[
        "Sa Pobla"
    ],
    "name:srd_x_preferred":[
        "Sa Pobla"
    ],
    "name:swe_x_preferred":[
        "Sa Pobla"
    ],
    "name:tur_x_preferred":[
        "sa Pobla"
    ],
    "name:tur_x_variant":[
        "Sa Pobla"
    ],
    "name:urd_x_preferred":[
        "\u0633\u0627 \u067e\u0648\u0628\u0644\u0627"
    ],
    "name:vie_x_preferred":[
        "Sa Pobla"
    ],
    "name:war_x_preferred":[
        "Sa Pobla"
    ],
    "name:zho_x_preferred":[
        "\u8428\u6ce2\u592b\u62c9"
    ],
    "qs_pg:aaroncc":"ES",
    "qs_pg:gn_country":"ES",
    "qs_pg:gn_fcode":"PPL",
    "qs_pg:gn_pop":12766,
    "qs_pg:name":"Sa Mola",
    "qs_pg:name_adm0":"Espa\u00f1a",
    "qs_pg:name_adm1":"Illes Balears",
    "qs_pg:photos_9r":0,
    "qs_pg:photos_sr":0,
    "qs_pg:pop_sr":6,
    "qs_pg:qs_pg_placetype":"locality",
    "qs_pg:qs_pg_placetype_gp":"Town",
    "qs_pg:woe_adm0":23424950,
    "woe:adm0_id":23424950,
    "woe:name_adm0":"Espa\u00f1a",
    "woe:name_adm1":"Illes Balears",
    "woe:placetype":"Town",
    "wof:name":"Sa Mola",
    "wof:placetype":"locality",
    "wof:population":12766
},
  "geometry": {"coordinates":[3.02394,39.7692],"type":"Point"}
}