{
  "type": "Feature",
  "properties": {
    "gn:gn_country":"ES",
    "gn:gn_fcode":"PPL",
    "gn:gn_pop":3303,
    "gn:population":3303,
    "iso:country":"ES",
    "name:ara_x_preferred":[
        "\u0641\u0627\u064a\u0631\u0645\u0648\u0633\u0648\u060c \u0633\u0627\u0646\u062a\u0627 \u0643\u0631\u0648\u062b \u062f\u064a \u062a\u064a\u0646\u064a\u0631\u064a\u0641\u0647"
    ],
    "name:baq_x_preferred":[
        "Vallehermoso"
    ],
    "name:bul_x_preferred":[
        "\u0412\u0430\u043b\u0435\u0445\u0435\u0440\u043c\u043e\u0441\u0430"
    ],
    "name:cat_x_preferred":[
        "Vallehermoso"
    ],
    "name:chi_x_preferred":[
        "\u5df4\u5217\u57c3\u5c14\u83ab\u7d22"
    ],
    "name:deu_x_preferred":[
        "Vallehermoso"
    ],
    "name:dut_x_preferred":[
        "Vallehermoso"
    ],
    "name:eng_x_preferred":[
        "Vallehermoso"
    ],
    "name:epo_x_preferred":[
        "Vallehermoso"
    ],
    "name:fra_x_preferred":[
        "Vallehermoso"
    ],
    "name:fre_x_preferred":[
        "Vallehermoso"
    ],
    "name:ger_x_preferred":[
        "Vallehermoso"
    ],
    "name:glg_x_preferred":[
        "Vallehermoso"
    ],
    "name:hun_x_preferred":[
        "Vallehermoso"
    ],
    "name:ita_x_preferred":[
        "Vallehermoso"
    ],
    "name:lat_x_preferred":[
        "Vallehermoso"
    ],
    "name:lit_x_preferred":[
        "Valjehermosas"
    ],
    "name:ltz_x_preferred":[
        "Vallehermoso"
    ],
    "name:may_x_preferred":[
        "Vallehermoso"
    ],
    "name:nld_x_preferred":[
        "Vallehermoso"
    ],
    "name:oci_x_preferred":[
        "Vallehermoso"
    ],
    "name:pol_x_preferred":[
        "Vallehermoso"
    ],
    "name:por_x_preferred":[
        "Vallehermoso"
    ],
    "name:rus_x_preferred":[
        "\u0412\u0430\u043b\u044c\u0435\u044d\u0440\u043c\u043e\u0441\u043e"
    ],
    "name:spa_x_preferred":[
        "Vallehermoso"
    ],
    "name:swe_x_preferred":[
        "Vallehermosa"
    ],
    "name:ukr_x_preferred":[
        "\u0412\u0430\u043b\u044c\u0454\u0435\u0440\u043c\u043e\u0441\u043e"
    ],
    "name:unk_x_variant":[
        "Vallehermosa"
    ],
    "name:uzb_x_preferred":[
        "Vallehermoso"
    ],
    "name:war_x_preferred":[
        "Vallehermoso"
    ],
    "qs_pg:aaroncc":"ES",
    "qs_pg:gn_country":"ES",
    "qs_pg:gn_fcode":"PPL",
    "qs_pg:gn_pop":3303,
    "qs_pg:name":"Vallehermoso",
    "qs_pg:name_adm0":"Espa\u00f1a",
    "qs_pg:name_adm1":"Islas Canarias",
    "qs_pg:photos":512,
    "qs_pg:photos_1k":104,
    "qs_pg:photos_9k":2,
    "qs_pg:photos_9r":5,
    "qs_pg:photos_all":512,
    "qs_pg:photos_sr":7,
    "qs_pg:pop_sr":4,
    "qs_pg:qs_pg_placetype":"locality",
    "qs_pg:qs_pg_placetype_gp":"Town",
    "qs_pg:woe_adm0":23424950,
    "woe:adm0_id":23424950,
    "woe:name_adm0":"Espa\u00f1a",
    "woe:name_adm1":"Islas Canarias",
    "woe:placetype":"Town",
    "wof:name":"Vallehermoso",
    "wof:placetype":"locality",
    "wof:population":3303
},
  "geometry": {"coordinates":[-17.26664,28.17944],"type":"Point"}
}