{
  "type": "Feature",
  "properties": {
    "iso:country":"ES",
    "name:eng_x_preferred":[
        "La Luz"
    ],
    "name:spa_x_preferred":[
        "La Luz"
    ],
    "wof:name":"La Luz",
    "wof:placetype":"neighbourhood"
},
  "geometry": {"coordinates":[-4.45451457758507,36.69674942536133],"type":"Point"}
}