{
  "type": "Feature",
  "properties": {
    "gn:admin1_code":"58",
    "gn:admin2_code":"PO",
    "gn:admin3_code":"36042",
    "gn:asciiname":"Cristinade",
    "gn:cc2":"ES",
    "gn:country_code":"ES",
    "gn:dem":24,
    "gn:feature_class":"P",
    "gn:feature_code":"PPL",
    "gn:name":"Cristi\u00f1ade",
    "gn:population":0,
    "gn:timezone":"Europe/Madrid",
    "iso:country":"ES",
    "name:und_x_variant":[
        "San Salvador",
        "Cristi\u00f1ade"
    ],
    "wof:name":"Cristinade",
    "wof:placetype":"locality"
},
  "geometry": {"coordinates":[-8.51667,42.15],"type":"Point"}
}