{
  "type": "Feature",
  "properties": {
    "gn:country":"ES",
    "gn:fcode":"PPLA3",
    "gn:population":425,
    "iso:country":"ES",
    "name:ara_x_preferred":[
        "\u0643\u0648\u0631\u0627\u0644-\u0631\u0648\u0628\u064a\u0648"
    ],
    "name:arg_x_preferred":[
        "Corral-Rubio"
    ],
    "name:ast_x_preferred":[
        "Corral-Rubio"
    ],
    "name:azb_x_preferred":[
        "\u06a9\u0631\u0627\u0644-\u0631\u0648\u0628\u06cc\u0648"
    ],
    "name:cat_x_preferred":[
        "Corral-Rubio"
    ],
    "name:ceb_x_preferred":[
        "Corral-Rubio"
    ],
    "name:eng_x_preferred":[
        "Corral-Rubio"
    ],
    "name:eus_x_preferred":[
        "Corral-Rubio"
    ],
    "name:fas_x_preferred":[
        "\u06a9\u0631\u0627\u0644-\u0631\u0648\u0628\u06cc\u0648"
    ],
    "name:fra_x_preferred":[
        "Corral-Rubio"
    ],
    "name:hun_x_preferred":[
        "Corral-Rubio"
    ],
    "name:ina_x_preferred":[
        "Corral-Rubio"
    ],
    "name:ita_x_preferred":[
        "Corral-Rubio"
    ],
    "name:msa_x_preferred":[
        "Corral-Rubio"
    ],
    "name:nan_x_preferred":[
        "Corral-Rubio"
    ],
    "name:nld_x_preferred":[
        "Corral-Rubio"
    ],
    "name:oci_x_preferred":[
        "Corral-Rubio"
    ],
    "name:pam_x_preferred":[
        "Corral-Rubio"
    ],
    "name:pol_x_preferred":[
        "Corral-Rubio"
    ],
    "name:por_x_preferred":[
        "Corral-Rubio"
    ],
    "name:ron_x_preferred":[
        "Corral-Rubio"
    ],
    "name:rus_x_preferred":[
        "\u041a\u043e\u0440\u0440\u0430\u043b\u044c-\u0420\u0443\u0431\u0438\u043e"
    ],
    "name:spa_x_preferred":[
        "Corral-Rubio"
    ],
    "name:swe_x_preferred":[
        "Corral-Rubio"
    ],
    "name:ukr_x_preferred":[
        "\u041a\u043e\u0440\u0440\u0430\u043b\u044c-\u0420\u0443\u0431\u0456\u043e"
    ],
    "name:vie_x_preferred":[
        "Corral-Rubio"
    ],
    "name:war_x_preferred":[
        "Corral-Rubio"
    ],
    "name:zho_x_preferred":[
        "\u79d1\u62c9\u5c14-\u9c81\u7ef4\u5965"
    ],
    "qs_pg:aaroncc":"ES",
    "qs_pg:gn_country":"ES",
    "qs_pg:gn_fcode":"PPLA3",
    "qs_pg:gn_pop":425,
    "qs_pg:name":"Corral-Rubio",
    "qs_pg:name_adm0":"Espa\u00f1a",
    "qs_pg:name_adm1":"Castilla-La Mancha",
    "qs_pg:photos":16,
    "qs_pg:photos_1k":3,
    "qs_pg:photos_9k":1,
    "qs_pg:photos_9r":1,
    "qs_pg:photos_all":16,
    "qs_pg:photos_sr":1,
    "qs_pg:pop_sr":2,
    "qs_pg:qs_pg_placetype":"locality",
    "qs_pg:qs_pg_placetype_gp":"Town",
    "qs_pg:woe_adm0":23424950,
    "woe:adm0_id":23424950,
    "woe:name_adm0":"Espa\u00f1a",
    "woe:name_adm1":"Castilla-La Mancha",
    "woe:placetype":"Town",
    "wof:name":"Corral-Rubio",
    "wof:placetype":"locality",
    "wof:population":425
},
  "geometry": {"coordinates":[-1.46034,38.83462],"type":"Point"}
}