{
  "type": "Feature",
  "properties": {
    "gn:admin1_code":"59",
    "gn:admin2_code":"VI",
    "gn:admin3_code":"01009",
    "gn:asciiname":"Ilarduya",
    "gn:country_code":"ES",
    "gn:dem":577,
    "gn:feature_class":"P",
    "gn:feature_code":"PPL",
    "gn:name":"Ilarduia",
    "gn:population":0,
    "gn:timezone":"Europe/Madrid",
    "iso:country":"ES",
    "wof:name":"Ilarduya",
    "wof:placetype":"locality"
},
  "geometry": {"coordinates":[-2.28567,42.87219],"type":"Point"}
}