{
  "type": "Feature",
  "properties": {
    "gn:admin1_code":"58",
    "gn:admin2_code":"LU",
    "gn:admin3_code":"27029",
    "gn:asciiname":"Grananova",
    "gn:country_code":"ES",
    "gn:dem":559,
    "gn:feature_class":"P",
    "gn:feature_code":"PPL",
    "gn:name":"Gra\u00f1anova",
    "gn:population":0,
    "gn:timezone":"Europe/Madrid",
    "iso:country":"ES",
    "wof:name":"Grananova",
    "wof:placetype":"locality"
},
  "geometry": {"coordinates":[-7.26971,43.21961],"type":"Point"}
}