{
  "type": "Feature",
  "properties": {
    "gn:admin1_code":"34",
    "gn:admin2_code":"O",
    "gn:admin3_code":"33012",
    "gn:asciiname":"Parda",
    "gn:country_code":"ES",
    "gn:dem":220,
    "gn:feature_class":"P",
    "gn:feature_code":"PPL",
    "gn:name":"Parda",
    "gn:population":0,
    "gn:timezone":"Europe/Madrid",
    "iso:country":"ES",
    "name:uzb_x_preferred":[
        "Parda"
    ],
    "wof:name":"Parda",
    "wof:placetype":"locality"
},
  "geometry": {"coordinates":[-5.10323,43.3798],"type":"Point"}
}