{
  "type": "Feature",
  "properties": {
    "gn:admin1_code":"58",
    "gn:admin2_code":"OR",
    "gn:admin3_code":"32059",
    "gn:asciiname":"Gueral",
    "gn:cc2":"ES",
    "gn:country_code":"ES",
    "gn:dem":454,
    "gn:feature_class":"P",
    "gn:feature_code":"PPL",
    "gn:name":"Gueral",
    "gn:population":0,
    "gn:timezone":"Europe/Madrid",
    "iso:country":"ES",
    "name:und_x_variant":[
        "San Mart\u00edn"
    ],
    "wof:name":"Gueral",
    "wof:placetype":"locality"
},
  "geometry": {"coordinates":[-7.83634,42.44259],"type":"Point"}
}