{
  "type": "Feature",
  "properties": {
    "gn:gn_country":"ES",
    "gn:gn_fcode":"PPLA3",
    "gn:gn_pop":1697,
    "gn:population":1697,
    "iso:country":"ES",
    "name:alb_x_preferred":[
        "Alcauc\u00edn"
    ],
    "name:ara_x_preferred":[
        "\u0623\u0644\u0643\u0627\u0648\u062b\u064a\u0646"
    ],
    "name:arm_x_preferred":[
        "\u0531\u056c\u056f\u0561\u0578\u0582\u057d\u056b\u0576"
    ],
    "name:baq_x_preferred":[
        "Alcauc\u00edn"
    ],
    "name:cat_x_preferred":[
        "Alcauc\u00edn"
    ],
    "name:chi_x_preferred":[
        "\u963f\u5c14\u8003\u8f9b"
    ],
    "name:dut_x_preferred":[
        "Alcauc\u00edn"
    ],
    "name:eng_x_preferred":[
        "Alcauc\u00edn"
    ],
    "name:fre_x_preferred":[
        "Alcauc\u00edn"
    ],
    "name:ger_x_preferred":[
        "Alcauc\u00edn"
    ],
    "name:hat_x_preferred":[
        "Alcaucin"
    ],
    "name:hun_x_preferred":[
        "Alcauc\u00edn"
    ],
    "name:ita_x_preferred":[
        "Alcauc\u00edn"
    ],
    "name:kaz_x_preferred":[
        "\u0410\u043b\u044c\u043a\u0430\u0443\u0441\u0438\u043d"
    ],
    "name:kon_x_preferred":[
        "Alcauc\u00edn"
    ],
    "name:may_x_preferred":[
        "Alcauc\u00edn"
    ],
    "name:nan_x_preferred":[
        "Alcauc\u00edn"
    ],
    "name:oci_x_preferred":[
        "Alcauc\u00edn"
    ],
    "name:per_x_preferred":[
        "\u0627\u0644\u06a9\u0627\u0648\u0633\u06cc\u0646"
    ],
    "name:pol_x_preferred":[
        "Alcauc\u00edn"
    ],
    "name:por_x_preferred":[
        "Alcauc\u00edn"
    ],
    "name:rus_x_preferred":[
        "\u0410\u043b\u044c\u043a\u0430\u0443\u0441\u0438\u043d"
    ],
    "name:spa_x_preferred":[
        "Alcauc\u00edn"
    ],
    "name:swe_x_preferred":[
        "Alcauc\u00edn"
    ],
    "name:ukr_x_preferred":[
        "\u0410\u043b\u044c\u043a\u0430\u0443\u0441\u0456\u043d"
    ],
    "name:uzb_x_preferred":[
        "Alcauc\u00edn"
    ],
    "name:vie_x_preferred":[
        "Alcauc\u00edn"
    ],
    "name:war_x_preferred":[
        "Alcauc\u00edn"
    ],
    "qs_pg:aaroncc":"ES",
    "qs_pg:gn_country":"ES",
    "qs_pg:gn_fcode":"PPLA3",
    "qs_pg:gn_pop":1697,
    "qs_pg:name":"Alcauc\u00edn",
    "qs_pg:name_adm0":"Espa\u00f1a",
    "qs_pg:name_adm1":"Andaluc\u00eda",
    "qs_pg:photos":157,
    "qs_pg:photos_1k":32,
    "qs_pg:photos_9k":1,
    "qs_pg:photos_9r":4,
    "qs_pg:photos_all":157,
    "qs_pg:photos_sr":4,
    "qs_pg:pop_sr":3,
    "qs_pg:qs_pg_placetype":"locality",
    "qs_pg:qs_pg_placetype_gp":"Town",
    "qs_pg:woe_adm0":23424950,
    "woe:adm0_id":23424950,
    "woe:name_adm0":"Espa\u00f1a",
    "woe:name_adm1":"Andaluc\u00eda",
    "woe:placetype":"Town",
    "wof:name":"Alcauc\u00edn",
    "wof:placetype":"locality",
    "wof:population":1697
},
  "geometry": {"coordinates":[-4.11406,36.90301],"type":"Point"}
}