{
  "type": "Feature",
  "properties": {
    "gn:admin1_code":"58",
    "gn:admin2_code":"PO",
    "gn:admin3_code":"36020",
    "gn:asciiname":"Ramil",
    "gn:country_code":"ES",
    "gn:dem":344,
    "gn:feature_class":"P",
    "gn:feature_code":"PPL",
    "gn:name":"Ramil",
    "gn:population":0,
    "gn:timezone":"Europe/Madrid",
    "iso:country":"ES",
    "name:rus_x_preferred":[
        "\u0420\u0430\u043c\u0438\u043b\u044c"
    ],
    "wof:name":"Ramil",
    "wof:placetype":"locality"
},
  "geometry": {"coordinates":[-7.96667,42.85],"type":"Point"}
}