{
  "type": "Feature",
  "properties": {
    "gn:admin1_code":"55",
    "gn:admin2_code":"BU",
    "gn:admin3_code":"09429",
    "gn:asciiname":"Villaescusa la Solana",
    "gn:country_code":"ES",
    "gn:dem":915,
    "gn:feature_class":"P",
    "gn:feature_code":"PPL",
    "gn:name":"Villaescusa la Solana",
    "gn:population":0,
    "gn:timezone":"Europe/Madrid",
    "iso:country":"ES",
    "wof:name":"Villaescusa la Solana",
    "wof:placetype":"locality"
},
  "geometry": {"coordinates":[-3.42008,42.42636],"type":"Point"}
}