{
  "type": "Feature",
  "properties": {
    "gn:admin1_code":"58",
    "gn:admin2_code":"OR",
    "gn:admin3_code":"32059",
    "gn:asciiname":"Carracedo",
    "gn:country_code":"ES",
    "gn:dem":348,
    "gn:feature_class":"P",
    "gn:feature_code":"PPL",
    "gn:name":"Carracedo",
    "gn:population":0,
    "gn:timezone":"Europe/Madrid",
    "iso:country":"ES",
    "wof:name":"Carracedo",
    "wof:placetype":"locality"
},
  "geometry": {"coordinates":[-7.76848,42.43285],"type":"Point"}
}