{
  "type": "Feature",
  "properties": {
    "gn:admin1_code":"54",
    "gn:admin2_code":"GU",
    "gn:admin3_code":"19099",
    "gn:asciiname":"Cuevas Minadas",
    "gn:country_code":"ES",
    "gn:dem":991,
    "gn:feature_class":"P",
    "gn:feature_code":"PPL",
    "gn:name":"Cuevas Minadas",
    "gn:population":0,
    "gn:timezone":"Europe/Madrid",
    "iso:country":"ES",
    "wof:name":"Cuevas Minadas",
    "wof:placetype":"locality"
},
  "geometry": {"coordinates":[-2.0292,40.80054000000001],"type":"Point"}
}