{
  "type": "Feature",
  "properties": {
    "gn:admin1_code":"55",
    "gn:admin2_code":"LE",
    "gn:admin3_code":"24152",
    "gn:asciiname":"Valdemanzanas",
    "gn:country_code":"ES",
    "gn:dem":1108,
    "gn:feature_class":"P",
    "gn:feature_code":"PPL",
    "gn:name":"Valdemanzanas",
    "gn:population":0,
    "gn:timezone":"Europe/Madrid",
    "iso:country":"ES",
    "wof:name":"Valdemanzanas",
    "wof:placetype":"locality"
},
  "geometry": {"coordinates":[-6.2851,42.43544],"type":"Point"}
}