{
  "type": "Feature",
  "properties": {
    "gn:admin1_code":"39",
    "gn:admin2_code":"S",
    "gn:admin3_code":"39047",
    "gn:asciiname":"Cabanzo",
    "gn:country_code":"ES",
    "gn:dem":19,
    "gn:feature_class":"P",
    "gn:feature_code":"PPL",
    "gn:name":"Cabanzo",
    "gn:population":0,
    "gn:timezone":"Europe/Madrid",
    "iso:country":"ES",
    "wof:name":"Cabanzo",
    "wof:placetype":"locality"
},
  "geometry": {"coordinates":[-3.5258,43.47349000000001],"type":"Point"}
}