{
  "type": "Feature",
  "properties": {
    "gn:admin1_code":"34",
    "gn:admin2_code":"O",
    "gn:admin3_code":"33051",
    "gn:asciiname":"Bances",
    "gn:country_code":"ES",
    "gn:dem":61,
    "gn:feature_class":"P",
    "gn:feature_code":"PPL",
    "gn:name":"Bances",
    "gn:population":0,
    "gn:timezone":"Europe/Madrid",
    "iso:country":"ES",
    "wof:name":"Bances",
    "wof:placetype":"locality"
},
  "geometry": {"coordinates":[-6.11236,43.50215],"type":"Point"}
}