{
  "type": "Feature",
  "properties": {
    "gn:admin1_code":"39",
    "gn:admin2_code":"S",
    "gn:admin3_code":"39092",
    "gn:asciiname":"La Cuadra",
    "gn:country_code":"ES",
    "gn:dem":953,
    "gn:feature_class":"P",
    "gn:feature_code":"PPL",
    "gn:name":"La Cuadra",
    "gn:population":0,
    "gn:timezone":"Europe/Madrid",
    "iso:country":"ES",
    "wof:name":"La Cuadra",
    "wof:placetype":"locality"
},
  "geometry": {"coordinates":[-4.19524,42.89937000000001],"type":"Point"}
}