{
  "type": "Feature",
  "properties": {
    "gn:admin1_code":"56",
    "gn:admin2_code":"GI",
    "gn:admin3_code":"17031",
    "gn:asciiname":"Sant Marti Sesserres",
    "gn:cc2":"ES",
    "gn:country_code":"ES",
    "gn:dem":337,
    "gn:feature_class":"P",
    "gn:feature_code":"PPL",
    "gn:name":"Sant Mart\u00ed Sesserres",
    "gn:population":0,
    "gn:timezone":"Europe/Madrid",
    "iso:country":"ES",
    "name:cat_x_preferred":[
        "Sant Mart\u00ed Sesserres"
    ],
    "wof:name":"Sant Marti Sesserres",
    "wof:placetype":"locality"
},
  "geometry": {"coordinates":[2.77443,42.25991],"type":"Point"}
}