{
  "type": "Feature",
  "properties": {
    "gn:gn_country":"ES",
    "gn:gn_fcode":"PPLA3",
    "gn:gn_pop":194,
    "gn:population":194,
    "iso:country":"ES",
    "name:arg_x_preferred":[
        "Bogajo"
    ],
    "name:arm_x_preferred":[
        "\u0532\u0578\u0563\u0561\u056d\u0578"
    ],
    "name:ast_x_preferred":[
        "Bogayu"
    ],
    "name:baq_x_preferred":[
        "Bogajo"
    ],
    "name:cat_x_preferred":[
        "Bogajo"
    ],
    "name:chi_x_preferred":[
        "\u535a\u52a0\u970d"
    ],
    "name:dut_x_preferred":[
        "Bogajo"
    ],
    "name:eng_x_preferred":[
        "Bogajo"
    ],
    "name:fre_x_preferred":[
        "Bogajo"
    ],
    "name:ger_x_preferred":[
        "Bogajo"
    ],
    "name:haw_x_preferred":[
        "Bogajo"
    ],
    "name:hun_x_preferred":[
        "Bogajo"
    ],
    "name:ina_x_preferred":[
        "Bogajo"
    ],
    "name:ita_x_preferred":[
        "Bogajo"
    ],
    "name:kaz_x_preferred":[
        "\u0411\u043e\u0433\u0430\u0445\u043e"
    ],
    "name:may_x_preferred":[
        "Bogajo"
    ],
    "name:nan_x_preferred":[
        "Bogajo"
    ],
    "name:oci_x_preferred":[
        "Bogajo"
    ],
    "name:pol_x_preferred":[
        "Bogajo"
    ],
    "name:por_x_preferred":[
        "Bogajo"
    ],
    "name:rus_x_preferred":[
        "\u0411\u043e\u0433\u0430\u0445\u043e"
    ],
    "name:spa_x_preferred":[
        "Bogajo"
    ],
    "name:swe_x_preferred":[
        "Bogajo"
    ],
    "name:ukr_x_preferred":[
        "\u0411\u043e\u0433\u0430\u0445\u043e"
    ],
    "name:uzb_x_preferred":[
        "Bogajo"
    ],
    "name:vie_x_preferred":[
        "Bogajo"
    ],
    "name:war_x_preferred":[
        "Bogajo"
    ],
    "qs_pg:aaroncc":"ES",
    "qs_pg:gn_country":"ES",
    "qs_pg:gn_fcode":"PPLA3",
    "qs_pg:gn_pop":194,
    "qs_pg:name":"Bogajo",
    "qs_pg:name_adm0":"Espa\u00f1a",
    "qs_pg:name_adm1":"Castilla y Le\u00f3n",
    "qs_pg:photos":30,
    "qs_pg:photos_1k":6,
    "qs_pg:photos_9k":1,
    "qs_pg:photos_9r":2,
    "qs_pg:photos_all":30,
    "qs_pg:photos_sr":2,
    "qs_pg:pop_sr":1,
    "qs_pg:qs_pg_placetype":"locality",
    "qs_pg:qs_pg_placetype_gp":"Town",
    "qs_pg:woe_adm0":23424950,
    "woe:adm0_id":23424950,
    "woe:name_adm0":"Espa\u00f1a",
    "woe:name_adm1":"Castilla y Le\u00f3n",
    "woe:placetype":"Town",
    "wof:name":"Bogajo",
    "wof:placetype":"locality",
    "wof:population":194
},
  "geometry": {"coordinates":[-6.53065,40.9071],"type":"Point"}
}