{
  "type": "Feature",
  "properties": {
    "gn:admin1_code":"54",
    "gn:admin2_code":"AB",
    "gn:admin3_code":"02072",
    "gn:asciiname":"Canada Buendia",
    "gn:country_code":"ES",
    "gn:dem":629,
    "gn:feature_class":"P",
    "gn:feature_code":"PPL",
    "gn:name":"Ca\u00f1ada Buend\u00eda",
    "gn:population":0,
    "gn:timezone":"Europe/Madrid",
    "iso:country":"ES",
    "wof:name":"Canada Buendia",
    "wof:placetype":"locality"
},
  "geometry": {"coordinates":[-1.88222,38.32705],"type":"Point"}
}