{
  "type": "Feature",
  "properties": {
    "gn:admin1_code":"56",
    "gn:admin2_code":"B",
    "gn:admin3_code":"08299",
    "gn:asciiname":"Castell de l'Areny",
    "gn:country_code":"ES",
    "gn:dem":938,
    "gn:feature_class":"P",
    "gn:feature_code":"PPL",
    "gn:name":"Castell de l'Areny",
    "gn:population":0,
    "gn:timezone":"Europe/Madrid",
    "iso:country":"ES",
    "name:ara_x_preferred":[
        "\u0643\u0627\u0633\u062a\u064a\u0644 \u062f\u064a \u0623\u0631\u064a\u0646\u064a"
    ],
    "name:ast_x_preferred":[
        "Castell del Areny"
    ],
    "name:cat_x_preferred":[
        "Castell de l'Areny"
    ],
    "name:fas_x_preferred":[
        "\u06a9\u0627\u0633\u062a\u06cc \u062f \u0644\u0627 \u0622\u0631\u0646\u06cc"
    ],
    "name:spa_x_preferred":[
        "Castell del Areny"
    ],
    "name:ukr_x_preferred":[
        "\u041a\u0430\u0441\u0442\u0435\u043b\u044c-\u0434\u0430-\u043b'\u0410\u0440\u0435\u043d\u044c"
    ],
    "name:zho_x_preferred":[
        "\u963f\u96f7\u5c3c\u5821"
    ],
    "wof:name":"Castell de l'Areny",
    "wof:placetype":"locality"
},
  "geometry": {"coordinates":[1.94529,42.17291],"type":"Point"}
}