{
  "type": "Feature",
  "properties": {
    "gn:admin1_code":"56",
    "gn:admin2_code":"B",
    "gn:admin3_code":"08299",
    "gn:asciiname":"Castell de l'Areny",
    "gn:country_code":"ES",
    "gn:dem":938,
    "gn:feature_class":"P",
    "gn:feature_code":"PPL",
    "gn:name":"Castell de l'Areny",
    "gn:population":0,
    "gn:timezone":"Europe/Madrid",
    "iso:country":"ES",
    "name:cat_x_preferred":[
        "Castell de l'Areny"
    ],
    "name:spa_x_preferred":[
        "Castell del Areny"
    ],
    "wof:name":"Castell de l'Areny",
    "wof:placetype":"locality"
},
  "geometry": {"coordinates":[1.94529,42.17291],"type":"Point"}
}