{
  "type": "Feature",
  "properties": {
    "gn:admin1_code":"55",
    "gn:admin2_code":"ZA",
    "gn:admin3_code":"49071",
    "gn:asciiname":"Fornillos de Aliste",
    "gn:country_code":"ES",
    "gn:dem":803,
    "gn:feature_class":"P",
    "gn:feature_code":"PPL",
    "gn:name":"Fornillos de Aliste",
    "gn:population":0,
    "gn:timezone":"Europe/Madrid",
    "iso:country":"ES",
    "name:und_x_variant":[
        "Fornillos",
        "Fornillos de Aliste"
    ],
    "wof:name":"Fornillos de Aliste",
    "wof:placetype":"locality"
},
  "geometry": {"coordinates":[-6.19139,41.65642],"type":"Point"}
}