{
  "type": "Feature",
  "properties": {
    "gn:admin1_code":"59",
    "gn:admin2_code":"BI",
    "gn:admin3_code":"48019",
    "gn:asciiname":"Sarria-Ausonia",
    "gn:country_code":"ES",
    "gn:dem":278,
    "gn:feature_class":"P",
    "gn:feature_code":"PPL",
    "gn:name":"Sarria",
    "gn:population":0,
    "gn:timezone":"Europe/Madrid",
    "iso:country":"ES",
    "name:und_x_variant":[
        "Sarria",
        "Sarr\u00eda-Ausonia"
    ],
    "wof:name":"Sarria-Ausonia",
    "wof:placetype":"locality"
},
  "geometry": {"coordinates":[-2.59572,43.19022],"type":"Point"}
}