{
  "type": "Feature",
  "properties": {
    "iso:country":"ES",
    "name:spa_x_preferred":[
        "Jard\u00edn Este"
    ],
    "wof:name":"Jardin Este",
    "wof:placetype":"neighbourhood"
},
  "geometry": {"coordinates":[-5.94516254542385,37.40553455107358],"type":"Point"}
}