{
  "type": "Feature",
  "properties": {
    "gn:country":"ES",
    "gn:fcode":"PPLA3",
    "gn:population":334,
    "iso:country":"ES",
    "name:ara_x_preferred":[
        "\u0641\u0648\u064a\u0643\u0633\u0627"
    ],
    "name:arg_x_preferred":[
        "Foix\u00e0"
    ],
    "name:ast_x_preferred":[
        "Foix\u00e0"
    ],
    "name:azb_x_preferred":[
        "\u0641\u06cc\u06a9\u0633\u0627"
    ],
    "name:cat_x_preferred":[
        "Foix\u00e0"
    ],
    "name:ceb_x_preferred":[
        "Foix\u00e0"
    ],
    "name:deu_x_preferred":[
        "Foix\u00e0"
    ],
    "name:eng_x_preferred":[
        "Foix\u00e0"
    ],
    "name:eus_x_preferred":[
        "Foix\u00e0"
    ],
    "name:fas_x_preferred":[
        "\u0641\u06cc\u06a9\u0633\u0627"
    ],
    "name:fra_x_preferred":[
        "Foix\u00e0"
    ],
    "name:hun_x_preferred":[
        "Foix\u00e0"
    ],
    "name:hye_x_preferred":[
        "\u0556\u0578\u0577\u0561"
    ],
    "name:ita_x_preferred":[
        "Foix\u00e0"
    ],
    "name:lat_x_preferred":[
        "Foix\u00e0"
    ],
    "name:msa_x_preferred":[
        "Foix\u00e0"
    ],
    "name:nld_x_preferred":[
        "Foix\u00e0"
    ],
    "name:oci_x_preferred":[
        "Foix\u00e0"
    ],
    "name:pol_x_preferred":[
        "Foix\u00e0"
    ],
    "name:por_x_preferred":[
        "Foix\u00e0"
    ],
    "name:rus_x_preferred":[
        "\u0424\u043e\u0448\u0430"
    ],
    "name:spa_x_preferred":[
        "Foix\u00e0"
    ],
    "name:spa_x_variant":[
        "Foix\u00e1"
    ],
    "name:sqi_x_preferred":[
        "Foix\u00e0"
    ],
    "name:swe_x_preferred":[
        "Foix\u00e0"
    ],
    "name:tah_x_preferred":[
        "Foix\u00e0"
    ],
    "name:ukr_x_preferred":[
        "\u0424\u0443\u0448\u044f"
    ],
    "name:uzb_x_preferred":[
        "Foix\u00e0"
    ],
    "name:war_x_preferred":[
        "Foix\u00e0"
    ],
    "name:zho_x_preferred":[
        "\u798f\u4f0a\u514b\u8428"
    ],
    "qs_pg:aaroncc":"ES",
    "qs_pg:gn_country":"ES",
    "qs_pg:gn_fcode":"PPLA3",
    "qs_pg:gn_pop":334,
    "qs_pg:name":"Foix\u00e0",
    "qs_pg:name_adm0":"Espa\u00f1a",
    "qs_pg:name_adm1":"Catalunya",
    "qs_pg:photos":64,
    "qs_pg:photos_1k":13,
    "qs_pg:photos_9k":1,
    "qs_pg:photos_9r":2,
    "qs_pg:photos_all":64,
    "qs_pg:photos_sr":2,
    "qs_pg:pop_sr":2,
    "qs_pg:qs_pg_placetype":"locality",
    "qs_pg:qs_pg_placetype_gp":"Town",
    "qs_pg:woe_adm0":23424950,
    "woe:adm0_id":23424950,
    "woe:name_adm0":"Espa\u00f1a",
    "woe:name_adm1":"Catalunya",
    "woe:placetype":"Town",
    "wof:name":"Foix\u00e0",
    "wof:placetype":"locality",
    "wof:population":334
},
  "geometry": {"coordinates":[3.00021,42.03626],"type":"Point"}
}