{
  "type": "Feature",
  "properties": {
    "gn:admin1_code":"58",
    "gn:admin2_code":"LU",
    "gn:admin3_code":"27018.0",
    "gn:asciiname":"San Martin de Robledo",
    "gn:country_code":"ES",
    "gn:dem":569,
    "gn:feature_class":"P",
    "gn:feature_code":"PPL",
    "gn:name":"San Mart\u00edn de Robledo",
    "gn:population":0,
    "gn:timezone":"Europe/Madrid",
    "iso:country":"ES",
    "wof:name":"San Martin de Robledo",
    "wof:placetype":"locality"
},
  "geometry": {"coordinates":[-7.0867,43.23267],"type":"Point"}
}