{
  "type": "Feature",
  "properties": {
    "gn:admin1_code":"60",
    "gn:admin2_code":"CS",
    "gn:admin3_code":"12093",
    "gn:asciiname":"Corachar",
    "gn:country_code":"ES",
    "gn:dem":1220,
    "gn:feature_class":"P",
    "gn:feature_code":"PPL",
    "gn:name":"Corachar",
    "gn:population":0,
    "gn:timezone":"Europe/Madrid",
    "iso:country":"ES",
    "name:cat_x_preferred":[
        "Coratxa"
    ],
    "name:spa_x_preferred":[
        "Corachar"
    ],
    "name:und_x_variant":[
        "Coratxar"
    ],
    "wof:name":"Corachar",
    "wof:placetype":"locality"
},
  "geometry": {"coordinates":[0.08458,40.68983],"type":"Point"}
}