{
  "type": "Feature",
  "properties": {
    "gn:country":"ES",
    "gn:fcode":"PPLA3",
    "gn:population":225,
    "iso:country":"ES",
    "name:arg_x_preferred":[
        "Videmala"
    ],
    "name:ast_x_preferred":[
        "Videmala"
    ],
    "name:cat_x_preferred":[
        "Videmala"
    ],
    "name:ceb_x_preferred":[
        "Videmala"
    ],
    "name:che_x_preferred":[
        "\u0412\u0438\u0434\u0435\u043c\u0430\u043b\u0430"
    ],
    "name:eng_x_preferred":[
        "Videmala"
    ],
    "name:epo_x_preferred":[
        "Videmala"
    ],
    "name:eus_x_preferred":[
        "Videmala"
    ],
    "name:fra_x_preferred":[
        "Videmala"
    ],
    "name:gle_x_preferred":[
        "Videmala"
    ],
    "name:glg_x_preferred":[
        "Videmala"
    ],
    "name:haw_x_preferred":[
        "Videmala"
    ],
    "name:hun_x_preferred":[
        "Videmala"
    ],
    "name:ile_x_preferred":[
        "Videmala"
    ],
    "name:ina_x_preferred":[
        "Videmala"
    ],
    "name:ita_x_preferred":[
        "Videmala"
    ],
    "name:lld_x_preferred":[
        "Videmala"
    ],
    "name:ltz_x_preferred":[
        "Videmala"
    ],
    "name:msa_x_preferred":[
        "Videmala"
    ],
    "name:nan_x_preferred":[
        "Videmala"
    ],
    "name:nld_x_preferred":[
        "Videmala"
    ],
    "name:nob_x_preferred":[
        "Videmala"
    ],
    "name:oci_x_preferred":[
        "Videmala"
    ],
    "name:pol_x_preferred":[
        "Videmala"
    ],
    "name:por_x_preferred":[
        "Videmala"
    ],
    "name:rus_x_preferred":[
        "\u0412\u0438\u0434\u0435\u043c\u0430\u043b\u0430"
    ],
    "name:spa_x_preferred":[
        "Videmala"
    ],
    "name:swe_x_preferred":[
        "Videmala"
    ],
    "name:tat_x_preferred":[
        "\u0412\u0438\u0434\u0435\u043c\u0430\u043b\u0430"
    ],
    "name:ukr_x_preferred":[
        "\u0412\u0456\u0434\u0435\u043c\u0430\u043b\u0430"
    ],
    "name:uzb_x_preferred":[
        "Videmala"
    ],
    "name:vec_x_preferred":[
        "Videmala"
    ],
    "name:vie_x_preferred":[
        "Videmala"
    ],
    "name:war_x_preferred":[
        "Videmala"
    ],
    "name:zho_x_preferred":[
        "\u6bd4\u5fb7\u9a6c\u62c9"
    ],
    "qs_pg:aaroncc":"ES",
    "qs_pg:gn_country":"ES",
    "qs_pg:gn_fcode":"PPLA3",
    "qs_pg:gn_pop":225,
    "qs_pg:name":"Videmala",
    "qs_pg:name_adm0":"Espa\u00f1a",
    "qs_pg:name_adm1":"Castilla y Le\u00f3n",
    "qs_pg:photos_9k":1,
    "qs_pg:photos_9r":1,
    "qs_pg:photos_all":1,
    "qs_pg:photos_sr":0,
    "qs_pg:pop_sr":2,
    "qs_pg:qs_pg_placetype":"locality",
    "qs_pg:qs_pg_placetype_gp":"Town",
    "qs_pg:woe_adm0":23424950,
    "woe:adm0_id":23424950,
    "woe:name_adm0":"Espa\u00f1a",
    "woe:name_adm1":"Castilla y Le\u00f3n",
    "woe:placetype":"Town",
    "wof:name":"Videmala",
    "wof:placetype":"locality",
    "wof:population":225
},
  "geometry": {"coordinates":[-6.04056,41.61299],"type":"Point"}
}