{
  "type": "Feature",
  "properties": {
    "gn:gn_country":"ES",
    "gn:gn_fcode":"PPL",
    "gn:gn_pop":10869,
    "gn:population":10869,
    "iso:country":"ES",
    "name:unk_x_variant":[
        "Alcal\u00e1"
    ],
    "qs_pg:aaroncc":"ES",
    "qs_pg:gn_country":"ES",
    "qs_pg:gn_fcode":"PPL",
    "qs_pg:gn_pop":10869,
    "qs_pg:name":"Acal\u00e1 del R\u00edo",
    "qs_pg:photos_9r":0,
    "qs_pg:photos_sr":0,
    "qs_pg:pop_sr":6,
    "qs_pg:qs_pg_placetype":"locality",
    "wof:name":"Acal\u00e1 del R\u00edo",
    "wof:placetype":"locality",
    "wof:population":10869
},
  "geometry": {"coordinates":[-5.98185,37.5178],"type":"Point"}
}