{
  "type": "Feature",
  "properties": {
    "gn:admin1_code":"55",
    "gn:admin2_code":"SA",
    "gn:admin3_code":"37135",
    "gn:asciiname":"Mercadillo",
    "gn:country_code":"ES",
    "gn:dem":768,
    "gn:feature_class":"P",
    "gn:feature_code":"PPL",
    "gn:name":"Mercadillo",
    "gn:population":0,
    "gn:timezone":"Europe/Madrid",
    "iso:country":"ES",
    "wof:name":"Mercadillo",
    "wof:placetype":"locality"
},
  "geometry": {"coordinates":[-6.18725,40.83105],"type":"Point"}
}