{
  "type": "Feature",
  "properties": {
    "gn:admin1_code":"60",
    "gn:admin2_code":"A",
    "gn:admin3_code":"03065",
    "gn:asciiname":"Valverde Alto",
    "gn:country_code":"ES",
    "gn:dem":17,
    "gn:feature_class":"P",
    "gn:feature_code":"PPL",
    "gn:name":"Valverde Alto",
    "gn:population":0,
    "gn:timezone":"Europe/Madrid",
    "iso:country":"ES",
    "wof:name":"Valverde Alto",
    "wof:placetype":"locality"
},
  "geometry": {"coordinates":[-0.59313,38.23777000000001],"type":"Point"}
}