{
  "type": "Feature",
  "properties": {
    "gn:admin1_code":"59",
    "gn:admin2_code":"BI",
    "gn:admin3_code":"48069",
    "gn:asciiname":"Trobica",
    "gn:country_code":"ES",
    "gn:dem":105,
    "gn:feature_class":"P",
    "gn:feature_code":"PPL",
    "gn:name":"Trobika",
    "gn:population":0,
    "gn:timezone":"Europe/Madrid",
    "iso:country":"ES",
    "wof:name":"Trobica",
    "wof:placetype":"locality"
},
  "geometry": {"coordinates":[-2.83333,43.36667],"type":"Point"}
}