{
  "type": "Feature",
  "properties": {
    "gn:admin1_code":"58",
    "gn:admin2_code":"C",
    "gn:admin3_code":"15052",
    "gn:asciiname":"Viseo",
    "gn:country_code":"ES",
    "gn:dem":159,
    "gn:feature_class":"P",
    "gn:feature_code":"PPL",
    "gn:name":"Viseo",
    "gn:population":0,
    "gn:timezone":"Europe/Madrid",
    "iso:country":"ES",
    "name:und_x_variant":[
        "Vis\u00e9n",
        "Viseo"
    ],
    "wof:name":"Viseo",
    "wof:placetype":"locality"
},
  "geometry": {"coordinates":[-9.24707,43.04514],"type":"Point"}
}