{
  "type": "Feature",
  "properties": {
    "gn:admin1_code":"59",
    "gn:admin2_code":"BI",
    "gn:admin3_code":"48033",
    "gn:asciiname":"Acorda",
    "gn:country_code":"ES",
    "gn:dem":282,
    "gn:feature_class":"P",
    "gn:feature_code":"PPL",
    "gn:name":"Akorda",
    "gn:population":0,
    "gn:timezone":"Europe/Madrid",
    "iso:country":"ES",
    "wof:name":"Acorda",
    "wof:placetype":"locality"
},
  "geometry": {"coordinates":[-2.60849,43.34665],"type":"Point"}
}