{
  "type": "Feature",
  "properties": {
    "gn:gn_country":"ES",
    "gn:gn_fcode":"PPL",
    "gn:gn_pop":1020,
    "gn:population":1020,
    "iso:country":"ES",
    "name:cat_x_preferred":[
        "Figar\u00f3"
    ],
    "name:cat_x_variant":[
        "el Figuer\u00f3"
    ],
    "name:spa_x_preferred":[
        "El Figar\u00f3"
    ],
    "qs_pg:aaroncc":"ES",
    "qs_pg:gn_country":"ES",
    "qs_pg:gn_fcode":"PPL",
    "qs_pg:gn_pop":1020,
    "qs_pg:name":"El Figar\u00f3",
    "qs_pg:name_adm0":"Espa\u00f1a",
    "qs_pg:name_adm1":"Catalunya",
    "qs_pg:photos":93,
    "qs_pg:photos_1k":19,
    "qs_pg:photos_9k":1,
    "qs_pg:photos_9r":3,
    "qs_pg:photos_all":93,
    "qs_pg:photos_sr":3,
    "qs_pg:pop_sr":3,
    "qs_pg:qs_pg_placetype":"locality",
    "qs_pg:qs_pg_placetype_gp":"Town",
    "qs_pg:woe_adm0":23424950,
    "woe:adm0_id":23424950,
    "woe:name_adm0":"Espa\u00f1a",
    "woe:name_adm1":"Catalunya",
    "woe:placetype":"Town",
    "wof:name":"El Figar\u00f3",
    "wof:placetype":"locality",
    "wof:population":1020
},
  "geometry": {"coordinates":[2.27297,41.72122],"type":"Point"}
}