{
  "type": "Feature",
  "properties": {
    "gn:gn_country":"ES",
    "gn:gn_fcode":"PPLA3",
    "gn:gn_pop":31,
    "gn:population":31,
    "iso:country":"ES",
    "name:ara_x_preferred":[
        "\u0628\u0648\u062b\u0648\u064a\u0644 \u062f\u064a \u0623\u0631\u064a\u062b\u0627"
    ],
    "name:arg_x_preferred":[
        "Pozuel de Fariza"
    ],
    "name:baq_x_preferred":[
        "Pozuel de Ariza"
    ],
    "name:cat_x_preferred":[
        "Pozuel de Ariza"
    ],
    "name:chi_x_preferred":[
        "\u6ce2\u82cf\u57c3\u5c14\u5fb7\u4e9a\u91cc\u8428"
    ],
    "name:dut_x_preferred":[
        "Pozuel de Ariza"
    ],
    "name:eng_x_preferred":[
        "Pozuel de Ariza"
    ],
    "name:fre_x_preferred":[
        "Pozuel de Ariza"
    ],
    "name:hun_x_preferred":[
        "Pozuel de Ariza"
    ],
    "name:ita_x_preferred":[
        "Pozuel de Ariza"
    ],
    "name:kaz_x_preferred":[
        "\u041f\u043e\u0441\u0443\u044d\u043b\u044c-\u0434\u0435-\u0410\u0440\u0438\u0441\u0430"
    ],
    "name:may_x_preferred":[
        "Pozuel de Ariza"
    ],
    "name:nan_x_preferred":[
        "Pozuel de Ariza"
    ],
    "name:oci_x_preferred":[
        "Pozuel de Ariza"
    ],
    "name:pol_x_preferred":[
        "Pozuel de Ariza"
    ],
    "name:por_x_preferred":[
        "Pozuel de Ariza"
    ],
    "name:rus_x_preferred":[
        "\u041f\u043e\u0441\u0443\u044d\u043b\u044c-\u0434\u0435-\u0410\u0440\u0438\u0441\u0430"
    ],
    "name:spa_x_preferred":[
        "Pozuel de Ariza"
    ],
    "name:swe_x_preferred":[
        "Pozuel de Ariza"
    ],
    "name:ukr_x_preferred":[
        "\u041f\u043e\u0441\u0443\u0435\u043b\u044c-\u0434\u0435-\u0410\u0440\u0456\u0441\u0430"
    ],
    "name:unk_x_variant":[
        "Pozuelo de Ariza"
    ],
    "name:uzb_x_preferred":[
        "Pozuel de Ariza"
    ],
    "name:vie_x_preferred":[
        "Pozuel de Ariza"
    ],
    "name:war_x_preferred":[
        "Pozuel de Ariza"
    ],
    "qs_pg:aaroncc":"ES",
    "qs_pg:gn_country":"ES",
    "qs_pg:gn_fcode":"PPLA3",
    "qs_pg:gn_pop":31,
    "qs_pg:name":"Pozuel de Ariza",
    "qs_pg:name_adm0":"Espa\u00f1a",
    "qs_pg:name_adm1":"Arag\u00f3n",
    "qs_pg:photos":22,
    "qs_pg:photos_1k":4,
    "qs_pg:photos_9k":1,
    "qs_pg:photos_9r":1,
    "qs_pg:photos_all":22,
    "qs_pg:photos_sr":1,
    "qs_pg:pop_sr":1,
    "qs_pg:qs_pg_placetype":"locality",
    "qs_pg:qs_pg_placetype_gp":"Town",
    "qs_pg:woe_adm0":23424950,
    "woe:adm0_id":23424950,
    "woe:name_adm0":"Espa\u00f1a",
    "woe:name_adm1":"Arag\u00f3n",
    "woe:placetype":"Town",
    "wof:name":"Pozuel de Ariza",
    "wof:placetype":"locality",
    "wof:population":31
},
  "geometry": {"coordinates":[-2.15,41.35],"type":"Point"}
}