{
  "type": "Feature",
  "properties": {
    "gn:gn_country":"ES",
    "gn:gn_fcode":"PPLA3",
    "gn:gn_pop":753,
    "gn:population":753,
    "iso:country":"ES",
    "name:arg_x_preferred":[
        "Rabanales"
    ],
    "name:arm_x_preferred":[
        "\u054c\u0561\u0562\u0561\u0576\u0561\u056c\u0565\u057d"
    ],
    "name:baq_x_preferred":[
        "Rabanales"
    ],
    "name:cat_x_preferred":[
        "Rabanales"
    ],
    "name:chi_x_preferred":[
        "\u62c9\u74e6\u7eb3\u83b1\u65af"
    ],
    "name:dut_x_preferred":[
        "Rabanales"
    ],
    "name:eng_x_preferred":[
        "Rabanales"
    ],
    "name:fre_x_preferred":[
        "Rabanales"
    ],
    "name:haw_x_preferred":[
        "Rabanales"
    ],
    "name:hun_x_preferred":[
        "Rabanales"
    ],
    "name:ile_x_preferred":[
        "Rabanales"
    ],
    "name:ina_x_preferred":[
        "Rabanales"
    ],
    "name:ita_x_preferred":[
        "Rabanales"
    ],
    "name:may_x_preferred":[
        "Rabanales"
    ],
    "name:nan_x_preferred":[
        "Rabanales"
    ],
    "name:oci_x_preferred":[
        "Rabanales"
    ],
    "name:pol_x_preferred":[
        "Rabanales"
    ],
    "name:por_x_preferred":[
        "Rabanales"
    ],
    "name:rus_x_preferred":[
        "\u0420\u0430\u0431\u0430\u043d\u0430\u043b\u0435\u0441"
    ],
    "name:spa_x_preferred":[
        "Rabanales"
    ],
    "name:swe_x_preferred":[
        "Rabanales"
    ],
    "name:ukr_x_preferred":[
        "\u0420\u0430\u0431\u0430\u043d\u0430\u043b\u0435\u0441"
    ],
    "name:vie_x_preferred":[
        "Rabanales"
    ],
    "name:war_x_preferred":[
        "Rabanales"
    ],
    "qs_pg:aaroncc":"ES",
    "qs_pg:gn_country":"ES",
    "qs_pg:gn_fcode":"PPLA3",
    "qs_pg:gn_pop":753,
    "qs_pg:name":"Rabanales",
    "qs_pg:name_adm0":"Espa\u00f1a",
    "qs_pg:name_adm1":"Castilla y Le\u00f3n",
    "qs_pg:photos_9r":0,
    "qs_pg:photos_sr":0,
    "qs_pg:pop_sr":2,
    "qs_pg:qs_pg_placetype":"locality",
    "qs_pg:qs_pg_placetype_gp":"Town",
    "qs_pg:woe_adm0":23424950,
    "woe:adm0_id":23424950,
    "woe:name_adm0":"Espa\u00f1a",
    "woe:name_adm1":"Castilla y Le\u00f3n",
    "woe:placetype":"Town",
    "wof:name":"Rabanales",
    "wof:placetype":"locality",
    "wof:population":753
},
  "geometry": {"coordinates":[-6.27674,41.74287],"type":"Point"}
}