{
  "type": "Feature",
  "properties": {
    "gn:admin1_code":"34",
    "gn:admin2_code":"O",
    "gn:admin3_code":"33001",
    "gn:asciiname":"Monon",
    "gn:country_code":"ES",
    "gn:dem":550,
    "gn:feature_class":"P",
    "gn:feature_code":"PPL",
    "gn:name":"Mon\u00f3n",
    "gn:population":0,
    "gn:timezone":"Europe/Madrid",
    "iso:country":"ES",
    "name:deu_x_preferred":[
        "Monon"
    ],
    "name:pol_x_preferred":[
        "Monon"
    ],
    "name:und_x_variant":[
        "Mon\u00f3n"
    ],
    "wof:name":"Monon",
    "wof:placetype":"locality"
},
  "geometry": {"coordinates":[-6.73752,43.29468],"type":"Point"}
}