{
  "type": "Feature",
  "properties": {
    "gn:admin1_code":"58",
    "gn:admin2_code":"C",
    "gn:admin3_code":"15034",
    "gn:asciiname":"Hospital",
    "gn:country_code":"ES",
    "gn:dem":334,
    "gn:feature_class":"P",
    "gn:feature_code":"PPL",
    "gn:name":"Hospital",
    "gn:population":0,
    "gn:timezone":"Europe/Madrid",
    "iso:country":"ES",
    "wof:name":"Hospital",
    "wof:placetype":"locality"
},
  "geometry": {"coordinates":[-9.0763,42.98446],"type":"Point"}
}