{
  "type": "Feature",
  "properties": {
    "gn:admin1_code":"60",
    "gn:admin2_code":"CS",
    "gn:admin3_code":"12080",
    "gn:asciiname":"Campello",
    "gn:country_code":"ES",
    "gn:dem":1083,
    "gn:feature_class":"P",
    "gn:feature_code":"PPL",
    "gn:name":"Campello",
    "gn:population":0,
    "gn:timezone":"Europe/Madrid",
    "iso:country":"ES",
    "name:ceb_x_preferred":[
        "Campello"
    ],
    "name:deu_x_preferred":[
        "Campello"
    ],
    "name:fra_x_preferred":[
        "Campello"
    ],
    "name:ita_x_preferred":[
        "Campello"
    ],
    "name:por_x_preferred":[
        "Campello"
    ],
    "name:swe_x_preferred":[
        "Campello"
    ],
    "name:und_x_variant":[
        "Mas del Campello",
        "Caser\u00edo Campello"
    ],
    "wof:name":"Campello",
    "wof:placetype":"locality"
},
  "geometry": {"coordinates":[-0.09855,40.51519],"type":"Point"}
}