{
  "type": "Feature",
  "properties": {
    "gn:admin1_code":"55",
    "gn:admin2_code":"BU",
    "gn:admin3_code":"09152",
    "gn:asciiname":"Ventosilla",
    "gn:country_code":"ES",
    "gn:dem":795,
    "gn:feature_class":"P",
    "gn:feature_code":"PPL",
    "gn:name":"Ventosilla",
    "gn:population":0,
    "gn:timezone":"Europe/Madrid",
    "iso:country":"ES",
    "name:und_x_variant":[
        "Granja de Ventosilla",
        "Ventosilla"
    ],
    "wof:name":"Ventosilla",
    "wof:placetype":"locality"
},
  "geometry": {"coordinates":[-3.82184,41.71739],"type":"Point"}
}