{
  "type": "Feature",
  "properties": {
    "gn:admin1_code":"58",
    "gn:admin2_code":"C",
    "gn:admin3_code":"15083",
    "gn:asciiname":"Mangueeiro",
    "gn:country_code":"ES",
    "gn:dem":494,
    "gn:feature_class":"P",
    "gn:feature_code":"PPL",
    "gn:name":"Mang\u00fceiro",
    "gn:population":0,
    "gn:timezone":"Europe/Madrid",
    "iso:country":"ES",
    "name:und_x_variant":[
        "Mang\u00fceiro"
    ],
    "wof:name":"Mangueeiro",
    "wof:placetype":"locality"
},
  "geometry": {"coordinates":[-7.9719,42.95965],"type":"Point"}
}