{
  "type": "Feature",
  "properties": {
    "gn:admin1_code":"58",
    "gn:admin2_code":"OR",
    "gn:admin3_code":"32001",
    "gn:asciiname":"Espineiros",
    "gn:country_code":"ES",
    "gn:dem":538,
    "gn:feature_class":"P",
    "gn:feature_code":"PPL",
    "gn:name":"Espi\u00f1eiros",
    "gn:population":0,
    "gn:timezone":"Europe/Madrid",
    "iso:country":"ES",
    "wof:name":"Espineiros",
    "wof:placetype":"locality"
},
  "geometry": {"coordinates":[-7.78218,42.21886],"type":"Point"}
}