{
  "type": "Feature",
  "properties": {
    "gn:admin1_code":"54",
    "gn:admin2_code":"AB",
    "gn:admin3_code":"02037",
    "gn:asciiname":"Rincon del Moro",
    "gn:country_code":"ES",
    "gn:dem":723,
    "gn:feature_class":"P",
    "gn:feature_code":"PPL",
    "gn:name":"Rinc\u00f3n del Moro",
    "gn:population":0,
    "gn:timezone":"Europe/Madrid",
    "iso:country":"ES",
    "name:und_x_variant":[
        "Caser\u00edo Rinc\u00f3n del Moro",
        "San Esteban",
        "Rinc\u00f3n del Moro"
    ],
    "wof:name":"Rincon del Moro",
    "wof:placetype":"locality"
},
  "geometry": {"coordinates":[-1.80316,38.59441],"type":"Point"}
}