{
  "type": "Feature",
  "properties": {
    "gn:admin1_code":"51",
    "gn:admin2_code":"J",
    "gn:admin3_code":"23050",
    "gn:asciiname":"Cano Quebrado",
    "gn:country_code":"ES",
    "gn:dem":794,
    "gn:feature_class":"P",
    "gn:feature_code":"PPL",
    "gn:name":"Ca\u00f1o Quebrado",
    "gn:population":0,
    "gn:timezone":"Europe/Madrid",
    "iso:country":"ES",
    "name:und_x_variant":[
        "Caser\u00edo Ca\u00f1o Quebrado",
        "Ca\u00f1o Quebrado"
    ],
    "wof:name":"Cano Quebrado",
    "wof:placetype":"locality"
},
  "geometry": {"coordinates":[-3.81765,37.77014000000001],"type":"Point"}
}