{
  "type": "Feature",
  "properties": {
    "iso:country":"ES",
    "name:eng_x_preferred":[
        "San Felipe Neri"
    ],
    "name:spa_x_preferred":[
        "San Felipe Neri"
    ],
    "wof:name":"San Felipe Neri",
    "wof:placetype":"neighbourhood"
},
  "geometry": {"coordinates":[-4.42156653469917,36.72583507932784],"type":"Point"}
}