{
  "type": "Feature",
  "properties": {
    "gn:admin1_code":"59",
    "gn:admin2_code":"BI",
    "gn:admin3_code":"48022",
    "gn:asciiname":"Bollain",
    "gn:country_code":"ES",
    "gn:dem":270,
    "gn:feature_class":"P",
    "gn:feature_code":"PPL",
    "gn:name":"Bollain",
    "gn:population":0,
    "gn:timezone":"Europe/Madrid",
    "iso:country":"ES",
    "name:und_x_variant":[
        "Bolla\u00edn"
    ],
    "wof:name":"Bollain",
    "wof:placetype":"locality"
},
  "geometry": {"coordinates":[-3.35801,43.24576],"type":"Point"}
}