{
  "type": "Feature",
  "properties": {
    "gn:admin1_code":"56",
    "gn:admin2_code":"T",
    "gn:admin3_code":"43167",
    "gn:asciiname":"Mont-roig del Camp",
    "gn:country_code":"ES",
    "gn:dem":112,
    "gn:feature_class":"P",
    "gn:feature_code":"PPL",
    "gn:name":"Mont-roig del Camp",
    "gn:population":12906,
    "gn:timezone":"Europe/Madrid",
    "iso:country":"ES",
    "name:cat_x_preferred":[
        "Mont-roig del Camp"
    ],
    "name:eng_x_preferred":[
        "Mont-roig del Camp"
    ],
    "name:spa_x_preferred":[
        "Montroig"
    ],
    "name:und_x_variant":[
        "Montroig"
    ],
    "wof:name":"Mont-roig del Camp",
    "wof:placetype":"locality",
    "wof:population":12906
},
  "geometry": {"coordinates":[0.95925,41.08675],"type":"Point"}
}