{
  "type": "Feature",
  "properties": {
    "gn:admin1_code":"56",
    "gn:admin2_code":"T",
    "gn:admin3_code":"43167",
    "gn:asciiname":"Mont-roig del Camp",
    "gn:country_code":"ES",
    "gn:dem":112,
    "gn:feature_class":"P",
    "gn:feature_code":"PPL",
    "gn:name":"Mont-roig del Camp",
    "gn:population":12906,
    "gn:timezone":"Europe/Madrid",
    "iso:country":"ES",
    "name:arg_x_preferred":[
        "Mont-roig del Camp"
    ],
    "name:bel_x_preferred":[
        "\u041c\u043e\u043d\u0442-\u0440\u043e\u0447-\u0434\u044d\u043b\u044c-\u041a\u0430\u043c\u043f"
    ],
    "name:cat_x_preferred":[
        "Mont-roig del Camp"
    ],
    "name:ceb_x_preferred":[
        "Mont-roig del Camp"
    ],
    "name:ces_x_preferred":[
        "Mont-roig del Camp"
    ],
    "name:deu_x_preferred":[
        "Mont-roig del Camp"
    ],
    "name:eng_x_preferred":[
        "Mont-roig del Camp"
    ],
    "name:eus_x_preferred":[
        "Mont-roig del Camp"
    ],
    "name:fin_x_preferred":[
        "Mont-roig del Camp"
    ],
    "name:fra_x_preferred":[
        "Mont-roig del Camp"
    ],
    "name:glg_x_preferred":[
        "Mont-roig del Camp"
    ],
    "name:hun_x_preferred":[
        "Mont-roig del Camp"
    ],
    "name:hye_x_preferred":[
        "\u0544\u0578\u0576\u057f \u057c\u0578\u0579 \u0564\u0565\u056c \u053f\u0561\u0574\u057a"
    ],
    "name:ita_x_preferred":[
        "Mont-roig del Camp"
    ],
    "name:jpn_x_preferred":[
        "\u30e0\u30f3\u30ed\u30c3\u30c1\u30fb\u30c0\u30eb\u30fb\u30ab\u30e0"
    ],
    "name:lat_x_preferred":[
        "Mont-roig del Camp"
    ],
    "name:msa_x_preferred":[
        "Mont-roig del Camp"
    ],
    "name:nld_x_preferred":[
        "Mont-roig del Camp"
    ],
    "name:oci_x_preferred":[
        "Mont-roig del Camp"
    ],
    "name:pol_x_preferred":[
        "Mont-roig del Camp"
    ],
    "name:por_x_preferred":[
        "Mont-roig del Camp"
    ],
    "name:rus_x_preferred":[
        "\u041c\u043e\u043d\u0442-\u0440\u043e\u0447-\u0434\u0435\u043b\u044c-\u041a\u0430\u043c\u043f"
    ],
    "name:spa_x_preferred":[
        "Montroig"
    ],
    "name:sqi_x_preferred":[
        "Mont-roig del Camp"
    ],
    "name:swe_x_preferred":[
        "Mont-roig del Camp"
    ],
    "name:ukr_x_preferred":[
        "\u041c\u043e\u043d-\u0440\u043e\u0447-\u0434\u0430\u043b-\u041a\u0430\u043c\u043f"
    ],
    "name:vie_x_preferred":[
        "Mont-roig del Camp"
    ],
    "name:war_x_preferred":[
        "Mont-roig del Camp"
    ],
    "name:zho_x_preferred":[
        "\u8499\u7279-\u7f57\u4f0a\u683c\u5fb7\u5c14\u574e\u666e"
    ],
    "wof:name":"Mont-roig del Camp",
    "wof:placetype":"locality",
    "wof:population":12906
},
  "geometry": {"coordinates":[0.95925,41.08675],"type":"Point"}
}