{
  "type": "Feature",
  "properties": {
    "gn:admin1_code":"58",
    "gn:admin2_code":"OR",
    "gn:admin3_code":"32002",
    "gn:asciiname":"Trasalva",
    "gn:cc2":"ES",
    "gn:country_code":"ES",
    "gn:dem":436,
    "gn:feature_class":"P",
    "gn:feature_code":"PPL",
    "gn:name":"Trasalva",
    "gn:population":0,
    "gn:timezone":"Europe/Madrid",
    "iso:country":"ES",
    "name:und_x_variant":[
        "San Pedro",
        "Trasalva"
    ],
    "wof:name":"Trasalva",
    "wof:placetype":"locality"
},
  "geometry": {"coordinates":[-7.96667,42.36667],"type":"Point"}
}