{
  "type": "Feature",
  "properties": {
    "gn:admin1_code":"55",
    "gn:admin2_code":"LE",
    "gn:admin3_code":"24198",
    "gn:asciiname":"La Laguna",
    "gn:country_code":"ES",
    "gn:dem":1115,
    "gn:feature_class":"P",
    "gn:feature_code":"PPL",
    "gn:name":"La Laguna",
    "gn:population":0,
    "gn:timezone":"Europe/Madrid",
    "iso:country":"ES",
    "wof:name":"La Laguna",
    "wof:placetype":"locality"
},
  "geometry": {"coordinates":[-7.01979,42.70143],"type":"Point"}
}