{
  "type": "Feature",
  "properties": {
    "iso:country":"ES",
    "wof:name":"Huerta del Rey-Vallellano",
    "wof:placetype":"neighbourhood"
},
  "geometry": {"coordinates":[-4.78404962095863,37.87834922432561],"type":"Point"}
}