{
  "type": "Feature",
  "properties": {
    "gn:admin1_code":"58",
    "gn:admin2_code":"LU",
    "gn:admin3_code":"27059",
    "gn:asciiname":"Millan",
    "gn:cc2":"ES",
    "gn:country_code":"ES",
    "gn:dem":363,
    "gn:feature_class":"P",
    "gn:feature_code":"PPL",
    "gn:name":"Mill\u00e1n",
    "gn:population":0,
    "gn:timezone":"Europe/Madrid",
    "iso:country":"ES",
    "name:und_x_variant":[
        "San Nicol\u00e1s",
        "Mill\u00e1n"
    ],
    "wof:name":"Millan",
    "wof:placetype":"locality"
},
  "geometry": {"coordinates":[-7.58333,42.46667],"type":"Point"}
}