{
  "type": "Feature",
  "properties": {
    "gn:admin1_code":"53",
    "gn:admin2_code":"GC",
    "gn:admin3_code":"35030",
    "gn:asciiname":"La Canada",
    "gn:country_code":"ES",
    "gn:dem":200,
    "gn:feature_class":"P",
    "gn:feature_code":"PPL",
    "gn:name":"La Ca\u00f1ada",
    "gn:population":0,
    "gn:timezone":"Atlantic/Canary",
    "iso:country":"ES",
    "wof:name":"La Canada",
    "wof:placetype":"locality"
},
  "geometry": {"coordinates":[-14.01667,28.35],"type":"Point"}
}