{
  "type": "Feature",
  "properties": {
    "gn:admin1_code":"34",
    "gn:admin2_code":"O",
    "gn:admin3_code":"33076",
    "gn:asciiname":"El Cueto",
    "gn:country_code":"ES",
    "gn:dem":141,
    "gn:feature_class":"P",
    "gn:feature_code":"PPL",
    "gn:name":"El Cueto",
    "gn:population":0,
    "gn:timezone":"Europe/Madrid",
    "iso:country":"ES",
    "name:und_x_variant":[
        "Cueto",
        "El Cueto"
    ],
    "wof:name":"El Cueto",
    "wof:placetype":"locality"
},
  "geometry": {"coordinates":[-5.49164,43.50849],"type":"Point"}
}