{
  "type": "Feature",
  "properties": {
    "gn:admin1_code":"51",
    "gn:admin2_code":"CO",
    "gn:admin3_code":"14029",
    "gn:asciiname":"Los Morenos",
    "gn:country_code":"ES",
    "gn:dem":638,
    "gn:feature_class":"P",
    "gn:feature_code":"PPL",
    "gn:name":"Los Morenos",
    "gn:population":0,
    "gn:timezone":"Europe/Madrid",
    "iso:country":"ES",
    "wof:name":"Los Morenos",
    "wof:placetype":"locality"
},
  "geometry": {"coordinates":[-5.35,38.15],"type":"Point"}
}