{
  "type": "Feature",
  "properties": {
    "gn:gn_country":"ES",
    "gn:gn_fcode":"PPLA3",
    "gn:gn_pop":28227,
    "gn:population":28227,
    "iso:country":"ES",
    "name:ara_x_preferred":[
        "\u0643\u0648\u0644\u064a\u0631\u064a\u062f\u0648"
    ],
    "name:baq_x_preferred":[
        "Culleredo"
    ],
    "name:bre_x_preferred":[
        "Culleredo"
    ],
    "name:cat_x_preferred":[
        "Culleredo"
    ],
    "name:chi_x_preferred":[
        "\u5e93\u5217\u96f7\u591a"
    ],
    "name:dut_x_preferred":[
        "Culleredo"
    ],
    "name:eng_x_preferred":[
        "Culleredo"
    ],
    "name:fre_x_preferred":[
        "Culleredo"
    ],
    "name:ger_x_preferred":[
        "Culleredo"
    ],
    "name:glg_x_preferred":[
        "Culleredo"
    ],
    "name:hun_x_preferred":[
        "Culleredo"
    ],
    "name:ita_x_preferred":[
        "Culleredo"
    ],
    "name:jpn_x_preferred":[
        "\u30af\u30b8\u30a7\u30ec\u30fc\u30c9"
    ],
    "name:lit_x_preferred":[
        "Kuljeredas"
    ],
    "name:lmo_x_preferred":[
        "Culleredo"
    ],
    "name:mac_x_preferred":[
        "\u041a\u0443\u043b\u0435\u0440\u0435\u0434\u043e"
    ],
    "name:may_x_preferred":[
        "Culleredo"
    ],
    "name:mkd_x_preferred":[
        "\u041a\u0443\u043b\u0435\u0440\u0435\u0434\u043e"
    ],
    "name:nan_x_preferred":[
        "Culleredo"
    ],
    "name:oci_x_preferred":[
        "Culleredo"
    ],
    "name:pam_x_preferred":[
        "Culleredo"
    ],
    "name:per_x_preferred":[
        "\u06a9\u0648\u0644\u0631\u062f\u0648"
    ],
    "name:pol_x_preferred":[
        "Culleredo"
    ],
    "name:por_x_preferred":[
        "Culleredo"
    ],
    "name:rup_x_preferred":[
        "Culleredo"
    ],
    "name:rus_x_preferred":[
        "\u041a\u0443\u043b\u044c\u0435\u0440\u0435\u0434\u043e"
    ],
    "name:spa_x_preferred":[
        "Culleredo"
    ],
    "name:swe_x_preferred":[
        "Culleredo"
    ],
    "name:tur_x_preferred":[
        "Culleredo"
    ],
    "name:ukr_x_preferred":[
        "\u041a\u0443\u043b\u044c\u0454\u0440\u0435\u0434\u043e"
    ],
    "name:unk_x_variant":[
        "San Esteban"
    ],
    "name:uzb_x_preferred":[
        "Culleredo"
    ],
    "name:vie_x_preferred":[
        "Culleredo"
    ],
    "name:war_x_preferred":[
        "Culleredo"
    ],
    "name:zho_x_preferred":[
        "\u5e93\u5217\u96f7\u591a"
    ],
    "qs_pg:aaroncc":"ES",
    "qs_pg:gn_country":"ES",
    "qs_pg:gn_fcode":"PPLA3",
    "qs_pg:gn_pop":28227,
    "qs_pg:name":"Culleredo",
    "qs_pg:name_adm0":"Espa\u00f1a",
    "qs_pg:name_adm1":"Galicia",
    "qs_pg:photos":1163,
    "qs_pg:photos_1k":236,
    "qs_pg:photos_9k":5,
    "qs_pg:photos_9r":7,
    "qs_pg:photos_all":1163,
    "qs_pg:photos_sr":11,
    "qs_pg:pop_sr":7,
    "qs_pg:qs_pg_placetype":"locality",
    "qs_pg:qs_pg_placetype_gp":"Town",
    "qs_pg:woe_adm0":23424950,
    "woe:adm0_id":23424950,
    "woe:name_adm0":"Espa\u00f1a",
    "woe:name_adm1":"Galicia",
    "woe:placetype":"Town",
    "wof:name":"Culleredo",
    "wof:placetype":"locality",
    "wof:population":28227
},
  "geometry": {"coordinates":[-8.38858,43.28788],"type":"Point"}
}