{
  "type": "Feature",
  "properties": {
    "gn:country":"ES",
    "gn:fcode":"PPL",
    "gn:population":0,
    "iso:country":"ES",
    "qs_pg:aaroncc":"ES",
    "qs_pg:gn_country":"ES",
    "qs_pg:gn_fcode":"PPL",
    "qs_pg:gn_pop":0,
    "qs_pg:name":"La Caleta",
    "qs_pg:name_adm0":"Espa\u00f1a",
    "qs_pg:name_adm1":"Islas Canarias",
    "qs_pg:photos":537,
    "qs_pg:photos_1k":109,
    "qs_pg:photos_9k":2,
    "qs_pg:photos_9r":5,
    "qs_pg:photos_all":537,
    "qs_pg:photos_sr":7,
    "qs_pg:pop_sr":0,
    "qs_pg:qs_pg_placetype":"locality",
    "qs_pg:qs_pg_placetype_gp":"Town",
    "qs_pg:woe_adm0":23424950,
    "woe:adm0_id":23424950,
    "woe:name_adm0":"Espa\u00f1a",
    "woe:name_adm1":"Islas Canarias",
    "woe:placetype":"Town",
    "wof:name":"La Caleta",
    "wof:placetype":"locality"
},
  "geometry": {"coordinates":[-16.7516,28.0983],"type":"Point"}
}