{
  "type": "Feature",
  "properties": {
    "gn:admin1_code":"34",
    "gn:admin2_code":"O",
    "gn:admin3_code":"33009",
    "gn:asciiname":"Pinera",
    "gn:country_code":"ES",
    "gn:dem":332,
    "gn:feature_class":"P",
    "gn:feature_code":"PPL",
    "gn:name":"Pi\u00f1era",
    "gn:population":0,
    "gn:timezone":"Europe/Madrid",
    "iso:country":"ES",
    "wof:name":"Pinera",
    "wof:placetype":"locality"
},
  "geometry": {"coordinates":[-5.42495,43.40014],"type":"Point"}
}