{
  "type": "Feature",
  "properties": {
    "gn:admin1_code":"39",
    "gn:admin2_code":"S",
    "gn:admin3_code":"39073",
    "gn:asciiname":"Soto de la Marina",
    "gn:country_code":"ES",
    "gn:dem":20,
    "gn:feature_class":"P",
    "gn:feature_code":"PPL",
    "gn:name":"Soto de la Marina",
    "gn:population":0,
    "gn:timezone":"Europe/Madrid",
    "iso:country":"ES",
    "name:und_x_variant":[
        "La Marina",
        "Soto la Marina",
        "Soto de la Marina"
    ],
    "wof:name":"Soto de la Marina",
    "wof:placetype":"locality"
},
  "geometry": {"coordinates":[-3.89758,43.46509],"type":"Point"}
}