{
  "type": "Feature",
  "properties": {
    "gn:gn_country":"ES",
    "gn:gn_fcode":"PPLA3",
    "gn:gn_pop":201,
    "gn:population":201,
    "iso:country":"ES",
    "name:ara_x_preferred":[
        "\u0623\u062a\u0627\u0628\u0648\u064a\u0631\u0643\u0627\u060c \u0628\u0631\u063a\u0634"
    ],
    "name:arg_x_preferred":[
        "Atapuerca"
    ],
    "name:baq_x_preferred":[
        "Atapuerca"
    ],
    "name:bul_x_preferred":[
        "\u0410\u0442\u0430\u043f\u0443\u0435\u0440\u043a\u0430"
    ],
    "name:cat_x_preferred":[
        "Atapuerca"
    ],
    "name:dan_x_preferred":[
        "Atapuerca"
    ],
    "name:dut_x_preferred":[
        "Atapuerca"
    ],
    "name:eng_x_preferred":[
        "Atapuerca"
    ],
    "name:fin_x_preferred":[
        "Atapuerca"
    ],
    "name:fre_x_preferred":[
        "Atapuerca"
    ],
    "name:ger_x_preferred":[
        "Atapuerca"
    ],
    "name:glg_x_preferred":[
        "Atapuerca"
    ],
    "name:haw_x_preferred":[
        "Atapuerca"
    ],
    "name:hun_x_preferred":[
        "Atapuerca"
    ],
    "name:ita_x_preferred":[
        "Atapuerca"
    ],
    "name:lad_x_preferred":[
        "Atapuerca"
    ],
    "name:nan_x_preferred":[
        "Atapuerca"
    ],
    "name:oci_x_preferred":[
        "Atapuerca"
    ],
    "name:per_x_preferred":[
        "\u0622\u062a\u0627\u067e\u0648\u0626\u0631\u06a9\u0627"
    ],
    "name:pol_x_preferred":[
        "Atapuerca"
    ],
    "name:por_x_preferred":[
        "Atapuerca"
    ],
    "name:rus_x_preferred":[
        "\u0410\u0442\u0430\u043f\u0443\u044d\u0440\u043a\u0430"
    ],
    "name:spa_x_preferred":[
        "Atapuerca"
    ],
    "name:tah_x_preferred":[
        "Atapuerca"
    ],
    "name:tpi_x_preferred":[
        "Atapuerca"
    ],
    "name:ukr_x_preferred":[
        "\u0410\u0442\u0430\u043f\u0443\u0435\u0440\u043a\u0430"
    ],
    "name:uzb_x_preferred":[
        "Atapuerca"
    ],
    "name:vie_x_preferred":[
        "Atapuerca"
    ],
    "qs_pg:aaroncc":"ES",
    "qs_pg:gn_country":"ES",
    "qs_pg:gn_fcode":"PPLA3",
    "qs_pg:gn_pop":201,
    "qs_pg:name":"Atapuerca",
    "qs_pg:name_adm0":"Espa\u00f1a",
    "qs_pg:name_adm1":"Castilla y Le\u00f3n",
    "qs_pg:photos":468,
    "qs_pg:photos_1k":95,
    "qs_pg:photos_9k":2,
    "qs_pg:photos_9r":5,
    "qs_pg:photos_all":468,
    "qs_pg:photos_sr":7,
    "qs_pg:pop_sr":2,
    "qs_pg:qs_pg_placetype":"locality",
    "qs_pg:qs_pg_placetype_gp":"Town",
    "qs_pg:woe_adm0":23424950,
    "woe:adm0_id":23424950,
    "woe:name_adm0":"Espa\u00f1a",
    "woe:name_adm1":"Castilla y Le\u00f3n",
    "woe:placetype":"Town",
    "wof:name":"Atapuerca",
    "wof:placetype":"locality",
    "wof:population":201
},
  "geometry": {"coordinates":[-3.5079,42.37757],"type":"Point"}
}