{
  "type": "Feature",
  "properties": {
    "gn:admin1_code":"58",
    "gn:admin2_code":"LU",
    "gn:admin3_code":"27006",
    "gn:asciiname":"Cerezal",
    "gn:country_code":"ES",
    "gn:dem":748,
    "gn:feature_class":"P",
    "gn:feature_code":"PPL",
    "gn:name":"Cerezal",
    "gn:population":0,
    "gn:timezone":"Europe/Madrid",
    "iso:country":"ES",
    "wof:name":"Cerezal",
    "wof:placetype":"locality"
},
  "geometry": {"coordinates":[-7.1744,42.87315],"type":"Point"}
}