{
  "type": "Feature",
  "properties": {
    "gn:admin1_code":"51",
    "gn:admin2_code":"GR",
    "gn:admin3_code":"18194",
    "gn:asciiname":"Banos de Zujar",
    "gn:country_code":"ES",
    "gn:dem":624,
    "gn:feature_class":"P",
    "gn:feature_code":"PPL",
    "gn:name":"Ba\u00f1os de Z\u00fajar",
    "gn:population":0,
    "gn:timezone":"Europe/Madrid",
    "iso:country":"ES",
    "wof:name":"Banos de Zujar",
    "wof:placetype":"locality"
},
  "geometry": {"coordinates":[-2.8151,37.59746],"type":"Point"}
}