{
  "type": "Feature",
  "properties": {
    "gn:admin1_code":"39",
    "gn:admin2_code":"S",
    "gn:admin3_code":"39073",
    "gn:asciiname":"Azonos",
    "gn:country_code":"ES",
    "gn:dem":78,
    "gn:feature_class":"P",
    "gn:feature_code":"PPL",
    "gn:name":"Azo\u00f1os",
    "gn:population":0,
    "gn:timezone":"Europe/Madrid",
    "iso:country":"ES",
    "name:und_x_variant":[
        "Azo\u00f1os"
    ],
    "wof:name":"Azonos",
    "wof:placetype":"locality"
},
  "geometry": {"coordinates":[-3.90998,43.42905],"type":"Point"}
}