{
  "type": "Feature",
  "properties": {
    "gn:country":"ES",
    "gn:fcode":"PPLA3",
    "gn:population":1763,
    "iso:country":"ES",
    "name:arg_x_preferred":[
        "Uceda"
    ],
    "name:ast_x_preferred":[
        "Uceda"
    ],
    "name:azb_x_preferred":[
        "\u0627\u0648\u0633\u062f\u0627"
    ],
    "name:cat_x_preferred":[
        "Uceda"
    ],
    "name:ceb_x_preferred":[
        "Uceda"
    ],
    "name:eng_x_preferred":[
        "Uceda"
    ],
    "name:epo_x_preferred":[
        "Uceda"
    ],
    "name:eus_x_preferred":[
        "Uceda"
    ],
    "name:fas_x_preferred":[
        "\u0627\u0648\u0633\u062f\u0627"
    ],
    "name:fra_x_preferred":[
        "Uceda"
    ],
    "name:hun_x_preferred":[
        "Uceda"
    ],
    "name:ina_x_preferred":[
        "Uceda"
    ],
    "name:ita_x_preferred":[
        "Uceda"
    ],
    "name:kaz_x_preferred":[
        "\u0423\u0441\u0435\u0434\u0430"
    ],
    "name:lit_x_preferred":[
        "Useda"
    ],
    "name:msa_x_preferred":[
        "Uceda"
    ],
    "name:nan_x_preferred":[
        "Uceda"
    ],
    "name:nld_x_preferred":[
        "Uceda"
    ],
    "name:oci_x_preferred":[
        "Uceda"
    ],
    "name:pol_x_preferred":[
        "Uceda"
    ],
    "name:por_x_preferred":[
        "Uceda"
    ],
    "name:rus_x_preferred":[
        "\u0423\u0441\u0435\u0434\u0430"
    ],
    "name:spa_x_preferred":[
        "Uceda"
    ],
    "name:swe_x_preferred":[
        "Uceda"
    ],
    "name:ukr_x_preferred":[
        "\u0423\u0441\u0435\u0434\u0430"
    ],
    "name:urd_x_preferred":[
        "\u0627\u06a9\u06cc\u0688\u0627"
    ],
    "name:uzb_x_preferred":[
        "Uceda"
    ],
    "name:vie_x_preferred":[
        "Uceda"
    ],
    "name:war_x_preferred":[
        "Uceda"
    ],
    "name:zho_x_preferred":[
        "\u4e4c\u585e\u8fbe"
    ],
    "qs_pg:aaroncc":"ES",
    "qs_pg:gn_country":"ES",
    "qs_pg:gn_fcode":"PPLA3",
    "qs_pg:gn_pop":1763,
    "qs_pg:name":"Uceda",
    "qs_pg:name_adm0":"Espa\u00f1a",
    "qs_pg:name_adm1":"Castilla-La Mancha",
    "qs_pg:photos":97,
    "qs_pg:photos_1k":20,
    "qs_pg:photos_9k":1,
    "qs_pg:photos_9r":3,
    "qs_pg:photos_all":97,
    "qs_pg:photos_sr":3,
    "qs_pg:pop_sr":3,
    "qs_pg:qs_pg_placetype":"locality",
    "qs_pg:qs_pg_placetype_gp":"Town",
    "qs_pg:woe_adm0":23424950,
    "woe:adm0_id":23424950,
    "woe:name_adm0":"Espa\u00f1a",
    "woe:name_adm1":"Castilla-La Mancha",
    "woe:placetype":"Town",
    "wof:name":"Uceda",
    "wof:placetype":"locality",
    "wof:population":1763
},
  "geometry": {"coordinates":[-3.4604,40.83944],"type":"Point"}
}