{
  "type": "Feature",
  "properties": {
    "gn:gn_country":"ES",
    "gn:gn_fcode":"PPL",
    "gn:gn_pop":504,
    "gn:population":504,
    "iso:country":"ES",
    "name:ara_x_preferred":[
        "\u0628\u064a\u0631\u0632\u0648\u0643\u0627\u0646\u0627"
    ],
    "name:cat_x_preferred":[
        "Berzocana"
    ],
    "name:eng_x_preferred":[
        "Berzocana"
    ],
    "name:epo_x_preferred":[
        "Berzocana"
    ],
    "name:eus_x_preferred":[
        "Berzocana"
    ],
    "name:fra_x_preferred":[
        "Berzocana"
    ],
    "name:hun_x_preferred":[
        "Berzocana"
    ],
    "name:hye_x_preferred":[
        "\u054d\u0565\u0578 \u0564\u0565 \u0548\u0582\u0580\u056a\u0565\u056c"
    ],
    "name:ina_x_preferred":[
        "Berzocana"
    ],
    "name:ita_x_preferred":[
        "Berzocana"
    ],
    "name:msa_x_preferred":[
        "Berzocana"
    ],
    "name:nan_x_preferred":[
        "Berzocana"
    ],
    "name:nld_x_preferred":[
        "Berzocana"
    ],
    "name:oci_x_preferred":[
        "Berzocana"
    ],
    "name:pol_x_preferred":[
        "Berzocana"
    ],
    "name:por_x_preferred":[
        "Berzocana"
    ],
    "name:ron_x_preferred":[
        "Berzocana"
    ],
    "name:rus_x_preferred":[
        "\u0411\u0435\u0440\u0441\u043e\u043a\u0430\u043d\u0430"
    ],
    "name:spa_x_preferred":[
        "Berzocana"
    ],
    "name:swe_x_preferred":[
        "Berzocana"
    ],
    "name:ukr_x_preferred":[
        "\u0411\u0435\u0440\u0441\u043e\u043a\u0430\u043d\u0430"
    ],
    "name:uzb_x_preferred":[
        "Berzocana"
    ],
    "name:vie_x_preferred":[
        "Berzocana"
    ],
    "name:war_x_preferred":[
        "Berzocana"
    ],
    "name:zho_x_preferred":[
        "\u8d1d\u5c14\u7d22\u5361\u7eb3"
    ],
    "qs_pg:aaroncc":"ES",
    "qs_pg:gn_country":"ES",
    "qs_pg:gn_fcode":"PPL",
    "qs_pg:gn_pop":504,
    "qs_pg:name":"Berzocana",
    "qs_pg:name_adm0":"Espa\u00f1a",
    "qs_pg:name_adm1":"Extremadura",
    "qs_pg:photos":135,
    "qs_pg:photos_1k":27,
    "qs_pg:photos_9k":1,
    "qs_pg:photos_9r":3,
    "qs_pg:photos_all":135,
    "qs_pg:photos_sr":3,
    "qs_pg:pop_sr":2,
    "qs_pg:qs_pg_placetype":"locality",
    "qs_pg:qs_pg_placetype_gp":"Town",
    "qs_pg:woe_adm0":23424950,
    "woe:adm0_id":23424950,
    "woe:name_adm0":"Espa\u00f1a",
    "woe:name_adm1":"Extremadura",
    "woe:placetype":"Town",
    "wof:name":"Berzocana",
    "wof:placetype":"locality",
    "wof:population":504
},
  "geometry": {"coordinates":[-5.46121,39.43673],"type":"Point"}
}