{
  "type": "Feature",
  "properties": {
    "gn:admin1_code":"34",
    "gn:admin2_code":"O",
    "gn:admin3_code":"33056",
    "gn:asciiname":"Fresno",
    "gn:country_code":"ES",
    "gn:dem":94,
    "gn:feature_class":"P",
    "gn:feature_code":"PPL",
    "gn:name":"Fresno",
    "gn:population":0,
    "gn:timezone":"Europe/Madrid",
    "iso:country":"ES",
    "wof:name":"Fresno",
    "wof:placetype":"locality"
},
  "geometry": {"coordinates":[-5.10203,43.45659000000001],"type":"Point"}
}