{
  "type": "Feature",
  "properties": {
    "gn:admin1_code":"55",
    "gn:admin2_code":"AV",
    "gn:admin3_code":"05132",
    "gn:asciiname":"La Higuera",
    "gn:country_code":"ES",
    "gn:dem":411,
    "gn:feature_class":"P",
    "gn:feature_code":"PPL",
    "gn:name":"La Higuera",
    "gn:population":0,
    "gn:timezone":"Europe/Madrid",
    "iso:country":"ES",
    "name:und_x_variant":[
        "Caser\u00edo La Higuera",
        "La Higuera"
    ],
    "wof:name":"La Higuera",
    "wof:placetype":"locality"
},
  "geometry": {"coordinates":[-4.99548,40.18773],"type":"Point"}
}