{
  "type": "Feature",
  "properties": {
    "gn:gn_country":"ES",
    "gn:gn_fcode":"PPLA3",
    "gn:gn_pop":172,
    "gn:population":172,
    "iso:country":"ES",
    "name:arg_x_preferred":[
        "Tartanedo"
    ],
    "name:cat_x_preferred":[
        "Tartanedo"
    ],
    "name:deu_x_preferred":[
        "Tartanedo"
    ],
    "name:eng_x_preferred":[
        "Tartanedo"
    ],
    "name:eus_x_preferred":[
        "Tartanedo"
    ],
    "name:fra_x_preferred":[
        "Tartanedo"
    ],
    "name:hun_x_preferred":[
        "Tartanedo"
    ],
    "name:ina_x_preferred":[
        "Tartanedo"
    ],
    "name:ita_x_preferred":[
        "Tartanedo"
    ],
    "name:kaz_x_preferred":[
        "\u0422\u0430\u0440\u0442\u0430\u043d\u0435\u0434\u043e"
    ],
    "name:msa_x_preferred":[
        "Tartanedo"
    ],
    "name:nan_x_preferred":[
        "Tartanedo"
    ],
    "name:nld_x_preferred":[
        "Tartanedo"
    ],
    "name:oci_x_preferred":[
        "Tartanedo"
    ],
    "name:pol_x_preferred":[
        "Tartanedo"
    ],
    "name:por_x_preferred":[
        "Tartanedo"
    ],
    "name:rus_x_preferred":[
        "\u0422\u0430\u0440\u0442\u0430\u043d\u0435\u0434\u043e"
    ],
    "name:spa_x_preferred":[
        "Tartanedo"
    ],
    "name:swe_x_preferred":[
        "Tartanedo"
    ],
    "name:ukr_x_preferred":[
        "\u0422\u0430\u0440\u0442\u0430\u043d\u0435\u0434\u043e"
    ],
    "name:vie_x_preferred":[
        "Tartanedo"
    ],
    "name:war_x_preferred":[
        "Tartanedo"
    ],
    "name:zho_x_preferred":[
        "\u5854\u5c14\u5854\u5185\u591a"
    ],
    "qs_pg:aaroncc":"ES",
    "qs_pg:gn_country":"ES",
    "qs_pg:gn_fcode":"PPLA3",
    "qs_pg:gn_pop":172,
    "qs_pg:name":"Tartanedo",
    "qs_pg:name_adm0":"Espa\u00f1a",
    "qs_pg:name_adm1":"Castilla-La Mancha",
    "qs_pg:photos_9k":1,
    "qs_pg:photos_9r":1,
    "qs_pg:photos_all":2,
    "qs_pg:photos_sr":0,
    "qs_pg:pop_sr":1,
    "qs_pg:qs_pg_placetype":"locality",
    "qs_pg:qs_pg_placetype_gp":"Town",
    "qs_pg:woe_adm0":23424950,
    "woe:adm0_id":23424950,
    "woe:name_adm0":"Espa\u00f1a",
    "woe:name_adm1":"Castilla-La Mancha",
    "woe:placetype":"Town",
    "wof:name":"Tartanedo",
    "wof:placetype":"locality",
    "wof:population":172
},
  "geometry": {"coordinates":[-1.92459,40.99347],"type":"Point"}
}