{
  "type": "Feature",
  "properties": {
    "gn:country":"ES",
    "gn:fcode":"PPL",
    "gn:population":994,
    "iso:country":"ES",
    "name:arg_x_preferred":[
        "La Puebla d'\u00cdxar"
    ],
    "name:azb_x_preferred":[
        "\u0644\u0627 \u067e\u0648\u0626\u0628\u0644\u0627 \u062f \u0647\u06cc\u062e\u0627\u0631"
    ],
    "name:cat_x_preferred":[
        "La Puebla de H\u00edjar"
    ],
    "name:eng_x_preferred":[
        "La Puebla de H\u00edjar"
    ],
    "name:eus_x_preferred":[
        "La Puebla de H\u00edjar"
    ],
    "name:fas_x_preferred":[
        "\u0644\u0627 \u067e\u0648\u0626\u0628\u0644\u0627 \u062f \u0647\u06cc\u062e\u0627\u0631"
    ],
    "name:fra_x_preferred":[
        "La Puebla de H\u00edjar"
    ],
    "name:hun_x_preferred":[
        "La Puebla de H\u00edjar"
    ],
    "name:ita_x_preferred":[
        "La Puebla de H\u00edjar"
    ],
    "name:kaz_x_preferred":[
        "\u041b\u0430-\u041f\u0443\u044d\u0431\u043b\u0430-\u0434\u0435-\u0418\u0445\u0430\u0440"
    ],
    "name:msa_x_preferred":[
        "La Puebla de H\u00edjar"
    ],
    "name:nan_x_preferred":[
        "La Puebla de H\u00edjar"
    ],
    "name:nld_x_preferred":[
        "La Puebla de H\u00edjar"
    ],
    "name:oci_x_preferred":[
        "La Puebla d'\u00cdxar"
    ],
    "name:pol_x_preferred":[
        "La Puebla de H\u00edjar"
    ],
    "name:por_x_preferred":[
        "La Puebla de H\u00edjar"
    ],
    "name:ron_x_preferred":[
        "La Puebla de H\u00edjar"
    ],
    "name:rus_x_preferred":[
        "\u041b\u0430-\u041f\u0443\u044d\u0431\u043b\u0430-\u0434\u0435-\u0418\u0445\u0430\u0440"
    ],
    "name:sco_x_preferred":[
        "La Puebla de H\u00edjar"
    ],
    "name:spa_x_preferred":[
        "La Puebla de H\u00edjar"
    ],
    "name:swe_x_preferred":[
        "La Puebla de H\u00edjar"
    ],
    "name:ukr_x_preferred":[
        "\u041b\u0430-\u041f\u0443\u0435\u0431\u043b\u0430-\u0434\u0435-\u0406\u0445\u0430\u0440"
    ],
    "name:und_x_variant":[
        "La Puebla"
    ],
    "name:urd_x_preferred":[
        "\u0644\u0627 \u067e\u06cc\u0648\u0628\u0644\u0627 \u062f\u06d2 \u06c1\u06cc\u062c\u0627\u0631"
    ],
    "name:uzb_x_preferred":[
        "La Puebla de H\u00edjar"
    ],
    "name:vie_x_preferred":[
        "La Puebla de H\u00edjar"
    ],
    "name:war_x_preferred":[
        "La Puebla de H\u00edjar"
    ],
    "name:zho_x_preferred":[
        "\u62c9\u666e\u57c3\u592b\u62c9\u5fb7\u4f0a\u54c8\u5c14"
    ],
    "qs_pg:aaroncc":"ES",
    "qs_pg:gn_country":"ES",
    "qs_pg:gn_fcode":"PPL",
    "qs_pg:gn_pop":994,
    "qs_pg:name":"Puebla de Hijar",
    "qs_pg:name_adm0":"Espa\u00f1a",
    "qs_pg:name_adm1":"Arag\u00f3n",
    "qs_pg:photos":91,
    "qs_pg:photos_1k":18,
    "qs_pg:photos_9k":1,
    "qs_pg:photos_9r":3,
    "qs_pg:photos_all":91,
    "qs_pg:photos_sr":3,
    "qs_pg:pop_sr":2,
    "qs_pg:qs_pg_placetype":"locality",
    "qs_pg:qs_pg_placetype_gp":"Town",
    "qs_pg:woe_adm0":23424950,
    "woe:adm0_id":23424950,
    "woe:name_adm0":"Espa\u00f1a",
    "woe:name_adm1":"Arag\u00f3n",
    "woe:placetype":"Town",
    "wof:name":"Puebla de Hijar",
    "wof:placetype":"locality",
    "wof:population":994
},
  "geometry": {"coordinates":[-0.44091,41.22216],"type":"Point"}
}