{
  "type": "Feature",
  "properties": {
    "gn:admin1_code":"56",
    "gn:admin2_code":"T",
    "gn:admin3_code":"43170",
    "gn:asciiname":"Vilarrodona",
    "gn:country_code":"ES",
    "gn:dem":275,
    "gn:feature_class":"P",
    "gn:feature_code":"PPL",
    "gn:name":"Vilarrodona",
    "gn:population":0,
    "gn:timezone":"Europe/Madrid",
    "iso:country":"ES",
    "name:und_x_variant":[
        "Villarodona",
        "Vilarrodona"
    ],
    "wof:name":"Vilarrodona",
    "wof:placetype":"locality"
},
  "geometry": {"coordinates":[1.35904,41.31233],"type":"Point"}
}