{
  "type": "Feature",
  "properties": {
    "gn:admin1_code":"54",
    "gn:admin2_code":"CR",
    "gn:admin3_code":"13094",
    "gn:asciiname":"La Alameda",
    "gn:country_code":"ES",
    "gn:dem":571,
    "gn:feature_class":"P",
    "gn:feature_code":"PPL",
    "gn:name":"La Alameda",
    "gn:population":0,
    "gn:timezone":"Europe/Madrid",
    "iso:country":"ES",
    "wof:name":"La Alameda",
    "wof:placetype":"locality"
},
  "geometry": {"coordinates":[-3.87596,38.60918],"type":"Point"}
}