{
  "type": "Feature",
  "properties": {
    "gn:admin1_code":"39",
    "gn:admin2_code":"S",
    "gn:admin3_code":"39038",
    "gn:asciiname":"Sena",
    "gn:country_code":"ES",
    "gn:dem":229,
    "gn:feature_class":"P",
    "gn:feature_code":"PPL",
    "gn:name":"Se\u00f1a",
    "gn:population":0,
    "gn:timezone":"Europe/Madrid",
    "iso:country":"ES",
    "name:bul_x_preferred":[
        "\u0421\u0435\u043d\u0430"
    ],
    "name:cat_x_preferred":[
        "Sena"
    ],
    "name:ceb_x_preferred":[
        "Sena"
    ],
    "name:deu_x_preferred":[
        "Sena"
    ],
    "name:fra_x_preferred":[
        "Sena"
    ],
    "name:glg_x_preferred":[
        "Sena"
    ],
    "name:ind_x_preferred":[
        "Sena"
    ],
    "name:ita_x_preferred":[
        "Sena"
    ],
    "name:lat_x_preferred":[
        "Sena"
    ],
    "name:lmo_x_preferred":[
        "Sena"
    ],
    "name:nld_x_preferred":[
        "Sena"
    ],
    "name:por_x_preferred":[
        "Sena"
    ],
    "name:ron_x_preferred":[
        "Sena"
    ],
    "name:rus_x_preferred":[
        "\u0421\u0435\u043d\u0430"
    ],
    "name:slv_x_preferred":[
        "Sena"
    ],
    "name:spa_x_preferred":[
        "Sena"
    ],
    "name:srp_x_preferred":[
        "\u0421\u0435\u043d\u0430"
    ],
    "name:swe_x_preferred":[
        "Sena"
    ],
    "name:ukr_x_preferred":[
        "\u0421\u0435\u043d\u0430"
    ],
    "name:und_x_variant":[
        "Se\u00f1a"
    ],
    "name:uzb_x_preferred":[
        "Sena"
    ],
    "wof:name":"Sena",
    "wof:placetype":"locality"
},
  "geometry": {"coordinates":[-3.41126,43.38545],"type":"Point"}
}