{
  "type": "Feature",
  "properties": {
    "iso:country":"ES",
    "name:eng_x_preferred":[
        "Parque Clavero"
    ],
    "name:spa_x_preferred":[
        "Parque Clavero"
    ],
    "wof:name":"Parque Clavero",
    "wof:placetype":"neighbourhood"
},
  "geometry": {"coordinates":[-4.39043858934958,36.72666060113969],"type":"Point"}
}