{
  "type": "Feature",
  "properties": {
    "iso:country":"ES",
    "name:eng_x_preferred":[
        "Canada de Ceuta"
    ],
    "name:spa_x_preferred":[
        "Ca\u00f1ada de Ceuta"
    ],
    "wof:name":"Canada de Ceuta",
    "wof:placetype":"neighbourhood"
},
  "geometry": {"coordinates":[-4.51441012316357,36.65206086105288],"type":"Point"}
}