{
  "type": "Feature",
  "properties": {
    "iso:country":"ES",
    "name:eng_x_preferred":[
        "Churriana"
    ],
    "name:spa_x_preferred":[
        "Churriana"
    ],
    "wof:name":"Churriana",
    "wof:placetype":"neighbourhood"
},
  "geometry": {"coordinates":[-4.50279436414524,36.66882641715837],"type":"Point"}
}