{
  "type": "Feature",
  "properties": {
    "gn:gn_country":"ES",
    "gn:gn_fcode":"PPLA3",
    "gn:gn_pop":74,
    "gn:population":74,
    "iso:country":"ES",
    "name:arg_x_preferred":[
        "Borau"
    ],
    "name:baq_x_preferred":[
        "Borau"
    ],
    "name:cat_x_preferred":[
        "Borau"
    ],
    "name:chi_x_preferred":[
        "\u535a\u52b3"
    ],
    "name:dut_x_preferred":[
        "Borau"
    ],
    "name:eng_x_preferred":[
        "Borau"
    ],
    "name:fre_x_preferred":[
        "Borau"
    ],
    "name:ger_x_preferred":[
        "Borau"
    ],
    "name:glg_x_preferred":[
        "Borau"
    ],
    "name:hun_x_preferred":[
        "Borau"
    ],
    "name:ita_x_preferred":[
        "Borau"
    ],
    "name:may_x_preferred":[
        "Borau"
    ],
    "name:nan_x_preferred":[
        "Borau"
    ],
    "name:oci_x_preferred":[
        "Borau"
    ],
    "name:pol_x_preferred":[
        "Borau"
    ],
    "name:por_x_preferred":[
        "Borau"
    ],
    "name:rus_x_preferred":[
        "\u0411\u043e\u0440\u0430\u0443"
    ],
    "name:spa_x_preferred":[
        "Borau"
    ],
    "name:ukr_x_preferred":[
        "\u0411\u043e\u0440\u0430\u0443"
    ],
    "name:uzb_x_preferred":[
        "Borau"
    ],
    "name:vie_x_preferred":[
        "Borau"
    ],
    "name:war_x_preferred":[
        "Borau"
    ],
    "qs_pg:aaroncc":"ES",
    "qs_pg:gn_country":"ES",
    "qs_pg:gn_fcode":"PPLA3",
    "qs_pg:gn_pop":74,
    "qs_pg:name":"Borau",
    "qs_pg:name_adm0":"Espa\u00f1a",
    "qs_pg:name_adm1":"Arag\u00f3n",
    "qs_pg:photos":33,
    "qs_pg:photos_1k":7,
    "qs_pg:photos_9k":1,
    "qs_pg:photos_9r":2,
    "qs_pg:photos_all":33,
    "qs_pg:photos_sr":2,
    "qs_pg:pop_sr":1,
    "qs_pg:qs_pg_placetype":"locality",
    "qs_pg:qs_pg_placetype_gp":"Town",
    "qs_pg:woe_adm0":23424950,
    "woe:adm0_id":23424950,
    "woe:name_adm0":"Espa\u00f1a",
    "woe:name_adm1":"Arag\u00f3n",
    "woe:placetype":"Town",
    "wof:name":"Borau",
    "wof:placetype":"locality",
    "wof:population":74
},
  "geometry": {"coordinates":[-0.58846,42.65858],"type":"Point"}
}