{
  "type": "Feature",
  "properties": {
    "gn:country":"ES",
    "gn:fcode":"PPLA3",
    "gn:population":108,
    "iso:country":"ES",
    "name:ara_x_preferred":[
        "\u062e\u064a\u0645\u064a\u0627\u0644\u0643\u0648\u0646"
    ],
    "name:ast_x_preferred":[
        "Gimialc\u00f3n"
    ],
    "name:cat_x_preferred":[
        "Gimialc\u00f3n"
    ],
    "name:ceb_x_preferred":[
        "Gimialc\u00f3n"
    ],
    "name:eng_x_preferred":[
        "Gimialc\u00f3n"
    ],
    "name:eus_x_preferred":[
        "Gimialc\u00f3n"
    ],
    "name:fas_x_preferred":[
        "\u06af\u06cc\u0645\u06cc\u0627\u0644\u06a9\u0648\u0646"
    ],
    "name:fra_x_preferred":[
        "Gimialc\u00f3n"
    ],
    "name:hun_x_preferred":[
        "Gimialc\u00f3n"
    ],
    "name:ina_x_preferred":[
        "Gimialc\u00f3n"
    ],
    "name:ita_x_preferred":[
        "Gimialc\u00f3n"
    ],
    "name:kaz_x_preferred":[
        "\u0425\u0438\u043c\u0438\u044f\u043b\u044c\u043a\u043e\u043d"
    ],
    "name:mkd_x_preferred":[
        "\u0413\u0438\u043b\u0431\u0443\u0435\u043d\u0430"
    ],
    "name:msa_x_preferred":[
        "Gimialc\u00f3n"
    ],
    "name:nld_x_preferred":[
        "Gimialc\u00f3n"
    ],
    "name:oci_x_preferred":[
        "Gimialc\u00f3n"
    ],
    "name:pol_x_preferred":[
        "Gimialc\u00f3n"
    ],
    "name:por_x_preferred":[
        "Gimialc\u00f3n"
    ],
    "name:rus_x_preferred":[
        "\u0425\u0438\u043c\u0438\u044f\u043b\u044c\u043a\u043e\u043d"
    ],
    "name:spa_x_preferred":[
        "Gimialc\u00f3n"
    ],
    "name:swe_x_preferred":[
        "Gimialc\u00f3n"
    ],
    "name:ukr_x_preferred":[
        "\u0425\u0456\u043c\u0456\u0430\u043b\u044c\u043a\u043e\u043d"
    ],
    "name:uzb_x_preferred":[
        "Gimialc\u00f3n"
    ],
    "name:vie_x_preferred":[
        "Gimialc\u00f3n"
    ],
    "name:war_x_preferred":[
        "Gimialc\u00f3n"
    ],
    "name:zho_x_preferred":[
        "\u5e0c\u7c73\u4e9a\u5c14\u5b54"
    ],
    "qs_pg:aaroncc":"ES",
    "qs_pg:gn_country":"ES",
    "qs_pg:gn_fcode":"PPLA3",
    "qs_pg:gn_pop":108,
    "qs_pg:name":"Gimialc\u00f3n",
    "qs_pg:name_adm0":"Espa\u00f1a",
    "qs_pg:name_adm1":"Castilla y Le\u00f3n",
    "qs_pg:photos_9k":1,
    "qs_pg:photos_9r":1,
    "qs_pg:photos_all":1,
    "qs_pg:photos_sr":0,
    "qs_pg:pop_sr":1,
    "qs_pg:qs_pg_placetype":"locality",
    "qs_pg:qs_pg_placetype_gp":"Town",
    "qs_pg:woe_adm0":23424950,
    "woe:adm0_id":23424950,
    "woe:name_adm0":"Espa\u00f1a",
    "woe:name_adm1":"Castilla y Le\u00f3n",
    "woe:placetype":"Town",
    "wof:name":"Gimialc\u00f3n",
    "wof:placetype":"locality",
    "wof:population":108
},
  "geometry": {"coordinates":[-5.12308,40.87705],"type":"Point"}
}