{
  "type": "Feature",
  "properties": {
    "gn:gn_country":"ES",
    "gn:gn_fcode":"PPLX",
    "gn:gn_pop":104923,
    "gn:population":104923,
    "iso:country":"ES",
    "name:epo_x_preferred":[
        "Moratalazo"
    ],
    "name:jpn_x_preferred":[
        "\u30e2\u30e9\u30bf\u30e9\u30b9"
    ],
    "name:que_x_preferred":[
        "Moratalaz distritu"
    ],
    "qs_pg:aaroncc":"ES",
    "qs_pg:gn_country":"ES",
    "qs_pg:gn_fcode":"PPLX",
    "qs_pg:gn_pop":104923,
    "qs_pg:name":"Barrio Moratalaz",
    "qs_pg:name_adm0":"Espa\u00f1a",
    "qs_pg:name_adm1":"Comunidad de Madrid",
    "qs_pg:photos":50,
    "qs_pg:photos_1k":10,
    "qs_pg:photos_9k":1,
    "qs_pg:photos_9r":2,
    "qs_pg:photos_all":50,
    "qs_pg:photos_sr":2,
    "qs_pg:pop_sr":9,
    "qs_pg:qs_pg_placetype":"neighbourhood",
    "qs_pg:qs_pg_placetype_gp":"Suburb",
    "qs_pg:woe_adm0":23424950,
    "woe:adm0_id":23424950,
    "woe:name_adm0":"Espa\u00f1a",
    "woe:name_adm1":"Comunidad de Madrid",
    "woe:placetype":"Suburb",
    "wof:name":"Barrio Moratalaz",
    "wof:placetype":"neighbourhood",
    "wof:population":104923
},
  "geometry": {"coordinates":[-3.65,40.41667],"type":"Point"}
}