{
  "type": "Feature",
  "properties": {
    "gn:gn_country":"ES",
    "gn:gn_fcode":"PPLA3",
    "gn:gn_pop":0,
    "iso:country":"ES",
    "name:ara_x_preferred":[
        "\u0633\u0627\u0646 \u0633\u0627\u062f\u0648\u0631\u0646\u064a\u0646\u0648"
    ],
    "name:azb_x_preferred":[
        "\u0633\u0627\u0646 \u0633\u0627\u062f\u0648\u0631\u0646\u0627\u06cc\u0646\u0648"
    ],
    "name:bre_x_preferred":[
        "San Sadurni\u00f1o"
    ],
    "name:cat_x_preferred":[
        "San Sadurni\u00f1o"
    ],
    "name:ceb_x_preferred":[
        "San Sadurni\u00f1o"
    ],
    "name:deu_x_preferred":[
        "San Sadurni\u00f1o"
    ],
    "name:eng_x_preferred":[
        "San Sadurni\u00f1o"
    ],
    "name:eus_x_preferred":[
        "San Sadurni\u00f1o"
    ],
    "name:fas_x_preferred":[
        "\u0633\u0627\u0646 \u0633\u0627\u062f\u0648\u0631\u0646\u0627\u06cc\u0646\u0648"
    ],
    "name:fra_x_preferred":[
        "San Sadurni\u00f1o"
    ],
    "name:glg_x_preferred":[
        "San Sadurni\u00f1o"
    ],
    "name:hun_x_preferred":[
        "San Sadurni\u00f1o"
    ],
    "name:ita_x_preferred":[
        "San Sadurni\u00f1o"
    ],
    "name:jpn_x_preferred":[
        "\u30b5\u30f3\u30fb\u30b5\u30c9\u30a5\u30eb\u30cb\u30fc\u30cb\u30e7"
    ],
    "name:lmo_x_preferred":[
        "San Sadurni\u00f1o"
    ],
    "name:mkd_x_preferred":[
        "\u0421\u0430\u043d \u0421\u0430\u0434\u0443\u0440\u043d\u0438\u045a\u043e"
    ],
    "name:msa_x_preferred":[
        "San Sadurni\u00f1o"
    ],
    "name:nan_x_preferred":[
        "San Sadurni\u00f1o"
    ],
    "name:nld_x_preferred":[
        "San Sadurni\u00f1o"
    ],
    "name:oci_x_preferred":[
        "San Sadurni\u00f1o"
    ],
    "name:pol_x_preferred":[
        "San Sadurni\u00f1o"
    ],
    "name:por_x_preferred":[
        "San Sadurni\u00f1o"
    ],
    "name:rus_x_preferred":[
        "\u0421\u0430\u043d-\u0421\u0430\u0442\u0443\u0440\u043d\u0438\u043d\u043e"
    ],
    "name:spa_x_preferred":[
        "San Saturnino"
    ],
    "name:swe_x_preferred":[
        "San Sadurni\u00f1o"
    ],
    "name:tur_x_preferred":[
        "San Sadurni\u00f1o"
    ],
    "name:ukr_x_preferred":[
        "\u0421\u0430\u043d-\u0421\u0430\u0434\u0443\u0440\u043d\u0456\u043d\u044c\u0439\u043e"
    ],
    "name:uzb_x_preferred":[
        "San Sadurni\u00f1o"
    ],
    "name:vie_x_preferred":[
        "San Sadurni\u00f1o"
    ],
    "name:war_x_preferred":[
        "San Sadurni\u00f1o"
    ],
    "name:zho_x_preferred":[
        "\u5723\u8428\u56fe\u5c14\u5c3c\u8bfa"
    ],
    "qs_pg:aaroncc":"ES",
    "qs_pg:gn_country":"ES",
    "qs_pg:gn_fcode":"PPLA3",
    "qs_pg:gn_pop":0,
    "qs_pg:name":"San Sadurni\u00f1o",
    "qs_pg:name_adm0":"Espa\u00f1a",
    "qs_pg:name_adm1":"Galicia",
    "qs_pg:photos":269,
    "qs_pg:photos_1k":55,
    "qs_pg:photos_9k":1,
    "qs_pg:photos_9r":4,
    "qs_pg:photos_all":269,
    "qs_pg:photos_sr":5,
    "qs_pg:pop_sr":0,
    "qs_pg:qs_pg_placetype":"locality",
    "qs_pg:qs_pg_placetype_gp":"Town",
    "qs_pg:woe_adm0":23424950,
    "woe:adm0_id":23424950,
    "woe:name_adm0":"Espa\u00f1a",
    "woe:name_adm1":"Galicia",
    "woe:placetype":"Town",
    "wof:name":"San Sadurni\u00f1o",
    "wof:placetype":"locality"
},
  "geometry": {"coordinates":[-8.06667,43.53333],"type":"Point"}
}