{
  "type": "Feature",
  "properties": {
    "gn:admin1_code":"52",
    "gn:admin2_code":"HU",
    "gn:admin3_code":"22067",
    "gn:admin4_code":"25173.0",
    "gn:asciiname":"Gabarret",
    "gn:country_code":"ES",
    "gn:dem":1194,
    "gn:feature_class":"P",
    "gn:feature_code":"PPL",
    "gn:name":"Gabarret",
    "gn:population":0,
    "gn:timezone":"Europe/Madrid",
    "iso:country":"ES",
    "wof:name":"Gabarret",
    "wof:placetype":"locality"
},
  "geometry": {"coordinates":[0.70896,42.41615],"type":"Point"}
}