{
  "type": "Feature",
  "properties": {
    "gn:admin1_code":"52",
    "gn:admin2_code":"HU",
    "gn:admin3_code":"22067",
    "gn:admin4_code":"25173.0",
    "gn:asciiname":"Gabarret",
    "gn:country_code":"ES",
    "gn:dem":1194,
    "gn:feature_class":"P",
    "gn:feature_code":"PPL",
    "gn:name":"Gabarret",
    "gn:population":0,
    "gn:timezone":"Europe/Madrid",
    "iso:country":"ES",
    "name:cat_x_preferred":[
        "Gavarret"
    ],
    "name:ceb_x_preferred":[
        "Gabarret"
    ],
    "name:deu_x_preferred":[
        "Gabarret"
    ],
    "name:eus_x_preferred":[
        "Gabarret"
    ],
    "name:fra_x_preferred":[
        "Gabarret"
    ],
    "name:hun_x_preferred":[
        "Gabarret"
    ],
    "name:ita_x_preferred":[
        "Gabarret"
    ],
    "name:kaz_x_preferred":[
        "\u0413\u0430\u0431\u0430\u0440\u0440\u0435"
    ],
    "name:lat_x_preferred":[
        "Gabarret"
    ],
    "name:msa_x_preferred":[
        "Gabarret"
    ],
    "name:nld_x_preferred":[
        "Gabarret"
    ],
    "name:oci_x_preferred":[
        "Gavarret"
    ],
    "name:pms_x_preferred":[
        "Gabarret"
    ],
    "name:pol_x_preferred":[
        "Gabarret"
    ],
    "name:por_x_preferred":[
        "Gabarret"
    ],
    "name:ron_x_preferred":[
        "Gabarret"
    ],
    "name:slk_x_preferred":[
        "Gabarret"
    ],
    "name:slv_x_preferred":[
        "Gabarret"
    ],
    "name:spa_x_preferred":[
        "Gabarret"
    ],
    "name:swe_x_preferred":[
        "Gabarret"
    ],
    "name:ukr_x_preferred":[
        "\u0413\u0430\u0431\u0430\u0440\u0440\u0435"
    ],
    "name:uzb_x_preferred":[
        "Gabarret"
    ],
    "name:vie_x_preferred":[
        "Gabarret"
    ],
    "name:vol_x_preferred":[
        "Gabarret"
    ],
    "name:war_x_preferred":[
        "Gabarret"
    ],
    "name:zho_x_preferred":[
        "\u52a0\u5df4\u96f7"
    ],
    "wof:name":"Gabarret",
    "wof:placetype":"locality"
},
  "geometry": {"coordinates":[0.70896,42.41615],"type":"Point"}
}