{
  "type": "Feature",
  "properties": {
    "gn:gn_country":"ES",
    "gn:gn_fcode":"PPLA3",
    "gn:gn_pop":49,
    "gn:population":49,
    "iso:country":"ES",
    "name:arg_x_preferred":[
        "Cubla"
    ],
    "name:ast_x_preferred":[
        "Cubla"
    ],
    "name:cat_x_preferred":[
        "Cubla"
    ],
    "name:ceb_x_preferred":[
        "Cubla"
    ],
    "name:eng_x_preferred":[
        "Cubla"
    ],
    "name:eus_x_preferred":[
        "Cubla"
    ],
    "name:fas_x_preferred":[
        "\u06a9\u0648\u0628\u0644\u0627"
    ],
    "name:fra_x_preferred":[
        "Cubla"
    ],
    "name:glg_x_preferred":[
        "Cubla"
    ],
    "name:hun_x_preferred":[
        "Cubla"
    ],
    "name:ita_x_preferred":[
        "Cubla"
    ],
    "name:kaz_x_preferred":[
        "\u041a\u0443\u0431\u043b\u0430"
    ],
    "name:msa_x_preferred":[
        "Cubla"
    ],
    "name:nan_x_preferred":[
        "Cubla"
    ],
    "name:nld_x_preferred":[
        "Cubla"
    ],
    "name:oci_x_preferred":[
        "Cubla"
    ],
    "name:pol_x_preferred":[
        "Cubla"
    ],
    "name:por_x_preferred":[
        "Cubla"
    ],
    "name:rus_x_preferred":[
        "\u041a\u0443\u0431\u043b\u0430"
    ],
    "name:spa_x_preferred":[
        "Cubla"
    ],
    "name:swe_x_preferred":[
        "Cubla"
    ],
    "name:ukr_x_preferred":[
        "\u041a\u0443\u0431\u043b\u0430"
    ],
    "name:uzb_x_preferred":[
        "Cubla"
    ],
    "name:vie_x_preferred":[
        "Cubla"
    ],
    "name:war_x_preferred":[
        "Cubla"
    ],
    "name:zho_x_preferred":[
        "\u5e93\u592b\u62c9"
    ],
    "qs_pg:aaroncc":"ES",
    "qs_pg:gn_country":"ES",
    "qs_pg:gn_fcode":"PPLA3",
    "qs_pg:gn_pop":49,
    "qs_pg:name":"Cubla",
    "qs_pg:name_adm0":"Espa\u00f1a",
    "qs_pg:name_adm1":"Arag\u00f3n",
    "qs_pg:photos_9r":0,
    "qs_pg:photos_sr":0,
    "qs_pg:pop_sr":1,
    "qs_pg:qs_pg_placetype":"locality",
    "qs_pg:qs_pg_placetype_gp":"Town",
    "qs_pg:woe_adm0":23424950,
    "woe:adm0_id":23424950,
    "woe:name_adm0":"Espa\u00f1a",
    "woe:name_adm1":"Arag\u00f3n",
    "woe:placetype":"Town",
    "wof:name":"Cubla",
    "wof:placetype":"locality",
    "wof:population":49
},
  "geometry": {"coordinates":[-1.07917,40.20978],"type":"Point"}
}