{
  "type": "Feature",
  "properties": {
    "gn:gn_country":"ES",
    "gn:gn_fcode":"PPLA3",
    "gn:gn_pop":547,
    "gn:population":547,
    "iso:country":"ES",
    "name:ara_x_preferred":[
        "\u0643\u0648\u0631\u0628\u0627\u060c \u0645\u062f\u0631\u064a\u062f"
    ],
    "name:ara_x_variant":[
        "\u0643\u0648\u0631\u0628\u0627"
    ],
    "name:ast_x_preferred":[
        "Corpa"
    ],
    "name:cat_x_preferred":[
        "Corpa"
    ],
    "name:ceb_x_preferred":[
        "Corpa"
    ],
    "name:eng_x_preferred":[
        "Corpa"
    ],
    "name:epo_x_preferred":[
        "Corpa"
    ],
    "name:eus_x_preferred":[
        "Corpa"
    ],
    "name:fra_x_preferred":[
        "Corpa"
    ],
    "name:hun_x_preferred":[
        "Corpa"
    ],
    "name:ita_x_preferred":[
        "Corpa"
    ],
    "name:ltz_x_preferred":[
        "Corpa"
    ],
    "name:msa_x_preferred":[
        "Corpa"
    ],
    "name:nan_x_preferred":[
        "Corpa"
    ],
    "name:nld_x_preferred":[
        "Corpa"
    ],
    "name:oci_x_preferred":[
        "Corpa"
    ],
    "name:pol_x_preferred":[
        "Corpa"
    ],
    "name:por_x_preferred":[
        "Corpa"
    ],
    "name:sco_x_preferred":[
        "Corpa"
    ],
    "name:spa_x_preferred":[
        "Corpa"
    ],
    "name:sqi_x_preferred":[
        "Corpa"
    ],
    "name:swe_x_preferred":[
        "Corpa"
    ],
    "name:ukr_x_preferred":[
        "\u041a\u043e\u0440\u043f\u0430"
    ],
    "name:vie_x_preferred":[
        "Corpa"
    ],
    "name:war_x_preferred":[
        "Corpa"
    ],
    "name:zho_x_preferred":[
        "\u79d1\u5c14\u5e15"
    ],
    "qs_pg:aaroncc":"ES",
    "qs_pg:gn_country":"ES",
    "qs_pg:gn_fcode":"PPLA3",
    "qs_pg:gn_pop":547,
    "qs_pg:name":"Corpa",
    "qs_pg:name_adm0":"Espa\u00f1a",
    "qs_pg:name_adm1":"Comunidad de Madrid",
    "qs_pg:photos_9k":1,
    "qs_pg:photos_9r":1,
    "qs_pg:photos_all":1,
    "qs_pg:photos_sr":0,
    "qs_pg:pop_sr":2,
    "qs_pg:qs_pg_placetype":"locality",
    "qs_pg:qs_pg_placetype_gp":"Town",
    "qs_pg:woe_adm0":23424950,
    "woe:adm0_id":23424950,
    "woe:name_adm0":"Espa\u00f1a",
    "woe:name_adm1":"Comunidad de Madrid",
    "woe:placetype":"Town",
    "wof:name":"Corpa",
    "wof:placetype":"locality",
    "wof:population":547
},
  "geometry": {"coordinates":[-3.26003,40.42327],"type":"Point"}
}