{
  "type": "Feature",
  "properties": {
    "gn:admin1_code":"55",
    "gn:admin2_code":"LE",
    "gn:admin3_code":"24070",
    "gn:asciiname":"Barcena de la Abadia",
    "gn:country_code":"ES",
    "gn:dem":711,
    "gn:feature_class":"P",
    "gn:feature_code":"PPL",
    "gn:name":"B\u00e1rcena de la Abad\u00eda",
    "gn:population":0,
    "gn:timezone":"Europe/Madrid",
    "iso:country":"ES",
    "name:und_x_variant":[
        "B\u00e1rcena de la Abad\u00eda"
    ],
    "wof:name":"Barcena de la Abadia",
    "wof:placetype":"locality"
},
  "geometry": {"coordinates":[-6.63142,42.7888],"type":"Point"}
}