{
  "type": "Feature",
  "properties": {
    "gn:admin1_code":"31",
    "gn:admin2_code":"MU",
    "gn:admin3_code":"30035",
    "gn:asciiname":"Roda",
    "gn:country_code":"ES",
    "gn:dem":21,
    "gn:feature_class":"P",
    "gn:feature_code":"PPL",
    "gn:name":"Roda",
    "gn:population":0,
    "gn:timezone":"Europe/Madrid",
    "iso:country":"ES",
    "wof:name":"Roda",
    "wof:placetype":"locality"
},
  "geometry": {"coordinates":[-0.85889,37.77176],"type":"Point"}
}