{
  "type": "Feature",
  "properties": {
    "gn:admin1_code":"51",
    "gn:admin2_code":"SE",
    "gn:admin3_code":"41031",
    "gn:asciiname":"El Peralejo",
    "gn:country_code":"ES",
    "gn:dem":505,
    "gn:feature_class":"P",
    "gn:feature_code":"PPL",
    "gn:name":"El Peralejo",
    "gn:population":0,
    "gn:timezone":"Europe/Madrid",
    "iso:country":"ES",
    "name:und_x_variant":[
        "El Paralejo",
        "El Peralejo"
    ],
    "wof:name":"El Peralejo",
    "wof:placetype":"locality"
},
  "geometry": {"coordinates":[-6.41449,37.71497],"type":"Point"}
}