{
  "type": "Feature",
  "properties": {
    "gn:gn_country":"ES",
    "gn:gn_fcode":"PPL",
    "gn:gn_pop":3072,
    "gn:population":3072,
    "iso:country":"ES",
    "name:unk_x_variant":[
        "Morcin"
    ],
    "qs_pg:aaroncc":"ES",
    "qs_pg:gn_country":"ES",
    "qs_pg:gn_fcode":"PPL",
    "qs_pg:gn_pop":3072,
    "qs_pg:name":"Castandiello",
    "qs_pg:name_adm0":"Espa\u00f1a",
    "qs_pg:name_adm1":"Principado de Asturias",
    "qs_pg:photos":195,
    "qs_pg:photos_1k":40,
    "qs_pg:photos_9k":1,
    "qs_pg:photos_9r":4,
    "qs_pg:photos_all":195,
    "qs_pg:photos_sr":4,
    "qs_pg:pop_sr":4,
    "qs_pg:qs_pg_placetype":"locality",
    "qs_pg:qs_pg_placetype_gp":"Town",
    "qs_pg:woe_adm0":23424950,
    "woe:adm0_id":23424950,
    "woe:name_adm0":"Espa\u00f1a",
    "woe:name_adm1":"Principado de Asturias",
    "woe:placetype":"Town",
    "wof:name":"Castandiello",
    "wof:placetype":"locality",
    "wof:population":3072
},
  "geometry": {"coordinates":[-5.892,43.27962],"type":"Point"}
}