{
  "type": "Feature",
  "properties": {
    "gn:admin1_code":"51",
    "gn:admin2_code":"SE",
    "gn:admin3_code":"41031",
    "gn:asciiname":"Las Cortecillas",
    "gn:country_code":"ES",
    "gn:dem":392,
    "gn:feature_class":"P",
    "gn:feature_code":"PPL",
    "gn:name":"Las Cortecillas",
    "gn:population":0,
    "gn:timezone":"Europe/Madrid",
    "iso:country":"ES",
    "wof:name":"Las Cortecillas",
    "wof:placetype":"locality"
},
  "geometry": {"coordinates":[-6.37215,37.74358],"type":"Point"}
}