{
  "type": "Feature",
  "properties": {
    "gn:gn_country":"ES",
    "gn:gn_fcode":"PPLA3",
    "gn:gn_pop":21,
    "gn:population":21,
    "iso:country":"ES",
    "name:arg_x_preferred":[
        "Castiello Nuevo"
    ],
    "name:ast_x_preferred":[
        "Castillonuevo"
    ],
    "name:bre_x_preferred":[
        "Gazteluberri"
    ],
    "name:cat_x_preferred":[
        "Gazteluberri"
    ],
    "name:ceb_x_preferred":[
        "Castillonuevo"
    ],
    "name:eng_x_preferred":[
        "Castillo-Nuevo"
    ],
    "name:eus_x_preferred":[
        "Gazteluberri"
    ],
    "name:fra_x_preferred":[
        "Castillo-Nuevo"
    ],
    "name:hun_x_preferred":[
        "Castillo-Nuevo"
    ],
    "name:ita_x_preferred":[
        "Castillonuevo"
    ],
    "name:jpn_x_preferred":[
        "\u30ab\u30b9\u30c6\u30a3\u30ea\u30e7\u30cc\u30a8\u30dc"
    ],
    "name:msa_x_preferred":[
        "Castillo-Nuevo"
    ],
    "name:nan_x_preferred":[
        "Castillo-Nuevo"
    ],
    "name:nld_x_preferred":[
        "Castillonuevo"
    ],
    "name:oci_x_preferred":[
        "Castillonuevo"
    ],
    "name:pol_x_preferred":[
        "Castillonuevo"
    ],
    "name:por_x_preferred":[
        "Castillonuevo"
    ],
    "name:rup_x_preferred":[
        "Castillonuevo"
    ],
    "name:rus_x_preferred":[
        "\u041a\u0430\u0441\u0442\u0438\u043b\u044c\u043e\u043d\u0443\u044d\u0432\u043e"
    ],
    "name:spa_x_preferred":[
        "Castillo-Nuevo"
    ],
    "name:swe_x_preferred":[
        "Castillonuevo"
    ],
    "name:ukr_x_preferred":[
        "\u041a\u0430\u0441\u0442\u0456\u043b\u044c\u0439\u043e\u043d\u0443\u0435\u0432\u043e"
    ],
    "name:uzb_x_preferred":[
        "Castillonuevo"
    ],
    "name:vie_x_preferred":[
        "Castillo-Nuevo"
    ],
    "name:war_x_preferred":[
        "Castillo-Nuevo"
    ],
    "name:zho_x_preferred":[
        "\u5361\u65af\u8482\u7565\u52aa\u57c3\u6c83"
    ],
    "qs_pg:aaroncc":"ES",
    "qs_pg:gn_country":"ES",
    "qs_pg:gn_fcode":"PPLA3",
    "qs_pg:gn_pop":21,
    "qs_pg:name":"Castillonuevo",
    "qs_pg:name_adm0":"Espa\u00f1a",
    "qs_pg:name_adm1":"Comunidad Foral de Navarra",
    "qs_pg:photos_9r":0,
    "qs_pg:photos_sr":0,
    "qs_pg:pop_sr":1,
    "qs_pg:qs_pg_placetype":"locality",
    "qs_pg:qs_pg_placetype_gp":"Town",
    "qs_pg:woe_adm0":23424950,
    "woe:adm0_id":23424950,
    "woe:name_adm0":"Espa\u00f1a",
    "woe:name_adm1":"Comunidad Foral de Navarra",
    "woe:placetype":"Town",
    "wof:name":"Castillonuevo",
    "wof:placetype":"locality",
    "wof:population":21
},
  "geometry": {"coordinates":[-1.03121,42.6827],"type":"Point"}
}