{
  "type": "Feature",
  "properties": {
    "gn:admin1_code":"34",
    "gn:admin2_code":"O",
    "gn:admin3_code":"33048",
    "gn:asciiname":"Pelorde",
    "gn:country_code":"ES",
    "gn:dem":148,
    "gn:feature_class":"P",
    "gn:feature_code":"PPL",
    "gn:name":"Pelorde",
    "gn:population":0,
    "gn:timezone":"Europe/Madrid",
    "iso:country":"ES",
    "wof:name":"Pelorde",
    "wof:placetype":"locality"
},
  "geometry": {"coordinates":[-6.83333,43.26667],"type":"Point"}
}