{
  "type": "Feature",
  "properties": {
    "gn:admin1_code":"58",
    "gn:admin2_code":"C",
    "gn:admin3_code":"15066",
    "gn:asciiname":"O Pino",
    "gn:country_code":"ES",
    "gn:dem":361,
    "gn:feature_class":"P",
    "gn:feature_code":"PPL",
    "gn:name":"O Pino",
    "gn:population":0,
    "gn:timezone":"Europe/Madrid",
    "iso:country":"ES",
    "wof:name":"O Pino",
    "wof:placetype":"locality"
},
  "geometry": {"coordinates":[-8.33284,42.93587],"type":"Point"}
}