{
  "type": "Feature",
  "properties": {
    "gn:admin1_code":"58",
    "gn:admin2_code":"C",
    "gn:admin3_code":"15066",
    "gn:asciiname":"O Pino",
    "gn:country_code":"ES",
    "gn:dem":361,
    "gn:feature_class":"P",
    "gn:feature_code":"PPL",
    "gn:name":"O Pino",
    "gn:population":0,
    "gn:timezone":"Europe/Madrid",
    "iso:country":"ES",
    "name:ara_x_preferred":[
        "\u0623\u0648 \u0628\u064a\u0646\u0648"
    ],
    "name:azb_x_preferred":[
        "\u0627\u0644 \u067e\u06cc\u0646\u0648"
    ],
    "name:bre_x_preferred":[
        "O Pino"
    ],
    "name:cat_x_preferred":[
        "O Pino"
    ],
    "name:deu_x_preferred":[
        "O Pino"
    ],
    "name:eus_x_preferred":[
        "O Pino"
    ],
    "name:fas_x_preferred":[
        "\u0627\u0644 \u067e\u06cc\u0646\u0648"
    ],
    "name:fra_x_preferred":[
        "O Pino"
    ],
    "name:glg_x_preferred":[
        "O Pino"
    ],
    "name:hun_x_preferred":[
        "O Pino"
    ],
    "name:ita_x_preferred":[
        "O Pino"
    ],
    "name:jpn_x_preferred":[
        "\u30aa\u30fb\u30d4\u30ce"
    ],
    "name:lmo_x_preferred":[
        "O Pino"
    ],
    "name:mkd_x_preferred":[
        "\u041e \u041f\u0438\u043d\u043e"
    ],
    "name:msa_x_preferred":[
        "O Pino"
    ],
    "name:nld_x_preferred":[
        "O Pino"
    ],
    "name:oci_x_preferred":[
        "O Pino"
    ],
    "name:pol_x_preferred":[
        "O Pino"
    ],
    "name:por_x_preferred":[
        "O Pino"
    ],
    "name:rus_x_preferred":[
        "\u042d\u043b\u044c-\u041f\u0438\u043d\u043e"
    ],
    "name:spa_x_preferred":[
        "El Pino"
    ],
    "name:tur_x_preferred":[
        "O Pino"
    ],
    "name:ukr_x_preferred":[
        "\u041e-\u041f\u0456\u043d\u043e"
    ],
    "name:uzb_x_preferred":[
        "O Pino"
    ],
    "name:vie_x_preferred":[
        "O Pino"
    ],
    "name:war_x_preferred":[
        "O Pino"
    ],
    "name:zho_x_preferred":[
        "\u6b27\u76ae\u8bfa"
    ],
    "wof:name":"O Pino",
    "wof:placetype":"locality"
},
  "geometry": {"coordinates":[-8.33284,42.93587],"type":"Point"}
}