{
  "type": "Feature",
  "properties": {
    "gn:admin1_code":"34",
    "gn:admin2_code":"O",
    "gn:admin3_code":"33041",
    "gn:asciiname":"Pinera",
    "gn:country_code":"ES",
    "gn:dem":81,
    "gn:feature_class":"P",
    "gn:feature_code":"PPL",
    "gn:name":"Pi\u00f1era",
    "gn:population":0,
    "gn:timezone":"Europe/Madrid",
    "iso:country":"ES",
    "name:und_x_variant":[
        "San Salvador de Pi\u00f1era",
        "Pi\u00f1era"
    ],
    "wof:name":"Pinera",
    "wof:placetype":"locality"
},
  "geometry": {"coordinates":[-6.67138,43.54304000000001],"type":"Point"}
}