{
  "type": "Feature",
  "properties": {
    "gn:country":"ES",
    "gn:fcode":"PPLA3",
    "gn:population":786,
    "iso:country":"ES",
    "name:ara_x_preferred":[
        "\u0625\u064a\u0633\u062a\u064a\u0628\u0627\u0631"
    ],
    "name:arg_x_preferred":[
        "Est\u00e9par"
    ],
    "name:ast_x_preferred":[
        "Est\u00e9par"
    ],
    "name:azb_x_preferred":[
        "\u0627\u0633\u062a\u067e\u0627\u0631"
    ],
    "name:cat_x_preferred":[
        "Est\u00e9par"
    ],
    "name:ceb_x_preferred":[
        "Est\u00e9par"
    ],
    "name:eng_x_preferred":[
        "Est\u00e9par"
    ],
    "name:eus_x_preferred":[
        "Est\u00e9par"
    ],
    "name:fas_x_preferred":[
        "\u0627\u0633\u062a\u067e\u0627\u0631"
    ],
    "name:fra_x_preferred":[
        "Est\u00e9par"
    ],
    "name:glg_x_preferred":[
        "Est\u00e9par"
    ],
    "name:haw_x_preferred":[
        "Est\u00e9par"
    ],
    "name:hun_x_preferred":[
        "Est\u00e9par"
    ],
    "name:ina_x_preferred":[
        "Est\u00e9par"
    ],
    "name:ita_x_preferred":[
        "Est\u00e9par"
    ],
    "name:lad_x_preferred":[
        "Est\u00e9par"
    ],
    "name:msa_x_preferred":[
        "Est\u00e9par"
    ],
    "name:nan_x_preferred":[
        "Est\u00e9par"
    ],
    "name:nld_x_preferred":[
        "Est\u00e9par"
    ],
    "name:oci_x_preferred":[
        "Est\u00e9par"
    ],
    "name:pol_x_preferred":[
        "Est\u00e9par"
    ],
    "name:por_x_preferred":[
        "Est\u00e9par"
    ],
    "name:rus_x_preferred":[
        "\u042d\u0441\u0442\u0435\u043f\u0430\u0440"
    ],
    "name:spa_x_preferred":[
        "Est\u00e9par"
    ],
    "name:swe_x_preferred":[
        "Est\u00e9par"
    ],
    "name:tpi_x_preferred":[
        "Est\u00e9par"
    ],
    "name:ukr_x_preferred":[
        "\u0415\u0441\u0442\u0435\u043f\u0430\u0440"
    ],
    "name:vie_x_preferred":[
        "Est\u00e9par"
    ],
    "name:war_x_preferred":[
        "Est\u00e9par"
    ],
    "name:zho_x_preferred":[
        "\u57c3\u65af\u7279\u5e15\u5c14"
    ],
    "qs_pg:aaroncc":"ES",
    "qs_pg:gn_country":"ES",
    "qs_pg:gn_fcode":"PPLA3",
    "qs_pg:gn_pop":786,
    "qs_pg:name":"Est\u00e9par",
    "qs_pg:name_adm0":"Espa\u00f1a",
    "qs_pg:name_adm1":"Castilla y Le\u00f3n",
    "qs_pg:photos_9r":0,
    "qs_pg:photos_sr":0,
    "qs_pg:pop_sr":2,
    "qs_pg:qs_pg_placetype":"locality",
    "qs_pg:qs_pg_placetype_gp":"Town",
    "qs_pg:woe_adm0":23424950,
    "woe:adm0_id":23424950,
    "woe:name_adm0":"Espa\u00f1a",
    "woe:name_adm1":"Castilla y Le\u00f3n",
    "woe:placetype":"Town",
    "wof:name":"Est\u00e9par",
    "wof:placetype":"locality",
    "wof:population":786
},
  "geometry": {"coordinates":[-3.89946,42.27731],"type":"Point"}
}