{
  "type": "Feature",
  "properties": {
    "gn:gn_country":"ES",
    "gn:gn_fcode":"PPL",
    "gn:gn_pop":123,
    "gn:population":123,
    "iso:country":"ES",
    "name:alb_x_preferred":[
        "Xodos"
    ],
    "name:ara_x_preferred":[
        "\u062a\u0634\u0648\u062f\u0648\u0633"
    ],
    "name:arg_x_preferred":[
        "Chodos"
    ],
    "name:baq_x_preferred":[
        "Xodos"
    ],
    "name:bul_x_preferred":[
        "\u0427\u043e\u0434\u043e\u0441"
    ],
    "name:cat_x_preferred":[
        "Xodos"
    ],
    "name:chi_x_preferred":[
        "\u4e54\u591a\u65af"
    ],
    "name:dut_x_preferred":[
        "Chodos"
    ],
    "name:eng_x_preferred":[
        "Xodos / Chodos"
    ],
    "name:fre_x_preferred":[
        "Xodos"
    ],
    "name:glg_x_preferred":[
        "Xodos"
    ],
    "name:hun_x_preferred":[
        "Chodos"
    ],
    "name:ita_x_preferred":[
        "Chodos"
    ],
    "name:may_x_preferred":[
        "Chodos/Xodos"
    ],
    "name:nan_x_preferred":[
        "Xodos"
    ],
    "name:oci_x_preferred":[
        "Chodos"
    ],
    "name:pol_x_preferred":[
        "Chodos"
    ],
    "name:por_x_preferred":[
        "Chodos"
    ],
    "name:rus_x_preferred":[
        "\u0427\u043e\u0434\u043e\u0441"
    ],
    "name:spa_x_preferred":[
        "Chodos"
    ],
    "name:swe_x_preferred":[
        "Chodos"
    ],
    "name:ukr_x_preferred":[
        "\u0427\u043e\u0434\u043e\u0441"
    ],
    "name:uzb_x_preferred":[
        "Chodos"
    ],
    "name:vie_x_preferred":[
        "Chodos"
    ],
    "name:war_x_preferred":[
        "Xodos"
    ],
    "qs_pg:aaroncc":"ES",
    "qs_pg:gn_country":"ES",
    "qs_pg:gn_fcode":"PPL",
    "qs_pg:gn_pop":123,
    "qs_pg:name":"Chodos",
    "qs_pg:name_adm0":"Espa\u00f1a",
    "qs_pg:name_adm1":"Comunitat Valenciana",
    "qs_pg:photos":99,
    "qs_pg:photos_1k":20,
    "qs_pg:photos_9k":1,
    "qs_pg:photos_9r":3,
    "qs_pg:photos_all":99,
    "qs_pg:photos_sr":3,
    "qs_pg:pop_sr":1,
    "qs_pg:qs_pg_placetype":"locality",
    "qs_pg:qs_pg_placetype_gp":"Town",
    "qs_pg:woe_adm0":23424950,
    "woe:adm0_id":23424950,
    "woe:name_adm0":"Espa\u00f1a",
    "woe:name_adm1":"Comunitat Valenciana",
    "woe:placetype":"Town",
    "wof:name":"Chodos",
    "wof:placetype":"locality",
    "wof:population":123
},
  "geometry": {"coordinates":[-0.28795,40.24517],"type":"Point"}
}