{
  "type": "Feature",
  "properties": {
    "gn:admin1_code":"34",
    "gn:admin2_code":"O",
    "gn:admin3_code":"33011",
    "gn:asciiname":"Villacibran",
    "gn:country_code":"ES",
    "gn:dem":791,
    "gn:feature_class":"P",
    "gn:feature_code":"PPL",
    "gn:name":"Villacibr\u00e1n",
    "gn:population":0,
    "gn:timezone":"Europe/Madrid",
    "iso:country":"ES",
    "name:und_x_variant":[
        "Villacibr\u00e1n"
    ],
    "wof:name":"Villacibran",
    "wof:placetype":"locality"
},
  "geometry": {"coordinates":[-6.52326,43.06465],"type":"Point"}
}