{
  "type": "Feature",
  "properties": {
    "gn:admin1_code":"60",
    "gn:admin2_code":"V",
    "gn:admin3_code":"46116",
    "gn:asciiname":"Vallesa de Mandor",
    "gn:cc2":"ES",
    "gn:country_code":"ES",
    "gn:dem":98,
    "gn:feature_class":"P",
    "gn:feature_code":"PPL",
    "gn:name":"Vallesa de Mandor",
    "gn:population":0,
    "gn:timezone":"Europe/Madrid",
    "iso:country":"ES",
    "name:und_x_variant":[
        "Caser\u00edo Vallesa de Mandor",
        "Vallesa de Mandor"
    ],
    "wof:name":"Vallesa de Mandor",
    "wof:placetype":"locality"
},
  "geometry": {"coordinates":[-0.51667,39.55],"type":"Point"}
}