{
  "type": "Feature",
  "properties": {
    "gn:admin1_code":"55",
    "gn:admin2_code":"SO",
    "gn:admin3_code":"42117",
    "gn:asciiname":"Campllonch",
    "gn:country_code":"ES",
    "gn:dem":1207,
    "gn:feature_class":"P",
    "gn:feature_code":"PPL",
    "gn:name":"Campllonch",
    "gn:population":0,
    "gn:timezone":"Europe/Madrid",
    "iso:country":"ES",
    "wof:name":"Campllonch",
    "wof:placetype":"locality"
},
  "geometry": {"coordinates":[-2.83333,41.88333],"type":"Point"}
}