{
  "type": "Feature",
  "properties": {
    "gn:admin1_code":"55",
    "gn:admin2_code":"SG",
    "gn:admin3_code":"40170",
    "gn:asciiname":"Becerril",
    "gn:country_code":"ES",
    "gn:dem":1238,
    "gn:feature_class":"P",
    "gn:feature_code":"PPL",
    "gn:name":"Becerril",
    "gn:population":0,
    "gn:timezone":"Europe/Madrid",
    "iso:country":"ES",
    "name:fra_x_preferred":[
        "Becerril"
    ],
    "name:ita_x_preferred":[
        "Becerril"
    ],
    "name:kat_x_preferred":[
        "\u10d1\u10d4\u10e1\u10d4\u10e0\u10d8\u10da\u10d8"
    ],
    "name:msa_x_preferred":[
        "Becerril"
    ],
    "name:nld_x_preferred":[
        "Becerril"
    ],
    "name:por_x_preferred":[
        "Becerril"
    ],
    "name:rus_x_preferred":[
        "\u0411\u0435\u0441\u0435\u0440\u0440\u0438\u043b\u044c"
    ],
    "name:spa_x_preferred":[
        "Becerril"
    ],
    "name:tgl_x_preferred":[
        "Becerril"
    ],
    "name:vie_x_preferred":[
        "Becerril"
    ],
    "name:war_x_preferred":[
        "Becerril"
    ],
    "name:zho_x_preferred":[
        "\u8c9d\u585e\u91cc\u723e"
    ],
    "wof:name":"Becerril",
    "wof:placetype":"locality"
},
  "geometry": {"coordinates":[-3.36461,41.2897],"type":"Point"}
}