{
  "type": "Feature",
  "properties": {
    "gn:country":"ES",
    "gn:fcode":"PPLA3",
    "gn:population":249,
    "iso:country":"ES",
    "name:arg_x_preferred":[
        "R\u00e1bano"
    ],
    "name:ast_x_preferred":[
        "R\u00e1bano"
    ],
    "name:azb_x_preferred":[
        "\u0631\u0627\u0628\u0627\u0646\u0648"
    ],
    "name:cat_x_preferred":[
        "R\u00e1bano"
    ],
    "name:ceb_x_preferred":[
        "R\u00e1bano"
    ],
    "name:che_x_preferred":[
        "\u0420\u0430\u0431\u0430\u043d\u043e"
    ],
    "name:deu_x_preferred":[
        "R\u00e1bano"
    ],
    "name:eng_x_preferred":[
        "R\u00e1bano"
    ],
    "name:epo_x_preferred":[
        "R\u00e1bano"
    ],
    "name:eus_x_preferred":[
        "R\u00e1bano"
    ],
    "name:fas_x_preferred":[
        "\u0631\u0627\u0628\u0627\u0646\u0648"
    ],
    "name:fra_x_preferred":[
        "R\u00e1bano"
    ],
    "name:gle_x_preferred":[
        "R\u00e1bano"
    ],
    "name:glg_x_preferred":[
        "R\u00e1bano"
    ],
    "name:hun_x_preferred":[
        "R\u00e1bano"
    ],
    "name:hye_x_preferred":[
        "\u054c\u0561\u0562\u0561\u0576\u0578"
    ],
    "name:ile_x_preferred":[
        "R\u00e1bano"
    ],
    "name:ina_x_preferred":[
        "R\u00e1bano"
    ],
    "name:ita_x_preferred":[
        "R\u00e1bano"
    ],
    "name:lld_x_preferred":[
        "R\u00e1bano"
    ],
    "name:msa_x_preferred":[
        "R\u00e1bano"
    ],
    "name:nan_x_preferred":[
        "R\u00e1bano"
    ],
    "name:nld_x_preferred":[
        "R\u00e1bano"
    ],
    "name:nob_x_preferred":[
        "R\u00e1bano"
    ],
    "name:oci_x_preferred":[
        "R\u00e1bano"
    ],
    "name:pol_x_preferred":[
        "R\u00e1bano"
    ],
    "name:por_x_preferred":[
        "R\u00e1bano"
    ],
    "name:rus_x_preferred":[
        "\u0420\u0430\u0431\u0430\u043d\u043e"
    ],
    "name:spa_x_preferred":[
        "R\u00e1bano"
    ],
    "name:swe_x_preferred":[
        "R\u00e1bano"
    ],
    "name:tat_x_preferred":[
        "\u0420\u0430\u0431\u0430\u043d\u043e"
    ],
    "name:ukr_x_preferred":[
        "\u0420\u0430\u0431\u0430\u043d\u043e"
    ],
    "name:uzb_x_preferred":[
        "R\u00e1bano"
    ],
    "name:vec_x_preferred":[
        "R\u00e1bano"
    ],
    "name:vie_x_preferred":[
        "R\u00e1bano"
    ],
    "name:war_x_preferred":[
        "R\u00e1bano"
    ],
    "name:zho_x_preferred":[
        "\u62c9\u74e6\u8bfa"
    ],
    "qs_pg:aaroncc":"ES",
    "qs_pg:gn_country":"ES",
    "qs_pg:gn_fcode":"PPLA3",
    "qs_pg:gn_pop":249,
    "qs_pg:name":"R\u00e1bano",
    "qs_pg:name_adm0":"Espa\u00f1a",
    "qs_pg:name_adm1":"Castilla y Le\u00f3n",
    "qs_pg:photos":36,
    "qs_pg:photos_1k":7,
    "qs_pg:photos_9k":1,
    "qs_pg:photos_9r":2,
    "qs_pg:photos_all":36,
    "qs_pg:photos_sr":2,
    "qs_pg:pop_sr":2,
    "qs_pg:qs_pg_placetype":"locality",
    "qs_pg:qs_pg_placetype_gp":"Town",
    "qs_pg:woe_adm0":23424950,
    "woe:adm0_id":23424950,
    "woe:name_adm0":"Espa\u00f1a",
    "woe:name_adm1":"Castilla y Le\u00f3n",
    "woe:placetype":"Town",
    "wof:name":"R\u00e1bano",
    "wof:placetype":"locality",
    "wof:population":249
},
  "geometry": {"coordinates":[-4.06214,41.53314],"type":"Point"}
}