{
  "type": "Feature",
  "properties": {
    "gn:admin1_code":"34",
    "gn:admin2_code":"O",
    "gn:admin3_code":"33011",
    "gn:asciiname":"San Esteban",
    "gn:country_code":"ES",
    "gn:dem":659,
    "gn:feature_class":"P",
    "gn:feature_code":"PPL",
    "gn:name":"San Esteban",
    "gn:population":0,
    "gn:timezone":"Europe/Madrid",
    "iso:country":"ES",
    "name:ast_x_preferred":[
        "San Esteban"
    ],
    "name:ceb_x_preferred":[
        "San Esteban"
    ],
    "name:deu_x_preferred":[
        "San Esteban"
    ],
    "name:eus_x_preferred":[
        "San Esteban"
    ],
    "name:fra_x_preferred":[
        "San Esteban"
    ],
    "name:ita_x_preferred":[
        "San Esteban"
    ],
    "name:nld_x_preferred":[
        "San Esteban"
    ],
    "name:por_x_preferred":[
        "San Esteban"
    ],
    "name:spa_x_preferred":[
        "San Esteban"
    ],
    "name:srp_x_preferred":[
        "\u0421\u0430\u043d \u0415\u0441\u0442\u0435\u0431\u0430\u043d"
    ],
    "name:swe_x_preferred":[
        "San Esteban"
    ],
    "name:war_x_preferred":[
        "San Esteban"
    ],
    "wof:name":"San Esteban",
    "wof:placetype":"locality"
},
  "geometry": {"coordinates":[-6.56667,43.11667],"type":"Point"}
}