{
  "type": "Feature",
  "properties": {
    "gn:gn_country":"ES",
    "gn:gn_fcode":"PPLA3",
    "gn:gn_pop":25,
    "gn:population":25,
    "iso:country":"ES",
    "name:arg_x_preferred":[
        "Torrecuadrada de Molina"
    ],
    "name:cat_x_preferred":[
        "Torrecuadrada de Molina"
    ],
    "name:deu_x_preferred":[
        "Torrecuadrada de Molina"
    ],
    "name:eng_x_preferred":[
        "Torrecuadrada de Molina"
    ],
    "name:eus_x_preferred":[
        "Torrecuadrada de Molina"
    ],
    "name:fra_x_preferred":[
        "Torrecuadrada de Molina"
    ],
    "name:hun_x_preferred":[
        "Torrecuadrada de Molina"
    ],
    "name:ina_x_preferred":[
        "Torrecuadrada de Molina"
    ],
    "name:ita_x_preferred":[
        "Torrecuadrada de Molina"
    ],
    "name:kaz_x_preferred":[
        "\u0422\u043e\u0440\u0440\u0435\u043a\u0443\u0430\u0434\u0440\u0430\u0434\u0430-\u0434\u0435-\u041c\u043e\u043b\u0438\u043d\u0430"
    ],
    "name:msa_x_preferred":[
        "Torrecuadrada de Molina"
    ],
    "name:nan_x_preferred":[
        "Torrecuadrada de Molina"
    ],
    "name:nld_x_preferred":[
        "Torrecuadrada de Molina"
    ],
    "name:oci_x_preferred":[
        "Torrecuadrada de Molina"
    ],
    "name:pol_x_preferred":[
        "Torrecuadrada de Molina"
    ],
    "name:por_x_preferred":[
        "Torrecuadrada de Molina"
    ],
    "name:rus_x_preferred":[
        "\u0422\u043e\u0440\u0440\u0435\u043a\u0443\u0430\u0434\u0440\u0430\u0434\u0430-\u0434\u0435-\u041c\u043e\u043b\u0438\u043d\u0430"
    ],
    "name:spa_x_preferred":[
        "Torrecuadrada de Molina"
    ],
    "name:swe_x_preferred":[
        "Torrecuadrada de Molina"
    ],
    "name:ukr_x_preferred":[
        "\u0422\u043e\u0440\u0440\u0435\u043a\u0443\u0430\u0434\u0440\u0430\u0434\u0430-\u0434\u0435-\u041c\u043e\u043b\u0456\u043d\u0430"
    ],
    "name:vie_x_preferred":[
        "Torrecuadrada de Molina"
    ],
    "name:war_x_preferred":[
        "Torrecuadrada de Molina"
    ],
    "name:zho_x_preferred":[
        "\u6258\u96f7\u5938\u5fb7\u62c9\u8fbe\u5fb7\u83ab\u5229\u7eb3"
    ],
    "qs_pg:aaroncc":"ES",
    "qs_pg:gn_country":"ES",
    "qs_pg:gn_fcode":"PPLA3",
    "qs_pg:gn_pop":25,
    "qs_pg:name":"Torrecuadrada de Molina",
    "qs_pg:name_adm0":"Espa\u00f1a",
    "qs_pg:name_adm1":"Castilla-La Mancha",
    "qs_pg:photos_9r":0,
    "qs_pg:photos_sr":0,
    "qs_pg:pop_sr":1,
    "qs_pg:qs_pg_placetype":"locality",
    "qs_pg:qs_pg_placetype_gp":"Town",
    "qs_pg:woe_adm0":23424950,
    "woe:adm0_id":23424950,
    "woe:name_adm0":"Espa\u00f1a",
    "woe:name_adm1":"Castilla-La Mancha",
    "woe:placetype":"Town",
    "wof:name":"Torrecuadrada de Molina",
    "wof:placetype":"locality",
    "wof:population":25
},
  "geometry": {"coordinates":[-1.80707,40.74946],"type":"Point"}
}