{
  "type": "Feature",
  "properties": {
    "gn:admin1_code":"53",
    "gn:admin2_code":"GC",
    "gn:admin3_code":"35009",
    "gn:asciiname":"Pico de Viento",
    "gn:cc2":"ES",
    "gn:country_code":"ES",
    "gn:dem":742,
    "gn:feature_class":"P",
    "gn:feature_code":"PPL",
    "gn:name":"Pico de Viento",
    "gn:population":0,
    "gn:timezone":"Atlantic/Canary",
    "iso:country":"ES",
    "name:und_x_variant":[
        "Pico del Viento"
    ],
    "wof:name":"Pico de Viento",
    "wof:placetype":"locality"
},
  "geometry": {"coordinates":[-15.65329,28.09939],"type":"Point"}
}