{
  "type": "Feature",
  "properties": {
    "gn:population":1065,
    "iso:country":"ES",
    "name:ara_x_preferred":[
        "\u062e\u064a\u0631\u064a\u062b \u062f\u064a\u0644 \u0645\u0627\u0631\u0643\u064a\u0633\u0627\u062f\u0648"
    ],
    "name:ast_x_preferred":[
        "J\u00e9rez del Marques\u00e1u"
    ],
    "name:cat_x_preferred":[
        "J\u00e9rez del Marquesado"
    ],
    "name:ceb_x_preferred":[
        "Jerez del Marquesado"
    ],
    "name:eng_x_preferred":[
        "Jeres del Marquesado"
    ],
    "name:eng_x_variant":[
        "J\u00e9rez del Marquesado"
    ],
    "name:epo_x_preferred":[
        "J\u00e9rez del Marquesado"
    ],
    "name:eus_x_preferred":[
        "J\u00e9rez del Marquesado"
    ],
    "name:fra_x_preferred":[
        "J\u00e9rez del Marquesado"
    ],
    "name:hun_x_preferred":[
        "J\u00e9rez del Marquesado"
    ],
    "name:hye_x_preferred":[
        "\u053d\u0565\u0580\u0565\u057d \u0564\u0565\u056c \u0544\u0561\u0580\u056f\u0565\u057d\u0561\u0564\u0578"
    ],
    "name:ita_x_preferred":[
        "J\u00e9rez del Marquesado"
    ],
    "name:kaz_x_preferred":[
        "\u0425\u0435\u0440\u0435\u0441-\u0434\u0435\u043b\u044c-\u041c\u0430\u0440\u043a\u0435\u0441\u0430\u0434\u043e"
    ],
    "name:msa_x_preferred":[
        "J\u00e9rez del Marquesado"
    ],
    "name:nan_x_preferred":[
        "J\u00e9rez del Marquesado"
    ],
    "name:nld_x_preferred":[
        "J\u00e9rez del Marquesado"
    ],
    "name:oci_x_preferred":[
        "Jerez del Marquesado"
    ],
    "name:pol_x_preferred":[
        "J\u00e9rez del Marquesado"
    ],
    "name:por_x_preferred":[
        "J\u00e9rez del Marquesado"
    ],
    "name:rus_x_preferred":[
        "\u0425\u0435\u0440\u0435\u0441-\u0434\u0435\u043b\u044c-\u041c\u0430\u0440\u043a\u0435\u0441\u0430\u0434\u043e"
    ],
    "name:spa_x_preferred":[
        "Jerez del Marquesado",
        "J\u00e9rez del Marquesado"
    ],
    "name:spa_x_variant":[
        "Jeres del Marquesado"
    ],
    "name:sqi_x_preferred":[
        "J\u00e9rez del Marquesado"
    ],
    "name:swe_x_preferred":[
        "Jerez del Marquesado"
    ],
    "name:tur_x_preferred":[
        "J\u00e9rez del Marquesado"
    ],
    "name:ukr_x_preferred":[
        "\u0425\u0435\u0440\u0435\u0441-\u0434\u0435\u043b\u044c-\u041c\u0430\u0440\u043a\u0435\u0441\u0430\u0434\u043e"
    ],
    "name:vie_x_preferred":[
        "J\u00e9rez del Marquesado"
    ],
    "name:war_x_preferred":[
        "Jerez del Marquesado"
    ],
    "name:zho_x_preferred":[
        "\u8d6b\u96f7\u65af\u5fb7\u5c14\u9a6c\u5c14\u514b\u8428\u591a"
    ],
    "qs:a0":"Espa\u00f1a",
    "qs:a1":"*Granada",
    "qs:a1r":"0Andaluc\u00eda",
    "qs:adm0":"Espa\u00f1a",
    "qs:la_lc":"*",
    "qs:level":"locality",
    "qs:loc":"Jerez del Marquesado",
    "qs:loc_alt":"Jerez del Marquesado",
    "qs:pop":0,
    "qs:type":"buffered point",
    "wd:wordcount":13,
    "wof:lang":[
        "spa"
    ],
    "wof:name":"Jerez del Marquesado",
    "wof:placetype":"locality",
    "wof:population":1065
},
  "geometry": {"coordinates":[-3.158977,37.184002],"type":"Point"}
}