{
  "type": "Feature",
  "properties": {
    "gn:admin1_code":"39",
    "gn:admin2_code":"S",
    "gn:admin3_code":"39076",
    "gn:asciiname":"Vispieres",
    "gn:country_code":"ES",
    "gn:dem":102,
    "gn:feature_class":"P",
    "gn:feature_code":"PPL",
    "gn:name":"Vispieres",
    "gn:population":0,
    "gn:timezone":"Europe/Madrid",
    "iso:country":"ES",
    "wof:name":"Vispieres",
    "wof:placetype":"locality"
},
  "geometry": {"coordinates":[-4.09752,43.37377],"type":"Point"}
}