{
  "type": "Feature",
  "properties": {
    "gn:admin1_code":"58",
    "gn:admin2_code":"LU",
    "gn:admin3_code":"27060",
    "gn:asciiname":"Castelo",
    "gn:country_code":"ES",
    "gn:dem":416,
    "gn:feature_class":"P",
    "gn:feature_code":"PPL",
    "gn:name":"Castelo",
    "gn:population":0,
    "gn:timezone":"Europe/Madrid",
    "iso:country":"ES",
    "wof:name":"Castelo",
    "wof:placetype":"locality"
},
  "geometry": {"coordinates":[-7.74506,42.69158],"type":"Point"}
}