{
  "type": "Feature",
  "properties": {
    "gn:admin1_code":"55",
    "gn:admin2_code":"LE",
    "gn:admin3_code":"24196",
    "gn:asciiname":"Penoselo",
    "gn:country_code":"ES",
    "gn:dem":899,
    "gn:feature_class":"P",
    "gn:feature_code":"PPL",
    "gn:name":"Penoselo",
    "gn:population":0,
    "gn:timezone":"Europe/Madrid",
    "iso:country":"ES",
    "wof:name":"Penoselo",
    "wof:placetype":"locality"
},
  "geometry": {"coordinates":[-6.75368,42.75803],"type":"Point"}
}