{
  "type": "Feature",
  "properties": {
    "iso:country":"ES",
    "name:arg_x_preferred":[
        "Torralba del R\u00edo"
    ],
    "name:baq_x_preferred":[
        "Torralba del R\u00edo"
    ],
    "name:bre_x_preferred":[
        "Torralba del R\u00edo"
    ],
    "name:cat_x_preferred":[
        "Torralba del R\u00edo"
    ],
    "name:chi_x_preferred":[
        "\u6ee8\u6cb3\u6258\u62c9\u5c14\u74e6"
    ],
    "name:dut_x_preferred":[
        "Torralba del R\u00edo"
    ],
    "name:eng_x_preferred":[
        "Torralba Del R\u00edo"
    ],
    "name:fre_x_preferred":[
        "Torralba del R\u00edo"
    ],
    "name:hun_x_preferred":[
        "Torralba Del R\u00edo"
    ],
    "name:ita_x_preferred":[
        "Torralba del R\u00edo"
    ],
    "name:jpn_x_preferred":[
        "\u30c8\u30e9\u30eb\u30d0\u30fb\u30c7\u30eb\u30fb\u30ea\u30aa"
    ],
    "name:may_x_preferred":[
        "Torralba Del R\u00edo"
    ],
    "name:nan_x_preferred":[
        "Torralba Del R\u00edo"
    ],
    "name:oci_x_preferred":[
        "Torralba del R\u00edo"
    ],
    "name:pol_x_preferred":[
        "Torralba del R\u00edo"
    ],
    "name:por_x_preferred":[
        "Torralba del R\u00edo"
    ],
    "name:rus_x_preferred":[
        "\u0422\u043e\u0440\u0440\u0430\u043b\u044c\u0431\u0430-\u0434\u0435\u043b\u044c-\u0420\u0438\u043e"
    ],
    "name:spa_x_preferred":[
        "Torralba del R\u00edo"
    ],
    "name:swe_x_preferred":[
        "Torralba del R\u00edo"
    ],
    "name:ukr_x_preferred":[
        "\u0422\u043e\u0440\u0440\u0430\u043b\u044c\u0431\u0430-\u0434\u0435\u043b\u044c-\u0420\u0456\u043e"
    ],
    "name:uzb_x_preferred":[
        "Torralba del R\u00edo"
    ],
    "name:vie_x_preferred":[
        "Torralba Del R\u00edo"
    ],
    "name:war_x_preferred":[
        "Torralba Del R\u00edo"
    ],
    "qs_pg:aaroncc":"ES",
    "qs_pg:name":"Toralba del R\u00edo",
    "qs_pg:name_adm0":"Espa\u00f1a",
    "qs_pg:name_adm1":"Comunidad Foral de Navarra",
    "qs_pg:photos":118,
    "qs_pg:photos_1k":24,
    "qs_pg:photos_9k":1,
    "qs_pg:photos_9r":3,
    "qs_pg:photos_all":118,
    "qs_pg:photos_sr":3,
    "qs_pg:pop_sr":0,
    "qs_pg:qs_pg_placetype":"locality",
    "qs_pg:qs_pg_placetype_gp":"Town",
    "qs_pg:woe_adm0":23424950,
    "woe:adm0_id":23424950,
    "woe:name_adm0":"Espa\u00f1a",
    "woe:name_adm1":"Comunidad Foral de Navarra",
    "woe:placetype":"Town",
    "wof:name":"Toralba del R\u00edo",
    "wof:placetype":"locality"
},
  "geometry": {"coordinates":[-2.35382,42.614254],"type":"Point"}
}