{
  "type": "Feature",
  "properties": {
    "gn:admin1_code":"55",
    "gn:admin2_code":"LE",
    "gn:admin3_code":"24049",
    "gn:asciiname":"Calamocos",
    "gn:country_code":"ES",
    "gn:dem":632,
    "gn:feature_class":"P",
    "gn:feature_code":"PPL",
    "gn:name":"Calamocos",
    "gn:population":0,
    "gn:timezone":"Europe/Madrid",
    "iso:country":"ES",
    "wof:name":"Calamocos",
    "wof:placetype":"locality"
},
  "geometry": {"coordinates":[-6.50765,42.57625],"type":"Point"}
}