{
  "type": "Feature",
  "properties": {
    "gn:admin1_code":"54",
    "gn:admin2_code":"GU",
    "gn:admin3_code":"19245",
    "gn:asciiname":"Corcoles",
    "gn:country_code":"ES",
    "gn:dem":832,
    "gn:feature_class":"P",
    "gn:feature_code":"PPL",
    "gn:name":"C\u00f3rcoles",
    "gn:population":0,
    "gn:timezone":"Europe/Madrid",
    "iso:country":"ES",
    "name:und_x_variant":[
        "C\u00f3rcoles"
    ],
    "wof:name":"Corcoles",
    "wof:placetype":"locality"
},
  "geometry": {"coordinates":[-2.66114,40.48451],"type":"Point"}
}