{
  "type": "Feature",
  "properties": {
    "gn:admin1_code":"56",
    "gn:admin2_code":"T",
    "gn:admin3_code":"43150",
    "gn:asciiname":"Fatges",
    "gn:country_code":"ES",
    "gn:dem":423,
    "gn:feature_class":"P",
    "gn:feature_code":"PPL",
    "gn:name":"Fatg\u00e9s",
    "gn:population":0,
    "gn:timezone":"Europe/Madrid",
    "iso:country":"ES",
    "name:und_x_variant":[
        "Fatg\u00e9s"
    ],
    "wof:name":"Fatges",
    "wof:placetype":"locality"
},
  "geometry": {"coordinates":[0.79683,41.0325],"type":"Point"}
}