{
  "type": "Feature",
  "properties": {
    "gn:gn_country":"ES",
    "gn:gn_fcode":"PPLA3",
    "gn:gn_pop":212,
    "gn:population":212,
    "iso:country":"ES",
    "name:ara_x_preferred":[
        "\u0623\u0644\u0628\u0627\u064a\u0644\u0648\u0633"
    ],
    "name:arg_x_preferred":[
        "Albillos"
    ],
    "name:ast_x_preferred":[
        "Albillos"
    ],
    "name:cat_x_preferred":[
        "Albillos"
    ],
    "name:ceb_x_preferred":[
        "Albillos"
    ],
    "name:deu_x_preferred":[
        "Albillos"
    ],
    "name:eng_x_preferred":[
        "Albillos"
    ],
    "name:eus_x_preferred":[
        "Albillos"
    ],
    "name:fas_x_preferred":[
        "\u0622\u0644\u0628\u06cc\u06cc\u0633"
    ],
    "name:fra_x_preferred":[
        "Albillos"
    ],
    "name:glg_x_preferred":[
        "Albillos"
    ],
    "name:haw_x_preferred":[
        "Albillos"
    ],
    "name:hun_x_preferred":[
        "Albillos"
    ],
    "name:ina_x_preferred":[
        "Albillos"
    ],
    "name:ita_x_preferred":[
        "Albillos"
    ],
    "name:lad_x_preferred":[
        "Albillos"
    ],
    "name:msa_x_preferred":[
        "Albillos"
    ],
    "name:nan_x_preferred":[
        "Albillos"
    ],
    "name:nld_x_preferred":[
        "Albillos"
    ],
    "name:oci_x_preferred":[
        "Albillos"
    ],
    "name:pam_x_preferred":[
        "Albillos"
    ],
    "name:pol_x_preferred":[
        "Albillos"
    ],
    "name:por_x_preferred":[
        "Albillos"
    ],
    "name:rup_x_preferred":[
        "Albillos"
    ],
    "name:rus_x_preferred":[
        "\u0410\u043b\u044c\u0431\u0438\u043b\u044c\u043e\u0441"
    ],
    "name:spa_x_preferred":[
        "Albillos"
    ],
    "name:swe_x_preferred":[
        "Albillos"
    ],
    "name:tah_x_preferred":[
        "Albillos"
    ],
    "name:ukr_x_preferred":[
        "\u0410\u043b\u044c\u0431\u0456\u043b\u044c\u0439\u043e\u0441"
    ],
    "name:vie_x_preferred":[
        "Albillos"
    ],
    "name:war_x_preferred":[
        "Albillos"
    ],
    "name:zho_x_preferred":[
        "\u963f\u5c14\u7ef4\u7565\u65af"
    ],
    "qs_pg:aaroncc":"ES",
    "qs_pg:gn_country":"ES",
    "qs_pg:gn_fcode":"PPLA3",
    "qs_pg:gn_pop":212,
    "qs_pg:name":"Albillos",
    "qs_pg:name_adm0":"Espa\u00f1a",
    "qs_pg:name_adm1":"Castilla y Le\u00f3n",
    "qs_pg:photos_9r":0,
    "qs_pg:photos_sr":0,
    "qs_pg:pop_sr":2,
    "qs_pg:qs_pg_placetype":"locality",
    "qs_pg:qs_pg_placetype_gp":"Town",
    "qs_pg:woe_adm0":23424950,
    "woe:adm0_id":23424950,
    "woe:name_adm0":"Espa\u00f1a",
    "woe:name_adm1":"Castilla y Le\u00f3n",
    "woe:placetype":"Town",
    "wof:name":"Albillos",
    "wof:placetype":"locality",
    "wof:population":212
},
  "geometry": {"coordinates":[-3.78908,42.2768],"type":"Point"}
}