{
  "type": "Feature",
  "properties": {
    "gn:admin1_code":"55",
    "gn:admin2_code":"LE",
    "gn:admin3_code":"24205",
    "gn:asciiname":"Celadilla del Paramo",
    "gn:country_code":"ES",
    "gn:dem":875,
    "gn:feature_class":"P",
    "gn:feature_code":"PPL",
    "gn:name":"Celadilla del P\u00e1ramo",
    "gn:population":0,
    "gn:timezone":"Europe/Madrid",
    "iso:country":"ES",
    "name:und_x_variant":[
        "Celadilla del P\u00e1ramo"
    ],
    "wof:name":"Celadilla del Paramo",
    "wof:placetype":"locality"
},
  "geometry": {"coordinates":[-5.80294,42.51909000000001],"type":"Point"}
}