{
  "type": "Feature",
  "properties": {
    "gn:admin1_code":"32",
    "gn:admin3_code":"31136",
    "gn:asciiname":"Aristregui",
    "gn:country_code":"ES",
    "gn:dem":605,
    "gn:feature_class":"P",
    "gn:feature_code":"PPL",
    "gn:name":"Ar\u00edstregui",
    "gn:population":0,
    "gn:timezone":"Europe/Madrid",
    "iso:country":"ES",
    "wof:name":"Aristregui",
    "wof:placetype":"locality"
},
  "geometry": {"coordinates":[-1.73704,42.89577],"type":"Point"}
}