{
  "type": "Feature",
  "properties": {
    "gn:admin1_code":"58",
    "gn:admin2_code":"C",
    "gn:admin3_code":"15042",
    "gn:asciiname":"Marracin de Arriba",
    "gn:country_code":"ES",
    "gn:dem":74,
    "gn:feature_class":"P",
    "gn:feature_code":"PPL",
    "gn:name":"Marrac\u00edn de Arriba",
    "gn:population":0,
    "gn:timezone":"Europe/Madrid",
    "iso:country":"ES",
    "name:und_x_variant":[
        "Marrac\u00edn de Arriba"
    ],
    "wof:name":"Marracin de Arriba",
    "wof:placetype":"locality"
},
  "geometry": {"coordinates":[-8.86581,42.75544],"type":"Point"}
}