{
  "type": "Feature",
  "properties": {
    "gn:admin1_code":"51",
    "gn:admin2_code":"GR",
    "gn:admin3_code":"18152",
    "gn:asciiname":"Pierres",
    "gn:country_code":"ES",
    "gn:dem":1104,
    "gn:feature_class":"P",
    "gn:feature_code":"PPL",
    "gn:name":"Pierres",
    "gn:population":0,
    "gn:timezone":"Europe/Madrid",
    "iso:country":"ES",
    "name:und_x_variant":[
        "Cortijo Pierre",
        "Caser\u00edo Pierres",
        "Pierres"
    ],
    "wof:name":"Pierres",
    "wof:placetype":"locality"
},
  "geometry": {"coordinates":[-3.25566,37.52455],"type":"Point"}
}