{
  "type": "Feature",
  "properties": {
    "gn:admin1_code":"51",
    "gn:admin2_code":"GR",
    "gn:admin3_code":"18152",
    "gn:asciiname":"Pierres",
    "gn:country_code":"ES",
    "gn:dem":1104,
    "gn:feature_class":"P",
    "gn:feature_code":"PPL",
    "gn:name":"Pierres",
    "gn:population":0,
    "gn:timezone":"Europe/Madrid",
    "iso:country":"ES",
    "name:ceb_x_preferred":[
        "Pierres"
    ],
    "name:deu_x_preferred":[
        "Pierres"
    ],
    "name:fra_x_preferred":[
        "Pierres"
    ],
    "name:ita_x_preferred":[
        "Pierres"
    ],
    "name:nds_x_preferred":[
        "Pierres"
    ],
    "name:nld_x_preferred":[
        "Pierres"
    ],
    "name:oci_x_preferred":[
        "Pierres"
    ],
    "name:pms_x_preferred":[
        "Pierres"
    ],
    "name:pol_x_preferred":[
        "Pierres"
    ],
    "name:por_x_preferred":[
        "Pierres"
    ],
    "name:rus_x_preferred":[
        "\u041f\u044c\u0435\u0440\u0440"
    ],
    "name:slk_x_preferred":[
        "Pierres"
    ],
    "name:spa_x_preferred":[
        "Pierres"
    ],
    "name:swe_x_preferred":[
        "Pierres"
    ],
    "name:ukr_x_preferred":[
        "\u041f'\u0454\u0440\u0440"
    ],
    "name:und_x_variant":[
        "Cortijo Pierre",
        "Caser\u00edo Pierres"
    ],
    "wof:name":"Pierres",
    "wof:placetype":"locality"
},
  "geometry": {"coordinates":[-3.25566,37.52455],"type":"Point"}
}