{
  "type": "Feature",
  "properties": {
    "gn:admin1_code":"55",
    "gn:admin2_code":"LE",
    "gn:admin3_code":"24902",
    "gn:asciiname":"Villaornate",
    "gn:country_code":"ES",
    "gn:dem":737,
    "gn:feature_class":"P",
    "gn:feature_code":"PPL",
    "gn:name":"Villaornate",
    "gn:population":0,
    "gn:timezone":"Europe/Madrid",
    "iso:country":"ES",
    "wof:name":"Villaornate",
    "wof:placetype":"locality"
},
  "geometry": {"coordinates":[-5.54946,42.18451],"type":"Point"}
}