{
  "type": "Feature",
  "properties": {
    "gn:gn_country":"ES",
    "gn:gn_fcode":"PPL",
    "gn:gn_pop":324,
    "gn:population":324,
    "iso:country":"ES",
    "name:ara_x_preferred":[
        "\u0641\u064a\u0644\u0627\u0633\u0648\u0631 \u062f\u064a \u0647\u064a\u0631\u064a\u0631\u0648\u0633"
    ],
    "name:arg_x_preferred":[
        "Villasur de Herreros"
    ],
    "name:baq_x_preferred":[
        "Villasur de Herreros"
    ],
    "name:cat_x_preferred":[
        "Villasur de Herreros"
    ],
    "name:chi_x_preferred":[
        "\u6bd4\u5229\u4e9a\u82cf\u5c14\u5fb7\u57c3\u96f7\u7f57\u65af"
    ],
    "name:dut_x_preferred":[
        "Villasur de Herreros"
    ],
    "name:eng_x_preferred":[
        "Villasur de Herreros"
    ],
    "name:fre_x_preferred":[
        "Villasur de Herreros"
    ],
    "name:glg_x_preferred":[
        "Villasur de Herreros"
    ],
    "name:haw_x_preferred":[
        "Villasur de Herreros"
    ],
    "name:hun_x_preferred":[
        "Villasur de Herreros"
    ],
    "name:ina_x_preferred":[
        "Villasur de Herreros"
    ],
    "name:ita_x_preferred":[
        "Villasur de Herreros"
    ],
    "name:may_x_preferred":[
        "Villasur de Herreros"
    ],
    "name:nan_x_preferred":[
        "Villasur de Herreros"
    ],
    "name:oci_x_preferred":[
        "Villasur de Herreros"
    ],
    "name:per_x_preferred":[
        "\u0628\u06cc\u06cc\u0627\u0633\u0648\u0631 \u062f \u0647\u0631\u0631\u0633"
    ],
    "name:pol_x_preferred":[
        "Villasur de Herreros"
    ],
    "name:por_x_preferred":[
        "Villasur de Herreros"
    ],
    "name:rus_x_preferred":[
        "\u0412\u0438\u043b\u044c\u044f\u0441\u0443\u0440-\u0434\u0435-\u042d\u0440\u0440\u0435\u0440\u043e\u0441"
    ],
    "name:spa_x_preferred":[
        "Villasur de Herreros"
    ],
    "name:swe_x_preferred":[
        "Villasur de Herreros"
    ],
    "name:ukr_x_preferred":[
        "\u0412\u0456\u043b\u044c\u044f\u0441\u0443\u0440-\u0434\u0435-\u0415\u0440\u0440\u0435\u0440\u043e\u0441"
    ],
    "name:unk_x_variant":[
        "Villasur"
    ],
    "name:vie_x_preferred":[
        "Villasur de Herreros"
    ],
    "name:war_x_preferred":[
        "Villasur de Herreros"
    ],
    "qs_pg:aaroncc":"ES",
    "qs_pg:gn_country":"ES",
    "qs_pg:gn_fcode":"PPL",
    "qs_pg:gn_pop":324,
    "qs_pg:name":"Villasur de Herreros",
    "qs_pg:name_adm0":"Espa\u00f1a",
    "qs_pg:name_adm1":"Castilla y Le\u00f3n",
    "qs_pg:photos":53,
    "qs_pg:photos_1k":11,
    "qs_pg:photos_9k":1,
    "qs_pg:photos_9r":2,
    "qs_pg:photos_all":53,
    "qs_pg:photos_sr":2,
    "qs_pg:pop_sr":2,
    "qs_pg:qs_pg_placetype":"locality",
    "qs_pg:qs_pg_placetype_gp":"Town",
    "qs_pg:woe_adm0":23424950,
    "woe:adm0_id":23424950,
    "woe:name_adm0":"Espa\u00f1a",
    "woe:name_adm1":"Castilla y Le\u00f3n",
    "woe:placetype":"Town",
    "wof:name":"Villasur de Herreros",
    "wof:placetype":"locality",
    "wof:population":324
},
  "geometry": {"coordinates":[-3.3942,42.30764],"type":"Point"}
}