{
  "type": "Feature",
  "properties": {
    "gn:admin1_code":"39",
    "gn:admin2_code":"S",
    "gn:admin3_code":"39046",
    "gn:asciiname":"Mediaconcha",
    "gn:country_code":"ES",
    "gn:dem":568,
    "gn:feature_class":"P",
    "gn:feature_code":"PPL",
    "gn:name":"Mediaconcha",
    "gn:population":0,
    "gn:timezone":"Europe/Madrid",
    "iso:country":"ES",
    "wof:name":"Mediaconcha",
    "wof:placetype":"locality"
},
  "geometry": {"coordinates":[-4.07509,43.10314],"type":"Point"}
}