{
  "type": "Feature",
  "properties": {
    "gn:country":"ES",
    "gn:fcode":"PPLA3",
    "gn:population":92,
    "iso:country":"ES",
    "name:ara_x_preferred":[
        "\u0646\u064a\u0628\u0631\u064a\u062f\u0627"
    ],
    "name:arg_x_preferred":[
        "Nebreda"
    ],
    "name:arz_x_preferred":[
        "\u0646\u064a\u0628\u0631\u064a\u062f\u0627"
    ],
    "name:ast_x_preferred":[
        "Nebreda"
    ],
    "name:bul_x_preferred":[
        "\u041d\u0435\u0431\u0440\u0435\u0434\u0430"
    ],
    "name:cat_x_preferred":[
        "Nebreda"
    ],
    "name:ceb_x_preferred":[
        "Nebreda"
    ],
    "name:che_x_preferred":[
        "\u041d\u0435\u0431\u0440\u0435\u0434\u0430"
    ],
    "name:deu_x_preferred":[
        "Nebreda"
    ],
    "name:eng_x_preferred":[
        "Nebreda"
    ],
    "name:epo_x_preferred":[
        "Nebreda"
    ],
    "name:eus_x_preferred":[
        "Nebreda"
    ],
    "name:fas_x_preferred":[
        "\u0646\u0628\u0631\u062f\u0627"
    ],
    "name:fra_x_preferred":[
        "Nebreda"
    ],
    "name:gle_x_preferred":[
        "Nebreda"
    ],
    "name:glg_x_preferred":[
        "Nebreda"
    ],
    "name:haw_x_preferred":[
        "Nebreda"
    ],
    "name:hun_x_preferred":[
        "Nebreda"
    ],
    "name:ile_x_preferred":[
        "Nebreda"
    ],
    "name:ina_x_preferred":[
        "Nebreda"
    ],
    "name:ita_x_preferred":[
        "Nebreda"
    ],
    "name:lad_x_preferred":[
        "Nebreda"
    ],
    "name:lld_x_preferred":[
        "Nebreda"
    ],
    "name:msa_x_preferred":[
        "Nebreda"
    ],
    "name:nan_x_preferred":[
        "Nebreda"
    ],
    "name:nld_x_preferred":[
        "Nebreda"
    ],
    "name:nob_x_preferred":[
        "Nebreda"
    ],
    "name:oci_x_preferred":[
        "Nebreda"
    ],
    "name:pol_x_preferred":[
        "Nebreda"
    ],
    "name:por_x_preferred":[
        "Nebreda"
    ],
    "name:rus_x_preferred":[
        "\u041d\u0435\u0431\u0440\u0435\u0434\u0430"
    ],
    "name:spa_x_preferred":[
        "Nebreda"
    ],
    "name:swe_x_preferred":[
        "Nebreda"
    ],
    "name:tat_x_preferred":[
        "\u041d\u0435\u0431\u0440\u0435\u0434\u0430"
    ],
    "name:tpi_x_preferred":[
        "Nebreda"
    ],
    "name:ukr_x_preferred":[
        "\u041d\u0435\u0431\u0440\u0435\u0434\u0430"
    ],
    "name:vec_x_preferred":[
        "Nebreda"
    ],
    "name:vie_x_preferred":[
        "Nebreda"
    ],
    "name:war_x_preferred":[
        "Nebreda"
    ],
    "name:zho_x_preferred":[
        "\u5185\u592b\u96f7\u8fbe"
    ],
    "qs_pg:aaroncc":"ES",
    "qs_pg:gn_country":"ES",
    "qs_pg:gn_fcode":"PPLA3",
    "qs_pg:gn_pop":92,
    "qs_pg:name":"Nebreda",
    "qs_pg:name_adm0":"Espa\u00f1a",
    "qs_pg:name_adm1":"Castilla y Le\u00f3n",
    "qs_pg:photos_9k":1,
    "qs_pg:photos_9r":1,
    "qs_pg:photos_all":1,
    "qs_pg:photos_sr":0,
    "qs_pg:pop_sr":1,
    "qs_pg:qs_pg_placetype":"locality",
    "qs_pg:qs_pg_placetype_gp":"Town",
    "qs_pg:woe_adm0":23424950,
    "woe:adm0_id":23424950,
    "woe:name_adm0":"Espa\u00f1a",
    "woe:name_adm1":"Castilla y Le\u00f3n",
    "woe:placetype":"Town",
    "wof:name":"Nebreda",
    "wof:placetype":"locality",
    "wof:population":92
},
  "geometry": {"coordinates":[-3.6343,41.96881],"type":"Point"}
}