{
  "type": "Feature",
  "properties": {
    "gn:admin1_code":"55",
    "gn:admin2_code":"SA",
    "gn:admin3_code":"37217",
    "gn:asciiname":"Prados Merinos",
    "gn:country_code":"ES",
    "gn:dem":786,
    "gn:feature_class":"P",
    "gn:feature_code":"PPL",
    "gn:name":"Prados Merinos",
    "gn:population":0,
    "gn:timezone":"Europe/Madrid",
    "iso:country":"ES",
    "name:und_x_variant":[
        "Caser\u00edo Prados Merinos",
        "Prados Merinos"
    ],
    "wof:name":"Prados Merinos",
    "wof:placetype":"locality"
},
  "geometry": {"coordinates":[-5.80759,40.42644],"type":"Point"}
}