{
  "type": "Feature",
  "properties": {
    "gn:admin1_code":"55",
    "gn:admin2_code":"ZA",
    "gn:admin3_code":"49145",
    "gn:asciiname":"Lobeznos",
    "gn:country_code":"ES",
    "gn:dem":983,
    "gn:feature_class":"P",
    "gn:feature_code":"PPL",
    "gn:name":"Lobeznos",
    "gn:population":0,
    "gn:timezone":"Europe/Madrid",
    "iso:country":"ES",
    "name:arg_x_preferred":[
        "Lobeznos"
    ],
    "name:ast_x_preferred":[
        "Llobeznos"
    ],
    "name:glg_x_preferred":[
        "Lobeznos"
    ],
    "name:spa_x_preferred":[
        "Lobeznos"
    ],
    "wof:name":"Lobeznos",
    "wof:placetype":"locality"
},
  "geometry": {"coordinates":[-6.66889,42.03741],"type":"Point"}
}