{
  "type": "Feature",
  "properties": {
    "gn:admin1_code":"58",
    "gn:admin2_code":"C",
    "gn:admin3_code":"15078",
    "gn:asciiname":"Carballal",
    "gn:cc2":"ES",
    "gn:country_code":"ES",
    "gn:dem":318,
    "gn:feature_class":"P",
    "gn:feature_code":"PPL",
    "gn:name":"Carballal",
    "gn:population":0,
    "gn:timezone":"Europe/Madrid",
    "iso:country":"ES",
    "name:und_x_variant":[
        "San Juli\u00e1n",
        "Carballal"
    ],
    "wof:name":"Carballal",
    "wof:placetype":"locality"
},
  "geometry": {"coordinates":[-8.43333,42.91667],"type":"Point"}
}