{
  "type": "Feature",
  "properties": {
    "gn:admin1_code":"55",
    "gn:admin2_code":"BU",
    "gn:admin3_code":"09211",
    "gn:asciiname":"Naveros de Pisuerga",
    "gn:country_code":"ES",
    "gn:dem":826,
    "gn:feature_class":"P",
    "gn:feature_code":"PPL",
    "gn:name":"Naveros de Pisuerga",
    "gn:population":0,
    "gn:timezone":"Europe/Madrid",
    "iso:country":"ES",
    "name:und_x_variant":[
        "Naveros",
        "Naveros de Pisuerga"
    ],
    "wof:name":"Naveros de Pisuerga",
    "wof:placetype":"locality"
},
  "geometry": {"coordinates":[-4.26516,42.47295],"type":"Point"}
}