{
  "type": "Feature",
  "properties": {
    "gn:admin1_code":"55",
    "gn:admin2_code":"LE",
    "gn:admin3_code":"24022",
    "gn:asciiname":"La Chana",
    "gn:country_code":"ES",
    "gn:dem":610,
    "gn:feature_class":"P",
    "gn:feature_code":"PPL",
    "gn:name":"La Chana",
    "gn:population":0,
    "gn:timezone":"Europe/Madrid",
    "iso:country":"ES",
    "wof:name":"La Chana",
    "wof:placetype":"locality"
},
  "geometry": {"coordinates":[-6.72472,42.48181],"type":"Point"}
}