{
  "type": "Feature",
  "properties": {
    "gn:country":"ES",
    "gn:fcode":"PPLA3",
    "gn:population":63,
    "iso:country":"ES",
    "name:arg_x_preferred":[
        "Navalmoral de B\u00e9jar"
    ],
    "name:cat_x_preferred":[
        "Navalmoral de B\u00e9jar"
    ],
    "name:eng_x_preferred":[
        "Navalmoral de B\u00e9jar"
    ],
    "name:eus_x_preferred":[
        "Navalmoral de B\u00e9jar"
    ],
    "name:fra_x_preferred":[
        "Navalmoral de B\u00e9jar"
    ],
    "name:haw_x_preferred":[
        "Navalmoral de B\u00e9jar"
    ],
    "name:hun_x_preferred":[
        "Navalmoral de B\u00e9jar"
    ],
    "name:ina_x_preferred":[
        "Navalmoral de B\u00e9jar"
    ],
    "name:ita_x_preferred":[
        "Navalmoral de B\u00e9jar"
    ],
    "name:kaz_x_preferred":[
        "\u041d\u0430\u0432\u0430\u043b\u044c\u043c\u043e\u0440\u0430\u043b\u044c-\u0434\u0435-\u0411\u0435\u0445\u0430\u0440"
    ],
    "name:msa_x_preferred":[
        "Navalmoral de B\u00e9jar"
    ],
    "name:nan_x_preferred":[
        "Navalmoral de B\u00e9jar"
    ],
    "name:nld_x_preferred":[
        "Navalmoral de B\u00e9jar"
    ],
    "name:oci_x_preferred":[
        "Navalmoral de B\u00e9jar"
    ],
    "name:pol_x_preferred":[
        "Navalmoral de B\u00e9jar"
    ],
    "name:por_x_preferred":[
        "Navalmoral de B\u00e9jar"
    ],
    "name:rus_x_preferred":[
        "\u041d\u0430\u0432\u0430\u043b\u044c\u043c\u043e\u0440\u0430\u043b\u044c-\u0434\u0435-\u0411\u0435\u0445\u0430\u0440"
    ],
    "name:spa_x_preferred":[
        "Navalmoral de B\u00e9jar"
    ],
    "name:swe_x_preferred":[
        "Navalmoral de B\u00e9jar"
    ],
    "name:ukr_x_preferred":[
        "\u041d\u0430\u0432\u0430\u043b\u044c\u043c\u043e\u0440\u0430\u043b\u044c-\u0434\u0435-\u0411\u0435\u0445\u0430\u0440"
    ],
    "name:vie_x_preferred":[
        "Navalmoral de B\u00e9jar"
    ],
    "name:war_x_preferred":[
        "Navalmoral de B\u00e9jar"
    ],
    "name:zho_x_preferred":[
        "\u7eb3\u74e6\u5c14\u83ab\u62c9\u5c14\u5fb7\u97e6\u54c8\u5c14"
    ],
    "qs_pg:aaroncc":"ES",
    "qs_pg:gn_country":"ES",
    "qs_pg:gn_fcode":"PPLA3",
    "qs_pg:gn_pop":63,
    "qs_pg:name":"Navalmoral de B\u00e9jar",
    "qs_pg:name_adm0":"Espa\u00f1a",
    "qs_pg:name_adm1":"Castilla y Le\u00f3n",
    "qs_pg:photos":36,
    "qs_pg:photos_1k":7,
    "qs_pg:photos_9k":1,
    "qs_pg:photos_9r":2,
    "qs_pg:photos_all":36,
    "qs_pg:photos_sr":2,
    "qs_pg:pop_sr":1,
    "qs_pg:qs_pg_placetype":"locality",
    "qs_pg:qs_pg_placetype_gp":"Town",
    "qs_pg:woe_adm0":23424950,
    "woe:adm0_id":23424950,
    "woe:name_adm0":"Espa\u00f1a",
    "woe:name_adm1":"Castilla y Le\u00f3n",
    "woe:placetype":"Town",
    "wof:name":"Navalmoral de B\u00e9jar",
    "wof:placetype":"locality",
    "wof:population":63
},
  "geometry": {"coordinates":[-5.7831,40.42264],"type":"Point"}
}