{
  "type": "Feature",
  "properties": {
    "gn:gn_country":"ES",
    "gn:gn_fcode":"PPLA3",
    "gn:gn_pop":288,
    "gn:population":288,
    "iso:country":"ES",
    "name:arg_x_preferred":[
        "Puerto de San Vicente"
    ],
    "name:azb_x_preferred":[
        "\u067e\u0648\u0626\u0631\u062a\u0648 \u062f \u0633\u0627\u0646 \u0628\u06cc\u0633\u0646\u062a\u0647"
    ],
    "name:cat_x_preferred":[
        "Puerto de San Vicente"
    ],
    "name:deu_x_preferred":[
        "Puerto de San Vicente"
    ],
    "name:eng_x_preferred":[
        "Puerto de San Vicente"
    ],
    "name:epo_x_preferred":[
        "Puerto de San Vicente"
    ],
    "name:eus_x_preferred":[
        "Puerto de San Vicente"
    ],
    "name:fas_x_preferred":[
        "\u067e\u0648\u0626\u0631\u062a\u0648 \u062f \u0633\u0627\u0646 \u0628\u06cc\u0633\u0646\u062a\u0647"
    ],
    "name:fra_x_preferred":[
        "Puerto de San Vicente"
    ],
    "name:hun_x_preferred":[
        "Puerto de San Vicente"
    ],
    "name:hye_x_preferred":[
        "\u054a\u0578\u0582\u0565\u0580\u057f\u0578 \u0564\u0565 \u054d\u0561\u0576 \u054e\u056b\u057d\u0565\u0576\u057f\u0565"
    ],
    "name:ina_x_preferred":[
        "Puerto de San Vicente"
    ],
    "name:ita_x_preferred":[
        "Puerto de San Vicente"
    ],
    "name:kaz_x_preferred":[
        "\u041f\u0443\u044d\u0440\u0442\u043e-\u0434\u0435-\u0421\u0430\u043d-\u0412\u0438\u0441\u0435\u043d\u0442\u0435"
    ],
    "name:msa_x_preferred":[
        "Puerto de San Vicente"
    ],
    "name:nan_x_preferred":[
        "Puerto de San Vicente"
    ],
    "name:nld_x_preferred":[
        "Puerto de San Vicente"
    ],
    "name:oci_x_preferred":[
        "Puerto de San Vicente"
    ],
    "name:pol_x_preferred":[
        "Puerto de San Vicente"
    ],
    "name:por_x_preferred":[
        "Puerto de San Vicente"
    ],
    "name:ron_x_preferred":[
        "Puerto de San Vicente"
    ],
    "name:rus_x_preferred":[
        "\u041f\u0443\u044d\u0440\u0442\u043e-\u0434\u0435-\u0421\u0430\u043d-\u0412\u0438\u0441\u0435\u043d\u0442\u0435"
    ],
    "name:spa_x_preferred":[
        "Puerto de San Vicente"
    ],
    "name:swe_x_preferred":[
        "Puerto de San Vicente"
    ],
    "name:ukr_x_preferred":[
        "\u041f\u0443\u0435\u0440\u0442\u043e-\u0434\u0435-\u0421\u0430\u043d-\u0412\u0456\u0441\u0435\u043d\u0442\u0435"
    ],
    "name:vie_x_preferred":[
        "Puerto de San Vicente"
    ],
    "name:war_x_preferred":[
        "Puerto de San Vicente"
    ],
    "name:zho_x_preferred":[
        "\u5723\u7ef4\u68ee\u7279\u6e2f"
    ],
    "qs_pg:aaroncc":"ES",
    "qs_pg:gn_country":"ES",
    "qs_pg:gn_fcode":"PPLA3",
    "qs_pg:gn_pop":288,
    "qs_pg:name":"Puerto de San Vicente",
    "qs_pg:name_adm0":"Espa\u00f1a",
    "qs_pg:name_adm1":"Castilla-La Mancha",
    "qs_pg:photos_9r":0,
    "qs_pg:photos_sr":0,
    "qs_pg:pop_sr":2,
    "qs_pg:qs_pg_placetype":"locality",
    "qs_pg:qs_pg_placetype_gp":"Town",
    "qs_pg:woe_adm0":23424950,
    "woe:adm0_id":23424950,
    "woe:name_adm0":"Espa\u00f1a",
    "woe:name_adm1":"Castilla-La Mancha",
    "woe:placetype":"Town",
    "wof:name":"Puerto de San Vicente",
    "wof:placetype":"locality",
    "wof:population":288
},
  "geometry": {"coordinates":[-5.11407,39.52283],"type":"Point"}
}