{
  "type": "Feature",
  "properties": {
    "gn:admin1_code":"54",
    "gn:admin2_code":"CU",
    "gn:admin3_code":"16065",
    "gn:asciiname":"Los Estesos",
    "gn:country_code":"ES",
    "gn:dem":726,
    "gn:feature_class":"P",
    "gn:feature_code":"PPL",
    "gn:name":"Los Estesos",
    "gn:population":0,
    "gn:timezone":"Europe/Madrid",
    "iso:country":"ES",
    "name:und_x_variant":[
        "Barrio Los Esresos",
        "Los Estesos"
    ],
    "wof:name":"Los Estesos",
    "wof:placetype":"locality"
},
  "geometry": {"coordinates":[-2.37099,39.32493],"type":"Point"}
}