{
  "type": "Feature",
  "properties": {
    "gn:admin1_code":"34",
    "gn:admin2_code":"O",
    "gn:admin3_code":"33071",
    "gn:asciiname":"Arrojo",
    "gn:country_code":"ES",
    "gn:dem":356,
    "gn:feature_class":"P",
    "gn:feature_code":"PPL",
    "gn:name":"Arrojo",
    "gn:population":0,
    "gn:timezone":"Europe/Madrid",
    "iso:country":"ES",
    "wof:name":"Arrojo",
    "wof:placetype":"locality"
},
  "geometry": {"coordinates":[-7.05899,43.37472],"type":"Point"}
}