{
  "type": "Feature",
  "properties": {
    "gn:admin1_code":"57",
    "gn:admin2_code":"CC",
    "gn:admin3_code":"10005",
    "gn:asciiname":"Aceituna",
    "gn:country_code":"ES",
    "gn:dem":485,
    "gn:feature_class":"P",
    "gn:feature_code":"PPLA3",
    "gn:name":"Aceituna",
    "gn:population":629,
    "gn:timezone":"Europe/Madrid",
    "iso:country":"ES",
    "wof:name":"Aceituna",
    "wof:placetype":"locality",
    "wof:population":629
},
  "geometry": {"coordinates":[-6.33292,40.15008],"type":"Point"}
}