{
  "type": "Feature",
  "properties": {
    "gn:admin1_code":"57",
    "gn:admin2_code":"CC",
    "gn:admin3_code":"10005",
    "gn:asciiname":"Aceituna",
    "gn:country_code":"ES",
    "gn:dem":485,
    "gn:feature_class":"P",
    "gn:feature_code":"PPLA3",
    "gn:name":"Aceituna",
    "gn:population":629,
    "gn:timezone":"Europe/Madrid",
    "iso:country":"ES",
    "name:ara_x_preferred":[
        "\u0623\u0633\u064a\u062a\u0648\u0646\u0627"
    ],
    "name:cat_x_preferred":[
        "Aceituna"
    ],
    "name:ceb_x_preferred":[
        "Aceituna"
    ],
    "name:epo_x_preferred":[
        "Aceituna"
    ],
    "name:eus_x_preferred":[
        "Aceituna"
    ],
    "name:fas_x_preferred":[
        "\u0627\u0633\u06cc\u062a\u0648\u0646\u0627"
    ],
    "name:fra_x_preferred":[
        "Aceituna"
    ],
    "name:glg_x_preferred":[
        "Aceituna"
    ],
    "name:hun_x_preferred":[
        "Aceituna"
    ],
    "name:ina_x_preferred":[
        "Aceituna"
    ],
    "name:ita_x_preferred":[
        "Aceituna"
    ],
    "name:msa_x_preferred":[
        "Aceituna"
    ],
    "name:nld_x_preferred":[
        "Aceituna"
    ],
    "name:oci_x_preferred":[
        "Aceituna"
    ],
    "name:pol_x_preferred":[
        "Aceituna"
    ],
    "name:por_x_preferred":[
        "Aceituna"
    ],
    "name:ron_x_preferred":[
        "Aceituna"
    ],
    "name:rus_x_preferred":[
        "\u0410\u0441\u0435\u0439\u0442\u0443\u043d\u0430"
    ],
    "name:spa_x_preferred":[
        "Aceituna"
    ],
    "name:swe_x_preferred":[
        "Aceituna"
    ],
    "name:ukr_x_preferred":[
        "\u0410\u0441\u0435\u0439\u0442\u0443\u043d\u0430"
    ],
    "name:uzb_x_preferred":[
        "Aceituna"
    ],
    "name:vie_x_preferred":[
        "Aceituna"
    ],
    "name:war_x_preferred":[
        "Aceituna"
    ],
    "wof:name":"Aceituna",
    "wof:placetype":"locality",
    "wof:population":629
},
  "geometry": {"coordinates":[-6.33292,40.15008],"type":"Point"}
}