{
  "type": "Feature",
  "properties": {
    "gn:admin1_code":"59",
    "gn:admin2_code":"SS",
    "gn:admin3_code":"20067",
    "gn:asciiname":"Alcibar",
    "gn:country_code":"ES",
    "gn:dem":36,
    "gn:feature_class":"P",
    "gn:feature_code":"PPL",
    "gn:name":"Altzibar",
    "gn:population":0,
    "gn:timezone":"Europe/Madrid",
    "iso:country":"ES",
    "name:eus_x_preferred":[
        "Altzibar"
    ],
    "name:spa_x_preferred":[
        "Alcibar"
    ],
    "wof:name":"Alcibar",
    "wof:placetype":"locality"
},
  "geometry": {"coordinates":[-1.85666,43.29268],"type":"Point"}
}