{
  "type": "Feature",
  "properties": {
    "gn:admin1_code":"58",
    "gn:admin2_code":"LU",
    "gn:admin3_code":"27009",
    "gn:asciiname":"Vilauxe",
    "gn:cc2":"ES",
    "gn:country_code":"ES",
    "gn:dem":523,
    "gn:feature_class":"P",
    "gn:feature_code":"PPL",
    "gn:name":"Vilauxe",
    "gn:population":0,
    "gn:timezone":"Europe/Madrid",
    "iso:country":"ES",
    "name:und_x_variant":[
        "San Salvador",
        "El Salvador"
    ],
    "wof:name":"Vilauxe",
    "wof:placetype":"locality"
},
  "geometry": {"coordinates":[-7.75,42.56667],"type":"Point"}
}