{
  "type": "Feature",
  "properties": {
    "gn:admin1_code":"58",
    "gn:admin2_code":"C",
    "gn:admin3_code":"15056",
    "gn:asciiname":"Pesadoira de Abaixo",
    "gn:cc2":"ES",
    "gn:country_code":"ES",
    "gn:dem":356,
    "gn:feature_class":"P",
    "gn:feature_code":"PPL",
    "gn:name":"Pesadoira de Abaixo",
    "gn:population":0,
    "gn:timezone":"Europe/Madrid",
    "iso:country":"ES",
    "name:und_x_variant":[
        "Pasadoira de Abajo"
    ],
    "wof:name":"Pesadoira de Abaixo",
    "wof:placetype":"locality"
},
  "geometry": {"coordinates":[-8.88333,42.93333],"type":"Point"}
}