{
  "type": "Feature",
  "properties": {
    "gn:admin1_code":"55",
    "gn:admin2_code":"BU",
    "gn:admin3_code":"09906",
    "gn:asciiname":"Quintanarruz",
    "gn:country_code":"ES",
    "gn:dem":767,
    "gn:feature_class":"P",
    "gn:feature_code":"PPL",
    "gn:name":"Quintanarruz",
    "gn:population":0,
    "gn:timezone":"Europe/Madrid",
    "iso:country":"ES",
    "wof:name":"Quintanarruz",
    "wof:placetype":"locality"
},
  "geometry": {"coordinates":[-3.59098,42.56674],"type":"Point"}
}