{
  "type": "Feature",
  "properties": {
    "gn:admin1_code":"51",
    "gn:admin2_code":"AL",
    "gn:admin3_code":"04089",
    "gn:asciiname":"Los Mundos",
    "gn:country_code":"ES",
    "gn:dem":583,
    "gn:feature_class":"P",
    "gn:feature_code":"PPL",
    "gn:name":"Los Mundos",
    "gn:population":0,
    "gn:timezone":"Europe/Madrid",
    "iso:country":"ES",
    "wof:name":"Los Mundos",
    "wof:placetype":"locality"
},
  "geometry": {"coordinates":[-2.03333,37.46667],"type":"Point"}
}