{
  "type": "Feature",
  "properties": {
    "gn:admin1_code":"55",
    "gn:admin2_code":"LE",
    "gn:admin3_code":"24122",
    "gn:asciiname":"San Pedro de Trones",
    "gn:country_code":"ES",
    "gn:dem":701,
    "gn:feature_class":"P",
    "gn:feature_code":"PPL",
    "gn:name":"San Pedro de Trones",
    "gn:population":0,
    "gn:timezone":"Europe/Madrid",
    "iso:country":"ES",
    "wof:name":"San Pedro de Trones",
    "wof:placetype":"locality"
},
  "geometry": {"coordinates":[-6.8016,42.39946],"type":"Point"}
}