{
  "type": "Feature",
  "properties": {
    "gn:population":1749,
    "iso:country":"ES",
    "name:alb_x_preferred":[
        "Torres"
    ],
    "name:ara_x_preferred":[
        "\u062a\u0648\u0631\u064a\u0633\u060c \u062e\u0627\u064a\u0646"
    ],
    "name:arm_x_preferred":[
        "\u054f\u0578\u057c\u0565\u057d"
    ],
    "name:baq_x_preferred":[
        "Torres"
    ],
    "name:cat_x_preferred":[
        "Torres"
    ],
    "name:chi_x_preferred":[
        "\u6258\u96f7\u65af"
    ],
    "name:dut_x_preferred":[
        "Torres"
    ],
    "name:eng_x_preferred":[
        "Torres"
    ],
    "name:fre_x_preferred":[
        "Torres"
    ],
    "name:ger_x_preferred":[
        "Torres"
    ],
    "name:hat_x_preferred":[
        "Torres"
    ],
    "name:hun_x_preferred":[
        "Torres"
    ],
    "name:ita_x_preferred":[
        "Torres"
    ],
    "name:may_x_preferred":[
        "Torres"
    ],
    "name:nan_x_preferred":[
        "Torres"
    ],
    "name:oci_x_preferred":[
        "Torres"
    ],
    "name:per_x_preferred":[
        "\u062a\u0631\u0633"
    ],
    "name:pol_x_preferred":[
        "Torres"
    ],
    "name:por_x_preferred":[
        "Torres"
    ],
    "name:rus_x_preferred":[
        "\u0422\u043e\u0440\u0440\u0435\u0441"
    ],
    "name:spa_x_preferred":[
        "Torres"
    ],
    "name:swe_x_preferred":[
        "Torres"
    ],
    "name:tur_x_preferred":[
        "Torres"
    ],
    "name:ukr_x_preferred":[
        "\u0422\u043e\u0440\u0440\u0435\u0441"
    ],
    "name:uzb_x_preferred":[
        "Torres"
    ],
    "name:vie_x_preferred":[
        "Torres"
    ],
    "name:war_x_preferred":[
        "Torres"
    ],
    "qs:a0":"Espa\u00f1a",
    "qs:a1":"*Ja\u00e9n",
    "qs:a1r":"0Andaluc\u00eda",
    "qs:adm0":"Espa\u00f1a",
    "qs:la_lc":"*",
    "qs:level":"locality",
    "qs:loc":"Torres",
    "qs:loc_alt":"Torres",
    "qs:pop":0,
    "qs:type":"buffered point",
    "wof:lang":[
        "spa"
    ],
    "wof:name":"Torres",
    "wof:placetype":"locality",
    "wof:population":1749
},
  "geometry": {"coordinates":[-3.508904,37.785118],"type":"Point"}
}