{
  "type": "Feature",
  "properties": {
    "gn:admin1_code":"58",
    "gn:admin2_code":"LU",
    "gn:admin3_code":"27054",
    "gn:asciiname":"Villaseca",
    "gn:country_code":"ES",
    "gn:dem":349,
    "gn:feature_class":"P",
    "gn:feature_code":"PPL",
    "gn:name":"Villaseca",
    "gn:population":0,
    "gn:timezone":"Europe/Madrid",
    "iso:country":"ES",
    "name:cat_x_preferred":[
        "Vila-seca"
    ],
    "name:eus_x_preferred":[
        "Vila-seca"
    ],
    "name:fra_x_preferred":[
        "Villaseca"
    ],
    "name:spa_x_preferred":[
        "Villaseca"
    ],
    "wof:name":"Villaseca",
    "wof:placetype":"locality"
},
  "geometry": {"coordinates":[-7.28182,43.36185],"type":"Point"}
}