{
  "type": "Feature",
  "properties": {
    "gn:country":"ES",
    "gn:fcode":"PPLA3",
    "gn:population":168,
    "iso:country":"ES",
    "name:arg_x_preferred":[
        "San Esteban del Molar"
    ],
    "name:ast_x_preferred":[
        "San Esteban del Molar"
    ],
    "name:cat_x_preferred":[
        "San Esteban del Molar"
    ],
    "name:ceb_x_preferred":[
        "San Esteban del Molar"
    ],
    "name:eng_x_preferred":[
        "San Esteban del Molar"
    ],
    "name:epo_x_preferred":[
        "San Esteban del Molar"
    ],
    "name:eus_x_preferred":[
        "San Esteban del Molar"
    ],
    "name:fra_x_preferred":[
        "San Esteban del Molar"
    ],
    "name:gle_x_preferred":[
        "San Esteban del Molar"
    ],
    "name:haw_x_preferred":[
        "San Esteban del Molar"
    ],
    "name:hun_x_preferred":[
        "San Esteban del Molar"
    ],
    "name:ile_x_preferred":[
        "San Esteban del Molar"
    ],
    "name:ina_x_preferred":[
        "San Esteban del Molar"
    ],
    "name:ita_x_preferred":[
        "San Esteban del Molar"
    ],
    "name:lit_x_preferred":[
        "San \u0116steban del Molaras"
    ],
    "name:lld_x_preferred":[
        "San Esteban del Molar"
    ],
    "name:msa_x_preferred":[
        "San Esteban del Molar"
    ],
    "name:nan_x_preferred":[
        "San Esteban del Molar"
    ],
    "name:nld_x_preferred":[
        "San Esteban del Molar"
    ],
    "name:nob_x_preferred":[
        "San Esteban del Molar"
    ],
    "name:oci_x_preferred":[
        "San Esteban del Molar"
    ],
    "name:pol_x_preferred":[
        "San Esteban del Molar"
    ],
    "name:por_x_preferred":[
        "San Esteban del Molar"
    ],
    "name:rus_x_preferred":[
        "\u0421\u0430\u043d-\u042d\u0441\u0442\u0435\u0431\u0430\u043d-\u0434\u0435\u043b\u044c-\u041c\u043e\u043b\u0430\u0440"
    ],
    "name:spa_x_preferred":[
        "San Esteban del Molar"
    ],
    "name:swe_x_preferred":[
        "San Esteban del Molar"
    ],
    "name:ukr_x_preferred":[
        "\u0421\u0430\u043d-\u0415\u0441\u0442\u0435\u0431\u0430\u043d-\u0434\u0435\u043b\u044c-\u041c\u043e\u043b\u0430\u0440"
    ],
    "name:vec_x_preferred":[
        "San Esteban del Molar"
    ],
    "name:vie_x_preferred":[
        "San Esteban del Molar"
    ],
    "name:war_x_preferred":[
        "San Esteban del Molar"
    ],
    "name:zho_x_preferred":[
        "\u5723\u57c3\u65af\u7279\u4e07\u5fb7\u5c14\u83ab\u62c9\u5c14"
    ],
    "qs_pg:aaroncc":"ES",
    "qs_pg:gn_country":"ES",
    "qs_pg:gn_fcode":"PPLA3",
    "qs_pg:gn_pop":168,
    "qs_pg:name":"San Esteban del Molar",
    "qs_pg:name_adm0":"Espa\u00f1a",
    "qs_pg:name_adm1":"Castilla y Le\u00f3n",
    "qs_pg:photos_9k":1,
    "qs_pg:photos_9r":1,
    "qs_pg:photos_all":2,
    "qs_pg:photos_sr":0,
    "qs_pg:pop_sr":1,
    "qs_pg:qs_pg_placetype":"locality",
    "qs_pg:qs_pg_placetype_gp":"Town",
    "qs_pg:woe_adm0":23424950,
    "woe:adm0_id":23424950,
    "woe:name_adm0":"Espa\u00f1a",
    "woe:name_adm1":"Castilla y Le\u00f3n",
    "woe:placetype":"Town",
    "wof:name":"San Esteban del Molar",
    "wof:placetype":"locality",
    "wof:population":168
},
  "geometry": {"coordinates":[-5.55158,41.93717],"type":"Point"}
}