{
  "type": "Feature",
  "properties": {
    "gn:admin1_code":"58",
    "gn:admin2_code":"OR",
    "gn:admin3_code":"32067",
    "gn:asciiname":"Sabariz",
    "gn:country_code":"ES",
    "gn:dem":686,
    "gn:feature_class":"P",
    "gn:feature_code":"PPL",
    "gn:name":"Sabariz",
    "gn:population":0,
    "gn:timezone":"Europe/Madrid",
    "iso:country":"ES",
    "wof:name":"Sabariz",
    "wof:placetype":"locality"
},
  "geometry": {"coordinates":[-7.84132,42.10854000000001],"type":"Point"}
}