{
  "type": "Feature",
  "properties": {
    "gn:admin1_code":"58",
    "gn:admin2_code":"LU",
    "gn:admin3_code":"27040",
    "gn:asciiname":"Moredo",
    "gn:country_code":"ES",
    "gn:dem":530,
    "gn:feature_class":"P",
    "gn:feature_code":"PPL",
    "gn:name":"Moredo",
    "gn:population":0,
    "gn:timezone":"Europe/Madrid",
    "iso:country":"ES",
    "wof:name":"Moredo",
    "wof:placetype":"locality"
},
  "geometry": {"coordinates":[-7.89983,42.92663],"type":"Point"}
}