{
  "type": "Feature",
  "properties": {
    "gn:admin1_code":"58",
    "gn:admin2_code":"C",
    "gn:admin3_code":"15041",
    "gn:asciiname":"Leston",
    "gn:country_code":"ES",
    "gn:dem":226,
    "gn:feature_class":"P",
    "gn:feature_code":"PPL",
    "gn:name":"Lest\u00f3n",
    "gn:population":0,
    "gn:timezone":"Europe/Madrid",
    "iso:country":"ES",
    "name:und_x_variant":[
        "San Martin",
        "Lest\u00f3n"
    ],
    "wof:name":"Leston",
    "wof:placetype":"locality"
},
  "geometry": {"coordinates":[-8.5612,43.25843],"type":"Point"}
}