{
  "type": "Feature",
  "properties": {
    "gn:admin1_code":"58",
    "gn:admin2_code":"OR",
    "gn:admin3_code":"32025",
    "gn:asciiname":"Sadurnin",
    "gn:country_code":"ES",
    "gn:dem":291,
    "gn:feature_class":"P",
    "gn:feature_code":"PPL",
    "gn:name":"Sadurn\u00edn",
    "gn:population":0,
    "gn:timezone":"Europe/Madrid",
    "iso:country":"ES",
    "name:und_x_variant":[
        "Sadurn\u00edn"
    ],
    "wof:name":"Sadurnin",
    "wof:placetype":"locality"
},
  "geometry": {"coordinates":[-8.08536,42.3278],"type":"Point"}
}