{
  "type": "Feature",
  "properties": {
    "gn:admin1_code":"58",
    "gn:admin2_code":"LU",
    "gn:admin3_code":"27020",
    "gn:asciiname":"Ousa",
    "gn:cc2":"ES",
    "gn:country_code":"ES",
    "gn:dem":591,
    "gn:feature_class":"P",
    "gn:feature_code":"PPL",
    "gn:name":"Ous\u00e1",
    "gn:population":0,
    "gn:timezone":"Europe/Madrid",
    "iso:country":"ES",
    "name:und_x_variant":[
        "San Juli\u00e1n",
        "Ous\u00e1"
    ],
    "wof:name":"Ousa",
    "wof:placetype":"locality"
},
  "geometry": {"coordinates":[-7.71667,43.08333],"type":"Point"}
}