{
  "type": "Feature",
  "properties": {
    "gn:admin1_code":"55",
    "gn:admin2_code":"BU",
    "gn:admin3_code":"09219",
    "gn:asciiname":"Valverde de Miranda",
    "gn:country_code":"ES",
    "gn:dem":510,
    "gn:feature_class":"P",
    "gn:feature_code":"PPL",
    "gn:name":"Valverde de Miranda",
    "gn:population":0,
    "gn:timezone":"Europe/Madrid",
    "iso:country":"ES",
    "wof:name":"Valverde de Miranda",
    "wof:placetype":"locality"
},
  "geometry": {"coordinates":[-2.9996,42.65167],"type":"Point"}
}