{
  "type": "Feature",
  "properties": {
    "gn:admin1_code":"55",
    "gn:admin2_code":"BU",
    "gn:admin3_code":"09238",
    "gn:asciiname":"Barcina de los Montes",
    "gn:country_code":"ES",
    "gn:dem":836,
    "gn:feature_class":"P",
    "gn:feature_code":"PPL",
    "gn:name":"Barcina de los Montes",
    "gn:population":0,
    "gn:timezone":"Europe/Madrid",
    "iso:country":"ES",
    "wof:name":"Barcina de los Montes",
    "wof:placetype":"locality"
},
  "geometry": {"coordinates":[-3.32234,42.71306],"type":"Point"}
}