{
  "type": "Feature",
  "properties": {
    "gn:admin1_code":"52",
    "gn:admin2_code":"HU",
    "gn:admin3_code":"22158",
    "gn:asciiname":"La Almunia de San Juan",
    "gn:country_code":"ES",
    "gn:dem":361,
    "gn:feature_class":"P",
    "gn:feature_code":"PPL",
    "gn:name":"La Almunia de San Juan",
    "gn:population":0,
    "gn:timezone":"Europe/Madrid",
    "iso:country":"ES",
    "name:cat_x_preferred":[
        "L\u2019Alm\u00fania de Sant Joan"
    ],
    "name:spa_x_preferred":[
        "La Almunia de San Juan"
    ],
    "wof:name":"La Almunia de San Juan",
    "wof:placetype":"locality"
},
  "geometry": {"coordinates":[0.24543,41.93652],"type":"Point"}
}