{
  "type": "Feature",
  "properties": {
    "gn:admin1_code":"56",
    "gn:admin2_code":"GI",
    "gn:admin3_code":"17117",
    "gn:asciiname":"Armadas",
    "gn:country_code":"ES",
    "gn:dem":38,
    "gn:feature_class":"P",
    "gn:feature_code":"PPL",
    "gn:name":"Armad\u00e1s",
    "gn:population":0,
    "gn:timezone":"Europe/Madrid",
    "iso:country":"ES",
    "name:und_x_variant":[
        "Caser\u00edo Armad\u00e1s",
        "Armad\u00e1s"
    ],
    "wof:name":"Armadas",
    "wof:placetype":"locality"
},
  "geometry": {"coordinates":[3.16317,41.89565],"type":"Point"}
}