{
  "type": "Feature",
  "properties": {
    "gn:gn_country":"ES",
    "gn:gn_fcode":"PPLA3",
    "gn:gn_pop":553,
    "gn:population":553,
    "iso:country":"ES",
    "name:arg_x_preferred":[
        "Zarzuela del Pinar"
    ],
    "name:cat_x_preferred":[
        "Zarzuela del Pinar"
    ],
    "name:deu_x_preferred":[
        "Zarzuela del Pinar"
    ],
    "name:eng_x_preferred":[
        "Zarzuela del Pinar"
    ],
    "name:eus_x_preferred":[
        "Zarzuela del Pinar"
    ],
    "name:fra_x_preferred":[
        "Zarzuela del Pinar"
    ],
    "name:hun_x_preferred":[
        "Zarzuela del Pinar"
    ],
    "name:ina_x_preferred":[
        "Zarzuela del Pinar"
    ],
    "name:ita_x_preferred":[
        "Zarzuela del Pinar"
    ],
    "name:msa_x_preferred":[
        "Zarzuela del Pinar"
    ],
    "name:nan_x_preferred":[
        "Zarzuela del Pinar"
    ],
    "name:nld_x_preferred":[
        "Zarzuela del Pinar"
    ],
    "name:oci_x_preferred":[
        "Zarzuela del Pinar"
    ],
    "name:pol_x_preferred":[
        "Zarzuela del Pinar"
    ],
    "name:por_x_preferred":[
        "Zarzuela del Pinar"
    ],
    "name:rus_x_preferred":[
        "\u0421\u0430\u0440\u0441\u0443\u044d\u043b\u0430-\u0434\u0435\u043b\u044c-\u041f\u0438\u043d\u0430\u0440"
    ],
    "name:spa_x_preferred":[
        "Zarzuela del Pinar"
    ],
    "name:sqi_x_preferred":[
        "Zarzuela del Pinar"
    ],
    "name:ukr_x_preferred":[
        "\u0421\u0430\u0440\u0441\u0443\u0435\u043b\u0430-\u0434\u0435\u043b\u044c-\u041f\u0456\u043d\u0430\u0440"
    ],
    "name:vie_x_preferred":[
        "Zarzuela del Pinar"
    ],
    "name:war_x_preferred":[
        "Zarzuela del Pinar"
    ],
    "name:zho_x_preferred":[
        "\u8428\u5c14\u82cf\u57c3\u62c9\u5fb7\u5c14\u76ae\u7eb3\u5c14"
    ],
    "qs_pg:aaroncc":"ES",
    "qs_pg:gn_country":"ES",
    "qs_pg:gn_fcode":"PPLA3",
    "qs_pg:gn_pop":553,
    "qs_pg:name":"Zarzuela del Pinar",
    "qs_pg:name_adm0":"Espa\u00f1a",
    "qs_pg:name_adm1":"Castilla y Le\u00f3n",
    "qs_pg:photos_9r":0,
    "qs_pg:photos_sr":0,
    "qs_pg:pop_sr":2,
    "qs_pg:qs_pg_placetype":"locality",
    "qs_pg:qs_pg_placetype_gp":"Town",
    "qs_pg:woe_adm0":23424950,
    "woe:adm0_id":23424950,
    "woe:name_adm0":"Espa\u00f1a",
    "woe:name_adm1":"Castilla y Le\u00f3n",
    "woe:placetype":"Town",
    "wof:name":"Zarzuela del Pinar",
    "wof:placetype":"locality",
    "wof:population":553
},
  "geometry": {"coordinates":[-4.18457,41.26018],"type":"Point"}
}