{
  "type": "Feature",
  "properties": {
    "gn:admin1_code":"58",
    "gn:admin2_code":"OR",
    "gn:admin3_code":"32017",
    "gn:asciiname":"Novais",
    "gn:country_code":"ES",
    "gn:dem":733,
    "gn:feature_class":"P",
    "gn:feature_code":"PPL",
    "gn:name":"Novais",
    "gn:population":0,
    "gn:timezone":"Europe/Madrid",
    "iso:country":"ES",
    "name:bpy_x_preferred":[
        "\u09a8\u09cb\u09ad\u09be\u0987\u09b8"
    ],
    "name:ceb_x_preferred":[
        "Novais"
    ],
    "name:deu_x_preferred":[
        "Novais"
    ],
    "name:fra_x_preferred":[
        "Novais"
    ],
    "name:glg_x_preferred":[
        "Novais"
    ],
    "name:nld_x_preferred":[
        "Novais"
    ],
    "name:por_x_preferred":[
        "Novais"
    ],
    "name:swe_x_preferred":[
        "Novais"
    ],
    "name:ukr_x_preferred":[
        "\u041d\u043e\u0432\u0430\u0439\u0448"
    ],
    "wof:name":"Novais",
    "wof:placetype":"locality"
},
  "geometry": {"coordinates":[-6.90652,42.38474],"type":"Point"}
}