{
  "type": "Feature",
  "properties": {
    "gn:admin1_code":"58",
    "gn:admin2_code":"OR",
    "gn:admin3_code":"32017",
    "gn:asciiname":"Novais",
    "gn:country_code":"ES",
    "gn:dem":733,
    "gn:feature_class":"P",
    "gn:feature_code":"PPL",
    "gn:name":"Novais",
    "gn:population":0,
    "gn:timezone":"Europe/Madrid",
    "iso:country":"ES",
    "wof:name":"Novais",
    "wof:placetype":"locality"
},
  "geometry": {"coordinates":[-6.90652,42.38474],"type":"Point"}
}