{
  "type": "Feature",
  "properties": {
    "gn:admin1_code":"58",
    "gn:admin2_code":"LU",
    "gn:admin3_code":"27034",
    "gn:asciiname":"Trabadelo",
    "gn:country_code":"ES",
    "gn:dem":612,
    "gn:feature_class":"P",
    "gn:feature_code":"PPL",
    "gn:name":"Trabadelo",
    "gn:population":0,
    "gn:timezone":"Europe/Madrid",
    "iso:country":"ES",
    "wof:name":"Trabadelo",
    "wof:placetype":"locality"
},
  "geometry": {"coordinates":[-6.9435,42.96908],"type":"Point"}
}