{
  "type": "Feature",
  "properties": {
    "gn:admin1_code":"58",
    "gn:admin2_code":"LU",
    "gn:admin3_code":"27034",
    "gn:asciiname":"Trabadelo",
    "gn:country_code":"ES",
    "gn:dem":612,
    "gn:feature_class":"P",
    "gn:feature_code":"PPL",
    "gn:name":"Trabadelo",
    "gn:population":0,
    "gn:timezone":"Europe/Madrid",
    "iso:country":"ES",
    "name:arg_x_preferred":[
        "Trabadelo"
    ],
    "name:azb_x_preferred":[
        "\u062a\u0631\u0627\u0628\u0627\u062f\u0644\u0648"
    ],
    "name:cat_x_preferred":[
        "Trabadelo"
    ],
    "name:ceb_x_preferred":[
        "Trabadelo"
    ],
    "name:deu_x_preferred":[
        "Trabadelo"
    ],
    "name:eus_x_preferred":[
        "Trabadelo"
    ],
    "name:fas_x_preferred":[
        "\u062a\u0631\u0627\u0628\u0627\u062f\u0644\u0648"
    ],
    "name:fra_x_preferred":[
        "Trabadelo"
    ],
    "name:glg_x_preferred":[
        "Trabadelo"
    ],
    "name:haw_x_preferred":[
        "Trabadelo"
    ],
    "name:hun_x_preferred":[
        "Trabadelo"
    ],
    "name:ido_x_preferred":[
        "Trabadelo"
    ],
    "name:ina_x_preferred":[
        "Trabadelo"
    ],
    "name:ita_x_preferred":[
        "Trabadelo"
    ],
    "name:jpn_x_preferred":[
        "\u30c8\u30e9\u30d0\u30c7\u30fc\u30ed"
    ],
    "name:msa_x_preferred":[
        "Trabadelo"
    ],
    "name:mwl_x_preferred":[
        "Trabadelo"
    ],
    "name:oci_x_preferred":[
        "Trabadelo"
    ],
    "name:pol_x_preferred":[
        "Trabadelo"
    ],
    "name:por_x_preferred":[
        "Trabadelo"
    ],
    "name:rus_x_preferred":[
        "\u0422\u0440\u0430\u0431\u0430\u0434\u0435\u043b\u043e"
    ],
    "name:spa_x_preferred":[
        "Trabadelo"
    ],
    "name:swe_x_preferred":[
        "Trabadelo"
    ],
    "name:tpi_x_preferred":[
        "Trabadelo"
    ],
    "name:ukr_x_preferred":[
        "\u0422\u0440\u0430\u0431\u0430\u0434\u0435\u043b\u043e"
    ],
    "name:vie_x_preferred":[
        "Trabadelo"
    ],
    "name:war_x_preferred":[
        "Trabadelo"
    ],
    "name:zho_x_preferred":[
        "\u7279\u62c9\u74e6\u5fb7\u6d1b"
    ],
    "wof:name":"Trabadelo",
    "wof:placetype":"locality"
},
  "geometry": {"coordinates":[-6.9435,42.96908],"type":"Point"}
}