{
  "type": "Feature",
  "properties": {
    "gn:country":"ES",
    "gn:fcode":"ADM3",
    "gn:population":257,
    "iso:country":"ES",
    "name:ara_x_preferred":[
        "\u0628\u064a\u0646\u0627\u062f\u0627\u0644\u064a\u062f"
    ],
    "name:arg_x_preferred":[
        "Benadalid"
    ],
    "name:ast_x_preferred":[
        "Benadalid"
    ],
    "name:bul_x_preferred":[
        "\u0411\u0435\u043d\u0430\u0434\u0430\u043b\u0438\u0434"
    ],
    "name:cat_x_preferred":[
        "Benadalid"
    ],
    "name:ceb_x_preferred":[
        "Benadalid"
    ],
    "name:eng_x_preferred":[
        "Benadalid"
    ],
    "name:epo_x_preferred":[
        "Benadalid"
    ],
    "name:eus_x_preferred":[
        "Benadalid"
    ],
    "name:fas_x_preferred":[
        "\u0628\u0646\u0627\u062f\u0627\u0644\u06cc\u062f"
    ],
    "name:fra_x_preferred":[
        "Benadalid"
    ],
    "name:hat_x_preferred":[
        "Benadalid"
    ],
    "name:hun_x_preferred":[
        "Benadalid"
    ],
    "name:hye_x_preferred":[
        "\u0532\u0565\u0576\u0561\u0564\u0561\u056c\u056b\u0564"
    ],
    "name:ita_x_preferred":[
        "Benadalid"
    ],
    "name:kaz_x_preferred":[
        "\u0411\u0435\u043d\u0430\u0434\u0430\u043b\u0438\u0434"
    ],
    "name:kon_x_preferred":[
        "Benadalid"
    ],
    "name:msa_x_preferred":[
        "Benadalid"
    ],
    "name:nan_x_preferred":[
        "Benadalid"
    ],
    "name:nld_x_preferred":[
        "Benadalid"
    ],
    "name:oci_x_preferred":[
        "Benadalid"
    ],
    "name:pol_x_preferred":[
        "Benadalid"
    ],
    "name:por_x_preferred":[
        "Benadalid"
    ],
    "name:rus_x_preferred":[
        "\u0411\u0435\u043d\u0430\u0434\u0430\u043b\u0438\u0434"
    ],
    "name:spa_x_preferred":[
        "Benadalid"
    ],
    "name:sqi_x_preferred":[
        "Benadalid"
    ],
    "name:swe_x_preferred":[
        "Benadalid"
    ],
    "name:ukr_x_preferred":[
        "\u0411\u0435\u043d\u0430\u0434\u0430\u043b\u0456\u0434"
    ],
    "name:uzb_x_preferred":[
        "Benadalid"
    ],
    "name:vie_x_preferred":[
        "Benadalid"
    ],
    "name:war_x_preferred":[
        "Benadalid"
    ],
    "name:zho_x_preferred":[
        "\u8d1d\u7eb3\u8fbe\u5229\u5fb7"
    ],
    "qs_pg:aaroncc":"ES",
    "qs_pg:gn_country":"ES",
    "qs_pg:gn_fcode":"ADM3",
    "qs_pg:gn_pop":257,
    "qs_pg:name":"Benadalid",
    "qs_pg:name_adm0":"Espa\u00f1a",
    "qs_pg:name_adm1":"Andaluc\u00eda",
    "qs_pg:photos":45,
    "qs_pg:photos_1k":9,
    "qs_pg:photos_9k":1,
    "qs_pg:photos_9r":2,
    "qs_pg:photos_all":45,
    "qs_pg:photos_sr":2,
    "qs_pg:pop_sr":2,
    "qs_pg:qs_pg_placetype":"locality",
    "qs_pg:qs_pg_placetype_gp":"Town",
    "qs_pg:woe_adm0":23424950,
    "woe:adm0_id":23424950,
    "woe:name_adm0":"Espa\u00f1a",
    "woe:name_adm1":"Andaluc\u00eda",
    "woe:placetype":"Town",
    "wof:name":"Benadalid",
    "wof:placetype":"locality",
    "wof:population":262
},
  "geometry": {"coordinates":[-5.26745,36.61492],"type":"Point"}
}