{
  "type": "Feature",
  "properties": {
    "gn:admin1_code":"53",
    "gn:admin2_code":"GC",
    "gn:admin3_code":"35017",
    "gn:asciiname":"Tamariche",
    "gn:country_code":"ES",
    "gn:dem":365,
    "gn:feature_class":"P",
    "gn:feature_code":"PPL",
    "gn:name":"Tamariche",
    "gn:population":0,
    "gn:timezone":"Atlantic/Canary",
    "iso:country":"ES",
    "wof:name":"Tamariche",
    "wof:placetype":"locality"
},
  "geometry": {"coordinates":[-13.93933,28.5411],"type":"Point"}
}