{
  "type": "Feature",
  "properties": {
    "gn:gn_country":"ES",
    "gn:gn_fcode":"PPLA3",
    "gn:gn_pop":310,
    "gn:population":310,
    "iso:country":"ES",
    "name:baq_x_preferred":[
        "Fuentesa\u00faco de Fuentidue\u00f1a"
    ],
    "name:cat_x_preferred":[
        "Fuentesa\u00faco de Fuentidue\u00f1a"
    ],
    "name:chi_x_preferred":[
        "\u4e30\u7279\u7ecd\u79d1\u5fb7\u4e30\u8482\u675c\u57c3\u5c3c\u4e9a"
    ],
    "name:dut_x_preferred":[
        "Fuentesa\u00faco de Fuentidue\u00f1a"
    ],
    "name:eng_x_preferred":[
        "Fuentesa\u00faco de Fuentidue\u00f1a"
    ],
    "name:fre_x_preferred":[
        "Fuentesa\u00faco de Fuentidue\u00f1a"
    ],
    "name:ger_x_preferred":[
        "Fuentesa\u00faco de Fuentidue\u00f1a"
    ],
    "name:hun_x_preferred":[
        "Fuentesa\u00faco de Fuentidue\u00f1a"
    ],
    "name:ina_x_preferred":[
        "Fuentesa\u00faco de Fuentidue\u00f1a"
    ],
    "name:ita_x_preferred":[
        "Fuentesa\u00faco de Fuentidue\u00f1a"
    ],
    "name:may_x_preferred":[
        "Fuentesa\u00faco de Fuentidue\u00f1a"
    ],
    "name:nan_x_preferred":[
        "Fuentesa\u00faco de Fuentidue\u00f1a"
    ],
    "name:oci_x_preferred":[
        "Fuentesa\u00faco de Fuentidue\u00f1a"
    ],
    "name:pol_x_preferred":[
        "Fuentesa\u00faco de Fuentidue\u00f1a"
    ],
    "name:por_x_preferred":[
        "Fuentesa\u00faco de Fuentidue\u00f1a"
    ],
    "name:rus_x_preferred":[
        "\u0424\u0443\u044d\u043d\u0442\u0435\u0441\u0430\u0443\u043a\u043e-\u0434\u0435-\u0424\u0443\u044d\u043d\u0442\u0438\u0434\u0443\u044d\u043d\u0438\u044f"
    ],
    "name:spa_x_preferred":[
        "Fuentesa\u00faco de Fuentidue\u00f1a"
    ],
    "name:swe_x_preferred":[
        "Fuentesa\u00faco de Fuentidue\u00f1a"
    ],
    "name:ukr_x_preferred":[
        "\u0424\u0443\u0435\u043d\u0442\u0435\u0441\u0430\u0443\u043a\u043e-\u0434\u0435-\u0424\u0443\u0435\u043d\u0442\u0456\u0434\u0443\u0435\u043d\u044c\u044f"
    ],
    "name:vie_x_preferred":[
        "Fuentesa\u00faco de Fuentidue\u00f1a"
    ],
    "name:war_x_preferred":[
        "Fuentesa\u00faco de Fuentidue\u00f1a"
    ],
    "qs_pg:aaroncc":"ES",
    "qs_pg:gn_country":"ES",
    "qs_pg:gn_fcode":"PPLA3",
    "qs_pg:gn_pop":310,
    "qs_pg:name":"Fuentesa\u00faco de Fuentidue\u00f1a",
    "qs_pg:name_adm0":"Espa\u00f1a",
    "qs_pg:name_adm1":"Castilla y Le\u00f3n",
    "qs_pg:photos":154,
    "qs_pg:photos_1k":31,
    "qs_pg:photos_9k":1,
    "qs_pg:photos_9r":4,
    "qs_pg:photos_all":154,
    "qs_pg:photos_sr":4,
    "qs_pg:pop_sr":2,
    "qs_pg:qs_pg_placetype":"locality",
    "qs_pg:qs_pg_placetype_gp":"Town",
    "qs_pg:woe_adm0":23424950,
    "woe:adm0_id":23424950,
    "woe:name_adm0":"Espa\u00f1a",
    "woe:name_adm1":"Castilla y Le\u00f3n",
    "woe:placetype":"Town",
    "wof:name":"Fuentesa\u00faco de Fuentidue\u00f1a",
    "wof:placetype":"locality",
    "wof:population":310
},
  "geometry": {"coordinates":[-4.06215,41.42445],"type":"Point"}
}