{
  "type": "Feature",
  "properties": {
    "gn:admin1_code":"58",
    "gn:admin2_code":"LU",
    "gn:admin3_code":"27008",
    "gn:asciiname":"Martino",
    "gn:country_code":"ES",
    "gn:dem":548,
    "gn:feature_class":"P",
    "gn:feature_code":"PPL",
    "gn:name":"Marti\u00f1o",
    "gn:population":0,
    "gn:timezone":"Europe/Madrid",
    "iso:country":"ES",
    "name:ces_x_preferred":[
        "Martino"
    ],
    "name:fas_x_preferred":[
        "\u0645\u0627\u0631\u062a\u06cc\u0646\u0648"
    ],
    "name:fin_x_preferred":[
        "Martino"
    ],
    "name:fra_x_preferred":[
        "Martino"
    ],
    "name:ita_x_preferred":[
        "Martino"
    ],
    "name:jpn_x_preferred":[
        "\u30de\u30eb\u30c6\u30a3\u30fc\u30ce"
    ],
    "name:kor_x_preferred":[
        "\ub9c8\ub974\ud2f0\ub178"
    ],
    "name:rus_x_preferred":[
        "\u041c\u0430\u0440\u0442\u0438\u043d\u043e"
    ],
    "name:slk_x_preferred":[
        "Martino"
    ],
    "name:ukr_x_preferred":[
        "\u041c\u0430\u0440\u0442\u0456\u043d\u043e"
    ],
    "wof:name":"Martino",
    "wof:placetype":"locality"
},
  "geometry": {"coordinates":[-7.53267,42.62155],"type":"Point"}
}