{
  "type": "Feature",
  "properties": {
    "gn:admin1_code":"58",
    "gn:admin2_code":"LU",
    "gn:admin3_code":"27008",
    "gn:asciiname":"Martino",
    "gn:country_code":"ES",
    "gn:dem":548,
    "gn:feature_class":"P",
    "gn:feature_code":"PPL",
    "gn:name":"Marti\u00f1o",
    "gn:population":0,
    "gn:timezone":"Europe/Madrid",
    "iso:country":"ES",
    "wof:name":"Martino",
    "wof:placetype":"locality"
},
  "geometry": {"coordinates":[-7.53267,42.62155],"type":"Point"}
}