{
  "type": "Feature",
  "properties": {
    "gn:admin1_code":"55",
    "gn:admin2_code":"ZA",
    "gn:admin3_code":"49179",
    "gn:asciiname":"Sampil",
    "gn:country_code":"ES",
    "gn:dem":978,
    "gn:feature_class":"P",
    "gn:feature_code":"PPL",
    "gn:name":"Sampil",
    "gn:population":0,
    "gn:timezone":"Europe/Madrid",
    "iso:country":"ES",
    "wof:name":"Sampil",
    "wof:placetype":"locality"
},
  "geometry": {"coordinates":[-6.61542,42.08203],"type":"Point"}
}