{
  "type": "Feature",
  "properties": {
    "gn:admin1_code":"58",
    "gn:admin2_code":"PO",
    "gn:admin3_code":"36045",
    "gn:asciiname":"Viso",
    "gn:country_code":"ES",
    "gn:dem":315,
    "gn:feature_class":"P",
    "gn:feature_code":"PPL",
    "gn:name":"Viso",
    "gn:population":0,
    "gn:timezone":"Europe/Madrid",
    "iso:country":"ES",
    "name:und_x_variant":[
        "Santa Mar\u00eda",
        "Viso"
    ],
    "wof:name":"Viso",
    "wof:placetype":"locality"
},
  "geometry": {"coordinates":[-8.58333,42.31667],"type":"Point"}
}