{
  "type": "Feature",
  "properties": {
    "gn:admin1_code":"55",
    "gn:admin2_code":"BU",
    "gn:admin3_code":"09905",
    "gn:asciiname":"Terradillos de Sedano",
    "gn:country_code":"ES",
    "gn:dem":863,
    "gn:feature_class":"P",
    "gn:feature_code":"PPL",
    "gn:name":"Terradillos de Sedano",
    "gn:population":0,
    "gn:timezone":"Europe/Madrid",
    "iso:country":"ES",
    "wof:name":"Terradillos de Sedano",
    "wof:placetype":"locality"
},
  "geometry": {"coordinates":[-3.82084,42.65189],"type":"Point"}
}