{
  "type": "Feature",
  "properties": {
    "gn:admin1_code":"34",
    "gn:admin2_code":"O",
    "gn:admin3_code":"33034",
    "gn:asciiname":"Silvamayor",
    "gn:country_code":"ES",
    "gn:dem":328,
    "gn:feature_class":"P",
    "gn:feature_code":"PPL",
    "gn:name":"Silvamayor",
    "gn:population":0,
    "gn:timezone":"Europe/Madrid",
    "iso:country":"ES",
    "wof:name":"Silvamayor",
    "wof:placetype":"locality"
},
  "geometry": {"coordinates":[-6.38674,43.5249],"type":"Point"}
}