{
  "type": "Feature",
  "properties": {
    "gn:admin1_code":"51",
    "gn:admin2_code":"GR",
    "gn:admin3_code":"18159",
    "gn:asciiname":"Pinar",
    "gn:country_code":"ES",
    "gn:dem":902,
    "gn:feature_class":"P",
    "gn:feature_code":"PPL",
    "gn:name":"Pi\u00f1ar",
    "gn:population":1110,
    "gn:timezone":"Europe/Madrid",
    "iso:country":"ES",
    "name:und_x_variant":[
        "Pi\u00f1ar"
    ],
    "wof:name":"Pinar",
    "wof:placetype":"locality",
    "wof:population":1110
},
  "geometry": {"coordinates":[-3.43861,37.44457],"type":"Point"}
}