{
  "type": "Feature",
  "properties": {
    "gn:admin1_code":"51",
    "gn:admin2_code":"GR",
    "gn:admin3_code":"18159",
    "gn:asciiname":"Pinar",
    "gn:country_code":"ES",
    "gn:dem":902,
    "gn:feature_class":"P",
    "gn:feature_code":"PPL",
    "gn:name":"Pi\u00f1ar",
    "gn:population":1110,
    "gn:timezone":"Europe/Madrid",
    "iso:country":"ES",
    "name:ara_x_preferred":[
        "\u0628\u064a\u0646\u064a\u0627\u0631"
    ],
    "name:ast_x_preferred":[
        "P\u00ed\u00f1ar"
    ],
    "name:cat_x_preferred":[
        "P\u00ed\u00f1ar"
    ],
    "name:ceb_x_preferred":[
        "P\u00ed\u00f1ar"
    ],
    "name:epo_x_preferred":[
        "P\u00ed\u00f1ar"
    ],
    "name:eus_x_preferred":[
        "P\u00ed\u00f1ar"
    ],
    "name:fra_x_preferred":[
        "P\u00ed\u00f1ar"
    ],
    "name:hun_x_preferred":[
        "P\u00ed\u00f1ar"
    ],
    "name:hye_x_preferred":[
        "\u054a\u056b\u0576\u0575\u0561\u0580"
    ],
    "name:ita_x_preferred":[
        "P\u00ed\u00f1ar"
    ],
    "name:kaz_x_preferred":[
        "\u041f\u0438\u043d\u044c\u044f\u0440"
    ],
    "name:mlg_x_preferred":[
        "P\u00ed\u00f1ar"
    ],
    "name:msa_x_preferred":[
        "P\u00ed\u00f1ar"
    ],
    "name:nld_x_preferred":[
        "P\u00ed\u00f1ar"
    ],
    "name:oci_x_preferred":[
        "P\u00ed\u00f1ar"
    ],
    "name:pol_x_preferred":[
        "P\u00ed\u00f1ar"
    ],
    "name:por_x_preferred":[
        "P\u00ed\u00f1ar"
    ],
    "name:rus_x_preferred":[
        "\u041f\u0438\u043d\u044c\u044f\u0440"
    ],
    "name:spa_x_preferred":[
        "P\u00ed\u00f1ar"
    ],
    "name:sqi_x_preferred":[
        "P\u00ed\u00f1ar"
    ],
    "name:swe_x_preferred":[
        "P\u00ed\u00f1ar"
    ],
    "name:tur_x_preferred":[
        "P\u00ed\u00f1ar"
    ],
    "name:ukr_x_preferred":[
        "\u041f\u0456\u043d\u044c\u044f\u0440"
    ],
    "name:und_x_variant":[
        "Pi\u00f1ar"
    ],
    "name:uzb_x_preferred":[
        "P\u00ed\u00f1ar"
    ],
    "name:vie_x_preferred":[
        "P\u00ed\u00f1ar"
    ],
    "name:war_x_preferred":[
        "P\u00ed\u00f1ar"
    ],
    "name:zho_x_preferred":[
        "\u76ae\u5c3c\u4e9a\u5c14"
    ],
    "wof:name":"Pinar",
    "wof:placetype":"locality",
    "wof:population":1110
},
  "geometry": {"coordinates":[-3.43861,37.44457],"type":"Point"}
}