{
  "type": "Feature",
  "properties": {
    "gn:admin1_code":"52",
    "gn:admin2_code":"Z",
    "gn:admin3_code":"50901",
    "gn:asciiname":"San Felices",
    "gn:country_code":"ES",
    "gn:dem":750,
    "gn:feature_class":"P",
    "gn:feature_code":"PPL",
    "gn:name":"San Felices",
    "gn:population":0,
    "gn:timezone":"Europe/Madrid",
    "iso:country":"ES",
    "name:afr_x_preferred":[
        "San Felices"
    ],
    "name:ang_x_preferred":[
        "San Felices"
    ],
    "name:ara_x_preferred":[
        "\u0633\u0627\u0646 \u0641\u064a\u0644\u064a\u0633\u064a\u0633"
    ],
    "name:arg_x_preferred":[
        "San Felices"
    ],
    "name:ast_x_preferred":[
        "San Felices"
    ],
    "name:azb_x_preferred":[
        "\u0633\u0627\u0646 \u0641\u0644\u06cc\u0633\u0633"
    ],
    "name:cat_x_preferred":[
        "San Felices"
    ],
    "name:ceb_x_preferred":[
        "San Felices"
    ],
    "name:cos_x_preferred":[
        "San Felices"
    ],
    "name:epo_x_preferred":[
        "San Felices"
    ],
    "name:eus_x_preferred":[
        "San Felices"
    ],
    "name:fas_x_preferred":[
        "\u0633\u0627\u0646 \u0641\u0644\u06cc\u0633\u0633"
    ],
    "name:fra_x_preferred":[
        "San Felices"
    ],
    "name:glg_x_preferred":[
        "San Felices"
    ],
    "name:hak_x_preferred":[
        "San Felices"
    ],
    "name:hat_x_preferred":[
        "San Felices"
    ],
    "name:haw_x_preferred":[
        "San Felices"
    ],
    "name:hun_x_preferred":[
        "San Felices"
    ],
    "name:ido_x_preferred":[
        "San Felices"
    ],
    "name:ile_x_preferred":[
        "San Felices"
    ],
    "name:ina_x_preferred":[
        "San Felices"
    ],
    "name:ita_x_preferred":[
        "San Felices"
    ],
    "name:jam_x_preferred":[
        "San Felices"
    ],
    "name:kaz_x_preferred":[
        "\u0421\u0430\u043d-\u0424\u0435\u043b\u0438\u0441\u0435\u0441"
    ],
    "name:lij_x_preferred":[
        "San Felices"
    ],
    "name:mlg_x_preferred":[
        "San Felices"
    ],
    "name:msa_x_preferred":[
        "San Felices"
    ],
    "name:nld_x_preferred":[
        "San Felices"
    ],
    "name:nrm_x_preferred":[
        "San Felices"
    ],
    "name:oci_x_preferred":[
        "San Felices"
    ],
    "name:pap_x_preferred":[
        "San Felices"
    ],
    "name:pdc_x_preferred":[
        "San Felices"
    ],
    "name:pol_x_preferred":[
        "San Felices"
    ],
    "name:por_x_preferred":[
        "San Felices"
    ],
    "name:rmy_x_preferred":[
        "San Felices"
    ],
    "name:rus_x_preferred":[
        "\u0421\u0430\u043d-\u0424\u0435\u043b\u0438\u0441\u0435\u0441"
    ],
    "name:scn_x_preferred":[
        "San Felices"
    ],
    "name:spa_x_preferred":[
        "San Felices"
    ],
    "name:sqi_x_preferred":[
        "San Felices"
    ],
    "name:tah_x_preferred":[
        "San Felices"
    ],
    "name:tpi_x_preferred":[
        "San Felices"
    ],
    "name:ukr_x_preferred":[
        "\u0421\u0430\u043d-\u0424\u0435\u043b\u0456\u0441\u0435\u0441"
    ],
    "name:uzb_x_preferred":[
        "San Felices"
    ],
    "name:vie_x_preferred":[
        "San Felices"
    ],
    "name:war_x_preferred":[
        "San Felices"
    ],
    "name:wln_x_preferred":[
        "San Felices"
    ],
    "name:zho_x_preferred":[
        "\u5723\u8d39\u5229\u585e\u65af"
    ],
    "wof:name":"San Felices",
    "wof:placetype":"locality"
},
  "geometry": {"coordinates":[-0.82418,42.37545],"type":"Point"}
}