{
  "type": "Feature",
  "properties": {
    "gn:country":"ES",
    "gn:fcode":"PPLA3",
    "gn:population":271,
    "iso:country":"ES",
    "name:arg_x_preferred":[
        "Budia"
    ],
    "name:ast_x_preferred":[
        "Budia"
    ],
    "name:cat_x_preferred":[
        "Budia"
    ],
    "name:ceb_x_preferred":[
        "Budia"
    ],
    "name:eng_x_preferred":[
        "Budia"
    ],
    "name:epo_x_preferred":[
        "Budia"
    ],
    "name:eus_x_preferred":[
        "Budia"
    ],
    "name:fra_x_preferred":[
        "Budia"
    ],
    "name:hun_x_preferred":[
        "Budia"
    ],
    "name:ina_x_preferred":[
        "Budia"
    ],
    "name:ita_x_preferred":[
        "Budia"
    ],
    "name:kaz_x_preferred":[
        "\u0411\u0443\u0434\u0438\u0430"
    ],
    "name:msa_x_preferred":[
        "Budia"
    ],
    "name:nan_x_preferred":[
        "Budia"
    ],
    "name:nld_x_preferred":[
        "Budia"
    ],
    "name:oci_x_preferred":[
        "Budia"
    ],
    "name:pol_x_preferred":[
        "Budia"
    ],
    "name:por_x_preferred":[
        "Budia"
    ],
    "name:rus_x_preferred":[
        "\u0411\u0443\u0434\u0438\u0430"
    ],
    "name:spa_x_preferred":[
        "Budia"
    ],
    "name:swe_x_preferred":[
        "Budia"
    ],
    "name:ukr_x_preferred":[
        "\u0411\u0443\u0434\u0456\u044f"
    ],
    "name:vie_x_preferred":[
        "Budia"
    ],
    "name:war_x_preferred":[
        "Budia"
    ],
    "name:zho_x_preferred":[
        "\u5e03\u8fea\u4e9a"
    ],
    "qs_pg:aaroncc":"ES",
    "qs_pg:gn_country":"ES",
    "qs_pg:gn_fcode":"PPLA3",
    "qs_pg:gn_pop":271,
    "qs_pg:name":"Budia",
    "qs_pg:name_adm0":"Espa\u00f1a",
    "qs_pg:name_adm1":"Castilla-La Mancha",
    "qs_pg:photos_9r":0,
    "qs_pg:photos_sr":0,
    "qs_pg:pop_sr":2,
    "qs_pg:qs_pg_placetype":"locality",
    "qs_pg:qs_pg_placetype_gp":"Town",
    "qs_pg:woe_adm0":23424950,
    "woe:adm0_id":23424950,
    "woe:name_adm0":"Espa\u00f1a",
    "woe:name_adm1":"Castilla-La Mancha",
    "woe:placetype":"Town",
    "wof:name":"Budia",
    "wof:placetype":"locality",
    "wof:population":271
},
  "geometry": {"coordinates":[-2.75846,40.62734],"type":"Point"}
}