{
  "type": "Feature",
  "properties": {
    "gn:admin1_code":"59",
    "gn:admin2_code":"VI",
    "gn:admin3_code":"1046.0",
    "gn:asciiname":"Mimbredo",
    "gn:country_code":"ES",
    "gn:dem":506,
    "gn:feature_class":"P",
    "gn:feature_code":"PPL",
    "gn:name":"Mimbredo",
    "gn:population":0,
    "gn:timezone":"Europe/Madrid",
    "iso:country":"ES",
    "wof:name":"Mimbredo",
    "wof:placetype":"locality"
},
  "geometry": {"coordinates":[-2.90258,42.79231],"type":"Point"}
}