{
  "type": "Feature",
  "properties": {
    "gn:gn_country":"ES",
    "gn:gn_fcode":"PPLA3",
    "gn:gn_pop":17315,
    "gn:population":17315,
    "iso:country":"ES",
    "name:alb_x_preferred":[
        "Sanxenxo"
    ],
    "name:ara_x_preferred":[
        "\u0633\u0627\u0646\u062e\u064a\u0646\u062e\u0648"
    ],
    "name:arm_x_preferred":[
        "\u054d\u0561\u0576\u056d\u0565\u0576\u056d\u0578"
    ],
    "name:baq_x_preferred":[
        "Sanxenxo"
    ],
    "name:cat_x_preferred":[
        "Sanxenxo"
    ],
    "name:chi_x_preferred":[
        "\u6851\u514b\u68ee\u514b\u7d22"
    ],
    "name:dut_x_preferred":[
        "Sanxenxo"
    ],
    "name:eng_x_preferred":[
        "Sanxenxo"
    ],
    "name:epo_x_preferred":[
        "San\u015den\u015do"
    ],
    "name:fre_x_preferred":[
        "Sanxenxo"
    ],
    "name:ger_x_preferred":[
        "Sanxenxo"
    ],
    "name:glg_x_preferred":[
        "Sanxenxo"
    ],
    "name:hun_x_preferred":[
        "Sanxenxo"
    ],
    "name:ita_x_preferred":[
        "Sanxenxo"
    ],
    "name:jpn_x_preferred":[
        "\u30b5\u30f3\u30b7\u30a7\u30f3\u30b7\u30e7"
    ],
    "name:lit_x_preferred":[
        "Sanksenksas"
    ],
    "name:lmo_x_preferred":[
        "Sanxenxo"
    ],
    "name:may_x_preferred":[
        "Sanxenxo"
    ],
    "name:nan_x_preferred":[
        "Sanxenxo"
    ],
    "name:oci_x_preferred":[
        "Sanxenxo"
    ],
    "name:per_x_preferred":[
        "\u0633\u0627\u0646\u06a9\u0633\u0646\u06a9\u0633\u0648"
    ],
    "name:pol_x_preferred":[
        "Sanxenxo"
    ],
    "name:por_x_preferred":[
        "Sanxenxo"
    ],
    "name:rus_x_preferred":[
        "\u0421\u0430\u043d\u0445\u0435\u043d\u0445\u043e"
    ],
    "name:spa_x_preferred":[
        "Sangenjo"
    ],
    "name:swe_x_preferred":[
        "Sanxenxo"
    ],
    "name:tur_x_preferred":[
        "Sanxenxo"
    ],
    "name:ukr_x_preferred":[
        "\u0421\u0430\u043d\u0448\u0435\u043d\u0448\u043e"
    ],
    "name:uzb_x_preferred":[
        "Sanxenxo"
    ],
    "name:vie_x_preferred":[
        "Sanxenxo"
    ],
    "name:war_x_preferred":[
        "Sanxenxo"
    ],
    "qs_pg:aaroncc":"ES",
    "qs_pg:gn_country":"ES",
    "qs_pg:gn_fcode":"PPLA3",
    "qs_pg:gn_pop":17315,
    "qs_pg:name":"Sanxenxo",
    "qs_pg:name_adm0":"Espa\u00f1a",
    "qs_pg:name_adm1":"Galicia",
    "qs_pg:photos":2586,
    "qs_pg:photos_1k":524,
    "qs_pg:photos_9k":11,
    "qs_pg:photos_9r":10,
    "qs_pg:photos_all":2586,
    "qs_pg:photos_sr":18,
    "qs_pg:pop_sr":6,
    "qs_pg:qs_pg_placetype":"locality",
    "qs_pg:qs_pg_placetype_gp":"Town",
    "qs_pg:woe_adm0":23424950,
    "woe:adm0_id":23424950,
    "woe:name_adm0":"Espa\u00f1a",
    "woe:name_adm1":"Galicia",
    "woe:placetype":"Town",
    "wof:name":"Sanxenxo",
    "wof:placetype":"locality",
    "wof:population":17315
},
  "geometry": {"coordinates":[-8.80698,42.39996],"type":"Point"}
}