{
  "type": "Feature",
  "properties": {
    "gn:country":"ES",
    "gn:fcode":"PPL",
    "gn:population":0,
    "iso:country":"ES",
    "name:cat_x_preferred":[
        "Cales de Mallorca"
    ],
    "name:deu_x_preferred":[
        "Cales de Mallorca"
    ],
    "name:eng_x_preferred":[
        "Cales de Mallorca"
    ],
    "name:spa_x_preferred":[
        "Cales de Mallorca"
    ],
    "qs_pg:aaroncc":"ES",
    "qs_pg:gn_country":"ES",
    "qs_pg:gn_fcode":"PPL",
    "qs_pg:gn_pop":0,
    "qs_pg:name":"Calas de Mallorca",
    "qs_pg:name_adm0":"Espa\u00f1a",
    "qs_pg:name_adm1":"Illes Balears",
    "qs_pg:photos":885,
    "qs_pg:photos_1k":179,
    "qs_pg:photos_9k":4,
    "qs_pg:photos_9r":6,
    "qs_pg:photos_all":885,
    "qs_pg:photos_sr":10,
    "qs_pg:pop_sr":0,
    "qs_pg:qs_pg_placetype":"locality",
    "qs_pg:qs_pg_placetype_gp":"Town",
    "qs_pg:woe_adm0":23424950,
    "woe:adm0_id":23424950,
    "woe:name_adm0":"Espa\u00f1a",
    "woe:name_adm1":"Illes Balears",
    "woe:placetype":"Town",
    "wof:name":"Calas de Mallorca",
    "wof:placetype":"locality"
},
  "geometry": {"coordinates":[3.27839,39.46363],"type":"Point"}
}