{
  "type": "Feature",
  "properties": {
    "gn:admin1_code":"58",
    "gn:admin2_code":"OR",
    "gn:admin3_code":"32082",
    "gn:asciiname":"Abavides",
    "gn:country_code":"ES",
    "gn:dem":644,
    "gn:feature_class":"P",
    "gn:feature_code":"PPL",
    "gn:name":"Abavides",
    "gn:population":0,
    "gn:timezone":"Europe/Madrid",
    "iso:country":"ES",
    "wof:name":"Abavides",
    "wof:placetype":"locality"
},
  "geometry": {"coordinates":[-7.65151,42.04504],"type":"Point"}
}