{
  "type": "Feature",
  "properties": {
    "gn:admin1_code":"59",
    "gn:admin2_code":"BI",
    "gn:admin3_code":"48088.0",
    "gn:asciiname":"Ubide",
    "gn:country_code":"ES",
    "gn:dem":571,
    "gn:feature_class":"P",
    "gn:feature_code":"PPLA3",
    "gn:name":"Ubide",
    "gn:population":0,
    "gn:timezone":"Europe/Madrid",
    "iso:country":"ES",
    "name:ara_x_preferred":[
        "\u0623\u0648\u0628\u0627\u064a\u062f\u064a\u0627"
    ],
    "name:arg_x_preferred":[
        "Ubide"
    ],
    "name:ast_x_preferred":[
        "Ubide"
    ],
    "name:bre_x_preferred":[
        "Ubide"
    ],
    "name:cat_x_preferred":[
        "Ubide"
    ],
    "name:ceb_x_preferred":[
        "Ubide"
    ],
    "name:eus_x_preferred":[
        "Ubide"
    ],
    "name:fra_x_preferred":[
        "Ubide"
    ],
    "name:glg_x_preferred":[
        "Ubide"
    ],
    "name:hun_x_preferred":[
        "Ubide"
    ],
    "name:ita_x_preferred":[
        "Ubide"
    ],
    "name:lat_x_preferred":[
        "Ubidea"
    ],
    "name:msa_x_preferred":[
        "Ubide"
    ],
    "name:nld_x_preferred":[
        "Ubide"
    ],
    "name:oci_x_preferred":[
        "Ubide"
    ],
    "name:pol_x_preferred":[
        "Ubide"
    ],
    "name:por_x_preferred":[
        "Ubidea"
    ],
    "name:rus_x_preferred":[
        "\u0423\u0431\u0438\u0434\u0435"
    ],
    "name:sco_x_preferred":[
        "Ubide"
    ],
    "name:spa_x_preferred":[
        "Ubidea"
    ],
    "name:swe_x_preferred":[
        "Ubide"
    ],
    "name:ukr_x_preferred":[
        "\u0423\u0431\u0456\u0434\u0435"
    ],
    "name:uzb_x_preferred":[
        "Ubide"
    ],
    "name:war_x_preferred":[
        "Ubide"
    ],
    "name:zho_x_preferred":[
        "\u4e4c\u7ef4\u5fb7"
    ],
    "wof:name":"Ubide",
    "wof:placetype":"locality"
},
  "geometry": {"coordinates":[-2.68759,43.02396],"type":"Point"}
}