{
  "type": "Feature",
  "properties": {
    "gn:admin1_code":"59",
    "gn:admin2_code":"BI",
    "gn:admin3_code":"48088.0",
    "gn:asciiname":"Ubide",
    "gn:country_code":"ES",
    "gn:dem":571,
    "gn:feature_class":"P",
    "gn:feature_code":"PPLA3",
    "gn:name":"Ubide",
    "gn:population":0,
    "gn:timezone":"Europe/Madrid",
    "iso:country":"ES",
    "wof:name":"Ubide",
    "wof:placetype":"locality"
},
  "geometry": {"coordinates":[-2.68759,43.02396],"type":"Point"}
}