{
  "type": "Feature",
  "properties": {
    "iso:country":"ES",
    "name:cat_x_preferred":[
        "El Perellonet"
    ],
    "name:spa_x_preferred":[
        "El Perellonet"
    ],
    "wof:name":"El Perellonet",
    "wof:placetype":"neighbourhood"
},
  "geometry": {"coordinates":[-0.29073831899726,39.29550457405176],"type":"Point"}
}