{
  "type": "Feature",
  "properties": {
    "gn:gn_country":"ES",
    "gn:gn_fcode":"PPLA3",
    "gn:gn_pop":83,
    "gn:population":83,
    "iso:country":"ES",
    "name:arg_x_preferred":[
        "Or\u00edsoain"
    ],
    "name:ast_x_preferred":[
        "Or\u00edsoain"
    ],
    "name:bre_x_preferred":[
        "Orisoain"
    ],
    "name:cat_x_preferred":[
        "Orisoain"
    ],
    "name:ceb_x_preferred":[
        "Or\u00edsoain"
    ],
    "name:eng_x_preferred":[
        "Or\u00edsoain"
    ],
    "name:eus_x_preferred":[
        "Orisoain"
    ],
    "name:fra_x_preferred":[
        "Or\u00edsoain"
    ],
    "name:hun_x_preferred":[
        "Or\u00edsoain"
    ],
    "name:ita_x_preferred":[
        "Or\u00edsoain"
    ],
    "name:jpn_x_preferred":[
        "\u30aa\u30ea\u30bd\u30a2\u30a4\u30f3"
    ],
    "name:msa_x_preferred":[
        "Or\u00edsoain"
    ],
    "name:nan_x_preferred":[
        "Or\u00edsoain"
    ],
    "name:nld_x_preferred":[
        "Or\u00edsoain"
    ],
    "name:oci_x_preferred":[
        "Orisoain"
    ],
    "name:pol_x_preferred":[
        "Or\u00edsoain"
    ],
    "name:por_x_preferred":[
        "Or\u00edsoain"
    ],
    "name:rus_x_preferred":[
        "\u041e\u0440\u0438\u0441\u043e\u0430\u0439\u043d"
    ],
    "name:spa_x_preferred":[
        "Or\u00edsoain"
    ],
    "name:swe_x_preferred":[
        "Or\u00edsoain"
    ],
    "name:ukr_x_preferred":[
        "\u041e\u0440\u0456\u0441\u043e\u0430\u0439\u043d"
    ],
    "name:uzb_x_preferred":[
        "Or\u00edsoain"
    ],
    "name:vie_x_preferred":[
        "Or\u00edsoain"
    ],
    "name:war_x_preferred":[
        "Or\u00edsoain"
    ],
    "name:zho_x_preferred":[
        "\u5965\u91cc\u7d22\u963f\u56e0"
    ],
    "qs_pg:aaroncc":"ES",
    "qs_pg:gn_country":"ES",
    "qs_pg:gn_fcode":"PPLA3",
    "qs_pg:gn_pop":83,
    "qs_pg:name":"Or\u00edsoain",
    "qs_pg:name_adm0":"Espa\u00f1a",
    "qs_pg:name_adm1":"Comunidad Foral de Navarra",
    "qs_pg:photos":71,
    "qs_pg:photos_1k":14,
    "qs_pg:photos_9k":1,
    "qs_pg:photos_9r":2,
    "qs_pg:photos_all":71,
    "qs_pg:photos_sr":2,
    "qs_pg:pop_sr":1,
    "qs_pg:qs_pg_placetype":"locality",
    "qs_pg:qs_pg_placetype_gp":"Town",
    "qs_pg:woe_adm0":23424950,
    "woe:adm0_id":23424950,
    "woe:name_adm0":"Espa\u00f1a",
    "woe:name_adm1":"Comunidad Foral de Navarra",
    "woe:placetype":"Town",
    "wof:name":"Or\u00edsoain",
    "wof:placetype":"locality",
    "wof:population":83
},
  "geometry": {"coordinates":[-1.60403,42.60122],"type":"Point"}
}