{
  "type": "Feature",
  "properties": {
    "gn:admin1_code":"51",
    "gn:admin2_code":"AL",
    "gn:admin3_code":"04083",
    "gn:asciiname":"El Rascador",
    "gn:country_code":"ES",
    "gn:dem":1459,
    "gn:feature_class":"P",
    "gn:feature_code":"PPL",
    "gn:name":"El Rascador",
    "gn:population":0,
    "gn:timezone":"Europe/Madrid",
    "iso:country":"ES",
    "name:und_x_variant":[
        "Barriada El Rascador",
        "El Rascador"
    ],
    "wof:name":"El Rascador",
    "wof:placetype":"locality"
},
  "geometry": {"coordinates":[-2.51255,37.28954],"type":"Point"}
}