{
  "type": "Feature",
  "properties": {
    "gn:country":"ES",
    "gn:fcode":"PPLA3",
    "gn:population":43,
    "iso:country":"ES",
    "name:arg_x_preferred":[
        "Valhermoso"
    ],
    "name:ast_x_preferred":[
        "Valhermoso"
    ],
    "name:bul_x_preferred":[
        "\u0412\u0430\u043b\u0445\u0435\u0440\u043c\u043e\u0441\u043e"
    ],
    "name:cat_x_preferred":[
        "Valhermoso"
    ],
    "name:ceb_x_preferred":[
        "Valhermoso"
    ],
    "name:che_x_preferred":[
        "\u0412\u0430\u043b\u0435\u0440\u043c\u043e\u0441\u043e"
    ],
    "name:eng_x_preferred":[
        "Valhermoso"
    ],
    "name:epo_x_preferred":[
        "Valhermoso"
    ],
    "name:eus_x_preferred":[
        "Valhermoso"
    ],
    "name:fra_x_preferred":[
        "Valhermoso"
    ],
    "name:gle_x_preferred":[
        "Valhermoso"
    ],
    "name:hun_x_preferred":[
        "Valhermoso"
    ],
    "name:ile_x_preferred":[
        "Valhermoso"
    ],
    "name:ina_x_preferred":[
        "Valhermoso"
    ],
    "name:ita_x_preferred":[
        "Valhermoso"
    ],
    "name:kaz_x_preferred":[
        "\u0412\u0430\u043b\u044c\u0445\u0435\u0440\u043c\u043e\u0441\u043e"
    ],
    "name:lld_x_preferred":[
        "Valhermoso"
    ],
    "name:ltz_x_preferred":[
        "Valhermoso"
    ],
    "name:msa_x_preferred":[
        "Valhermoso"
    ],
    "name:nan_x_preferred":[
        "Valhermoso"
    ],
    "name:nld_x_preferred":[
        "Valhermoso"
    ],
    "name:nob_x_preferred":[
        "Valhermoso"
    ],
    "name:oci_x_preferred":[
        "Valhermoso"
    ],
    "name:pol_x_preferred":[
        "Valhermoso"
    ],
    "name:por_x_preferred":[
        "Valhermoso"
    ],
    "name:rus_x_preferred":[
        "\u0412\u0430\u043b\u044c\u0445\u0435\u0440\u043c\u043e\u0441\u043e"
    ],
    "name:spa_x_preferred":[
        "Valhermoso"
    ],
    "name:swe_x_preferred":[
        "Valhermoso"
    ],
    "name:tat_x_preferred":[
        "\u0412\u0430\u043b\u0435\u0440\u043c\u043e\u0441\u043e"
    ],
    "name:ukr_x_preferred":[
        "\u0412\u0430\u043b\u0435\u0440\u043c\u043e\u0441\u043e"
    ],
    "name:vec_x_preferred":[
        "Valhermoso"
    ],
    "name:vie_x_preferred":[
        "Valhermoso"
    ],
    "name:war_x_preferred":[
        "Valhermoso"
    ],
    "name:zho_x_preferred":[
        "\u5df4\u5c14\u57c3\u5c14\u83ab\u7d22"
    ],
    "qs_pg:aaroncc":"ES",
    "qs_pg:gn_country":"ES",
    "qs_pg:gn_fcode":"PPLA3",
    "qs_pg:gn_pop":43,
    "qs_pg:name":"Valhermoso",
    "qs_pg:name_adm0":"Espa\u00f1a",
    "qs_pg:name_adm1":"Castilla-La Mancha",
    "qs_pg:photos_9k":1,
    "qs_pg:photos_9r":1,
    "qs_pg:photos_all":1,
    "qs_pg:photos_sr":0,
    "qs_pg:pop_sr":1,
    "qs_pg:qs_pg_placetype":"locality",
    "qs_pg:qs_pg_placetype_gp":"Town",
    "qs_pg:woe_adm0":23424950,
    "woe:adm0_id":23424950,
    "woe:name_adm0":"Espa\u00f1a",
    "woe:name_adm1":"Castilla-La Mancha",
    "woe:placetype":"Town",
    "wof:name":"Valhermoso",
    "wof:placetype":"locality",
    "wof:population":43
},
  "geometry": {"coordinates":[-1.96121,40.7859],"type":"Point"}
}