{
  "type": "Feature",
  "properties": {
    "gn:admin1_code":"59",
    "gn:admin2_code":"VI",
    "gn:admin3_code":"01053",
    "gn:asciiname":"Chinchetru",
    "gn:country_code":"ES",
    "gn:dem":600,
    "gn:feature_class":"P",
    "gn:feature_code":"PPL",
    "gn:name":"Txintxetru",
    "gn:population":0,
    "gn:timezone":"Europe/Madrid",
    "iso:country":"ES",
    "name:eus_x_preferred":[
        "Txintxetru"
    ],
    "name:eus_x_variant":[
        "Intxetru"
    ],
    "name:spa_x_preferred":[
        "Chinchetru"
    ],
    "wof:name":"Chinchetru",
    "wof:placetype":"locality"
},
  "geometry": {"coordinates":[-2.45549,42.8359],"type":"Point"}
}