{
  "type": "Feature",
  "properties": {
    "gn:admin1_code":"51",
    "gn:admin2_code":"GR",
    "gn:admin3_code":"18105",
    "gn:asciiname":"Montalbanes",
    "gn:country_code":"ES",
    "gn:dem":888,
    "gn:feature_class":"P",
    "gn:feature_code":"PPL",
    "gn:name":"Montalbanes",
    "gn:population":0,
    "gn:timezone":"Europe/Madrid",
    "iso:country":"ES",
    "name:und_x_variant":[
        "Caser\u00edo Montalbanes",
        "Montalbanes"
    ],
    "wof:name":"Montalbanes",
    "wof:placetype":"locality"
},
  "geometry": {"coordinates":[-3.52056,37.42709],"type":"Point"}
}