{
  "type": "Feature",
  "properties": {
    "gn:admin1_code":"58",
    "gn:admin2_code":"LU",
    "gn:admin3_code":"27019",
    "gn:asciiname":"Santa Cilla de Valadouro",
    "gn:country_code":"ES",
    "gn:dem":160,
    "gn:feature_class":"P",
    "gn:feature_code":"PPL",
    "gn:name":"Santa Cilla de Valadouro",
    "gn:population":0,
    "gn:timezone":"Europe/Madrid",
    "iso:country":"ES",
    "name:und_x_variant":[
        "Santa Cecilia",
        "Valle de Oro"
    ],
    "wof:name":"Santa Cilla de Valadouro",
    "wof:placetype":"locality"
},
  "geometry": {"coordinates":[-7.35086,43.55579],"type":"Point"}
}