{
  "type": "Feature",
  "properties": {
    "gn:admin1_code":"55",
    "gn:admin2_code":"LE",
    "gn:admin3_code":"24043",
    "gn:asciiname":"Nogar",
    "gn:country_code":"ES",
    "gn:dem":821,
    "gn:feature_class":"P",
    "gn:feature_code":"PPL",
    "gn:name":"Nogar",
    "gn:population":0,
    "gn:timezone":"Europe/Madrid",
    "iso:country":"ES",
    "wof:name":"Nogar",
    "wof:placetype":"locality"
},
  "geometry": {"coordinates":[-6.50905,42.29914],"type":"Point"}
}