{
  "type": "Feature",
  "properties": {
    "gn:admin1_code":"60",
    "gn:admin2_code":"V",
    "gn:admin3_code":"46208",
    "gn:asciiname":"Alcudiola",
    "gn:country_code":"ES",
    "gn:dem":39,
    "gn:feature_class":"P",
    "gn:feature_code":"PPL",
    "gn:name":"Alcudiola",
    "gn:population":0,
    "gn:timezone":"Europe/Madrid",
    "iso:country":"ES",
    "wof:name":"Alcudiola",
    "wof:placetype":"locality"
},
  "geometry": {"coordinates":[-0.16667,38.93333],"type":"Point"}
}