{
  "type": "Feature",
  "properties": {
    "gn:admin1_code":"55",
    "gn:admin2_code":"BU",
    "gn:admin3_code":"09415",
    "gn:asciiname":"Mundilla",
    "gn:country_code":"ES",
    "gn:dem":1035,
    "gn:feature_class":"P",
    "gn:feature_code":"PPL",
    "gn:name":"Mundilla",
    "gn:population":0,
    "gn:timezone":"Europe/Madrid",
    "iso:country":"ES",
    "wof:name":"Mundilla",
    "wof:placetype":"locality"
},
  "geometry": {"coordinates":[-4.05479,42.72854],"type":"Point"}
}