{
  "type": "Feature",
  "properties": {
    "gn:admin1_code":"58",
    "gn:admin2_code":"C",
    "gn:admin3_code":"15007",
    "gn:asciiname":"Barcala",
    "gn:cc2":"ES",
    "gn:country_code":"ES",
    "gn:dem":251,
    "gn:feature_class":"P",
    "gn:feature_code":"PPL",
    "gn:name":"Barcala",
    "gn:population":0,
    "gn:timezone":"Europe/Madrid",
    "iso:country":"ES",
    "name:und_x_variant":[
        "San Cipriano",
        "San Cipri\u00e1n",
        "Barcala"
    ],
    "wof:name":"Barcala",
    "wof:placetype":"locality"
},
  "geometry": {"coordinates":[-8.73333,42.93333],"type":"Point"}
}