{
  "type": "Feature",
  "properties": {
    "iso:country":"ES",
    "qs:a0":"Espa\u00f1a",
    "qs:a1":"*Alicante",
    "qs:a1r":"0Comunidad Valenciana",
    "qs:adm0":"Espa\u00f1a",
    "qs:la_lc":"*",
    "qs:level":"locality",
    "qs:loc":"Mirarrosa",
    "qs:loc_alt":"Mirarrosa",
    "qs:pop":0,
    "qs:type":"buffered point",
    "wof:name":"Mirarrosa",
    "wof:placetype":"locality"
},
  "geometry": {"coordinates":[0.019565,38.847521],"type":"Point"}
}