{
  "type": "Feature",
  "properties": {
    "iso:country":"ES",
    "name:arg_x_preferred":[
        "El Catllar"
    ],
    "name:ast_x_preferred":[
        "El Catllar"
    ],
    "name:cat_x_preferred":[
        "el Catllar"
    ],
    "name:ceb_x_preferred":[
        "El Catllar"
    ],
    "name:che_x_preferred":[
        "\u042d\u043b\u044c-\u041a\u0430\u043b\u043b\u044c\u044f\u0440"
    ],
    "name:deu_x_preferred":[
        "El Catllar"
    ],
    "name:eng_x_preferred":[
        "El Catllar"
    ],
    "name:eus_x_preferred":[
        "El Catllar"
    ],
    "name:fas_x_preferred":[
        "\u0627\u0644 \u06a9\u0627\u062a\u06cc\u0627\u0631"
    ],
    "name:fra_x_preferred":[
        "El Catllar"
    ],
    "name:gle_x_preferred":[
        "el Catllar"
    ],
    "name:glg_x_preferred":[
        "El Catllar"
    ],
    "name:hun_x_preferred":[
        "El Catllar"
    ],
    "name:hye_x_preferred":[
        "\u0537\u056c \u053f\u0561\u056c\u0575\u0561\u0580"
    ],
    "name:ile_x_preferred":[
        "El Catllar"
    ],
    "name:ita_x_preferred":[
        "El Catllar"
    ],
    "name:lat_x_preferred":[
        "El Catllar"
    ],
    "name:lld_x_preferred":[
        "El Catllar"
    ],
    "name:msa_x_preferred":[
        "El Catllar"
    ],
    "name:nld_x_preferred":[
        "El Catllar"
    ],
    "name:oci_x_preferred":[
        "El Catllar"
    ],
    "name:pol_x_preferred":[
        "El Catllar"
    ],
    "name:por_x_preferred":[
        "El Catllar"
    ],
    "name:rus_x_preferred":[
        "\u042d\u043b\u044c-\u041a\u0430\u043b\u043b\u044c\u044f\u0440"
    ],
    "name:spa_x_preferred":[
        "Catllar"
    ],
    "name:spa_x_variant":[
        "El Catllar"
    ],
    "name:sqi_x_preferred":[
        "El Catllar"
    ],
    "name:swe_x_preferred":[
        "El Catllar"
    ],
    "name:tat_x_preferred":[
        "\u042d\u043b\u044c-\u041a\u0430\u043b\u043b\u044c\u044f\u0440"
    ],
    "name:uzb_x_preferred":[
        "El Catllar"
    ],
    "name:vec_x_preferred":[
        "El Catllar"
    ],
    "name:vie_x_preferred":[
        "El Catllar"
    ],
    "name:war_x_preferred":[
        "El Catllar"
    ],
    "name:zho_x_preferred":[
        "\u57c3\u5c14\u5361\u7279\u5229\u4e9a\u5c14"
    ],
    "qs:a0":"Espa\u00f1a",
    "qs:a1":"*Tarragona",
    "qs:a1r":"0Catalu\u00f1a",
    "qs:adm0":"Espa\u00f1a",
    "qs:la_lc":"*",
    "qs:level":"locality",
    "qs:loc":"Catllar,El",
    "qs:loc_alt":"Catllar,El",
    "qs:pop":0,
    "qs:type":"buffered point",
    "wof:lang":[
        "spa"
    ],
    "wof:name":"Catllar,El",
    "wof:placetype":"locality"
},
  "geometry": {"coordinates":[1.325218,41.175114],"type":"Point"}
}