{
  "type": "Feature",
  "properties": {
    "gn:admin1_code":"52",
    "gn:admin2_code":"TE",
    "gn:admin3_code":"44192",
    "gn:asciiname":"La Puebla de Valverde",
    "gn:country_code":"ES",
    "gn:dem":1108,
    "gn:feature_class":"P",
    "gn:feature_code":"PPL",
    "gn:name":"La Puebla de Valverde",
    "gn:population":513,
    "gn:timezone":"Europe/Madrid",
    "iso:country":"ES",
    "name:azb_x_preferred":[
        "\u0644\u0627 \u067e\u0648\u0626\u0628\u0644\u0627 \u062f \u0628\u0627\u0644\u0628\u0631\u062f\u0647"
    ],
    "name:fas_x_preferred":[
        "\u0644\u0627 \u067e\u0648\u0626\u0628\u0644\u0627 \u062f \u0628\u0627\u0644\u0628\u0631\u062f\u0647"
    ],
    "name:hye_x_preferred":[
        "\u053c\u0561 \u054a\u0578\u0582\u0565\u0562\u056c\u0561 \u0564\u0565 \u054e\u0561\u056c\u057e\u0565\u0580\u0564\u0565"
    ],
    "name:urd_x_preferred":[
        "\u0644\u0627 \u067e\u06cc\u0648\u0628\u0644\u0627 \u062f\u06d2 \u0627\u0644\u0648\u06cc\u0631\u0688\u06cc"
    ],
    "wof:name":"La Puebla de Valverde",
    "wof:placetype":"locality",
    "wof:population":513
},
  "geometry": {"coordinates":[-0.92783,40.22409],"type":"Point"}
}