{
  "type": "Feature",
  "properties": {
    "gn:admin1_code":"51",
    "gn:admin2_code":"AL",
    "gn:admin3_code":"04016",
    "gn:asciiname":"Morata",
    "gn:country_code":"ES",
    "gn:dem":73,
    "gn:feature_class":"P",
    "gn:feature_code":"PPL",
    "gn:name":"Morata",
    "gn:population":0,
    "gn:timezone":"Europe/Madrid",
    "iso:country":"ES",
    "name:ara_x_preferred":[
        "\u0645\u0648\u0631\u0627\u062a\u0627"
    ],
    "name:cat_x_preferred":[
        "Morata"
    ],
    "name:ceb_x_preferred":[
        "Morata"
    ],
    "name:deu_x_preferred":[
        "Morata"
    ],
    "name:fra_x_preferred":[
        "Morata"
    ],
    "name:rus_x_preferred":[
        "\u041c\u043e\u0440\u0430\u0442\u0430"
    ],
    "name:spa_x_preferred":[
        "Morata"
    ],
    "name:und_x_variant":[
        "Casas Morata"
    ],
    "wof:name":"Morata",
    "wof:placetype":"locality"
},
  "geometry": {"coordinates":[-1.89936,37.23348],"type":"Point"}
}