{
  "type": "Feature",
  "properties": {
    "gn:admin1_code":"58",
    "gn:admin2_code":"LU",
    "gn:admin3_code":"27015",
    "gn:asciiname":"Moman",
    "gn:cc2":"ES",
    "gn:country_code":"ES",
    "gn:dem":407,
    "gn:feature_class":"P",
    "gn:feature_code":"PPL",
    "gn:name":"Mom\u00e1n",
    "gn:population":0,
    "gn:timezone":"Europe/Madrid",
    "iso:country":"ES",
    "name:und_x_variant":[
        "San Pedro",
        "Mom\u00e1n"
    ],
    "wof:name":"Moman",
    "wof:placetype":"locality"
},
  "geometry": {"coordinates":[-7.48333,43.21667],"type":"Point"}
}