{
  "type": "Feature",
  "properties": {
    "gn:gn_country":"ES",
    "gn:gn_fcode":"PPLA3",
    "gn:gn_pop":269,
    "gn:population":269,
    "iso:country":"ES",
    "name:ara_x_preferred":[
        "\u0623\u0644\u0643\u0627\u0644\u0627 \u062f\u064a \u0625\u0628\u0631\u0648"
    ],
    "name:arg_x_preferred":[
        "Alcal\u00e1 d'Ebro"
    ],
    "name:baq_x_preferred":[
        "Alcal\u00e1 de Ebro"
    ],
    "name:cat_x_preferred":[
        "Alcal\u00e1 de Ebro"
    ],
    "name:chi_x_preferred":[
        "\u963f\u5c14\u5361\u62c9\u5fb7\u57c3\u592b\u7f57"
    ],
    "name:dut_x_preferred":[
        "Alcal\u00e1 de Ebro"
    ],
    "name:eng_x_preferred":[
        "Alcal\u00e1 de Ebro"
    ],
    "name:fre_x_preferred":[
        "Alcal\u00e1 de Ebro"
    ],
    "name:ger_x_preferred":[
        "Alcal\u00e1 de Ebro"
    ],
    "name:hun_x_preferred":[
        "Alcal\u00e1 de Ebro"
    ],
    "name:ita_x_preferred":[
        "Alcal\u00e1 de Ebro"
    ],
    "name:kaz_x_preferred":[
        "\u0410\u043b\u044c\u043a\u0430\u043b\u0430-\u0434\u0435-\u042d\u0431\u0440\u043e"
    ],
    "name:may_x_preferred":[
        "Alcal\u00e1 de Ebro"
    ],
    "name:nan_x_preferred":[
        "Alcal\u00e1 de Ebro"
    ],
    "name:oci_x_preferred":[
        "Alcal\u00e1 de Ebro"
    ],
    "name:per_x_preferred":[
        "\u0627\u0644\u06a9\u0627\u0644\u0627 \u062f\u0648 \u0627\u0628\u0631\u0648"
    ],
    "name:pol_x_preferred":[
        "Alcal\u00e1 de Ebro"
    ],
    "name:por_x_preferred":[
        "Alcal\u00e1 de Ebro"
    ],
    "name:rus_x_preferred":[
        "\u0410\u043b\u044c\u043a\u0430\u043b\u0430-\u0434\u0435-\u042d\u0431\u0440\u043e"
    ],
    "name:spa_x_preferred":[
        "Alcal\u00e1 de Ebro"
    ],
    "name:swe_x_preferred":[
        "Alcal\u00e1 de Ebro"
    ],
    "name:ukr_x_preferred":[
        "\u0410\u043b\u044c\u043a\u0430\u043b\u0430-\u0434\u0435-\u0415\u0431\u0440\u043e"
    ],
    "name:uzb_x_preferred":[
        "Alcal\u00e1 de Ebro"
    ],
    "name:vie_x_preferred":[
        "Alcal\u00e1 de Ebro"
    ],
    "name:war_x_preferred":[
        "Alcal\u00e1 de Ebro"
    ],
    "qs_pg:aaroncc":"ES",
    "qs_pg:gn_country":"ES",
    "qs_pg:gn_fcode":"PPLA3",
    "qs_pg:gn_pop":269,
    "qs_pg:name":"Alcal\u00e1 de Ebro",
    "qs_pg:name_adm0":"Espa\u00f1a",
    "qs_pg:name_adm1":"Arag\u00f3n",
    "qs_pg:photos":41,
    "qs_pg:photos_1k":8,
    "qs_pg:photos_9k":1,
    "qs_pg:photos_9r":2,
    "qs_pg:photos_all":41,
    "qs_pg:photos_sr":2,
    "qs_pg:pop_sr":2,
    "qs_pg:qs_pg_placetype":"locality",
    "qs_pg:qs_pg_placetype_gp":"Town",
    "qs_pg:woe_adm0":23424950,
    "woe:adm0_id":23424950,
    "woe:name_adm0":"Espa\u00f1a",
    "woe:name_adm1":"Arag\u00f3n",
    "woe:placetype":"Town",
    "wof:name":"Alcal\u00e1 de Ebro",
    "wof:placetype":"locality",
    "wof:population":269
},
  "geometry": {"coordinates":[-1.19429,41.81495],"type":"Point"}
}