{
  "type": "Feature",
  "properties": {
    "gn:admin1_code":"58",
    "gn:admin2_code":"C",
    "gn:admin3_code":"15039",
    "gn:asciiname":"Verines",
    "gn:country_code":"ES",
    "gn:dem":380,
    "gn:feature_class":"P",
    "gn:feature_code":"PPL",
    "gn:name":"Verines",
    "gn:population":0,
    "gn:timezone":"Europe/Madrid",
    "iso:country":"ES",
    "name:und_x_variant":[
        "Santa Mar\u00eda",
        "Verines"
    ],
    "wof:name":"Verines",
    "wof:placetype":"locality"
},
  "geometry": {"coordinates":[-8.05,43.26667],"type":"Point"}
}