{
  "type": "Feature",
  "properties": {
    "gn:admin1_code":"39",
    "gn:admin2_code":"S",
    "gn:admin3_code":"39003",
    "gn:asciiname":"Calga",
    "gn:country_code":"ES",
    "gn:dem":315,
    "gn:feature_class":"P",
    "gn:feature_code":"PPL",
    "gn:name":"Calga",
    "gn:population":0,
    "gn:timezone":"Europe/Madrid",
    "iso:country":"ES",
    "wof:name":"Calga",
    "wof:placetype":"locality"
},
  "geometry": {"coordinates":[-4.02029,43.20025],"type":"Point"}
}