{
  "type": "Feature",
  "properties": {
    "gn:admin1_code":"32",
    "gn:admin3_code":"31120",
    "gn:asciiname":"Estenoz",
    "gn:country_code":"ES",
    "gn:dem":524,
    "gn:feature_class":"P",
    "gn:feature_code":"PPL",
    "gn:name":"Est\u00e9noz",
    "gn:population":0,
    "gn:timezone":"Europe/Madrid",
    "iso:country":"ES",
    "wof:name":"Estenoz",
    "wof:placetype":"locality"
},
  "geometry": {"coordinates":[-1.92278,42.74424000000001],"type":"Point"}
}