{
  "type": "Feature",
  "properties": {
    "gn:admin1_code":"34",
    "gn:admin2_code":"O",
    "gn:admin3_code":"33011",
    "gn:asciiname":"Bustiello",
    "gn:country_code":"ES",
    "gn:dem":717,
    "gn:feature_class":"P",
    "gn:feature_code":"PPL",
    "gn:name":"Bustiello",
    "gn:population":0,
    "gn:timezone":"Europe/Madrid",
    "iso:country":"ES",
    "name:deu_x_preferred":[
        "Bustiello"
    ],
    "name:spa_x_preferred":[
        "Bustiello"
    ],
    "wof:name":"Bustiello",
    "wof:placetype":"locality"
},
  "geometry": {"coordinates":[-6.54744,43.08853],"type":"Point"}
}