{
  "type": "Feature",
  "properties": {
    "gn:admin1_code":"39",
    "gn:admin2_code":"S",
    "gn:admin3_code":"39102",
    "gn:asciiname":"San Bartolome de los Montes",
    "gn:country_code":"ES",
    "gn:dem":269,
    "gn:feature_class":"P",
    "gn:feature_code":"PPL",
    "gn:name":"San Bartolom\u00e9 de los Montes",
    "gn:population":0,
    "gn:timezone":"Europe/Madrid",
    "iso:country":"ES",
    "name:und_x_variant":[
        "San Bartolom\u00e9 de los Montes"
    ],
    "wof:name":"San Bartolome de los Montes",
    "wof:placetype":"locality"
},
  "geometry": {"coordinates":[-3.4863,43.32381],"type":"Point"}
}