{
  "type": "Feature",
  "properties": {
    "gn:admin1_code":"51",
    "gn:admin2_code":"AL",
    "gn:admin3_code":"04007",
    "gn:asciiname":"Los Lozanos",
    "gn:cc2":"ES",
    "gn:country_code":"ES",
    "gn:dem":603,
    "gn:feature_class":"P",
    "gn:feature_code":"PPL",
    "gn:name":"Los Lozanos",
    "gn:population":0,
    "gn:timezone":"Europe/Madrid",
    "iso:country":"ES",
    "name:und_x_variant":[
        "Caser\u00edo Los Lozanos",
        "Los Lozanos"
    ],
    "wof:name":"Los Lozanos",
    "wof:placetype":"locality"
},
  "geometry": {"coordinates":[-3.06667,36.93333],"type":"Point"}
}