{
  "type": "Feature",
  "properties": {
    "iso:country":"ES",
    "qs_pg:aaroncc":"ES",
    "qs_pg:name":"Coa\u00f1ana",
    "qs_pg:name_adm0":"Espa\u00f1a",
    "qs_pg:name_adm1":"Principado de Asturias",
    "qs_pg:photos":71,
    "qs_pg:photos_1k":14,
    "qs_pg:photos_9k":1,
    "qs_pg:photos_9r":2,
    "qs_pg:photos_all":71,
    "qs_pg:photos_sr":2,
    "qs_pg:pop_sr":0,
    "qs_pg:qs_pg_placetype":"locality",
    "qs_pg:qs_pg_placetype_gp":"Town",
    "qs_pg:woe_adm0":23424950,
    "woe:adm0_id":23424950,
    "woe:name_adm0":"Espa\u00f1a",
    "woe:name_adm1":"Principado de Asturias",
    "woe:placetype":"Town",
    "wof:name":"Coa\u00f1ana",
    "wof:placetype":"locality"
},
  "geometry": {"coordinates":[-5.98551,43.158306],"type":"Point"}
}