{
  "type": "Feature",
  "properties": {
    "gn:gn_country":"ES",
    "gn:gn_fcode":"PPLA3",
    "gn:gn_pop":145,
    "gn:population":145,
    "iso:country":"ES",
    "name:arg_x_preferred":[
        "Vallecillo"
    ],
    "name:cat_x_preferred":[
        "Vallecillo"
    ],
    "name:eng_x_preferred":[
        "Vallecillo"
    ],
    "name:eus_x_preferred":[
        "Vallecillo"
    ],
    "name:fra_x_preferred":[
        "Vallecillo"
    ],
    "name:glg_x_preferred":[
        "Vallecillo"
    ],
    "name:haw_x_preferred":[
        "Vallecillo"
    ],
    "name:hun_x_preferred":[
        "Vallecillo"
    ],
    "name:ido_x_preferred":[
        "Vallecillo"
    ],
    "name:ina_x_preferred":[
        "Vallecillo"
    ],
    "name:ita_x_preferred":[
        "Vallecillo"
    ],
    "name:msa_x_preferred":[
        "Vallecillo"
    ],
    "name:nan_x_preferred":[
        "Vallecillo"
    ],
    "name:nld_x_preferred":[
        "Vallecillo"
    ],
    "name:oci_x_preferred":[
        "Vallecillo"
    ],
    "name:pol_x_preferred":[
        "Vallecillo"
    ],
    "name:por_x_preferred":[
        "Vallecillo"
    ],
    "name:rus_x_preferred":[
        "\u0412\u0430\u043b\u044c\u0435\u0441\u0438\u043b\u044c\u043e"
    ],
    "name:spa_x_preferred":[
        "Vallecillo"
    ],
    "name:swe_x_preferred":[
        "Vallecillo"
    ],
    "name:tpi_x_preferred":[
        "Vallecillo"
    ],
    "name:ukr_x_preferred":[
        "\u0412\u0430\u043b\u044c\u0454\u0441\u0456\u043b\u044c\u0439\u043e"
    ],
    "name:war_x_preferred":[
        "Vallecillo"
    ],
    "name:zho_x_preferred":[
        "\u5df4\u5217\u897f\u7565"
    ],
    "qs_pg:aaroncc":"ES",
    "qs_pg:gn_country":"ES",
    "qs_pg:gn_fcode":"PPLA3",
    "qs_pg:gn_pop":145,
    "qs_pg:name":"Vallecillo",
    "qs_pg:name_adm0":"Espa\u00f1a",
    "qs_pg:name_adm1":"Castilla y Le\u00f3n",
    "qs_pg:photos_9k":1,
    "qs_pg:photos_9r":1,
    "qs_pg:photos_all":2,
    "qs_pg:photos_sr":0,
    "qs_pg:pop_sr":1,
    "qs_pg:qs_pg_placetype":"locality",
    "qs_pg:qs_pg_placetype_gp":"Town",
    "qs_pg:woe_adm0":23424950,
    "woe:adm0_id":23424950,
    "woe:name_adm0":"Espa\u00f1a",
    "woe:name_adm1":"Castilla y Le\u00f3n",
    "woe:placetype":"Town",
    "wof:name":"Vallecillo",
    "wof:placetype":"locality",
    "wof:population":145
},
  "geometry": {"coordinates":[-5.21088,42.35604],"type":"Point"}
}