{
  "type": "Feature",
  "properties": {
    "gn:admin1_code":"34",
    "gn:admin2_code":"O",
    "gn:admin3_code":"33075",
    "gn:asciiname":"Salgueiras",
    "gn:country_code":"ES",
    "gn:dem":818,
    "gn:feature_class":"P",
    "gn:feature_code":"PPL",
    "gn:name":"Salgueiras",
    "gn:population":0,
    "gn:timezone":"Europe/Madrid",
    "iso:country":"ES",
    "wof:name":"Salgueiras",
    "wof:placetype":"locality"
},
  "geometry": {"coordinates":[-7.02478,43.31871],"type":"Point"}
}