{
  "type": "Feature",
  "properties": {
    "gn:admin1_code":"58",
    "gn:admin2_code":"OR",
    "gn:admin3_code":"32085",
    "gn:asciiname":"Mourazos",
    "gn:country_code":"ES",
    "gn:dem":389,
    "gn:feature_class":"P",
    "gn:feature_code":"PPL",
    "gn:name":"Mourazos",
    "gn:population":0,
    "gn:timezone":"Europe/Madrid",
    "iso:country":"ES",
    "wof:name":"Mourazos",
    "wof:placetype":"locality"
},
  "geometry": {"coordinates":[-7.43397,41.88337],"type":"Point"}
}