{
  "type": "Feature",
  "properties": {
    "gn:admin1_code":"51",
    "gn:admin2_code":"MA",
    "gn:admin3_code":"29051.0",
    "gn:asciiname":"Buenas Noches",
    "gn:country_code":"ES",
    "gn:dem":20,
    "gn:feature_class":"P",
    "gn:feature_code":"PPLS",
    "gn:name":"Buenas Noches",
    "gn:population":0,
    "gn:timezone":"Europe/Madrid",
    "iso:country":"ES",
    "wof:name":"Buenas Noches",
    "wof:placetype":"locality"
},
  "geometry": {"coordinates":[-5.20439,36.39261],"type":"Point"}
}