{
  "type": "Feature",
  "properties": {
    "gn:admin1_code":"58",
    "gn:admin2_code":"C",
    "gn:admin3_code":"15002",
    "gn:asciiname":"Quintans",
    "gn:country_code":"ES",
    "gn:dem":80,
    "gn:feature_class":"P",
    "gn:feature_code":"PPL",
    "gn:name":"Quint\u00e1ns",
    "gn:population":0,
    "gn:timezone":"Europe/Madrid",
    "iso:country":"ES",
    "wof:name":"Quintans",
    "wof:placetype":"locality"
},
  "geometry": {"coordinates":[-8.65487,42.89524],"type":"Point"}
}