{
  "type": "Feature",
  "properties": {
    "gn:gn_country":"ES",
    "gn:gn_fcode":"PPLA3",
    "gn:gn_pop":130,
    "gn:population":130,
    "iso:country":"ES",
    "name:ara_x_preferred":[
        "\u0623\u0648\u0644\u0641\u064a\u0633"
    ],
    "name:arg_x_preferred":[
        "Olb\u00e9s"
    ],
    "name:baq_x_preferred":[
        "Olv\u00e9s"
    ],
    "name:cat_x_preferred":[
        "Olv\u00e9s"
    ],
    "name:chi_x_preferred":[
        "\u5965\u5c14\u97e6\u65af"
    ],
    "name:dut_x_preferred":[
        "Olv\u00e9s"
    ],
    "name:eng_x_preferred":[
        "Olv\u00e9s"
    ],
    "name:fre_x_preferred":[
        "Olv\u00e9s"
    ],
    "name:ger_x_preferred":[
        "Olv\u00e9s"
    ],
    "name:hun_x_preferred":[
        "Olv\u00e9s"
    ],
    "name:ita_x_preferred":[
        "Olv\u00e9s"
    ],
    "name:kaz_x_preferred":[
        "\u041e\u043b\u044c\u0432\u0435\u0441"
    ],
    "name:may_x_preferred":[
        "Olv\u00e9s"
    ],
    "name:nan_x_preferred":[
        "Olv\u00e9s"
    ],
    "name:oci_x_preferred":[
        "Olv\u00e9s"
    ],
    "name:pol_x_preferred":[
        "Olv\u00e9s"
    ],
    "name:por_x_preferred":[
        "Olv\u00e9s"
    ],
    "name:rus_x_preferred":[
        "\u041e\u043b\u044c\u0432\u0435\u0441"
    ],
    "name:spa_x_preferred":[
        "Olv\u00e9s"
    ],
    "name:swe_x_preferred":[
        "Olv\u00e9s"
    ],
    "name:ukr_x_preferred":[
        "\u041e\u043b\u044c\u0432\u0435\u0441"
    ],
    "name:uzb_x_preferred":[
        "Olv\u00e9s"
    ],
    "name:vie_x_preferred":[
        "Olv\u00e9s"
    ],
    "name:war_x_preferred":[
        "Olv\u00e9s"
    ],
    "qs_pg:aaroncc":"ES",
    "qs_pg:gn_country":"ES",
    "qs_pg:gn_fcode":"PPLA3",
    "qs_pg:gn_pop":130,
    "qs_pg:name":"Olv\u00e9s",
    "qs_pg:name_adm0":"Espa\u00f1a",
    "qs_pg:name_adm1":"Arag\u00f3n",
    "qs_pg:photos_9r":0,
    "qs_pg:photos_sr":0,
    "qs_pg:pop_sr":1,
    "qs_pg:qs_pg_placetype":"locality",
    "qs_pg:qs_pg_placetype_gp":"Town",
    "qs_pg:woe_adm0":23424950,
    "woe:adm0_id":23424950,
    "woe:name_adm0":"Espa\u00f1a",
    "woe:name_adm1":"Arag\u00f3n",
    "woe:placetype":"Town",
    "wof:name":"Olv\u00e9s",
    "wof:placetype":"locality",
    "wof:population":130
},
  "geometry": {"coordinates":[-1.64647,41.23965],"type":"Point"}
}