{
  "type": "Feature",
  "properties": {
    "gn:admin1_code":"58",
    "gn:admin2_code":"LU",
    "gn:admin3_code":"27018",
    "gn:asciiname":"Villadrid",
    "gn:country_code":"ES",
    "gn:dem":678,
    "gn:feature_class":"P",
    "gn:feature_code":"PPL",
    "gn:name":"Villadrid",
    "gn:population":0,
    "gn:timezone":"Europe/Madrid",
    "iso:country":"ES",
    "wof:name":"Villadrid",
    "wof:placetype":"locality"
},
  "geometry": {"coordinates":[-7.09897,43.05334000000001],"type":"Point"}
}