{
  "type": "Feature",
  "properties": {
    "gn:admin1_code":"53",
    "gn:admin2_code":"GC",
    "gn:admin3_code":"35010",
    "gn:asciiname":"Tabayesco",
    "gn:country_code":"ES",
    "gn:dem":28,
    "gn:feature_class":"P",
    "gn:feature_code":"PPL",
    "gn:name":"Tabayesco",
    "gn:population":0,
    "gn:timezone":"Atlantic/Canary",
    "iso:country":"ES",
    "name:fra_x_preferred":[
        "Tabayesco"
    ],
    "wof:name":"Tabayesco",
    "wof:placetype":"locality"
},
  "geometry": {"coordinates":[-13.46667,29.11667000000001],"type":"Point"}
}