{
  "type": "Feature",
  "properties": {
    "iso:country":"ES",
    "name:bar_x_preferred":[
        "Costa Daurada"
    ],
    "name:bel_x_preferred":[
        "\u041a\u043e\u0441\u0442\u0430-\u0414\u0430\u0440\u0430\u0434\u0430"
    ],
    "name:cat_x_preferred":[
        "Costa Daurada"
    ],
    "name:ceb_x_preferred":[
        "Costa Dorada"
    ],
    "name:deu_x_preferred":[
        "Costa Daurada"
    ],
    "name:eus_x_preferred":[
        "Costa Daurada"
    ],
    "name:fra_x_preferred":[
        "Costa Daurada"
    ],
    "name:glg_x_preferred":[
        "Costa Daurada"
    ],
    "name:heb_x_preferred":[
        "\u05e7\u05d5\u05e1\u05d8\u05d4 \u05d3\u05d0\u05d5\u05e8\u05d3\u05d4"
    ],
    "name:hrv_x_preferred":[
        "Costa Daurada"
    ],
    "name:ita_x_preferred":[
        "Costa Daurada"
    ],
    "name:kor_x_preferred":[
        "\ub3c4\ub77c\ub2e4 \ud574\uc548"
    ],
    "name:lit_x_preferred":[
        "Kosta Dorada"
    ],
    "name:ltz_x_preferred":[
        "Costa Dorada"
    ],
    "name:nld_x_preferred":[
        "Costa Daurada"
    ],
    "name:nno_x_preferred":[
        "Costa Daurada"
    ],
    "name:pol_x_preferred":[
        "Costa Dorada"
    ],
    "name:ron_x_preferred":[
        "Costa Daurada"
    ],
    "name:rus_x_preferred":[
        "\u041a\u043e\u0441\u0442\u0430-\u0414\u043e\u0440\u0430\u0434\u0430"
    ],
    "name:spa_x_preferred":[
        "Costa Dorada"
    ],
    "name:srp_x_preferred":[
        "\u041a\u043e\u0441\u0442\u0430 \u0414\u043e\u0440\u0430\u0434\u0430"
    ],
    "name:swe_x_preferred":[
        "Costa Daurada"
    ],
    "name:ukr_x_preferred":[
        "\u041a\u043e\u0441\u0442\u0430-\u0414\u043e\u0440\u0430\u0434\u0430"
    ],
    "name:zho_x_preferred":[
        "\u9ec4\u91d1\u6d77\u5cb8"
    ],
    "qs_pg:aaroncc":"ES",
    "qs_pg:name":"Costa Daurada",
    "qs_pg:name_adm0":"Espa\u00f1a",
    "qs_pg:name_adm1":"Catalunya",
    "qs_pg:photos":125,
    "qs_pg:photos_1k":25,
    "qs_pg:photos_9k":1,
    "qs_pg:photos_9r":3,
    "qs_pg:photos_all":125,
    "qs_pg:photos_sr":3,
    "qs_pg:pop_sr":0,
    "qs_pg:qs_pg_placetype":"locality",
    "qs_pg:qs_pg_placetype_gp":"Town",
    "qs_pg:woe_adm0":23424950,
    "woe:adm0_id":23424950,
    "woe:name_adm0":"Espa\u00f1a",
    "woe:name_adm1":"Catalunya",
    "woe:placetype":"Town",
    "wof:name":"Costa Daurada",
    "wof:placetype":"locality"
},
  "geometry": {"coordinates":[1.48736,41.174123],"type":"Point"}
}