{
  "type": "Feature",
  "properties": {
    "gn:admin1_code":"39",
    "gn:admin2_code":"S",
    "gn:admin3_code":"39077",
    "gn:asciiname":"Lantueno",
    "gn:country_code":"ES",
    "gn:dem":661,
    "gn:feature_class":"P",
    "gn:feature_code":"PPL",
    "gn:name":"Lantueno",
    "gn:population":0,
    "gn:timezone":"Europe/Madrid",
    "iso:country":"ES",
    "wof:name":"Lantueno",
    "wof:placetype":"locality"
},
  "geometry": {"coordinates":[-4.08233,43.04969000000001],"type":"Point"}
}