{
  "type": "Feature",
  "properties": {
    "gn:admin1_code":"55",
    "gn:admin2_code":"BU",
    "gn:admin3_code":"09902",
    "gn:asciiname":"Los Tremellos",
    "gn:country_code":"ES",
    "gn:dem":950,
    "gn:feature_class":"P",
    "gn:feature_code":"PPL",
    "gn:name":"Los Tremellos",
    "gn:population":0,
    "gn:timezone":"Europe/Madrid",
    "iso:country":"ES",
    "wof:name":"Los Tremellos",
    "wof:placetype":"locality"
},
  "geometry": {"coordinates":[-3.83262,42.51745],"type":"Point"}
}