{
  "type": "Feature",
  "properties": {
    "gn:gn_country":"ES",
    "gn:gn_fcode":"PPLA3",
    "gn:gn_pop":537,
    "gn:population":537,
    "iso:country":"ES",
    "name:arg_x_preferred":[
        "Pozuelo del P\u00e1ramo"
    ],
    "name:cat_x_preferred":[
        "Pozuelo del P\u00e1ramo"
    ],
    "name:ceb_x_preferred":[
        "Pozuelo del P\u00e1ramo"
    ],
    "name:eng_x_preferred":[
        "Pozuelo del P\u00e1ramo"
    ],
    "name:eus_x_preferred":[
        "Pozuelo del P\u00e1ramo"
    ],
    "name:fra_x_preferred":[
        "Pozuelo del P\u00e1ramo"
    ],
    "name:glg_x_preferred":[
        "Pozuelo del P\u00e1ramo"
    ],
    "name:haw_x_preferred":[
        "Pozuelo del P\u00e1ramo"
    ],
    "name:hun_x_preferred":[
        "Pozuelo del P\u00e1ramo"
    ],
    "name:ido_x_preferred":[
        "Pozuelo del P\u00e1ramo"
    ],
    "name:ina_x_preferred":[
        "Pozuelo del P\u00e1ramo"
    ],
    "name:ita_x_preferred":[
        "Pozuelo del P\u00e1ramo"
    ],
    "name:jpn_x_preferred":[
        "\u30dd\u30b9\u30a8\u30fc\u30ed\u30fb\u30c7\u30eb\u30fb\u30d1\u30e9\u30e2"
    ],
    "name:msa_x_preferred":[
        "Pozuelo del P\u00e1ramo"
    ],
    "name:nan_x_preferred":[
        "Pozuelo del P\u00e1ramo"
    ],
    "name:nld_x_preferred":[
        "Pozuelo del P\u00e1ramo"
    ],
    "name:oci_x_preferred":[
        "Pozuelo del P\u00e1ramo"
    ],
    "name:pol_x_preferred":[
        "Pozuelo del P\u00e1ramo"
    ],
    "name:por_x_preferred":[
        "Pozuelo del P\u00e1ramo"
    ],
    "name:rus_x_preferred":[
        "\u041f\u043e\u0441\u0443\u044d\u043b\u043e-\u0434\u0435\u043b\u044c-\u041f\u0430\u0440\u0430\u043c\u043e"
    ],
    "name:spa_x_preferred":[
        "Pozuelo del P\u00e1ramo"
    ],
    "name:swe_x_preferred":[
        "Pozuelo del P\u00e1ramo"
    ],
    "name:tpi_x_preferred":[
        "Pozuelo del P\u00e1ramo"
    ],
    "name:ukr_x_preferred":[
        "\u041f\u043e\u0441\u0443\u0435\u043b\u043e-\u0434\u0435\u043b\u044c-\u041f\u0430\u0440\u0430\u043c\u043e"
    ],
    "name:vie_x_preferred":[
        "Pozuelo del P\u00e1ramo"
    ],
    "name:war_x_preferred":[
        "Pozuelo del P\u00e1ramo"
    ],
    "name:zho_x_preferred":[
        "\u6ce2\u82cf\u57c3\u6d1b\u5fb7\u5c14\u5e15\u62c9\u83ab"
    ],
    "qs_pg:aaroncc":"ES",
    "qs_pg:gn_country":"ES",
    "qs_pg:gn_fcode":"PPLA3",
    "qs_pg:gn_pop":537,
    "qs_pg:name":"Pozuelo del P\u00e1ramo",
    "qs_pg:name_adm0":"Espa\u00f1a",
    "qs_pg:name_adm1":"Castilla y Le\u00f3n",
    "qs_pg:photos_9k":1,
    "qs_pg:photos_9r":1,
    "qs_pg:photos_all":2,
    "qs_pg:photos_sr":0,
    "qs_pg:pop_sr":2,
    "qs_pg:qs_pg_placetype":"locality",
    "qs_pg:qs_pg_placetype_gp":"Town",
    "qs_pg:woe_adm0":23424950,
    "woe:adm0_id":23424950,
    "woe:name_adm0":"Espa\u00f1a",
    "woe:name_adm1":"Castilla y Le\u00f3n",
    "woe:placetype":"Town",
    "wof:name":"Pozuelo del P\u00e1ramo",
    "wof:placetype":"locality",
    "wof:population":537
},
  "geometry": {"coordinates":[-5.76813,42.171],"type":"Point"}
}