{
  "type": "Feature",
  "properties": {
    "gn:country":"ES",
    "gn:fcode":"PPLA3",
    "gn:population":43,
    "iso:country":"ES",
    "name:arg_x_preferred":[
        "Gat\u00f3n de Campos"
    ],
    "name:cat_x_preferred":[
        "Gat\u00f3n de Campos"
    ],
    "name:deu_x_preferred":[
        "Gat\u00f3n de Campos"
    ],
    "name:eng_x_preferred":[
        "Gat\u00f3n de Campos"
    ],
    "name:eus_x_preferred":[
        "Gat\u00f3n de Campos"
    ],
    "name:fas_x_preferred":[
        "\u06af\u0627\u062a\u0646 \u062f \u06a9\u0627\u0645\u067e\u0633"
    ],
    "name:fra_x_preferred":[
        "Gat\u00f3n de Campos"
    ],
    "name:hun_x_preferred":[
        "Gat\u00f3n de Campos"
    ],
    "name:hye_x_preferred":[
        "\u0533\u0561\u057f\u0578\u0576 \u0564\u0565 \u053f\u0561\u0574\u057a\u0578\u057d"
    ],
    "name:ina_x_preferred":[
        "Gat\u00f3n de Campos"
    ],
    "name:ita_x_preferred":[
        "Gat\u00f3n de Campos"
    ],
    "name:msa_x_preferred":[
        "Gat\u00f3n de Campos"
    ],
    "name:nan_x_preferred":[
        "Gat\u00f3n de Campos"
    ],
    "name:nld_x_preferred":[
        "Gat\u00f3n de Campos"
    ],
    "name:oci_x_preferred":[
        "Gat\u00f3n de Campos"
    ],
    "name:pol_x_preferred":[
        "Gat\u00f3n de Campos"
    ],
    "name:por_x_preferred":[
        "Gat\u00f3n de Campos"
    ],
    "name:rus_x_preferred":[
        "\u0413\u0430\u0442\u043e\u043d-\u0434\u0435-\u041a\u0430\u043c\u043f\u043e\u0441"
    ],
    "name:spa_x_preferred":[
        "Gat\u00f3n de Campos"
    ],
    "name:swe_x_preferred":[
        "Gat\u00f3n de Campos"
    ],
    "name:ukr_x_preferred":[
        "\u0413\u0430\u0442\u043e\u043d-\u0434\u0435-\u041a\u0430\u043c\u043f\u043e\u0441"
    ],
    "name:und_x_variant":[
        "Gat\u00f3n"
    ],
    "name:vie_x_preferred":[
        "Gat\u00f3n de Campos"
    ],
    "name:war_x_preferred":[
        "Gat\u00f3n de Campos"
    ],
    "name:zho_x_preferred":[
        "\u52a0\u901a\u5fb7\u574e\u6ce2\u65af"
    ],
    "qs_pg:aaroncc":"ES",
    "qs_pg:gn_country":"ES",
    "qs_pg:gn_fcode":"PPLA3",
    "qs_pg:gn_pop":43,
    "qs_pg:name":"Gat\u00f3n de Campos",
    "qs_pg:name_adm0":"Espa\u00f1a",
    "qs_pg:name_adm1":"Castilla y Le\u00f3n",
    "qs_pg:photos_9k":1,
    "qs_pg:photos_9r":1,
    "qs_pg:photos_all":1,
    "qs_pg:photos_sr":0,
    "qs_pg:pop_sr":1,
    "qs_pg:qs_pg_placetype":"locality",
    "qs_pg:qs_pg_placetype_gp":"Town",
    "qs_pg:woe_adm0":23424950,
    "woe:adm0_id":23424950,
    "woe:name_adm0":"Espa\u00f1a",
    "woe:name_adm1":"Castilla y Le\u00f3n",
    "woe:placetype":"Town",
    "wof:name":"Gat\u00f3n de Campos",
    "wof:placetype":"locality",
    "wof:population":43
},
  "geometry": {"coordinates":[-4.98078,42.04984],"type":"Point"}
}