{
  "type": "Feature",
  "properties": {
    "gn:admin1_code":"55",
    "gn:admin2_code":"BU",
    "gn:admin3_code":"09906",
    "gn:asciiname":"Mata",
    "gn:country_code":"ES",
    "gn:dem":924,
    "gn:feature_class":"P",
    "gn:feature_code":"PPL",
    "gn:name":"Mata",
    "gn:population":0,
    "gn:timezone":"Europe/Madrid",
    "iso:country":"ES",
    "wof:name":"Mata",
    "wof:placetype":"locality"
},
  "geometry": {"coordinates":[-3.69381,42.53702],"type":"Point"}
}