{
  "type": "Feature",
  "properties": {
    "gn:admin1_code":"57",
    "gn:admin2_code":"BA",
    "gn:admin3_code":"06067",
    "gn:asciiname":"Las Nieves",
    "gn:cc2":"ES",
    "gn:country_code":"ES",
    "gn:dem":523,
    "gn:feature_class":"P",
    "gn:feature_code":"PPL",
    "gn:name":"Las Nieves",
    "gn:population":0,
    "gn:timezone":"Europe/Madrid",
    "iso:country":"ES",
    "name:ceb_x_preferred":[
        "Las Nieves"
    ],
    "name:deu_x_preferred":[
        "Las Nieves"
    ],
    "name:ita_x_preferred":[
        "Las Nieves"
    ],
    "name:nld_x_preferred":[
        "Las Nieves"
    ],
    "name:spa_x_preferred":[
        "Las Nieves"
    ],
    "name:swe_x_preferred":[
        "Las Nieves"
    ],
    "name:und_x_variant":[
        "Caser\u00edo Las Nieves"
    ],
    "wof:name":"Las Nieves",
    "wof:placetype":"locality"
},
  "geometry": {"coordinates":[-6.66667,38.11667],"type":"Point"}
}