{
  "type": "Feature",
  "properties": {
    "gn:admin1_code":"55",
    "gn:admin2_code":"LE",
    "gn:admin3_code":"24132",
    "gn:asciiname":"Inicio",
    "gn:country_code":"ES",
    "gn:dem":1014,
    "gn:feature_class":"P",
    "gn:feature_code":"PPL",
    "gn:name":"Inicio",
    "gn:population":0,
    "gn:timezone":"Europe/Madrid",
    "iso:country":"ES",
    "wof:name":"Inicio",
    "wof:placetype":"locality"
},
  "geometry": {"coordinates":[-5.96282,42.75587],"type":"Point"}
}