{
  "type": "Feature",
  "properties": {
    "gn:admin1_code":"55",
    "gn:admin2_code":"LE",
    "gn:admin3_code":"24009",
    "gn:asciiname":"Quintela",
    "gn:country_code":"ES",
    "gn:dem":662,
    "gn:feature_class":"P",
    "gn:feature_code":"PPL",
    "gn:name":"Quintela",
    "gn:population":0,
    "gn:timezone":"Europe/Madrid",
    "iso:country":"ES",
    "name:ceb_x_preferred":[
        "Quintela"
    ],
    "name:deu_x_preferred":[
        "Quintela"
    ],
    "name:glg_x_preferred":[
        "Quintela"
    ],
    "name:kaz_x_preferred":[
        "\u041a\u0438\u043d\u0442\u0435\u043b\u0430"
    ],
    "name:nld_x_preferred":[
        "Quintela"
    ],
    "name:por_x_preferred":[
        "Quintela"
    ],
    "name:rus_x_preferred":[
        "\u041a\u0438\u043d\u0442\u0435\u043b\u0430"
    ],
    "name:spa_x_preferred":[
        "Quintela"
    ],
    "name:tur_x_preferred":[
        "Quintela"
    ],
    "wof:name":"Quintela",
    "wof:placetype":"locality"
},
  "geometry": {"coordinates":[-6.92885,42.68816],"type":"Point"}
}