{
  "type": "Feature",
  "properties": {
    "gn:admin1_code":"58",
    "gn:admin2_code":"C",
    "gn:admin3_code":"15019",
    "gn:asciiname":"Rus",
    "gn:cc2":"ES",
    "gn:country_code":"ES",
    "gn:dem":263,
    "gn:feature_class":"P",
    "gn:feature_code":"PPL",
    "gn:name":"Rus",
    "gn:population":0,
    "gn:timezone":"Europe/Madrid",
    "iso:country":"ES",
    "name:und_x_variant":[
        "Santa Mar\u00eda",
        "Rus"
    ],
    "wof:name":"Rus",
    "wof:placetype":"locality"
},
  "geometry": {"coordinates":[-8.66667,43.15],"type":"Point"}
}