{
  "type": "Feature",
  "properties": {
    "gn:admin1_code":"58",
    "gn:admin2_code":"C",
    "gn:admin3_code":"15019",
    "gn:asciiname":"Rus",
    "gn:cc2":"ES",
    "gn:country_code":"ES",
    "gn:dem":263,
    "gn:feature_class":"P",
    "gn:feature_code":"PPL",
    "gn:name":"Rus",
    "gn:population":0,
    "gn:timezone":"Europe/Madrid",
    "iso:country":"ES",
    "name:cat_x_preferred":[
        "Rus"
    ],
    "name:ceb_x_preferred":[
        "Rus"
    ],
    "name:ces_x_preferred":[
        "Rus"
    ],
    "name:dan_x_preferred":[
        "Rus"
    ],
    "name:deu_x_preferred":[
        "Rus"
    ],
    "name:eus_x_preferred":[
        "Rus"
    ],
    "name:fin_x_preferred":[
        "Rus"
    ],
    "name:fra_x_preferred":[
        "Rus"
    ],
    "name:glg_x_preferred":[
        "Rus"
    ],
    "name:hun_x_preferred":[
        "Rusz"
    ],
    "name:ind_x_preferred":[
        "Rus"
    ],
    "name:nld_x_preferred":[
        "Rus"
    ],
    "name:pol_x_preferred":[
        "Ru\u015b"
    ],
    "name:por_x_preferred":[
        "Rus"
    ],
    "name:ron_x_preferred":[
        "Rus"
    ],
    "name:rus_x_preferred":[
        "\u0420\u0443\u0441"
    ],
    "name:slk_x_preferred":[
        "Rus"
    ],
    "name:spa_x_preferred":[
        "Rus"
    ],
    "name:srp_x_preferred":[
        "\u0420\u0443\u0441"
    ],
    "name:swe_x_preferred":[
        "Rus"
    ],
    "name:tur_x_preferred":[
        "Rus"
    ],
    "name:ukr_x_preferred":[
        "\u0420\u0443\u0441"
    ],
    "name:und_x_variant":[
        "Santa Mar\u00eda"
    ],
    "name:vie_x_preferred":[
        "Rus"
    ],
    "name:vol_x_preferred":[
        "Rus"
    ],
    "wof:name":"Rus",
    "wof:placetype":"locality"
},
  "geometry": {"coordinates":[-8.66667,43.15],"type":"Point"}
}