{
  "type": "Feature",
  "properties": {
    "gn:admin1_code":"07",
    "gn:admin2_code":"PM",
    "gn:admin3_code":"07059",
    "gn:asciiname":"Colonia de Sant Jordi",
    "gn:country_code":"ES",
    "gn:dem":4,
    "gn:feature_class":"P",
    "gn:feature_code":"PPL",
    "gn:name":"Col\u00f2nia de Sant Jordi",
    "gn:population":2900,
    "gn:timezone":"Europe/Madrid",
    "iso:country":"ES",
    "name:cat_x_preferred":[
        "Col\u00f2nia de Sant Jordi"
    ],
    "name:deu_x_preferred":[
        "Col\u00f2nia de Sant Jordi"
    ],
    "name:eng_x_preferred":[
        "Col\u00f2nia de Sant Jordi"
    ],
    "name:spa_x_preferred":[
        "Col\u00f2nia de Sant Jordi"
    ],
    "name:und_x_variant":[
        "Colonia Sant Jordi"
    ],
    "wof:name":"Colonia de Sant Jordi",
    "wof:placetype":"locality",
    "wof:population":2900
},
  "geometry": {"coordinates":[2.99197,39.3181],"type":"Point"}
}