{
  "type": "Feature",
  "properties": {
    "gn:admin1_code":"34",
    "gn:admin2_code":"O",
    "gn:admin3_code":"33026",
    "gn:asciiname":"Raneces",
    "gn:country_code":"ES",
    "gn:dem":291,
    "gn:feature_class":"P",
    "gn:feature_code":"PPL",
    "gn:name":"Ra\u00f1eces",
    "gn:population":0,
    "gn:timezone":"Europe/Madrid",
    "iso:country":"ES",
    "name:ast_x_preferred":[
        "Ra\u00f1eces"
    ],
    "name:spa_x_preferred":[
        "Ra\u00f1eces"
    ],
    "name:und_x_variant":[
        "Ra\u00f1eces"
    ],
    "wof:name":"Raneces",
    "wof:placetype":"locality"
},
  "geometry": {"coordinates":[-6.06895,43.34788],"type":"Point"}
}