{
  "type": "Feature",
  "properties": {
    "gn:admin1_code":"58",
    "gn:admin2_code":"C",
    "gn:admin3_code":"15013",
    "gn:asciiname":"Bastavales",
    "gn:cc2":"ES",
    "gn:country_code":"ES",
    "gn:dem":63,
    "gn:feature_class":"P",
    "gn:feature_code":"PPL",
    "gn:name":"Bastavales",
    "gn:population":0,
    "gn:timezone":"Europe/Madrid",
    "iso:country":"ES",
    "name:und_x_variant":[
        "San Juli\u00e1n",
        "Bastavales"
    ],
    "wof:name":"Bastavales",
    "wof:placetype":"locality"
},
  "geometry": {"coordinates":[-8.66667,42.81667],"type":"Point"}
}