{
  "type": "Feature",
  "properties": {
    "gn:gn_country":"ES",
    "gn:gn_fcode":"PPLA3",
    "gn:gn_pop":210,
    "gn:population":210,
    "iso:country":"ES",
    "name:arg_x_preferred":[
        "Olmos de Esgueva"
    ],
    "name:cat_x_preferred":[
        "Olmos de Esgueva"
    ],
    "name:eng_x_preferred":[
        "Olmos de Esgueva"
    ],
    "name:eus_x_preferred":[
        "Olmos de Esgueva"
    ],
    "name:fas_x_preferred":[
        "\u0627\u0644\u0645\u0633 \u062f \u0627\u0633\u06af\u0628\u0627"
    ],
    "name:fra_x_preferred":[
        "Olmos de Esgueva"
    ],
    "name:hun_x_preferred":[
        "Olmos de Esgueva"
    ],
    "name:hye_x_preferred":[
        "\u0555\u056c\u0574\u0578\u057d \u0564\u0565 \u0537\u057d\u0563\u0587\u0561"
    ],
    "name:ina_x_preferred":[
        "Olmos de Esgueva"
    ],
    "name:ita_x_preferred":[
        "Olmos de Esgueva"
    ],
    "name:msa_x_preferred":[
        "Olmos de Esgueva"
    ],
    "name:nan_x_preferred":[
        "Olmos de Esgueva"
    ],
    "name:nld_x_preferred":[
        "Olmos de Esgueva"
    ],
    "name:oci_x_preferred":[
        "Olmos de Esgueva"
    ],
    "name:pol_x_preferred":[
        "Olmos de Esgueva"
    ],
    "name:por_x_preferred":[
        "Olmos de Esgueva"
    ],
    "name:rus_x_preferred":[
        "\u041e\u043b\u044c\u043c\u043e\u0441-\u0434\u0435-\u042d\u0441\u0433\u0435\u0432\u0430"
    ],
    "name:spa_x_preferred":[
        "Olmos de Esgueva"
    ],
    "name:swe_x_preferred":[
        "Olmos de Esgueva"
    ],
    "name:ukr_x_preferred":[
        "\u041e\u043b\u044c\u043c\u043e\u0441-\u0434\u0435-\u0415\u0441\u0433\u0435\u0432\u0430"
    ],
    "name:vie_x_preferred":[
        "Olmos de Esgueva"
    ],
    "name:war_x_preferred":[
        "Olmos de Esgueva"
    ],
    "name:zho_x_preferred":[
        "\u5965\u5c14\u83ab\u65af\u5fb7\u57c3\u65af\u683c\u74e6"
    ],
    "qs_pg:aaroncc":"ES",
    "qs_pg:gn_country":"ES",
    "qs_pg:gn_fcode":"PPLA3",
    "qs_pg:gn_pop":210,
    "qs_pg:name":"Olmos de Esgueva",
    "qs_pg:name_adm0":"Espa\u00f1a",
    "qs_pg:name_adm1":"Castilla y Le\u00f3n",
    "qs_pg:photos_9k":1,
    "qs_pg:photos_9r":1,
    "qs_pg:photos_all":2,
    "qs_pg:photos_sr":0,
    "qs_pg:pop_sr":2,
    "qs_pg:qs_pg_placetype":"locality",
    "qs_pg:qs_pg_placetype_gp":"Town",
    "qs_pg:woe_adm0":23424950,
    "woe:adm0_id":23424950,
    "woe:name_adm0":"Espa\u00f1a",
    "woe:name_adm1":"Castilla y Le\u00f3n",
    "woe:placetype":"Town",
    "wof:name":"Olmos de Esgueva",
    "wof:placetype":"locality",
    "wof:population":210
},
  "geometry": {"coordinates":[-4.52254,41.68815],"type":"Point"}
}