{
  "type": "Feature",
  "properties": {
    "gn:admin1_code":"58",
    "gn:admin2_code":"C",
    "gn:admin3_code":"15045",
    "gn:asciiname":"San Cristobal",
    "gn:country_code":"ES",
    "gn:dem":361,
    "gn:feature_class":"P",
    "gn:feature_code":"PPL",
    "gn:name":"San Crist\u00f3bal",
    "gn:population":0,
    "gn:timezone":"Europe/Madrid",
    "iso:country":"ES",
    "name:fas_x_preferred":[
        "\u0633\u0627\u0646 \u06a9\u0631\u06cc\u0633\u062a\u0648\u0628\u0627\u0644"
    ],
    "name:heb_x_preferred":[
        "\u05d0\u05d9\u05d9 \u05e1\u05df \u05db\u05e8\u05d9\u05e1\u05d8\u05d5\u05d1\u05dc"
    ],
    "name:hun_x_preferred":[
        "San Cristobal"
    ],
    "wof:name":"San Cristobal",
    "wof:placetype":"locality"
},
  "geometry": {"coordinates":[-8.9869,42.85952],"type":"Point"}
}