{
  "type": "Feature",
  "properties": {
    "gn:admin1_code":"58",
    "gn:admin2_code":"LU",
    "gn:admin3_code":"27046",
    "gn:asciiname":"Susa",
    "gn:country_code":"ES",
    "gn:dem":584,
    "gn:feature_class":"P",
    "gn:feature_code":"PPL",
    "gn:name":"Sus\u00e1",
    "gn:population":0,
    "gn:timezone":"Europe/Madrid",
    "iso:country":"ES",
    "wof:name":"Susa",
    "wof:placetype":"locality"
},
  "geometry": {"coordinates":[-7.28294,43.14305],"type":"Point"}
}