{
  "type": "Feature",
  "properties": {
    "gn:country":"ES",
    "gn:fcode":"PPLA3",
    "gn:population":213,
    "iso:country":"ES",
    "name:arg_x_preferred":[
        "Jambrina"
    ],
    "name:ast_x_preferred":[
        "Jambrina"
    ],
    "name:cat_x_preferred":[
        "Jambrina"
    ],
    "name:ceb_x_preferred":[
        "Jambrina"
    ],
    "name:eng_x_preferred":[
        "Jambrina"
    ],
    "name:eus_x_preferred":[
        "Jambrina"
    ],
    "name:fra_x_preferred":[
        "Jambrina"
    ],
    "name:haw_x_preferred":[
        "Jambrina"
    ],
    "name:hun_x_preferred":[
        "Jambrina"
    ],
    "name:ile_x_preferred":[
        "Jambrina"
    ],
    "name:ina_x_preferred":[
        "Jambrina"
    ],
    "name:ita_x_preferred":[
        "Jambrina"
    ],
    "name:ltz_x_preferred":[
        "Jambrina"
    ],
    "name:msa_x_preferred":[
        "Jambrina"
    ],
    "name:nan_x_preferred":[
        "Jambrina"
    ],
    "name:nld_x_preferred":[
        "Jambrina"
    ],
    "name:oci_x_preferred":[
        "Jambrina"
    ],
    "name:pol_x_preferred":[
        "Jambrina"
    ],
    "name:por_x_preferred":[
        "Jambrina"
    ],
    "name:rus_x_preferred":[
        "\u0425\u0430\u043c\u0431\u0440\u0438\u043d\u0430"
    ],
    "name:spa_x_preferred":[
        "Jambrina"
    ],
    "name:swe_x_preferred":[
        "Jambrina"
    ],
    "name:ukr_x_preferred":[
        "\u0425\u0430\u043c\u0431\u0440\u0456\u043d\u0430"
    ],
    "name:urd_x_preferred":[
        "\u062c\u0645\u0628\u0631\u06cc\u0646\u06c1"
    ],
    "name:uzb_x_preferred":[
        "Jambrina"
    ],
    "name:vie_x_preferred":[
        "Jambrina"
    ],
    "name:war_x_preferred":[
        "Jambrina"
    ],
    "name:zho_x_preferred":[
        "\u6c49\u592b\u91cc\u7eb3"
    ],
    "qs_pg:aaroncc":"ES",
    "qs_pg:gn_country":"ES",
    "qs_pg:gn_fcode":"PPLA3",
    "qs_pg:gn_pop":213,
    "qs_pg:name":"Jambrina",
    "qs_pg:name_adm0":"Espa\u00f1a",
    "qs_pg:name_adm1":"Castilla y Le\u00f3n",
    "qs_pg:photos_9r":0,
    "qs_pg:photos_sr":0,
    "qs_pg:pop_sr":2,
    "qs_pg:qs_pg_placetype":"locality",
    "qs_pg:qs_pg_placetype_gp":"Town",
    "qs_pg:woe_adm0":23424950,
    "woe:adm0_id":23424950,
    "woe:name_adm0":"Espa\u00f1a",
    "woe:name_adm1":"Castilla y Le\u00f3n",
    "woe:placetype":"Town",
    "wof:name":"Jambrina",
    "wof:placetype":"locality",
    "wof:population":213
},
  "geometry": {"coordinates":[-5.66411,41.39196],"type":"Point"}
}