{
  "type": "Feature",
  "properties": {
    "gn:admin1_code":"57",
    "gn:admin2_code":"CC",
    "gn:admin3_code":"10079",
    "gn:asciiname":"Garganta la Olla",
    "gn:country_code":"ES",
    "gn:dem":581,
    "gn:feature_class":"P",
    "gn:feature_code":"PPLA3",
    "gn:name":"Garganta la Olla",
    "gn:population":1154,
    "gn:timezone":"Europe/Madrid",
    "iso:country":"ES",
    "name:ara_x_preferred":[
        "\u062c\u0627\u0631\u062c\u0627\u0646\u062a\u0627 \u0644\u0627 \u0623\u0648\u0644\u0627"
    ],
    "name:arg_x_preferred":[
        "Garganta la Olla"
    ],
    "name:cat_x_preferred":[
        "Garganta la Olla"
    ],
    "name:ceb_x_preferred":[
        "Garganta la Olla"
    ],
    "name:epo_x_preferred":[
        "Garganta la Olla"
    ],
    "name:eus_x_preferred":[
        "Garganta la Olla"
    ],
    "name:fra_x_preferred":[
        "Garganta la Olla"
    ],
    "name:hun_x_preferred":[
        "Garganta la Olla"
    ],
    "name:ina_x_preferred":[
        "Garganta la Olla"
    ],
    "name:ita_x_preferred":[
        "Garganta la Olla"
    ],
    "name:msa_x_preferred":[
        "Garganta la Olla"
    ],
    "name:nld_x_preferred":[
        "Garganta la Olla"
    ],
    "name:oci_x_preferred":[
        "Garganta la Olla"
    ],
    "name:pol_x_preferred":[
        "Garganta la Olla"
    ],
    "name:por_x_preferred":[
        "Garganta la Olla"
    ],
    "name:ron_x_preferred":[
        "Garganta la Olla"
    ],
    "name:rus_x_preferred":[
        "\u0413\u0430\u0440\u0433\u0430\u043d\u0442\u0430-\u043b\u0430-\u041e\u043b\u044c\u044f"
    ],
    "name:spa_x_preferred":[
        "Garganta la Olla"
    ],
    "name:srd_x_preferred":[
        "Garganta la Olla"
    ],
    "name:swe_x_preferred":[
        "Garganta la Olla"
    ],
    "name:ukr_x_preferred":[
        "\u0413\u0430\u0440\u0433\u0430\u043d\u0442\u0430-\u043b\u0430-\u041e\u043b\u044c\u044f"
    ],
    "name:uzb_x_preferred":[
        "Garganta la Olla"
    ],
    "name:vie_x_preferred":[
        "Garganta la Olla"
    ],
    "name:war_x_preferred":[
        "Garganta la Olla"
    ],
    "name:zho_x_preferred":[
        "\u52a0\u5c14\u7518\u5854\u52b3\u5229\u4e9a"
    ],
    "wof:name":"Garganta la Olla",
    "wof:placetype":"locality",
    "wof:population":1154
},
  "geometry": {"coordinates":[-5.77665,40.11049000000001],"type":"Point"}
}