{
  "type": "Feature",
  "properties": {
    "gn:admin1_code":"53",
    "gn:admin2_code":"TF",
    "gn:admin3_code":"38040",
    "gn:asciiname":"El Molledo",
    "gn:country_code":"ES",
    "gn:dem":842,
    "gn:feature_class":"P",
    "gn:feature_code":"PPL",
    "gn:name":"El Molledo",
    "gn:population":0,
    "gn:timezone":"Atlantic/Canary",
    "iso:country":"ES",
    "wof:name":"El Molledo",
    "wof:placetype":"locality"
},
  "geometry": {"coordinates":[-16.81495,28.28604],"type":"Point"}
}