{
  "type": "Feature",
  "properties": {
    "gn:admin1_code":"34",
    "gn:admin2_code":"O",
    "gn:admin3_code":"33012",
    "gn:asciiname":"Tarano",
    "gn:cc2":"ES",
    "gn:country_code":"ES",
    "gn:dem":268,
    "gn:feature_class":"P",
    "gn:feature_code":"PPL",
    "gn:name":"T\u00e1rano",
    "gn:population":0,
    "gn:timezone":"Europe/Madrid",
    "iso:country":"ES",
    "name:und_x_variant":[
        "T\u00e1ramo"
    ],
    "wof:name":"Tarano",
    "wof:placetype":"locality"
},
  "geometry": {"coordinates":[-5.03981,43.3635],"type":"Point"}
}