{
  "type": "Feature",
  "properties": {
    "gn:admin1_code":"34",
    "gn:admin2_code":"O",
    "gn:admin3_code":"33012",
    "gn:asciiname":"Tarano",
    "gn:cc2":"ES",
    "gn:country_code":"ES",
    "gn:dem":268,
    "gn:feature_class":"P",
    "gn:feature_code":"PPL",
    "gn:name":"T\u00e1rano",
    "gn:population":0,
    "gn:timezone":"Europe/Madrid",
    "iso:country":"ES",
    "name:azb_x_preferred":[
        "\u062a\u0627\u0631\u0627\u0646\u0648"
    ],
    "name:bcl_x_preferred":[
        "Tarano"
    ],
    "name:bul_x_preferred":[
        "\u0422\u0430\u0440\u0430\u043d\u043e"
    ],
    "name:ceb_x_preferred":[
        "Tarano"
    ],
    "name:deu_x_preferred":[
        "Tarano"
    ],
    "name:epo_x_preferred":[
        "Tarano"
    ],
    "name:est_x_preferred":[
        "Tarano"
    ],
    "name:eus_x_preferred":[
        "Tarano"
    ],
    "name:fas_x_preferred":[
        "\u062a\u0627\u0631\u0627\u0646\u0648"
    ],
    "name:fra_x_preferred":[
        "Tarano"
    ],
    "name:hun_x_preferred":[
        "Tarano"
    ],
    "name:hye_x_preferred":[
        "\u054f\u0561\u0580\u0561\u0576\u0578"
    ],
    "name:ina_x_preferred":[
        "Tarano"
    ],
    "name:ita_x_preferred":[
        "Tarano"
    ],
    "name:jpn_x_preferred":[
        "\u30bf\u30e9\u30fc\u30ce"
    ],
    "name:kaz_x_preferred":[
        "\u0422\u0430\u0440\u0430\u043d\u043e"
    ],
    "name:kor_x_preferred":[
        "\ud0c0\ub77c\ub178"
    ],
    "name:lat_x_preferred":[
        "Taramne"
    ],
    "name:lmo_x_preferred":[
        "Tarano"
    ],
    "name:msa_x_preferred":[
        "Tarano"
    ],
    "name:nap_x_preferred":[
        "Tarano"
    ],
    "name:nld_x_preferred":[
        "Tarano"
    ],
    "name:pms_x_preferred":[
        "Tarano"
    ],
    "name:pol_x_preferred":[
        "Tarano"
    ],
    "name:por_x_preferred":[
        "Tarano"
    ],
    "name:ron_x_preferred":[
        "Tarano"
    ],
    "name:rus_x_preferred":[
        "\u0422\u0430\u0440\u0430\u043d\u043e"
    ],
    "name:scn_x_preferred":[
        "Taranu"
    ],
    "name:spa_x_preferred":[
        "Tarano"
    ],
    "name:srp_x_preferred":[
        "\u0422\u0430\u0440\u0430\u043d\u043e"
    ],
    "name:ukr_x_preferred":[
        "\u0422\u0430\u0440\u0430\u043d\u043e"
    ],
    "name:und_x_variant":[
        "T\u00e1ramo"
    ],
    "name:uzb_x_preferred":[
        "Tarano"
    ],
    "name:vie_x_preferred":[
        "Tarano"
    ],
    "name:vol_x_preferred":[
        "Tarano"
    ],
    "name:war_x_preferred":[
        "Tarano"
    ],
    "name:zho_x_preferred":[
        "\u5854\u62c9\u8bfa"
    ],
    "wof:name":"Tarano",
    "wof:placetype":"locality"
},
  "geometry": {"coordinates":[-5.03981,43.3635],"type":"Point"}
}