{
  "type": "Feature",
  "properties": {
    "gn:admin1_code":"51",
    "gn:admin2_code":"AL",
    "gn:admin3_code":"04066",
    "gn:asciiname":"Las Manicas",
    "gn:country_code":"ES",
    "gn:dem":867,
    "gn:feature_class":"P",
    "gn:feature_code":"PPL",
    "gn:name":"Las Ma\u00f1icas",
    "gn:population":0,
    "gn:timezone":"Europe/Madrid",
    "iso:country":"ES",
    "name:und_x_variant":[
        "Caser\u00edo Las Ma\u00f1icas",
        "Las Ma\u00f1icas"
    ],
    "wof:name":"Las Manicas",
    "wof:placetype":"locality"
},
  "geometry": {"coordinates":[-2.29442,36.97229],"type":"Point"}
}