{
  "type": "Feature",
  "properties": {
    "gn:gn_country":"ES",
    "gn:gn_fcode":"PPLA3",
    "gn:gn_pop":127,
    "gn:population":127,
    "iso:country":"ES",
    "name:ara_x_preferred":[
        "\u0643\u0627\u064a\u0648\u064a\u0644\u0627"
    ],
    "name:arg_x_preferred":[
        "Cayuela"
    ],
    "name:cat_x_preferred":[
        "Cayuela"
    ],
    "name:deu_x_preferred":[
        "Cayuela"
    ],
    "name:eng_x_preferred":[
        "Cayuela"
    ],
    "name:eus_x_preferred":[
        "Cayuela"
    ],
    "name:fas_x_preferred":[
        "\u06a9\u0627\u06cc\u0648\u0626\u0644\u0627"
    ],
    "name:fra_x_preferred":[
        "Cayuela"
    ],
    "name:glg_x_preferred":[
        "Cayuela"
    ],
    "name:haw_x_preferred":[
        "Cayuela"
    ],
    "name:hun_x_preferred":[
        "Cayuela"
    ],
    "name:ina_x_preferred":[
        "Cayuela"
    ],
    "name:ita_x_preferred":[
        "Cayuela"
    ],
    "name:lad_x_preferred":[
        "Cayuela"
    ],
    "name:msa_x_preferred":[
        "Cayuela"
    ],
    "name:nan_x_preferred":[
        "Cayuela"
    ],
    "name:nld_x_preferred":[
        "Cayuela"
    ],
    "name:oci_x_preferred":[
        "Cayuela"
    ],
    "name:pol_x_preferred":[
        "Cayuela"
    ],
    "name:por_x_preferred":[
        "Cayuela"
    ],
    "name:rup_x_preferred":[
        "Cayuela"
    ],
    "name:rus_x_preferred":[
        "\u041a\u0430\u044e\u044d\u043b\u0430"
    ],
    "name:spa_x_preferred":[
        "Cayuela"
    ],
    "name:swe_x_preferred":[
        "Cayuela"
    ],
    "name:ukr_x_preferred":[
        "\u041a\u0430\u044e\u0435\u043b\u0430"
    ],
    "name:vie_x_preferred":[
        "Cayuela"
    ],
    "name:war_x_preferred":[
        "Cayuela"
    ],
    "name:zho_x_preferred":[
        "\u51ef\u97e6\u62c9"
    ],
    "qs_pg:aaroncc":"ES",
    "qs_pg:gn_country":"ES",
    "qs_pg:gn_fcode":"PPLA3",
    "qs_pg:gn_pop":127,
    "qs_pg:name":"Cayuela",
    "qs_pg:name_adm0":"Espa\u00f1a",
    "qs_pg:name_adm1":"Castilla y Le\u00f3n",
    "qs_pg:photos_9k":1,
    "qs_pg:photos_9r":1,
    "qs_pg:photos_all":1,
    "qs_pg:photos_sr":0,
    "qs_pg:pop_sr":1,
    "qs_pg:qs_pg_placetype":"locality",
    "qs_pg:qs_pg_placetype_gp":"Town",
    "qs_pg:woe_adm0":23424950,
    "woe:adm0_id":23424950,
    "woe:name_adm0":"Espa\u00f1a",
    "woe:name_adm1":"Castilla y Le\u00f3n",
    "woe:placetype":"Town",
    "wof:name":"Cayuela",
    "wof:placetype":"locality",
    "wof:population":127
},
  "geometry": {"coordinates":[-3.81895,42.27223],"type":"Point"}
}