{
  "type": "Feature",
  "properties": {
    "gn:admin1_code":"34",
    "gn:admin2_code":"O",
    "gn:admin3_code":"33041",
    "gn:asciiname":"Frejulfe",
    "gn:country_code":"ES",
    "gn:dem":69,
    "gn:feature_class":"P",
    "gn:feature_code":"PPL",
    "gn:name":"Frejulfe",
    "gn:population":0,
    "gn:timezone":"Europe/Madrid",
    "iso:country":"ES",
    "wof:name":"Frejulfe",
    "wof:placetype":"locality"
},
  "geometry": {"coordinates":[-6.68216,43.55158],"type":"Point"}
}