{
  "type": "Feature",
  "properties": {
    "gn:admin1_code":"34",
    "gn:admin2_code":"O",
    "gn:admin3_code":"33028",
    "gn:asciiname":"Pineira",
    "gn:country_code":"ES",
    "gn:dem":472,
    "gn:feature_class":"P",
    "gn:feature_code":"PPL",
    "gn:name":"Pi\u00f1eira",
    "gn:population":0,
    "gn:timezone":"Europe/Madrid",
    "iso:country":"ES",
    "wof:name":"Pineira",
    "wof:placetype":"locality"
},
  "geometry": {"coordinates":[-6.86216,43.05072],"type":"Point"}
}