{
  "type": "Feature",
  "properties": {
    "gn:admin1_code":"55",
    "gn:admin2_code":"LE",
    "gn:admin3_code":"24123",
    "gn:asciiname":"Villameca",
    "gn:country_code":"ES",
    "gn:dem":974,
    "gn:feature_class":"P",
    "gn:feature_code":"PPL",
    "gn:name":"Villameca",
    "gn:population":0,
    "gn:timezone":"Europe/Madrid",
    "iso:country":"ES",
    "wof:name":"Villameca",
    "wof:placetype":"locality"
},
  "geometry": {"coordinates":[-6.07191,42.64003],"type":"Point"}
}