{
  "type": "Feature",
  "properties": {
    "gn:admin1_code":"55",
    "gn:admin2_code":"BU",
    "gn:admin3_code":"09238",
    "gn:asciiname":"La Aldea del Portillo de Busto",
    "gn:country_code":"ES",
    "gn:dem":793,
    "gn:feature_class":"P",
    "gn:feature_code":"PPL",
    "gn:name":"La Aldea del Portillo de Busto",
    "gn:population":0,
    "gn:timezone":"Europe/Madrid",
    "iso:country":"ES",
    "name:und_x_variant":[
        "La Aldea del Portillo del Busto",
        "La Aldea del Portillo de Busto"
    ],
    "wof:name":"La Aldea del Portillo de Busto",
    "wof:placetype":"locality"
},
  "geometry": {"coordinates":[-3.27632,42.70309],"type":"Point"}
}