{
  "type": "Feature",
  "properties": {
    "gn:admin1_code":"34",
    "gn:admin2_code":"O",
    "gn:admin3_code":"33052",
    "gn:asciiname":"Serandi",
    "gn:country_code":"ES",
    "gn:dem":434,
    "gn:feature_class":"P",
    "gn:feature_code":"PPL",
    "gn:name":"Serandi",
    "gn:population":0,
    "gn:timezone":"Europe/Madrid",
    "iso:country":"ES",
    "wof:name":"Serandi",
    "wof:placetype":"locality"
},
  "geometry": {"coordinates":[-5.99449,43.25699],"type":"Point"}
}