{
  "type": "Feature",
  "properties": {
    "gn:admin1_code":"59",
    "gn:admin2_code":"BI",
    "gn:admin3_code":"48023",
    "gn:asciiname":"Bildosola",
    "gn:country_code":"ES",
    "gn:dem":126,
    "gn:feature_class":"P",
    "gn:feature_code":"PPL",
    "gn:name":"Bildosola",
    "gn:population":0,
    "gn:timezone":"Europe/Madrid",
    "iso:country":"ES",
    "name:eus_x_preferred":[
        "Bildosola"
    ],
    "name:spa_x_preferred":[
        "Vild\u00f3sola"
    ],
    "wof:name":"Bildosola",
    "wof:placetype":"locality"
},
  "geometry": {"coordinates":[-2.78333,43.13333],"type":"Point"}
}