{
  "type": "Feature",
  "properties": {
    "gn:admin1_code":"55",
    "gn:admin2_code":"LE",
    "gn:admin3_code":"24005.0",
    "gn:asciiname":"Grajal de Ribera",
    "gn:country_code":"ES",
    "gn:dem":761,
    "gn:feature_class":"P",
    "gn:feature_code":"PPLL",
    "gn:name":"Grajal de Ribera",
    "gn:population":0,
    "gn:timezone":"Europe/Madrid",
    "iso:country":"ES",
    "wof:name":"Grajal de Ribera",
    "wof:placetype":"locality"
},
  "geometry": {"coordinates":[-5.67375,42.17587],"type":"Point"}
}