{
  "type": "Feature",
  "properties": {
    "gn:admin1_code":"58",
    "gn:admin2_code":"C",
    "gn:admin3_code":"15034",
    "gn:asciiname":"Bujan",
    "gn:country_code":"ES",
    "gn:dem":187,
    "gn:feature_class":"P",
    "gn:feature_code":"PPL",
    "gn:name":"Buj\u00e1n",
    "gn:population":0,
    "gn:timezone":"Europe/Madrid",
    "iso:country":"ES",
    "name:ces_x_preferred":[
        "Bujan"
    ],
    "name:hun_x_preferred":[
        "Bujan"
    ],
    "name:ita_x_preferred":[
        "Bujan"
    ],
    "name:msa_x_preferred":[
        "Bujan"
    ],
    "name:pol_x_preferred":[
        "Gmina Bujan"
    ],
    "name:por_x_preferred":[
        "Bujan"
    ],
    "name:rus_x_preferred":[
        "\u0411\u0443\u044f\u043d"
    ],
    "name:tur_x_preferred":[
        "Bujan"
    ],
    "name:vie_x_preferred":[
        "Bujan"
    ],
    "name:war_x_preferred":[
        "Bujan"
    ],
    "wof:name":"Bujan",
    "wof:placetype":"locality"
},
  "geometry": {"coordinates":[-9.11761,43.0104],"type":"Point"}
}