{
  "type": "Feature",
  "properties": {
    "gn:admin1_code":"34",
    "gn:admin2_code":"O",
    "gn:admin3_code":"33045",
    "gn:asciiname":"Cayarga",
    "gn:country_code":"ES",
    "gn:dem":115,
    "gn:feature_class":"P",
    "gn:feature_code":"PPL",
    "gn:name":"Cayarga",
    "gn:population":0,
    "gn:timezone":"Europe/Madrid",
    "iso:country":"ES",
    "name:und_x_variant":[
        "Santa Mar\u00eda Magdalena",
        "Cayarga"
    ],
    "wof:name":"Cayarga",
    "wof:placetype":"locality"
},
  "geometry": {"coordinates":[-5.14488,43.41348],"type":"Point"}
}