{
  "type": "Feature",
  "properties": {
    "gn:admin1_code":"58",
    "gn:admin2_code":"PO",
    "gn:admin3_code":"36028",
    "gn:asciiname":"Nogueira",
    "gn:cc2":"ES",
    "gn:country_code":"ES",
    "gn:dem":86,
    "gn:feature_class":"P",
    "gn:feature_code":"PPL",
    "gn:name":"Nogueira",
    "gn:population":0,
    "gn:timezone":"Europe/Madrid",
    "iso:country":"ES",
    "name:cat_x_preferred":[
        "Nogueira"
    ],
    "name:ceb_x_preferred":[
        "Nogueira"
    ],
    "name:deu_x_preferred":[
        "Nogueira"
    ],
    "name:fra_x_preferred":[
        "Nogueira"
    ],
    "name:glg_x_preferred":[
        "Nogueira"
    ],
    "name:jpn_x_preferred":[
        "\u30ce\u30b2\u30a4\u30e9"
    ],
    "name:nld_x_preferred":[
        "Nogueira"
    ],
    "name:por_x_preferred":[
        "Nogueira"
    ],
    "name:rus_x_preferred":[
        "\u041d\u043e\u0433\u0435\u0439\u0440\u0430"
    ],
    "name:spa_x_preferred":[
        "Nogueira"
    ],
    "name:swe_x_preferred":[
        "Nogueira"
    ],
    "name:tur_x_preferred":[
        "Nogueira"
    ],
    "name:ukr_x_preferred":[
        "\u041d\u043e\u0433\u0435\u0439\u0440\u0430"
    ],
    "name:und_x_variant":[
        "Santo Tom\u00e9"
    ],
    "wof:name":"Nogueira",
    "wof:placetype":"locality"
},
  "geometry": {"coordinates":[-8.6998,42.51058],"type":"Point"}
}