{
  "type": "Feature",
  "properties": {
    "gn:admin1_code":"52",
    "gn:admin2_code":"TE",
    "gn:admin3_code":"44009",
    "gn:asciiname":"La Vega",
    "gn:cc2":"ES",
    "gn:country_code":"ES",
    "gn:dem":1167,
    "gn:feature_class":"P",
    "gn:feature_code":"PPL",
    "gn:name":"La Vega",
    "gn:population":0,
    "gn:timezone":"Europe/Madrid",
    "iso:country":"ES",
    "name:ast_x_preferred":[
        "La Vega"
    ],
    "name:bre_x_preferred":[
        "La Vega"
    ],
    "name:ceb_x_preferred":[
        "La Vega"
    ],
    "name:fas_x_preferred":[
        "\u0644\u0627 \u0648\u06af\u0627"
    ],
    "name:fra_x_preferred":[
        "La Vega"
    ],
    "name:ita_x_preferred":[
        "La Vega"
    ],
    "name:nld_x_preferred":[
        "La Vega"
    ],
    "name:pol_x_preferred":[
        "La Vega"
    ],
    "name:sco_x_preferred":[
        "La Vega"
    ],
    "name:spa_x_preferred":[
        "La Vega"
    ],
    "name:srp_x_preferred":[
        "\u041b\u0430 \u0412\u0435\u0433\u0430"
    ],
    "name:swe_x_preferred":[
        "La Vega"
    ],
    "name:und_x_variant":[
        "Caser\u00edo La Vega"
    ],
    "wof:name":"La Vega",
    "wof:placetype":"locality"
},
  "geometry": {"coordinates":[-1.43333,40.41667],"type":"Point"}
}