{
  "type": "Feature",
  "properties": {
    "gn:admin1_code":"52",
    "gn:admin2_code":"TE",
    "gn:admin3_code":"44009",
    "gn:asciiname":"La Vega",
    "gn:cc2":"ES",
    "gn:country_code":"ES",
    "gn:dem":1167,
    "gn:feature_class":"P",
    "gn:feature_code":"PPL",
    "gn:name":"La Vega",
    "gn:population":0,
    "gn:timezone":"Europe/Madrid",
    "iso:country":"ES",
    "name:und_x_variant":[
        "Caser\u00edo La Vega",
        "La Vega"
    ],
    "wof:name":"La Vega",
    "wof:placetype":"locality"
},
  "geometry": {"coordinates":[-1.43333,40.41667],"type":"Point"}
}