{
  "type": "Feature",
  "properties": {
    "gn:gn_country":"ES",
    "gn:gn_fcode":"PPL",
    "gn:gn_pop":0,
    "iso:country":"ES",
    "name:cat_x_preferred":[
        "Beto\u00f1u"
    ],
    "name:ceb_x_preferred":[
        "Beto\u00f1o"
    ],
    "name:eng_x_preferred":[
        "Beto\u00f1o"
    ],
    "name:eus_x_preferred":[
        "Beto\u00f1u"
    ],
    "name:fra_x_preferred":[
        "Beto\u00f1o"
    ],
    "name:nld_x_preferred":[
        "Beto\u00f1o"
    ],
    "name:spa_x_preferred":[
        "Beto\u00f1o"
    ],
    "name:swe_x_preferred":[
        "Beto\u00f1o"
    ],
    "qs_pg:aaroncc":"ES",
    "qs_pg:gn_country":"ES",
    "qs_pg:gn_fcode":"PPL",
    "qs_pg:gn_pop":0,
    "qs_pg:name":"Beto\u00f1o",
    "qs_pg:name_adm0":"Espa\u00f1a",
    "qs_pg:name_adm1":"Euskadi",
    "qs_pg:photos":118,
    "qs_pg:photos_1k":24,
    "qs_pg:photos_9k":1,
    "qs_pg:photos_9r":3,
    "qs_pg:photos_all":118,
    "qs_pg:photos_sr":3,
    "qs_pg:pop_sr":0,
    "qs_pg:qs_pg_placetype":"locality",
    "qs_pg:qs_pg_placetype_gp":"Town",
    "qs_pg:woe_adm0":23424950,
    "woe:adm0_id":23424950,
    "woe:name_adm0":"Espa\u00f1a",
    "woe:name_adm1":"Euskadi",
    "woe:placetype":"Town",
    "wof:name":"Beto\u00f1o",
    "wof:placetype":"locality"
},
  "geometry": {"coordinates":[-2.65514,42.86267],"type":"Point"}
}