{
  "type": "Feature",
  "properties": {
    "gn:admin1_code":"32",
    "gn:admin3_code":"31049",
    "gn:asciiname":"Igoa",
    "gn:country_code":"ES",
    "gn:dem":719,
    "gn:feature_class":"P",
    "gn:feature_code":"PPL",
    "gn:name":"Igoa",
    "gn:population":0,
    "gn:timezone":"Europe/Madrid",
    "iso:country":"ES",
    "wof:name":"Igoa",
    "wof:placetype":"locality"
},
  "geometry": {"coordinates":[-1.78588,43.03182],"type":"Point"}
}