{
  "type": "Feature",
  "properties": {
    "gn:country":"ES",
    "gn:fcode":"PPLA3",
    "gn:population":201,
    "iso:country":"ES",
    "name:arg_x_preferred":[
        "Medrano"
    ],
    "name:ast_x_preferred":[
        "Medrano"
    ],
    "name:cat_x_preferred":[
        "Medrano"
    ],
    "name:ceb_x_preferred":[
        "Medrano"
    ],
    "name:che_x_preferred":[
        "\u041c\u0435\u0434\u0440\u0430\u043d\u043e"
    ],
    "name:deu_x_preferred":[
        "Medrano"
    ],
    "name:eng_x_preferred":[
        "Medrano"
    ],
    "name:epo_x_preferred":[
        "Medrano"
    ],
    "name:eus_x_preferred":[
        "Medrano"
    ],
    "name:fra_x_preferred":[
        "Medrano"
    ],
    "name:gle_x_preferred":[
        "Medrano"
    ],
    "name:hun_x_preferred":[
        "Medrano"
    ],
    "name:hye_x_preferred":[
        "\u0544\u0565\u0564\u0580\u0561\u0576\u0578"
    ],
    "name:ina_x_preferred":[
        "Medrano"
    ],
    "name:ita_x_preferred":[
        "Medrano"
    ],
    "name:kaz_x_preferred":[
        "\u041c\u0435\u0434\u0440\u0430\u043d\u043e"
    ],
    "name:lld_x_preferred":[
        "Medrano"
    ],
    "name:ltz_x_preferred":[
        "Medrano"
    ],
    "name:msa_x_preferred":[
        "Medrano"
    ],
    "name:nan_x_preferred":[
        "Medrano"
    ],
    "name:nld_x_preferred":[
        "Medrano"
    ],
    "name:nob_x_preferred":[
        "Medrano"
    ],
    "name:oci_x_preferred":[
        "Medrano"
    ],
    "name:pol_x_preferred":[
        "Medrano"
    ],
    "name:por_x_preferred":[
        "Medrano"
    ],
    "name:rup_x_preferred":[
        "Medrano"
    ],
    "name:rus_x_preferred":[
        "\u041c\u0435\u0434\u0440\u0430\u043d\u043e"
    ],
    "name:spa_x_preferred":[
        "Medrano"
    ],
    "name:swe_x_preferred":[
        "Medrano"
    ],
    "name:tat_x_preferred":[
        "\u041c\u0435\u0434\u0440\u0430\u043d\u043e"
    ],
    "name:ukr_x_preferred":[
        "\u041c\u0435\u0434\u0440\u0430\u043d\u043e"
    ],
    "name:uzb_x_preferred":[
        "Medrano"
    ],
    "name:vec_x_preferred":[
        "Medrano"
    ],
    "name:vie_x_preferred":[
        "Medrano"
    ],
    "name:war_x_preferred":[
        "Medrano"
    ],
    "name:zho_x_preferred":[
        "\u6885\u5fb7\u62c9\u8bfa"
    ],
    "qs_pg:aaroncc":"ES",
    "qs_pg:gn_country":"ES",
    "qs_pg:gn_fcode":"PPLA3",
    "qs_pg:gn_pop":201,
    "qs_pg:name":"Medrano",
    "qs_pg:name_adm0":"Espa\u00f1a",
    "qs_pg:name_adm1":"La Rioja",
    "qs_pg:photos_9r":0,
    "qs_pg:photos_sr":0,
    "qs_pg:pop_sr":2,
    "qs_pg:qs_pg_placetype":"locality",
    "qs_pg:qs_pg_placetype_gp":"Town",
    "qs_pg:woe_adm0":23424950,
    "woe:adm0_id":23424950,
    "woe:name_adm0":"Espa\u00f1a",
    "woe:name_adm1":"La Rioja",
    "woe:placetype":"Town",
    "wof:name":"Medrano",
    "wof:placetype":"locality",
    "wof:population":201
},
  "geometry": {"coordinates":[-2.55394,42.38361],"type":"Point"}
}