{
  "type": "Feature",
  "properties": {
    "gn:admin1_code":"58",
    "gn:admin2_code":"PO",
    "gn:admin3_code":"36046",
    "gn:asciiname":"Lois",
    "gn:cc2":"ES",
    "gn:country_code":"ES",
    "gn:dem":29,
    "gn:feature_class":"P",
    "gn:feature_code":"PPL",
    "gn:name":"Lois",
    "gn:population":0,
    "gn:timezone":"Europe/Madrid",
    "iso:country":"ES",
    "name:ita_x_preferred":[
        "Lois"
    ],
    "name:und_x_variant":[
        "San F\u00e9lix",
        "Lois"
    ],
    "wof:name":"Lois",
    "wof:placetype":"locality"
},
  "geometry": {"coordinates":[-8.71667,42.53333],"type":"Point"}
}