{
  "type": "Feature",
  "properties": {
    "gn:admin1_code":"59",
    "gn:admin2_code":"VI",
    "gn:admin3_code":"01059",
    "gn:asciiname":"Jungitu",
    "gn:country_code":"ES",
    "gn:dem":518,
    "gn:feature_class":"P",
    "gn:feature_code":"PPL",
    "gn:name":"Jungitu",
    "gn:population":0,
    "gn:timezone":"Europe/Madrid",
    "iso:country":"ES",
    "name:eus_x_preferred":[
        "Jungitu"
    ],
    "name:spa_x_preferred":[
        "Junguitu"
    ],
    "wof:name":"Jungitu",
    "wof:placetype":"locality"
},
  "geometry": {"coordinates":[-2.59501,42.87269000000001],"type":"Point"}
}