{
  "type": "Feature",
  "properties": {
    "gn:admin1_code":"55",
    "gn:admin2_code":"P",
    "gn:admin3_code":"34056",
    "gn:asciiname":"Rueda",
    "gn:country_code":"ES",
    "gn:dem":964,
    "gn:feature_class":"P",
    "gn:feature_code":"PPL",
    "gn:name":"Rueda",
    "gn:population":0,
    "gn:timezone":"Europe/Madrid",
    "iso:country":"ES",
    "name:arg_x_preferred":[
        "Rueda"
    ],
    "name:cat_x_preferred":[
        "Rueda"
    ],
    "name:ceb_x_preferred":[
        "Rueda"
    ],
    "name:deu_x_preferred":[
        "Rueda"
    ],
    "name:fra_x_preferred":[
        "Rueda"
    ],
    "name:por_x_preferred":[
        "Rueda"
    ],
    "name:rus_x_preferred":[
        "\u0420\u0443\u044d\u0434\u0430"
    ],
    "name:spa_x_preferred":[
        "Rueda"
    ],
    "name:swe_x_preferred":[
        "Rueda"
    ],
    "name:tur_x_preferred":[
        "Rueda"
    ],
    "wof:name":"Rueda",
    "wof:placetype":"locality"
},
  "geometry": {"coordinates":[-4.41663,42.85672],"type":"Point"}
}