{
  "type": "Feature",
  "properties": {
    "gn:gn_country":"ES",
    "gn:gn_fcode":"PPLA3",
    "gn:gn_pop":26,
    "gn:population":26,
    "iso:country":"ES",
    "name:arg_x_preferred":[
        "Pinilla de Molina"
    ],
    "name:cat_x_preferred":[
        "Pinilla de Molina"
    ],
    "name:eng_x_preferred":[
        "Pinilla de Molina"
    ],
    "name:eus_x_preferred":[
        "Pinilla de Molina"
    ],
    "name:fra_x_preferred":[
        "Pinilla de Molina"
    ],
    "name:hun_x_preferred":[
        "Pinilla de Molina"
    ],
    "name:ina_x_preferred":[
        "Pinilla de Molina"
    ],
    "name:ita_x_preferred":[
        "Pinilla de Molina"
    ],
    "name:kaz_x_preferred":[
        "\u041f\u0438\u043d\u0438\u043b\u044c\u044f-\u0434\u0435-\u041c\u043e\u043b\u0438\u043d\u0430"
    ],
    "name:msa_x_preferred":[
        "Pinilla de Molina"
    ],
    "name:nan_x_preferred":[
        "Pinilla de Molina"
    ],
    "name:nld_x_preferred":[
        "Pinilla de Molina"
    ],
    "name:oci_x_preferred":[
        "Pinilla de Molina"
    ],
    "name:pam_x_preferred":[
        "Pinilla de Molina"
    ],
    "name:pol_x_preferred":[
        "Pinilla de Molina"
    ],
    "name:por_x_preferred":[
        "Pinilla de Molina"
    ],
    "name:rus_x_preferred":[
        "\u041f\u0438\u043d\u0438\u043b\u044c\u044f-\u0434\u0435-\u041c\u043e\u043b\u0438\u043d\u0430"
    ],
    "name:spa_x_preferred":[
        "Pinilla de Molina"
    ],
    "name:swe_x_preferred":[
        "Pinilla de Molina"
    ],
    "name:ukr_x_preferred":[
        "\u041f\u0456\u043d\u0456\u043b\u044c\u044f-\u0434\u0435-\u041c\u043e\u043b\u0456\u043d\u0430"
    ],
    "name:vie_x_preferred":[
        "Pinilla de Molina"
    ],
    "name:war_x_preferred":[
        "Pinilla de Molina"
    ],
    "name:zho_x_preferred":[
        "\u76ae\u5c3c\u5229\u4e9a\u5fb7\u83ab\u5229\u7eb3"
    ],
    "qs_pg:aaroncc":"ES",
    "qs_pg:gn_country":"ES",
    "qs_pg:gn_fcode":"PPLA3",
    "qs_pg:gn_pop":26,
    "qs_pg:name":"Pinilla de Molina",
    "qs_pg:name_adm0":"Espa\u00f1a",
    "qs_pg:name_adm1":"Castilla-La Mancha",
    "qs_pg:photos_9r":0,
    "qs_pg:photos_sr":0,
    "qs_pg:pop_sr":1,
    "qs_pg:qs_pg_placetype":"locality",
    "qs_pg:qs_pg_placetype_gp":"Town",
    "qs_pg:woe_adm0":23424950,
    "woe:adm0_id":23424950,
    "woe:name_adm0":"Espa\u00f1a",
    "woe:name_adm1":"Castilla-La Mancha",
    "woe:placetype":"Town",
    "wof:name":"Pinilla de Molina",
    "wof:placetype":"locality",
    "wof:population":26
},
  "geometry": {"coordinates":[-1.88034,40.67969],"type":"Point"}
}