{
  "type": "Feature",
  "properties": {
    "gn:admin1_code":"51",
    "gn:admin2_code":"GR",
    "gn:admin3_code":"18056",
    "gn:asciiname":"Almendro",
    "gn:country_code":"ES",
    "gn:dem":1077,
    "gn:feature_class":"P",
    "gn:feature_code":"PPL",
    "gn:name":"Almendro",
    "gn:population":0,
    "gn:timezone":"Europe/Madrid",
    "iso:country":"ES",
    "name:und_x_variant":[
        "Caser\u00edo Almendro",
        "Almendro"
    ],
    "wof:name":"Almendro",
    "wof:placetype":"locality"
},
  "geometry": {"coordinates":[-2.57883,37.47717],"type":"Point"}
}