{
  "type": "Feature",
  "properties": {
    "gn:admin1_code":"56",
    "gn:admin2_code":"L",
    "gn:admin3_code":"25024",
    "gn:asciiname":"Valencia d'Aneu",
    "gn:cc2":"ES",
    "gn:country_code":"ES",
    "gn:dem":1089,
    "gn:feature_class":"P",
    "gn:feature_code":"PPL",
    "gn:name":"Val\u00e8ncia d'\u00c0neu",
    "gn:population":0,
    "gn:timezone":"Europe/Madrid",
    "iso:country":"ES",
    "wof:name":"Valencia d'Aneu",
    "wof:placetype":"locality"
},
  "geometry": {"coordinates":[1.10945,42.63418],"type":"Point"}
}