{
  "type": "Feature",
  "properties": {
    "gn:gn_country":"ES",
    "gn:gn_fcode":"PPL",
    "gn:gn_pop":383,
    "gn:population":383,
    "iso:country":"ES",
    "name:arg_x_preferred":[
        "El Ma\u00edllo"
    ],
    "name:baq_x_preferred":[
        "El Ma\u00edllo"
    ],
    "name:cat_x_preferred":[
        "El Ma\u00edllo"
    ],
    "name:chi_x_preferred":[
        "\u57c3\u5c14\u8fc8\u7565"
    ],
    "name:dut_x_preferred":[
        "El Ma\u00edllo"
    ],
    "name:eng_x_preferred":[
        "El Ma\u00edllo"
    ],
    "name:fre_x_preferred":[
        "El Ma\u00edllo"
    ],
    "name:ger_x_preferred":[
        "El Ma\u00edllo"
    ],
    "name:hun_x_preferred":[
        "El Ma\u00edllo"
    ],
    "name:ina_x_preferred":[
        "El Ma\u00edllo"
    ],
    "name:ita_x_preferred":[
        "El Ma\u00edllo"
    ],
    "name:kaz_x_preferred":[
        "\u042d\u043b\u044c-\u041c\u0430\u0438\u043b\u044c\u043e"
    ],
    "name:may_x_preferred":[
        "El Ma\u00edllo"
    ],
    "name:nan_x_preferred":[
        "El Ma\u00edllo"
    ],
    "name:oci_x_preferred":[
        "El Ma\u00edllo"
    ],
    "name:pol_x_preferred":[
        "El Ma\u00edllo"
    ],
    "name:por_x_preferred":[
        "El Ma\u00edllo"
    ],
    "name:rup_x_preferred":[
        "El Ma\u00edllo"
    ],
    "name:rus_x_preferred":[
        "\u042d\u043b\u044c-\u041c\u0430\u0438\u043b\u044c\u043e"
    ],
    "name:spa_x_preferred":[
        "El Ma\u00edllo"
    ],
    "name:swe_x_preferred":[
        "El Maillo"
    ],
    "name:ukr_x_preferred":[
        "\u0415\u043b\u044c-\u041c\u0430\u0457\u043b\u044c\u0439\u043e"
    ],
    "name:unk_x_variant":[
        "El Maillo"
    ],
    "name:uzb_x_preferred":[
        "El Ma\u00edllo"
    ],
    "name:vie_x_preferred":[
        "El Ma\u00edllo"
    ],
    "name:war_x_preferred":[
        "El Ma\u00edllo"
    ],
    "qs_pg:aaroncc":"ES",
    "qs_pg:gn_country":"ES",
    "qs_pg:gn_fcode":"PPL",
    "qs_pg:gn_pop":383,
    "qs_pg:name":"El Ma\u00edllo",
    "qs_pg:name_adm0":"Espa\u00f1a",
    "qs_pg:name_adm1":"Castilla y Le\u00f3n",
    "qs_pg:photos_9k":2,
    "qs_pg:photos_9r":5,
    "qs_pg:photos_all":379,
    "qs_pg:photos_sr":0,
    "qs_pg:pop_sr":2,
    "qs_pg:qs_pg_placetype":"locality",
    "qs_pg:qs_pg_placetype_gp":"Town",
    "qs_pg:woe_adm0":23424950,
    "woe:adm0_id":23424950,
    "woe:name_adm0":"Espa\u00f1a",
    "woe:name_adm1":"Castilla y Le\u00f3n",
    "woe:placetype":"Town",
    "wof:name":"El Ma\u00edllo",
    "wof:placetype":"locality",
    "wof:population":383
},
  "geometry": {"coordinates":[-6.16667,40.56667],"type":"Point"}
}