{
  "type": "Feature",
  "properties": {
    "gn:admin1_code":"58",
    "gn:admin2_code":"OR",
    "gn:admin3_code":"32047",
    "gn:asciiname":"Olas de Villarino",
    "gn:cc2":"ES",
    "gn:country_code":"ES",
    "gn:dem":487,
    "gn:feature_class":"P",
    "gn:feature_code":"PPL",
    "gn:name":"Ol\u00e1s de Villari\u00f1o",
    "gn:population":0,
    "gn:timezone":"Europe/Madrid",
    "iso:country":"ES",
    "name:und_x_variant":[
        "Santa Mar\u00eda",
        "Ol\u00e1s de Vilari\u00f1o"
    ],
    "wof:name":"Olas de Villarino",
    "wof:placetype":"locality"
},
  "geometry": {"coordinates":[-7.89462,42.18637],"type":"Point"}
}