{
  "type": "Feature",
  "properties": {
    "gn:admin1_code":"60",
    "gn:admin2_code":"V",
    "gn:admin3_code":"46038",
    "gn:asciiname":"La Pobleta",
    "gn:country_code":"ES",
    "gn:dem":927,
    "gn:feature_class":"P",
    "gn:feature_code":"PPL",
    "gn:name":"La Pobleta",
    "gn:population":0,
    "gn:timezone":"Europe/Madrid",
    "iso:country":"ES",
    "wof:name":"La Pobleta",
    "wof:placetype":"locality"
},
  "geometry": {"coordinates":[-0.81667,39.83333],"type":"Point"}
}