{
  "type": "Feature",
  "properties": {
    "gn:admin1_code":"59",
    "gn:admin2_code":"VI",
    "gn:admin3_code":"01008",
    "gn:asciiname":"Nanclares de Gamboa",
    "gn:country_code":"ES",
    "gn:dem":555,
    "gn:feature_class":"P",
    "gn:feature_code":"PPL",
    "gn:name":"Langara Ganboa / Nanclares de Ganboa",
    "gn:population":0,
    "gn:timezone":"Europe/Madrid",
    "iso:country":"ES",
    "name:eus_x_preferred":[
        "Langara Ganboa"
    ],
    "name:spa_x_preferred":[
        "Nanclares de Ganboa"
    ],
    "wof:name":"Nanclares de Gamboa",
    "wof:placetype":"locality"
},
  "geometry": {"coordinates":[-2.57569,42.92149000000001],"type":"Point"}
}