{
  "type": "Feature",
  "properties": {
    "gn:admin1_code":"59",
    "gn:admin2_code":"SS",
    "gn:admin3_code":"20031",
    "gn:asciiname":"Elduayen",
    "gn:country_code":"ES",
    "gn:dem":243,
    "gn:feature_class":"P",
    "gn:feature_code":"PPLA3",
    "gn:name":"Elduain",
    "gn:population":0,
    "gn:timezone":"Europe/Madrid",
    "iso:country":"ES",
    "name:eus_x_preferred":[
        "Elduain"
    ],
    "name:spa_x_preferred":[
        "Elduayen"
    ],
    "wof:name":"Elduayen",
    "wof:placetype":"locality"
},
  "geometry": {"coordinates":[-2.00102,43.14017],"type":"Point"}
}