{
  "type": "Feature",
  "properties": {
    "gn:admin1_code":"55",
    "gn:admin2_code":"P",
    "gn:admin3_code":"34171",
    "gn:asciiname":"Villaoliva",
    "gn:country_code":"ES",
    "gn:dem":1109,
    "gn:feature_class":"P",
    "gn:feature_code":"PPL",
    "gn:name":"Villaoliva",
    "gn:population":0,
    "gn:timezone":"Europe/Madrid",
    "iso:country":"ES",
    "wof:name":"Villaoliva",
    "wof:placetype":"locality"
},
  "geometry": {"coordinates":[-4.75591,42.78419],"type":"Point"}
}