{
  "type": "Feature",
  "properties": {
    "gn:admin1_code":"55",
    "gn:admin2_code":"BU",
    "gn:admin3_code":"09195",
    "gn:asciiname":"Movilla",
    "gn:country_code":"ES",
    "gn:dem":666,
    "gn:feature_class":"P",
    "gn:feature_code":"PPL",
    "gn:name":"Movilla",
    "gn:population":0,
    "gn:timezone":"Europe/Madrid",
    "iso:country":"ES",
    "name:und_x_variant":[
        "Monvilla",
        "Movilla"
    ],
    "wof:name":"Movilla",
    "wof:placetype":"locality"
},
  "geometry": {"coordinates":[-3.42899,42.61164],"type":"Point"}
}