{
  "type": "Feature",
  "properties": {
    "gn:admin1_code":"58",
    "gn:admin2_code":"C",
    "gn:admin3_code":"15023",
    "gn:asciiname":"Berroge",
    "gn:country_code":"ES",
    "gn:dem":27,
    "gn:feature_class":"P",
    "gn:feature_code":"PPL",
    "gn:name":"Berroge",
    "gn:population":0,
    "gn:timezone":"Europe/Madrid",
    "iso:country":"ES",
    "name:und_x_variant":[
        "Berroje",
        "Berroge"
    ],
    "wof:name":"Berroge",
    "wof:placetype":"locality"
},
  "geometry": {"coordinates":[-9.16562,42.94543],"type":"Point"}
}