{
  "type": "Feature",
  "properties": {
    "gn:admin1_code":"34",
    "gn:asciiname":"Matafoyada",
    "gn:country_code":"ES",
    "gn:dem":835,
    "gn:feature_class":"P",
    "gn:feature_code":"PPL",
    "gn:name":"Matafoyada",
    "gn:population":0,
    "gn:timezone":"Europe/Lisbon",
    "iso:country":"ES",
    "wof:name":"Matafoyada",
    "wof:placetype":"locality"
},
  "geometry": {"coordinates":[-6.88333,40.51667],"type":"Point"}
}