{
  "type": "Feature",
  "properties": {
    "iso:country":"ES",
    "name:als_x_preferred":[
        "Kornett"
    ],
    "name:ara_x_preferred":[
        "\u0634\u064a\u0627\u0639"
    ],
    "name:ast_x_preferred":[
        "Corneta"
    ],
    "name:bel_x_preferred":[
        "\u041a\u0430\u0440\u043d\u0435\u0442"
    ],
    "name:ces_x_preferred":[
        "Kornet"
    ],
    "name:dan_x_preferred":[
        "Kornet"
    ],
    "name:deu_x_preferred":[
        "Kornett"
    ],
    "name:epo_x_preferred":[
        "Pi\u015dtokorneto"
    ],
    "name:est_x_preferred":[
        "Kornet"
    ],
    "name:eus_x_preferred":[
        "Korneta"
    ],
    "name:fas_x_preferred":[
        "\u06a9\u0648\u0631\u0646\u062a"
    ],
    "name:fin_x_preferred":[
        "Kornetti"
    ],
    "name:fry_x_preferred":[
        "Kornet"
    ],
    "name:gle_x_preferred":[
        "Coirn\u00e9ad"
    ],
    "name:glg_x_preferred":[
        "Corneta"
    ],
    "name:heb_x_preferred":[
        "\u05e7\u05d5\u05e8\u05e0\u05d9\u05ea"
    ],
    "name:hrv_x_preferred":[
        "Kornet"
    ],
    "name:hun_x_preferred":[
        "Kornett"
    ],
    "name:hye_x_preferred":[
        "\u053f\u0578\u057c\u0576\u0565\u057f"
    ],
    "name:isl_x_preferred":[
        "Kornett"
    ],
    "name:ita_x_preferred":[
        "Cornetta"
    ],
    "name:jpn_x_preferred":[
        "\u30b3\u30eb\u30cd\u30c3\u30c8"
    ],
    "name:kir_x_preferred":[
        "\u041a\u043e\u0440\u043d\u0435\u0442"
    ],
    "name:lit_x_preferred":[
        "Kornetas"
    ],
    "name:mya_x_preferred":[
        "\u1000\u1031\u102c\u1014\u1000\u103a"
    ],
    "name:nld_x_preferred":[
        "Kornet"
    ],
    "name:nno_x_preferred":[
        "Kornett"
    ],
    "name:nor_x_preferred":[
        "Kornett"
    ],
    "name:oci_x_preferred":[
        "Cornet"
    ],
    "name:pol_x_preferred":[
        "Kornet"
    ],
    "name:por_x_preferred":[
        "Corneta"
    ],
    "name:ron_x_preferred":[
        "Cornet"
    ],
    "name:rus_x_preferred":[
        "\u041a\u043e\u0440\u043d\u0435\u0442"
    ],
    "name:spa_x_preferred":[
        "Corneta"
    ],
    "name:swe_x_preferred":[
        "Kornett"
    ],
    "name:tha_x_preferred":[
        "\u0e04\u0e2d\u0e23\u0e4c\u0e40\u0e19\u0e15"
    ],
    "name:tur_x_preferred":[
        "Kornet"
    ],
    "name:ukr_x_preferred":[
        "\u041a\u043e\u0440\u043d\u0435\u0442"
    ],
    "name:uzb_x_preferred":[
        "Kornet"
    ],
    "qs_pg:aaroncc":"ES",
    "qs_pg:name":"Cornet",
    "qs_pg:name_adm0":"Espa\u00f1a",
    "qs_pg:name_adm1":"Catalunya",
    "qs_pg:photos":19,
    "qs_pg:photos_1k":4,
    "qs_pg:photos_9k":1,
    "qs_pg:photos_9r":1,
    "qs_pg:photos_all":19,
    "qs_pg:photos_sr":1,
    "qs_pg:pop_sr":0,
    "qs_pg:qs_pg_placetype":"locality",
    "qs_pg:qs_pg_placetype_gp":"Town",
    "qs_pg:woe_adm0":23424950,
    "woe:adm0_id":23424950,
    "woe:name_adm0":"Espa\u00f1a",
    "woe:name_adm1":"Catalunya",
    "woe:placetype":"Town",
    "wof:name":"Cornet",
    "wof:placetype":"locality"
},
  "geometry": {"coordinates":[1.937398,41.895248],"type":"Point"}
}