{
  "type": "Feature",
  "properties": {
    "gn:gn_country":"ES",
    "gn:gn_fcode":"PPLA3",
    "gn:gn_pop":103,
    "gn:population":103,
    "iso:country":"ES",
    "name:arg_x_preferred":[
        "Arruazu"
    ],
    "name:baq_x_preferred":[
        "Arruazu"
    ],
    "name:bre_x_preferred":[
        "Arruazu"
    ],
    "name:cat_x_preferred":[
        "Arruazu"
    ],
    "name:chi_x_preferred":[
        "\u963f\u9c81\u963f\u82cf"
    ],
    "name:dut_x_preferred":[
        "Arruazu"
    ],
    "name:eng_x_preferred":[
        "Arruazu"
    ],
    "name:fre_x_preferred":[
        "Arruazu"
    ],
    "name:hun_x_preferred":[
        "Arruazu"
    ],
    "name:ita_x_preferred":[
        "Arruazu"
    ],
    "name:jpn_x_preferred":[
        "\u30a2\u30eb\u30a2\u30b9"
    ],
    "name:may_x_preferred":[
        "Arruazu"
    ],
    "name:nan_x_preferred":[
        "Arruazu"
    ],
    "name:oci_x_preferred":[
        "Arruazu"
    ],
    "name:pol_x_preferred":[
        "Arruazu"
    ],
    "name:por_x_preferred":[
        "Arruazu"
    ],
    "name:rup_x_preferred":[
        "Arruazu"
    ],
    "name:rus_x_preferred":[
        "\u0410\u0440\u0440\u0443\u0430\u0441\u0443"
    ],
    "name:spa_x_preferred":[
        "Arruazu"
    ],
    "name:swe_x_preferred":[
        "Arruazu"
    ],
    "name:ukr_x_preferred":[
        "\u0410\u0440\u0440\u0443\u0430\u0441\u0443"
    ],
    "name:uzb_x_preferred":[
        "Arruazu"
    ],
    "name:vie_x_preferred":[
        "Arruazu"
    ],
    "name:war_x_preferred":[
        "Arruazu"
    ],
    "qs_pg:aaroncc":"ES",
    "qs_pg:gn_country":"ES",
    "qs_pg:gn_fcode":"PPLA3",
    "qs_pg:gn_pop":103,
    "qs_pg:name":"Arruazu",
    "qs_pg:name_adm0":"Espa\u00f1a",
    "qs_pg:name_adm1":"Comunidad Foral de Navarra",
    "qs_pg:photos":14,
    "qs_pg:photos_1k":3,
    "qs_pg:photos_9k":1,
    "qs_pg:photos_9r":1,
    "qs_pg:photos_all":14,
    "qs_pg:photos_sr":1,
    "qs_pg:pop_sr":1,
    "qs_pg:qs_pg_placetype":"locality",
    "qs_pg:qs_pg_placetype_gp":"Town",
    "qs_pg:woe_adm0":23424950,
    "woe:adm0_id":23424950,
    "woe:name_adm0":"Espa\u00f1a",
    "woe:name_adm1":"Comunidad Foral de Navarra",
    "woe:placetype":"Town",
    "wof:name":"Arruazu",
    "wof:placetype":"locality",
    "wof:population":103
},
  "geometry": {"coordinates":[-2.00157,42.92186],"type":"Point"}
}