{
  "type": "Feature",
  "properties": {
    "gn:admin1_code":"39",
    "gn:admin2_code":"S",
    "gn:admin3_code":"39094",
    "gn:asciiname":"San Martin de Valdelomar",
    "gn:country_code":"ES",
    "gn:dem":859,
    "gn:feature_class":"P",
    "gn:feature_code":"PPL",
    "gn:name":"San Mart\u00edn de Valdelomar",
    "gn:population":0,
    "gn:timezone":"Europe/Madrid",
    "iso:country":"ES",
    "wof:name":"San Martin de Valdelomar",
    "wof:placetype":"locality"
},
  "geometry": {"coordinates":[-4.14657,42.79647],"type":"Point"}
}