{
  "type": "Feature",
  "properties": {
    "iso:country":"ES",
    "name:eng_x_preferred":[
        "San Jose"
    ],
    "name:spa_x_preferred":[
        "San Jos\u00e9"
    ],
    "wof:name":"San Jose",
    "wof:placetype":"neighbourhood"
},
  "geometry": {"coordinates":[-4.42358690394267,36.75590029142165],"type":"Point"}
}