{
  "type": "Feature",
  "properties": {
    "gn:admin1_code":"57",
    "gn:admin2_code":"BA",
    "gn:admin3_code":"06109",
    "gn:asciiname":"Quintana de la Serena",
    "gn:country_code":"ES",
    "gn:dem":411,
    "gn:feature_class":"P",
    "gn:feature_code":"PPLA3",
    "gn:name":"Quintana de la Serena",
    "gn:population":5242,
    "gn:timezone":"Europe/Madrid",
    "iso:country":"ES",
    "wof:name":"Quintana de la Serena",
    "wof:placetype":"locality",
    "wof:population":5242
},
  "geometry": {"coordinates":[-5.67233,38.74595],"type":"Point"}
}