{
  "type": "Feature",
  "properties": {
    "gn:admin1_code":"59",
    "gn:admin2_code":"BI",
    "gn:admin3_code":"48041",
    "gn:asciiname":"Islabekoa",
    "gn:cc2":"ES",
    "gn:country_code":"ES",
    "gn:dem":29,
    "gn:feature_class":"P",
    "gn:feature_code":"PPL",
    "gn:name":"Islabekoa",
    "gn:population":0,
    "gn:timezone":"Europe/Madrid",
    "iso:country":"ES",
    "name:und_x_variant":[
        "Islas"
    ],
    "wof:name":"Islabekoa",
    "wof:placetype":"locality"
},
  "geometry": {"coordinates":[-2.6677,43.36045],"type":"Point"}
}