{
  "type": "Feature",
  "properties": {
    "gn:admin1_code":"55",
    "gn:admin2_code":"SO",
    "gn:admin3_code":"42053",
    "gn:asciiname":"Pozuelo",
    "gn:country_code":"ES",
    "gn:dem":1148,
    "gn:feature_class":"P",
    "gn:feature_code":"PPL",
    "gn:name":"Pozuelo",
    "gn:population":0,
    "gn:timezone":"Europe/Madrid",
    "iso:country":"ES",
    "wof:name":"Pozuelo",
    "wof:placetype":"locality"
},
  "geometry": {"coordinates":[-3.05945,41.40838],"type":"Point"}
}