{
  "type": "Feature",
  "properties": {
    "gn:admin1_code":"55",
    "gn:admin2_code":"ZA",
    "gn:admin3_code":"49085",
    "gn:asciiname":"Llanes",
    "gn:country_code":"ES",
    "gn:dem":933,
    "gn:feature_class":"P",
    "gn:feature_code":"PPL",
    "gn:name":"Llanes",
    "gn:population":0,
    "gn:timezone":"Europe/Madrid",
    "iso:country":"ES",
    "name:ara_x_preferred":[
        "\u064a\u0627\u0646\u064a\u0633"
    ],
    "name:arg_x_preferred":[
        "Llanes"
    ],
    "name:ast_x_preferred":[
        "Llanes"
    ],
    "name:cat_x_preferred":[
        "Llanes"
    ],
    "name:ceb_x_preferred":[
        "Llanes"
    ],
    "name:cym_x_preferred":[
        "Llanes"
    ],
    "name:deu_x_preferred":[
        "Llanes"
    ],
    "name:eus_x_preferred":[
        "Llanes"
    ],
    "name:fas_x_preferred":[
        "\u06cc\u0627\u0646\u0633"
    ],
    "name:fra_x_preferred":[
        "Llanes"
    ],
    "name:glg_x_preferred":[
        "Llanes"
    ],
    "name:hrv_x_preferred":[
        "Llanes"
    ],
    "name:hun_x_preferred":[
        "Llanes"
    ],
    "name:ina_x_preferred":[
        "Llanes"
    ],
    "name:ita_x_preferred":[
        "Llanes"
    ],
    "name:jpn_x_preferred":[
        "\u30ea\u30e3\u30cd\u30b9"
    ],
    "name:msa_x_preferred":[
        "Llanes"
    ],
    "name:nld_x_preferred":[
        "Llanes"
    ],
    "name:oci_x_preferred":[
        "Llanes"
    ],
    "name:pol_x_preferred":[
        "Llanes"
    ],
    "name:por_x_preferred":[
        "Llanes"
    ],
    "name:rus_x_preferred":[
        "\u041b\u044c\u044f\u043d\u0435\u0441"
    ],
    "name:spa_x_preferred":[
        "Llanes"
    ],
    "name:sqi_x_preferred":[
        "Llanes"
    ],
    "name:swe_x_preferred":[
        "Llanes"
    ],
    "name:tur_x_preferred":[
        "Llanes"
    ],
    "name:ukr_x_preferred":[
        "\u041b\u044c\u044f\u043d\u0435\u0441"
    ],
    "name:uzb_x_preferred":[
        "Llanes"
    ],
    "name:vie_x_preferred":[
        "Llanes"
    ],
    "name:war_x_preferred":[
        "Llanes"
    ],
    "name:zho_x_preferred":[
        "\u5229\u4e9a\u5185\u65af"
    ],
    "wof:name":"Llanes",
    "wof:placetype":"locality"
},
  "geometry": {"coordinates":[-6.66063,42.08778],"type":"Point"}
}