{
  "type": "Feature",
  "properties": {
    "gn:admin1_code":"55",
    "gn:admin2_code":"ZA",
    "gn:admin3_code":"49085",
    "gn:asciiname":"Llanes",
    "gn:country_code":"ES",
    "gn:dem":933,
    "gn:feature_class":"P",
    "gn:feature_code":"PPL",
    "gn:name":"Llanes",
    "gn:population":0,
    "gn:timezone":"Europe/Madrid",
    "iso:country":"ES",
    "wof:name":"Llanes",
    "wof:placetype":"locality"
},
  "geometry": {"coordinates":[-6.66063,42.08778],"type":"Point"}
}