{
  "type": "Feature",
  "properties": {
    "gn:gn_country":"ES",
    "gn:gn_fcode":"PPLA3",
    "gn:gn_pop":745,
    "gn:population":745,
    "iso:country":"ES",
    "name:arg_x_preferred":[
        "Quesa"
    ],
    "name:ast_x_preferred":[
        "Quesa"
    ],
    "name:cat_x_preferred":[
        "Quesa"
    ],
    "name:ceb_x_preferred":[
        "Quesa"
    ],
    "name:deu_x_preferred":[
        "Quesa"
    ],
    "name:eng_x_preferred":[
        "Quesa"
    ],
    "name:eus_x_preferred":[
        "Quesa"
    ],
    "name:fra_x_preferred":[
        "Quesa"
    ],
    "name:hun_x_preferred":[
        "Quesa"
    ],
    "name:ita_x_preferred":[
        "Quesa"
    ],
    "name:msa_x_preferred":[
        "Quesa"
    ],
    "name:nan_x_preferred":[
        "Quesa"
    ],
    "name:nld_x_preferred":[
        "Quesa"
    ],
    "name:oci_x_preferred":[
        "Quesa"
    ],
    "name:pol_x_preferred":[
        "Quesa"
    ],
    "name:por_x_preferred":[
        "Quesa"
    ],
    "name:rus_x_preferred":[
        "\u041a\u0435\u0441\u0430"
    ],
    "name:spa_x_preferred":[
        "Quesa"
    ],
    "name:sqi_x_preferred":[
        "Quesa"
    ],
    "name:swe_x_preferred":[
        "Quesa"
    ],
    "name:ukr_x_preferred":[
        "\u041a\u0435\u0441\u0430"
    ],
    "name:war_x_preferred":[
        "Quesa"
    ],
    "name:zho_x_preferred":[
        "\u514b\u8428"
    ],
    "qs_pg:aaroncc":"ES",
    "qs_pg:gn_country":"ES",
    "qs_pg:gn_fcode":"PPLA3",
    "qs_pg:gn_pop":745,
    "qs_pg:name":"Quesa",
    "qs_pg:name_adm0":"Espa\u00f1a",
    "qs_pg:name_adm1":"Comunitat Valenciana",
    "qs_pg:photos_9r":0,
    "qs_pg:photos_sr":0,
    "qs_pg:pop_sr":2,
    "qs_pg:qs_pg_placetype":"locality",
    "qs_pg:qs_pg_placetype_gp":"Town",
    "qs_pg:woe_adm0":23424950,
    "woe:adm0_id":23424950,
    "woe:name_adm0":"Espa\u00f1a",
    "woe:name_adm1":"Comunitat Valenciana",
    "woe:placetype":"Town",
    "wof:name":"Quesa",
    "wof:placetype":"locality",
    "wof:population":745
},
  "geometry": {"coordinates":[-0.74,39.1197],"type":"Point"}
}