{
  "type": "Feature",
  "properties": {
    "gn:country":"ES",
    "gn:fcode":"PPL",
    "gn:population":790,
    "iso:country":"ES",
    "name:arg_x_preferred":[
        "La Galera"
    ],
    "name:ast_x_preferred":[
        "La Galera"
    ],
    "name:azb_x_preferred":[
        "\u0644\u0627 \u0642\u0627\u0644\u0631\u0627"
    ],
    "name:cat_x_preferred":[
        "la Galera"
    ],
    "name:cat_x_variant":[
        "La Galera"
    ],
    "name:ceb_x_preferred":[
        "La Galera"
    ],
    "name:che_x_preferred":[
        "\u041b\u0430-\u0413\u0430\u043b\u0435\u0440\u0430"
    ],
    "name:eng_x_preferred":[
        "La Galera"
    ],
    "name:eus_x_preferred":[
        "La Galera"
    ],
    "name:fas_x_preferred":[
        "\u0644\u0627 \u06af\u0627\u0644\u0631\u0627"
    ],
    "name:fra_x_preferred":[
        "La Galera"
    ],
    "name:gle_x_preferred":[
        "la Galera"
    ],
    "name:glg_x_preferred":[
        "La Galera"
    ],
    "name:hun_x_preferred":[
        "La Galera"
    ],
    "name:hye_x_preferred":[
        "\u053c\u0561 \u0533\u0561\u056c\u0565\u0580\u0561"
    ],
    "name:ile_x_preferred":[
        "La Galera"
    ],
    "name:ita_x_preferred":[
        "La Galera"
    ],
    "name:lat_x_preferred":[
        "La Galera"
    ],
    "name:lld_x_preferred":[
        "La Galera"
    ],
    "name:msa_x_preferred":[
        "La Galera"
    ],
    "name:nld_x_preferred":[
        "La Galera"
    ],
    "name:oci_x_preferred":[
        "La Galera"
    ],
    "name:pol_x_preferred":[
        "La Galera"
    ],
    "name:por_x_preferred":[
        "La Galera"
    ],
    "name:rus_x_preferred":[
        "\u041b\u0430-\u0413\u0430\u043b\u0435\u0440\u0430"
    ],
    "name:spa_x_preferred":[
        "La Galera"
    ],
    "name:sqi_x_preferred":[
        "La Galera"
    ],
    "name:swe_x_preferred":[
        "La Galera"
    ],
    "name:tat_x_preferred":[
        "\u041b\u0430-\u0413\u0430\u043b\u0435\u0440\u0430"
    ],
    "name:ukr_x_preferred":[
        "\u041b\u0430-\u0490\u0430\u043b\u0435\u0440\u0430"
    ],
    "name:urd_x_preferred":[
        "\u0644\u0627 \u06af\u0627\u0644\u06cc\u0631\u0627"
    ],
    "name:vec_x_preferred":[
        "La Galera"
    ],
    "name:war_x_preferred":[
        "La Galera"
    ],
    "name:zho_x_preferred":[
        "\u62c9\u52a0\u83b1\u62c9"
    ],
    "qs_pg:aaroncc":"ES",
    "qs_pg:gn_country":"ES",
    "qs_pg:gn_fcode":"PPL",
    "qs_pg:gn_pop":790,
    "qs_pg:name":"La Palmera",
    "qs_pg:name_adm0":"Espa\u00f1a",
    "qs_pg:name_adm1":"Comunitat Valenciana",
    "qs_pg:photos_9k":1,
    "qs_pg:photos_9r":1,
    "qs_pg:photos_all":2,
    "qs_pg:photos_sr":0,
    "qs_pg:pop_sr":2,
    "qs_pg:qs_pg_placetype":"locality",
    "qs_pg:qs_pg_placetype_gp":"Town",
    "qs_pg:woe_adm0":23424950,
    "woe:adm0_id":23424950,
    "woe:name_adm0":"Espa\u00f1a",
    "woe:name_adm1":"Comunitat Valenciana",
    "woe:placetype":"Town",
    "wof:name":"La Palmera",
    "wof:placetype":"locality",
    "wof:population":790
},
  "geometry": {"coordinates":[0.46342,40.68149],"type":"Point"}
}