{
  "type": "Feature",
  "properties": {
    "gn:admin1_code":"58",
    "gn:admin2_code":"PO",
    "gn:admin3_code":"36056",
    "gn:asciiname":"Louro",
    "gn:cc2":"ES",
    "gn:country_code":"ES",
    "gn:dem":44,
    "gn:feature_class":"P",
    "gn:feature_code":"PPL",
    "gn:name":"Louro",
    "gn:population":0,
    "gn:timezone":"Europe/Madrid",
    "iso:country":"ES",
    "name:und_x_variant":[
        "Santa Columba"
    ],
    "wof:name":"Louro",
    "wof:placetype":"locality"
},
  "geometry": {"coordinates":[-8.65903,42.69045],"type":"Point"}
}