{
  "type": "Feature",
  "properties": {
    "gn:gn_country":"ES",
    "gn:gn_fcode":"PPLA3",
    "gn:gn_pop":361,
    "gn:population":361,
    "iso:country":"ES",
    "name:arg_x_preferred":[
        "Villel"
    ],
    "name:ast_x_preferred":[
        "Villel"
    ],
    "name:cat_x_preferred":[
        "Villel"
    ],
    "name:ceb_x_preferred":[
        "Villel"
    ],
    "name:deu_x_preferred":[
        "Villel"
    ],
    "name:eng_x_preferred":[
        "Villel"
    ],
    "name:eus_x_preferred":[
        "Villel"
    ],
    "name:fra_x_preferred":[
        "Villel"
    ],
    "name:hun_x_preferred":[
        "Villel"
    ],
    "name:ita_x_preferred":[
        "Villel"
    ],
    "name:kaz_x_preferred":[
        "\u0412\u0438\u043b\u044c\u0435\u043b\u044c"
    ],
    "name:msa_x_preferred":[
        "Villel"
    ],
    "name:nan_x_preferred":[
        "Villel"
    ],
    "name:nld_x_preferred":[
        "Villel"
    ],
    "name:oci_x_preferred":[
        "Villel"
    ],
    "name:pol_x_preferred":[
        "Villel"
    ],
    "name:por_x_preferred":[
        "Villel"
    ],
    "name:rus_x_preferred":[
        "\u0412\u0438\u043b\u044c\u0435\u043b\u044c"
    ],
    "name:spa_x_preferred":[
        "Villel"
    ],
    "name:swe_x_preferred":[
        "Villel"
    ],
    "name:ukr_x_preferred":[
        "\u0412\u0456\u043b\u044c\u0454\u043b\u044c"
    ],
    "name:uzb_x_preferred":[
        "Villel"
    ],
    "name:vie_x_preferred":[
        "Villel"
    ],
    "name:war_x_preferred":[
        "Villel"
    ],
    "name:zho_x_preferred":[
        "\u6bd4\u5217\u5c14"
    ],
    "qs_pg:aaroncc":"ES",
    "qs_pg:gn_country":"ES",
    "qs_pg:gn_fcode":"PPLA3",
    "qs_pg:gn_pop":361,
    "qs_pg:name":"Villel",
    "qs_pg:name_adm0":"Espa\u00f1a",
    "qs_pg:name_adm1":"Arag\u00f3n",
    "qs_pg:photos":32,
    "qs_pg:photos_1k":6,
    "qs_pg:photos_9k":1,
    "qs_pg:photos_9r":2,
    "qs_pg:photos_all":32,
    "qs_pg:photos_sr":2,
    "qs_pg:pop_sr":2,
    "qs_pg:qs_pg_placetype":"locality",
    "qs_pg:qs_pg_placetype_gp":"Town",
    "qs_pg:woe_adm0":23424950,
    "woe:adm0_id":23424950,
    "woe:name_adm0":"Espa\u00f1a",
    "woe:name_adm1":"Arag\u00f3n",
    "woe:placetype":"Town",
    "wof:name":"Villel",
    "wof:placetype":"locality",
    "wof:population":361
},
  "geometry": {"coordinates":[-1.18611,40.23464],"type":"Point"}
}