{
  "type": "Feature",
  "properties": {
    "gn:admin1_code":"58",
    "gn:admin2_code":"PO",
    "gn:admin3_code":"36020",
    "gn:asciiname":"Artono",
    "gn:country_code":"ES",
    "gn:dem":483,
    "gn:feature_class":"P",
    "gn:feature_code":"PPL",
    "gn:name":"Arto\u00f1o",
    "gn:population":0,
    "gn:timezone":"Europe/Madrid",
    "iso:country":"ES",
    "wof:name":"Artono",
    "wof:placetype":"locality"
},
  "geometry": {"coordinates":[-8.02706,42.81388],"type":"Point"}
}