{
  "type": "Feature",
  "properties": {
    "gn:admin1_code":"39",
    "gn:admin2_code":"S",
    "gn:admin3_code":"39018",
    "gn:asciiname":"Mijarojos",
    "gn:country_code":"ES",
    "gn:dem":83,
    "gn:feature_class":"P",
    "gn:feature_code":"PPL",
    "gn:name":"Mijarojos",
    "gn:population":0,
    "gn:timezone":"Europe/Madrid",
    "iso:country":"ES",
    "wof:name":"Mijarojos",
    "wof:placetype":"locality"
},
  "geometry": {"coordinates":[-4.08121,43.33828],"type":"Point"}
}