{
  "type": "Feature",
  "properties": {
    "gn:admin1_code":"54",
    "gn:admin2_code":"AB",
    "gn:admin3_code":"02019",
    "gn:asciiname":"Los Puercos",
    "gn:cc2":"ES",
    "gn:country_code":"ES",
    "gn:dem":917,
    "gn:feature_class":"P",
    "gn:feature_code":"PPL",
    "gn:name":"Los Puercos",
    "gn:population":0,
    "gn:timezone":"Europe/Madrid",
    "iso:country":"ES",
    "name:und_x_variant":[
        "Caser\u00edo Los Puercos",
        "Los Puercos"
    ],
    "wof:name":"Los Puercos",
    "wof:placetype":"locality"
},
  "geometry": {"coordinates":[-2.65,39.03333],"type":"Point"}
}