{
  "type": "Feature",
  "properties": {
    "gn:gn_country":"ES",
    "gn:gn_fcode":"PPLA3",
    "gn:gn_pop":53,
    "gn:population":53,
    "iso:country":"ES",
    "name:arg_x_preferred":[
        "Zorraqu\u00edn"
    ],
    "name:ast_x_preferred":[
        "Zorraqu\u00edn"
    ],
    "name:cat_x_preferred":[
        "Zorraqu\u00edn"
    ],
    "name:ceb_x_preferred":[
        "Zorraqu\u00edn"
    ],
    "name:eng_x_preferred":[
        "Zorraqu\u00edn"
    ],
    "name:eus_x_preferred":[
        "Zorraqu\u00edn"
    ],
    "name:fra_x_preferred":[
        "Zorraqu\u00edn"
    ],
    "name:hun_x_preferred":[
        "Zorraqu\u00edn"
    ],
    "name:hye_x_preferred":[
        "\u054d\u0578\u057c\u0561\u056f\u056b\u0576"
    ],
    "name:ita_x_preferred":[
        "Zorraqu\u00edn"
    ],
    "name:kaz_x_preferred":[
        "\u0421\u043e\u0440\u0440\u0430\u043a\u0438\u043d"
    ],
    "name:msa_x_preferred":[
        "Zorraqu\u00edn"
    ],
    "name:nan_x_preferred":[
        "Zorraqu\u00edn"
    ],
    "name:nld_x_preferred":[
        "Zorraqu\u00edn"
    ],
    "name:oci_x_preferred":[
        "Zorraqu\u00edn"
    ],
    "name:pol_x_preferred":[
        "Zorraqu\u00edn"
    ],
    "name:por_x_preferred":[
        "Zorraqu\u00edn"
    ],
    "name:rup_x_preferred":[
        "Zorraqu\u00edn"
    ],
    "name:rus_x_preferred":[
        "\u0421\u043e\u0440\u0440\u0430\u043a\u0438\u043d"
    ],
    "name:spa_x_preferred":[
        "Zorraqu\u00edn"
    ],
    "name:swe_x_preferred":[
        "Zorraqu\u00edn"
    ],
    "name:ukr_x_preferred":[
        "\u0421\u043e\u0440\u0440\u0430\u043a\u0456\u043d"
    ],
    "name:vie_x_preferred":[
        "Zorraqu\u00edn"
    ],
    "name:war_x_preferred":[
        "Zorraqu\u00edn"
    ],
    "name:zho_x_preferred":[
        "\u7d22\u62c9\u91d1"
    ],
    "qs_pg:aaroncc":"ES",
    "qs_pg:gn_country":"ES",
    "qs_pg:gn_fcode":"PPLA3",
    "qs_pg:gn_pop":53,
    "qs_pg:name":"Zorraqu\u00edn",
    "qs_pg:name_adm0":"Espa\u00f1a",
    "qs_pg:name_adm1":"La Rioja",
    "qs_pg:photos_9k":1,
    "qs_pg:photos_9r":1,
    "qs_pg:photos_all":4,
    "qs_pg:photos_sr":0,
    "qs_pg:pop_sr":1,
    "qs_pg:qs_pg_placetype":"locality",
    "qs_pg:qs_pg_placetype_gp":"Town",
    "qs_pg:woe_adm0":23424950,
    "woe:adm0_id":23424950,
    "woe:name_adm0":"Espa\u00f1a",
    "woe:name_adm1":"La Rioja",
    "woe:placetype":"Town",
    "wof:name":"Zorraqu\u00edn",
    "wof:placetype":"locality",
    "wof:population":53
},
  "geometry": {"coordinates":[-3.03925,42.32565],"type":"Point"}
}