{
  "type": "Feature",
  "properties": {
    "gn:admin1_code":"55",
    "gn:admin2_code":"AV",
    "gn:admin3_code":"05097",
    "gn:asciiname":"La Horcajada",
    "gn:country_code":"ES",
    "gn:dem":1018,
    "gn:feature_class":"P",
    "gn:feature_code":"PPL",
    "gn:name":"La Horcajada",
    "gn:population":678,
    "gn:timezone":"Europe/Madrid",
    "iso:country":"ES",
    "name:ara_x_preferred":[
        "\u0644\u0627 \u0623\u0648\u0631\u0643\u0627\u062e\u0627\u062f\u0627"
    ],
    "name:azb_x_preferred":[
        "\u0644\u0627 \u0647\u0631\u06a9\u0627\u062e\u0627\u062f\u0627"
    ],
    "name:cat_x_preferred":[
        "La Horcajada"
    ],
    "name:ceb_x_preferred":[
        "La Horcajada"
    ],
    "name:eus_x_preferred":[
        "La Horcajada"
    ],
    "name:fas_x_preferred":[
        "\u0644\u0627 \u0647\u0631\u06a9\u0627\u062e\u0627\u062f\u0627"
    ],
    "name:fra_x_preferred":[
        "La Horcajada"
    ],
    "name:hun_x_preferred":[
        "La Horcajada"
    ],
    "name:ina_x_preferred":[
        "La Horcajada"
    ],
    "name:ita_x_preferred":[
        "La Horcajada"
    ],
    "name:kaz_x_preferred":[
        "\u041b\u0430-\u041e\u0440\u043a\u0430\u0445\u0430\u0434\u0430"
    ],
    "name:mkd_x_preferred":[
        "\u041b\u0430 \u041e\u0440\u043a\u0430\u0445\u0430\u0434\u0430"
    ],
    "name:msa_x_preferred":[
        "La Horcajada"
    ],
    "name:nld_x_preferred":[
        "La Horcajada"
    ],
    "name:oci_x_preferred":[
        "La Horcajada"
    ],
    "name:pol_x_preferred":[
        "La Horcajada"
    ],
    "name:por_x_preferred":[
        "La Horcajada"
    ],
    "name:rus_x_preferred":[
        "\u041b\u0430-\u041e\u0440\u043a\u0430\u0445\u0430\u0434\u0430"
    ],
    "name:spa_x_preferred":[
        "La Horcajada"
    ],
    "name:swe_x_preferred":[
        "La Horcajada"
    ],
    "name:ukr_x_preferred":[
        "\u041b\u0430-\u041e\u0440\u043a\u0430\u0445\u0430\u0434\u0430"
    ],
    "name:uzb_x_preferred":[
        "La Horcajada"
    ],
    "name:vie_x_preferred":[
        "La Horcajada"
    ],
    "name:war_x_preferred":[
        "La Horcajada"
    ],
    "name:zho_x_preferred":[
        "\u62c9\u5965\u5c14\u5361\u54c8\u8fbe"
    ],
    "wof:name":"La Horcajada",
    "wof:placetype":"locality",
    "wof:population":678
},
  "geometry": {"coordinates":[-5.46615,40.43674],"type":"Point"}
}