{
  "type": "Feature",
  "properties": {
    "gn:admin1_code":"58",
    "gn:admin2_code":"LU",
    "gn:admin3_code":"27062",
    "gn:asciiname":"Queijadoiro",
    "gn:country_code":"ES",
    "gn:dem":1099,
    "gn:feature_class":"P",
    "gn:feature_code":"PPL",
    "gn:name":"Queijadoiro",
    "gn:population":0,
    "gn:timezone":"Europe/Madrid",
    "iso:country":"ES",
    "wof:name":"Queijadoiro",
    "wof:placetype":"locality"
},
  "geometry": {"coordinates":[-7.18676,42.73033],"type":"Point"}
}