{
  "type": "Feature",
  "properties": {
    "iso:country":"ES",
    "name:cat_x_variant":[
        "Poblats del Nord"
    ],
    "name:spa_x_preferred":[
        "Poblados del Norte"
    ],
    "wof:name":"Pobles del Nord",
    "wof:placetype":"neighbourhood"
},
  "geometry": {"coordinates":[-0.38583876967911,39.51579358875343],"type":"Point"}
}