{
  "type": "Feature",
  "properties": {
    "gn:admin1_code":"60",
    "gn:admin2_code":"V",
    "gn:admin3_code":"46254",
    "gn:asciiname":"Casas de Pradas",
    "gn:country_code":"ES",
    "gn:dem":693,
    "gn:feature_class":"P",
    "gn:feature_code":"PPL",
    "gn:name":"Casas de Pradas",
    "gn:population":0,
    "gn:timezone":"Europe/Madrid",
    "iso:country":"ES",
    "wof:name":"Casas de Pradas",
    "wof:placetype":"locality"
},
  "geometry": {"coordinates":[-1.33333,39.45],"type":"Point"}
}