{
  "type": "Feature",
  "properties": {
    "gn:country":"ES",
    "gn:fcode":"PPLA3",
    "gn:population":486,
    "iso:country":"ES",
    "name:ara_x_preferred":[
        "\u0641\u064a\u0644\u0627\u0643\u0648\u0646\u064a\u062e\u0648\u0633 \u062f\u064a \u062a\u0631\u0627\u0628\u0627\u062c\u064a"
    ],
    "name:arg_x_preferred":[
        "Villaconejos de Trabac"
    ],
    "name:cat_x_preferred":[
        "Villaconejos de Trabaque"
    ],
    "name:eng_x_preferred":[
        "Villaconejos de Trabaque"
    ],
    "name:eus_x_preferred":[
        "Villaconejos de Trabaque"
    ],
    "name:fra_x_preferred":[
        "Villaconejos de Trabaque"
    ],
    "name:hun_x_preferred":[
        "Villaconejos de Trabaque"
    ],
    "name:ita_x_preferred":[
        "Villaconejos de Trabaque"
    ],
    "name:kaz_x_preferred":[
        "\u0412\u0438\u043b\u044c\u044f\u043a\u043e\u043d\u0435\u0445\u043e\u0441-\u0434\u0435-\u0422\u0440\u0430\u0431\u0430\u043a\u0435"
    ],
    "name:msa_x_preferred":[
        "Villaconejos de Trabaque"
    ],
    "name:nan_x_preferred":[
        "Villaconejos de Trabaque"
    ],
    "name:nld_x_preferred":[
        "Villaconejos de Trabaque"
    ],
    "name:oci_x_preferred":[
        "Villaconejos de Trabaque"
    ],
    "name:pol_x_preferred":[
        "Villaconejos de Trabaque"
    ],
    "name:por_x_preferred":[
        "Villaconejos de Trabaque"
    ],
    "name:rus_x_preferred":[
        "\u0412\u0438\u043b\u044c\u044f\u043a\u043e\u043d\u0435\u0445\u043e\u0441-\u0434\u0435-\u0422\u0440\u0430\u0431\u0430\u043a\u0435"
    ],
    "name:spa_x_preferred":[
        "Villaconejos de Trabaque"
    ],
    "name:swe_x_preferred":[
        "Villaconejos de Trabaque"
    ],
    "name:ukr_x_preferred":[
        "\u0412\u0456\u043b\u044c\u044f\u043a\u043e\u043d\u0435\u0445\u043e\u0441-\u0434\u0435-\u0422\u0440\u0430\u0431\u0430\u043a\u0435"
    ],
    "name:und_x_variant":[
        "Villaconejos"
    ],
    "name:vie_x_preferred":[
        "Villaconejos de Trabaque"
    ],
    "name:war_x_preferred":[
        "Villaconejos de Trabaque"
    ],
    "name:zho_x_preferred":[
        "\u6bd4\u5229\u4e9a\u79d1\u5185\u970d\u65af\u5fb7\u7279\u62c9\u74e6\u514b"
    ],
    "qs_pg:aaroncc":"ES",
    "qs_pg:gn_country":"ES",
    "qs_pg:gn_fcode":"PPLA3",
    "qs_pg:gn_pop":486,
    "qs_pg:name":"Villaconejos de Trabaque",
    "qs_pg:photos_9r":0,
    "qs_pg:photos_sr":0,
    "qs_pg:pop_sr":2,
    "qs_pg:qs_pg_placetype":"locality",
    "wof:name":"Villaconejos de Trabaque",
    "wof:placetype":"locality",
    "wof:population":486
},
  "geometry": {"coordinates":[-2.31956,40.40064],"type":"Point"}
}