{
  "type": "Feature",
  "properties": {
    "gn:admin1_code":"55",
    "gn:admin2_code":"ZA",
    "gn:admin3_code":"49069",
    "gn:asciiname":"Villarino de Manzanas",
    "gn:country_code":"ES",
    "gn:dem":666,
    "gn:feature_class":"P",
    "gn:feature_code":"PPL",
    "gn:name":"Villarino de Manzanas",
    "gn:population":0,
    "gn:timezone":"Europe/Madrid",
    "iso:country":"ES",
    "wof:name":"Villarino de Manzanas",
    "wof:placetype":"locality"
},
  "geometry": {"coordinates":[-6.49929,41.88002],"type":"Point"}
}