{
  "type": "Feature",
  "properties": {
    "gn:admin1_code":"07",
    "gn:admin2_code":"PM",
    "gn:admin3_code":"07031",
    "gn:asciiname":"Son Veri Nou",
    "gn:country_code":"ES",
    "gn:dem":21,
    "gn:feature_class":"P",
    "gn:feature_code":"PPL",
    "gn:name":"Son Ver\u00ed Nou",
    "gn:population":0,
    "gn:timezone":"Europe/Madrid",
    "iso:country":"ES",
    "name:cat_x_preferred":[
        "Son Ver\u00ed"
    ],
    "name:deu_x_preferred":[
        "Son Ver\u00ed"
    ],
    "name:eng_x_preferred":[
        "Son Ver\u00ed"
    ],
    "name:spa_x_preferred":[
        "Son Ver\u00ed"
    ],
    "wof:name":"Son Veri Nou",
    "wof:placetype":"locality"
},
  "geometry": {"coordinates":[2.74105,39.49192],"type":"Point"}
}