{
  "type": "Feature",
  "properties": {
    "gn:admin1_code":"58",
    "gn:admin2_code":"OR",
    "gn:admin3_code":"32074",
    "gn:asciiname":"Salamonde",
    "gn:cc2":"ES",
    "gn:country_code":"ES",
    "gn:dem":383,
    "gn:feature_class":"P",
    "gn:feature_code":"PPL",
    "gn:name":"Salamonde",
    "gn:population":0,
    "gn:timezone":"Europe/Madrid",
    "iso:country":"ES",
    "name:und_x_variant":[
        "Santa Mar\u00eda",
        "Salamonde"
    ],
    "wof:name":"Salamonde",
    "wof:placetype":"locality"
},
  "geometry": {"coordinates":[-8.03333,42.36667],"type":"Point"}
}