{
  "type": "Feature",
  "properties": {
    "gn:admin1_code":"51",
    "gn:admin2_code":"J",
    "gn:admin3_code":"23039",
    "gn:asciiname":"Zocueca",
    "gn:country_code":"ES",
    "gn:dem":269,
    "gn:feature_class":"P",
    "gn:feature_code":"PPL",
    "gn:name":"Zocueca",
    "gn:population":0,
    "gn:timezone":"Europe/Madrid",
    "iso:country":"ES",
    "wof:name":"Zocueca",
    "wof:placetype":"locality"
},
  "geometry": {"coordinates":[-3.83645,38.09094],"type":"Point"}
}