{
  "type": "Feature",
  "properties": {
    "gn:admin1_code":"52",
    "gn:admin2_code":"HU",
    "gn:admin3_code":"22109",
    "gn:asciiname":"Campol",
    "gn:country_code":"ES",
    "gn:dem":1028,
    "gn:feature_class":"P",
    "gn:feature_code":"PPL",
    "gn:name":"Campol",
    "gn:population":0,
    "gn:timezone":"Europe/Madrid",
    "iso:country":"ES",
    "wof:name":"Campol",
    "wof:placetype":"locality"
},
  "geometry": {"coordinates":[-0.0097,42.49833],"type":"Point"}
}