{
  "type": "Feature",
  "properties": {
    "gn:admin1_code":"58",
    "gn:admin2_code":"OR",
    "gn:admin3_code":"32011",
    "gn:asciiname":"Lebozan",
    "gn:country_code":"ES",
    "gn:dem":792,
    "gn:feature_class":"P",
    "gn:feature_code":"PPL",
    "gn:name":"Leboz\u00e1n",
    "gn:population":0,
    "gn:timezone":"Europe/Madrid",
    "iso:country":"ES",
    "name:und_x_variant":[
        "Leboz\u00e1n"
    ],
    "wof:name":"Lebozan",
    "wof:placetype":"locality"
},
  "geometry": {"coordinates":[-8.25,42.48333],"type":"Point"}
}