{
  "type": "Feature",
  "properties": {
    "gn:country":"ES",
    "gn:fcode":"PPL",
    "gn:population":0,
    "iso:country":"ES",
    "name:cat_x_preferred":[
        "l'Arrac\u00f3"
    ],
    "name:cat_x_variant":[
        "s'Arrac\u00f3"
    ],
    "name:deu_x_preferred":[
        "s'Arrac\u00f3"
    ],
    "name:eng_x_preferred":[
        "s'Arrac\u00f3"
    ],
    "name:spa_x_preferred":[
        "s'Arrac\u00f3"
    ],
    "qs_pg:aaroncc":"ES",
    "qs_pg:gn_country":"ES",
    "qs_pg:gn_fcode":"PPL",
    "qs_pg:gn_pop":0,
    "qs_pg:name":"S'Arrac\u00f3",
    "qs_pg:name_adm0":"Espa\u00f1a",
    "qs_pg:name_adm1":"Illes Balears",
    "qs_pg:photos_9r":0,
    "qs_pg:photos_sr":0,
    "qs_pg:pop_sr":0,
    "qs_pg:qs_pg_placetype":"locality",
    "qs_pg:qs_pg_placetype_gp":"Town",
    "qs_pg:woe_adm0":23424950,
    "woe:adm0_id":23424950,
    "woe:name_adm0":"Espa\u00f1a",
    "woe:name_adm1":"Illes Balears",
    "woe:placetype":"Town",
    "wof:name":"S'Arrac\u00f3",
    "wof:placetype":"locality"
},
  "geometry": {"coordinates":[2.39266,39.57817],"type":"Point"}
}