{
  "type": "Feature",
  "properties": {
    "gn:admin1_code":"39",
    "gn:admin2_code":"S",
    "gn:admin3_code":"39039",
    "gn:asciiname":"Urdiales",
    "gn:country_code":"ES",
    "gn:dem":674,
    "gn:feature_class":"P",
    "gn:feature_code":"PPL",
    "gn:name":"Urdiales",
    "gn:population":0,
    "gn:timezone":"Europe/Madrid",
    "iso:country":"ES",
    "wof:name":"Urdiales",
    "wof:placetype":"locality"
},
  "geometry": {"coordinates":[-3.92147,43.12644],"type":"Point"}
}