{
  "type": "Feature",
  "properties": {
    "gn:admin1_code":"58",
    "gn:admin2_code":"OR",
    "gn:admin3_code":"32012",
    "gn:asciiname":"Cobelas",
    "gn:country_code":"ES",
    "gn:dem":811,
    "gn:feature_class":"P",
    "gn:feature_code":"PPL",
    "gn:name":"Cobelas",
    "gn:population":0,
    "gn:timezone":"Europe/Madrid",
    "iso:country":"ES",
    "wof:name":"Cobelas",
    "wof:placetype":"locality"
},
  "geometry": {"coordinates":[-7.72271,42.00185],"type":"Point"}
}