{
  "type": "Feature",
  "properties": {
    "iso:country":"ES",
    "name:spa_x_preferred":[
        "Barrio del Naranjo"
    ],
    "name:spa_x_variant":[
        "Barrio del Naranjo"
    ],
    "qs:gn_adm0_cc":"ES",
    "qs:gn_local":0,
    "qs:gn_nam_loc":"C\u00f3rdoba, C\u00f3rdoba, C\u00f3rdoba, Andaluc\u00eda, ES",
    "qs:gn_namadm1":"51",
    "qs:local_max":18851,
    "qs:local_sum":52543,
    "qs:localhoods":32,
    "qs:name":"Barrio del Naranjo",
    "qs:name_adm0":"Espa\u00f1a",
    "qs:name_adm1":"Andaluc\u00eda",
    "qs:name_adm2":"C\u00f3rdoba",
    "qs:name_lau":"C\u00f3rdoba",
    "qs:name_local":"C\u00f3rdoba",
    "qs:photo_max":5,
    "qs:photo_sum":6,
    "qs:placetype":"Suburb",
    "qs:quad_count":2,
    "qs:woe_adm0":23424950,
    "qs:woe_adm1":12578029,
    "qs:woe_adm2":12602098,
    "qs:woe_lau":12688792,
    "qs:woe_local":758007,
    "qs:woe_ver":"7.10.0",
    "wof:lang":[
        "spa"
    ],
    "wof:name":"El Naranjo",
    "wof:placetype":"neighbourhood"
},
  "geometry": {"coordinates":[-4.777603,37.908392],"type":"Point"}
}