{
  "type": "Feature",
  "properties": {
    "gn:admin1_code":"53",
    "gn:admin2_code":"GC",
    "gn:admin3_code":"35025",
    "gn:asciiname":"Guardaya",
    "gn:country_code":"ES",
    "gn:dem":1112,
    "gn:feature_class":"P",
    "gn:feature_code":"PPL",
    "gn:name":"Guardaya",
    "gn:population":0,
    "gn:timezone":"Atlantic/Canary",
    "iso:country":"ES",
    "wof:name":"Guardaya",
    "wof:placetype":"locality"
},
  "geometry": {"coordinates":[-15.6139,28.0045],"type":"Point"}
}