{
  "type": "Feature",
  "properties": {
    "gn:admin1_code":"58",
    "gn:admin2_code":"OR",
    "gn:admin3_code":"32059",
    "gn:asciiname":"Orban",
    "gn:cc2":"ES",
    "gn:country_code":"ES",
    "gn:dem":613,
    "gn:feature_class":"P",
    "gn:feature_code":"PPL",
    "gn:name":"Orb\u00e1n",
    "gn:population":0,
    "gn:timezone":"Europe/Madrid",
    "iso:country":"ES",
    "name:ben_x_preferred":[
        "\u0989\u09b0\u09ac\u09be\u09a8"
    ],
    "name:fra_x_preferred":[
        "Urbain"
    ],
    "name:heb_x_preferred":[
        "\u05d0\u05d5\u05e8\u05d1\u05d0\u05df"
    ],
    "name:hrv_x_preferred":[
        "Orban"
    ],
    "name:ita_x_preferred":[
        "Urban"
    ],
    "name:jpn_x_preferred":[
        "\u30a6\u30eb\u30d0\u30f3"
    ],
    "name:mlg_x_preferred":[
        "Urbain"
    ],
    "name:ron_x_preferred":[
        "Orban"
    ],
    "name:rus_x_preferred":[
        "\u0423\u0440\u0431\u0430\u043d"
    ],
    "name:slv_x_preferred":[
        "Orban"
    ],
    "name:spa_x_preferred":[
        "Orb\u00f3n"
    ],
    "name:tur_x_preferred":[
        "Urban"
    ],
    "name:ukr_x_preferred":[
        "\u0423\u0440\u0431\u0430\u043d"
    ],
    "name:und_x_variant":[
        "Santa Mar\u00eda",
        "Orb\u00e1n"
    ],
    "wof:name":"Orban",
    "wof:placetype":"locality"
},
  "geometry": {"coordinates":[-7.83333,42.48333],"type":"Point"}
}