{
  "type": "Feature",
  "properties": {
    "gn:admin1_code":"55",
    "gn:admin2_code":"ZA",
    "gn:admin3_code":"49097",
    "gn:asciiname":"Quintanilla",
    "gn:country_code":"ES",
    "gn:dem":935,
    "gn:feature_class":"P",
    "gn:feature_code":"PPL",
    "gn:name":"Quintanilla",
    "gn:population":0,
    "gn:timezone":"Europe/Madrid",
    "iso:country":"ES",
    "wof:name":"Quintanilla",
    "wof:placetype":"locality"
},
  "geometry": {"coordinates":[-6.27853,42.15308],"type":"Point"}
}