{
  "type": "Feature",
  "properties": {
    "gn:admin1_code":"59",
    "gn:admin2_code":"BI",
    "gn:admin3_code":"48907",
    "gn:asciiname":"Terleguiz",
    "gn:country_code":"ES",
    "gn:dem":39,
    "gn:feature_class":"P",
    "gn:feature_code":"PPL",
    "gn:name":"Terlegiz",
    "gn:population":0,
    "gn:timezone":"Europe/Madrid",
    "iso:country":"ES",
    "wof:name":"Terleguiz",
    "wof:placetype":"locality"
},
  "geometry": {"coordinates":[-2.64305,43.33723],"type":"Point"}
}