{
  "type": "Feature",
  "properties": {
    "gn:admin1_code":"55",
    "gn:admin2_code":"ZA",
    "gn:admin3_code":"49128",
    "gn:asciiname":"Vecilla de la Polvorosa",
    "gn:country_code":"ES",
    "gn:dem":723,
    "gn:feature_class":"P",
    "gn:feature_code":"PPL",
    "gn:name":"Vecilla de la Polvorosa",
    "gn:population":0,
    "gn:timezone":"Europe/Madrid",
    "iso:country":"ES",
    "wof:name":"Vecilla de la Polvorosa",
    "wof:placetype":"locality"
},
  "geometry": {"coordinates":[-5.75085,42.07154],"type":"Point"}
}