{
  "type": "Feature",
  "properties": {
    "gn:admin1_code":"52",
    "gn:admin2_code":"HU",
    "gn:admin3_code":"22066",
    "gn:asciiname":"Matidero",
    "gn:country_code":"ES",
    "gn:dem":1202,
    "gn:feature_class":"P",
    "gn:feature_code":"PPL",
    "gn:name":"Matidero",
    "gn:population":0,
    "gn:timezone":"Europe/Madrid",
    "iso:country":"ES",
    "wof:name":"Matidero",
    "wof:placetype":"locality"
},
  "geometry": {"coordinates":[-0.08836,42.39538],"type":"Point"}
}