{
  "type": "Feature",
  "properties": {
    "gn:admin1_code":"34",
    "gn:admin2_code":"O",
    "gn:admin3_code":"33005",
    "gn:asciiname":"Cuevas",
    "gn:country_code":"ES",
    "gn:dem":500,
    "gn:feature_class":"P",
    "gn:feature_code":"PPL",
    "gn:name":"Cuevas",
    "gn:population":0,
    "gn:timezone":"Europe/Madrid",
    "iso:country":"ES",
    "wof:name":"Cuevas",
    "wof:placetype":"locality"
},
  "geometry": {"coordinates":[-6.30643,43.1868],"type":"Point"}
}