{
  "type": "Feature",
  "properties": {
    "gn:admin1_code":"59",
    "gn:admin2_code":"BI",
    "gn:admin3_code":"48910",
    "gn:asciiname":"San Fausto",
    "gn:country_code":"ES",
    "gn:dem":193,
    "gn:feature_class":"P",
    "gn:feature_code":"PPL",
    "gn:name":"Fauste",
    "gn:population":0,
    "gn:timezone":"Europe/Madrid",
    "iso:country":"ES",
    "wof:name":"San Fausto",
    "wof:placetype":"locality"
},
  "geometry": {"coordinates":[-2.66481,43.19286],"type":"Point"}
}