{
  "type": "Feature",
  "properties": {
    "gn:admin1_code":"32",
    "gn:admin3_code":"31248",
    "gn:asciiname":"Archurieta",
    "gn:country_code":"ES",
    "gn:dem":437,
    "gn:feature_class":"P",
    "gn:feature_code":"PPL",
    "gn:name":"Archurieta",
    "gn:population":0,
    "gn:timezone":"Europe/Madrid",
    "iso:country":"ES",
    "name:und_x_variant":[
        "Caser\u00edo de Archurieta",
        "Archurieta"
    ],
    "wof:name":"Archurieta",
    "wof:placetype":"locality"
},
  "geometry": {"coordinates":[-1.30843,43.07465],"type":"Point"}
}