{
  "type": "Feature",
  "properties": {
    "gn:gn_country":"ES",
    "gn:gn_fcode":"PPLA3",
    "gn:gn_pop":583,
    "gn:population":583,
    "iso:country":"ES",
    "name:alb_x_preferred":[
        "Benimuslem"
    ],
    "name:arg_x_preferred":[
        "Benimuslem"
    ],
    "name:baq_x_preferred":[
        "Benimuslem"
    ],
    "name:cat_x_preferred":[
        "Benimuslem"
    ],
    "name:chi_x_preferred":[
        "\u8d1d\u5c3c\u7a46\u65af\u83b1\u59c6"
    ],
    "name:dut_x_preferred":[
        "Benimuslem"
    ],
    "name:eng_x_preferred":[
        "Benimuslem"
    ],
    "name:fre_x_preferred":[
        "Benimuslem"
    ],
    "name:ger_x_preferred":[
        "Benimuslem"
    ],
    "name:hun_x_preferred":[
        "Benimuslem"
    ],
    "name:ita_x_preferred":[
        "Benimuslem"
    ],
    "name:may_x_preferred":[
        "Benimuslem"
    ],
    "name:nan_x_preferred":[
        "Benimuslem"
    ],
    "name:oci_x_preferred":[
        "Benimuslem"
    ],
    "name:per_x_preferred":[
        "\u0628\u0646\u06cc\u0645\u0648\u0633\u0644\u0645"
    ],
    "name:pol_x_preferred":[
        "Benimuslem"
    ],
    "name:rup_x_preferred":[
        "Benimuslem"
    ],
    "name:rus_x_preferred":[
        "\u0411\u0435\u043d\u0438\u043c\u0443\u0441\u043b\u0435\u043c"
    ],
    "name:spa_x_preferred":[
        "Benimuslem"
    ],
    "name:swe_x_preferred":[
        "Benimuslem"
    ],
    "name:ukr_x_preferred":[
        "\u0411\u0435\u043d\u0456\u043c\u0443\u0441\u043b\u0435\u043c"
    ],
    "name:vie_x_preferred":[
        "Benimuslem"
    ],
    "name:war_x_preferred":[
        "Benimuslem"
    ],
    "qs_pg:aaroncc":"ES",
    "qs_pg:gn_country":"ES",
    "qs_pg:gn_fcode":"PPLA3",
    "qs_pg:gn_pop":583,
    "qs_pg:name":"Benimuslem",
    "qs_pg:name_adm0":"Espa\u00f1a",
    "qs_pg:name_adm1":"Comunitat Valenciana",
    "qs_pg:photos_9r":0,
    "qs_pg:photos_sr":0,
    "qs_pg:pop_sr":2,
    "qs_pg:qs_pg_placetype":"locality",
    "qs_pg:qs_pg_placetype_gp":"Town",
    "qs_pg:woe_adm0":23424950,
    "woe:adm0_id":23424950,
    "woe:name_adm0":"Espa\u00f1a",
    "woe:name_adm1":"Comunitat Valenciana",
    "woe:placetype":"Town",
    "wof:name":"Benimuslem",
    "wof:placetype":"locality",
    "wof:population":583
},
  "geometry": {"coordinates":[-0.49288,39.13162],"type":"Point"}
}