{
  "type": "Feature",
  "properties": {
    "gn:admin1_code":"56",
    "gn:admin2_code":"GI",
    "gn:admin3_code":"17218",
    "gn:asciiname":"San Esteban de Guialbes",
    "gn:country_code":"ES",
    "gn:dem":182,
    "gn:feature_class":"P",
    "gn:feature_code":"PPL",
    "gn:name":"San Esteban de Guialbes",
    "gn:population":0,
    "gn:timezone":"Europe/Madrid",
    "iso:country":"ES",
    "wof:name":"San Esteban de Guialbes",
    "wof:placetype":"locality"
},
  "geometry": {"coordinates":[2.87777,42.11531],"type":"Point"}
}