{
  "type": "Feature",
  "properties": {
    "gn:country":"ES",
    "gn:fcode":"PPL",
    "gn:population":58,
    "iso:country":"ES",
    "name:arg_x_preferred":[
        "Aldehorno"
    ],
    "name:ast_x_preferred":[
        "Aldehorno"
    ],
    "name:bul_x_preferred":[
        "\u0410\u043b\u0434\u0435\u0445\u043e\u0440\u043d\u043e"
    ],
    "name:cat_x_preferred":[
        "Aldehorno"
    ],
    "name:ceb_x_preferred":[
        "Aldehorno"
    ],
    "name:eng_x_preferred":[
        "Aldehorno"
    ],
    "name:eus_x_preferred":[
        "Aldehorno"
    ],
    "name:fas_x_preferred":[
        "\u0627\u0644\u062f\u06cc\u0647\u0648\u0631\u0646\u0648"
    ],
    "name:fra_x_preferred":[
        "Aldehorno"
    ],
    "name:hun_x_preferred":[
        "Aldehorno"
    ],
    "name:ina_x_preferred":[
        "Aldehorno"
    ],
    "name:ita_x_preferred":[
        "Aldehorno"
    ],
    "name:msa_x_preferred":[
        "Aldehorno"
    ],
    "name:nan_x_preferred":[
        "Aldehorno"
    ],
    "name:nld_x_preferred":[
        "Aldehorno"
    ],
    "name:oci_x_preferred":[
        "Aldehorno"
    ],
    "name:pol_x_preferred":[
        "Aldehorno"
    ],
    "name:por_x_preferred":[
        "Aldehorno"
    ],
    "name:rup_x_preferred":[
        "Aldehorno"
    ],
    "name:rus_x_preferred":[
        "\u0410\u043b\u044c\u0434\u0435\u043e\u0440\u043d\u043e"
    ],
    "name:spa_x_preferred":[
        "Aldehorno"
    ],
    "name:swe_x_preferred":[
        "Aldehorno"
    ],
    "name:ukr_x_preferred":[
        "\u0410\u043b\u044c\u0434\u0435\u043e\u0440\u043d\u043e"
    ],
    "name:vie_x_preferred":[
        "Aldehorno"
    ],
    "name:war_x_preferred":[
        "Aldehorno"
    ],
    "name:zho_x_preferred":[
        "\u963f\u5c14\u5fb7\u5965\u5c14\u8bfa"
    ],
    "qs_pg:aaroncc":"ES",
    "qs_pg:gn_country":"ES",
    "qs_pg:gn_fcode":"PPL",
    "qs_pg:gn_pop":58,
    "qs_pg:name":"Aldehorno",
    "qs_pg:photos_9r":0,
    "qs_pg:photos_sr":0,
    "qs_pg:pop_sr":1,
    "qs_pg:qs_pg_placetype":"locality",
    "wof:name":"Aldehorno",
    "wof:placetype":"locality",
    "wof:population":58
},
  "geometry": {"coordinates":[-3.77822,41.51275],"type":"Point"}
}