{
  "type": "Feature",
  "properties": {
    "gn:admin1_code":"52",
    "gn:admin2_code":"TE",
    "gn:admin3_code":"44071",
    "gn:asciiname":"Los Alagones",
    "gn:country_code":"ES",
    "gn:dem":760,
    "gn:feature_class":"P",
    "gn:feature_code":"PPL",
    "gn:name":"Los Alagones",
    "gn:population":0,
    "gn:timezone":"Europe/Madrid",
    "iso:country":"ES",
    "name:und_x_variant":[
        "Caser\u00edo Los Alagones",
        "Los Alagones"
    ],
    "wof:name":"Los Alagones",
    "wof:placetype":"locality"
},
  "geometry": {"coordinates":[-0.30612,40.72346],"type":"Point"}
}