{
  "type": "Feature",
  "properties": {
    "gn:admin1_code":"55",
    "gn:admin2_code":"BU",
    "gn:admin3_code":"09908",
    "gn:asciiname":"Lastras de Teza",
    "gn:country_code":"ES",
    "gn:dem":669,
    "gn:feature_class":"P",
    "gn:feature_code":"PPL",
    "gn:name":"Lastras de Teza",
    "gn:population":0,
    "gn:timezone":"Europe/Madrid",
    "iso:country":"ES",
    "wof:name":"Lastras de Teza",
    "wof:placetype":"locality"
},
  "geometry": {"coordinates":[-3.21224,42.97605],"type":"Point"}
}