{
  "type": "Feature",
  "properties": {
    "gn:admin1_code":"29",
    "gn:admin2_code":"M",
    "gn:admin3_code":"28072",
    "gn:asciiname":"El Berzalejo",
    "gn:country_code":"ES",
    "gn:dem":928,
    "gn:feature_class":"P",
    "gn:feature_code":"PPL",
    "gn:name":"El Berzalejo",
    "gn:population":0,
    "gn:timezone":"Europe/Madrid",
    "iso:country":"ES",
    "wof:name":"El Berzalejo",
    "wof:placetype":"locality"
},
  "geometry": {"coordinates":[-3.9101,40.60053],"type":"Point"}
}