{
  "type": "Feature",
  "properties": {
    "gn:admin1_code":"55",
    "gn:admin2_code":"BU",
    "gn:admin3_code":"09215",
    "gn:asciiname":"Pereda",
    "gn:country_code":"ES",
    "gn:dem":674,
    "gn:feature_class":"P",
    "gn:feature_code":"PPL",
    "gn:name":"Pereda",
    "gn:population":0,
    "gn:timezone":"Europe/Madrid",
    "iso:country":"ES",
    "wof:name":"Pereda",
    "wof:placetype":"locality"
},
  "geometry": {"coordinates":[-3.57571,43.01532],"type":"Point"}
}