{
  "type": "Feature",
  "properties": {
    "gn:gn_country":"ES",
    "gn:gn_fcode":"PPLA3",
    "gn:gn_pop":865,
    "gn:population":865,
    "iso:country":"ES",
    "name:ara_x_preferred":[
        "\u0623\u0648\u0647\u0627\u0646\u0633"
    ],
    "name:arm_x_preferred":[
        "\u0555\u0561\u0576\u0565\u057d"
    ],
    "name:baq_x_preferred":[
        "Ohanes"
    ],
    "name:cat_x_preferred":[
        "Ohanes"
    ],
    "name:chi_x_preferred":[
        "\u5965\u963f\u5185\u65af"
    ],
    "name:dut_x_preferred":[
        "Ohanes"
    ],
    "name:eng_x_preferred":[
        "Ohanes"
    ],
    "name:epo_x_preferred":[
        "Ohanes"
    ],
    "name:fre_x_preferred":[
        "Ohanes"
    ],
    "name:hat_x_preferred":[
        "Ohanes"
    ],
    "name:hun_x_preferred":[
        "Ohanes"
    ],
    "name:ina_x_preferred":[
        "Ohanes"
    ],
    "name:ita_x_preferred":[
        "Ohanes"
    ],
    "name:mac_x_preferred":[
        "\u041e\u0445\u0430\u043d\u0435\u0441"
    ],
    "name:may_x_preferred":[
        "Ohanes"
    ],
    "name:nan_x_preferred":[
        "Ohanes"
    ],
    "name:oci_x_preferred":[
        "Ohanes"
    ],
    "name:per_x_preferred":[
        "\u0627\u0647\u0627\u0646\u0633"
    ],
    "name:pol_x_preferred":[
        "Ohanes"
    ],
    "name:rum_x_preferred":[
        "Ohanes"
    ],
    "name:rus_x_preferred":[
        "\u041e\u0430\u043d\u0435\u0441"
    ],
    "name:spa_x_preferred":[
        "Ohanes"
    ],
    "name:swe_x_preferred":[
        "Ohanes"
    ],
    "name:tur_x_preferred":[
        "Ohanes"
    ],
    "name:ukr_x_preferred":[
        "\u041e\u0430\u043d\u0435\u0441"
    ],
    "name:uzb_x_preferred":[
        "Ohanes"
    ],
    "name:vie_x_preferred":[
        "Ohanes"
    ],
    "name:war_x_preferred":[
        "Ohanes"
    ],
    "qs_pg:aaroncc":"ES",
    "qs_pg:gn_country":"ES",
    "qs_pg:gn_fcode":"PPLA3",
    "qs_pg:gn_pop":865,
    "qs_pg:name":"Ohanes",
    "qs_pg:name_adm0":"Espa\u00f1a",
    "qs_pg:name_adm1":"Andaluc\u00eda",
    "qs_pg:photos":151,
    "qs_pg:photos_1k":31,
    "qs_pg:photos_9k":1,
    "qs_pg:photos_9r":4,
    "qs_pg:photos_all":151,
    "qs_pg:photos_sr":4,
    "qs_pg:pop_sr":2,
    "qs_pg:qs_pg_placetype":"locality",
    "qs_pg:qs_pg_placetype_gp":"Town",
    "qs_pg:woe_adm0":23424950,
    "woe:adm0_id":23424950,
    "woe:name_adm0":"Espa\u00f1a",
    "woe:name_adm1":"Andaluc\u00eda",
    "woe:placetype":"Town",
    "wof:name":"Ohanes",
    "wof:placetype":"locality",
    "wof:population":865
},
  "geometry": {"coordinates":[-2.74524,37.03861],"type":"Point"}
}