{
  "type": "Feature",
  "properties": {
    "gn:admin1_code":"58",
    "gn:admin2_code":"C",
    "gn:admin3_code":"15062",
    "gn:asciiname":"Cuns",
    "gn:country_code":"ES",
    "gn:dem":156,
    "gn:feature_class":"P",
    "gn:feature_code":"PPL",
    "gn:name":"Cuns",
    "gn:population":0,
    "gn:timezone":"Europe/Madrid",
    "iso:country":"ES",
    "wof:name":"Cuns",
    "wof:placetype":"locality"
},
  "geometry": {"coordinates":[-8.86875,42.85633],"type":"Point"}
}