{
  "type": "Feature",
  "properties": {
    "gn:gn_country":"ES",
    "gn:gn_fcode":"PPLA3",
    "gn:gn_pop":70,
    "gn:population":70,
    "iso:country":"ES",
    "name:ara_x_preferred":[
        "\u0633\u0627\u0646\u062a\u0627 \u0645\u0627\u0631\u064a\u0627 \u062f\u064a\u0644 \u0625\u0646\u0641\u0627\u064a\u0631\u0646\u0648"
    ],
    "name:arg_x_preferred":[
        "Santa Mar\u00eda del Invierno"
    ],
    "name:cat_x_preferred":[
        "Santa Mar\u00eda del Invierno"
    ],
    "name:eng_x_preferred":[
        "Santa Mar\u00eda del Invierno"
    ],
    "name:eus_x_preferred":[
        "Santa Mar\u00eda del Invierno"
    ],
    "name:fas_x_preferred":[
        "\u0633\u0627\u0646\u062a\u0627 \u0645\u0627\u0631\u06cc\u0627 \u062f\u0644 \u0627\u06cc\u0646\u0628\u06cc\u0631\u0646\u0648"
    ],
    "name:fra_x_preferred":[
        "Santa Mar\u00eda del Invierno"
    ],
    "name:glg_x_preferred":[
        "Santa Mar\u00eda del Invierno"
    ],
    "name:haw_x_preferred":[
        "Santa Mar\u00eda del Invierno"
    ],
    "name:hun_x_preferred":[
        "Santa Mar\u00eda del Invierno"
    ],
    "name:ina_x_preferred":[
        "Santa Mar\u00eda del Invierno"
    ],
    "name:ita_x_preferred":[
        "Santa Mar\u00eda del Invierno"
    ],
    "name:msa_x_preferred":[
        "Santa Mar\u00eda del Invierno"
    ],
    "name:nan_x_preferred":[
        "Santa Mar\u00eda del Invierno"
    ],
    "name:nld_x_preferred":[
        "Santa Mar\u00eda del Invierno"
    ],
    "name:oci_x_preferred":[
        "Santa Mar\u00eda del Invierno"
    ],
    "name:pol_x_preferred":[
        "Santa Mar\u00eda del Invierno"
    ],
    "name:por_x_preferred":[
        "Santa Mar\u00eda del Invierno"
    ],
    "name:rus_x_preferred":[
        "\u0421\u0430\u043d\u0442\u0430-\u041c\u0430\u0440\u0438\u044f-\u0434\u0435\u043b\u044c-\u0418\u043d\u0432\u044c\u0435\u0440\u043d\u043e"
    ],
    "name:spa_x_preferred":[
        "Santa Mar\u00eda del Invierno"
    ],
    "name:swe_x_preferred":[
        "Santa Mar\u00eda del Invierno"
    ],
    "name:ukr_x_preferred":[
        "\u0421\u0430\u043d\u0442\u0430-\u041c\u0430\u0440\u0456\u044f-\u0434\u0435\u043b\u044c-\u0406\u043d\u0432'\u0454\u0440\u043d\u043e"
    ],
    "name:vie_x_preferred":[
        "Santa Mar\u00eda del Invierno"
    ],
    "name:war_x_preferred":[
        "Santa Mar\u00eda del Invierno"
    ],
    "name:zho_x_preferred":[
        "\u5723\u9a6c\u91cc\u4e9a\u5fb7\u6797\u7ef4\u8036\u5c14\u8bfa"
    ],
    "qs_pg:aaroncc":"ES",
    "qs_pg:gn_country":"ES",
    "qs_pg:gn_fcode":"PPLA3",
    "qs_pg:gn_pop":70,
    "qs_pg:name":"Santa Mar\u00eda del Invierno",
    "qs_pg:name_adm0":"Espa\u00f1a",
    "qs_pg:name_adm1":"Castilla y Le\u00f3n",
    "qs_pg:photos_9k":1,
    "qs_pg:photos_9r":1,
    "qs_pg:photos_all":2,
    "qs_pg:photos_sr":0,
    "qs_pg:pop_sr":1,
    "qs_pg:qs_pg_placetype":"locality",
    "qs_pg:qs_pg_placetype_gp":"Town",
    "qs_pg:woe_adm0":23424950,
    "woe:adm0_id":23424950,
    "woe:name_adm0":"Espa\u00f1a",
    "woe:name_adm1":"Castilla y Le\u00f3n",
    "woe:placetype":"Town",
    "wof:name":"Santa Mar\u00eda del Invierno",
    "wof:placetype":"locality",
    "wof:population":70
},
  "geometry": {"coordinates":[-3.43782,42.44288],"type":"Point"}
}