{
  "type": "Feature",
  "properties": {
    "gn:admin1_code":"55",
    "gn:admin2_code":"ZA",
    "gn:admin3_code":"49048",
    "gn:asciiname":"Anta de Tera",
    "gn:country_code":"ES",
    "gn:dem":863,
    "gn:feature_class":"P",
    "gn:feature_code":"PPL",
    "gn:name":"Anta de Tera",
    "gn:population":0,
    "gn:timezone":"Europe/Madrid",
    "iso:country":"ES",
    "wof:name":"Anta de Tera",
    "wof:placetype":"locality"
},
  "geometry": {"coordinates":[-6.38438,41.99879],"type":"Point"}
}