{
  "type": "Feature",
  "properties": {
    "gn:admin1_code":"54",
    "gn:admin2_code":"AB",
    "gn:admin3_code":"02049",
    "gn:asciiname":"Los Alejos",
    "gn:country_code":"ES",
    "gn:dem":813,
    "gn:feature_class":"P",
    "gn:feature_code":"PPL",
    "gn:name":"Los Alejos",
    "gn:population":0,
    "gn:timezone":"Europe/Madrid",
    "iso:country":"ES",
    "name:und_x_variant":[
        "La Alejos",
        "Los Alejos"
    ],
    "wof:name":"Los Alejos",
    "wof:placetype":"locality"
},
  "geometry": {"coordinates":[-2.24262,38.51303],"type":"Point"}
}