{
  "type": "Feature",
  "properties": {
    "gn:admin1_code":"58",
    "gn:admin2_code":"LU",
    "gn:admin3_code":"27010",
    "gn:asciiname":"Mondriz",
    "gn:cc2":"ES",
    "gn:country_code":"ES",
    "gn:dem":429,
    "gn:feature_class":"P",
    "gn:feature_code":"PPL",
    "gn:name":"Mondriz",
    "gn:population":0,
    "gn:timezone":"Europe/Madrid",
    "iso:country":"ES",
    "name:und_x_variant":[
        "Mondrid",
        "Mondriz"
    ],
    "wof:name":"Mondriz",
    "wof:placetype":"locality"
},
  "geometry": {"coordinates":[-7.45,43.11667],"type":"Point"}
}