{
  "type": "Feature",
  "properties": {
    "gn:admin1_code":"59",
    "gn:admin2_code":"BI",
    "gn:admin3_code":"48002",
    "gn:asciiname":"Cotorrio",
    "gn:country_code":"ES",
    "gn:dem":146,
    "gn:feature_class":"P",
    "gn:feature_code":"PPL",
    "gn:name":"Cotorrio",
    "gn:population":0,
    "gn:timezone":"Europe/Madrid",
    "iso:country":"ES",
    "wof:name":"Cotorrio",
    "wof:placetype":"locality"
},
  "geometry": {"coordinates":[-3.11042,43.31106],"type":"Point"}
}