{
  "type": "Feature",
  "properties": {
    "gn:admin1_code":"58",
    "gn:admin2_code":"C",
    "gn:admin3_code":"15012",
    "gn:asciiname":"Pazos",
    "gn:country_code":"ES",
    "gn:dem":242,
    "gn:feature_class":"P",
    "gn:feature_code":"PPL",
    "gn:name":"Pazos",
    "gn:population":0,
    "gn:timezone":"Europe/Madrid",
    "iso:country":"ES",
    "wof:name":"Pazos",
    "wof:placetype":"locality"
},
  "geometry": {"coordinates":[-8.46772,42.79369000000001],"type":"Point"}
}