{
  "type": "Feature",
  "properties": {
    "gn:admin1_code":"59",
    "gn:admin2_code":"SS",
    "gn:admin3_code":"20032",
    "gn:asciiname":"Idotorbe (San Pedro)",
    "gn:country_code":"ES",
    "gn:dem":412,
    "gn:feature_class":"P",
    "gn:feature_code":"PPL",
    "gn:name":"Idotorbe (San Pedro)",
    "gn:population":0,
    "gn:timezone":"Europe/Madrid",
    "iso:country":"ES",
    "name:eus_x_colloquial":[
        "San Pedro"
    ],
    "name:eus_x_preferred":[
        "Idotorbe"
    ],
    "name:eus_x_variant":[
        "San Pedro"
    ],
    "name:spa_x_preferred":[
        "San Pedro de Idotorbe"
    ],
    "wof:name":"Idotorbe (San Pedro)",
    "wof:placetype":"locality"
},
  "geometry": {"coordinates":[-2.43939,43.21415],"type":"Point"}
}