{
  "type": "Feature",
  "properties": {
    "gn:admin1_code":"55",
    "gn:admin2_code":"LE",
    "gn:admin3_code":"24021",
    "gn:asciiname":"Veneros",
    "gn:country_code":"ES",
    "gn:dem":1030,
    "gn:feature_class":"P",
    "gn:feature_code":"PPL",
    "gn:name":"Veneros",
    "gn:population":0,
    "gn:timezone":"Europe/Madrid",
    "iso:country":"ES",
    "wof:name":"Veneros",
    "wof:placetype":"locality"
},
  "geometry": {"coordinates":[-5.27104,42.83443],"type":"Point"}
}