{
  "type": "Feature",
  "properties": {
    "gn:gn_fcode":"PPL",
    "gn:gn_pop":4185,
    "gn:population":4185,
    "iso:country":"ES",
    "name:cat_x_preferred":[
        "Port d'Alc\u00fadia"
    ],
    "name:deu_x_preferred":[
        "Port d'Alc\u00fadia"
    ],
    "name:eng_x_preferred":[
        "Port d'Alcudia"
    ],
    "name:spa_x_preferred":[
        "Port d'Alc\u00fadia"
    ],
    "qs_pg:aaroncc":"ES",
    "qs_pg:gn_fcode":"PPL",
    "qs_pg:gn_pop":4185,
    "qs_pg:name":"Port d'Alc\u00fadia",
    "qs_pg:name_adm0":"Espa\u00f1a",
    "qs_pg:name_adm1":"Illes Balears",
    "qs_pg:photos":392,
    "qs_pg:photos_1k":79,
    "qs_pg:photos_9k":2,
    "qs_pg:photos_9r":5,
    "qs_pg:photos_all":392,
    "qs_pg:photos_sr":6,
    "qs_pg:pop_sr":0,
    "qs_pg:qs_pg_placetype":"locality",
    "qs_pg:qs_pg_placetype_gp":"Town",
    "qs_pg:woe_adm0":23424950,
    "woe:adm0_id":23424950,
    "woe:name_adm0":"Espa\u00f1a",
    "woe:name_adm1":"Illes Balears",
    "woe:placetype":"Town",
    "wof:name":"Port d'Alc\u00fadia",
    "wof:placetype":"locality",
    "wof:population":4185
},
  "geometry": {"coordinates":[3.131103,39.841313],"type":"Point"}
}