{
  "type": "Feature",
  "properties": {
    "gn:admin1_code":"59",
    "gn:admin2_code":"VI",
    "gn:admin3_code":"01046",
    "gn:asciiname":"Anucita",
    "gn:country_code":"ES",
    "gn:dem":581,
    "gn:feature_class":"P",
    "gn:feature_code":"PPL",
    "gn:name":"Anuntzeta / An\u00facita",
    "gn:population":0,
    "gn:timezone":"Europe/Madrid",
    "iso:country":"ES",
    "name:eus_x_preferred":[
        "Anuntzeta"
    ],
    "name:eus_x_variant":[
        "Anuzita"
    ],
    "name:spa_x_preferred":[
        "An\u00facita"
    ],
    "name:spa_x_variant":[
        "Anucita"
    ],
    "wof:name":"Anucita",
    "wof:placetype":"locality"
},
  "geometry": {"coordinates":[-2.89839,42.80133],"type":"Point"}
}