{
  "type": "Feature",
  "properties": {
    "gn:country":"ES",
    "gn:fcode":"PPLA3",
    "gn:population":201,
    "iso:country":"ES",
    "name:ara_x_preferred":[
        "\u0644\u0648\u062f\u0627\u064a\u0646\u062a\u064a"
    ],
    "name:arg_x_preferred":[
        "Ludient"
    ],
    "name:arz_x_preferred":[
        "\u0644\u0648\u062f\u0627\u064a\u0646\u062a\u0649"
    ],
    "name:ast_x_preferred":[
        "Ludiente"
    ],
    "name:cat_x_preferred":[
        "Lludient"
    ],
    "name:ceb_x_preferred":[
        "Ludiente"
    ],
    "name:che_x_preferred":[
        "\u041b\u0443\u0434\u044c\u0435\u043d\u0442\u0435"
    ],
    "name:eng_x_preferred":[
        "Ludiente"
    ],
    "name:eus_x_preferred":[
        "Ludiente"
    ],
    "name:fra_x_preferred":[
        "Ludiente"
    ],
    "name:gle_x_preferred":[
        "Ludiente"
    ],
    "name:hun_x_preferred":[
        "Ludiente"
    ],
    "name:ita_x_preferred":[
        "Ludiente"
    ],
    "name:kat_x_preferred":[
        "\u10da\u10e3\u10d3\u10d8\u10d4\u10dc\u10e2\u10d4"
    ],
    "name:lld_x_preferred":[
        "Ludiente"
    ],
    "name:msa_x_preferred":[
        "Ludiente"
    ],
    "name:nan_x_preferred":[
        "Ludiente"
    ],
    "name:nld_x_preferred":[
        "Ludiente"
    ],
    "name:nob_x_preferred":[
        "Ludiente"
    ],
    "name:oci_x_preferred":[
        "Ludiente"
    ],
    "name:pol_x_preferred":[
        "Ludiente"
    ],
    "name:por_x_preferred":[
        "Ludiente"
    ],
    "name:rus_x_preferred":[
        "\u041b\u0443\u0434\u044c\u0435\u043d\u0442\u0435"
    ],
    "name:spa_x_preferred":[
        "Ludiente"
    ],
    "name:swe_x_preferred":[
        "Ludiente"
    ],
    "name:tat_x_preferred":[
        "\u041b\u0443\u0434\u044c\u0435\u043d\u0442\u0435"
    ],
    "name:ukr_x_preferred":[
        "\u041b\u0443\u0434\u044c\u0454\u043d\u0442\u0435"
    ],
    "name:uzb_x_preferred":[
        "Ludiente"
    ],
    "name:vec_x_preferred":[
        "Ludiente"
    ],
    "name:vie_x_preferred":[
        "Ludiente"
    ],
    "name:war_x_preferred":[
        "Ludiente"
    ],
    "name:zho_x_preferred":[
        "\u5362\u8fea\u6069\u7279"
    ],
    "qs_pg:aaroncc":"ES",
    "qs_pg:gn_country":"ES",
    "qs_pg:gn_fcode":"PPLA3",
    "qs_pg:gn_pop":201,
    "qs_pg:name":"Ludiente",
    "qs_pg:name_adm0":"Espa\u00f1a",
    "qs_pg:name_adm1":"Comunitat Valenciana",
    "qs_pg:photos":74,
    "qs_pg:photos_1k":15,
    "qs_pg:photos_9k":1,
    "qs_pg:photos_9r":2,
    "qs_pg:photos_all":74,
    "qs_pg:photos_sr":2,
    "qs_pg:pop_sr":2,
    "qs_pg:qs_pg_placetype":"locality",
    "qs_pg:qs_pg_placetype_gp":"Town",
    "qs_pg:woe_adm0":23424950,
    "woe:adm0_id":23424950,
    "woe:name_adm0":"Espa\u00f1a",
    "woe:name_adm1":"Comunitat Valenciana",
    "woe:placetype":"Town",
    "wof:name":"Ludiente",
    "wof:placetype":"locality",
    "wof:population":201
},
  "geometry": {"coordinates":[-0.36667,40.08333],"type":"Point"}
}