{
  "type": "Feature",
  "properties": {
    "iso:country":"ES",
    "name:ara_x_preferred":[
        "\u0623\u0644\u0628\u064a\u0633\u062a\u0648\u0631"
    ],
    "name:arg_x_preferred":[
        "Albiztur"
    ],
    "name:ast_x_preferred":[
        "Albiztur"
    ],
    "name:bre_x_preferred":[
        "Albiztur"
    ],
    "name:cat_x_preferred":[
        "Albiztur"
    ],
    "name:ceb_x_preferred":[
        "Albiztur"
    ],
    "name:eng_x_preferred":[
        "Albiztur"
    ],
    "name:eus_x_preferred":[
        "Albiztur"
    ],
    "name:fra_x_preferred":[
        "Albiztur"
    ],
    "name:glg_x_preferred":[
        "Albiztur"
    ],
    "name:hun_x_preferred":[
        "Albiztur"
    ],
    "name:ita_x_preferred":[
        "Albiztur"
    ],
    "name:jpn_x_preferred":[
        "\u30a2\u30eb\u30d3\u30b9\u30c8\u30a5\u30eb"
    ],
    "name:msa_x_preferred":[
        "Albiztur"
    ],
    "name:nld_x_preferred":[
        "Albiztur"
    ],
    "name:oci_x_preferred":[
        "Albiztur"
    ],
    "name:pol_x_preferred":[
        "Albiztur"
    ],
    "name:por_x_preferred":[
        "Albiztur"
    ],
    "name:rus_x_preferred":[
        "\u0410\u043b\u044c\u0431\u0438\u0441\u0442\u0443\u0440"
    ],
    "name:sco_x_preferred":[
        "Albiztur"
    ],
    "name:spa_x_preferred":[
        "Alb\u00edstur"
    ],
    "name:swe_x_preferred":[
        "Albiztur"
    ],
    "name:ukr_x_preferred":[
        "\u0410\u043b\u044c\u0431\u0456\u0441\u0442\u0443\u0440"
    ],
    "name:uzb_x_preferred":[
        "Alb\u00edstur"
    ],
    "name:vie_x_preferred":[
        "Albiztur"
    ],
    "name:war_x_preferred":[
        "Albiztur"
    ],
    "name:zho_x_preferred":[
        "\u963f\u5c14\u7ef4\u65af\u56fe\u5c14"
    ],
    "qs_pg:aaroncc":"ES",
    "qs_pg:name":"Albiztur",
    "qs_pg:name_adm0":"Espa\u00f1a",
    "qs_pg:name_adm1":"Euskadi",
    "qs_pg:photos":25,
    "qs_pg:photos_1k":5,
    "qs_pg:photos_9k":1,
    "qs_pg:photos_9r":1,
    "qs_pg:photos_all":25,
    "qs_pg:photos_sr":1,
    "qs_pg:pop_sr":0,
    "qs_pg:qs_pg_placetype":"locality",
    "qs_pg:qs_pg_placetype_gp":"Town",
    "qs_pg:woe_adm0":23424950,
    "woe:adm0_id":23424950,
    "woe:name_adm0":"Espa\u00f1a",
    "woe:name_adm1":"Euskadi",
    "woe:placetype":"Town",
    "wof:name":"Albiztur",
    "wof:placetype":"locality"
},
  "geometry": {"coordinates":[-2.132077,43.129853],"type":"Point"}
}