{
  "type": "Feature",
  "properties": {
    "gn:admin1_code":"51",
    "gn:admin2_code":"SE",
    "gn:admin3_code":"41009",
    "gn:asciiname":"Mina del Esterquizo",
    "gn:country_code":"ES",
    "gn:dem":446,
    "gn:feature_class":"P",
    "gn:feature_code":"PPL",
    "gn:name":"Mina del Esterquizo",
    "gn:population":0,
    "gn:timezone":"Europe/Madrid",
    "iso:country":"ES",
    "wof:name":"Mina del Esterquizo",
    "wof:placetype":"locality"
},
  "geometry": {"coordinates":[-6.06667,37.88333],"type":"Point"}
}