{
  "type": "Feature",
  "properties": {
    "gn:admin1_code":"59",
    "gn:admin2_code":"BI",
    "gn:admin3_code":"48028",
    "gn:asciiname":"Alloa",
    "gn:country_code":"ES",
    "gn:dem":186,
    "gn:feature_class":"P",
    "gn:feature_code":"PPL",
    "gn:name":"Alloa",
    "gn:population":0,
    "gn:timezone":"Europe/Madrid",
    "iso:country":"ES",
    "name:azb_x_preferred":[
        "\u0627\u0644\u0648\u0622"
    ],
    "name:aze_x_preferred":[
        "Alloa"
    ],
    "name:bre_x_preferred":[
        "Alamhagh"
    ],
    "name:bul_x_preferred":[
        "\u0410\u043b\u043e\u0430"
    ],
    "name:ceb_x_preferred":[
        "Alloa"
    ],
    "name:cym_x_preferred":[
        "Alloa"
    ],
    "name:deu_x_preferred":[
        "Alloa"
    ],
    "name:epo_x_preferred":[
        "Alloa"
    ],
    "name:eus_x_preferred":[
        "Alloa"
    ],
    "name:fas_x_preferred":[
        "\u0627\u0644\u0648\u0622"
    ],
    "name:fra_x_preferred":[
        "Alloa"
    ],
    "name:gla_x_preferred":[
        "Alamhagh"
    ],
    "name:gle_x_preferred":[
        "Alamhagh"
    ],
    "name:glg_x_preferred":[
        "Alloa"
    ],
    "name:ita_x_preferred":[
        "Alloa"
    ],
    "name:kor_x_preferred":[
        "\uc568\ub85c\uc544"
    ],
    "name:lit_x_preferred":[
        "Aloa"
    ],
    "name:nld_x_preferred":[
        "Alloa"
    ],
    "name:nno_x_preferred":[
        "Alloa"
    ],
    "name:nor_x_preferred":[
        "Alloa"
    ],
    "name:pol_x_preferred":[
        "Alloa"
    ],
    "name:rus_x_preferred":[
        "\u0410\u043b\u043b\u043e\u0430"
    ],
    "name:sco_x_preferred":[
        "Allowae"
    ],
    "name:spa_x_preferred":[
        "Alloa"
    ],
    "name:swe_x_preferred":[
        "Alloa"
    ],
    "name:ukr_x_preferred":[
        "\u0410\u043b\u043b\u043e\u0430"
    ],
    "wof:name":"Alloa",
    "wof:placetype":"locality"
},
  "geometry": {"coordinates":[-2.59076,43.37059],"type":"Point"}
}