{
  "type": "Feature",
  "properties": {
    "gn:admin1_code":"59",
    "gn:admin2_code":"BI",
    "gn:admin3_code":"48028",
    "gn:asciiname":"Alloa",
    "gn:country_code":"ES",
    "gn:dem":186,
    "gn:feature_class":"P",
    "gn:feature_code":"PPL",
    "gn:name":"Alloa",
    "gn:population":0,
    "gn:timezone":"Europe/Madrid",
    "iso:country":"ES",
    "wof:name":"Alloa",
    "wof:placetype":"locality"
},
  "geometry": {"coordinates":[-2.59076,43.37059],"type":"Point"}
}