{
  "type": "Feature",
  "properties": {
    "gn:admin1_code":"58",
    "gn:admin2_code":"C",
    "gn:admin3_code":"15086",
    "gn:asciiname":"Restande",
    "gn:cc2":"ES",
    "gn:country_code":"ES",
    "gn:dem":317,
    "gn:feature_class":"P",
    "gn:feature_code":"PPL",
    "gn:name":"Restande",
    "gn:population":0,
    "gn:timezone":"Europe/Madrid",
    "iso:country":"ES",
    "name:und_x_variant":[
        "Santa Mar\u00eda",
        "Restande"
    ],
    "wof:name":"Restande",
    "wof:placetype":"locality"
},
  "geometry": {"coordinates":[-8.58333,43.03333],"type":"Point"}
}