{
  "type": "Feature",
  "properties": {
    "gn:admin1_code":"55",
    "gn:admin2_code":"SA",
    "gn:admin3_code":"37189",
    "gn:asciiname":"Navagallega",
    "gn:country_code":"ES",
    "gn:dem":1060,
    "gn:feature_class":"P",
    "gn:feature_code":"PPL",
    "gn:name":"Navagallega",
    "gn:population":0,
    "gn:timezone":"Europe/Madrid",
    "iso:country":"ES",
    "wof:name":"Navagallega",
    "wof:placetype":"locality"
},
  "geometry": {"coordinates":[-5.79041,40.69844000000001],"type":"Point"}
}