{
  "type": "Feature",
  "properties": {
    "gn:admin1_code":"51",
    "gn:admin2_code":"AL",
    "gn:admin3_code":"04017",
    "gn:asciiname":"Apeadero",
    "gn:country_code":"ES",
    "gn:dem":289,
    "gn:feature_class":"P",
    "gn:feature_code":"PPL",
    "gn:name":"Apeadero",
    "gn:population":0,
    "gn:timezone":"Europe/Madrid",
    "iso:country":"ES",
    "name:spa_x_preferred":[
        "Apeadero"
    ],
    "wof:name":"Apeadero",
    "wof:placetype":"locality"
},
  "geometry": {"coordinates":[-2.08333,37.35],"type":"Point"}
}