{
  "type": "Feature",
  "properties": {
    "gn:admin1_code":"55",
    "gn:admin2_code":"BU",
    "gn:admin3_code":"09211",
    "gn:asciiname":"Valtierra de Riopisuerga",
    "gn:country_code":"ES",
    "gn:dem":830,
    "gn:feature_class":"P",
    "gn:feature_code":"PPL",
    "gn:name":"Valtierra de R\u00edopisuerga",
    "gn:population":0,
    "gn:timezone":"Europe/Madrid",
    "iso:country":"ES",
    "name:und_x_variant":[
        "Valtierra de R\u00edopisuerga"
    ],
    "wof:name":"Valtierra de Riopisuerga",
    "wof:placetype":"locality"
},
  "geometry": {"coordinates":[-4.24072,42.47605],"type":"Point"}
}