{
  "type": "Feature",
  "properties": {
    "gn:country":"ES",
    "gn:fcode":"PPL",
    "gn:population":0,
    "iso:country":"ES",
    "name:cat_x_preferred":[
        "Gar\u00f2s"
    ],
    "name:deu_x_preferred":[
        "Gar\u00f2s"
    ],
    "name:eng_x_preferred":[
        "Gar\u00f3s"
    ],
    "name:eng_x_variant":[
        "Gar\u00f2s"
    ],
    "name:eus_x_preferred":[
        "Gar\u00f2s"
    ],
    "name:fra_x_preferred":[
        "Gar\u00f2s"
    ],
    "name:gle_x_preferred":[
        "Gar\u00f2s"
    ],
    "name:glg_x_preferred":[
        "Gar\u00f2s"
    ],
    "name:ita_x_preferred":[
        "Gar\u00f2s"
    ],
    "name:oci_x_preferred":[
        "Gar\u00f2s"
    ],
    "name:por_x_preferred":[
        "Gar\u00f2s"
    ],
    "name:spa_x_preferred":[
        "Gar\u00f3s"
    ],
    "qs_pg:aaroncc":"ES",
    "qs_pg:gn_country":"ES",
    "qs_pg:gn_fcode":"PPL",
    "qs_pg:gn_pop":0,
    "qs_pg:name":"Gar\u00f3s",
    "qs_pg:name_adm0":"Espa\u00f1a",
    "qs_pg:name_adm1":"Catalunya",
    "qs_pg:photos":92,
    "qs_pg:photos_1k":19,
    "qs_pg:photos_9k":1,
    "qs_pg:photos_9r":3,
    "qs_pg:photos_all":92,
    "qs_pg:photos_sr":3,
    "qs_pg:pop_sr":0,
    "qs_pg:qs_pg_placetype":"locality",
    "qs_pg:qs_pg_placetype_gp":"Town",
    "qs_pg:woe_adm0":23424950,
    "woe:adm0_id":23424950,
    "woe:name_adm0":"Espa\u00f1a",
    "woe:name_adm1":"Catalunya",
    "woe:placetype":"Town",
    "wof:name":"Gar\u00f3s",
    "wof:placetype":"locality"
},
  "geometry": {"coordinates":[0.84745,42.70023],"type":"Point"}
}