{
  "type": "Feature",
  "properties": {
    "gn:gn_country":"ES",
    "gn:gn_fcode":"PPLA3",
    "gn:gn_pop":69,
    "gn:population":69,
    "iso:country":"ES",
    "name:ara_x_preferred":[
        "\u062f\u0648\u0646\u0641\u064a\u062f\u0627\u0633"
    ],
    "name:bul_x_preferred":[
        "\u0414\u043e\u043d\u0432\u0438\u0434\u0430\u0441"
    ],
    "name:cat_x_preferred":[
        "Donvidas"
    ],
    "name:deu_x_preferred":[
        "Donvidas"
    ],
    "name:eng_x_preferred":[
        "Donvidas"
    ],
    "name:eus_x_preferred":[
        "Donvidas"
    ],
    "name:fas_x_preferred":[
        "\u062f\u0646\u0628\u06cc\u062f\u0627\u0633"
    ],
    "name:fra_x_preferred":[
        "Donvidas"
    ],
    "name:hun_x_preferred":[
        "Donvidas"
    ],
    "name:ina_x_preferred":[
        "Donvidas"
    ],
    "name:ita_x_preferred":[
        "Donvidas"
    ],
    "name:kaz_x_preferred":[
        "\u0414\u043e\u043d\u0432\u0438\u0434\u0430\u0441"
    ],
    "name:mkd_x_preferred":[
        "\u0414\u043e\u043d\u0432\u0438\u0434\u0430\u0441"
    ],
    "name:msa_x_preferred":[
        "Donvidas"
    ],
    "name:nld_x_preferred":[
        "Donvidas"
    ],
    "name:oci_x_preferred":[
        "Donvidas"
    ],
    "name:pol_x_preferred":[
        "Donvidas"
    ],
    "name:por_x_preferred":[
        "Donvidas"
    ],
    "name:rup_x_preferred":[
        "Donvidas"
    ],
    "name:rus_x_preferred":[
        "\u0414\u043e\u043d\u0432\u0438\u0434\u0430\u0441"
    ],
    "name:spa_x_preferred":[
        "Donvidas"
    ],
    "name:swe_x_preferred":[
        "Donvidas"
    ],
    "name:ukr_x_preferred":[
        "\u0414\u043e\u043d\u0432\u0456\u0434\u0430\u0441"
    ],
    "name:uzb_x_preferred":[
        "Donvidas"
    ],
    "name:vie_x_preferred":[
        "Donvidas"
    ],
    "name:war_x_preferred":[
        "Donvidas"
    ],
    "name:zho_x_preferred":[
        "\u4e1c\u7ef4\u8fbe\u65af"
    ],
    "qs_pg:aaroncc":"ES",
    "qs_pg:gn_country":"ES",
    "qs_pg:gn_fcode":"PPLA3",
    "qs_pg:gn_pop":69,
    "qs_pg:name":"Donvidas",
    "qs_pg:name_adm0":"Espa\u00f1a",
    "qs_pg:name_adm1":"Castilla y Le\u00f3n",
    "qs_pg:photos_9r":0,
    "qs_pg:photos_sr":0,
    "qs_pg:pop_sr":1,
    "qs_pg:qs_pg_placetype":"locality",
    "qs_pg:qs_pg_placetype_gp":"Town",
    "qs_pg:woe_adm0":23424950,
    "woe:adm0_id":23424950,
    "woe:name_adm0":"Espa\u00f1a",
    "woe:name_adm1":"Castilla y Le\u00f3n",
    "woe:placetype":"Town",
    "wof:name":"Donvidas",
    "wof:placetype":"locality",
    "wof:population":69
},
  "geometry": {"coordinates":[-4.80634,41.08954],"type":"Point"}
}