{
  "type": "Feature",
  "properties": {
    "gn:admin1_code":"31",
    "gn:admin2_code":"MU",
    "gn:admin3_code":"30028",
    "gn:asciiname":"Benizar",
    "gn:country_code":"ES",
    "gn:dem":886,
    "gn:feature_class":"P",
    "gn:feature_code":"PPL",
    "gn:name":"Benizar",
    "gn:population":0,
    "gn:timezone":"Europe/Madrid",
    "iso:country":"ES",
    "wof:name":"Benizar",
    "wof:placetype":"locality"
},
  "geometry": {"coordinates":[-1.98402,38.26989],"type":"Point"}
}