{
  "type": "Feature",
  "properties": {
    "gn:gn_country":"ES",
    "gn:gn_fcode":"PPLA3",
    "gn:gn_pop":231,
    "gn:population":231,
    "iso:country":"ES",
    "name:arm_x_preferred":[
        "\u053f\u0578\u0576\u0563\u0578\u057d\u057f\u0578 \u0564\u0565 \u054e\u0561\u056c\u0564\u0561\u057e\u056b\u0561"
    ],
    "name:baq_x_preferred":[
        "Congosto de Valdavia"
    ],
    "name:cat_x_preferred":[
        "Congosto de Valdavia"
    ],
    "name:chi_x_preferred":[
        "\u5b54\u6208\u65af\u6258\u5fb7\u74e6\u5c14\u8fbe\u7ef4\u4e9a"
    ],
    "name:dut_x_preferred":[
        "Congosto de Valdavia"
    ],
    "name:eng_x_preferred":[
        "Congosto de Valdavia"
    ],
    "name:fre_x_preferred":[
        "Congosto de Valdavia"
    ],
    "name:ger_x_preferred":[
        "Congosto de Valdavia"
    ],
    "name:glg_x_preferred":[
        "Congosto de Valdavia"
    ],
    "name:hun_x_preferred":[
        "Congosto de Valdavia"
    ],
    "name:ina_x_preferred":[
        "Congosto de Valdavia"
    ],
    "name:ita_x_preferred":[
        "Congosto de Valdavia"
    ],
    "name:may_x_preferred":[
        "Congosto de Valdavia"
    ],
    "name:nan_x_preferred":[
        "Congosto de Valdavia"
    ],
    "name:oci_x_preferred":[
        "Congosto de Valdavia"
    ],
    "name:per_x_preferred":[
        "\u06a9\u0646\u06af\u0633\u062a\u0648 \u062f \u0628\u0627\u0644\u062f\u0627\u0628\u06cc\u0627"
    ],
    "name:pol_x_preferred":[
        "Congosto de Valdavia"
    ],
    "name:por_x_preferred":[
        "Congosto de Valdavia"
    ],
    "name:rus_x_preferred":[
        "\u041a\u043e\u043d\u0433\u043e\u0441\u0442\u043e-\u0434\u0435-\u0412\u0430\u043b\u044c\u0434\u0430\u0432\u0438\u0430"
    ],
    "name:spa_x_preferred":[
        "Congosto de Valdavia"
    ],
    "name:swe_x_preferred":[
        "Congosto de Valdavia"
    ],
    "name:ukr_x_preferred":[
        "\u041a\u043e\u043d\u0433\u043e\u0441\u0442\u043e-\u0434\u0435-\u0412\u0430\u043b\u044c\u0434\u0430\u0432\u0456\u044f"
    ],
    "name:uzb_x_preferred":[
        "Congosto de Valdavia"
    ],
    "name:vie_x_preferred":[
        "Congosto de Valdavia"
    ],
    "name:war_x_preferred":[
        "Congosto de Valdavia"
    ],
    "qs_pg:aaroncc":"ES",
    "qs_pg:gn_country":"ES",
    "qs_pg:gn_fcode":"PPLA3",
    "qs_pg:gn_pop":231,
    "qs_pg:name":"Congosto de Valdavia",
    "qs_pg:name_adm0":"Espa\u00f1a",
    "qs_pg:name_adm1":"Castilla y Le\u00f3n",
    "qs_pg:photos_9k":1,
    "qs_pg:photos_9r":1,
    "qs_pg:photos_all":2,
    "qs_pg:photos_sr":0,
    "qs_pg:pop_sr":2,
    "qs_pg:qs_pg_placetype":"locality",
    "qs_pg:qs_pg_placetype_gp":"Town",
    "qs_pg:woe_adm0":23424950,
    "woe:adm0_id":23424950,
    "woe:name_adm0":"Espa\u00f1a",
    "woe:name_adm1":"Castilla y Le\u00f3n",
    "woe:placetype":"Town",
    "wof:name":"Congosto de Valdavia",
    "wof:placetype":"locality",
    "wof:population":231
},
  "geometry": {"coordinates":[-4.63366,42.71584],"type":"Point"}
}