{
  "type": "Feature",
  "properties": {
    "gn:admin1_code":"60",
    "gn:admin2_code":"CS",
    "gn:admin3_code":"12130",
    "gn:asciiname":"La Masada",
    "gn:country_code":"ES",
    "gn:dem":925,
    "gn:feature_class":"P",
    "gn:feature_code":"PPL",
    "gn:name":"La Masada",
    "gn:population":0,
    "gn:timezone":"Europe/Madrid",
    "iso:country":"ES",
    "name:und_x_variant":[
        "Caser\u00edo La Masada",
        "La Masada"
    ],
    "wof:name":"La Masada",
    "wof:placetype":"locality"
},
  "geometry": {"coordinates":[-0.44448,40.19608],"type":"Point"}
}