{
  "type": "Feature",
  "properties": {
    "gn:admin1_code":"58",
    "gn:admin2_code":"C",
    "gn:admin3_code":"15053",
    "gn:asciiname":"Pando",
    "gn:country_code":"ES",
    "gn:dem":240,
    "gn:feature_class":"P",
    "gn:feature_code":"PPL",
    "gn:name":"Pando",
    "gn:population":0,
    "gn:timezone":"Europe/Madrid",
    "iso:country":"ES",
    "wof:name":"Pando",
    "wof:placetype":"locality"
},
  "geometry": {"coordinates":[-9.03333,42.81667],"type":"Point"}
}