{
  "type": "Feature",
  "properties": {
    "gn:admin1_code":"58",
    "gn:admin2_code":"LU",
    "gn:admin3_code":"27046.0",
    "gn:asciiname":"Milleiros",
    "gn:country_code":"ES",
    "gn:dem":589,
    "gn:feature_class":"P",
    "gn:feature_code":"PPL",
    "gn:name":"Milleir\u00f3s",
    "gn:population":0,
    "gn:timezone":"Europe/Madrid",
    "iso:country":"ES",
    "wof:name":"Milleiros",
    "wof:placetype":"locality"
},
  "geometry": {"coordinates":[-7.27861,43.13065],"type":"Point"}
}