{
  "type": "Feature",
  "properties": {
    "gn:admin1_code":"55",
    "gn:admin2_code":"LE",
    "gn:admin3_code":"24226",
    "gn:asciiname":"Valdavida",
    "gn:country_code":"ES",
    "gn:dem":909,
    "gn:feature_class":"P",
    "gn:feature_code":"PPL",
    "gn:name":"Valdavida",
    "gn:population":0,
    "gn:timezone":"Europe/Madrid",
    "iso:country":"ES",
    "wof:name":"Valdavida",
    "wof:placetype":"locality"
},
  "geometry": {"coordinates":[-5.00798,42.58892],"type":"Point"}
}