{
  "type": "Feature",
  "properties": {
    "gn:admin1_code":"56",
    "gn:admin2_code":"GI",
    "gn:admin3_code":"17056",
    "gn:asciiname":"Rabos del Terri",
    "gn:country_code":"ES",
    "gn:dem":114,
    "gn:feature_class":"P",
    "gn:feature_code":"PPL",
    "gn:name":"Rab\u00f3s del Terri",
    "gn:population":0,
    "gn:timezone":"Europe/Madrid",
    "iso:country":"ES",
    "wof:name":"Rabos del Terri",
    "wof:placetype":"locality"
},
  "geometry": {"coordinates":[2.8357,42.07162],"type":"Point"}
}