{
  "type": "Feature",
  "properties": {
    "gn:admin1_code":"55",
    "gn:admin2_code":"LE",
    "gn:admin3_code":"24226",
    "gn:asciiname":"Castroane",
    "gn:country_code":"ES",
    "gn:dem":878,
    "gn:feature_class":"P",
    "gn:feature_code":"PPL",
    "gn:name":"Castroa\u00f1e",
    "gn:population":0,
    "gn:timezone":"Europe/Madrid",
    "iso:country":"ES",
    "name:und_x_variant":[
        "Castroa\u00f1e"
    ],
    "wof:name":"Castroane",
    "wof:placetype":"locality"
},
  "geometry": {"coordinates":[-5.05445,42.54754000000001],"type":"Point"}
}