{
  "type": "Feature",
  "properties": {
    "gn:gn_country":"ES",
    "gn:gn_fcode":"PPLA3",
    "gn:gn_pop":93,
    "gn:population":93,
    "iso:country":"ES",
    "name:arg_x_preferred":[
        "Curiel de Duero"
    ],
    "name:cat_x_preferred":[
        "Curiel de Duero"
    ],
    "name:deu_x_preferred":[
        "Curiel de Duero"
    ],
    "name:eng_x_preferred":[
        "Curiel de Duero"
    ],
    "name:eus_x_preferred":[
        "Curiel de Duero"
    ],
    "name:fas_x_preferred":[
        "\u06a9\u0648\u0631\u06cc\u0644 \u062f \u062f\u0648\u0626\u0631\u0648"
    ],
    "name:fra_x_preferred":[
        "Curiel de Duero"
    ],
    "name:hun_x_preferred":[
        "Curiel de Duero"
    ],
    "name:hye_x_preferred":[
        "\u053f\u0578\u0582\u0580\u056b\u0565\u056c \u0564\u0565 \u0534\u0578\u0582\u0565\u0580\u0578"
    ],
    "name:ina_x_preferred":[
        "Curiel de Duero"
    ],
    "name:ita_x_preferred":[
        "Curiel de Duero"
    ],
    "name:msa_x_preferred":[
        "Curiel de Duero"
    ],
    "name:nan_x_preferred":[
        "Curiel de Duero"
    ],
    "name:nld_x_preferred":[
        "Curiel de Duero"
    ],
    "name:oci_x_preferred":[
        "Curiel de Duero"
    ],
    "name:pol_x_preferred":[
        "Curiel de Duero"
    ],
    "name:por_x_preferred":[
        "Curiel de Duero"
    ],
    "name:rus_x_preferred":[
        "\u041a\u0443\u0440\u044c\u0435\u043b\u044c-\u0434\u0435-\u0414\u0443\u044d\u0440\u043e"
    ],
    "name:spa_x_preferred":[
        "Curiel de Duero"
    ],
    "name:swe_x_preferred":[
        "Curiel de Duero"
    ],
    "name:ukr_x_preferred":[
        "\u041a\u0443\u0440'\u0454\u043b\u044c-\u0434\u0435-\u0414\u0443\u0435\u0440\u043e"
    ],
    "name:unk_x_variant":[
        "Curiel"
    ],
    "name:uzb_x_preferred":[
        "Curiel de Duero"
    ],
    "name:vie_x_preferred":[
        "Curiel de Duero"
    ],
    "name:war_x_preferred":[
        "Curiel de Duero"
    ],
    "name:zho_x_preferred":[
        "\u5e93\u5217\u5c14\u5fb7\u675c\u57c3\u7f57"
    ],
    "qs_pg:aaroncc":"ES",
    "qs_pg:gn_country":"ES",
    "qs_pg:gn_fcode":"PPLA3",
    "qs_pg:gn_pop":93,
    "qs_pg:name":"Curiel de Duero",
    "qs_pg:name_adm0":"Espa\u00f1a",
    "qs_pg:name_adm1":"Castilla y Le\u00f3n",
    "qs_pg:photos":79,
    "qs_pg:photos_1k":16,
    "qs_pg:photos_9k":1,
    "qs_pg:photos_9r":3,
    "qs_pg:photos_all":79,
    "qs_pg:photos_sr":3,
    "qs_pg:pop_sr":1,
    "qs_pg:qs_pg_placetype":"locality",
    "qs_pg:qs_pg_placetype_gp":"Town",
    "qs_pg:woe_adm0":23424950,
    "woe:adm0_id":23424950,
    "woe:name_adm0":"Espa\u00f1a",
    "woe:name_adm1":"Castilla y Le\u00f3n",
    "woe:placetype":"Town",
    "wof:name":"Curiel de Duero",
    "wof:placetype":"locality",
    "wof:population":93
},
  "geometry": {"coordinates":[-4.1011,41.64327],"type":"Point"}
}