{
  "type": "Feature",
  "properties": {
    "gn:admin1_code":"59",
    "gn:admin2_code":"VI",
    "gn:admin3_code":"01016",
    "gn:asciiname":"Izarza",
    "gn:country_code":"ES",
    "gn:dem":897,
    "gn:feature_class":"P",
    "gn:feature_code":"PPL",
    "gn:name":"Izartza",
    "gn:population":0,
    "gn:timezone":"Europe/Madrid",
    "iso:country":"ES",
    "name:eus_x_preferred":[
        "Izartza"
    ],
    "name:spa_x_preferred":[
        "Izarza"
    ],
    "wof:name":"Izarza",
    "wof:placetype":"locality"
},
  "geometry": {"coordinates":[-2.55797,42.78041],"type":"Point"}
}