{
  "type": "Feature",
  "properties": {
    "gn:admin1_code":"51",
    "gn:admin2_code":"H",
    "gn:admin3_code":"21021",
    "gn:asciiname":"Dehesa de las Yeguas",
    "gn:country_code":"ES",
    "gn:dem":77,
    "gn:feature_class":"P",
    "gn:feature_code":"PPL",
    "gn:name":"Dehesa de las Yeguas",
    "gn:population":0,
    "gn:timezone":"Europe/Madrid",
    "iso:country":"ES",
    "name:und_x_variant":[
        "Caser\u00edo Dehesa de las Yeguas",
        "Cortijo Dehesa de las Yeguas",
        "Dehesa de las Yeguas"
    ],
    "wof:name":"Dehesa de las Yeguas",
    "wof:placetype":"locality"
},
  "geometry": {"coordinates":[-7.24872,37.3636],"type":"Point"}
}