{
  "type": "Feature",
  "properties": {
    "gn:admin1_code":"60",
    "gn:admin2_code":"A",
    "gn:admin3_code":"03076",
    "gn:asciiname":"Urbanizacion El Raso",
    "gn:country_code":"ES",
    "gn:dem":16,
    "gn:feature_class":"P",
    "gn:feature_code":"PPL",
    "gn:name":"Urbanizaci\u00f3n El Raso",
    "gn:population":0,
    "gn:timezone":"Europe/Madrid",
    "iso:country":"ES",
    "name:eng_x_preferred":[
        "El Raso"
    ],
    "wof:name":"Urbanizacion El Raso",
    "wof:placetype":"locality"
},
  "geometry": {"coordinates":[-0.68343,38.06032],"type":"Point"}
}