{
  "type": "Feature",
  "properties": {
    "gn:admin1_code":"55",
    "gn:admin2_code":"BU",
    "gn:admin3_code":"09906",
    "gn:asciiname":"Villanueva de Rio-Ubierna",
    "gn:country_code":"ES",
    "gn:dem":900,
    "gn:feature_class":"P",
    "gn:feature_code":"PPL",
    "gn:name":"Villanueva de R\u00edo-Ubierna",
    "gn:population":0,
    "gn:timezone":"Europe/Madrid",
    "iso:country":"ES",
    "name:und_x_variant":[
        "Villanueva de R\u00edo-Ubierna"
    ],
    "wof:name":"Villanueva de Rio-Ubierna",
    "wof:placetype":"locality"
},
  "geometry": {"coordinates":[-3.72706,42.43476],"type":"Point"}
}