{
  "type": "Feature",
  "properties": {
    "gn:gn_country":"ES",
    "gn:gn_fcode":"PPLA3",
    "gn:gn_pop":400,
    "gn:population":400,
    "iso:country":"ES",
    "name:baq_x_preferred":[
        "Antig\u00fcedad"
    ],
    "name:cat_x_preferred":[
        "Antig\u00fcedad"
    ],
    "name:chi_x_preferred":[
        "\u5b89\u8482\u683c\u8fbe\u5fb7"
    ],
    "name:dut_x_preferred":[
        "Antig\u00fcedad"
    ],
    "name:eng_x_preferred":[
        "Antig\u00fcedad"
    ],
    "name:fre_x_preferred":[
        "Antig\u00fcedad"
    ],
    "name:glg_x_preferred":[
        "Antig\u00fcedad"
    ],
    "name:hun_x_preferred":[
        "Antig\u00fcedad"
    ],
    "name:ile_x_preferred":[
        "Antig\u00fcedad"
    ],
    "name:ina_x_preferred":[
        "Antig\u00fcedad"
    ],
    "name:ita_x_preferred":[
        "Antig\u00fcedad"
    ],
    "name:may_x_preferred":[
        "Antig\u00fcedad"
    ],
    "name:nan_x_preferred":[
        "Antig\u00fcedad"
    ],
    "name:oci_x_preferred":[
        "Antig\u00fcedad"
    ],
    "name:per_x_preferred":[
        "\u0622\u0646\u062a\u06cc\u06af\u062f\u0627\u062f"
    ],
    "name:pol_x_preferred":[
        "Antig\u00fcedad"
    ],
    "name:por_x_preferred":[
        "Antig\u00fcedad"
    ],
    "name:rus_x_preferred":[
        "\u0410\u043d\u0442\u0438\u0433\u0443\u044d\u0434\u0430\u0434"
    ],
    "name:spa_x_preferred":[
        "Antig\u00fcedad"
    ],
    "name:swe_x_preferred":[
        "Antig\u00fcedad"
    ],
    "name:ukr_x_preferred":[
        "\u0410\u043d\u0442\u0456\u0433\u0443\u0435\u0434\u0430\u0434"
    ],
    "name:uzb_x_preferred":[
        "Antig\u00fcedad"
    ],
    "name:vie_x_preferred":[
        "Antig\u00fcedad"
    ],
    "name:war_x_preferred":[
        "Antig\u00fcedad"
    ],
    "qs_pg:aaroncc":"ES",
    "qs_pg:gn_country":"ES",
    "qs_pg:gn_fcode":"PPLA3",
    "qs_pg:gn_pop":400,
    "qs_pg:name":"Antig\u00fcedad",
    "qs_pg:photos_9r":0,
    "qs_pg:photos_sr":0,
    "qs_pg:pop_sr":2,
    "qs_pg:qs_pg_placetype":"locality",
    "wof:name":"Antig\u00fcedad",
    "wof:placetype":"locality",
    "wof:population":400
},
  "geometry": {"coordinates":[-4.12058,41.94681],"type":"Point"}
}