{
  "type": "Feature",
  "properties": {
    "gn:admin1_code":"31",
    "gn:admin2_code":"MU",
    "gn:admin3_code":"30038",
    "gn:asciiname":"Los Pulpites",
    "gn:country_code":"ES",
    "gn:dem":107,
    "gn:feature_class":"P",
    "gn:feature_code":"PPL",
    "gn:name":"Los Pulpites",
    "gn:population":0,
    "gn:timezone":"Europe/Madrid",
    "iso:country":"ES",
    "wof:name":"Los Pulpites",
    "wof:placetype":"locality"
},
  "geometry": {"coordinates":[-1.24336,38.01384],"type":"Point"}
}