{
  "type": "Feature",
  "properties": {
    "iso:country":"ES",
    "name:ara_x_preferred":[
        "\u0633\u0627\u0644\u064a\u0646\u062a \u062f\u064a \u064a\u0648\u0628\u0631\u064a\u063a\u0627\u062a"
    ],
    "name:arg_x_preferred":[
        "Sallent"
    ],
    "name:ast_x_preferred":[
        "Sallent"
    ],
    "name:azb_x_preferred":[
        "\u0633\u0627\u06cc\u0646\u062a"
    ],
    "name:cat_x_preferred":[
        "Sallent"
    ],
    "name:ceb_x_preferred":[
        "Sallent"
    ],
    "name:che_x_preferred":[
        "\u0421\u0430\u043b\u044c\u0435\u043d"
    ],
    "name:deu_x_preferred":[
        "Sallent de Llobregat"
    ],
    "name:diq_x_preferred":[
        "Sallent"
    ],
    "name:eus_x_preferred":[
        "Sallent"
    ],
    "name:fas_x_preferred":[
        "\u0633\u0627\u06cc\u0646\u062a"
    ],
    "name:fra_x_preferred":[
        "Sallent"
    ],
    "name:heb_x_preferred":[
        "\u05e1\u05dc\u05d9\u05d9\u05e0\u05d8"
    ],
    "name:hun_x_preferred":[
        "Sallent"
    ],
    "name:hye_x_preferred":[
        "\u054d\u0561\u056c\u0575\u0565\u0576\u057f"
    ],
    "name:ile_x_preferred":[
        "Sallent"
    ],
    "name:ind_x_preferred":[
        "Sallent"
    ],
    "name:ita_x_preferred":[
        "Sallent"
    ],
    "name:jpn_x_preferred":[
        "\u30b5\u30b8\u30a7\u30f3"
    ],
    "name:kaz_x_preferred":[
        "\u0421\u0430\u043b\u044c\u0435\u043d"
    ],
    "name:lat_x_preferred":[
        "Sallent"
    ],
    "name:msa_x_preferred":[
        "Sallent"
    ],
    "name:nld_x_preferred":[
        "Sallent"
    ],
    "name:oci_x_preferred":[
        "Sallent"
    ],
    "name:pol_x_preferred":[
        "Sallent"
    ],
    "name:por_x_preferred":[
        "Sallent"
    ],
    "name:que_x_preferred":[
        "Sallent"
    ],
    "name:ron_x_preferred":[
        "Sallent"
    ],
    "name:rus_x_preferred":[
        "\u0421\u0430\u043b\u044c\u0435\u043d"
    ],
    "name:sco_x_preferred":[
        "Sallent"
    ],
    "name:spa_x_preferred":[
        "Sallent de Llobregat"
    ],
    "name:sqi_x_preferred":[
        "Sallent"
    ],
    "name:swe_x_preferred":[
        "Sallent"
    ],
    "name:tat_x_preferred":[
        "\u0421\u0430\u043b\u044c\u0435\u043d"
    ],
    "name:ukr_x_preferred":[
        "\u0421\u0430\u043b\u044c\u0454\u043d"
    ],
    "name:uzb_x_preferred":[
        "Sallent"
    ],
    "name:vec_x_preferred":[
        "Sallent"
    ],
    "name:vie_x_preferred":[
        "Sallent"
    ],
    "name:war_x_preferred":[
        "Sallent"
    ],
    "name:zho_x_preferred":[
        "\u8428\u8fde\u7279"
    ],
    "qs:a0":"Espa\u00f1a",
    "qs:a1":"*Lleida",
    "qs:a1r":"0Catalu\u00f1a",
    "qs:adm0":"Espa\u00f1a",
    "qs:la_lc":"*",
    "qs:level":"locality",
    "qs:loc":"Sallent",
    "qs:loc_alt":"Sallent",
    "qs:pop":0,
    "qs:type":"buffered point",
    "wd:wordcount":82,
    "wof:name":"Sallent",
    "wof:placetype":"locality"
},
  "geometry": {"coordinates":[1.335175,41.903867],"type":"Point"}
}