{
  "type": "Feature",
  "properties": {
    "gn:admin1_code":"55",
    "gn:admin2_code":"BU",
    "gn:admin3_code":"09059",
    "gn:asciiname":"Villatoro",
    "gn:country_code":"ES",
    "gn:dem":871,
    "gn:feature_class":"P",
    "gn:feature_code":"PPL",
    "gn:name":"Villatoro",
    "gn:population":0,
    "gn:timezone":"Europe/Madrid",
    "iso:country":"ES",
    "name:ara_x_preferred":[
        "\u0641\u064a\u0627\u062a\u0648\u0631\u0648"
    ],
    "name:ast_x_preferred":[
        "Villatoro"
    ],
    "name:azb_x_preferred":[
        "\u0628\u06cc\u06cc\u0627\u062a\u0631\u0648"
    ],
    "name:cat_x_preferred":[
        "Villatoro"
    ],
    "name:ceb_x_preferred":[
        "Villatoro"
    ],
    "name:deu_x_preferred":[
        "Villatoro"
    ],
    "name:eus_x_preferred":[
        "Villatoro"
    ],
    "name:fas_x_preferred":[
        "\u0628\u06cc\u06cc\u0627\u062a\u0631\u0648"
    ],
    "name:fra_x_preferred":[
        "Villatoro"
    ],
    "name:hun_x_preferred":[
        "Villatoro"
    ],
    "name:ina_x_preferred":[
        "Villatoro"
    ],
    "name:ita_x_preferred":[
        "Villatoro"
    ],
    "name:kaz_x_preferred":[
        "\u0412\u0438\u043b\u044c\u044f\u0442\u043e\u0440\u043e"
    ],
    "name:mkd_x_preferred":[
        "\u0412\u0438\u043b\u0430\u0442\u043e\u0440\u043e"
    ],
    "name:msa_x_preferred":[
        "Villatoro"
    ],
    "name:nld_x_preferred":[
        "Villatoro"
    ],
    "name:oci_x_preferred":[
        "Villatoro"
    ],
    "name:pol_x_preferred":[
        "Villatoro"
    ],
    "name:por_x_preferred":[
        "Villatoro"
    ],
    "name:rus_x_preferred":[
        "\u0412\u0438\u043b\u044c\u044f\u0442\u043e\u0440\u043e"
    ],
    "name:spa_x_preferred":[
        "Villatoro"
    ],
    "name:swe_x_preferred":[
        "Villatoro"
    ],
    "name:ukr_x_preferred":[
        "\u0412\u0456\u043b\u044c\u044f\u0442\u043e\u0440\u043e"
    ],
    "name:uzb_x_preferred":[
        "Villatoro"
    ],
    "name:vie_x_preferred":[
        "Villatoro"
    ],
    "name:war_x_preferred":[
        "Villatoro"
    ],
    "name:zho_x_preferred":[
        "\u6bd4\u5229\u4e9a\u6258\u7f57"
    ],
    "wof:name":"Villatoro",
    "wof:placetype":"locality"
},
  "geometry": {"coordinates":[-3.69295,42.37491],"type":"Point"}
}