{
  "type": "Feature",
  "properties": {
    "gn:admin1_code":"55",
    "gn:admin2_code":"BU",
    "gn:admin3_code":"09059",
    "gn:asciiname":"Villatoro",
    "gn:country_code":"ES",
    "gn:dem":871,
    "gn:feature_class":"P",
    "gn:feature_code":"PPL",
    "gn:name":"Villatoro",
    "gn:population":0,
    "gn:timezone":"Europe/Madrid",
    "iso:country":"ES",
    "wof:name":"Villatoro",
    "wof:placetype":"locality"
},
  "geometry": {"coordinates":[-3.69295,42.37491],"type":"Point"}
}