{
  "type": "Feature",
  "properties": {
    "gn:admin1_code":"58",
    "gn:admin2_code":"PO",
    "gn:admin3_code":"36045",
    "gn:asciiname":"A Portela",
    "gn:country_code":"ES",
    "gn:dem":51,
    "gn:elevation":"20.0",
    "gn:feature_class":"P",
    "gn:feature_code":"PPL",
    "gn:name":"A Portela",
    "gn:population":0,
    "gn:timezone":"Europe/Madrid",
    "iso:country":"ES",
    "wof:name":"A Portela",
    "wof:placetype":"locality"
},
  "geometry": {"coordinates":[-8.62343,42.28507000000001],"type":"Point"}
}