{
  "type": "Feature",
  "properties": {
    "gn:admin1_code":"34",
    "gn:admin2_code":"O",
    "gn:admin3_code":"33001",
    "gn:asciiname":"Carcedo",
    "gn:country_code":"ES",
    "gn:dem":726,
    "gn:feature_class":"P",
    "gn:feature_code":"PPL",
    "gn:name":"Carcedo",
    "gn:population":0,
    "gn:timezone":"Europe/Madrid",
    "iso:country":"ES",
    "name:arg_x_preferred":[
        "Carcedo"
    ],
    "name:spa_x_preferred":[
        "Carcedo"
    ],
    "wof:name":"Carcedo",
    "wof:placetype":"locality"
},
  "geometry": {"coordinates":[-6.73687,43.24151],"type":"Point"}
}