{
  "type": "Feature",
  "properties": {
    "gn:admin1_code":"56",
    "gn:admin2_code":"GI",
    "gn:admin3_code":"17183",
    "gn:asciiname":"Sant Esteve de Llemena",
    "gn:cc2":"ES",
    "gn:country_code":"ES",
    "gn:dem":317,
    "gn:feature_class":"P",
    "gn:feature_code":"PPL",
    "gn:name":"Sant Esteve de Ll\u00e9mena",
    "gn:population":0,
    "gn:timezone":"Europe/Madrid",
    "iso:country":"ES",
    "name:cat_x_preferred":[
        "Sant Esteve de Ll\u00e9mena"
    ],
    "name:eng_x_preferred":[
        "Sant Esteve de Ll\u00e9mena"
    ],
    "name:eus_x_preferred":[
        "Sant Esteve de Ll\u00e9mena"
    ],
    "name:oci_x_preferred":[
        "Sant Esteve de Ll\u00e9mena"
    ],
    "name:und_x_variant":[
        "Sant Esteve de Ll\u00e9mena"
    ],
    "wof:name":"Sant Esteve de Llemena",
    "wof:placetype":"locality"
},
  "geometry": {"coordinates":[2.63088,42.05847],"type":"Point"}
}