{
  "type": "Feature",
  "properties": {
    "gn:gn_country":"ES",
    "gn:gn_fcode":"PPLA3",
    "gn:gn_pop":170,
    "gn:population":170,
    "iso:country":"ES",
    "name:alb_x_preferred":[
        "Vilamaniscle"
    ],
    "name:ara_x_preferred":[
        "\u0641\u064a\u0644\u0627\u0645\u0627\u0646\u064a\u0633\u0643\u0644\u064a"
    ],
    "name:arg_x_preferred":[
        "Vilamaniscle"
    ],
    "name:arm_x_preferred":[
        "\u054e\u056b\u056c\u0561\u0574\u0561\u0576\u056b\u057d\u056f\u056c\u0565"
    ],
    "name:baq_x_preferred":[
        "Vilamaniscle"
    ],
    "name:cat_x_preferred":[
        "Vilamaniscle"
    ],
    "name:chi_x_preferred":[
        "\u6bd4\u62c9\u9a6c\u5c3c\u65af\u514b\u83b1"
    ],
    "name:dut_x_preferred":[
        "Vilamaniscle"
    ],
    "name:eng_x_preferred":[
        "Vilamaniscle"
    ],
    "name:fre_x_preferred":[
        "Vilamaniscle"
    ],
    "name:ger_x_preferred":[
        "Vilamaniscle"
    ],
    "name:hun_x_preferred":[
        "Vilamaniscle"
    ],
    "name:ita_x_preferred":[
        "Vilamaniscle"
    ],
    "name:kaz_x_preferred":[
        "\u0412\u0438\u043b\u0430\u043c\u0430\u043d\u0438\u0441\u043a\u043b\u0435"
    ],
    "name:lat_x_preferred":[
        "Vilamaniscle"
    ],
    "name:may_x_preferred":[
        "Vilamaniscle"
    ],
    "name:oci_x_preferred":[
        "Vilamaniscle"
    ],
    "name:pol_x_preferred":[
        "Vilamaniscle"
    ],
    "name:por_x_preferred":[
        "Vilamaniscle"
    ],
    "name:rus_x_preferred":[
        "\u0412\u0438\u043b\u0430\u043c\u0430\u043d\u0438\u0441\u043a\u043b\u0435"
    ],
    "name:spa_x_preferred":[
        "Vilamaniscle"
    ],
    "name:swe_x_preferred":[
        "Vilamaniscle"
    ],
    "name:tah_x_preferred":[
        "Vilamaniscle"
    ],
    "name:ukr_x_preferred":[
        "\u0411\u0456\u043b\u0430\u043c\u0430\u043d\u0456\u0441\u043a\u043b\u0430"
    ],
    "name:uzb_x_preferred":[
        "Vilamaniscle"
    ],
    "name:vie_x_preferred":[
        "Vilamaniscle"
    ],
    "name:war_x_preferred":[
        "Vilamaniscle"
    ],
    "qs_pg:aaroncc":"ES",
    "qs_pg:gn_country":"ES",
    "qs_pg:gn_fcode":"PPLA3",
    "qs_pg:gn_pop":170,
    "qs_pg:name":"Vilamaniscle",
    "qs_pg:name_adm0":"Espa\u00f1a",
    "qs_pg:name_adm1":"Catalunya",
    "qs_pg:photos_9r":0,
    "qs_pg:photos_sr":0,
    "qs_pg:pop_sr":1,
    "qs_pg:qs_pg_placetype":"locality",
    "qs_pg:qs_pg_placetype_gp":"Town",
    "qs_pg:woe_adm0":23424950,
    "woe:adm0_id":23424950,
    "woe:name_adm0":"Espa\u00f1a",
    "woe:name_adm1":"Catalunya",
    "woe:placetype":"Town",
    "wof:name":"Vilamaniscle",
    "wof:placetype":"locality",
    "wof:population":170
},
  "geometry": {"coordinates":[3.06755,42.37522],"type":"Point"}
}