{
  "type": "Feature",
  "properties": {
    "gn:admin1_code":"60",
    "gn:asciiname":"Lleus",
    "gn:cc2":"ES",
    "gn:country_code":"ES",
    "gn:dem":-9999,
    "gn:feature_class":"P",
    "gn:feature_code":"PPL",
    "gn:name":"Lleus",
    "gn:population":0,
    "gn:timezone":"Europe/Madrid",
    "iso:country":"ES",
    "name:und_x_variant":[
        "Casas Lleus",
        "Casas Llens",
        "Lleus"
    ],
    "wof:name":"Lleus",
    "wof:placetype":"locality"
},
  "geometry": {"coordinates":[0.18333,38.68333],"type":"Point"}
}