{
  "type": "Feature",
  "properties": {
    "gn:admin1_code":"51",
    "gn:admin2_code":"J",
    "gn:admin3_code":"23901",
    "gn:asciiname":"Cazalla",
    "gn:country_code":"ES",
    "gn:dem":745,
    "gn:feature_class":"P",
    "gn:feature_code":"PPL",
    "gn:name":"Cazalla",
    "gn:population":0,
    "gn:timezone":"Europe/Madrid",
    "iso:country":"ES",
    "name:spa_x_preferred":[
        "Cazalla"
    ],
    "name:und_x_variant":[
        "Casas Cazalla"
    ],
    "wof:name":"Cazalla",
    "wof:placetype":"locality"
},
  "geometry": {"coordinates":[-3.61475,37.62181],"type":"Point"}
}