{
  "type": "Feature",
  "properties": {
    "gn:admin1_code":"51",
    "gn:admin2_code":"SE",
    "gn:admin3_code":"41070",
    "gn:asciiname":"Palomares del Rio",
    "gn:country_code":"ES",
    "gn:dem":39,
    "gn:feature_class":"P",
    "gn:feature_code":"PPLA3",
    "gn:name":"Palomares del R\u00edo",
    "gn:population":4782,
    "gn:timezone":"Europe/Madrid",
    "iso:country":"ES",
    "name:und_x_variant":[
        "Palomares",
        "Palomares del R\u00edo"
    ],
    "wof:name":"Palomares del Rio",
    "wof:placetype":"locality",
    "wof:population":4782
},
  "geometry": {"coordinates":[-6.05863,37.32225],"type":"Point"}
}