{
  "type": "Feature",
  "properties": {
    "gn:admin1_code":"51",
    "gn:admin2_code":"SE",
    "gn:admin3_code":"41070",
    "gn:asciiname":"Palomares del Rio",
    "gn:country_code":"ES",
    "gn:dem":39,
    "gn:feature_class":"P",
    "gn:feature_code":"PPLA3",
    "gn:name":"Palomares del R\u00edo",
    "gn:population":4782,
    "gn:timezone":"Europe/Madrid",
    "iso:country":"ES",
    "name:arg_x_preferred":[
        "Palomares del R\u00edo"
    ],
    "name:ast_x_preferred":[
        "Palomares del R\u00edo"
    ],
    "name:bul_x_preferred":[
        "\u041f\u0430\u043b\u043e\u043c\u0430\u0440\u0435\u0441 \u0434\u0435\u043b \u0420\u0438\u043e"
    ],
    "name:cat_x_preferred":[
        "Palomares del R\u00edo"
    ],
    "name:ceb_x_preferred":[
        "Palomares del R\u00edo"
    ],
    "name:diq_x_preferred":[
        "Palomares del R\u00edo"
    ],
    "name:epo_x_preferred":[
        "Palomares del R\u00edo"
    ],
    "name:eus_x_preferred":[
        "Palomares del R\u00edo"
    ],
    "name:fra_x_preferred":[
        "Palomares del R\u00edo"
    ],
    "name:hat_x_preferred":[
        "Palomares del R\u00edo"
    ],
    "name:hun_x_preferred":[
        "Palomares del R\u00edo"
    ],
    "name:hye_x_preferred":[
        "\u054a\u0561\u056c\u0578\u0574\u0561\u0580\u0565\u057d \u0564\u0565\u056c \u054c\u056b\u0578"
    ],
    "name:ind_x_preferred":[
        "Palomares del R\u00edo"
    ],
    "name:ita_x_preferred":[
        "Palomares del R\u00edo"
    ],
    "name:kaz_x_preferred":[
        "\u041f\u0430\u043b\u043e\u043c\u0430\u0440\u0435\u0441-\u0434\u0435\u043b\u044c-\u0420\u0438\u043e"
    ],
    "name:msa_x_preferred":[
        "Palomares del R\u00edo"
    ],
    "name:nld_x_preferred":[
        "Palomares del R\u00edo"
    ],
    "name:oci_x_preferred":[
        "Palomares del R\u00edo"
    ],
    "name:pol_x_preferred":[
        "Palomares del R\u00edo"
    ],
    "name:por_x_preferred":[
        "Palomares del R\u00edo"
    ],
    "name:ron_x_preferred":[
        "Palomares del R\u00edo"
    ],
    "name:rus_x_preferred":[
        "\u041f\u0430\u043b\u043e\u043c\u0430\u0440\u0435\u0441-\u0434\u0435\u043b\u044c-\u0420\u0438\u043e"
    ],
    "name:spa_x_preferred":[
        "Palomares del R\u00edo"
    ],
    "name:swe_x_preferred":[
        "Palomares del R\u00edo"
    ],
    "name:tur_x_preferred":[
        "Palomares del R\u00edo"
    ],
    "name:ukr_x_preferred":[
        "\u041f\u0430\u043b\u043e\u043c\u0430\u0440\u0435\u0441-\u0434\u0435\u043b\u044c-\u0420\u0456\u043e"
    ],
    "name:und_x_variant":[
        "Palomares"
    ],
    "name:uzb_x_preferred":[
        "Palomares del R\u00edo"
    ],
    "name:vie_x_preferred":[
        "Palomares del R\u00edo"
    ],
    "name:war_x_preferred":[
        "Palomares del R\u00edo"
    ],
    "name:zho_x_preferred":[
        "\u5e15\u6d1b\u9a6c\u96f7\u65af\u5fb7\u5c14\u91cc\u5965"
    ],
    "wof:name":"Palomares del Rio",
    "wof:placetype":"locality",
    "wof:population":4782
},
  "geometry": {"coordinates":[-6.05863,37.32225],"type":"Point"}
}