{
  "type": "Feature",
  "properties": {
    "gn:admin1_code":"51",
    "gn:admin2_code":"GR",
    "gn:admin3_code":"18054",
    "gn:asciiname":"Los Banos",
    "gn:country_code":"ES",
    "gn:dem":959,
    "gn:feature_class":"P",
    "gn:feature_code":"PPL",
    "gn:name":"Los Ba\u00f1os",
    "gn:population":0,
    "gn:timezone":"Europe/Madrid",
    "iso:country":"ES",
    "wof:name":"Los Banos",
    "wof:placetype":"locality"
},
  "geometry": {"coordinates":[-3.21037,37.30489],"type":"Point"}
}