{
  "type": "Feature",
  "properties": {
    "gn:admin1_code":"32",
    "gn:admin3_code":"31050",
    "gn:asciiname":"Aniz",
    "gn:country_code":"ES",
    "gn:dem":388,
    "gn:feature_class":"P",
    "gn:feature_code":"PPL",
    "gn:name":"Aniz",
    "gn:population":0,
    "gn:timezone":"Europe/Madrid",
    "iso:country":"ES",
    "wof:name":"Aniz",
    "wof:placetype":"locality"
},
  "geometry": {"coordinates":[-1.58137,43.11213],"type":"Point"}
}