{
  "type": "Feature",
  "properties": {
    "gn:admin1_code":"55",
    "gn:admin2_code":"SO",
    "gn:admin3_code":"42165",
    "gn:asciiname":"Villarijo",
    "gn:country_code":"ES",
    "gn:dem":819,
    "gn:feature_class":"P",
    "gn:feature_code":"PPL",
    "gn:name":"Villarijo",
    "gn:population":0,
    "gn:timezone":"Europe/Madrid",
    "iso:country":"ES",
    "wof:name":"Villarijo",
    "wof:placetype":"locality"
},
  "geometry": {"coordinates":[-2.14875,42.08363],"type":"Point"}
}