{
  "type": "Feature",
  "properties": {
    "gn:admin1_code":"55",
    "gn:admin2_code":"LE",
    "gn:admin3_code":"24202",
    "gn:asciiname":"Rioscuro",
    "gn:country_code":"ES",
    "gn:dem":1008,
    "gn:feature_class":"P",
    "gn:feature_code":"PPL",
    "gn:name":"R\u00edoscuro",
    "gn:population":0,
    "gn:timezone":"Europe/Madrid",
    "iso:country":"ES",
    "name:und_x_variant":[
        "R\u00edoscuro"
    ],
    "wof:name":"Rioscuro",
    "wof:placetype":"locality"
},
  "geometry": {"coordinates":[-6.28859,42.93232],"type":"Point"}
}