{
  "type": "Feature",
  "properties": {
    "gn:admin1_code":"52",
    "gn:admin2_code":"TE",
    "gn:admin3_code":"44206",
    "gn:asciiname":"Mases y Tamboril",
    "gn:cc2":"ES",
    "gn:country_code":"ES",
    "gn:dem":883,
    "gn:feature_class":"P",
    "gn:feature_code":"PPL",
    "gn:name":"Mases y Tamboril",
    "gn:population":0,
    "gn:timezone":"Europe/Madrid",
    "iso:country":"ES",
    "name:und_x_variant":[
        "Caser\u00edo Mases y Tamboril",
        "Mases y Tamboril"
    ],
    "wof:name":"Mases y Tamboril",
    "wof:placetype":"locality"
},
  "geometry": {"coordinates":[-0.66667,40.06667],"type":"Point"}
}