{
  "type": "Feature",
  "properties": {
    "iso:country":"ES",
    "name:eng_x_preferred":[
        "Centro de Ocio"
    ],
    "name:spa_x_preferred":[
        "Centro de Ocio"
    ],
    "wof:name":"Centro de Ocio",
    "wof:placetype":"neighbourhood"
},
  "geometry": {"coordinates":[-4.47947701537692,36.65900391964399],"type":"Point"}
}