{
  "type": "Feature",
  "properties": {
    "gn:admin1_code":"58",
    "gn:admin2_code":"OR",
    "gn:admin3_code":"32059",
    "gn:asciiname":"Marzas",
    "gn:country_code":"ES",
    "gn:dem":657,
    "gn:feature_class":"P",
    "gn:feature_code":"PPL",
    "gn:name":"Marz\u00e1s",
    "gn:population":0,
    "gn:timezone":"Europe/Madrid",
    "iso:country":"ES",
    "name:eus_x_preferred":[
        "Martzak"
    ],
    "name:spa_x_preferred":[
        "Marzas"
    ],
    "wof:name":"Marzas",
    "wof:placetype":"locality"
},
  "geometry": {"coordinates":[-7.78333,42.48333],"type":"Point"}
}