{
  "type": "Feature",
  "properties": {
    "gn:admin1_code":"57",
    "gn:admin2_code":"CC",
    "gn:admin3_code":"10090",
    "gn:asciiname":"Los Berrocosos",
    "gn:cc2":"ES",
    "gn:country_code":"ES",
    "gn:dem":389,
    "gn:feature_class":"P",
    "gn:feature_code":"PPL",
    "gn:name":"Los Berrocosos",
    "gn:population":0,
    "gn:timezone":"Europe/Madrid",
    "iso:country":"ES",
    "name:und_x_variant":[
        "Caser\u00edo los Berrocosos",
        "Los Berrocosos"
    ],
    "wof:name":"Los Berrocosos",
    "wof:placetype":"locality"
},
  "geometry": {"coordinates":[-6.11667,40.16667],"type":"Point"}
}