{
  "type": "Feature",
  "properties": {
    "gn:admin1_code":"34",
    "gn:admin2_code":"O",
    "gn:admin3_code":"33068",
    "gn:asciiname":"Cores",
    "gn:country_code":"ES",
    "gn:dem":853,
    "gn:feature_class":"P",
    "gn:feature_code":"PPL",
    "gn:name":"Cor\u00e9s",
    "gn:population":0,
    "gn:timezone":"Europe/Madrid",
    "iso:country":"ES",
    "name:und_x_variant":[
        "Cor\u00e9s"
    ],
    "wof:name":"Cores",
    "wof:placetype":"locality"
},
  "geometry": {"coordinates":[-6.32035,43.10918],"type":"Point"}
}