{
  "type": "Feature",
  "properties": {
    "gn:admin1_code":"58",
    "gn:admin2_code":"LU",
    "gn:admin3_code":"27901",
    "gn:asciiname":"Covas",
    "gn:country_code":"ES",
    "gn:dem":513,
    "gn:feature_class":"P",
    "gn:feature_code":"PPL",
    "gn:name":"Covas",
    "gn:population":0,
    "gn:timezone":"Europe/Madrid",
    "iso:country":"ES",
    "wof:name":"Covas",
    "wof:placetype":"locality"
},
  "geometry": {"coordinates":[-7.30552,42.86831],"type":"Point"}
}