{
  "type": "Feature",
  "properties": {
    "gn:gn_country":"ES",
    "gn:gn_fcode":"PPLA3",
    "gn:gn_pop":0,
    "iso:country":"ES",
    "name:ara_x_preferred":[
        "\u0633\u0627\u0646 \u0645\u064a\u063a\u064a\u0644 \u062f\u064a \u0643\u0627\u0645\u0628\u0645\u0627\u062c\u0648\u0631"
    ],
    "name:arg_x_preferred":[
        "Sant Miquel de Campmajor"
    ],
    "name:cat_x_preferred":[
        "Sant Miquel de Campmajor"
    ],
    "name:deu_x_preferred":[
        "Sant Miquel de Campmajor"
    ],
    "name:eng_x_preferred":[
        "Sant Miquel de Campmajor"
    ],
    "name:eus_x_preferred":[
        "Sant Miquel de Campmajor"
    ],
    "name:fra_x_preferred":[
        "Sant Miquel de Campmajor"
    ],
    "name:hun_x_preferred":[
        "Sant Miquel de Campmajor"
    ],
    "name:hye_x_preferred":[
        "\u054d\u0561\u0576 \u0544\u056b\u056f\u0565\u056c \u0564\u0565 \u053f\u0561\u0574\u057a\u0574\u0561\u056a\u0578\u0580"
    ],
    "name:ita_x_preferred":[
        "Sant Miquel de Campmajor"
    ],
    "name:kaz_x_preferred":[
        "\u0421\u0430\u043d\u0442-\u041c\u0438\u043a\u0435\u043b\u044c-\u0434\u0435-\u041a\u0430\u043c\u043f\u043c\u0430\u0445\u043e\u0440"
    ],
    "name:lat_x_preferred":[
        "Sant Miquel de Campmajor"
    ],
    "name:nld_x_preferred":[
        "Sant Miquel de Campmajor"
    ],
    "name:oci_x_preferred":[
        "Sant Miquel de Campmajor"
    ],
    "name:pol_x_preferred":[
        "Sant Miquel de Campmajor"
    ],
    "name:por_x_preferred":[
        "Sant Miquel de Campmajor"
    ],
    "name:rus_x_preferred":[
        "\u0421\u0430\u043d\u0442-\u041c\u0438\u043a\u0435\u043b\u044c-\u0434\u0435-\u041a\u0430\u043c\u043f\u043c\u0430\u0445\u043e\u0440"
    ],
    "name:spa_x_preferred":[
        "San Miguel de Campmajor"
    ],
    "name:sqi_x_preferred":[
        "Sant Miquel de Campmajor"
    ],
    "name:swe_x_preferred":[
        "Sant Miquel de Campmajor"
    ],
    "name:tah_x_preferred":[
        "Sant Miquel de Campmajor"
    ],
    "name:unk_x_variant":[
        "San Miguel de Campmajor"
    ],
    "name:uzb_x_preferred":[
        "San Miguel de Campmajor"
    ],
    "name:war_x_preferred":[
        "Sant Miquel de Campmajor"
    ],
    "name:zho_x_preferred":[
        "\u6851\u7279\u7c73\u514b\u5c14\u5fb7\u574e\u666e\u9a6c\u970d\u5c14"
    ],
    "qs_pg:aaroncc":"ES",
    "qs_pg:gn_country":"ES",
    "qs_pg:gn_fcode":"PPLA3",
    "qs_pg:gn_pop":0,
    "qs_pg:name":"Sant Miquel de Campmajor",
    "qs_pg:name_adm0":"Espa\u00f1a",
    "qs_pg:name_adm1":"Catalunya",
    "qs_pg:photos":36,
    "qs_pg:photos_1k":7,
    "qs_pg:photos_9k":1,
    "qs_pg:photos_9r":2,
    "qs_pg:photos_all":36,
    "qs_pg:photos_sr":2,
    "qs_pg:pop_sr":0,
    "qs_pg:qs_pg_placetype":"locality",
    "qs_pg:qs_pg_placetype_gp":"Town",
    "qs_pg:woe_adm0":23424950,
    "woe:adm0_id":23424950,
    "woe:name_adm0":"Espa\u00f1a",
    "woe:name_adm1":"Catalunya",
    "woe:placetype":"Town",
    "wof:name":"Sant Miquel de Campmajor",
    "wof:placetype":"locality"
},
  "geometry": {"coordinates":[2.68333,42.13333],"type":"Point"}
}