{
  "type": "Feature",
  "properties": {
    "gn:admin1_code":"59",
    "gn:admin2_code":"BI",
    "gn:admin3_code":"48029",
    "gn:asciiname":"Lequizamon",
    "gn:country_code":"ES",
    "gn:dem":132,
    "gn:feature_class":"P",
    "gn:feature_code":"PPL",
    "gn:name":"Legizamon",
    "gn:population":0,
    "gn:timezone":"Europe/Madrid",
    "iso:country":"ES",
    "wof:name":"Lequizamon",
    "wof:placetype":"locality"
},
  "geometry": {"coordinates":[-2.88312,43.25385],"type":"Point"}
}