{
  "type": "Feature",
  "properties": {
    "gn:admin1_code":"51",
    "gn:admin2_code":"GR",
    "gn:admin3_code":"18007",
    "gn:asciiname":"Barrio Bajo",
    "gn:country_code":"ES",
    "gn:dem":708,
    "gn:feature_class":"P",
    "gn:feature_code":"PPL",
    "gn:name":"Barrio Bajo",
    "gn:population":0,
    "gn:timezone":"Europe/Madrid",
    "iso:country":"ES",
    "wof:name":"Barrio Bajo",
    "wof:placetype":"locality"
},
  "geometry": {"coordinates":[-3.62283,36.92787],"type":"Point"}
}