{
  "type": "Feature",
  "properties": {
    "gn:admin1_code":"39",
    "gn:admin2_code":"S",
    "gn:admin3_code":"39017",
    "gn:asciiname":"Servillejas",
    "gn:country_code":"ES",
    "gn:dem":912,
    "gn:feature_class":"P",
    "gn:feature_code":"PPL",
    "gn:name":"Servillejas",
    "gn:population":0,
    "gn:timezone":"Europe/Madrid",
    "iso:country":"ES",
    "wof:name":"Servillejas",
    "wof:placetype":"locality"
},
  "geometry": {"coordinates":[-4.00761,43.02834],"type":"Point"}
}