{
  "type": "Feature",
  "properties": {
    "gn:admin1_code":"55",
    "gn:admin2_code":"SO",
    "gn:admin3_code":"42024",
    "gn:asciiname":"Calderuela",
    "gn:country_code":"ES",
    "gn:dem":1109,
    "gn:feature_class":"P",
    "gn:feature_code":"PPL",
    "gn:name":"Calderuela",
    "gn:population":0,
    "gn:timezone":"Europe/Madrid",
    "iso:country":"ES",
    "wof:name":"Calderuela",
    "wof:placetype":"locality"
},
  "geometry": {"coordinates":[-2.23482,41.79574],"type":"Point"}
}