{
  "type": "Feature",
  "properties": {
    "gn:admin1_code":"51",
    "gn:admin2_code":"GR",
    "gn:admin3_code":"18056",
    "gn:asciiname":"Mazarra",
    "gn:country_code":"ES",
    "gn:dem":886,
    "gn:feature_class":"P",
    "gn:feature_code":"PPL",
    "gn:name":"Mazarra",
    "gn:population":0,
    "gn:timezone":"Europe/Madrid",
    "iso:country":"ES",
    "name:und_x_variant":[
        "Caser\u00edo Mazarra",
        "Cortijo de Mazarra",
        "Mazarra"
    ],
    "wof:name":"Mazarra",
    "wof:placetype":"locality"
},
  "geometry": {"coordinates":[-2.63841,37.53623],"type":"Point"}
}