{
  "type": "Feature",
  "properties": {
    "gn:admin1_code":"58",
    "gn:admin2_code":"LU",
    "gn:admin3_code":"27042",
    "gn:asciiname":"Aldosende",
    "gn:country_code":"ES",
    "gn:dem":562,
    "gn:feature_class":"P",
    "gn:feature_code":"PPL",
    "gn:name":"Aldosende",
    "gn:population":0,
    "gn:timezone":"Europe/Madrid",
    "iso:country":"ES",
    "wof:name":"Aldosende",
    "wof:placetype":"locality"
},
  "geometry": {"coordinates":[-7.6361,42.74682],"type":"Point"}
}