{
  "type": "Feature",
  "properties": {
    "gn:admin1_code":"51",
    "gn:admin2_code":"AL",
    "gn:admin3_code":"04053",
    "gn:asciiname":"El Saltador",
    "gn:country_code":"ES",
    "gn:dem":289,
    "gn:feature_class":"P",
    "gn:feature_code":"PPL",
    "gn:name":"El Saltador",
    "gn:population":0,
    "gn:timezone":"Europe/Madrid",
    "iso:country":"ES",
    "name:und_x_variant":[
        "Caser\u00edo El Saltador",
        "El Saltador"
    ],
    "wof:name":"El Saltador",
    "wof:placetype":"locality"
},
  "geometry": {"coordinates":[-1.90646,37.4044],"type":"Point"}
}