{
  "type": "Feature",
  "properties": {
    "gn:admin1_code":"34",
    "gn:admin2_code":"O",
    "gn:admin3_code":"33036",
    "gn:asciiname":"La Galguera",
    "gn:country_code":"ES",
    "gn:dem":49,
    "gn:feature_class":"P",
    "gn:feature_code":"PPL",
    "gn:name":"La Galguera",
    "gn:population":0,
    "gn:timezone":"Europe/Madrid",
    "iso:country":"ES",
    "wof:name":"La Galguera",
    "wof:placetype":"locality"
},
  "geometry": {"coordinates":[-4.74887,43.39975],"type":"Point"}
}