{
  "type": "Feature",
  "properties": {
    "gn:admin1_code":"55",
    "gn:admin2_code":"LE",
    "gn:admin3_code":"24209",
    "gn:asciiname":"Cela",
    "gn:country_code":"ES",
    "gn:dem":824,
    "gn:feature_class":"P",
    "gn:feature_code":"PPL",
    "gn:name":"Cela",
    "gn:population":0,
    "gn:timezone":"Europe/Madrid",
    "iso:country":"ES",
    "name:ceb_x_preferred":[
        "Cela"
    ],
    "name:ces_x_preferred":[
        "Cela"
    ],
    "name:deu_x_preferred":[
        "Cela"
    ],
    "name:fra_x_preferred":[
        "Cela"
    ],
    "name:glg_x_preferred":[
        "Cela"
    ],
    "name:heb_x_preferred":[
        "\u05e1\u05dc\u05d4"
    ],
    "name:hrv_x_preferred":[
        "Cela"
    ],
    "name:nld_x_preferred":[
        "Cela"
    ],
    "name:pol_x_preferred":[
        "Cela"
    ],
    "name:por_x_preferred":[
        "Cela"
    ],
    "name:slk_x_preferred":[
        "Cela"
    ],
    "name:spa_x_preferred":[
        "Cela"
    ],
    "name:swe_x_preferred":[
        "Cela"
    ],
    "wof:name":"Cela",
    "wof:placetype":"locality"
},
  "geometry": {"coordinates":[-6.82674,42.68451],"type":"Point"}
}