{
  "type": "Feature",
  "properties": {
    "gn:admin1_code":"56",
    "gn:admin2_code":"GI",
    "gn:admin3_code":"17201",
    "gn:asciiname":"Fornells de la Montanya",
    "gn:country_code":"ES",
    "gn:dem":1496,
    "gn:feature_class":"P",
    "gn:feature_code":"PPL",
    "gn:name":"Fornells de la Montanya",
    "gn:population":0,
    "gn:timezone":"Europe/Madrid",
    "iso:country":"ES",
    "wof:name":"Fornells de la Montanya",
    "wof:placetype":"locality"
},
  "geometry": {"coordinates":[2.05,42.31667],"type":"Point"}
}