{
  "type": "Feature",
  "properties": {
    "gn:gn_country":"ES",
    "gn:gn_fcode":"PPLA3",
    "gn:gn_pop":512,
    "gn:population":512,
    "iso:country":"ES",
    "name:ara_x_preferred":[
        "\u0627\u0644\u0645\u0648\u062f\u0648\u0641\u0627\u0631 \u062f\u064a\u0644 \u0628\u0627\u064a\u0646\u0627\u0631"
    ],
    "name:arg_x_preferred":[
        "Almod\u00f3var del Pinar"
    ],
    "name:cat_x_preferred":[
        "Almod\u00f3var del Pinar"
    ],
    "name:eng_x_preferred":[
        "Almod\u00f3var del Pinar"
    ],
    "name:eus_x_preferred":[
        "Almod\u00f3var del Pinar"
    ],
    "name:fas_x_preferred":[
        "\u0627\u0644\u0645\u062f\u0648\u0631 \u062f\u0644 \u067e\u06cc\u0646\u0627\u0631"
    ],
    "name:fra_x_preferred":[
        "Almod\u00f3var del Pinar"
    ],
    "name:hun_x_preferred":[
        "Almod\u00f3var del Pinar"
    ],
    "name:hye_x_preferred":[
        "\u0531\u056c\u0574\u0578\u0564\u0578\u057e\u0561\u0580 \u0564\u0565\u056c \u054a\u056b\u0576\u0561\u0580"
    ],
    "name:ita_x_preferred":[
        "Almod\u00f3var del Pinar"
    ],
    "name:kaz_x_preferred":[
        "\u0410\u043b\u044c\u043c\u043e\u0434\u043e\u0432\u0430\u0440-\u0434\u0435\u043b\u044c-\u041f\u0438\u043d\u0430\u0440"
    ],
    "name:msa_x_preferred":[
        "Almod\u00f3var del Pinar"
    ],
    "name:nan_x_preferred":[
        "Almod\u00f3var del Pinar"
    ],
    "name:nld_x_preferred":[
        "Almod\u00f3var del Pinar"
    ],
    "name:oci_x_preferred":[
        "Almod\u00f3var del Pinar"
    ],
    "name:pol_x_preferred":[
        "Almod\u00f3var del Pinar"
    ],
    "name:rus_x_preferred":[
        "\u0410\u043b\u044c\u043c\u043e\u0434\u043e\u0432\u0430\u0440-\u0434\u0435\u043b\u044c-\u041f\u0438\u043d\u0430\u0440"
    ],
    "name:spa_x_preferred":[
        "Almod\u00f3var del Pinar"
    ],
    "name:sqi_x_preferred":[
        "Almod\u00f3var del Pinar"
    ],
    "name:ukr_x_preferred":[
        "\u0410\u043b\u044c\u043c\u043e\u0434\u043e\u0432\u0430\u0440-\u0434\u0435\u043b\u044c-\u041f\u0456\u043d\u0430\u0440"
    ],
    "name:vie_x_preferred":[
        "Almod\u00f3var del Pinar"
    ],
    "name:war_x_preferred":[
        "Almod\u00f3var del Pinar"
    ],
    "name:zho_x_preferred":[
        "\u963f\u5c14\u83ab\u591a\u74e6\u5c14\u5fb7\u5c14\u76ae\u7eb3\u5c14"
    ],
    "qs_pg:aaroncc":"ES",
    "qs_pg:gn_country":"ES",
    "qs_pg:gn_fcode":"PPLA3",
    "qs_pg:gn_pop":512,
    "qs_pg:name":"Almod\u00f3var del Pinar",
    "qs_pg:photos_9r":0,
    "qs_pg:photos_sr":0,
    "qs_pg:pop_sr":2,
    "qs_pg:qs_pg_placetype":"locality",
    "wof:name":"Almod\u00f3var del Pinar",
    "wof:placetype":"locality",
    "wof:population":512
},
  "geometry": {"coordinates":[-1.88333,39.71667],"type":"Point"}
}