{
  "type": "Feature",
  "properties": {
    "gn:admin1_code":"56",
    "gn:admin2_code":"T",
    "gn:admin3_code":"43153",
    "gn:asciiname":"La Marina",
    "gn:country_code":"ES",
    "gn:dem":17,
    "gn:feature_class":"P",
    "gn:feature_code":"PPL",
    "gn:name":"La Marina",
    "gn:population":0,
    "gn:timezone":"Europe/Madrid",
    "iso:country":"ES",
    "name:ceb_x_preferred":[
        "La Marina"
    ],
    "name:spa_x_preferred":[
        "La Marina"
    ],
    "name:swe_x_preferred":[
        "La Marina"
    ],
    "wof:name":"La Marina",
    "wof:placetype":"locality"
},
  "geometry": {"coordinates":[1.41775,41.15029000000001],"type":"Point"}
}