{
  "type": "Feature",
  "properties": {
    "iso:country":"ES",
    "qs:a0":"Espa\u00f1a",
    "qs:a1":"*Barcelona",
    "qs:a1r":"0Catalu\u00f1a",
    "qs:adm0":"Espa\u00f1a",
    "qs:la_lc":"*",
    "qs:level":"locality",
    "qs:loc":"Salut de Sabadell, la",
    "qs:loc_alt":"Salut de Sabadell, la",
    "qs:pop":0,
    "qs:type":"buffered point",
    "wd:elevation":190.0,
    "wd:population":207814,
    "wd:wordcount":1498,
    "wof:name":"Salut de Sabadell, la",
    "wof:placetype":"locality",
    "wof:population":207814
},
  "geometry": {"coordinates":[2.123491,41.565915],"type":"Point"}
}