{
  "type": "Feature",
  "properties": {
    "gn:admin1_code":"57",
    "gn:admin2_code":"BA",
    "gn:admin3_code":"06149",
    "gn:asciiname":"Villafranca de los Barros",
    "gn:country_code":"ES",
    "gn:dem":422,
    "gn:feature_class":"P",
    "gn:feature_code":"PPLA3",
    "gn:name":"Villafranca de los Barros",
    "gn:population":13356,
    "gn:timezone":"Europe/Madrid",
    "iso:country":"ES",
    "name:ara_x_preferred":[
        "\u0641\u064a\u0644\u0627\u0641\u0631\u0627\u0646\u0643\u0627 \u062f\u064a \u0644\u0648\u0633 \u0628\u0627\u0631\u0648\u0633"
    ],
    "name:azb_x_preferred":[
        "\u0628\u06cc\u06cc\u0627\u0641\u0631\u0627\u0646\u06a9\u0627 \u062f \u0644\u0633 \u0628\u0627\u0631\u0633"
    ],
    "name:fas_x_preferred":[
        "\u0628\u06cc\u06cc\u0627\u0641\u0631\u0627\u0646\u06a9\u0627 \u062f \u0644\u0633 \u0628\u0627\u0631\u0633"
    ],
    "name:hye_x_preferred":[
        "\u054e\u056b\u056c\u0575\u0561\u0586\u0580\u0561\u0576\u056f\u0561 \u0564\u0565 \u056c\u0578\u057d \u0532\u0561\u057c\u0578\u057d"
    ],
    "name:mkd_x_preferred":[
        "\u0412\u0438\u043b\u0458\u0430\u0444\u0440\u0430\u043d\u043a\u0430 \u0434\u0435 \u043b\u043e\u0441 \u0411\u0430\u0440\u043e\u0441"
    ],
    "wof:name":"Villafranca de los Barros",
    "wof:placetype":"locality",
    "wof:population":13356
},
  "geometry": {"coordinates":[-6.3381,38.56144000000001],"type":"Point"}
}