{
  "type": "Feature",
  "properties": {
    "gn:admin1_code":"57",
    "gn:admin2_code":"BA",
    "gn:admin3_code":"06149",
    "gn:asciiname":"Villafranca de los Barros",
    "gn:country_code":"ES",
    "gn:dem":422,
    "gn:feature_class":"P",
    "gn:feature_code":"PPLA3",
    "gn:name":"Villafranca de los Barros",
    "gn:population":13356,
    "gn:timezone":"Europe/Madrid",
    "iso:country":"ES",
    "wof:name":"Villafranca de los Barros",
    "wof:placetype":"locality",
    "wof:population":13356
},
  "geometry": {"coordinates":[-6.3381,38.56144000000001],"type":"Point"}
}