{
  "type": "Feature",
  "properties": {
    "gn:admin1_code":"58",
    "gn:admin2_code":"LU",
    "gn:admin3_code":"27040",
    "gn:asciiname":"Mato",
    "gn:country_code":"ES",
    "gn:dem":503,
    "gn:feature_class":"P",
    "gn:feature_code":"PPL",
    "gn:name":"Mato",
    "gn:population":0,
    "gn:timezone":"Europe/Madrid",
    "iso:country":"ES",
    "name:ceb_x_preferred":[
        "Mato"
    ],
    "name:deu_x_preferred":[
        "Mato"
    ],
    "name:fin_x_preferred":[
        "Mato"
    ],
    "name:fra_x_preferred":[
        "Mato"
    ],
    "name:glg_x_preferred":[
        "Mato"
    ],
    "name:ita_x_preferred":[
        "Mato"
    ],
    "name:por_x_preferred":[
        "Mato"
    ],
    "name:sqi_x_preferred":[
        "Mato"
    ],
    "name:swe_x_preferred":[
        "Mato"
    ],
    "name:ukr_x_preferred":[
        "\u041c\u0430\u0442\u0443"
    ],
    "wof:name":"Mato",
    "wof:placetype":"locality"
},
  "geometry": {"coordinates":[-7.93333,42.88333],"type":"Point"}
}