{
  "type": "Feature",
  "properties": {
    "gn:admin1_code":"58",
    "gn:admin2_code":"PO",
    "gn:admin3_code":"36017",
    "gn:asciiname":"Olives",
    "gn:cc2":"ES",
    "gn:country_code":"ES",
    "gn:dem":450,
    "gn:feature_class":"P",
    "gn:feature_code":"PPL",
    "gn:name":"Olives",
    "gn:population":0,
    "gn:timezone":"Europe/Madrid",
    "iso:country":"ES",
    "name:und_x_variant":[
        "Santa Mar\u00eda",
        "Olives"
    ],
    "wof:name":"Olives",
    "wof:placetype":"locality"
},
  "geometry": {"coordinates":[-8.38333,42.68333],"type":"Point"}
}