{
  "type": "Feature",
  "properties": {
    "gn:admin1_code":"55",
    "gn:admin2_code":"LE",
    "gn:admin3_code":"24152",
    "gn:asciiname":"San Martin del Agostedo",
    "gn:country_code":"ES",
    "gn:dem":923,
    "gn:feature_class":"P",
    "gn:feature_code":"PPL",
    "gn:name":"San Mart\u00edn del Agostedo",
    "gn:population":0,
    "gn:timezone":"Europe/Madrid",
    "iso:country":"ES",
    "name:und_x_variant":[
        "San Mart\u00edn del Agostedo"
    ],
    "wof:name":"San Martin del Agostedo",
    "wof:placetype":"locality"
},
  "geometry": {"coordinates":[-6.17475,42.43749],"type":"Point"}
}