{
  "type": "Feature",
  "properties": {
    "gn:gn_country":"ES",
    "gn:gn_fcode":"PPLA3",
    "gn:gn_pop":43,
    "gn:population":43,
    "iso:country":"ES",
    "name:ara_x_preferred":[
        "\u063a\u0631\u0627\u064a\u0633\u0627\u0644\u064a\u0646\u064a\u0627"
    ],
    "name:arg_x_preferred":[
        "Grisale\u00f1a"
    ],
    "name:cat_x_preferred":[
        "Grisale\u00f1a"
    ],
    "name:eng_x_preferred":[
        "Grisale\u00f1a"
    ],
    "name:eus_x_preferred":[
        "Grisale\u00f1a"
    ],
    "name:fas_x_preferred":[
        "\u06af\u0631\u06cc\u0633\u0627\u0644\u0646\u06cc\u0627"
    ],
    "name:fra_x_preferred":[
        "Grisale\u00f1a"
    ],
    "name:glg_x_preferred":[
        "Grisale\u00f1a"
    ],
    "name:haw_x_preferred":[
        "Grisale\u00f1a"
    ],
    "name:hun_x_preferred":[
        "Grisale\u00f1a"
    ],
    "name:ina_x_preferred":[
        "Grisale\u00f1a"
    ],
    "name:ita_x_preferred":[
        "Grisale\u00f1a"
    ],
    "name:lad_x_preferred":[
        "Grisale\u00f1a"
    ],
    "name:msa_x_preferred":[
        "Grisale\u00f1a"
    ],
    "name:nan_x_preferred":[
        "Grisale\u00f1a"
    ],
    "name:nld_x_preferred":[
        "Grisale\u00f1a"
    ],
    "name:oci_x_preferred":[
        "Grisale\u00f1a"
    ],
    "name:pol_x_preferred":[
        "Grisale\u00f1a"
    ],
    "name:por_x_preferred":[
        "Grisale\u00f1a"
    ],
    "name:rus_x_preferred":[
        "\u0413\u0440\u0438\u0441\u0430\u043b\u0435\u043d\u0438\u044f"
    ],
    "name:spa_x_preferred":[
        "Grisale\u00f1a"
    ],
    "name:swe_x_preferred":[
        "Grisale\u00f1a"
    ],
    "name:tpi_x_preferred":[
        "Grisale\u00f1a"
    ],
    "name:ukr_x_preferred":[
        "\u0413\u0440\u0456\u0441\u0430\u043b\u0435\u043d\u044c\u044f"
    ],
    "name:uzb_x_preferred":[
        "Grisale\u00f1a"
    ],
    "name:vie_x_preferred":[
        "Grisale\u00f1a"
    ],
    "name:war_x_preferred":[
        "Grisale\u00f1a"
    ],
    "name:zho_x_preferred":[
        "\u683c\u91cc\u8428\u83b1\u5c3c\u4e9a"
    ],
    "qs_pg:aaroncc":"ES",
    "qs_pg:gn_country":"ES",
    "qs_pg:gn_fcode":"PPLA3",
    "qs_pg:gn_pop":43,
    "qs_pg:name":"Grisale\u00f1a",
    "qs_pg:name_adm0":"Espa\u00f1a",
    "qs_pg:name_adm1":"Castilla y Le\u00f3n",
    "qs_pg:photos_9r":0,
    "qs_pg:photos_sr":0,
    "qs_pg:pop_sr":1,
    "qs_pg:qs_pg_placetype":"locality",
    "qs_pg:qs_pg_placetype_gp":"Town",
    "qs_pg:woe_adm0":23424950,
    "woe:adm0_id":23424950,
    "woe:name_adm0":"Espa\u00f1a",
    "woe:name_adm1":"Castilla y Le\u00f3n",
    "woe:placetype":"Town",
    "wof:name":"Grisale\u00f1a",
    "wof:placetype":"locality",
    "wof:population":43
},
  "geometry": {"coordinates":[-3.26416,42.59122],"type":"Point"}
}