{
  "type": "Feature",
  "properties": {
    "gn:admin1_code":"58",
    "gn:admin2_code":"C",
    "gn:admin3_code":"15046",
    "gn:asciiname":"Carballas",
    "gn:country_code":"ES",
    "gn:dem":561,
    "gn:feature_class":"P",
    "gn:feature_code":"PPL",
    "gn:name":"Carball\u00e1s",
    "gn:population":0,
    "gn:timezone":"Europe/Madrid",
    "iso:country":"ES",
    "name:und_x_variant":[
        "Carball\u00e1s",
        "La Cruz"
    ],
    "wof:name":"Carballas",
    "wof:placetype":"locality"
},
  "geometry": {"coordinates":[-8.09471,42.97476],"type":"Point"}
}