{
  "type": "Feature",
  "properties": {
    "gn:admin1_code":"56",
    "gn:admin2_code":"L",
    "gn:admin3_code":"25216",
    "gn:asciiname":"Sant Antoli i Vilanova",
    "gn:country_code":"ES",
    "gn:dem":583,
    "gn:feature_class":"P",
    "gn:feature_code":"PPL",
    "gn:name":"Sant Antol\u00ed i Vilanova",
    "gn:population":0,
    "gn:timezone":"Europe/Madrid",
    "iso:country":"ES",
    "wof:name":"Sant Antoli i Vilanova",
    "wof:placetype":"locality"
},
  "geometry": {"coordinates":[1.35,41.61667],"type":"Point"}
}