{
  "type": "Feature",
  "properties": {
    "gn:admin1_code":"55",
    "gn:admin2_code":"LE",
    "gn:admin3_code":"24027",
    "gn:asciiname":"El Teso",
    "gn:country_code":"ES",
    "gn:dem":580,
    "gn:feature_class":"P",
    "gn:feature_code":"PPL",
    "gn:name":"El Teso",
    "gn:population":0,
    "gn:timezone":"Europe/Madrid",
    "iso:country":"ES",
    "wof:name":"El Teso",
    "wof:placetype":"locality"
},
  "geometry": {"coordinates":[-6.63261,42.61649],"type":"Point"}
}