{
  "type": "Feature",
  "properties": {
    "gn:admin1_code":"54",
    "gn:admin2_code":"GU",
    "gn:admin3_code":"19257",
    "gn:asciiname":"Matas",
    "gn:country_code":"ES",
    "gn:dem":984,
    "gn:feature_class":"P",
    "gn:feature_code":"PPL",
    "gn:name":"Matas",
    "gn:population":0,
    "gn:timezone":"Europe/Madrid",
    "iso:country":"ES",
    "wof:name":"Matas",
    "wof:placetype":"locality"
},
  "geometry": {"coordinates":[-2.68333,41.11667],"type":"Point"}
}