{
  "type": "Feature",
  "properties": {
    "gn:gn_country":"ES",
    "gn:gn_fcode":"PPLA3",
    "gn:gn_pop":112,
    "gn:population":112,
    "iso:country":"ES",
    "name:ara_x_preferred":[
        "\u0633\u0627\u0646\u062a\u0648 \u062a\u0648\u0645\u064a \u062f\u064a \u062b\u0627\u0628\u0627\u0631\u0643\u0648\u0633"
    ],
    "name:bre_x_preferred":[
        "Santo Tom\u00e9 de Zabarcos"
    ],
    "name:cat_x_preferred":[
        "Santo Tom\u00e9 de Zabarcos"
    ],
    "name:deu_x_preferred":[
        "Santo Tom\u00e9 de Zabarcos"
    ],
    "name:eng_x_preferred":[
        "Santo Tom\u00e9 de Zabarcos"
    ],
    "name:eus_x_preferred":[
        "Santo Tom\u00e9 de Zabarcos"
    ],
    "name:fas_x_preferred":[
        "\u0633\u0627\u0646\u062a\u0648 \u062a\u0645\u0647 \u062f \u0633\u0627\u0628\u0627\u0631\u06a9\u0633"
    ],
    "name:fra_x_preferred":[
        "Santo Tom\u00e9 de Zabarcos"
    ],
    "name:hun_x_preferred":[
        "Santo Tom\u00e9 de Zabarcos"
    ],
    "name:ina_x_preferred":[
        "Santo Tom\u00e9 de Zabarcos"
    ],
    "name:ita_x_preferred":[
        "Santo Tom\u00e9 de Zabarcos"
    ],
    "name:kaz_x_preferred":[
        "\u0421\u0430\u043d\u0442\u043e-\u0422\u043e\u043c\u0435-\u0434\u0435-\u0421\u0430\u0431\u0430\u0440\u043a\u043e\u0441"
    ],
    "name:mkd_x_preferred":[
        "\u0421\u0430\u043d\u0442\u043e \u0422\u043e\u043c\u0435 \u0434\u0435 \u0417\u0430\u0431\u0430\u0440\u043a\u043e\u0441"
    ],
    "name:msa_x_preferred":[
        "Santo Tom\u00e9 de Zabarcos"
    ],
    "name:nld_x_preferred":[
        "Santo Tom\u00e9 de Zabarcos"
    ],
    "name:oci_x_preferred":[
        "Santo Tom\u00e9 de Zabarcos"
    ],
    "name:pol_x_preferred":[
        "Santo Tom\u00e9 de Zabarcos"
    ],
    "name:por_x_preferred":[
        "Santo Tom\u00e9 de Zabarcos"
    ],
    "name:rus_x_preferred":[
        "\u0421\u0430\u043d\u0442\u043e-\u0422\u043e\u043c\u0435-\u0434\u0435-\u0421\u0430\u0431\u0430\u0440\u043a\u043e\u0441"
    ],
    "name:spa_x_preferred":[
        "Santo Tom\u00e9 de Zabarcos"
    ],
    "name:swe_x_preferred":[
        "Santo Tom\u00e9 de Zabarcos"
    ],
    "name:ukr_x_preferred":[
        "\u0421\u0430\u043d\u0442\u043e-\u0422\u043e\u043c\u0435-\u0434\u0435-\u0421\u0430\u0431\u0430\u0440\u043a\u043e\u0441"
    ],
    "name:uzb_x_preferred":[
        "Santo Tom\u00e9 de Zabarcos"
    ],
    "name:vie_x_preferred":[
        "Santo Tom\u00e9 de Zabarcos"
    ],
    "name:war_x_preferred":[
        "Santo Tom\u00e9 de Zabarcos"
    ],
    "name:zho_x_preferred":[
        "\u6851\u6258\u6258\u6885\u5fb7\u8428\u74e6\u5c14\u79d1\u65af"
    ],
    "qs_pg:aaroncc":"ES",
    "qs_pg:gn_country":"ES",
    "qs_pg:gn_fcode":"PPLA3",
    "qs_pg:gn_pop":112,
    "qs_pg:name":"Santo Tom\u00e9 de Zabarcos",
    "qs_pg:name_adm0":"Espa\u00f1a",
    "qs_pg:name_adm1":"Castilla y Le\u00f3n",
    "qs_pg:photos_9r":0,
    "qs_pg:photos_sr":0,
    "qs_pg:pop_sr":1,
    "qs_pg:qs_pg_placetype":"locality",
    "qs_pg:qs_pg_placetype_gp":"Town",
    "qs_pg:woe_adm0":23424950,
    "woe:adm0_id":23424950,
    "woe:name_adm0":"Espa\u00f1a",
    "woe:name_adm1":"Castilla y Le\u00f3n",
    "woe:placetype":"Town",
    "wof:name":"Santo Tom\u00e9 de Zabarcos",
    "wof:placetype":"locality",
    "wof:population":112
},
  "geometry": {"coordinates":[-4.91048,40.78726],"type":"Point"}
}