{
  "type": "Feature",
  "properties": {
    "gn:gn_country":"ES",
    "gn:gn_fcode":"PPLA3",
    "gn:gn_pop":529,
    "gn:population":529,
    "iso:country":"ES",
    "name:arg_x_preferred":[
        "Loporzano"
    ],
    "name:cat_x_preferred":[
        "Loporzano"
    ],
    "name:ceb_x_preferred":[
        "Loporzano"
    ],
    "name:eng_x_preferred":[
        "Loporzano"
    ],
    "name:eus_x_preferred":[
        "Loporzano"
    ],
    "name:fra_x_preferred":[
        "Loporzano"
    ],
    "name:hak_x_preferred":[
        "Loporzano"
    ],
    "name:hun_x_preferred":[
        "Loporzano"
    ],
    "name:ita_x_preferred":[
        "Loporzano"
    ],
    "name:msa_x_preferred":[
        "Loporzano"
    ],
    "name:nan_x_preferred":[
        "Loporzano"
    ],
    "name:nld_x_preferred":[
        "Loporzano"
    ],
    "name:oci_x_preferred":[
        "Loporzano"
    ],
    "name:pol_x_preferred":[
        "Loporzano"
    ],
    "name:por_x_preferred":[
        "Loporzano"
    ],
    "name:rus_x_preferred":[
        "\u041b\u043e\u043f\u043e\u0440\u0441\u0430\u043d\u043e"
    ],
    "name:spa_x_preferred":[
        "Loporzano"
    ],
    "name:swe_x_preferred":[
        "Loporzano"
    ],
    "name:ukr_x_preferred":[
        "\u041b\u043e\u043f\u043e\u0440\u0441\u0430\u043d\u043e"
    ],
    "name:uzb_x_preferred":[
        "Loporzano"
    ],
    "name:war_x_preferred":[
        "Loporzano"
    ],
    "name:zho_x_preferred":[
        "\u6d1b\u6ce2\u5c14\u8428\u8bfa"
    ],
    "qs_pg:aaroncc":"ES",
    "qs_pg:gn_country":"ES",
    "qs_pg:gn_fcode":"PPLA3",
    "qs_pg:gn_pop":529,
    "qs_pg:name":"Loporzano",
    "qs_pg:name_adm0":"Espa\u00f1a",
    "qs_pg:name_adm1":"Arag\u00f3n",
    "qs_pg:photos":21,
    "qs_pg:photos_1k":4,
    "qs_pg:photos_9k":1,
    "qs_pg:photos_9r":1,
    "qs_pg:photos_all":21,
    "qs_pg:photos_sr":1,
    "qs_pg:pop_sr":2,
    "qs_pg:qs_pg_placetype":"locality",
    "qs_pg:qs_pg_placetype_gp":"Town",
    "qs_pg:woe_adm0":23424950,
    "woe:adm0_id":23424950,
    "woe:name_adm0":"Espa\u00f1a",
    "woe:name_adm1":"Arag\u00f3n",
    "woe:placetype":"Town",
    "wof:name":"Loporzano",
    "wof:placetype":"locality",
    "wof:population":529
},
  "geometry": {"coordinates":[-0.32337,42.16137],"type":"Point"}
}