{
  "type": "Feature",
  "properties": {
    "gn:admin1_code":"56",
    "gn:admin2_code":"GI",
    "gn:admin3_code":"17079",
    "gn:asciiname":"Sant Daniel",
    "gn:country_code":"ES",
    "gn:dem":174,
    "gn:feature_class":"P",
    "gn:feature_code":"PPL",
    "gn:name":"Sant Daniel",
    "gn:population":0,
    "gn:timezone":"Europe/Madrid",
    "iso:country":"ES",
    "wof:name":"Sant Daniel",
    "wof:placetype":"locality"
},
  "geometry": {"coordinates":[2.85,41.98333],"type":"Point"}
}