{
  "type": "Feature",
  "properties": {
    "gn:gn_country":"ES",
    "gn:gn_fcode":"PPLA3",
    "gn:gn_pop":42,
    "gn:population":42,
    "iso:country":"ES",
    "name:arg_x_preferred":[
        "Pazuengos"
    ],
    "name:bul_x_preferred":[
        "\u041f\u0430\u0437\u0443\u0435\u043d\u0433\u043e\u0441"
    ],
    "name:cat_x_preferred":[
        "Pazuengos"
    ],
    "name:ceb_x_preferred":[
        "Pazuengos"
    ],
    "name:deu_x_preferred":[
        "Pazuengos"
    ],
    "name:eng_x_preferred":[
        "Pazuengos"
    ],
    "name:eus_x_preferred":[
        "Pazuengos"
    ],
    "name:fra_x_preferred":[
        "Pazuengos"
    ],
    "name:hun_x_preferred":[
        "Pazuengos"
    ],
    "name:hye_x_preferred":[
        "\u054a\u0561\u057d\u0578\u0582\u0565\u0576\u0563\u0578\u057d"
    ],
    "name:ita_x_preferred":[
        "Pazuengos"
    ],
    "name:kaz_x_preferred":[
        "\u041f\u0430\u0441\u0443\u044d\u043d\u0433\u043e\u0441"
    ],
    "name:ltz_x_preferred":[
        "Pazuengos"
    ],
    "name:msa_x_preferred":[
        "Pazuengos"
    ],
    "name:nan_x_preferred":[
        "Pazuengos"
    ],
    "name:nld_x_preferred":[
        "Pazuengos"
    ],
    "name:oci_x_preferred":[
        "Pazuengos"
    ],
    "name:pol_x_preferred":[
        "Pazuengos"
    ],
    "name:por_x_preferred":[
        "Pazuengos"
    ],
    "name:rup_x_preferred":[
        "Pazuengos"
    ],
    "name:rus_x_preferred":[
        "\u041f\u0430\u0441\u0443\u044d\u043d\u0433\u043e\u0441"
    ],
    "name:spa_x_preferred":[
        "Pazuengos"
    ],
    "name:swe_x_preferred":[
        "Pazuengos"
    ],
    "name:ukr_x_preferred":[
        "\u041f\u0430\u0441\u0443\u0435\u043d\u0433\u043e\u0441"
    ],
    "name:uzb_x_preferred":[
        "Pazuengos"
    ],
    "name:vie_x_preferred":[
        "Pazuengos"
    ],
    "name:war_x_preferred":[
        "Pazuengos"
    ],
    "name:zho_x_preferred":[
        "\u5e15\u5b59\u6208\u65af"
    ],
    "qs_pg:aaroncc":"ES",
    "qs_pg:gn_country":"ES",
    "qs_pg:gn_fcode":"PPLA3",
    "qs_pg:gn_pop":42,
    "qs_pg:name":"Pazuengos",
    "qs_pg:name_adm0":"Espa\u00f1a",
    "qs_pg:name_adm1":"La Rioja",
    "qs_pg:photos_9k":1,
    "qs_pg:photos_9r":3,
    "qs_pg:photos_all":119,
    "qs_pg:photos_sr":0,
    "qs_pg:pop_sr":1,
    "qs_pg:qs_pg_placetype":"locality",
    "qs_pg:qs_pg_placetype_gp":"Town",
    "qs_pg:woe_adm0":23424950,
    "woe:adm0_id":23424950,
    "woe:name_adm0":"Espa\u00f1a",
    "woe:name_adm1":"La Rioja",
    "woe:placetype":"Town",
    "wof:name":"Pazuengos",
    "wof:placetype":"locality",
    "wof:population":42
},
  "geometry": {"coordinates":[-2.92539,42.31776],"type":"Point"}
}