{
  "type": "Feature",
  "properties": {
    "gn:admin1_code":"58",
    "gn:admin2_code":"C",
    "gn:admin3_code":"15052",
    "gn:asciiname":"Morquintian",
    "gn:country_code":"ES",
    "gn:dem":149,
    "gn:feature_class":"P",
    "gn:feature_code":"PPL",
    "gn:name":"Morquinti\u00e1n",
    "gn:population":0,
    "gn:timezone":"Europe/Madrid",
    "iso:country":"ES",
    "name:und_x_variant":[
        "Morquitians",
        "Morquinti\u00e1n"
    ],
    "wof:name":"Morquintian",
    "wof:placetype":"locality"
},
  "geometry": {"coordinates":[-9.23215,43.04723],"type":"Point"}
}