{
  "type": "Feature",
  "properties": {
    "gn:gn_country":"ES",
    "gn:gn_fcode":"PPLX",
    "gn:gn_pop":30228,
    "gn:population":30228,
    "iso:country":"ES",
    "qs_pg:aaroncc":"ES",
    "qs_pg:gn_country":"ES",
    "qs_pg:gn_fcode":"PPLX",
    "qs_pg:gn_pop":30228,
    "qs_pg:name":"Oliver-Valdefierro, Oliver, Valdefierro",
    "qs_pg:photos_9r":0,
    "qs_pg:photos_sr":0,
    "qs_pg:pop_sr":7,
    "qs_pg:qs_pg_placetype":"neighbourhood",
    "wof:name":"Oliver-Valdefierro, Oliver, Valdefierro",
    "wof:placetype":"neighbourhood",
    "wof:population":30228
},
  "geometry": {"coordinates":[-0.93349,41.64454],"type":"Point"}
}