{
  "type": "Feature",
  "properties": {
    "gn:admin1_code":"51",
    "gn:admin2_code":"AL",
    "gn:admin3_code":"04067",
    "gn:asciiname":"Tices",
    "gn:country_code":"ES",
    "gn:dem":1100,
    "gn:feature_class":"P",
    "gn:feature_code":"PPL",
    "gn:name":"Tices",
    "gn:population":0,
    "gn:timezone":"Europe/Madrid",
    "iso:country":"ES",
    "name:und_x_variant":[
        "Barriada Tices",
        "Tices"
    ],
    "wof:name":"Tices",
    "wof:placetype":"locality"
},
  "geometry": {"coordinates":[-2.73482,37.06207],"type":"Point"}
}