{
  "type": "Feature",
  "properties": {
    "gn:admin1_code":"59",
    "gn:admin2_code":"SS",
    "gn:admin3_code":"20025",
    "gn:asciiname":"Zuloagas",
    "gn:country_code":"ES",
    "gn:dem":387,
    "gn:feature_class":"P",
    "gn:feature_code":"PPL",
    "gn:name":"Zuloaga",
    "gn:population":0,
    "gn:timezone":"Europe/Madrid",
    "iso:country":"ES",
    "name:eus_x_preferred":[
        "Zulaaldea"
    ],
    "name:spa_x_preferred":[
        "Zuloagas"
    ],
    "wof:name":"Zuloagas",
    "wof:placetype":"locality"
},
  "geometry": {"coordinates":[-2.27722,42.98255],"type":"Point"}
}