{
  "type": "Feature",
  "properties": {
    "gn:admin1_code":"39",
    "gn:admin2_code":"S",
    "gn:admin3_code":"39060",
    "gn:asciiname":"Valles",
    "gn:country_code":"ES",
    "gn:dem":60,
    "gn:feature_class":"P",
    "gn:feature_code":"PPL",
    "gn:name":"Valles",
    "gn:population":0,
    "gn:timezone":"Europe/Madrid",
    "iso:country":"ES",
    "name:arg_x_preferred":[
        "Vall\u00e9s"
    ],
    "name:ceb_x_preferred":[
        "Valles"
    ],
    "name:deu_x_preferred":[
        "Valles"
    ],
    "name:fra_x_preferred":[
        "Valles"
    ],
    "name:nld_x_preferred":[
        "Valles"
    ],
    "name:spa_x_preferred":[
        "Vall\u00e9s"
    ],
    "name:swe_x_preferred":[
        "Valles"
    ],
    "wof:name":"Valles",
    "wof:placetype":"locality"
},
  "geometry": {"coordinates":[-4.11565,43.35155],"type":"Point"}
}