{
  "type": "Feature",
  "properties": {
    "gn:admin1_code":"34",
    "gn:admin2_code":"O",
    "gn:admin3_code":"33028",
    "gn:asciiname":"Boiro",
    "gn:country_code":"ES",
    "gn:dem":606,
    "gn:feature_class":"P",
    "gn:feature_code":"PPL",
    "gn:name":"Boiro",
    "gn:population":0,
    "gn:timezone":"Europe/Madrid",
    "iso:country":"ES",
    "name:ara_x_preferred":[
        "\u0628\u0648\u064a\u0631\u0648"
    ],
    "name:azb_x_preferred":[
        "\u0628\u0648\u06cc\u0631\u0648"
    ],
    "name:bre_x_preferred":[
        "Boiro"
    ],
    "name:cat_x_preferred":[
        "Boiro"
    ],
    "name:ceb_x_preferred":[
        "Boiro"
    ],
    "name:deu_x_preferred":[
        "Boiro"
    ],
    "name:eus_x_preferred":[
        "Boiro"
    ],
    "name:fas_x_preferred":[
        "\u0628\u0648\u06cc\u0631\u0648"
    ],
    "name:fra_x_preferred":[
        "Boiro"
    ],
    "name:glg_x_preferred":[
        "Boiro"
    ],
    "name:hun_x_preferred":[
        "Boiro"
    ],
    "name:hye_x_preferred":[
        "\u0532\u0578\u0575\u0580\u0578"
    ],
    "name:ita_x_preferred":[
        "Boiro"
    ],
    "name:jpn_x_preferred":[
        "\u30dc\u30a4\u30ed"
    ],
    "name:lmo_x_preferred":[
        "Boiro"
    ],
    "name:mkd_x_preferred":[
        "\u0411\u043e\u0438\u0440\u043e"
    ],
    "name:msa_x_preferred":[
        "Boiro"
    ],
    "name:nld_x_preferred":[
        "Boiro"
    ],
    "name:oci_x_preferred":[
        "Boiro"
    ],
    "name:pam_x_preferred":[
        "Boiro"
    ],
    "name:pol_x_preferred":[
        "Boiro"
    ],
    "name:por_x_preferred":[
        "Boiro"
    ],
    "name:rus_x_preferred":[
        "\u0411\u043e\u0439\u0440\u043e"
    ],
    "name:spa_x_preferred":[
        "Boiro"
    ],
    "name:swe_x_preferred":[
        "Boiro"
    ],
    "name:tur_x_preferred":[
        "Boiro"
    ],
    "name:ukr_x_preferred":[
        "\u0411\u043e\u0439\u0440\u043e"
    ],
    "name:uzb_x_preferred":[
        "Boiro"
    ],
    "name:vie_x_preferred":[
        "Boiro"
    ],
    "name:war_x_preferred":[
        "Boiro"
    ],
    "name:zho_x_preferred":[
        "\u535a\u4f0a\u7f57"
    ],
    "wof:name":"Boiro",
    "wof:placetype":"locality"
},
  "geometry": {"coordinates":[-6.85089,42.99875],"type":"Point"}
}