{
  "type": "Feature",
  "properties": {
    "gn:admin1_code":"32",
    "gn:admin3_code":"31050",
    "gn:asciiname":"Ariztegui de Garzain",
    "gn:country_code":"ES",
    "gn:dem":206,
    "gn:feature_class":"P",
    "gn:feature_code":"PPL",
    "gn:name":"Ariztegui de Garz\u00e1in",
    "gn:population":0,
    "gn:timezone":"Europe/Madrid",
    "iso:country":"ES",
    "wof:name":"Ariztegui de Garzain",
    "wof:placetype":"locality"
},
  "geometry": {"coordinates":[-1.52579,43.13374],"type":"Point"}
}