{
  "type": "Feature",
  "properties": {
    "gn:admin1_code":"57",
    "gn:admin2_code":"BA",
    "gn:admin3_code":"06063",
    "gn:asciiname":"Helechosa",
    "gn:country_code":"ES",
    "gn:dem":439,
    "gn:feature_class":"P",
    "gn:feature_code":"PPL",
    "gn:name":"Helechosa",
    "gn:population":792,
    "gn:timezone":"Europe/Madrid",
    "iso:country":"ES",
    "wof:name":"Helechosa",
    "wof:placetype":"locality",
    "wof:population":792
},
  "geometry": {"coordinates":[-4.9085,39.3117],"type":"Point"}
}