{
  "type": "Feature",
  "properties": {
    "gn:admin1_code":"58",
    "gn:admin2_code":"C",
    "gn:admin3_code":"15019",
    "gn:asciiname":"Queo de Abaixo",
    "gn:country_code":"ES",
    "gn:dem":132,
    "gn:feature_class":"P",
    "gn:feature_code":"PPL",
    "gn:name":"Queo de Abaixo",
    "gn:population":0,
    "gn:timezone":"Europe/Madrid",
    "iso:country":"ES",
    "wof:name":"Queo de Abaixo",
    "wof:placetype":"locality"
},
  "geometry": {"coordinates":[-8.65281,43.23592],"type":"Point"}
}