{
  "type": "Feature",
  "properties": {
    "gn:country":"ES",
    "gn:fcode":"PPLA3",
    "gn:population":155,
    "iso:country":"ES",
    "name:ara_x_preferred":[
        "\u0645\u062d\u0645\u0648\u062f"
    ],
    "name:arg_x_preferred":[
        "Mahamud"
    ],
    "name:arz_x_preferred":[
        "\u0645\u062d\u0645\u0648\u062f"
    ],
    "name:ast_x_preferred":[
        "Mahamud"
    ],
    "name:azb_x_preferred":[
        "\u0645\u0627\u0647\u0627\u0645\u0648\u062f"
    ],
    "name:cat_x_preferred":[
        "Mahamud"
    ],
    "name:ceb_x_preferred":[
        "Mahamud"
    ],
    "name:che_x_preferred":[
        "\u041c\u0430\u0430\u043c\u0443\u0434"
    ],
    "name:deu_x_preferred":[
        "Mahamud"
    ],
    "name:eng_x_preferred":[
        "Mahamud"
    ],
    "name:epo_x_preferred":[
        "Mahamud"
    ],
    "name:eus_x_preferred":[
        "Mahamud"
    ],
    "name:fas_x_preferred":[
        "\u0645\u0627\u0647\u0627\u0645\u0648\u062f"
    ],
    "name:fra_x_preferred":[
        "Mahamud"
    ],
    "name:gle_x_preferred":[
        "Mahamud"
    ],
    "name:glg_x_preferred":[
        "Mahamud"
    ],
    "name:haw_x_preferred":[
        "Mahamud"
    ],
    "name:hun_x_preferred":[
        "Mahamud"
    ],
    "name:ile_x_preferred":[
        "Mahamud"
    ],
    "name:ina_x_preferred":[
        "Mahamud"
    ],
    "name:ita_x_preferred":[
        "Mahamud"
    ],
    "name:lld_x_preferred":[
        "Mahamud"
    ],
    "name:msa_x_preferred":[
        "Mahamud"
    ],
    "name:nan_x_preferred":[
        "Mahamud"
    ],
    "name:nld_x_preferred":[
        "Mahamud"
    ],
    "name:nob_x_preferred":[
        "Mahamud"
    ],
    "name:oci_x_preferred":[
        "Mahamud"
    ],
    "name:pol_x_preferred":[
        "Mahamud"
    ],
    "name:por_x_preferred":[
        "Mahamud"
    ],
    "name:rus_x_preferred":[
        "\u041c\u0430\u0430\u043c\u0443\u0434"
    ],
    "name:spa_x_preferred":[
        "Mahamud"
    ],
    "name:swe_x_preferred":[
        "Mahamud"
    ],
    "name:tat_x_preferred":[
        "\u041c\u0430\u0430\u043c\u0443\u0434"
    ],
    "name:ukr_x_preferred":[
        "\u041c\u0430\u0430\u043c\u0443\u0434"
    ],
    "name:vec_x_preferred":[
        "Mahamud"
    ],
    "name:vie_x_preferred":[
        "Mahamud"
    ],
    "name:war_x_preferred":[
        "Mahamud"
    ],
    "name:zho_x_preferred":[
        "\u9a6c\u963f\u7a46\u5fb7"
    ],
    "qs_pg:aaroncc":"ES",
    "qs_pg:gn_country":"ES",
    "qs_pg:gn_fcode":"PPLA3",
    "qs_pg:gn_pop":155,
    "qs_pg:name":"Mahamud",
    "qs_pg:name_adm0":"Espa\u00f1a",
    "qs_pg:name_adm1":"Castilla y Le\u00f3n",
    "qs_pg:photos_9r":0,
    "qs_pg:photos_sr":0,
    "qs_pg:pop_sr":1,
    "qs_pg:qs_pg_placetype":"locality",
    "qs_pg:qs_pg_placetype_gp":"Town",
    "qs_pg:woe_adm0":23424950,
    "woe:adm0_id":23424950,
    "woe:name_adm0":"Espa\u00f1a",
    "woe:name_adm1":"Castilla y Le\u00f3n",
    "woe:placetype":"Town",
    "wof:name":"Mahamud",
    "wof:placetype":"locality",
    "wof:population":155
},
  "geometry": {"coordinates":[-3.9406,42.11981],"type":"Point"}
}