{
  "type": "Feature",
  "properties": {
    "gn:gn_country":"ES",
    "gn:gn_fcode":"PPLA3",
    "gn:gn_pop":58,
    "gn:population":58,
    "iso:country":"ES",
    "name:ara_x_preferred":[
        "\u0633\u0627\u0646 \u0644\u0648\u0631\u064a\u0646\u062b\u0648 \u062f\u064a \u062a\u0648\u0631\u0645\u064a\u0633"
    ],
    "name:azb_x_preferred":[
        "\u0633\u0627\u0646 \u0644\u0631\u0646\u0633\u0648 \u062f \u062a\u0631\u0645\u0633"
    ],
    "name:cat_x_preferred":[
        "San Lorenzo de Tormes"
    ],
    "name:eng_x_preferred":[
        "San Lorenzo de Tormes"
    ],
    "name:eus_x_preferred":[
        "San Lorenzo de Tormes"
    ],
    "name:fas_x_preferred":[
        "\u0633\u0627\u0646 \u0644\u0631\u0646\u0633\u0648 \u062f \u062a\u0631\u0645\u0633"
    ],
    "name:fra_x_preferred":[
        "San Lorenzo de Tormes"
    ],
    "name:hun_x_preferred":[
        "San Lorenzo de Tormes"
    ],
    "name:ina_x_preferred":[
        "San Lorenzo de Tormes"
    ],
    "name:ita_x_preferred":[
        "San Lorenzo de Tormes"
    ],
    "name:kaz_x_preferred":[
        "\u0421\u0430\u043d-\u041b\u043e\u0440\u0435\u043d\u0441\u043e-\u0434\u0435-\u0422\u043e\u0440\u043c\u0435\u0441"
    ],
    "name:mkd_x_preferred":[
        "\u0421\u0430\u043d \u041b\u043e\u0440\u0435\u043d\u0446\u043e \u0434\u0435\u043b \u0422\u043e\u0440\u043c\u0435\u0441"
    ],
    "name:msa_x_preferred":[
        "San Lorenzo de Tormes"
    ],
    "name:nld_x_preferred":[
        "San Lorenzo de Tormes"
    ],
    "name:oci_x_preferred":[
        "San Lorenzo de Tormes"
    ],
    "name:pol_x_preferred":[
        "San Lorenzo de Tormes"
    ],
    "name:por_x_preferred":[
        "San Lorenzo de Tormes"
    ],
    "name:rus_x_preferred":[
        "\u0421\u0430\u043d-\u041b\u043e\u0440\u0435\u043d\u0441\u043e-\u0434\u0435-\u0422\u043e\u0440\u043c\u0435\u0441"
    ],
    "name:spa_x_preferred":[
        "Lorenzo de Tormes"
    ],
    "name:swe_x_preferred":[
        "San Lorenzo de Tormes"
    ],
    "name:ukr_x_preferred":[
        "\u0421\u0430\u043d-\u041b\u043e\u0440\u0435\u043d\u0441\u043e-\u0434\u0435-\u0422\u043e\u0440\u043c\u0435\u0441"
    ],
    "name:uzb_x_preferred":[
        "San Lorenzo de Tormes"
    ],
    "name:vie_x_preferred":[
        "San Lorenzo de Tormes"
    ],
    "name:war_x_preferred":[
        "San Lorenzo de Tormes"
    ],
    "name:zho_x_preferred":[
        "\u5723\u6d1b\u4f26\u7d22\u5fb7\u6258\u5c14\u6885\u65af"
    ],
    "qs_pg:aaroncc":"ES",
    "qs_pg:gn_country":"ES",
    "qs_pg:gn_fcode":"PPLA3",
    "qs_pg:gn_pop":58,
    "qs_pg:name":"San Lorenzo de Tormes",
    "qs_pg:name_adm0":"Espa\u00f1a",
    "qs_pg:name_adm1":"Castilla y Le\u00f3n",
    "qs_pg:photos_9r":0,
    "qs_pg:photos_sr":0,
    "qs_pg:pop_sr":1,
    "qs_pg:qs_pg_placetype":"locality",
    "qs_pg:qs_pg_placetype_gp":"Town",
    "qs_pg:woe_adm0":23424950,
    "woe:adm0_id":23424950,
    "woe:name_adm0":"Espa\u00f1a",
    "woe:name_adm1":"Castilla y Le\u00f3n",
    "woe:placetype":"Town",
    "wof:name":"San Lorenzo de Tormes",
    "wof:placetype":"locality",
    "wof:population":58
},
  "geometry": {"coordinates":[-5.48848,40.36984],"type":"Point"}
}