{
  "type": "Feature",
  "properties": {
    "gn:admin1_code":"51",
    "gn:admin2_code":"GR",
    "gn:admin3_code":"18061",
    "gn:asciiname":"Cortijada Noniles",
    "gn:country_code":"ES",
    "gn:dem":769,
    "gn:feature_class":"P",
    "gn:feature_code":"PPL",
    "gn:name":"Cortijada Noniles",
    "gn:population":0,
    "gn:timezone":"Europe/Madrid",
    "iso:country":"ES",
    "name:und_x_variant":[
        "Cortijo de Nonites",
        "Cortijada Noniles"
    ],
    "wof:name":"Cortijada Noniles",
    "wof:placetype":"locality"
},
  "geometry": {"coordinates":[-3.81267,37.09944],"type":"Point"}
}