{
  "type": "Feature",
  "properties": {
    "gn:admin1_code":"58",
    "gn:admin2_code":"C",
    "gn:admin3_code":"15037",
    "gn:asciiname":"Insua",
    "gn:country_code":"ES",
    "gn:dem":53,
    "gn:feature_class":"P",
    "gn:feature_code":"PPL",
    "gn:name":"Insua",
    "gn:population":0,
    "gn:timezone":"Europe/Madrid",
    "iso:country":"ES",
    "wof:name":"Insua",
    "wof:placetype":"locality"
},
  "geometry": {"coordinates":[-9.26843,42.90533],"type":"Point"}
}