{
  "type": "Feature",
  "properties": {
    "gn:admin1_code":"58",
    "gn:admin2_code":"C",
    "gn:admin3_code":"15061",
    "gn:asciiname":"Veiga",
    "gn:country_code":"ES",
    "gn:dem":2,
    "gn:feature_class":"P",
    "gn:feature_code":"PPL",
    "gn:name":"Veiga",
    "gn:population":0,
    "gn:timezone":"Europe/Madrid",
    "iso:country":"ES",
    "name:cat_x_preferred":[
        "Veiga"
    ],
    "name:deu_x_preferred":[
        "Veiga"
    ],
    "name:fra_x_preferred":[
        "Veiga"
    ],
    "name:glg_x_preferred":[
        "Veiga"
    ],
    "name:por_x_preferred":[
        "Veiga"
    ],
    "name:rus_x_preferred":[
        "\u0412\u0435\u0439\u0433\u0430"
    ],
    "name:spa_x_preferred":[
        "Veiga"
    ],
    "wof:name":"Veiga",
    "wof:placetype":"locality"
},
  "geometry": {"coordinates":[-7.88333,43.68333],"type":"Point"}
}