{
  "type": "Feature",
  "properties": {
    "gn:admin1_code":"58",
    "gn:admin2_code":"C",
    "gn:admin3_code":"15061",
    "gn:asciiname":"Veiga",
    "gn:country_code":"ES",
    "gn:dem":2,
    "gn:feature_class":"P",
    "gn:feature_code":"PPL",
    "gn:name":"Veiga",
    "gn:population":0,
    "gn:timezone":"Europe/Madrid",
    "iso:country":"ES",
    "wof:name":"Veiga",
    "wof:placetype":"locality"
},
  "geometry": {"coordinates":[-7.88333,43.68333],"type":"Point"}
}