{
  "type": "Feature",
  "properties": {
    "iso:country":"ES",
    "name:eng_x_preferred":[
        "Los Chocales"
    ],
    "name:spa_x_preferred":[
        "Los Chocales"
    ],
    "wof:name":"Los Chocales",
    "wof:placetype":"neighbourhood"
},
  "geometry": {"coordinates":[-4.47323998220944,36.66423662106664],"type":"Point"}
}