{
  "type": "Feature",
  "properties": {
    "gn:admin1_code":"34",
    "gn:admin2_code":"O",
    "gn:admin3_code":"33015",
    "gn:asciiname":"La Foz",
    "gn:country_code":"ES",
    "gn:dem":669,
    "gn:feature_class":"P",
    "gn:feature_code":"PPL",
    "gn:name":"La Foz",
    "gn:population":0,
    "gn:timezone":"Europe/Madrid",
    "iso:country":"ES",
    "name:ast_x_preferred":[
        "La Foz"
    ],
    "name:deu_x_preferred":[
        "La Foz"
    ],
    "name:spa_x_preferred":[
        "La Foz"
    ],
    "name:urd_x_preferred":[
        "\u0644\u0627 \u0641\u0648\u0632"
    ],
    "wof:name":"La Foz",
    "wof:placetype":"locality"
},
  "geometry": {"coordinates":[-5.27934,43.1499],"type":"Point"}
}