{
  "type": "Feature",
  "properties": {
    "gn:admin1_code":"59",
    "gn:admin2_code":"SS",
    "gn:admin3_code":"20043",
    "gn:asciiname":"Etxegarate",
    "gn:country_code":"ES",
    "gn:dem":694,
    "gn:feature_class":"P",
    "gn:feature_code":"PPL",
    "gn:name":"Etxegarate",
    "gn:population":0,
    "gn:timezone":"Europe/Madrid",
    "iso:country":"ES",
    "name:eus_x_preferred":[
        "Etxegarate"
    ],
    "name:spa_x_preferred":[
        "Echegarate"
    ],
    "wof:name":"Etxegarate",
    "wof:placetype":"locality"
},
  "geometry": {"coordinates":[-2.22512,42.95066],"type":"Point"}
}