{
  "type": "Feature",
  "properties": {
    "gn:gn_country":"ES",
    "gn:gn_fcode":"PPLA3",
    "gn:gn_pop":126,
    "gn:population":126,
    "iso:country":"ES",
    "name:ara_x_preferred":[
        "\u0647\u0648\u0631\u062a\u0627\u064a\u063a\u0648\u064a\u0644\u0627"
    ],
    "name:arg_x_preferred":[
        "Hortig\u00fcela"
    ],
    "name:ast_x_preferred":[
        "Hortig\u00fcela"
    ],
    "name:azb_x_preferred":[
        "\u0627\u0648\u0631\u062a\u06cc\u0642\u0644\u0627"
    ],
    "name:cat_x_preferred":[
        "Hortig\u00fcela"
    ],
    "name:ceb_x_preferred":[
        "Hortig\u00fcela"
    ],
    "name:deu_x_preferred":[
        "Hortig\u00fcela"
    ],
    "name:eng_x_preferred":[
        "Hortig\u00fcela"
    ],
    "name:epo_x_preferred":[
        "Hortig\u00fcela"
    ],
    "name:eus_x_preferred":[
        "Hortig\u00fcela"
    ],
    "name:fas_x_preferred":[
        "\u0647\u0631\u062a\u06cc\u06af\u0644\u0627"
    ],
    "name:fra_x_preferred":[
        "Hortig\u00fcela"
    ],
    "name:glg_x_preferred":[
        "Hortig\u00fcela"
    ],
    "name:haw_x_preferred":[
        "Hortig\u00fcela"
    ],
    "name:hun_x_preferred":[
        "Hortig\u00fcela"
    ],
    "name:ina_x_preferred":[
        "Hortig\u00fcela"
    ],
    "name:ita_x_preferred":[
        "Hortig\u00fcela"
    ],
    "name:msa_x_preferred":[
        "Hortig\u00fcela"
    ],
    "name:nan_x_preferred":[
        "Hortig\u00fcela"
    ],
    "name:nld_x_preferred":[
        "Hortig\u00fcela"
    ],
    "name:oci_x_preferred":[
        "Hortig\u00fcela"
    ],
    "name:pol_x_preferred":[
        "Hortig\u00fcela"
    ],
    "name:por_x_preferred":[
        "Hortig\u00fcela"
    ],
    "name:rus_x_preferred":[
        "\u041e\u0440\u0442\u0438\u0433\u0443\u044d\u043b\u0430"
    ],
    "name:spa_x_preferred":[
        "Hortig\u00fcela"
    ],
    "name:swe_x_preferred":[
        "Hortig\u00fcela"
    ],
    "name:ukr_x_preferred":[
        "\u041e\u0440\u0442\u0456\u0433\u0443\u0435\u043b\u0430"
    ],
    "name:vie_x_preferred":[
        "Hortig\u00fcela"
    ],
    "name:war_x_preferred":[
        "Hortig\u00fcela"
    ],
    "name:zho_x_preferred":[
        "\u5965\u5c14\u8482\u683c\u62c9"
    ],
    "qs_pg:aaroncc":"ES",
    "qs_pg:gn_country":"ES",
    "qs_pg:gn_fcode":"PPLA3",
    "qs_pg:gn_pop":126,
    "qs_pg:name":"Hortig\u00fcela",
    "qs_pg:name_adm0":"Espa\u00f1a",
    "qs_pg:name_adm1":"Castilla y Le\u00f3n",
    "qs_pg:photos":95,
    "qs_pg:photos_1k":19,
    "qs_pg:photos_9k":1,
    "qs_pg:photos_9r":3,
    "qs_pg:photos_all":95,
    "qs_pg:photos_sr":3,
    "qs_pg:pop_sr":1,
    "qs_pg:qs_pg_placetype":"locality",
    "qs_pg:qs_pg_placetype_gp":"Town",
    "qs_pg:woe_adm0":23424950,
    "woe:adm0_id":23424950,
    "woe:name_adm0":"Espa\u00f1a",
    "woe:name_adm1":"Castilla y Le\u00f3n",
    "woe:placetype":"Town",
    "wof:name":"Hortig\u00fcela",
    "wof:placetype":"locality",
    "wof:population":126
},
  "geometry": {"coordinates":[-3.42578,42.06842],"type":"Point"}
}