{
  "type": "Feature",
  "properties": {
    "gn:admin1_code":"55",
    "gn:admin2_code":"LE",
    "gn:admin3_code":"24005",
    "gn:asciiname":"Grajal de Ribera",
    "gn:cc2":"ES",
    "gn:country_code":"ES",
    "gn:dem":779,
    "gn:feature_class":"P",
    "gn:feature_code":"PPL",
    "gn:name":"Grajal de Ribera",
    "gn:population":0,
    "gn:timezone":"Europe/Madrid",
    "iso:country":"ES",
    "name:und_x_variant":[
        "Grajal",
        "Grajal de Ribera"
    ],
    "wof:name":"Grajal de Ribera",
    "wof:placetype":"locality"
},
  "geometry": {"coordinates":[-5.61667,42.18333],"type":"Point"}
}