{
  "type": "Feature",
  "properties": {
    "gn:admin1_code":"58",
    "gn:admin2_code":"LU",
    "gn:admin3_code":"27012",
    "gn:asciiname":"Robledo",
    "gn:country_code":"ES",
    "gn:dem":823,
    "gn:feature_class":"P",
    "gn:feature_code":"PPL",
    "gn:name":"Robledo",
    "gn:population":0,
    "gn:timezone":"Europe/Madrid",
    "iso:country":"ES",
    "name:ceb_x_preferred":[
        "Robledo"
    ],
    "name:deu_x_preferred":[
        "Robledo"
    ],
    "name:glg_x_preferred":[
        "Robledo"
    ],
    "name:ita_x_preferred":[
        "Robledo"
    ],
    "name:rus_x_preferred":[
        "\u0420\u043e\u0431\u043b\u0435\u0434\u043e"
    ],
    "name:slk_x_preferred":[
        "Robledo"
    ],
    "name:spa_x_preferred":[
        "Robledo"
    ],
    "name:swe_x_preferred":[
        "Robledo"
    ],
    "name:ukr_x_preferred":[
        "\u0420\u043e\u0431\u043b\u0435\u0434\u043e"
    ],
    "wof:name":"Robledo",
    "wof:placetype":"locality"
},
  "geometry": {"coordinates":[-6.91674,42.84801],"type":"Point"}
}