{
  "type": "Feature",
  "properties": {
    "gn:gn_country":"ES",
    "gn:gn_fcode":"PPLA3",
    "gn:gn_pop":157,
    "gn:population":157,
    "iso:country":"ES",
    "name:arg_x_preferred":[
        "Castrillo de Duero"
    ],
    "name:cat_x_preferred":[
        "Castrillo de Duero"
    ],
    "name:eng_x_preferred":[
        "Castrillo de Duero"
    ],
    "name:eus_x_preferred":[
        "Castrillo de Duero"
    ],
    "name:fra_x_preferred":[
        "Castrillo de Duero"
    ],
    "name:hun_x_preferred":[
        "Castrillo de Duero"
    ],
    "name:hye_x_preferred":[
        "\u053f\u0561\u057d\u057f\u0580\u056b\u056c\u0575\u0578 \u0564\u0565 \u0534\u0578\u0582\u0565\u0580\u0578"
    ],
    "name:ina_x_preferred":[
        "Castrillo de Duero"
    ],
    "name:ita_x_preferred":[
        "Castrillo de Duero"
    ],
    "name:msa_x_preferred":[
        "Castrillo de Duero"
    ],
    "name:nld_x_preferred":[
        "Castrillo de Duero"
    ],
    "name:oci_x_preferred":[
        "Castrillo de Duero"
    ],
    "name:pol_x_preferred":[
        "Castrillo de Duero"
    ],
    "name:por_x_preferred":[
        "Castrillo de Duero"
    ],
    "name:rus_x_preferred":[
        "\u041a\u0430\u0441\u0442\u0440\u0438\u043b\u044c\u043e-\u0434\u0435-\u0414\u0443\u044d\u0440\u043e"
    ],
    "name:spa_x_preferred":[
        "Castrillo de Duero"
    ],
    "name:swe_x_preferred":[
        "Castrillo de Duero"
    ],
    "name:ukr_x_preferred":[
        "\u041a\u0430\u0441\u0442\u0440\u0456\u043b\u044c\u0439\u043e-\u0434\u0435-\u0414\u0443\u0435\u0440\u043e"
    ],
    "name:uzb_x_preferred":[
        "Castrillo de Duero"
    ],
    "name:war_x_preferred":[
        "Castrillo de Duero"
    ],
    "name:zho_x_preferred":[
        "\u5361\u65af\u7279\u91cc\u7565\u5fb7\u675c\u57c3\u7f57"
    ],
    "qs_pg:aaroncc":"ES",
    "qs_pg:gn_country":"ES",
    "qs_pg:gn_fcode":"PPLA3",
    "qs_pg:gn_pop":157,
    "qs_pg:name":"Castrillo de Duero",
    "qs_pg:name_adm0":"Espa\u00f1a",
    "qs_pg:name_adm1":"Castilla y Le\u00f3n",
    "qs_pg:photos_9k":1,
    "qs_pg:photos_9r":1,
    "qs_pg:photos_all":2,
    "qs_pg:photos_sr":0,
    "qs_pg:pop_sr":1,
    "qs_pg:qs_pg_placetype":"locality",
    "qs_pg:qs_pg_placetype_gp":"Town",
    "qs_pg:woe_adm0":23424950,
    "woe:adm0_id":23424950,
    "woe:name_adm0":"Espa\u00f1a",
    "woe:name_adm1":"Castilla y Le\u00f3n",
    "woe:placetype":"Town",
    "wof:name":"Castrillo de Duero",
    "wof:placetype":"locality",
    "wof:population":157
},
  "geometry": {"coordinates":[-4.01547,41.57494],"type":"Point"}
}