{
  "type": "Feature",
  "properties": {
    "gn:population":1153,
    "iso:country":"ES",
    "name:ara_x_preferred":[
        "\u0641\u064a\u0644\u0627\u0644\u0628\u0627\u0631\u062f\u0648"
    ],
    "name:arg_x_preferred":[
        "Villalpardo"
    ],
    "name:ast_x_preferred":[
        "Villalpardo"
    ],
    "name:cat_x_preferred":[
        "Villalpardo"
    ],
    "name:ceb_x_preferred":[
        "Villalpardo"
    ],
    "name:eng_x_preferred":[
        "Villalpardo"
    ],
    "name:epo_x_preferred":[
        "Villalpardo"
    ],
    "name:eus_x_preferred":[
        "Villalpardo"
    ],
    "name:fra_x_preferred":[
        "Villalpardo"
    ],
    "name:hun_x_preferred":[
        "Villalpardo"
    ],
    "name:ita_x_preferred":[
        "Villalpardo"
    ],
    "name:kaz_x_preferred":[
        "\u0412\u0438\u043b\u044c\u044f\u043b\u044c\u043f\u0430\u0440\u0434\u043e"
    ],
    "name:msa_x_preferred":[
        "Villalpardo"
    ],
    "name:nan_x_preferred":[
        "Villalpardo"
    ],
    "name:nld_x_preferred":[
        "Villalpardo"
    ],
    "name:oci_x_preferred":[
        "Villalpardo"
    ],
    "name:pol_x_preferred":[
        "Villalpardo"
    ],
    "name:por_x_preferred":[
        "Villalpardo"
    ],
    "name:rus_x_preferred":[
        "\u0412\u0438\u043b\u044c\u044f\u043b\u044c\u043f\u0430\u0440\u0434\u043e"
    ],
    "name:spa_x_preferred":[
        "Villalpardo"
    ],
    "name:swe_x_preferred":[
        "Villalpardo"
    ],
    "name:ukr_x_preferred":[
        "\u0412\u0456\u043b\u044c\u044f\u043b\u044c\u043f\u0430\u0440\u0434\u043e"
    ],
    "name:vie_x_preferred":[
        "Villalpardo"
    ],
    "name:war_x_preferred":[
        "Villalpardo"
    ],
    "name:zho_min_nan_x_preferred":[
        "Villalpardo"
    ],
    "name:zho_x_preferred":[
        "\u6bd4\u5229\u4e9a\u5c14\u5e15\u5c14\u591a"
    ],
    "qs:a0":"Espa\u00f1a",
    "qs:a1":"*Cuenca",
    "qs:a1r":"0Castilla-La Mancha",
    "qs:adm0":"Espa\u00f1a",
    "qs:la_lc":"*",
    "qs:level":"locality",
    "qs:loc":"Villalpardo",
    "qs:loc_alt":"Villalpardo",
    "qs:pop":0,
    "qs:type":"buffered point",
    "wd:wordcount":45,
    "wof:lang":[
        "spa"
    ],
    "wof:name":"Villalpardo",
    "wof:placetype":"locality",
    "wof:population":1153
},
  "geometry": {"coordinates":[-1.623648,39.47184],"type":"Point"}
}