{
  "type": "Feature",
  "properties": {
    "gn:admin1_code":"07",
    "gn:admin2_code":"PM",
    "gn:admin3_code":"7002.0",
    "gn:asciiname":"Torre Soli Nou",
    "gn:country_code":"ES",
    "gn:dem":69,
    "gn:feature_class":"P",
    "gn:feature_code":"PPL",
    "gn:name":"Torre Soli Nou",
    "gn:population":0,
    "gn:timezone":"Europe/Madrid",
    "iso:country":"ES",
    "name:spa_x_preferred":[
        "Torre Sol\u00ed Nou"
    ],
    "wof:name":"Torre Soli Nou",
    "wof:placetype":"locality"
},
  "geometry": {"coordinates":[4.07335,39.9075],"type":"Point"}
}