{
  "type": "Feature",
  "properties": {
    "iso:country":"ES",
    "name:spa_x_colloquial":[
        "La Rabita"
    ],
    "name:spa_x_preferred":[
        "La R\u00e1bita"
    ],
    "qs:a0":"Espa\u00f1a",
    "qs:a1":"*Granada",
    "qs:a1r":"0Andaluc\u00eda",
    "qs:adm0":"Espa\u00f1a",
    "qs:la_lc":"*",
    "qs:level":"locality",
    "qs:loc":"R\u00e1bita,La",
    "qs:loc_alt":"Rabita,La",
    "qs:pop":0,
    "qs:type":"buffered point",
    "wof:name":"R\u00e1bita,La",
    "wof:placetype":"locality"
},
  "geometry": {"coordinates":[-3.170689,36.74834],"type":"Point"}
}