{
  "type": "Feature",
  "properties": {
    "gn:admin1_code":"39",
    "gn:admin2_code":"S",
    "gn:admin3_code":"39075",
    "gn:asciiname":"Penacastillo",
    "gn:country_code":"ES",
    "gn:dem":36,
    "gn:feature_class":"P",
    "gn:feature_code":"PPL",
    "gn:name":"Pe\u00f1acastillo",
    "gn:population":0,
    "gn:timezone":"Europe/Madrid",
    "iso:country":"ES",
    "name:und_x_variant":[
        "Pe\u00f1acastillo"
    ],
    "wof:name":"Penacastillo",
    "wof:placetype":"locality"
},
  "geometry": {"coordinates":[-3.86757,43.44537],"type":"Point"}
}