{
  "type": "Feature",
  "properties": {
    "gn:admin1_code":"58",
    "gn:admin2_code":"LU",
    "gn:admin3_code":"27057",
    "gn:asciiname":"Vilamaior",
    "gn:country_code":"ES",
    "gn:dem":605,
    "gn:feature_class":"P",
    "gn:feature_code":"PPL",
    "gn:name":"Vilamaior",
    "gn:population":0,
    "gn:timezone":"Europe/Madrid",
    "iso:country":"ES",
    "wof:name":"Vilamaior",
    "wof:placetype":"locality"
},
  "geometry": {"coordinates":[-7.5143,42.72961],"type":"Point"}
}