{
  "type": "Feature",
  "properties": {
    "gn:admin1_code":"55",
    "gn:admin2_code":"LE",
    "gn:admin3_code":"24004",
    "gn:asciiname":"Castromudarra",
    "gn:country_code":"ES",
    "gn:dem":931,
    "gn:feature_class":"P",
    "gn:feature_code":"PPL",
    "gn:name":"Castromudarra",
    "gn:population":0,
    "gn:timezone":"Europe/Madrid",
    "iso:country":"ES",
    "wof:name":"Castromudarra",
    "wof:placetype":"locality"
},
  "geometry": {"coordinates":[-5.06197,42.61228],"type":"Point"}
}