{
  "type": "Feature",
  "properties": {
    "gn:admin1_code":"58",
    "gn:admin2_code":"PO",
    "gn:admin3_code":"36061",
    "gn:asciiname":"Caleiro",
    "gn:country_code":"ES",
    "gn:dem":13,
    "gn:feature_class":"P",
    "gn:feature_code":"PPL",
    "gn:name":"Caleiro",
    "gn:population":0,
    "gn:timezone":"Europe/Madrid",
    "iso:country":"ES",
    "wof:name":"Caleiro",
    "wof:placetype":"locality"
},
  "geometry": {"coordinates":[-8.81021,42.5607],"type":"Point"}
}