{
  "type": "Feature",
  "properties": {
    "gn:country":"ES",
    "gn:fcode":"PPLA3",
    "gn:population":0,
    "iso:country":"ES",
    "name:arg_x_preferred":[
        "Els Pallaresos"
    ],
    "name:ast_x_preferred":[
        "Els Pallaresos"
    ],
    "name:azb_x_preferred":[
        "\u0627\u0644\u0633 \u067e\u0627\u06cc\u0627\u0631\u0633\u0633"
    ],
    "name:cat_x_preferred":[
        "els Pallaresos"
    ],
    "name:ceb_x_preferred":[
        "Els Pallaresos"
    ],
    "name:eng_x_preferred":[
        "Els Pallaresos"
    ],
    "name:eus_x_preferred":[
        "Els Pallaresos"
    ],
    "name:fas_x_preferred":[
        "\u0627\u0644\u0633 \u067e\u0627\u06cc\u0627\u0631\u0633\u0633"
    ],
    "name:fra_x_preferred":[
        "Els Pallaresos"
    ],
    "name:glg_x_preferred":[
        "Els Pallaresos"
    ],
    "name:hun_x_preferred":[
        "Els Pallaresos"
    ],
    "name:hye_x_preferred":[
        "\u0537\u056c \u054a\u0561\u056c\u0575\u0561\u0580\u0565\u057d\u0578\u057d"
    ],
    "name:ita_x_preferred":[
        "Els Pallaresos"
    ],
    "name:lat_x_preferred":[
        "Els Pallaresos"
    ],
    "name:msa_x_preferred":[
        "Els Pallaresos"
    ],
    "name:nld_x_preferred":[
        "Els Pallaresos"
    ],
    "name:oci_x_preferred":[
        "Els Pallaresos"
    ],
    "name:pol_x_preferred":[
        "Els Pallaresos"
    ],
    "name:por_x_preferred":[
        "Els Pallaresos"
    ],
    "name:rus_x_preferred":[
        "\u042d\u043b\u044c\u0441-\u041f\u0430\u043b\u044c\u044f\u0440\u0435\u0441\u043e\u0441"
    ],
    "name:spa_x_preferred":[
        "Pallaresos"
    ],
    "name:sqi_x_preferred":[
        "Els Pallaresos"
    ],
    "name:swe_x_preferred":[
        "Els Pallaresos"
    ],
    "name:uzb_x_preferred":[
        "Pallaresos"
    ],
    "name:vie_x_preferred":[
        "Els Pallaresos"
    ],
    "name:war_x_preferred":[
        "Els Pallaresos"
    ],
    "name:zho_x_preferred":[
        "\u57c3\u5c14\u65af\u5e15\u5229\u4e9a\u96f7\u7d22\u65af"
    ],
    "qs_pg:aaroncc":"ES",
    "qs_pg:gn_country":"ES",
    "qs_pg:gn_fcode":"PPLA3",
    "qs_pg:gn_pop":0,
    "qs_pg:name":"Pallaresos",
    "qs_pg:name_adm0":"Espa\u00f1a",
    "qs_pg:name_adm1":"Catalunya",
    "qs_pg:photos":60,
    "qs_pg:photos_1k":12,
    "qs_pg:photos_9k":1,
    "qs_pg:photos_9r":2,
    "qs_pg:photos_all":60,
    "qs_pg:photos_sr":2,
    "qs_pg:pop_sr":0,
    "qs_pg:qs_pg_placetype":"locality",
    "qs_pg:qs_pg_placetype_gp":"Town",
    "qs_pg:woe_adm0":23424950,
    "woe:adm0_id":23424950,
    "woe:name_adm0":"Espa\u00f1a",
    "woe:name_adm1":"Catalunya",
    "woe:placetype":"Town",
    "wof:name":"Pallaresos",
    "wof:placetype":"locality",
    "wof:population":3991
},
  "geometry": {"coordinates":[1.26667,41.16667],"type":"Point"}
}