{
  "type": "Feature",
  "properties": {
    "gn:admin1_code":"34",
    "gn:admin2_code":"O",
    "gn:admin3_code":"33022",
    "gn:asciiname":"Cerredo",
    "gn:country_code":"ES",
    "gn:dem":1027,
    "gn:feature_class":"P",
    "gn:feature_code":"PPL",
    "gn:name":"Cerredo",
    "gn:population":867,
    "gn:timezone":"Europe/Madrid",
    "iso:country":"ES",
    "name:ast_x_preferred":[
        "Zarr\u00e9u"
    ],
    "name:cat_x_preferred":[
        "Zarr\u00e9u"
    ],
    "name:ceb_x_preferred":[
        "Cerredo"
    ],
    "name:deu_x_preferred":[
        "Cerredo"
    ],
    "name:spa_x_preferred":[
        "Cerredo"
    ],
    "wof:name":"Cerredo",
    "wof:placetype":"locality",
    "wof:population":867
},
  "geometry": {"coordinates":[-6.48956,42.9466],"type":"Point"}
}