{
  "type": "Feature",
  "properties": {
    "gn:admin1_code":"58",
    "gn:admin2_code":"OR",
    "gn:admin3_code":"32030",
    "gn:asciiname":"Venceas",
    "gn:country_code":"ES",
    "gn:dem":832,
    "gn:feature_class":"P",
    "gn:feature_code":"PPL",
    "gn:name":"Vence\u00e1s",
    "gn:population":0,
    "gn:timezone":"Europe/Madrid",
    "iso:country":"ES",
    "wof:name":"Venceas",
    "wof:placetype":"locality"
},
  "geometry": {"coordinates":[-8.09737,41.96316],"type":"Point"}
}