{
  "type": "Feature",
  "properties": {
    "gn:admin1_code":"52",
    "gn:admin2_code":"Z",
    "gn:admin3_code":"50243",
    "gn:asciiname":"Viver de la Sierra",
    "gn:country_code":"ES",
    "gn:dem":908,
    "gn:feature_class":"P",
    "gn:feature_code":"PPL",
    "gn:name":"Viver de la Sierra",
    "gn:population":0,
    "gn:timezone":"Europe/Madrid",
    "iso:country":"ES",
    "wof:name":"Viver de la Sierra",
    "wof:placetype":"locality"
},
  "geometry": {"coordinates":[-1.63742,41.47473],"type":"Point"}
}