{
  "type": "Feature",
  "properties": {
    "iso:country":"ES",
    "wof:name":"San Roque",
    "wof:placetype":"neighbourhood"
},
  "geometry": {"coordinates":[-5.98217413552531,37.39067269341107],"type":"Point"}
}