{
  "type": "Feature",
  "properties": {
    "iso:country":"ES",
    "name:ara_x_preferred":[
        "\u0633\u0627\u0646 \u0631\u0648\u062c"
    ],
    "name:ast_x_preferred":[
        "San Roque"
    ],
    "name:bre_x_preferred":[
        "San Roque"
    ],
    "name:ceb_x_preferred":[
        "San Roque"
    ],
    "name:deu_x_preferred":[
        "San Roque"
    ],
    "name:eus_x_preferred":[
        "San Roque"
    ],
    "name:fra_x_preferred":[
        "San Roque"
    ],
    "name:glg_x_preferred":[
        "San Roque"
    ],
    "name:hun_x_preferred":[
        "San Roque"
    ],
    "name:ita_x_preferred":[
        "San Roque"
    ],
    "name:jpn_x_preferred":[
        "\u30b5\u30f3\u30fb\u30ed\u30b1"
    ],
    "name:mlg_x_preferred":[
        "San Roque"
    ],
    "name:msa_x_preferred":[
        "San Roque"
    ],
    "name:nld_x_preferred":[
        "San Roque"
    ],
    "name:por_x_preferred":[
        "San Roque"
    ],
    "name:rus_x_preferred":[
        "\u0421\u0430\u043d-\u0420\u043e\u043a\u0435"
    ],
    "name:slk_x_preferred":[
        "San Roque"
    ],
    "name:spa_x_preferred":[
        "San Roque"
    ],
    "name:swe_x_preferred":[
        "San Roque"
    ],
    "name:ukr_x_preferred":[
        "\u0421\u0430\u043d-\u0420\u043e\u043a\u0435"
    ],
    "name:vie_x_preferred":[
        "San Roque"
    ],
    "name:war_x_preferred":[
        "San Roque"
    ],
    "wof:name":"San Roque",
    "wof:placetype":"neighbourhood"
},
  "geometry": {"coordinates":[-5.98217413552531,37.39067269341107],"type":"Point"}
}