{
  "type": "Feature",
  "properties": {
    "gn:admin1_code":"55",
    "gn:admin2_code":"LE",
    "gn:admin3_code":"24116",
    "gn:asciiname":"Los Llanos",
    "gn:country_code":"ES",
    "gn:dem":924,
    "gn:feature_class":"P",
    "gn:feature_code":"PPL",
    "gn:name":"Los Llanos",
    "gn:population":0,
    "gn:timezone":"Europe/Madrid",
    "iso:country":"ES",
    "wof:name":"Los Llanos",
    "wof:placetype":"locality"
},
  "geometry": {"coordinates":[-4.91616,43.15456],"type":"Point"}
}