{
  "type": "Feature",
  "properties": {
    "gn:admin1_code":"52",
    "gn:admin2_code":"HU",
    "gn:admin3_code":"22023",
    "gn:asciiname":"Frula",
    "gn:country_code":"ES",
    "gn:dem":361,
    "gn:feature_class":"P",
    "gn:feature_code":"PPL",
    "gn:name":"Frula",
    "gn:population":0,
    "gn:timezone":"Europe/Madrid",
    "iso:country":"ES",
    "name:hrv_x_preferred":[
        "Frula"
    ],
    "name:ita_x_preferred":[
        "Dvojnice"
    ],
    "name:srp_x_preferred":[
        "\u0424\u0440\u0443\u043b\u0430"
    ],
    "wof:name":"Frula",
    "wof:placetype":"locality"
},
  "geometry": {"coordinates":[-0.44801,41.91043],"type":"Point"}
}