{
  "type": "Feature",
  "properties": {
    "gn:admin1_code":"53",
    "gn:admin2_code":"GC",
    "gn:admin3_code":"35028",
    "gn:asciiname":"Conil",
    "gn:country_code":"ES",
    "gn:dem":272,
    "gn:feature_class":"P",
    "gn:feature_code":"PPL",
    "gn:name":"Conil",
    "gn:population":0,
    "gn:timezone":"Atlantic/Canary",
    "iso:country":"ES",
    "wof:name":"Conil",
    "wof:placetype":"locality"
},
  "geometry": {"coordinates":[-13.67203,28.96614000000001],"type":"Point"}
}