{
  "type": "Feature",
  "properties": {
    "gn:admin1_code":"59",
    "gn:admin2_code":"VI",
    "gn:admin3_code":"01042",
    "gn:asciiname":"Molinar",
    "gn:country_code":"ES",
    "gn:dem":79,
    "gn:feature_class":"P",
    "gn:feature_code":"PPL",
    "gn:name":"Molinar",
    "gn:population":0,
    "gn:timezone":"Europe/Madrid",
    "iso:country":"ES",
    "wof:name":"Molinar",
    "wof:placetype":"locality"
},
  "geometry": {"coordinates":[-3.07432,43.18022],"type":"Point"}
}