{
  "type": "Feature",
  "properties": {
    "gn:admin1_code":"58",
    "gn:admin2_code":"LU",
    "gn:admin3_code":"27028",
    "gn:asciiname":"Mera",
    "gn:cc2":"ES",
    "gn:country_code":"ES",
    "gn:dem":548,
    "gn:feature_class":"P",
    "gn:feature_code":"PPL",
    "gn:name":"Mera",
    "gn:population":0,
    "gn:timezone":"Europe/Madrid",
    "iso:country":"ES",
    "name:bel_x_preferred":[
        "\u041c\u0435\u0440\u0430"
    ],
    "name:bre_x_preferred":[
        "Mera"
    ],
    "name:cat_x_preferred":[
        "Mera"
    ],
    "name:ceb_x_preferred":[
        "Mera"
    ],
    "name:ces_x_preferred":[
        "Mera"
    ],
    "name:deu_x_preferred":[
        "Mera"
    ],
    "name:fra_x_preferred":[
        "Mera"
    ],
    "name:glg_x_preferred":[
        "Mera"
    ],
    "name:hun_x_preferred":[
        "Mera"
    ],
    "name:ita_x_preferred":[
        "Mera"
    ],
    "name:nld_x_preferred":[
        "Mera"
    ],
    "name:pol_x_preferred":[
        "Mera"
    ],
    "name:por_x_preferred":[
        "Mera"
    ],
    "name:ron_x_preferred":[
        "Mera"
    ],
    "name:rus_x_preferred":[
        "\u041c\u0435\u0440\u0430"
    ],
    "name:spa_x_preferred":[
        "Mera"
    ],
    "name:srp_x_preferred":[
        "\u041c\u0435\u0440\u0430"
    ],
    "name:swe_x_preferred":[
        "Mera"
    ],
    "name:und_x_variant":[
        "San Pedro"
    ],
    "name:vie_x_preferred":[
        "Mera"
    ],
    "wof:name":"Mera",
    "wof:placetype":"locality"
},
  "geometry": {"coordinates":[-7.71667,42.96667],"type":"Point"}
}