{
  "type": "Feature",
  "properties": {
    "gn:gn_country":"ES",
    "gn:gn_fcode":"PPL",
    "gn:gn_pop":0,
    "iso:country":"ES",
    "name:cat_x_preferred":[
        "Portals Nous"
    ],
    "name:deu_x_preferred":[
        "Portals Nous"
    ],
    "name:eng_x_preferred":[
        "Portals Nous"
    ],
    "name:fra_x_preferred":[
        "Portals Nous"
    ],
    "name:nld_x_preferred":[
        "Portals Nous"
    ],
    "name:pol_x_preferred":[
        "Portals Nous"
    ],
    "name:spa_x_preferred":[
        "Portals Nous"
    ],
    "name:swe_x_preferred":[
        "Portals Nous"
    ],
    "qs_pg:aaroncc":"ES",
    "qs_pg:gn_country":"ES",
    "qs_pg:gn_fcode":"PPL",
    "qs_pg:gn_pop":0,
    "qs_pg:name":"Portals Nous",
    "qs_pg:name_adm0":"Espa\u00f1a",
    "qs_pg:name_adm1":"Illes Balears",
    "qs_pg:photos":1184,
    "qs_pg:photos_1k":240,
    "qs_pg:photos_9k":5,
    "qs_pg:photos_9r":7,
    "qs_pg:photos_all":1184,
    "qs_pg:photos_sr":11,
    "qs_pg:pop_sr":0,
    "qs_pg:qs_pg_placetype":"locality",
    "qs_pg:qs_pg_placetype_gp":"Town",
    "qs_pg:woe_adm0":23424950,
    "woe:adm0_id":23424950,
    "woe:name_adm0":"Espa\u00f1a",
    "woe:name_adm1":"Illes Balears",
    "woe:placetype":"Town",
    "wof:name":"Portals Nous",
    "wof:placetype":"locality"
},
  "geometry": {"coordinates":[2.57029,39.53397],"type":"Point"}
}