{
  "type": "Feature",
  "properties": {
    "gn:admin1_code":"59",
    "gn:admin2_code":"VI",
    "gn:admin3_code":"01046",
    "gn:asciiname":"Ormijana",
    "gn:country_code":"ES",
    "gn:dem":621,
    "gn:feature_class":"P",
    "gn:feature_code":"PPL",
    "gn:name":"Ormijana",
    "gn:population":0,
    "gn:timezone":"Europe/Madrid",
    "iso:country":"ES",
    "name:eus_x_preferred":[
        "Urbilana"
    ],
    "name:spa_x_preferred":[
        "Ormijana"
    ],
    "wof:name":"Ormijana",
    "wof:placetype":"locality"
},
  "geometry": {"coordinates":[-2.93196,42.83405],"type":"Point"}
}