{
  "type": "Feature",
  "properties": {
    "gn:admin1_code":"55",
    "gn:admin2_code":"LE",
    "gn:admin3_code":"24011",
    "gn:asciiname":"Moldes",
    "gn:country_code":"ES",
    "gn:dem":881,
    "gn:feature_class":"P",
    "gn:feature_code":"PPL",
    "gn:name":"Moldes",
    "gn:population":0,
    "gn:timezone":"Europe/Madrid",
    "iso:country":"ES",
    "name:spa_x_preferred":[
        "Moldes"
    ],
    "wof:name":"Moldes",
    "wof:placetype":"locality"
},
  "geometry": {"coordinates":[-6.96117,42.63352],"type":"Point"}
}