{
  "type": "Feature",
  "properties": {
    "gn:admin1_code":"53",
    "gn:admin2_code":"TF",
    "gn:admin3_code":"38038",
    "gn:asciiname":"El Meson",
    "gn:country_code":"ES",
    "gn:dem":188,
    "gn:feature_class":"P",
    "gn:feature_code":"PPL",
    "gn:name":"El Mes\u00f3n",
    "gn:population":0,
    "gn:timezone":"Atlantic/Canary",
    "iso:country":"ES",
    "wof:name":"El Meson",
    "wof:placetype":"locality"
},
  "geometry": {"coordinates":[-16.20754,28.52212],"type":"Point"}
}