{
  "type": "Feature",
  "properties": {
    "gn:admin1_code":"55",
    "gn:admin2_code":"LE",
    "gn:admin3_code":"24201",
    "gn:asciiname":"San Vicente del Condado",
    "gn:country_code":"ES",
    "gn:dem":843,
    "gn:feature_class":"P",
    "gn:feature_code":"PPL",
    "gn:name":"San Vicente del Condado",
    "gn:population":0,
    "gn:timezone":"Europe/Madrid",
    "iso:country":"ES",
    "wof:name":"San Vicente del Condado",
    "wof:placetype":"locality"
},
  "geometry": {"coordinates":[-5.3693,42.64213],"type":"Point"}
}