{
  "type": "Feature",
  "properties": {
    "gn:admin1_code":"34",
    "gn:admin2_code":"O",
    "gn:admin3_code":"33033",
    "gn:asciiname":"Pineda de Abajo",
    "gn:country_code":"ES",
    "gn:dem":600,
    "gn:feature_class":"P",
    "gn:feature_code":"PPL",
    "gn:name":"Pi\u00f1eda de Abajo",
    "gn:population":0,
    "gn:timezone":"Europe/Madrid",
    "iso:country":"ES",
    "name:und_x_variant":[
        "Pi\u00f1era de Abajo",
        "Pi\u00f1eda de Abajo"
    ],
    "wof:name":"Pineda de Abajo",
    "wof:placetype":"locality"
},
  "geometry": {"coordinates":[-5.82395,43.05347],"type":"Point"}
}