{
  "type": "Feature",
  "properties": {
    "gn:gn_country":"ES",
    "gn:gn_fcode":"PPLA3",
    "gn:gn_pop":41,
    "gn:population":41,
    "iso:country":"ES",
    "name:arg_x_preferred":[
        "Torm\u00f3n"
    ],
    "name:baq_x_preferred":[
        "Torm\u00f3n"
    ],
    "name:cat_x_preferred":[
        "Torm\u00f3n"
    ],
    "name:chi_x_preferred":[
        "\u6258\u5c14\u8499"
    ],
    "name:dut_x_preferred":[
        "Torm\u00f3n"
    ],
    "name:eng_x_preferred":[
        "Torm\u00f3n"
    ],
    "name:fre_x_preferred":[
        "Torm\u00f3n"
    ],
    "name:glg_x_preferred":[
        "Torm\u00f3n"
    ],
    "name:hun_x_preferred":[
        "Torm\u00f3n"
    ],
    "name:ita_x_preferred":[
        "Torm\u00f3n"
    ],
    "name:kaz_x_preferred":[
        "\u0422\u043e\u0440\u043c\u043e\u043d"
    ],
    "name:may_x_preferred":[
        "Torm\u00f3n"
    ],
    "name:nan_x_preferred":[
        "Torm\u00f3n"
    ],
    "name:oci_x_preferred":[
        "Torm\u00f3n"
    ],
    "name:pol_x_preferred":[
        "Torm\u00f3n"
    ],
    "name:por_x_preferred":[
        "Torm\u00f3n"
    ],
    "name:rus_x_preferred":[
        "\u0422\u043e\u0440\u043c\u043e\u043d"
    ],
    "name:spa_x_preferred":[
        "Torm\u00f3n"
    ],
    "name:ukr_x_preferred":[
        "\u0422\u043e\u0440\u043c\u043e\u043d"
    ],
    "name:uzb_x_preferred":[
        "Torm\u00f3n"
    ],
    "name:vie_x_preferred":[
        "Torm\u00f3n"
    ],
    "name:war_x_preferred":[
        "Torm\u00f3n"
    ],
    "qs_pg:aaroncc":"ES",
    "qs_pg:gn_country":"ES",
    "qs_pg:gn_fcode":"PPLA3",
    "qs_pg:gn_pop":41,
    "qs_pg:name":"Torm\u00f3n",
    "qs_pg:name_adm0":"Espa\u00f1a",
    "qs_pg:name_adm1":"Arag\u00f3n",
    "qs_pg:photos_9k":1,
    "qs_pg:photos_9r":1,
    "qs_pg:photos_all":2,
    "qs_pg:photos_sr":0,
    "qs_pg:pop_sr":1,
    "qs_pg:qs_pg_placetype":"locality",
    "qs_pg:qs_pg_placetype_gp":"Town",
    "qs_pg:woe_adm0":23424950,
    "woe:adm0_id":23424950,
    "woe:name_adm0":"Espa\u00f1a",
    "woe:name_adm1":"Arag\u00f3n",
    "woe:placetype":"Town",
    "wof:name":"Torm\u00f3n",
    "wof:placetype":"locality",
    "wof:population":41
},
  "geometry": {"coordinates":[-1.35406,40.20266],"type":"Point"}
}