{
  "type": "Feature",
  "properties": {
    "gn:admin1_code":"55",
    "gn:admin2_code":"AV",
    "gn:admin3_code":"05041",
    "gn:asciiname":"Palancar de Abajo",
    "gn:country_code":"ES",
    "gn:dem":984,
    "gn:feature_class":"P",
    "gn:feature_code":"PPL",
    "gn:name":"Palancar de Abajo",
    "gn:population":0,
    "gn:timezone":"Europe/Madrid",
    "iso:country":"ES",
    "name:und_x_variant":[
        "Caser\u00edo Palancar de Abajo",
        "Palancar de Abajo"
    ],
    "wof:name":"Palancar de Abajo",
    "wof:placetype":"locality"
},
  "geometry": {"coordinates":[-4.75632,40.3793],"type":"Point"}
}