{
  "type": "Feature",
  "properties": {
    "gn:admin1_code":"54",
    "gn:admin2_code":"GU",
    "gn:admin3_code":"19053",
    "gn:asciiname":"Tomellosa",
    "gn:country_code":"ES",
    "gn:dem":798,
    "gn:feature_class":"P",
    "gn:feature_code":"PPL",
    "gn:name":"Tomellosa",
    "gn:population":0,
    "gn:timezone":"Europe/Madrid",
    "iso:country":"ES",
    "wof:name":"Tomellosa",
    "wof:placetype":"locality"
},
  "geometry": {"coordinates":[-2.92556,40.65107],"type":"Point"}
}