{
  "type": "Feature",
  "properties": {
    "gn:admin1_code":"58",
    "gn:admin2_code":"C",
    "gn:admin3_code":"15071",
    "gn:asciiname":"Xuno",
    "gn:country_code":"ES",
    "gn:dem":35,
    "gn:feature_class":"P",
    "gn:feature_code":"PPL",
    "gn:name":"Xu\u00f1o",
    "gn:population":0,
    "gn:timezone":"Europe/Madrid",
    "iso:country":"ES",
    "wof:name":"Xuno",
    "wof:placetype":"locality"
},
  "geometry": {"coordinates":[-9.03333,42.63333],"type":"Point"}
}