{
  "type": "Feature",
  "properties": {
    "gn:admin1_code":"57",
    "gn:admin2_code":"CC",
    "gn:admin3_code":"10086",
    "gn:asciiname":"La Granja",
    "gn:country_code":"ES",
    "gn:dem":418,
    "gn:feature_class":"P",
    "gn:feature_code":"PPL",
    "gn:name":"La Granja",
    "gn:population":0,
    "gn:timezone":"Europe/Madrid",
    "iso:country":"ES",
    "wof:name":"La Granja",
    "wof:placetype":"locality"
},
  "geometry": {"coordinates":[-5.99481,40.23935],"type":"Point"}
}