{
  "type": "Feature",
  "properties": {
    "gn:admin1_code":"57",
    "gn:admin2_code":"CC",
    "gn:admin3_code":"10086",
    "gn:asciiname":"La Granja",
    "gn:country_code":"ES",
    "gn:dem":418,
    "gn:feature_class":"P",
    "gn:feature_code":"PPL",
    "gn:name":"La Granja",
    "gn:population":0,
    "gn:timezone":"Europe/Madrid",
    "iso:country":"ES",
    "name:ara_x_preferred":[
        "\u0644\u0627 \u063a\u0631\u0627\u0646\u062e\u0627"
    ],
    "name:cat_x_preferred":[
        "La Granja"
    ],
    "name:epo_x_preferred":[
        "La Granja"
    ],
    "name:eus_x_preferred":[
        "La Granja"
    ],
    "name:fra_x_preferred":[
        "La Granja"
    ],
    "name:hun_x_preferred":[
        "La Granja"
    ],
    "name:ina_x_preferred":[
        "La Granja"
    ],
    "name:ita_x_preferred":[
        "La Granja"
    ],
    "name:msa_x_preferred":[
        "La Granja"
    ],
    "name:nld_x_preferred":[
        "La Granja"
    ],
    "name:oci_x_preferred":[
        "La Granja"
    ],
    "name:pol_x_preferred":[
        "La Granja"
    ],
    "name:por_x_preferred":[
        "La Granja"
    ],
    "name:ron_x_preferred":[
        "La Granja"
    ],
    "name:rus_x_preferred":[
        "\u041b\u0430-\u0413\u0440\u0430\u043d\u0445\u0430"
    ],
    "name:spa_x_preferred":[
        "La Granja"
    ],
    "name:ukr_x_preferred":[
        "\u041b\u0430-\u0413\u0440\u0430\u043d\u0445\u0430"
    ],
    "name:vie_x_preferred":[
        "La Granja"
    ],
    "name:war_x_preferred":[
        "La Granja"
    ],
    "name:zho_x_preferred":[
        "\u62c9\u683c\u5170\u54c8"
    ],
    "wof:name":"La Granja",
    "wof:placetype":"locality"
},
  "geometry": {"coordinates":[-5.99481,40.23935],"type":"Point"}
}