{
  "type": "Feature",
  "properties": {
    "gn:admin1_code":"39",
    "gn:admin2_code":"S",
    "gn:admin3_code":"39022",
    "gn:asciiname":"Pumarena",
    "gn:country_code":"ES",
    "gn:dem":466,
    "gn:feature_class":"P",
    "gn:feature_code":"PPL",
    "gn:name":"Pumare\u00f1a",
    "gn:population":0,
    "gn:timezone":"Europe/Madrid",
    "iso:country":"ES",
    "name:und_x_variant":[
        "Pumare\u00f1a"
    ],
    "wof:name":"Pumarena",
    "wof:placetype":"locality"
},
  "geometry": {"coordinates":[-4.58243,43.18355],"type":"Point"}
}