{
  "type": "Feature",
  "properties": {
    "gn:admin1_code":"53",
    "gn:admin2_code":"TF",
    "gn:admin3_code":"38020",
    "gn:asciiname":"Tonaso",
    "gn:country_code":"ES",
    "gn:dem":228,
    "gn:feature_class":"P",
    "gn:feature_code":"PPL",
    "gn:name":"Tonaso",
    "gn:population":0,
    "gn:timezone":"Atlantic/Canary",
    "iso:country":"ES",
    "wof:name":"Tonaso",
    "wof:placetype":"locality"
},
  "geometry": {"coordinates":[-16.40347,28.31595],"type":"Point"}
}