{
  "type": "Feature",
  "properties": {
    "gn:admin1_code":"58",
    "gn:admin2_code":"PO",
    "gn:admin3_code":"36018",
    "gn:asciiname":"Meabia",
    "gn:cc2":"ES",
    "gn:country_code":"ES",
    "gn:dem":548,
    "gn:feature_class":"P",
    "gn:feature_code":"PPL",
    "gn:name":"Meabia",
    "gn:population":0,
    "gn:timezone":"Europe/Madrid",
    "iso:country":"ES",
    "name:und_x_variant":[
        "San Juan",
        "Meabia"
    ],
    "wof:name":"Meabia",
    "wof:placetype":"locality"
},
  "geometry": {"coordinates":[-8.36667,42.65],"type":"Point"}
}