{
  "type": "Feature",
  "properties": {
    "gn:country":"ES",
    "gn:fcode":"PPLA3",
    "gn:population":179,
    "iso:country":"ES",
    "name:arg_x_preferred":[
        "Hormilleja"
    ],
    "name:ast_x_preferred":[
        "Hormilleja"
    ],
    "name:cat_x_preferred":[
        "Hormilleja"
    ],
    "name:ceb_x_preferred":[
        "Hormilleja"
    ],
    "name:deu_x_preferred":[
        "Hormilleja"
    ],
    "name:eng_x_preferred":[
        "Hormilleja"
    ],
    "name:eus_x_preferred":[
        "Hormilleja"
    ],
    "name:fra_x_preferred":[
        "Hormilleja"
    ],
    "name:hun_x_preferred":[
        "Hormilleja"
    ],
    "name:hye_x_preferred":[
        "\u0555\u0580\u0574\u056b\u056c\u056b\u0565\u056d\u0561"
    ],
    "name:ita_x_preferred":[
        "Hormilleja"
    ],
    "name:kaz_x_preferred":[
        "\u041e\u0440\u043c\u0438\u043b\u044c\u0435\u0445\u0430"
    ],
    "name:msa_x_preferred":[
        "Hormilleja"
    ],
    "name:nan_x_preferred":[
        "Hormilleja"
    ],
    "name:nld_x_preferred":[
        "Hormilleja"
    ],
    "name:oci_x_preferred":[
        "Hormilleja"
    ],
    "name:pol_x_preferred":[
        "Hormilleja"
    ],
    "name:por_x_preferred":[
        "Hormilleja"
    ],
    "name:rup_x_preferred":[
        "Hormilleja"
    ],
    "name:rus_x_preferred":[
        "\u041e\u0440\u043c\u0438\u043b\u044c\u0435\u0445\u0430"
    ],
    "name:spa_x_preferred":[
        "Hormilleja"
    ],
    "name:swe_x_preferred":[
        "Hormilleja"
    ],
    "name:ukr_x_preferred":[
        "\u041e\u0440\u043c\u0456\u043b\u044c\u0454\u0445\u0430"
    ],
    "name:vie_x_preferred":[
        "Hormilleja"
    ],
    "name:war_x_preferred":[
        "Hormilleja"
    ],
    "name:zho_x_preferred":[
        "\u5965\u5c14\u7c73\u5217\u54c8"
    ],
    "qs_pg:aaroncc":"ES",
    "qs_pg:gn_country":"ES",
    "qs_pg:gn_fcode":"PPLA3",
    "qs_pg:gn_pop":179,
    "qs_pg:name":"Hormilleja",
    "qs_pg:name_adm0":"Espa\u00f1a",
    "qs_pg:name_adm1":"La Rioja",
    "qs_pg:photos":1,
    "qs_pg:photos_1k":1,
    "qs_pg:photos_9k":1,
    "qs_pg:photos_9r":1,
    "qs_pg:photos_all":1,
    "qs_pg:photos_sr":1,
    "qs_pg:pop_sr":1,
    "qs_pg:qs_pg_placetype":"locality",
    "qs_pg:qs_pg_placetype_gp":"Town",
    "qs_pg:woe_adm0":23424950,
    "woe:adm0_id":23424950,
    "woe:name_adm0":"Espa\u00f1a",
    "woe:name_adm1":"La Rioja",
    "woe:placetype":"Town",
    "wof:name":"Hormilleja",
    "wof:placetype":"locality",
    "wof:population":179
},
  "geometry": {"coordinates":[-2.73155,42.45628],"type":"Point"}
}