{
  "type": "Feature",
  "properties": {
    "gn:gn_country":"ES",
    "gn:gn_fcode":"PPL",
    "gn:gn_pop":0,
    "iso:country":"ES",
    "name:ara_x_preferred":[
        "\u0633\u0627\u0646\u062a\u0627 \u0645\u0627\u0631\u064a\u0627 \u062f\u064a \u0645\u0627\u0631\u062a\u0648\u0631\u064a\u0644\u0627\u0633"
    ],
    "name:arg_x_preferred":[
        "Santa Maria de Martorelles"
    ],
    "name:cat_x_preferred":[
        "Santa Maria de Martorelles"
    ],
    "name:deu_x_preferred":[
        "Santa Mar\u00eda de Martorellas de Arriba"
    ],
    "name:eng_x_preferred":[
        "Santa Maria de Martorelles"
    ],
    "name:eus_x_preferred":[
        "Santa Maria de Martorelles"
    ],
    "name:fas_x_preferred":[
        "\u0633\u0627\u0646\u062a\u0627 \u0645\u0627\u0631\u06cc\u0627 \u062f \u0645\u0627\u0631\u062a\u0631\u06cc\u0633"
    ],
    "name:fra_x_preferred":[
        "Santa Maria de Martorelles"
    ],
    "name:glg_x_preferred":[
        "Santa Maria de Martorelles"
    ],
    "name:hun_x_preferred":[
        "Santa Maria de Martorelles"
    ],
    "name:hye_x_preferred":[
        "\u054d\u0561\u0576\u057f\u0561 \u0544\u0561\u0580\u056b\u0561 \u0564\u0565 \u0544\u0561\u0580\u057f\u0578\u0580\u0565\u056c\u0575\u0561\u057d \u0564\u0565 \u0531\u057c\u056b\u0562\u0561"
    ],
    "name:ita_x_preferred":[
        "Santa Maria de Martorelles"
    ],
    "name:lat_x_preferred":[
        "Santa Maria de Martorelles"
    ],
    "name:nld_x_preferred":[
        "Santa Maria de Martorelles"
    ],
    "name:oci_x_preferred":[
        "Santa Maria de Martorelles"
    ],
    "name:pol_x_preferred":[
        "Santa Maria de Martorelles"
    ],
    "name:por_x_preferred":[
        "Santa Maria de Martorelles"
    ],
    "name:rus_x_preferred":[
        "\u0421\u0430\u043d\u0442\u0430-\u041c\u0430\u0440\u0438\u044f-\u0434\u0435-\u041c\u0430\u0440\u0442\u043e\u0440\u0435\u043b\u044c\u0435\u0441"
    ],
    "name:sco_x_preferred":[
        "Santa Maria de Martorelles"
    ],
    "name:spa_x_preferred":[
        "Santa Mar\u00eda de Martorellas de Arriba"
    ],
    "name:swe_x_preferred":[
        "Santa Maria de Martorelles"
    ],
    "name:ukr_x_preferred":[
        "\u0421\u0430\u043d\u0442\u0430-\u041c\u0430\u0440\u0456\u044f-\u0434\u0430-\u041c\u0430\u0440\u0442\u0443\u0440\u0435\u043b\u044f\u0441"
    ],
    "name:unk_x_variant":[
        "Santa Mar\u00eda de Martorellas de Arriba"
    ],
    "name:uzb_x_preferred":[
        "Santa Maria de Martorelles"
    ],
    "name:war_x_preferred":[
        "Santa Maria de Martorelles"
    ],
    "name:zho_x_preferred":[
        "\u5723\u9a6c\u91cc\u4e9a\u5fb7\u9a6c\u5c14\u6258\u96f7\u5217\u65af"
    ],
    "qs_pg:aaroncc":"ES",
    "qs_pg:gn_country":"ES",
    "qs_pg:gn_fcode":"PPL",
    "qs_pg:gn_pop":0,
    "qs_pg:name":"Santa Maria de Martorelles",
    "qs_pg:name_adm0":"Espa\u00f1a",
    "qs_pg:name_adm1":"Catalunya",
    "qs_pg:photos":136,
    "qs_pg:photos_1k":28,
    "qs_pg:photos_9k":1,
    "qs_pg:photos_9r":3,
    "qs_pg:photos_all":136,
    "qs_pg:photos_sr":3,
    "qs_pg:pop_sr":0,
    "qs_pg:qs_pg_placetype":"locality",
    "qs_pg:qs_pg_placetype_gp":"Town",
    "qs_pg:woe_adm0":23424950,
    "woe:adm0_id":23424950,
    "woe:name_adm0":"Espa\u00f1a",
    "woe:name_adm1":"Catalunya",
    "woe:placetype":"Town",
    "wof:name":"Santa Maria de Martorelles",
    "wof:placetype":"locality"
},
  "geometry": {"coordinates":[2.25,41.51667],"type":"Point"}
}