{
  "type": "Feature",
  "properties": {
    "gn:admin1_code":"39",
    "gn:admin2_code":"S",
    "gn:admin3_code":"39080",
    "gn:asciiname":"Sejo de Arriba",
    "gn:country_code":"ES",
    "gn:dem":80,
    "gn:feature_class":"P",
    "gn:feature_code":"PPL",
    "gn:name":"Sejo de Arriba",
    "gn:population":0,
    "gn:timezone":"Europe/Madrid",
    "iso:country":"ES",
    "wof:name":"Sejo de Arriba",
    "wof:placetype":"locality"
},
  "geometry": {"coordinates":[-4.34965,43.36794],"type":"Point"}
}