{
  "type": "Feature",
  "properties": {
    "gn:admin1_code":"31",
    "gn:admin2_code":"MU",
    "gn:admin3_code":"30024",
    "gn:asciiname":"El Cantal",
    "gn:country_code":"ES",
    "gn:dem":125,
    "gn:feature_class":"P",
    "gn:feature_code":"PPL",
    "gn:name":"El Cantal",
    "gn:population":0,
    "gn:timezone":"Europe/Madrid",
    "iso:country":"ES",
    "name:und_x_variant":[
        "Caser\u00edo El Cantal",
        "El Cantar",
        "El Cantal"
    ],
    "wof:name":"El Cantal",
    "wof:placetype":"locality"
},
  "geometry": {"coordinates":[-1.48016,37.49552],"type":"Point"}
}