{
  "type": "Feature",
  "properties": {
    "gn:admin1_code":"58",
    "gn:admin2_code":"C",
    "gn:admin3_code":"15092",
    "gn:asciiname":"Sansobre",
    "gn:country_code":"ES",
    "gn:dem":178,
    "gn:feature_class":"P",
    "gn:feature_code":"PPL",
    "gn:name":"Sansobre",
    "gn:population":0,
    "gn:timezone":"Europe/Madrid",
    "iso:country":"ES",
    "name:und_x_variant":[
        "Sausobre",
        "Sansobre"
    ],
    "wof:name":"Sansobre",
    "wof:placetype":"locality"
},
  "geometry": {"coordinates":[-9.02667,43.10112],"type":"Point"}
}