{
  "type": "Feature",
  "properties": {
    "gn:admin1_code":"55",
    "gn:admin2_code":"SO",
    "gn:admin3_code":"42113",
    "gn:asciiname":"Benamira",
    "gn:country_code":"ES",
    "gn:dem":1097,
    "gn:feature_class":"P",
    "gn:feature_code":"PPL",
    "gn:name":"Benamira",
    "gn:population":0,
    "gn:timezone":"Europe/Madrid",
    "iso:country":"ES",
    "wof:name":"Benamira",
    "wof:placetype":"locality"
},
  "geometry": {"coordinates":[-2.42299,41.09315],"type":"Point"}
}