{
  "type": "Feature",
  "properties": {
    "gn:gn_country":"ES",
    "gn:gn_fcode":"PPLA3",
    "gn:gn_pop":47,
    "gn:population":47,
    "iso:country":"ES",
    "name:ara_x_preferred":[
        "\u0646\u0627\u0641\u0627\u0643\u064a\u0633\u064a\u0631\u0627"
    ],
    "name:cat_x_preferred":[
        "Navaquesera"
    ],
    "name:eng_x_preferred":[
        "Navaquesera"
    ],
    "name:eus_x_preferred":[
        "Navaquesera"
    ],
    "name:fas_x_preferred":[
        "\u0646\u0627\u0628\u0627\u06a9\u0633\u0631\u0627"
    ],
    "name:fra_x_preferred":[
        "Navaquesera"
    ],
    "name:hun_x_preferred":[
        "Navaquesera"
    ],
    "name:ina_x_preferred":[
        "Navaquesera"
    ],
    "name:ita_x_preferred":[
        "Navaquesera"
    ],
    "name:kaz_x_preferred":[
        "\u041d\u0430\u0432\u0430\u043a\u0435\u0441\u0435\u0440\u0430"
    ],
    "name:mkd_x_preferred":[
        "\u041d\u0430\u0432\u0430\u043a\u0435\u0441\u0435\u0440\u0430"
    ],
    "name:msa_x_preferred":[
        "Navaquesera"
    ],
    "name:nld_x_preferred":[
        "Navaquesera"
    ],
    "name:oci_x_preferred":[
        "Navaquesera"
    ],
    "name:pol_x_preferred":[
        "Navaquesera"
    ],
    "name:por_x_preferred":[
        "Navaquesera"
    ],
    "name:rus_x_preferred":[
        "\u041d\u0430\u0432\u0430\u043a\u0435\u0441\u0435\u0440\u0430"
    ],
    "name:spa_x_preferred":[
        "Navaquesera"
    ],
    "name:swe_x_preferred":[
        "Navaquesera"
    ],
    "name:ukr_x_preferred":[
        "\u041d\u0430\u0432\u0430\u043a\u0435\u0441\u0435\u0440\u0430"
    ],
    "name:uzb_x_preferred":[
        "Navaquesera"
    ],
    "name:vie_x_preferred":[
        "Navaquesera"
    ],
    "name:war_x_preferred":[
        "Navaquesera"
    ],
    "name:zho_x_preferred":[
        "\u7eb3\u74e6\u514b\u585e\u62c9"
    ],
    "qs_pg:aaroncc":"ES",
    "qs_pg:gn_country":"ES",
    "qs_pg:gn_fcode":"PPLA3",
    "qs_pg:gn_pop":47,
    "qs_pg:name":"Navaquesera",
    "qs_pg:name_adm0":"Espa\u00f1a",
    "qs_pg:name_adm1":"Castilla y Le\u00f3n",
    "qs_pg:photos_9k":1,
    "qs_pg:photos_9r":1,
    "qs_pg:photos_all":2,
    "qs_pg:photos_sr":0,
    "qs_pg:pop_sr":1,
    "qs_pg:qs_pg_placetype":"locality",
    "qs_pg:qs_pg_placetype_gp":"Town",
    "qs_pg:woe_adm0":23424950,
    "woe:adm0_id":23424950,
    "woe:name_adm0":"Espa\u00f1a",
    "woe:name_adm1":"Castilla y Le\u00f3n",
    "woe:placetype":"Town",
    "wof:name":"Navaquesera",
    "wof:placetype":"locality",
    "wof:population":47
},
  "geometry": {"coordinates":[-4.91108,40.42558],"type":"Point"}
}