{
  "type": "Feature",
  "properties": {
    "gn:country":"ES",
    "gn:fcode":"PPL",
    "gn:population":1175,
    "iso:country":"ES",
    "name:arg_x_preferred":[
        "Gradefes"
    ],
    "name:azb_x_preferred":[
        "\u0642\u0631\u0627\u062f\u0641\u0633"
    ],
    "name:cat_x_preferred":[
        "Gradefes"
    ],
    "name:ceb_x_preferred":[
        "Gradefes"
    ],
    "name:deu_x_preferred":[
        "Gradefes"
    ],
    "name:eng_x_preferred":[
        "Gradefes"
    ],
    "name:eus_x_preferred":[
        "Gradefes"
    ],
    "name:fas_x_preferred":[
        "\u06af\u0631\u0627\u062f\u0641\u0633"
    ],
    "name:fra_x_preferred":[
        "Gradefes"
    ],
    "name:glg_x_preferred":[
        "Gradefes"
    ],
    "name:haw_x_preferred":[
        "Gradefes"
    ],
    "name:hun_x_preferred":[
        "Gradefes"
    ],
    "name:ido_x_preferred":[
        "Gradefes"
    ],
    "name:ina_x_preferred":[
        "Gradefes"
    ],
    "name:ita_x_preferred":[
        "Gradefes"
    ],
    "name:msa_x_preferred":[
        "Gradefes"
    ],
    "name:nan_x_preferred":[
        "Gradefes"
    ],
    "name:nld_x_preferred":[
        "Gradefes"
    ],
    "name:oci_x_preferred":[
        "Gradefes"
    ],
    "name:pol_x_preferred":[
        "Gradefes"
    ],
    "name:por_x_preferred":[
        "Gradefes"
    ],
    "name:rus_x_preferred":[
        "\u0413\u0440\u0430\u0434\u0435\u0444\u0435\u0441"
    ],
    "name:spa_x_preferred":[
        "Gradefes"
    ],
    "name:swe_x_preferred":[
        "Gradefes"
    ],
    "name:tpi_x_preferred":[
        "Gradefes"
    ],
    "name:ukr_x_preferred":[
        "\u0413\u0440\u0430\u0434\u0435\u0444\u0435\u0441"
    ],
    "name:vie_x_preferred":[
        "Gradefes"
    ],
    "name:war_x_preferred":[
        "Gradefes"
    ],
    "name:zho_x_preferred":[
        "\u683c\u62c9\u5fb7\u8d39\u65af"
    ],
    "qs_pg:aaroncc":"ES",
    "qs_pg:gn_country":"ES",
    "qs_pg:gn_fcode":"PPL",
    "qs_pg:gn_pop":1175,
    "qs_pg:name":"Gradefes",
    "qs_pg:name_adm0":"Espa\u00f1a",
    "qs_pg:name_adm1":"Castilla y Le\u00f3n",
    "qs_pg:photos":169,
    "qs_pg:photos_1k":34,
    "qs_pg:photos_9k":1,
    "qs_pg:photos_9r":4,
    "qs_pg:photos_all":169,
    "qs_pg:photos_sr":4,
    "qs_pg:pop_sr":3,
    "qs_pg:qs_pg_placetype":"locality",
    "qs_pg:qs_pg_placetype_gp":"Town",
    "qs_pg:woe_adm0":23424950,
    "woe:adm0_id":23424950,
    "woe:name_adm0":"Espa\u00f1a",
    "woe:name_adm1":"Castilla y Le\u00f3n",
    "woe:placetype":"Town",
    "wof:name":"Gradefes",
    "wof:placetype":"locality",
    "wof:population":1175
},
  "geometry": {"coordinates":[-5.22691,42.62396],"type":"Point"}
}