{
  "type": "Feature",
  "properties": {
    "gn:admin1_code":"55",
    "gn:admin2_code":"LE",
    "gn:admin3_code":"24103",
    "gn:asciiname":"Arnadelo",
    "gn:country_code":"ES",
    "gn:dem":553,
    "gn:feature_class":"P",
    "gn:feature_code":"PPL",
    "gn:name":"Arnadelo",
    "gn:population":0,
    "gn:timezone":"Europe/Madrid",
    "iso:country":"ES",
    "wof:name":"Arnadelo",
    "wof:placetype":"locality"
},
  "geometry": {"coordinates":[-6.90782,42.55555],"type":"Point"}
}