{
  "type": "Feature",
  "properties": {
    "gn:admin1_code":"59",
    "gn:admin2_code":"VI",
    "gn:admin3_code":"01063",
    "gn:asciiname":"Guillerna",
    "gn:country_code":"ES",
    "gn:dem":660,
    "gn:feature_class":"P",
    "gn:feature_code":"PPL",
    "gn:name":"Gilierna / Guillerna",
    "gn:population":0,
    "gn:timezone":"Europe/Madrid",
    "iso:country":"ES",
    "name:eus_x_preferred":[
        "Gillerna"
    ],
    "name:eus_x_variant":[
        "Gilierna"
    ],
    "name:spa_x_preferred":[
        "Guillerna"
    ],
    "wof:name":"Guillerna",
    "wof:placetype":"locality"
},
  "geometry": {"coordinates":[-2.85413,42.9502],"type":"Point"}
}