{
  "type": "Feature",
  "properties": {
    "gn:admin1_code":"58",
    "gn:admin2_code":"OR",
    "gn:admin3_code":"32057",
    "gn:asciiname":"Pradomao",
    "gn:country_code":"ES",
    "gn:dem":859,
    "gn:feature_class":"P",
    "gn:feature_code":"PPL",
    "gn:name":"Pradomao",
    "gn:population":0,
    "gn:timezone":"Europe/Madrid",
    "iso:country":"ES",
    "wof:name":"Pradomao",
    "wof:placetype":"locality"
},
  "geometry": {"coordinates":[-7.52918,42.34061],"type":"Point"}
}