{
  "type": "Feature",
  "properties": {
    "gn:admin1_code":"59",
    "gn:admin2_code":"BI",
    "gn:admin3_code":"48037",
    "gn:asciiname":"Mendizelai",
    "gn:country_code":"ES",
    "gn:dem":248,
    "gn:feature_class":"P",
    "gn:feature_code":"PPL",
    "gn:name":"Montellano",
    "gn:population":0,
    "gn:timezone":"Europe/Madrid",
    "iso:country":"ES",
    "name:eus_x_preferred":[
        "Mendizelai"
    ],
    "name:spa_x_preferred":[
        "Montellano"
    ],
    "wof:name":"Mendizelai",
    "wof:placetype":"locality"
},
  "geometry": {"coordinates":[-3.13505,43.29477],"type":"Point"}
}