{
  "type": "Feature",
  "properties": {
    "gn:admin1_code":"58",
    "gn:admin2_code":"OR",
    "gn:admin3_code":"32077",
    "gn:asciiname":"Pineira de Abaixo",
    "gn:country_code":"ES",
    "gn:dem":635,
    "gn:feature_class":"P",
    "gn:feature_code":"PPL",
    "gn:name":"Pi\u00f1eira de Abaixo",
    "gn:population":0,
    "gn:timezone":"Europe/Madrid",
    "iso:country":"ES",
    "wof:name":"Pineira de Abaixo",
    "wof:placetype":"locality"
},
  "geometry": {"coordinates":[-7.75931,42.14046],"type":"Point"}
}