{
  "type": "Feature",
  "properties": {
    "gn:admin1_code":"60",
    "gn:admin2_code":"A",
    "gn:admin3_code":"03099",
    "gn:asciiname":"Hurchillo",
    "gn:country_code":"ES",
    "gn:dem":43,
    "gn:feature_class":"P",
    "gn:feature_code":"PPL",
    "gn:name":"Hurchillo",
    "gn:population":0,
    "gn:timezone":"Europe/Madrid",
    "iso:country":"ES",
    "name:spa_x_preferred":[
        "Hurchillo"
    ],
    "wof:name":"Hurchillo",
    "wof:placetype":"locality"
},
  "geometry": {"coordinates":[-0.91915,38.05696],"type":"Point"}
}