{
  "type": "Feature",
  "properties": {
    "gn:admin1_code":"51",
    "gn:admin2_code":"H",
    "gn:admin3_code":"21078",
    "gn:asciiname":"El Buitron",
    "gn:country_code":"ES",
    "gn:dem":309,
    "gn:feature_class":"P",
    "gn:feature_code":"PPL",
    "gn:name":"El Buitr\u00f3n",
    "gn:population":0,
    "gn:timezone":"Europe/Madrid",
    "iso:country":"ES",
    "name:und_x_variant":[
        "Buitr\u00f3n",
        "El Buitr\u00f3n"
    ],
    "wof:name":"El Buitron",
    "wof:placetype":"locality"
},
  "geometry": {"coordinates":[-6.73867,37.64021],"type":"Point"}
}