{
  "type": "Feature",
  "properties": {
    "gn:gn_country":"ES",
    "gn:gn_fcode":"PPLA3",
    "gn:gn_pop":176,
    "gn:population":176,
    "iso:country":"ES",
    "name:ara_x_preferred":[
        "\u0645\u0648\u0646\u062a\u0627\u0644\u0628\u0627\u0646\u064a\u062e\u0648"
    ],
    "name:arg_x_preferred":[
        "Montalbanejo"
    ],
    "name:ast_x_preferred":[
        "Montalbanejo"
    ],
    "name:cat_x_preferred":[
        "Montalbanejo"
    ],
    "name:ceb_x_preferred":[
        "Montalbanejo"
    ],
    "name:deu_x_preferred":[
        "Montalbanejo"
    ],
    "name:eng_x_preferred":[
        "Montalbanejo"
    ],
    "name:epo_x_preferred":[
        "Montalbanejo"
    ],
    "name:eus_x_preferred":[
        "Montalbanejo"
    ],
    "name:fra_x_preferred":[
        "Montalbanejo"
    ],
    "name:hun_x_preferred":[
        "Montalbanejo"
    ],
    "name:ita_x_preferred":[
        "Montalbanejo"
    ],
    "name:kaz_x_preferred":[
        "\u041c\u043e\u043d\u0442\u0430\u043b\u044c\u0431\u0430\u043d\u0435\u0445\u043e"
    ],
    "name:msa_x_preferred":[
        "Montalbanejo"
    ],
    "name:nan_x_preferred":[
        "Montalbanejo"
    ],
    "name:nld_x_preferred":[
        "Montalbanejo"
    ],
    "name:oci_x_preferred":[
        "Montalbanejo"
    ],
    "name:pol_x_preferred":[
        "Montalbanejo"
    ],
    "name:por_x_preferred":[
        "Montalbanejo"
    ],
    "name:rus_x_preferred":[
        "\u041c\u043e\u043d\u0442\u0430\u043b\u044c\u0431\u0430\u043d\u0435\u0445\u043e"
    ],
    "name:spa_x_preferred":[
        "Montalbanejo"
    ],
    "name:swe_x_preferred":[
        "Montalbanejo"
    ],
    "name:ukr_x_preferred":[
        "\u041c\u043e\u043d\u0442\u0430\u043b\u044c\u0431\u0430\u043d\u0435\u0445\u043e"
    ],
    "name:vie_x_preferred":[
        "Montalbanejo"
    ],
    "name:war_x_preferred":[
        "Montalbanejo"
    ],
    "name:zho_x_preferred":[
        "\u8499\u5854\u5c14\u74e6\u5185\u970d"
    ],
    "qs_pg:aaroncc":"ES",
    "qs_pg:gn_country":"ES",
    "qs_pg:gn_fcode":"PPLA3",
    "qs_pg:gn_pop":176,
    "qs_pg:name":"Montalbanejo",
    "qs_pg:name_adm0":"Espa\u00f1a",
    "qs_pg:name_adm1":"Castilla-La Mancha",
    "qs_pg:photos_9r":0,
    "qs_pg:photos_sr":0,
    "qs_pg:pop_sr":1,
    "qs_pg:qs_pg_placetype":"locality",
    "qs_pg:qs_pg_placetype_gp":"Town",
    "qs_pg:woe_adm0":23424950,
    "woe:adm0_id":23424950,
    "woe:name_adm0":"Espa\u00f1a",
    "woe:name_adm1":"Castilla-La Mancha",
    "woe:placetype":"Town",
    "wof:name":"Montalbanejo",
    "wof:placetype":"locality",
    "wof:population":176
},
  "geometry": {"coordinates":[-2.49911,39.7337],"type":"Point"}
}