{
  "type": "Feature",
  "properties": {
    "gn:admin1_code":"58",
    "gn:admin2_code":"LU",
    "gn:admin3_code":"27011",
    "gn:asciiname":"Arrubial",
    "gn:country_code":"ES",
    "gn:dem":763,
    "gn:feature_class":"P",
    "gn:feature_code":"PPL",
    "gn:name":"Arrubial",
    "gn:population":0,
    "gn:timezone":"Europe/Madrid",
    "iso:country":"ES",
    "wof:name":"Arrubial",
    "wof:placetype":"locality"
},
  "geometry": {"coordinates":[-7.28588,42.94843],"type":"Point"}
}