{
  "type": "Feature",
  "properties": {
    "iso:country":"ES",
    "name:cat_x_preferred":[
        "Tormos"
    ],
    "name:eng_x_preferred":[
        "Tormos"
    ],
    "name:glg_x_preferred":[
        "Tormos"
    ],
    "name:spa_x_preferred":[
        "Tormos"
    ],
    "wof:name":"Tormos",
    "wof:placetype":"neighbourhood"
},
  "geometry": {"coordinates":[-0.37825705504894,39.48923668024158],"type":"Point"}
}