{
  "type": "Feature",
  "properties": {
    "iso:country":"ES",
    "name:cat_x_preferred":[
        "Tormos"
    ],
    "name:eng_x_preferred":[
        "Tormos"
    ],
    "name:glg_x_preferred":[
        "Tormos"
    ],
    "name:nld_x_preferred":[
        "Tormos"
    ],
    "name:spa_x_preferred":[
        "Tormos"
    ],
    "wof:name":"Tormos",
    "wof:placetype":"neighbourhood"
},
  "geometry": {"coordinates":[-0.378257,39.489237],"type":"Point"}
}