{
  "type": "Feature",
  "properties": {
    "gn:admin1_code":"55",
    "gn:admin2_code":"VA",
    "gn:admin3_code":"47157",
    "gn:asciiname":"Sardoncillo",
    "gn:country_code":"ES",
    "gn:dem":724,
    "gn:feature_class":"P",
    "gn:feature_code":"PPL",
    "gn:name":"Sardoncillo",
    "gn:population":0,
    "gn:timezone":"Europe/Madrid",
    "iso:country":"ES",
    "name:und_x_variant":[
        "Granja de Sard\u00f3n",
        "La Granja",
        "Caser\u00edo Sardoncillo",
        "Sardoncillo"
    ],
    "wof:name":"Sardoncillo",
    "wof:placetype":"locality"
},
  "geometry": {"coordinates":[-4.41723,41.61712],"type":"Point"}
}