{
  "type": "Feature",
  "properties": {
    "gn:admin1_code":"58",
    "gn:admin2_code":"C",
    "gn:admin3_code":"15080",
    "gn:asciiname":"Codesoso",
    "gn:cc2":"ES",
    "gn:country_code":"ES",
    "gn:dem":588,
    "gn:feature_class":"P",
    "gn:feature_code":"PPL",
    "gn:name":"Codesoso",
    "gn:population":0,
    "gn:timezone":"Europe/Madrid",
    "iso:country":"ES",
    "name:und_x_variant":[
        "San Miguel",
        "Codesoso"
    ],
    "wof:name":"Codesoso",
    "wof:placetype":"locality"
},
  "geometry": {"coordinates":[-7.98333,43.03333],"type":"Point"}
}