{
  "type": "Feature",
  "properties": {
    "gn:admin1_code":"55",
    "gn:admin2_code":"LE",
    "gn:admin3_code":"24056",
    "gn:asciiname":"Fuentes de Penacorada",
    "gn:country_code":"ES",
    "gn:dem":1159,
    "gn:feature_class":"P",
    "gn:feature_code":"PPL",
    "gn:name":"Fuentes de Pe\u00f1acorada",
    "gn:population":0,
    "gn:timezone":"Europe/Madrid",
    "iso:country":"ES",
    "name:und_x_variant":[
        "Fuentes de Pe\u00f1acorada"
    ],
    "wof:name":"Fuentes de Penacorada",
    "wof:placetype":"locality"
},
  "geometry": {"coordinates":[-5.09046,42.83555],"type":"Point"}
}