{
  "type": "Feature",
  "properties": {
    "gn:admin1_code":"55",
    "gn:admin2_code":"AV",
    "gn:admin3_code":"05065",
    "gn:asciiname":"Chaherrero",
    "gn:country_code":"ES",
    "gn:dem":958,
    "gn:feature_class":"P",
    "gn:feature_code":"PPL",
    "gn:name":"Chaherrero",
    "gn:population":0,
    "gn:timezone":"Europe/Madrid",
    "iso:country":"ES",
    "wof:name":"Chaherrero",
    "wof:placetype":"locality"
},
  "geometry": {"coordinates":[-4.9624,40.85037],"type":"Point"}
}