{
  "type": "Feature",
  "properties": {
    "gn:gn_country":"ES",
    "gn:gn_fcode":"PPLA3",
    "gn:gn_pop":188,
    "gn:population":188,
    "iso:country":"ES",
    "name:arg_x_preferred":[
        "Velasc\u00e1lvaro"
    ],
    "name:cat_x_preferred":[
        "Velasc\u00e1lvaro"
    ],
    "name:eng_x_preferred":[
        "Velasc\u00e1lvaro"
    ],
    "name:eus_x_preferred":[
        "Velasc\u00e1lvaro"
    ],
    "name:fas_x_preferred":[
        "\u0648\u0644\u0633\u06a9\u0627\u0644\u0648\u0631\u0648"
    ],
    "name:fra_x_preferred":[
        "Velasc\u00e1lvaro"
    ],
    "name:hun_x_preferred":[
        "Velasc\u00e1lvaro"
    ],
    "name:hye_x_preferred":[
        "\u054e\u0565\u056c\u0561\u057d\u056f\u0561\u056c\u057e\u0561\u0580\u0578"
    ],
    "name:ina_x_preferred":[
        "Velasc\u00e1lvaro"
    ],
    "name:ita_x_preferred":[
        "Velasc\u00e1lvaro"
    ],
    "name:msa_x_preferred":[
        "Velasc\u00e1lvaro"
    ],
    "name:nan_x_preferred":[
        "Velasc\u00e1lvaro"
    ],
    "name:nld_x_preferred":[
        "Velasc\u00e1lvaro"
    ],
    "name:oci_x_preferred":[
        "Velasc\u00e1lvaro"
    ],
    "name:pol_x_preferred":[
        "Velasc\u00e1lvaro"
    ],
    "name:por_x_preferred":[
        "Velasc\u00e1lvaro"
    ],
    "name:rus_x_preferred":[
        "\u0412\u0435\u043b\u0430\u0441\u043a\u0430\u043b\u044c\u0432\u0430\u0440\u043e"
    ],
    "name:spa_x_preferred":[
        "Velasc\u00e1lvaro"
    ],
    "name:swe_x_preferred":[
        "Velasc\u00e1lvaro"
    ],
    "name:ukr_x_preferred":[
        "\u0412\u0435\u043b\u0430\u0441\u043a\u0430\u043b\u044c\u0432\u0430\u0440\u043e"
    ],
    "name:uzb_x_preferred":[
        "Velasc\u00e1lvaro"
    ],
    "name:vie_x_preferred":[
        "Velasc\u00e1lvaro"
    ],
    "name:war_x_preferred":[
        "Velasc\u00e1lvaro"
    ],
    "name:zho_x_preferred":[
        "\u8d1d\u62c9\u65af\u5361\u5c14\u74e6\u7f57"
    ],
    "qs_pg:aaroncc":"ES",
    "qs_pg:gn_country":"ES",
    "qs_pg:gn_fcode":"PPLA3",
    "qs_pg:gn_pop":188,
    "qs_pg:name":"Velasc\u00e1lvaro",
    "qs_pg:name_adm0":"Espa\u00f1a",
    "qs_pg:name_adm1":"Castilla y Le\u00f3n",
    "qs_pg:photos_9r":0,
    "qs_pg:photos_sr":0,
    "qs_pg:pop_sr":1,
    "qs_pg:qs_pg_placetype":"locality",
    "qs_pg:qs_pg_placetype_gp":"Town",
    "qs_pg:woe_adm0":23424950,
    "woe:adm0_id":23424950,
    "woe:name_adm0":"Espa\u00f1a",
    "woe:name_adm1":"Castilla y Le\u00f3n",
    "woe:placetype":"Town",
    "wof:name":"Velasc\u00e1lvaro",
    "wof:placetype":"locality",
    "wof:population":188
},
  "geometry": {"coordinates":[-4.97242,41.23028],"type":"Point"}
}