{
  "type": "Feature",
  "properties": {
    "gn:admin1_code":"58",
    "gn:admin2_code":"C",
    "gn:admin3_code":"15016",
    "gn:asciiname":"Santa Marina",
    "gn:country_code":"ES",
    "gn:dem":102,
    "gn:feature_class":"P",
    "gn:feature_code":"PPL",
    "gn:name":"Santa Marina",
    "gn:population":0,
    "gn:timezone":"Europe/Madrid",
    "iso:country":"ES",
    "name:ast_x_preferred":[
        "Santa Marina"
    ],
    "name:bel_x_preferred":[
        "\u0421\u0430\u043d\u0442\u0430-\u041c\u0430\u0440\u044b\u043d\u0430"
    ],
    "name:cat_x_preferred":[
        "Santa Marina"
    ],
    "name:ceb_x_preferred":[
        "Santa Marina"
    ],
    "name:eus_x_preferred":[
        "Santa Marina"
    ],
    "name:fra_x_preferred":[
        "Santa Marina"
    ],
    "name:ita_x_preferred":[
        "Santa Marina"
    ],
    "name:nld_x_preferred":[
        "Santa Marina"
    ],
    "name:scn_x_preferred":[
        "Santa Marina"
    ],
    "name:spa_x_preferred":[
        "Santa Marina"
    ],
    "name:srp_x_preferred":[
        "\u0421\u0430\u043d\u0442\u0430 \u041c\u0430\u0440\u0438\u043d\u0430"
    ],
    "name:swe_x_preferred":[
        "Santa Marina"
    ],
    "wof:name":"Santa Marina",
    "wof:placetype":"locality"
},
  "geometry": {"coordinates":[-9.12661,43.18294],"type":"Point"}
}