{
  "type": "Feature",
  "properties": {
    "gn:admin1_code":"56",
    "gn:admin2_code":"GI",
    "gn:admin3_code":"17057",
    "gn:asciiname":"Matajudaica",
    "gn:country_code":"ES",
    "gn:dem":32,
    "gn:feature_class":"P",
    "gn:feature_code":"PPL",
    "gn:name":"Matajudaica",
    "gn:population":0,
    "gn:timezone":"Europe/Madrid",
    "iso:country":"ES",
    "wof:name":"Matajudaica",
    "wof:placetype":"locality"
},
  "geometry": {"coordinates":[3.04399,42.00543],"type":"Point"}
}