{
  "type": "Feature",
  "properties": {
    "gn:country":"ES",
    "gn:fcode":"PPLA3",
    "gn:population":222,
    "iso:country":"ES",
    "name:arg_x_preferred":[
        "Luelmu"
    ],
    "name:ast_x_preferred":[
        "Lluelmu"
    ],
    "name:cat_x_preferred":[
        "Luelmo"
    ],
    "name:ceb_x_preferred":[
        "Luelmo"
    ],
    "name:eng_x_preferred":[
        "Luelmo"
    ],
    "name:eus_x_preferred":[
        "Luelmo"
    ],
    "name:fra_x_preferred":[
        "Luelmo"
    ],
    "name:haw_x_preferred":[
        "Luelmo"
    ],
    "name:hun_x_preferred":[
        "Luelmo"
    ],
    "name:ile_x_preferred":[
        "Luelmo"
    ],
    "name:ina_x_preferred":[
        "Luelmo"
    ],
    "name:ita_x_preferred":[
        "Luelmo"
    ],
    "name:msa_x_preferred":[
        "Luelmo"
    ],
    "name:nan_x_preferred":[
        "Luelmo"
    ],
    "name:nld_x_preferred":[
        "Luelmo"
    ],
    "name:oci_x_preferred":[
        "Luelmo"
    ],
    "name:pol_x_preferred":[
        "Luelmo"
    ],
    "name:por_x_preferred":[
        "Luelmo"
    ],
    "name:rus_x_preferred":[
        "\u041b\u0443\u044d\u043b\u044c\u043c\u043e"
    ],
    "name:spa_x_preferred":[
        "Luelmo"
    ],
    "name:swe_x_preferred":[
        "Luelmo"
    ],
    "name:ukr_x_preferred":[
        "\u041b\u0443\u0435\u043b\u044c\u043c\u043e"
    ],
    "name:vie_x_preferred":[
        "Luelmo"
    ],
    "name:war_x_preferred":[
        "Luelmo"
    ],
    "name:zho_x_preferred":[
        "\u5362\u57c3\u5c14\u83ab"
    ],
    "qs_pg:aaroncc":"ES",
    "qs_pg:gn_country":"ES",
    "qs_pg:gn_fcode":"PPLA3",
    "qs_pg:gn_pop":222,
    "qs_pg:name":"Luelmo",
    "qs_pg:name_adm0":"Espa\u00f1a",
    "qs_pg:name_adm1":"Castilla y Le\u00f3n",
    "qs_pg:photos_9r":0,
    "qs_pg:photos_sr":0,
    "qs_pg:pop_sr":2,
    "qs_pg:qs_pg_placetype":"locality",
    "qs_pg:qs_pg_placetype_gp":"Town",
    "qs_pg:woe_adm0":23424950,
    "woe:adm0_id":23424950,
    "woe:name_adm0":"Espa\u00f1a",
    "woe:name_adm1":"Castilla y Le\u00f3n",
    "woe:placetype":"Town",
    "wof:name":"Luelmo",
    "wof:placetype":"locality",
    "wof:population":222
},
  "geometry": {"coordinates":[-6.13338,41.4403],"type":"Point"}
}