{
  "type": "Feature",
  "properties": {
    "gn:admin1_code":"58",
    "gn:admin2_code":"LU",
    "gn:admin3_code":"27015",
    "gn:asciiname":"Pino",
    "gn:cc2":"ES",
    "gn:country_code":"ES",
    "gn:dem":477,
    "gn:feature_class":"P",
    "gn:feature_code":"PPL",
    "gn:name":"Pino",
    "gn:population":0,
    "gn:timezone":"Europe/Madrid",
    "iso:country":"ES",
    "name:cat_x_preferred":[
        "Pino"
    ],
    "name:ceb_x_preferred":[
        "Pino"
    ],
    "name:deu_x_preferred":[
        "Pino"
    ],
    "name:eus_x_preferred":[
        "Pino"
    ],
    "name:fra_x_preferred":[
        "Pino"
    ],
    "name:glg_x_preferred":[
        "Pino"
    ],
    "name:ita_x_preferred":[
        "Pino"
    ],
    "name:nld_x_preferred":[
        "Pino"
    ],
    "name:por_x_preferred":[
        "Pino"
    ],
    "name:rus_x_preferred":[
        "\u041f\u0438\u043d\u043e"
    ],
    "name:slk_x_preferred":[
        "Pino"
    ],
    "name:spa_x_preferred":[
        "Pino"
    ],
    "name:srp_x_preferred":[
        "Pino"
    ],
    "name:swe_x_preferred":[
        "Pino"
    ],
    "name:ukr_x_preferred":[
        "\u041f\u0456\u043d\u043e"
    ],
    "name:und_x_variant":[
        "San Mart\u00edn"
    ],
    "wof:name":"Pino",
    "wof:placetype":"locality"
},
  "geometry": {"coordinates":[-7.61667,43.21667],"type":"Point"}
}