{
  "type": "Feature",
  "properties": {
    "gn:admin1_code":"54",
    "gn:admin2_code":"AB",
    "gn:admin3_code":"02044",
    "gn:asciiname":"Casa Colorada",
    "gn:country_code":"ES",
    "gn:dem":785,
    "gn:feature_class":"P",
    "gn:feature_code":"PPL",
    "gn:name":"Casa Colorada",
    "gn:population":0,
    "gn:timezone":"Europe/Madrid",
    "iso:country":"ES",
    "name:und_x_variant":[
        "Caser\u00edo Casa Colorada",
        "Casa Colorada"
    ],
    "wof:name":"Casa Colorada",
    "wof:placetype":"locality"
},
  "geometry": {"coordinates":[-1.85765,38.58313],"type":"Point"}
}