{
  "type": "Feature",
  "properties": {
    "gn:admin1_code":"58",
    "gn:admin2_code":"PO",
    "gn:admin3_code":"36055",
    "gn:asciiname":"Caldelas",
    "gn:cc2":"ES",
    "gn:country_code":"ES",
    "gn:dem":34,
    "gn:feature_class":"P",
    "gn:feature_code":"PPL",
    "gn:name":"Caldelas",
    "gn:population":0,
    "gn:timezone":"Europe/Lisbon",
    "iso:country":"ES",
    "name:und_x_variant":[
        "San Mart\u00edn",
        "Caldelas"
    ],
    "wof:name":"Caldelas",
    "wof:placetype":"locality"
},
  "geometry": {"coordinates":[-8.56667,42.05],"type":"Point"}
}