{
  "type": "Feature",
  "properties": {
    "gn:admin1_code":"58",
    "gn:admin2_code":"PO",
    "gn:admin3_code":"36055",
    "gn:asciiname":"Caldelas",
    "gn:cc2":"ES",
    "gn:country_code":"ES",
    "gn:dem":34,
    "gn:feature_class":"P",
    "gn:feature_code":"PPL",
    "gn:name":"Caldelas",
    "gn:population":0,
    "gn:timezone":"Europe/Lisbon",
    "iso:country":"ES",
    "name:cat_x_preferred":[
        "Caldelas"
    ],
    "name:ceb_x_preferred":[
        "Caldelas"
    ],
    "name:deu_x_preferred":[
        "Caldelas"
    ],
    "name:fra_x_preferred":[
        "Caldelas"
    ],
    "name:glg_x_preferred":[
        "Caldelas"
    ],
    "name:ita_x_preferred":[
        "Caldelas"
    ],
    "name:por_x_preferred":[
        "Caldelas"
    ],
    "name:rus_x_preferred":[
        "\u041a\u0430\u043b\u0434\u0435\u043b\u0430\u0448"
    ],
    "name:spa_x_preferred":[
        "Caldelas"
    ],
    "name:ukr_x_preferred":[
        "\u041a\u0430\u043b\u0434\u0435\u043b\u0430\u0448"
    ],
    "name:und_x_variant":[
        "San Mart\u00edn"
    ],
    "wof:name":"Caldelas",
    "wof:placetype":"locality"
},
  "geometry": {"coordinates":[-8.56667,42.05],"type":"Point"}
}