{
  "type": "Feature",
  "properties": {
    "gn:admin1_code":"58",
    "gn:admin2_code":"LU",
    "gn:admin3_code":"27024",
    "gn:asciiname":"Pacios",
    "gn:country_code":"ES",
    "gn:dem":648,
    "gn:feature_class":"P",
    "gn:feature_code":"PPL",
    "gn:name":"Pacios",
    "gn:population":0,
    "gn:timezone":"Europe/Madrid",
    "iso:country":"ES",
    "wof:name":"Pacios",
    "wof:placetype":"locality"
},
  "geometry": {"coordinates":[-7.39945,42.70476],"type":"Point"}
}