{
  "type": "Feature",
  "properties": {
    "gn:admin1_code":"51",
    "gn:admin2_code":"AL",
    "gn:admin3_code":"04007",
    "gn:asciiname":"Rambla Seca",
    "gn:cc2":"ES",
    "gn:country_code":"ES",
    "gn:dem":587,
    "gn:feature_class":"P",
    "gn:feature_code":"PPL",
    "gn:name":"Rambla Seca",
    "gn:population":0,
    "gn:timezone":"Europe/Madrid",
    "iso:country":"ES",
    "name:und_x_variant":[
        "Caser\u00edo Rambla Seca",
        "Rambla Seca"
    ],
    "wof:name":"Rambla Seca",
    "wof:placetype":"locality"
},
  "geometry": {"coordinates":[-3.06667,36.95],"type":"Point"}
}