{
  "type": "Feature",
  "properties": {
    "gn:admin1_code":"58",
    "gn:admin2_code":"OR",
    "gn:admin3_code":"32001",
    "gn:asciiname":"Torneiros",
    "gn:country_code":"ES",
    "gn:dem":683,
    "gn:feature_class":"P",
    "gn:feature_code":"PPL",
    "gn:name":"Torneiros",
    "gn:population":0,
    "gn:timezone":"Europe/Madrid",
    "iso:country":"ES",
    "wof:name":"Torneiros",
    "wof:placetype":"locality"
},
  "geometry": {"coordinates":[-7.7815,42.15036],"type":"Point"}
}