{
  "type": "Feature",
  "properties": {
    "gn:admin1_code":"60",
    "gn:admin2_code":"CS",
    "gn:admin3_code":"12032",
    "gn:asciiname":"Vila-real",
    "gn:country_code":"ES",
    "gn:dem":48,
    "gn:feature_class":"P",
    "gn:feature_code":"PPL",
    "gn:name":"Vila-real",
    "gn:population":51205,
    "gn:timezone":"Europe/Madrid",
    "iso:country":"ES",
    "name:cat_x_preferred":[
        "Vila-real"
    ],
    "name:eng_x_preferred":[
        "Vila-real"
    ],
    "name:por_x_preferred":[
        "Vila-real"
    ],
    "name:rus_x_preferred":[
        "\u0412\u0438\u043b\u044c\u044f\u0440\u0440\u0435\u0430\u043b\u044c"
    ],
    "name:spa_x_preferred":[
        "Villareal"
    ],
    "name:spa_x_variant":[
        "Villarreal"
    ],
    "wof:name":"Vila-real",
    "wof:placetype":"locality",
    "wof:population":51205
},
  "geometry": {"coordinates":[-0.10087,39.9383],"type":"Point"}
}