{
  "type": "Feature",
  "properties": {
    "gn:admin1_code":"54",
    "gn:admin2_code":"GU",
    "gn:admin3_code":"19901",
    "gn:asciiname":"Las Cabezadas",
    "gn:country_code":"ES",
    "gn:dem":1159,
    "gn:feature_class":"P",
    "gn:feature_code":"PPL",
    "gn:name":"Las Cabezadas",
    "gn:population":0,
    "gn:timezone":"Europe/Madrid",
    "iso:country":"ES",
    "wof:name":"Las Cabezadas",
    "wof:placetype":"locality"
},
  "geometry": {"coordinates":[-3.10803,41.07438],"type":"Point"}
}