{
  "type": "Feature",
  "properties": {
    "gn:admin1_code":"54",
    "gn:admin2_code":"GU",
    "gn:admin3_code":"19257",
    "gn:asciiname":"Bujalcayado",
    "gn:country_code":"ES",
    "gn:dem":1005,
    "gn:feature_class":"P",
    "gn:feature_code":"PPL",
    "gn:name":"Bujalcayado",
    "gn:population":0,
    "gn:timezone":"Europe/Madrid",
    "iso:country":"ES",
    "wof:name":"Bujalcayado",
    "wof:placetype":"locality"
},
  "geometry": {"coordinates":[-2.71517,41.1283],"type":"Point"}
}