{
  "type": "Feature",
  "properties": {
    "gn:admin1_code":"58",
    "gn:admin2_code":"OR",
    "gn:admin3_code":"32027",
    "gn:asciiname":"Zaparin",
    "gn:country_code":"ES",
    "gn:dem":400,
    "gn:feature_class":"P",
    "gn:feature_code":"PPL",
    "gn:name":"Zapar\u00edn",
    "gn:population":0,
    "gn:timezone":"Europe/Madrid",
    "iso:country":"ES",
    "name:und_x_variant":[
        "Zapar\u00edn"
    ],
    "wof:name":"Zaparin",
    "wof:placetype":"locality"
},
  "geometry": {"coordinates":[-8.11667,42.21667],"type":"Point"}
}