{
  "type": "Feature",
  "properties": {
    "gn:admin1_code":"57",
    "gn:admin2_code":"BA",
    "gn:admin3_code":"06065",
    "gn:asciiname":"Rubiales",
    "gn:cc2":"ES",
    "gn:country_code":"ES",
    "gn:dem":555,
    "gn:feature_class":"P",
    "gn:feature_code":"PPL",
    "gn:name":"Rubiales",
    "gn:population":0,
    "gn:timezone":"Europe/Madrid",
    "iso:country":"ES",
    "name:bul_x_preferred":[
        "Rubiales"
    ],
    "name:dan_x_preferred":[
        "Krap-ordenen"
    ],
    "name:fra_x_preferred":[
        "Rubiales"
    ],
    "name:ind_x_preferred":[
        "Rubiales"
    ],
    "name:jpn_x_preferred":[
        "\u30a2\u30ab\u30cd\u76ee"
    ],
    "name:lit_x_preferred":[
        "Raudie\u010diai"
    ],
    "name:nld_x_preferred":[
        "Rubiales"
    ],
    "name:pol_x_preferred":[
        "Marzanowce"
    ],
    "name:spa_x_preferred":[
        "Rubiales"
    ],
    "name:und_x_variant":[
        "Cortijos Rubiales"
    ],
    "name:zho_x_preferred":[
        "\u831c\u8349\u76ee"
    ],
    "wof:name":"Rubiales",
    "wof:placetype":"locality"
},
  "geometry": {"coordinates":[-5.92077,38.37248],"type":"Point"}
}