{
  "type": "Feature",
  "properties": {
    "gn:admin1_code":"57",
    "gn:admin2_code":"BA",
    "gn:admin3_code":"06065",
    "gn:asciiname":"Rubiales",
    "gn:cc2":"ES",
    "gn:country_code":"ES",
    "gn:dem":555,
    "gn:feature_class":"P",
    "gn:feature_code":"PPL",
    "gn:name":"Rubiales",
    "gn:population":0,
    "gn:timezone":"Europe/Madrid",
    "iso:country":"ES",
    "name:und_x_variant":[
        "Cortijos Rubiales",
        "Rubiales"
    ],
    "wof:name":"Rubiales",
    "wof:placetype":"locality"
},
  "geometry": {"coordinates":[-5.92077,38.37248],"type":"Point"}
}