{
  "type": "Feature",
  "properties": {
    "gn:population":3580,
    "iso:country":"ES",
    "name:ara_x_preferred":[
        "\u064a\u0633\u062a\u064a"
    ],
    "name:arg_x_preferred":[
        "Yeste"
    ],
    "name:ast_x_preferred":[
        "Yeste"
    ],
    "name:cat_x_preferred":[
        "Yeste"
    ],
    "name:ceb_x_preferred":[
        "Yeste"
    ],
    "name:eng_x_preferred":[
        "Yeste"
    ],
    "name:eus_x_preferred":[
        "Yeste"
    ],
    "name:fas_x_preferred":[
        "\u06cc\u0633\u062a\u0647"
    ],
    "name:fra_x_preferred":[
        "Yeste"
    ],
    "name:hun_x_preferred":[
        "Yeste"
    ],
    "name:ina_x_preferred":[
        "Yeste"
    ],
    "name:ita_x_preferred":[
        "Yeste"
    ],
    "name:lit_x_preferred":[
        "Jest\u0117"
    ],
    "name:msa_x_preferred":[
        "Yeste"
    ],
    "name:nan_x_preferred":[
        "Yeste"
    ],
    "name:nld_x_preferred":[
        "Yeste"
    ],
    "name:oci_x_preferred":[
        "Yeste"
    ],
    "name:pam_x_preferred":[
        "Yeste"
    ],
    "name:pol_x_preferred":[
        "Yeste"
    ],
    "name:por_x_preferred":[
        "Yeste"
    ],
    "name:ron_x_preferred":[
        "Yeste"
    ],
    "name:rus_x_preferred":[
        "\u0415\u0441\u0442\u0435"
    ],
    "name:spa_x_preferred":[
        "Yeste"
    ],
    "name:spa_x_variant":[
        "Zoste"
    ],
    "name:swe_x_preferred":[
        "Yeste"
    ],
    "name:ukr_x_preferred":[
        "\u0404\u0441\u0442\u0435"
    ],
    "name:vie_x_preferred":[
        "Yeste"
    ],
    "name:war_x_preferred":[
        "Yeste"
    ],
    "name:zho_min_nan_x_preferred":[
        "Yeste"
    ],
    "name:zho_x_preferred":[
        "\u8036\u65af\u7279"
    ],
    "qs:a0":"Espa\u00f1a",
    "qs:a1":"*Albacete",
    "qs:a1r":"0Castilla-La Mancha",
    "qs:adm0":"Espa\u00f1a",
    "qs:la_lc":"*",
    "qs:level":"locality",
    "qs:loc":"Yeste",
    "qs:loc_alt":"Yeste",
    "qs:pop":0,
    "qs:type":"buffered point",
    "wd:wordcount":61,
    "wof:lang":[
        "spa"
    ],
    "wof:name":"Yeste",
    "wof:placetype":"locality",
    "wof:population":3580
},
  "geometry": {"coordinates":[-2.319032,38.367359],"type":"Point"}
}