{
  "type": "Feature",
  "properties": {
    "gn:admin1_code":"59",
    "gn:admin2_code":"SS",
    "gn:admin3_code":"20019",
    "gn:asciiname":"Arriaran",
    "gn:country_code":"ES",
    "gn:dem":219,
    "gn:feature_class":"P",
    "gn:feature_code":"PPL",
    "gn:name":"Arriaran",
    "gn:population":0,
    "gn:timezone":"Europe/Madrid",
    "iso:country":"ES",
    "name:eus_x_preferred":[
        "Arriaran"
    ],
    "name:spa_x_preferred":[
        "Arriar\u00e1n"
    ],
    "wof:name":"Arriaran",
    "wof:placetype":"locality"
},
  "geometry": {"coordinates":[-2.23785,43.0603],"type":"Point"}
}