{
  "type": "Feature",
  "properties": {
    "iso:country":"ES",
    "name:ara_x_preferred":[
        "\u0628\u0627\u0628\u0644"
    ],
    "name:arz_x_preferred":[
        "\u0628\u0627\u0628\u0644"
    ],
    "name:bre_x_preferred":[
        "Babel"
    ],
    "name:cat_x_preferred":[
        "Babel"
    ],
    "name:ces_x_preferred":[
        "Babel"
    ],
    "name:cym_x_preferred":[
        "Babel"
    ],
    "name:deu_x_preferred":[
        "Babel"
    ],
    "name:ell_x_preferred":[
        "\u0392\u03b1\u03b2\u03ad\u03bb"
    ],
    "name:eus_x_preferred":[
        "Babel"
    ],
    "name:fas_x_preferred":[
        "\u0628\u0627\u0628\u0644"
    ],
    "name:fin_x_preferred":[
        "Babel"
    ],
    "name:fra_x_preferred":[
        "Babel"
    ],
    "name:heb_x_preferred":[
        "\u05d1\u05d0\u05d1\u05dc"
    ],
    "name:hun_x_preferred":[
        "B\u00e1bel"
    ],
    "name:ind_x_preferred":[
        "Babel"
    ],
    "name:ita_x_preferred":[
        "Babel"
    ],
    "name:jpn_x_preferred":[
        "\u30d0\u30d9\u30eb"
    ],
    "name:kor_x_preferred":[
        "\ubc14\ubca8"
    ],
    "name:lit_x_preferred":[
        "Babilonas"
    ],
    "name:nld_x_preferred":[
        "Babel"
    ],
    "name:pol_x_preferred":[
        "Babel"
    ],
    "name:por_x_preferred":[
        "Babel"
    ],
    "name:ron_x_preferred":[
        "Babel"
    ],
    "name:spa_x_preferred":[
        "Babel"
    ],
    "name:swe_x_preferred":[
        "Babel"
    ],
    "name:tha_x_preferred":[
        "Babel"
    ],
    "name:unk_x_variant":[
        "Babel"
    ],
    "name:zho_x_preferred":[
        "Babel"
    ],
    "qs:gn_adm0_cc":"ES",
    "qs:gn_local":2521978,
    "qs:gn_nam_loc":"Alicante, Alicante, Alicante, Comunitat Valenciana, ES",
    "qs:gn_namadm1":"60",
    "qs:local_max":6358,
    "qs:local_sum":21789,
    "qs:localhoods":20,
    "qs:name":"Babel",
    "qs:name_adm0":"Espa\u00f1a",
    "qs:name_adm1":"Comunitat Valenciana",
    "qs:name_adm2":"Alicante",
    "qs:name_lau":"Alicante",
    "qs:name_local":"Alicante",
    "qs:photo_max":27,
    "qs:photo_sum":190,
    "qs:placetype":"Suburb",
    "qs:quad_count":17,
    "qs:woe_adm0":23424950,
    "qs:woe_adm1":12578038,
    "qs:woe_adm2":12602137,
    "qs:woe_lau":12695279,
    "qs:woe_local":752101,
    "qs:woe_ver":"7.10.0",
    "wd:wordcount":439,
    "wof:lang":[
        "spa"
    ],
    "wof:name":"Babel",
    "wof:placetype":"neighbourhood"
},
  "geometry": {"coordinates":[-0.511527,38.342261],"type":"Point"}
}