{
  "type": "Feature",
  "properties": {
    "gn:admin1_code":"58",
    "gn:admin2_code":"OR",
    "gn:admin3_code":"32035",
    "gn:asciiname":"Irijo",
    "gn:country_code":"ES",
    "gn:dem":530,
    "gn:feature_class":"P",
    "gn:feature_code":"PPL",
    "gn:name":"Irijo",
    "gn:population":0,
    "gn:timezone":"Europe/Madrid",
    "iso:country":"ES",
    "name:und_x_variant":[
        "Puente-Irijo",
        "Irijo"
    ],
    "wof:name":"Irijo",
    "wof:placetype":"locality"
},
  "geometry": {"coordinates":[-8.11474,42.52401],"type":"Point"}
}