{
  "type": "Feature",
  "properties": {
    "gn:admin1_code":"58",
    "gn:admin2_code":"C",
    "gn:admin3_code":"15077",
    "gn:asciiname":"Mallon",
    "gn:country_code":"ES",
    "gn:dem":336,
    "gn:feature_class":"P",
    "gn:feature_code":"PPL",
    "gn:name":"Mall\u00f3n",
    "gn:population":0,
    "gn:timezone":"Europe/Madrid",
    "iso:country":"ES",
    "name:und_x_variant":[
        "Mall\u00f3n"
    ],
    "wof:name":"Mallon",
    "wof:placetype":"locality"
},
  "geometry": {"coordinates":[-8.86075,43.04231],"type":"Point"}
}