{
  "type": "Feature",
  "properties": {
    "gn:admin1_code":"39",
    "gn:admin2_code":"S",
    "gn:admin3_code":"39076",
    "gn:asciiname":"Arroyo",
    "gn:country_code":"ES",
    "gn:dem":106,
    "gn:feature_class":"P",
    "gn:feature_code":"PPL",
    "gn:name":"Arroyo",
    "gn:population":0,
    "gn:timezone":"Europe/Madrid",
    "iso:country":"ES",
    "wof:name":"Arroyo",
    "wof:placetype":"locality"
},
  "geometry": {"coordinates":[-4.12652,43.40368],"type":"Point"}
}