{
  "type": "Feature",
  "properties": {
    "gn:admin1_code":"56",
    "gn:admin2_code":"L",
    "gn:admin3_code":"25239",
    "gn:asciiname":"Os de Civis",
    "gn:country_code":"ES",
    "gn:dem":1506,
    "gn:feature_class":"P",
    "gn:feature_code":"PPL",
    "gn:name":"Os de Civ\u00eds",
    "gn:population":0,
    "gn:timezone":"Europe/Madrid",
    "iso:country":"ES",
    "name:cat_x_preferred":[
        "Os de Civ\u00eds"
    ],
    "wof:name":"Os de Civis",
    "wof:placetype":"locality"
},
  "geometry": {"coordinates":[1.44076,42.51121],"type":"Point"}
}