{
  "type": "Feature",
  "properties": {
    "gn:admin1_code":"55",
    "gn:admin2_code":"SO",
    "gn:admin3_code":"42183",
    "gn:asciiname":"Zamajon",
    "gn:country_code":"ES",
    "gn:dem":983,
    "gn:feature_class":"P",
    "gn:feature_code":"PPL",
    "gn:name":"Zamaj\u00f3n",
    "gn:population":0,
    "gn:timezone":"Europe/Madrid",
    "iso:country":"ES",
    "name:und_x_variant":[
        "Zamaj\u00f3n"
    ],
    "wof:name":"Zamajon",
    "wof:placetype":"locality"
},
  "geometry": {"coordinates":[-2.33517,41.61595],"type":"Point"}
}