{
  "type": "Feature",
  "properties": {
    "gn:gn_country":"ES",
    "gn:gn_fcode":"PPLA3",
    "gn:gn_pop":317,
    "gn:population":317,
    "iso:country":"ES",
    "name:arg_x_preferred":[
        "Torrecilla de la Jara"
    ],
    "name:cat_x_preferred":[
        "Torrecilla de la Jara"
    ],
    "name:deu_x_preferred":[
        "Torrecilla de la Jara"
    ],
    "name:eng_x_preferred":[
        "Torrecilla de la Jara"
    ],
    "name:epo_x_preferred":[
        "Torrecilla de la Jara"
    ],
    "name:eus_x_preferred":[
        "Torrecilla de la Jara"
    ],
    "name:fas_x_preferred":[
        "\u062a\u0631\u0633\u06cc\u06cc\u0627 \u062f \u0644\u0627 \u062e\u0627\u0631\u0627"
    ],
    "name:fra_x_preferred":[
        "Torrecilla de la Jara"
    ],
    "name:hun_x_preferred":[
        "Torrecilla de la Jara"
    ],
    "name:hye_x_preferred":[
        "\u054f\u0578\u057c\u0565\u057d\u056b\u056c\u0575\u0561 \u0564\u0565 \u056c\u0561 \u053d\u0561\u0580\u0561"
    ],
    "name:ina_x_preferred":[
        "Torrecilla de la Jara"
    ],
    "name:ita_x_preferred":[
        "Torrecilla de la Jara"
    ],
    "name:kaz_x_preferred":[
        "\u0422\u043e\u0440\u0440\u0435\u0441\u0438\u043b\u044c\u044f-\u0434\u0435-\u043b\u0430-\u0425\u0430\u0440\u0430"
    ],
    "name:msa_x_preferred":[
        "Torrecilla de la Jara"
    ],
    "name:nan_x_preferred":[
        "Torrecilla de la Jara"
    ],
    "name:nld_x_preferred":[
        "Torrecilla de la Jara"
    ],
    "name:oci_x_preferred":[
        "Torrecilla de la Jara"
    ],
    "name:pol_x_preferred":[
        "Torrecilla de la Jara"
    ],
    "name:por_x_preferred":[
        "Torrecilla de la Jara"
    ],
    "name:ron_x_preferred":[
        "Torrecilla de la Jara"
    ],
    "name:rus_x_preferred":[
        "\u0422\u043e\u0440\u0440\u0435\u0441\u0438\u043b\u044c\u044f-\u0434\u0435-\u043b\u0430-\u0425\u0430\u0440\u0430"
    ],
    "name:spa_x_preferred":[
        "Torrecilla de la Jara"
    ],
    "name:swe_x_preferred":[
        "Torrecilla de la Jara"
    ],
    "name:ukr_x_preferred":[
        "\u0422\u043e\u0440\u0440\u0435\u0441\u0456\u043b\u044c\u044f-\u0434\u0435-\u043b\u0430-\u0425\u0430\u0440\u0430"
    ],
    "name:unk_x_variant":[
        "Torrecilla"
    ],
    "name:vie_x_preferred":[
        "Torrecilla de la Jara"
    ],
    "name:war_x_preferred":[
        "Torrecilla de la Jara"
    ],
    "name:zho_x_preferred":[
        "\u6258\u96f7\u897f\u5229\u4e9a\u5fb7\u62c9\u54c8\u62c9"
    ],
    "qs_pg:aaroncc":"ES",
    "qs_pg:gn_country":"ES",
    "qs_pg:gn_fcode":"PPLA3",
    "qs_pg:gn_pop":317,
    "qs_pg:name":"Torrecilla de la Jara",
    "qs_pg:name_adm0":"Espa\u00f1a",
    "qs_pg:name_adm1":"Castilla-La Mancha",
    "qs_pg:photos_9r":0,
    "qs_pg:photos_sr":0,
    "qs_pg:pop_sr":2,
    "qs_pg:qs_pg_placetype":"locality",
    "qs_pg:qs_pg_placetype_gp":"Town",
    "qs_pg:woe_adm0":23424950,
    "woe:adm0_id":23424950,
    "woe:name_adm0":"Espa\u00f1a",
    "woe:name_adm1":"Castilla-La Mancha",
    "woe:placetype":"Town",
    "wof:name":"Torrecilla de la Jara",
    "wof:placetype":"locality",
    "wof:population":317
},
  "geometry": {"coordinates":[-4.77186,39.70425],"type":"Point"}
}