{
  "type": "Feature",
  "properties": {
    "gn:admin1_code":"55",
    "gn:admin2_code":"BU",
    "gn:admin3_code":"09421",
    "gn:asciiname":"Guma",
    "gn:country_code":"ES",
    "gn:dem":840,
    "gn:feature_class":"P",
    "gn:feature_code":"PPL",
    "gn:name":"Guma",
    "gn:population":0,
    "gn:timezone":"Europe/Madrid",
    "iso:country":"ES",
    "wof:name":"Guma",
    "wof:placetype":"locality"
},
  "geometry": {"coordinates":[-3.51551,41.64267],"type":"Point"}
}