{
  "type": "Feature",
  "properties": {
    "gn:admin1_code":"31",
    "gn:admin2_code":"MU",
    "gn:admin3_code":"30028",
    "gn:asciiname":"Otos",
    "gn:cc2":"ES",
    "gn:country_code":"ES",
    "gn:dem":986,
    "gn:feature_class":"P",
    "gn:feature_code":"PPL",
    "gn:name":"Otos",
    "gn:population":0,
    "gn:timezone":"Europe/Madrid",
    "iso:country":"ES",
    "name:und_x_variant":[
        "Caser\u00edo Otos",
        "Otos"
    ],
    "wof:name":"Otos",
    "wof:placetype":"locality"
},
  "geometry": {"coordinates":[-2.01667,38.26667],"type":"Point"}
}