{
  "type": "Feature",
  "properties": {
    "gn:gn_country":"ES",
    "gn:gn_fcode":"PPLA3",
    "gn:gn_pop":6143,
    "gn:population":6143,
    "iso:country":"ES",
    "name:ara_x_preferred":[
        "\u0641\u0627\u0644\u063a\u0627\u060c \u0628\u0648\u0646\u062a\u064a\u0641\u064a\u062f\u0631\u0627"
    ],
    "name:ara_x_variant":[
        "\u0641\u0627\u0644\u063a\u0627"
    ],
    "name:ast_x_preferred":[
        "Valga"
    ],
    "name:azb_x_preferred":[
        "\u0628\u0627\u0644\u0642\u0627"
    ],
    "name:cat_x_preferred":[
        "Valga"
    ],
    "name:ceb_x_preferred":[
        "Valga"
    ],
    "name:deu_x_preferred":[
        "Ponte Valga"
    ],
    "name:eng_x_preferred":[
        "Valga"
    ],
    "name:eus_x_preferred":[
        "Valga"
    ],
    "name:fas_x_preferred":[
        "\u0628\u0627\u0644\u06af\u0627"
    ],
    "name:fra_x_preferred":[
        "Valga"
    ],
    "name:glg_x_preferred":[
        "Valga"
    ],
    "name:hun_x_preferred":[
        "Valga"
    ],
    "name:hye_x_preferred":[
        "\u054e\u0561\u056c\u0563\u0561"
    ],
    "name:ita_x_preferred":[
        "Valga"
    ],
    "name:jpn_x_preferred":[
        "\u30d0\u30eb\u30ac"
    ],
    "name:kaz_x_preferred":[
        "\u0412\u0430\u043b\u044c\u0433\u0430"
    ],
    "name:kor_x_preferred":[
        "\ubc1c\uac00"
    ],
    "name:lit_x_preferred":[
        "Valga"
    ],
    "name:msa_x_preferred":[
        "Valga"
    ],
    "name:nld_x_preferred":[
        "Valga"
    ],
    "name:oci_x_preferred":[
        "Valga"
    ],
    "name:pol_x_preferred":[
        "Valga"
    ],
    "name:por_x_preferred":[
        "Valga"
    ],
    "name:rus_x_preferred":[
        "\u0412\u0430\u043b\u044c\u0433\u0430"
    ],
    "name:spa_x_preferred":[
        "Valga"
    ],
    "name:swe_x_preferred":[
        "Valga"
    ],
    "name:tur_x_preferred":[
        "Valga"
    ],
    "name:ukr_x_preferred":[
        "\u0412\u0430\u043b\u044c\u0433\u0430"
    ],
    "name:uzb_x_preferred":[
        "Valga"
    ],
    "name:vie_x_preferred":[
        "Valga"
    ],
    "name:war_x_preferred":[
        "Valga"
    ],
    "name:zho_x_preferred":[
        "\u5df4\u5c14\u52a0"
    ],
    "qs_pg:aaroncc":"ES",
    "qs_pg:gn_country":"ES",
    "qs_pg:gn_fcode":"PPLA3",
    "qs_pg:gn_pop":6143,
    "qs_pg:name":"Valga",
    "qs_pg:name_adm0":"Espa\u00f1a",
    "qs_pg:name_adm1":"Galicia",
    "qs_pg:photos":54,
    "qs_pg:photos_1k":11,
    "qs_pg:photos_9k":1,
    "qs_pg:photos_9r":2,
    "qs_pg:photos_all":54,
    "qs_pg:photos_sr":2,
    "qs_pg:pop_sr":5,
    "qs_pg:qs_pg_placetype":"locality",
    "qs_pg:qs_pg_placetype_gp":"Town",
    "qs_pg:woe_adm0":23424950,
    "woe:adm0_id":23424950,
    "woe:name_adm0":"Espa\u00f1a",
    "woe:name_adm1":"Galicia",
    "woe:placetype":"Town",
    "wof:name":"Valga",
    "wof:placetype":"locality",
    "wof:population":6143
},
  "geometry": {"coordinates":[-8.63959,42.69792],"type":"Point"}
}