{
  "type": "Feature",
  "properties": {
    "gn:admin1_code":"32",
    "gn:admin3_code":"31237",
    "gn:asciiname":"Najurieta",
    "gn:country_code":"ES",
    "gn:dem":615,
    "gn:feature_class":"P",
    "gn:feature_code":"PPL",
    "gn:name":"Najurieta",
    "gn:population":0,
    "gn:timezone":"Europe/Madrid",
    "iso:country":"ES",
    "wof:name":"Najurieta",
    "wof:placetype":"locality"
},
  "geometry": {"coordinates":[-1.4828,42.73135],"type":"Point"}
}