{
  "type": "Feature",
  "properties": {
    "gn:admin1_code":"55",
    "gn:admin2_code":"ZA",
    "gn:admin3_code":"49208",
    "gn:asciiname":"Palazuelo de las Cuevas",
    "gn:country_code":"ES",
    "gn:dem":770,
    "gn:feature_class":"P",
    "gn:feature_code":"PPL",
    "gn:name":"Palazuelo de las Cuevas",
    "gn:population":0,
    "gn:timezone":"Europe/Madrid",
    "iso:country":"ES",
    "wof:name":"Palazuelo de las Cuevas",
    "wof:placetype":"locality"
},
  "geometry": {"coordinates":[-6.27591,41.82043],"type":"Point"}
}