{
  "type": "Feature",
  "properties": {
    "gn:admin1_code":"58",
    "gn:admin2_code":"LU",
    "gn:admin3_code":"27006",
    "gn:asciiname":"Castelmaria",
    "gn:country_code":"ES",
    "gn:dem":689,
    "gn:feature_class":"P",
    "gn:feature_code":"PPL",
    "gn:name":"Castelmar\u00eda",
    "gn:population":0,
    "gn:timezone":"Europe/Madrid",
    "iso:country":"ES",
    "wof:name":"Castelmaria",
    "wof:placetype":"locality"
},
  "geometry": {"coordinates":[-7.11848,42.94866],"type":"Point"}
}