{
  "type": "Feature",
  "properties": {
    "gn:admin1_code":"39",
    "gn:admin2_code":"S",
    "gn:admin3_code":"39004",
    "gn:asciiname":"San Vicente de Leon",
    "gn:country_code":"ES",
    "gn:dem":468,
    "gn:feature_class":"P",
    "gn:feature_code":"PPL",
    "gn:name":"San Vicente de Le\u00f3n",
    "gn:population":0,
    "gn:timezone":"Europe/Madrid",
    "iso:country":"ES",
    "name:und_x_variant":[
        "San Vicente",
        "San Vicente de Le\u00f3n"
    ],
    "wof:name":"San Vicente de Leon",
    "wof:placetype":"locality"
},
  "geometry": {"coordinates":[-4.09424,43.17861],"type":"Point"}
}