{
  "type": "Feature",
  "properties": {
    "gn:admin1_code":"57",
    "gn:admin2_code":"CC",
    "gn:admin3_code":"10148",
    "gn:asciiname":"Casas del Manco",
    "gn:country_code":"ES",
    "gn:dem":414,
    "gn:feature_class":"P",
    "gn:feature_code":"PPL",
    "gn:name":"Casas del Manco",
    "gn:population":0,
    "gn:timezone":"Europe/Madrid",
    "iso:country":"ES",
    "name:und_x_variant":[
        "Caser\u00edo Casas del Manco",
        "Casas del Manco"
    ],
    "wof:name":"Casas del Manco",
    "wof:placetype":"locality"
},
  "geometry": {"coordinates":[-6.14229,40.03194000000001],"type":"Point"}
}