{
  "type": "Feature",
  "properties": {
    "gn:admin1_code":"34",
    "gn:admin2_code":"O",
    "gn:admin3_code":"33023",
    "gn:asciiname":"La Ronda",
    "gn:country_code":"ES",
    "gn:dem":60,
    "gn:feature_class":"P",
    "gn:feature_code":"PPL",
    "gn:name":"La Ronda",
    "gn:population":0,
    "gn:timezone":"Europe/Madrid",
    "iso:country":"ES",
    "name:deu_x_preferred":[
        "La Ronda"
    ],
    "name:spa_x_preferred":[
        "La Ronda"
    ],
    "name:urd_x_preferred":[
        "\u0644\u0627 \u0631\u0648\u0646\u0688\u0627"
    ],
    "wof:name":"La Ronda",
    "wof:placetype":"locality"
},
  "geometry": {"coordinates":[-6.84883,43.54998],"type":"Point"}
}