{
  "type": "Feature",
  "properties": {
    "gn:admin1_code":"60",
    "gn:admin2_code":"V",
    "gn:admin3_code":"46181",
    "gn:asciiname":"Tejares",
    "gn:country_code":"ES",
    "gn:dem":14,
    "gn:feature_class":"P",
    "gn:feature_code":"PPL",
    "gn:name":"Tejares",
    "gn:population":0,
    "gn:timezone":"Europe/Madrid",
    "iso:country":"ES",
    "wof:name":"Tejares",
    "wof:placetype":"locality"
},
  "geometry": {"coordinates":[-0.11667,38.91667],"type":"Point"}
}