{
  "type": "Feature",
  "properties": {
    "gn:admin1_code":"39",
    "gn:admin2_code":"S",
    "gn:admin3_code":"39094",
    "gn:asciiname":"Renedo de Bricia",
    "gn:country_code":"ES",
    "gn:dem":1002,
    "gn:feature_class":"P",
    "gn:feature_code":"PPL",
    "gn:name":"Renedo de Bricia",
    "gn:population":0,
    "gn:timezone":"Europe/Madrid",
    "iso:country":"ES",
    "wof:name":"Renedo de Bricia",
    "wof:placetype":"locality"
},
  "geometry": {"coordinates":[-3.8393,42.92337],"type":"Point"}
}