{
  "type": "Feature",
  "properties": {
    "gn:admin1_code":"55",
    "gn:admin2_code":"BU",
    "gn:admin3_code":"09032",
    "gn:asciiname":"Paules del Agua",
    "gn:country_code":"ES",
    "gn:dem":831,
    "gn:feature_class":"P",
    "gn:feature_code":"PPL",
    "gn:name":"Pa\u00fales del Agua",
    "gn:population":0,
    "gn:timezone":"Europe/Madrid",
    "iso:country":"ES",
    "name:und_x_variant":[
        "Pa\u00fales del Agua"
    ],
    "wof:name":"Paules del Agua",
    "wof:placetype":"locality"
},
  "geometry": {"coordinates":[-3.85096,42.00966],"type":"Point"}
}