{
  "type": "Feature",
  "properties": {
    "gn:admin1_code":"39",
    "gn:admin2_code":"S",
    "gn:admin3_code":"39053",
    "gn:asciiname":"Santa Eulalia",
    "gn:country_code":"ES",
    "gn:dem":964,
    "gn:feature_class":"P",
    "gn:feature_code":"PPL",
    "gn:name":"Santa Eulalia",
    "gn:population":0,
    "gn:timezone":"Europe/Madrid",
    "iso:country":"ES",
    "wof:name":"Santa Eulalia",
    "wof:placetype":"locality"
},
  "geometry": {"coordinates":[-4.44381,43.08878],"type":"Point"}
}