{
  "type": "Feature",
  "properties": {
    "gn:admin1_code":"34",
    "gn:admin2_code":"O",
    "gn:admin3_code":"33056",
    "gn:asciiname":"Tezangos",
    "gn:country_code":"ES",
    "gn:dem":140,
    "gn:feature_class":"P",
    "gn:feature_code":"PPL",
    "gn:name":"Tezangos",
    "gn:population":0,
    "gn:timezone":"Europe/Madrid",
    "iso:country":"ES",
    "wof:name":"Tezangos",
    "wof:placetype":"locality"
},
  "geometry": {"coordinates":[-5.08821,43.4442],"type":"Point"}
}