{
  "type": "Feature",
  "properties": {
    "gn:gn_country":"ES",
    "gn:gn_fcode":"ADM3",
    "gn:gn_pop":300,
    "gn:population":294,
    "iso:country":"ES",
    "name:arg_x_preferred":[
        "Riner"
    ],
    "name:ast_x_preferred":[
        "Riner"
    ],
    "name:cat_x_preferred":[
        "Riner"
    ],
    "name:ceb_x_preferred":[
        "Riner"
    ],
    "name:eng_x_preferred":[
        "Riner"
    ],
    "name:eus_x_preferred":[
        "Riner"
    ],
    "name:fra_x_preferred":[
        "Riner"
    ],
    "name:hun_x_preferred":[
        "Riner"
    ],
    "name:hye_x_preferred":[
        "\u054c\u056b\u0576\u0565\u0580"
    ],
    "name:ita_x_preferred":[
        "Riner"
    ],
    "name:msa_x_preferred":[
        "Riner"
    ],
    "name:nld_x_preferred":[
        "Riner"
    ],
    "name:oci_x_preferred":[
        "Riner"
    ],
    "name:pol_x_preferred":[
        "Riner"
    ],
    "name:por_x_preferred":[
        "Riner"
    ],
    "name:ron_x_preferred":[
        "Riner"
    ],
    "name:rus_x_preferred":[
        "\u0420\u0438\u043d\u0435\u0440"
    ],
    "name:sco_x_preferred":[
        "Riner"
    ],
    "name:spa_x_preferred":[
        "Riner"
    ],
    "name:sqi_x_preferred":[
        "Riner"
    ],
    "name:swe_x_preferred":[
        "Riner"
    ],
    "name:uzb_x_preferred":[
        "Riner"
    ],
    "name:vie_x_preferred":[
        "Riner"
    ],
    "name:war_x_preferred":[
        "Riner"
    ],
    "name:zho_x_preferred":[
        "\u91cc\u5185\u5c14"
    ],
    "qs_pg:aaroncc":"ES",
    "qs_pg:gn_country":"ES",
    "qs_pg:gn_fcode":"ADM3",
    "qs_pg:gn_pop":300,
    "qs_pg:name":"Riner",
    "qs_pg:name_adm0":"Espa\u00f1a",
    "qs_pg:name_adm1":"Catalunya",
    "qs_pg:photos":17,
    "qs_pg:photos_1k":3,
    "qs_pg:photos_9k":1,
    "qs_pg:photos_9r":1,
    "qs_pg:photos_all":17,
    "qs_pg:photos_sr":1,
    "qs_pg:pop_sr":2,
    "qs_pg:qs_pg_placetype":"locality",
    "qs_pg:qs_pg_placetype_gp":"Town",
    "qs_pg:woe_adm0":23424950,
    "woe:adm0_id":23424950,
    "woe:name_adm0":"Espa\u00f1a",
    "woe:name_adm1":"Catalunya",
    "woe:placetype":"Town",
    "wof:name":"Riner",
    "wof:placetype":"locality",
    "wof:population":294
},
  "geometry": {"coordinates":[1.55908,41.92883],"type":"Point"}
}