{
  "type": "Feature",
  "properties": {
    "gn:admin1_code":"55",
    "gn:admin2_code":"AV",
    "gn:admin3_code":"05238",
    "gn:asciiname":"Villaviciosa",
    "gn:country_code":"ES",
    "gn:dem":1179,
    "gn:feature_class":"P",
    "gn:feature_code":"PPL",
    "gn:name":"Villaviciosa",
    "gn:population":0,
    "gn:timezone":"Europe/Madrid",
    "iso:country":"ES",
    "wof:name":"Villaviciosa",
    "wof:placetype":"locality"
},
  "geometry": {"coordinates":[-4.89845,40.53651],"type":"Point"}
}