{
  "type": "Feature",
  "properties": {
    "gn:admin1_code":"55",
    "gn:admin2_code":"AV",
    "gn:admin3_code":"05238",
    "gn:asciiname":"Villaviciosa",
    "gn:country_code":"ES",
    "gn:dem":1179,
    "gn:feature_class":"P",
    "gn:feature_code":"PPL",
    "gn:name":"Villaviciosa",
    "gn:population":0,
    "gn:timezone":"Europe/Madrid",
    "iso:country":"ES",
    "name:ceb_x_preferred":[
        "Villaviciosa"
    ],
    "name:cym_x_preferred":[
        "Villaviciosa"
    ],
    "name:deu_x_preferred":[
        "Villaviciosa"
    ],
    "name:fra_x_preferred":[
        "Villaviciosa"
    ],
    "name:ita_x_preferred":[
        "Villaviciosa"
    ],
    "name:msa_x_preferred":[
        "Villaviciosa"
    ],
    "name:nld_x_preferred":[
        "Villaviciosa"
    ],
    "name:sco_x_preferred":[
        "Villaviciosa"
    ],
    "name:spa_x_preferred":[
        "Villaviciosa"
    ],
    "name:swe_x_preferred":[
        "Villaviciosa"
    ],
    "name:vie_x_preferred":[
        "Villaviciosa"
    ],
    "name:war_x_preferred":[
        "Villaviciosa"
    ],
    "wof:name":"Villaviciosa",
    "wof:placetype":"locality"
},
  "geometry": {"coordinates":[-4.89845,40.53651],"type":"Point"}
}