{
  "type": "Feature",
  "properties": {
    "gn:admin1_code":"56",
    "gn:admin2_code":"B",
    "gn:admin3_code":"08012",
    "gn:asciiname":"Horta d'Avinyo",
    "gn:country_code":"ES",
    "gn:dem":318,
    "gn:feature_class":"P",
    "gn:feature_code":"PPL",
    "gn:name":"Horta d'Aviny\u00f3",
    "gn:population":0,
    "gn:timezone":"Europe/Madrid",
    "iso:country":"ES",
    "name:cat_x_preferred":[
        "Horta d'Aviny\u00f3"
    ],
    "name:und_x_variant":[
        "Horta d'Aviny\u00f3"
    ],
    "wof:name":"Horta d'Avinyo",
    "wof:placetype":"locality"
},
  "geometry": {"coordinates":[1.96667,41.83333],"type":"Point"}
}