{
  "type": "Feature",
  "properties": {
    "gn:admin1_code":"58",
    "gn:admin2_code":"LU",
    "gn:admin3_code":"27016",
    "gn:asciiname":"Herbedeiro",
    "gn:cc2":"ES",
    "gn:country_code":"ES",
    "gn:dem":308,
    "gn:feature_class":"P",
    "gn:feature_code":"PPL",
    "gn:name":"Herbedeiro",
    "gn:population":0,
    "gn:timezone":"Europe/Madrid",
    "iso:country":"ES",
    "name:und_x_variant":[
        "Hervedeiro",
        "Herbedeiro"
    ],
    "wof:name":"Herbedeiro",
    "wof:placetype":"locality"
},
  "geometry": {"coordinates":[-7.71667,42.53333],"type":"Point"}
}