{
  "type": "Feature",
  "properties": {
    "gn:gn_country":"ES",
    "gn:gn_fcode":"PPLA3",
    "gn:gn_pop":52,
    "gn:population":52,
    "iso:country":"ES",
    "name:arg_x_preferred":[
        "Semillas"
    ],
    "name:ast_x_preferred":[
        "Semillas"
    ],
    "name:bul_x_preferred":[
        "\u0421\u0435\u043c\u0438\u043b\u0430\u0441"
    ],
    "name:cat_x_preferred":[
        "Semillas"
    ],
    "name:ceb_x_preferred":[
        "Semillas"
    ],
    "name:eng_x_preferred":[
        "Semillas"
    ],
    "name:epo_x_preferred":[
        "Semillas"
    ],
    "name:eus_x_preferred":[
        "Semillas"
    ],
    "name:fra_x_preferred":[
        "Semillas"
    ],
    "name:hun_x_preferred":[
        "Semillas"
    ],
    "name:ina_x_preferred":[
        "Semillas"
    ],
    "name:ita_x_preferred":[
        "Semillas"
    ],
    "name:kaz_x_preferred":[
        "\u0421\u0435\u043c\u0438\u043b\u044c\u044f\u0441"
    ],
    "name:msa_x_preferred":[
        "Semillas"
    ],
    "name:nan_x_preferred":[
        "Semillas"
    ],
    "name:nld_x_preferred":[
        "Semillas"
    ],
    "name:oci_x_preferred":[
        "Semillas"
    ],
    "name:pol_x_preferred":[
        "Semillas"
    ],
    "name:por_x_preferred":[
        "Semillas"
    ],
    "name:rus_x_preferred":[
        "\u0421\u0435\u043c\u0438\u043b\u044c\u044f\u0441"
    ],
    "name:spa_x_preferred":[
        "Semillas"
    ],
    "name:swe_x_preferred":[
        "Semillas"
    ],
    "name:ukr_x_preferred":[
        "\u0421\u0435\u043c\u0456\u043b\u044c\u044f\u0441"
    ],
    "name:vie_x_preferred":[
        "Semillas"
    ],
    "name:war_x_preferred":[
        "Semillas"
    ],
    "name:zho_x_preferred":[
        "\u585e\u7c73\u5229\u4e9a\u65af"
    ],
    "qs_pg:aaroncc":"ES",
    "qs_pg:gn_country":"ES",
    "qs_pg:gn_fcode":"PPLA3",
    "qs_pg:gn_pop":52,
    "qs_pg:name":"Semillas",
    "qs_pg:name_adm0":"Espa\u00f1a",
    "qs_pg:name_adm1":"Castilla-La Mancha",
    "qs_pg:photos_9r":0,
    "qs_pg:photos_sr":0,
    "qs_pg:pop_sr":1,
    "qs_pg:qs_pg_placetype":"locality",
    "qs_pg:qs_pg_placetype_gp":"Town",
    "qs_pg:woe_adm0":23424950,
    "woe:adm0_id":23424950,
    "woe:name_adm0":"Espa\u00f1a",
    "woe:name_adm1":"Castilla-La Mancha",
    "woe:placetype":"Town",
    "wof:name":"Semillas",
    "wof:placetype":"locality",
    "wof:population":52
},
  "geometry": {"coordinates":[-3.11945,41.05857],"type":"Point"}
}