{
  "type": "Feature",
  "properties": {
    "gn:country":"ES",
    "gn:fcode":"ADM3",
    "gn:population":40,
    "iso:country":"ES",
    "name:ara_x_preferred":[
        "\u0633\u064a\u0644\u0627\u0628\u064a\u0631\u0644\u0627\u062a\u0627"
    ],
    "name:arg_x_preferred":[
        "Cillaperlata"
    ],
    "name:ast_x_preferred":[
        "Cillaperlata"
    ],
    "name:cat_x_preferred":[
        "Cillaperlata"
    ],
    "name:ceb_x_preferred":[
        "Cillaperlata"
    ],
    "name:eng_x_preferred":[
        "Cillaperlata"
    ],
    "name:eus_x_preferred":[
        "Cillaperlata"
    ],
    "name:fas_x_preferred":[
        "\u0633\u06cc\u06cc\u0627\u067e\u0631\u0644\u0627\u062a\u0627"
    ],
    "name:fra_x_preferred":[
        "Cillaperlata"
    ],
    "name:glg_x_preferred":[
        "Cillaperlata"
    ],
    "name:haw_x_preferred":[
        "Cillaperlata"
    ],
    "name:hun_x_preferred":[
        "Cillaperlata"
    ],
    "name:ina_x_preferred":[
        "Cillaperlata"
    ],
    "name:ita_x_preferred":[
        "Cillaperlata"
    ],
    "name:lad_x_preferred":[
        "Cillaperlata"
    ],
    "name:msa_x_preferred":[
        "Cillaperlata"
    ],
    "name:nan_x_preferred":[
        "Cillaperlata"
    ],
    "name:nld_x_preferred":[
        "Cillaperlata"
    ],
    "name:oci_x_preferred":[
        "Cillaperlata"
    ],
    "name:pol_x_preferred":[
        "Cillaperlata"
    ],
    "name:por_x_preferred":[
        "Cillaperlata"
    ],
    "name:rus_x_preferred":[
        "\u0421\u0438\u043b\u044c\u044f\u043f\u0435\u0440\u043b\u0430\u0442\u0430"
    ],
    "name:spa_x_preferred":[
        "Cillaperlata"
    ],
    "name:swe_x_preferred":[
        "Cillaperlata"
    ],
    "name:ukr_x_preferred":[
        "\u0421\u0456\u043b\u044c\u044f\u043f\u0435\u0440\u043b\u0430\u0442\u0430"
    ],
    "name:uzb_x_preferred":[
        "Cillaperlata"
    ],
    "name:vie_x_preferred":[
        "Cillaperlata"
    ],
    "name:war_x_preferred":[
        "Cillaperlata"
    ],
    "name:zho_x_preferred":[
        "\u897f\u5229\u4e9a\u4f69\u5c14\u62c9\u5854"
    ],
    "qs_pg:aaroncc":"ES",
    "qs_pg:gn_country":"ES",
    "qs_pg:gn_fcode":"ADM3",
    "qs_pg:gn_pop":40,
    "qs_pg:name":"Cillaperlata",
    "qs_pg:name_adm0":"Espa\u00f1a",
    "qs_pg:name_adm1":"Castilla y Le\u00f3n",
    "qs_pg:photos":213,
    "qs_pg:photos_1k":43,
    "qs_pg:photos_9k":1,
    "qs_pg:photos_9r":4,
    "qs_pg:photos_all":213,
    "qs_pg:photos_sr":4,
    "qs_pg:pop_sr":1,
    "qs_pg:qs_pg_placetype":"locality",
    "qs_pg:qs_pg_placetype_gp":"Town",
    "qs_pg:woe_adm0":23424950,
    "woe:adm0_id":23424950,
    "woe:name_adm0":"Espa\u00f1a",
    "woe:name_adm1":"Castilla y Le\u00f3n",
    "woe:placetype":"Town",
    "wof:name":"Cillaperlata",
    "wof:placetype":"locality",
    "wof:population":46
},
  "geometry": {"coordinates":[-3.37599,42.7807],"type":"Point"}
}