{
  "type": "Feature",
  "properties": {
    "gn:country":"ES",
    "gn:fcode":"PPLA3",
    "gn:population":1021,
    "iso:country":"ES",
    "name:arg_x_preferred":[
        "Ballobar"
    ],
    "name:ceb_x_preferred":[
        "Ballobar"
    ],
    "name:eng_x_preferred":[
        "Argavieso"
    ],
    "name:eus_x_preferred":[
        "Ballobar"
    ],
    "name:ita_x_preferred":[
        "Ballobar"
    ],
    "name:nld_x_preferred":[
        "Ballobar"
    ],
    "name:por_x_preferred":[
        "Ballobar"
    ],
    "name:spa_x_preferred":[
        "Ballobar"
    ],
    "name:swe_x_preferred":[
        "Ballobar"
    ],
    "qs_pg:aaroncc":"ES",
    "qs_pg:gn_country":"ES",
    "qs_pg:gn_fcode":"PPLA3",
    "qs_pg:gn_pop":1021,
    "qs_pg:name":"Ballobar",
    "qs_pg:name_adm0":"Espa\u00f1a",
    "qs_pg:name_adm1":"Arag\u00f3n",
    "qs_pg:photos":25,
    "qs_pg:photos_1k":5,
    "qs_pg:photos_9k":1,
    "qs_pg:photos_9r":1,
    "qs_pg:photos_all":25,
    "qs_pg:photos_sr":1,
    "qs_pg:pop_sr":3,
    "qs_pg:qs_pg_placetype":"locality",
    "qs_pg:qs_pg_placetype_gp":"Town",
    "qs_pg:woe_adm0":23424950,
    "woe:adm0_id":23424950,
    "woe:name_adm0":"Espa\u00f1a",
    "woe:name_adm1":"Arag\u00f3n",
    "woe:placetype":"Town",
    "wof:name":"Ballobar",
    "wof:placetype":"locality",
    "wof:population":1021
},
  "geometry": {"coordinates":[0.192,41.62106],"type":"Point"}
}