{
  "type": "Feature",
  "properties": {
    "gn:admin1_code":"55",
    "gn:admin2_code":"AV",
    "gn:admin3_code":"05162",
    "gn:asciiname":"Ortigosa de Tormes",
    "gn:country_code":"ES",
    "gn:dem":1597,
    "gn:feature_class":"P",
    "gn:feature_code":"PPL",
    "gn:name":"Ortigosa de Tormes",
    "gn:population":0,
    "gn:timezone":"Europe/Madrid",
    "iso:country":"ES",
    "wof:name":"Ortigosa de Tormes",
    "wof:placetype":"locality"
},
  "geometry": {"coordinates":[-5.30388,40.36561],"type":"Point"}
}