{
  "type": "Feature",
  "properties": {
    "gn:admin1_code":"57",
    "gn:admin2_code":"CC",
    "gn:admin3_code":"10218",
    "gn:asciiname":"Moreras",
    "gn:cc2":"ES",
    "gn:country_code":"ES",
    "gn:dem":321,
    "gn:feature_class":"P",
    "gn:feature_code":"PPL",
    "gn:name":"Moreras",
    "gn:population":0,
    "gn:timezone":"Europe/Madrid",
    "iso:country":"ES",
    "name:und_x_variant":[
        "Casas Moreras",
        "Moreras"
    ],
    "wof:name":"Moreras",
    "wof:placetype":"locality"
},
  "geometry": {"coordinates":[-6.86667,39.98333],"type":"Point"}
}