{
  "type": "Feature",
  "properties": {
    "gn:admin1_code":"07",
    "gn:admin2_code":"PM",
    "gn:admin3_code":"07011",
    "gn:asciiname":"Bendinat",
    "gn:country_code":"ES",
    "gn:dem":27,
    "gn:feature_class":"P",
    "gn:feature_code":"PPL",
    "gn:name":"Bendinat",
    "gn:population":0,
    "gn:timezone":"Europe/Madrid",
    "iso:country":"ES",
    "wof:name":"Bendinat",
    "wof:placetype":"locality"
},
  "geometry": {"coordinates":[2.57917,39.53493],"type":"Point"}
}