{
  "type": "Feature",
  "properties": {
    "gn:admin1_code":"39",
    "gn:admin2_code":"S",
    "gn:admin3_code":"39002",
    "gn:asciiname":"Bulco",
    "gn:country_code":"ES",
    "gn:dem":39,
    "gn:feature_class":"P",
    "gn:feature_code":"PPL",
    "gn:name":"Bulco",
    "gn:population":0,
    "gn:timezone":"Europe/Madrid",
    "iso:country":"ES",
    "wof:name":"Bulco",
    "wof:placetype":"locality"
},
  "geometry": {"coordinates":[-3.44817,43.31048],"type":"Point"}
}