{
  "type": "Feature",
  "properties": {
    "iso:country":"ES",
    "name:eng_x_preferred":[
        "Santa Julia"
    ],
    "name:spa_x_preferred":[
        "Santa Julia"
    ],
    "wof:name":"Santa Julia",
    "wof:placetype":"neighbourhood"
},
  "geometry": {"coordinates":[-4.44364268490782,36.71105116400017],"type":"Point"}
}