{
  "type": "Feature",
  "properties": {
    "gn:admin1_code":"55",
    "gn:admin2_code":"ZA",
    "gn:admin3_code":"49189",
    "gn:asciiname":"San Ciprian",
    "gn:country_code":"ES",
    "gn:dem":1168,
    "gn:feature_class":"P",
    "gn:feature_code":"PPL",
    "gn:name":"San Cipri\u00e1n",
    "gn:population":0,
    "gn:timezone":"Europe/Madrid",
    "iso:country":"ES",
    "wof:name":"San Ciprian",
    "wof:placetype":"locality"
},
  "geometry": {"coordinates":[-6.65958,42.17328],"type":"Point"}
}