{
  "type": "Feature",
  "properties": {
    "gn:admin1_code":"34",
    "gn:admin2_code":"O",
    "gn:admin3_code":"33011",
    "gn:asciiname":"Trones",
    "gn:country_code":"ES",
    "gn:dem":806,
    "gn:feature_class":"P",
    "gn:feature_code":"PPL",
    "gn:name":"Trones",
    "gn:population":0,
    "gn:timezone":"Europe/Madrid",
    "iso:country":"ES",
    "name:ast_x_preferred":[
        "Trones"
    ],
    "name:spa_x_preferred":[
        "Trones"
    ],
    "wof:name":"Trones",
    "wof:placetype":"locality"
},
  "geometry": {"coordinates":[-6.59883,43.18714],"type":"Point"}
}