{
  "type": "Feature",
  "properties": {
    "iso:country":"ES",
    "name:eng_x_preferred":[
        "Pilar del Prado"
    ],
    "name:spa_x_preferred":[
        "Pilar del Prado"
    ],
    "wof:name":"Pilar del Prado",
    "wof:placetype":"neighbourhood"
},
  "geometry": {"coordinates":[-4.53360044425112,36.72111927587252],"type":"Point"}
}