{
  "type": "Feature",
  "properties": {
    "gn:admin1_code":"54",
    "gn:admin2_code":"GU",
    "gn:admin3_code":"19257",
    "gn:asciiname":"Torre de Valdealmendras",
    "gn:cc2":"ES",
    "gn:country_code":"ES",
    "gn:dem":1007,
    "gn:feature_class":"P",
    "gn:feature_code":"PPL",
    "gn:name":"Torre de Valdealmendras",
    "gn:population":0,
    "gn:timezone":"Europe/Madrid",
    "iso:country":"ES",
    "name:und_x_variant":[
        "Torre de Valdea",
        "Torre de Valdealmendras"
    ],
    "wof:name":"Torre de Valdealmendras",
    "wof:placetype":"locality"
},
  "geometry": {"coordinates":[-2.65,41.15],"type":"Point"}
}