{
  "type": "Feature",
  "properties": {
    "gn:admin1_code":"55",
    "gn:admin2_code":"LE",
    "gn:admin3_code":"24093",
    "gn:asciiname":"Zacos",
    "gn:country_code":"ES",
    "gn:dem":936,
    "gn:feature_class":"P",
    "gn:feature_code":"PPL",
    "gn:name":"Zacos",
    "gn:population":0,
    "gn:timezone":"Europe/Madrid",
    "iso:country":"ES",
    "wof:name":"Zacos",
    "wof:placetype":"locality"
},
  "geometry": {"coordinates":[-6.08391,42.56648],"type":"Point"}
}