{
  "type": "Feature",
  "properties": {
    "gn:gn_country":"ES",
    "gn:gn_fcode":"PPLA3",
    "gn:gn_pop":149,
    "gn:population":149,
    "iso:country":"ES",
    "name:baq_x_preferred":[
        "Santa Cecilia del Alcor"
    ],
    "name:cat_x_preferred":[
        "Santa Cecilia del Alcor"
    ],
    "name:chi_x_preferred":[
        "\u5723\u585e\u897f\u5229\u4e9a\u5fb7\u62c9\u5c14\u79d1\u5c14"
    ],
    "name:dut_x_preferred":[
        "Santa Cecilia del Alcor"
    ],
    "name:eng_x_preferred":[
        "Santa Cecilia del Alcor"
    ],
    "name:fre_x_preferred":[
        "Santa Cecilia del Alcor"
    ],
    "name:ger_x_preferred":[
        "Santa Cecilia del Alcor"
    ],
    "name:glg_x_preferred":[
        "Santa Cecilia del Alcor"
    ],
    "name:hun_x_preferred":[
        "Santa Cecilia del Alcor"
    ],
    "name:ina_x_preferred":[
        "Santa Cecilia del Alcor"
    ],
    "name:ita_x_preferred":[
        "Santa Cecilia del Alcor"
    ],
    "name:may_x_preferred":[
        "Santa Cecilia del Alcor"
    ],
    "name:nan_x_preferred":[
        "Santa Cecilia del Alcor"
    ],
    "name:oci_x_preferred":[
        "Santa Cecilia del Alcor"
    ],
    "name:per_x_preferred":[
        "\u0633\u0627\u0646\u062a\u0627 \u0633\u0633\u06cc\u0644\u06cc\u0627 \u062f\u0644 \u0622\u0644\u06a9\u0631"
    ],
    "name:pol_x_preferred":[
        "Santa Cecilia del Alcor"
    ],
    "name:por_x_preferred":[
        "Santa Cecilia del Alcor"
    ],
    "name:rus_x_preferred":[
        "\u0421\u0430\u043d\u0442\u0430-\u0421\u0435\u0441\u0438\u043b\u0438\u0430-\u0434\u0435\u043b\u044c-\u0410\u043b\u044c\u043a\u043e\u0440"
    ],
    "name:spa_x_preferred":[
        "Santa Cecilia del Alcor"
    ],
    "name:swe_x_preferred":[
        "Santa Cecilia del Alcor"
    ],
    "name:ukr_x_preferred":[
        "\u0421\u0430\u043d\u0442\u0430-\u0421\u0435\u0441\u0456\u043b\u0456\u044f-\u0434\u0435\u043b\u044c-\u0410\u043b\u044c\u043a\u043e\u0440"
    ],
    "name:vie_x_preferred":[
        "Santa Cecilia del Alcor"
    ],
    "name:war_x_preferred":[
        "Santa Cecilia del Alcor"
    ],
    "qs_pg:aaroncc":"ES",
    "qs_pg:gn_country":"ES",
    "qs_pg:gn_fcode":"PPLA3",
    "qs_pg:gn_pop":149,
    "qs_pg:name":"Santa Cecilia del Alcor",
    "qs_pg:name_adm0":"Espa\u00f1a",
    "qs_pg:name_adm1":"Castilla y Le\u00f3n",
    "qs_pg:photos_9k":1,
    "qs_pg:photos_9r":1,
    "qs_pg:photos_all":3,
    "qs_pg:photos_sr":0,
    "qs_pg:pop_sr":1,
    "qs_pg:qs_pg_placetype":"locality",
    "qs_pg:qs_pg_placetype_gp":"Town",
    "qs_pg:woe_adm0":23424950,
    "woe:adm0_id":23424950,
    "woe:name_adm0":"Espa\u00f1a",
    "woe:name_adm1":"Castilla y Le\u00f3n",
    "woe:placetype":"Town",
    "wof:name":"Santa Cecilia del Alcor",
    "wof:placetype":"locality",
    "wof:population":149
},
  "geometry": {"coordinates":[-4.65546,41.93227],"type":"Point"}
}