{
  "type": "Feature",
  "properties": {
    "gn:admin1_code":"58",
    "gn:admin2_code":"OR",
    "gn:admin3_code":"32034",
    "gn:asciiname":"Tameiron",
    "gn:country_code":"ES",
    "gn:dem":979,
    "gn:feature_class":"P",
    "gn:feature_code":"PPL",
    "gn:name":"Tameir\u00f3n",
    "gn:population":0,
    "gn:timezone":"Europe/Madrid",
    "iso:country":"ES",
    "name:und_x_variant":[
        "Santa Mar\u00eda de Tameir\u00f3n",
        "Tameir\u00f3n"
    ],
    "wof:name":"Tameiron",
    "wof:placetype":"locality"
},
  "geometry": {"coordinates":[-7.12027,42.00663],"type":"Point"}
}