{
  "type": "Feature",
  "properties": {
    "gn:admin1_code":"55",
    "gn:admin2_code":"AV",
    "gn:admin3_code":"05014",
    "gn:asciiname":"Ramacastanas",
    "gn:country_code":"ES",
    "gn:dem":409,
    "gn:feature_class":"P",
    "gn:feature_code":"PPL",
    "gn:name":"Ramacasta\u00f1as",
    "gn:population":0,
    "gn:timezone":"Europe/Madrid",
    "iso:country":"ES",
    "name:und_x_variant":[
        "Ramacasta\u00f1as"
    ],
    "wof:name":"Ramacastanas",
    "wof:placetype":"locality"
},
  "geometry": {"coordinates":[-5.04678,40.18602],"type":"Point"}
}