{
  "type": "Feature",
  "properties": {
    "gn:country":"ES",
    "gn:fcode":"PPLA3",
    "gn:population":14,
    "iso:country":"ES",
    "name:arg_x_preferred":[
        "Fuembellida"
    ],
    "name:ast_x_preferred":[
        "Fuembellida"
    ],
    "name:bul_x_preferred":[
        "\u0424\u0443\u0435\u043c\u0431\u0435\u043b\u0438\u0434\u0430"
    ],
    "name:cat_x_preferred":[
        "Fuembellida"
    ],
    "name:ceb_x_preferred":[
        "Fuembellida"
    ],
    "name:che_x_preferred":[
        "\u0424\u0443\u044d\u043c\u0431\u0435\u043b\u044c\u0438\u0434\u0430"
    ],
    "name:eng_x_preferred":[
        "Fuembellida"
    ],
    "name:epo_x_preferred":[
        "Fuembellida"
    ],
    "name:eus_x_preferred":[
        "Fuembellida"
    ],
    "name:fra_x_preferred":[
        "Fuembellida"
    ],
    "name:gle_x_preferred":[
        "Fuembellida"
    ],
    "name:hun_x_preferred":[
        "Fuembellida"
    ],
    "name:ile_x_preferred":[
        "Fuembellida"
    ],
    "name:ina_x_preferred":[
        "Fuembellida"
    ],
    "name:ita_x_preferred":[
        "Fuembellida"
    ],
    "name:kaz_x_preferred":[
        "\u0424\u0443\u044d\u043c\u0431\u0435\u043b\u044c\u0438\u0434\u0430"
    ],
    "name:lld_x_preferred":[
        "Fuembellida"
    ],
    "name:ltz_x_preferred":[
        "Fuembellida"
    ],
    "name:msa_x_preferred":[
        "Fuembellida"
    ],
    "name:nan_x_preferred":[
        "Fuembellida"
    ],
    "name:nld_x_preferred":[
        "Fuembellida"
    ],
    "name:nob_x_preferred":[
        "Fuembellida"
    ],
    "name:oci_x_preferred":[
        "Fuembellida"
    ],
    "name:pol_x_preferred":[
        "Fuembellida"
    ],
    "name:por_x_preferred":[
        "Fuembellida"
    ],
    "name:rus_x_preferred":[
        "\u0424\u0443\u044d\u043c\u0431\u0435\u043b\u044c\u0438\u0434\u0430"
    ],
    "name:spa_x_preferred":[
        "Fuembellida"
    ],
    "name:swe_x_preferred":[
        "Fuembellida"
    ],
    "name:tat_x_preferred":[
        "\u0424\u0443\u044d\u043c\u0431\u0435\u043b\u044c\u0438\u0434\u0430"
    ],
    "name:ukr_x_preferred":[
        "\u0424\u0443\u0435\u043c\u0431\u0435\u043b\u044c\u0457\u0434\u0430"
    ],
    "name:vec_x_preferred":[
        "Fuembellida"
    ],
    "name:vie_x_preferred":[
        "Fuembellida"
    ],
    "name:war_x_preferred":[
        "Fuembellida"
    ],
    "qs_pg:aaroncc":"ES",
    "qs_pg:gn_country":"ES",
    "qs_pg:gn_fcode":"PPLA3",
    "qs_pg:gn_pop":14,
    "qs_pg:name":"Fuembellida",
    "qs_pg:name_adm0":"Espa\u00f1a",
    "qs_pg:name_adm1":"Castilla-La Mancha",
    "qs_pg:photos_9r":0,
    "qs_pg:photos_sr":0,
    "qs_pg:pop_sr":1,
    "qs_pg:qs_pg_placetype":"locality",
    "qs_pg:qs_pg_placetype_gp":"Town",
    "qs_pg:woe_adm0":23424950,
    "woe:adm0_id":23424950,
    "woe:name_adm0":"Espa\u00f1a",
    "woe:name_adm1":"Castilla-La Mancha",
    "woe:placetype":"Town",
    "wof:name":"Fuembellida",
    "wof:placetype":"locality",
    "wof:population":14
},
  "geometry": {"coordinates":[-1.99861,40.75589],"type":"Point"}
}