{
  "type": "Feature",
  "properties": {
    "gn:admin1_code":"58",
    "gn:admin2_code":"PO",
    "gn:admin3_code":"36018",
    "gn:asciiname":"Quintillan",
    "gn:country_code":"ES",
    "gn:dem":550,
    "gn:feature_class":"P",
    "gn:feature_code":"PPL",
    "gn:name":"Quintill\u00e1n",
    "gn:population":0,
    "gn:timezone":"Europe/Madrid",
    "iso:country":"ES",
    "name:und_x_variant":[
        "Quintill\u00e1n"
    ],
    "wof:name":"Quintillan",
    "wof:placetype":"locality"
},
  "geometry": {"coordinates":[-8.37312,42.63012],"type":"Point"}
}