{
  "type": "Feature",
  "properties": {
    "gn:admin1_code":"58",
    "gn:admin2_code":"PO",
    "gn:admin3_code":"36018",
    "gn:asciiname":"Quintillan",
    "gn:country_code":"ES",
    "gn:dem":550,
    "gn:feature_class":"P",
    "gn:feature_code":"PPL",
    "gn:name":"Quintill\u00e1n",
    "gn:population":0,
    "gn:timezone":"Europe/Madrid",
    "iso:country":"ES",
    "name:cat_x_preferred":[
        "Quintilhan"
    ],
    "name:ceb_x_preferred":[
        "Quintillan"
    ],
    "name:deu_x_preferred":[
        "Quintillan"
    ],
    "name:eus_x_preferred":[
        "Quintilhan"
    ],
    "name:fra_x_preferred":[
        "Quintillan"
    ],
    "name:hun_x_preferred":[
        "Quintillan"
    ],
    "name:hye_x_preferred":[
        "\u0554\u0565\u0576\u057f\u056b\u0575\u0561\u0576"
    ],
    "name:ita_x_preferred":[
        "Quintillan"
    ],
    "name:kaz_x_preferred":[
        "\u041a\u0435\u043d\u0442\u0438\u044f\u043d"
    ],
    "name:lat_x_preferred":[
        "Quintillan"
    ],
    "name:lmo_x_preferred":[
        "Quintillan"
    ],
    "name:mlg_x_preferred":[
        "Quintillan"
    ],
    "name:msa_x_preferred":[
        "Quintillan"
    ],
    "name:nld_x_preferred":[
        "Quintillan"
    ],
    "name:oci_x_preferred":[
        "Quintilhan"
    ],
    "name:pms_x_preferred":[
        "Quintillan"
    ],
    "name:pol_x_preferred":[
        "Quintillan"
    ],
    "name:por_x_preferred":[
        "Quintillan"
    ],
    "name:ron_x_preferred":[
        "Quintillan"
    ],
    "name:rus_x_preferred":[
        "\u041a\u0435\u043d\u0442\u0438\u0439\u0430\u043d"
    ],
    "name:slk_x_preferred":[
        "Quintillan"
    ],
    "name:spa_x_preferred":[
        "Quintillan"
    ],
    "name:swe_x_preferred":[
        "Quintillan"
    ],
    "name:ukr_x_preferred":[
        "\u041a\u0435\u043d\u0442\u0456\u044f\u043d"
    ],
    "name:und_x_variant":[
        "Quintill\u00e1n"
    ],
    "name:vie_x_preferred":[
        "Quintillan"
    ],
    "name:vol_x_preferred":[
        "Quintillan"
    ],
    "name:war_x_preferred":[
        "Quintillan"
    ],
    "name:zho_x_preferred":[
        "\u574e\u63d0\u626c"
    ],
    "wof:name":"Quintillan",
    "wof:placetype":"locality"
},
  "geometry": {"coordinates":[-8.37312,42.63012],"type":"Point"}
}