{
  "type": "Feature",
  "properties": {
    "gn:admin1_code":"51",
    "gn:admin2_code":"CA",
    "gn:admin3_code":"11006",
    "gn:asciiname":"Cortijo Rey",
    "gn:country_code":"ES",
    "gn:dem":109,
    "gn:feature_class":"P",
    "gn:feature_code":"PPL",
    "gn:name":"Cortijo Rey",
    "gn:population":0,
    "gn:timezone":"Europe/Madrid",
    "iso:country":"ES",
    "name:und_x_variant":[
        "Caser\u00edo Cortijo Rey",
        "Cortijo Rey"
    ],
    "wof:name":"Cortijo Rey",
    "wof:placetype":"locality"
},
  "geometry": {"coordinates":[-5.84253,36.82177],"type":"Point"}
}