{
  "type": "Feature",
  "properties": {
    "gn:admin1_code":"54",
    "gn:admin2_code":"AB",
    "gn:admin3_code":"02067",
    "gn:asciiname":"El Nogueron",
    "gn:country_code":"ES",
    "gn:dem":1070,
    "gn:feature_class":"P",
    "gn:feature_code":"PPL",
    "gn:name":"El Noguer\u00f3n",
    "gn:population":0,
    "gn:timezone":"Europe/Madrid",
    "iso:country":"ES",
    "name:und_x_variant":[
        "Caser\u00edo El Noguer\u00f3n",
        "El Noguer\u00f3n"
    ],
    "wof:name":"El Nogueron",
    "wof:placetype":"locality"
},
  "geometry": {"coordinates":[-2.45708,38.51399],"type":"Point"}
}