{
  "type": "Feature",
  "properties": {
    "gn:admin1_code":"58",
    "gn:admin2_code":"PO",
    "gn:admin3_code":"36024",
    "gn:asciiname":"Lodeiro",
    "gn:country_code":"ES",
    "gn:dem":577,
    "gn:feature_class":"P",
    "gn:feature_code":"PPL",
    "gn:name":"Lodeiro",
    "gn:population":0,
    "gn:timezone":"Europe/Madrid",
    "iso:country":"ES",
    "name:und_x_variant":[
        "San Pelagio",
        "Lodeiro"
    ],
    "wof:name":"Lodeiro",
    "wof:placetype":"locality"
},
  "geometry": {"coordinates":[-8.18573,42.60169000000001],"type":"Point"}
}