{
  "type": "Feature",
  "properties": {
    "gn:admin1_code":"51",
    "gn:admin2_code":"GR",
    "gn:admin3_code":"18122",
    "gn:asciiname":"Riofrio",
    "gn:country_code":"ES",
    "gn:dem":493,
    "gn:feature_class":"P",
    "gn:feature_code":"PPL",
    "gn:name":"Riofr\u00edo",
    "gn:population":0,
    "gn:timezone":"Europe/Madrid",
    "iso:country":"ES",
    "wof:name":"Riofrio",
    "wof:placetype":"locality"
},
  "geometry": {"coordinates":[-4.20768,37.15471],"type":"Point"}
}