{
  "type": "Feature",
  "properties": {
    "gn:admin1_code":"55",
    "gn:admin2_code":"LE",
    "gn:admin3_code":"24165",
    "gn:asciiname":"Sobredo",
    "gn:country_code":"ES",
    "gn:dem":743,
    "gn:feature_class":"P",
    "gn:feature_code":"PPL",
    "gn:name":"Sobredo",
    "gn:population":0,
    "gn:timezone":"Europe/Madrid",
    "iso:country":"ES",
    "wof:name":"Sobredo",
    "wof:placetype":"locality"
},
  "geometry": {"coordinates":[-6.90639,42.5401],"type":"Point"}
}