{
  "type": "Feature",
  "properties": {
    "gn:admin1_code":"59",
    "gn:admin2_code":"VI",
    "gn:admin3_code":"01008",
    "gn:asciiname":"Arroyabe",
    "gn:country_code":"ES",
    "gn:dem":527,
    "gn:feature_class":"P",
    "gn:feature_code":"PPL",
    "gn:name":"Arroiabe",
    "gn:population":0,
    "gn:timezone":"Europe/Madrid",
    "iso:country":"ES",
    "name:eus_x_preferred":[
        "Arroiabe"
    ],
    "name:fra_x_preferred":[
        "Arroiabe"
    ],
    "name:spa_x_preferred":[
        "Arr\u00f3yabe"
    ],
    "name:spa_x_variant":[
        "Arroyabe"
    ],
    "wof:name":"Arroyabe",
    "wof:placetype":"locality"
},
  "geometry": {"coordinates":[-2.61667,42.91667],"type":"Point"}
}