{
  "type": "Feature",
  "properties": {
    "gn:admin1_code":"55",
    "gn:admin2_code":"SG",
    "gn:admin3_code":"40079",
    "gn:asciiname":"Castiltierra",
    "gn:country_code":"ES",
    "gn:dem":967,
    "gn:feature_class":"P",
    "gn:feature_code":"PPL",
    "gn:name":"Castiltierra",
    "gn:population":0,
    "gn:timezone":"Europe/Madrid",
    "iso:country":"ES",
    "wof:name":"Castiltierra",
    "wof:placetype":"locality"
},
  "geometry": {"coordinates":[-3.53297,41.38531],"type":"Point"}
}