{
  "type": "Feature",
  "properties": {
    "gn:admin1_code":"51",
    "gn:admin2_code":"J",
    "gn:admin3_code":"23065",
    "gn:asciiname":"Chozas",
    "gn:cc2":"ES",
    "gn:country_code":"ES",
    "gn:dem":625,
    "gn:feature_class":"P",
    "gn:feature_code":"PPL",
    "gn:name":"Chozas",
    "gn:population":0,
    "gn:timezone":"Europe/Madrid",
    "iso:country":"ES",
    "name:glg_x_preferred":[
        "Chozas"
    ],
    "name:und_x_variant":[
        "Caser\u00edo Chozas"
    ],
    "wof:name":"Chozas",
    "wof:placetype":"locality"
},
  "geometry": {"coordinates":[-2.86667,38.46667],"type":"Point"}
}