{
  "type": "Feature",
  "properties": {
    "gn:country":"ES",
    "gn:fcode":"PPLL",
    "gn:population":0,
    "iso:country":"ES",
    "name:cat_x_preferred":[
        "Lluc"
    ],
    "name:deu_x_preferred":[
        "Lluc"
    ],
    "name:eng_x_preferred":[
        "Lluc"
    ],
    "name:spa_x_preferred":[
        "Lluc"
    ],
    "qs_pg:aaroncc":"ES",
    "qs_pg:gn_country":"ES",
    "qs_pg:gn_fcode":"PPLL",
    "qs_pg:gn_pop":0,
    "qs_pg:name":"Lluc",
    "qs_pg:name_adm0":"Espa\u00f1a",
    "qs_pg:name_adm1":"Illes Balears",
    "qs_pg:photos":362,
    "qs_pg:photos_1k":73,
    "qs_pg:photos_9k":2,
    "qs_pg:photos_9r":5,
    "qs_pg:photos_all":362,
    "qs_pg:photos_sr":6,
    "qs_pg:pop_sr":0,
    "qs_pg:qs_pg_placetype":"locality",
    "qs_pg:qs_pg_placetype_gp":"Town",
    "qs_pg:woe_adm0":23424950,
    "woe:adm0_id":23424950,
    "woe:name_adm0":"Espa\u00f1a",
    "woe:name_adm1":"Illes Balears",
    "woe:placetype":"Town",
    "wof:name":"Lluc",
    "wof:placetype":"locality"
},
  "geometry": {"coordinates":[2.88453,39.82208],"type":"Point"}
}