{
  "type": "Feature",
  "properties": {
    "gn:admin1_code":"58",
    "gn:admin2_code":"LU",
    "gn:admin3_code":"27044",
    "gn:asciiname":"Cadabedo",
    "gn:country_code":"ES",
    "gn:dem":634,
    "gn:feature_class":"P",
    "gn:feature_code":"PPL",
    "gn:name":"Cadabedo",
    "gn:population":0,
    "gn:timezone":"Europe/Madrid",
    "iso:country":"ES",
    "wof:name":"Cadabedo",
    "wof:placetype":"locality"
},
  "geometry": {"coordinates":[-7.36667,43.36667],"type":"Point"}
}