{
  "type": "Feature",
  "properties": {
    "gn:admin1_code":"51",
    "gn:admin2_code":"AL",
    "gn:admin3_code":"04035",
    "gn:asciiname":"Las Jaulas",
    "gn:cc2":"ES",
    "gn:country_code":"ES",
    "gn:dem":65,
    "gn:feature_class":"P",
    "gn:feature_code":"PPL",
    "gn:name":"Las Jaulas",
    "gn:population":0,
    "gn:timezone":"Europe/Madrid",
    "iso:country":"ES",
    "name:und_x_variant":[
        "Cortijo Jaulas",
        "Cortijada Las Jaulas",
        "Las Jaulas"
    ],
    "wof:name":"Las Jaulas",
    "wof:placetype":"locality"
},
  "geometry": {"coordinates":[-1.78333,37.31667],"type":"Point"}
}