{
  "type": "Feature",
  "properties": {
    "gn:country":"ES",
    "gn:fcode":"PPLA3",
    "gn:population":84,
    "iso:country":"ES",
    "name:ara_x_preferred":[
        "\u0628\u064a\u0633\u062c\u0648\u064a\u0631\u0627\u060c \u0643\u0627\u0646\u062a\u0627\u0628\u0631\u064a\u0627"
    ],
    "name:ara_x_variant":[
        "\u0628\u064a\u0633\u062c\u0648\u064a\u0631\u0627"
    ],
    "name:arg_x_preferred":[
        "Pesquera"
    ],
    "name:ast_x_preferred":[
        "Pesquera"
    ],
    "name:cat_x_preferred":[
        "Pesquera"
    ],
    "name:deu_x_preferred":[
        "Pesquera"
    ],
    "name:eng_x_preferred":[
        "Pesquera"
    ],
    "name:epo_x_preferred":[
        "Pesquera"
    ],
    "name:eus_x_preferred":[
        "Pesquera"
    ],
    "name:fra_x_preferred":[
        "Pesquera"
    ],
    "name:glg_x_preferred":[
        "Pesquera"
    ],
    "name:hun_x_preferred":[
        "Pesquera"
    ],
    "name:hye_x_preferred":[
        "\u054a\u0565\u057d\u056f\u0565\u0580\u0561"
    ],
    "name:ina_x_preferred":[
        "Pesquera"
    ],
    "name:ita_x_preferred":[
        "Pesquera"
    ],
    "name:msa_x_preferred":[
        "Pesquera"
    ],
    "name:nan_x_preferred":[
        "Pesquera"
    ],
    "name:nld_x_preferred":[
        "Pesquera"
    ],
    "name:oci_x_preferred":[
        "Pesquera"
    ],
    "name:pol_x_preferred":[
        "Pesquera"
    ],
    "name:por_x_preferred":[
        "Pesquera"
    ],
    "name:rus_x_preferred":[
        "\u041f\u0435\u0441\u043a\u0435\u0440\u0430"
    ],
    "name:spa_x_preferred":[
        "Pesquera"
    ],
    "name:sqi_x_preferred":[
        "Pesquera"
    ],
    "name:tur_x_preferred":[
        "Pesquera"
    ],
    "name:ukr_x_preferred":[
        "\u041f\u0435\u0441\u043a\u0435\u0440\u0430"
    ],
    "name:und_x_variant":[
        "Pesquero"
    ],
    "name:uzb_x_preferred":[
        "Pesquera"
    ],
    "name:vie_x_preferred":[
        "Pesquera"
    ],
    "name:war_x_preferred":[
        "Pesquera"
    ],
    "name:zho_x_preferred":[
        "\u4f69\u65af\u514b\u62c9"
    ],
    "qs_pg:aaroncc":"ES",
    "qs_pg:gn_country":"ES",
    "qs_pg:gn_fcode":"PPLA3",
    "qs_pg:gn_pop":84,
    "qs_pg:name":"Pesquera",
    "qs_pg:name_adm0":"Espa\u00f1a",
    "qs_pg:name_adm1":"Cantabria",
    "qs_pg:photos_9k":1,
    "qs_pg:photos_9r":1,
    "qs_pg:photos_all":4,
    "qs_pg:photos_sr":0,
    "qs_pg:pop_sr":1,
    "qs_pg:qs_pg_placetype":"locality",
    "qs_pg:qs_pg_placetype_gp":"Town",
    "qs_pg:woe_adm0":23424950,
    "woe:adm0_id":23424950,
    "woe:name_adm0":"Espa\u00f1a",
    "woe:name_adm1":"Cantabria",
    "woe:placetype":"Town",
    "wof:name":"Pesquera",
    "wof:placetype":"locality",
    "wof:population":84
},
  "geometry": {"coordinates":[-4.07932,43.08223],"type":"Point"}
}