{
  "type": "Feature",
  "properties": {
    "gn:admin1_code":"56",
    "gn:admin2_code":"L",
    "gn:admin3_code":"25139",
    "gn:asciiname":"Musa",
    "gn:country_code":"ES",
    "gn:dem":1253,
    "gn:feature_class":"P",
    "gn:feature_code":"PPL",
    "gn:name":"Musa",
    "gn:population":0,
    "gn:timezone":"Europe/Madrid",
    "iso:country":"ES",
    "wof:name":"Musa",
    "wof:placetype":"locality"
},
  "geometry": {"coordinates":[1.66909,42.3783],"type":"Point"}
}