{
  "type": "Feature",
  "properties": {
    "gn:admin1_code":"55",
    "gn:admin2_code":"AV",
    "gn:admin3_code":"05247",
    "gn:asciiname":"Guarena",
    "gn:country_code":"ES",
    "gn:dem":1154,
    "gn:feature_class":"P",
    "gn:feature_code":"PPL",
    "gn:name":"Guare\u00f1a",
    "gn:population":0,
    "gn:timezone":"Europe/Madrid",
    "iso:country":"ES",
    "name:und_x_variant":[
        "Guare\u00f1a"
    ],
    "wof:name":"Guarena",
    "wof:placetype":"locality"
},
  "geometry": {"coordinates":[-4.9763,40.6086],"type":"Point"}
}