{
  "type": "Feature",
  "properties": {
    "gn:admin1_code":"55",
    "gn:admin2_code":"LE",
    "gn:admin3_code":"24218",
    "gn:asciiname":"Riego del Monte",
    "gn:country_code":"ES",
    "gn:dem":782,
    "gn:feature_class":"P",
    "gn:feature_code":"PPL",
    "gn:name":"Riego del Monte",
    "gn:population":0,
    "gn:timezone":"Europe/Madrid",
    "iso:country":"ES",
    "wof:name":"Riego del Monte",
    "wof:placetype":"locality"
},
  "geometry": {"coordinates":[-5.47042,42.44239],"type":"Point"}
}