{
  "type": "Feature",
  "properties": {
    "gn:admin1_code":"54",
    "gn:admin2_code":"CU",
    "gn:admin3_code":"16019",
    "gn:asciiname":"Poveda de la Obispalia",
    "gn:country_code":"ES",
    "gn:dem":979,
    "gn:feature_class":"P",
    "gn:feature_code":"PPL",
    "gn:name":"Poveda de la Obispal\u00eda",
    "gn:population":0,
    "gn:timezone":"Europe/Madrid",
    "iso:country":"ES",
    "name:und_x_variant":[
        "Poveda de la Obispal\u00eda"
    ],
    "wof:name":"Poveda de la Obispalia",
    "wof:placetype":"locality"
},
  "geometry": {"coordinates":[-2.42766,39.95591],"type":"Point"}
}