{
  "type": "Feature",
  "properties": {
    "gn:admin1_code":"59",
    "gn:admin2_code":"SS",
    "gn:admin3_code":"20069",
    "gn:asciiname":"Ergobia",
    "gn:country_code":"ES",
    "gn:dem":6,
    "gn:feature_class":"P",
    "gn:feature_code":"PPL",
    "gn:name":"Ergobia",
    "gn:population":0,
    "gn:timezone":"Europe/Madrid",
    "iso:country":"ES",
    "name:eus_x_preferred":[
        "Ergobi"
    ],
    "name:spa_x_preferred":[
        "Ergobi"
    ],
    "wof:name":"Ergobia",
    "wof:placetype":"locality"
},
  "geometry": {"coordinates":[-1.95504,43.27628],"type":"Point"}
}