{
  "type": "Feature",
  "properties": {
    "gn:admin1_code":"27",
    "gn:admin2_code":"LO",
    "gn:admin3_code":"26130",
    "gn:asciiname":"El Rio",
    "gn:country_code":"ES",
    "gn:dem":791,
    "gn:feature_class":"P",
    "gn:feature_code":"PPL",
    "gn:name":"El R\u00edo",
    "gn:population":0,
    "gn:timezone":"Europe/Madrid",
    "iso:country":"ES",
    "name:und_x_variant":[
        "El R\u00edo"
    ],
    "wof:name":"El Rio",
    "wof:placetype":"locality"
},
  "geometry": {"coordinates":[-2.88093,42.31143],"type":"Point"}
}