{
  "type": "Feature",
  "properties": {
    "iso:country":"ES",
    "name:ara_x_preferred":[
        "\u0633\u0627\u0644\u064a\u0646\u0627\u0633"
    ],
    "name:ben_x_preferred":[
        "\u09b8\u09cd\u09af\u09be\u09b2\u09bf\u09a8\u09be\u09b8"
    ],
    "name:ell_x_preferred":[
        "\u03a3\u03b1\u03bb\u03af\u03bd\u03b1\u03c2"
    ],
    "name:eng_x_preferred":[
        "Salinas"
    ],
    "name:fas_x_preferred":[
        "\u0633\u0627\u0644\u06cc\u0646\u0627\u0633"
    ],
    "name:heb_x_preferred":[
        "\u05e1\u05d0\u05dc\u05d9\u05e0\u05d0\u05e1"
    ],
    "name:hin_x_preferred":[
        "\u0938\u0947\u0932\u093f\u0928\u093e\u0938"
    ],
    "name:hun_x_preferred":[
        "Salinas"
    ],
    "name:ind_x_preferred":[
        "Salinas"
    ],
    "name:kor_x_preferred":[
        "\uc0b4\ub9ac\ub098\uc2a4"
    ],
    "name:pol_x_preferred":[
        "Salinas"
    ],
    "name:por_x_preferred":[
        "Salinas"
    ],
    "name:rus_x_preferred":[
        "\u0440\u0435\u043a\u0430 \u0421\u0430\u043b\u0438\u043d\u0430\u0441"
    ],
    "name:spa_x_preferred":[
        "Salinas"
    ],
    "name:swe_x_preferred":[
        "Salinas River"
    ],
    "name:tur_x_preferred":[
        "Salinas"
    ],
    "name:ukr_x_preferred":[
        "\u0421\u0430\u043b\u0456\u043d\u0430\u0441"
    ],
    "name:urd_x_preferred":[
        "\u0633\u0627\u0644\u06cc\u0646\u0627\u0633"
    ],
    "name:vie_x_preferred":[
        "S\u00f4ng Salinas"
    ],
    "wof:name":"Salinas",
    "wof:placetype":"neighbourhood"
},
  "geometry": {"coordinates":[-4.490578,36.74633],"type":"Point"}
}