{
  "type": "Feature",
  "properties": {
    "iso:country":"ES",
    "name:eng_x_preferred":[
        "Salinas"
    ],
    "name:spa_x_preferred":[
        "Salinas"
    ],
    "wof:name":"Salinas",
    "wof:placetype":"neighbourhood"
},
  "geometry": {"coordinates":[-4.49057779000528,36.74632963255193],"type":"Point"}
}