{
  "type": "Feature",
  "properties": {
    "gn:country":"ES",
    "iso:country":"ES",
    "name:cat_x_preferred":[
        "Carvajal"
    ],
    "name:ceb_x_preferred":[
        "Carvajal"
    ],
    "name:deu_x_preferred":[
        "Carvajal"
    ],
    "name:fra_x_preferred":[
        "Carvajal"
    ],
    "name:heb_x_preferred":[
        "\u05e7\u05e8\u05d5\u05d5\u05d7\u05dc"
    ],
    "name:ita_x_preferred":[
        "Carvajal"
    ],
    "name:jpn_x_preferred":[
        "\u30ab\u30eb\u30d0\u30cf\u30eb"
    ],
    "name:pol_x_preferred":[
        "Carvajal"
    ],
    "name:rus_x_preferred":[
        "\u041a\u0430\u0440\u0432\u0430\u0445\u0430\u043b\u044c"
    ],
    "name:spa_x_preferred":[
        "Carvajal"
    ],
    "name:swe_x_preferred":[
        "Carvajal"
    ],
    "name:ukr_x_preferred":[
        "\u041a\u0430\u0440\u0432\u0430\u0445\u0430\u043b\u044c"
    ],
    "qs_pg:aaroncc":"ES",
    "qs_pg:gn_country":"ES",
    "qs_pg:name":"Carvajal",
    "qs_pg:name_adm0":"Espa\u00f1a",
    "qs_pg:name_adm1":"Andaluc\u00eda",
    "qs_pg:photos":193,
    "qs_pg:photos_1k":39,
    "qs_pg:photos_9k":1,
    "qs_pg:photos_9r":4,
    "qs_pg:photos_all":193,
    "qs_pg:photos_sr":4,
    "qs_pg:pop_sr":0,
    "qs_pg:qs_pg_placetype":"locality",
    "qs_pg:qs_pg_placetype_gp":"Town",
    "qs_pg:woe_adm0":23424950,
    "woe:adm0_id":23424950,
    "woe:name_adm0":"Espa\u00f1a",
    "woe:name_adm1":"Andaluc\u00eda",
    "woe:placetype":"Town",
    "wof:name":"Carvajal",
    "wof:placetype":"locality"
},
  "geometry": {"coordinates":[-4.592456,36.56546],"type":"Point"}
}