{
  "type": "Feature",
  "properties": {
    "gn:admin1_code":"55",
    "gn:admin2_code":"SA",
    "gn:admin3_code":"37221",
    "gn:asciiname":"El Coisal",
    "gn:country_code":"ES",
    "gn:dem":867,
    "gn:feature_class":"P",
    "gn:feature_code":"PPL",
    "gn:name":"El Coisal",
    "gn:population":0,
    "gn:timezone":"Europe/Madrid",
    "iso:country":"ES",
    "name:und_x_variant":[
        "Caser\u00edo El Coisal",
        "El Coisal"
    ],
    "wof:name":"El Coisal",
    "wof:placetype":"locality"
},
  "geometry": {"coordinates":[-6.78601,40.32762],"type":"Point"}
}