{
  "type": "Feature",
  "properties": {
    "gn:admin1_code":"56",
    "gn:admin2_code":"L",
    "gn:admin3_code":"25051",
    "gn:asciiname":"Pedra",
    "gn:country_code":"ES",
    "gn:dem":1103,
    "gn:feature_class":"P",
    "gn:feature_code":"PPL",
    "gn:name":"Pedra",
    "gn:population":0,
    "gn:timezone":"Europe/Madrid",
    "iso:country":"ES",
    "wof:name":"Pedra",
    "wof:placetype":"locality"
},
  "geometry": {"coordinates":[1.8088,42.34421],"type":"Point"}
}