{
  "type": "Feature",
  "properties": {
    "gn:gn_country":"ES",
    "gn:gn_fcode":"PPL",
    "gn:gn_pop":157,
    "gn:population":157,
    "iso:country":"ES",
    "name:alb_x_preferred":[
        "Queralbs"
    ],
    "name:ara_x_preferred":[
        "\u0643\u064a\u0631\u0627\u0644\u0628\u0633"
    ],
    "name:arg_x_preferred":[
        "Queralbs"
    ],
    "name:arm_x_preferred":[
        "\u053f\u0565\u0580\u0561\u056c\u0562\u057d"
    ],
    "name:baq_x_preferred":[
        "Queralbs"
    ],
    "name:cat_x_preferred":[
        "Queralbs"
    ],
    "name:chi_x_preferred":[
        "\u514b\u62c9\u5c14\u592b\u65af"
    ],
    "name:dut_x_preferred":[
        "Queralbs"
    ],
    "name:eng_x_preferred":[
        "Queralbs"
    ],
    "name:eus_x_preferred":[
        "Queralbs"
    ],
    "name:fre_x_preferred":[
        "Queralbs"
    ],
    "name:ger_x_preferred":[
        "Queralbs"
    ],
    "name:glg_x_preferred":[
        "Queralbs"
    ],
    "name:hun_x_preferred":[
        "Queralbs"
    ],
    "name:ita_x_preferred":[
        "Queralbs"
    ],
    "name:kaz_x_preferred":[
        "\u041a\u0435\u0440\u0430\u043b\u044c\u0431\u0441"
    ],
    "name:lat_x_preferred":[
        "Queralbs"
    ],
    "name:oci_x_preferred":[
        "Queralbs"
    ],
    "name:per_x_preferred":[
        "\u06a9\u0631\u0627\u0644\u0628\u0633"
    ],
    "name:pol_x_preferred":[
        "Queralbs"
    ],
    "name:por_x_preferred":[
        "Queralbs"
    ],
    "name:rus_x_preferred":[
        "\u041a\u0435\u0440\u0430\u043b\u044c\u0431\u0441"
    ],
    "name:spa_x_preferred":[
        "Queralbs"
    ],
    "name:swe_x_preferred":[
        "Queralbs"
    ],
    "name:uzb_x_preferred":[
        "Queralbs"
    ],
    "name:war_x_preferred":[
        "Queralbs"
    ],
    "qs_pg:aaroncc":"ES",
    "qs_pg:gn_country":"ES",
    "qs_pg:gn_fcode":"PPL",
    "qs_pg:gn_pop":157,
    "qs_pg:name":"Queralbs",
    "qs_pg:name_adm0":"Espa\u00f1a",
    "qs_pg:name_adm1":"Catalunya",
    "qs_pg:photos":933,
    "qs_pg:photos_1k":189,
    "qs_pg:photos_9k":4,
    "qs_pg:photos_9r":6,
    "qs_pg:photos_all":933,
    "qs_pg:photos_sr":10,
    "qs_pg:pop_sr":1,
    "qs_pg:qs_pg_placetype":"locality",
    "qs_pg:qs_pg_placetype_gp":"Town",
    "qs_pg:woe_adm0":23424950,
    "woe:adm0_id":23424950,
    "woe:name_adm0":"Espa\u00f1a",
    "woe:name_adm1":"Catalunya",
    "woe:placetype":"Town",
    "wof:name":"Queralbs",
    "wof:placetype":"locality",
    "wof:population":157
},
  "geometry": {"coordinates":[2.16285,42.34928],"type":"Point"}
}