{
  "type": "Feature",
  "properties": {
    "gn:admin1_code":"32",
    "gn:admin3_code":"31050",
    "gn:asciiname":"Inarbil de Errazu",
    "gn:country_code":"ES",
    "gn:dem":381,
    "gn:feature_class":"P",
    "gn:feature_code":"PPL",
    "gn:name":"I\u00f1\u00e1rbil de Errazu",
    "gn:population":0,
    "gn:timezone":"Europe/Madrid",
    "iso:country":"ES",
    "name:und_x_variant":[
        "I\u00f1\u00e1rbil de Errazu"
    ],
    "wof:name":"Inarbil de Errazu",
    "wof:placetype":"locality"
},
  "geometry": {"coordinates":[-1.45,43.16667],"type":"Point"}
}