{
  "type": "Feature",
  "properties": {
    "gn:admin1_code":"59",
    "gn:admin2_code":"VI",
    "gn:admin3_code":"01059",
    "gn:asciiname":"Lermanda",
    "gn:country_code":"ES",
    "gn:dem":506,
    "gn:feature_class":"P",
    "gn:feature_code":"PPL",
    "gn:name":"Lermanda",
    "gn:population":0,
    "gn:timezone":"Europe/Madrid",
    "iso:country":"ES",
    "wof:name":"Lermanda",
    "wof:placetype":"locality"
},
  "geometry": {"coordinates":[-2.74532,42.84638],"type":"Point"}
}