{
  "type": "Feature",
  "properties": {
    "gn:admin1_code":"34",
    "gn:admin2_code":"O",
    "gn:admin3_code":"33017",
    "gn:asciiname":"Bourio",
    "gn:country_code":"ES",
    "gn:dem":187,
    "gn:feature_class":"P",
    "gn:feature_code":"PPL",
    "gn:name":"Bourio",
    "gn:population":0,
    "gn:timezone":"Europe/Madrid",
    "iso:country":"ES",
    "wof:name":"Bourio",
    "wof:placetype":"locality"
},
  "geometry": {"coordinates":[-6.95671,43.51159000000001],"type":"Point"}
}