{
  "type": "Feature",
  "properties": {
    "gn:admin1_code":"58",
    "gn:admin2_code":"LU",
    "gn:admin3_code":"27005",
    "gn:asciiname":"Pena",
    "gn:country_code":"ES",
    "gn:dem":27,
    "gn:feature_class":"P",
    "gn:feature_code":"PPL",
    "gn:name":"Pena",
    "gn:population":0,
    "gn:timezone":"Europe/Madrid",
    "iso:country":"ES",
    "wof:name":"Pena",
    "wof:placetype":"locality"
},
  "geometry": {"coordinates":[-7.21499,43.55373],"type":"Point"}
}