{
  "type": "Feature",
  "properties": {
    "gn:admin1_code":"58",
    "gn:admin2_code":"PO",
    "gn:admin3_code":"36017",
    "gn:asciiname":"Balboa",
    "gn:country_code":"ES",
    "gn:dem":229,
    "gn:feature_class":"P",
    "gn:feature_code":"PPL",
    "gn:name":"Balboa",
    "gn:population":0,
    "gn:timezone":"Europe/Madrid",
    "iso:country":"ES",
    "name:bul_x_preferred":[
        "\u0411\u0430\u043b\u0431\u043e\u0430"
    ],
    "name:cat_x_preferred":[
        "Balboa"
    ],
    "name:ceb_x_preferred":[
        "Balboa"
    ],
    "name:ces_x_preferred":[
        "Balboa"
    ],
    "name:deu_x_preferred":[
        "Balboa"
    ],
    "name:ell_x_preferred":[
        "\u039c\u03c0\u03b1\u03bb\u03bc\u03c0\u03cc\u03b1"
    ],
    "name:epo_x_preferred":[
        "Balboo"
    ],
    "name:fin_x_preferred":[
        "Balboa"
    ],
    "name:fra_x_preferred":[
        "Balboa"
    ],
    "name:glg_x_preferred":[
        "Balboa"
    ],
    "name:heb_x_preferred":[
        "\u05d1\u05dc\u05d1\u05d5\u05d0\u05d4"
    ],
    "name:hun_x_preferred":[
        "Balboa"
    ],
    "name:ita_x_preferred":[
        "Balboa"
    ],
    "name:jpn_x_preferred":[
        "\u30d0\u30eb\u30dc\u30a2"
    ],
    "name:kor_x_preferred":[
        "\ubc1c\ubcf4\uc544"
    ],
    "name:lav_x_preferred":[
        "Balboa"
    ],
    "name:lit_x_preferred":[
        "Balboa"
    ],
    "name:nld_x_preferred":[
        "Balboa"
    ],
    "name:nor_x_preferred":[
        "Balboa"
    ],
    "name:pol_x_preferred":[
        "Balboa"
    ],
    "name:por_x_preferred":[
        "Balboa"
    ],
    "name:rus_x_preferred":[
        "\u0411\u0430\u043b\u044c\u0431\u043e\u0430"
    ],
    "name:sco_x_preferred":[
        "Balboa"
    ],
    "name:slv_x_preferred":[
        "Balboa"
    ],
    "name:spa_x_preferred":[
        "Balboa"
    ],
    "name:swe_x_preferred":[
        "Balboa"
    ],
    "name:ukr_x_preferred":[
        "\u0411\u0430\u043b\u044c\u0431\u043e\u0430"
    ],
    "wof:name":"Balboa",
    "wof:placetype":"locality"
},
  "geometry": {"coordinates":[-8.39339,42.75787],"type":"Point"}
}