{
  "type": "Feature",
  "properties": {
    "gn:admin1_code":"58",
    "gn:admin2_code":"PO",
    "gn:admin3_code":"36006",
    "gn:asciiname":"Couto de Arriba",
    "gn:country_code":"ES",
    "gn:dem":53,
    "gn:feature_class":"P",
    "gn:feature_code":"PPL",
    "gn:name":"Couto de Arriba",
    "gn:population":0,
    "gn:timezone":"Europe/Madrid",
    "iso:country":"ES",
    "wof:name":"Couto de Arriba",
    "wof:placetype":"locality"
},
  "geometry": {"coordinates":[-8.80944,42.47084],"type":"Point"}
}