{
  "type": "Feature",
  "properties": {
    "gn:admin1_code":"56",
    "gn:admin2_code":"L",
    "gn:admin3_code":"25173",
    "gn:asciiname":"Mesull",
    "gn:country_code":"ES",
    "gn:dem":1411,
    "gn:feature_class":"P",
    "gn:feature_code":"PPL",
    "gn:name":"Mesull",
    "gn:population":0,
    "gn:timezone":"Europe/Madrid",
    "iso:country":"ES",
    "wof:name":"Mesull",
    "wof:placetype":"locality"
},
  "geometry": {"coordinates":[0.87556,42.42007],"type":"Point"}
}