{
  "type": "Feature",
  "properties": {
    "gn:country":"ES",
    "gn:fcode":"ADM3",
    "gn:population":4764,
    "iso:country":"ES",
    "name:ara_x_preferred":[
        "\u0628\u0648\u0644\u0627\u0646\u0643\u0648"
    ],
    "name:arg_x_preferred":[
        "Polanco"
    ],
    "name:ast_x_preferred":[
        "Polanco"
    ],
    "name:cat_x_preferred":[
        "Polanco"
    ],
    "name:eng_x_preferred":[
        "Polanco"
    ],
    "name:eus_x_preferred":[
        "Polanco"
    ],
    "name:fra_x_preferred":[
        "Polanco"
    ],
    "name:glg_x_preferred":[
        "Polanco"
    ],
    "name:hun_x_preferred":[
        "Polanco"
    ],
    "name:ina_x_preferred":[
        "Polanco"
    ],
    "name:ita_x_preferred":[
        "Polanco"
    ],
    "name:lit_x_preferred":[
        "Polankas"
    ],
    "name:msa_x_preferred":[
        "Polanco"
    ],
    "name:nan_x_preferred":[
        "Polanco"
    ],
    "name:nld_x_preferred":[
        "Polanco"
    ],
    "name:oci_x_preferred":[
        "Polanco"
    ],
    "name:pol_x_preferred":[
        "Polanco"
    ],
    "name:por_x_preferred":[
        "Polanco"
    ],
    "name:rus_x_preferred":[
        "\u041f\u043e\u043b\u0430\u043d\u043a\u043e"
    ],
    "name:spa_x_preferred":[
        "Polanco"
    ],
    "name:sqi_x_preferred":[
        "Polanco"
    ],
    "name:tur_x_preferred":[
        "Polanco"
    ],
    "name:ukr_x_preferred":[
        "\u041f\u043e\u043b\u0430\u043d\u043a\u043e"
    ],
    "name:uzb_x_preferred":[
        "Polanco"
    ],
    "name:vie_x_preferred":[
        "Polanco"
    ],
    "name:war_x_preferred":[
        "Polanco"
    ],
    "name:zho_x_preferred":[
        "\u6ce2\u5170\u79d1"
    ],
    "qs_pg:aaroncc":"ES",
    "qs_pg:gn_country":"ES",
    "qs_pg:gn_fcode":"ADM3",
    "qs_pg:gn_pop":4764,
    "qs_pg:name":"Polanco",
    "qs_pg:name_adm0":"Espa\u00f1a",
    "qs_pg:name_adm1":"Cantabria",
    "qs_pg:photos":110,
    "qs_pg:photos_1k":22,
    "qs_pg:photos_9k":1,
    "qs_pg:photos_9r":3,
    "qs_pg:photos_all":110,
    "qs_pg:photos_sr":3,
    "qs_pg:pop_sr":4,
    "qs_pg:qs_pg_placetype":"locality",
    "qs_pg:qs_pg_placetype_gp":"Town",
    "qs_pg:woe_adm0":23424950,
    "woe:adm0_id":23424950,
    "woe:name_adm0":"Espa\u00f1a",
    "woe:name_adm1":"Cantabria",
    "woe:placetype":"Town",
    "wof:name":"Polanco",
    "wof:placetype":"locality",
    "wof:population":5486
},
  "geometry": {"coordinates":[-4.02076,43.38341],"type":"Point"}
}