{
  "type": "Feature",
  "properties": {
    "gn:gn_country":"ES",
    "gn:gn_fcode":"PPLA3",
    "gn:gn_pop":457,
    "gn:population":457,
    "iso:country":"ES",
    "name:arg_x_preferred":[
        "Vega de Tera"
    ],
    "name:baq_x_preferred":[
        "Vega de Tera"
    ],
    "name:cat_x_preferred":[
        "Vega de Tera"
    ],
    "name:chi_x_preferred":[
        "\u8d1d\u52a0\u5fb7\u7279\u62c9"
    ],
    "name:dut_x_preferred":[
        "Vega de Tera"
    ],
    "name:eng_x_preferred":[
        "Vega de Tera"
    ],
    "name:fre_x_preferred":[
        "Vega de Tera"
    ],
    "name:ger_x_preferred":[
        "Vega de Tera"
    ],
    "name:haw_x_preferred":[
        "Vega de Tera"
    ],
    "name:hun_x_preferred":[
        "Vega de Tera"
    ],
    "name:ile_x_preferred":[
        "Vega de Tera"
    ],
    "name:ita_x_preferred":[
        "Vega de Tera"
    ],
    "name:may_x_preferred":[
        "Vega de Tera"
    ],
    "name:nan_x_preferred":[
        "Vega de Tera"
    ],
    "name:oci_x_preferred":[
        "Vega de Tera"
    ],
    "name:per_x_preferred":[
        "\u0648\u06af\u0627 \u062f\u0648 \u062a\u0631\u0627"
    ],
    "name:pol_x_preferred":[
        "Vega de Tera"
    ],
    "name:por_x_preferred":[
        "Vega de Tera"
    ],
    "name:rus_x_preferred":[
        "\u0412\u0435\u0433\u0430-\u0434\u0435-\u0422\u0435\u0440\u0430"
    ],
    "name:spa_x_preferred":[
        "Vega de Tera"
    ],
    "name:swe_x_preferred":[
        "Vega de Tera"
    ],
    "name:ukr_x_preferred":[
        "\u0412\u0435\u0433\u0430-\u0434\u0435-\u0422\u0435\u0440\u0430"
    ],
    "name:uzb_x_preferred":[
        "Vega de Tera"
    ],
    "name:vie_x_preferred":[
        "Vega de Tera"
    ],
    "name:war_x_preferred":[
        "Vega de Tera"
    ],
    "qs_pg:aaroncc":"ES",
    "qs_pg:gn_country":"ES",
    "qs_pg:gn_fcode":"PPLA3",
    "qs_pg:gn_pop":457,
    "qs_pg:name":"Vega de Tera",
    "qs_pg:name_adm0":"Espa\u00f1a",
    "qs_pg:name_adm1":"Castilla y Le\u00f3n",
    "qs_pg:photos_9k":1,
    "qs_pg:photos_9r":1,
    "qs_pg:photos_all":1,
    "qs_pg:photos_sr":0,
    "qs_pg:pop_sr":2,
    "qs_pg:qs_pg_placetype":"locality",
    "qs_pg:qs_pg_placetype_gp":"Town",
    "qs_pg:woe_adm0":23424950,
    "woe:adm0_id":23424950,
    "woe:name_adm0":"Espa\u00f1a",
    "woe:name_adm1":"Castilla y Le\u00f3n",
    "woe:placetype":"Town",
    "wof:name":"Vega de Tera",
    "wof:placetype":"locality",
    "wof:population":457
},
  "geometry": {"coordinates":[-6.125,41.99759],"type":"Point"}
}