{
  "type": "Feature",
  "properties": {
    "gn:gn_country":"ES",
    "gn:gn_fcode":"PPL",
    "gn:gn_pop":0,
    "iso:country":"ES",
    "name:eng_x_preferred":[
        "Y\u00e9"
    ],
    "name:fra_x_preferred":[
        "Ye"
    ],
    "name:nld_x_preferred":[
        "Y\u00e9"
    ],
    "name:spa_x_preferred":[
        "Ye"
    ],
    "name:unk_x_variant":[
        "Caser\u00edo de Ye"
    ],
    "qs_pg:aaroncc":"ES",
    "qs_pg:gn_country":"ES",
    "qs_pg:gn_fcode":"PPL",
    "qs_pg:gn_pop":0,
    "qs_pg:name":"Ye",
    "qs_pg:name_adm0":"Espa\u00f1a",
    "qs_pg:name_adm1":"Islas Canarias",
    "qs_pg:photos":1065,
    "qs_pg:photos_1k":216,
    "qs_pg:photos_9k":5,
    "qs_pg:photos_9r":7,
    "qs_pg:photos_all":1065,
    "qs_pg:photos_sr":11,
    "qs_pg:pop_sr":0,
    "qs_pg:qs_pg_placetype":"locality",
    "qs_pg:qs_pg_placetype_gp":"Town",
    "qs_pg:woe_adm0":23424950,
    "woe:adm0_id":23424950,
    "woe:name_adm0":"Espa\u00f1a",
    "woe:name_adm1":"Islas Canarias",
    "woe:placetype":"Town",
    "wof:name":"Ye",
    "wof:placetype":"locality"
},
  "geometry": {"coordinates":[-13.48115,29.1913],"type":"Point"}
}