{
  "type": "Feature",
  "properties": {
    "gn:gn_country":"ES",
    "gn:gn_fcode":"PPLA3",
    "gn:gn_pop":154,
    "gn:population":154,
    "iso:country":"ES",
    "name:baq_x_preferred":[
        "Laguna de Contreras"
    ],
    "name:cat_x_preferred":[
        "Laguna de Contreras"
    ],
    "name:chi_x_preferred":[
        "\u62c9\u53e4\u7eb3\u5fb7\u5b54\u7279\u96f7\u62c9\u65af"
    ],
    "name:dut_x_preferred":[
        "Laguna de Contreras"
    ],
    "name:eng_x_preferred":[
        "Laguna de Contreras"
    ],
    "name:fre_x_preferred":[
        "Laguna de Contreras"
    ],
    "name:ger_x_preferred":[
        "Laguna de Contreras"
    ],
    "name:hun_x_preferred":[
        "Laguna de Contreras"
    ],
    "name:ina_x_preferred":[
        "Laguna de Contreras"
    ],
    "name:ita_x_preferred":[
        "Laguna de Contreras"
    ],
    "name:may_x_preferred":[
        "Laguna de Contreras"
    ],
    "name:nan_x_preferred":[
        "Laguna de Contreras"
    ],
    "name:oci_x_preferred":[
        "Laguna de Contreras"
    ],
    "name:pol_x_preferred":[
        "Laguna de Contreras"
    ],
    "name:por_x_preferred":[
        "Laguna de Contreras"
    ],
    "name:rus_x_preferred":[
        "\u041b\u0430\u0433\u0443\u043d\u0430-\u0434\u0435-\u041a\u043e\u043d\u0442\u0440\u0435\u0440\u0430\u0441"
    ],
    "name:spa_x_preferred":[
        "Laguna de Contreras"
    ],
    "name:swe_x_preferred":[
        "Laguna de Contreras"
    ],
    "name:ukr_x_preferred":[
        "\u041b\u0430\u0433\u0443\u043d\u0430-\u0434\u0435-\u041a\u043e\u043d\u0442\u0440\u0435\u0440\u0430\u0441"
    ],
    "name:vie_x_preferred":[
        "Laguna de Contreras"
    ],
    "name:war_x_preferred":[
        "Laguna de Contreras"
    ],
    "qs_pg:aaroncc":"ES",
    "qs_pg:gn_country":"ES",
    "qs_pg:gn_fcode":"PPLA3",
    "qs_pg:gn_pop":154,
    "qs_pg:name":"Laguna de Contreras",
    "qs_pg:name_adm0":"Espa\u00f1a",
    "qs_pg:name_adm1":"Castilla y Le\u00f3n",
    "qs_pg:photos":9,
    "qs_pg:photos_1k":2,
    "qs_pg:photos_9k":1,
    "qs_pg:photos_9r":1,
    "qs_pg:photos_all":9,
    "qs_pg:photos_sr":1,
    "qs_pg:pop_sr":1,
    "qs_pg:qs_pg_placetype":"locality",
    "qs_pg:qs_pg_placetype_gp":"Town",
    "qs_pg:woe_adm0":23424950,
    "woe:adm0_id":23424950,
    "woe:name_adm0":"Espa\u00f1a",
    "woe:name_adm1":"Castilla y Le\u00f3n",
    "woe:placetype":"Town",
    "wof:name":"Laguna de Contreras",
    "wof:placetype":"locality",
    "wof:population":154
},
  "geometry": {"coordinates":[-4.02874,41.49513],"type":"Point"}
}