{
  "type": "Feature",
  "properties": {
    "gn:admin1_code":"55",
    "gn:admin2_code":"LE",
    "gn:admin3_code":"24006",
    "gn:asciiname":"Fresnellino del Monte",
    "gn:country_code":"ES",
    "gn:dem":820,
    "gn:feature_class":"P",
    "gn:feature_code":"PPL",
    "gn:name":"Fresnellino del Monte",
    "gn:population":0,
    "gn:timezone":"Europe/Madrid",
    "iso:country":"ES",
    "name:und_x_variant":[
        "Fresnellino",
        "Fresnellino del Monte"
    ],
    "wof:name":"Fresnellino del Monte",
    "wof:placetype":"locality"
},
  "geometry": {"coordinates":[-5.62012,42.44273],"type":"Point"}
}