{
  "type": "Feature",
  "properties": {
    "gn:admin1_code":"58",
    "gn:admin2_code":"LU",
    "gn:admin3_code":"27006",
    "gn:asciiname":"Regosmil",
    "gn:country_code":"ES",
    "gn:dem":804,
    "gn:feature_class":"P",
    "gn:feature_code":"PPL",
    "gn:name":"Regosmil",
    "gn:population":0,
    "gn:timezone":"Europe/Madrid",
    "iso:country":"ES",
    "wof:name":"Regosmil",
    "wof:placetype":"locality"
},
  "geometry": {"coordinates":[-7.15677,42.9469],"type":"Point"}
}