{
  "type": "Feature",
  "properties": {
    "gn:admin1_code":"58",
    "gn:admin2_code":"LU",
    "gn:admin3_code":"27018",
    "gn:asciiname":"Aldobren",
    "gn:country_code":"ES",
    "gn:dem":577,
    "gn:feature_class":"P",
    "gn:feature_code":"PPL",
    "gn:name":"Aldobr\u00e9n",
    "gn:population":0,
    "gn:timezone":"Europe/Madrid",
    "iso:country":"ES",
    "wof:name":"Aldobren",
    "wof:placetype":"locality"
},
  "geometry": {"coordinates":[-7.07667,43.04942],"type":"Point"}
}