{
  "type": "Feature",
  "properties": {
    "gn:admin1_code":"34",
    "gn:admin2_code":"O",
    "gn:admin3_code":"33032",
    "gn:asciiname":"Ordaliego",
    "gn:country_code":"ES",
    "gn:dem":418,
    "gn:feature_class":"P",
    "gn:feature_code":"PPL",
    "gn:name":"Ordaliego",
    "gn:population":0,
    "gn:timezone":"Europe/Madrid",
    "iso:country":"ES",
    "wof:name":"Ordaliego",
    "wof:placetype":"locality"
},
  "geometry": {"coordinates":[-5.5336,43.27995],"type":"Point"}
}