{
  "type": "Feature",
  "properties": {
    "gn:admin1_code":"51",
    "gn:admin2_code":"H",
    "gn:admin3_code":"21012",
    "gn:asciiname":"Mascote",
    "gn:cc2":"ES",
    "gn:country_code":"ES",
    "gn:dem":225,
    "gn:feature_class":"P",
    "gn:feature_code":"PPL",
    "gn:name":"Mascote",
    "gn:population":0,
    "gn:timezone":"Europe/Madrid",
    "iso:country":"ES",
    "name:epo_x_preferred":[
        "Mascote"
    ],
    "name:eus_x_preferred":[
        "Mascote"
    ],
    "name:fra_x_preferred":[
        "Mascote"
    ],
    "name:hye_x_preferred":[
        "\u0544\u0561\u057d\u056f\u0578\u057f\u056b"
    ],
    "name:ita_x_preferred":[
        "Mascote"
    ],
    "name:kat_x_preferred":[
        "\u10db\u10d0\u10e1\u10d9\u10dd\u10e2\u10d8"
    ],
    "name:kaz_x_preferred":[
        "\u041c\u0430\u0441\u043a\u043e\u0442\u0438"
    ],
    "name:mlg_x_preferred":[
        "Mascote"
    ],
    "name:nld_x_preferred":[
        "Mascote"
    ],
    "name:nor_x_preferred":[
        "Mascote"
    ],
    "name:pol_x_preferred":[
        "Mascote"
    ],
    "name:por_x_preferred":[
        "Mascote"
    ],
    "name:ron_x_preferred":[
        "Mascote"
    ],
    "name:rus_x_preferred":[
        "\u041c\u0430\u0441\u043a\u043e\u0442\u0438"
    ],
    "name:spa_x_preferred":[
        "Mascote"
    ],
    "name:und_x_variant":[
        "Caser\u00edo Mascote",
        "Mascote"
    ],
    "name:vie_x_preferred":[
        "Mascote"
    ],
    "name:vol_x_preferred":[
        "Mascote"
    ],
    "name:war_x_preferred":[
        "Mascote"
    ],
    "name:zho_x_preferred":[
        "\u9a6c\u65af\u79d1\u8482"
    ],
    "wof:name":"Mascote",
    "wof:placetype":"locality"
},
  "geometry": {"coordinates":[-6.56667,37.55],"type":"Point"}
}