{
  "type": "Feature",
  "properties": {
    "gn:admin1_code":"51",
    "gn:admin2_code":"H",
    "gn:admin3_code":"21012",
    "gn:asciiname":"Mascote",
    "gn:cc2":"ES",
    "gn:country_code":"ES",
    "gn:dem":225,
    "gn:feature_class":"P",
    "gn:feature_code":"PPL",
    "gn:name":"Mascote",
    "gn:population":0,
    "gn:timezone":"Europe/Madrid",
    "iso:country":"ES",
    "name:und_x_variant":[
        "Caser\u00edo Mascote",
        "Mascote"
    ],
    "wof:name":"Mascote",
    "wof:placetype":"locality"
},
  "geometry": {"coordinates":[-6.56667,37.55],"type":"Point"}
}