{
  "type": "Feature",
  "properties": {
    "gn:gn_country":"ES",
    "gn:gn_fcode":"PPLA3",
    "gn:gn_pop":3519,
    "gn:population":3519,
    "iso:country":"ES",
    "name:alb_x_preferred":[
        "Catoira"
    ],
    "name:ara_x_preferred":[
        "\u0643\u0627\u062a\u0648\u064a\u0631\u0627"
    ],
    "name:baq_x_preferred":[
        "Catoira"
    ],
    "name:cat_x_preferred":[
        "Catoira"
    ],
    "name:chi_x_preferred":[
        "\u5361\u6258\u4f0a\u62c9"
    ],
    "name:deu_x_preferred":[
        "Catoira"
    ],
    "name:dut_x_preferred":[
        "Catoira"
    ],
    "name:eng_x_preferred":[
        "Catoira"
    ],
    "name:fra_x_preferred":[
        "Catoira"
    ],
    "name:fre_x_preferred":[
        "Catoira"
    ],
    "name:ger_x_preferred":[
        "Catoira"
    ],
    "name:glg_x_preferred":[
        "Catoira"
    ],
    "name:hun_x_preferred":[
        "Catoira"
    ],
    "name:ita_x_preferred":[
        "Catoira"
    ],
    "name:jpn_x_preferred":[
        "\u30ab\u30c8\u30a4\u30e9"
    ],
    "name:may_x_preferred":[
        "Catoira"
    ],
    "name:nan_x_preferred":[
        "Catoira"
    ],
    "name:nld_x_preferred":[
        "Catoira"
    ],
    "name:nno_x_preferred":[
        "Catoira"
    ],
    "name:nob_x_preferred":[
        "Catoira"
    ],
    "name:nor_x_preferred":[
        "Catoira"
    ],
    "name:oci_x_preferred":[
        "Catoira"
    ],
    "name:per_x_preferred":[
        "\u06a9\u0627\u062a\u06cc\u0631\u0627"
    ],
    "name:pol_x_preferred":[
        "Catoira"
    ],
    "name:por_x_preferred":[
        "Catoira"
    ],
    "name:roh_x_preferred":[
        "Catoira"
    ],
    "name:rus_x_preferred":[
        "\u041a\u0430\u0442\u043e\u0439\u0440\u0430"
    ],
    "name:spa_x_preferred":[
        "Catoira"
    ],
    "name:swe_x_preferred":[
        "Catoira"
    ],
    "name:tur_x_preferred":[
        "Catoira"
    ],
    "name:ukr_x_preferred":[
        "\u041a\u0430\u0442\u043e\u0439\u0440\u0430"
    ],
    "name:uzb_x_preferred":[
        "Catoira"
    ],
    "name:vie_x_preferred":[
        "Catoira"
    ],
    "name:war_x_preferred":[
        "Catoira"
    ],
    "qs_pg:aaroncc":"ES",
    "qs_pg:gn_country":"ES",
    "qs_pg:gn_fcode":"PPLA3",
    "qs_pg:gn_pop":3519,
    "qs_pg:name":"Catoira",
    "qs_pg:name_adm0":"Espa\u00f1a",
    "qs_pg:name_adm1":"Galicia",
    "qs_pg:photos":957,
    "qs_pg:photos_1k":194,
    "qs_pg:photos_9k":4,
    "qs_pg:photos_9r":6,
    "qs_pg:photos_all":957,
    "qs_pg:photos_sr":10,
    "qs_pg:pop_sr":4,
    "qs_pg:qs_pg_placetype":"locality",
    "qs_pg:qs_pg_placetype_gp":"Town",
    "qs_pg:woe_adm0":23424950,
    "woe:adm0_id":23424950,
    "woe:name_adm0":"Espa\u00f1a",
    "woe:name_adm1":"Galicia",
    "woe:placetype":"Town",
    "wof:name":"Catoira",
    "wof:placetype":"locality",
    "wof:population":3519
},
  "geometry": {"coordinates":[-8.72323,42.66748],"type":"Point"}
}