{
  "type": "Feature",
  "properties": {
    "gn:admin1_code":"55",
    "gn:admin2_code":"LE",
    "gn:admin3_code":"24174",
    "gn:asciiname":"Villarrin del Paramo",
    "gn:cc2":"ES",
    "gn:country_code":"ES",
    "gn:dem":823,
    "gn:feature_class":"P",
    "gn:feature_code":"PPL",
    "gn:name":"Villarr\u00edn del P\u00e1ramo",
    "gn:population":0,
    "gn:timezone":"Europe/Madrid",
    "iso:country":"ES",
    "name:und_x_variant":[
        "Villar\u00edn"
    ],
    "wof:name":"Villarrin del Paramo",
    "wof:placetype":"locality"
},
  "geometry": {"coordinates":[-5.74903,42.39247],"type":"Point"}
}