{
  "type": "Feature",
  "properties": {
    "gn:admin1_code":"55",
    "gn:admin2_code":"SG",
    "gn:admin3_code":"40170",
    "gn:asciiname":"Villacorta",
    "gn:country_code":"ES",
    "gn:dem":1103,
    "gn:feature_class":"P",
    "gn:feature_code":"PPL",
    "gn:name":"Villacorta",
    "gn:population":0,
    "gn:timezone":"Europe/Madrid",
    "iso:country":"ES",
    "wof:name":"Villacorta",
    "wof:placetype":"locality"
},
  "geometry": {"coordinates":[-3.36298,41.32589],"type":"Point"}
}