{
  "type": "Feature",
  "properties": {
    "gn:gn_country":"ES",
    "gn:gn_fcode":"PPLA3",
    "gn:gn_pop":2334,
    "gn:population":2334,
    "iso:country":"ES",
    "name:alb_x_preferred":[
        "Barlovento"
    ],
    "name:ara_x_preferred":[
        "\u0628\u0627\u0631\u0644\u0648\u0641\u064a\u0646\u062a\u0648\u060c \u0633\u0627\u0646\u062a\u0627 \u0643\u0631\u0648\u062b \u062f\u064a \u062a\u064a\u0646\u064a\u0631\u064a\u0641\u0647"
    ],
    "name:baq_x_preferred":[
        "Barlovento"
    ],
    "name:cat_x_preferred":[
        "Barlovento"
    ],
    "name:chi_x_preferred":[
        "\u5df4\u5c14\u6d1b\u6587\u6258"
    ],
    "name:dut_x_preferred":[
        "Barlovento"
    ],
    "name:eng_x_preferred":[
        "Barlovento"
    ],
    "name:fre_x_preferred":[
        "Barlovento"
    ],
    "name:ger_x_preferred":[
        "Barlovento"
    ],
    "name:glg_x_preferred":[
        "Barlovento"
    ],
    "name:hun_x_preferred":[
        "Barlovento"
    ],
    "name:ita_x_preferred":[
        "Barlovento"
    ],
    "name:lat_x_preferred":[
        "Barlovento"
    ],
    "name:may_x_preferred":[
        "Barlovento"
    ],
    "name:oci_x_preferred":[
        "Barlovento"
    ],
    "name:pol_x_preferred":[
        "Barlovento"
    ],
    "name:por_x_preferred":[
        "Barlovento"
    ],
    "name:rus_x_preferred":[
        "\u0411\u0430\u0440\u043b\u043e\u0432\u0435\u043d\u0442\u043e"
    ],
    "name:spa_x_preferred":[
        "Barlovento"
    ],
    "name:swe_x_preferred":[
        "Barlovento"
    ],
    "name:ukr_x_preferred":[
        "\u0411\u0430\u0440\u043b\u043e\u0432\u0435\u043d\u0442\u043e"
    ],
    "name:uzb_x_preferred":[
        "Barlovento"
    ],
    "name:war_x_preferred":[
        "Barlovento"
    ],
    "name:wel_x_preferred":[
        "Barlovento"
    ],
    "qs_pg:aaroncc":"ES",
    "qs_pg:gn_country":"ES",
    "qs_pg:gn_fcode":"PPLA3",
    "qs_pg:gn_pop":2334,
    "qs_pg:name":"Barlovento",
    "qs_pg:name_adm0":"Espa\u00f1a",
    "qs_pg:name_adm1":"Islas Canarias",
    "qs_pg:photos":233,
    "qs_pg:photos_1k":47,
    "qs_pg:photos_9k":1,
    "qs_pg:photos_9r":4,
    "qs_pg:photos_all":233,
    "qs_pg:photos_sr":4,
    "qs_pg:pop_sr":4,
    "qs_pg:qs_pg_placetype":"locality",
    "qs_pg:qs_pg_placetype_gp":"Town",
    "qs_pg:woe_adm0":23424950,
    "woe:adm0_id":23424950,
    "woe:name_adm0":"Espa\u00f1a",
    "woe:name_adm1":"Islas Canarias",
    "woe:placetype":"Town",
    "wof:name":"Barlovento",
    "wof:placetype":"locality",
    "wof:population":2334
},
  "geometry": {"coordinates":[-17.80377,28.82708],"type":"Point"}
}