{
  "type": "Feature",
  "properties": {
    "gn:admin1_code":"55",
    "gn:admin2_code":"SO",
    "gn:admin3_code":"42080",
    "gn:asciiname":"San Asenjo",
    "gn:country_code":"ES",
    "gn:dem":1094,
    "gn:feature_class":"P",
    "gn:feature_code":"PPL",
    "gn:name":"San Asenjo",
    "gn:population":0,
    "gn:timezone":"Europe/Madrid",
    "iso:country":"ES",
    "wof:name":"San Asenjo",
    "wof:placetype":"locality"
},
  "geometry": {"coordinates":[-3.23088,41.82446],"type":"Point"}
}