{
  "type": "Feature",
  "properties": {
    "gn:admin1_code":"58",
    "gn:admin2_code":"LU",
    "gn:admin3_code":"27017",
    "gn:asciiname":"Bustofrio",
    "gn:country_code":"ES",
    "gn:dem":1128,
    "gn:feature_class":"P",
    "gn:feature_code":"PPL",
    "gn:name":"Bustofr\u00edo",
    "gn:population":0,
    "gn:timezone":"Europe/Madrid",
    "iso:country":"ES",
    "wof:name":"Bustofrio",
    "wof:placetype":"locality"
},
  "geometry": {"coordinates":[-7.21667,42.66667],"type":"Point"}
}