{
  "type": "Feature",
  "properties": {
    "gn:admin1_code":"55",
    "gn:admin2_code":"ZA",
    "gn:admin3_code":"49050",
    "gn:asciiname":"Quintana de Sanabria",
    "gn:country_code":"ES",
    "gn:dem":988,
    "gn:feature_class":"P",
    "gn:feature_code":"PPL",
    "gn:name":"Quintana de Sanabria",
    "gn:population":0,
    "gn:timezone":"Europe/Madrid",
    "iso:country":"ES",
    "wof:name":"Quintana de Sanabria",
    "wof:placetype":"locality"
},
  "geometry": {"coordinates":[-6.68081,42.09355],"type":"Point"}
}