{
  "type": "Feature",
  "properties": {
    "gn:admin1_code":"56",
    "gn:admin2_code":"T",
    "gn:admin3_code":"43090",
    "gn:asciiname":"Las Poblas",
    "gn:country_code":"ES",
    "gn:dem":455,
    "gn:feature_class":"P",
    "gn:feature_code":"PPL",
    "gn:name":"Las Poblas",
    "gn:population":0,
    "gn:timezone":"Europe/Madrid",
    "iso:country":"ES",
    "name:und_x_variant":[
        "Les Pobles",
        "Las Poblas"
    ],
    "wof:name":"Las Poblas",
    "wof:placetype":"locality"
},
  "geometry": {"coordinates":[1.402,41.36106],"type":"Point"}
}