{
  "type": "Feature",
  "properties": {
    "gn:admin1_code":"58",
    "gn:admin2_code":"LU",
    "gn:admin3_code":"27060",
    "gn:asciiname":"Mesonfrio",
    "gn:country_code":"ES",
    "gn:dem":636,
    "gn:feature_class":"P",
    "gn:feature_code":"PPL",
    "gn:name":"Mesonfr\u00edo",
    "gn:population":0,
    "gn:timezone":"Europe/Madrid",
    "iso:country":"ES",
    "name:und_x_variant":[
        "Mesonfr\u00edo"
    ],
    "wof:name":"Mesonfrio",
    "wof:placetype":"locality"
},
  "geometry": {"coordinates":[-7.75,42.76667],"type":"Point"}
}