{
  "type": "Feature",
  "properties": {
    "gn:admin1_code":"58",
    "gn:admin2_code":"LU",
    "gn:admin3_code":"27053",
    "gn:asciiname":"Meiroy",
    "gn:country_code":"ES",
    "gn:dem":398,
    "gn:feature_class":"P",
    "gn:feature_code":"PPL",
    "gn:name":"Meiroy",
    "gn:population":0,
    "gn:timezone":"Europe/Madrid",
    "iso:country":"ES",
    "wof:name":"Meiroy",
    "wof:placetype":"locality"
},
  "geometry": {"coordinates":[-7.22221,43.20599],"type":"Point"}
}