{
  "type": "Feature",
  "properties": {
    "gn:admin1_code":"56",
    "gn:admin2_code":"B",
    "gn:admin3_code":"08161",
    "gn:asciiname":"Monistrol de Noya",
    "gn:country_code":"ES",
    "gn:dem":139,
    "gn:feature_class":"P",
    "gn:feature_code":"PPL",
    "gn:name":"Monistrol de Noya",
    "gn:population":0,
    "gn:timezone":"Europe/Madrid",
    "iso:country":"ES",
    "wof:name":"Monistrol de Noya",
    "wof:placetype":"locality"
},
  "geometry": {"coordinates":[1.78547,41.44693],"type":"Point"}
}