{
  "type": "Feature",
  "properties": {
    "gn:admin1_code":"55",
    "gn:admin2_code":"P",
    "gn:admin3_code":"34222",
    "gn:asciiname":"Villorquite de Herrera",
    "gn:country_code":"ES",
    "gn:dem":910,
    "gn:feature_class":"P",
    "gn:feature_code":"PPL",
    "gn:name":"Villorquite de Herrera",
    "gn:population":0,
    "gn:timezone":"Europe/Madrid",
    "iso:country":"ES",
    "wof:name":"Villorquite de Herrera",
    "wof:placetype":"locality"
},
  "geometry": {"coordinates":[-4.44487,42.49944],"type":"Point"}
}