{
  "type": "Feature",
  "properties": {
    "gn:admin1_code":"32",
    "gn:admin3_code":"31123",
    "gn:asciiname":"Huarte-Araquil",
    "gn:cc2":"ES",
    "gn:country_code":"ES",
    "gn:dem":464,
    "gn:feature_class":"P",
    "gn:feature_code":"PPL",
    "gn:name":"Huarte-Araquil",
    "gn:population":0,
    "gn:timezone":"Europe/Madrid",
    "iso:country":"ES",
    "name:und_x_variant":[
        "Huerte-Araquil"
    ],
    "wof:name":"Huarte-Araquil",
    "wof:placetype":"locality"
},
  "geometry": {"coordinates":[-1.96638,42.92161],"type":"Point"}
}