{
  "type": "Feature",
  "properties": {
    "gn:country":"ES",
    "gn:fcode":"PPLA3",
    "gn:population":296,
    "iso:country":"ES",
    "name:arg_x_preferred":[
        "Veganzones"
    ],
    "name:ast_x_preferred":[
        "Veganzones"
    ],
    "name:cat_x_preferred":[
        "Veganzones"
    ],
    "name:ceb_x_preferred":[
        "Veganzones"
    ],
    "name:che_x_preferred":[
        "\u0412\u0435\u0433\u0430\u043d\u0441\u043e\u043d\u0435\u0441"
    ],
    "name:eng_x_preferred":[
        "Veganzones"
    ],
    "name:epo_x_preferred":[
        "Veganzones"
    ],
    "name:eus_x_preferred":[
        "Veganzones"
    ],
    "name:fas_x_preferred":[
        "\u0648\u06af\u0646\u0632\u0646\u0633"
    ],
    "name:fra_x_preferred":[
        "Veganzones"
    ],
    "name:gle_x_preferred":[
        "Veganzones"
    ],
    "name:hun_x_preferred":[
        "Veganzones"
    ],
    "name:ile_x_preferred":[
        "Veganzones"
    ],
    "name:ina_x_preferred":[
        "Veganzones"
    ],
    "name:ita_x_preferred":[
        "Veganzones"
    ],
    "name:lld_x_preferred":[
        "Veganzones"
    ],
    "name:ltz_x_preferred":[
        "Veganzones"
    ],
    "name:msa_x_preferred":[
        "Veganzones"
    ],
    "name:nan_x_preferred":[
        "Veganzones"
    ],
    "name:nld_x_preferred":[
        "Veganzones"
    ],
    "name:nob_x_preferred":[
        "Veganzones"
    ],
    "name:oci_x_preferred":[
        "Veganzones"
    ],
    "name:pol_x_preferred":[
        "Veganzones"
    ],
    "name:por_x_preferred":[
        "Veganzones"
    ],
    "name:rus_x_preferred":[
        "\u0412\u0435\u0433\u0430\u043d\u0441\u043e\u043d\u0435\u0441"
    ],
    "name:spa_x_preferred":[
        "Veganzones"
    ],
    "name:swe_x_preferred":[
        "Veganzones"
    ],
    "name:tat_x_preferred":[
        "\u0412\u0435\u0433\u0430\u043d\u0441\u043e\u043d\u0435\u0441"
    ],
    "name:ukr_x_preferred":[
        "\u0412\u0435\u0433\u0430\u043d\u0441\u043e\u043d\u0435\u0441"
    ],
    "name:und_x_variant":[
        "Beganzones"
    ],
    "name:uzb_x_preferred":[
        "Veganzones"
    ],
    "name:vec_x_preferred":[
        "Veganzones"
    ],
    "name:vie_x_preferred":[
        "Veganzones"
    ],
    "name:war_x_preferred":[
        "Veganzones"
    ],
    "name:zho_x_preferred":[
        "\u8d1d\u7518\u7d22\u5185\u65af"
    ],
    "qs_pg:aaroncc":"ES",
    "qs_pg:gn_country":"ES",
    "qs_pg:gn_fcode":"PPLA3",
    "qs_pg:gn_pop":296,
    "qs_pg:name":"Veganzones",
    "qs_pg:name_adm0":"Espa\u00f1a",
    "qs_pg:name_adm1":"Castilla y Le\u00f3n",
    "qs_pg:photos":23,
    "qs_pg:photos_1k":5,
    "qs_pg:photos_9k":1,
    "qs_pg:photos_9r":1,
    "qs_pg:photos_all":23,
    "qs_pg:photos_sr":1,
    "qs_pg:pop_sr":2,
    "qs_pg:qs_pg_placetype":"locality",
    "qs_pg:qs_pg_placetype_gp":"Town",
    "qs_pg:woe_adm0":23424950,
    "woe:adm0_id":23424950,
    "woe:name_adm0":"Espa\u00f1a",
    "woe:name_adm1":"Castilla y Le\u00f3n",
    "woe:placetype":"Town",
    "wof:name":"Veganzones",
    "wof:placetype":"locality",
    "wof:population":296
},
  "geometry": {"coordinates":[-3.99329,41.19308],"type":"Point"}
}