{
  "type": "Feature",
  "properties": {
    "gn:admin1_code":"34",
    "gn:admin2_code":"O",
    "gn:admin3_code":"33077",
    "gn:asciiname":"Martintorin",
    "gn:country_code":"ES",
    "gn:dem":258,
    "gn:feature_class":"P",
    "gn:feature_code":"PPL",
    "gn:name":"Martintor\u00edn",
    "gn:population":0,
    "gn:timezone":"Europe/Madrid",
    "iso:country":"ES",
    "name:und_x_variant":[
        "Martintor\u00edn"
    ],
    "wof:name":"Martintorin",
    "wof:placetype":"locality"
},
  "geometry": {"coordinates":[-6.69932,43.45514],"type":"Point"}
}