{
  "type": "Feature",
  "properties": {
    "gn:admin1_code":"57",
    "gn:admin2_code":"CC",
    "gn:admin3_code":"10008",
    "gn:asciiname":"Estorninos",
    "gn:country_code":"ES",
    "gn:dem":294,
    "gn:feature_class":"P",
    "gn:feature_code":"PPL",
    "gn:name":"Estorninos",
    "gn:population":0,
    "gn:timezone":"Europe/Madrid",
    "iso:country":"ES",
    "wof:name":"Estorninos",
    "wof:placetype":"locality"
},
  "geometry": {"coordinates":[-6.93298,39.74014],"type":"Point"}
}