{
  "type": "Feature",
  "properties": {
    "gn:admin1_code":"55",
    "gn:admin2_code":"SA",
    "gn:admin3_code":"37170",
    "gn:asciiname":"Aldeagutierrez",
    "gn:country_code":"ES",
    "gn:dem":759,
    "gn:feature_class":"P",
    "gn:feature_code":"PPL",
    "gn:name":"Aldeaguti\u00e9rrez",
    "gn:population":0,
    "gn:timezone":"Europe/Madrid",
    "iso:country":"ES",
    "name:und_x_variant":[
        "Aldeaguti\u00e9rrez"
    ],
    "wof:name":"Aldeagutierrez",
    "wof:placetype":"locality"
},
  "geometry": {"coordinates":[-6.02554,41.10886],"type":"Point"}
}