{
  "type": "Feature",
  "properties": {
    "gn:gn_country":"ES",
    "gn:gn_fcode":"PPLA3",
    "gn:gn_pop":29,
    "gn:population":29,
    "iso:country":"ES",
    "name:arg_x_preferred":[
        "Terroba"
    ],
    "name:ast_x_preferred":[
        "Terroba"
    ],
    "name:cat_x_preferred":[
        "Terroba"
    ],
    "name:ceb_x_preferred":[
        "Terroba"
    ],
    "name:deu_x_preferred":[
        "Terroba"
    ],
    "name:eng_x_preferred":[
        "Terroba"
    ],
    "name:eus_x_preferred":[
        "Terroba"
    ],
    "name:fra_x_preferred":[
        "Terroba"
    ],
    "name:glg_x_preferred":[
        "Terroba"
    ],
    "name:hun_x_preferred":[
        "Terroba"
    ],
    "name:hye_x_preferred":[
        "\u054f\u0565\u057c\u0578\u0562\u0561"
    ],
    "name:ita_x_preferred":[
        "Terroba"
    ],
    "name:kaz_x_preferred":[
        "\u0422\u0435\u0440\u0440\u043e\u0431\u0430"
    ],
    "name:lat_x_preferred":[
        "Terroba"
    ],
    "name:msa_x_preferred":[
        "Terroba"
    ],
    "name:nan_x_preferred":[
        "Terroba"
    ],
    "name:nld_x_preferred":[
        "Terroba"
    ],
    "name:oci_x_preferred":[
        "Terroba"
    ],
    "name:pol_x_preferred":[
        "Terroba"
    ],
    "name:por_x_preferred":[
        "Terroba"
    ],
    "name:rup_x_preferred":[
        "Terroba"
    ],
    "name:rus_x_preferred":[
        "\u0422\u0435\u0440\u0440\u043e\u0431\u0430"
    ],
    "name:spa_x_preferred":[
        "Terroba"
    ],
    "name:swe_x_preferred":[
        "Terroba"
    ],
    "name:ukr_x_preferred":[
        "\u0422\u0435\u0440\u0440\u043e\u0431\u0430"
    ],
    "name:uzb_x_preferred":[
        "Terroba"
    ],
    "name:vie_x_preferred":[
        "Terroba"
    ],
    "name:war_x_preferred":[
        "Terroba"
    ],
    "name:zho_x_preferred":[
        "\u7279\u7f57\u74e6"
    ],
    "qs_pg:aaroncc":"ES",
    "qs_pg:gn_country":"ES",
    "qs_pg:gn_fcode":"PPLA3",
    "qs_pg:gn_pop":29,
    "qs_pg:name":"Terroba",
    "qs_pg:name_adm0":"Espa\u00f1a",
    "qs_pg:name_adm1":"La Rioja",
    "qs_pg:photos_9r":0,
    "qs_pg:photos_sr":0,
    "qs_pg:pop_sr":1,
    "qs_pg:qs_pg_placetype":"locality",
    "qs_pg:qs_pg_placetype_gp":"Town",
    "qs_pg:woe_adm0":23424950,
    "woe:adm0_id":23424950,
    "woe:name_adm0":"Espa\u00f1a",
    "woe:name_adm1":"La Rioja",
    "woe:placetype":"Town",
    "wof:name":"Terroba",
    "wof:placetype":"locality",
    "wof:population":29
},
  "geometry": {"coordinates":[-2.44375,42.25808],"type":"Point"}
}