{
  "type": "Feature",
  "properties": {
    "gn:admin1_code":"58",
    "gn:admin2_code":"OR",
    "gn:admin3_code":"32001",
    "gn:asciiname":"Augasantas",
    "gn:cc2":"ES",
    "gn:country_code":"ES",
    "gn:dem":603,
    "gn:feature_class":"P",
    "gn:feature_code":"PPL",
    "gn:name":"Augasantas",
    "gn:population":0,
    "gn:timezone":"Europe/Madrid",
    "iso:country":"ES",
    "wof:name":"Augasantas",
    "wof:placetype":"locality"
},
  "geometry": {"coordinates":[-7.78613,42.23894],"type":"Point"}
}