{
  "type": "Feature",
  "properties": {
    "gn:country":"ES",
    "gn:fcode":"PPLA3",
    "gn:population":318,
    "iso:country":"ES",
    "name:arg_x_preferred":[
        "Bellestar"
    ],
    "name:ast_x_preferred":[
        "Villastar"
    ],
    "name:cat_x_preferred":[
        "Villastar"
    ],
    "name:ceb_x_preferred":[
        "Villastar"
    ],
    "name:deu_x_preferred":[
        "Villastar"
    ],
    "name:eng_x_preferred":[
        "Villastar"
    ],
    "name:eus_x_preferred":[
        "Villastar"
    ],
    "name:fra_x_preferred":[
        "Villastar"
    ],
    "name:hun_x_preferred":[
        "Villastar"
    ],
    "name:ita_x_preferred":[
        "Villastar"
    ],
    "name:kaz_x_preferred":[
        "\u0412\u0438\u043b\u044c\u044f\u0441\u0442\u0430\u0440"
    ],
    "name:msa_x_preferred":[
        "Villastar"
    ],
    "name:nan_x_preferred":[
        "Villastar"
    ],
    "name:nld_x_preferred":[
        "Villastar"
    ],
    "name:oci_x_preferred":[
        "Villastar"
    ],
    "name:pol_x_preferred":[
        "Villastar"
    ],
    "name:rus_x_preferred":[
        "\u0412\u0438\u043b\u044c\u044f\u0441\u0442\u0430\u0440"
    ],
    "name:spa_x_preferred":[
        "Villastar"
    ],
    "name:swe_x_preferred":[
        "Villastar"
    ],
    "name:ukr_x_preferred":[
        "\u0412\u0456\u043b\u044c\u044f\u0441\u0442\u0430\u0440"
    ],
    "name:uzb_x_preferred":[
        "Villastar"
    ],
    "name:vie_x_preferred":[
        "Villastar"
    ],
    "name:war_x_preferred":[
        "Villastar"
    ],
    "name:zho_x_preferred":[
        "\u6bd4\u5229\u4e9a\u65af\u5854\u5c14"
    ],
    "qs_pg:aaroncc":"ES",
    "qs_pg:gn_country":"ES",
    "qs_pg:gn_fcode":"PPLA3",
    "qs_pg:gn_pop":318,
    "qs_pg:name":"Villastar",
    "qs_pg:name_adm0":"Espa\u00f1a",
    "qs_pg:name_adm1":"Arag\u00f3n",
    "qs_pg:photos_9k":1,
    "qs_pg:photos_9r":1,
    "qs_pg:photos_all":1,
    "qs_pg:photos_sr":0,
    "qs_pg:pop_sr":2,
    "qs_pg:qs_pg_placetype":"locality",
    "qs_pg:qs_pg_placetype_gp":"Town",
    "qs_pg:woe_adm0":23424950,
    "woe:adm0_id":23424950,
    "woe:name_adm0":"Espa\u00f1a",
    "woe:name_adm1":"Arag\u00f3n",
    "woe:placetype":"Town",
    "wof:name":"Villastar",
    "wof:placetype":"locality",
    "wof:population":318
},
  "geometry": {"coordinates":[-1.15139,40.28102],"type":"Point"}
}