{
  "type": "Feature",
  "properties": {
    "iso:country":"ES",
    "wof:name":"Felipe II-Los Diez Mandamientos",
    "wof:placetype":"neighbourhood"
},
  "geometry": {"coordinates":[-5.97248241540843,37.37081149716847],"type":"Point"}
}