{
  "type": "Feature",
  "properties": {
    "gn:country":"ES",
    "gn:fcode":"PPL",
    "gn:population":65,
    "iso:country":"ES",
    "name:ara_x_preferred":[
        "\u0641\u064a\u0644\u0627\u0645\u0628\u0627\u064a\u0633\u062a\u0627\u064a\u0627"
    ],
    "name:arg_x_preferred":[
        "Villambistia"
    ],
    "name:ast_x_preferred":[
        "Villambistia"
    ],
    "name:azb_x_preferred":[
        "\u0628\u06cc\u06cc\u0627\u0645\u0628\u06cc\u0633\u062a\u06cc\u0627"
    ],
    "name:bul_x_preferred":[
        "\u0412\u0438\u043b\u0430\u043c\u0431\u0438\u0441\u0442\u0438\u0430"
    ],
    "name:cat_x_preferred":[
        "Villambistia"
    ],
    "name:ceb_x_preferred":[
        "Villambistia"
    ],
    "name:deu_x_preferred":[
        "Villambistia"
    ],
    "name:eng_x_preferred":[
        "Villambistia"
    ],
    "name:eus_x_preferred":[
        "Villambistia"
    ],
    "name:fas_x_preferred":[
        "\u0628\u06cc\u06cc\u0627\u0645\u0628\u06cc\u0633\u062a\u06cc\u0627"
    ],
    "name:fra_x_preferred":[
        "Villambistia"
    ],
    "name:glg_x_preferred":[
        "Villambistia"
    ],
    "name:haw_x_preferred":[
        "Villambistia"
    ],
    "name:hun_x_preferred":[
        "Villambistia"
    ],
    "name:ina_x_preferred":[
        "Villambistia"
    ],
    "name:ita_x_preferred":[
        "Villambistia"
    ],
    "name:msa_x_preferred":[
        "Villambistia"
    ],
    "name:nan_x_preferred":[
        "Villambistia"
    ],
    "name:nld_x_preferred":[
        "Villambistia"
    ],
    "name:oci_x_preferred":[
        "Villambistia"
    ],
    "name:pol_x_preferred":[
        "Villambistia"
    ],
    "name:por_x_preferred":[
        "Villambistia"
    ],
    "name:rus_x_preferred":[
        "\u0412\u0438\u043b\u044c\u044f\u043c\u0431\u0438\u0441\u0442\u0438\u0430"
    ],
    "name:spa_x_preferred":[
        "Villambistia"
    ],
    "name:swe_x_preferred":[
        "Villambistia"
    ],
    "name:ukr_x_preferred":[
        "\u0412\u0456\u043b\u044c\u044f\u043c\u0431\u0456\u0441\u0442\u0456\u044f"
    ],
    "name:und_x_variant":[
        "Villamb\u00edstia"
    ],
    "name:vie_x_preferred":[
        "Villambistia"
    ],
    "name:war_x_preferred":[
        "Villambistia"
    ],
    "name:zho_x_preferred":[
        "\u6bd4\u826f\u7ef4\u65af\u8482\u4e9a"
    ],
    "qs_pg:aaroncc":"ES",
    "qs_pg:gn_country":"ES",
    "qs_pg:gn_fcode":"PPL",
    "qs_pg:gn_pop":65,
    "qs_pg:name":"Villambistia",
    "qs_pg:name_adm0":"Espa\u00f1a",
    "qs_pg:name_adm1":"Castilla y Le\u00f3n",
    "qs_pg:photos":40,
    "qs_pg:photos_1k":8,
    "qs_pg:photos_9k":1,
    "qs_pg:photos_9r":2,
    "qs_pg:photos_all":40,
    "qs_pg:photos_sr":2,
    "qs_pg:pop_sr":1,
    "qs_pg:qs_pg_placetype":"locality",
    "qs_pg:qs_pg_placetype_gp":"Town",
    "qs_pg:woe_adm0":23424950,
    "woe:adm0_id":23424950,
    "woe:name_adm0":"Espa\u00f1a",
    "woe:name_adm1":"Castilla y Le\u00f3n",
    "woe:placetype":"Town",
    "wof:name":"Villambistia",
    "wof:placetype":"locality",
    "wof:population":65
},
  "geometry": {"coordinates":[-3.26192,42.40543],"type":"Point"}
}