{
  "type": "Feature",
  "properties": {
    "gn:admin1_code":"58",
    "gn:admin2_code":"LU",
    "gn:admin3_code":"27041",
    "gn:asciiname":"Castillon",
    "gn:country_code":"ES",
    "gn:dem":557,
    "gn:feature_class":"P",
    "gn:feature_code":"PPL",
    "gn:name":"Castill\u00f3n",
    "gn:population":0,
    "gn:timezone":"Europe/Madrid",
    "iso:country":"ES",
    "name:und_x_variant":[
        "Santiago",
        "San Vicente",
        "Castill\u00f3n"
    ],
    "wof:name":"Castillon",
    "wof:placetype":"locality"
},
  "geometry": {"coordinates":[-7.63642,42.53306],"type":"Point"}
}