{
  "type": "Feature",
  "properties": {
    "iso:country":"ES",
    "name:eng_x_preferred":[
        "Las Virreinas"
    ],
    "name:spa_x_preferred":[
        "Las Virreinas"
    ],
    "wof:name":"Las Virreinas",
    "wof:placetype":"neighbourhood"
},
  "geometry": {"coordinates":[-4.42664820003863,36.74792291487737],"type":"Point"}
}