{
  "type": "Feature",
  "properties": {
    "iso:country":"ES",
    "name:cat_x_preferred":[
        "Jaume Roig"
    ],
    "name:eus_x_preferred":[
        "Jaume Roig"
    ],
    "name:fra_x_preferred":[
        "Jaume Roig"
    ],
    "name:ita_x_preferred":[
        "Jaume Roig"
    ],
    "name:spa_x_preferred":[
        "Jaume Roig"
    ],
    "wof:name":"Jaume Roig",
    "wof:placetype":"neighbourhood"
},
  "geometry": {"coordinates":[-0.36269308237417,39.48170706564763],"type":"Point"}
}