{
  "type": "Feature",
  "properties": {
    "gn:admin1_code":"39",
    "gn:admin2_code":"S",
    "gn:admin3_code":"33047",
    "gn:asciiname":"Siejo",
    "gn:country_code":"ES",
    "gn:dem":29,
    "gn:feature_class":"P",
    "gn:feature_code":"PPL",
    "gn:name":"Siejo",
    "gn:population":0,
    "gn:timezone":"Europe/Madrid",
    "iso:country":"ES",
    "name:ast_x_preferred":[
        "Sie\u1e25u"
    ],
    "name:deu_x_preferred":[
        "Siejo"
    ],
    "name:spa_x_preferred":[
        "Siejo"
    ],
    "wof:name":"Siejo",
    "wof:placetype":"locality"
},
  "geometry": {"coordinates":[-4.58593,43.32799],"type":"Point"}
}