{
  "type": "Feature",
  "properties": {
    "gn:gn_country":"ES",
    "gn:gn_fcode":"PPLA3",
    "gn:gn_pop":77,
    "gn:population":77,
    "iso:country":"ES",
    "name:cat_x_preferred":[
        "Revilla de Collazos"
    ],
    "name:deu_x_preferred":[
        "Revilla de Collazos"
    ],
    "name:eng_x_preferred":[
        "Revilla de Collazos"
    ],
    "name:eus_x_preferred":[
        "Revilla de Collazos"
    ],
    "name:fas_x_preferred":[
        "\u0631\u0628\u06cc\u06cc\u0627 \u062f \u06a9\u06cc\u0627\u0633\u0633"
    ],
    "name:fra_x_preferred":[
        "Revilla de Collazos"
    ],
    "name:glg_x_preferred":[
        "Revilla de Collazos"
    ],
    "name:hun_x_preferred":[
        "Revilla de Collazos"
    ],
    "name:ina_x_preferred":[
        "Revilla de Collazos"
    ],
    "name:ita_x_preferred":[
        "Revilla de Collazos"
    ],
    "name:msa_x_preferred":[
        "Revilla de Collazos"
    ],
    "name:nan_x_preferred":[
        "Revilla de Collazos"
    ],
    "name:nld_x_preferred":[
        "Revilla de Collazos"
    ],
    "name:oci_x_preferred":[
        "Revilla de Collazos"
    ],
    "name:pol_x_preferred":[
        "Revilla de Collazos"
    ],
    "name:por_x_preferred":[
        "Revilla de Collazos"
    ],
    "name:rus_x_preferred":[
        "\u0420\u0435\u0432\u0438\u043b\u044c\u044f-\u0434\u0435-\u041a\u043e\u043b\u044c\u044f\u0441\u043e\u0441"
    ],
    "name:spa_x_preferred":[
        "Revilla de Collazos"
    ],
    "name:swe_x_preferred":[
        "Revilla de Collazos"
    ],
    "name:ukr_x_preferred":[
        "\u0420\u0435\u0432\u0456\u043b\u044c\u044f-\u0434\u0435-\u041a\u043e\u043b\u044c\u044f\u0441\u043e\u0441"
    ],
    "name:uzb_x_preferred":[
        "Revilla de Collazos"
    ],
    "name:vie_x_preferred":[
        "Revilla de Collazos"
    ],
    "name:war_x_preferred":[
        "Revilla de Collazos"
    ],
    "name:zho_x_preferred":[
        "\u96f7\u7ef4\u5229\u4e9a\u5fb7\u79d1\u5229\u4e9a\u7d22\u65af"
    ],
    "qs_pg:aaroncc":"ES",
    "qs_pg:gn_country":"ES",
    "qs_pg:gn_fcode":"PPLA3",
    "qs_pg:gn_pop":77,
    "qs_pg:name":"Revilla de Collazos",
    "qs_pg:name_adm0":"Espa\u00f1a",
    "qs_pg:name_adm1":"Castilla y Le\u00f3n",
    "qs_pg:photos_9k":1,
    "qs_pg:photos_9r":1,
    "qs_pg:photos_all":2,
    "qs_pg:photos_sr":0,
    "qs_pg:pop_sr":1,
    "qs_pg:qs_pg_placetype":"locality",
    "qs_pg:qs_pg_placetype_gp":"Town",
    "qs_pg:woe_adm0":23424950,
    "woe:adm0_id":23424950,
    "woe:name_adm0":"Espa\u00f1a",
    "woe:name_adm1":"Castilla y Le\u00f3n",
    "woe:placetype":"Town",
    "wof:name":"Revilla de Collazos",
    "wof:placetype":"locality",
    "wof:population":77
},
  "geometry": {"coordinates":[-4.50343,42.6296],"type":"Point"}
}