{
  "type": "Feature",
  "properties": {
    "gn:admin1_code":"52",
    "gn:admin2_code":"HU",
    "gn:admin3_code":"22125",
    "gn:asciiname":"Tabernas de Isuela",
    "gn:country_code":"ES",
    "gn:dem":391,
    "gn:feature_class":"P",
    "gn:feature_code":"PPL",
    "gn:name":"Tabernas de Isuela",
    "gn:population":0,
    "gn:timezone":"Europe/Madrid",
    "iso:country":"ES",
    "wof:name":"Tabernas de Isuela",
    "wof:placetype":"locality"
},
  "geometry": {"coordinates":[-0.41117,42.0557],"type":"Point"}
}