{
  "type": "Feature",
  "properties": {
    "gn:country":"ES",
    "gn:fcode":"PPLA3",
    "gn:population":668,
    "iso:country":"ES",
    "name:arg_x_preferred":[
        "San Vitero"
    ],
    "name:ast_x_preferred":[
        "San Vitero"
    ],
    "name:cat_x_preferred":[
        "San Vitero"
    ],
    "name:ceb_x_preferred":[
        "San Vitero"
    ],
    "name:che_x_preferred":[
        "\u0421\u0430\u043d-\u0412\u0438\u0442\u0435\u0440\u043e"
    ],
    "name:eng_x_preferred":[
        "San Vitero"
    ],
    "name:epo_x_preferred":[
        "San Vitero"
    ],
    "name:eus_x_preferred":[
        "San Vitero"
    ],
    "name:fra_x_preferred":[
        "San Vitero"
    ],
    "name:gle_x_preferred":[
        "San Vitero"
    ],
    "name:haw_x_preferred":[
        "San Vitero"
    ],
    "name:hun_x_preferred":[
        "San Vitero"
    ],
    "name:hye_x_preferred":[
        "\u054d\u0561\u0576 \u054e\u056b\u057f\u0565\u0580\u0578"
    ],
    "name:ile_x_preferred":[
        "San Vitero"
    ],
    "name:ina_x_preferred":[
        "San Vitero"
    ],
    "name:ita_x_preferred":[
        "San Vitero"
    ],
    "name:lld_x_preferred":[
        "San Vitero"
    ],
    "name:ltz_x_preferred":[
        "San Vitero"
    ],
    "name:msa_x_preferred":[
        "San Vitero"
    ],
    "name:nan_x_preferred":[
        "San Vitero"
    ],
    "name:nld_x_preferred":[
        "San Vitero"
    ],
    "name:nob_x_preferred":[
        "San Vitero"
    ],
    "name:oci_x_preferred":[
        "San Vitero"
    ],
    "name:pol_x_preferred":[
        "San Vitero"
    ],
    "name:por_x_preferred":[
        "San Vitero"
    ],
    "name:rus_x_preferred":[
        "\u0421\u0430\u043d-\u0412\u0438\u0442\u0435\u0440\u043e"
    ],
    "name:spa_x_preferred":[
        "San Vitero"
    ],
    "name:swe_x_preferred":[
        "San Vitero"
    ],
    "name:tat_x_preferred":[
        "\u0421\u0430\u043d-\u0412\u0438\u0442\u0435\u0440\u043e"
    ],
    "name:ukr_x_preferred":[
        "\u0421\u0430\u043d-\u0412\u0456\u0442\u0435\u0440\u043e"
    ],
    "name:vec_x_preferred":[
        "San Vitero"
    ],
    "name:vie_x_preferred":[
        "San Vitero"
    ],
    "name:war_x_preferred":[
        "San Vitero"
    ],
    "name:zho_x_preferred":[
        "\u5723\u6bd4\u7279\u7f57"
    ],
    "qs_pg:aaroncc":"ES",
    "qs_pg:gn_country":"ES",
    "qs_pg:gn_fcode":"PPLA3",
    "qs_pg:gn_pop":668,
    "qs_pg:name":"San Vitero",
    "qs_pg:name_adm0":"Espa\u00f1a",
    "qs_pg:name_adm1":"Castilla y Le\u00f3n",
    "qs_pg:photos":19,
    "qs_pg:photos_1k":4,
    "qs_pg:photos_9k":1,
    "qs_pg:photos_9r":1,
    "qs_pg:photos_all":19,
    "qs_pg:photos_sr":1,
    "qs_pg:pop_sr":2,
    "qs_pg:qs_pg_placetype":"locality",
    "qs_pg:qs_pg_placetype_gp":"Town",
    "qs_pg:woe_adm0":23424950,
    "woe:adm0_id":23424950,
    "woe:name_adm0":"Espa\u00f1a",
    "woe:name_adm1":"Castilla y Le\u00f3n",
    "woe:placetype":"Town",
    "wof:name":"San Vitero",
    "wof:placetype":"locality",
    "wof:population":668
},
  "geometry": {"coordinates":[-6.34877,41.7774],"type":"Point"}
}