{
  "type": "Feature",
  "properties": {
    "gn:admin1_code":"55",
    "gn:admin2_code":"BU",
    "gn:admin3_code":"09466",
    "gn:asciiname":"Revenga",
    "gn:country_code":"ES",
    "gn:dem":837,
    "gn:feature_class":"P",
    "gn:feature_code":"PPL",
    "gn:name":"Revenga",
    "gn:population":0,
    "gn:timezone":"Europe/Madrid",
    "iso:country":"ES",
    "wof:name":"Revenga",
    "wof:placetype":"locality"
},
  "geometry": {"coordinates":[-3.86357,42.15827],"type":"Point"}
}