{
  "type": "Feature",
  "properties": {
    "gn:country":"ES",
    "gn:fcode":"PPLA3",
    "gn:population":46,
    "iso:country":"ES",
    "name:arg_x_preferred":[
        "Jal\u00f3n de Cameros"
    ],
    "name:cat_x_preferred":[
        "Jal\u00f3n de Cameros"
    ],
    "name:eng_x_preferred":[
        "Jal\u00f3n de Cameros"
    ],
    "name:eus_x_preferred":[
        "Jal\u00f3n de Cameros"
    ],
    "name:fra_x_preferred":[
        "Jal\u00f3n de Cameros"
    ],
    "name:hun_x_preferred":[
        "Jal\u00f3n de Cameros"
    ],
    "name:hye_x_preferred":[
        "\u053d\u0561\u056c\u0578\u0576 \u0564\u0565 \u053f\u0561\u0574\u0565\u0580\u0578\u057d"
    ],
    "name:ita_x_preferred":[
        "Jal\u00f3n de Cameros"
    ],
    "name:kaz_x_preferred":[
        "\u0425\u0430\u043b\u043e\u043d-\u0434\u0435-\u041a\u0430\u043c\u0435\u0440\u043e\u0441"
    ],
    "name:msa_x_preferred":[
        "Jal\u00f3n de Cameros"
    ],
    "name:nan_x_preferred":[
        "Jal\u00f3n de Cameros"
    ],
    "name:nld_x_preferred":[
        "Jal\u00f3n de Cameros"
    ],
    "name:oci_x_preferred":[
        "Jal\u00f3n de Cameros"
    ],
    "name:pol_x_preferred":[
        "Jal\u00f3n de Cameros"
    ],
    "name:por_x_preferred":[
        "Jal\u00f3n de Cameros"
    ],
    "name:rup_x_preferred":[
        "Jal\u00f3n de Cameros"
    ],
    "name:rus_x_preferred":[
        "\u0425\u0430\u043b\u043e\u043d-\u0434\u0435-\u041a\u0430\u043c\u0435\u0440\u043e\u0441"
    ],
    "name:spa_x_preferred":[
        "Jal\u00f3n de Cameros"
    ],
    "name:swe_x_preferred":[
        "Jal\u00f3n de Cameros"
    ],
    "name:ukr_x_preferred":[
        "\u0425\u0430\u043b\u043e\u043d-\u0434\u0435-\u041a\u0430\u043c\u0435\u0440\u043e\u0441"
    ],
    "name:uzb_x_preferred":[
        "Jal\u00f3n de Cameros"
    ],
    "name:vie_x_preferred":[
        "Jal\u00f3n de Cameros"
    ],
    "name:war_x_preferred":[
        "Jal\u00f3n de Cameros"
    ],
    "name:zho_x_preferred":[
        "\u54c8\u9686\u5fb7\u5361\u6885\u7f57\u65af"
    ],
    "qs_pg:aaroncc":"ES",
    "qs_pg:gn_country":"ES",
    "qs_pg:gn_fcode":"PPLA3",
    "qs_pg:gn_pop":46,
    "qs_pg:name":"Jal\u00f3n de Cameros",
    "qs_pg:name_adm0":"Espa\u00f1a",
    "qs_pg:name_adm1":"La Rioja",
    "qs_pg:photos_9k":1,
    "qs_pg:photos_9r":1,
    "qs_pg:photos_all":1,
    "qs_pg:photos_sr":0,
    "qs_pg:pop_sr":1,
    "qs_pg:qs_pg_placetype":"locality",
    "qs_pg:qs_pg_placetype_gp":"Town",
    "qs_pg:woe_adm0":23424950,
    "woe:adm0_id":23424950,
    "woe:name_adm0":"Espa\u00f1a",
    "woe:name_adm1":"La Rioja",
    "woe:placetype":"Town",
    "wof:name":"Jal\u00f3n de Cameros",
    "wof:placetype":"locality",
    "wof:population":46
},
  "geometry": {"coordinates":[-2.49004,42.21804],"type":"Point"}
}