{
  "type": "Feature",
  "properties": {
    "gn:admin1_code":"55",
    "gn:admin2_code":"LE",
    "gn:admin3_code":"24055",
    "gn:asciiname":"Velilla de la Reina",
    "gn:country_code":"ES",
    "gn:dem":893,
    "gn:feature_class":"P",
    "gn:feature_code":"PPL",
    "gn:name":"Velilla de la Reina",
    "gn:population":0,
    "gn:timezone":"Europe/Madrid",
    "iso:country":"ES",
    "wof:name":"Velilla de la Reina",
    "wof:placetype":"locality"
},
  "geometry": {"coordinates":[-5.79461,42.5505],"type":"Point"}
}