{
  "type": "Feature",
  "properties": {
    "gn:admin1_code":"54",
    "gn:admin2_code":"CR",
    "gn:admin3_code":"13010",
    "gn:asciiname":"Pozo de la Serna",
    "gn:country_code":"ES",
    "gn:dem":769,
    "gn:feature_class":"P",
    "gn:feature_code":"PPL",
    "gn:name":"Pozo de la Serna",
    "gn:population":0,
    "gn:timezone":"Europe/Madrid",
    "iso:country":"ES",
    "wof:name":"Pozo de la Serna",
    "wof:placetype":"locality"
},
  "geometry": {"coordinates":[-3.23266,38.77655],"type":"Point"}
}