{
  "type": "Feature",
  "properties": {
    "gn:admin1_code":"57",
    "gn:admin2_code":"CC",
    "gn:admin3_code":"10167",
    "gn:asciiname":"El Bronco",
    "gn:country_code":"ES",
    "gn:dem":423,
    "gn:feature_class":"P",
    "gn:feature_code":"PPL",
    "gn:name":"El Bronco",
    "gn:population":0,
    "gn:timezone":"Europe/Madrid",
    "iso:country":"ES",
    "wof:name":"El Bronco",
    "wof:placetype":"locality"
},
  "geometry": {"coordinates":[-6.31572,40.21957],"type":"Point"}
}