{
  "type": "Feature",
  "properties": {
    "iso:country":"ES",
    "name:spa_x_preferred":[
        "Poligono San Blas",
        "Plaza de Andaluc\u00eda"
    ],
    "name:spa_x_variant":[
        "Poligono S Blas",
        "Poligono S. Blas"
    ],
    "qs:gn_adm0_cc":"ES",
    "qs:gn_local":2521978,
    "qs:gn_nam_loc":"Alicante, Alicante, Alicante, Comunitat Valenciana, ES",
    "qs:gn_namadm1":"60",
    "qs:local_max":6358,
    "qs:local_sum":21789,
    "qs:localhoods":20,
    "qs:name":"Poligono San Blas",
    "qs:name_adm0":"Espa\u00f1a",
    "qs:name_adm1":"Comunitat Valenciana",
    "qs:name_adm2":"Alicante",
    "qs:name_lau":"Alicante",
    "qs:name_local":"Alicante",
    "qs:photo_max":60,
    "qs:photo_sum":558,
    "qs:placetype":"Suburb",
    "qs:quad_count":33,
    "qs:woe_adm0":23424950,
    "qs:woe_adm1":12578038,
    "qs:woe_adm2":12602137,
    "qs:woe_lau":12695279,
    "qs:woe_local":752101,
    "qs:woe_ver":"7.10.0",
    "wof:lang":[
        "spa"
    ],
    "wof:name":"Poligono San Blas",
    "wof:placetype":"neighbourhood"
},
  "geometry": {"coordinates":[-0.498538,38.353434],"type":"Point"}
}