{
  "type": "Feature",
  "properties": {
    "gn:admin1_code":"58",
    "gn:admin2_code":"OR",
    "gn:admin3_code":"32001",
    "gn:asciiname":"Pazo",
    "gn:cc2":"ES",
    "gn:country_code":"ES",
    "gn:dem":677,
    "gn:feature_class":"P",
    "gn:feature_code":"PPL",
    "gn:name":"Paz\u00f3",
    "gn:population":0,
    "gn:timezone":"Europe/Madrid",
    "iso:country":"ES",
    "name:cat_x_preferred":[
        "Pazo"
    ],
    "name:eus_x_preferred":[
        "Pazo"
    ],
    "name:fra_x_preferred":[
        "Pazo"
    ],
    "name:glg_x_preferred":[
        "Pazo"
    ],
    "name:por_x_preferred":[
        "Pazo"
    ],
    "name:spa_x_preferred":[
        "Pazo"
    ],
    "name:und_x_variant":[
        "San Mart\u00edn",
        "Paz\u00f3"
    ],
    "wof:name":"Pazo",
    "wof:placetype":"locality"
},
  "geometry": {"coordinates":[-7.83333,42.16667],"type":"Point"}
}