{
  "type": "Feature",
  "properties": {
    "gn:country":"ES",
    "gn:fcode":"PPLA3",
    "gn:population":113,
    "iso:country":"ES",
    "name:arg_x_preferred":[
        "Torralba d'Arag\u00f3n"
    ],
    "name:cat_x_preferred":[
        "Torralba de Arag\u00f3n"
    ],
    "name:deu_x_preferred":[
        "Torralba de Arag\u00f3n"
    ],
    "name:eng_x_preferred":[
        "Torralba de Arag\u00f3n"
    ],
    "name:eus_x_preferred":[
        "Torralba de Arag\u00f3n"
    ],
    "name:fra_x_preferred":[
        "Torralba de Arag\u00f3n"
    ],
    "name:hak_x_preferred":[
        "Torralba de Arag\u00f3n"
    ],
    "name:hun_x_preferred":[
        "Torralba de Arag\u00f3n"
    ],
    "name:ita_x_preferred":[
        "Torralba de Arag\u00f3n"
    ],
    "name:msa_x_preferred":[
        "Torralba de Arag\u00f3n"
    ],
    "name:nan_x_preferred":[
        "Torralba de Arag\u00f3n"
    ],
    "name:nld_x_preferred":[
        "Torralba de Arag\u00f3n"
    ],
    "name:oci_x_preferred":[
        "Torralba de Arag\u00f3n"
    ],
    "name:pol_x_preferred":[
        "Torralba de Arag\u00f3n"
    ],
    "name:por_x_preferred":[
        "Torralba de Arag\u00f3n"
    ],
    "name:rus_x_preferred":[
        "\u0422\u043e\u0440\u0440\u0430\u043b\u044c\u0431\u0430-\u0434\u0435-\u0410\u0440\u0430\u0433\u043e\u043d"
    ],
    "name:spa_x_preferred":[
        "Torralba de Arag\u00f3n"
    ],
    "name:swe_x_preferred":[
        "Torralba de Arag\u00f3n"
    ],
    "name:ukr_x_preferred":[
        "\u0422\u043e\u0440\u0440\u0430\u043b\u044c\u0431\u0430-\u0434\u0435-\u0410\u0440\u0430\u0433\u043e\u043d"
    ],
    "name:uzb_x_preferred":[
        "Torralba de Arag\u00f3n"
    ],
    "name:vie_x_preferred":[
        "Torralba de Arag\u00f3n"
    ],
    "name:war_x_preferred":[
        "Torralba de Arag\u00f3n"
    ],
    "name:zho_x_preferred":[
        "\u6258\u62c9\u5c14\u74e6\u5fb7\u4e9a\u62c9\u8d21"
    ],
    "qs_pg:aaroncc":"ES",
    "qs_pg:gn_country":"ES",
    "qs_pg:gn_fcode":"PPLA3",
    "qs_pg:gn_pop":113,
    "qs_pg:name":"Torralba de Arag\u00f3n",
    "qs_pg:name_adm0":"Espa\u00f1a",
    "qs_pg:name_adm1":"Arag\u00f3n",
    "qs_pg:photos_9r":0,
    "qs_pg:photos_sr":0,
    "qs_pg:pop_sr":1,
    "qs_pg:qs_pg_placetype":"locality",
    "qs_pg:qs_pg_placetype_gp":"Town",
    "qs_pg:woe_adm0":23424950,
    "woe:adm0_id":23424950,
    "woe:name_adm0":"Espa\u00f1a",
    "woe:name_adm1":"Arag\u00f3n",
    "woe:placetype":"Town",
    "wof:name":"Torralba de Arag\u00f3n",
    "wof:placetype":"locality",
    "wof:population":113
},
  "geometry": {"coordinates":[-0.51053,41.93487],"type":"Point"}
}