{
  "type": "Feature",
  "properties": {
    "gn:admin1_code":"57",
    "gn:admin2_code":"CC",
    "gn:admin3_code":"10026",
    "gn:asciiname":"Casas de Belvis",
    "gn:country_code":"ES",
    "gn:dem":415,
    "gn:feature_class":"P",
    "gn:feature_code":"PPL",
    "gn:name":"Casas de Belvis",
    "gn:population":0,
    "gn:timezone":"Europe/Madrid",
    "iso:country":"ES",
    "wof:name":"Casas de Belvis",
    "wof:placetype":"locality"
},
  "geometry": {"coordinates":[-5.59007,39.82541],"type":"Point"}
}