{
  "type": "Feature",
  "properties": {
    "gn:gn_country":"ES",
    "gn:gn_fcode":"PPLA3",
    "gn:gn_pop":0,
    "gn:population":155,
    "iso:country":"ES",
    "name:ara_x_preferred":[
        "\u062b\u064a\u0648\u0631\u0627\u0646\u0627"
    ],
    "name:arg_x_preferred":[
        "Siurana"
    ],
    "name:ast_x_preferred":[
        "Siurana"
    ],
    "name:bul_x_preferred":[
        "\u0421\u0438\u0443\u0440\u0430\u043d\u0430"
    ],
    "name:cat_x_preferred":[
        "Siurana"
    ],
    "name:ceb_x_preferred":[
        "Siurana"
    ],
    "name:deu_x_preferred":[
        "Siurana"
    ],
    "name:eng_x_preferred":[
        "Siurana"
    ],
    "name:eus_x_preferred":[
        "Siurana"
    ],
    "name:fra_x_preferred":[
        "Siurana"
    ],
    "name:hun_x_preferred":[
        "Siurana"
    ],
    "name:hye_x_preferred":[
        "\u054d\u0575\u0578\u0582\u0580\u0561\u0576\u0561"
    ],
    "name:ita_x_preferred":[
        "Siurana"
    ],
    "name:kaz_x_preferred":[
        "\u0421\u0438\u0443\u0440\u0430\u043d\u0430"
    ],
    "name:lat_x_preferred":[
        "Siurana"
    ],
    "name:msa_x_preferred":[
        "Siurana"
    ],
    "name:nld_x_preferred":[
        "Siurana"
    ],
    "name:oci_x_preferred":[
        "Siurana"
    ],
    "name:pol_x_preferred":[
        "Siurana"
    ],
    "name:por_x_preferred":[
        "Siurana"
    ],
    "name:ron_x_preferred":[
        "Siurana"
    ],
    "name:rus_x_preferred":[
        "\u0421\u0438\u0443\u0440\u0430\u043d\u0430"
    ],
    "name:spa_x_preferred":[
        "Ciurana"
    ],
    "name:sqi_x_preferred":[
        "Siurana"
    ],
    "name:swe_x_preferred":[
        "Siurana"
    ],
    "name:tah_x_preferred":[
        "Siurana"
    ],
    "name:ukr_x_preferred":[
        "\u0421\u0456\u0443\u0440\u0430\u043d\u0430"
    ],
    "name:uzb_x_preferred":[
        "Ciurana"
    ],
    "name:vie_x_preferred":[
        "Siurana"
    ],
    "name:war_x_preferred":[
        "Siurana"
    ],
    "name:zho_x_preferred":[
        "\u4f11\u62c9\u7eb3"
    ],
    "qs_pg:aaroncc":"ES",
    "qs_pg:gn_country":"ES",
    "qs_pg:gn_fcode":"PPLA3",
    "qs_pg:gn_pop":0,
    "qs_pg:name":"Siurana",
    "qs_pg:name_adm0":"Espa\u00f1a",
    "qs_pg:name_adm1":"Catalunya",
    "qs_pg:photos":131,
    "qs_pg:photos_1k":27,
    "qs_pg:photos_9k":1,
    "qs_pg:photos_9r":3,
    "qs_pg:photos_all":131,
    "qs_pg:photos_sr":3,
    "qs_pg:pop_sr":0,
    "qs_pg:qs_pg_placetype":"locality",
    "qs_pg:qs_pg_placetype_gp":"Town",
    "qs_pg:woe_adm0":23424950,
    "woe:adm0_id":23424950,
    "woe:name_adm0":"Espa\u00f1a",
    "woe:name_adm1":"Catalunya",
    "woe:placetype":"Town",
    "wof:name":"Siurana",
    "wof:placetype":"locality",
    "wof:population":155
},
  "geometry": {"coordinates":[2.99392,42.20916],"type":"Point"}
}