{
  "type": "Feature",
  "properties": {
    "gn:admin1_code":"57",
    "gn:admin2_code":"CC",
    "gn:admin3_code":"10904.0",
    "gn:asciiname":"Tietar",
    "gn:country_code":"ES",
    "gn:dem":275,
    "gn:feature_class":"P",
    "gn:feature_code":"PPLA3",
    "gn:name":"Ti\u00e9tar",
    "gn:population":0,
    "gn:timezone":"Europe/Madrid",
    "iso:country":"ES",
    "wof:name":"Tietar",
    "wof:placetype":"locality"
},
  "geometry": {"coordinates":[-5.48192,40.02945],"type":"Point"}
}