{
  "type": "Feature",
  "properties": {
    "gn:admin1_code":"55",
    "gn:admin2_code":"SO",
    "gn:admin3_code":"42181",
    "gn:asciiname":"Cascajosa",
    "gn:country_code":"ES",
    "gn:dem":994,
    "gn:feature_class":"P",
    "gn:feature_code":"PPL",
    "gn:name":"Cascajosa",
    "gn:population":0,
    "gn:timezone":"Europe/Madrid",
    "iso:country":"ES",
    "wof:name":"Cascajosa",
    "wof:placetype":"locality"
},
  "geometry": {"coordinates":[-2.6798,41.58534],"type":"Point"}
}