{
  "type": "Feature",
  "properties": {
    "gn:gn_country":"ES",
    "gn:gn_fcode":"PPLA3",
    "gn:gn_pop":113,
    "gn:population":113,
    "iso:country":"ES",
    "name:ara_x_preferred":[
        "\u0628\u0627\u062e\u0627\u0631\u0648\u0646"
    ],
    "name:arg_x_preferred":[
        "Pajar\u00f3n"
    ],
    "name:baq_x_preferred":[
        "Pajar\u00f3n"
    ],
    "name:cat_x_preferred":[
        "Pajar\u00f3n"
    ],
    "name:chi_x_preferred":[
        "\u5e15\u54c8\u9f99"
    ],
    "name:dut_x_preferred":[
        "Pajar\u00f3n"
    ],
    "name:eng_x_preferred":[
        "Pajar\u00f3n"
    ],
    "name:fre_x_preferred":[
        "Pajar\u00f3n"
    ],
    "name:hun_x_preferred":[
        "Pajar\u00f3n"
    ],
    "name:ita_x_preferred":[
        "Pajar\u00f3n"
    ],
    "name:kaz_x_preferred":[
        "\u041f\u0430\u0445\u0430\u0440\u043e\u043d"
    ],
    "name:may_x_preferred":[
        "Pajar\u00f3n"
    ],
    "name:nan_x_preferred":[
        "Pajar\u00f3n"
    ],
    "name:oci_x_preferred":[
        "Pajar\u00f3n"
    ],
    "name:pol_x_preferred":[
        "Pajar\u00f3n"
    ],
    "name:por_x_preferred":[
        "Pajar\u00f3n"
    ],
    "name:rus_x_preferred":[
        "\u041f\u0430\u0445\u0430\u0440\u043e\u043d"
    ],
    "name:sco_x_preferred":[
        "Pajar\u00f3n"
    ],
    "name:spa_x_preferred":[
        "Pajar\u00f3n"
    ],
    "name:swe_x_preferred":[
        "Pajar\u00f3n"
    ],
    "name:ukr_x_preferred":[
        "\u041f\u0430\u0445\u0430\u0440\u043e\u043d"
    ],
    "name:vie_x_preferred":[
        "Pajar\u00f3n"
    ],
    "name:war_x_preferred":[
        "Pajar\u00f3n"
    ],
    "qs_pg:aaroncc":"ES",
    "qs_pg:gn_country":"ES",
    "qs_pg:gn_fcode":"PPLA3",
    "qs_pg:gn_pop":113,
    "qs_pg:name":"Pajar\u00f3n",
    "qs_pg:name_adm0":"Espa\u00f1a",
    "qs_pg:name_adm1":"Castilla-La Mancha",
    "qs_pg:photos_9r":0,
    "qs_pg:photos_sr":0,
    "qs_pg:pop_sr":1,
    "qs_pg:qs_pg_placetype":"locality",
    "qs_pg:qs_pg_placetype_gp":"Town",
    "qs_pg:woe_adm0":23424950,
    "woe:adm0_id":23424950,
    "woe:name_adm0":"Espa\u00f1a",
    "woe:name_adm1":"Castilla-La Mancha",
    "woe:placetype":"Town",
    "wof:name":"Pajar\u00f3n",
    "wof:placetype":"locality",
    "wof:population":113
},
  "geometry": {"coordinates":[-1.78333,39.95],"type":"Point"}
}