{
  "type": "Feature",
  "properties": {
    "gn:admin1_code":"56",
    "gn:admin2_code":"GI",
    "gn:admin3_code":"17198",
    "gn:asciiname":"Vilacolum",
    "gn:country_code":"ES",
    "gn:dem":9,
    "gn:feature_class":"P",
    "gn:feature_code":"PPL",
    "gn:name":"Vilacolum",
    "gn:population":0,
    "gn:timezone":"Europe/Madrid",
    "iso:country":"ES",
    "name:cat_x_preferred":[
        "Vilacolum"
    ],
    "name:pol_x_preferred":[
        "Vilacolum"
    ],
    "name:spa_x_preferred":[
        "Vilacolum"
    ],
    "name:tah_x_preferred":[
        "Vilacolum"
    ],
    "wof:name":"Vilacolum",
    "wof:placetype":"locality"
},
  "geometry": {"coordinates":[3.03738,42.19427],"type":"Point"}
}