{
  "type": "Feature",
  "properties": {
    "gn:admin1_code":"39",
    "gn:admin2_code":"S",
    "gn:admin3_code":"39094",
    "gn:asciiname":"Otero",
    "gn:country_code":"ES",
    "gn:dem":937,
    "gn:feature_class":"P",
    "gn:feature_code":"PPL",
    "gn:name":"Otero",
    "gn:population":0,
    "gn:timezone":"Europe/Madrid",
    "iso:country":"ES",
    "wof:name":"Otero",
    "wof:placetype":"locality"
},
  "geometry": {"coordinates":[-4.03046,42.82781],"type":"Point"}
}