{
  "type": "Feature",
  "properties": {
    "gn:gn_country":"ES",
    "gn:gn_fcode":"PPLA3",
    "gn:gn_pop":144,
    "gn:population":144,
    "iso:country":"ES",
    "name:arg_x_preferred":[
        "Villamayor de Mont Chard\u00edn"
    ],
    "name:baq_x_preferred":[
        "Villamayor de Monjard\u00edn"
    ],
    "name:bre_x_preferred":[
        "Villamayor de Monjardin"
    ],
    "name:cat_x_preferred":[
        "Villamayor de Monjard\u00edn"
    ],
    "name:chi_x_preferred":[
        "\u8499\u54c8\u5c14\u4e01\u5927\u9547"
    ],
    "name:dut_x_preferred":[
        "Villamayor de Monjard\u00edn"
    ],
    "name:eng_x_preferred":[
        "Villamayor de Monjard\u00edn"
    ],
    "name:fre_x_preferred":[
        "Villamayor de Monjardin"
    ],
    "name:ger_x_preferred":[
        "Villamayor de Monjard\u00edn"
    ],
    "name:hun_x_preferred":[
        "Villamayor de Monjard\u00edn"
    ],
    "name:ita_x_preferred":[
        "Villamayor de Monjard\u00edn"
    ],
    "name:jpn_x_preferred":[
        "\u30d3\u30ea\u30e3\u30de\u30b8\u30e7\u30fc\u30eb\u30fb\u30c7\u30fb\u30e2\u30f3\u30cf\u30eb\u30c7\u30a3\u30f3"
    ],
    "name:may_x_preferred":[
        "Villamayor de Monjard\u00edn"
    ],
    "name:nan_x_preferred":[
        "Villamayor de Monjard\u00edn"
    ],
    "name:oci_x_preferred":[
        "Villamayor de Monjard\u00edn"
    ],
    "name:pol_x_preferred":[
        "Villamayor de Monjard\u00edn"
    ],
    "name:por_x_preferred":[
        "Villamayor de Monjard\u00edn"
    ],
    "name:rus_x_preferred":[
        "\u0412\u0438\u043b\u044c\u044f\u043c\u0430\u0439\u043e\u0440-\u0434\u0435-\u041c\u043e\u043d\u0445\u0430\u0440\u0434\u0438\u043d"
    ],
    "name:sco_x_preferred":[
        "Villamayor de Monjard\u00edn"
    ],
    "name:spa_x_preferred":[
        "Villamayor de Monjard\u00edn"
    ],
    "name:swe_x_preferred":[
        "Villamayor de Monjard\u00edn"
    ],
    "name:ukr_x_preferred":[
        "\u0412\u0456\u043b\u044c\u044f\u043c\u0430\u0439\u043e\u0440-\u0434\u0435-\u041c\u043e\u043d\u0445\u0430\u0440\u0434\u0456\u043d"
    ],
    "name:uzb_x_preferred":[
        "Villamayor de Monjard\u00edn"
    ],
    "name:vie_x_preferred":[
        "Villamayor de Monjard\u00edn"
    ],
    "name:war_x_preferred":[
        "Villamayor de Monjard\u00edn"
    ],
    "qs_pg:aaroncc":"ES",
    "qs_pg:gn_country":"ES",
    "qs_pg:gn_fcode":"PPLA3",
    "qs_pg:gn_pop":144,
    "qs_pg:name":"Villamayor de Monjard\u00edn",
    "qs_pg:name_adm0":"Espa\u00f1a",
    "qs_pg:name_adm1":"Comunidad Foral de Navarra",
    "qs_pg:photos":329,
    "qs_pg:photos_1k":67,
    "qs_pg:photos_9k":1,
    "qs_pg:photos_9r":5,
    "qs_pg:photos_all":329,
    "qs_pg:photos_sr":5,
    "qs_pg:pop_sr":1,
    "qs_pg:qs_pg_placetype":"locality",
    "qs_pg:qs_pg_placetype_gp":"Town",
    "qs_pg:woe_adm0":23424950,
    "woe:adm0_id":23424950,
    "woe:name_adm0":"Espa\u00f1a",
    "woe:name_adm1":"Comunidad Foral de Navarra",
    "woe:placetype":"Town",
    "wof:name":"Villamayor de Monjard\u00edn",
    "wof:placetype":"locality",
    "wof:population":144
},
  "geometry": {"coordinates":[-2.10503,42.62937],"type":"Point"}
}