{
  "type": "Feature",
  "properties": {
    "gn:gn_country":"ES",
    "gn:gn_fcode":"PPLA3",
    "gn:gn_pop":108,
    "gn:population":108,
    "iso:country":"ES",
    "name:arg_x_preferred":[
        "Tronch\u00f3n"
    ],
    "name:cat_x_preferred":[
        "Tronx\u00f3"
    ],
    "name:eng_x_preferred":[
        "Tronch\u00f3n"
    ],
    "name:eus_x_preferred":[
        "Tronch\u00f3n"
    ],
    "name:fra_x_preferred":[
        "Tronch\u00f3n"
    ],
    "name:hun_x_preferred":[
        "Tronch\u00f3n"
    ],
    "name:ita_x_preferred":[
        "Tronch\u00f3n"
    ],
    "name:msa_x_preferred":[
        "Tronch\u00f3n"
    ],
    "name:nan_x_preferred":[
        "Tronch\u00f3n"
    ],
    "name:nld_x_preferred":[
        "Tronch\u00f3n"
    ],
    "name:oci_x_preferred":[
        "Tronch\u00f3n"
    ],
    "name:pol_x_preferred":[
        "Tronch\u00f3n"
    ],
    "name:por_x_preferred":[
        "Tronch\u00f3n"
    ],
    "name:rus_x_preferred":[
        "\u0422\u0440\u043e\u043d\u0447\u043e\u043d"
    ],
    "name:spa_x_preferred":[
        "Tronch\u00f3n"
    ],
    "name:sqi_x_preferred":[
        "Tronch\u00f3n"
    ],
    "name:swe_x_preferred":[
        "Tronch\u00f3n"
    ],
    "name:ukr_x_preferred":[
        "\u0422\u0440\u043e\u043d\u0447\u043e\u043d"
    ],
    "name:uzb_x_preferred":[
        "Tronch\u00f3n"
    ],
    "name:vie_x_preferred":[
        "Tronch\u00f3n"
    ],
    "name:war_x_preferred":[
        "Tronch\u00f3n"
    ],
    "name:zho_x_preferred":[
        "\u7279\u9f99\u743c"
    ],
    "qs_pg:aaroncc":"ES",
    "qs_pg:gn_country":"ES",
    "qs_pg:gn_fcode":"PPLA3",
    "qs_pg:gn_pop":108,
    "qs_pg:name":"Tronch\u00f3n",
    "qs_pg:name_adm0":"Espa\u00f1a",
    "qs_pg:name_adm1":"Arag\u00f3n",
    "qs_pg:photos":162,
    "qs_pg:photos_1k":33,
    "qs_pg:photos_9k":1,
    "qs_pg:photos_9r":4,
    "qs_pg:photos_all":162,
    "qs_pg:photos_sr":4,
    "qs_pg:pop_sr":1,
    "qs_pg:qs_pg_placetype":"locality",
    "qs_pg:qs_pg_placetype_gp":"Town",
    "qs_pg:woe_adm0":23424950,
    "woe:adm0_id":23424950,
    "woe:name_adm0":"Espa\u00f1a",
    "woe:name_adm1":"Arag\u00f3n",
    "woe:placetype":"Town",
    "wof:name":"Tronch\u00f3n",
    "wof:placetype":"locality",
    "wof:population":108
},
  "geometry": {"coordinates":[-0.39833,40.62092],"type":"Point"}
}