{
  "type": "Feature",
  "properties": {
    "gn:country":"ES",
    "gn:fcode":"PPLA3",
    "gn:population":162,
    "iso:country":"ES",
    "name:arg_x_preferred":[
        "Villares de Yeltes"
    ],
    "name:cat_x_preferred":[
        "Villares de Yeltes"
    ],
    "name:che_x_preferred":[
        "\u0412\u0438\u043b\u044c\u044f\u0440\u0435\u0441-\u0434\u0435-\u0415\u043b\u044c\u0442\u0435\u0441"
    ],
    "name:deu_x_preferred":[
        "Villares de Yeltes"
    ],
    "name:eng_x_preferred":[
        "Villares de Yeltes"
    ],
    "name:eus_x_preferred":[
        "Villares de Yeltes"
    ],
    "name:fra_x_preferred":[
        "Villares de Yeltes"
    ],
    "name:hun_x_preferred":[
        "Villares de Yeltes"
    ],
    "name:ina_x_preferred":[
        "Villares de Yeltes"
    ],
    "name:ita_x_preferred":[
        "Villares de Yeltes"
    ],
    "name:kaz_x_preferred":[
        "\u0412\u0438\u043b\u044c\u044f\u0440\u0435\u0441-\u0434\u0435-\u0415\u043b\u044c\u0442\u0435\u0441"
    ],
    "name:msa_x_preferred":[
        "Villares de Yeltes"
    ],
    "name:nan_x_preferred":[
        "Villares de Yeltes"
    ],
    "name:nld_x_preferred":[
        "Villares de Yeltes"
    ],
    "name:oci_x_preferred":[
        "Villares de Yeltes"
    ],
    "name:pol_x_preferred":[
        "Villares de Yeltes"
    ],
    "name:por_x_preferred":[
        "Villares de Yeltes"
    ],
    "name:rus_x_preferred":[
        "\u0412\u0438\u043b\u044c\u044f\u0440\u0435\u0441-\u0434\u0435-\u0415\u043b\u044c\u0442\u0435\u0441"
    ],
    "name:spa_x_preferred":[
        "Villares de Yeltes"
    ],
    "name:swe_x_preferred":[
        "Villares de Yeltes"
    ],
    "name:tat_x_preferred":[
        "\u0412\u0438\u043b\u044c\u044f\u0440\u0435\u0441-\u0434\u0435-\u0415\u043b\u044c\u0442\u0435\u0441"
    ],
    "name:ukr_x_preferred":[
        "\u0412\u0456\u043b\u044c\u044f\u0440\u0435\u0441-\u0434\u0435-\u0404\u043b\u044c\u0442\u0435\u0441"
    ],
    "name:uzb_x_preferred":[
        "Villares de Yeltes"
    ],
    "name:vie_x_preferred":[
        "Villares de Yeltes"
    ],
    "name:war_x_preferred":[
        "Villares de Yeltes"
    ],
    "name:zho_x_preferred":[
        "\u6bd4\u5229\u4e9a\u96f7\u65af\u5fb7\u57c3\u5c14\u7279\u65af"
    ],
    "qs_pg:aaroncc":"ES",
    "qs_pg:gn_country":"ES",
    "qs_pg:gn_fcode":"PPLA3",
    "qs_pg:gn_pop":162,
    "qs_pg:name":"Villares de Yeltes",
    "qs_pg:name_adm0":"Espa\u00f1a",
    "qs_pg:name_adm1":"Castilla y Le\u00f3n",
    "qs_pg:photos_9r":0,
    "qs_pg:photos_sr":0,
    "qs_pg:pop_sr":1,
    "qs_pg:qs_pg_placetype":"locality",
    "qs_pg:qs_pg_placetype_gp":"Town",
    "qs_pg:woe_adm0":23424950,
    "woe:adm0_id":23424950,
    "woe:name_adm0":"Espa\u00f1a",
    "woe:name_adm1":"Castilla y Le\u00f3n",
    "woe:placetype":"Town",
    "wof:name":"Villares de Yeltes",
    "wof:placetype":"locality",
    "wof:population":162
},
  "geometry": {"coordinates":[-6.413,40.86594],"type":"Point"}
}