{
  "type": "Feature",
  "properties": {
    "gn:admin1_code":"58",
    "gn:admin2_code":"C",
    "gn:admin3_code":"15068",
    "gn:asciiname":"Pazos de Abajo",
    "gn:country_code":"ES",
    "gn:dem":113,
    "gn:feature_class":"P",
    "gn:feature_code":"PPL",
    "gn:name":"Pazos de Abajo",
    "gn:population":0,
    "gn:timezone":"Europe/Madrid",
    "iso:country":"ES",
    "wof:name":"Pazos de Abajo",
    "wof:placetype":"locality"
},
  "geometry": {"coordinates":[-8.82401,43.26041],"type":"Point"}
}