{
  "type": "Feature",
  "properties": {
    "gn:admin1_code":"58",
    "gn:admin2_code":"LU",
    "gn:admin3_code":"27060",
    "gn:asciiname":"Bembibre",
    "gn:cc2":"ES",
    "gn:country_code":"ES",
    "gn:dem":554,
    "gn:feature_class":"P",
    "gn:feature_code":"PPL",
    "gn:name":"Bembibre",
    "gn:population":0,
    "gn:timezone":"Europe/Madrid",
    "iso:country":"ES",
    "name:arg_x_preferred":[
        "Bembibre"
    ],
    "name:ast_x_preferred":[
        "Bembibre"
    ],
    "name:cat_x_preferred":[
        "Bembibre"
    ],
    "name:ceb_x_preferred":[
        "Bembibre"
    ],
    "name:epo_x_preferred":[
        "Bembibro"
    ],
    "name:eus_x_preferred":[
        "Bembibre"
    ],
    "name:fra_x_preferred":[
        "Bembibre"
    ],
    "name:glg_x_preferred":[
        "Bembibre"
    ],
    "name:haw_x_preferred":[
        "Bembibre"
    ],
    "name:hun_x_preferred":[
        "Bembibre"
    ],
    "name:ido_x_preferred":[
        "Bembibre"
    ],
    "name:ina_x_preferred":[
        "Bembibre"
    ],
    "name:ita_x_preferred":[
        "Bembibre"
    ],
    "name:jpn_x_preferred":[
        "\u30d9\u30f3\u30d3\u30d6\u30ec"
    ],
    "name:msa_x_preferred":[
        "Bembibre"
    ],
    "name:nld_x_preferred":[
        "Bembibre"
    ],
    "name:oci_x_preferred":[
        "Bembibre"
    ],
    "name:pol_x_preferred":[
        "Bembibre"
    ],
    "name:por_x_preferred":[
        "Bembibre"
    ],
    "name:rus_x_preferred":[
        "\u0411\u0435\u043c\u0431\u0438\u0431\u0440\u0435"
    ],
    "name:spa_x_preferred":[
        "Bembibre"
    ],
    "name:swe_x_preferred":[
        "Bembibre"
    ],
    "name:tpi_x_preferred":[
        "Bembibre"
    ],
    "name:ukr_x_preferred":[
        "\u0411\u0435\u043c\u0431\u0456\u0431\u0440\u0435"
    ],
    "name:und_x_variant":[
        "San Pedro"
    ],
    "name:vie_x_preferred":[
        "Bembibre"
    ],
    "name:war_x_preferred":[
        "Bembibre"
    ],
    "name:zho_x_preferred":[
        "\u672c\u7ef4\u592b\u96f7"
    ],
    "wof:name":"Bembibre",
    "wof:placetype":"locality"
},
  "geometry": {"coordinates":[-7.75978,42.72343],"type":"Point"}
}