{
  "type": "Feature",
  "properties": {
    "gn:gn_country":"ES",
    "gn:gn_fcode":"PPL",
    "gn:gn_pop":264,
    "gn:population":264,
    "iso:country":"ES",
    "name:ara_x_preferred":[
        "\u0623\u0648\u063a\u0627\u0633\u0627"
    ],
    "name:arg_x_preferred":[
        "Ogassa"
    ],
    "name:cat_x_preferred":[
        "Ogassa"
    ],
    "name:deu_x_preferred":[
        "Ogassa"
    ],
    "name:eng_x_preferred":[
        "Ogassa"
    ],
    "name:eus_x_preferred":[
        "Ogassa"
    ],
    "name:fra_x_preferred":[
        "Ogassa"
    ],
    "name:hun_x_preferred":[
        "Ogassa"
    ],
    "name:hye_x_preferred":[
        "\u0555\u0563\u0561\u057d\u0561"
    ],
    "name:ita_x_preferred":[
        "Ogassa"
    ],
    "name:kaz_x_preferred":[
        "\u041e\u0433\u0430\u0441\u0441\u0430"
    ],
    "name:lat_x_preferred":[
        "Ogassa"
    ],
    "name:nld_x_preferred":[
        "Ogassa"
    ],
    "name:oci_x_preferred":[
        "Ogassa"
    ],
    "name:pol_x_preferred":[
        "Ogassa"
    ],
    "name:por_x_preferred":[
        "Ogassa"
    ],
    "name:ron_x_preferred":[
        "Ogassa"
    ],
    "name:rus_x_preferred":[
        "\u041e\u0433\u0430\u0441\u0441\u0430"
    ],
    "name:spa_x_preferred":[
        "Ogassa"
    ],
    "name:sqi_x_preferred":[
        "Ogassa"
    ],
    "name:swe_x_preferred":[
        "Ogassa"
    ],
    "name:uzb_x_preferred":[
        "Ogassa"
    ],
    "name:war_x_preferred":[
        "Ogassa"
    ],
    "name:zho_x_preferred":[
        "\u5965\u52a0\u8428"
    ],
    "qs_pg:aaroncc":"ES",
    "qs_pg:gn_country":"ES",
    "qs_pg:gn_fcode":"PPL",
    "qs_pg:gn_pop":264,
    "qs_pg:name":"Ogassa",
    "qs_pg:name_adm0":"Espa\u00f1a",
    "qs_pg:name_adm1":"Catalunya",
    "qs_pg:photos":171,
    "qs_pg:photos_1k":35,
    "qs_pg:photos_9k":1,
    "qs_pg:photos_9r":4,
    "qs_pg:photos_all":171,
    "qs_pg:photos_sr":4,
    "qs_pg:pop_sr":2,
    "qs_pg:qs_pg_placetype":"locality",
    "qs_pg:qs_pg_placetype_gp":"Town",
    "qs_pg:woe_adm0":23424950,
    "woe:adm0_id":23424950,
    "woe:name_adm0":"Espa\u00f1a",
    "woe:name_adm1":"Catalunya",
    "woe:placetype":"Town",
    "wof:name":"Ogassa",
    "wof:placetype":"locality",
    "wof:population":264
},
  "geometry": {"coordinates":[2.23148,42.27159],"type":"Point"}
}