{
  "type": "Feature",
  "properties": {
    "gn:admin1_code":"39",
    "gn:admin2_code":"S",
    "gn:admin3_code":"39022",
    "gn:asciiname":"Salarzon",
    "gn:country_code":"ES",
    "gn:dem":706,
    "gn:feature_class":"P",
    "gn:feature_code":"PPL",
    "gn:name":"Salarz\u00f3n",
    "gn:population":0,
    "gn:timezone":"Europe/Madrid",
    "iso:country":"ES",
    "name:und_x_variant":[
        "Salarz\u00f3n"
    ],
    "wof:name":"Salarzon",
    "wof:placetype":"locality"
},
  "geometry": {"coordinates":[-4.5716,43.18804],"type":"Point"}
}