{
  "type": "Feature",
  "properties": {
    "gn:gn_country":"ES",
    "gn:gn_fcode":"PPLA3",
    "gn:gn_pop":3481,
    "gn:population":3481,
    "iso:country":"ES",
    "name:arg_x_preferred":[
        "Carracedelo"
    ],
    "name:cat_x_preferred":[
        "Carracedelo"
    ],
    "name:ceb_x_preferred":[
        "Carracedelo"
    ],
    "name:deu_x_preferred":[
        "Carracedelo"
    ],
    "name:eng_x_preferred":[
        "Carracedelo"
    ],
    "name:eus_x_preferred":[
        "Carracedelo"
    ],
    "name:fra_x_preferred":[
        "Carracedelo"
    ],
    "name:glg_x_preferred":[
        "Carracedelo"
    ],
    "name:haw_x_preferred":[
        "Carracedelo"
    ],
    "name:hun_x_preferred":[
        "Carracedelo"
    ],
    "name:ido_x_preferred":[
        "Carracedelo"
    ],
    "name:ina_x_preferred":[
        "Carracedelo"
    ],
    "name:ita_x_preferred":[
        "Carracedelo"
    ],
    "name:jpn_x_preferred":[
        "\u30ab\u30e9\u30bb\u30c7\u30fc\u30ed"
    ],
    "name:lit_x_preferred":[
        "Karasedelas"
    ],
    "name:msa_x_preferred":[
        "Carracedelo"
    ],
    "name:nld_x_preferred":[
        "Carracedelo"
    ],
    "name:oci_x_preferred":[
        "Carracedelo"
    ],
    "name:pol_x_preferred":[
        "Carracedelo"
    ],
    "name:por_x_preferred":[
        "Carracedelo"
    ],
    "name:rup_x_preferred":[
        "Carracedelo"
    ],
    "name:rus_x_preferred":[
        "\u041a\u0430\u0440\u0440\u0430\u0441\u0435\u0434\u0435\u043b\u043e"
    ],
    "name:spa_x_preferred":[
        "Carracedelo"
    ],
    "name:swe_x_preferred":[
        "Carracedelo"
    ],
    "name:tpi_x_preferred":[
        "Carracedelo"
    ],
    "name:ukr_x_preferred":[
        "\u041a\u0430\u0440\u0440\u0430\u0441\u0435\u0434\u0435\u043b\u043e"
    ],
    "name:vie_x_preferred":[
        "Carracedelo"
    ],
    "name:war_x_preferred":[
        "Carracedelo"
    ],
    "name:zho_x_preferred":[
        "\u5361\u62c9\u585e\u5fb7\u6d1b"
    ],
    "qs_pg:aaroncc":"ES",
    "qs_pg:gn_country":"ES",
    "qs_pg:gn_fcode":"PPLA3",
    "qs_pg:gn_pop":3481,
    "qs_pg:name":"Carracedelo",
    "qs_pg:name_adm0":"Espa\u00f1a",
    "qs_pg:name_adm1":"Castilla y Le\u00f3n",
    "qs_pg:photos":39,
    "qs_pg:photos_1k":8,
    "qs_pg:photos_9k":1,
    "qs_pg:photos_9r":2,
    "qs_pg:photos_all":39,
    "qs_pg:photos_sr":2,
    "qs_pg:pop_sr":4,
    "qs_pg:qs_pg_placetype":"locality",
    "qs_pg:qs_pg_placetype_gp":"Town",
    "qs_pg:woe_adm0":23424950,
    "woe:adm0_id":23424950,
    "woe:name_adm0":"Espa\u00f1a",
    "woe:name_adm1":"Castilla y Le\u00f3n",
    "woe:placetype":"Town",
    "wof:name":"Carracedelo",
    "wof:placetype":"locality",
    "wof:population":3481
},
  "geometry": {"coordinates":[-6.73317,42.55602],"type":"Point"}
}