{
  "type": "Feature",
  "properties": {
    "gn:admin1_code":"59",
    "gn:admin2_code":"VI",
    "gn:admin3_code":"01902",
    "gn:asciiname":"Comunion",
    "gn:country_code":"ES",
    "gn:dem":481,
    "gn:feature_class":"P",
    "gn:feature_code":"PPL",
    "gn:name":"Komunioi / Comuni\u00f3n",
    "gn:population":0,
    "gn:timezone":"Europe/Madrid",
    "iso:country":"ES",
    "name:eus_x_preferred":[
        "Komunioi"
    ],
    "name:spa_x_preferred":[
        "Comuni\u00f3n"
    ],
    "name:spa_x_variant":[
        "Comunion"
    ],
    "wof:name":"Comunion",
    "wof:placetype":"locality"
},
  "geometry": {"coordinates":[-2.96667,42.71667],"type":"Point"}
}