{
  "type": "Feature",
  "properties": {
    "gn:admin1_code":"58",
    "gn:admin2_code":"PO",
    "gn:admin3_code":"36025",
    "gn:asciiname":"Escuadra",
    "gn:cc2":"ES",
    "gn:country_code":"ES",
    "gn:dem":684,
    "gn:feature_class":"P",
    "gn:feature_code":"PPL",
    "gn:name":"Escuadra",
    "gn:population":0,
    "gn:timezone":"Europe/Madrid",
    "iso:country":"ES",
    "name:und_x_variant":[
        "San Lorenzo",
        "Escuadra"
    ],
    "wof:name":"Escuadra",
    "wof:placetype":"locality"
},
  "geometry": {"coordinates":[-8.41667,42.43333],"type":"Point"}
}