{
  "type": "Feature",
  "properties": {
    "gn:admin1_code":"31",
    "gn:admin2_code":"MU",
    "gn:admin3_code":"30030",
    "gn:asciiname":"El Caracolero",
    "gn:country_code":"ES",
    "gn:dem":232,
    "gn:feature_class":"P",
    "gn:feature_code":"PPL",
    "gn:name":"El Caracolero",
    "gn:population":0,
    "gn:timezone":"Europe/Madrid",
    "iso:country":"ES",
    "name:und_x_variant":[
        "Caser\u00edo El Caracolero",
        "Casa el Caracolero",
        "El Caracolero"
    ],
    "wof:name":"El Caracolero",
    "wof:placetype":"locality"
},
  "geometry": {"coordinates":[-1.05215,37.88842],"type":"Point"}
}