{
  "type": "Feature",
  "properties": {
    "gn:gn_country":"ES",
    "gn:gn_fcode":"PPLA3",
    "gn:gn_pop":33443,
    "gn:population":33443,
    "iso:country":"ES",
    "name:ara_x_preferred":[
        "\u0623\u0648\u0644\u064a\u0631\u0648\u0633"
    ],
    "name:baq_x_preferred":[
        "Oleiros"
    ],
    "name:bel_x_preferred":[
        "\u0410\u043b\u0435\u0439\u0440\u0430\u0441"
    ],
    "name:bre_x_preferred":[
        "Oleiros"
    ],
    "name:cat_x_preferred":[
        "Oleiros"
    ],
    "name:chi_x_preferred":[
        "\u5965\u83b1\u7f57\u65af"
    ],
    "name:dut_x_preferred":[
        "Oleiros"
    ],
    "name:eng_x_preferred":[
        "Oleiros"
    ],
    "name:fas_x_preferred":[
        "\u0627\u0648\u0644\u06cc\u0631\u0648\u0633"
    ],
    "name:fre_x_preferred":[
        "Oleiros"
    ],
    "name:ger_x_preferred":[
        "Oleiros"
    ],
    "name:glg_x_preferred":[
        "Oleiros"
    ],
    "name:hun_x_preferred":[
        "Oleiros"
    ],
    "name:ita_x_preferred":[
        "Oleiros"
    ],
    "name:jpn_x_preferred":[
        "\u30aa\u30ec\u30a4\u30ed\u30b9"
    ],
    "name:lit_x_preferred":[
        "Oleirosas"
    ],
    "name:mac_x_preferred":[
        "\u041e\u043b\u0435\u0438\u0440\u043e\u0441"
    ],
    "name:may_x_preferred":[
        "Oleiros"
    ],
    "name:mkd_x_preferred":[
        "\u041e\u043b\u0435\u0438\u0440\u043e\u0441"
    ],
    "name:nan_x_preferred":[
        "Oleiros"
    ],
    "name:oci_x_preferred":[
        "Oleiros"
    ],
    "name:per_x_preferred":[
        "\u0627\u0648\u0644\u06cc\u0631\u0648\u0633"
    ],
    "name:pnb_x_preferred":[
        "\u0627\u0648\u0644\u0626\u06cc\u0631\u0648\u0633"
    ],
    "name:pol_x_preferred":[
        "Oleiros"
    ],
    "name:por_x_preferred":[
        "Oleiros"
    ],
    "name:rus_x_preferred":[
        "\u041e\u043b\u0435\u0439\u0440\u043e\u0441"
    ],
    "name:spa_x_preferred":[
        "Oleiros"
    ],
    "name:swe_x_preferred":[
        "Oleiros"
    ],
    "name:tur_x_preferred":[
        "Oleiros"
    ],
    "name:ukr_x_preferred":[
        "\u041e\u043b\u0435\u0439\u0440\u043e\u0441"
    ],
    "name:unk_x_variant":[
        "Santa Mar\u00eda"
    ],
    "name:uzb_x_preferred":[
        "Oleiros"
    ],
    "name:vie_x_preferred":[
        "Oleiros"
    ],
    "name:war_x_preferred":[
        "Oleiros"
    ],
    "name:zho_x_preferred":[
        "\u5965\u83b1\u7f57\u65af"
    ],
    "qs_pg:aaroncc":"ES",
    "qs_pg:gn_country":"ES",
    "qs_pg:gn_fcode":"PPLA3",
    "qs_pg:gn_pop":33443,
    "qs_pg:name":"Oleiros",
    "qs_pg:name_adm0":"Espa\u00f1a",
    "qs_pg:name_adm1":"Galicia",
    "qs_pg:photos":466,
    "qs_pg:photos_1k":94,
    "qs_pg:photos_9k":2,
    "qs_pg:photos_9r":5,
    "qs_pg:photos_all":466,
    "qs_pg:photos_sr":7,
    "qs_pg:pop_sr":7,
    "qs_pg:qs_pg_placetype":"locality",
    "qs_pg:qs_pg_placetype_gp":"Town",
    "qs_pg:woe_adm0":23424950,
    "woe:adm0_id":23424950,
    "woe:name_adm0":"Espa\u00f1a",
    "woe:name_adm1":"Galicia",
    "woe:placetype":"Town",
    "wof:name":"Oleiros",
    "wof:placetype":"locality",
    "wof:population":33443
},
  "geometry": {"coordinates":[-8.31667,43.33333],"type":"Point"}
}