{
  "type": "Feature",
  "properties": {
    "gn:gn_country":"ES",
    "gn:gn_fcode":"PPLA3",
    "gn:gn_pop":585,
    "gn:population":585,
    "iso:country":"ES",
    "name:ara_x_preferred":[
        "\u0623\u0644\u0627\u062a\u0648\u062b"
    ],
    "name:arg_x_preferred":[
        "Alatoz"
    ],
    "name:baq_x_preferred":[
        "Alatoz"
    ],
    "name:cat_x_preferred":[
        "Alatoz"
    ],
    "name:dut_x_preferred":[
        "Alatoz"
    ],
    "name:eng_x_preferred":[
        "Alatoz"
    ],
    "name:fre_x_preferred":[
        "Alatoz"
    ],
    "name:hun_x_preferred":[
        "Alatoz"
    ],
    "name:ina_x_preferred":[
        "Alatoz"
    ],
    "name:ind_x_preferred":[
        "Alatoz"
    ],
    "name:ita_x_preferred":[
        "Alatoz"
    ],
    "name:may_x_preferred":[
        "Alatoz"
    ],
    "name:nan_x_preferred":[
        "Alatoz"
    ],
    "name:oci_x_preferred":[
        "Alatoz"
    ],
    "name:pam_x_preferred":[
        "Alatoz"
    ],
    "name:per_x_preferred":[
        "\u0622\u0644\u0627\u062a\u0633"
    ],
    "name:pol_x_preferred":[
        "Alatoz"
    ],
    "name:por_x_preferred":[
        "Alatoz"
    ],
    "name:rum_x_preferred":[
        "Alatoz"
    ],
    "name:rus_x_preferred":[
        "\u0410\u043b\u0430\u0442\u043e\u0441"
    ],
    "name:spa_x_preferred":[
        "Alatoz"
    ],
    "name:swe_x_preferred":[
        "Alatoz"
    ],
    "name:ukr_x_preferred":[
        "\u0410\u043b\u0430\u0442\u043e\u0441"
    ],
    "name:vie_x_preferred":[
        "Alatoz"
    ],
    "name:war_x_preferred":[
        "Alatoz"
    ],
    "qs_pg:aaroncc":"ES",
    "qs_pg:gn_country":"ES",
    "qs_pg:gn_fcode":"PPLA3",
    "qs_pg:gn_pop":585,
    "qs_pg:name":"Alatoz",
    "qs_pg:photos_9r":0,
    "qs_pg:photos_sr":0,
    "qs_pg:pop_sr":2,
    "qs_pg:qs_pg_placetype":"locality",
    "wof:name":"Alatoz",
    "wof:placetype":"locality",
    "wof:population":585
},
  "geometry": {"coordinates":[-1.36098,39.09495],"type":"Point"}
}