{
  "type": "Feature",
  "properties": {
    "gn:gn_country":"ES",
    "gn:gn_fcode":"PPLA3",
    "gn:gn_pop":474,
    "gn:population":474,
    "iso:country":"ES",
    "name:arg_x_preferred":[
        "Cirauqui"
    ],
    "name:ast_x_preferred":[
        "Cirauqui"
    ],
    "name:bre_x_preferred":[
        "Zirauki"
    ],
    "name:cat_x_preferred":[
        "Zirauki"
    ],
    "name:ceb_x_preferred":[
        "Cirauqui"
    ],
    "name:ces_x_preferred":[
        "Cirauqui"
    ],
    "name:deu_x_preferred":[
        "Cirauqui"
    ],
    "name:eng_x_preferred":[
        "Cirauqui"
    ],
    "name:eus_x_preferred":[
        "Zirauki"
    ],
    "name:fra_x_preferred":[
        "Cirauqui"
    ],
    "name:hun_x_preferred":[
        "Cirauqui"
    ],
    "name:ita_x_preferred":[
        "Cirauqui"
    ],
    "name:jpn_x_preferred":[
        "\u30b7\u30e9\u30a6\u30ad"
    ],
    "name:msa_x_preferred":[
        "Cirauqui"
    ],
    "name:nan_x_preferred":[
        "Cirauqui"
    ],
    "name:nld_x_preferred":[
        "Cirauqui"
    ],
    "name:oci_x_preferred":[
        "Zirauki"
    ],
    "name:pol_x_preferred":[
        "Cirauqui"
    ],
    "name:por_x_preferred":[
        "Cirauqui"
    ],
    "name:rup_x_preferred":[
        "Cirauqui"
    ],
    "name:rus_x_preferred":[
        "\u0421\u0438\u0440\u0430\u0443\u043a\u0438"
    ],
    "name:sco_x_preferred":[
        "Cirauqui"
    ],
    "name:spa_x_preferred":[
        "Cirauqui"
    ],
    "name:swe_x_preferred":[
        "Cirauqui"
    ],
    "name:ukr_x_preferred":[
        "\u0421\u0456\u0440\u0430\u0443\u043a\u0456"
    ],
    "name:uzb_x_preferred":[
        "Cirauqui"
    ],
    "name:vie_x_preferred":[
        "Cirauqui"
    ],
    "name:war_x_preferred":[
        "Cirauqui"
    ],
    "name:zho_x_preferred":[
        "\u897f\u52b3\u57fa"
    ],
    "qs_pg:aaroncc":"ES",
    "qs_pg:gn_country":"ES",
    "qs_pg:gn_fcode":"PPLA3",
    "qs_pg:gn_pop":474,
    "qs_pg:name":"Cirauqui",
    "qs_pg:name_adm0":"Espa\u00f1a",
    "qs_pg:name_adm1":"Comunidad Foral de Navarra",
    "qs_pg:photos":213,
    "qs_pg:photos_1k":43,
    "qs_pg:photos_9k":1,
    "qs_pg:photos_9r":4,
    "qs_pg:photos_all":213,
    "qs_pg:photos_sr":4,
    "qs_pg:pop_sr":2,
    "qs_pg:qs_pg_placetype":"locality",
    "qs_pg:qs_pg_placetype_gp":"Town",
    "qs_pg:woe_adm0":23424950,
    "woe:adm0_id":23424950,
    "woe:name_adm0":"Espa\u00f1a",
    "woe:name_adm1":"Comunidad Foral de Navarra",
    "woe:placetype":"Town",
    "wof:name":"Cirauqui",
    "wof:placetype":"locality",
    "wof:population":474
},
  "geometry": {"coordinates":[-1.89115,42.67596],"type":"Point"}
}