{
  "type": "Feature",
  "properties": {
    "gn:admin1_code":"58",
    "gn:admin2_code":"OR",
    "gn:admin3_code":"32015",
    "gn:asciiname":"Villaseco",
    "gn:country_code":"ES",
    "gn:dem":876,
    "gn:feature_class":"P",
    "gn:feature_code":"PPL",
    "gn:name":"Villaseco",
    "gn:population":0,
    "gn:timezone":"Europe/Madrid",
    "iso:country":"ES",
    "wof:name":"Villaseco",
    "wof:placetype":"locality"
},
  "geometry": {"coordinates":[-7.11645,42.28388],"type":"Point"}
}