{
  "type": "Feature",
  "properties": {
    "gn:admin1_code":"34",
    "gn:admin2_code":"O",
    "gn:admin3_code":"33025",
    "gn:asciiname":"Ovies",
    "gn:country_code":"ES",
    "gn:dem":83,
    "gn:feature_class":"P",
    "gn:feature_code":"PPL",
    "gn:name":"Ovies",
    "gn:population":0,
    "gn:timezone":"Europe/Madrid",
    "iso:country":"ES",
    "wof:name":"Ovies",
    "wof:placetype":"locality"
},
  "geometry": {"coordinates":[-5.85013,43.62443],"type":"Point"}
}