{
  "type": "Feature",
  "properties": {
    "gn:admin1_code":"39",
    "gn:admin2_code":"S",
    "gn:admin3_code":"39092",
    "gn:asciiname":"Santa Olalla",
    "gn:country_code":"ES",
    "gn:dem":959,
    "gn:feature_class":"P",
    "gn:feature_code":"PPL",
    "gn:name":"Santa Olalla",
    "gn:population":0,
    "gn:timezone":"Europe/Madrid",
    "iso:country":"ES",
    "wof:name":"Santa Olalla",
    "wof:placetype":"locality"
},
  "geometry": {"coordinates":[-4.20167,42.93263],"type":"Point"}
}