{
  "type": "Feature",
  "properties": {
    "gn:gn_country":"ES",
    "gn:gn_fcode":"PPLA3",
    "gn:gn_pop":103,
    "gn:population":103,
    "iso:country":"ES",
    "name:ara_x_preferred":[
        "\u0623\u0644\u0628\u064a\u0631\u064a\u062a\u064a \u062f\u064a \u0633\u0627\u0646 \u062e\u0648\u0627\u0646"
    ],
    "name:arg_x_preferred":[
        "Alberit de Sant Chuan"
    ],
    "name:cat_x_preferred":[
        "Alberite de San Juan"
    ],
    "name:eng_x_preferred":[
        "Alberite de San Juan"
    ],
    "name:eus_x_preferred":[
        "Alberite de San Juan"
    ],
    "name:fas_x_preferred":[
        "\u0627\u0644\u0628\u0631\u06cc\u062a \u062f\u0648 \u0633\u0627\u0646 \u062c\u0648\u0627\u0646"
    ],
    "name:fra_x_preferred":[
        "Alberite de San Juan"
    ],
    "name:hun_x_preferred":[
        "Alberite de San Juan"
    ],
    "name:ita_x_preferred":[
        "Alberite de San Juan"
    ],
    "name:kaz_x_preferred":[
        "\u0410\u043b\u044c\u0431\u0435\u0440\u0438\u0442\u0435-\u0434\u0435-\u0421\u0430\u043d-\u0425\u0443\u0430\u043d"
    ],
    "name:msa_x_preferred":[
        "Alberite de San Juan"
    ],
    "name:nan_x_preferred":[
        "Alberite de San Juan"
    ],
    "name:nld_x_preferred":[
        "Alberite de San Juan"
    ],
    "name:oci_x_preferred":[
        "Alberite de San Juan"
    ],
    "name:pol_x_preferred":[
        "Alberite de San Juan"
    ],
    "name:por_x_preferred":[
        "Alberite de San Juan"
    ],
    "name:rus_x_preferred":[
        "\u0410\u043b\u044c\u0431\u0435\u0440\u0438\u0442\u0435-\u0434\u0435-\u0421\u0430\u043d-\u0425\u0443\u0430\u043d"
    ],
    "name:spa_x_preferred":[
        "Alberite de San Juan"
    ],
    "name:swe_x_preferred":[
        "Alberite de San Juan"
    ],
    "name:ukr_x_preferred":[
        "\u0410\u043b\u044c\u0431\u0435\u0440\u0456\u0442\u0435-\u0434\u0435-\u0421\u0430\u043d-\u0425\u0443\u0430\u043d"
    ],
    "name:uzb_x_preferred":[
        "Alberite de San Juan"
    ],
    "name:vie_x_preferred":[
        "Alberite de San Juan"
    ],
    "name:war_x_preferred":[
        "Alberite de San Juan"
    ],
    "name:zho_x_preferred":[
        "\u963f\u5c14\u97e6\u91cc\u7279\u5fb7\u5723\u80e1\u5b89"
    ],
    "qs_pg:aaroncc":"ES",
    "qs_pg:gn_country":"ES",
    "qs_pg:gn_fcode":"PPLA3",
    "qs_pg:gn_pop":103,
    "qs_pg:name":"Alberite de San Juan",
    "qs_pg:name_adm0":"Espa\u00f1a",
    "qs_pg:name_adm1":"Arag\u00f3n",
    "qs_pg:photos_9r":0,
    "qs_pg:photos_sr":0,
    "qs_pg:pop_sr":1,
    "qs_pg:qs_pg_placetype":"locality",
    "qs_pg:qs_pg_placetype_gp":"Town",
    "qs_pg:woe_adm0":23424950,
    "woe:adm0_id":23424950,
    "woe:name_adm0":"Espa\u00f1a",
    "woe:name_adm1":"Arag\u00f3n",
    "woe:placetype":"Town",
    "wof:name":"Alberite de San Juan",
    "wof:placetype":"locality",
    "wof:population":103
},
  "geometry": {"coordinates":[-1.47063,41.82009],"type":"Point"}
}