{
  "type": "Feature",
  "properties": {
    "gn:admin1_code":"55",
    "gn:admin2_code":"LE",
    "gn:admin3_code":"24061",
    "gn:asciiname":"Cascantes",
    "gn:country_code":"ES",
    "gn:dem":928,
    "gn:feature_class":"P",
    "gn:feature_code":"PPL",
    "gn:name":"Cascantes",
    "gn:population":0,
    "gn:timezone":"Europe/Madrid",
    "iso:country":"ES",
    "wof:name":"Cascantes",
    "wof:placetype":"locality"
},
  "geometry": {"coordinates":[-5.63717,42.76549],"type":"Point"}
}