{
  "type": "Feature",
  "properties": {
    "gn:admin1_code":"39",
    "gn:admin2_code":"S",
    "gn:admin3_code":"39033",
    "gn:asciiname":"Camijanes",
    "gn:country_code":"ES",
    "gn:dem":109,
    "gn:feature_class":"P",
    "gn:feature_code":"PPL",
    "gn:name":"Camijanes",
    "gn:population":0,
    "gn:timezone":"Europe/Madrid",
    "iso:country":"ES",
    "wof:name":"Camijanes",
    "wof:placetype":"locality"
},
  "geometry": {"coordinates":[-4.48355,43.3282],"type":"Point"}
}