{
  "type": "Feature",
  "properties": {
    "gn:gn_country":"ES",
    "gn:gn_fcode":"PPLA3",
    "gn:gn_pop":827,
    "gn:population":827,
    "iso:country":"ES",
    "name:ara_x_preferred":[
        "\u0632\u0648\u0647\u064a\u0631\u0648\u0633\u060c \u0642\u0631\u0637\u0628\u0629"
    ],
    "name:arg_x_preferred":[
        "Zuheros"
    ],
    "name:cat_x_preferred":[
        "Zuheros"
    ],
    "name:chi_x_preferred":[
        "\u82cf\u57c3\u7f57\u65af"
    ],
    "name:dut_x_preferred":[
        "Zuheros"
    ],
    "name:eng_x_preferred":[
        "Zuheros"
    ],
    "name:epo_x_preferred":[
        "Zuheros"
    ],
    "name:fre_x_preferred":[
        "Zuheros"
    ],
    "name:ger_x_preferred":[
        "Zuheros"
    ],
    "name:glg_x_preferred":[
        "Zuheros"
    ],
    "name:hun_x_preferred":[
        "Zuheros"
    ],
    "name:ina_x_preferred":[
        "Zuheros"
    ],
    "name:ita_x_preferred":[
        "Zuheros"
    ],
    "name:may_x_preferred":[
        "Zuheros"
    ],
    "name:nan_x_preferred":[
        "Zuheros"
    ],
    "name:oci_x_preferred":[
        "Zuheros"
    ],
    "name:pol_x_preferred":[
        "Zuheros"
    ],
    "name:por_x_preferred":[
        "Zuheros"
    ],
    "name:rum_x_preferred":[
        "Zuheros"
    ],
    "name:rus_x_preferred":[
        "\u0421\u0443\u0435\u0440\u043e\u0441"
    ],
    "name:spa_x_preferred":[
        "Zuheros"
    ],
    "name:swe_x_preferred":[
        "Zuheros"
    ],
    "name:tur_x_preferred":[
        "Zuheros"
    ],
    "name:ukr_x_preferred":[
        "\u0421\u0443\u0435\u0440\u043e\u0441"
    ],
    "name:unk_x_variant":[
        "Zuh\u00e9res"
    ],
    "name:uzb_x_preferred":[
        "Zuheros"
    ],
    "name:vie_x_preferred":[
        "Zuheros"
    ],
    "name:war_x_preferred":[
        "Zuheros"
    ],
    "qs_pg:aaroncc":"ES",
    "qs_pg:gn_country":"ES",
    "qs_pg:gn_fcode":"PPLA3",
    "qs_pg:gn_pop":827,
    "qs_pg:name":"Zuheros",
    "qs_pg:name_adm0":"Espa\u00f1a",
    "qs_pg:name_adm1":"Andaluc\u00eda",
    "qs_pg:photos":504,
    "qs_pg:photos_1k":102,
    "qs_pg:photos_9k":2,
    "qs_pg:photos_9r":5,
    "qs_pg:photos_all":504,
    "qs_pg:photos_sr":7,
    "qs_pg:pop_sr":2,
    "qs_pg:qs_pg_placetype":"locality",
    "qs_pg:qs_pg_placetype_gp":"Town",
    "qs_pg:woe_adm0":23424950,
    "woe:adm0_id":23424950,
    "woe:name_adm0":"Espa\u00f1a",
    "woe:name_adm1":"Andaluc\u00eda",
    "woe:placetype":"Town",
    "wof:name":"Zuheros",
    "wof:placetype":"locality",
    "wof:population":827
},
  "geometry": {"coordinates":[-4.31531,37.54332],"type":"Point"}
}