{
  "type": "Feature",
  "properties": {
    "gn:admin1_code":"55",
    "gn:admin2_code":"P",
    "gn:admin3_code":"34228",
    "gn:asciiname":"Arenillas de Nuno Perez",
    "gn:country_code":"ES",
    "gn:dem":864,
    "gn:feature_class":"P",
    "gn:feature_code":"PPL",
    "gn:name":"Arenillas de Nu\u00f1o P\u00e9rez",
    "gn:population":0,
    "gn:timezone":"Europe/Madrid",
    "iso:country":"ES",
    "name:und_x_variant":[
        "Arenillas de Perez Nu\u00f1o",
        "Arenillas de Nu\u00f1o P\u00e9rez"
    ],
    "wof:name":"Arenillas de Nuno Perez",
    "wof:placetype":"locality"
},
  "geometry": {"coordinates":[-4.53199,42.51651],"type":"Point"}
}