{
  "type": "Feature",
  "properties": {
    "gn:admin1_code":"51",
    "gn:admin2_code":"AL",
    "gn:admin3_code":"04066",
    "gn:asciiname":"El Cortijo de los Olivos",
    "gn:country_code":"ES",
    "gn:dem":130,
    "gn:feature_class":"P",
    "gn:feature_code":"PPL",
    "gn:name":"El Cortijo de los Olivos",
    "gn:population":0,
    "gn:timezone":"Europe/Madrid",
    "iso:country":"ES",
    "name:und_x_variant":[
        "Cortijada El Cortijo de los Olivos",
        "El Cortijo de los Olivos"
    ],
    "wof:name":"El Cortijo de los Olivos",
    "wof:placetype":"locality"
},
  "geometry": {"coordinates":[-2.12476,36.91642],"type":"Point"}
}