{
  "type": "Feature",
  "properties": {
    "gn:gn_country":"ES",
    "gn:gn_fcode":"PPL",
    "gn:gn_pop":0,
    "iso:country":"ES",
    "name:ceb_x_preferred":[
        "Bolonia"
    ],
    "name:deu_x_preferred":[
        "Bolonia"
    ],
    "name:eng_x_preferred":[
        "Bolonia"
    ],
    "name:glg_x_preferred":[
        "Praia de Bolonia"
    ],
    "name:nld_x_preferred":[
        "Bolonia"
    ],
    "name:nob_x_preferred":[
        "Bolonia"
    ],
    "name:spa_x_preferred":[
        "Playa de Bolonia"
    ],
    "name:swe_x_preferred":[
        "Bolonia"
    ],
    "name:unk_x_variant":[
        "Cortijada de Bolonia"
    ],
    "qs_pg:aaroncc":"ES",
    "qs_pg:gn_country":"ES",
    "qs_pg:gn_fcode":"PPL",
    "qs_pg:gn_pop":0,
    "qs_pg:name":"Bolonia",
    "qs_pg:name_adm0":"Espa\u00f1a",
    "qs_pg:name_adm1":"Andaluc\u00eda",
    "qs_pg:photos":1918,
    "qs_pg:photos_1k":389,
    "qs_pg:photos_9k":9,
    "qs_pg:photos_9r":9,
    "qs_pg:photos_all":1918,
    "qs_pg:photos_sr":15,
    "qs_pg:pop_sr":0,
    "qs_pg:qs_pg_placetype":"locality",
    "qs_pg:qs_pg_placetype_gp":"Town",
    "qs_pg:woe_adm0":23424950,
    "woe:adm0_id":23424950,
    "woe:name_adm0":"Espa\u00f1a",
    "woe:name_adm1":"Andaluc\u00eda",
    "woe:placetype":"Town",
    "wof:name":"Bolonia",
    "wof:placetype":"locality"
},
  "geometry": {"coordinates":[-5.77426,36.089],"type":"Point"}
}