{
  "type": "Feature",
  "properties": {
    "gn:admin1_code":"51",
    "gn:admin2_code":"GR",
    "gn:admin3_code":"18100",
    "gn:asciiname":"Caseria San Sebastian",
    "gn:country_code":"ES",
    "gn:dem":492,
    "gn:feature_class":"P",
    "gn:feature_code":"PPLF",
    "gn:name":"Caser\u00eda San Sebasti\u00e1n",
    "gn:population":0,
    "gn:timezone":"Europe/Madrid",
    "iso:country":"ES",
    "wof:name":"Caseria San Sebastian",
    "wof:placetype":"locality"
},
  "geometry": {"coordinates":[-4.06182,37.20995],"type":"Point"}
}