{
  "type": "Feature",
  "properties": {
    "gn:admin1_code":"59",
    "gn:admin2_code":"BI",
    "gn:admin3_code":"48032",
    "gn:asciiname":"Mendraka",
    "gn:country_code":"ES",
    "gn:dem":458,
    "gn:feature_class":"P",
    "gn:feature_code":"PPL",
    "gn:name":"Mendraka",
    "gn:population":0,
    "gn:timezone":"Europe/Madrid",
    "iso:country":"ES",
    "name:eus_x_preferred":[
        "Mendraka"
    ],
    "name:spa_x_preferred":[
        "Mendraca"
    ],
    "wof:name":"Mendraka",
    "wof:placetype":"locality"
},
  "geometry": {"coordinates":[-2.53333,43.15],"type":"Point"}
}