{
  "type": "Feature",
  "properties": {
    "gn:admin1_code":"59",
    "gn:admin2_code":"BI",
    "gn:admin3_code":"48910",
    "gn:asciiname":"Orozketa",
    "gn:country_code":"ES",
    "gn:dem":181,
    "gn:feature_class":"P",
    "gn:feature_code":"PPL",
    "gn:name":"Orozketa",
    "gn:population":0,
    "gn:timezone":"Europe/Madrid",
    "iso:country":"ES",
    "name:eus_x_preferred":[
        "Orozketa"
    ],
    "name:spa_x_preferred":[
        "Orozqueta"
    ],
    "name:spa_x_variant":[
        "Or\u00f3zqueta"
    ],
    "wof:name":"Orozketa",
    "wof:placetype":"locality"
},
  "geometry": {"coordinates":[-2.65,43.16667],"type":"Point"}
}