{
  "type": "Feature",
  "properties": {
    "gn:admin1_code":"52",
    "gn:admin2_code":"HU",
    "gn:admin3_code":"22113",
    "gn:asciiname":"El Humo",
    "gn:country_code":"ES",
    "gn:dem":768,
    "gn:feature_class":"P",
    "gn:feature_code":"PPL",
    "gn:name":"El Humo",
    "gn:population":0,
    "gn:timezone":"Europe/Madrid",
    "iso:country":"ES",
    "wof:name":"El Humo",
    "wof:placetype":"locality"
},
  "geometry": {"coordinates":[0.29852,42.38429],"type":"Point"}
}