{
  "type": "Feature",
  "properties": {
    "gn:admin1_code":"55",
    "gn:admin2_code":"LE",
    "gn:admin3_code":"24115",
    "gn:asciiname":"Manzanedo de Valdueza",
    "gn:country_code":"ES",
    "gn:dem":931,
    "gn:feature_class":"P",
    "gn:feature_code":"PPL",
    "gn:name":"Manzanedo de Valdueza",
    "gn:population":0,
    "gn:timezone":"Europe/Madrid",
    "iso:country":"ES",
    "wof:name":"Manzanedo de Valdueza",
    "wof:placetype":"locality"
},
  "geometry": {"coordinates":[-6.52407,42.45732],"type":"Point"}
}