{
  "type": "Feature",
  "properties": {
    "gn:admin1_code":"58",
    "gn:admin2_code":"C",
    "gn:admin3_code":"15052",
    "gn:asciiname":"Cuno",
    "gn:country_code":"ES",
    "gn:dem":107,
    "gn:feature_class":"P",
    "gn:feature_code":"PPL",
    "gn:name":"Cu\u00f1o",
    "gn:population":0,
    "gn:timezone":"Europe/Madrid",
    "iso:country":"ES",
    "name:und_x_variant":[
        "Cu\u00f1o"
    ],
    "wof:name":"Cuno",
    "wof:placetype":"locality"
},
  "geometry": {"coordinates":[-9.25,43.06667],"type":"Point"}
}