{
  "type": "Feature",
  "properties": {
    "gn:admin1_code":"51",
    "gn:admin2_code":"GR",
    "gn:admin3_code":"18122",
    "gn:asciiname":"Ventorros de San Jose",
    "gn:country_code":"ES",
    "gn:dem":829,
    "gn:feature_class":"P",
    "gn:feature_code":"PPL",
    "gn:name":"Ventorros de San Jos\u00e9",
    "gn:population":0,
    "gn:timezone":"Europe/Madrid",
    "iso:country":"ES",
    "wof:name":"Ventorros de San Jose",
    "wof:placetype":"locality"
},
  "geometry": {"coordinates":[-4.15137,37.24755],"type":"Point"}
}