{
  "type": "Feature",
  "properties": {
    "gn:admin1_code":"58",
    "gn:admin2_code":"OR",
    "gn:admin3_code":"32068",
    "gn:asciiname":"Villamea de Ramiras",
    "gn:country_code":"ES",
    "gn:dem":470,
    "gn:feature_class":"P",
    "gn:feature_code":"PPL",
    "gn:name":"Villame\u00e1 de Ramir\u00e1s",
    "gn:population":0,
    "gn:timezone":"Europe/Madrid",
    "iso:country":"ES",
    "wof:name":"Villamea de Ramiras",
    "wof:placetype":"locality"
},
  "geometry": {"coordinates":[-8.03845,42.17018],"type":"Point"}
}