{
  "type": "Feature",
  "properties": {
    "gn:admin1_code":"51",
    "gn:admin2_code":"MA",
    "gn:admin3_code":"29086",
    "gn:asciiname":"Carraspite",
    "gn:country_code":"ES",
    "gn:dem":493,
    "gn:feature_class":"P",
    "gn:feature_code":"PPL",
    "gn:name":"Carraspite",
    "gn:population":0,
    "gn:timezone":"Europe/Madrid",
    "iso:country":"ES",
    "name:und_x_variant":[
        "Caser\u00edo Carraspite",
        "Carraspite"
    ],
    "wof:name":"Carraspite",
    "wof:placetype":"locality"
},
  "geometry": {"coordinates":[-4.01629,36.78344],"type":"Point"}
}