{
  "type": "Feature",
  "properties": {
    "gn:gn_country":"ES",
    "gn:gn_fcode":"PPL",
    "gn:gn_pop":280,
    "gn:population":280,
    "iso:country":"ES",
    "name:ara_x_preferred":[
        "\u0644\u0627 \u0628\u0648\u0628\u0644\u0627 \u062f\u064a \u0628\u064a\u0646\u064a\u0641\u0627\u0633\u0627"
    ],
    "name:arg_x_preferred":[
        "La Puebla de Benifaz\u00e1n"
    ],
    "name:cat_x_preferred":[
        "La Pobla de Benifassa"
    ],
    "name:eng_x_preferred":[
        "La Pobla de Benifass\u00e0"
    ],
    "name:eus_x_preferred":[
        "La Pobla de Benifass\u00e0"
    ],
    "name:fra_x_preferred":[
        "La Pobla de Benifass\u00e0"
    ],
    "name:hun_x_preferred":[
        "La Pobla de Benifass\u00e0"
    ],
    "name:ita_x_preferred":[
        "La Pobla de Benifass\u00e0"
    ],
    "name:msa_x_preferred":[
        "La Pobla de Benifass\u00e0"
    ],
    "name:nan_x_preferred":[
        "La Pobla de Benifass\u00e0"
    ],
    "name:nld_x_preferred":[
        "La Pobla de Benifass\u00e0"
    ],
    "name:oci_x_preferred":[
        "La Pobla de Benifass\u00e0"
    ],
    "name:pol_x_preferred":[
        "La Pobla de Benifass\u00e0"
    ],
    "name:por_x_preferred":[
        "La Pobla de Benifass\u00e0"
    ],
    "name:rus_x_preferred":[
        "\u041f\u0443\u044d\u0431\u043b\u0430-\u0434\u0435-\u0411\u0435\u043d\u0438\u0444\u0430\u0441\u0430\u0440"
    ],
    "name:spa_x_preferred":[
        "Puebla de Benifasar"
    ],
    "name:sqi_x_preferred":[
        "La Pobla de Benifass\u00e0"
    ],
    "name:swe_x_preferred":[
        "Puebla de Benifasar"
    ],
    "name:ukr_x_preferred":[
        "\u041b\u0430-\u041f\u043e\u0431\u043b\u0430-\u0434\u0435-\u0411\u0435\u043d\u0456\u0444\u0430\u0441\u0430"
    ],
    "name:unk_x_variant":[
        "Pobla de Benifassar"
    ],
    "name:urd_x_preferred":[
        "\u0644\u0627 \u067e\u0648\u0628\u0644\u0627 \u062f\u06d2 \u0628\u06cc\u0646\u06cc\u0641\u0627\u0633\u0627"
    ],
    "name:uzb_x_preferred":[
        "Puebla de Benifasar"
    ],
    "name:vie_x_preferred":[
        "La Pobla de Benifass\u00e0"
    ],
    "name:war_x_preferred":[
        "La Pobla de Benifass\u00e0"
    ],
    "name:zho_x_preferred":[
        "\u62c9\u6ce2\u592b\u62c9\u5fb7\u97e6\u5c3c\u6cd5\u8428"
    ],
    "qs_pg:aaroncc":"ES",
    "qs_pg:gn_country":"ES",
    "qs_pg:gn_fcode":"PPL",
    "qs_pg:gn_pop":280,
    "qs_pg:name":"Puebla de Benifasar",
    "qs_pg:name_adm0":"Espa\u00f1a",
    "qs_pg:name_adm1":"Comunitat Valenciana",
    "qs_pg:photos":207,
    "qs_pg:photos_1k":42,
    "qs_pg:photos_9k":1,
    "qs_pg:photos_9r":4,
    "qs_pg:photos_all":207,
    "qs_pg:photos_sr":4,
    "qs_pg:pop_sr":2,
    "qs_pg:qs_pg_placetype":"locality",
    "qs_pg:qs_pg_placetype_gp":"Town",
    "qs_pg:woe_adm0":23424950,
    "woe:adm0_id":23424950,
    "woe:name_adm0":"Espa\u00f1a",
    "woe:name_adm1":"Comunitat Valenciana",
    "woe:placetype":"Town",
    "wof:name":"Puebla de Benifasar",
    "wof:placetype":"locality",
    "wof:population":280
},
  "geometry": {"coordinates":[0.15793,40.65629],"type":"Point"}
}