{
  "type": "Feature",
  "properties": {
    "gn:admin1_code":"60",
    "gn:admin2_code":"A",
    "gn:admin3_code":"03089",
    "gn:asciiname":"Alforins",
    "gn:cc2":"ES",
    "gn:country_code":"ES",
    "gn:dem":480,
    "gn:feature_class":"P",
    "gn:feature_code":"PPL",
    "gn:name":"Alforins",
    "gn:population":0,
    "gn:timezone":"Europe/Madrid",
    "iso:country":"ES",
    "name:und_x_variant":[
        "Caser\u00edo Alforins",
        "Alforins"
    ],
    "wof:name":"Alforins",
    "wof:placetype":"locality"
},
  "geometry": {"coordinates":[-0.91667,38.38333],"type":"Point"}
}