{
  "type": "Feature",
  "properties": {
    "gn:admin1_code":"51",
    "gn:admin2_code":"H",
    "gn:admin3_code":"21004",
    "gn:asciiname":"Cincho",
    "gn:country_code":"ES",
    "gn:dem":605,
    "gn:feature_class":"P",
    "gn:feature_code":"PPL",
    "gn:name":"Cincho",
    "gn:population":0,
    "gn:timezone":"Europe/Madrid",
    "iso:country":"ES",
    "wof:name":"Cincho",
    "wof:placetype":"locality"
},
  "geometry": {"coordinates":[-6.82261,37.89311],"type":"Point"}
}