{
  "type": "Feature",
  "properties": {
    "gn:country":"ES",
    "gn:fcode":"PPLA3",
    "gn:population":177,
    "iso:country":"ES",
    "name:azb_x_preferred":[
        "\u0631\u06cc\u0628\u0627\u0633 \u062f \u06a9\u0627\u0645\u067e\u0633"
    ],
    "name:cat_x_preferred":[
        "Ribas de Campos"
    ],
    "name:che_x_preferred":[
        "\u0420\u0438\u0431\u0430\u0441-\u0434\u0435-\u041a\u0430\u043c\u043f\u043e\u0441"
    ],
    "name:eng_x_preferred":[
        "Ribas de Campos"
    ],
    "name:eus_x_preferred":[
        "Ribas de Campos"
    ],
    "name:fas_x_preferred":[
        "\u0631\u06cc\u0628\u0627\u0633 \u062f \u06a9\u0627\u0645\u067e\u0633"
    ],
    "name:fra_x_preferred":[
        "Ribas de Campos"
    ],
    "name:glg_x_preferred":[
        "Ribas de Campos"
    ],
    "name:hun_x_preferred":[
        "Ribas de Campos"
    ],
    "name:ina_x_preferred":[
        "Ribas de Campos"
    ],
    "name:ita_x_preferred":[
        "Ribas de Campos"
    ],
    "name:msa_x_preferred":[
        "Ribas de Campos"
    ],
    "name:nan_x_preferred":[
        "Ribas de Campos"
    ],
    "name:nld_x_preferred":[
        "Ribas de Campos"
    ],
    "name:oci_x_preferred":[
        "Ribas de Campos"
    ],
    "name:pol_x_preferred":[
        "Ribas de Campos"
    ],
    "name:por_x_preferred":[
        "Ribas de Campos"
    ],
    "name:rus_x_preferred":[
        "\u0420\u0438\u0431\u0430\u0441-\u0434\u0435-\u041a\u0430\u043c\u043f\u043e\u0441"
    ],
    "name:spa_x_preferred":[
        "Ribas de Campos"
    ],
    "name:swe_x_preferred":[
        "Ribas de Campos"
    ],
    "name:tat_x_preferred":[
        "\u0420\u0438\u0431\u0430\u0441-\u0434\u0435-\u041a\u0430\u043c\u043f\u043e\u0441"
    ],
    "name:ukr_x_preferred":[
        "\u0420\u0456\u0431\u0430\u0441-\u0434\u0435-\u041a\u0430\u043c\u043f\u043e\u0441"
    ],
    "name:und_x_variant":[
        "Ribas"
    ],
    "name:uzb_x_preferred":[
        "Ribas de Campos"
    ],
    "name:vie_x_preferred":[
        "Ribas de Campos"
    ],
    "name:war_x_preferred":[
        "Ribas de Campos"
    ],
    "name:zho_x_preferred":[
        "\u91cc\u74e6\u65af\u5fb7\u574e\u6ce2\u65af"
    ],
    "qs_pg:aaroncc":"ES",
    "qs_pg:gn_country":"ES",
    "qs_pg:gn_fcode":"PPLA3",
    "qs_pg:gn_pop":177,
    "qs_pg:name":"Ribas de Campos",
    "qs_pg:name_adm0":"Espa\u00f1a",
    "qs_pg:name_adm1":"Castilla y Le\u00f3n",
    "qs_pg:photos_9k":1,
    "qs_pg:photos_9r":1,
    "qs_pg:photos_all":1,
    "qs_pg:photos_sr":0,
    "qs_pg:pop_sr":1,
    "qs_pg:qs_pg_placetype":"locality",
    "qs_pg:qs_pg_placetype_gp":"Town",
    "qs_pg:woe_adm0":23424950,
    "woe:adm0_id":23424950,
    "woe:name_adm0":"Espa\u00f1a",
    "woe:name_adm1":"Castilla y Le\u00f3n",
    "woe:placetype":"Town",
    "wof:name":"Ribas de Campos",
    "wof:placetype":"locality",
    "wof:population":177
},
  "geometry": {"coordinates":[-4.51649,42.15249],"type":"Point"}
}