{
  "type": "Feature",
  "properties": {
    "gn:admin1_code":"56",
    "gn:admin2_code":"L",
    "gn:admin3_code":"25227",
    "gn:asciiname":"Pauls",
    "gn:country_code":"ES",
    "gn:dem":1133,
    "gn:feature_class":"P",
    "gn:feature_code":"PPL",
    "gn:name":"Pa\u00fals",
    "gn:population":0,
    "gn:timezone":"Europe/Madrid",
    "iso:country":"ES",
    "name:deu_x_preferred":[
        "Pauls"
    ],
    "name:ita_x_preferred":[
        "Pauls"
    ],
    "name:lav_x_preferred":[
        "Pauls"
    ],
    "name:pol_x_preferred":[
        "Pauls"
    ],
    "name:rus_x_preferred":[
        "\u041f\u0430\u0443\u043b\u044c\u0441"
    ],
    "name:spa_x_preferred":[
        "Pauls"
    ],
    "name:ukr_x_preferred":[
        "\u041f\u0430\u0443\u043b\u0441"
    ],
    "wof:name":"Pauls",
    "wof:placetype":"locality"
},
  "geometry": {"coordinates":[0.9826,42.39652],"type":"Point"}
}