{
  "type": "Feature",
  "properties": {
    "gn:admin1_code":"60",
    "gn:admin2_code":"V",
    "gn:admin3_code":"46181",
    "gn:asciiname":"Huertas",
    "gn:cc2":"ES",
    "gn:country_code":"ES",
    "gn:dem":14,
    "gn:feature_class":"P",
    "gn:feature_code":"PPL",
    "gn:name":"Huertas",
    "gn:population":0,
    "gn:timezone":"Europe/Madrid",
    "iso:country":"ES",
    "name:und_x_variant":[
        "Casas Huertas",
        "Huertas"
    ],
    "wof:name":"Huertas",
    "wof:placetype":"locality"
},
  "geometry": {"coordinates":[-0.11667,38.91667],"type":"Point"}
}