{
  "type": "Feature",
  "properties": {
    "gn:admin1_code":"55",
    "gn:admin2_code":"AV",
    "gn:admin3_code":"05195",
    "gn:asciiname":"Escalonilla",
    "gn:country_code":"ES",
    "gn:dem":1165,
    "gn:feature_class":"P",
    "gn:feature_code":"PPL",
    "gn:name":"Escalonilla",
    "gn:population":0,
    "gn:timezone":"Europe/Madrid",
    "iso:country":"ES",
    "name:arg_x_preferred":[
        "Escalonilla"
    ],
    "name:ast_x_preferred":[
        "Escalonilla"
    ],
    "name:cat_x_preferred":[
        "Escalonilla"
    ],
    "name:ceb_x_preferred":[
        "Escalonilla"
    ],
    "name:epo_x_preferred":[
        "Escalonilla"
    ],
    "name:eus_x_preferred":[
        "Escalonilla"
    ],
    "name:fas_x_preferred":[
        "\u0627\u0633\u06a9\u0627\u0644\u0646\u06cc\u06cc\u0627"
    ],
    "name:fra_x_preferred":[
        "Escalonilla"
    ],
    "name:hun_x_preferred":[
        "Escalonilla"
    ],
    "name:hye_x_preferred":[
        "\u0537\u057d\u056f\u0561\u056c\u0578\u0576\u056b\u056c\u0575\u0561"
    ],
    "name:ina_x_preferred":[
        "Escalonilla"
    ],
    "name:ita_x_preferred":[
        "Escalonilla"
    ],
    "name:kaz_x_preferred":[
        "\u042d\u0441\u043a\u0430\u043b\u043e\u043d\u0438\u043b\u044c\u044f"
    ],
    "name:msa_x_preferred":[
        "Escalonilla"
    ],
    "name:nld_x_preferred":[
        "Escalonilla"
    ],
    "name:oci_x_preferred":[
        "Escalonilla"
    ],
    "name:pol_x_preferred":[
        "Escalonilla"
    ],
    "name:por_x_preferred":[
        "Escalonilla"
    ],
    "name:ron_x_preferred":[
        "Escalonilla"
    ],
    "name:rus_x_preferred":[
        "\u042d\u0441\u043a\u0430\u043b\u043e\u043d\u0438\u043b\u044c\u044f"
    ],
    "name:spa_x_preferred":[
        "Escalonilla"
    ],
    "name:swe_x_preferred":[
        "Escalonilla"
    ],
    "name:ukr_x_preferred":[
        "\u0415\u0441\u043a\u0430\u043b\u043e\u043d\u0456\u043b\u044c\u044f"
    ],
    "name:und_x_variant":[
        "Barrio Escalonilla",
        "Escalonilla"
    ],
    "name:vie_x_preferred":[
        "Escalonilla"
    ],
    "name:war_x_preferred":[
        "Escalonilla"
    ],
    "name:zho_x_preferred":[
        "\u57c3\u65af\u5361\u6d1b\u5c3c\u5229\u4e9a"
    ],
    "wof:name":"Escalonilla",
    "wof:placetype":"locality"
},
  "geometry": {"coordinates":[-4.78594,40.54656],"type":"Point"}
}