{
  "type": "Feature",
  "properties": {
    "gn:admin1_code":"58",
    "gn:admin2_code":"C",
    "gn:admin3_code":"15042",
    "gn:asciiname":"Choura",
    "gn:country_code":"ES",
    "gn:dem":123,
    "gn:feature_class":"P",
    "gn:feature_code":"PPL",
    "gn:name":"Choura",
    "gn:population":0,
    "gn:timezone":"Europe/Madrid",
    "iso:country":"ES",
    "name:und_x_variant":[
        "Chouza",
        "Choura"
    ],
    "wof:name":"Choura",
    "wof:placetype":"locality"
},
  "geometry": {"coordinates":[-8.91762,42.75835],"type":"Point"}
}