{
  "type": "Feature",
  "properties": {
    "gn:admin1_code":"32",
    "gn:admin3_code":"31086",
    "gn:asciiname":"Irotz",
    "gn:country_code":"ES",
    "gn:dem":581,
    "gn:feature_class":"P",
    "gn:feature_code":"PPL",
    "gn:name":"Irotz",
    "gn:population":0,
    "gn:timezone":"Europe/Madrid",
    "iso:country":"ES",
    "name:eus_x_preferred":[
        "Irotz"
    ],
    "name:spa_x_preferred":[
        "Iroz"
    ],
    "wof:name":"Irotz",
    "wof:placetype":"locality"
},
  "geometry": {"coordinates":[-1.56667,42.86667],"type":"Point"}
}