{
  "type": "Feature",
  "properties": {
    "gn:admin1_code":"58",
    "gn:admin2_code":"LU",
    "gn:admin3_code":"27028",
    "gn:asciiname":"Castro",
    "gn:country_code":"ES",
    "gn:dem":474,
    "gn:feature_class":"P",
    "gn:feature_code":"PPL",
    "gn:name":"Castro",
    "gn:population":0,
    "gn:timezone":"Europe/Madrid",
    "iso:country":"ES",
    "name:bel_x_preferred":[
        "\u041a\u0430\u0441\u0442\u0440\u0430"
    ],
    "name:bre_x_preferred":[
        "Castro"
    ],
    "name:bul_x_preferred":[
        "\u041a\u0430\u0441\u0442\u0440\u043e"
    ],
    "name:cat_x_preferred":[
        "Castro"
    ],
    "name:ceb_x_preferred":[
        "Castro"
    ],
    "name:ces_x_preferred":[
        "Castro"
    ],
    "name:cym_x_preferred":[
        "Castro"
    ],
    "name:deu_x_preferred":[
        "Castro"
    ],
    "name:epo_x_preferred":[
        "Castro"
    ],
    "name:eus_x_preferred":[
        "Castro"
    ],
    "name:fas_x_preferred":[
        "\u06a9\u0627\u0633\u062a\u0631\u0648"
    ],
    "name:fin_x_preferred":[
        "Castro"
    ],
    "name:fra_x_preferred":[
        "Castro"
    ],
    "name:glg_x_preferred":[
        "Castro"
    ],
    "name:heb_x_preferred":[
        "\u05e7\u05e1\u05d8\u05e8\u05d5"
    ],
    "name:hye_x_preferred":[
        "\u053f\u0561\u057d\u057f\u0580\u0578"
    ],
    "name:isl_x_preferred":[
        "Castro"
    ],
    "name:ita_x_preferred":[
        "Castro"
    ],
    "name:jpn_x_preferred":[
        "\u30ab\u30b9\u30c8\u30ed"
    ],
    "name:kor_x_preferred":[
        "\uce74\uc2a4\ud2b8\ub85c"
    ],
    "name:lit_x_preferred":[
        "Castro"
    ],
    "name:nld_x_preferred":[
        "Castro"
    ],
    "name:nor_x_preferred":[
        "Castro"
    ],
    "name:pms_x_preferred":[
        "Castro"
    ],
    "name:pol_x_preferred":[
        "Castro"
    ],
    "name:por_x_preferred":[
        "Castro"
    ],
    "name:ron_x_preferred":[
        "Castro"
    ],
    "name:rus_x_preferred":[
        "\u041a\u0430\u0441\u0442\u0440\u043e"
    ],
    "name:slk_x_preferred":[
        "Castro"
    ],
    "name:slv_x_preferred":[
        "Castro"
    ],
    "name:spa_x_preferred":[
        "Castro"
    ],
    "name:srp_x_preferred":[
        "\u041a\u0430\u0441\u0442\u0440\u043e"
    ],
    "name:swe_x_preferred":[
        "Castro"
    ],
    "name:tur_x_preferred":[
        "Castro"
    ],
    "name:ukr_x_preferred":[
        "\u041a\u0430\u0448\u0442\u0440\u0443"
    ],
    "name:ukr_x_variant":[
        "\u041a\u0430\u0441\u0442\u0440\u043e"
    ],
    "name:urd_x_preferred":[
        "\u06a9\u06cc\u0633\u0679\u0631\u0648"
    ],
    "name:vol_x_preferred":[
        "Castro"
    ],
    "name:zho_cn_x_preferred":[
        "\u5361\u65af\u7279\u9c81"
    ],
    "name:zho_tw_x_preferred":[
        "\u5361\u65af\u7279\u7f85"
    ],
    "name:zho_x_preferred":[
        "\u5361\u65af\u7279\u7f57"
    ],
    "wof:name":"Castro",
    "wof:placetype":"locality"
},
  "geometry": {"coordinates":[-7.56667,42.95],"type":"Point"}
}