{
  "type": "Feature",
  "properties": {
    "gn:country":"ES",
    "gn:fcode":"PPLA3",
    "gn:population":0,
    "iso:country":"ES",
    "name:ara_x_preferred":[
        "\u0645\u0646\u062f\u064a\u0643\u0633\u0627"
    ],
    "name:arg_x_preferred":[
        "Mendexa"
    ],
    "name:arz_x_preferred":[
        "\u0645\u0646\u062f\u064a\u0643\u0633\u0627"
    ],
    "name:azb_x_preferred":[
        "\u0645\u0646\u062f\u06a9\u0633\u0627"
    ],
    "name:cat_x_preferred":[
        "Mendexa"
    ],
    "name:ceb_x_preferred":[
        "Mendexa"
    ],
    "name:che_x_preferred":[
        "\u041c\u0435\u043d\u0434\u0435\u0445\u0430"
    ],
    "name:eng_x_preferred":[
        "Mendexa"
    ],
    "name:eus_x_preferred":[
        "Mendexa"
    ],
    "name:fas_x_preferred":[
        "\u0645\u0646\u062f\u06a9\u0633\u0627"
    ],
    "name:fra_x_preferred":[
        "Mendexa"
    ],
    "name:gle_x_preferred":[
        "Mendexa"
    ],
    "name:glg_x_preferred":[
        "Mendexa"
    ],
    "name:hun_x_preferred":[
        "Mendexa"
    ],
    "name:ita_x_preferred":[
        "Mendexa"
    ],
    "name:jpn_x_preferred":[
        "\u30e1\u30f3\u30c7\u30b7\u30e3"
    ],
    "name:kat_x_preferred":[
        "\u10db\u10d4\u10dc\u10d3\u10d4\u10ee\u10d0"
    ],
    "name:lat_x_preferred":[
        "Mendeja"
    ],
    "name:lld_x_preferred":[
        "Mendexa"
    ],
    "name:ltz_x_preferred":[
        "Mendexa"
    ],
    "name:msa_x_preferred":[
        "Mendexa"
    ],
    "name:nld_x_preferred":[
        "Mendexa"
    ],
    "name:nob_x_preferred":[
        "Mendeja"
    ],
    "name:oci_x_preferred":[
        "Mendexa"
    ],
    "name:pol_x_preferred":[
        "Mendexa"
    ],
    "name:por_x_preferred":[
        "Mendeja"
    ],
    "name:rus_x_preferred":[
        "\u041c\u0435\u043d\u0434\u0435\u0445\u0430"
    ],
    "name:sco_x_preferred":[
        "Mendexa"
    ],
    "name:spa_x_preferred":[
        "Mendeja"
    ],
    "name:sqi_x_preferred":[
        "Mendexa"
    ],
    "name:swe_x_preferred":[
        "Mendexa"
    ],
    "name:tat_x_preferred":[
        "\u041c\u0435\u043d\u0434\u0435\u0445\u0430"
    ],
    "name:ukr_x_preferred":[
        "\u041c\u0435\u043d\u0434\u0435\u0448\u0430"
    ],
    "name:uzb_x_preferred":[
        "Mendeja"
    ],
    "name:vec_x_preferred":[
        "Mendexa"
    ],
    "name:war_x_preferred":[
        "Mendexa"
    ],
    "name:zho_x_preferred":[
        "\u95e8\u5fb7\u514b\u8428"
    ],
    "name:zho_x_variant":[
        "\u95e8\u5fb7\u54c8"
    ],
    "qs_pg:aaroncc":"ES",
    "qs_pg:gn_country":"ES",
    "qs_pg:gn_fcode":"PPLA3",
    "qs_pg:gn_pop":0,
    "qs_pg:name":"Mendexa",
    "qs_pg:name_adm0":"Espa\u00f1a",
    "qs_pg:name_adm1":"Euskadi",
    "qs_pg:photos":10,
    "qs_pg:photos_1k":2,
    "qs_pg:photos_9k":1,
    "qs_pg:photos_9r":1,
    "qs_pg:photos_all":10,
    "qs_pg:photos_sr":1,
    "qs_pg:pop_sr":0,
    "qs_pg:qs_pg_placetype":"locality",
    "qs_pg:qs_pg_placetype_gp":"Town",
    "qs_pg:woe_adm0":23424950,
    "woe:adm0_id":23424950,
    "woe:name_adm0":"Espa\u00f1a",
    "woe:name_adm1":"Euskadi",
    "woe:placetype":"Town",
    "wof:name":"Mendexa",
    "wof:placetype":"locality"
},
  "geometry": {"coordinates":[-2.4842,43.3459],"type":"Point"}
}