{
  "type": "Feature",
  "properties": {
    "gn:admin1_code":"55",
    "gn:admin2_code":"BU",
    "gn:admin3_code":"09209",
    "gn:asciiname":"Moneo",
    "gn:country_code":"ES",
    "gn:dem":577,
    "gn:feature_class":"P",
    "gn:feature_code":"PPL",
    "gn:name":"Moneo",
    "gn:population":0,
    "gn:timezone":"Europe/Madrid",
    "iso:country":"ES",
    "name:fra_x_preferred":[
        "Moneo"
    ],
    "wof:name":"Moneo",
    "wof:placetype":"locality"
},
  "geometry": {"coordinates":[-3.46562,42.89321],"type":"Point"}
}