{
  "type": "Feature",
  "properties": {
    "gn:admin1_code":"58",
    "gn:admin2_code":"LU",
    "gn:admin3_code":"27034",
    "gn:asciiname":"Ventosa",
    "gn:country_code":"ES",
    "gn:dem":731,
    "gn:feature_class":"P",
    "gn:feature_code":"PPL",
    "gn:name":"Ventosa",
    "gn:population":0,
    "gn:timezone":"Europe/Madrid",
    "iso:country":"ES",
    "name:cat_x_preferred":[
        "Ventosa"
    ],
    "name:ceb_x_preferred":[
        "Ventosa"
    ],
    "name:deu_x_preferred":[
        "Ventosa"
    ],
    "name:eus_x_preferred":[
        "Ventosa"
    ],
    "name:fra_x_preferred":[
        "Ventosa"
    ],
    "name:glg_x_preferred":[
        "Ventosa"
    ],
    "name:hun_x_preferred":[
        "Ventosa"
    ],
    "name:ita_x_preferred":[
        "Ventosa"
    ],
    "name:nld_x_preferred":[
        "Ventosa"
    ],
    "name:por_x_preferred":[
        "Ventosa"
    ],
    "name:rus_x_preferred":[
        "\u0412\u0435\u043d\u0442\u043e\u0437\u0430"
    ],
    "name:sco_x_preferred":[
        "Ventosa"
    ],
    "name:spa_x_preferred":[
        "Ventosa"
    ],
    "name:swe_x_preferred":[
        "Ventosa"
    ],
    "name:tur_x_preferred":[
        "Ventosa"
    ],
    "name:ukr_x_preferred":[
        "\u0412\u0435\u043d\u0442\u043e\u0437\u0430"
    ],
    "wof:name":"Ventosa",
    "wof:placetype":"locality"
},
  "geometry": {"coordinates":[-6.93257,42.94808],"type":"Point"}
}