{
  "type": "Feature",
  "properties": {
    "gn:admin1_code":"31",
    "gn:admin2_code":"MU",
    "gn:admin3_code":"30021",
    "gn:asciiname":"Los Guijarros",
    "gn:country_code":"ES",
    "gn:dem":206,
    "gn:feature_class":"P",
    "gn:feature_code":"PPL",
    "gn:name":"Los Guijarros",
    "gn:population":0,
    "gn:timezone":"Europe/Madrid",
    "iso:country":"ES",
    "name:und_x_variant":[
        "Caser\u00edo Los Guijarros",
        "Los Guijarros"
    ],
    "wof:name":"Los Guijarros",
    "wof:placetype":"locality"
},
  "geometry": {"coordinates":[-1.20439,37.6583],"type":"Point"}
}