{
  "type": "Feature",
  "properties": {
    "iso:country":"ES",
    "wof:name":"Els Orriols",
    "wof:placetype":"neighbourhood"
},
  "geometry": {"coordinates":[-0.36838652090777,39.49449147067988],"type":"Point"}
}