{
  "type": "Feature",
  "properties": {
    "gn:admin1_code":"54",
    "gn:admin2_code":"GU",
    "gn:admin3_code":"19086",
    "gn:asciiname":"Carrascosa de Tajo",
    "gn:country_code":"ES",
    "gn:dem":849,
    "gn:feature_class":"P",
    "gn:feature_code":"PPL",
    "gn:name":"Carrascosa de Tajo",
    "gn:population":0,
    "gn:timezone":"Europe/Madrid",
    "iso:country":"ES",
    "name:und_x_variant":[
        "Carracosa",
        "Carrascosa de Tajo"
    ],
    "wof:name":"Carrascosa de Tajo",
    "wof:placetype":"locality"
},
  "geometry": {"coordinates":[-2.4838,40.72498],"type":"Point"}
}