{
  "type": "Feature",
  "properties": {
    "gn:admin1_code":"58",
    "gn:admin2_code":"OR",
    "gn:admin3_code":"32001",
    "gn:asciiname":"Urrios",
    "gn:cc2":"ES",
    "gn:country_code":"ES",
    "gn:dem":581,
    "gn:feature_class":"P",
    "gn:feature_code":"PPL",
    "gn:name":"Urri\u00f3s",
    "gn:population":0,
    "gn:timezone":"Europe/Madrid",
    "iso:country":"ES",
    "name:und_x_variant":[
        "San Mam\u00e9d",
        "Urr\u00f3s",
        "Urri\u00f3s"
    ],
    "wof:name":"Urrios",
    "wof:placetype":"locality"
},
  "geometry": {"coordinates":[-7.86667,42.21667],"type":"Point"}
}