{
  "type": "Feature",
  "properties": {
    "gn:admin1_code":"51",
    "gn:admin2_code":"GR",
    "gn:admin3_code":"18023",
    "gn:asciiname":"Blanques del Sauco",
    "gn:country_code":"ES",
    "gn:dem":1386,
    "gn:feature_class":"P",
    "gn:feature_code":"PPL",
    "gn:name":"Blanques del Sa\u00faco",
    "gn:population":0,
    "gn:timezone":"Europe/Madrid",
    "iso:country":"ES",
    "name:und_x_variant":[
        "Cortijada Blanques del So\u00faco",
        "Los Blanquez del Sauco",
        "Blanques del Sa\u00faco"
    ],
    "wof:name":"Blanques del Sauco",
    "wof:placetype":"locality"
},
  "geometry": {"coordinates":[-2.6331,37.27854],"type":"Point"}
}