{
  "type": "Feature",
  "properties": {
    "gn:admin1_code":"55",
    "gn:admin2_code":"P",
    "gn:admin3_code":"34171",
    "gn:asciiname":"Cornon",
    "gn:country_code":"ES",
    "gn:dem":1160,
    "gn:feature_class":"P",
    "gn:feature_code":"PPL",
    "gn:name":"Corn\u00f3n",
    "gn:population":0,
    "gn:timezone":"Europe/Madrid",
    "iso:country":"ES",
    "wof:name":"Cornon",
    "wof:placetype":"locality"
},
  "geometry": {"coordinates":[-4.7481,42.76717],"type":"Point"}
}