{
  "type": "Feature",
  "properties": {
    "gn:admin1_code":"51",
    "gn:admin2_code":"J",
    "gn:admin3_code":"23030",
    "gn:asciiname":"Cortijo Grande",
    "gn:country_code":"ES",
    "gn:dem":582,
    "gn:feature_class":"P",
    "gn:feature_code":"PPL",
    "gn:name":"Cortijo Grande",
    "gn:population":0,
    "gn:timezone":"Europe/Madrid",
    "iso:country":"ES",
    "name:und_x_variant":[
        "Casas Cortijo Grande",
        "Cortijo Grande"
    ],
    "wof:name":"Cortijo Grande",
    "wof:placetype":"locality"
},
  "geometry": {"coordinates":[-3.00449,37.99229],"type":"Point"}
}