{
  "type": "Feature",
  "properties": {
    "gn:gn_country":"ES",
    "gn:gn_fcode":"PPL",
    "gn:gn_pop":0,
    "iso:country":"ES",
    "name:bul_x_preferred":[
        "\u041b\u0430\u0441 \u0411\u0440\u0435\u043d\u0430\u0441"
    ],
    "name:ceb_x_preferred":[
        "Las Bre\u00f1as"
    ],
    "name:deu_x_preferred":[
        "Las Bre\u00f1as"
    ],
    "name:fra_x_preferred":[
        "Las Bre\u00f1as"
    ],
    "name:ita_x_preferred":[
        "Las Bre\u00f1as"
    ],
    "name:nld_x_preferred":[
        "Las Bre\u00f1as"
    ],
    "name:pol_x_preferred":[
        "Las Bre\u00f1as"
    ],
    "name:por_x_preferred":[
        "Las Bre\u00f1as"
    ],
    "name:spa_x_preferred":[
        "Las Bre\u00f1as"
    ],
    "name:swe_x_preferred":[
        "Las Bre\u00f1as"
    ],
    "name:zho_x_preferred":[
        "\u62c9\u65af\u5e03\u96f7\u5c3c\u4e9e\u65af"
    ],
    "qs_pg:aaroncc":"ES",
    "qs_pg:gn_country":"ES",
    "qs_pg:gn_fcode":"PPL",
    "qs_pg:gn_pop":0,
    "qs_pg:name":"Las Bre\u00f1as",
    "qs_pg:name_adm0":"Espa\u00f1a",
    "qs_pg:name_adm1":"Islas Canarias",
    "qs_pg:photos":71,
    "qs_pg:photos_1k":14,
    "qs_pg:photos_9k":1,
    "qs_pg:photos_9r":2,
    "qs_pg:photos_all":71,
    "qs_pg:photos_sr":2,
    "qs_pg:pop_sr":0,
    "qs_pg:qs_pg_placetype":"locality",
    "qs_pg:qs_pg_placetype_gp":"Town",
    "qs_pg:woe_adm0":23424950,
    "woe:adm0_id":23424950,
    "woe:name_adm0":"Espa\u00f1a",
    "woe:name_adm1":"Islas Canarias",
    "woe:placetype":"Town",
    "wof:name":"Las Bre\u00f1as",
    "wof:placetype":"locality"
},
  "geometry": {"coordinates":[-13.81033,28.91985],"type":"Point"}
}