{
  "type": "Feature",
  "properties": {
    "gn:admin1_code":"58",
    "gn:admin2_code":"C",
    "gn:admin3_code":"15022",
    "gn:asciiname":"Montoxo",
    "gn:cc2":"ES",
    "gn:country_code":"ES",
    "gn:dem":208,
    "gn:feature_class":"P",
    "gn:feature_code":"PPL",
    "gn:name":"Montoxo",
    "gn:population":0,
    "gn:timezone":"Europe/Madrid",
    "iso:country":"ES",
    "name:und_x_variant":[
        "San Juli\u00e1n"
    ],
    "wof:name":"Montoxo",
    "wof:placetype":"locality"
},
  "geometry": {"coordinates":[-7.98333,43.65],"type":"Point"}
}