{
  "type": "Feature",
  "properties": {
    "gn:admin1_code":"59",
    "gn:admin2_code":"SS",
    "gn:admin3_code":"20019",
    "gn:asciiname":"Garin",
    "gn:country_code":"ES",
    "gn:dem":427,
    "gn:feature_class":"P",
    "gn:feature_code":"PPL",
    "gn:name":"Garin",
    "gn:population":0,
    "gn:timezone":"Europe/Madrid",
    "iso:country":"ES",
    "name:eus_x_preferred":[
        "Garin"
    ],
    "wof:name":"Garin",
    "wof:placetype":"locality"
},
  "geometry": {"coordinates":[-2.22596,43.07811],"type":"Point"}
}