{
  "type": "Feature",
  "properties": {
    "gn:admin1_code":"59",
    "gn:admin2_code":"SS",
    "gn:admin3_code":"20019",
    "gn:asciiname":"Garin",
    "gn:country_code":"ES",
    "gn:dem":427,
    "gn:feature_class":"P",
    "gn:feature_code":"PPL",
    "gn:name":"Garin",
    "gn:population":0,
    "gn:timezone":"Europe/Madrid",
    "iso:country":"ES",
    "name:ceb_x_preferred":[
        "Garin"
    ],
    "name:deu_x_preferred":[
        "Garin"
    ],
    "name:eus_x_preferred":[
        "Garin"
    ],
    "name:fra_x_preferred":[
        "Garin"
    ],
    "name:ita_x_preferred":[
        "Garin"
    ],
    "name:nds_x_preferred":[
        "Garin"
    ],
    "name:nld_x_preferred":[
        "Garin"
    ],
    "name:pol_x_preferred":[
        "Garin"
    ],
    "name:rus_x_preferred":[
        "\u0413\u0430\u0440\u0435\u043d"
    ],
    "name:slk_x_preferred":[
        "Garin"
    ],
    "name:slv_x_preferred":[
        "Garin"
    ],
    "name:spa_x_preferred":[
        "Gar\u00edn"
    ],
    "name:swe_x_preferred":[
        "Garin"
    ],
    "name:ukr_x_preferred":[
        "\u0413\u0430\u0440\u0456\u043d"
    ],
    "wof:name":"Garin",
    "wof:placetype":"locality"
},
  "geometry": {"coordinates":[-2.22596,43.07811],"type":"Point"}
}