{
  "type": "Feature",
  "properties": {
    "gn:admin1_code":"51",
    "gn:admin2_code":"J",
    "gn:admin3_code":"23002.0",
    "gn:asciiname":"Pilas de Fuente Soto",
    "gn:country_code":"ES",
    "gn:dem":848,
    "gn:feature_class":"P",
    "gn:feature_code":"PPL",
    "gn:name":"Pilas de Fuente Soto",
    "gn:population":0,
    "gn:timezone":"Europe/Madrid",
    "iso:country":"ES",
    "wof:name":"Pilas de Fuente Soto",
    "wof:placetype":"locality"
},
  "geometry": {"coordinates":[-4.01181,37.43929],"type":"Point"}
}