{
  "type": "Feature",
  "properties": {
    "gn:admin1_code":"58",
    "gn:admin2_code":"OR",
    "gn:admin3_code":"32005",
    "gn:asciiname":"Tejones",
    "gn:country_code":"ES",
    "gn:dem":841,
    "gn:feature_class":"P",
    "gn:feature_code":"PPL",
    "gn:name":"Tejones",
    "gn:population":0,
    "gn:timezone":"Europe/Madrid",
    "iso:country":"ES",
    "wof:name":"Tejones",
    "wof:placetype":"locality"
},
  "geometry": {"coordinates":[-7.71217,41.96466],"type":"Point"}
}