{
  "type": "Feature",
  "properties": {
    "gn:admin1_code":"39",
    "gn:admin2_code":"S",
    "gn:admin3_code":"39020",
    "gn:asciiname":"Setares",
    "gn:country_code":"ES",
    "gn:dem":249,
    "gn:feature_class":"P",
    "gn:feature_code":"PPL",
    "gn:name":"Setares",
    "gn:population":0,
    "gn:timezone":"Europe/Madrid",
    "iso:country":"ES",
    "wof:name":"Setares",
    "wof:placetype":"locality"
},
  "geometry": {"coordinates":[-3.18159,43.33519],"type":"Point"}
}