{
  "type": "Feature",
  "properties": {
    "gn:admin1_code":"60",
    "gn:admin2_code":"V",
    "gn:admin3_code":"46111",
    "gn:asciiname":"Ribarroja del Turia",
    "gn:country_code":"ES",
    "gn:dem":103,
    "gn:feature_class":"P",
    "gn:feature_code":"PPL",
    "gn:name":"Ribarroja del Turia",
    "gn:population":20468,
    "gn:timezone":"Europe/Madrid",
    "iso:country":"ES",
    "name:cat_x_preferred":[
        "Riba-roja de T\u00faria"
    ],
    "wof:name":"Ribarroja del Turia",
    "wof:placetype":"locality",
    "wof:population":20468
},
  "geometry": {"coordinates":[-0.57069,39.54595],"type":"Point"}
}