{
  "type": "Feature",
  "properties": {
    "gn:admin1_code":"59",
    "gn:admin2_code":"BI",
    "gn:admin3_code":"48042",
    "gn:asciiname":"El Ponton",
    "gn:country_code":"ES",
    "gn:dem":85,
    "gn:feature_class":"P",
    "gn:feature_code":"PPL",
    "gn:name":"El Pont\u00f3n-Urarte",
    "gn:population":0,
    "gn:timezone":"Europe/Madrid",
    "iso:country":"ES",
    "wof:name":"El Ponton",
    "wof:placetype":"locality"
},
  "geometry": {"coordinates":[-3.08748,43.17584],"type":"Point"}
}