{
  "type": "Feature",
  "properties": {
    "gn:gn_country":"ES",
    "gn:gn_fcode":"PPL",
    "gn:gn_pop":0,
    "iso:country":"ES",
    "name:bul_x_preferred":[
        "\u0420\u0435\u043e\u043b\u0438\u0434"
    ],
    "name:dut_x_preferred":[
        "Reolid"
    ],
    "name:eng_x_preferred":[
        "Reolid"
    ],
    "name:spa_x_preferred":[
        "Reolid"
    ],
    "name:swe_x_preferred":[
        "Reolid"
    ],
    "qs_pg:aaroncc":"ES",
    "qs_pg:gn_country":"ES",
    "qs_pg:gn_fcode":"PPL",
    "qs_pg:gn_pop":0,
    "qs_pg:name":"Reolid",
    "qs_pg:name_adm0":"Espa\u00f1a",
    "qs_pg:name_adm1":"Castilla-La Mancha",
    "qs_pg:photos_9k":1,
    "qs_pg:photos_9r":3,
    "qs_pg:photos_all":111,
    "qs_pg:photos_sr":0,
    "qs_pg:pop_sr":0,
    "qs_pg:qs_pg_placetype":"locality",
    "qs_pg:qs_pg_placetype_gp":"Town",
    "qs_pg:woe_adm0":23424950,
    "woe:adm0_id":23424950,
    "woe:name_adm0":"Espa\u00f1a",
    "woe:name_adm1":"Castilla-La Mancha",
    "woe:placetype":"Town",
    "wof:name":"Reolid",
    "wof:placetype":"locality"
},
  "geometry": {"coordinates":[-2.56841,38.62126],"type":"Point"}
}