{
  "type": "Feature",
  "properties": {
    "gn:gn_country":"ES",
    "gn:gn_fcode":"PPL",
    "gn:gn_pop":0,
    "iso:country":"ES",
    "name:bpy_x_preferred":[
        "\u09b2\u09be\u099c\u09c7"
    ],
    "name:epo_x_preferred":[
        "Laje"
    ],
    "name:eus_x_preferred":[
        "Laje"
    ],
    "name:fra_x_preferred":[
        "Laje"
    ],
    "name:hye_x_preferred":[
        "\u053c\u0561\u056a\u056b"
    ],
    "name:ita_x_preferred":[
        "Laje"
    ],
    "name:kat_x_preferred":[
        "\u10da\u10d0\u10df\u10d8"
    ],
    "name:kaz_x_preferred":[
        "\u041b\u0430\u0436\u0438"
    ],
    "name:mlg_x_preferred":[
        "Laje"
    ],
    "name:nld_x_preferred":[
        "Laje"
    ],
    "name:nor_x_preferred":[
        "Laje"
    ],
    "name:pol_x_preferred":[
        "Laje"
    ],
    "name:por_x_preferred":[
        "Laje"
    ],
    "name:ron_x_preferred":[
        "Laje"
    ],
    "name:rus_x_preferred":[
        "\u041b\u0430\u0436\u0438"
    ],
    "name:unk_x_variant":[
        "Santiago"
    ],
    "name:urd_x_preferred":[
        "\u0644\u0627\u062e\u06cc"
    ],
    "name:vie_x_preferred":[
        "Laje"
    ],
    "name:vol_x_preferred":[
        "Laje"
    ],
    "name:war_x_preferred":[
        "Laje"
    ],
    "qs_pg:aaroncc":"ES",
    "qs_pg:gn_country":"ES",
    "qs_pg:gn_fcode":"PPL",
    "qs_pg:gn_pop":0,
    "qs_pg:name":"Laje",
    "qs_pg:name_adm0":"Espa\u00f1a",
    "qs_pg:name_adm1":"Galicia",
    "qs_pg:photos":60,
    "qs_pg:photos_1k":12,
    "qs_pg:photos_9k":1,
    "qs_pg:photos_9r":2,
    "qs_pg:photos_all":60,
    "qs_pg:photos_sr":2,
    "qs_pg:pop_sr":0,
    "qs_pg:qs_pg_placetype":"locality",
    "qs_pg:qs_pg_placetype_gp":"Town",
    "qs_pg:woe_adm0":23424950,
    "woe:adm0_id":23424950,
    "woe:name_adm0":"Espa\u00f1a",
    "woe:name_adm1":"Galicia",
    "woe:placetype":"Town",
    "wof:name":"Laje",
    "wof:placetype":"locality"
},
  "geometry": {"coordinates":[-7.56667,42.78333],"type":"Point"}
}