{
  "type": "Feature",
  "properties": {
    "gn:admin1_code":"55",
    "gn:admin2_code":"LE",
    "gn:admin3_code":"24214",
    "gn:asciiname":"Castrillo de Cepeda",
    "gn:country_code":"ES",
    "gn:dem":925,
    "gn:feature_class":"P",
    "gn:feature_code":"PPL",
    "gn:name":"Castrillo de Cepeda",
    "gn:population":0,
    "gn:timezone":"Europe/Madrid",
    "iso:country":"ES",
    "wof:name":"Castrillo de Cepeda",
    "wof:placetype":"locality"
},
  "geometry": {"coordinates":[-6.01743,42.58306],"type":"Point"}
}