{
  "type": "Feature",
  "properties": {
    "gn:admin1_code":"55",
    "gn:admin2_code":"LE",
    "gn:admin3_code":"24152",
    "gn:asciiname":"Pedredo",
    "gn:country_code":"ES",
    "gn:dem":968,
    "gn:feature_class":"P",
    "gn:feature_code":"PPL",
    "gn:name":"Pedredo",
    "gn:population":0,
    "gn:timezone":"Europe/Madrid",
    "iso:country":"ES",
    "wof:name":"Pedredo",
    "wof:placetype":"locality"
},
  "geometry": {"coordinates":[-6.20109,42.44635],"type":"Point"}
}