{
  "type": "Feature",
  "properties": {
    "gn:gn_country":"ES",
    "gn:gn_fcode":"PPLA3",
    "gn:gn_pop":5711,
    "gn:population":5711,
    "iso:country":"ES",
    "name:ara_x_preferred":[
        "\u0623\u0628\u064a\u063a\u0648\u0646\u062f\u0648"
    ],
    "name:bre_x_preferred":[
        "Abegondo"
    ],
    "name:cat_x_preferred":[
        "Abegondo"
    ],
    "name:deu_x_preferred":[
        "Abegondo"
    ],
    "name:eng_x_preferred":[
        "Abegondo"
    ],
    "name:est_x_preferred":[
        "Abegondo vald"
    ],
    "name:eus_x_preferred":[
        "Abegondo"
    ],
    "name:fas_x_preferred":[
        "\u0627\u0628\u06af\u0648\u0646\u062f\u0627"
    ],
    "name:fra_x_preferred":[
        "Abegondo"
    ],
    "name:glg_x_preferred":[
        "Abegondo"
    ],
    "name:hun_x_preferred":[
        "Abegondo"
    ],
    "name:hye_x_preferred":[
        "\u0531\u0562\u0565\u0563\u0578\u0576\u0564\u0578"
    ],
    "name:ita_x_preferred":[
        "Abegondo"
    ],
    "name:jpn_x_preferred":[
        "\u30a2\u30d9\u30b4\u30f3\u30c9"
    ],
    "name:lit_x_preferred":[
        "Abegondas"
    ],
    "name:lmo_x_preferred":[
        "Abegondo"
    ],
    "name:mkd_x_preferred":[
        "\u0410\u0431\u0435\u0433\u043e\u043d\u0434\u043e"
    ],
    "name:msa_x_preferred":[
        "Abegondo"
    ],
    "name:nan_x_preferred":[
        "Abegondo"
    ],
    "name:nld_x_preferred":[
        "Abegondo"
    ],
    "name:oci_x_preferred":[
        "Abegondo"
    ],
    "name:pam_x_preferred":[
        "Abegondo"
    ],
    "name:pol_x_preferred":[
        "Abegondo"
    ],
    "name:por_x_preferred":[
        "Abegondo"
    ],
    "name:rup_x_preferred":[
        "Abegondo"
    ],
    "name:rus_x_preferred":[
        "\u0410\u0431\u0435\u0433\u043e\u043d\u0434\u043e"
    ],
    "name:spa_x_preferred":[
        "Abegondo"
    ],
    "name:sqi_x_preferred":[
        "Abegondo"
    ],
    "name:swe_x_preferred":[
        "Abegondo"
    ],
    "name:tur_x_preferred":[
        "Abegondo"
    ],
    "name:ukr_x_preferred":[
        "\u0410\u0431\u0435\u0433\u043e\u043d\u0434\u043e"
    ],
    "name:unk_x_variant":[
        "Santa Eulalia"
    ],
    "name:uzb_x_preferred":[
        "Abegondo"
    ],
    "name:vie_x_preferred":[
        "Abegondo"
    ],
    "name:war_x_preferred":[
        "Abegondo"
    ],
    "name:zho_x_preferred":[
        "\u963f\u97e6\u8d21\u591a"
    ],
    "qs_pg:aaroncc":"ES",
    "qs_pg:gn_country":"ES",
    "qs_pg:gn_fcode":"PPLA3",
    "qs_pg:gn_pop":5711,
    "qs_pg:name":"Abegondo",
    "qs_pg:name_adm0":"Espa\u00f1a",
    "qs_pg:name_adm1":"Galicia",
    "qs_pg:photos":46,
    "qs_pg:photos_1k":9,
    "qs_pg:photos_9k":1,
    "qs_pg:photos_9r":2,
    "qs_pg:photos_all":46,
    "qs_pg:photos_sr":2,
    "qs_pg:pop_sr":5,
    "qs_pg:qs_pg_placetype":"locality",
    "qs_pg:qs_pg_placetype_gp":"Town",
    "qs_pg:woe_adm0":23424950,
    "woe:adm0_id":23424950,
    "woe:name_adm0":"Espa\u00f1a",
    "woe:name_adm1":"Galicia",
    "woe:placetype":"Town",
    "wof:name":"Abegondo",
    "wof:placetype":"locality",
    "wof:population":5711
},
  "geometry": {"coordinates":[-8.28333,43.21667],"type":"Point"}
}