{
  "type": "Feature",
  "properties": {
    "iso:country":"ES",
    "wof:name":"La Plata",
    "wof:placetype":"neighbourhood"
},
  "geometry": {"coordinates":[-5.94827099651869,37.36963199327861],"type":"Point"}
}