{
  "type": "Feature",
  "properties": {
    "gn:admin1_code":"59",
    "gn:admin2_code":"VI",
    "gn:admin3_code":"01032",
    "gn:asciiname":"Binasperi / Vinaspre",
    "gn:country_code":"ES",
    "gn:dem":607,
    "gn:feature_class":"P",
    "gn:feature_code":"PPL",
    "gn:name":"Binasperi / Vi\u00f1aspre",
    "gn:population":0,
    "gn:timezone":"Europe/Madrid",
    "iso:country":"ES",
    "name:eus_x_preferred":[
        "Binasperi"
    ],
    "name:spa_x_preferred":[
        "Vi\u00f1aspre"
    ],
    "wof:name":"Binasperi / Vinaspre",
    "wof:placetype":"locality"
},
  "geometry": {"coordinates":[-2.49548,42.57678],"type":"Point"}
}