{
  "type": "Feature",
  "properties": {
    "gn:admin1_code":"51",
    "gn:admin2_code":"AL",
    "gn:admin3_code":"4902.0",
    "gn:asciiname":"Santa Maria del Aguila",
    "gn:country_code":"ES",
    "gn:dem":80,
    "gn:feature_class":"P",
    "gn:feature_code":"PPL",
    "gn:name":"Santa Maria del Aguila",
    "gn:population":0,
    "gn:timezone":"Europe/Madrid",
    "iso:country":"ES",
    "wof:name":"Santa Maria del Aguila",
    "wof:placetype":"locality"
},
  "geometry": {"coordinates":[-2.77508,36.78413],"type":"Point"}
}