{
  "type": "Feature",
  "properties": {
    "gn:admin1_code":"39",
    "gn:admin2_code":"S",
    "gn:admin3_code":"39092",
    "gn:asciiname":"La Haya",
    "gn:country_code":"ES",
    "gn:dem":996,
    "gn:feature_class":"P",
    "gn:feature_code":"PPL",
    "gn:name":"La Haya",
    "gn:population":0,
    "gn:timezone":"Europe/Madrid",
    "iso:country":"ES",
    "wof:name":"La Haya",
    "wof:placetype":"locality"
},
  "geometry": {"coordinates":[-4.15653,42.9089],"type":"Point"}
}