{
  "type": "Feature",
  "properties": {
    "gn:admin1_code":"55",
    "gn:admin2_code":"LE",
    "gn:admin3_code":"24158",
    "gn:asciiname":"Riocastrillo de Ordas",
    "gn:country_code":"ES",
    "gn:dem":1021,
    "gn:feature_class":"P",
    "gn:feature_code":"PPL",
    "gn:name":"R\u00edocastrillo de Ord\u00e1s",
    "gn:population":0,
    "gn:timezone":"Europe/Madrid",
    "iso:country":"ES",
    "name:und_x_variant":[
        "R\u00edocastrillo de Ord\u00e1s"
    ],
    "wof:name":"Riocastrillo de Ordas",
    "wof:placetype":"locality"
},
  "geometry": {"coordinates":[-5.85685,42.74442],"type":"Point"}
}