{
  "type": "Feature",
  "properties": {
    "gn:admin1_code":"55",
    "gn:admin2_code":"ZA",
    "gn:admin3_code":"49134",
    "gn:asciiname":"Gramedo",
    "gn:country_code":"ES",
    "gn:dem":940,
    "gn:feature_class":"P",
    "gn:feature_code":"PPL",
    "gn:name":"Gramedo",
    "gn:population":0,
    "gn:timezone":"Europe/Madrid",
    "iso:country":"ES",
    "wof:name":"Gramedo",
    "wof:placetype":"locality"
},
  "geometry": {"coordinates":[-6.36039,42.10692],"type":"Point"}
}