{
  "type": "Feature",
  "properties": {
    "gn:admin1_code":"58",
    "gn:admin2_code":"C",
    "gn:admin3_code":"15083",
    "gn:asciiname":"Vilouriz",
    "gn:country_code":"ES",
    "gn:dem":579,
    "gn:feature_class":"P",
    "gn:feature_code":"PPL",
    "gn:name":"Vilouriz",
    "gn:population":0,
    "gn:timezone":"Europe/Madrid",
    "iso:country":"ES",
    "wof:name":"Vilouriz",
    "wof:placetype":"locality"
},
  "geometry": {"coordinates":[-7.93281,42.94239],"type":"Point"}
}