{
  "type": "Feature",
  "properties": {
    "gn:country":"ES",
    "gn:fcode":"PPLA3",
    "gn:population":136,
    "iso:country":"ES",
    "name:arg_x_preferred":[
        "Zamarra"
    ],
    "name:ast_x_preferred":[
        "Zamarru"
    ],
    "name:cat_x_preferred":[
        "Zamarra"
    ],
    "name:ceb_x_preferred":[
        "Zamarra"
    ],
    "name:deu_x_preferred":[
        "Zamarra"
    ],
    "name:eng_x_preferred":[
        "Zamarra"
    ],
    "name:eus_x_preferred":[
        "Zamarra"
    ],
    "name:fra_x_preferred":[
        "Zamarra"
    ],
    "name:haw_x_preferred":[
        "Zamarra"
    ],
    "name:hun_x_preferred":[
        "Zamarra"
    ],
    "name:ina_x_preferred":[
        "Zamarra"
    ],
    "name:ita_x_preferred":[
        "Zamarra"
    ],
    "name:kaz_x_preferred":[
        "\u0421\u0430\u043c\u0430\u0440\u0440\u0430"
    ],
    "name:msa_x_preferred":[
        "Zamarra"
    ],
    "name:nan_x_preferred":[
        "Zamarra"
    ],
    "name:nld_x_preferred":[
        "Zamarra"
    ],
    "name:oci_x_preferred":[
        "Zamarra"
    ],
    "name:pol_x_preferred":[
        "Zamarra"
    ],
    "name:por_x_preferred":[
        "Samarra"
    ],
    "name:por_x_variant":[
        "Zamarra"
    ],
    "name:rus_x_preferred":[
        "\u0421\u0430\u043c\u0430\u0440\u0440\u0430"
    ],
    "name:spa_x_preferred":[
        "Zamarra"
    ],
    "name:swe_x_preferred":[
        "Zamarra"
    ],
    "name:ukr_x_preferred":[
        "\u0421\u0430\u043c\u0430\u0440\u0440\u0430"
    ],
    "name:vie_x_preferred":[
        "Zamarra"
    ],
    "name:war_x_preferred":[
        "Zamarra"
    ],
    "name:zho_x_preferred":[
        "\u8428\u9a6c\u62c9"
    ],
    "qs_pg:aaroncc":"ES",
    "qs_pg:gn_country":"ES",
    "qs_pg:gn_fcode":"PPLA3",
    "qs_pg:gn_pop":136,
    "qs_pg:name":"Zamarra",
    "qs_pg:name_adm0":"Espa\u00f1a",
    "qs_pg:name_adm1":"Castilla y Le\u00f3n",
    "qs_pg:photos_9r":0,
    "qs_pg:photos_sr":0,
    "qs_pg:pop_sr":1,
    "qs_pg:qs_pg_placetype":"locality",
    "qs_pg:qs_pg_placetype_gp":"Town",
    "qs_pg:woe_adm0":23424950,
    "woe:adm0_id":23424950,
    "woe:name_adm0":"Espa\u00f1a",
    "woe:name_adm1":"Castilla y Le\u00f3n",
    "woe:placetype":"Town",
    "wof:name":"Zamarra",
    "wof:placetype":"locality",
    "wof:population":136
},
  "geometry": {"coordinates":[-6.45248,40.51893],"type":"Point"}
}