{
  "type": "Feature",
  "properties": {
    "gn:gn_country":"ES",
    "gn:gn_fcode":"PPLA3",
    "gn:gn_pop":221,
    "gn:population":221,
    "iso:country":"ES",
    "name:arg_x_preferred":[
        "Samir de los Ca\u00f1os"
    ],
    "name:cat_x_preferred":[
        "Samir de los Ca\u00f1os"
    ],
    "name:eng_x_preferred":[
        "Samir de los Ca\u00f1os"
    ],
    "name:eus_x_preferred":[
        "Samir de los Ca\u00f1os"
    ],
    "name:fra_x_preferred":[
        "Samir de los Ca\u00f1os"
    ],
    "name:haw_x_preferred":[
        "Samir de los Ca\u00f1os"
    ],
    "name:hun_x_preferred":[
        "Samir de los Ca\u00f1os"
    ],
    "name:ile_x_preferred":[
        "Samir de los Ca\u00f1os"
    ],
    "name:ina_x_preferred":[
        "Samir de los Ca\u00f1os"
    ],
    "name:ita_x_preferred":[
        "Samir de los Ca\u00f1os"
    ],
    "name:msa_x_preferred":[
        "Samir de los Ca\u00f1os"
    ],
    "name:nan_x_preferred":[
        "Samir de los Ca\u00f1os"
    ],
    "name:nld_x_preferred":[
        "Samir de los Ca\u00f1os"
    ],
    "name:oci_x_preferred":[
        "Samir de los Ca\u00f1os"
    ],
    "name:pol_x_preferred":[
        "Samir de los Ca\u00f1os"
    ],
    "name:por_x_preferred":[
        "Samir de los Ca\u00f1os"
    ],
    "name:rus_x_preferred":[
        "\u0421\u0430\u043c\u0438\u0440-\u0434\u0435-\u043b\u043e\u0441-\u041a\u0430\u043d\u044c\u043e\u0441"
    ],
    "name:spa_x_preferred":[
        "Samir de los Ca\u00f1os"
    ],
    "name:swe_x_preferred":[
        "Samir de los Ca\u00f1os"
    ],
    "name:ukr_x_preferred":[
        "\u0421\u0430\u043c\u0456\u0440-\u0434\u0435-\u043b\u043e\u0441-\u041a\u0430\u043d\u044c\u0439\u043e\u0441"
    ],
    "name:unk_x_variant":[
        "Samir de los Ca\u00f1os"
    ],
    "name:vie_x_preferred":[
        "Samir de los Ca\u00f1os"
    ],
    "name:war_x_preferred":[
        "Samir de los Ca\u00f1os"
    ],
    "name:zho_x_preferred":[
        "\u8428\u7c73\u5c14\u5fb7\u6d1b\u65af\u5361\u5c3c\u5965\u65af"
    ],
    "qs_pg:aaroncc":"ES",
    "qs_pg:gn_country":"ES",
    "qs_pg:gn_fcode":"PPLA3",
    "qs_pg:gn_pop":221,
    "qs_pg:name":"Samir de Los Ca\u00f1os",
    "qs_pg:name_adm0":"Espa\u00f1a",
    "qs_pg:name_adm1":"Castilla y Le\u00f3n",
    "qs_pg:photos":8,
    "qs_pg:photos_1k":2,
    "qs_pg:photos_9k":1,
    "qs_pg:photos_9r":1,
    "qs_pg:photos_all":8,
    "qs_pg:photos_sr":1,
    "qs_pg:pop_sr":2,
    "qs_pg:qs_pg_placetype":"locality",
    "qs_pg:qs_pg_placetype_gp":"Town",
    "qs_pg:woe_adm0":23424950,
    "woe:adm0_id":23424950,
    "woe:name_adm0":"Espa\u00f1a",
    "woe:name_adm1":"Castilla y Le\u00f3n",
    "woe:placetype":"Town",
    "wof:name":"Samir de Los Ca\u00f1os",
    "wof:placetype":"locality",
    "wof:population":221
},
  "geometry": {"coordinates":[-6.16415,41.6728],"type":"Point"}
}