{
  "type": "Feature",
  "properties": {
    "gn:admin1_code":"32",
    "gn:admin3_code":"31236",
    "gn:asciiname":"Larrainzar",
    "gn:country_code":"ES",
    "gn:dem":555,
    "gn:feature_class":"P",
    "gn:feature_code":"PPL",
    "gn:name":"Larr\u00e1inzar",
    "gn:population":0,
    "gn:timezone":"Europe/Madrid",
    "iso:country":"ES",
    "wof:name":"Larrainzar",
    "wof:placetype":"locality"
},
  "geometry": {"coordinates":[-1.69626,42.97826],"type":"Point"}
}