{
  "type": "Feature",
  "properties": {
    "gn:admin1_code":"32",
    "gn:admin3_code":"31101",
    "gn:asciiname":"Olabe",
    "gn:country_code":"ES",
    "gn:dem":490,
    "gn:feature_class":"P",
    "gn:feature_code":"PPL",
    "gn:name":"Olabe",
    "gn:population":0,
    "gn:timezone":"Europe/Madrid",
    "iso:country":"ES",
    "name:eus_x_preferred":[
        "Olabe"
    ],
    "name:spa_x_preferred":[
        "Olave"
    ],
    "wof:name":"Olabe",
    "wof:placetype":"locality"
},
  "geometry": {"coordinates":[-1.60263,42.88464000000001],"type":"Point"}
}