{
  "type": "Feature",
  "properties": {
    "gn:admin1_code":"58",
    "gn:admin2_code":"OR",
    "gn:admin3_code":"32029",
    "gn:asciiname":"Cadelina",
    "gn:country_code":"ES",
    "gn:dem":1077,
    "gn:feature_class":"P",
    "gn:feature_code":"PPL",
    "gn:name":"Cadeli\u00f1a",
    "gn:population":0,
    "gn:timezone":"Europe/Madrid",
    "iso:country":"ES",
    "name:und_x_variant":[
        "Cadeli\u00f1a"
    ],
    "wof:name":"Cadelina",
    "wof:placetype":"locality"
},
  "geometry": {"coordinates":[-7.41667,42.28333],"type":"Point"}
}