{
  "type": "Feature",
  "properties": {
    "gn:gn_country":"ES",
    "gn:gn_fcode":"PPLA3",
    "gn:gn_pop":145,
    "gn:population":145,
    "iso:country":"ES",
    "name:ara_x_preferred":[
        "\u0641\u064a\u0627\u0631 \u062f\u064a \u0644\u0648\u0633 \u0646\u0627\u0641\u0627\u0631\u0648\u0633"
    ],
    "name:arg_x_preferred":[
        "Villar de los Navarros"
    ],
    "name:cat_x_preferred":[
        "Villar de los Navarros"
    ],
    "name:eng_x_preferred":[
        "Villar de los Navarros"
    ],
    "name:eus_x_preferred":[
        "Villar de los Navarros"
    ],
    "name:fra_x_preferred":[
        "Villar de los Navarros"
    ],
    "name:hun_x_preferred":[
        "Villar de los Navarros"
    ],
    "name:hye_x_preferred":[
        "\u054e\u056b\u056c\u0575\u0561\u0580 \u0564\u0565 \u056c\u0578\u057d \u0546\u0561\u057e\u0561\u057c\u0578\u057d"
    ],
    "name:ita_x_preferred":[
        "Villar de los Navarros"
    ],
    "name:kaz_x_preferred":[
        "\u0412\u0438\u043b\u044c\u044f\u0440-\u0434\u0435-\u043b\u043e\u0441-\u041d\u0430\u0432\u0430\u0440\u0440\u043e\u0441"
    ],
    "name:msa_x_preferred":[
        "Villar de los Navarros"
    ],
    "name:nan_x_preferred":[
        "Villar de los Navarros"
    ],
    "name:nld_x_preferred":[
        "Villar de los Navarros"
    ],
    "name:oci_x_preferred":[
        "Villar de los Navarros"
    ],
    "name:pol_x_preferred":[
        "Villar de los Navarros"
    ],
    "name:por_x_preferred":[
        "Villar de los Navarros"
    ],
    "name:rus_x_preferred":[
        "\u0412\u0438\u043b\u044c\u044f\u0440-\u0434\u0435-\u043b\u043e\u0441-\u041d\u0430\u0432\u0430\u0440\u0440\u043e\u0441"
    ],
    "name:spa_x_preferred":[
        "Villar de los Navarros"
    ],
    "name:swe_x_preferred":[
        "Villar de los Navarros"
    ],
    "name:ukr_x_preferred":[
        "\u0412\u0456\u043b\u044c\u044f\u0440-\u0434\u0435-\u043b\u043e\u0441-\u041d\u0430\u0432\u0430\u0440\u0440\u043e\u0441"
    ],
    "name:unk_x_variant":[
        "Villar de los Navarros"
    ],
    "name:uzb_x_preferred":[
        "Villar de los Navarros"
    ],
    "name:vie_x_preferred":[
        "Villar de los Navarros"
    ],
    "name:war_x_preferred":[
        "Villar de los Navarros"
    ],
    "name:zho_x_preferred":[
        "\u7eb3\u74e6\u7f57\u65af\u6751"
    ],
    "qs_pg:aaroncc":"ES",
    "qs_pg:gn_country":"ES",
    "qs_pg:gn_fcode":"PPLA3",
    "qs_pg:gn_pop":145,
    "qs_pg:name":"Villar de Los Navarros",
    "qs_pg:name_adm0":"Espa\u00f1a",
    "qs_pg:name_adm1":"Arag\u00f3n",
    "qs_pg:photos_9r":0,
    "qs_pg:photos_sr":0,
    "qs_pg:pop_sr":1,
    "qs_pg:qs_pg_placetype":"locality",
    "qs_pg:qs_pg_placetype_gp":"Town",
    "qs_pg:woe_adm0":23424950,
    "woe:adm0_id":23424950,
    "woe:name_adm0":"Espa\u00f1a",
    "woe:name_adm1":"Arag\u00f3n",
    "woe:placetype":"Town",
    "wof:name":"Villar de Los Navarros",
    "wof:placetype":"locality",
    "wof:population":145
},
  "geometry": {"coordinates":[-1.04199,41.15949],"type":"Point"}
}