{
  "type": "Feature",
  "properties": {
    "gn:admin1_code":"54",
    "gn:admin2_code":"CU",
    "gn:admin3_code":"16909",
    "gn:asciiname":"Sotos",
    "gn:country_code":"ES",
    "gn:dem":990,
    "gn:feature_class":"P",
    "gn:feature_code":"PPL",
    "gn:name":"Sotos",
    "gn:population":0,
    "gn:timezone":"Europe/Madrid",
    "iso:country":"ES",
    "wof:name":"Sotos",
    "wof:placetype":"locality"
},
  "geometry": {"coordinates":[-2.16456,40.19498],"type":"Point"}
}