{
  "type": "Feature",
  "properties": {
    "gn:admin1_code":"52",
    "gn:admin2_code":"HU",
    "gn:admin3_code":"22107",
    "gn:asciiname":"Buisan",
    "gn:country_code":"ES",
    "gn:dem":1266,
    "gn:feature_class":"P",
    "gn:feature_code":"PPL",
    "gn:name":"Buis\u00e1n",
    "gn:population":0,
    "gn:timezone":"Europe/Madrid",
    "iso:country":"ES",
    "name:und_x_variant":[
        "Buis\u00e1n"
    ],
    "wof:name":"Buisan",
    "wof:placetype":"locality"
},
  "geometry": {"coordinates":[-0.00937,42.58116],"type":"Point"}
}