{
  "type": "Feature",
  "properties": {
    "gn:admin1_code":"51",
    "gn:admin2_code":"SE",
    "gn:admin3_code":"41101",
    "gn:asciiname":"Mesa Redonda",
    "gn:cc2":"ES",
    "gn:country_code":"ES",
    "gn:dem":53,
    "gn:feature_class":"P",
    "gn:feature_code":"PPL",
    "gn:name":"Mesa Redonda",
    "gn:population":0,
    "gn:timezone":"Europe/Madrid",
    "iso:country":"ES",
    "name:und_x_variant":[
        "Caser\u00edos Mesa Redonda",
        "Mesa Redonda"
    ],
    "wof:name":"Mesa Redonda",
    "wof:placetype":"locality"
},
  "geometry": {"coordinates":[-5.88333,37.61667],"type":"Point"}
}