{
  "type": "Feature",
  "properties": {
    "gn:admin1_code":"52",
    "gn:admin2_code":"HU",
    "gn:admin3_code":"22035",
    "gn:asciiname":"Berganui",
    "gn:country_code":"ES",
    "gn:dem":865,
    "gn:feature_class":"P",
    "gn:feature_code":"PPL",
    "gn:name":"Berganui",
    "gn:population":0,
    "gn:timezone":"Europe/Madrid",
    "iso:country":"ES",
    "name:cat_x_preferred":[
        "Berganui"
    ],
    "wof:name":"Berganui",
    "wof:placetype":"locality"
},
  "geometry": {"coordinates":[0.68188,42.25635],"type":"Point"}
}