{
  "type": "Feature",
  "properties": {
    "gn:admin1_code":"59",
    "gn:admin2_code":"BI",
    "gn:admin3_code":"48049",
    "gn:asciiname":"Curchiaga",
    "gn:country_code":"ES",
    "gn:dem":14,
    "gn:feature_class":"P",
    "gn:feature_code":"PPL",
    "gn:name":"Kurtziaga",
    "gn:population":0,
    "gn:timezone":"Europe/Madrid",
    "iso:country":"ES",
    "wof:name":"Curchiaga",
    "wof:placetype":"locality"
},
  "geometry": {"coordinates":[-2.5045,43.35071],"type":"Point"}
}