{
  "type": "Feature",
  "properties": {
    "gn:admin1_code":"51",
    "gn:admin2_code":"AL",
    "gn:admin3_code":"04036",
    "gn:asciiname":"El Soto",
    "gn:cc2":"ES",
    "gn:country_code":"ES",
    "gn:dem":888,
    "gn:feature_class":"P",
    "gn:feature_code":"PPL",
    "gn:name":"El Soto",
    "gn:population":0,
    "gn:timezone":"Europe/Madrid",
    "iso:country":"ES",
    "name:und_x_variant":[
        "Cortijada El Soto",
        "El Soto"
    ],
    "wof:name":"El Soto",
    "wof:placetype":"locality"
},
  "geometry": {"coordinates":[-2.25,37.26667],"type":"Point"}
}