{
  "type": "Feature",
  "properties": {
    "gn:admin1_code":"34",
    "gn:admin2_code":"O",
    "gn:admin3_code":"33046",
    "gn:asciiname":"Trescares",
    "gn:country_code":"ES",
    "gn:dem":110,
    "gn:feature_class":"P",
    "gn:feature_code":"PPL",
    "gn:name":"Trescares",
    "gn:population":0,
    "gn:timezone":"Europe/Madrid",
    "iso:country":"ES",
    "name:ast_x_preferred":[
        "Trescares"
    ],
    "name:spa_x_preferred":[
        "Trescares"
    ],
    "wof:name":"Trescares",
    "wof:placetype":"locality"
},
  "geometry": {"coordinates":[-4.7091,43.31868],"type":"Point"}
}