{
  "type": "Feature",
  "properties": {
    "gn:country":"ES",
    "gn:fcode":"PPL",
    "gn:population":784,
    "iso:country":"ES",
    "name:arg_x_preferred":[
        "Benicull de X\u00faquer"
    ],
    "name:cat_x_preferred":[
        "Benicull de X\u00faquer"
    ],
    "name:che_x_preferred":[
        "\u0411\u0435\u043d\u0438\u043a\u0443\u043b\u044c"
    ],
    "name:eng_x_preferred":[
        "Benicull de X\u00faquer"
    ],
    "name:eus_x_preferred":[
        "Benicull de X\u00faquer"
    ],
    "name:fra_x_preferred":[
        "Benicull de X\u00faquer"
    ],
    "name:ile_x_preferred":[
        "Benicull"
    ],
    "name:ita_x_preferred":[
        "Benicull de X\u00faquer"
    ],
    "name:kat_x_preferred":[
        "\u10d1\u10d4\u10dc\u10d8\u10d9\u10e3\u10da\u10d8"
    ],
    "name:msa_x_preferred":[
        "Benicull de X\u00faquer"
    ],
    "name:nan_x_preferred":[
        "Benicull de X\u00faquer"
    ],
    "name:nld_x_preferred":[
        "Benicull de X\u00faquer"
    ],
    "name:nob_x_preferred":[
        "Benicull"
    ],
    "name:oci_x_preferred":[
        "Benicull de X\u00faquer"
    ],
    "name:pol_x_preferred":[
        "Benicull de X\u00faquer"
    ],
    "name:rus_x_preferred":[
        "\u0411\u0435\u043d\u0438\u043a\u0443\u043b\u044c"
    ],
    "name:spa_x_preferred":[
        "Benicull"
    ],
    "name:sqi_x_preferred":[
        "Benicull de X\u00faquer"
    ],
    "name:swe_x_preferred":[
        "Benicull de X\u00faquer"
    ],
    "name:tat_x_preferred":[
        "\u0411\u0435\u043d\u0438\u043a\u0443\u043b\u044c"
    ],
    "name:ukr_x_preferred":[
        "\u0411\u0435\u043d\u0456\u043a\u0443\u043b\u044c-\u0434\u0435-\u0428\u0443\u043a\u0435\u0440"
    ],
    "name:und_x_variant":[
        "Barrio Benicull"
    ],
    "name:vie_x_preferred":[
        "Benicull de X\u00faquer"
    ],
    "name:zho_x_preferred":[
        "\u8d1d\u5c3c\u5e93\u5229\u5fb7\u514b\u82cf\u514b\u5c14"
    ],
    "qs_pg:aaroncc":"ES",
    "qs_pg:gn_country":"ES",
    "qs_pg:gn_fcode":"PPL",
    "qs_pg:gn_pop":784,
    "qs_pg:name":"Benicull de X\u00faquer",
    "qs_pg:name_adm0":"Espa\u00f1a",
    "qs_pg:name_adm1":"Comunitat Valenciana",
    "qs_pg:photos_9r":0,
    "qs_pg:photos_sr":0,
    "qs_pg:pop_sr":2,
    "qs_pg:qs_pg_placetype":"locality",
    "qs_pg:qs_pg_placetype_gp":"Town",
    "qs_pg:woe_adm0":23424950,
    "woe:adm0_id":23424950,
    "woe:name_adm0":"Espa\u00f1a",
    "woe:name_adm1":"Comunitat Valenciana",
    "woe:placetype":"Town",
    "wof:name":"Benicull de X\u00faquer",
    "wof:placetype":"locality",
    "wof:population":784
},
  "geometry": {"coordinates":[-0.38333,39.18333],"type":"Point"}
}