{
  "type": "Feature",
  "properties": {
    "gn:admin1_code":"51",
    "gn:admin2_code":"AL",
    "gn:admin3_code":"04068",
    "gn:asciiname":"El Tallon Bajo",
    "gn:country_code":"ES",
    "gn:dem":973,
    "gn:feature_class":"P",
    "gn:feature_code":"PPL",
    "gn:name":"El Tall\u00f3n Bajo",
    "gn:population":0,
    "gn:timezone":"Europe/Madrid",
    "iso:country":"ES",
    "name:und_x_variant":[
        "Caser\u00edo Tall\u00f3n Bajo",
        "El Tall\u00f3n Bajo"
    ],
    "wof:name":"El Tallon Bajo",
    "wof:placetype":"locality"
},
  "geometry": {"coordinates":[-2.49051,37.16607],"type":"Point"}
}