{
  "type": "Feature",
  "properties": {
    "gn:admin1_code":"58",
    "gn:admin2_code":"C",
    "gn:admin3_code":"15023",
    "gn:asciiname":"Tedin",
    "gn:country_code":"ES",
    "gn:dem":80,
    "gn:feature_class":"P",
    "gn:feature_code":"PPL",
    "gn:name":"Ted\u00edn",
    "gn:population":0,
    "gn:timezone":"Europe/Madrid",
    "iso:country":"ES",
    "name:und_x_variant":[
        "Tendin",
        "Ted\u00edn"
    ],
    "wof:name":"Tedin",
    "wof:placetype":"locality"
},
  "geometry": {"coordinates":[-9.2395,42.97652],"type":"Point"}
}