{
  "type": "Feature",
  "properties": {
    "gn:admin1_code":"32",
    "gn:admin3_code":"31088",
    "gn:asciiname":"Oriz",
    "gn:country_code":"ES",
    "gn:dem":486,
    "gn:feature_class":"P",
    "gn:feature_code":"PPL",
    "gn:name":"Oriz",
    "gn:population":0,
    "gn:timezone":"Europe/Madrid",
    "iso:country":"ES",
    "wof:name":"Oriz",
    "wof:placetype":"locality"
},
  "geometry": {"coordinates":[-1.61516,42.72552],"type":"Point"}
}