{
  "type": "Feature",
  "properties": {
    "gn:country":"ES",
    "gn:fcode":"PPLA3",
    "gn:population":128,
    "iso:country":"ES",
    "name:ara_x_preferred":[
        "\u0645\u0631\u062c \u062e\u0644\u0641"
    ],
    "name:arg_x_preferred":[
        "Margalef"
    ],
    "name:ast_x_preferred":[
        "Margalef"
    ],
    "name:azb_x_preferred":[
        "\u0645\u0627\u0631\u0642\u0627\u0644\u0641"
    ],
    "name:cat_x_preferred":[
        "Margalef"
    ],
    "name:ceb_x_preferred":[
        "Margalef"
    ],
    "name:deu_x_preferred":[
        "Margalef"
    ],
    "name:eng_x_preferred":[
        "Margalef"
    ],
    "name:eus_x_preferred":[
        "Margalef"
    ],
    "name:fas_x_preferred":[
        "\u0645\u0627\u0631\u06af\u0627\u0644\u0641"
    ],
    "name:fra_x_preferred":[
        "Margalef"
    ],
    "name:glg_x_preferred":[
        "Margalef"
    ],
    "name:hun_x_preferred":[
        "Margalef"
    ],
    "name:hye_x_preferred":[
        "\u0544\u0561\u0580\u0563\u0561\u056c\u0565\u0586"
    ],
    "name:ita_x_preferred":[
        "Margalef"
    ],
    "name:lat_x_preferred":[
        "Margalef"
    ],
    "name:msa_x_preferred":[
        "Margalef"
    ],
    "name:nld_x_preferred":[
        "Margalef"
    ],
    "name:oci_x_preferred":[
        "Margalef"
    ],
    "name:pol_x_preferred":[
        "Margalef"
    ],
    "name:por_x_preferred":[
        "Margalef"
    ],
    "name:rus_x_preferred":[
        "\u041c\u0430\u0440\u0433\u0430\u043b\u0435\u0444"
    ],
    "name:spa_x_preferred":[
        "Margalef de Montsant"
    ],
    "name:sqi_x_preferred":[
        "Margalef"
    ],
    "name:swe_x_preferred":[
        "Margalef"
    ],
    "name:ukr_x_preferred":[
        "\u041c\u0430\u0440\u0491\u0430\u043b\u0435\u0444"
    ],
    "name:uzb_x_preferred":[
        "Margalef de Montsant"
    ],
    "name:war_x_preferred":[
        "Margalef"
    ],
    "name:xmf_x_preferred":[
        "\u10db\u10d0\u10e0\u10d2\u10d0\u10da\u10d4\u10e4\u10d8\u10e8 \u10db\u10e3\u10dc\u10d8\u10ea\u10d8\u10de\u10d0\u10da\u10d8\u10e2\u10d4\u10e2\u10d8"
    ],
    "name:zho_x_preferred":[
        "\u9a6c\u5c14\u52a0\u83b1\u592b"
    ],
    "qs_pg:aaroncc":"ES",
    "qs_pg:gn_country":"ES",
    "qs_pg:gn_fcode":"PPLA3",
    "qs_pg:gn_pop":128,
    "qs_pg:name":"Margalef",
    "qs_pg:name_adm0":"Espa\u00f1a",
    "qs_pg:name_adm1":"Catalunya",
    "qs_pg:photos":191,
    "qs_pg:photos_1k":39,
    "qs_pg:photos_9k":1,
    "qs_pg:photos_9r":4,
    "qs_pg:photos_all":191,
    "qs_pg:photos_sr":4,
    "qs_pg:pop_sr":1,
    "qs_pg:qs_pg_placetype":"locality",
    "qs_pg:qs_pg_placetype_gp":"Town",
    "qs_pg:woe_adm0":23424950,
    "woe:adm0_id":23424950,
    "woe:name_adm0":"Espa\u00f1a",
    "woe:name_adm1":"Catalunya",
    "woe:placetype":"Town",
    "wof:name":"Margalef",
    "wof:placetype":"locality",
    "wof:population":128
},
  "geometry": {"coordinates":[0.75331,41.28496],"type":"Point"}
}