{
  "type": "Feature",
  "properties": {
    "gn:admin1_code":"55",
    "gn:admin2_code":"LE",
    "gn:admin3_code":"24066",
    "gn:asciiname":"Robledo de la Valduerna",
    "gn:country_code":"ES",
    "gn:dem":854,
    "gn:feature_class":"P",
    "gn:feature_code":"PPL",
    "gn:name":"Robledo de la Valduerna",
    "gn:population":0,
    "gn:timezone":"Europe/Madrid",
    "iso:country":"ES",
    "name:und_x_variant":[
        "Robledo",
        "Robledo de la Valduerna"
    ],
    "wof:name":"Robledo de la Valduerna",
    "wof:placetype":"locality"
},
  "geometry": {"coordinates":[-6.05915,42.32779],"type":"Point"}
}