{
  "type": "Feature",
  "properties": {
    "gn:admin1_code":"58",
    "gn:admin2_code":"LU",
    "gn:admin3_code":"27054",
    "gn:asciiname":"Cruz",
    "gn:country_code":"ES",
    "gn:dem":232,
    "gn:feature_class":"P",
    "gn:feature_code":"PPL",
    "gn:name":"Cruz",
    "gn:population":0,
    "gn:timezone":"Europe/Madrid",
    "iso:country":"ES",
    "name:ces_x_preferred":[
        "Cruz"
    ],
    "name:deu_x_preferred":[
        "Cruz"
    ],
    "wof:name":"Cruz",
    "wof:placetype":"locality"
},
  "geometry": {"coordinates":[-7.27144,43.32733],"type":"Point"}
}