{
  "type": "Feature",
  "properties": {
    "gn:population":1498,
    "iso:country":"ES",
    "name:arg_x_preferred":[
        "Antella"
    ],
    "name:ast_x_preferred":[
        "Antella"
    ],
    "name:azb_x_preferred":[
        "\u0622\u0646\u062a\u06cc\u0627"
    ],
    "name:cat_x_preferred":[
        "Antella"
    ],
    "name:ceb_x_preferred":[
        "Antella"
    ],
    "name:deu_x_preferred":[
        "Antella"
    ],
    "name:eng_x_preferred":[
        "Antella"
    ],
    "name:eus_x_preferred":[
        "Antella"
    ],
    "name:fas_x_preferred":[
        "\u0622\u0646\u062a\u06cc\u0627"
    ],
    "name:fra_x_preferred":[
        "Antella"
    ],
    "name:hun_x_preferred":[
        "Antella"
    ],
    "name:ita_x_preferred":[
        "Antella"
    ],
    "name:msa_x_preferred":[
        "Antella"
    ],
    "name:nan_x_preferred":[
        "Antella"
    ],
    "name:nld_x_preferred":[
        "Antella"
    ],
    "name:oci_x_preferred":[
        "Antella"
    ],
    "name:pol_x_preferred":[
        "Antella"
    ],
    "name:por_x_preferred":[
        "Antella"
    ],
    "name:rup_x_preferred":[
        "Antella"
    ],
    "name:rus_x_preferred":[
        "\u0410\u043d\u0442\u0435\u043b\u044c\u044f"
    ],
    "name:spa_x_preferred":[
        "Antella"
    ],
    "name:sqi_x_preferred":[
        "Antella"
    ],
    "name:swe_x_preferred":[
        "Antella"
    ],
    "name:ukr_x_preferred":[
        "\u0410\u043d\u0442\u0435\u043b\u044c\u044f"
    ],
    "name:vie_x_preferred":[
        "Antella"
    ],
    "name:war_x_preferred":[
        "Antella"
    ],
    "name:zho_min_nan_x_preferred":[
        "Antella"
    ],
    "name:zho_x_preferred":[
        "\u5b89\u7279\u5229\u4e9a"
    ],
    "qs:a0":"Espa\u00f1a",
    "qs:a1":"*Valencia/Val\u00e8ncia",
    "qs:a1r":"0Comunidad Valenciana",
    "qs:adm0":"Espa\u00f1a",
    "qs:la_lc":"*",
    "qs:level":"locality",
    "qs:loc":"Antella",
    "qs:loc_alt":"Antella",
    "qs:pop":0,
    "qs:type":"buffered point",
    "wd:wordcount":29,
    "wof:name":"Antella",
    "wof:placetype":"locality",
    "wof:population":1498
},
  "geometry": {"coordinates":[-0.592036,39.080444],"type":"Point"}
}