{
  "type": "Feature",
  "properties": {
    "gn:country":"ES",
    "gn:fcode":"PPL",
    "gn:population":0,
    "iso:country":"ES",
    "name:cat_x_preferred":[
        "Abdet"
    ],
    "name:deu_x_preferred":[
        "Abdet"
    ],
    "name:eng_x_preferred":[
        "Abdet"
    ],
    "name:fra_x_preferred":[
        "Abdet"
    ],
    "name:ita_x_preferred":[
        "Abdet"
    ],
    "name:nld_x_preferred":[
        "Abdet"
    ],
    "name:spa_x_preferred":[
        "Abdet"
    ],
    "name:und_x_variant":[
        "Caser\u00edo Abdet"
    ],
    "qs_pg:aaroncc":"ES",
    "qs_pg:gn_country":"ES",
    "qs_pg:gn_fcode":"PPL",
    "qs_pg:gn_pop":0,
    "qs_pg:name":"l'Abdet",
    "qs_pg:name_adm0":"Espa\u00f1a",
    "qs_pg:name_adm1":"Comunitat Valenciana",
    "qs_pg:photos":68,
    "qs_pg:photos_1k":14,
    "qs_pg:photos_9k":1,
    "qs_pg:photos_9r":2,
    "qs_pg:photos_all":68,
    "qs_pg:photos_sr":2,
    "qs_pg:pop_sr":0,
    "qs_pg:qs_pg_placetype":"locality",
    "qs_pg:qs_pg_placetype_gp":"Town",
    "qs_pg:woe_adm0":23424950,
    "woe:adm0_id":23424950,
    "woe:name_adm0":"Espa\u00f1a",
    "woe:name_adm1":"Comunitat Valenciana",
    "woe:placetype":"Town",
    "wof:name":"l'Abdet",
    "wof:placetype":"locality"
},
  "geometry": {"coordinates":[-0.25726,38.69422],"type":"Point"}
}