{
  "type": "Feature",
  "properties": {
    "gn:country":"ES",
    "gn:fcode":"PPL",
    "gn:population":1008,
    "iso:country":"ES",
    "name:arg_x_preferred":[
        "Riofr\u00edo de Aliste"
    ],
    "name:cat_x_preferred":[
        "Riofr\u00edo de Aliste"
    ],
    "name:deu_x_preferred":[
        "Riofr\u00edo de Aliste"
    ],
    "name:eng_x_preferred":[
        "Riofr\u00edo de Aliste"
    ],
    "name:eus_x_preferred":[
        "Riofr\u00edo de Aliste"
    ],
    "name:fra_x_preferred":[
        "Riofr\u00edo de Aliste"
    ],
    "name:haw_x_preferred":[
        "Riofr\u00edo de Aliste"
    ],
    "name:hun_x_preferred":[
        "Riofr\u00edo de Aliste"
    ],
    "name:ile_x_preferred":[
        "Riofr\u00edo de Aliste"
    ],
    "name:ina_x_preferred":[
        "Riofr\u00edo de Aliste"
    ],
    "name:ita_x_preferred":[
        "Riofr\u00edo de Aliste"
    ],
    "name:msa_x_preferred":[
        "Riofr\u00edo de Aliste"
    ],
    "name:nan_x_preferred":[
        "Riofr\u00edo de Aliste"
    ],
    "name:nld_x_preferred":[
        "Riofr\u00edo de Aliste"
    ],
    "name:oci_x_preferred":[
        "Riofr\u00edo de Aliste"
    ],
    "name:pol_x_preferred":[
        "Riofr\u00edo de Aliste"
    ],
    "name:por_x_preferred":[
        "Riofr\u00edo de Aliste"
    ],
    "name:rus_x_preferred":[
        "\u0420\u0438\u043e\u0444\u0440\u0438\u043e-\u0434\u0435-\u0410\u043b\u0438\u0441\u0442\u0435"
    ],
    "name:spa_x_preferred":[
        "Riofr\u00edo de Aliste"
    ],
    "name:swe_x_preferred":[
        "R\u00edofr\u00edo de Aliste"
    ],
    "name:ukr_x_preferred":[
        "\u0420\u0456\u043e\u0444\u0440\u0456\u043e-\u0434\u0435-\u0410\u043b\u0456\u0441\u0442\u0435"
    ],
    "name:und_x_variant":[
        "Riofrio"
    ],
    "name:vie_x_preferred":[
        "Riofr\u00edo de Aliste"
    ],
    "name:war_x_preferred":[
        "Riofr\u00edo de Aliste"
    ],
    "name:zho_x_preferred":[
        "\u91cc\u5965\u592b\u91cc\u5965\u5fb7\u4e9a\u5229\u65af\u7279"
    ],
    "qs_pg:aaroncc":"ES",
    "qs_pg:gn_country":"ES",
    "qs_pg:gn_fcode":"PPL",
    "qs_pg:gn_pop":1008,
    "qs_pg:name":"R\u00edofr\u00edo de Aliste",
    "qs_pg:photos_9r":0,
    "qs_pg:photos_sr":0,
    "qs_pg:pop_sr":3,
    "qs_pg:qs_pg_placetype":"locality",
    "wof:name":"R\u00edofr\u00edo de Aliste",
    "wof:placetype":"locality",
    "wof:population":1008
},
  "geometry": {"coordinates":[-6.17742,41.81724],"type":"Point"}
}