{
  "type": "Feature",
  "properties": {
    "gn:gn_country":"ES",
    "gn:gn_fcode":"PPL",
    "gn:gn_pop":0,
    "iso:country":"ES",
    "name:ceb_x_preferred":[
        "El Llano"
    ],
    "name:deu_x_preferred":[
        "El Llano"
    ],
    "name:fra_x_preferred":[
        "El Llano"
    ],
    "name:ita_x_preferred":[
        "El Llano"
    ],
    "name:spa_x_preferred":[
        "El Llano"
    ],
    "name:swe_x_preferred":[
        "El Llano"
    ],
    "qs_pg:aaroncc":"ES",
    "qs_pg:gn_country":"ES",
    "qs_pg:gn_fcode":"PPL",
    "qs_pg:gn_pop":0,
    "qs_pg:name":"El Llano",
    "qs_pg:name_adm0":"Espa\u00f1a",
    "qs_pg:name_adm1":"Principado de Asturias",
    "qs_pg:photos":16,
    "qs_pg:photos_1k":3,
    "qs_pg:photos_9k":1,
    "qs_pg:photos_9r":1,
    "qs_pg:photos_all":16,
    "qs_pg:photos_sr":1,
    "qs_pg:pop_sr":0,
    "qs_pg:qs_pg_placetype":"locality",
    "qs_pg:qs_pg_placetype_gp":"Town",
    "qs_pg:woe_adm0":23424950,
    "woe:adm0_id":23424950,
    "woe:name_adm0":"Espa\u00f1a",
    "woe:name_adm1":"Principado de Asturias",
    "woe:placetype":"Town",
    "wof:name":"El Llano",
    "wof:placetype":"locality"
},
  "geometry": {"coordinates":[-5.47651,43.46096],"type":"Point"}
}