{
  "type": "Feature",
  "properties": {
    "gn:country":"ES",
    "gn:fcode":"PPLA3",
    "gn:population":230,
    "iso:country":"ES",
    "name:ara_x_preferred":[
        "\u0628\u0631\u0627\u062f\u0648\u0633\u064a\u063a\u0627\u0631"
    ],
    "name:ast_x_preferred":[
        "Pradosegar"
    ],
    "name:azb_x_preferred":[
        "\u067e\u0631\u0627\u062f\u0633\u0642\u0627\u0631"
    ],
    "name:cat_x_preferred":[
        "Pradosegar"
    ],
    "name:ceb_x_preferred":[
        "Pradosegar"
    ],
    "name:eng_x_preferred":[
        "Pradosegar"
    ],
    "name:eus_x_preferred":[
        "Pradosegar"
    ],
    "name:fas_x_preferred":[
        "\u067e\u0631\u0627\u062f\u0633\u06af\u0627\u0631"
    ],
    "name:fra_x_preferred":[
        "Pradosegar"
    ],
    "name:hun_x_preferred":[
        "Pradosegar"
    ],
    "name:ina_x_preferred":[
        "Pradosegar"
    ],
    "name:ita_x_preferred":[
        "Pradosegar"
    ],
    "name:kaz_x_preferred":[
        "\u041f\u0440\u0430\u0434\u043e\u0441\u0435\u0433\u0430\u0440"
    ],
    "name:mkd_x_preferred":[
        "\u041f\u0440\u0430\u0434\u043e\u0441\u0435\u0433\u0430\u0440"
    ],
    "name:msa_x_preferred":[
        "Pradosegar"
    ],
    "name:nld_x_preferred":[
        "Pradosegar"
    ],
    "name:oci_x_preferred":[
        "Pradosegar"
    ],
    "name:pol_x_preferred":[
        "Pradosegar"
    ],
    "name:por_x_preferred":[
        "Pradosegar"
    ],
    "name:rus_x_preferred":[
        "\u041f\u0440\u0430\u0434\u043e\u0441\u0435\u0433\u0430\u0440"
    ],
    "name:spa_x_preferred":[
        "Pradosegar"
    ],
    "name:swe_x_preferred":[
        "Pradosegar"
    ],
    "name:ukr_x_preferred":[
        "\u041f\u0440\u0430\u0434\u043e\u0441\u0435\u0433\u0430\u0440"
    ],
    "name:uzb_x_preferred":[
        "Pradosegar"
    ],
    "name:vie_x_preferred":[
        "Pradosegar"
    ],
    "name:war_x_preferred":[
        "Pradosegar"
    ],
    "name:zho_x_preferred":[
        "\u666e\u62c9\u591a\u585e\u52a0\u5c14"
    ],
    "qs_pg:aaroncc":"ES",
    "qs_pg:gn_country":"ES",
    "qs_pg:gn_fcode":"PPLA3",
    "qs_pg:gn_pop":230,
    "qs_pg:name":"Pradosegar",
    "qs_pg:name_adm0":"Espa\u00f1a",
    "qs_pg:name_adm1":"Castilla y Le\u00f3n",
    "qs_pg:photos_9r":0,
    "qs_pg:photos_sr":0,
    "qs_pg:pop_sr":2,
    "qs_pg:qs_pg_placetype":"locality",
    "qs_pg:qs_pg_placetype_gp":"Town",
    "qs_pg:woe_adm0":23424950,
    "woe:adm0_id":23424950,
    "woe:name_adm0":"Espa\u00f1a",
    "woe:name_adm1":"Castilla y Le\u00f3n",
    "woe:placetype":"Town",
    "wof:name":"Pradosegar",
    "wof:placetype":"locality",
    "wof:population":230
},
  "geometry": {"coordinates":[-5.07015,40.5502],"type":"Point"}
}