{
  "type": "Feature",
  "properties": {
    "gn:admin1_code":"58",
    "gn:admin2_code":"OR",
    "gn:admin3_code":"32086",
    "gn:asciiname":"Cepedelo",
    "gn:country_code":"ES",
    "gn:dem":1337,
    "gn:feature_class":"P",
    "gn:feature_code":"PPL",
    "gn:name":"Cepedelo",
    "gn:population":0,
    "gn:timezone":"Europe/Madrid",
    "iso:country":"ES",
    "name:und_x_variant":[
        "Santa Mar\u00eda de Cepedelo",
        "Cepedelo"
    ],
    "wof:name":"Cepedelo",
    "wof:placetype":"locality"
},
  "geometry": {"coordinates":[-7.00372,42.12543],"type":"Point"}
}