{
  "type": "Feature",
  "properties": {
    "gn:admin1_code":"55",
    "gn:admin2_code":"AV",
    "gn:admin3_code":"05152",
    "gn:asciiname":"Magazos",
    "gn:country_code":"ES",
    "gn:dem":864,
    "gn:feature_class":"P",
    "gn:feature_code":"PPL",
    "gn:name":"Magazos",
    "gn:population":0,
    "gn:timezone":"Europe/Madrid",
    "iso:country":"ES",
    "wof:name":"Magazos",
    "wof:placetype":"locality"
},
  "geometry": {"coordinates":[-4.80687,41.00403],"type":"Point"}
}