{
  "type": "Feature",
  "properties": {
    "gn:admin1_code":"58",
    "gn:admin2_code":"PO",
    "gn:admin3_code":"36052",
    "gn:asciiname":"Laro",
    "gn:country_code":"ES",
    "gn:dem":457,
    "gn:feature_class":"P",
    "gn:feature_code":"PPL",
    "gn:name":"Laro",
    "gn:population":0,
    "gn:timezone":"Europe/Madrid",
    "iso:country":"ES",
    "wof:name":"Laro",
    "wof:placetype":"locality"
},
  "geometry": {"coordinates":[-8.234,42.62542],"type":"Point"}
}