{
  "type": "Feature",
  "properties": {
    "gn:admin1_code":"55",
    "gn:admin2_code":"AV",
    "gn:admin3_code":"05186",
    "gn:asciiname":"La Almohalla",
    "gn:country_code":"ES",
    "gn:dem":1098,
    "gn:feature_class":"P",
    "gn:feature_code":"PPL",
    "gn:name":"La Almohalla",
    "gn:population":0,
    "gn:timezone":"Europe/Madrid",
    "iso:country":"ES",
    "wof:name":"La Almohalla",
    "wof:placetype":"locality"
},
  "geometry": {"coordinates":[-5.37247,40.4596],"type":"Point"}
}