{
  "type": "Feature",
  "properties": {
    "gn:admin1_code":"58",
    "gn:admin2_code":"C",
    "gn:admin3_code":"15045",
    "gn:asciiname":"Beba",
    "gn:country_code":"ES",
    "gn:dem":315,
    "gn:feature_class":"P",
    "gn:feature_code":"PPL",
    "gn:name":"Beba",
    "gn:population":0,
    "gn:timezone":"Europe/Madrid",
    "iso:country":"ES",
    "name:ceb_x_preferred":[
        "Beba"
    ],
    "name:deu_x_preferred":[
        "Beba"
    ],
    "name:fra_x_preferred":[
        "Beba"
    ],
    "name:glg_x_preferred":[
        "Beba"
    ],
    "name:swe_x_preferred":[
        "Beba"
    ],
    "name:vie_x_preferred":[
        "Beba"
    ],
    "wof:name":"Beba",
    "wof:placetype":"locality"
},
  "geometry": {"coordinates":[-9.00644,42.91278],"type":"Point"}
}