{
  "type": "Feature",
  "properties": {
    "gn:admin1_code":"58",
    "gn:admin2_code":"C",
    "gn:admin3_code":"15093",
    "gn:asciiname":"Muino",
    "gn:cc2":"ES",
    "gn:country_code":"ES",
    "gn:dem":338,
    "gn:feature_class":"P",
    "gn:feature_code":"PPL",
    "gn:name":"Mui\u00f1o",
    "gn:population":0,
    "gn:timezone":"Europe/Madrid",
    "iso:country":"ES",
    "name:und_x_variant":[
        "San Tirso",
        "Mui\u00f1o"
    ],
    "wof:name":"Muino",
    "wof:placetype":"locality"
},
  "geometry": {"coordinates":[-8.95,43.03333],"type":"Point"}
}