{
  "type": "Feature",
  "properties": {
    "gn:admin1_code":"58",
    "gn:admin2_code":"C",
    "gn:admin3_code":"15061",
    "gn:asciiname":"Barbos",
    "gn:cc2":"ES",
    "gn:country_code":"ES",
    "gn:dem":108,
    "gn:feature_class":"P",
    "gn:feature_code":"PPL",
    "gn:name":"Barbos",
    "gn:population":0,
    "gn:timezone":"Europe/Madrid",
    "iso:country":"ES",
    "name:und_x_variant":[
        "San Juli\u00e1n",
        "Barbos"
    ],
    "wof:name":"Barbos",
    "wof:placetype":"locality"
},
  "geometry": {"coordinates":[-7.81667,43.68333],"type":"Point"}
}