{
  "type": "Feature",
  "properties": {
    "gn:gn_country":"ES",
    "gn:gn_fcode":"PPLA3",
    "gn:gn_pop":2281,
    "gn:population":2281,
    "iso:country":"ES",
    "name:arg_x_preferred":[
        "Santa Marina del Rey"
    ],
    "name:cat_x_preferred":[
        "Santa Marina del Rey"
    ],
    "name:deu_x_preferred":[
        "Santa Marina del Rey"
    ],
    "name:eng_x_preferred":[
        "Santa Marina del Rey"
    ],
    "name:eus_x_preferred":[
        "Santa Marina del Rey"
    ],
    "name:fra_x_preferred":[
        "Santa Marina del Rey"
    ],
    "name:glg_x_preferred":[
        "Santa Marina del Rey"
    ],
    "name:haw_x_preferred":[
        "Santa Marina del Rey"
    ],
    "name:hun_x_preferred":[
        "Santa Marina del Rey"
    ],
    "name:ido_x_preferred":[
        "Santa Marina del Rey"
    ],
    "name:ina_x_preferred":[
        "Santa Marina del Rey"
    ],
    "name:ita_x_preferred":[
        "Santa Marina del Rey"
    ],
    "name:msa_x_preferred":[
        "Santa Marina del Rey"
    ],
    "name:nan_x_preferred":[
        "Santa Marina del Rey"
    ],
    "name:nld_x_preferred":[
        "Santa Marina del Rey"
    ],
    "name:oci_x_preferred":[
        "Santa Marina del Rey"
    ],
    "name:pol_x_preferred":[
        "Santa Marina del Rey"
    ],
    "name:por_x_preferred":[
        "Santa Marina del Rey"
    ],
    "name:rus_x_preferred":[
        "\u0421\u0430\u043d\u0442\u0430-\u041c\u0430\u0440\u0438\u043d\u0430-\u0434\u0435\u043b\u044c-\u0420\u0435\u0439"
    ],
    "name:spa_x_preferred":[
        "Santa Marina del Rey"
    ],
    "name:swe_x_preferred":[
        "Santa Marina del Rey"
    ],
    "name:tpi_x_preferred":[
        "Santa Marina del Rey"
    ],
    "name:ukr_x_preferred":[
        "\u0421\u0430\u043d\u0442\u0430-\u041c\u0430\u0440\u0456\u043d\u0430-\u0434\u0435\u043b\u044c-\u0420\u0435\u0439"
    ],
    "name:vie_x_preferred":[
        "Santa Marina del Rey"
    ],
    "name:war_x_preferred":[
        "Santa Marina del Rey"
    ],
    "name:zho_x_preferred":[
        "\u5723\u9a6c\u91cc\u7eb3\u5fb7\u5c14\u96f7"
    ],
    "qs_pg:aaroncc":"ES",
    "qs_pg:gn_country":"ES",
    "qs_pg:gn_fcode":"PPLA3",
    "qs_pg:gn_pop":2281,
    "qs_pg:name":"Santa Marina del Rey",
    "qs_pg:name_adm0":"Espa\u00f1a",
    "qs_pg:name_adm1":"Castilla y Le\u00f3n",
    "qs_pg:photos":55,
    "qs_pg:photos_1k":11,
    "qs_pg:photos_9k":1,
    "qs_pg:photos_9r":2,
    "qs_pg:photos_all":55,
    "qs_pg:photos_sr":2,
    "qs_pg:pop_sr":4,
    "qs_pg:qs_pg_placetype":"locality",
    "qs_pg:qs_pg_placetype_gp":"Town",
    "qs_pg:woe_adm0":23424950,
    "woe:adm0_id":23424950,
    "woe:name_adm0":"Espa\u00f1a",
    "woe:name_adm1":"Castilla y Le\u00f3n",
    "woe:placetype":"Town",
    "wof:name":"Santa Marina del Rey",
    "wof:placetype":"locality",
    "wof:population":2281
},
  "geometry": {"coordinates":[-5.86065,42.51334],"type":"Point"}
}