{
  "type": "Feature",
  "properties": {
    "gn:admin1_code":"39",
    "gn:admin2_code":"S",
    "gn:admin3_code":"39013",
    "gn:asciiname":"Torices",
    "gn:country_code":"ES",
    "gn:dem":721,
    "gn:feature_class":"P",
    "gn:feature_code":"PPL",
    "gn:name":"Torices",
    "gn:population":0,
    "gn:timezone":"Europe/Madrid",
    "iso:country":"ES",
    "wof:name":"Torices",
    "wof:placetype":"locality"
},
  "geometry": {"coordinates":[-4.54721,43.13422],"type":"Point"}
}