{
  "type": "Feature",
  "properties": {
    "gn:country":"ES",
    "gn:fcode":"PPLA3",
    "gn:population":69,
    "iso:country":"ES",
    "name:cat_x_preferred":[
        "Castro de Fuentidue\u00f1a"
    ],
    "name:che_x_preferred":[
        "\u041a\u0430\u0441\u0442\u0440\u043e-\u0434\u0435-\u0424\u0443\u044d\u043d\u0442\u0438\u0434\u0443\u044d\u043d\u044c\u044f"
    ],
    "name:eng_x_preferred":[
        "Castro de Fuentidue\u00f1a"
    ],
    "name:eus_x_preferred":[
        "Castro de Fuentidue\u00f1a"
    ],
    "name:fra_x_preferred":[
        "Castro de Fuentidue\u00f1a"
    ],
    "name:hun_x_preferred":[
        "Castro de Fuentidue\u00f1a"
    ],
    "name:ina_x_preferred":[
        "Castro de Fuentidue\u00f1a"
    ],
    "name:ita_x_preferred":[
        "Castro de Fuentidue\u00f1a"
    ],
    "name:msa_x_preferred":[
        "Castro de Fuentidue\u00f1a"
    ],
    "name:nan_x_preferred":[
        "Castro de Fuentidue\u00f1a"
    ],
    "name:nld_x_preferred":[
        "Castro de Fuentidue\u00f1a"
    ],
    "name:oci_x_preferred":[
        "Castro de Fuentidue\u00f1a"
    ],
    "name:pol_x_preferred":[
        "Castro de Fuentidue\u00f1a"
    ],
    "name:por_x_preferred":[
        "Castro de Fuentidue\u00f1a"
    ],
    "name:rus_x_preferred":[
        "\u041a\u0430\u0441\u0442\u0440\u043e-\u0434\u0435-\u0424\u0443\u044d\u043d\u0442\u0438\u0434\u0443\u044d\u043d\u0438\u044f"
    ],
    "name:spa_x_preferred":[
        "Castro de Fuentidue\u00f1a"
    ],
    "name:swe_x_preferred":[
        "Castro de Fuentidue\u00f1a"
    ],
    "name:tat_x_preferred":[
        "\u041a\u0430\u0441\u0442\u0440\u043e-\u0434\u0435-\u0424\u0443\u044d\u043d\u0442\u0438\u0434\u0443\u044d\u043d\u044c\u044f"
    ],
    "name:ukr_x_preferred":[
        "\u041a\u0430\u0441\u0442\u0440\u043e-\u0434\u0435-\u0424\u0443\u0435\u043d\u0442\u0456\u0434\u0443\u0435\u043d\u044c\u044f"
    ],
    "name:vie_x_preferred":[
        "Castro de Fuentidue\u00f1a"
    ],
    "name:war_x_preferred":[
        "Castro de Fuentidue\u00f1a"
    ],
    "name:zho_x_preferred":[
        "\u5361\u65af\u7279\u7f57\u5fb7\u4e30\u8482\u675c\u57c3\u5c3c\u4e9a"
    ],
    "qs_pg:aaroncc":"ES",
    "qs_pg:gn_country":"ES",
    "qs_pg:gn_fcode":"PPLA3",
    "qs_pg:gn_pop":69,
    "qs_pg:name":"Castro de Fuentidue\u00f1a",
    "qs_pg:name_adm0":"Espa\u00f1a",
    "qs_pg:name_adm1":"Castilla y Le\u00f3n",
    "qs_pg:photos_9k":1,
    "qs_pg:photos_9r":1,
    "qs_pg:photos_all":1,
    "qs_pg:photos_sr":0,
    "qs_pg:pop_sr":1,
    "qs_pg:qs_pg_placetype":"locality",
    "qs_pg:qs_pg_placetype_gp":"Town",
    "qs_pg:woe_adm0":23424950,
    "woe:adm0_id":23424950,
    "woe:name_adm0":"Espa\u00f1a",
    "woe:name_adm1":"Castilla y Le\u00f3n",
    "woe:placetype":"Town",
    "wof:name":"Castro de Fuentidue\u00f1a",
    "wof:placetype":"locality",
    "wof:population":69
},
  "geometry": {"coordinates":[-3.85528,41.42044],"type":"Point"}
}