{
  "type": "Feature",
  "properties": {
    "gn:admin1_code":"59",
    "gn:admin2_code":"SS",
    "gn:admin3_code":"20038",
    "gn:asciiname":"Gabiria",
    "gn:country_code":"ES",
    "gn:dem":401,
    "gn:feature_class":"P",
    "gn:feature_code":"PPLA3",
    "gn:name":"Gabiria",
    "gn:population":0,
    "gn:timezone":"Europe/Madrid",
    "iso:country":"ES",
    "name:ara_x_preferred":[
        "\u063a\u0627\u0641\u064a\u0631\u064a\u0627"
    ],
    "name:arg_x_preferred":[
        "Gabiria"
    ],
    "name:ast_x_preferred":[
        "Gabiria"
    ],
    "name:bre_x_preferred":[
        "Gabiria"
    ],
    "name:cat_x_preferred":[
        "Gabiria"
    ],
    "name:ceb_x_preferred":[
        "Gabiria"
    ],
    "name:eus_x_preferred":[
        "Gabiria"
    ],
    "name:fra_x_preferred":[
        "Gabiria"
    ],
    "name:glg_x_preferred":[
        "Gabiria"
    ],
    "name:hun_x_preferred":[
        "Gabiria"
    ],
    "name:ita_x_preferred":[
        "Gabiria"
    ],
    "name:msa_x_preferred":[
        "Gabiria"
    ],
    "name:nld_x_preferred":[
        "Gabiria"
    ],
    "name:oci_x_preferred":[
        "Gabiria"
    ],
    "name:pol_x_preferred":[
        "Gabiria"
    ],
    "name:por_x_preferred":[
        "Gabiria"
    ],
    "name:rus_x_preferred":[
        "\u0413\u0430\u0432\u0438\u0440\u0438\u044f"
    ],
    "name:sco_x_preferred":[
        "Gabiria"
    ],
    "name:spa_x_preferred":[
        "Gaviria"
    ],
    "name:swe_x_preferred":[
        "Gabiria"
    ],
    "name:ukr_x_preferred":[
        "\u0413\u0430\u0431\u0456\u0440\u0456\u044f"
    ],
    "name:uzb_x_preferred":[
        "Gabiria"
    ],
    "name:vie_x_preferred":[
        "Gabiria"
    ],
    "name:war_x_preferred":[
        "Gabiria"
    ],
    "name:zho_x_preferred":[
        "\u52a0\u7ef4\u91cc\u4e9a"
    ],
    "wof:name":"Gabiria",
    "wof:placetype":"locality"
},
  "geometry": {"coordinates":[-2.27962,43.04934],"type":"Point"}
}