{
  "type": "Feature",
  "properties": {
    "gn:admin1_code":"59",
    "gn:admin2_code":"SS",
    "gn:admin3_code":"20038",
    "gn:asciiname":"Gabiria",
    "gn:country_code":"ES",
    "gn:dem":401,
    "gn:feature_class":"P",
    "gn:feature_code":"PPLA3",
    "gn:name":"Gabiria",
    "gn:population":0,
    "gn:timezone":"Europe/Madrid",
    "iso:country":"ES",
    "name:eus_x_preferred":[
        "Gabiria"
    ],
    "name:spa_x_preferred":[
        "Gaviria"
    ],
    "wof:name":"Gabiria",
    "wof:placetype":"locality"
},
  "geometry": {"coordinates":[-2.27962,43.04934],"type":"Point"}
}