{
  "type": "Feature",
  "properties": {
    "gn:admin1_code":"55",
    "gn:admin2_code":"SO",
    "gn:admin3_code":"42049",
    "gn:asciiname":"Duanez",
    "gn:country_code":"ES",
    "gn:dem":1036,
    "gn:feature_class":"P",
    "gn:feature_code":"PPL",
    "gn:name":"Du\u00e1\u00f1ez",
    "gn:population":0,
    "gn:timezone":"Europe/Madrid",
    "iso:country":"ES",
    "name:und_x_variant":[
        "Du\u00e1\u00f1ez"
    ],
    "wof:name":"Duanez",
    "wof:placetype":"locality"
},
  "geometry": {"coordinates":[-2.33374,41.73865],"type":"Point"}
}