{
  "type": "Feature",
  "properties": {
    "gn:admin1_code":"55",
    "gn:admin2_code":"LE",
    "gn:admin3_code":"24132",
    "gn:asciiname":"Andarraso",
    "gn:country_code":"ES",
    "gn:dem":1414,
    "gn:feature_class":"P",
    "gn:feature_code":"PPL",
    "gn:name":"Andarraso",
    "gn:population":0,
    "gn:timezone":"Europe/Madrid",
    "iso:country":"ES",
    "wof:name":"Andarraso",
    "wof:placetype":"locality"
},
  "geometry": {"coordinates":[-6.00941,42.74671],"type":"Point"}
}