{
  "type": "Feature",
  "properties": {
    "gn:gn_country":"ES",
    "gn:gn_fcode":"PPLA3",
    "gn:gn_pop":114,
    "gn:population":114,
    "iso:country":"ES",
    "name:ara_x_preferred":[
        "\u0641\u064a\u0644\u0627\u0644\u063a\u0648\u0631\u062f\u0648 \u062f\u064a\u0644 \u0645\u0627\u0631\u0643\u064a\u0633\u0648\u062f\u0648"
    ],
    "name:arg_x_preferred":[
        "Villalgordo del Marquesado"
    ],
    "name:ast_x_preferred":[
        "Villalgordo del Marquesado"
    ],
    "name:cat_x_preferred":[
        "Villalgordo del Marquesado"
    ],
    "name:ceb_x_preferred":[
        "Villalgordo del Marquesado"
    ],
    "name:eng_x_preferred":[
        "Villalgordo del Marquesado"
    ],
    "name:epo_x_preferred":[
        "Villalgordo del Marquesado"
    ],
    "name:eus_x_preferred":[
        "Villalgordo del Marquesado"
    ],
    "name:fra_x_preferred":[
        "Villalgordo del Marquesado"
    ],
    "name:hun_x_preferred":[
        "Villalgordo del Marquesado"
    ],
    "name:ita_x_preferred":[
        "Villalgordo del Marquesado"
    ],
    "name:kaz_x_preferred":[
        "\u0412\u0438\u043b\u044c\u044f\u043b\u044c\u0433\u043e\u0440\u0434\u043e-\u0434\u0435\u043b\u044c-\u041c\u0430\u0440\u043a\u0435\u0441\u0430\u0434\u043e"
    ],
    "name:msa_x_preferred":[
        "Villalgordo del Marquesado"
    ],
    "name:nan_x_preferred":[
        "Villalgordo del Marquesado"
    ],
    "name:nld_x_preferred":[
        "Villalgordo del Marquesado"
    ],
    "name:oci_x_preferred":[
        "Villalgordo del Marquesado"
    ],
    "name:pol_x_preferred":[
        "Villalgordo del Marquesado"
    ],
    "name:por_x_preferred":[
        "Villalgordo del Marquesado"
    ],
    "name:rus_x_preferred":[
        "\u0412\u0438\u043b\u044c\u044f\u043b\u044c\u0433\u043e\u0440\u0434\u043e-\u0434\u0435\u043b\u044c-\u041c\u0430\u0440\u043a\u0435\u0441\u0430\u0434\u043e"
    ],
    "name:spa_x_preferred":[
        "Villalgordo del Marquesado"
    ],
    "name:swe_x_preferred":[
        "Villalgordo del Marquesado"
    ],
    "name:ukr_x_preferred":[
        "\u0412\u0456\u043b\u044c\u044f\u043b\u044c\u0433\u043e\u0440\u0434\u043e-\u0434\u0435\u043b\u044c-\u041c\u0430\u0440\u043a\u0435\u0441\u0430\u0434\u043e"
    ],
    "name:vie_x_preferred":[
        "Villalgordo del Marquesado"
    ],
    "name:war_x_preferred":[
        "Villalgordo del Marquesado"
    ],
    "name:zho_x_preferred":[
        "\u6bd4\u5229\u4e9a\u5c14\u6208\u5c14\u591a\u5fb7\u5c14\u9a6c\u5c14\u514b\u8428\u591a"
    ],
    "qs_pg:aaroncc":"ES",
    "qs_pg:gn_country":"ES",
    "qs_pg:gn_fcode":"PPLA3",
    "qs_pg:gn_pop":114,
    "qs_pg:name":"Villalgordo del Marquesado",
    "qs_pg:name_adm0":"Espa\u00f1a",
    "qs_pg:name_adm1":"Castilla-La Mancha",
    "qs_pg:photos_9r":0,
    "qs_pg:photos_sr":0,
    "qs_pg:pop_sr":1,
    "qs_pg:qs_pg_placetype":"locality",
    "qs_pg:qs_pg_placetype_gp":"Town",
    "qs_pg:woe_adm0":23424950,
    "woe:adm0_id":23424950,
    "woe:name_adm0":"Espa\u00f1a",
    "woe:name_adm1":"Castilla-La Mancha",
    "woe:placetype":"Town",
    "wof:name":"Villalgordo del Marquesado",
    "wof:placetype":"locality",
    "wof:population":114
},
  "geometry": {"coordinates":[-2.50885,39.68245],"type":"Point"}
}