{
  "type": "Feature",
  "properties": {
    "gn:admin1_code":"52",
    "gn:admin2_code":"Z",
    "gn:admin3_code":"50231",
    "gn:asciiname":"Salillas de Jalon",
    "gn:country_code":"ES",
    "gn:dem":336,
    "gn:feature_class":"P",
    "gn:feature_code":"PPLA3",
    "gn:name":"Salillas de Jal\u00f3n",
    "gn:population":341,
    "gn:timezone":"Europe/Madrid",
    "iso:country":"ES",
    "name:ara_x_preferred":[
        "\u0633\u0627\u0644\u064a\u0627\u0633 \u062f\u064a \u062e\u0627\u0644\u0648\u0646"
    ],
    "name:kaz_x_preferred":[
        "\u0421\u0430\u043b\u0438\u043b\u044c\u044f\u0441-\u0434\u0435-\u0425\u0430\u043b\u043e\u043d"
    ],
    "name:rus_x_preferred":[
        "\u0421\u0430\u043b\u0438\u043b\u044c\u044f\u0441-\u0434\u0435-\u0425\u0430\u043b\u043e\u043d"
    ],
    "name:ukr_x_preferred":[
        "\u0421\u0430\u043b\u0456\u043b\u044c\u044f\u0441-\u0434\u0435-\u0425\u0430\u043b\u043e\u043d"
    ],
    "name:und_x_variant":[
        "Salillas de Jal\u00f3n"
    ],
    "name:zho_x_preferred":[
        "\u8428\u5229\u5229\u4e9a\u65af\u5fb7\u54c8\u9686"
    ],
    "wof:name":"Salillas de Jalon",
    "wof:placetype":"locality",
    "wof:population":341
},
  "geometry": {"coordinates":[-1.32344,41.56789000000001],"type":"Point"}
}