{
  "type": "Feature",
  "properties": {
    "gn:admin1_code":"52",
    "gn:admin2_code":"Z",
    "gn:admin3_code":"50231",
    "gn:asciiname":"Salillas de Jalon",
    "gn:country_code":"ES",
    "gn:dem":336,
    "gn:feature_class":"P",
    "gn:feature_code":"PPLA3",
    "gn:name":"Salillas de Jal\u00f3n",
    "gn:population":341,
    "gn:timezone":"Europe/Madrid",
    "iso:country":"ES",
    "name:und_x_variant":[
        "Salillas de Jal\u00f3n"
    ],
    "wof:name":"Salillas de Jalon",
    "wof:placetype":"locality",
    "wof:population":341
},
  "geometry": {"coordinates":[-1.32344,41.56789000000001],"type":"Point"}
}