{
  "type": "Feature",
  "properties": {
    "gn:admin1_code":"58",
    "gn:admin2_code":"C",
    "gn:admin3_code":"15078",
    "gn:asciiname":"Cesar",
    "gn:cc2":"ES",
    "gn:country_code":"ES",
    "gn:dem":227,
    "gn:feature_class":"P",
    "gn:feature_code":"PPL",
    "gn:name":"C\u00e9sar",
    "gn:population":0,
    "gn:timezone":"Europe/Madrid",
    "iso:country":"ES",
    "name:arg_x_preferred":[
        "C\u00e9sar"
    ],
    "name:ast_x_preferred":[
        "C\u00e9sar"
    ],
    "name:bre_x_preferred":[
        "Cesar"
    ],
    "name:cat_x_preferred":[
        "C\u00e8sar"
    ],
    "name:ceb_x_preferred":[
        "Cesar"
    ],
    "name:deu_x_preferred":[
        "Cesar"
    ],
    "name:fra_x_preferred":[
        "C\u00e9sar"
    ],
    "name:glg_x_preferred":[
        "Cesar"
    ],
    "name:heb_x_preferred":[
        "\u05e1\u05d6\u05d0\u05e8"
    ],
    "name:ita_x_preferred":[
        "C\u00e9sar"
    ],
    "name:jpn_x_preferred":[
        "\u30bb\u30b6\u30fc\u30eb"
    ],
    "name:kor_x_preferred":[
        "\uc138\uc0ac\ub974"
    ],
    "name:ltz_x_preferred":[
        "C\u00e9sar"
    ],
    "name:nld_x_preferred":[
        "Cesar"
    ],
    "name:nor_x_preferred":[
        "C\u00e9sar"
    ],
    "name:pol_x_preferred":[
        "C\u00e9sar"
    ],
    "name:por_x_preferred":[
        "C\u00e9sar"
    ],
    "name:rus_x_preferred":[
        "\u0421\u0435\u0437\u0430\u0440"
    ],
    "name:sco_x_preferred":[
        "Cesar"
    ],
    "name:slv_x_preferred":[
        "Cesar"
    ],
    "name:spa_x_preferred":[
        "C\u00e9sar"
    ],
    "name:ukr_x_preferred":[
        "\u0421\u0435\u0437\u0430\u0440"
    ],
    "name:und_x_variant":[
        "Santa Mar\u00eda"
    ],
    "name:vie_x_preferred":[
        "Cesar"
    ],
    "name:zho_x_preferred":[
        "\u585e\u8428\u5c14"
    ],
    "wof:name":"Cesar",
    "wof:placetype":"locality"
},
  "geometry": {"coordinates":[-8.41667,42.96667],"type":"Point"}
}