{
  "type": "Feature",
  "properties": {
    "gn:admin1_code":"58",
    "gn:admin2_code":"C",
    "gn:admin3_code":"15078",
    "gn:asciiname":"Cesar",
    "gn:cc2":"ES",
    "gn:country_code":"ES",
    "gn:dem":227,
    "gn:feature_class":"P",
    "gn:feature_code":"PPL",
    "gn:name":"C\u00e9sar",
    "gn:population":0,
    "gn:timezone":"Europe/Madrid",
    "iso:country":"ES",
    "name:und_x_variant":[
        "Santa Mar\u00eda",
        "C\u00e9sar"
    ],
    "wof:name":"Cesar",
    "wof:placetype":"locality"
},
  "geometry": {"coordinates":[-8.41667,42.96667],"type":"Point"}
}