{
  "type": "Feature",
  "properties": {
    "gn:admin1_code":"56",
    "gn:admin2_code":"GI",
    "gn:admin3_code":"17134",
    "gn:asciiname":"Neva",
    "gn:country_code":"ES",
    "gn:dem":1175,
    "gn:feature_class":"P",
    "gn:feature_code":"PPL",
    "gn:name":"Nev\u00e0",
    "gn:population":0,
    "gn:timezone":"Europe/Madrid",
    "iso:country":"ES",
    "wof:name":"Neva",
    "wof:placetype":"locality"
},
  "geometry": {"coordinates":[2.08333,42.31667],"type":"Point"}
}