{
  "type": "Feature",
  "properties": {
    "gn:gn_country":"ES",
    "gn:gn_fcode":"PPL",
    "gn:gn_pop":0,
    "iso:country":"ES",
    "name:ast_x_preferred":[
        "Cimavilla"
    ],
    "name:eng_x_preferred":[
        "Cimadevilla"
    ],
    "name:eus_x_preferred":[
        "Cimadevilla"
    ],
    "name:jpn_x_preferred":[
        "\u30b7\u30de\u30c7\u30d3\u30fc\u30b8\u30e3"
    ],
    "name:nld_x_preferred":[
        "Cimavilla"
    ],
    "name:spa_x_preferred":[
        "Cimadevilla"
    ],
    "qs_pg:aaroncc":"ES",
    "qs_pg:gn_country":"ES",
    "qs_pg:gn_fcode":"PPL",
    "qs_pg:gn_pop":0,
    "qs_pg:name":"Cimadevilla",
    "qs_pg:name_adm0":"Espa\u00f1a",
    "qs_pg:name_adm1":"Principado de Asturias",
    "qs_pg:photos":618,
    "qs_pg:photos_1k":125,
    "qs_pg:photos_9k":3,
    "qs_pg:photos_9r":5,
    "qs_pg:photos_all":618,
    "qs_pg:photos_sr":8,
    "qs_pg:pop_sr":0,
    "qs_pg:qs_pg_placetype":"locality",
    "qs_pg:qs_pg_placetype_gp":"Town",
    "qs_pg:woe_adm0":23424950,
    "woe:adm0_id":23424950,
    "woe:name_adm0":"Espa\u00f1a",
    "woe:name_adm1":"Principado de Asturias",
    "woe:placetype":"Town",
    "wof:name":"Cimadevilla",
    "wof:placetype":"locality"
},
  "geometry": {"coordinates":[-5.59013,43.52725],"type":"Point"}
}