{
  "type": "Feature",
  "properties": {
    "gn:admin1_code":"59",
    "gn:admin2_code":"BI",
    "gn:admin3_code":"48909",
    "gn:asciiname":"Inchaurragas",
    "gn:country_code":"ES",
    "gn:dem":319,
    "gn:feature_class":"P",
    "gn:feature_code":"PPL",
    "gn:name":"Intxaurraga",
    "gn:population":0,
    "gn:timezone":"Europe/Madrid",
    "iso:country":"ES",
    "wof:name":"Inchaurragas",
    "wof:placetype":"locality"
},
  "geometry": {"coordinates":[-2.58771,43.32838],"type":"Point"}
}