{
  "type": "Feature",
  "properties": {
    "gn:admin1_code":"58",
    "gn:admin2_code":"C",
    "gn:admin3_code":"15093",
    "gn:asciiname":"Vilaestevez",
    "gn:cc2":"ES",
    "gn:country_code":"ES",
    "gn:dem":219,
    "gn:feature_class":"P",
    "gn:feature_code":"PPL",
    "gn:name":"Vilaest\u00e9vez",
    "gn:population":0,
    "gn:timezone":"Europe/Madrid",
    "iso:country":"ES",
    "name:und_x_variant":[
        "Villateves"
    ],
    "wof:name":"Vilaestevez",
    "wof:placetype":"locality"
},
  "geometry": {"coordinates":[-8.88333,43.13333],"type":"Point"}
}