{
  "type": "Feature",
  "properties": {
    "gn:admin1_code":"55",
    "gn:admin2_code":"SO",
    "gn:admin3_code":"42020",
    "gn:asciiname":"Balluncar",
    "gn:country_code":"ES",
    "gn:dem":978,
    "gn:feature_class":"P",
    "gn:feature_code":"PPL",
    "gn:name":"Balluncar",
    "gn:population":0,
    "gn:timezone":"Europe/Madrid",
    "iso:country":"ES",
    "wof:name":"Balluncar",
    "wof:placetype":"locality"
},
  "geometry": {"coordinates":[-2.54496,41.42585],"type":"Point"}
}