{
  "type": "Feature",
  "properties": {
    "gn:admin1_code":"58",
    "gn:admin2_code":"C",
    "gn:admin3_code":"15077",
    "gn:asciiname":"Pragais",
    "gn:country_code":"ES",
    "gn:dem":337,
    "gn:feature_class":"P",
    "gn:feature_code":"PPL",
    "gn:name":"Pragais",
    "gn:population":0,
    "gn:timezone":"Europe/Madrid",
    "iso:country":"ES",
    "wof:name":"Pragais",
    "wof:placetype":"locality"
},
  "geometry": {"coordinates":[-8.87984,42.98844],"type":"Point"}
}