{
  "type": "Feature",
  "properties": {
    "gn:admin1_code":"31",
    "gn:admin2_code":"MU",
    "gn:admin3_code":"30016",
    "gn:asciiname":"Lo Tacon",
    "gn:country_code":"ES",
    "gn:dem":46,
    "gn:feature_class":"P",
    "gn:feature_code":"PPL",
    "gn:name":"Lo Tac\u00f3n",
    "gn:population":0,
    "gn:timezone":"Europe/Madrid",
    "iso:country":"ES",
    "name:und_x_variant":[
        "Caser\u00edo Lo Tac\u00f3n",
        "Lo Tac\u00f3n"
    ],
    "wof:name":"Lo Tacon",
    "wof:placetype":"locality"
},
  "geometry": {"coordinates":[-0.98918,37.69003],"type":"Point"}
}