{
  "type": "Feature",
  "properties": {
    "gn:admin1_code":"55",
    "gn:admin2_code":"AV",
    "gn:admin3_code":"05163",
    "gn:asciiname":"La Lobera",
    "gn:country_code":"ES",
    "gn:dem":984,
    "gn:feature_class":"P",
    "gn:feature_code":"PPL",
    "gn:name":"La Lobera",
    "gn:population":0,
    "gn:timezone":"Europe/Madrid",
    "iso:country":"ES",
    "name:und_x_variant":[
        "Caser\u00edo La Lobera",
        "La Lobera"
    ],
    "wof:name":"La Lobera",
    "wof:placetype":"locality"
},
  "geometry": {"coordinates":[-4.66747,40.38854],"type":"Point"}
}