{
  "type": "Feature",
  "properties": {
    "gn:admin1_code":"60",
    "gn:admin2_code":"A",
    "gn:admin3_code":"03063",
    "gn:asciiname":"Les Rotes",
    "gn:cc2":"ES",
    "gn:country_code":"ES",
    "gn:dem":1,
    "gn:feature_class":"P",
    "gn:feature_code":"PPL",
    "gn:name":"Les Rotes",
    "gn:population":0,
    "gn:timezone":"Europe/Madrid",
    "iso:country":"ES",
    "name:und_x_variant":[
        "Caser\u00edo Rotes",
        "Casa Rotes de Oliver"
    ],
    "wof:name":"Les Rotes",
    "wof:placetype":"locality"
},
  "geometry": {"coordinates":[0.15,38.83333],"type":"Point"}
}