{
  "type": "Feature",
  "properties": {
    "gn:admin1_code":"58",
    "gn:admin2_code":"C",
    "gn:admin3_code":"15052",
    "gn:asciiname":"Leis",
    "gn:country_code":"ES",
    "gn:dem":73,
    "gn:feature_class":"P",
    "gn:feature_code":"PPL",
    "gn:name":"Leis",
    "gn:population":0,
    "gn:timezone":"Europe/Madrid",
    "iso:country":"ES",
    "wof:name":"Leis",
    "wof:placetype":"locality"
},
  "geometry": {"coordinates":[-9.15523,43.11557],"type":"Point"}
}