{
  "type": "Feature",
  "properties": {
    "gn:admin1_code":"58",
    "gn:admin2_code":"C",
    "gn:admin3_code":"15093",
    "gn:asciiname":"Carreira",
    "gn:country_code":"ES",
    "gn:dem":237,
    "gn:feature_class":"P",
    "gn:feature_code":"PPL",
    "gn:name":"Carreira",
    "gn:population":0,
    "gn:timezone":"Europe/Madrid",
    "iso:country":"ES",
    "wof:name":"Carreira",
    "wof:placetype":"locality"
},
  "geometry": {"coordinates":[-8.88291,43.1213],"type":"Point"}
}