{
  "type": "Feature",
  "properties": {
    "gn:gn_country":"ES",
    "gn:gn_fcode":"PPLA3",
    "gn:gn_pop":181,
    "gn:population":181,
    "iso:country":"ES",
    "name:ara_x_preferred":[
        "\u0643\u0648\u064a\u0646\u062a\u0627\u0646\u0627 \u062f\u064a\u0644 \u0628\u064a\u062f\u064a\u0648"
    ],
    "name:arg_x_preferred":[
        "Quintana del Pidio"
    ],
    "name:baq_x_preferred":[
        "Quintana del Pidio"
    ],
    "name:cat_x_preferred":[
        "Quintana del Pidio"
    ],
    "name:chi_x_preferred":[
        "\u91d1\u5854\u7eb3\u5fb7\u5c14\u76ae\u8fea\u5965"
    ],
    "name:dut_x_preferred":[
        "Quintana del Pidio"
    ],
    "name:eng_x_preferred":[
        "Quintana del Pidio"
    ],
    "name:epo_x_preferred":[
        "Quintana del Pidio"
    ],
    "name:fre_x_preferred":[
        "Quintana del Pidio"
    ],
    "name:glg_x_preferred":[
        "Quintana del Pidio"
    ],
    "name:haw_x_preferred":[
        "Quintana del Pidio"
    ],
    "name:hun_x_preferred":[
        "Quintana del Pidio"
    ],
    "name:ina_x_preferred":[
        "Quintana del Pidio"
    ],
    "name:ita_x_preferred":[
        "Quintana del Pidio"
    ],
    "name:may_x_preferred":[
        "Quintana del Pidio"
    ],
    "name:nan_x_preferred":[
        "Quintana del Pidio"
    ],
    "name:oci_x_preferred":[
        "Quintana del Pidio"
    ],
    "name:per_x_preferred":[
        "\u06a9\u06cc\u0646\u062a\u0627\u0646\u0627 \u062f\u0644 \u067e\u06cc\u062f\u06cc\u0648"
    ],
    "name:pol_x_preferred":[
        "Quintana del Pidio"
    ],
    "name:por_x_preferred":[
        "Quintana del Pidio"
    ],
    "name:rus_x_preferred":[
        "\u041a\u0438\u043d\u0442\u0430\u043d\u0430-\u0434\u0435\u043b\u044c-\u041f\u0438\u0434\u0438\u043e"
    ],
    "name:spa_x_preferred":[
        "Quintana del Pidio"
    ],
    "name:swe_x_preferred":[
        "Quintana del Pidio"
    ],
    "name:ukr_x_preferred":[
        "\u041a\u0456\u043d\u0442\u0430\u043d\u0430-\u0434\u0435\u043b\u044c-\u041f\u0456\u0434\u0456\u043e"
    ],
    "name:uzb_x_preferred":[
        "Quintana del Pidio"
    ],
    "name:vie_x_preferred":[
        "Quintana del Pidio"
    ],
    "name:war_x_preferred":[
        "Quintana del Pidio"
    ],
    "qs_pg:aaroncc":"ES",
    "qs_pg:gn_country":"ES",
    "qs_pg:gn_fcode":"PPLA3",
    "qs_pg:gn_pop":181,
    "qs_pg:name":"Quintana del Pidio",
    "qs_pg:name_adm0":"Espa\u00f1a",
    "qs_pg:name_adm1":"Castilla y Le\u00f3n",
    "qs_pg:photos_9r":0,
    "qs_pg:photos_sr":0,
    "qs_pg:pop_sr":1,
    "qs_pg:qs_pg_placetype":"locality",
    "qs_pg:qs_pg_placetype_gp":"Town",
    "qs_pg:woe_adm0":23424950,
    "woe:adm0_id":23424950,
    "woe:name_adm0":"Espa\u00f1a",
    "woe:name_adm1":"Castilla y Le\u00f3n",
    "woe:placetype":"Town",
    "wof:name":"Quintana del Pidio",
    "wof:placetype":"locality",
    "wof:population":181
},
  "geometry": {"coordinates":[-3.75121,41.75886],"type":"Point"}
}