{
  "type": "Feature",
  "properties": {
    "gn:admin1_code":"58",
    "gn:admin2_code":"LU",
    "gn:admin3_code":"27050",
    "gn:asciiname":"Castrofoya",
    "gn:country_code":"ES",
    "gn:dem":314,
    "gn:feature_class":"P",
    "gn:feature_code":"PPL",
    "gn:name":"Castrofoya",
    "gn:population":0,
    "gn:timezone":"Europe/Madrid",
    "iso:country":"ES",
    "name:und_x_variant":[
        "Barrio de Castrofoya",
        "Castrofoya"
    ],
    "wof:name":"Castrofoya",
    "wof:placetype":"locality"
},
  "geometry": {"coordinates":[-7.12109,42.37988],"type":"Point"}
}