{
  "type": "Feature",
  "properties": {
    "gn:admin1_code":"54",
    "gn:admin2_code":"AB",
    "gn:admin3_code":"02012",
    "gn:asciiname":"Los Partidores",
    "gn:cc2":"ES",
    "gn:country_code":"ES",
    "gn:dem":733,
    "gn:feature_class":"P",
    "gn:feature_code":"PPL",
    "gn:name":"Los Partidores",
    "gn:population":0,
    "gn:timezone":"Europe/Madrid",
    "iso:country":"ES",
    "name:und_x_variant":[
        "Caser\u00edo Los Partidores",
        "Los Partidores"
    ],
    "wof:name":"Los Partidores",
    "wof:placetype":"locality"
},
  "geometry": {"coordinates":[-2.11667,38.91667],"type":"Point"}
}