{
  "type": "Feature",
  "properties": {
    "gn:admin1_code":"59",
    "gn:admin2_code":"BI",
    "gn:admin3_code":"48060",
    "gn:asciiname":"Larruscain",
    "gn:country_code":"ES",
    "gn:dem":195,
    "gn:feature_class":"P",
    "gn:feature_code":"PPL",
    "gn:name":"Larruskain",
    "gn:population":0,
    "gn:timezone":"Europe/Madrid",
    "iso:country":"ES",
    "wof:name":"Larruscain",
    "wof:placetype":"locality"
},
  "geometry": {"coordinates":[-2.44656,43.27181],"type":"Point"}
}