{
  "type": "Feature",
  "properties": {
    "gn:admin1_code":"58",
    "gn:admin2_code":"LU",
    "gn:admin3_code":"27004",
    "gn:asciiname":"Moina",
    "gn:country_code":"ES",
    "gn:dem":736,
    "gn:feature_class":"P",
    "gn:feature_code":"PPL",
    "gn:name":"Mo\u00ed\u00f1a",
    "gn:population":0,
    "gn:timezone":"Europe/Madrid",
    "iso:country":"ES",
    "name:ceb_x_preferred":[
        "Moina"
    ],
    "name:ces_x_preferred":[
        "Moina"
    ],
    "name:kir_x_preferred":[
        "\u041c\u043e\u0438\u043d\u0430\u043b\u0430\u0440"
    ],
    "name:nld_x_preferred":[
        "Moina"
    ],
    "name:rus_x_preferred":[
        "Moina"
    ],
    "name:swe_x_preferred":[
        "Moina"
    ],
    "name:tha_x_preferred":[
        "\u0e44\u0e23\u0e41\u0e14\u0e07"
    ],
    "name:war_x_preferred":[
        "Moina"
    ],
    "wof:name":"Moina",
    "wof:placetype":"locality"
},
  "geometry": {"coordinates":[-7.26667,43.11667],"type":"Point"}
}