{
  "type": "Feature",
  "properties": {
    "gn:admin1_code":"58",
    "gn:admin2_code":"LU",
    "gn:admin3_code":"27004",
    "gn:asciiname":"Moina",
    "gn:country_code":"ES",
    "gn:dem":736,
    "gn:feature_class":"P",
    "gn:feature_code":"PPL",
    "gn:name":"Mo\u00ed\u00f1a",
    "gn:population":0,
    "gn:timezone":"Europe/Madrid",
    "iso:country":"ES",
    "wof:name":"Moina",
    "wof:placetype":"locality"
},
  "geometry": {"coordinates":[-7.26667,43.11667],"type":"Point"}
}