{
  "type": "Feature",
  "properties": {
    "gn:admin1_code":"31",
    "gn:admin2_code":"MU",
    "gn:admin3_code":"30016",
    "gn:asciiname":"El Mojon",
    "gn:cc2":"ES",
    "gn:country_code":"ES",
    "gn:dem":16,
    "gn:feature_class":"P",
    "gn:feature_code":"PPL",
    "gn:name":"El Moj\u00f3n",
    "gn:population":0,
    "gn:timezone":"Europe/Madrid",
    "iso:country":"ES",
    "name:und_x_variant":[
        "Caser\u00edo El Moj\u00f3n",
        "Casas del Moj\u00f3n"
    ],
    "wof:name":"El Mojon",
    "wof:placetype":"locality"
},
  "geometry": {"coordinates":[-1.21442,37.57635],"type":"Point"}
}