{
  "type": "Feature",
  "properties": {
    "gn:admin1_code":"34",
    "gn:admin2_code":"O",
    "gn:admin3_code":"33028",
    "gn:asciiname":"La Sierra",
    "gn:country_code":"ES",
    "gn:dem":787,
    "gn:feature_class":"P",
    "gn:feature_code":"PPL",
    "gn:name":"La Sierra",
    "gn:population":0,
    "gn:timezone":"Europe/Madrid",
    "iso:country":"ES",
    "name:ast_x_preferred":[
        "La Sierra"
    ],
    "name:ceb_x_preferred":[
        "La Sierra"
    ],
    "name:ita_x_preferred":[
        "La Sierra"
    ],
    "name:spa_x_preferred":[
        "La Sierra"
    ],
    "name:swe_x_preferred":[
        "La Sierra"
    ],
    "name:vie_x_preferred":[
        "La Sierra"
    ],
    "wof:name":"La Sierra",
    "wof:placetype":"locality"
},
  "geometry": {"coordinates":[-6.83254,42.98483],"type":"Point"}
}