{
  "type": "Feature",
  "properties": {
    "gn:admin1_code":"55",
    "gn:admin2_code":"LE",
    "gn:admin3_code":"24172",
    "gn:asciiname":"Cunas",
    "gn:country_code":"ES",
    "gn:dem":1180,
    "gn:feature_class":"P",
    "gn:feature_code":"PPL",
    "gn:name":"Cunas",
    "gn:population":0,
    "gn:timezone":"Europe/Madrid",
    "iso:country":"ES",
    "wof:name":"Cunas",
    "wof:placetype":"locality"
},
  "geometry": {"coordinates":[-6.38028,42.25442],"type":"Point"}
}