{
  "type": "Feature",
  "properties": {
    "gn:admin1_code":"57",
    "gn:admin2_code":"BA",
    "gn:admin3_code":"06092",
    "gn:asciiname":"Los Entrines",
    "gn:cc2":"ES",
    "gn:country_code":"ES",
    "gn:dem":280,
    "gn:feature_class":"P",
    "gn:feature_code":"PPL",
    "gn:name":"Los Entrines",
    "gn:population":0,
    "gn:timezone":"Europe/Madrid",
    "iso:country":"ES",
    "name:und_x_variant":[
        "Entrines",
        "Cortijos Los Entrines",
        "Los Entrines"
    ],
    "wof:name":"Los Entrines",
    "wof:placetype":"locality"
},
  "geometry": {"coordinates":[-6.71667,38.65],"type":"Point"}
}