{
  "type": "Feature",
  "properties": {
    "gn:admin1_code":"55",
    "gn:admin2_code":"BU",
    "gn:admin3_code":"09048",
    "gn:asciiname":"Avellanosa de Rioja",
    "gn:country_code":"ES",
    "gn:dem":1061,
    "gn:feature_class":"P",
    "gn:feature_code":"PPL",
    "gn:name":"Avellanosa de Rioja",
    "gn:population":0,
    "gn:timezone":"Europe/Madrid",
    "iso:country":"ES",
    "wof:name":"Avellanosa de Rioja",
    "wof:placetype":"locality"
},
  "geometry": {"coordinates":[-3.09349,42.36266],"type":"Point"}
}