{
  "type": "Feature",
  "properties": {
    "gn:gn_country":"ES",
    "gn:gn_fcode":"PPL",
    "gn:gn_pop":1080,
    "gn:population":1080,
    "iso:country":"ES",
    "name:eus_x_preferred":[
        "Uribarri Gaubea"
    ],
    "name:spa_x_preferred":[
        "Valdegovia"
    ],
    "name:spa_x_variant":[
        "Valdegobia",
        "Villanueva de Valdegov\u00eda"
    ],
    "qs_pg:aaroncc":"ES",
    "qs_pg:gn_country":"ES",
    "qs_pg:gn_fcode":"PPL",
    "qs_pg:gn_pop":1080,
    "qs_pg:name":"Villanueva de Valdegov\u00eda",
    "qs_pg:name_adm0":"Espa\u00f1a",
    "qs_pg:name_adm1":"Euskadi",
    "qs_pg:photos_9r":0,
    "qs_pg:photos_sr":0,
    "qs_pg:pop_sr":3,
    "qs_pg:qs_pg_placetype":"locality",
    "qs_pg:qs_pg_placetype_gp":"Town",
    "qs_pg:woe_adm0":23424950,
    "woe:adm0_id":23424950,
    "woe:name_adm0":"Espa\u00f1a",
    "woe:name_adm1":"Euskadi",
    "woe:placetype":"Town",
    "wof:name":"Villanueva de Valdegov\u00eda",
    "wof:placetype":"locality",
    "wof:population":1080
},
  "geometry": {"coordinates":[-3.09883,42.84777],"type":"Point"}
}