{
  "type": "Feature",
  "properties": {
    "gn:admin1_code":"34",
    "gn:admin2_code":"O",
    "gn:admin3_code":"33034",
    "gn:asciiname":"Rellon de Meras",
    "gn:country_code":"ES",
    "gn:dem":170,
    "gn:feature_class":"P",
    "gn:feature_code":"PPL",
    "gn:name":"Rell\u00f3n de Mer\u00e1s",
    "gn:population":0,
    "gn:timezone":"Europe/Madrid",
    "iso:country":"ES",
    "wof:name":"Rellon de Meras",
    "wof:placetype":"locality"
},
  "geometry": {"coordinates":[-6.47149,43.47175],"type":"Point"}
}