{
  "type": "Feature",
  "properties": {
    "gn:admin1_code":"51",
    "gn:admin2_code":"H",
    "gn:admin3_code":"21010.0",
    "gn:asciiname":"Moral de la Frontera",
    "gn:country_code":"ES",
    "gn:dem":10,
    "gn:feature_class":"P",
    "gn:feature_code":"PPL",
    "gn:name":"Moral de la Frontera",
    "gn:population":500,
    "gn:timezone":"Europe/Madrid",
    "iso:country":"ES",
    "wof:name":"Moral de la Frontera",
    "wof:placetype":"locality",
    "wof:population":500
},
  "geometry": {"coordinates":[-7.39187,37.23257],"type":"Point"}
}