{
  "type": "Feature",
  "properties": {
    "gn:admin1_code":"54",
    "gn:admin2_code":"CR",
    "gn:admin3_code":"13052",
    "gn:asciiname":"La Canada",
    "gn:country_code":"ES",
    "gn:dem":664,
    "gn:feature_class":"P",
    "gn:feature_code":"PPL",
    "gn:name":"La Ca\u00f1ada",
    "gn:population":0,
    "gn:timezone":"Europe/Madrid",
    "iso:country":"ES",
    "name:und_x_variant":[
        "Caser\u00edo Ca\u00f1ada",
        "La Ca\u00f1ada"
    ],
    "wof:name":"La Canada",
    "wof:placetype":"locality"
},
  "geometry": {"coordinates":[-3.85248,39.23396],"type":"Point"}
}