{
  "type": "Feature",
  "properties": {
    "gn:admin1_code":"34",
    "gn:admin2_code":"O",
    "gn:admin3_code":"33070",
    "gn:asciiname":"Pelogra",
    "gn:country_code":"ES",
    "gn:dem":128,
    "gn:feature_class":"P",
    "gn:feature_code":"PPL",
    "gn:name":"Pelogra",
    "gn:population":0,
    "gn:timezone":"Europe/Madrid",
    "iso:country":"ES",
    "wof:name":"Pelogra",
    "wof:placetype":"locality"
},
  "geometry": {"coordinates":[-6.89515,43.52807],"type":"Point"}
}