{
  "type": "Feature",
  "properties": {
    "gn:admin1_code":"51",
    "gn:admin2_code":"J",
    "gn:admin3_code":"23017",
    "gn:asciiname":"Estacion de Larva",
    "gn:country_code":"ES",
    "gn:dem":640,
    "gn:feature_class":"P",
    "gn:feature_code":"PPL",
    "gn:name":"Estaci\u00f3n de Larva",
    "gn:population":0,
    "gn:timezone":"Europe/Madrid",
    "iso:country":"ES",
    "wof:name":"Estacion de Larva",
    "wof:placetype":"locality"
},
  "geometry": {"coordinates":[-3.23181,37.77701],"type":"Point"}
}