{
  "type": "Feature",
  "properties": {
    "gn:admin1_code":"58",
    "gn:admin2_code":"LU",
    "gn:admin3_code":"27027",
    "gn:asciiname":"Arrojo",
    "gn:country_code":"ES",
    "gn:dem":222,
    "gn:feature_class":"P",
    "gn:feature_code":"PPL",
    "gn:name":"Arrojo",
    "gn:population":0,
    "gn:timezone":"Europe/Madrid",
    "iso:country":"ES",
    "wof:name":"Arrojo",
    "wof:placetype":"locality"
},
  "geometry": {"coordinates":[-7.31819,43.45616],"type":"Point"}
}