{
  "type": "Feature",
  "properties": {
    "gn:gn_country":"ES",
    "gn:gn_fcode":"PPLA3",
    "gn:gn_pop":222,
    "gn:population":222,
    "iso:country":"ES",
    "name:arg_x_preferred":[
        "Villanueva del Conde"
    ],
    "name:baq_x_preferred":[
        "Villanueva del Conde"
    ],
    "name:cat_x_preferred":[
        "Villanueva del Conde"
    ],
    "name:chi_x_preferred":[
        "\u5b54\u5fb7\u65b0\u9547"
    ],
    "name:dut_x_preferred":[
        "Villanueva del Conde"
    ],
    "name:eng_x_preferred":[
        "Villanueva del Conde"
    ],
    "name:fre_x_preferred":[
        "Villanueva del Conde"
    ],
    "name:ger_x_preferred":[
        "Villanueva del Conde"
    ],
    "name:hun_x_preferred":[
        "Villanueva del Conde"
    ],
    "name:ina_x_preferred":[
        "Villanueva del Conde"
    ],
    "name:ita_x_preferred":[
        "Villanueva del Conde"
    ],
    "name:jpn_x_preferred":[
        "\u30d3\u30b8\u30e3\u30cc\u30a8\u30d0\u30fb\u30c7\u30eb\u30fb\u30b3\u30f3\u30c7"
    ],
    "name:kaz_x_preferred":[
        "\u0412\u0438\u043b\u044c\u044f\u043d\u0443\u044d\u0432\u0430-\u0434\u0435\u043b\u044c-\u041a\u043e\u043d\u0434\u0435"
    ],
    "name:may_x_preferred":[
        "Villanueva del Conde"
    ],
    "name:nan_x_preferred":[
        "Villanueva del Conde"
    ],
    "name:oci_x_preferred":[
        "Villanueva del Conde"
    ],
    "name:pol_x_preferred":[
        "Villanueva del Conde"
    ],
    "name:por_x_preferred":[
        "Villanueva del Conde"
    ],
    "name:rus_x_preferred":[
        "\u0412\u0438\u043b\u044c\u044f\u043d\u0443\u044d\u0432\u0430-\u0434\u0435\u043b\u044c-\u041a\u043e\u043d\u0434\u0435"
    ],
    "name:spa_x_preferred":[
        "Villanueva del Conde"
    ],
    "name:swe_x_preferred":[
        "Villanueva del Conde"
    ],
    "name:ukr_x_preferred":[
        "\u0412\u0456\u043b\u044c\u044f\u043d\u0443\u0435\u0432\u0430-\u0434\u0435\u043b\u044c-\u041a\u043e\u043d\u0434\u0435"
    ],
    "name:uzb_x_preferred":[
        "Villanueva del Conde"
    ],
    "name:vie_x_preferred":[
        "Villanueva del Conde"
    ],
    "name:war_x_preferred":[
        "Villanueva del Conde"
    ],
    "qs_pg:aaroncc":"ES",
    "qs_pg:gn_country":"ES",
    "qs_pg:gn_fcode":"PPLA3",
    "qs_pg:gn_pop":222,
    "qs_pg:name":"Villanueva del Conde",
    "qs_pg:name_adm0":"Espa\u00f1a",
    "qs_pg:name_adm1":"Castilla y Le\u00f3n",
    "qs_pg:photos_9r":0,
    "qs_pg:photos_sr":0,
    "qs_pg:pop_sr":2,
    "qs_pg:qs_pg_placetype":"locality",
    "qs_pg:qs_pg_placetype_gp":"Town",
    "qs_pg:woe_adm0":23424950,
    "woe:adm0_id":23424950,
    "woe:name_adm0":"Espa\u00f1a",
    "woe:name_adm1":"Castilla y Le\u00f3n",
    "woe:placetype":"Town",
    "wof:name":"Villanueva del Conde",
    "wof:placetype":"locality",
    "wof:population":222
},
  "geometry": {"coordinates":[-6.0121,40.51039],"type":"Point"}
}