{
  "type": "Feature",
  "properties": {
    "gn:admin1_code":"58",
    "gn:admin2_code":"C",
    "gn:admin3_code":"15093",
    "gn:asciiname":"Pombal",
    "gn:country_code":"ES",
    "gn:dem":198,
    "gn:feature_class":"P",
    "gn:feature_code":"PPL",
    "gn:name":"Pombal",
    "gn:population":0,
    "gn:timezone":"Europe/Madrid",
    "iso:country":"ES",
    "wof:name":"Pombal",
    "wof:placetype":"locality"
},
  "geometry": {"coordinates":[-8.94304,43.15831],"type":"Point"}
}