{
  "type": "Feature",
  "properties": {
    "gn:gn_country":"ES",
    "gn:gn_fcode":"PPL",
    "gn:gn_pop":0,
    "iso:country":"ES",
    "name:ara_x_preferred":[
        "\u063a\u0631\u0627\u064a\u062c\u0627\u0644\u0628\u0627"
    ],
    "name:arg_x_preferred":[
        "Grijalba"
    ],
    "name:ast_x_preferred":[
        "Grijalba"
    ],
    "name:cat_x_preferred":[
        "Grijalba"
    ],
    "name:ceb_x_preferred":[
        "Grijalba"
    ],
    "name:eus_x_preferred":[
        "Grijalba"
    ],
    "name:fas_x_preferred":[
        "\u06af\u0631\u06cc\u062e\u0627\u0644\u0628\u0627"
    ],
    "name:fra_x_preferred":[
        "Grijalba"
    ],
    "name:glg_x_preferred":[
        "Grijalba"
    ],
    "name:haw_x_preferred":[
        "Grijalba"
    ],
    "name:hun_x_preferred":[
        "Grijalba"
    ],
    "name:ina_x_preferred":[
        "Grijalba"
    ],
    "name:ita_x_preferred":[
        "Grijalba"
    ],
    "name:msa_x_preferred":[
        "Grijalba"
    ],
    "name:nld_x_preferred":[
        "Grijalba"
    ],
    "name:oci_x_preferred":[
        "Grijalba"
    ],
    "name:pol_x_preferred":[
        "Grijalba"
    ],
    "name:por_x_preferred":[
        "Grijalba"
    ],
    "name:rus_x_preferred":[
        "\u0413\u0440\u0438\u0445\u0430\u043b\u044c\u0431\u0430"
    ],
    "name:spa_x_preferred":[
        "Grijalba"
    ],
    "name:swe_x_preferred":[
        "Grijalba"
    ],
    "name:tpi_x_preferred":[
        "Grijalba"
    ],
    "name:ukr_x_preferred":[
        "\u0413\u0440\u0456\u0445\u0430\u043b\u044c\u0431\u0430"
    ],
    "name:unk_x_variant":[
        "San Juli\u00e1n"
    ],
    "name:vie_x_preferred":[
        "Grijalba"
    ],
    "name:war_x_preferred":[
        "Grijalba"
    ],
    "name:zho_x_preferred":[
        "\u683c\u91cc\u54c8\u5c14\u74e6"
    ],
    "qs_pg:aaroncc":"ES",
    "qs_pg:gn_country":"ES",
    "qs_pg:gn_fcode":"PPL",
    "qs_pg:gn_pop":0,
    "qs_pg:name":"Grijalba",
    "qs_pg:name_adm0":"Espa\u00f1a",
    "qs_pg:name_adm1":"Galicia",
    "qs_pg:photos":14,
    "qs_pg:photos_1k":3,
    "qs_pg:photos_9k":1,
    "qs_pg:photos_9r":1,
    "qs_pg:photos_all":14,
    "qs_pg:photos_sr":1,
    "qs_pg:pop_sr":0,
    "qs_pg:qs_pg_placetype":"locality",
    "qs_pg:qs_pg_placetype_gp":"Town",
    "qs_pg:woe_adm0":23424950,
    "woe:adm0_id":23424950,
    "woe:name_adm0":"Espa\u00f1a",
    "woe:name_adm1":"Galicia",
    "woe:placetype":"Town",
    "wof:name":"Grijalba",
    "wof:placetype":"locality"
},
  "geometry": {"coordinates":[-7.98333,43.08333],"type":"Point"}
}