{
  "type": "Feature",
  "properties": {
    "gn:admin1_code":"52",
    "gn:admin2_code":"HU",
    "gn:admin3_code":"22060",
    "gn:asciiname":"Las Pueblas",
    "gn:country_code":"ES",
    "gn:dem":271,
    "gn:feature_class":"P",
    "gn:feature_code":"PPL",
    "gn:name":"Las Pueblas",
    "gn:population":0,
    "gn:timezone":"Europe/Madrid",
    "iso:country":"ES",
    "wof:name":"Las Pueblas",
    "wof:placetype":"locality"
},
  "geometry": {"coordinates":[0.2912,41.81305],"type":"Point"}
}