{
  "type": "Feature",
  "properties": {
    "gn:admin1_code":"53",
    "gn:admin2_code":"TF",
    "gn:admin3_code":"38037",
    "gn:asciiname":"Las Nieves",
    "gn:country_code":"ES",
    "gn:dem":49,
    "gn:feature_class":"P",
    "gn:feature_code":"PPL",
    "gn:name":"Las Nieves",
    "gn:population":0,
    "gn:timezone":"Atlantic/Canary",
    "iso:country":"ES",
    "name:ceb_x_preferred":[
        "Las Nieves"
    ],
    "name:deu_x_preferred":[
        "Las Nieves"
    ],
    "name:ita_x_preferred":[
        "Las Nieves"
    ],
    "name:nld_x_preferred":[
        "Las Nieves"
    ],
    "name:spa_x_preferred":[
        "Las Nieves"
    ],
    "name:swe_x_preferred":[
        "Las Nieves"
    ],
    "wof:name":"Las Nieves",
    "wof:placetype":"locality"
},
  "geometry": {"coordinates":[-17.76667,28.68333],"type":"Point"}
}