{
  "type": "Feature",
  "properties": {
    "gn:admin1_code":"58",
    "gn:admin2_code":"OR",
    "gn:admin3_code":"32083",
    "gn:asciiname":"Corexido",
    "gn:country_code":"ES",
    "gn:dem":980,
    "gn:feature_class":"P",
    "gn:feature_code":"PPL",
    "gn:name":"Corexido",
    "gn:population":0,
    "gn:timezone":"Europe/Madrid",
    "iso:country":"ES",
    "wof:name":"Corexido",
    "wof:placetype":"locality"
},
  "geometry": {"coordinates":[-7.05,42.28333],"type":"Point"}
}