{
  "type": "Feature",
  "properties": {
    "gn:admin1_code":"52",
    "gn:admin2_code":"TE",
    "gn:admin3_code":"44158",
    "gn:asciiname":"Incosas",
    "gn:country_code":"ES",
    "gn:dem":986,
    "gn:feature_class":"P",
    "gn:feature_code":"PPL",
    "gn:name":"Incosas",
    "gn:population":0,
    "gn:timezone":"Europe/Madrid",
    "iso:country":"ES",
    "name:und_x_variant":[
        "Caser\u00edo Incosas",
        "Masia de las Incosas",
        "Incosas"
    ],
    "wof:name":"Incosas",
    "wof:placetype":"locality"
},
  "geometry": {"coordinates":[-0.74426,40.21322],"type":"Point"}
}