{
  "type": "Feature",
  "properties": {
    "gn:admin1_code":"39",
    "gn:admin2_code":"S",
    "gn:admin3_code":"39014",
    "gn:asciiname":"Viana",
    "gn:country_code":"ES",
    "gn:dem":464,
    "gn:feature_class":"P",
    "gn:feature_code":"PPL",
    "gn:name":"Via\u00f1a",
    "gn:population":0,
    "gn:timezone":"Europe/Madrid",
    "iso:country":"ES",
    "name:bpy_x_preferred":[
        "\u09ad\u09bf\u09af\u09bc\u09be\u09a8\u09be"
    ],
    "name:bre_x_preferred":[
        "Viana"
    ],
    "name:ceb_x_preferred":[
        "Viana"
    ],
    "name:deu_x_preferred":[
        "Viana"
    ],
    "name:fra_x_preferred":[
        "Viana"
    ],
    "name:glg_x_preferred":[
        "Viana"
    ],
    "name:ita_x_preferred":[
        "Viana"
    ],
    "name:jpn_x_preferred":[
        "\u30d3\u30a2\u30ca"
    ],
    "name:mlg_x_preferred":[
        "Viana"
    ],
    "name:nep_x_preferred":[
        "\u092d\u093f\u090f\u0928\u093e"
    ],
    "name:nld_x_preferred":[
        "Viana"
    ],
    "name:nor_x_preferred":[
        "Viana"
    ],
    "name:oci_x_preferred":[
        "Viana"
    ],
    "name:por_x_preferred":[
        "Viana"
    ],
    "name:spa_x_preferred":[
        "Viana"
    ],
    "name:swe_x_preferred":[
        "Viana"
    ],
    "name:ukr_x_preferred":[
        "\u0412\u0456\u0430\u043d\u0430"
    ],
    "name:vie_x_preferred":[
        "Viana"
    ],
    "name:vol_x_preferred":[
        "Viana"
    ],
    "wof:name":"Viana",
    "wof:placetype":"locality"
},
  "geometry": {"coordinates":[-4.2589,43.18954],"type":"Point"}
}