{
  "type": "Feature",
  "properties": {
    "gn:admin1_code":"55",
    "gn:admin2_code":"SA",
    "gn:admin3_code":"37106",
    "gn:asciiname":"Grandes",
    "gn:country_code":"ES",
    "gn:dem":789,
    "gn:feature_class":"P",
    "gn:feature_code":"PPL",
    "gn:name":"Grandes",
    "gn:population":0,
    "gn:timezone":"Europe/Madrid",
    "iso:country":"ES",
    "wof:name":"Grandes",
    "wof:placetype":"locality"
},
  "geometry": {"coordinates":[-6.21543,40.98004],"type":"Point"}
}