{
  "type": "Feature",
  "properties": {
    "gn:gn_country":"ES",
    "gn:gn_fcode":"PPLA3",
    "gn:gn_pop":168,
    "gn:population":168,
    "iso:country":"ES",
    "name:ara_x_preferred":[
        "\u0633\u0627\u0646 \u062e\u0648\u0627\u0646 \u062f\u064a\u0644 \u0645\u0648\u0646\u062a\u064a"
    ],
    "name:arg_x_preferred":[
        "San Juan del Monte"
    ],
    "name:ast_x_preferred":[
        "San Juan del Monte"
    ],
    "name:cat_x_preferred":[
        "San Juan del Monte"
    ],
    "name:ceb_x_preferred":[
        "San Juan del Monte"
    ],
    "name:deu_x_preferred":[
        "San Juan del Monte"
    ],
    "name:eng_x_preferred":[
        "San Juan del Monte"
    ],
    "name:epo_x_preferred":[
        "San Juan del Monte"
    ],
    "name:eus_x_preferred":[
        "San Juan del Monte"
    ],
    "name:fas_x_preferred":[
        "\u0633\u0627\u0646 \u062e\u0648\u0627\u0646 \u062f\u0644 \u0645\u0646\u062a\u0647"
    ],
    "name:fra_x_preferred":[
        "San Juan del Monte"
    ],
    "name:glg_x_preferred":[
        "San Juan del Monte"
    ],
    "name:haw_x_preferred":[
        "San Juan del Monte"
    ],
    "name:hun_x_preferred":[
        "San Juan del Monte"
    ],
    "name:ina_x_preferred":[
        "San Juan del Monte"
    ],
    "name:ita_x_preferred":[
        "San Juan del Monte"
    ],
    "name:msa_x_preferred":[
        "San Juan del Monte"
    ],
    "name:nan_x_preferred":[
        "San Juan del Monte"
    ],
    "name:nld_x_preferred":[
        "San Juan del Monte"
    ],
    "name:oci_x_preferred":[
        "San Juan del Monte"
    ],
    "name:pol_x_preferred":[
        "San Juan del Monte"
    ],
    "name:por_x_preferred":[
        "San Juan del Monte"
    ],
    "name:rus_x_preferred":[
        "\u0421\u0430\u043d-\u0425\u0443\u0430\u043d-\u0434\u0435\u043b\u044c-\u041c\u043e\u043d\u0442\u0435"
    ],
    "name:spa_x_preferred":[
        "San Juan del Monte"
    ],
    "name:swe_x_preferred":[
        "San Juan del Monte"
    ],
    "name:ukr_x_preferred":[
        "\u0421\u0430\u043d-\u0425\u0443\u0430\u043d-\u0434\u0435\u043b\u044c-\u041c\u043e\u043d\u0442\u0435"
    ],
    "name:uzb_x_preferred":[
        "San Juan del Monte"
    ],
    "name:vie_x_preferred":[
        "San Juan del Monte"
    ],
    "name:war_x_preferred":[
        "San Juan del Monte"
    ],
    "qs_pg:aaroncc":"ES",
    "qs_pg:gn_country":"ES",
    "qs_pg:gn_fcode":"PPLA3",
    "qs_pg:gn_pop":168,
    "qs_pg:name":"San Juan del Monte",
    "qs_pg:name_adm0":"Espa\u00f1a",
    "qs_pg:name_adm1":"Castilla y Le\u00f3n",
    "qs_pg:photos_9k":1,
    "qs_pg:photos_9r":1,
    "qs_pg:photos_all":1,
    "qs_pg:photos_sr":0,
    "qs_pg:pop_sr":1,
    "qs_pg:qs_pg_placetype":"locality",
    "qs_pg:qs_pg_placetype_gp":"Town",
    "qs_pg:woe_adm0":23424950,
    "woe:adm0_id":23424950,
    "woe:name_adm0":"Espa\u00f1a",
    "woe:name_adm1":"Castilla y Le\u00f3n",
    "woe:placetype":"Town",
    "wof:name":"San Juan del Monte",
    "wof:placetype":"locality",
    "wof:population":168
},
  "geometry": {"coordinates":[-3.52337,41.68313],"type":"Point"}
}