{
  "type": "Feature",
  "properties": {
    "gn:admin1_code":"55",
    "gn:admin2_code":"P",
    "gn:admin3_code":"34174",
    "gn:asciiname":"Santiago del Val",
    "gn:country_code":"ES",
    "gn:dem":819,
    "gn:feature_class":"P",
    "gn:feature_code":"PPL",
    "gn:name":"Santiago del Val",
    "gn:population":0,
    "gn:timezone":"Europe/Madrid",
    "iso:country":"ES",
    "wof:name":"Santiago del Val",
    "wof:placetype":"locality"
},
  "geometry": {"coordinates":[-4.35731,42.20779],"type":"Point"}
}