{
  "type": "Feature",
  "properties": {
    "gn:admin1_code":"51",
    "gn:admin2_code":"GR",
    "gn:admin3_code":"18098",
    "gn:asciiname":"El Patronato",
    "gn:country_code":"ES",
    "gn:dem":1562,
    "gn:feature_class":"P",
    "gn:feature_code":"PPL",
    "gn:name":"El Patronato",
    "gn:population":0,
    "gn:timezone":"Europe/Madrid",
    "iso:country":"ES",
    "name:und_x_variant":[
        "Caser\u00edo Patronato",
        "Caser\u00edo del Patronato",
        "El Patronato"
    ],
    "wof:name":"El Patronato",
    "wof:placetype":"locality"
},
  "geometry": {"coordinates":[-2.64979,38.04327],"type":"Point"}
}