{
  "type": "Feature",
  "properties": {
    "gn:admin1_code":"58",
    "gn:admin2_code":"OR",
    "gn:admin3_code":"32076",
    "gn:asciiname":"Lamas",
    "gn:country_code":"ES",
    "gn:dem":455,
    "gn:feature_class":"P",
    "gn:feature_code":"PPL",
    "gn:name":"Lamas",
    "gn:population":0,
    "gn:timezone":"Europe/Madrid",
    "iso:country":"ES",
    "name:ceb_x_preferred":[
        "Lamas"
    ],
    "name:deu_x_preferred":[
        "Lamas"
    ],
    "name:fra_x_preferred":[
        "Lamas"
    ],
    "name:glg_x_preferred":[
        "Lamas"
    ],
    "name:ita_x_preferred":[
        "Lamas"
    ],
    "name:nds_x_preferred":[
        "Lamas"
    ],
    "name:nld_x_preferred":[
        "Lamas"
    ],
    "name:pol_x_preferred":[
        "Lamas"
    ],
    "name:por_x_preferred":[
        "Lamas"
    ],
    "name:rus_x_preferred":[
        "\u041b\u0430\u043c\u0430\u0448"
    ],
    "name:spa_x_preferred":[
        "Lamas"
    ],
    "name:swe_x_preferred":[
        "Lamas"
    ],
    "name:ukr_x_preferred":[
        "\u041b\u0430\u043c\u0430\u0448"
    ],
    "wof:name":"Lamas",
    "wof:placetype":"locality"
},
  "geometry": {"coordinates":[-8.03261,42.47188],"type":"Point"}
}