{
  "type": "Feature",
  "properties": {
    "gn:country":"ES",
    "gn:fcode":"PPL",
    "gn:population":0,
    "iso:country":"ES",
    "name:bul_x_preferred":[
        "\u0422\u043e\u0440\u0435\u043b\u0430\u043c\u0430\u0442\u0430"
    ],
    "name:cat_x_preferred":[
        "la Mata"
    ],
    "name:ceb_x_preferred":[
        "Torrelamata"
    ],
    "name:eng_x_preferred":[
        "Torre La Mata"
    ],
    "name:nob_x_preferred":[
        "La Mata"
    ],
    "name:spa_x_preferred":[
        "Torrelamata"
    ],
    "name:swe_x_preferred":[
        "Torrelamata"
    ],
    "qs_pg:aaroncc":"ES",
    "qs_pg:gn_country":"ES",
    "qs_pg:gn_fcode":"PPL",
    "qs_pg:gn_pop":0,
    "qs_pg:name":"Torrelamata",
    "qs_pg:name_adm0":"Espa\u00f1a",
    "qs_pg:name_adm1":"Comunitat Valenciana",
    "qs_pg:photos":682,
    "qs_pg:photos_1k":138,
    "qs_pg:photos_9k":3,
    "qs_pg:photos_9r":5,
    "qs_pg:photos_all":682,
    "qs_pg:photos_sr":8,
    "qs_pg:pop_sr":0,
    "qs_pg:qs_pg_placetype":"locality",
    "qs_pg:qs_pg_placetype_gp":"Town",
    "qs_pg:woe_adm0":23424950,
    "woe:adm0_id":23424950,
    "woe:name_adm0":"Espa\u00f1a",
    "woe:name_adm1":"Comunitat Valenciana",
    "woe:placetype":"Town",
    "wof:name":"Torrelamata",
    "wof:placetype":"locality"
},
  "geometry": {"coordinates":[-0.65506,38.02828],"type":"Point"}
}