{
  "type": "Feature",
  "properties": {
    "gn:admin1_code":"52",
    "gn:admin2_code":"HU",
    "gn:admin3_code":"22109",
    "gn:asciiname":"Cajol",
    "gn:country_code":"ES",
    "gn:dem":1354,
    "gn:feature_class":"P",
    "gn:feature_code":"PPL",
    "gn:name":"Cajol",
    "gn:population":0,
    "gn:timezone":"Europe/Madrid",
    "iso:country":"ES",
    "wof:name":"Cajol",
    "wof:placetype":"locality"
},
  "geometry": {"coordinates":[-0.06317,42.52977],"type":"Point"}
}