{
  "type": "Feature",
  "properties": {
    "gn:admin1_code":"58",
    "gn:admin2_code":"OR",
    "gn:admin3_code":"32060",
    "gn:asciiname":"Carballal",
    "gn:country_code":"ES",
    "gn:dem":440,
    "gn:feature_class":"P",
    "gn:feature_code":"PPL",
    "gn:name":"Carballal",
    "gn:population":0,
    "gn:timezone":"Europe/Madrid",
    "iso:country":"ES",
    "wof:name":"Carballal",
    "wof:placetype":"locality"
},
  "geometry": {"coordinates":[-7.11881,42.37004],"type":"Point"}
}