{
  "type": "Feature",
  "properties": {
    "gn:admin1_code":"55",
    "gn:admin2_code":"P",
    "gn:admin3_code":"34107",
    "gn:asciiname":"Berzosa de los Hidalgos",
    "gn:country_code":"ES",
    "gn:dem":962,
    "gn:feature_class":"P",
    "gn:feature_code":"PPL",
    "gn:name":"Berzosa de los Hidalgos",
    "gn:population":0,
    "gn:timezone":"Europe/Madrid",
    "iso:country":"ES",
    "wof:name":"Berzosa de los Hidalgos",
    "wof:placetype":"locality"
},
  "geometry": {"coordinates":[-4.44941,42.67229],"type":"Point"}
}