{
  "type": "Feature",
  "properties": {
    "gn:admin1_code":"58",
    "gn:admin2_code":"C",
    "gn:admin3_code":"15082",
    "gn:asciiname":"Raris",
    "gn:country_code":"ES",
    "gn:dem":132,
    "gn:feature_class":"P",
    "gn:feature_code":"PPL",
    "gn:name":"Rar\u00eds",
    "gn:population":0,
    "gn:timezone":"Europe/Madrid",
    "iso:country":"ES",
    "name:und_x_variant":[
        "Rar\u00eds"
    ],
    "wof:name":"Raris",
    "wof:placetype":"locality"
},
  "geometry": {"coordinates":[-8.56243,42.78212],"type":"Point"}
}