{
  "type": "Feature",
  "properties": {
    "gn:admin1_code":"34",
    "gn:admin2_code":"O",
    "gn:admin3_code":"33055",
    "gn:asciiname":"Andinas",
    "gn:country_code":"ES",
    "gn:dem":51,
    "gn:feature_class":"P",
    "gn:feature_code":"PPL",
    "gn:name":"Andinas",
    "gn:population":0,
    "gn:timezone":"Europe/Madrid",
    "iso:country":"ES",
    "wof:name":"Andinas",
    "wof:placetype":"locality"
},
  "geometry": {"coordinates":[-4.5439,43.34792],"type":"Point"}
}