{
  "type": "Feature",
  "properties": {
    "gn:country":"ES",
    "gn:fcode":"PPLA3",
    "gn:population":104,
    "iso:country":"ES",
    "name:arg_x_preferred":[
        "Ca\u00f1izar"
    ],
    "name:ast_x_preferred":[
        "Ca\u00f1izar"
    ],
    "name:cat_x_preferred":[
        "Ca\u00f1izar"
    ],
    "name:ceb_x_preferred":[
        "Ca\u00f1izar"
    ],
    "name:deu_x_preferred":[
        "Ca\u00f1izar"
    ],
    "name:eng_x_preferred":[
        "Ca\u00f1izar"
    ],
    "name:epo_x_preferred":[
        "Ca\u00f1izar"
    ],
    "name:eus_x_preferred":[
        "Ca\u00f1izar"
    ],
    "name:fra_x_preferred":[
        "Ca\u00f1izar"
    ],
    "name:hun_x_preferred":[
        "Ca\u00f1izar"
    ],
    "name:ina_x_preferred":[
        "Ca\u00f1izar"
    ],
    "name:ita_x_preferred":[
        "Ca\u00f1izar"
    ],
    "name:kaz_x_preferred":[
        "\u041a\u0430\u043d\u044c\u0438\u0441\u0430\u0440"
    ],
    "name:msa_x_preferred":[
        "Ca\u00f1izar"
    ],
    "name:nan_x_preferred":[
        "Ca\u00f1izar"
    ],
    "name:nld_x_preferred":[
        "Ca\u00f1izar"
    ],
    "name:nno_x_preferred":[
        "Ca\u00f1izar"
    ],
    "name:nob_x_preferred":[
        "Ca\u00f1izar"
    ],
    "name:oci_x_preferred":[
        "Ca\u00f1izar"
    ],
    "name:pol_x_preferred":[
        "Ca\u00f1izar"
    ],
    "name:por_x_preferred":[
        "Ca\u00f1izar"
    ],
    "name:rus_x_preferred":[
        "\u041a\u0430\u043d\u044c\u0438\u0441\u0430\u0440"
    ],
    "name:slv_x_preferred":[
        "Ca\u00f1izar"
    ],
    "name:spa_x_preferred":[
        "Ca\u00f1izar"
    ],
    "name:swe_x_preferred":[
        "Ca\u00f1izar"
    ],
    "name:ukr_x_preferred":[
        "\u041a\u0430\u043d\u044c\u0457\u0441\u0430\u0440"
    ],
    "name:vie_x_preferred":[
        "Ca\u00f1izar"
    ],
    "name:war_x_preferred":[
        "Ca\u00f1izar"
    ],
    "name:zho_x_preferred":[
        "\u5361\u5c3c\u4f0a\u8428\u5c14"
    ],
    "qs_pg:aaroncc":"ES",
    "qs_pg:gn_country":"ES",
    "qs_pg:gn_fcode":"PPLA3",
    "qs_pg:gn_pop":104,
    "qs_pg:name":"Ca\u00f1izar",
    "qs_pg:name_adm0":"Espa\u00f1a",
    "qs_pg:name_adm1":"Castilla-La Mancha",
    "qs_pg:photos_9r":0,
    "qs_pg:photos_sr":0,
    "qs_pg:pop_sr":1,
    "qs_pg:qs_pg_placetype":"locality",
    "qs_pg:qs_pg_placetype_gp":"Town",
    "qs_pg:woe_adm0":23424950,
    "woe:adm0_id":23424950,
    "woe:name_adm0":"Espa\u00f1a",
    "woe:name_adm1":"Castilla-La Mancha",
    "woe:placetype":"Town",
    "wof:name":"Ca\u00f1izar",
    "wof:placetype":"locality",
    "wof:population":104
},
  "geometry": {"coordinates":[-3.06399,40.76763],"type":"Point"}
}