{
  "type": "Feature",
  "properties": {
    "gn:gn_country":"ES",
    "gn:gn_fcode":"PPLA3",
    "gn:gn_pop":148,
    "gn:population":148,
    "iso:country":"ES",
    "name:baq_x_preferred":[
        "Labajos"
    ],
    "name:cat_x_preferred":[
        "Labajos"
    ],
    "name:chi_x_preferred":[
        "\u62c9\u74e6\u970d\u65af"
    ],
    "name:dut_x_preferred":[
        "Labajos"
    ],
    "name:eng_x_preferred":[
        "Labajos"
    ],
    "name:fre_x_preferred":[
        "Labajos"
    ],
    "name:hun_x_preferred":[
        "Labajos"
    ],
    "name:ina_x_preferred":[
        "Labajos"
    ],
    "name:ita_x_preferred":[
        "Labajos"
    ],
    "name:may_x_preferred":[
        "Labajos"
    ],
    "name:nan_x_preferred":[
        "Labajos"
    ],
    "name:oci_x_preferred":[
        "Labajos"
    ],
    "name:pol_x_preferred":[
        "Labajos"
    ],
    "name:por_x_preferred":[
        "Labajos"
    ],
    "name:rus_x_preferred":[
        "\u041b\u0430\u0431\u0430\u0445\u043e\u0441"
    ],
    "name:spa_x_preferred":[
        "Labajos"
    ],
    "name:swe_x_preferred":[
        "Labajos"
    ],
    "name:ukr_x_preferred":[
        "\u041b\u0430\u0431\u0430\u0445\u043e\u0441"
    ],
    "name:unk_x_variant":[
        "Labajoz"
    ],
    "name:vie_x_preferred":[
        "Labajos"
    ],
    "name:war_x_preferred":[
        "Labajos"
    ],
    "qs_pg:aaroncc":"ES",
    "qs_pg:gn_country":"ES",
    "qs_pg:gn_fcode":"PPLA3",
    "qs_pg:gn_pop":148,
    "qs_pg:name":"Labajos",
    "qs_pg:name_adm0":"Espa\u00f1a",
    "qs_pg:name_adm1":"Castilla y Le\u00f3n",
    "qs_pg:photos":306,
    "qs_pg:photos_1k":62,
    "qs_pg:photos_9k":1,
    "qs_pg:photos_9r":5,
    "qs_pg:photos_all":306,
    "qs_pg:photos_sr":5,
    "qs_pg:pop_sr":1,
    "qs_pg:qs_pg_placetype":"locality",
    "qs_pg:qs_pg_placetype_gp":"Town",
    "qs_pg:woe_adm0":23424950,
    "woe:adm0_id":23424950,
    "woe:name_adm0":"Espa\u00f1a",
    "woe:name_adm1":"Castilla y Le\u00f3n",
    "woe:placetype":"Town",
    "wof:name":"Labajos",
    "wof:placetype":"locality",
    "wof:population":148
},
  "geometry": {"coordinates":[-4.52005,40.84335],"type":"Point"}
}