{
  "type": "Feature",
  "properties": {
    "gn:admin1_code":"51",
    "gn:admin2_code":"J",
    "gn:admin3_code":"23065",
    "gn:asciiname":"El Aguadero",
    "gn:country_code":"ES",
    "gn:dem":654,
    "gn:feature_class":"P",
    "gn:feature_code":"PPL",
    "gn:name":"El Aguadero",
    "gn:population":0,
    "gn:timezone":"Europe/Madrid",
    "iso:country":"ES",
    "name:und_x_variant":[
        "Caser\u00edo El Aguadero",
        "Cortijo del Aguadero",
        "El Aguadero"
    ],
    "wof:name":"El Aguadero",
    "wof:placetype":"locality"
},
  "geometry": {"coordinates":[-2.69608,38.31475],"type":"Point"}
}