{
  "type": "Feature",
  "properties": {
    "iso:country":"ES",
    "name:ara_x_preferred":[
        "\u062a\u0648\u0631\u064a\u0628\u0644\u0627\u0646\u0643\u0627"
    ],
    "name:arg_x_preferred":[
        "Torreblanca"
    ],
    "name:cat_x_preferred":[
        "Torreblanca"
    ],
    "name:ceb_x_preferred":[
        "Torreblanca"
    ],
    "name:eus_x_preferred":[
        "Torreblanca"
    ],
    "name:fra_x_preferred":[
        "Torreblanca"
    ],
    "name:hun_x_preferred":[
        "Torreblanca"
    ],
    "name:ita_x_preferred":[
        "Torreblanca"
    ],
    "name:msa_x_preferred":[
        "Torreblanca"
    ],
    "name:nld_x_preferred":[
        "Torreblanca"
    ],
    "name:oci_x_preferred":[
        "Torreblanca"
    ],
    "name:pol_x_preferred":[
        "Torreblanca"
    ],
    "name:por_x_preferred":[
        "Torreblanca"
    ],
    "name:rus_x_preferred":[
        "\u0422\u043e\u0440\u0440\u0435\u0431\u043b\u0430\u043d\u043a\u0430"
    ],
    "name:spa_x_preferred":[
        "Torreblanca"
    ],
    "name:sqi_x_preferred":[
        "Torreblanca"
    ],
    "name:swe_x_preferred":[
        "Torreblanca"
    ],
    "name:ukr_x_preferred":[
        "\u0422\u043e\u0440\u0440\u0435\u0431\u043b\u0430\u043d\u043a\u0430"
    ],
    "name:uzb_x_preferred":[
        "Torreblanca"
    ],
    "name:vie_x_preferred":[
        "Torreblanca"
    ],
    "name:war_x_preferred":[
        "Torreblanca"
    ],
    "name:zho_x_preferred":[
        "\u6258\u96f7\u592b\u5170\u5361"
    ],
    "wof:name":"Torreblanca",
    "wof:placetype":"neighbourhood"
},
  "geometry": {"coordinates":[-5.90811227958956,37.38543007315091],"type":"Point"}
}