{
  "type": "Feature",
  "properties": {
    "iso:country":"ES",
    "wof:name":"Torreblanca",
    "wof:placetype":"neighbourhood"
},
  "geometry": {"coordinates":[-5.90811227958956,37.38543007315091],"type":"Point"}
}