{
  "type": "Feature",
  "properties": {
    "gn:admin1_code":"55",
    "gn:admin2_code":"AV",
    "gn:admin3_code":"05228",
    "gn:asciiname":"Casas de Navancuerda",
    "gn:country_code":"ES",
    "gn:dem":1281,
    "gn:feature_class":"P",
    "gn:feature_code":"PPL",
    "gn:name":"Casas de Navancuerda",
    "gn:population":0,
    "gn:timezone":"Europe/Madrid",
    "iso:country":"ES",
    "wof:name":"Casas de Navancuerda",
    "wof:placetype":"locality"
},
  "geometry": {"coordinates":[-5.33152,40.44013],"type":"Point"}
}