{
  "type": "Feature",
  "properties": {
    "gn:gn_country":"ES",
    "gn:gn_fcode":"PPLA3",
    "gn:gn_pop":380,
    "gn:population":380,
    "iso:country":"ES",
    "name:ara_x_preferred":[
        "\u0631\u0627\u062c\u0648\u0644"
    ],
    "name:cat_x_preferred":[
        "R\u00e1gol"
    ],
    "name:eng_x_preferred":[
        "R\u00e1gol"
    ],
    "name:epo_x_preferred":[
        "R\u00e1gol"
    ],
    "name:eus_x_preferred":[
        "R\u00e1gol"
    ],
    "name:fas_x_preferred":[
        "\u0631\u0627\u06af\u0648\u0644"
    ],
    "name:fra_x_preferred":[
        "R\u00e1gol"
    ],
    "name:hat_x_preferred":[
        "R\u00e1gol"
    ],
    "name:hun_x_preferred":[
        "R\u00e1gol"
    ],
    "name:hye_x_preferred":[
        "\u054c\u0561\u0563\u0578\u056c"
    ],
    "name:ina_x_preferred":[
        "R\u00e1gol"
    ],
    "name:ita_x_preferred":[
        "R\u00e1gol"
    ],
    "name:mkd_x_preferred":[
        "\u0420\u0430\u0433\u043e\u043b"
    ],
    "name:msa_x_preferred":[
        "R\u00e1gol"
    ],
    "name:nan_x_preferred":[
        "R\u00e1gol"
    ],
    "name:nld_x_preferred":[
        "R\u00e1gol"
    ],
    "name:oci_x_preferred":[
        "R\u00e1gol"
    ],
    "name:pol_x_preferred":[
        "R\u00e1gol"
    ],
    "name:ron_x_preferred":[
        "R\u00e1gol"
    ],
    "name:rus_x_preferred":[
        "\u0420\u0430\u0433\u043e\u043b\u044c"
    ],
    "name:spa_x_preferred":[
        "R\u00e1gol"
    ],
    "name:swe_x_preferred":[
        "R\u00e1gol"
    ],
    "name:tur_x_preferred":[
        "R\u00e1gol"
    ],
    "name:ukr_x_preferred":[
        "\u0420\u0430\u0433\u043e\u043b\u044c"
    ],
    "name:uzb_x_preferred":[
        "R\u00e1gol"
    ],
    "name:vie_x_preferred":[
        "R\u00e1gol"
    ],
    "name:war_x_preferred":[
        "R\u00e1gol"
    ],
    "name:zho_x_preferred":[
        "\u62c9\u6208\u5c14"
    ],
    "qs_pg:aaroncc":"ES",
    "qs_pg:gn_country":"ES",
    "qs_pg:gn_fcode":"PPLA3",
    "qs_pg:gn_pop":380,
    "qs_pg:name":"R\u00e1gol",
    "qs_pg:name_adm0":"Espa\u00f1a",
    "qs_pg:name_adm1":"Andaluc\u00eda",
    "qs_pg:photos":12,
    "qs_pg:photos_1k":2,
    "qs_pg:photos_9k":1,
    "qs_pg:photos_9r":1,
    "qs_pg:photos_all":12,
    "qs_pg:photos_sr":1,
    "qs_pg:pop_sr":2,
    "qs_pg:qs_pg_placetype":"locality",
    "qs_pg:qs_pg_placetype_gp":"Town",
    "qs_pg:woe_adm0":23424950,
    "woe:adm0_id":23424950,
    "woe:name_adm0":"Espa\u00f1a",
    "woe:name_adm1":"Andaluc\u00eda",
    "woe:placetype":"Town",
    "wof:name":"R\u00e1gol",
    "wof:placetype":"locality",
    "wof:population":380
},
  "geometry": {"coordinates":[-2.68178,36.99523],"type":"Point"}
}