{
  "type": "Feature",
  "properties": {
    "gn:admin1_code":"55",
    "gn:admin2_code":"P",
    "gn:admin3_code":"34126",
    "gn:asciiname":"Lobera",
    "gn:country_code":"ES",
    "gn:dem":896,
    "gn:feature_class":"P",
    "gn:feature_code":"PPL",
    "gn:name":"Lobera",
    "gn:population":0,
    "gn:timezone":"Europe/Madrid",
    "iso:country":"ES",
    "name:ceb_x_preferred":[
        "Lobera"
    ],
    "name:fra_x_preferred":[
        "Lobera"
    ],
    "name:spa_x_preferred":[
        "Lobera"
    ],
    "name:swe_x_preferred":[
        "Lobera"
    ],
    "wof:name":"Lobera",
    "wof:placetype":"locality"
},
  "geometry": {"coordinates":[-4.7291,42.49944],"type":"Point"}
}