{
  "type": "Feature",
  "properties": {
    "gn:admin1_code":"54",
    "gn:admin2_code":"TO",
    "gn:admin3_code":"45181",
    "gn:asciiname":"Aldea de Arango",
    "gn:country_code":"ES",
    "gn:dem":553,
    "gn:feature_class":"P",
    "gn:feature_code":"PPL",
    "gn:name":"Aldea de Arango",
    "gn:population":0,
    "gn:timezone":"Europe/Madrid",
    "iso:country":"ES",
    "wof:name":"Aldea de Arango",
    "wof:placetype":"locality"
},
  "geometry": {"coordinates":[-4.99271,40.0956],"type":"Point"}
}