{
  "type": "Feature",
  "properties": {
    "gn:gn_country":"ES",
    "gn:gn_fcode":"PPL",
    "gn:gn_pop":0,
    "iso:country":"ES",
    "name:bel_x_preferred":[
        "\u0411\u043e\u0440"
    ],
    "name:bos_x_preferred":[
        "Bor"
    ],
    "name:bul_x_preferred":[
        "\u0411\u043e\u0440"
    ],
    "name:cat_x_preferred":[
        "Bor"
    ],
    "name:ceb_x_preferred":[
        "Bor"
    ],
    "name:ces_x_preferred":[
        "Bor"
    ],
    "name:dan_x_preferred":[
        "Bor"
    ],
    "name:deu_x_preferred":[
        "Bor"
    ],
    "name:fin_x_preferred":[
        "Bor"
    ],
    "name:fra_x_preferred":[
        "Bor"
    ],
    "name:frr_x_preferred":[
        "Bor"
    ],
    "name:heb_x_preferred":[
        "\u05d1\u05d5\u05e8"
    ],
    "name:hrv_x_preferred":[
        "Bor"
    ],
    "name:hun_x_preferred":[
        "Bor"
    ],
    "name:hye_x_preferred":[
        "\u0532\u0578\u0580"
    ],
    "name:kaz_x_preferred":[
        "\u0411\u043e\u0440"
    ],
    "name:mkd_x_preferred":[
        "\u0411\u043e\u0440"
    ],
    "name:myv_x_preferred":[
        "\u041a\u0430\u043b\u0433\u043e\u0434\u043e \u043c\u0430\u0440\u044c"
    ],
    "name:nds_x_preferred":[
        "Bor"
    ],
    "name:nld_x_preferred":[
        "Bor"
    ],
    "name:nno_x_preferred":[
        "Bor"
    ],
    "name:nor_x_preferred":[
        "Bor"
    ],
    "name:oci_x_preferred":[
        "Bor"
    ],
    "name:pol_x_preferred":[
        "Bor"
    ],
    "name:por_x_preferred":[
        "Bor"
    ],
    "name:ron_x_preferred":[
        "Bor"
    ],
    "name:rus_x_preferred":[
        "\u0411\u043e\u0440"
    ],
    "name:sco_x_preferred":[
        "Bor"
    ],
    "name:slk_x_preferred":[
        "Bor"
    ],
    "name:slv_x_preferred":[
        "Bor"
    ],
    "name:spa_x_preferred":[
        "Bor"
    ],
    "name:srp_x_preferred":[
        "\u0411\u043e\u0440"
    ],
    "name:swe_x_preferred":[
        "Bor"
    ],
    "name:tur_x_preferred":[
        "Bor"
    ],
    "name:ukr_x_preferred":[
        "\u0411\u043e\u0440"
    ],
    "name:vep_x_preferred":[
        "Bor"
    ],
    "qs_pg:aaroncc":"ES",
    "qs_pg:gn_country":"ES",
    "qs_pg:gn_fcode":"PPL",
    "qs_pg:gn_pop":0,
    "qs_pg:name":"Bor",
    "qs_pg:name_adm0":"Espa\u00f1a",
    "qs_pg:name_adm1":"Catalunya",
    "qs_pg:photos":28,
    "qs_pg:photos_1k":6,
    "qs_pg:photos_9k":1,
    "qs_pg:photos_9r":2,
    "qs_pg:photos_all":28,
    "qs_pg:photos_sr":2,
    "qs_pg:pop_sr":0,
    "qs_pg:qs_pg_placetype":"locality",
    "qs_pg:qs_pg_placetype_gp":"Town",
    "qs_pg:woe_adm0":23424950,
    "woe:adm0_id":23424950,
    "woe:name_adm0":"Espa\u00f1a",
    "woe:name_adm1":"Catalunya",
    "woe:placetype":"Town",
    "wof:name":"Bor",
    "wof:placetype":"locality"
},
  "geometry": {"coordinates":[1.80262,42.34656],"type":"Point"}
}