{
  "type": "Feature",
  "properties": {
    "gn:admin1_code":"56",
    "gn:admin2_code":"B",
    "gn:admin3_code":"08307",
    "gn:asciiname":"Vilanova i la Geltru",
    "gn:country_code":"ES",
    "gn:dem":25,
    "gn:feature_class":"P",
    "gn:feature_code":"PPL",
    "gn:name":"Vilanova i la Geltr\u00fa",
    "gn:population":65890,
    "gn:timezone":"Europe/Madrid",
    "iso:country":"ES",
    "name:cat_x_preferred":[
        "Vilanova i la Geltr\u00fa"
    ],
    "name:cat_x_variant":[
        "Vilanova"
    ],
    "name:deu_x_preferred":[
        "Vilanova i la Geltr\u00fa"
    ],
    "name:eng_x_preferred":[
        "Vilanova i la Geltr\u00fa"
    ],
    "name:epo_x_preferred":[
        "Vilanova i la Geltr\u00fa"
    ],
    "name:est_x_preferred":[
        "Vilanova i la Geltr\u00fa"
    ],
    "name:eus_x_preferred":[
        "Vilanova i la Geltru"
    ],
    "name:ita_x_preferred":[
        "Vilanova i la Geltr\u00fa"
    ],
    "name:nld_x_preferred":[
        "Vilanova i la Geltr\u00fa"
    ],
    "name:por_x_preferred":[
        "Vilanova i la Geltr\u00fa"
    ],
    "name:spa_x_preferred":[
        "Vilanova i la Geltr\u00fa"
    ],
    "name:tah_x_preferred":[
        "Vilanova i la Geltr\u00fa"
    ],
    "wof:name":"Vilanova i la Geltru",
    "wof:placetype":"locality",
    "wof:population":65890
},
  "geometry": {"coordinates":[1.72511,41.22392],"type":"Point"}
}