{
  "type": "Feature",
  "properties": {
    "gn:admin1_code":"54",
    "gn:admin2_code":"AB",
    "gn:admin3_code":"02074",
    "gn:asciiname":"Albojarico",
    "gn:country_code":"ES",
    "gn:dem":622,
    "gn:feature_class":"P",
    "gn:feature_code":"PPL",
    "gn:name":"Albojarico",
    "gn:population":0,
    "gn:timezone":"Europe/Madrid",
    "iso:country":"ES",
    "name:und_x_variant":[
        "Caser\u00edo Albojarico",
        "Alborajico",
        "Albojarico"
    ],
    "wof:name":"Albojarico",
    "wof:placetype":"locality"
},
  "geometry": {"coordinates":[-1.63417,38.59289],"type":"Point"}
}