{
  "type": "Feature",
  "properties": {
    "gn:admin1_code":"51",
    "gn:admin2_code":"J",
    "gn:admin3_code":"23099",
    "gn:asciiname":"Los Villares",
    "gn:country_code":"ES",
    "gn:dem":617,
    "gn:feature_class":"P",
    "gn:feature_code":"PPL",
    "gn:name":"Los Villares",
    "gn:population":0,
    "gn:timezone":"Europe/Madrid",
    "iso:country":"ES",
    "wof:name":"Los Villares",
    "wof:placetype":"locality"
},
  "geometry": {"coordinates":[-3.81868,37.69146],"type":"Point"}
}