{
  "type": "Feature",
  "properties": {
    "gn:admin1_code":"51",
    "gn:admin2_code":"J",
    "gn:admin3_code":"23099",
    "gn:asciiname":"Los Villares",
    "gn:country_code":"ES",
    "gn:dem":617,
    "gn:feature_class":"P",
    "gn:feature_code":"PPL",
    "gn:name":"Los Villares",
    "gn:population":0,
    "gn:timezone":"Europe/Madrid",
    "iso:country":"ES",
    "name:ara_x_preferred":[
        "\u0644\u0648\u0633 \u0641\u064a\u0627\u0631\u064a\u0633"
    ],
    "name:azb_x_preferred":[
        "\u0644\u0633 \u0628\u06cc\u06cc\u0627\u0631\u0633"
    ],
    "name:cat_x_preferred":[
        "Los Villares"
    ],
    "name:eus_x_preferred":[
        "Los Villares"
    ],
    "name:fas_x_preferred":[
        "\u0644\u0633 \u0628\u06cc\u06cc\u0627\u0631\u0633"
    ],
    "name:fra_x_preferred":[
        "Los Villares"
    ],
    "name:hat_x_preferred":[
        "Los Villares"
    ],
    "name:hun_x_preferred":[
        "Los Villares"
    ],
    "name:hye_x_preferred":[
        "\u053c\u0578\u057d \u054e\u056b\u056c\u0575\u0561\u0580\u0565\u057d"
    ],
    "name:ita_x_preferred":[
        "Los Villares"
    ],
    "name:msa_x_preferred":[
        "Los Villares"
    ],
    "name:nld_x_preferred":[
        "Los Villares"
    ],
    "name:oci_x_preferred":[
        "Los Villares"
    ],
    "name:pol_x_preferred":[
        "Los Villares"
    ],
    "name:por_x_preferred":[
        "Los Villares"
    ],
    "name:rus_x_preferred":[
        "\u041b\u043e\u0441-\u0412\u0438\u043b\u044c\u044f\u0440\u0435\u0441"
    ],
    "name:spa_x_preferred":[
        "Los Villares"
    ],
    "name:szl_x_preferred":[
        "Los Villares"
    ],
    "name:tur_x_preferred":[
        "Los Villares"
    ],
    "name:ukr_x_preferred":[
        "\u041b\u043e\u0441-\u0412\u0456\u043b\u044c\u044f\u0440\u0435\u0441"
    ],
    "name:uzb_x_preferred":[
        "Los Villares"
    ],
    "name:vie_x_preferred":[
        "Los Villares"
    ],
    "name:war_x_preferred":[
        "Los Villares"
    ],
    "name:zho_x_preferred":[
        "\u6d1b\u65af\u7ef4\u5229\u4e9a\u96f7\u65af"
    ],
    "wof:name":"Los Villares",
    "wof:placetype":"locality"
},
  "geometry": {"coordinates":[-3.81868,37.69146],"type":"Point"}
}