{
  "type": "Feature",
  "properties": {
    "gn:admin1_code":"55",
    "gn:admin2_code":"SO",
    "gn:admin3_code":"42165",
    "gn:asciiname":"Fuentebella",
    "gn:country_code":"ES",
    "gn:dem":1117,
    "gn:feature_class":"P",
    "gn:feature_code":"PPL",
    "gn:name":"Fuentebella",
    "gn:population":0,
    "gn:timezone":"Europe/Madrid",
    "iso:country":"ES",
    "wof:name":"Fuentebella",
    "wof:placetype":"locality"
},
  "geometry": {"coordinates":[-2.15499,42.03266],"type":"Point"}
}