{
  "type": "Feature",
  "properties": {
    "gn:admin1_code":"34",
    "gn:admin2_code":"O",
    "gn:admin3_code":"33037",
    "gn:asciiname":"La Rebollada",
    "gn:country_code":"ES",
    "gn:dem":289,
    "gn:feature_class":"P",
    "gn:feature_code":"PPL",
    "gn:name":"La Rebollada",
    "gn:population":0,
    "gn:timezone":"Europe/Madrid",
    "iso:country":"ES",
    "wof:name":"La Rebollada",
    "wof:placetype":"locality"
},
  "geometry": {"coordinates":[-5.79108,43.26927],"type":"Point"}
}