{
  "type": "Feature",
  "properties": {
    "gn:admin1_code":"55",
    "gn:admin2_code":"BU",
    "gn:admin3_code":"09221",
    "gn:asciiname":"Cojobar",
    "gn:country_code":"ES",
    "gn:dem":878,
    "gn:feature_class":"P",
    "gn:feature_code":"PPL",
    "gn:name":"Coj\u00f3bar",
    "gn:population":0,
    "gn:timezone":"Europe/Madrid",
    "iso:country":"ES",
    "wof:name":"Cojobar",
    "wof:placetype":"locality"
},
  "geometry": {"coordinates":[-3.66926,42.24644],"type":"Point"}
}