{
  "type": "Feature",
  "properties": {
    "gn:admin1_code":"51",
    "gn:admin2_code":"J",
    "gn:admin3_code":"23095",
    "gn:asciiname":"La Caleruela",
    "gn:country_code":"ES",
    "gn:dem":425,
    "gn:feature_class":"P",
    "gn:feature_code":"PPL",
    "gn:name":"La Caleruela",
    "gn:population":0,
    "gn:timezone":"Europe/Madrid",
    "iso:country":"ES",
    "name:und_x_variant":[
        "Cortijada La Caleruela",
        "La Caleruela"
    ],
    "wof:name":"La Caleruela",
    "wof:placetype":"locality"
},
  "geometry": {"coordinates":[-3.09699,38.04259],"type":"Point"}
}