{
  "type": "Feature",
  "properties": {
    "gn:admin1_code":"59",
    "gn:admin2_code":"VI",
    "gn:admin3_code":"01053",
    "gn:asciiname":"Eguilaz",
    "gn:country_code":"ES",
    "gn:dem":601,
    "gn:feature_class":"P",
    "gn:feature_code":"PPL",
    "gn:name":"Egilatz / Eguilaz",
    "gn:population":0,
    "gn:timezone":"Europe/Madrid",
    "iso:country":"ES",
    "name:eus_x_preferred":[
        "Egilatz"
    ],
    "name:eus_x_variant":[
        "Egiraz"
    ],
    "name:spa_x_preferred":[
        "Eguilaz"
    ],
    "wof:name":"Eguilaz",
    "wof:placetype":"locality"
},
  "geometry": {"coordinates":[-2.33477,42.86389000000001],"type":"Point"}
}