{
  "type": "Feature",
  "properties": {
    "gn:admin1_code":"58",
    "gn:admin2_code":"C",
    "gn:admin3_code":"15037",
    "gn:asciiname":"San Martino de Arriba",
    "gn:country_code":"ES",
    "gn:dem":115,
    "gn:feature_class":"P",
    "gn:feature_code":"PPL",
    "gn:name":"San Marti\u00f1o de Arriba",
    "gn:population":0,
    "gn:timezone":"Europe/Madrid",
    "iso:country":"ES",
    "name:und_x_variant":[
        "San Marti\u00f1o de Buio"
    ],
    "wof:name":"San Martino de Arriba",
    "wof:placetype":"locality"
},
  "geometry": {"coordinates":[-9.27315,42.91947],"type":"Point"}
}