{
  "type": "Feature",
  "properties": {
    "gn:admin1_code":"51",
    "gn:admin2_code":"GR",
    "gn:admin3_code":"18192",
    "gn:asciiname":"Cortijo de Chinales",
    "gn:cc2":"ES",
    "gn:country_code":"ES",
    "gn:dem":893,
    "gn:feature_class":"P",
    "gn:feature_code":"PPL",
    "gn:name":"Cortijo de Chinales",
    "gn:population":0,
    "gn:timezone":"Europe/Madrid",
    "iso:country":"ES",
    "name:und_x_variant":[
        "Casas Cortijo de Chinales",
        "Cortijo de Chinales"
    ],
    "wof:name":"Cortijo de Chinales",
    "wof:placetype":"locality"
},
  "geometry": {"coordinates":[-4.13333,36.96667],"type":"Point"}
}