{
  "type": "Feature",
  "properties": {
    "gn:admin1_code":"58",
    "gn:admin2_code":"C",
    "gn:admin3_code":"15012",
    "gn:asciiname":"Gastrar",
    "gn:country_code":"ES",
    "gn:dem":230,
    "gn:feature_class":"P",
    "gn:feature_code":"PPL",
    "gn:name":"Gastrar",
    "gn:population":0,
    "gn:timezone":"Europe/Madrid",
    "iso:country":"ES",
    "wof:name":"Gastrar",
    "wof:placetype":"locality"
},
  "geometry": {"coordinates":[-8.41893,42.85003],"type":"Point"}
}