{
  "type": "Feature",
  "properties": {
    "gn:admin1_code":"58",
    "gn:admin2_code":"OR",
    "gn:admin3_code":"32027",
    "gn:asciiname":"Balongo",
    "gn:cc2":"ES",
    "gn:country_code":"ES",
    "gn:dem":228,
    "gn:feature_class":"P",
    "gn:feature_code":"PPL",
    "gn:name":"Balongo",
    "gn:population":0,
    "gn:timezone":"Europe/Madrid",
    "iso:country":"ES",
    "name:und_x_variant":[
        "San Mart\u00edn",
        "Balongo"
    ],
    "wof:name":"Balongo",
    "wof:placetype":"locality"
},
  "geometry": {"coordinates":[-8.13333,42.18333],"type":"Point"}
}