{
  "type": "Feature",
  "properties": {
    "gn:admin1_code":"31",
    "gn:admin2_code":"MU",
    "gn:admin3_code":"30003",
    "gn:asciiname":"Cuesta de la Cabra",
    "gn:country_code":"ES",
    "gn:dem":267,
    "gn:feature_class":"P",
    "gn:feature_code":"PPL",
    "gn:name":"Cuesta de la Cabra",
    "gn:population":0,
    "gn:timezone":"Europe/Madrid",
    "iso:country":"ES",
    "name:und_x_variant":[
        "Caser\u00edo Cuesta de la Cabra",
        "Cuesta de la Cabra"
    ],
    "wof:name":"Cuesta de la Cabra",
    "wof:placetype":"locality"
},
  "geometry": {"coordinates":[-1.58077,37.46622],"type":"Point"}
}