{
  "type": "Feature",
  "properties": {
    "gn:admin1_code":"60",
    "gn:admin2_code":"CS",
    "gn:admin3_code":"12039",
    "gn:asciiname":"Penalba",
    "gn:cc2":"ES",
    "gn:country_code":"ES",
    "gn:dem":381,
    "gn:feature_class":"P",
    "gn:feature_code":"PPL",
    "gn:name":"Pe\u00f1alba",
    "gn:population":0,
    "gn:timezone":"Europe/Madrid",
    "iso:country":"ES",
    "name:und_x_variant":[
        "Pe\u00f1alva",
        "Pe\u00f1alba"
    ],
    "wof:name":"Penalba",
    "wof:placetype":"locality"
},
  "geometry": {"coordinates":[-0.46667,39.86667],"type":"Point"}
}