{
  "type": "Feature",
  "properties": {
    "gn:admin1_code":"34",
    "gn:admin2_code":"O",
    "gn:admin3_code":"33059",
    "gn:asciiname":"Ablanedo",
    "gn:country_code":"ES",
    "gn:dem":551,
    "gn:feature_class":"P",
    "gn:feature_code":"PPL",
    "gn:name":"Ablanedo",
    "gn:population":0,
    "gn:timezone":"Europe/Madrid",
    "iso:country":"ES",
    "wof:name":"Ablanedo",
    "wof:placetype":"locality"
},
  "geometry": {"coordinates":[-6.34305,43.42151],"type":"Point"}
}