{
  "type": "Feature",
  "properties": {
    "gn:admin1_code":"60",
    "gn:admin2_code":"A",
    "gn:admin3_code":"03002",
    "gn:asciiname":"Escandella",
    "gn:country_code":"ES",
    "gn:dem":317,
    "gn:feature_class":"P",
    "gn:feature_code":"PPL",
    "gn:name":"Escandella",
    "gn:population":0,
    "gn:timezone":"Europe/Madrid",
    "iso:country":"ES",
    "name:und_x_variant":[
        "Caser\u00edo Escandella",
        "Escandella"
    ],
    "wof:name":"Escandella",
    "wof:placetype":"locality"
},
  "geometry": {"coordinates":[-0.67513,38.42578],"type":"Point"}
}