{
  "type": "Feature",
  "properties": {
    "gn:country":"ES",
    "gn:fcode":"PPLA3",
    "gn:population":403,
    "iso:country":"ES",
    "name:arg_x_preferred":[
        "Ali\u00f3"
    ],
    "name:ast_x_preferred":[
        "Ali\u00f3"
    ],
    "name:cat_x_preferred":[
        "Ali\u00f3"
    ],
    "name:ceb_x_preferred":[
        "Ali\u00f3"
    ],
    "name:deu_x_preferred":[
        "Ali\u00f3"
    ],
    "name:eng_x_preferred":[
        "Ali\u00f3"
    ],
    "name:eus_x_preferred":[
        "Ali\u00f3"
    ],
    "name:fra_x_preferred":[
        "Ali\u00f3"
    ],
    "name:glg_x_preferred":[
        "Ali\u00f3"
    ],
    "name:hun_x_preferred":[
        "Ali\u00f3"
    ],
    "name:hye_x_preferred":[
        "\u0531\u056c\u056b\u0578"
    ],
    "name:ita_x_preferred":[
        "Ali\u00f3"
    ],
    "name:lat_x_preferred":[
        "Ali\u00f3"
    ],
    "name:msa_x_preferred":[
        "Ali\u00f3"
    ],
    "name:nld_x_preferred":[
        "Ali\u00f3"
    ],
    "name:oci_x_preferred":[
        "Ali\u00f3"
    ],
    "name:pol_x_preferred":[
        "Ali\u00f3"
    ],
    "name:por_x_preferred":[
        "Ali\u00f3"
    ],
    "name:rus_x_preferred":[
        "\u0410\u043b\u0438\u043e"
    ],
    "name:spa_x_preferred":[
        "Ali\u00f3"
    ],
    "name:sqi_x_preferred":[
        "Ali\u00f3"
    ],
    "name:swe_x_preferred":[
        "Ali\u00f3"
    ],
    "name:ukr_x_preferred":[
        "\u0410\u043b\u0456\u043e"
    ],
    "name:uzb_x_preferred":[
        "Ali\u00f3"
    ],
    "name:vie_x_preferred":[
        "Ali\u00f3"
    ],
    "name:war_x_preferred":[
        "Ali\u00f3"
    ],
    "name:zho_x_preferred":[
        "\u963f\u5229\u5965"
    ],
    "qs_pg:aaroncc":"ES",
    "qs_pg:gn_country":"ES",
    "qs_pg:gn_fcode":"PPLA3",
    "qs_pg:gn_pop":403,
    "qs_pg:name":"Ali\u00f3",
    "qs_pg:name_adm0":"Espa\u00f1a",
    "qs_pg:name_adm1":"Catalunya",
    "qs_pg:photos":67,
    "qs_pg:photos_1k":14,
    "qs_pg:photos_9k":1,
    "qs_pg:photos_9r":2,
    "qs_pg:photos_all":67,
    "qs_pg:photos_sr":2,
    "qs_pg:pop_sr":2,
    "qs_pg:qs_pg_placetype":"locality",
    "qs_pg:qs_pg_placetype_gp":"Town",
    "qs_pg:woe_adm0":23424950,
    "woe:adm0_id":23424950,
    "woe:name_adm0":"Espa\u00f1a",
    "woe:name_adm1":"Catalunya",
    "woe:placetype":"Town",
    "wof:name":"Ali\u00f3",
    "wof:placetype":"locality",
    "wof:population":403
},
  "geometry": {"coordinates":[1.30585,41.29422],"type":"Point"}
}