{
  "type": "Feature",
  "properties": {
    "gn:admin1_code":"60",
    "gn:admin2_code":"V",
    "gn:admin3_code":"46145",
    "gn:asciiname":"Torre Lloris",
    "gn:country_code":"ES",
    "gn:dem":66,
    "gn:feature_class":"P",
    "gn:feature_code":"PPL",
    "gn:name":"Torre Lloris",
    "gn:population":0,
    "gn:timezone":"Europe/Madrid",
    "iso:country":"ES",
    "wof:name":"Torre Lloris",
    "wof:placetype":"locality"
},
  "geometry": {"coordinates":[-0.48934,39.0299],"type":"Point"}
}