{
  "type": "Feature",
  "properties": {
    "gn:admin1_code":"39",
    "gn:admin2_code":"S",
    "gn:admin3_code":"39090",
    "gn:asciiname":"La Virgen",
    "gn:country_code":"ES",
    "gn:dem":122,
    "gn:feature_class":"P",
    "gn:feature_code":"PPL",
    "gn:name":"La Virgen",
    "gn:population":0,
    "gn:timezone":"Europe/Madrid",
    "iso:country":"ES",
    "wof:name":"La Virgen",
    "wof:placetype":"locality"
},
  "geometry": {"coordinates":[-4.2489,43.3304],"type":"Point"}
}