{
  "type": "Feature",
  "properties": {
    "gn:admin1_code":"58",
    "gn:admin2_code":"OR",
    "gn:admin3_code":"32061",
    "gn:asciiname":"Barran",
    "gn:country_code":"ES",
    "gn:dem":591,
    "gn:feature_class":"P",
    "gn:feature_code":"PPL",
    "gn:name":"Barr\u00e1n",
    "gn:population":0,
    "gn:timezone":"Europe/Madrid",
    "iso:country":"ES",
    "name:arg_x_preferred":[
        "Barran"
    ],
    "name:bug_x_preferred":[
        "Barran"
    ],
    "name:cat_x_preferred":[
        "Barran"
    ],
    "name:ceb_x_preferred":[
        "Barran"
    ],
    "name:deu_x_preferred":[
        "Barran"
    ],
    "name:eus_x_preferred":[
        "Barran"
    ],
    "name:fra_x_preferred":[
        "Barran"
    ],
    "name:hun_x_preferred":[
        "Barran"
    ],
    "name:ita_x_preferred":[
        "Barran"
    ],
    "name:lat_x_preferred":[
        "Barran"
    ],
    "name:mlg_x_preferred":[
        "Barran"
    ],
    "name:msa_x_preferred":[
        "Barran"
    ],
    "name:nld_x_preferred":[
        "Barran"
    ],
    "name:oci_x_preferred":[
        "Barran"
    ],
    "name:pol_x_preferred":[
        "Barran"
    ],
    "name:ron_x_preferred":[
        "Barran"
    ],
    "name:rus_x_preferred":[
        "\u0411\u0430\u0440\u0440\u0430\u043d"
    ],
    "name:slk_x_preferred":[
        "Barran"
    ],
    "name:spa_x_preferred":[
        "Barran"
    ],
    "name:sqi_x_preferred":[
        "Barran"
    ],
    "name:srp_x_preferred":[
        "\u0411\u0430\u0440\u0430\u043d"
    ],
    "name:swe_x_preferred":[
        "Barran"
    ],
    "name:ukr_x_preferred":[
        "\u0411\u0430\u0440\u0440\u0430\u043d"
    ],
    "name:vie_x_preferred":[
        "Barran"
    ],
    "name:vol_x_preferred":[
        "Barran"
    ],
    "name:war_x_preferred":[
        "Barran"
    ],
    "name:zho_x_preferred":[
        "\u5df4\u5c14\u6717"
    ],
    "wof:name":"Barran",
    "wof:placetype":"locality"
},
  "geometry": {"coordinates":[-7.99644,42.50704],"type":"Point"}
}