{
  "type": "Feature",
  "properties": {
    "gn:admin1_code":"55",
    "gn:admin2_code":"VA",
    "gn:admin3_code":"47145",
    "gn:asciiname":"Santiago del Arroyo",
    "gn:country_code":"ES",
    "gn:dem":792,
    "gn:feature_class":"P",
    "gn:feature_code":"PPL",
    "gn:name":"Santiago del Arroyo",
    "gn:population":0,
    "gn:timezone":"Europe/Madrid",
    "iso:country":"ES",
    "wof:name":"Santiago del Arroyo",
    "wof:placetype":"locality"
},
  "geometry": {"coordinates":[-4.51915,41.45125],"type":"Point"}
}