{
  "type": "Feature",
  "properties": {
    "iso:country":"ES",
    "name:eng_x_preferred":[
        "Zubianu"
    ],
    "name:eus_x_preferred":[
        "Zubiaur"
    ],
    "name:spa_x_preferred":[
        "Zubiaur"
    ],
    "qs:a0":"Espa\u00f1a",
    "qs:a1":"*Bizkaia",
    "qs:a1r":"0Pa\u00eds Vasco",
    "qs:adm0":"Espa\u00f1a",
    "qs:la_lc":"*",
    "qs:level":"locality",
    "qs:loc":"Zubiaur",
    "qs:loc_alt":"Zubiaur",
    "qs:pop":0,
    "qs:type":"buffered point",
    "wof:lang":[
        "spa"
    ],
    "wof:name":"Zubiaur",
    "wof:placetype":"locality"
},
  "geometry": {"coordinates":[-2.912265,43.10725],"type":"Point"}
}