{
  "type": "Feature",
  "properties": {
    "iso:country":"ES",
    "wof:name":"Parque Empresarial Torneo",
    "wof:placetype":"neighbourhood"
},
  "geometry": {"coordinates":[-5.97531774248126,37.4270423009807],"type":"Point"}
}