{
  "type": "Feature",
  "properties": {
    "gn:admin1_code":"32",
    "gn:admin3_code":"31011",
    "gn:asciiname":"Galdeano",
    "gn:country_code":"ES",
    "gn:dem":553,
    "gn:feature_class":"P",
    "gn:feature_code":"PPL",
    "gn:name":"Galdeano",
    "gn:population":0,
    "gn:timezone":"Europe/Madrid",
    "iso:country":"ES",
    "wof:name":"Galdeano",
    "wof:placetype":"locality"
},
  "geometry": {"coordinates":[-2.09255,42.72495],"type":"Point"}
}