{
  "type": "Feature",
  "properties": {
    "gn:admin1_code":"34",
    "gn:admin2_code":"O",
    "gn:admin3_code":"33001",
    "gn:asciiname":"Parajas",
    "gn:country_code":"ES",
    "gn:dem":502,
    "gn:feature_class":"P",
    "gn:feature_code":"PPL",
    "gn:name":"Parajas",
    "gn:population":0,
    "gn:timezone":"Europe/Madrid",
    "iso:country":"ES",
    "name:ast_x_preferred":[
        "Paraxes"
    ],
    "name:cat_x_preferred":[
        "Parajas"
    ],
    "name:deu_x_preferred":[
        "Parajas"
    ],
    "name:spa_x_preferred":[
        "Parajas"
    ],
    "wof:name":"Parajas",
    "wof:placetype":"locality"
},
  "geometry": {"coordinates":[-6.58582,43.20327],"type":"Point"}
}