{
  "type": "Feature",
  "properties": {
    "gn:admin1_code":"59",
    "gn:admin2_code":"BI",
    "gn:admin3_code":"48079",
    "gn:asciiname":"Metxika",
    "gn:country_code":"ES",
    "gn:dem":332,
    "gn:feature_class":"P",
    "gn:feature_code":"PPL",
    "gn:name":"Metxika",
    "gn:population":0,
    "gn:timezone":"Europe/Madrid",
    "iso:country":"ES",
    "name:eus_x_preferred":[
        "Metxika"
    ],
    "name:spa_x_preferred":[
        "Mechicas"
    ],
    "wof:name":"Metxika",
    "wof:placetype":"locality"
},
  "geometry": {"coordinates":[-2.73333,43.33333],"type":"Point"}
}