{
  "type": "Feature",
  "properties": {
    "gn:admin1_code":"52",
    "gn:admin2_code":"HU",
    "gn:admin3_code":"22015",
    "gn:asciiname":"Fananas",
    "gn:country_code":"ES",
    "gn:dem":501,
    "gn:feature_class":"P",
    "gn:feature_code":"PPL",
    "gn:name":"Fa\u00f1an\u00e1s",
    "gn:population":0,
    "gn:timezone":"Europe/Madrid",
    "iso:country":"ES",
    "name:und_x_variant":[
        "Fa\u00f1an\u00e1s"
    ],
    "wof:name":"Fananas",
    "wof:placetype":"locality"
},
  "geometry": {"coordinates":[-0.27583,42.07646],"type":"Point"}
}