{
  "type": "Feature",
  "properties": {
    "gn:admin1_code":"51",
    "gn:admin2_code":"H",
    "gn:admin3_code":"21028",
    "gn:asciiname":"Valles de Carrasco",
    "gn:cc2":"ES",
    "gn:country_code":"ES",
    "gn:dem":459,
    "gn:feature_class":"P",
    "gn:feature_code":"PPL",
    "gn:name":"Valles de Carrasco",
    "gn:population":0,
    "gn:timezone":"Europe/Madrid",
    "iso:country":"ES",
    "name:und_x_variant":[
        "Cortijada Valles de Carrasco",
        "Valles de Carrasco"
    ],
    "wof:name":"Valles de Carrasco",
    "wof:placetype":"locality"
},
  "geometry": {"coordinates":[-6.76667,38.03333],"type":"Point"}
}