{
  "type": "Feature",
  "properties": {
    "gn:admin1_code":"32",
    "gn:admin3_code":"31050",
    "gn:asciiname":"Arraioz",
    "gn:country_code":"ES",
    "gn:dem":375,
    "gn:feature_class":"P",
    "gn:feature_code":"PPL",
    "gn:name":"Arraioz",
    "gn:population":0,
    "gn:timezone":"Europe/Madrid",
    "iso:country":"ES",
    "name:cat_x_preferred":[
        "Arraioz"
    ],
    "name:eus_x_preferred":[
        "Arraioz"
    ],
    "name:fra_x_preferred":[
        "Arraioz"
    ],
    "name:spa_x_preferred":[
        "Arrayoz"
    ],
    "name:spa_x_variant":[
        "Arr\u00e1yoz"
    ],
    "wof:name":"Arraioz",
    "wof:placetype":"locality"
},
  "geometry": {"coordinates":[-1.56667,43.15],"type":"Point"}
}