{
  "type": "Feature",
  "properties": {
    "gn:admin1_code":"51",
    "gn:admin2_code":"GR",
    "gn:admin3_code":"18164",
    "gn:asciiname":"La Canada Grande",
    "gn:country_code":"ES",
    "gn:dem":1085,
    "gn:feature_class":"P",
    "gn:feature_code":"PPL",
    "gn:name":"La Ca\u00f1ada Grande",
    "gn:population":0,
    "gn:timezone":"Europe/Madrid",
    "iso:country":"ES",
    "name:und_x_variant":[
        "Caser\u00edo La Ca\u00f1ada Grande",
        "La Ca\u00f1ada Grande"
    ],
    "wof:name":"La Canada Grande",
    "wof:placetype":"locality"
},
  "geometry": {"coordinates":[-2.26813,37.81741],"type":"Point"}
}