{
  "type": "Feature",
  "properties": {
    "gn:population":1544,
    "iso:country":"ES",
    "name:ara_x_preferred":[
        "\u0643\u0648\u0644\u0648\u0645\u064a\u0631\u0627"
    ],
    "name:cat_x_preferred":[
        "Colomera"
    ],
    "name:ceb_x_preferred":[
        "Colomera"
    ],
    "name:eng_x_preferred":[
        "Colomera"
    ],
    "name:epo_x_preferred":[
        "Colomera"
    ],
    "name:eus_x_preferred":[
        "Colomera"
    ],
    "name:fra_x_preferred":[
        "Colomera"
    ],
    "name:hat_x_preferred":[
        "Colomera"
    ],
    "name:hun_x_preferred":[
        "Colomera"
    ],
    "name:hye_x_preferred":[
        "\u053f\u0578\u056c\u0578\u0574\u0565\u0580\u0561"
    ],
    "name:ita_x_preferred":[
        "Colomera"
    ],
    "name:kaz_x_preferred":[
        "\u041a\u043e\u043b\u043e\u043c\u0435\u0440\u0430"
    ],
    "name:msa_x_preferred":[
        "Colomera"
    ],
    "name:nan_x_preferred":[
        "Colomera"
    ],
    "name:nld_x_preferred":[
        "Colomera"
    ],
    "name:oci_x_preferred":[
        "Colomera"
    ],
    "name:pol_x_preferred":[
        "Colomera"
    ],
    "name:por_x_preferred":[
        "Colomera"
    ],
    "name:rus_x_preferred":[
        "\u041a\u043e\u043b\u043e\u043c\u0435\u0440\u0430"
    ],
    "name:spa_x_preferred":[
        "Colomera"
    ],
    "name:swe_x_preferred":[
        "Colomera"
    ],
    "name:tur_x_preferred":[
        "Colomera"
    ],
    "name:ukr_x_preferred":[
        "\u041a\u043e\u043b\u043e\u043c\u0435\u0440\u0430"
    ],
    "name:uzb_x_preferred":[
        "Colomera"
    ],
    "name:vie_x_preferred":[
        "Colomera"
    ],
    "name:war_x_preferred":[
        "Colomera"
    ],
    "name:zho_min_nan_x_preferred":[
        "Colomera"
    ],
    "name:zho_x_preferred":[
        "\u79d1\u6d1b\u6885\u62c9"
    ],
    "qs:a0":"Espa\u00f1a",
    "qs:a1":"*Granada",
    "qs:a1r":"0Andaluc\u00eda",
    "qs:adm0":"Espa\u00f1a",
    "qs:la_lc":"*",
    "qs:level":"locality",
    "qs:loc":"Colomera",
    "qs:loc_alt":"Colomera",
    "qs:pop":0,
    "qs:type":"buffered point",
    "wd:wordcount":210,
    "wof:lang":[
        "spa"
    ],
    "wof:name":"Colomera",
    "wof:placetype":"locality",
    "wof:population":1544
},
  "geometry": {"coordinates":[-3.714244,37.371696],"type":"Point"}
}