{
  "type": "Feature",
  "properties": {
    "gn:admin1_code":"39",
    "gn:admin2_code":"S",
    "gn:admin3_code":"39052",
    "gn:asciiname":"Carandia",
    "gn:country_code":"ES",
    "gn:dem":36,
    "gn:feature_class":"P",
    "gn:feature_code":"PPL",
    "gn:name":"Carand\u00eda",
    "gn:population":0,
    "gn:timezone":"Europe/Madrid",
    "iso:country":"ES",
    "name:und_x_variant":[
        "Carand\u00eda"
    ],
    "wof:name":"Carandia",
    "wof:placetype":"locality"
},
  "geometry": {"coordinates":[-3.97566,43.33518],"type":"Point"}
}