{
  "type": "Feature",
  "properties": {
    "gn:admin1_code":"55",
    "gn:admin2_code":"BU",
    "gn:admin3_code":"09238",
    "gn:asciiname":"Villanueva de los Montes",
    "gn:country_code":"ES",
    "gn:dem":823,
    "gn:feature_class":"P",
    "gn:feature_code":"PPL",
    "gn:name":"Villanueva de los Montes",
    "gn:population":0,
    "gn:timezone":"Europe/Madrid",
    "iso:country":"ES",
    "wof:name":"Villanueva de los Montes",
    "wof:placetype":"locality"
},
  "geometry": {"coordinates":[-3.34063,42.75111],"type":"Point"}
}