{
  "type": "Feature",
  "properties": {
    "gn:admin1_code":"34",
    "gn:admin2_code":"O",
    "gn:admin3_code":"33050",
    "gn:asciiname":"Ambingue",
    "gn:country_code":"ES",
    "gn:dem":469,
    "gn:feature_class":"P",
    "gn:feature_code":"PPL",
    "gn:name":"Ambingue",
    "gn:population":0,
    "gn:timezone":"Europe/Madrid",
    "iso:country":"ES",
    "name:und_x_variant":[
        "Ambigue",
        "Ambingue"
    ],
    "wof:name":"Ambingue",
    "wof:placetype":"locality"
},
  "geometry": {"coordinates":[-5.22323,43.26091],"type":"Point"}
}