{
  "type": "Feature",
  "properties": {
    "iso:country":"ES",
    "name:eng_x_preferred":[
        "Ind. San Alberto"
    ],
    "name:spa_x_preferred":[
        "Ind. San Alberto"
    ],
    "wof:name":"Ind. San Alberto",
    "wof:placetype":"neighbourhood"
},
  "geometry": {"coordinates":[-4.45161063783049,36.73391465243441],"type":"Point"}
}