{
  "type": "Feature",
  "properties": {
    "gn:admin1_code":"55",
    "gn:admin2_code":"AV",
    "gn:admin3_code":"05114",
    "gn:asciiname":"Villar de Matacabras",
    "gn:country_code":"ES",
    "gn:dem":816,
    "gn:feature_class":"P",
    "gn:feature_code":"PPL",
    "gn:name":"Villar de Matacabras",
    "gn:population":0,
    "gn:timezone":"Europe/Madrid",
    "iso:country":"ES",
    "wof:name":"Villar de Matacabras",
    "wof:placetype":"locality"
},
  "geometry": {"coordinates":[-5.01945,41.06096],"type":"Point"}
}