{
  "type": "Feature",
  "properties": {
    "gn:admin1_code":"53",
    "gn:admin2_code":"TF",
    "gn:admin3_code":"38023",
    "gn:asciiname":"Batan de Abajo",
    "gn:country_code":"ES",
    "gn:dem":582,
    "gn:feature_class":"P",
    "gn:feature_code":"PPL",
    "gn:name":"Bat\u00e1n de Abajo",
    "gn:population":0,
    "gn:timezone":"Atlantic/Canary",
    "iso:country":"ES",
    "name:und_x_variant":[
        "Bat\u00e1n de Abajo"
    ],
    "wof:name":"Batan de Abajo",
    "wof:placetype":"locality"
},
  "geometry": {"coordinates":[-16.29796,28.54474],"type":"Point"}
}