{
  "type": "Feature",
  "properties": {
    "gn:admin1_code":"51",
    "gn:admin2_code":"AL",
    "gn:admin3_code":"04059",
    "gn:asciiname":"El Marchal",
    "gn:country_code":"ES",
    "gn:dem":376,
    "gn:feature_class":"P",
    "gn:feature_code":"PPL",
    "gn:name":"El Marchal",
    "gn:population":0,
    "gn:timezone":"Europe/Madrid",
    "iso:country":"ES",
    "name:und_x_variant":[
        "Cortijada El Marchal",
        "El Marchal"
    ],
    "wof:name":"El Marchal",
    "wof:placetype":"locality"
},
  "geometry": {"coordinates":[-2.02355,37.21621],"type":"Point"}
}