{
  "type": "Feature",
  "properties": {
    "gn:country":"ES",
    "gn:fcode":"ADM3",
    "gn:population":116,
    "iso:country":"ES",
    "name:ara_x_preferred":[
        "\u0641\u064a\u0644\u0627\u0631 \u064a \u0641\u064a\u0644\u0627\u0633\u0643\u0648"
    ],
    "name:arg_x_preferred":[
        "Villar y Velasco"
    ],
    "name:ast_x_preferred":[
        "Villar y Velasco"
    ],
    "name:cat_x_preferred":[
        "Villar y Velasco"
    ],
    "name:ceb_x_preferred":[
        "Villar y Velasco"
    ],
    "name:eng_x_preferred":[
        "Villar y Velasco"
    ],
    "name:epo_x_preferred":[
        "Villar y Velasco"
    ],
    "name:eus_x_preferred":[
        "Villar y Velasco"
    ],
    "name:fra_x_preferred":[
        "Villar y Velasco"
    ],
    "name:glg_x_preferred":[
        "Villar y Velasco"
    ],
    "name:hun_x_preferred":[
        "Villar y Velasco"
    ],
    "name:ita_x_preferred":[
        "Villar y Velasco"
    ],
    "name:kaz_x_preferred":[
        "\u0412\u0438\u043b\u044c\u044f\u0440-\u0438-\u0412\u0435\u043b\u0430\u0441\u043a\u043e"
    ],
    "name:msa_x_preferred":[
        "Villar y Velasco"
    ],
    "name:nan_x_preferred":[
        "Villar y Velasco"
    ],
    "name:nld_x_preferred":[
        "Villar y Velasco"
    ],
    "name:oci_x_preferred":[
        "Villar y Velasco"
    ],
    "name:pol_x_preferred":[
        "Villar y Velasco"
    ],
    "name:por_x_preferred":[
        "Villar y Velasco"
    ],
    "name:rus_x_preferred":[
        "\u0412\u0438\u043b\u044c\u044f\u0440-\u0438-\u0412\u0435\u043b\u0430\u0441\u043a\u043e"
    ],
    "name:spa_x_preferred":[
        "Villar y Velasco"
    ],
    "name:swe_x_preferred":[
        "Villar y Velasco"
    ],
    "name:ukr_x_preferred":[
        "\u0412\u0456\u043b\u044c\u044f\u0440-\u0456-\u0412\u0435\u043b\u0430\u0441\u043a\u043e"
    ],
    "name:vie_x_preferred":[
        "Villar y Velasco"
    ],
    "name:war_x_preferred":[
        "Villar y Velasco"
    ],
    "name:zho_x_preferred":[
        "\u6bd4\u5229\u4e9a\u91cc\u97e6\u62c9\u65af\u79d1"
    ],
    "qs_pg:aaroncc":"ES",
    "qs_pg:gn_country":"ES",
    "qs_pg:gn_fcode":"ADM3",
    "qs_pg:gn_pop":116,
    "qs_pg:name":"Villar y Velasco",
    "qs_pg:name_adm0":"Espa\u00f1a",
    "qs_pg:name_adm1":"Castilla-La Mancha",
    "qs_pg:photos_9r":0,
    "qs_pg:photos_sr":0,
    "qs_pg:pop_sr":1,
    "qs_pg:qs_pg_placetype":"locality",
    "qs_pg:qs_pg_placetype_gp":"Town",
    "qs_pg:woe_adm0":23424950,
    "woe:adm0_id":23424950,
    "woe:name_adm0":"Espa\u00f1a",
    "woe:name_adm1":"Castilla-La Mancha",
    "woe:placetype":"Town",
    "wof:name":"Villar y Velasco",
    "wof:placetype":"locality",
    "wof:population":104
},
  "geometry": {"coordinates":[-2.39121,40.13759],"type":"Point"}
}