{
  "type": "Feature",
  "properties": {
    "gn:admin1_code":"55",
    "gn:admin2_code":"LE",
    "gn:admin3_code":"24009",
    "gn:asciiname":"Villarinos",
    "gn:country_code":"ES",
    "gn:dem":990,
    "gn:feature_class":"P",
    "gn:feature_code":"PPL",
    "gn:name":"Villari\u00f1os",
    "gn:population":0,
    "gn:timezone":"Europe/Madrid",
    "iso:country":"ES",
    "name:und_x_variant":[
        "Villari\u00f1os"
    ],
    "wof:name":"Villarinos",
    "wof:placetype":"locality"
},
  "geometry": {"coordinates":[-6.91382,42.72743],"type":"Point"}
}