{
  "type": "Feature",
  "properties": {
    "gn:admin1_code":"58",
    "gn:admin2_code":"C",
    "gn:admin3_code":"15092",
    "gn:asciiname":"Salto",
    "gn:cc2":"ES",
    "gn:country_code":"ES",
    "gn:dem":186,
    "gn:feature_class":"P",
    "gn:feature_code":"PPL",
    "gn:name":"Salto",
    "gn:population":0,
    "gn:timezone":"Europe/Madrid",
    "iso:country":"ES",
    "name:und_x_variant":[
        "Santa Mar\u00eda"
    ],
    "wof:name":"Salto",
    "wof:placetype":"locality"
},
  "geometry": {"coordinates":[-8.9987,43.10947],"type":"Point"}
}