{
  "type": "Feature",
  "properties": {
    "gn:admin1_code":"55",
    "gn:admin2_code":"BU",
    "gn:admin3_code":"09209",
    "gn:asciiname":"Pomar",
    "gn:country_code":"ES",
    "gn:dem":596,
    "gn:feature_class":"P",
    "gn:feature_code":"PPL",
    "gn:name":"Pomar",
    "gn:population":0,
    "gn:timezone":"Europe/Madrid",
    "iso:country":"ES",
    "name:cat_x_preferred":[
        "Pomar"
    ],
    "name:deu_x_preferred":[
        "Pomar"
    ],
    "name:fra_x_preferred":[
        "Pomar"
    ],
    "name:glg_x_preferred":[
        "Pomar"
    ],
    "name:spa_x_preferred":[
        "Pomar"
    ],
    "wof:name":"Pomar",
    "wof:placetype":"locality"
},
  "geometry": {"coordinates":[-3.47782,42.94129],"type":"Point"}
}