{
  "type": "Feature",
  "properties": {
    "gn:admin1_code":"59",
    "gn:admin2_code":"VI",
    "gn:admin3_code":"01037",
    "gn:asciiname":"Roitegui",
    "gn:country_code":"ES",
    "gn:dem":947,
    "gn:feature_class":"P",
    "gn:feature_code":"PPL",
    "gn:name":"Erroitegi / R\u00f3itegui",
    "gn:population":0,
    "gn:timezone":"Europe/Madrid",
    "iso:country":"ES",
    "name:eus_x_preferred":[
        "Erroitegi"
    ],
    "name:fra_x_preferred":[
        "R\u00f3itegui"
    ],
    "name:spa_x_preferred":[
        "R\u00f3itegui"
    ],
    "name:spa_x_variant":[
        "Roitegui"
    ],
    "wof:name":"Roitegui",
    "wof:placetype":"locality"
},
  "geometry": {"coordinates":[-2.3836,42.77908],"type":"Point"}
}