{
  "type": "Feature",
  "properties": {
    "iso:country":"ES",
    "name:cat_x_preferred":[
        "La Moraleja"
    ],
    "name:eng_x_preferred":[
        "La Moraleja"
    ],
    "name:eus_x_preferred":[
        "La Moraleja"
    ],
    "name:fin_x_preferred":[
        "La Moraleja"
    ],
    "name:heb_x_preferred":[
        "\u05dc\u05d4 \u05de\u05d5\u05e8\u05dc\u05d7\u05d4"
    ],
    "name:nld_x_preferred":[
        "La Moraleja"
    ],
    "name:nob_x_preferred":[
        "La Moraleja"
    ],
    "name:slv_x_preferred":[
        "La Moraleja"
    ],
    "name:spa_x_preferred":[
        "La Moraleja"
    ],
    "name:tgl_x_preferred":[
        "La Moraleja"
    ],
    "qs_pg:aaroncc":"ES",
    "qs_pg:name":"La Moraleja",
    "qs_pg:name_adm0":"Espa\u00f1a",
    "qs_pg:name_adm1":"Comunidad de Madrid",
    "qs_pg:photos":172,
    "qs_pg:photos_1k":35,
    "qs_pg:photos_9k":1,
    "qs_pg:photos_9r":4,
    "qs_pg:photos_all":172,
    "qs_pg:photos_sr":4,
    "qs_pg:pop_sr":0,
    "qs_pg:qs_pg_placetype":"locality",
    "qs_pg:qs_pg_placetype_gp":"Town",
    "qs_pg:woe_adm0":23424950,
    "woe:adm0_id":23424950,
    "woe:name_adm0":"Espa\u00f1a",
    "woe:name_adm1":"Comunidad de Madrid",
    "woe:placetype":"Town",
    "wof:name":"La Moraleja",
    "wof:placetype":"locality"
},
  "geometry": {"coordinates":[-3.626679,40.4931595],"type":"Point"}
}