{
  "type": "Feature",
  "properties": {
    "gn:country":"ES",
    "gn:fcode":"PPL",
    "gn:population":0,
    "iso:country":"ES",
    "name:arg_x_preferred":[
        "Barinas"
    ],
    "name:bre_x_preferred":[
        "Barinas"
    ],
    "name:ceb_x_preferred":[
        "Barinas"
    ],
    "name:eus_x_preferred":[
        "Barinas"
    ],
    "name:fra_x_preferred":[
        "Barinas"
    ],
    "name:hun_x_preferred":[
        "Barinas"
    ],
    "name:ita_x_preferred":[
        "Barinas"
    ],
    "name:nld_x_preferred":[
        "Barinas"
    ],
    "name:nor_x_preferred":[
        "Barinas"
    ],
    "name:pol_x_preferred":[
        "Barinas"
    ],
    "name:sco_x_preferred":[
        "Barinas"
    ],
    "name:spa_x_preferred":[
        "Barinas"
    ],
    "qs_pg:aaroncc":"ES",
    "qs_pg:gn_country":"ES",
    "qs_pg:gn_fcode":"PPL",
    "qs_pg:gn_pop":0,
    "qs_pg:name":"Barinas",
    "qs_pg:name_adm0":"Espa\u00f1a",
    "qs_pg:name_adm1":"Regi\u00f3n de Murcia",
    "qs_pg:photos_9r":0,
    "qs_pg:photos_sr":0,
    "qs_pg:pop_sr":0,
    "qs_pg:qs_pg_placetype":"locality",
    "qs_pg:qs_pg_placetype_gp":"Town",
    "qs_pg:woe_adm0":23424950,
    "woe:adm0_id":23424950,
    "woe:name_adm0":"Espa\u00f1a",
    "woe:name_adm1":"Regi\u00f3n de Murcia",
    "woe:placetype":"Town",
    "wof:name":"Barinas",
    "wof:placetype":"locality"
},
  "geometry": {"coordinates":[-1.05773,38.27006],"type":"Point"}
}