{
  "type": "Feature",
  "properties": {
    "gn:admin1_code":"34",
    "gn:admin2_code":"O",
    "gn:admin3_code":"33070",
    "gn:asciiname":"Lomba",
    "gn:country_code":"ES",
    "gn:dem":61,
    "gn:feature_class":"P",
    "gn:feature_code":"PPL",
    "gn:name":"Lomba",
    "gn:population":0,
    "gn:timezone":"Europe/Madrid",
    "iso:country":"ES",
    "name:ceb_x_preferred":[
        "Lomba"
    ],
    "name:deu_x_preferred":[
        "Lomba"
    ],
    "name:fra_x_preferred":[
        "Lomba"
    ],
    "name:glg_x_preferred":[
        "Lomba"
    ],
    "name:nld_x_preferred":[
        "Lomba"
    ],
    "name:por_x_preferred":[
        "Lomba"
    ],
    "name:rus_x_preferred":[
        "\u041b\u043e\u043c\u0431\u0430"
    ],
    "name:swe_x_preferred":[
        "Lomba"
    ],
    "wof:name":"Lomba",
    "wof:placetype":"locality"
},
  "geometry": {"coordinates":[-6.96667,43.53333],"type":"Point"}
}