{
  "type": "Feature",
  "properties": {
    "gn:admin1_code":"58",
    "gn:admin2_code":"C",
    "gn:admin3_code":"15014",
    "gn:asciiname":"Ures",
    "gn:country_code":"ES",
    "gn:dem":101,
    "gn:feature_class":"P",
    "gn:feature_code":"PPL",
    "gn:name":"Ures",
    "gn:population":0,
    "gn:timezone":"Europe/Madrid",
    "iso:country":"ES",
    "wof:name":"Ures",
    "wof:placetype":"locality"
},
  "geometry": {"coordinates":[-8.95909,43.2088],"type":"Point"}
}