{
  "type": "Feature",
  "properties": {
    "gn:admin1_code":"56",
    "gn:admin2_code":"GI",
    "gn:admin3_code":"17121",
    "gn:asciiname":"Sant Julia de Boada",
    "gn:country_code":"ES",
    "gn:dem":24,
    "gn:feature_class":"P",
    "gn:feature_code":"PPL",
    "gn:name":"Sant Juli\u00e0 de Boada",
    "gn:population":0,
    "gn:timezone":"Europe/Madrid",
    "iso:country":"ES",
    "wof:name":"Sant Julia de Boada",
    "wof:placetype":"locality"
},
  "geometry": {"coordinates":[3.12201,41.98489],"type":"Point"}
}