{
  "type": "Feature",
  "properties": {
    "gn:admin1_code":"59",
    "gn:admin2_code":"VI",
    "gn:admin3_code":"01059",
    "gn:asciiname":"Gomecha",
    "gn:country_code":"ES",
    "gn:dem":558,
    "gn:feature_class":"P",
    "gn:feature_code":"PPL",
    "gn:name":"Gometxa",
    "gn:population":0,
    "gn:timezone":"Europe/Madrid",
    "iso:country":"ES",
    "name:eus_x_preferred":[
        "Gometxa"
    ],
    "name:spa_x_preferred":[
        "Gomecha"
    ],
    "wof:name":"Gomecha",
    "wof:placetype":"locality"
},
  "geometry": {"coordinates":[-2.732,42.8274],"type":"Point"}
}