{
  "type": "Feature",
  "properties": {
    "gn:gn_country":"ES",
    "gn:gn_fcode":"ADM3",
    "gn:gn_pop":365,
    "gn:population":395,
    "iso:country":"ES",
    "name:alb_x_preferred":[
        "Talaveruela de la Vera"
    ],
    "name:ara_x_preferred":[
        "\u062a\u0627\u0644\u0627\u0641\u064a\u0644\u0648\u064a\u0631\u0627 \u062f\u064a \u0644\u0627 \u0641\u064a\u0631\u0627"
    ],
    "name:baq_x_preferred":[
        "Talaveruela de la Vera"
    ],
    "name:cat_x_preferred":[
        "Talaveruela de la Vera"
    ],
    "name:chi_x_preferred":[
        "\u5854\u62c9\u97e6\u9c81\u57c3\u62c9\u5fb7\u62c9\u97e6\u62c9"
    ],
    "name:dut_x_preferred":[
        "Talaveruela de la Vera"
    ],
    "name:eng_x_preferred":[
        "Talaveruela de la Vera"
    ],
    "name:epo_x_preferred":[
        "Talaveruela de la Vera"
    ],
    "name:fre_x_preferred":[
        "Talaveruela de la Vera"
    ],
    "name:hun_x_preferred":[
        "Talaveruela de la Vera"
    ],
    "name:ina_x_preferred":[
        "Talaveruela de la Vera"
    ],
    "name:ita_x_preferred":[
        "Talaveruela de la Vera"
    ],
    "name:may_x_preferred":[
        "Talaveruela de la Vera"
    ],
    "name:nan_x_preferred":[
        "Talaveruela de la Vera"
    ],
    "name:oci_x_preferred":[
        "Talaveruela de la Vera"
    ],
    "name:pol_x_preferred":[
        "Talaveruela de la Vera"
    ],
    "name:por_x_preferred":[
        "Talaveruela de la Vera"
    ],
    "name:rum_x_preferred":[
        "Talaveruela de la Vera"
    ],
    "name:rus_x_preferred":[
        "\u0422\u0430\u043b\u0430\u0432\u0435\u0440\u0443\u044d\u043b\u0430-\u0434\u0435-\u043b\u0430-\u0412\u0435\u0440\u0430"
    ],
    "name:spa_x_preferred":[
        "Talaveruela de la Vera"
    ],
    "name:swe_x_preferred":[
        "Talaveruela de la Vera"
    ],
    "name:ukr_x_preferred":[
        "\u0422\u0430\u043b\u0430\u0432\u0435\u0440\u0443\u0435\u043b\u0430-\u0434\u0435-\u043b\u0430-\u0412\u0435\u0440\u0430"
    ],
    "name:uzb_x_preferred":[
        "Talaveruela de la Vera"
    ],
    "name:vie_x_preferred":[
        "Talaveruela de la Vera"
    ],
    "name:war_x_preferred":[
        "Talaveruela de la Vera"
    ],
    "qs_pg:aaroncc":"ES",
    "qs_pg:gn_country":"ES",
    "qs_pg:gn_fcode":"ADM3",
    "qs_pg:gn_pop":365,
    "qs_pg:name":"Talaveruela de la Vera",
    "qs_pg:name_adm0":"Espa\u00f1a",
    "qs_pg:name_adm1":"Extremadura",
    "qs_pg:photos_9r":0,
    "qs_pg:photos_sr":0,
    "qs_pg:pop_sr":2,
    "qs_pg:qs_pg_placetype":"locality",
    "qs_pg:qs_pg_placetype_gp":"Town",
    "qs_pg:woe_adm0":23424950,
    "woe:adm0_id":23424950,
    "woe:name_adm0":"Espa\u00f1a",
    "woe:name_adm1":"Extremadura",
    "woe:placetype":"Town",
    "wof:name":"Talaveruela de la Vera",
    "wof:placetype":"locality",
    "wof:population":395
},
  "geometry": {"coordinates":[-5.52016,40.12099],"type":"Point"}
}