{
  "type": "Feature",
  "properties": {
    "iso:country":"ES",
    "wof:name":"Hermandad del Trabajo",
    "wof:placetype":"neighbourhood"
},
  "geometry": {"coordinates":[-5.98179796272178,37.40946617001725],"type":"Point"}
}