{
  "type": "Feature",
  "properties": {
    "iso:country":"ES",
    "name:ara_x_preferred":[
        "\u0623\u0631\u064a\u062a\u0632\u0627"
    ],
    "name:arg_x_preferred":[
        "Areatza"
    ],
    "name:ast_x_preferred":[
        "Areatza"
    ],
    "name:azb_x_preferred":[
        "\u0622\u0631\u0647\u200c\u0622\u062a\u0632\u0627"
    ],
    "name:bre_x_preferred":[
        "Areatza"
    ],
    "name:bul_x_preferred":[
        "\u0410\u0440\u0435\u0430\u0442\u0437\u0430"
    ],
    "name:cat_x_preferred":[
        "Areatza"
    ],
    "name:ceb_x_preferred":[
        "Areatza"
    ],
    "name:eng_x_preferred":[
        "Areatza"
    ],
    "name:eus_x_preferred":[
        "Areatza"
    ],
    "name:fas_x_preferred":[
        "\u0622\u0631\u0647\u200c\u0622\u062a\u0632\u0627"
    ],
    "name:fra_x_preferred":[
        "Areatza"
    ],
    "name:glg_x_preferred":[
        "Areatza"
    ],
    "name:hun_x_preferred":[
        "Areatza"
    ],
    "name:ita_x_preferred":[
        "Areatza"
    ],
    "name:jpn_x_preferred":[
        "\u30a2\u30ec\u30a2\u30c4\u30a1"
    ],
    "name:lat_x_preferred":[
        "Villaro"
    ],
    "name:msa_x_preferred":[
        "Areatza"
    ],
    "name:nld_x_preferred":[
        "Areatza"
    ],
    "name:oci_x_preferred":[
        "Areatza"
    ],
    "name:pol_x_preferred":[
        "Areatza"
    ],
    "name:por_x_preferred":[
        "Villaro"
    ],
    "name:rus_x_preferred":[
        "\u0412\u0438\u043b\u044c\u044f\u0440\u043e"
    ],
    "name:sco_x_preferred":[
        "Areatza"
    ],
    "name:spa_x_preferred":[
        "Villaro"
    ],
    "name:swe_x_preferred":[
        "Areatza"
    ],
    "name:ukr_x_preferred":[
        "\u0410\u0440\u0435\u0430\u0446\u0430"
    ],
    "name:uzb_x_preferred":[
        "Villaro"
    ],
    "name:war_x_preferred":[
        "Areatza"
    ],
    "name:zho_x_preferred":[
        "\u963f\u96f7\u4e9a\u7279\u8428"
    ],
    "qs:a0":"Espa\u00f1a",
    "qs:a1":"*Bizkaia",
    "qs:a1r":"0Pa\u00eds Vasco",
    "qs:adm0":"Espa\u00f1a",
    "qs:la_lc":"*",
    "qs:level":"locality",
    "qs:loc":"Areatza",
    "qs:loc_alt":"Areatza",
    "qs:pop":0,
    "qs:type":"buffered point",
    "wd:wordcount":39,
    "wof:name":"Areatza",
    "wof:placetype":"locality"
},
  "geometry": {"coordinates":[-2.769894,43.121281],"type":"Point"}
}