{
  "type": "Feature",
  "properties": {
    "gn:gn_country":"ES",
    "gn:gn_fcode":"PPLA3",
    "gn:gn_pop":211,
    "gn:population":211,
    "iso:country":"ES",
    "name:ara_x_preferred":[
        "\u0645\u0648\u0631\u0627\u062f\u0627\u064a\u0644\u0648 \u062f\u064a \u0631\u0648\u0627"
    ],
    "name:arg_x_preferred":[
        "Moradillo de Roa"
    ],
    "name:azb_x_preferred":[
        "\u0645\u0631\u0627\u062f\u06cc\u06cc\u0648 \u062f \u0631\u0626\u0627"
    ],
    "name:cat_x_preferred":[
        "Moradillo de Roa"
    ],
    "name:eng_x_preferred":[
        "Moradillo de Roa"
    ],
    "name:epo_x_preferred":[
        "Moradillo de Roa"
    ],
    "name:eus_x_preferred":[
        "Moradillo de Roa"
    ],
    "name:fas_x_preferred":[
        "\u0645\u0631\u0627\u062f\u06cc\u06cc\u0648 \u062f \u0631\u0626\u0627"
    ],
    "name:fra_x_preferred":[
        "Moradillo de Roa"
    ],
    "name:glg_x_preferred":[
        "Moradillo de Roa"
    ],
    "name:haw_x_preferred":[
        "Moradillo de Roa"
    ],
    "name:hun_x_preferred":[
        "Moradillo de Roa"
    ],
    "name:ina_x_preferred":[
        "Moradillo de Roa"
    ],
    "name:ita_x_preferred":[
        "Moradillo de Roa"
    ],
    "name:msa_x_preferred":[
        "Moradillo de Roa"
    ],
    "name:nan_x_preferred":[
        "Moradillo de Roa"
    ],
    "name:nld_x_preferred":[
        "Moradillo de Roa"
    ],
    "name:oci_x_preferred":[
        "Moradillo de Roa"
    ],
    "name:pol_x_preferred":[
        "Moradillo de Roa"
    ],
    "name:por_x_preferred":[
        "Moradillo de Roa"
    ],
    "name:rus_x_preferred":[
        "\u041c\u043e\u0440\u0430\u0434\u0438\u043b\u044c\u043e-\u0434\u0435-\u0420\u043e\u0430"
    ],
    "name:spa_x_preferred":[
        "Moradillo de Roa"
    ],
    "name:swe_x_preferred":[
        "Moradillo de Roa"
    ],
    "name:ukr_x_preferred":[
        "\u041c\u043e\u0440\u0430\u0434\u0456\u043b\u044c\u0439\u043e-\u0434\u0435-\u0420\u043e\u0430"
    ],
    "name:uzb_x_preferred":[
        "Moradillo de Roa"
    ],
    "name:vie_x_preferred":[
        "Moradillo de Roa"
    ],
    "name:war_x_preferred":[
        "Moradillo de Roa"
    ],
    "name:zho_x_preferred":[
        "\u83ab\u62c9\u8fea\u7565\u5fb7\u7f57\u963f"
    ],
    "qs_pg:aaroncc":"ES",
    "qs_pg:gn_country":"ES",
    "qs_pg:gn_fcode":"PPLA3",
    "qs_pg:gn_pop":211,
    "qs_pg:name":"Moradillo de Roa",
    "qs_pg:name_adm0":"Espa\u00f1a",
    "qs_pg:name_adm1":"Castilla y Le\u00f3n",
    "qs_pg:photos_9k":1,
    "qs_pg:photos_9r":1,
    "qs_pg:photos_all":4,
    "qs_pg:photos_sr":0,
    "qs_pg:pop_sr":2,
    "qs_pg:qs_pg_placetype":"locality",
    "qs_pg:qs_pg_placetype_gp":"Town",
    "qs_pg:woe_adm0":23424950,
    "woe:adm0_id":23424950,
    "woe:name_adm0":"Espa\u00f1a",
    "woe:name_adm1":"Castilla y Le\u00f3n",
    "woe:placetype":"Town",
    "wof:name":"Moradillo de Roa",
    "wof:placetype":"locality",
    "wof:population":211
},
  "geometry": {"coordinates":[-3.79118,41.55164],"type":"Point"}
}