{
  "type": "Feature",
  "properties": {
    "gn:admin1_code":"52",
    "gn:admin2_code":"HU",
    "gn:admin3_code":"22130",
    "gn:asciiname":"Abay",
    "gn:country_code":"ES",
    "gn:dem":776,
    "gn:feature_class":"P",
    "gn:feature_code":"PPL",
    "gn:name":"Abay",
    "gn:population":0,
    "gn:timezone":"Europe/Madrid",
    "iso:country":"ES",
    "wof:name":"Abay",
    "wof:placetype":"locality"
},
  "geometry": {"coordinates":[-0.61017,42.56983],"type":"Point"}
}