{
  "type": "Feature",
  "properties": {
    "gn:admin1_code":"52",
    "gn:admin2_code":"HU",
    "gn:admin3_code":"22130",
    "gn:asciiname":"Abay",
    "gn:country_code":"ES",
    "gn:dem":776,
    "gn:feature_class":"P",
    "gn:feature_code":"PPL",
    "gn:name":"Abay",
    "gn:population":0,
    "gn:timezone":"Europe/Madrid",
    "iso:country":"ES",
    "name:ceb_x_preferred":[
        "Abay"
    ],
    "name:deu_x_preferred":[
        "Abay"
    ],
    "name:est_x_preferred":[
        "Abai"
    ],
    "name:kaa_x_preferred":[
        "Abay"
    ],
    "name:kaz_x_preferred":[
        "\u0410\u0431\u0430\u0439"
    ],
    "name:lit_x_preferred":[
        "Abajus"
    ],
    "name:rus_x_preferred":[
        "\u0410\u0431\u0430\u044f"
    ],
    "name:rus_x_variant":[
        "\u0410\u0431\u0430\u0439"
    ],
    "name:spa_x_preferred":[
        "Abay"
    ],
    "name:swe_x_preferred":[
        "Abay"
    ],
    "name:tur_x_preferred":[
        "Abay"
    ],
    "name:ukr_x_preferred":[
        "\u0410\u0431\u0430\u044f"
    ],
    "name:urd_x_preferred":[
        "\u0627\u0628\u06d2"
    ],
    "name:uzb_x_preferred":[
        "Abay"
    ],
    "name:vie_x_preferred":[
        "Abay"
    ],
    "name:zho_cn_x_preferred":[
        "\u963f\u62dc\u6cb3"
    ],
    "name:zho_tw_x_preferred":[
        "\u963f\u62dc"
    ],
    "wof:name":"Abay",
    "wof:placetype":"locality"
},
  "geometry": {"coordinates":[-0.61017,42.56983],"type":"Point"}
}