{
  "type": "Feature",
  "properties": {
    "gn:gn_country":"ES",
    "gn:gn_fcode":"PPLA3",
    "gn:gn_pop":59,
    "gn:population":59,
    "iso:country":"ES",
    "name:ara_x_preferred":[
        "\u0623\u0631\u0628\u064a\u062a\u064a\u062a\u0627"
    ],
    "name:arg_x_preferred":[
        "Arbeteta"
    ],
    "name:baq_x_preferred":[
        "Arbeteta"
    ],
    "name:bul_x_preferred":[
        "\u0410\u0440\u0431\u0435\u0442\u0435\u0442\u0430"
    ],
    "name:cat_x_preferred":[
        "Arbeteta"
    ],
    "name:chi_x_preferred":[
        "\u963f\u5c14\u97e6\u7279\u5854"
    ],
    "name:dut_x_preferred":[
        "Arbeteta"
    ],
    "name:eng_x_preferred":[
        "Arbeteta"
    ],
    "name:fre_x_preferred":[
        "Arbeteta"
    ],
    "name:hun_x_preferred":[
        "Arbeteta"
    ],
    "name:ina_x_preferred":[
        "Arbeteta"
    ],
    "name:ita_x_preferred":[
        "Arbeteta"
    ],
    "name:kaz_x_preferred":[
        "\u0410\u0440\u0431\u0435\u0442\u0435\u0442\u0430"
    ],
    "name:may_x_preferred":[
        "Arbeteta"
    ],
    "name:nan_x_preferred":[
        "Arbeteta"
    ],
    "name:oci_x_preferred":[
        "Arbeteta"
    ],
    "name:pol_x_preferred":[
        "Arbeteta"
    ],
    "name:por_x_preferred":[
        "Arbeteta"
    ],
    "name:rus_x_preferred":[
        "\u0410\u0440\u0431\u0435\u0442\u0435\u0442\u0430"
    ],
    "name:spa_x_preferred":[
        "Arbeteta"
    ],
    "name:swe_x_preferred":[
        "Arbeteta"
    ],
    "name:ukr_x_preferred":[
        "\u0410\u0440\u0431\u0435\u0442\u0435\u0442\u0430"
    ],
    "name:vie_x_preferred":[
        "Arbeteta"
    ],
    "name:war_x_preferred":[
        "Arbeteta"
    ],
    "qs_pg:aaroncc":"ES",
    "qs_pg:gn_country":"ES",
    "qs_pg:gn_fcode":"PPLA3",
    "qs_pg:gn_pop":59,
    "qs_pg:name":"Arbeteta",
    "qs_pg:name_adm0":"Espa\u00f1a",
    "qs_pg:name_adm1":"Castilla-La Mancha",
    "qs_pg:photos":13,
    "qs_pg:photos_1k":3,
    "qs_pg:photos_9k":1,
    "qs_pg:photos_9r":1,
    "qs_pg:photos_all":13,
    "qs_pg:photos_sr":1,
    "qs_pg:pop_sr":1,
    "qs_pg:qs_pg_placetype":"locality",
    "qs_pg:qs_pg_placetype_gp":"Town",
    "qs_pg:woe_adm0":23424950,
    "woe:adm0_id":23424950,
    "woe:name_adm0":"Espa\u00f1a",
    "woe:name_adm1":"Castilla-La Mancha",
    "woe:placetype":"Town",
    "wof:name":"Arbeteta",
    "wof:placetype":"locality",
    "wof:population":59
},
  "geometry": {"coordinates":[-2.40236,40.66999],"type":"Point"}
}