{
  "type": "Feature",
  "properties": {
    "gn:gn_country":"ES",
    "gn:gn_fcode":"PPLA3",
    "gn:gn_pop":78,
    "gn:population":78,
    "iso:country":"ES",
    "name:arg_x_preferred":[
        "Villaverde de Rioja"
    ],
    "name:cat_x_preferred":[
        "Villaverde de Rioja"
    ],
    "name:deu_x_preferred":[
        "Villaverde de Rioja"
    ],
    "name:eng_x_preferred":[
        "Villaverde de Rioja"
    ],
    "name:eus_x_preferred":[
        "Villaverde de Rioja"
    ],
    "name:fra_x_preferred":[
        "Villaverde de Rioja"
    ],
    "name:hun_x_preferred":[
        "Villaverde de Rioja"
    ],
    "name:hye_x_preferred":[
        "\u054e\u056b\u056c\u056b\u0561\u057e\u0565\u0580\u0564\u0565 \u0564\u0565 \u054c\u056b\u0578\u056d\u0561"
    ],
    "name:hye_x_variant":[
        "\u054e\u056b\u056c\u0575\u0561\u057e\u0565\u0580\u0564\u0565 \u0564\u0565 \u054c\u056b\u0578\u056d\u0561"
    ],
    "name:ita_x_preferred":[
        "Villaverde de Rioja"
    ],
    "name:kaz_x_preferred":[
        "\u0412\u0438\u043b\u044c\u044f\u0432\u0435\u0440\u0434\u0435-\u0434\u0435-\u0420\u0438\u043e\u0445\u0430"
    ],
    "name:msa_x_preferred":[
        "Villaverde de Rioja"
    ],
    "name:nan_x_preferred":[
        "Villaverde de Rioja"
    ],
    "name:nld_x_preferred":[
        "Villaverde de Rioja"
    ],
    "name:oci_x_preferred":[
        "Villaverde de Rioja"
    ],
    "name:pol_x_preferred":[
        "Villaverde de Rioja"
    ],
    "name:por_x_preferred":[
        "Villaverde de Rioja"
    ],
    "name:rup_x_preferred":[
        "Villaverde de Rioja"
    ],
    "name:rus_x_preferred":[
        "\u0412\u0438\u043b\u044c\u044f\u0432\u0435\u0440\u0434\u0435-\u0434\u0435-\u0420\u0438\u043e\u0445\u0430"
    ],
    "name:spa_x_preferred":[
        "Villaverde de Rioja"
    ],
    "name:swe_x_preferred":[
        "Villaverde de Rioja"
    ],
    "name:ukr_x_preferred":[
        "\u0412\u0456\u043b\u044c\u044f\u0432\u0435\u0440\u0434\u0435-\u0434\u0435-\u0420\u0456\u043e\u0445\u0430"
    ],
    "name:uzb_x_preferred":[
        "Villaverde de Rioja"
    ],
    "name:vie_x_preferred":[
        "Villaverde de Rioja"
    ],
    "name:war_x_preferred":[
        "Villaverde de Rioja"
    ],
    "name:zho_x_preferred":[
        "\u6bd4\u5229\u4e9a\u97e6\u5c14\u5fb7\u5fb7\u91cc\u5965\u54c8"
    ],
    "qs_pg:aaroncc":"ES",
    "qs_pg:gn_country":"ES",
    "qs_pg:gn_fcode":"PPLA3",
    "qs_pg:gn_pop":78,
    "qs_pg:name":"Villaverde de Rioja",
    "qs_pg:name_adm0":"Espa\u00f1a",
    "qs_pg:name_adm1":"La Rioja",
    "qs_pg:photos_9k":1,
    "qs_pg:photos_9r":1,
    "qs_pg:photos_all":4,
    "qs_pg:photos_sr":0,
    "qs_pg:pop_sr":1,
    "qs_pg:qs_pg_placetype":"locality",
    "qs_pg:qs_pg_placetype_gp":"Town",
    "qs_pg:woe_adm0":23424950,
    "woe:adm0_id":23424950,
    "woe:name_adm0":"Espa\u00f1a",
    "woe:name_adm1":"La Rioja",
    "woe:placetype":"Town",
    "wof:name":"Villaverde de Rioja",
    "wof:placetype":"locality",
    "wof:population":78
},
  "geometry": {"coordinates":[-2.8137,42.32051],"type":"Point"}
}