{
  "type": "Feature",
  "properties": {
    "gn:admin1_code":"55",
    "gn:admin2_code":"ZA",
    "gn:admin3_code":"49092",
    "gn:asciiname":"Cunquilla de Vidriales",
    "gn:country_code":"ES",
    "gn:dem":721,
    "gn:feature_class":"P",
    "gn:feature_code":"PPL",
    "gn:name":"Cunquilla de Vidriales",
    "gn:population":0,
    "gn:timezone":"Europe/Madrid",
    "iso:country":"ES",
    "wof:name":"Cunquilla de Vidriales",
    "wof:placetype":"locality"
},
  "geometry": {"coordinates":[-5.89844,42.0463],"type":"Point"}
}