{
  "type": "Feature",
  "properties": {
    "gn:country":"ES",
    "gn:fcode":"PPLA3",
    "gn:population":354,
    "iso:country":"ES",
    "name:ara_x_preferred":[
        "\u0623\u0631\u0627\u0648\u0632\u0648 \u062f\u064a \u0645\u0627\u064a\u0644"
    ],
    "name:arg_x_preferred":[
        "Arauzo de Miel"
    ],
    "name:azb_x_preferred":[
        "\u0622\u0631\u0627\u0648\u0633\u0648 \u062f \u0645\u06cc\u0644"
    ],
    "name:cat_x_preferred":[
        "Arauzo de Miel"
    ],
    "name:eng_x_preferred":[
        "Arauzo de Miel"
    ],
    "name:epo_x_preferred":[
        "Arauzo de Miel"
    ],
    "name:eus_x_preferred":[
        "Arauzo de Miel"
    ],
    "name:fas_x_preferred":[
        "\u0622\u0631\u0627\u0648\u0633\u0648 \u062f \u0645\u06cc\u0644"
    ],
    "name:fra_x_preferred":[
        "Arauzo de Miel"
    ],
    "name:glg_x_preferred":[
        "Arauzo de Miel"
    ],
    "name:haw_x_preferred":[
        "Arauzo de Miel"
    ],
    "name:hun_x_preferred":[
        "Arauzo de Miel"
    ],
    "name:ina_x_preferred":[
        "Arauzo de Miel"
    ],
    "name:ita_x_preferred":[
        "Arauzo de Miel"
    ],
    "name:lad_x_preferred":[
        "Arauzo de Miel"
    ],
    "name:msa_x_preferred":[
        "Arauzo de Miel"
    ],
    "name:nan_x_preferred":[
        "Arauzo de Miel"
    ],
    "name:nld_x_preferred":[
        "Arauzo de Miel"
    ],
    "name:oci_x_preferred":[
        "Arauzo de Miel"
    ],
    "name:pam_x_preferred":[
        "Arauzo de Miel"
    ],
    "name:pol_x_preferred":[
        "Arauzo de Miel"
    ],
    "name:por_x_preferred":[
        "Arauzo de Miel"
    ],
    "name:rus_x_preferred":[
        "\u0410\u0440\u0430\u0443\u0441\u043e-\u0434\u0435-\u041c\u044c\u0435\u043b\u044c"
    ],
    "name:spa_x_preferred":[
        "Arauzo de Miel"
    ],
    "name:swe_x_preferred":[
        "Arauzo de Miel"
    ],
    "name:tah_x_preferred":[
        "Arauzo de Miel"
    ],
    "name:ukr_x_preferred":[
        "\u0410\u0440\u0430\u0443\u0441\u043e-\u0434\u0435-\u041c'\u0454\u043b\u044c"
    ],
    "name:uzb_x_preferred":[
        "Arauzo de Miel"
    ],
    "name:vie_x_preferred":[
        "Arauzo de Miel"
    ],
    "name:war_x_preferred":[
        "Arauzo de Miel"
    ],
    "name:zho_x_preferred":[
        "\u963f\u52b3\u7d22\u5fb7\u7c73\u8036\u5c14"
    ],
    "qs_pg:aaroncc":"ES",
    "qs_pg:gn_country":"ES",
    "qs_pg:gn_fcode":"PPLA3",
    "qs_pg:gn_pop":354,
    "qs_pg:name":"Arauzo de Miel",
    "qs_pg:name_adm0":"Espa\u00f1a",
    "qs_pg:name_adm1":"Castilla y Le\u00f3n",
    "qs_pg:photos_9k":1,
    "qs_pg:photos_9r":1,
    "qs_pg:photos_all":1,
    "qs_pg:photos_sr":0,
    "qs_pg:pop_sr":2,
    "qs_pg:qs_pg_placetype":"locality",
    "qs_pg:qs_pg_placetype_gp":"Town",
    "qs_pg:woe_adm0":23424950,
    "woe:adm0_id":23424950,
    "woe:name_adm0":"Espa\u00f1a",
    "woe:name_adm1":"Castilla y Le\u00f3n",
    "woe:placetype":"Town",
    "wof:name":"Arauzo de Miel",
    "wof:placetype":"locality",
    "wof:population":354
},
  "geometry": {"coordinates":[-3.38773,41.85878],"type":"Point"}
}