{
  "type": "Feature",
  "properties": {
    "gn:gn_country":"ES",
    "gn:gn_fcode":"PPL",
    "gn:gn_pop":0,
    "iso:country":"ES",
    "name:alb_x_preferred":[
        "Cervi\u00e0 de les Garrigues"
    ],
    "name:arg_x_preferred":[
        "Cervi\u00e0 de les Garrigues"
    ],
    "name:baq_x_preferred":[
        "Cervi\u00e0 de les Garrigues"
    ],
    "name:cat_x_preferred":[
        "Cervi\u00e0 de les Garrigues"
    ],
    "name:chi_x_preferred":[
        "\u585e\u5c14\u7ef4\u4e9a\u5fb7\u83b1\u65af\u52a0\u91cc\u683c\u65af"
    ],
    "name:dut_x_preferred":[
        "Cervi\u00e0 de les Garrigues"
    ],
    "name:eng_x_preferred":[
        "Cervi\u00e0 de les Garrigues"
    ],
    "name:eus_x_preferred":[
        "Cervi\u00e0 de les Garrigues"
    ],
    "name:fre_x_preferred":[
        "Cervi\u00e0 de les Garrigues"
    ],
    "name:ger_x_preferred":[
        "Cervi\u00e0 de les Garrigues"
    ],
    "name:hun_x_preferred":[
        "Cervi\u00e0 de les Garrigues"
    ],
    "name:ita_x_preferred":[
        "Cervi\u00e0 de les Garrigues"
    ],
    "name:oci_x_preferred":[
        "Cervi\u00e0 de les Garrigues"
    ],
    "name:pol_x_preferred":[
        "Cervi\u00e0 de les Garrigues"
    ],
    "name:por_x_preferred":[
        "Cervi\u00e0 de les Garrigues"
    ],
    "name:rum_x_preferred":[
        "Cervi\u00e0 de les Garrigues"
    ],
    "name:rus_x_preferred":[
        "\u0421\u0435\u0440\u0432\u0438\u044f-\u0434\u0435-\u043b\u0430\u0441-\u0413\u0430\u0440\u0440\u0438\u0433\u0430\u0441"
    ],
    "name:spa_x_preferred":[
        "Cervi\u00e1"
    ],
    "name:swe_x_preferred":[
        "Cervi\u00e0 de les Garrigues"
    ],
    "name:uzb_x_preferred":[
        "Cervi\u00e0 de les Garrigues"
    ],
    "name:vie_x_preferred":[
        "Cervi\u00e0 de les Garrigues"
    ],
    "name:war_x_preferred":[
        "Cervi\u00e0 de les Garrigues"
    ],
    "qs_pg:aaroncc":"ES",
    "qs_pg:gn_country":"ES",
    "qs_pg:gn_fcode":"PPL",
    "qs_pg:gn_pop":0,
    "qs_pg:name":"Cervi\u00e0 de les Garrigues",
    "qs_pg:name_adm0":"Espa\u00f1a",
    "qs_pg:name_adm1":"Catalunya",
    "qs_pg:photos":118,
    "qs_pg:photos_1k":24,
    "qs_pg:photos_9k":1,
    "qs_pg:photos_9r":3,
    "qs_pg:photos_all":118,
    "qs_pg:photos_sr":3,
    "qs_pg:pop_sr":0,
    "qs_pg:qs_pg_placetype":"locality",
    "qs_pg:qs_pg_placetype_gp":"Town",
    "qs_pg:woe_adm0":23424950,
    "woe:adm0_id":23424950,
    "woe:name_adm0":"Espa\u00f1a",
    "woe:name_adm1":"Catalunya",
    "woe:placetype":"Town",
    "wof:name":"Cervi\u00e0 de les Garrigues",
    "wof:placetype":"locality"
},
  "geometry": {"coordinates":[0.86667,41.41667],"type":"Point"}
}