{
  "type": "Feature",
  "properties": {
    "gn:admin1_code":"31",
    "gn:admin2_code":"MU",
    "gn:admin3_code":"30019.0",
    "gn:asciiname":"Ascoy",
    "gn:country_code":"ES",
    "gn:dem":270,
    "gn:feature_class":"P",
    "gn:feature_code":"PPL",
    "gn:name":"Ascoy",
    "gn:population":0,
    "gn:timezone":"Europe/Madrid",
    "iso:country":"ES",
    "wof:name":"Ascoy",
    "wof:placetype":"locality"
},
  "geometry": {"coordinates":[-1.41874,38.27906],"type":"Point"}
}