{
  "type": "Feature",
  "properties": {
    "gn:gn_country":"ES",
    "gn:gn_fcode":"PPLA3",
    "gn:gn_pop":75,
    "gn:population":75,
    "iso:country":"ES",
    "name:ara_x_preferred":[
        "\u0623\u0648\u0643\u0648\u0627\u064a\u0644\u0627\u0633"
    ],
    "name:arg_x_preferred":[
        "Oquillas"
    ],
    "name:arm_x_preferred":[
        "\u0555\u056f\u056b\u056c\u0575\u0561\u057d"
    ],
    "name:baq_x_preferred":[
        "Oquillas"
    ],
    "name:cat_x_preferred":[
        "Oquillas"
    ],
    "name:chi_x_preferred":[
        "\u5965\u57fa\u5229\u4e9a\u65af"
    ],
    "name:dut_x_preferred":[
        "Oquillas"
    ],
    "name:eng_x_preferred":[
        "Oquillas"
    ],
    "name:epo_x_preferred":[
        "Oquillas"
    ],
    "name:fre_x_preferred":[
        "Oquillas"
    ],
    "name:glg_x_preferred":[
        "Oquillas"
    ],
    "name:haw_x_preferred":[
        "Oquillas"
    ],
    "name:hun_x_preferred":[
        "Oquillas"
    ],
    "name:ina_x_preferred":[
        "Oquillas"
    ],
    "name:ita_x_preferred":[
        "Oquillas"
    ],
    "name:lad_x_preferred":[
        "Oquillas"
    ],
    "name:may_x_preferred":[
        "Oquillas"
    ],
    "name:nan_x_preferred":[
        "Oquillas"
    ],
    "name:oci_x_preferred":[
        "Oquillas"
    ],
    "name:per_x_preferred":[
        "\u0627\u06a9\u06cc\u06cc\u0627\u0633"
    ],
    "name:pol_x_preferred":[
        "Oquillas"
    ],
    "name:por_x_preferred":[
        "Oquillas"
    ],
    "name:rus_x_preferred":[
        "\u041e\u043a\u0438\u043b\u044c\u044f\u0441"
    ],
    "name:spa_x_preferred":[
        "Oquillas"
    ],
    "name:swe_x_preferred":[
        "Oquillas"
    ],
    "name:tpi_x_preferred":[
        "Oquillas"
    ],
    "name:ukr_x_preferred":[
        "\u041e\u043a\u0456\u043b\u044c\u044f\u0441"
    ],
    "name:uzb_x_preferred":[
        "Oquillas"
    ],
    "name:vie_x_preferred":[
        "Oquillas"
    ],
    "name:war_x_preferred":[
        "Oquillas"
    ],
    "qs_pg:aaroncc":"ES",
    "qs_pg:gn_country":"ES",
    "qs_pg:gn_fcode":"PPLA3",
    "qs_pg:gn_pop":75,
    "qs_pg:name":"Oquillas",
    "qs_pg:name_adm0":"Espa\u00f1a",
    "qs_pg:name_adm1":"Castilla y Le\u00f3n",
    "qs_pg:photos_9k":1,
    "qs_pg:photos_9r":1,
    "qs_pg:photos_all":1,
    "qs_pg:photos_sr":0,
    "qs_pg:pop_sr":1,
    "qs_pg:qs_pg_placetype":"locality",
    "qs_pg:qs_pg_placetype_gp":"Town",
    "qs_pg:woe_adm0":23424950,
    "woe:adm0_id":23424950,
    "woe:name_adm0":"Espa\u00f1a",
    "woe:name_adm1":"Castilla y Le\u00f3n",
    "woe:placetype":"Town",
    "wof:name":"Oquillas",
    "wof:placetype":"locality",
    "wof:population":75
},
  "geometry": {"coordinates":[-3.70564,41.83085],"type":"Point"}
}