{
  "type": "Feature",
  "properties": {
    "gn:admin1_code":"55",
    "gn:admin2_code":"P",
    "gn:admin3_code":"34004",
    "gn:asciiname":"Cozuelos de Ojeda",
    "gn:country_code":"ES",
    "gn:dem":988,
    "gn:feature_class":"P",
    "gn:feature_code":"PPL",
    "gn:name":"Cozuelos de Ojeda",
    "gn:population":0,
    "gn:timezone":"Europe/Madrid",
    "iso:country":"ES",
    "wof:name":"Cozuelos de Ojeda",
    "wof:placetype":"locality"
},
  "geometry": {"coordinates":[-4.39572,42.75453],"type":"Point"}
}