{
  "type": "Feature",
  "properties": {
    "gn:gn_country":"ES",
    "gn:gn_fcode":"PPL",
    "gn:gn_pop":0,
    "iso:country":"ES",
    "name:alb_x_preferred":[
        "Aia"
    ],
    "name:ara_x_preferred":[
        "\u0623\u064a\u0627\u060c \u063a\u064a\u0628\u0648\u062b\u0643\u0648\u0627"
    ],
    "name:arg_x_preferred":[
        "Aia"
    ],
    "name:ast_x_preferred":[
        "Aia"
    ],
    "name:baq_x_preferred":[
        "Aia"
    ],
    "name:bre_x_preferred":[
        "Aia"
    ],
    "name:cat_x_preferred":[
        "Aia"
    ],
    "name:chi_x_preferred":[
        "\u827e\u963f"
    ],
    "name:dut_x_preferred":[
        "Aia"
    ],
    "name:eng_x_preferred":[
        "Aia"
    ],
    "name:eus_x_preferred":[
        "Aia"
    ],
    "name:fre_x_preferred":[
        "Aia"
    ],
    "name:glg_x_preferred":[
        "Aia"
    ],
    "name:hun_x_preferred":[
        "Aia"
    ],
    "name:ita_x_preferred":[
        "Aia"
    ],
    "name:jpn_x_preferred":[
        "\u30a2\u30a4\u30a2"
    ],
    "name:kor_x_preferred":[
        "\uc544\uc774\uc544"
    ],
    "name:may_x_preferred":[
        "Aia"
    ],
    "name:oci_x_preferred":[
        "Aia"
    ],
    "name:per_x_preferred":[
        "\u0627\u06cc\u0627"
    ],
    "name:pol_x_preferred":[
        "Aia"
    ],
    "name:por_x_preferred":[
        "Aia"
    ],
    "name:rus_x_preferred":[
        "\u0410\u0439\u044f"
    ],
    "name:spa_x_preferred":[
        "Aya"
    ],
    "name:swe_x_preferred":[
        "Aia"
    ],
    "name:ukr_x_preferred":[
        "\u0410\u044f"
    ],
    "name:uzb_x_preferred":[
        "Aya"
    ],
    "name:vie_x_preferred":[
        "Aia"
    ],
    "name:war_x_preferred":[
        "Aia"
    ],
    "qs_pg:aaroncc":"ES",
    "qs_pg:gn_country":"ES",
    "qs_pg:gn_fcode":"PPL",
    "qs_pg:gn_pop":0,
    "qs_pg:name":"Aia",
    "qs_pg:name_adm0":"Espa\u00f1a",
    "qs_pg:name_adm1":"Euskadi",
    "qs_pg:photos":810,
    "qs_pg:photos_1k":164,
    "qs_pg:photos_9k":4,
    "qs_pg:photos_9r":6,
    "qs_pg:photos_all":810,
    "qs_pg:photos_sr":9,
    "qs_pg:pop_sr":0,
    "qs_pg:qs_pg_placetype":"locality",
    "qs_pg:qs_pg_placetype_gp":"Town",
    "qs_pg:woe_adm0":23424950,
    "woe:adm0_id":23424950,
    "woe:name_adm0":"Espa\u00f1a",
    "woe:name_adm1":"Euskadi",
    "woe:placetype":"Town",
    "wof:name":"Aia",
    "wof:placetype":"locality"
},
  "geometry": {"coordinates":[-2.15512,42.96607],"type":"Point"}
}