{
  "type": "Feature",
  "properties": {
    "iso:country":"ES",
    "qs:a0":"Espa\u00f1a",
    "qs:a1":"*Santa Cruz de Tenerife",
    "qs:a1r":"0Canarias",
    "qs:adm0":"Espa\u00f1a",
    "qs:la_lc":"*",
    "qs:level":"locality",
    "qs:loc":"Pueblo (El)",
    "qs:loc_alt":"Pueblo (El)",
    "qs:pop":0,
    "qs:type":"buffered point",
    "wof:name":"Pueblo (El)",
    "wof:placetype":"locality"
},
  "geometry": {"coordinates":[-17.957147,28.709154],"type":"Point"}
}