{
  "type": "Feature",
  "properties": {
    "gn:admin1_code":"52",
    "gn:admin2_code":"TE",
    "gn:admin3_code":"44013",
    "gn:asciiname":"Valmuel",
    "gn:country_code":"ES",
    "gn:dem":271,
    "gn:feature_class":"P",
    "gn:feature_code":"PPL",
    "gn:name":"Valmuel",
    "gn:population":0,
    "gn:timezone":"Europe/Madrid",
    "iso:country":"ES",
    "wof:name":"Valmuel",
    "wof:placetype":"locality"
},
  "geometry": {"coordinates":[-0.21578,41.12724],"type":"Point"}
}