{
  "type": "Feature",
  "properties": {
    "gn:admin1_code":"51",
    "gn:admin2_code":"AL",
    "gn:admin3_code":"04035",
    "gn:asciiname":"La Arnilla",
    "gn:country_code":"ES",
    "gn:dem":61,
    "gn:feature_class":"P",
    "gn:feature_code":"PPL",
    "gn:name":"La Arnilla",
    "gn:population":0,
    "gn:timezone":"Europe/Madrid",
    "iso:country":"ES",
    "name:und_x_variant":[
        "Cortijada de Arnilla",
        "Arnilla",
        "Caser\u00edo La Arnilla",
        "La Arnilla"
    ],
    "wof:name":"La Arnilla",
    "wof:placetype":"locality"
},
  "geometry": {"coordinates":[-1.86424,37.28441],"type":"Point"}
}