{
  "type": "Feature",
  "properties": {
    "gn:gn_country":"ES",
    "gn:gn_fcode":"PPLA3",
    "gn:gn_pop":212,
    "gn:population":212,
    "iso:country":"ES",
    "name:arg_x_preferred":[
        "Erustes"
    ],
    "name:arm_x_preferred":[
        "\u0537\u0580\u0578\u0582\u057d\u057f\u0565\u057d"
    ],
    "name:baq_x_preferred":[
        "Erustes"
    ],
    "name:cat_x_preferred":[
        "Erustes"
    ],
    "name:chi_x_preferred":[
        "\u57c3\u9c81\u65af\u7279\u65af"
    ],
    "name:dut_x_preferred":[
        "Erustes"
    ],
    "name:eng_x_preferred":[
        "Erustes"
    ],
    "name:epo_x_preferred":[
        "Erustes"
    ],
    "name:fre_x_preferred":[
        "Erustes"
    ],
    "name:hun_x_preferred":[
        "Erustes"
    ],
    "name:ina_x_preferred":[
        "Erustes"
    ],
    "name:ita_x_preferred":[
        "Erustes"
    ],
    "name:kaz_x_preferred":[
        "\u042d\u0440\u0443\u0441\u0442\u0435\u0441"
    ],
    "name:may_x_preferred":[
        "Erustes"
    ],
    "name:nan_x_preferred":[
        "Erustes"
    ],
    "name:oci_x_preferred":[
        "Erustes"
    ],
    "name:per_x_preferred":[
        "\u0627\u0631\u0648\u0633\u062a\u0633"
    ],
    "name:pol_x_preferred":[
        "Erustes"
    ],
    "name:por_x_preferred":[
        "Erustes"
    ],
    "name:rum_x_preferred":[
        "Erustes"
    ],
    "name:rus_x_preferred":[
        "\u042d\u0440\u0443\u0441\u0442\u0435\u0441"
    ],
    "name:spa_x_preferred":[
        "Erustes"
    ],
    "name:swe_x_preferred":[
        "Erustes"
    ],
    "name:ukr_x_preferred":[
        "\u0415\u0440\u0443\u0441\u0442\u0435\u0441"
    ],
    "name:vie_x_preferred":[
        "Erustes"
    ],
    "name:war_x_preferred":[
        "Erustes"
    ],
    "qs_pg:aaroncc":"ES",
    "qs_pg:gn_country":"ES",
    "qs_pg:gn_fcode":"PPLA3",
    "qs_pg:gn_pop":212,
    "qs_pg:name":"Erustes",
    "qs_pg:name_adm0":"Espa\u00f1a",
    "qs_pg:name_adm1":"Castilla-La Mancha",
    "qs_pg:photos_9r":0,
    "qs_pg:photos_sr":0,
    "qs_pg:pop_sr":2,
    "qs_pg:qs_pg_placetype":"locality",
    "qs_pg:qs_pg_placetype_gp":"Town",
    "qs_pg:woe_adm0":23424950,
    "woe:adm0_id":23424950,
    "woe:name_adm0":"Espa\u00f1a",
    "woe:name_adm1":"Castilla-La Mancha",
    "woe:placetype":"Town",
    "wof:name":"Erustes",
    "wof:placetype":"locality",
    "wof:population":212
},
  "geometry": {"coordinates":[-4.49656,39.95667],"type":"Point"}
}