{
  "type": "Feature",
  "properties": {
    "gn:admin1_code":"55",
    "gn:admin2_code":"BU",
    "gn:admin3_code":"09214",
    "gn:asciiname":"Quintanilla de Pienza",
    "gn:country_code":"ES",
    "gn:dem":638,
    "gn:feature_class":"P",
    "gn:feature_code":"PPL",
    "gn:name":"Quintanilla de Pienza",
    "gn:population":0,
    "gn:timezone":"Europe/Madrid",
    "iso:country":"ES",
    "wof:name":"Quintanilla de Pienza",
    "wof:placetype":"locality"
},
  "geometry": {"coordinates":[-3.48061,43.00189],"type":"Point"}
}