{
  "type": "Feature",
  "properties": {
    "gn:gn_country":"ES",
    "gn:gn_fcode":"PPLA3",
    "gn:gn_pop":46,
    "gn:population":46,
    "iso:country":"ES",
    "name:arg_x_preferred":[
        "Valderrebollo"
    ],
    "name:bul_x_preferred":[
        "\u0412\u0430\u043b\u0434\u0435\u0440\u0435\u0431\u043e\u043b\u043e"
    ],
    "name:cat_x_preferred":[
        "Valderrebollo"
    ],
    "name:deu_x_preferred":[
        "Valderrebollo"
    ],
    "name:eng_x_preferred":[
        "Valderrebollo"
    ],
    "name:eus_x_preferred":[
        "Valderrebollo"
    ],
    "name:fra_x_preferred":[
        "Valderrebollo"
    ],
    "name:hun_x_preferred":[
        "Valderrebollo"
    ],
    "name:ina_x_preferred":[
        "Valderrebollo"
    ],
    "name:ita_x_preferred":[
        "Valderrebollo"
    ],
    "name:kaz_x_preferred":[
        "\u0412\u0430\u043b\u044c\u0434\u0435\u0440\u0440\u0435\u0431\u043e\u043b\u044c\u043e"
    ],
    "name:msa_x_preferred":[
        "Valderrebollo"
    ],
    "name:nan_x_preferred":[
        "Valderrebollo"
    ],
    "name:nld_x_preferred":[
        "Valderrebollo"
    ],
    "name:oci_x_preferred":[
        "Valderrebollo"
    ],
    "name:pol_x_preferred":[
        "Valderrebollo"
    ],
    "name:por_x_preferred":[
        "Valderrebollo"
    ],
    "name:rus_x_preferred":[
        "\u0412\u0430\u043b\u044c\u0434\u0435\u0440\u0440\u0435\u0431\u043e\u043b\u044c\u043e"
    ],
    "name:spa_x_preferred":[
        "Valderrebollo"
    ],
    "name:swe_x_preferred":[
        "Valderrebollo"
    ],
    "name:ukr_x_preferred":[
        "\u0412\u0430\u043b\u044c\u0434\u0435\u0440\u0440\u0435\u0431\u043e\u043b\u044c\u0439\u043e"
    ],
    "name:vie_x_preferred":[
        "Valderrebollo"
    ],
    "name:war_x_preferred":[
        "Valderrebollo"
    ],
    "name:zho_x_preferred":[
        "\u5df4\u5c14\u5fb7\u96f7\u6c83\u7565"
    ],
    "qs_pg:aaroncc":"ES",
    "qs_pg:gn_country":"ES",
    "qs_pg:gn_fcode":"PPLA3",
    "qs_pg:gn_pop":46,
    "qs_pg:name":"Valderrebollo",
    "qs_pg:name_adm0":"Espa\u00f1a",
    "qs_pg:name_adm1":"Castilla-La Mancha",
    "qs_pg:photos_9r":0,
    "qs_pg:photos_sr":0,
    "qs_pg:pop_sr":1,
    "qs_pg:qs_pg_placetype":"locality",
    "qs_pg:qs_pg_placetype_gp":"Town",
    "qs_pg:woe_adm0":23424950,
    "woe:adm0_id":23424950,
    "woe:name_adm0":"Espa\u00f1a",
    "woe:name_adm1":"Castilla-La Mancha",
    "woe:placetype":"Town",
    "wof:name":"Valderrebollo",
    "wof:placetype":"locality",
    "wof:population":46
},
  "geometry": {"coordinates":[-2.72887,40.81035],"type":"Point"}
}