{
  "type": "Feature",
  "properties": {
    "gn:admin1_code":"58",
    "gn:admin2_code":"LU",
    "gn:admin3_code":"27011",
    "gn:asciiname":"Recesende",
    "gn:country_code":"ES",
    "gn:dem":526,
    "gn:feature_class":"P",
    "gn:feature_code":"PPL",
    "gn:name":"Recesende",
    "gn:population":0,
    "gn:timezone":"Europe/Madrid",
    "iso:country":"ES",
    "wof:name":"Recesende",
    "wof:placetype":"locality"
},
  "geometry": {"coordinates":[-7.35137,43.01631],"type":"Point"}
}