{
  "type": "Feature",
  "properties": {
    "gn:admin1_code":"60",
    "gn:admin2_code":"A",
    "gn:admin3_code":"03077",
    "gn:asciiname":"La Solana",
    "gn:cc2":"ES",
    "gn:country_code":"ES",
    "gn:dem":540,
    "gn:feature_class":"P",
    "gn:feature_code":"PPL",
    "gn:name":"La Solana",
    "gn:population":0,
    "gn:timezone":"Europe/Madrid",
    "iso:country":"ES",
    "name:und_x_variant":[
        "Casas La Solana",
        "La Solana"
    ],
    "wof:name":"La Solana",
    "wof:placetype":"locality"
},
  "geometry": {"coordinates":[-0.91667,38.31667],"type":"Point"}
}