{
  "type": "Feature",
  "properties": {
    "gn:admin1_code":"59",
    "gn:admin2_code":"VI",
    "gn:admin3_code":"01018",
    "gn:asciiname":"Acosta",
    "gn:country_code":"ES",
    "gn:dem":632,
    "gn:feature_class":"P",
    "gn:feature_code":"PPL",
    "gn:name":"Okoizta / Acosta",
    "gn:population":0,
    "gn:timezone":"Europe/Madrid",
    "iso:country":"ES",
    "name:cat_x_preferred":[
        "Acosta"
    ],
    "name:ceb_x_preferred":[
        "Acosta"
    ],
    "name:ces_x_preferred":[
        "Acosta"
    ],
    "name:deu_x_preferred":[
        "Acosta"
    ],
    "name:eus_x_preferred":[
        "Okoizta"
    ],
    "name:eus_x_variant":[
        "Akosta"
    ],
    "name:fin_x_preferred":[
        "Acosta"
    ],
    "name:fra_x_preferred":[
        "Acosta"
    ],
    "name:glg_x_preferred":[
        "Acosta"
    ],
    "name:ita_x_preferred":[
        "Acosta"
    ],
    "name:jpn_x_preferred":[
        "\u30a2\u30b3\u30b9\u30bf"
    ],
    "name:kor_x_preferred":[
        "\uc544\ucf54\uc2a4\ud0c0"
    ],
    "name:nds_x_preferred":[
        "Acosta"
    ],
    "name:nld_x_preferred":[
        "Acosta"
    ],
    "name:por_x_preferred":[
        "Acosta"
    ],
    "name:rus_x_preferred":[
        "\u0410\u043a\u043e\u0441\u0442\u0430"
    ],
    "name:slv_x_preferred":[
        "Acosta"
    ],
    "name:spa_x_preferred":[
        "Acosta"
    ],
    "name:srp_x_preferred":[
        "\u0410\u043a\u043e\u0441\u0442\u0430"
    ],
    "name:swe_x_preferred":[
        "Acosta"
    ],
    "name:ukr_x_preferred":[
        "\u0410\u043a\u043e\u0441\u0442\u0430"
    ],
    "name:zho_x_preferred":[
        "\u65b0\u6d6a\u535a\u5ba2#\u4eba\u7269 Acosta"
    ],
    "wof:name":"Acosta",
    "wof:placetype":"locality"
},
  "geometry": {"coordinates":[-2.71302,42.97351],"type":"Point"}
}