{
  "type": "Feature",
  "properties": {
    "gn:admin1_code":"60",
    "gn:admin2_code":"A",
    "gn:admin3_code":"03041",
    "gn:asciiname":"Berdica",
    "gn:cc2":"ES",
    "gn:country_code":"ES",
    "gn:dem":243,
    "gn:feature_class":"P",
    "gn:feature_code":"PPL",
    "gn:name":"Berdica",
    "gn:population":0,
    "gn:timezone":"Europe/Madrid",
    "iso:country":"ES",
    "name:und_x_variant":[
        "Casas Berdica",
        "Berdica"
    ],
    "wof:name":"Berdica",
    "wof:placetype":"locality"
},
  "geometry": {"coordinates":[0.06667,38.71667],"type":"Point"}
}