{
  "type": "Feature",
  "properties": {
    "iso:country":"ES",
    "name:arg_x_preferred":[
        "Puerto"
    ],
    "name:ast_x_preferred":[
        "Puertu"
    ],
    "name:ceb_x_preferred":[
        "Puerto"
    ],
    "name:deu_x_preferred":[
        "Puerto"
    ],
    "name:ita_x_preferred":[
        "Puerto"
    ],
    "name:rus_x_preferred":[
        "\u041f\u0443\u044d\u0440\u0442\u043e"
    ],
    "name:spa_x_preferred":[
        "Puerto"
    ],
    "name:swe_x_preferred":[
        "Puerto"
    ],
    "wof:name":"Puerto",
    "wof:placetype":"neighbourhood"
},
  "geometry": {"coordinates":[-5.98988459625297,37.36263985451779],"type":"Point"}
}