{
  "type": "Feature",
  "properties": {
    "gn:admin1_code":"58",
    "gn:admin2_code":"LU",
    "gn:admin3_code":"27017",
    "gn:asciiname":"Pineira",
    "gn:country_code":"ES",
    "gn:dem":858,
    "gn:feature_class":"P",
    "gn:feature_code":"PPL",
    "gn:name":"Pi\u00f1eira",
    "gn:population":0,
    "gn:timezone":"Europe/Madrid",
    "iso:country":"ES",
    "wof:name":"Pineira",
    "wof:placetype":"locality"
},
  "geometry": {"coordinates":[-7.13581,42.64908],"type":"Point"}
}