{
  "type": "Feature",
  "properties": {
    "gn:gn_country":"ES",
    "gn:gn_fcode":"PPL",
    "gn:gn_pop":735,
    "gn:population":735,
    "iso:country":"ES",
    "name:arg_x_preferred":[
        "Iza"
    ],
    "name:baq_x_preferred":[
        "Itza"
    ],
    "name:bre_x_preferred":[
        "Itza"
    ],
    "name:bul_x_preferred":[
        "\u0418\u0442\u0437\u0430"
    ],
    "name:cat_x_preferred":[
        "Itza"
    ],
    "name:chi_x_preferred":[
        "\u4f0a\u8428"
    ],
    "name:dut_x_preferred":[
        "Iza"
    ],
    "name:eng_x_preferred":[
        "Iza"
    ],
    "name:eus_x_preferred":[
        "Itza"
    ],
    "name:fre_x_preferred":[
        "Iza"
    ],
    "name:hun_x_preferred":[
        "Iza"
    ],
    "name:ita_x_preferred":[
        "Iza"
    ],
    "name:jpn_x_preferred":[
        "\u30a4\u30b5\uff1d\u30a4\u30c4\u30a1"
    ],
    "name:may_x_preferred":[
        "Iza"
    ],
    "name:nan_x_preferred":[
        "Iza"
    ],
    "name:oci_x_preferred":[
        "Itza"
    ],
    "name:pol_x_preferred":[
        "Itza"
    ],
    "name:por_x_preferred":[
        "Cendea de Iza"
    ],
    "name:rus_x_preferred":[
        "\u0418\u0441\u0430"
    ],
    "name:sco_x_preferred":[
        "Iza"
    ],
    "name:spa_x_preferred":[
        "Iza"
    ],
    "name:swe_x_preferred":[
        "Iza"
    ],
    "name:ukr_x_preferred":[
        "\u0406\u0441\u0430"
    ],
    "name:uzb_x_preferred":[
        "Iza"
    ],
    "name:vie_x_preferred":[
        "Iza"
    ],
    "name:war_x_preferred":[
        "Iza"
    ],
    "qs_pg:aaroncc":"ES",
    "qs_pg:gn_country":"ES",
    "qs_pg:gn_fcode":"PPL",
    "qs_pg:gn_pop":735,
    "qs_pg:name":"Iza",
    "qs_pg:name_adm0":"Espa\u00f1a",
    "qs_pg:name_adm1":"Comunidad Foral de Navarra",
    "qs_pg:photos":11,
    "qs_pg:photos_1k":2,
    "qs_pg:photos_9k":1,
    "qs_pg:photos_9r":1,
    "qs_pg:photos_all":11,
    "qs_pg:photos_sr":1,
    "qs_pg:pop_sr":2,
    "qs_pg:qs_pg_placetype":"locality",
    "qs_pg:qs_pg_placetype_gp":"Town",
    "qs_pg:woe_adm0":23424950,
    "woe:adm0_id":23424950,
    "woe:name_adm0":"Espa\u00f1a",
    "woe:name_adm1":"Comunidad Foral de Navarra",
    "woe:placetype":"Town",
    "wof:name":"Iza",
    "wof:placetype":"locality",
    "wof:population":735
},
  "geometry": {"coordinates":[-1.7294,42.83664],"type":"Point"}
}