{
  "type": "Feature",
  "properties": {
    "gn:admin1_code":"58",
    "gn:admin2_code":"LU",
    "gn:admin3_code":"27040",
    "gn:asciiname":"Cabana",
    "gn:cc2":"ES",
    "gn:country_code":"ES",
    "gn:dem":481,
    "gn:feature_class":"P",
    "gn:feature_code":"PPL",
    "gn:name":"Cabana",
    "gn:population":0,
    "gn:timezone":"Europe/Madrid",
    "iso:country":"ES",
    "name:bre_x_preferred":[
        "Cabana"
    ],
    "name:ceb_x_preferred":[
        "Cabana"
    ],
    "name:deu_x_preferred":[
        "Cabana"
    ],
    "name:fra_x_preferred":[
        "Cabana"
    ],
    "name:glg_x_preferred":[
        "Cabana"
    ],
    "name:ita_x_preferred":[
        "Cabana"
    ],
    "name:por_x_preferred":[
        "Cabana"
    ],
    "name:spa_x_preferred":[
        "Cabana"
    ],
    "name:und_x_variant":[
        "Santiago",
        "Cabana"
    ],
    "wof:name":"Cabana",
    "wof:placetype":"locality"
},
  "geometry": {"coordinates":[-7.93333,42.83333],"type":"Point"}
}