{
  "type": "Feature",
  "properties": {
    "gn:admin1_code":"55",
    "gn:admin2_code":"BU",
    "gn:admin3_code":"09177",
    "gn:asciiname":"Salguero de Juarros",
    "gn:country_code":"ES",
    "gn:dem":973,
    "gn:feature_class":"P",
    "gn:feature_code":"PPL",
    "gn:name":"Salg\u00fcero de Juarros",
    "gn:population":0,
    "gn:timezone":"Europe/Madrid",
    "iso:country":"ES",
    "name:und_x_variant":[
        "Salg\u00fcero de Juarros"
    ],
    "wof:name":"Salguero de Juarros",
    "wof:placetype":"locality"
},
  "geometry": {"coordinates":[-3.48982,42.2948],"type":"Point"}
}