{
  "type": "Feature",
  "properties": {
    "gn:admin1_code":"58",
    "gn:admin2_code":"LU",
    "gn:admin3_code":"27035",
    "gn:asciiname":"Entralgo",
    "gn:country_code":"ES",
    "gn:dem":703,
    "gn:feature_class":"P",
    "gn:feature_code":"PPL",
    "gn:name":"Entralgo",
    "gn:population":0,
    "gn:timezone":"Europe/Madrid",
    "iso:country":"ES",
    "wof:name":"Entralgo",
    "wof:placetype":"locality"
},
  "geometry": {"coordinates":[-6.85,43.15],"type":"Point"}
}