{
  "type": "Feature",
  "properties": {
    "iso:country":"ES",
    "name:spa_x_preferred":[
        "Larrasquitu"
    ],
    "wof:name":"Larraskitu",
    "wof:placetype":"neighbourhood"
},
  "geometry": {"coordinates":[-2.93513309358636,43.24449232019686],"type":"Point"}
}