{
  "type": "Feature",
  "properties": {
    "gn:gn_country":"ES",
    "gn:gn_fcode":"PPLA3",
    "gn:gn_pop":55,
    "gn:population":55,
    "iso:country":"ES",
    "name:ara_x_preferred":[
        "\u063a\u0627\u0631\u063a\u0627\u0646\u062a\u0627 \u062f\u064a\u0644 \u0641\u064a\u0627\u0631"
    ],
    "name:cat_x_preferred":[
        "Garganta del Villar"
    ],
    "name:eng_x_preferred":[
        "Garganta del Villar"
    ],
    "name:eus_x_preferred":[
        "Garganta del Villar"
    ],
    "name:fas_x_preferred":[
        "\u06af\u0627\u0631\u06af\u0627\u0646\u062a\u0627 \u062f\u0644 \u0628\u06cc\u06cc\u0627\u0631"
    ],
    "name:fra_x_preferred":[
        "Garganta del Villar"
    ],
    "name:hun_x_preferred":[
        "Garganta del Villar"
    ],
    "name:hye_x_preferred":[
        "\u0533\u0561\u0580\u0563\u0561\u0576\u057f\u0561 \u0564\u0565\u056c \u054e\u056b\u056c\u0575\u0561\u0580"
    ],
    "name:ina_x_preferred":[
        "Garganta del Villar"
    ],
    "name:ita_x_preferred":[
        "Garganta del Villar"
    ],
    "name:kaz_x_preferred":[
        "\u0413\u0430\u0440\u0433\u0430\u043d\u0442\u0430-\u0434\u0435\u043b\u044c-\u0412\u0438\u043b\u044c\u044f\u0440"
    ],
    "name:mkd_x_preferred":[
        "\u0413\u0430\u0440\u0433\u0430\u043d\u0442\u0430 \u0434\u0435\u043b \u0412\u0438\u043b\u0458\u0430\u0440"
    ],
    "name:msa_x_preferred":[
        "Garganta del Villar"
    ],
    "name:nld_x_preferred":[
        "Garganta del Villar"
    ],
    "name:oci_x_preferred":[
        "Garganta del Villar"
    ],
    "name:pol_x_preferred":[
        "Garganta del Villar"
    ],
    "name:por_x_preferred":[
        "Garganta del Villar"
    ],
    "name:rus_x_preferred":[
        "\u0413\u0430\u0440\u0433\u0430\u043d\u0442\u0430-\u0434\u0435\u043b\u044c-\u0412\u0438\u043b\u044c\u044f\u0440"
    ],
    "name:spa_x_preferred":[
        "Garganta del Villar"
    ],
    "name:swe_x_preferred":[
        "Garganta del Villar"
    ],
    "name:ukr_x_preferred":[
        "\u0413\u0430\u0440\u0433\u0430\u043d\u0442\u0430-\u0434\u0435\u043b\u044c-\u0412\u0456\u043b\u044c\u044f\u0440"
    ],
    "name:uzb_x_preferred":[
        "Garganta del Villar"
    ],
    "name:vie_x_preferred":[
        "Garganta del Villar"
    ],
    "name:war_x_preferred":[
        "Garganta del Villar"
    ],
    "name:zho_x_preferred":[
        "\u52a0\u5c14\u7518\u5854\u5fb7\u5c14\u7ef4\u5229\u4e9a\u5c14"
    ],
    "qs_pg:aaroncc":"ES",
    "qs_pg:gn_country":"ES",
    "qs_pg:gn_fcode":"PPLA3",
    "qs_pg:gn_pop":55,
    "qs_pg:name":"Garganta del Villar",
    "qs_pg:name_adm0":"Espa\u00f1a",
    "qs_pg:name_adm1":"Castilla y Le\u00f3n",
    "qs_pg:photos_9r":0,
    "qs_pg:photos_sr":0,
    "qs_pg:pop_sr":1,
    "qs_pg:qs_pg_placetype":"locality",
    "qs_pg:qs_pg_placetype_gp":"Town",
    "qs_pg:woe_adm0":23424950,
    "woe:adm0_id":23424950,
    "woe:name_adm0":"Espa\u00f1a",
    "woe:name_adm1":"Castilla y Le\u00f3n",
    "woe:placetype":"Town",
    "wof:name":"Garganta del Villar",
    "wof:placetype":"locality",
    "wof:population":55
},
  "geometry": {"coordinates":[-5.1042,40.44965],"type":"Point"}
}