{
  "type": "Feature",
  "properties": {
    "gn:gn_country":"ES",
    "gn:gn_fcode":"PPLA3",
    "gn:gn_pop":130,
    "gn:population":130,
    "iso:country":"ES",
    "name:ara_x_preferred":[
        "\u0641\u064a\u0627\u0644\u0628\u0627 \u062f\u064a \u0628\u064a\u0631\u064a\u062e\u064a\u0644"
    ],
    "name:arg_x_preferred":[
        "Villalba"
    ],
    "name:baq_x_preferred":[
        "Villalba de Perejil"
    ],
    "name:cat_x_preferred":[
        "Villalba de Perejil"
    ],
    "name:chi_x_preferred":[
        "\u6bd4\u5229\u4e9a\u5c14\u74e6\u5fb7\u4f69\u96f7\u5e0c\u5c14"
    ],
    "name:dut_x_preferred":[
        "Villalba de Perejil"
    ],
    "name:eng_x_preferred":[
        "Villalba de Perejil"
    ],
    "name:fre_x_preferred":[
        "Villalba de Perejil"
    ],
    "name:hun_x_preferred":[
        "Villalba de Perejil"
    ],
    "name:ita_x_preferred":[
        "Villalba de Perejil"
    ],
    "name:kaz_x_preferred":[
        "\u0412\u0438\u043b\u044c\u044f\u043b\u044c\u0431\u0430-\u0434\u0435-\u041f\u0435\u0440\u0435\u0445\u0438\u043b\u044c"
    ],
    "name:may_x_preferred":[
        "Villalba de Perejil"
    ],
    "name:nan_x_preferred":[
        "Villalba de Perejil"
    ],
    "name:oci_x_preferred":[
        "Villalba de Perejil"
    ],
    "name:pol_x_preferred":[
        "Villalba de Perejil"
    ],
    "name:por_x_preferred":[
        "Villalba de Perejil"
    ],
    "name:rus_x_preferred":[
        "\u0412\u0438\u043b\u044c\u044f\u043b\u044c\u0431\u0430-\u0434\u0435-\u041f\u0435\u0440\u0435\u0445\u0438\u043b\u044c"
    ],
    "name:spa_x_preferred":[
        "Villalba de Perejil"
    ],
    "name:swe_x_preferred":[
        "Villalba de Perejil"
    ],
    "name:ukr_x_preferred":[
        "\u0412\u0456\u043b\u044c\u044f\u043b\u044c\u0431\u0430-\u0434\u0435-\u041f\u0435\u0440\u0435\u0445\u0456\u043b\u044c"
    ],
    "name:uzb_x_preferred":[
        "Villalba de Perejil"
    ],
    "name:vie_x_preferred":[
        "Villalba de Perejil"
    ],
    "name:war_x_preferred":[
        "Villalba de Perejil"
    ],
    "qs_pg:aaroncc":"ES",
    "qs_pg:gn_country":"ES",
    "qs_pg:gn_fcode":"PPLA3",
    "qs_pg:gn_pop":130,
    "qs_pg:name":"Villalba de Perejil",
    "qs_pg:name_adm0":"Espa\u00f1a",
    "qs_pg:name_adm1":"Arag\u00f3n",
    "qs_pg:photos_9r":0,
    "qs_pg:photos_sr":0,
    "qs_pg:pop_sr":1,
    "qs_pg:qs_pg_placetype":"locality",
    "qs_pg:qs_pg_placetype_gp":"Town",
    "qs_pg:woe_adm0":23424950,
    "woe:adm0_id":23424950,
    "woe:name_adm0":"Espa\u00f1a",
    "woe:name_adm1":"Arag\u00f3n",
    "woe:placetype":"Town",
    "wof:name":"Villalba de Perejil",
    "wof:placetype":"locality",
    "wof:population":130
},
  "geometry": {"coordinates":[-1.54833,41.32742],"type":"Point"}
}