{
  "type": "Feature",
  "properties": {
    "iso:country":"ES",
    "name:ceb_x_preferred":[
        "El Rinc\u00f3n"
    ],
    "name:deu_x_preferred":[
        "El Rinc\u00f3n"
    ],
    "name:ita_x_preferred":[
        "El Rinc\u00f3n"
    ],
    "name:spa_x_preferred":[
        "El Rinc\u00f3n"
    ],
    "name:swe_x_preferred":[
        "El Rinc\u00f3n"
    ],
    "qs_pg:aaroncc":"ES",
    "qs_pg:name":"El Rinc\u00f3n",
    "qs_pg:name_adm0":"Espa\u00f1a",
    "qs_pg:name_adm1":"Islas Canarias",
    "qs_pg:photos":34,
    "qs_pg:photos_1k":7,
    "qs_pg:photos_9k":1,
    "qs_pg:photos_9r":2,
    "qs_pg:photos_all":34,
    "qs_pg:photos_sr":2,
    "qs_pg:pop_sr":0,
    "qs_pg:qs_pg_placetype":"locality",
    "qs_pg:qs_pg_placetype_gp":"Town",
    "qs_pg:woe_adm0":23424950,
    "woe:adm0_id":23424950,
    "woe:name_adm0":"Espa\u00f1a",
    "woe:name_adm1":"Islas Canarias",
    "woe:placetype":"Town",
    "wof:name":"El Rinc\u00f3n",
    "wof:placetype":"locality"
},
  "geometry": {"coordinates":[-15.53721,27.9717975],"type":"Point"}
}