{
  "type": "Feature",
  "properties": {
    "gn:admin1_code":"51",
    "gn:admin2_code":"J",
    "gn:admin3_code":"23101",
    "gn:asciiname":"La Solana",
    "gn:country_code":"ES",
    "gn:dem":849,
    "gn:feature_class":"P",
    "gn:feature_code":"PPL",
    "gn:name":"La Solana",
    "gn:population":0,
    "gn:timezone":"Europe/Madrid",
    "iso:country":"ES",
    "name:und_x_variant":[
        "Caser\u00edo La Solana",
        "La Solana"
    ],
    "wof:name":"La Solana",
    "wof:placetype":"locality"
},
  "geometry": {"coordinates":[-2.64985,38.45754],"type":"Point"}
}