{
  "type": "Feature",
  "properties": {
    "gn:admin1_code":"58",
    "gn:admin2_code":"C",
    "gn:admin3_code":"15010",
    "gn:asciiname":"Sendelle",
    "gn:cc2":"ES",
    "gn:country_code":"ES",
    "gn:dem":428,
    "gn:feature_class":"P",
    "gn:feature_code":"PPL",
    "gn:name":"Sendelle",
    "gn:population":0,
    "gn:timezone":"Europe/Madrid",
    "iso:country":"ES",
    "name:und_x_variant":[
        "Santa Mar\u00eda",
        "Sendelle"
    ],
    "wof:name":"Sendelle",
    "wof:placetype":"locality"
},
  "geometry": {"coordinates":[-8.16667,42.98333],"type":"Point"}
}