{
  "type": "Feature",
  "properties": {
    "gn:admin1_code":"51",
    "gn:admin2_code":"CA",
    "gn:admin3_code":"11030",
    "gn:asciiname":"El Campillo",
    "gn:cc2":"ES",
    "gn:country_code":"ES",
    "gn:dem":9,
    "gn:feature_class":"P",
    "gn:feature_code":"PPL",
    "gn:name":"El Campillo",
    "gn:population":0,
    "gn:timezone":"Europe/Madrid",
    "iso:country":"ES",
    "name:und_x_variant":[
        "Caser\u00edo El Campillo",
        "El Campillo"
    ],
    "wof:name":"El Campillo",
    "wof:placetype":"locality"
},
  "geometry": {"coordinates":[-6.31667,36.65],"type":"Point"}
}