{
  "type": "Feature",
  "properties": {
    "gn:admin1_code":"51",
    "gn:admin2_code":"CA",
    "gn:admin3_code":"11030",
    "gn:asciiname":"El Campillo",
    "gn:cc2":"ES",
    "gn:country_code":"ES",
    "gn:dem":9,
    "gn:feature_class":"P",
    "gn:feature_code":"PPL",
    "gn:name":"El Campillo",
    "gn:population":0,
    "gn:timezone":"Europe/Madrid",
    "iso:country":"ES",
    "name:arg_x_preferred":[
        "El Campillo"
    ],
    "name:cat_x_preferred":[
        "El Campillo"
    ],
    "name:deu_x_preferred":[
        "El Campillo"
    ],
    "name:epo_x_preferred":[
        "El Campillo"
    ],
    "name:eus_x_preferred":[
        "El Campillo"
    ],
    "name:fra_x_preferred":[
        "El Campillo"
    ],
    "name:glg_x_preferred":[
        "El Campillo"
    ],
    "name:hun_x_preferred":[
        "El Campillo"
    ],
    "name:hye_x_preferred":[
        "\u0537\u056c \u053f\u0561\u0574\u057a\u056b\u056c\u0575\u0578"
    ],
    "name:ita_x_preferred":[
        "El Campillo"
    ],
    "name:msa_x_preferred":[
        "El Campillo"
    ],
    "name:nld_x_preferred":[
        "El Campillo"
    ],
    "name:oci_x_preferred":[
        "El Campillo"
    ],
    "name:pol_x_preferred":[
        "El Campillo"
    ],
    "name:por_x_preferred":[
        "El Campillo"
    ],
    "name:rus_x_preferred":[
        "\u042d\u043b\u044c-\u041a\u0430\u043c\u043f\u0438\u043b\u044c\u043e"
    ],
    "name:spa_x_preferred":[
        "El Campillo"
    ],
    "name:ukr_x_preferred":[
        "\u0415\u043b\u044c-\u041a\u0430\u043c\u043f\u0456\u043b\u044c\u0439\u043e"
    ],
    "name:und_x_variant":[
        "Caser\u00edo El Campillo"
    ],
    "name:vie_x_preferred":[
        "El Campillo"
    ],
    "name:war_x_preferred":[
        "El Campillo"
    ],
    "wof:name":"El Campillo",
    "wof:placetype":"locality"
},
  "geometry": {"coordinates":[-6.31667,36.65],"type":"Point"}
}