{
  "type": "Feature",
  "properties": {
    "gn:gn_country":"ES",
    "gn:gn_fcode":"PPLA3",
    "gn:gn_pop":616,
    "gn:population":616,
    "iso:country":"ES",
    "name:ara_x_preferred":[
        "\u062a\u0648\u0631\u064a\u0645\u064a\u0646\u062c\u0627"
    ],
    "name:arm_x_preferred":[
        "\u054f\u0578\u057c\u0565\u0574\u0565\u0576\u0563\u0561"
    ],
    "name:baq_x_preferred":[
        "Torremenga"
    ],
    "name:cat_x_preferred":[
        "Torremenga"
    ],
    "name:chi_x_preferred":[
        "\u6258\u96f7\u95e8\u52a0"
    ],
    "name:dut_x_preferred":[
        "Torremenga"
    ],
    "name:eng_x_preferred":[
        "Torremenga"
    ],
    "name:epo_x_preferred":[
        "Torremenga"
    ],
    "name:fre_x_preferred":[
        "Torremenga"
    ],
    "name:hun_x_preferred":[
        "Torremenga"
    ],
    "name:ina_x_preferred":[
        "Torremenga"
    ],
    "name:ita_x_preferred":[
        "Torremenga"
    ],
    "name:may_x_preferred":[
        "Torremenga"
    ],
    "name:nan_x_preferred":[
        "Torremenga"
    ],
    "name:oci_x_preferred":[
        "Torremenga"
    ],
    "name:pol_x_preferred":[
        "Torremenga"
    ],
    "name:por_x_preferred":[
        "Torremenga"
    ],
    "name:rum_x_preferred":[
        "Torremenga"
    ],
    "name:rus_x_preferred":[
        "\u0422\u043e\u0440\u0440\u0435\u043c\u0435\u043d\u0433\u0430"
    ],
    "name:spa_x_preferred":[
        "Torremenga"
    ],
    "name:swe_x_preferred":[
        "Torremenga"
    ],
    "name:ukr_x_preferred":[
        "\u0422\u043e\u0440\u0440\u0435\u043c\u0435\u043d\u0433\u0430"
    ],
    "name:uzb_x_preferred":[
        "Torremenga"
    ],
    "name:vie_x_preferred":[
        "Torremenga"
    ],
    "name:war_x_preferred":[
        "Torremenga"
    ],
    "qs_pg:aaroncc":"ES",
    "qs_pg:gn_country":"ES",
    "qs_pg:gn_fcode":"PPLA3",
    "qs_pg:gn_pop":616,
    "qs_pg:name":"Torremenga",
    "qs_pg:name_adm0":"Espa\u00f1a",
    "qs_pg:name_adm1":"Extremadura",
    "qs_pg:photos":85,
    "qs_pg:photos_1k":17,
    "qs_pg:photos_9k":1,
    "qs_pg:photos_9r":3,
    "qs_pg:photos_all":85,
    "qs_pg:photos_sr":3,
    "qs_pg:pop_sr":2,
    "qs_pg:qs_pg_placetype":"locality",
    "qs_pg:qs_pg_placetype_gp":"Town",
    "qs_pg:woe_adm0":23424950,
    "woe:adm0_id":23424950,
    "woe:name_adm0":"Espa\u00f1a",
    "woe:name_adm1":"Extremadura",
    "woe:placetype":"Town",
    "wof:name":"Torremenga",
    "wof:placetype":"locality",
    "wof:population":616
},
  "geometry": {"coordinates":[-5.77471,40.04658],"type":"Point"}
}