{
  "type": "Feature",
  "properties": {
    "gn:admin1_code":"31",
    "gn:admin2_code":"MU",
    "gn:admin3_code":"30026",
    "gn:asciiname":"Fuente de Meca",
    "gn:country_code":"ES",
    "gn:dem":139,
    "gn:feature_class":"P",
    "gn:feature_code":"PPL",
    "gn:name":"Fuente de Meca",
    "gn:population":0,
    "gn:timezone":"Europe/Madrid",
    "iso:country":"ES",
    "name:und_x_variant":[
        "Caser\u00edo Fuente de Meca",
        "Fuente de Meca"
    ],
    "wof:name":"Fuente de Meca",
    "wof:placetype":"locality"
},
  "geometry": {"coordinates":[-1.38078,37.5904],"type":"Point"}
}