{
  "type": "Feature",
  "properties": {
    "gn:admin1_code":"51",
    "gn:admin2_code":"GR",
    "gn:admin3_code":"18100",
    "gn:asciiname":"Cortijo de Tejas Verdes",
    "gn:country_code":"ES",
    "gn:dem":491,
    "gn:feature_class":"P",
    "gn:feature_code":"PPLF",
    "gn:name":"Cortijo de Tejas Verdes",
    "gn:population":0,
    "gn:timezone":"Europe/Madrid",
    "iso:country":"ES",
    "wof:name":"Cortijo de Tejas Verdes",
    "wof:placetype":"locality"
},
  "geometry": {"coordinates":[-4.06903,37.20115],"type":"Point"}
}