{
  "type": "Feature",
  "properties": {
    "gn:country":"ES",
    "gn:fcode":"PPLA3",
    "gn:population":498,
    "iso:country":"ES",
    "name:ara_x_preferred":[
        "\u0628\u064a\u062f\u0631\u0648\u0633\u0627 \u062f\u064a \u062f\u0648\u064a\u0631\u0648"
    ],
    "name:arg_x_preferred":[
        "Pedrosa de Duero"
    ],
    "name:azb_x_preferred":[
        "\u067e\u062f\u0631\u0633\u0627 \u062f \u062f\u0648\u0626\u0631\u0648"
    ],
    "name:cat_x_preferred":[
        "Pedrosa de Duero"
    ],
    "name:eng_x_preferred":[
        "Pedrosa de Duero"
    ],
    "name:epo_x_preferred":[
        "Pedrosa de Duero"
    ],
    "name:eus_x_preferred":[
        "Pedrosa de Duero"
    ],
    "name:fas_x_preferred":[
        "\u067e\u062f\u0631\u0633\u0627 \u062f \u062f\u0648\u0626\u0631\u0648"
    ],
    "name:fra_x_preferred":[
        "Pedrosa de Duero"
    ],
    "name:glg_x_preferred":[
        "Pedrosa de Duero"
    ],
    "name:haw_x_preferred":[
        "Pedrosa de Duero"
    ],
    "name:hun_x_preferred":[
        "Pedrosa de Duero"
    ],
    "name:ina_x_preferred":[
        "Pedrosa de Duero"
    ],
    "name:ita_x_preferred":[
        "Pedrosa de Duero"
    ],
    "name:msa_x_preferred":[
        "Pedrosa de Duero"
    ],
    "name:nan_x_preferred":[
        "Pedrosa de Duero"
    ],
    "name:nld_x_preferred":[
        "Pedrosa de Duero"
    ],
    "name:oci_x_preferred":[
        "Pedrosa de Duero"
    ],
    "name:pol_x_preferred":[
        "Pedrosa de Duero"
    ],
    "name:por_x_preferred":[
        "Pedrosa de Duero"
    ],
    "name:rus_x_preferred":[
        "\u041f\u0435\u0434\u0440\u043e\u0441\u0430-\u0434\u0435-\u0414\u0443\u044d\u0440\u043e"
    ],
    "name:spa_x_preferred":[
        "Pedrosa de Duero"
    ],
    "name:swe_x_preferred":[
        "Pedrosa de Duero"
    ],
    "name:ukr_x_preferred":[
        "\u041f\u0435\u0434\u0440\u043e\u0441\u0430-\u0434\u0435-\u0414\u0443\u0435\u0440\u043e"
    ],
    "name:uzb_x_preferred":[
        "Pedrosa de Duero"
    ],
    "name:vie_x_preferred":[
        "Pedrosa de Duero"
    ],
    "name:war_x_preferred":[
        "Pedrosa de Duero"
    ],
    "name:zho_x_preferred":[
        "\u4f69\u5fb7\u7f57\u8428\u5fb7\u675c\u57c3\u7f57"
    ],
    "qs_pg:aaroncc":"ES",
    "qs_pg:gn_country":"ES",
    "qs_pg:gn_fcode":"PPLA3",
    "qs_pg:gn_pop":498,
    "qs_pg:name":"Pedrosa de Duero",
    "qs_pg:name_adm0":"Espa\u00f1a",
    "qs_pg:name_adm1":"Castilla y Le\u00f3n",
    "qs_pg:photos_9r":0,
    "qs_pg:photos_sr":0,
    "qs_pg:pop_sr":2,
    "qs_pg:qs_pg_placetype":"locality",
    "qs_pg:qs_pg_placetype_gp":"Town",
    "qs_pg:woe_adm0":23424950,
    "woe:adm0_id":23424950,
    "woe:name_adm0":"Espa\u00f1a",
    "woe:name_adm1":"Castilla y Le\u00f3n",
    "woe:placetype":"Town",
    "wof:name":"Pedrosa de Duero",
    "wof:placetype":"locality",
    "wof:population":498
},
  "geometry": {"coordinates":[-3.98804,41.71289],"type":"Point"}
}