{
  "type": "Feature",
  "properties": {
    "gn:admin1_code":"55",
    "gn:admin2_code":"ZA",
    "gn:admin3_code":"49068",
    "gn:asciiname":"Escober",
    "gn:country_code":"ES",
    "gn:dem":793,
    "gn:feature_class":"P",
    "gn:feature_code":"PPL",
    "gn:name":"Escober",
    "gn:population":0,
    "gn:timezone":"Europe/Madrid",
    "iso:country":"ES",
    "wof:name":"Escober",
    "wof:placetype":"locality"
},
  "geometry": {"coordinates":[-5.98635,41.78294],"type":"Point"}
}