{
  "type": "Feature",
  "properties": {
    "gn:gn_country":"ES",
    "gn:gn_fcode":"PPLA3",
    "gn:gn_pop":143,
    "gn:population":143,
    "iso:country":"ES",
    "name:cat_x_preferred":[
        "Meneses de Campos"
    ],
    "name:deu_x_preferred":[
        "Meneses de Campos"
    ],
    "name:eng_x_preferred":[
        "Meneses de Campos"
    ],
    "name:eus_x_preferred":[
        "Meneses de Campos"
    ],
    "name:fas_x_preferred":[
        "\u0645\u0646\u0633\u0633 \u062f \u06a9\u0627\u0645\u067e\u0633"
    ],
    "name:fra_x_preferred":[
        "Meneses de Campos"
    ],
    "name:glg_x_preferred":[
        "Meneses de Campos"
    ],
    "name:hun_x_preferred":[
        "Meneses de Campos"
    ],
    "name:hye_x_preferred":[
        "\u0544\u0565\u0576\u0565\u057d\u0565\u057d \u0564\u0565 \u053f\u0561\u0574\u057a\u0578\u057d"
    ],
    "name:ina_x_preferred":[
        "Meneses de Campos"
    ],
    "name:ita_x_preferred":[
        "Meneses de Campos"
    ],
    "name:msa_x_preferred":[
        "Meneses de Campos"
    ],
    "name:nan_x_preferred":[
        "Meneses de Campos"
    ],
    "name:nld_x_preferred":[
        "Meneses de Campos"
    ],
    "name:oci_x_preferred":[
        "Meneses de Campos"
    ],
    "name:pol_x_preferred":[
        "Meneses de Campos"
    ],
    "name:por_x_preferred":[
        "Meneses de Campos"
    ],
    "name:rus_x_preferred":[
        "\u041c\u0435\u043d\u0435\u0441\u0435\u0441-\u0434\u0435-\u041a\u0430\u043c\u043f\u043e\u0441"
    ],
    "name:spa_x_preferred":[
        "Meneses de Campos"
    ],
    "name:swe_x_preferred":[
        "Meneses de Campos"
    ],
    "name:ukr_x_preferred":[
        "\u041c\u0435\u043d\u0435\u0441\u0435\u0441-\u0434\u0435-\u041a\u0430\u043c\u043f\u043e\u0441"
    ],
    "name:uzb_x_preferred":[
        "Meneses de Campos"
    ],
    "name:vie_x_preferred":[
        "Meneses de Campos"
    ],
    "name:war_x_preferred":[
        "Meneses de Campos"
    ],
    "name:zho_x_preferred":[
        "\u6885\u5185\u585e\u65af\u5fb7\u574e\u6ce2\u65af"
    ],
    "qs_pg:aaroncc":"ES",
    "qs_pg:gn_country":"ES",
    "qs_pg:gn_fcode":"PPLA3",
    "qs_pg:gn_pop":143,
    "qs_pg:name":"Meneses de Campos",
    "qs_pg:photos_9r":0,
    "qs_pg:photos_sr":0,
    "qs_pg:pop_sr":1,
    "qs_pg:qs_pg_placetype":"locality",
    "wof:name":"Meneses de Campos",
    "wof:placetype":"locality",
    "wof:population":143
},
  "geometry": {"coordinates":[-4.91927,41.94142],"type":"Point"}
}