{
  "type": "Feature",
  "properties": {
    "gn:admin1_code":"56",
    "gn:admin2_code":"L",
    "gn:admin3_code":"25071",
    "gn:asciiname":"el Quer Foradat",
    "gn:country_code":"ES",
    "gn:dem":1393,
    "gn:feature_class":"P",
    "gn:feature_code":"PPL",
    "gn:name":"el Quer Foradat",
    "gn:population":0,
    "gn:timezone":"Europe/Madrid",
    "iso:country":"ES",
    "wof:name":"el Quer Foradat",
    "wof:placetype":"locality"
},
  "geometry": {"coordinates":[1.63576,42.32276],"type":"Point"}
}