{
  "type": "Feature",
  "properties": {
    "gn:admin1_code":"51",
    "gn:admin2_code":"GR",
    "gn:admin3_code":"18906",
    "gn:asciiname":"Guajar Fondon",
    "gn:country_code":"ES",
    "gn:dem":270,
    "gn:feature_class":"P",
    "gn:feature_code":"PPL",
    "gn:name":"Gu\u00e1jar Fond\u00f3n",
    "gn:population":0,
    "gn:timezone":"Europe/Madrid",
    "iso:country":"ES",
    "name:und_x_variant":[
        "Gu\u00e1jar Fond\u00f3n"
    ],
    "wof:name":"Guajar Fondon",
    "wof:placetype":"locality"
},
  "geometry": {"coordinates":[-3.57909,36.83535],"type":"Point"}
}