{
  "type": "Feature",
  "properties": {
    "gn:country":"ES",
    "gn:fcode":"PPL",
    "gn:population":10174,
    "iso:country":"ES",
    "name:ara_x_preferred":[
        "\u062b\u064a\u0648\u062a\u064a"
    ],
    "name:arg_x_preferred":[
        "Ceut\u00ed"
    ],
    "name:arz_x_preferred":[
        "\u062b\u064a\u0648\u062a\u0649"
    ],
    "name:ast_x_preferred":[
        "Ceut\u00ed"
    ],
    "name:azb_x_preferred":[
        "\u0633\u0626\u0648\u062a\u06cc"
    ],
    "name:cat_x_preferred":[
        "Ceut\u00ed"
    ],
    "name:ceb_x_preferred":[
        "Ceut\u00ed"
    ],
    "name:che_x_preferred":[
        "\u0421\u0435\u0443\u0442\u0438"
    ],
    "name:deu_x_preferred":[
        "Ceut\u00ed"
    ],
    "name:eng_x_preferred":[
        "Ceut\u00ed"
    ],
    "name:epo_x_preferred":[
        "Ceut\u00ed"
    ],
    "name:eus_x_preferred":[
        "Ceut\u00ed"
    ],
    "name:fas_x_preferred":[
        "\u0633\u0626\u0648\u062a\u06cc"
    ],
    "name:fra_x_preferred":[
        "Ceut\u00ed"
    ],
    "name:gle_x_preferred":[
        "Ceut\u00ed"
    ],
    "name:glg_x_preferred":[
        "Ceut\u00ed"
    ],
    "name:hun_x_preferred":[
        "Ceut\u00ed"
    ],
    "name:ina_x_preferred":[
        "Ceut\u00ed"
    ],
    "name:ita_x_preferred":[
        "Ceut\u00ed"
    ],
    "name:kat_x_preferred":[
        "\u10e1\u10d4\u10e3\u10e2\u10d8"
    ],
    "name:lit_x_preferred":[
        "Seutis"
    ],
    "name:lld_x_preferred":[
        "Ceut\u00ed"
    ],
    "name:nan_x_preferred":[
        "Ceut\u00ed"
    ],
    "name:nld_x_preferred":[
        "Ceut\u00ed"
    ],
    "name:nob_x_preferred":[
        "Ceut\u00ed"
    ],
    "name:oci_x_preferred":[
        "Ceut\u00ed"
    ],
    "name:pol_x_preferred":[
        "Ceut\u00ed"
    ],
    "name:por_x_preferred":[
        "Ceut\u00ed"
    ],
    "name:rup_x_preferred":[
        "Ceut\u00ed"
    ],
    "name:rus_x_preferred":[
        "\u0421\u0435\u0443\u0442\u0438"
    ],
    "name:spa_x_preferred":[
        "Ceut\u00ed"
    ],
    "name:sqi_x_preferred":[
        "Ceut\u00ed"
    ],
    "name:swe_x_preferred":[
        "Ceut\u00ed"
    ],
    "name:tat_x_preferred":[
        "\u0421\u0435\u0443\u0442\u0438"
    ],
    "name:ukr_x_preferred":[
        "\u0421\u0435\u0443\u0442\u0456"
    ],
    "name:vec_x_preferred":[
        "Ceut\u00ed"
    ],
    "name:war_x_preferred":[
        "Ceut\u00ed"
    ],
    "name:zho_x_preferred":[
        "\u585e\u4e4c\u8482"
    ],
    "qs_pg:aaroncc":"ES",
    "qs_pg:gn_country":"ES",
    "qs_pg:gn_fcode":"PPL",
    "qs_pg:gn_pop":10174,
    "qs_pg:name":"Ceuti",
    "qs_pg:photos_9r":0,
    "qs_pg:photos_sr":0,
    "qs_pg:pop_sr":6,
    "qs_pg:qs_pg_placetype":"locality",
    "wof:name":"Ceuti",
    "wof:placetype":"locality",
    "wof:population":10174
},
  "geometry": {"coordinates":[-1.27467,38.07859],"type":"Point"}
}