{
  "type": "Feature",
  "properties": {
    "gn:admin1_code":"55",
    "gn:admin2_code":"SA",
    "gn:admin3_code":"37370",
    "gn:asciiname":"La Sagrada",
    "gn:country_code":"ES",
    "gn:dem":735,
    "gn:feature_class":"P",
    "gn:feature_code":"PPL",
    "gn:name":"La Sagrada",
    "gn:population":0,
    "gn:timezone":"Europe/Madrid",
    "iso:country":"ES",
    "wof:name":"La Sagrada",
    "wof:placetype":"locality"
},
  "geometry": {"coordinates":[-6.13333,41.15],"type":"Point"}
}