{
  "type": "Feature",
  "properties": {
    "gn:admin1_code":"55",
    "gn:admin2_code":"SA",
    "gn:admin3_code":"37370",
    "gn:asciiname":"La Sagrada",
    "gn:country_code":"ES",
    "gn:dem":735,
    "gn:feature_class":"P",
    "gn:feature_code":"PPL",
    "gn:name":"La Sagrada",
    "gn:population":0,
    "gn:timezone":"Europe/Madrid",
    "iso:country":"ES",
    "name:arg_x_preferred":[
        "La Sagrada"
    ],
    "name:cat_x_preferred":[
        "La Sagrada"
    ],
    "name:eus_x_preferred":[
        "La Sagrada"
    ],
    "name:fra_x_preferred":[
        "La Sagrada"
    ],
    "name:hun_x_preferred":[
        "La Sagrada"
    ],
    "name:ina_x_preferred":[
        "La Sagrada"
    ],
    "name:ita_x_preferred":[
        "La Sagrada"
    ],
    "name:kaz_x_preferred":[
        "\u041b\u0430-\u0421\u0430\u0433\u0440\u0430\u0434\u0430"
    ],
    "name:msa_x_preferred":[
        "La Sagrada"
    ],
    "name:nld_x_preferred":[
        "La Sagrada"
    ],
    "name:oci_x_preferred":[
        "La Sagrada"
    ],
    "name:pol_x_preferred":[
        "La Sagrada"
    ],
    "name:por_x_preferred":[
        "La Sagrada"
    ],
    "name:rus_x_preferred":[
        "\u041b\u0430-\u0421\u0430\u0433\u0440\u0430\u0434\u0430"
    ],
    "name:spa_x_preferred":[
        "La Sagrada"
    ],
    "name:ukr_x_preferred":[
        "\u041b\u0430-\u0421\u0430\u0433\u0440\u0430\u0434\u0430"
    ],
    "name:uzb_x_preferred":[
        "La Sagrada"
    ],
    "name:vie_x_preferred":[
        "La Sagrada"
    ],
    "name:war_x_preferred":[
        "La Sagrada"
    ],
    "name:zho_x_preferred":[
        "\u62c9\u8428\u683c\u62c9\u8fbe"
    ],
    "wof:name":"La Sagrada",
    "wof:placetype":"locality"
},
  "geometry": {"coordinates":[-6.13333,41.15],"type":"Point"}
}