{
  "type": "Feature",
  "properties": {
    "gn:admin1_code":"55",
    "gn:admin2_code":"P",
    "gn:admin3_code":"34038",
    "gn:asciiname":"Lagunilla de la Vega",
    "gn:country_code":"ES",
    "gn:dem":883,
    "gn:feature_class":"P",
    "gn:feature_code":"PPL",
    "gn:name":"Lagunilla de la Vega",
    "gn:population":0,
    "gn:timezone":"Europe/Madrid",
    "iso:country":"ES",
    "name:und_x_variant":[
        "Lagunilla",
        "Lagunilla de la Vega"
    ],
    "wof:name":"Lagunilla de la Vega",
    "wof:placetype":"locality"
},
  "geometry": {"coordinates":[-4.75458,42.43816],"type":"Point"}
}