{
  "type": "Feature",
  "properties": {
    "gn:admin1_code":"53",
    "gn:admin2_code":"TF",
    "gn:admin3_code":"38038",
    "gn:asciiname":"Tahodio",
    "gn:country_code":"ES",
    "gn:dem":192,
    "gn:feature_class":"P",
    "gn:feature_code":"PPL",
    "gn:name":"Tahodio",
    "gn:population":0,
    "gn:timezone":"Atlantic/Canary",
    "iso:country":"ES",
    "wof:name":"Tahodio",
    "wof:placetype":"locality"
},
  "geometry": {"coordinates":[-16.25,28.48333],"type":"Point"}
}