{
  "type": "Feature",
  "properties": {
    "gn:admin1_code":"51",
    "gn:admin2_code":"MA",
    "gn:admin3_code":"29094",
    "gn:asciiname":"Triana",
    "gn:country_code":"ES",
    "gn:dem":71,
    "gn:feature_class":"P",
    "gn:feature_code":"PPL",
    "gn:name":"Triana",
    "gn:population":0,
    "gn:timezone":"Europe/Madrid",
    "iso:country":"ES",
    "name:cat_x_preferred":[
        "Triana"
    ],
    "name:ceb_x_preferred":[
        "Triana"
    ],
    "name:deu_x_preferred":[
        "Triana"
    ],
    "name:fra_x_preferred":[
        "Triana"
    ],
    "name:glg_x_preferred":[
        "Triana"
    ],
    "name:ita_x_preferred":[
        "Triana"
    ],
    "name:nld_x_preferred":[
        "Triana"
    ],
    "name:por_x_preferred":[
        "Triana"
    ],
    "name:spa_x_preferred":[
        "Triana"
    ],
    "name:swe_x_preferred":[
        "Triana"
    ],
    "name:ukr_x_preferred":[
        "\u0422\u0440\u0456\u0430\u043d\u0430"
    ],
    "wof:name":"Triana",
    "wof:placetype":"locality"
},
  "geometry": {"coordinates":[-4.16575,36.8187],"type":"Point"}
}