{
  "type": "Feature",
  "properties": {
    "gn:admin1_code":"34",
    "gn:admin2_code":"O",
    "gn:admin3_code":"33034",
    "gn:asciiname":"Cortina",
    "gn:country_code":"ES",
    "gn:dem":36,
    "gn:feature_class":"P",
    "gn:feature_code":"PPL",
    "gn:name":"Cortina",
    "gn:population":0,
    "gn:timezone":"Europe/Madrid",
    "iso:country":"ES",
    "name:ast_x_preferred":[
        "Cortina"
    ],
    "name:cat_x_preferred":[
        "Cortina"
    ],
    "name:ceb_x_preferred":[
        "Cortina"
    ],
    "name:deu_x_preferred":[
        "Cortina"
    ],
    "name:fas_x_preferred":[
        "\u06a9\u0648\u0631\u062a\u06cc\u0646\u0627"
    ],
    "name:heb_x_preferred":[
        "\u05e7\u05d5\u05e8\u05d8\u05d9\u05e0\u05d4"
    ],
    "name:ita_x_preferred":[
        "Cortina"
    ],
    "name:jpn_x_preferred":[
        "\u30b3\u30eb\u30c1\u30ca"
    ],
    "name:nld_x_preferred":[
        "Cortina"
    ],
    "name:nor_x_preferred":[
        "Cortina"
    ],
    "name:pol_x_preferred":[
        "Cortina"
    ],
    "name:por_x_preferred":[
        "Cortina"
    ],
    "name:spa_x_preferred":[
        "Cortina"
    ],
    "name:srp_x_preferred":[
        "\u041a\u043e\u0440\u0442\u0438\u043d\u0430"
    ],
    "name:swe_x_preferred":[
        "Cortina"
    ],
    "wof:name":"Cortina",
    "wof:placetype":"locality"
},
  "geometry": {"coordinates":[-6.42971,43.51364],"type":"Point"}
}