{
  "type": "Feature",
  "properties": {
    "gn:admin1_code":"55",
    "gn:admin2_code":"LE",
    "gn:admin3_code":"24030",
    "gn:asciiname":"Villabuena",
    "gn:country_code":"ES",
    "gn:dem":517,
    "gn:feature_class":"P",
    "gn:feature_code":"PPL",
    "gn:name":"Villabuena",
    "gn:population":0,
    "gn:timezone":"Europe/Madrid",
    "iso:country":"ES",
    "wof:name":"Villabuena",
    "wof:placetype":"locality"
},
  "geometry": {"coordinates":[-6.7377,42.63521],"type":"Point"}
}