{
  "type": "Feature",
  "properties": {
    "gn:admin1_code":"60",
    "gn:admin2_code":"A",
    "gn:admin3_code":"03136",
    "gn:asciiname":"Llombay",
    "gn:country_code":"ES",
    "gn:dem":436,
    "gn:feature_class":"P",
    "gn:feature_code":"PPL",
    "gn:name":"Llombay",
    "gn:population":0,
    "gn:timezone":"Europe/Madrid",
    "iso:country":"ES",
    "wof:name":"Llombay",
    "wof:placetype":"locality"
},
  "geometry": {"coordinates":[-0.27062,38.81565],"type":"Point"}
}