{
  "type": "Feature",
  "properties": {
    "gn:admin1_code":"58",
    "gn:admin2_code":"LU",
    "gn:admin3_code":"27023",
    "gn:asciiname":"Grolos",
    "gn:country_code":"ES",
    "gn:dem":502,
    "gn:feature_class":"P",
    "gn:feature_code":"PPL",
    "gn:name":"Grolos",
    "gn:population":0,
    "gn:timezone":"Europe/Madrid",
    "iso:country":"ES",
    "wof:name":"Grolos",
    "wof:placetype":"locality"
},
  "geometry": {"coordinates":[-7.61698,42.88263],"type":"Point"}
}