{
  "type": "Feature",
  "properties": {
    "gn:gn_country":"ES",
    "gn:gn_fcode":"PPLA3",
    "gn:gn_pop":81,
    "gn:population":81,
    "iso:country":"ES",
    "name:ara_x_preferred":[
        "\u0643\u0648\u064a\u0646\u062a\u0627\u0646\u0627\u0644\u064a\u0632"
    ],
    "name:arg_x_preferred":[
        "Quintana\u00e9lez"
    ],
    "name:cat_x_preferred":[
        "Quintana\u00e9lez"
    ],
    "name:deu_x_preferred":[
        "Quintana\u00e9lez"
    ],
    "name:eng_x_preferred":[
        "Quintana\u00e9lez"
    ],
    "name:eus_x_preferred":[
        "Quintana\u00e9lez"
    ],
    "name:fas_x_preferred":[
        "\u06a9\u06cc\u0646\u062a\u0627\u0646\u0627\u0626\u0631\u062a\u0648\u0646\u06cc\u0648"
    ],
    "name:fra_x_preferred":[
        "Quintana\u00e9lez"
    ],
    "name:glg_x_preferred":[
        "Quintana\u00e9lez"
    ],
    "name:haw_x_preferred":[
        "Quintana\u00e9lez"
    ],
    "name:hun_x_preferred":[
        "Quintana\u00e9lez"
    ],
    "name:ina_x_preferred":[
        "Quintana\u00e9lez"
    ],
    "name:ita_x_preferred":[
        "Quintana\u00e9lez"
    ],
    "name:msa_x_preferred":[
        "Quintana\u00e9lez"
    ],
    "name:nan_x_preferred":[
        "Quintana\u00e9lez"
    ],
    "name:nld_x_preferred":[
        "Quintana\u00e9lez"
    ],
    "name:oci_x_preferred":[
        "Quintana\u00e9lez"
    ],
    "name:pol_x_preferred":[
        "Quintana\u00e9lez"
    ],
    "name:por_x_preferred":[
        "Quintana\u00e9lez"
    ],
    "name:rus_x_preferred":[
        "\u041a\u0438\u043d\u0442\u0430\u043d\u0430\u044d\u043b\u0435\u0441"
    ],
    "name:spa_x_preferred":[
        "Quintana\u00e9lez"
    ],
    "name:swe_x_preferred":[
        "Quintana\u00e9lez"
    ],
    "name:ukr_x_preferred":[
        "\u041a\u0456\u043d\u0442\u0430\u043d\u0430\u0435\u043b\u0435\u0441"
    ],
    "name:vie_x_preferred":[
        "Quintana\u00e9lez"
    ],
    "name:war_x_preferred":[
        "Quintana\u00e9lez"
    ],
    "name:zho_x_preferred":[
        "\u91d1\u5854\u5948\u83b1\u65af"
    ],
    "qs_pg:aaroncc":"ES",
    "qs_pg:gn_country":"ES",
    "qs_pg:gn_fcode":"PPLA3",
    "qs_pg:gn_pop":81,
    "qs_pg:name":"Quintana\u00e9lez",
    "qs_pg:name_adm0":"Espa\u00f1a",
    "qs_pg:name_adm1":"Castilla y Le\u00f3n",
    "qs_pg:photos_9k":1,
    "qs_pg:photos_9r":1,
    "qs_pg:photos_all":1,
    "qs_pg:photos_sr":0,
    "qs_pg:pop_sr":1,
    "qs_pg:qs_pg_placetype":"locality",
    "qs_pg:qs_pg_placetype_gp":"Town",
    "qs_pg:woe_adm0":23424950,
    "woe:adm0_id":23424950,
    "woe:name_adm0":"Espa\u00f1a",
    "woe:name_adm1":"Castilla y Le\u00f3n",
    "woe:placetype":"Town",
    "wof:name":"Quintana\u00e9lez",
    "wof:placetype":"locality",
    "wof:population":81
},
  "geometry": {"coordinates":[-3.29877,42.66921],"type":"Point"}
}