{
  "type": "Feature",
  "properties": {
    "gn:admin1_code":"55",
    "gn:admin2_code":"BU",
    "gn:admin3_code":"09363",
    "gn:asciiname":"Villandiego",
    "gn:country_code":"ES",
    "gn:dem":860,
    "gn:feature_class":"P",
    "gn:feature_code":"PPL",
    "gn:name":"Villandiego",
    "gn:population":0,
    "gn:timezone":"Europe/Madrid",
    "iso:country":"ES",
    "wof:name":"Villandiego",
    "wof:placetype":"locality"
},
  "geometry": {"coordinates":[-4.02769,42.36831],"type":"Point"}
}