{
  "type": "Feature",
  "properties": {
    "gn:country":"ES",
    "gn:fcode":"PPLA3",
    "gn:population":224,
    "iso:country":"ES",
    "name:ara_x_preferred":[
        "\u0628\u0631\u064a\u0633\u064a\u0646\u0634\u064a\u0648"
    ],
    "name:arg_x_preferred":[
        "Presencio"
    ],
    "name:ast_x_preferred":[
        "Presencio"
    ],
    "name:cat_x_preferred":[
        "Presencio"
    ],
    "name:ceb_x_preferred":[
        "Presencio"
    ],
    "name:eng_x_preferred":[
        "Presencio"
    ],
    "name:epo_x_preferred":[
        "Presencio"
    ],
    "name:eus_x_preferred":[
        "Presencio"
    ],
    "name:fas_x_preferred":[
        "\u067e\u0631\u0627\u062f\u0627\u0646\u0633 \u062f \u0628\u0648\u0631\u0628\u0627"
    ],
    "name:fra_x_preferred":[
        "Presencio"
    ],
    "name:glg_x_preferred":[
        "Presencio"
    ],
    "name:haw_x_preferred":[
        "Presencio"
    ],
    "name:hun_x_preferred":[
        "Presencio"
    ],
    "name:ina_x_preferred":[
        "Presencio"
    ],
    "name:ita_x_preferred":[
        "Presencio"
    ],
    "name:msa_x_preferred":[
        "Presencio"
    ],
    "name:nan_x_preferred":[
        "Presencio"
    ],
    "name:nld_x_preferred":[
        "Presencio"
    ],
    "name:oci_x_preferred":[
        "Presencio"
    ],
    "name:pol_x_preferred":[
        "Presencio"
    ],
    "name:por_x_preferred":[
        "Presencio"
    ],
    "name:rus_x_preferred":[
        "\u041f\u0440\u0435\u0441\u0435\u043d\u0441\u0438\u043e"
    ],
    "name:spa_x_preferred":[
        "Presencio"
    ],
    "name:swe_x_preferred":[
        "Presencio"
    ],
    "name:ukr_x_preferred":[
        "\u041f\u0440\u0435\u0441\u0435\u043d\u0441\u0456\u043e"
    ],
    "name:vie_x_preferred":[
        "Presencio"
    ],
    "name:war_x_preferred":[
        "Presencio"
    ],
    "name:zho_x_preferred":[
        "\u666e\u96f7\u68ee\u897f\u5965"
    ],
    "qs_pg:aaroncc":"ES",
    "qs_pg:gn_country":"ES",
    "qs_pg:gn_fcode":"PPLA3",
    "qs_pg:gn_pop":224,
    "qs_pg:name":"Presencio",
    "qs_pg:name_adm0":"Espa\u00f1a",
    "qs_pg:name_adm1":"Castilla y Le\u00f3n",
    "qs_pg:photos_9k":1,
    "qs_pg:photos_9r":1,
    "qs_pg:photos_all":1,
    "qs_pg:photos_sr":0,
    "qs_pg:pop_sr":2,
    "qs_pg:qs_pg_placetype":"locality",
    "qs_pg:qs_pg_placetype_gp":"Town",
    "qs_pg:woe_adm0":23424950,
    "woe:adm0_id":23424950,
    "woe:name_adm0":"Espa\u00f1a",
    "woe:name_adm1":"Castilla y Le\u00f3n",
    "woe:placetype":"Town",
    "wof:name":"Presencio",
    "wof:placetype":"locality",
    "wof:population":224
},
  "geometry": {"coordinates":[-3.90135,42.18656],"type":"Point"}
}