{
  "type": "Feature",
  "properties": {
    "gn:admin1_code":"58",
    "gn:admin2_code":"C",
    "gn:admin3_code":"15902",
    "gn:asciiname":"Reboredo",
    "gn:cc2":"ES",
    "gn:country_code":"ES",
    "gn:dem":163,
    "gn:feature_class":"P",
    "gn:feature_code":"PPL",
    "gn:name":"Reboredo",
    "gn:population":0,
    "gn:timezone":"Europe/Madrid",
    "iso:country":"ES",
    "name:und_x_variant":[
        "Santiago",
        "Reboredo"
    ],
    "wof:name":"Reboredo",
    "wof:placetype":"locality"
},
  "geometry": {"coordinates":[-8.15,43.21667],"type":"Point"}
}