{
  "type": "Feature",
  "properties": {
    "gn:gn_country":"ES",
    "gn:gn_fcode":"PPL",
    "gn:gn_pop":324,
    "gn:population":324,
    "iso:country":"ES",
    "name:arg_x_preferred":[
        "Arana"
    ],
    "name:ceb_x_preferred":[
        "Arana"
    ],
    "name:deu_x_preferred":[
        "Arana"
    ],
    "name:epo_x_preferred":[
        "Arana"
    ],
    "name:eus_x_preferred":[
        "Arana"
    ],
    "name:fra_x_preferred":[
        "Arana"
    ],
    "name:jpn_x_preferred":[
        "\u30a2\u30e9\u30ca"
    ],
    "name:rus_x_preferred":[
        "\u0410\u0440\u0430\u043d\u0430"
    ],
    "name:slv_x_preferred":[
        "Arana"
    ],
    "name:spa_x_preferred":[
        "Arana"
    ],
    "name:swe_x_preferred":[
        "Arana"
    ],
    "name:tgl_x_preferred":[
        "Arana"
    ],
    "qs_pg:aaroncc":"ES",
    "qs_pg:gn_country":"ES",
    "qs_pg:gn_fcode":"PPL",
    "qs_pg:gn_pop":324,
    "qs_pg:name":"Arana",
    "qs_pg:name_adm0":"Espa\u00f1a",
    "qs_pg:name_adm1":"Castilla y Le\u00f3n",
    "qs_pg:photos_9k":1,
    "qs_pg:photos_9r":1,
    "qs_pg:photos_all":1,
    "qs_pg:photos_sr":0,
    "qs_pg:pop_sr":2,
    "qs_pg:qs_pg_placetype":"locality",
    "qs_pg:qs_pg_placetype_gp":"Town",
    "qs_pg:woe_adm0":23424950,
    "woe:adm0_id":23424950,
    "woe:name_adm0":"Espa\u00f1a",
    "woe:name_adm1":"Castilla y Le\u00f3n",
    "woe:placetype":"Town",
    "wof:name":"Arana",
    "wof:placetype":"locality",
    "wof:population":324
},
  "geometry": {"coordinates":[-2.71844,42.70071],"type":"Point"}
}