{
  "type": "Feature",
  "properties": {
    "gn:admin1_code":"32",
    "gn:admin3_code":"31120",
    "gn:asciiname":"Viguria",
    "gn:country_code":"ES",
    "gn:dem":573,
    "gn:feature_class":"P",
    "gn:feature_code":"PPL",
    "gn:name":"Viguria",
    "gn:population":0,
    "gn:timezone":"Europe/Madrid",
    "iso:country":"ES",
    "wof:name":"Viguria",
    "wof:placetype":"locality"
},
  "geometry": {"coordinates":[-1.90905,42.75684],"type":"Point"}
}