{
  "type": "Feature",
  "properties": {
    "gn:admin1_code":"59",
    "gn:admin2_code":"SS",
    "gn:admin3_code":"20029",
    "gn:asciiname":"Lastur",
    "gn:country_code":"ES",
    "gn:dem":151,
    "gn:feature_class":"P",
    "gn:feature_code":"PPL",
    "gn:name":"Lastur",
    "gn:population":0,
    "gn:timezone":"Europe/Madrid",
    "iso:country":"ES",
    "name:eus_x_preferred":[
        "Lastur"
    ],
    "name:spa_x_preferred":[
        "San Nicol\u00e1s de Lastur"
    ],
    "name:spa_x_variant":[
        "Lastur"
    ],
    "wof:name":"Lastur",
    "wof:placetype":"locality"
},
  "geometry": {"coordinates":[-2.33361,43.25072],"type":"Point"}
}