{
  "type": "Feature",
  "properties": {
    "gn:country":"ES",
    "gn:fcode":"PPLA3",
    "gn:population":58,
    "iso:country":"ES",
    "name:ara_x_preferred":[
        "\u0623\u0648\u062e\u0648\u0633-\u0623\u0644\u0628\u0648\u0633"
    ],
    "name:ast_x_preferred":[
        "Ojos-Albos"
    ],
    "name:azb_x_preferred":[
        "\u0627\u062e\u0633-\u0622\u0644\u0628\u0633"
    ],
    "name:cat_x_preferred":[
        "Ojos-Albos"
    ],
    "name:ceb_x_preferred":[
        "Ojos-Albos"
    ],
    "name:deu_x_preferred":[
        "Ojos-Albos"
    ],
    "name:eng_x_preferred":[
        "Ojos-Albos"
    ],
    "name:eus_x_preferred":[
        "Ojos-Albos"
    ],
    "name:fas_x_preferred":[
        "\u0627\u062e\u0633-\u0622\u0644\u0628\u0633"
    ],
    "name:fra_x_preferred":[
        "Ojos-Albos"
    ],
    "name:hun_x_preferred":[
        "Ojos-Albos"
    ],
    "name:ina_x_preferred":[
        "Ojos-Albos"
    ],
    "name:ita_x_preferred":[
        "Ojos-Albos"
    ],
    "name:kaz_x_preferred":[
        "\u041e\u0445\u043e\u0441-\u0410\u043b\u044c\u0431\u043e\u0441"
    ],
    "name:mkd_x_preferred":[
        "\u041e\u0445\u043e\u0441 \u0410\u043b\u0431\u043e\u0441"
    ],
    "name:msa_x_preferred":[
        "Ojos-Albos"
    ],
    "name:nld_x_preferred":[
        "Ojos-Albos"
    ],
    "name:oci_x_preferred":[
        "Ojos-Albos"
    ],
    "name:pol_x_preferred":[
        "Ojos-Albos"
    ],
    "name:por_x_preferred":[
        "Ojos-Albos"
    ],
    "name:rus_x_preferred":[
        "\u041e\u0445\u043e\u0441-\u0410\u043b\u044c\u0431\u043e\u0441"
    ],
    "name:spa_x_preferred":[
        "Ojos-Albos"
    ],
    "name:swe_x_preferred":[
        "Ojos-Albos"
    ],
    "name:ukr_x_preferred":[
        "\u041e\u0445\u043e\u0441-\u0410\u043b\u044c\u0431\u043e\u0441"
    ],
    "name:uzb_x_preferred":[
        "Ojos-Albos"
    ],
    "name:vie_x_preferred":[
        "Ojos-Albos"
    ],
    "name:war_x_preferred":[
        "Ojos-Albos"
    ],
    "name:zho_x_preferred":[
        "\u5965\u970d\u65af-\u963f\u5c14\u6c83\u65af"
    ],
    "qs_pg:aaroncc":"ES",
    "qs_pg:gn_country":"ES",
    "qs_pg:gn_fcode":"PPLA3",
    "qs_pg:gn_pop":58,
    "qs_pg:name":"Ojos-Albos",
    "qs_pg:name_adm0":"Espa\u00f1a",
    "qs_pg:name_adm1":"Castilla y Le\u00f3n",
    "qs_pg:photos_9k":1,
    "qs_pg:photos_9r":1,
    "qs_pg:photos_all":6,
    "qs_pg:photos_sr":0,
    "qs_pg:pop_sr":1,
    "qs_pg:qs_pg_placetype":"locality",
    "qs_pg:qs_pg_placetype_gp":"Town",
    "qs_pg:woe_adm0":23424950,
    "woe:adm0_id":23424950,
    "woe:name_adm0":"Espa\u00f1a",
    "woe:name_adm1":"Castilla y Le\u00f3n",
    "woe:placetype":"Town",
    "wof:name":"Ojos-Albos",
    "wof:placetype":"locality",
    "wof:population":58
},
  "geometry": {"coordinates":[-4.51633,40.70596],"type":"Point"}
}