{
  "type": "Feature",
  "properties": {
    "gn:admin1_code":"59",
    "gn:admin2_code":"VI",
    "gn:admin3_code":"01018",
    "gn:asciiname":"Zaitegui",
    "gn:country_code":"ES",
    "gn:dem":611,
    "gn:feature_class":"P",
    "gn:feature_code":"PPL",
    "gn:name":"Zaitegi",
    "gn:population":0,
    "gn:timezone":"Europe/Madrid",
    "iso:country":"ES",
    "name:eus_x_preferred":[
        "Zaitegi"
    ],
    "name:spa_x_preferred":[
        "Z\u00e1itegui"
    ],
    "wof:name":"Zaitegui",
    "wof:placetype":"locality"
},
  "geometry": {"coordinates":[-2.75,42.93333],"type":"Point"}
}