{
  "type": "Feature",
  "properties": {
    "gn:population":1125,
    "iso:country":"ES",
    "name:ara_x_preferred":[
        "\u0625\u0644\u062e\u0627\u0633"
    ],
    "name:ast_x_preferred":[
        "As Ellas"
    ],
    "name:ast_x_variant":[
        "Eljas"
    ],
    "name:cat_x_preferred":[
        "Eljas"
    ],
    "name:ceb_x_preferred":[
        "Eljas"
    ],
    "name:eng_x_preferred":[
        "Eljas"
    ],
    "name:epo_x_preferred":[
        "Eljas"
    ],
    "name:eus_x_preferred":[
        "Eljas"
    ],
    "name:fin_x_preferred":[
        "Eljas"
    ],
    "name:fra_x_preferred":[
        "Eljas"
    ],
    "name:glg_x_preferred":[
        "As Ellas"
    ],
    "name:hun_x_preferred":[
        "Eljas"
    ],
    "name:ina_x_preferred":[
        "Eljas"
    ],
    "name:ita_x_preferred":[
        "Eljas"
    ],
    "name:jpn_x_preferred":[
        "\u30a8\u30eb\u30cf\u30b9"
    ],
    "name:msa_x_preferred":[
        "Eljas"
    ],
    "name:nan_x_preferred":[
        "Eljas"
    ],
    "name:nld_x_preferred":[
        "Eljas"
    ],
    "name:oci_x_preferred":[
        "Eljas"
    ],
    "name:pol_x_preferred":[
        "Eljas"
    ],
    "name:por_x_preferred":[
        "Eljas"
    ],
    "name:ron_x_preferred":[
        "Eljas"
    ],
    "name:rus_x_preferred":[
        "\u042d\u043b\u044c\u0445\u0430\u0441"
    ],
    "name:spa_x_preferred":[
        "Eljas"
    ],
    "name:spa_x_variant":[
        "Elijas"
    ],
    "name:swe_x_preferred":[
        "Eljas"
    ],
    "name:ukr_x_preferred":[
        "\u0415\u043b\u044c\u0445\u0430\u0441"
    ],
    "name:uzb_x_preferred":[
        "Eljas"
    ],
    "name:vie_x_preferred":[
        "Eljas"
    ],
    "name:war_x_preferred":[
        "Eljas"
    ],
    "name:zho_min_nan_x_preferred":[
        "Eljas"
    ],
    "name:zho_x_preferred":[
        "\u57c3\u5c14\u54c8\u65af"
    ],
    "qs:a0":"Espa\u00f1a",
    "qs:a1":"*C\u00e1ceres",
    "qs:a1r":"0Extremadura",
    "qs:adm0":"Espa\u00f1a",
    "qs:la_lc":"*",
    "qs:level":"locality",
    "qs:loc":"Eljas",
    "qs:loc_alt":"Eljas",
    "qs:pop":0,
    "qs:type":"buffered point",
    "wd:wordcount":50,
    "wof:name":"Eljas",
    "wof:placetype":"locality",
    "wof:population":1125
},
  "geometry": {"coordinates":[-6.846111,40.217155],"type":"Point"}
}