{
  "type": "Feature",
  "properties": {
    "gn:gn_country":"ES",
    "gn:gn_fcode":"PPL",
    "gn:gn_pop":0,
    "iso:country":"ES",
    "name:bel_x_preferred":[
        "\u0410\u0440\u0433\u0456\u043d\u0435\u0433\u0456\u043d"
    ],
    "name:deu_x_preferred":[
        "Arguinegu\u00edn"
    ],
    "name:eng_x_preferred":[
        "Arguinegu\u00edn"
    ],
    "name:fra_x_preferred":[
        "Arguinegu\u00edn"
    ],
    "name:glg_x_preferred":[
        "Arguinegu\u00edn"
    ],
    "name:heb_x_preferred":[
        "\u05d0\u05e8\u05d2\u05d9\u05e0\u05d2\u05d9\u05df"
    ],
    "name:ita_x_preferred":[
        "Arguinegu\u00edn"
    ],
    "name:jpn_x_preferred":[
        "\u30a2\u30eb\u30ae\u30cd\u30b0\u30a4\u30f3"
    ],
    "name:nld_x_preferred":[
        "Arguinegu\u00edn"
    ],
    "name:nno_x_preferred":[
        "Arguineguin"
    ],
    "name:nob_x_preferred":[
        "Arguinegu\u00edn"
    ],
    "name:por_x_preferred":[
        "Arguinegu\u00edn"
    ],
    "name:rus_x_preferred":[
        "\u0410\u0440\u0433\u0438\u043d\u0435\u0433\u0438\u043d"
    ],
    "name:spa_x_preferred":[
        "Arguinegu\u00edn"
    ],
    "name:swe_x_preferred":[
        "Arguineguin"
    ],
    "name:tur_x_preferred":[
        "Arguinegu\u00edn"
    ],
    "name:unk_x_variant":[
        "Arquinequin"
    ],
    "qs_pg:aaroncc":"ES",
    "qs_pg:gn_country":"ES",
    "qs_pg:gn_fcode":"PPL",
    "qs_pg:gn_pop":0,
    "qs_pg:name":"Arguinegu\u00edn",
    "qs_pg:name_adm0":"Espa\u00f1a",
    "qs_pg:name_adm1":"Islas Canarias",
    "qs_pg:photos":398,
    "qs_pg:photos_1k":81,
    "qs_pg:photos_9k":2,
    "qs_pg:photos_9r":5,
    "qs_pg:photos_all":398,
    "qs_pg:photos_sr":6,
    "qs_pg:pop_sr":0,
    "qs_pg:qs_pg_placetype":"locality",
    "qs_pg:qs_pg_placetype_gp":"Town",
    "qs_pg:woe_adm0":23424950,
    "woe:adm0_id":23424950,
    "woe:name_adm0":"Espa\u00f1a",
    "woe:name_adm1":"Islas Canarias",
    "woe:placetype":"Town",
    "wof:name":"Arguinegu\u00edn",
    "wof:placetype":"locality"
},
  "geometry": {"coordinates":[-15.68079,27.75647],"type":"Point"}
}