{
  "type": "Feature",
  "properties": {
    "gn:admin1_code":"60",
    "gn:admin2_code":"CS",
    "gn:admin3_code":"12084",
    "gn:asciiname":"Mas de Gil y Viuda",
    "gn:country_code":"ES",
    "gn:dem":163,
    "gn:feature_class":"P",
    "gn:feature_code":"PPL",
    "gn:name":"Mas de Gil y Viuda",
    "gn:population":0,
    "gn:timezone":"Europe/Madrid",
    "iso:country":"ES",
    "wof:name":"Mas de Gil y Viuda",
    "wof:placetype":"locality"
},
  "geometry": {"coordinates":[-0.23333,40.01667],"type":"Point"}
}