{
  "type": "Feature",
  "properties": {
    "gn:gn_country":"ES",
    "gn:gn_fcode":"PPL",
    "gn:gn_pop":0,
    "iso:country":"ES",
    "name:arg_x_preferred":[
        "Pina"
    ],
    "name:bre_x_preferred":[
        "Pina"
    ],
    "name:cat_x_preferred":[
        "Pina"
    ],
    "name:ceb_x_preferred":[
        "Pina"
    ],
    "name:ces_x_preferred":[
        "Pina"
    ],
    "name:deu_x_preferred":[
        "Pina"
    ],
    "name:eng_x_preferred":[
        "Pina"
    ],
    "name:fas_x_preferred":[
        "\u067e\u06cc\u0646\u0627"
    ],
    "name:fra_x_preferred":[
        "Pina"
    ],
    "name:hun_x_preferred":[
        "Pina"
    ],
    "name:pol_x_preferred":[
        "Pina"
    ],
    "name:por_x_preferred":[
        "Pina"
    ],
    "name:spa_x_preferred":[
        "Pina"
    ],
    "name:swe_x_preferred":[
        "Pina"
    ],
    "qs_pg:aaroncc":"ES",
    "qs_pg:gn_country":"ES",
    "qs_pg:gn_fcode":"PPL",
    "qs_pg:gn_pop":0,
    "qs_pg:name":"Pina",
    "qs_pg:name_adm0":"Espa\u00f1a",
    "qs_pg:name_adm1":"Illes Balears",
    "qs_pg:photos_9r":0,
    "qs_pg:photos_sr":0,
    "qs_pg:pop_sr":0,
    "qs_pg:qs_pg_placetype":"locality",
    "qs_pg:qs_pg_placetype_gp":"Town",
    "qs_pg:woe_adm0":23424950,
    "woe:adm0_id":23424950,
    "woe:name_adm0":"Espa\u00f1a",
    "woe:name_adm1":"Illes Balears",
    "woe:placetype":"Town",
    "wof:name":"Pina",
    "wof:placetype":"locality"
},
  "geometry": {"coordinates":[2.92417,39.59911],"type":"Point"}
}