{
  "type": "Feature",
  "properties": {
    "gn:country":"ES",
    "gn:fcode":"PPL",
    "gn:population":0,
    "iso:country":"ES",
    "name:ara_x_preferred":[
        "\u0625\u064a\u0631\u064a\u0646\u064a\u0648"
    ],
    "name:arg_x_preferred":[
        "Ere\u00f1o"
    ],
    "name:ast_x_preferred":[
        "Ere\u00f1o"
    ],
    "name:bre_x_preferred":[
        "Ere\u00f1o"
    ],
    "name:cat_x_preferred":[
        "Ere\u00f1o"
    ],
    "name:eng_x_preferred":[
        "Ere\u00f1o"
    ],
    "name:eus_x_preferred":[
        "Elexalde-Zeeta"
    ],
    "name:eus_x_variant":[
        "Ere\u00f1o"
    ],
    "name:fra_x_preferred":[
        "Ere\u00f1o"
    ],
    "name:glg_x_preferred":[
        "Ere\u00f1o"
    ],
    "name:hun_x_preferred":[
        "Ere\u00f1o"
    ],
    "name:ita_x_preferred":[
        "Ere\u00f1o"
    ],
    "name:jpn_x_preferred":[
        "\u30a8\u30ec\u30cb\u30e7"
    ],
    "name:lat_x_preferred":[
        "Ere\u00f1o"
    ],
    "name:msa_x_preferred":[
        "Ere\u00f1o"
    ],
    "name:nld_x_preferred":[
        "Ere\u00f1o"
    ],
    "name:oci_x_preferred":[
        "Ere\u00f1o"
    ],
    "name:pol_x_preferred":[
        "Ere\u00f1o"
    ],
    "name:por_x_preferred":[
        "Ere\u00f1o"
    ],
    "name:rup_x_preferred":[
        "Ere\u00f1o"
    ],
    "name:rus_x_preferred":[
        "\u042d\u0440\u0435\u043d\u044c\u043e"
    ],
    "name:sco_x_preferred":[
        "Ere\u00f1o"
    ],
    "name:spa_x_preferred":[
        "Elejalde"
    ],
    "name:spa_x_variant":[
        "Ere\u00f1o"
    ],
    "name:ukr_x_preferred":[
        "\u0415\u0440\u0435\u043d\u044c\u0439\u043e"
    ],
    "name:uzb_x_preferred":[
        "Ere\u00f1o"
    ],
    "name:war_x_preferred":[
        "Ere\u00f1o"
    ],
    "name:zho_x_preferred":[
        "\u57c3\u96f7\u5c3c\u5965"
    ],
    "qs_pg:aaroncc":"ES",
    "qs_pg:gn_country":"ES",
    "qs_pg:gn_fcode":"PPL",
    "qs_pg:gn_pop":0,
    "qs_pg:name":"Ere\u00f1o",
    "qs_pg:name_adm0":"Espa\u00f1a",
    "qs_pg:name_adm1":"Euskadi",
    "qs_pg:photos":32,
    "qs_pg:photos_1k":6,
    "qs_pg:photos_9k":1,
    "qs_pg:photos_9r":2,
    "qs_pg:photos_all":32,
    "qs_pg:photos_sr":2,
    "qs_pg:pop_sr":0,
    "qs_pg:qs_pg_placetype":"locality",
    "qs_pg:qs_pg_placetype_gp":"Town",
    "qs_pg:woe_adm0":23424950,
    "woe:adm0_id":23424950,
    "woe:name_adm0":"Espa\u00f1a",
    "woe:name_adm1":"Euskadi",
    "woe:placetype":"Town",
    "wof:name":"Ere\u00f1o",
    "wof:placetype":"locality"
},
  "geometry": {"coordinates":[-2.62302,43.3555],"type":"Point"}
}