{
  "type": "Feature",
  "properties": {
    "gn:admin1_code":"59",
    "gn:admin2_code":"SS",
    "gn:admin3_code":"20081",
    "gn:asciiname":"Oiquina",
    "gn:cc2":"ES",
    "gn:country_code":"ES",
    "gn:dem":34,
    "gn:feature_class":"P",
    "gn:feature_code":"PPL",
    "gn:name":"Oikia",
    "gn:population":0,
    "gn:timezone":"Europe/Madrid",
    "iso:country":"ES",
    "name:eus_x_preferred":[
        "Oikia"
    ],
    "name:spa_x_preferred":[
        "Oiquina"
    ],
    "wof:name":"Oiquina",
    "wof:placetype":"locality"
},
  "geometry": {"coordinates":[-2.23134,43.27947],"type":"Point"}
}