{
  "type": "Feature",
  "properties": {
    "gn:admin1_code":"52",
    "gn:admin2_code":"HU",
    "gn:admin3_code":"22069",
    "gn:asciiname":"Ayerbe de Broto",
    "gn:country_code":"ES",
    "gn:dem":1185,
    "gn:feature_class":"P",
    "gn:feature_code":"PPL",
    "gn:name":"Ayerbe de Broto",
    "gn:population":0,
    "gn:timezone":"Europe/Madrid",
    "iso:country":"ES",
    "wof:name":"Ayerbe de Broto",
    "wof:placetype":"locality"
},
  "geometry": {"coordinates":[-0.14282,42.5484],"type":"Point"}
}