{
  "type": "Feature",
  "properties": {
    "gn:admin1_code":"51",
    "gn:admin2_code":"GR",
    "gn:admin3_code":"18053",
    "gn:asciiname":"Cortijillos de Campocamara",
    "gn:country_code":"ES",
    "gn:dem":1001,
    "gn:feature_class":"P",
    "gn:feature_code":"PPL",
    "gn:name":"Cortijillos de Campoc\u00e1mara",
    "gn:population":0,
    "gn:timezone":"Europe/Madrid",
    "iso:country":"ES",
    "name:und_x_variant":[
        "Caser\u00edo Cortijillos de Campoc\u00e1mara",
        "Cortijillos de Campoc\u00e1mara"
    ],
    "wof:name":"Cortijillos de Campocamara",
    "wof:placetype":"locality"
},
  "geometry": {"coordinates":[-2.85952,37.73691],"type":"Point"}
}