{
  "type": "Feature",
  "properties": {
    "gn:admin1_code":"59",
    "gn:admin2_code":"VI",
    "gn:admin3_code":"01027",
    "gn:asciiname":"Gauna",
    "gn:country_code":"ES",
    "gn:dem":600,
    "gn:feature_class":"P",
    "gn:feature_code":"PPL",
    "gn:name":"Gauna",
    "gn:population":0,
    "gn:timezone":"Europe/Madrid",
    "iso:country":"ES",
    "wof:name":"Gauna",
    "wof:placetype":"locality"
},
  "geometry": {"coordinates":[-2.49531,42.82448],"type":"Point"}
}