{
  "type": "Feature",
  "properties": {
    "gn:population":1055,
    "iso:country":"ES",
    "name:ara_x_preferred":[
        "\u0623\u0648\u062a\u064a\u0641\u0627\u0631"
    ],
    "name:arg_x_preferred":[
        "Ot\u00edvar"
    ],
    "name:ast_x_preferred":[
        "Ot\u00edvar"
    ],
    "name:cat_x_preferred":[
        "Ot\u00edvar"
    ],
    "name:ceb_x_preferred":[
        "Ot\u00edvar"
    ],
    "name:deu_x_preferred":[
        "Ot\u00edvar"
    ],
    "name:eng_x_preferred":[
        "Ot\u00edvar"
    ],
    "name:epo_x_preferred":[
        "Ot\u00edvar"
    ],
    "name:eus_x_preferred":[
        "Ot\u00edvar"
    ],
    "name:fra_x_preferred":[
        "Ot\u00edvar"
    ],
    "name:hat_x_preferred":[
        "Ot\u00edvar"
    ],
    "name:hun_x_preferred":[
        "Ot\u00edvar"
    ],
    "name:hye_x_preferred":[
        "\u0555\u057f\u056b\u057e\u0561\u0580"
    ],
    "name:ita_x_preferred":[
        "Ot\u00edvar"
    ],
    "name:kaz_x_preferred":[
        "\u041e\u0442\u0438\u0432\u0430\u0440"
    ],
    "name:msa_x_preferred":[
        "Ot\u00edvar"
    ],
    "name:nan_x_preferred":[
        "Ot\u00edvar"
    ],
    "name:nld_x_preferred":[
        "Ot\u00edvar"
    ],
    "name:oci_x_preferred":[
        "Ot\u00edvar"
    ],
    "name:pol_x_preferred":[
        "Ot\u00edvar"
    ],
    "name:por_x_preferred":[
        "Ot\u00edvar"
    ],
    "name:rus_x_preferred":[
        "\u041e\u0442\u0438\u0432\u0430\u0440"
    ],
    "name:spa_x_colloquial":[
        "Otivar"
    ],
    "name:spa_x_preferred":[
        "Ot\u00edvar"
    ],
    "name:swe_x_preferred":[
        "Ot\u00edvar"
    ],
    "name:tur_x_preferred":[
        "Ot\u00edvar"
    ],
    "name:ukr_x_preferred":[
        "\u041e\u0442\u0456\u0432\u0430\u0440"
    ],
    "name:vie_x_preferred":[
        "Ot\u00edvar"
    ],
    "name:war_x_preferred":[
        "Ot\u00edvar"
    ],
    "name:zho_x_preferred":[
        "\u5965\u8482\u74e6\u5c14"
    ],
    "qs:a0":"Espa\u00f1a",
    "qs:a1":"*Granada",
    "qs:a1r":"0Andaluc\u00eda",
    "qs:adm0":"Espa\u00f1a",
    "qs:la_lc":"*",
    "qs:level":"locality",
    "qs:loc":"Ot\u00edvar",
    "qs:loc_alt":"Otivar",
    "qs:pop":0,
    "qs:type":"buffered point",
    "wd:wordcount":192,
    "wof:lang":[
        "spa"
    ],
    "wof:name":"Ot\u00edvar",
    "wof:placetype":"locality",
    "wof:population":1055
},
  "geometry": {"coordinates":[-3.681406,36.815498],"type":"Point"}
}