{
  "type": "Feature",
  "properties": {
    "gn:admin1_code":"51",
    "gn:admin2_code":"AL",
    "gn:admin3_code":"04070",
    "gn:asciiname":"El Arroyo de Medina",
    "gn:country_code":"ES",
    "gn:dem":780,
    "gn:feature_class":"P",
    "gn:feature_code":"PPL",
    "gn:name":"El Arroyo de Medina",
    "gn:population":0,
    "gn:timezone":"Europe/Madrid",
    "iso:country":"ES",
    "wof:name":"El Arroyo de Medina",
    "wof:placetype":"locality"
},
  "geometry": {"coordinates":[-2.19686,37.47418],"type":"Point"}
}