{
  "type": "Feature",
  "properties": {
    "gn:admin1_code":"54",
    "gn:admin2_code":"GU",
    "gn:admin3_code":"19086",
    "gn:asciiname":"Gargoles de Arriba",
    "gn:country_code":"ES",
    "gn:dem":842,
    "gn:feature_class":"P",
    "gn:feature_code":"PPL",
    "gn:name":"G\u00e1rgoles de Arriba",
    "gn:population":0,
    "gn:timezone":"Europe/Madrid",
    "iso:country":"ES",
    "name:und_x_variant":[
        "G\u00e1rgoles de Arriba"
    ],
    "wof:name":"Gargoles de Arriba",
    "wof:placetype":"locality"
},
  "geometry": {"coordinates":[-2.63333,40.75],"type":"Point"}
}