{
  "type": "Feature",
  "properties": {
    "gn:gn_country":"ES",
    "gn:gn_fcode":"PPLA3",
    "gn:gn_pop":70,
    "gn:population":70,
    "iso:country":"ES",
    "name:arg_x_preferred":[
        "Saelices de la Sal"
    ],
    "name:baq_x_preferred":[
        "Saelices de la Sal"
    ],
    "name:cat_x_preferred":[
        "Saelices de la Sal"
    ],
    "name:chi_x_preferred":[
        "\u8d5b\u5229\u585e\u65af\u5fb7\u62c9\u8428\u5c14"
    ],
    "name:dut_x_preferred":[
        "Saelices de la Sal"
    ],
    "name:eng_x_preferred":[
        "Saelices de la Sal"
    ],
    "name:fre_x_preferred":[
        "Saelices de la Sal"
    ],
    "name:hun_x_preferred":[
        "Saelices de la Sal"
    ],
    "name:ina_x_preferred":[
        "Saelices de la Sal"
    ],
    "name:ita_x_preferred":[
        "Saelices de la Sal"
    ],
    "name:kaz_x_preferred":[
        "\u0421\u0430\u044d\u043b\u0438\u0441\u0435\u0441-\u0434\u0435-\u043b\u0430-\u0421\u0430\u043b\u044c"
    ],
    "name:may_x_preferred":[
        "Saelices de la Sal"
    ],
    "name:nan_x_preferred":[
        "Saelices de la Sal"
    ],
    "name:oci_x_preferred":[
        "Saelices de la Sal"
    ],
    "name:pol_x_preferred":[
        "Saelices de la Sal"
    ],
    "name:por_x_preferred":[
        "Saelices de la Sal"
    ],
    "name:rus_x_preferred":[
        "\u0421\u0430\u044d\u043b\u0438\u0441\u0435\u0441-\u0434\u0435-\u043b\u0430-\u0421\u0430\u043b\u044c"
    ],
    "name:spa_x_preferred":[
        "Saelices de la Sal"
    ],
    "name:swe_x_preferred":[
        "Saelices de la Sal"
    ],
    "name:ukr_x_preferred":[
        "\u0421\u0430\u0435\u043b\u0456\u0441\u0435\u0441-\u0434\u0435-\u043b\u0430-\u0421\u0430\u043b\u044c"
    ],
    "name:urd_x_preferred":[
        "\u0633\u06cc\u0644\u06a9\u0633 \u062f\u06d2 \u0644\u0627 \u0633\u0627\u0644"
    ],
    "name:vie_x_preferred":[
        "Saelices de la Sal"
    ],
    "name:war_x_preferred":[
        "Saelices de la Sal"
    ],
    "qs_pg:aaroncc":"ES",
    "qs_pg:gn_country":"ES",
    "qs_pg:gn_fcode":"PPLA3",
    "qs_pg:gn_pop":70,
    "qs_pg:name":"Saelices de la Sal",
    "qs_pg:name_adm0":"Espa\u00f1a",
    "qs_pg:name_adm1":"Castilla-La Mancha",
    "qs_pg:photos_9r":0,
    "qs_pg:photos_sr":0,
    "qs_pg:pop_sr":1,
    "qs_pg:qs_pg_placetype":"locality",
    "qs_pg:qs_pg_placetype_gp":"Town",
    "qs_pg:woe_adm0":23424950,
    "woe:adm0_id":23424950,
    "woe:name_adm0":"Espa\u00f1a",
    "woe:name_adm1":"Castilla-La Mancha",
    "woe:placetype":"Town",
    "wof:name":"Saelices de la Sal",
    "wof:placetype":"locality",
    "wof:population":70
},
  "geometry": {"coordinates":[-2.32325,40.90723],"type":"Point"}
}