{
  "type": "Feature",
  "properties": {
    "gn:admin1_code":"55",
    "gn:admin2_code":"LE",
    "gn:admin3_code":"24177",
    "gn:asciiname":"La Brana",
    "gn:country_code":"ES",
    "gn:dem":1266,
    "gn:feature_class":"P",
    "gn:feature_code":"PPL",
    "gn:name":"La Bra\u00f1a",
    "gn:population":0,
    "gn:timezone":"Europe/Madrid",
    "iso:country":"ES",
    "wof:name":"La Brana",
    "wof:placetype":"locality"
},
  "geometry": {"coordinates":[-5.37129,42.94054000000001],"type":"Point"}
}