{
  "type": "Feature",
  "properties": {
    "gn:gn_country":"ES",
    "gn:gn_fcode":"PPL",
    "gn:gn_pop":300,
    "gn:population":300,
    "iso:country":"ES",
    "name:unk_x_variant":[
        "R\u00edo Jallas"
    ],
    "qs_pg:aaroncc":"ES",
    "qs_pg:gn_country":"ES",
    "qs_pg:gn_fcode":"PPL",
    "qs_pg:gn_pop":300,
    "qs_pg:name":"O Pindo",
    "qs_pg:photos_9r":0,
    "qs_pg:photos_sr":0,
    "qs_pg:pop_sr":2,
    "qs_pg:qs_pg_placetype":"locality",
    "wof:name":"O Pindo",
    "wof:placetype":"locality",
    "wof:population":300
},
  "geometry": {"coordinates":[-9.13419,42.89508],"type":"Point"}
}