{
  "type": "Feature",
  "properties": {
    "gn:admin1_code":"56",
    "gn:admin2_code":"GI",
    "gn:admin3_code":"17196",
    "gn:asciiname":"la Guardia",
    "gn:country_code":"ES",
    "gn:dem":222,
    "gn:feature_class":"P",
    "gn:feature_code":"PPL",
    "gn:name":"la Gu\u00e0rdia",
    "gn:population":0,
    "gn:timezone":"Europe/Madrid",
    "iso:country":"ES",
    "name:cat_x_preferred":[
        "a Gu\u00e0rdia"
    ],
    "wof:name":"la Guardia",
    "wof:placetype":"locality"
},
  "geometry": {"coordinates":[2.87458,42.3088],"type":"Point"}
}