{
  "type": "Feature",
  "properties": {
    "gn:admin1_code":"56",
    "gn:admin2_code":"GI",
    "gn:admin3_code":"17196",
    "gn:asciiname":"la Guardia",
    "gn:country_code":"ES",
    "gn:dem":222,
    "gn:feature_class":"P",
    "gn:feature_code":"PPL",
    "gn:name":"la Gu\u00e0rdia",
    "gn:population":0,
    "gn:timezone":"Europe/Madrid",
    "iso:country":"ES",
    "name:cat_x_preferred":[
        "a Gu\u00e0rdia"
    ],
    "name:ceb_x_preferred":[
        "La Guardia"
    ],
    "name:deu_x_preferred":[
        "La Guardia"
    ],
    "name:epo_x_preferred":[
        "La Guardia"
    ],
    "name:fra_x_preferred":[
        "La Guardia"
    ],
    "name:heb_x_preferred":[
        "\u05dc\u05d4 \u05d2\u05d5\u05d0\u05e8\u05d3\u05d9\u05d4"
    ],
    "name:hun_x_preferred":[
        "La Guardia"
    ],
    "name:ita_x_preferred":[
        "La Guardia"
    ],
    "name:kor_x_preferred":[
        "\ub77c\uac00\ub514\uc544"
    ],
    "name:nld_x_preferred":[
        "La Guardia"
    ],
    "name:rus_x_preferred":[
        "\u041b\u0430-\u0413\u0443\u0430\u0440\u0434\u0438\u044f"
    ],
    "name:sco_x_preferred":[
        "La Guardia"
    ],
    "name:spa_x_preferred":[
        "La Guardia"
    ],
    "name:srp_x_preferred":[
        "La Guardia"
    ],
    "name:swe_x_preferred":[
        "La Guardia"
    ],
    "wof:name":"la Guardia",
    "wof:placetype":"locality"
},
  "geometry": {"coordinates":[2.87458,42.3088],"type":"Point"}
}