{
  "type": "Feature",
  "properties": {
    "gn:gn_country":"ES",
    "gn:gn_fcode":"PPL",
    "gn:gn_pop":307,
    "gn:population":307,
    "iso:country":"ES",
    "name:ara_x_preferred":[
        "\u0644\u0627 \u0644\u0627\u0628\u0627"
    ],
    "name:ast_x_preferred":[
        "La Lapa"
    ],
    "name:cat_x_preferred":[
        "La Lapa"
    ],
    "name:ceb_x_preferred":[
        "La Lapa"
    ],
    "name:ces_x_preferred":[
        "La Lapa"
    ],
    "name:eng_x_preferred":[
        "La Lapa"
    ],
    "name:epo_x_preferred":[
        "La Lapa"
    ],
    "name:eus_x_preferred":[
        "La Lapa"
    ],
    "name:fas_x_preferred":[
        "\u0644\u0627 \u0644\u0627\u067e\u0627"
    ],
    "name:fra_x_preferred":[
        "La Lapa"
    ],
    "name:hun_x_preferred":[
        "La Lapa"
    ],
    "name:ido_x_preferred":[
        "La Lapa"
    ],
    "name:ina_x_preferred":[
        "La Lapa"
    ],
    "name:ita_x_preferred":[
        "La Lapa"
    ],
    "name:mkd_x_preferred":[
        "\u041b\u0430 \u041b\u0430\u043f\u0430"
    ],
    "name:msa_x_preferred":[
        "La Lapa"
    ],
    "name:nan_x_preferred":[
        "La Lapa"
    ],
    "name:nld_x_preferred":[
        "La Lapa"
    ],
    "name:oci_x_preferred":[
        "La Lapa"
    ],
    "name:pol_x_preferred":[
        "La Lapa"
    ],
    "name:por_x_preferred":[
        "La Lapa"
    ],
    "name:ron_x_preferred":[
        "La Lapa"
    ],
    "name:rus_x_preferred":[
        "\u041b\u0430-\u041b\u0430\u043f\u0430"
    ],
    "name:spa_x_preferred":[
        "La Lapa"
    ],
    "name:swe_x_preferred":[
        "La Lapa"
    ],
    "name:ukr_x_preferred":[
        "\u041b\u0430-\u041b\u0430\u043f\u0430"
    ],
    "name:uzb_x_preferred":[
        "La Lapa"
    ],
    "name:vie_x_preferred":[
        "La Lapa"
    ],
    "name:war_x_preferred":[
        "La Lapa"
    ],
    "name:zho_x_preferred":[
        "\u62c9\u62c9\u5e15"
    ],
    "qs_pg:aaroncc":"ES",
    "qs_pg:gn_country":"ES",
    "qs_pg:gn_fcode":"PPL",
    "qs_pg:gn_pop":307,
    "qs_pg:name":"La Lapa",
    "qs_pg:name_adm0":"Espa\u00f1a",
    "qs_pg:name_adm1":"Extremadura",
    "qs_pg:photos_9k":2,
    "qs_pg:photos_9r":5,
    "qs_pg:photos_all":376,
    "qs_pg:photos_sr":0,
    "qs_pg:pop_sr":2,
    "qs_pg:qs_pg_placetype":"locality",
    "qs_pg:qs_pg_placetype_gp":"Town",
    "qs_pg:woe_adm0":23424950,
    "woe:adm0_id":23424950,
    "woe:name_adm0":"Espa\u00f1a",
    "woe:name_adm1":"Extremadura",
    "woe:placetype":"Town",
    "wof:name":"La Lapa",
    "wof:placetype":"locality",
    "wof:population":307
},
  "geometry": {"coordinates":[-6.51667,38.45],"type":"Point"}
}