{
  "type": "Feature",
  "properties": {
    "gn:admin1_code":"56",
    "gn:admin2_code":"L",
    "gn:admin3_code":"25252",
    "gn:asciiname":"Utxafaba",
    "gn:country_code":"ES",
    "gn:dem":248,
    "gn:feature_class":"P",
    "gn:feature_code":"PPL",
    "gn:name":"Utxafaba",
    "gn:population":0,
    "gn:timezone":"Europe/Madrid",
    "iso:country":"ES",
    "wof:name":"Utxafaba",
    "wof:placetype":"locality"
},
  "geometry": {"coordinates":[0.93333,41.66667],"type":"Point"}
}