{
  "type": "Feature",
  "properties": {
    "iso:country":"ES",
    "name:spa_x_preferred":[
        "Higuer\u00f3n"
    ],
    "wof:name":"Higueron",
    "wof:placetype":"neighbourhood"
},
  "geometry": {"coordinates":[-4.85440838941194,37.86941705476433],"type":"Point"}
}