{
  "type": "Feature",
  "properties": {
    "gn:gn_country":"ES",
    "gn:gn_fcode":"PPLA3",
    "gn:gn_pop":212,
    "gn:population":212,
    "iso:country":"ES",
    "name:ara_x_preferred":[
        "\u0627\u0644\u0628\u0648\u0631\u0646\u0648\u0633"
    ],
    "name:cat_x_preferred":[
        "Albornos"
    ],
    "name:eng_x_preferred":[
        "Albornos"
    ],
    "name:eus_x_preferred":[
        "Albornos"
    ],
    "name:fas_x_preferred":[
        "\u0622\u0644\u0628\u0631\u0646\u0633"
    ],
    "name:fra_x_preferred":[
        "Albornos"
    ],
    "name:hun_x_preferred":[
        "Albornos"
    ],
    "name:hye_x_preferred":[
        "\u0531\u056c\u0562\u0578\u0580\u0576\u0578\u057d"
    ],
    "name:ina_x_preferred":[
        "Albornos"
    ],
    "name:ita_x_preferred":[
        "Albornos"
    ],
    "name:kaz_x_preferred":[
        "\u0410\u043b\u044c\u0431\u043e\u0440\u043d\u043e\u0441"
    ],
    "name:mkd_x_preferred":[
        "\u0410\u043b\u0431\u043e\u0440\u043d\u043e\u0441"
    ],
    "name:msa_x_preferred":[
        "Albornos"
    ],
    "name:nld_x_preferred":[
        "Albornos"
    ],
    "name:oci_x_preferred":[
        "Albornos"
    ],
    "name:pam_x_preferred":[
        "Albornos"
    ],
    "name:pol_x_preferred":[
        "Albornos"
    ],
    "name:por_x_preferred":[
        "Albornos"
    ],
    "name:rup_x_preferred":[
        "Albornos"
    ],
    "name:rus_x_preferred":[
        "\u0410\u043b\u044c\u0431\u043e\u0440\u043d\u043e\u0441"
    ],
    "name:spa_x_preferred":[
        "Albornos"
    ],
    "name:swe_x_preferred":[
        "Albornos"
    ],
    "name:ukr_x_preferred":[
        "\u0410\u043b\u044c\u0431\u043e\u0440\u043d\u043e\u0441"
    ],
    "name:uzb_x_preferred":[
        "Albornos"
    ],
    "name:vie_x_preferred":[
        "Albornos"
    ],
    "name:war_x_preferred":[
        "Albornos"
    ],
    "name:zho_x_preferred":[
        "\u963f\u5c14\u6c83\u5c14\u8bfa\u65af"
    ],
    "qs_pg:aaroncc":"ES",
    "qs_pg:gn_country":"ES",
    "qs_pg:gn_fcode":"PPLA3",
    "qs_pg:gn_pop":212,
    "qs_pg:name":"Albornos",
    "qs_pg:name_adm0":"Espa\u00f1a",
    "qs_pg:name_adm1":"Castilla y Le\u00f3n",
    "qs_pg:photos_9r":0,
    "qs_pg:photos_sr":0,
    "qs_pg:pop_sr":2,
    "qs_pg:qs_pg_placetype":"locality",
    "qs_pg:qs_pg_placetype_gp":"Town",
    "qs_pg:woe_adm0":23424950,
    "woe:adm0_id":23424950,
    "woe:name_adm0":"Espa\u00f1a",
    "woe:name_adm1":"Castilla y Le\u00f3n",
    "woe:placetype":"Town",
    "wof:name":"Albornos",
    "wof:placetype":"locality",
    "wof:population":212
},
  "geometry": {"coordinates":[-4.88129,40.83795],"type":"Point"}
}