{
  "type": "Feature",
  "properties": {
    "gn:admin1_code":"51",
    "gn:admin2_code":"J",
    "gn:admin3_code":"23065",
    "gn:asciiname":"Los Arroyos",
    "gn:country_code":"ES",
    "gn:dem":1261,
    "gn:feature_class":"P",
    "gn:feature_code":"PPL",
    "gn:name":"Los Arroyos",
    "gn:population":0,
    "gn:timezone":"Europe/Madrid",
    "iso:country":"ES",
    "name:und_x_variant":[
        "Cortijo Los Arroyos",
        "Los Arroyos"
    ],
    "wof:name":"Los Arroyos",
    "wof:placetype":"locality"
},
  "geometry": {"coordinates":[-2.60009,38.30878],"type":"Point"}
}