{
  "type": "Feature",
  "properties": {
    "gn:admin1_code":"59",
    "gn:admin2_code":"BI",
    "gn:admin3_code":"48022",
    "gn:asciiname":"San Cipriano",
    "gn:country_code":"ES",
    "gn:dem":462,
    "gn:feature_class":"P",
    "gn:feature_code":"PPL",
    "gn:name":"San Cipri\u00e1n",
    "gn:population":0,
    "gn:timezone":"Europe/Madrid",
    "iso:country":"ES",
    "wof:name":"San Cipriano",
    "wof:placetype":"locality"
},
  "geometry": {"coordinates":[-3.39495,43.22428],"type":"Point"}
}