{
  "type": "Feature",
  "properties": {
    "iso:country":"ES",
    "name:eng_x_preferred":[
        "El Polvorin"
    ],
    "name:spa_x_preferred":[
        "El Polvorin"
    ],
    "wof:name":"El Polvorin",
    "wof:placetype":"neighbourhood"
},
  "geometry": {"coordinates":[-4.37481001439495,36.72658279559039],"type":"Point"}
}