{
  "type": "Feature",
  "properties": {
    "gn:admin1_code":"34",
    "gn:admin2_code":"O",
    "gn:admin3_code":"33024",
    "gn:asciiname":"Santa Cecilia",
    "gn:country_code":"ES",
    "gn:dem":153,
    "gn:feature_class":"P",
    "gn:feature_code":"PPL",
    "gn:name":"Santa Cecilia",
    "gn:population":0,
    "gn:timezone":"Europe/Madrid",
    "iso:country":"ES",
    "name:ara_x_preferred":[
        "\u0633\u0627\u0646\u062a\u0627 \u0633\u064a\u0633\u064a\u0644\u064a\u0627"
    ],
    "name:arg_x_preferred":[
        "Santa Cecilia"
    ],
    "name:azb_x_preferred":[
        "\u0633\u0627\u0646\u062a\u0627 \u0633\u0633\u06cc\u0644\u06cc\u0627"
    ],
    "name:cat_x_preferred":[
        "Santa Cecilia"
    ],
    "name:epo_x_preferred":[
        "Santa Cecilia"
    ],
    "name:eus_x_preferred":[
        "Santa Cecilia"
    ],
    "name:fas_x_preferred":[
        "\u0633\u0627\u0646\u062a\u0627 \u0633\u0633\u06cc\u0644\u06cc\u0627"
    ],
    "name:fra_x_preferred":[
        "Santa Cecilia"
    ],
    "name:glg_x_preferred":[
        "Santa Cecilia"
    ],
    "name:haw_x_preferred":[
        "Santa Cecilia"
    ],
    "name:hun_x_preferred":[
        "Santa Cecilia"
    ],
    "name:ina_x_preferred":[
        "Santa Cecilia"
    ],
    "name:ita_x_preferred":[
        "Santa Cecilia"
    ],
    "name:msa_x_preferred":[
        "Santa Cecilia"
    ],
    "name:nld_x_preferred":[
        "Santa Cecilia"
    ],
    "name:oci_x_preferred":[
        "Santa Cecilia"
    ],
    "name:pol_x_preferred":[
        "Santa Cecilia"
    ],
    "name:por_x_preferred":[
        "Santa Cecilia"
    ],
    "name:rus_x_preferred":[
        "\u0421\u0430\u043d\u0442\u0430-\u0421\u0435\u0441\u0438\u043b\u0438\u044f"
    ],
    "name:spa_x_preferred":[
        "Santa Cecilia"
    ],
    "name:ukr_x_preferred":[
        "\u0421\u0430\u043d\u0442\u0430-\u0421\u0435\u0441\u0456\u043b\u0456\u044f"
    ],
    "name:vie_x_preferred":[
        "Santa Cecilia"
    ],
    "name:war_x_preferred":[
        "Santa Cecilia"
    ],
    "name:zho_x_preferred":[
        "\u5723\u585e\u897f\u5229\u4e9a"
    ],
    "wof:name":"Santa Cecilia",
    "wof:placetype":"locality"
},
  "geometry": {"coordinates":[-5.66199,43.47801],"type":"Point"}
}