{
  "type": "Feature",
  "properties": {
    "gn:admin1_code":"31",
    "gn:admin2_code":"MU",
    "gn:admin3_code":"30019",
    "gn:asciiname":"Caserio Carrasquilla",
    "gn:country_code":"ES",
    "gn:dem":326,
    "gn:feature_class":"P",
    "gn:feature_code":"PPL",
    "gn:name":"Caser\u00edo Carrasquilla",
    "gn:population":0,
    "gn:timezone":"Europe/Madrid",
    "iso:country":"ES",
    "name:und_x_variant":[
        "Casa de la Carrasquilla",
        "Caser\u00edo Carrasquilla"
    ],
    "wof:name":"Caserio Carrasquilla",
    "wof:placetype":"locality"
},
  "geometry": {"coordinates":[-1.38832,38.28984000000001],"type":"Point"}
}