{
  "type": "Feature",
  "properties": {
    "gn:gn_country":"ES",
    "gn:gn_fcode":"PPLA3",
    "gn:gn_pop":54,
    "gn:population":54,
    "iso:country":"ES",
    "name:arg_x_preferred":[
        "Lagueruela"
    ],
    "name:bul_x_preferred":[
        "\u041b\u0430\u0433\u0443\u0435\u0440\u0443\u0435\u043b\u0430"
    ],
    "name:cat_x_preferred":[
        "Lagueruela"
    ],
    "name:eng_x_preferred":[
        "Lagueruela"
    ],
    "name:eus_x_preferred":[
        "Lagueruela"
    ],
    "name:fas_x_preferred":[
        "\u0644\u0627\u06af\u0631\u0648\u0626\u0644\u0627"
    ],
    "name:fra_x_preferred":[
        "Lagueruela"
    ],
    "name:hun_x_preferred":[
        "Lagueruela"
    ],
    "name:ita_x_preferred":[
        "Lagueruela"
    ],
    "name:kaz_x_preferred":[
        "\u041b\u0430\u0433\u0435\u0440\u0443\u044d\u043b\u0430"
    ],
    "name:msa_x_preferred":[
        "Lagueruela"
    ],
    "name:nan_x_preferred":[
        "Lagueruela"
    ],
    "name:nld_x_preferred":[
        "Lagueruela"
    ],
    "name:oci_x_preferred":[
        "Lagueruela"
    ],
    "name:pol_x_preferred":[
        "Lagueruela"
    ],
    "name:por_x_preferred":[
        "Lagueruela"
    ],
    "name:rus_x_preferred":[
        "\u041b\u0430\u0433\u0435\u0440\u0443\u044d\u043b\u0430"
    ],
    "name:spa_x_preferred":[
        "Lagueruela"
    ],
    "name:swe_x_preferred":[
        "Lagueruela"
    ],
    "name:ukr_x_preferred":[
        "\u041b\u0430\u0433\u0435\u0440\u0443\u0435\u043b\u0430"
    ],
    "name:urd_x_preferred":[
        "\u0644\u0627\u06af\u0648\u06cc\u0631\u0648\u06cc\u0644\u0627"
    ],
    "name:uzb_x_preferred":[
        "Lagueruela"
    ],
    "name:vie_x_preferred":[
        "Lagueruela"
    ],
    "name:war_x_preferred":[
        "Lagueruela"
    ],
    "name:zho_x_preferred":[
        "\u62c9\u683c\u9c81\u57c3\u62c9"
    ],
    "qs_pg:aaroncc":"ES",
    "qs_pg:gn_country":"ES",
    "qs_pg:gn_fcode":"PPLA3",
    "qs_pg:gn_pop":54,
    "qs_pg:name":"Lagueruela",
    "qs_pg:name_adm0":"Espa\u00f1a",
    "qs_pg:name_adm1":"Arag\u00f3n",
    "qs_pg:photos_9r":0,
    "qs_pg:photos_sr":0,
    "qs_pg:pop_sr":1,
    "qs_pg:qs_pg_placetype":"locality",
    "qs_pg:qs_pg_placetype_gp":"Town",
    "qs_pg:woe_adm0":23424950,
    "woe:adm0_id":23424950,
    "woe:name_adm0":"Espa\u00f1a",
    "woe:name_adm1":"Arag\u00f3n",
    "woe:placetype":"Town",
    "wof:name":"Lagueruela",
    "wof:placetype":"locality",
    "wof:population":54
},
  "geometry": {"coordinates":[-1.19283,41.0425],"type":"Point"}
}