{
  "type": "Feature",
  "properties": {
    "gn:gn_country":"ES",
    "gn:gn_fcode":"PPLA3",
    "gn:gn_pop":596,
    "gn:population":596,
    "iso:country":"ES",
    "name:arg_x_preferred":[
        "Torreciella en Cameros"
    ],
    "name:ast_x_preferred":[
        "Torrecilla en Cameros"
    ],
    "name:cat_x_preferred":[
        "Torrecilla en Cameros"
    ],
    "name:ceb_x_preferred":[
        "Torrecilla en Cameros"
    ],
    "name:deu_x_preferred":[
        "Torrecilla en Cameros"
    ],
    "name:eng_x_preferred":[
        "Torrecilla en Cameros"
    ],
    "name:eus_x_preferred":[
        "Torrecilla en Cameros"
    ],
    "name:fra_x_preferred":[
        "Torrecilla en Cameros"
    ],
    "name:glg_x_preferred":[
        "Torrecilla en Cameros"
    ],
    "name:hun_x_preferred":[
        "Torrecilla en Cameros"
    ],
    "name:hye_x_preferred":[
        "\u054f\u0578\u057c\u0565\u057d\u056b\u056c\u056b\u0561 \u0567\u0576 \u053f\u0561\u0574\u0565\u0580\u0578\u057d"
    ],
    "name:ita_x_preferred":[
        "Torrecilla en Cameros"
    ],
    "name:kaz_x_preferred":[
        "\u0422\u043e\u0440\u0440\u0435\u0441\u0438\u043b\u044c\u044f-\u044d\u043d-\u041a\u0430\u043c\u0435\u0440\u043e\u0441"
    ],
    "name:lad_x_preferred":[
        "Torrecilla en Cameros"
    ],
    "name:msa_x_preferred":[
        "Torrecilla en Cameros"
    ],
    "name:nan_x_preferred":[
        "Torrecilla en Cameros"
    ],
    "name:nld_x_preferred":[
        "Torrecilla en Cameros"
    ],
    "name:oci_x_preferred":[
        "Torrecilla en Cameros"
    ],
    "name:pol_x_preferred":[
        "Torrecilla en Cameros"
    ],
    "name:por_x_preferred":[
        "Torrecilla en Cameros"
    ],
    "name:rup_x_preferred":[
        "Torrecilla en Cameros"
    ],
    "name:rus_x_preferred":[
        "\u0422\u043e\u0440\u0440\u0435\u0441\u0438\u043b\u044c\u044f-\u044d\u043d-\u041a\u0430\u043c\u0435\u0440\u043e\u0441"
    ],
    "name:spa_x_preferred":[
        "Torrecilla en Cameros"
    ],
    "name:swe_x_preferred":[
        "Torrecilla en Cameros"
    ],
    "name:ukr_x_preferred":[
        "\u0422\u043e\u0440\u0440\u0435\u0441\u0456\u043b\u044c\u044f-\u0435\u043d-\u041a\u0430\u043c\u0435\u0440\u043e\u0441"
    ],
    "name:unk_x_variant":[
        "Torrecilla de Cameros"
    ],
    "name:uzb_x_preferred":[
        "Torrecilla en Cameros"
    ],
    "name:vie_x_preferred":[
        "Torrecilla en Cameros"
    ],
    "name:war_x_preferred":[
        "Torrecilla en Cameros"
    ],
    "name:zho_x_preferred":[
        "\u6258\u96f7\u897f\u5229\u827e\u6069\u5361\u6885\u7f57\u65af"
    ],
    "qs_pg:aaroncc":"ES",
    "qs_pg:gn_country":"ES",
    "qs_pg:gn_fcode":"PPLA3",
    "qs_pg:gn_pop":596,
    "qs_pg:name":"Torrecilla en Cameros",
    "qs_pg:name_adm0":"Espa\u00f1a",
    "qs_pg:name_adm1":"La Rioja",
    "qs_pg:photos":101,
    "qs_pg:photos_1k":20,
    "qs_pg:photos_9k":1,
    "qs_pg:photos_9r":3,
    "qs_pg:photos_all":101,
    "qs_pg:photos_sr":3,
    "qs_pg:pop_sr":2,
    "qs_pg:qs_pg_placetype":"locality",
    "qs_pg:qs_pg_placetype_gp":"Town",
    "qs_pg:woe_adm0":23424950,
    "woe:adm0_id":23424950,
    "woe:name_adm0":"Espa\u00f1a",
    "woe:name_adm1":"La Rioja",
    "woe:placetype":"Town",
    "wof:name":"Torrecilla en Cameros",
    "wof:placetype":"locality",
    "wof:population":596
},
  "geometry": {"coordinates":[-2.63109,42.25532],"type":"Point"}
}