{
  "type": "Feature",
  "properties": {
    "gn:country":"ES",
    "gn:fcode":"PPL",
    "gn:population":588,
    "iso:country":"ES",
    "name:ara_x_preferred":[
        "\u062a\u0627\u064a\u0631\u064a\u062c"
    ],
    "name:arg_x_preferred":[
        "T\u00e9rich"
    ],
    "name:cat_x_preferred":[
        "T\u00edrig"
    ],
    "name:ceb_x_preferred":[
        "Tirig"
    ],
    "name:eng_x_preferred":[
        "T\u00edrig"
    ],
    "name:eus_x_preferred":[
        "T\u00edrig"
    ],
    "name:fra_x_preferred":[
        "T\u00edrig"
    ],
    "name:hun_x_preferred":[
        "T\u00edrig"
    ],
    "name:ita_x_preferred":[
        "T\u00edrig"
    ],
    "name:msa_x_preferred":[
        "T\u00edrig"
    ],
    "name:nan_x_preferred":[
        "T\u00edrig"
    ],
    "name:nld_x_preferred":[
        "T\u00edrig"
    ],
    "name:oci_x_preferred":[
        "T\u00edrig"
    ],
    "name:pol_x_preferred":[
        "T\u00edrig"
    ],
    "name:por_x_preferred":[
        "T\u00edrig"
    ],
    "name:rus_x_preferred":[
        "\u0422\u0438\u0440\u0438\u0447"
    ],
    "name:spa_x_preferred":[
        "T\u00edrig"
    ],
    "name:srd_x_preferred":[
        "T\u00edrig"
    ],
    "name:swe_x_preferred":[
        "Tirig"
    ],
    "name:ukr_x_preferred":[
        "\u0422\u0456\u0440\u0456\u0447"
    ],
    "name:uzb_x_preferred":[
        "T\u00edrig"
    ],
    "name:war_x_preferred":[
        "T\u00edrig"
    ],
    "name:zho_x_preferred":[
        "\u8482\u91cc\u683c"
    ],
    "qs_pg:aaroncc":"ES",
    "qs_pg:gn_country":"ES",
    "qs_pg:gn_fcode":"PPL",
    "qs_pg:gn_pop":588,
    "qs_pg:name":"T\u00edrig",
    "qs_pg:name_adm0":"Espa\u00f1a",
    "qs_pg:name_adm1":"Comunitat Valenciana",
    "qs_pg:photos":73,
    "qs_pg:photos_1k":15,
    "qs_pg:photos_9k":1,
    "qs_pg:photos_9r":2,
    "qs_pg:photos_all":73,
    "qs_pg:photos_sr":2,
    "qs_pg:pop_sr":2,
    "qs_pg:qs_pg_placetype":"locality",
    "qs_pg:qs_pg_placetype_gp":"Town",
    "qs_pg:woe_adm0":23424950,
    "woe:adm0_id":23424950,
    "woe:name_adm0":"Espa\u00f1a",
    "woe:name_adm1":"Comunitat Valenciana",
    "woe:placetype":"Town",
    "wof:name":"T\u00edrig",
    "wof:placetype":"locality",
    "wof:population":588
},
  "geometry": {"coordinates":[0.07792,40.42316],"type":"Point"}
}