{
  "type": "Feature",
  "properties": {
    "gn:admin1_code":"34",
    "gn:admin2_code":"O",
    "gn:admin3_code":"33015",
    "gn:asciiname":"Las Tablas",
    "gn:country_code":"ES",
    "gn:dem":745,
    "gn:feature_class":"P",
    "gn:feature_code":"PPL",
    "gn:name":"Las Tablas",
    "gn:population":0,
    "gn:timezone":"Europe/Madrid",
    "iso:country":"ES",
    "wof:name":"Las Tablas",
    "wof:placetype":"locality"
},
  "geometry": {"coordinates":[-5.39768,43.25315],"type":"Point"}
}