{
  "type": "Feature",
  "properties": {
    "gn:admin1_code":"57",
    "gn:admin2_code":"BA",
    "gn:admin3_code":"06015",
    "gn:asciiname":"Santa Engracia",
    "gn:country_code":"ES",
    "gn:dem":193,
    "gn:feature_class":"P",
    "gn:feature_code":"PPL",
    "gn:name":"Santa Engracia",
    "gn:population":0,
    "gn:timezone":"Europe/Madrid",
    "iso:country":"ES",
    "name:und_x_variant":[
        "Casa Santa Engracia",
        "Santa Engracia"
    ],
    "wof:name":"Santa Engracia",
    "wof:placetype":"locality"
},
  "geometry": {"coordinates":[-6.98477,38.91148],"type":"Point"}
}