{
  "type": "Feature",
  "properties": {
    "gn:admin1_code":"39",
    "gn:admin2_code":"S",
    "gn:admin3_code":"39054",
    "gn:asciiname":"Sona",
    "gn:country_code":"ES",
    "gn:dem":45,
    "gn:feature_class":"P",
    "gn:feature_code":"PPL",
    "gn:name":"So\u00f1a",
    "gn:population":0,
    "gn:timezone":"Europe/Madrid",
    "iso:country":"ES",
    "name:aze_x_preferred":[
        "Sona"
    ],
    "name:bul_x_preferred":[
        "\u0421\u043e\u043d\u0430"
    ],
    "name:ceb_x_preferred":[
        "Sona"
    ],
    "name:ces_x_preferred":[
        "Sona"
    ],
    "name:deu_x_preferred":[
        "Sona"
    ],
    "name:epo_x_preferred":[
        "Sona"
    ],
    "name:fra_x_preferred":[
        "Sona"
    ],
    "name:hun_x_preferred":[
        "Sona"
    ],
    "name:hye_x_preferred":[
        "\u054d\u0578\u0576\u0561"
    ],
    "name:ita_x_preferred":[
        "Sona"
    ],
    "name:nld_x_preferred":[
        "Sona"
    ],
    "name:pol_x_preferred":[
        "Sona"
    ],
    "name:rus_x_preferred":[
        "\u0421\u043e\u043d\u0430"
    ],
    "name:spa_x_preferred":[
        "Sona"
    ],
    "name:swe_x_preferred":[
        "Sona"
    ],
    "name:tgl_x_preferred":[
        "Sona"
    ],
    "name:tur_x_preferred":[
        "Sona"
    ],
    "name:ukr_x_preferred":[
        "\u0421\u043e\u043d\u0430"
    ],
    "name:und_x_variant":[
        "So\u00f1a"
    ],
    "wof:name":"Sona",
    "wof:placetype":"locality"
},
  "geometry": {"coordinates":[-4.00241,43.38278],"type":"Point"}
}