{
  "type": "Feature",
  "properties": {
    "gn:admin1_code":"39",
    "gn:admin2_code":"S",
    "gn:admin3_code":"39054",
    "gn:asciiname":"Sona",
    "gn:country_code":"ES",
    "gn:dem":45,
    "gn:feature_class":"P",
    "gn:feature_code":"PPL",
    "gn:name":"So\u00f1a",
    "gn:population":0,
    "gn:timezone":"Europe/Madrid",
    "iso:country":"ES",
    "name:und_x_variant":[
        "So\u00f1a"
    ],
    "wof:name":"Sona",
    "wof:placetype":"locality"
},
  "geometry": {"coordinates":[-4.00241,43.38278],"type":"Point"}
}