{
  "type": "Feature",
  "properties": {
    "gn:admin1_code":"51",
    "gn:admin2_code":"AL",
    "gn:admin3_code":"04053",
    "gn:asciiname":"Almajalejo",
    "gn:country_code":"ES",
    "gn:dem":307,
    "gn:feature_class":"P",
    "gn:feature_code":"PPL",
    "gn:name":"Almajalejo",
    "gn:population":0,
    "gn:timezone":"Europe/Madrid",
    "iso:country":"ES",
    "wof:name":"Almajalejo",
    "wof:placetype":"locality"
},
  "geometry": {"coordinates":[-1.99421,37.38697],"type":"Point"}
}