{
  "type": "Feature",
  "properties": {
    "iso:country":"ES",
    "name:ast_x_preferred":[
        "Quimar\u00e1n"
    ],
    "name:spa_x_preferred":[
        "Guimar\u00e1n"
    ],
    "qs_pg:aaroncc":"ES",
    "qs_pg:name":"Guimar\u00e1n",
    "qs_pg:name_adm0":"Espa\u00f1a",
    "qs_pg:name_adm1":"Principado de Asturias",
    "qs_pg:photos":12,
    "qs_pg:photos_1k":2,
    "qs_pg:photos_9k":1,
    "qs_pg:photos_9r":1,
    "qs_pg:photos_all":12,
    "qs_pg:photos_sr":1,
    "qs_pg:pop_sr":0,
    "qs_pg:qs_pg_placetype":"locality",
    "qs_pg:qs_pg_placetype_gp":"Town",
    "qs_pg:woe_adm0":23424950,
    "woe:adm0_id":23424950,
    "woe:name_adm0":"Espa\u00f1a",
    "woe:name_adm1":"Principado de Asturias",
    "woe:placetype":"Town",
    "wof:name":"Guimar\u00e1n",
    "wof:placetype":"locality"
},
  "geometry": {"coordinates":[-5.749497,43.5366785],"type":"Point"}
}