{
  "type": "Feature",
  "properties": {
    "gn:admin1_code":"34",
    "gn:admin2_code":"O",
    "gn:admin3_code":"33049",
    "gn:asciiname":"Fresnedal",
    "gn:country_code":"ES",
    "gn:dem":366,
    "gn:feature_class":"P",
    "gn:feature_code":"PPL",
    "gn:name":"Fresnedal",
    "gn:population":0,
    "gn:timezone":"Europe/Madrid",
    "iso:country":"ES",
    "wof:name":"Fresnedal",
    "wof:placetype":"locality"
},
  "geometry": {"coordinates":[-5.42211,43.29025],"type":"Point"}
}