{
  "type": "Feature",
  "properties": {
    "gn:admin1_code":"51",
    "gn:admin2_code":"AL",
    "gn:admin3_code":"04017",
    "gn:asciiname":"El Arroyo Aceituno",
    "gn:cc2":"ES",
    "gn:country_code":"ES",
    "gn:dem":288,
    "gn:feature_class":"P",
    "gn:feature_code":"PPL",
    "gn:name":"El Arroyo Aceituno",
    "gn:population":0,
    "gn:timezone":"Europe/Madrid",
    "iso:country":"ES",
    "name:und_x_variant":[
        "Caser\u00edo El Arroyo Aceituno",
        "El Arroyo Aceituno"
    ],
    "wof:name":"El Arroyo Aceituno",
    "wof:placetype":"locality"
},
  "geometry": {"coordinates":[-2.06667,37.35],"type":"Point"}
}