{
  "type": "Feature",
  "properties": {
    "gn:admin1_code":"55",
    "gn:admin2_code":"LE",
    "gn:admin3_code":"24067",
    "gn:asciiname":"Trabazos",
    "gn:country_code":"ES",
    "gn:dem":1130,
    "gn:feature_class":"P",
    "gn:feature_code":"PPL",
    "gn:name":"Trabazos",
    "gn:population":0,
    "gn:timezone":"Europe/Madrid",
    "iso:country":"ES",
    "wof:name":"Trabazos",
    "wof:placetype":"locality"
},
  "geometry": {"coordinates":[-6.59631,42.28402],"type":"Point"}
}