{
  "type": "Feature",
  "properties": {
    "gn:admin1_code":"55",
    "gn:admin2_code":"LE",
    "gn:admin3_code":"24067",
    "gn:asciiname":"Trabazos",
    "gn:country_code":"ES",
    "gn:dem":1130,
    "gn:feature_class":"P",
    "gn:feature_code":"PPL",
    "gn:name":"Trabazos",
    "gn:population":0,
    "gn:timezone":"Europe/Madrid",
    "iso:country":"ES",
    "name:arg_x_preferred":[
        "Trabazos"
    ],
    "name:cat_x_preferred":[
        "Trabazos"
    ],
    "name:ceb_x_preferred":[
        "Trabazos"
    ],
    "name:eus_x_preferred":[
        "Trabazos"
    ],
    "name:fra_x_preferred":[
        "Trabazos"
    ],
    "name:haw_x_preferred":[
        "Trabazos"
    ],
    "name:hun_x_preferred":[
        "Trabazos"
    ],
    "name:ile_x_preferred":[
        "Trabazos"
    ],
    "name:ina_x_preferred":[
        "Trabazos"
    ],
    "name:ita_x_preferred":[
        "Trabazos"
    ],
    "name:msa_x_preferred":[
        "Trabazos"
    ],
    "name:nld_x_preferred":[
        "Trabazos"
    ],
    "name:oci_x_preferred":[
        "Trabazos"
    ],
    "name:pol_x_preferred":[
        "Trabazos"
    ],
    "name:por_x_preferred":[
        "Trabazos"
    ],
    "name:rus_x_preferred":[
        "\u0422\u0440\u0430\u0431\u0430\u0441\u043e\u0441"
    ],
    "name:spa_x_preferred":[
        "Trabazos"
    ],
    "name:swe_x_preferred":[
        "Trabazos"
    ],
    "name:ukr_x_preferred":[
        "\u0422\u0440\u0430\u0431\u0430\u0441\u043e\u0441"
    ],
    "name:vie_x_preferred":[
        "Trabazos"
    ],
    "name:war_x_preferred":[
        "Trabazos"
    ],
    "name:zho_x_preferred":[
        "\u7279\u62c9\u74e6\u7d22\u65af"
    ],
    "wof:name":"Trabazos",
    "wof:placetype":"locality"
},
  "geometry": {"coordinates":[-6.59631,42.28402],"type":"Point"}
}