{
  "type": "Feature",
  "properties": {
    "gn:admin1_code":"55",
    "gn:admin2_code":"BU",
    "gn:admin3_code":"09219",
    "gn:asciiname":"Ayuelas",
    "gn:country_code":"ES",
    "gn:dem":536,
    "gn:feature_class":"P",
    "gn:feature_code":"PPL",
    "gn:name":"Ayuelas",
    "gn:population":0,
    "gn:timezone":"Europe/Madrid",
    "iso:country":"ES",
    "wof:name":"Ayuelas",
    "wof:placetype":"locality"
},
  "geometry": {"coordinates":[-3.03868,42.69649],"type":"Point"}
}