{
  "type": "Feature",
  "properties": {
    "gn:gn_country":"ES",
    "gn:gn_fcode":"PPLA3",
    "gn:gn_pop":839,
    "gn:population":839,
    "iso:country":"ES",
    "name:ara_x_preferred":[
        "\u062a\u0631\u064a\u0641\u064a\u0644\u064a\u062b"
    ],
    "name:ast_x_preferred":[
        "Trev\u00e9lez"
    ],
    "name:bul_x_preferred":[
        "\u0422\u0440\u0435\u0432\u0435\u043b\u0435\u0441"
    ],
    "name:cat_x_preferred":[
        "Trev\u00e9lez"
    ],
    "name:ceb_x_preferred":[
        "Trev\u00e9lez"
    ],
    "name:ces_x_preferred":[
        "Trev\u00e9lez"
    ],
    "name:deu_x_preferred":[
        "Trev\u00e9lez"
    ],
    "name:eng_x_preferred":[
        "Trev\u00e9lez"
    ],
    "name:epo_x_preferred":[
        "Trev\u00e9lez"
    ],
    "name:eus_x_preferred":[
        "Trev\u00e9lez"
    ],
    "name:fra_x_preferred":[
        "Trev\u00e9lez"
    ],
    "name:hat_x_preferred":[
        "Trev\u00e9lez"
    ],
    "name:hun_x_preferred":[
        "Trev\u00e9lez"
    ],
    "name:hye_x_preferred":[
        "\u054f\u0580\u0587\u0565\u056c\u0565\u057d"
    ],
    "name:ita_x_preferred":[
        "Trev\u00e9lez"
    ],
    "name:jpn_x_preferred":[
        "\u30c8\u30ec\u30d9\u30ec\u30b9"
    ],
    "name:kaz_x_preferred":[
        "\u0422\u0440\u0435\u0432\u0435\u043b\u0435\u0441"
    ],
    "name:msa_x_preferred":[
        "Trev\u00e9lez"
    ],
    "name:nan_x_preferred":[
        "Trev\u00e9lez"
    ],
    "name:nld_x_preferred":[
        "Trev\u00e9lez"
    ],
    "name:oci_x_preferred":[
        "Trev\u00e9lez"
    ],
    "name:pol_x_preferred":[
        "Trev\u00e9lez"
    ],
    "name:por_x_preferred":[
        "Trev\u00e9lez"
    ],
    "name:rus_x_preferred":[
        "\u0422\u0440\u0435\u0432\u0435\u043b\u0435\u0441"
    ],
    "name:spa_x_preferred":[
        "Trev\u00e9lez"
    ],
    "name:sqi_x_preferred":[
        "Trev\u00e9lez"
    ],
    "name:swe_x_preferred":[
        "Trev\u00e9lez"
    ],
    "name:tur_x_preferred":[
        "Trev\u00e9lez"
    ],
    "name:ukr_x_preferred":[
        "\u0422\u0440\u0435\u0432\u0435\u043b\u0435\u0441"
    ],
    "name:uzb_x_preferred":[
        "Trev\u00e9lez"
    ],
    "name:vie_x_preferred":[
        "Trev\u00e9lez"
    ],
    "name:war_x_preferred":[
        "Trev\u00e9lez"
    ],
    "name:zho_x_preferred":[
        "\u7279\u96f7\u97e6\u83b1\u65af"
    ],
    "qs_pg:aaroncc":"ES",
    "qs_pg:gn_country":"ES",
    "qs_pg:gn_fcode":"PPLA3",
    "qs_pg:gn_pop":839,
    "qs_pg:name":"Trev\u00e9lez",
    "qs_pg:name_adm0":"Espa\u00f1a",
    "qs_pg:name_adm1":"Andaluc\u00eda",
    "qs_pg:photos":697,
    "qs_pg:photos_1k":141,
    "qs_pg:photos_9k":3,
    "qs_pg:photos_9r":5,
    "qs_pg:photos_all":697,
    "qs_pg:photos_sr":8,
    "qs_pg:pop_sr":2,
    "qs_pg:qs_pg_placetype":"locality",
    "qs_pg:qs_pg_placetype_gp":"Town",
    "qs_pg:woe_adm0":23424950,
    "woe:adm0_id":23424950,
    "woe:name_adm0":"Espa\u00f1a",
    "woe:name_adm1":"Andaluc\u00eda",
    "woe:placetype":"Town",
    "wof:name":"Trev\u00e9lez",
    "wof:placetype":"locality",
    "wof:population":839
},
  "geometry": {"coordinates":[-3.26544,37.00037],"type":"Point"}
}