{
  "type": "Feature",
  "properties": {
    "gn:admin1_code":"31",
    "gn:admin2_code":"MU",
    "gn:admin3_code":"30003",
    "gn:asciiname":"El Labradorcico",
    "gn:country_code":"ES",
    "gn:dem":79,
    "gn:feature_class":"P",
    "gn:feature_code":"PPL",
    "gn:name":"El Labradorcico",
    "gn:population":0,
    "gn:timezone":"Europe/Madrid",
    "iso:country":"ES",
    "name:und_x_variant":[
        "Caser\u00edo El Labradorcico",
        "El Labradorcico"
    ],
    "wof:name":"El Labradorcico",
    "wof:placetype":"locality"
},
  "geometry": {"coordinates":[-1.57865,37.43273],"type":"Point"}
}