{
  "type": "Feature",
  "properties": {
    "gn:admin1_code":"27",
    "gn:admin2_code":"LO",
    "gn:admin3_code":"26017",
    "gn:asciiname":"Peroblasco",
    "gn:country_code":"ES",
    "gn:dem":728,
    "gn:feature_class":"P",
    "gn:feature_code":"PPL",
    "gn:name":"Peroblasco",
    "gn:population":0,
    "gn:timezone":"Europe/Madrid",
    "iso:country":"ES",
    "wof:name":"Peroblasco",
    "wof:placetype":"locality"
},
  "geometry": {"coordinates":[-2.25764,42.19852],"type":"Point"}
}