{
  "type": "Feature",
  "properties": {
    "gn:admin1_code":"55",
    "gn:admin2_code":"LE",
    "gn:admin3_code":"24130",
    "gn:asciiname":"Carande",
    "gn:country_code":"ES",
    "gn:dem":1123,
    "gn:feature_class":"P",
    "gn:feature_code":"PPL",
    "gn:name":"Carande",
    "gn:population":0,
    "gn:timezone":"Europe/Madrid",
    "iso:country":"ES",
    "wof:name":"Carande",
    "wof:placetype":"locality"
},
  "geometry": {"coordinates":[-5.01763,42.94724],"type":"Point"}
}