{
  "type": "Feature",
  "properties": {
    "gn:country":"ES",
    "gn:fcode":"PPLA3",
    "gn:population":381,
    "iso:country":"ES",
    "name:ast_x_preferred":[
        "Mu\u00f1opedro"
    ],
    "name:cat_x_preferred":[
        "Mu\u00f1opedro"
    ],
    "name:ceb_x_preferred":[
        "Mu\u00f1opedro"
    ],
    "name:eng_x_preferred":[
        "Mu\u00f1opedro"
    ],
    "name:eus_x_preferred":[
        "Mu\u00f1opedro"
    ],
    "name:fra_x_preferred":[
        "Mu\u00f1opedro"
    ],
    "name:hun_x_preferred":[
        "Mu\u00f1opedro"
    ],
    "name:ina_x_preferred":[
        "Mu\u00f1opedro"
    ],
    "name:ita_x_preferred":[
        "Mu\u00f1opedro"
    ],
    "name:msa_x_preferred":[
        "Mu\u00f1opedro"
    ],
    "name:nan_x_preferred":[
        "Mu\u00f1opedro"
    ],
    "name:nld_x_preferred":[
        "Mu\u00f1opedro"
    ],
    "name:oci_x_preferred":[
        "Mu\u00f1opedro"
    ],
    "name:pol_x_preferred":[
        "Mu\u00f1opedro"
    ],
    "name:por_x_preferred":[
        "Mu\u00f1opedro"
    ],
    "name:rus_x_preferred":[
        "\u041c\u0443\u043d\u044c\u043e\u043f\u0435\u0434\u0440\u043e"
    ],
    "name:spa_x_preferred":[
        "Mu\u00f1opedro"
    ],
    "name:swe_x_preferred":[
        "Mu\u00f1opedro"
    ],
    "name:ukr_x_preferred":[
        "\u041c\u0443\u043d\u044c\u0439\u043e\u043f\u0435\u0434\u0440\u043e"
    ],
    "name:vie_x_preferred":[
        "Mu\u00f1opedro"
    ],
    "name:war_x_preferred":[
        "Mu\u00f1opedro"
    ],
    "name:zho_x_preferred":[
        "\u7a46\u5c3c\u5965\u4f69\u5fb7\u7f57"
    ],
    "qs_pg:aaroncc":"ES",
    "qs_pg:gn_country":"ES",
    "qs_pg:gn_fcode":"PPLA3",
    "qs_pg:gn_pop":381,
    "qs_pg:name":"Mu\u00f1opedro",
    "qs_pg:name_adm0":"Espa\u00f1a",
    "qs_pg:name_adm1":"Castilla y Le\u00f3n",
    "qs_pg:photos_9k":1,
    "qs_pg:photos_9r":1,
    "qs_pg:photos_all":1,
    "qs_pg:photos_sr":0,
    "qs_pg:pop_sr":2,
    "qs_pg:qs_pg_placetype":"locality",
    "qs_pg:qs_pg_placetype_gp":"Town",
    "qs_pg:woe_adm0":23424950,
    "woe:adm0_id":23424950,
    "woe:name_adm0":"Espa\u00f1a",
    "woe:name_adm1":"Castilla y Le\u00f3n",
    "woe:placetype":"Town",
    "wof:name":"Mu\u00f1opedro",
    "wof:placetype":"locality",
    "wof:population":381
},
  "geometry": {"coordinates":[-4.47212,40.88804],"type":"Point"}
}