{
  "type": "Feature",
  "properties": {
    "gn:admin1_code":"27",
    "gn:admin2_code":"LO",
    "gn:admin3_code":"26132",
    "gn:asciiname":"Santa Maria en Cameros",
    "gn:country_code":"ES",
    "gn:dem":1007,
    "gn:feature_class":"P",
    "gn:feature_code":"PPL",
    "gn:name":"Santa Mar\u00eda en Cameros",
    "gn:population":0,
    "gn:timezone":"Europe/Madrid",
    "iso:country":"ES",
    "wof:name":"Santa Maria en Cameros",
    "wof:placetype":"locality"
},
  "geometry": {"coordinates":[-2.49964,42.24961],"type":"Point"}
}