{
  "type": "Feature",
  "properties": {
    "gn:admin1_code":"59",
    "gn:admin2_code":"BI",
    "gn:admin3_code":"48075",
    "gn:asciiname":"Zaloa",
    "gn:country_code":"ES",
    "gn:dem":340,
    "gn:feature_class":"P",
    "gn:feature_code":"PPL",
    "gn:name":"Zaloa",
    "gn:population":0,
    "gn:timezone":"Europe/Madrid",
    "iso:country":"ES",
    "wof:name":"Zaloa",
    "wof:placetype":"locality"
},
  "geometry": {"coordinates":[-2.85466,43.09486],"type":"Point"}
}