{
  "type": "Feature",
  "properties": {
    "gn:gn_country":"ES",
    "gn:gn_fcode":"PPLA3",
    "gn:gn_pop":212,
    "gn:population":212,
    "iso:country":"ES",
    "name:arg_x_preferred":[
        "Villardefrades"
    ],
    "name:arm_x_preferred":[
        "\u054e\u056b\u056c\u0575\u0561\u0580\u0564\u0565\u0586\u0580\u0561\u0564\u0565\u057d"
    ],
    "name:baq_x_preferred":[
        "Villardefrades"
    ],
    "name:cat_x_preferred":[
        "Villardefrades"
    ],
    "name:chi_x_preferred":[
        "\u6bd4\u5229\u4e9a\u5c14\u5fb7\u592b\u62c9\u5fb7\u65af"
    ],
    "name:dut_x_preferred":[
        "Villardefrades"
    ],
    "name:eng_x_preferred":[
        "Villardefrades"
    ],
    "name:fre_x_preferred":[
        "Villardefrades"
    ],
    "name:hun_x_preferred":[
        "Villardefrades"
    ],
    "name:ina_x_preferred":[
        "Villardefrades"
    ],
    "name:ita_x_preferred":[
        "Villardefrades"
    ],
    "name:lit_x_preferred":[
        "Viljardefradesas"
    ],
    "name:may_x_preferred":[
        "Villardefrades"
    ],
    "name:nan_x_preferred":[
        "Villardefrades"
    ],
    "name:oci_x_preferred":[
        "Villardefrades"
    ],
    "name:per_x_preferred":[
        "\u0628\u06cc\u06cc\u0627\u0631\u062f\u0641\u0631\u0627\u062f\u0633"
    ],
    "name:pol_x_preferred":[
        "Villardefrades"
    ],
    "name:por_x_preferred":[
        "Villardefrades"
    ],
    "name:rus_x_preferred":[
        "\u0412\u0438\u043b\u044c\u044f\u0440\u0434\u0435\u0444\u0440\u0430\u0434\u0435\u0441"
    ],
    "name:spa_x_preferred":[
        "Villardefrades"
    ],
    "name:swe_x_preferred":[
        "Villardefrades"
    ],
    "name:ukr_x_preferred":[
        "\u0412\u0456\u043b\u044c\u044f\u0440\u0434\u0435\u0444\u0440\u0430\u0434\u0435\u0441"
    ],
    "name:vie_x_preferred":[
        "Villardefrades"
    ],
    "name:war_x_preferred":[
        "Villardefrades"
    ],
    "qs_pg:aaroncc":"ES",
    "qs_pg:gn_country":"ES",
    "qs_pg:gn_fcode":"PPLA3",
    "qs_pg:gn_pop":212,
    "qs_pg:name":"Villardefrades",
    "qs_pg:name_adm0":"Espa\u00f1a",
    "qs_pg:name_adm1":"Castilla y Le\u00f3n",
    "qs_pg:photos_9k":1,
    "qs_pg:photos_9r":4,
    "qs_pg:photos_all":184,
    "qs_pg:photos_sr":0,
    "qs_pg:pop_sr":2,
    "qs_pg:qs_pg_placetype":"locality",
    "qs_pg:qs_pg_placetype_gp":"Town",
    "qs_pg:woe_adm0":23424950,
    "woe:adm0_id":23424950,
    "woe:name_adm0":"Espa\u00f1a",
    "woe:name_adm1":"Castilla y Le\u00f3n",
    "woe:placetype":"Town",
    "wof:name":"Villardefrades",
    "wof:placetype":"locality",
    "wof:population":212
},
  "geometry": {"coordinates":[-5.25513,41.72358],"type":"Point"}
}