{
  "type": "Feature",
  "properties": {
    "gn:admin1_code":"56",
    "gn:admin2_code":"T",
    "gn:admin3_code":"43076",
    "gn:asciiname":"Marsa",
    "gn:country_code":"ES",
    "gn:dem":317,
    "gn:feature_class":"P",
    "gn:feature_code":"PPL",
    "gn:name":"Mars\u00e1",
    "gn:population":0,
    "gn:timezone":"Europe/Madrid",
    "iso:country":"ES",
    "name:ceb_x_preferred":[
        "Marsa"
    ],
    "name:deu_x_preferred":[
        "Marsa"
    ],
    "name:fra_x_preferred":[
        "Marsa"
    ],
    "name:hye_x_preferred":[
        "\u0544\u0561\u0580\u057d\u0561"
    ],
    "name:ita_x_preferred":[
        "Marsa"
    ],
    "name:nld_x_preferred":[
        "Marsa"
    ],
    "name:pol_x_preferred":[
        "Marsa"
    ],
    "name:por_x_preferred":[
        "Marsa"
    ],
    "name:rus_x_preferred":[
        "\u041c\u0430\u0440\u0441\u0430"
    ],
    "name:scn_x_preferred":[
        "Marsa"
    ],
    "name:swe_x_preferred":[
        "Marsa"
    ],
    "name:ukr_x_preferred":[
        "\u041c\u0430\u0440\u0441\u0430"
    ],
    "wof:name":"Marsa",
    "wof:placetype":"locality"
},
  "geometry": {"coordinates":[0.80258,41.12724],"type":"Point"}
}