{
  "type": "Feature",
  "properties": {
    "gn:admin1_code":"56",
    "gn:admin2_code":"T",
    "gn:admin3_code":"43076",
    "gn:asciiname":"Marsa",
    "gn:country_code":"ES",
    "gn:dem":317,
    "gn:feature_class":"P",
    "gn:feature_code":"PPL",
    "gn:name":"Mars\u00e1",
    "gn:population":0,
    "gn:timezone":"Europe/Madrid",
    "iso:country":"ES",
    "wof:name":"Marsa",
    "wof:placetype":"locality"
},
  "geometry": {"coordinates":[0.80258,41.12724],"type":"Point"}
}