{
  "type": "Feature",
  "properties": {
    "gn:gn_country":"ES",
    "gn:gn_fcode":"PPLA3",
    "gn:gn_pop":197,
    "gn:population":197,
    "iso:country":"ES",
    "name:arg_x_preferred":[
        "Puertomingalvo"
    ],
    "name:arm_x_preferred":[
        "\u054a\u0578\u0582\u0565\u0580\u057f\u0578\u0574\u056b\u0576\u0563\u0561\u056c\u057e\u0578"
    ],
    "name:baq_x_preferred":[
        "Puertomingalvo"
    ],
    "name:cat_x_preferred":[
        "Puertomingalvo"
    ],
    "name:chi_x_preferred":[
        "\u666e\u57c3\u5c14\u6258\u660e\u52a0\u5c14\u6c83"
    ],
    "name:dut_x_preferred":[
        "Puertomingalvo"
    ],
    "name:eng_x_preferred":[
        "Puertomingalvo"
    ],
    "name:fre_x_preferred":[
        "Puertomingalvo"
    ],
    "name:hun_x_preferred":[
        "Puertomingalvo"
    ],
    "name:ita_x_preferred":[
        "Puertomingalvo"
    ],
    "name:kaz_x_preferred":[
        "\u041f\u0443\u044d\u0440\u0442\u043e\u043c\u0438\u043d\u0433\u0430\u043b\u044c\u0432\u043e"
    ],
    "name:may_x_preferred":[
        "Puertomingalvo"
    ],
    "name:nan_x_preferred":[
        "Puertomingalvo"
    ],
    "name:oci_x_preferred":[
        "Puertomingalvo"
    ],
    "name:pol_x_preferred":[
        "Puertomingalvo"
    ],
    "name:por_x_preferred":[
        "Puertomingalvo"
    ],
    "name:rus_x_preferred":[
        "\u041f\u0443\u044d\u0440\u0442\u043e\u043c\u0438\u043d\u0433\u0430\u043b\u044c\u0432\u043e"
    ],
    "name:spa_x_preferred":[
        "Puertomingalvo"
    ],
    "name:swe_x_preferred":[
        "Puertomingalvo"
    ],
    "name:ukr_x_preferred":[
        "\u041f\u0443\u0435\u0440\u0442\u043e\u043c\u0456\u043d\u0433\u0430\u043b\u044c\u0432\u043e"
    ],
    "name:uzb_x_preferred":[
        "Puertomingalvo"
    ],
    "name:vie_x_preferred":[
        "Puertomingalvo"
    ],
    "name:war_x_preferred":[
        "Puertomingalvo"
    ],
    "qs_pg:aaroncc":"ES",
    "qs_pg:gn_country":"ES",
    "qs_pg:gn_fcode":"PPLA3",
    "qs_pg:gn_pop":197,
    "qs_pg:name":"Puertomingalvo",
    "qs_pg:photos_9r":0,
    "qs_pg:photos_sr":0,
    "qs_pg:pop_sr":1,
    "qs_pg:qs_pg_placetype":"locality",
    "wof:name":"Puertomingalvo",
    "wof:placetype":"locality",
    "wof:population":197
},
  "geometry": {"coordinates":[-0.45756,40.2643],"type":"Point"}
}