{
  "type": "Feature",
  "properties": {
    "gn:admin1_code":"58",
    "gn:admin2_code":"C",
    "gn:admin3_code":"15086",
    "gn:asciiname":"Vilouchada",
    "gn:country_code":"ES",
    "gn:dem":226,
    "gn:feature_class":"P",
    "gn:feature_code":"PPL",
    "gn:name":"Vilouchada",
    "gn:population":0,
    "gn:timezone":"Europe/Madrid",
    "iso:country":"ES",
    "wof:name":"Vilouchada",
    "wof:placetype":"locality"
},
  "geometry": {"coordinates":[-8.52652,42.98562],"type":"Point"}
}