{
  "type": "Feature",
  "properties": {
    "gn:admin1_code":"31",
    "gn:admin2_code":"MU",
    "gn:admin3_code":"30003",
    "gn:asciiname":"Majada del Moro",
    "gn:country_code":"ES",
    "gn:dem":388,
    "gn:feature_class":"P",
    "gn:feature_code":"PPL",
    "gn:name":"Majada del Moro",
    "gn:population":0,
    "gn:timezone":"Europe/Madrid",
    "iso:country":"ES",
    "name:und_x_variant":[
        "Caser\u00edo Majada del Moro",
        "Majada del Moro"
    ],
    "wof:name":"Majada del Moro",
    "wof:placetype":"locality"
},
  "geometry": {"coordinates":[-1.60224,37.47999],"type":"Point"}
}