{
  "type": "Feature",
  "properties": {
    "gn:gn_country":"ES",
    "gn:gn_fcode":"PPL",
    "gn:gn_pop":0,
    "iso:country":"ES",
    "name:alb_x_preferred":[
        "Albany\u00e0"
    ],
    "name:ara_x_preferred":[
        "\u0623\u0644\u0628\u0646\u064a\u0627\u060c \u062c\u0631\u0646\u062f\u0629"
    ],
    "name:arg_x_preferred":[
        "Albany\u00e0"
    ],
    "name:arm_x_preferred":[
        "\u0531\u056c\u0562\u0561\u0576\u056b\u0561"
    ],
    "name:baq_x_preferred":[
        "Albany\u00e0"
    ],
    "name:cat_x_preferred":[
        "Albany\u00e0"
    ],
    "name:chi_x_preferred":[
        "\u963f\u5c14\u74e6\u5c3c\u4e9a"
    ],
    "name:dut_x_preferred":[
        "Albany\u00e0"
    ],
    "name:eng_x_preferred":[
        "Albany\u00e0"
    ],
    "name:fre_x_preferred":[
        "Albany\u00e0"
    ],
    "name:ger_x_preferred":[
        "Albany\u00e0"
    ],
    "name:glg_x_preferred":[
        "Albany\u00e0"
    ],
    "name:hun_x_preferred":[
        "Albany\u00e0"
    ],
    "name:ita_x_preferred":[
        "Albany\u00e0"
    ],
    "name:kaz_x_preferred":[
        "\u0410\u043b\u044c\u0431\u0430\u043d\u044c\u044f"
    ],
    "name:lat_x_preferred":[
        "Albany\u00e0"
    ],
    "name:may_x_preferred":[
        "Albany\u00e0"
    ],
    "name:nob_x_preferred":[
        "Albany\u00e0"
    ],
    "name:oci_x_preferred":[
        "Albany\u00e0"
    ],
    "name:pam_x_preferred":[
        "Albany\u00e0"
    ],
    "name:pol_x_preferred":[
        "Albany\u00e0"
    ],
    "name:por_x_preferred":[
        "Albany\u00e0"
    ],
    "name:rum_x_preferred":[
        "Albany\u00e0"
    ],
    "name:rus_x_preferred":[
        "\u0410\u043b\u044c\u0431\u0430\u043d\u044c\u044f"
    ],
    "name:spa_x_preferred":[
        "Alba\u00f1\u00e1"
    ],
    "name:swe_x_preferred":[
        "Albany\u00e0"
    ],
    "name:tah_x_preferred":[
        "Albany\u00e0"
    ],
    "name:ukr_x_preferred":[
        "\u0410\u043b\u0431\u0430\u043d\u044c\u044f"
    ],
    "name:uzb_x_preferred":[
        "Alba\u00f1\u00e1"
    ],
    "name:vie_x_preferred":[
        "Albany\u00e0"
    ],
    "name:war_x_preferred":[
        "Albany\u00e0"
    ],
    "qs_pg:aaroncc":"ES",
    "qs_pg:gn_country":"ES",
    "qs_pg:gn_fcode":"PPL",
    "qs_pg:gn_pop":0,
    "qs_pg:name":"Albany\u00e0",
    "qs_pg:name_adm0":"Espa\u00f1a",
    "qs_pg:name_adm1":"Catalunya",
    "qs_pg:photos":174,
    "qs_pg:photos_1k":35,
    "qs_pg:photos_9k":1,
    "qs_pg:photos_9r":4,
    "qs_pg:photos_all":174,
    "qs_pg:photos_sr":4,
    "qs_pg:pop_sr":0,
    "qs_pg:qs_pg_placetype":"locality",
    "qs_pg:qs_pg_placetype_gp":"Town",
    "qs_pg:woe_adm0":23424950,
    "woe:adm0_id":23424950,
    "woe:name_adm0":"Espa\u00f1a",
    "woe:name_adm1":"Catalunya",
    "woe:placetype":"Town",
    "wof:name":"Albany\u00e0",
    "wof:placetype":"locality"
},
  "geometry": {"coordinates":[2.71995,42.30431],"type":"Point"}
}