{
  "type": "Feature",
  "properties": {
    "gn:gn_country":"ES",
    "gn:gn_fcode":"PPL",
    "gn:gn_pop":420,
    "gn:population":420,
    "iso:country":"ES",
    "name:arg_x_preferred":[
        "La Vecilla"
    ],
    "name:baq_x_preferred":[
        "La Vecilla"
    ],
    "name:cat_x_preferred":[
        "La Vecilla"
    ],
    "name:chi_x_preferred":[
        "\u62c9\u97e6\u897f\u5229\u4e9a"
    ],
    "name:dut_x_preferred":[
        "La Vecilla"
    ],
    "name:eng_x_preferred":[
        "La Vecilla"
    ],
    "name:fre_x_preferred":[
        "La Vecilla"
    ],
    "name:ger_x_preferred":[
        "La Vecilla"
    ],
    "name:glg_x_preferred":[
        "La Vecilla"
    ],
    "name:haw_x_preferred":[
        "La Vecilla"
    ],
    "name:hun_x_preferred":[
        "La Vecilla"
    ],
    "name:ido_x_preferred":[
        "La Vecilla"
    ],
    "name:ina_x_preferred":[
        "La Vecilla"
    ],
    "name:ita_x_preferred":[
        "La Vecilla"
    ],
    "name:jpn_x_preferred":[
        "\u30e9\u30fb\u30d9\u30b7\u30fc\u30b8\u30e3"
    ],
    "name:may_x_preferred":[
        "La Vecilla"
    ],
    "name:nan_x_preferred":[
        "La Vecilla"
    ],
    "name:oci_x_preferred":[
        "La Vecilla"
    ],
    "name:pol_x_preferred":[
        "La Vecilla"
    ],
    "name:por_x_preferred":[
        "La Vecilla"
    ],
    "name:rus_x_preferred":[
        "\u041b\u0430-\u0412\u0435\u0441\u0438\u043b\u044c\u044f"
    ],
    "name:spa_x_preferred":[
        "La Vecilla"
    ],
    "name:swe_x_preferred":[
        "La Vecilla de Curue\u00f1o"
    ],
    "name:tpi_x_preferred":[
        "La Vecilla"
    ],
    "name:ukr_x_preferred":[
        "\u041b\u0430-\u0412\u0435\u0441\u0456\u043b\u044c\u044f"
    ],
    "name:unk_x_variant":[
        "Vecilla de Curue\u00f1o"
    ],
    "name:vie_x_preferred":[
        "La Vecilla"
    ],
    "name:war_x_preferred":[
        "La Vecilla"
    ],
    "qs_pg:aaroncc":"ES",
    "qs_pg:gn_country":"ES",
    "qs_pg:gn_fcode":"PPL",
    "qs_pg:gn_pop":420,
    "qs_pg:name":"La Vecilla de Curue\u00f1o",
    "qs_pg:name_adm0":"Espa\u00f1a",
    "qs_pg:name_adm1":"Castilla y Le\u00f3n",
    "qs_pg:photos":91,
    "qs_pg:photos_1k":18,
    "qs_pg:photos_9k":1,
    "qs_pg:photos_9r":3,
    "qs_pg:photos_all":91,
    "qs_pg:photos_sr":3,
    "qs_pg:pop_sr":2,
    "qs_pg:qs_pg_placetype":"locality",
    "qs_pg:qs_pg_placetype_gp":"Town",
    "qs_pg:woe_adm0":23424950,
    "woe:adm0_id":23424950,
    "woe:name_adm0":"Espa\u00f1a",
    "woe:name_adm1":"Castilla y Le\u00f3n",
    "woe:placetype":"Town",
    "wof:name":"La Vecilla de Curue\u00f1o",
    "wof:placetype":"locality",
    "wof:population":420
},
  "geometry": {"coordinates":[-5.40643,42.84852],"type":"Point"}
}