{
  "type": "Feature",
  "properties": {
    "gn:admin1_code":"55",
    "gn:admin2_code":"SG",
    "gn:admin3_code":"40022",
    "gn:asciiname":"Carbonero de Ahusin",
    "gn:country_code":"ES",
    "gn:dem":895,
    "gn:feature_class":"P",
    "gn:feature_code":"PPL",
    "gn:name":"Carbonero de Ahus\u00edn",
    "gn:population":0,
    "gn:timezone":"Europe/Madrid",
    "iso:country":"ES",
    "name:und_x_variant":[
        "Carbonero de Ahus\u00edn"
    ],
    "wof:name":"Carbonero de Ahusin",
    "wof:placetype":"locality"
},
  "geometry": {"coordinates":[-4.23677,41.03912],"type":"Point"}
}