{
  "type": "Feature",
  "properties": {
    "gn:admin1_code":"31",
    "gn:admin2_code":"MU",
    "gn:admin3_code":"30030",
    "gn:asciiname":"La Paloma",
    "gn:country_code":"ES",
    "gn:dem":113,
    "gn:feature_class":"P",
    "gn:feature_code":"PPL",
    "gn:name":"La Paloma",
    "gn:population":0,
    "gn:timezone":"Europe/Madrid",
    "iso:country":"ES",
    "name:und_x_variant":[
        "Caser\u00edo la Paloma",
        "Venta de la Paloma",
        "La Paloma"
    ],
    "wof:name":"La Paloma",
    "wof:placetype":"locality"
},
  "geometry": {"coordinates":[-1.16108,37.92589],"type":"Point"}
}