{
  "type": "Feature",
  "properties": {
    "gn:admin1_code":"51",
    "gn:admin2_code":"J",
    "gn:admin3_code":"23045",
    "gn:asciiname":"Picos del Guadiana",
    "gn:country_code":"ES",
    "gn:dem":688,
    "gn:feature_class":"P",
    "gn:feature_code":"PPL",
    "gn:name":"Picos del Guadiana",
    "gn:population":0,
    "gn:timezone":"Europe/Madrid",
    "iso:country":"ES",
    "name:und_x_variant":[
        "Caser\u00edo Picos del Guadiana",
        "Picos del Guadiana"
    ],
    "wof:name":"Picos del Guadiana",
    "wof:placetype":"locality"
},
  "geometry": {"coordinates":[-3.09849,37.74812],"type":"Point"}
}