{
  "type": "Feature",
  "properties": {
    "gn:admin1_code":"58",
    "gn:admin2_code":"OR",
    "gn:admin3_code":"32059",
    "gn:asciiname":"A Peroxa",
    "gn:cc2":"ES",
    "gn:country_code":"ES",
    "gn:dem":504,
    "gn:feature_class":"P",
    "gn:feature_code":"PPL",
    "gn:name":"A Peroxa",
    "gn:population":0,
    "gn:timezone":"Europe/Madrid",
    "iso:country":"ES",
    "name:und_x_variant":[
        "San Gin\u00e9s"
    ],
    "wof:name":"A Peroxa",
    "wof:placetype":"locality"
},
  "geometry": {"coordinates":[-7.79454,42.44132000000001],"type":"Point"}
}