{
  "type": "Feature",
  "properties": {
    "gn:admin1_code":"58",
    "gn:admin2_code":"OR",
    "gn:admin3_code":"32059",
    "gn:asciiname":"A Peroxa",
    "gn:cc2":"ES",
    "gn:country_code":"ES",
    "gn:dem":504,
    "gn:feature_class":"P",
    "gn:feature_code":"PPL",
    "gn:name":"A Peroxa",
    "gn:population":0,
    "gn:timezone":"Europe/Madrid",
    "iso:country":"ES",
    "name:ara_x_preferred":[
        "\u0644\u0627 \u0628\u064a\u0631\u0648\u062e\u0627"
    ],
    "name:ast_x_preferred":[
        "A Peroxa"
    ],
    "name:cat_x_preferred":[
        "A Peroxa"
    ],
    "name:eus_x_preferred":[
        "A Peroxa"
    ],
    "name:fra_x_preferred":[
        "A Peroxa"
    ],
    "name:glg_x_preferred":[
        "A Peroxa"
    ],
    "name:hun_x_preferred":[
        "A Peroxa"
    ],
    "name:ita_x_preferred":[
        "A Peroxa"
    ],
    "name:jpn_x_preferred":[
        "\u30a2\u30fb\u30da\u30ed\u30fc\u30b7\u30e3"
    ],
    "name:kaz_x_preferred":[
        "\u041b\u0430-\u041f\u0435\u0440\u043e\u0445\u0430"
    ],
    "name:lmo_x_preferred":[
        "A Peroxa"
    ],
    "name:msa_x_preferred":[
        "A Peroxa"
    ],
    "name:nld_x_preferred":[
        "A Peroxa"
    ],
    "name:oci_x_preferred":[
        "A Peroxa"
    ],
    "name:pol_x_preferred":[
        "A Peroxa"
    ],
    "name:por_x_preferred":[
        "A Peroxa"
    ],
    "name:rus_x_preferred":[
        "\u041b\u0430-\u041f\u0435\u0440\u043e\u0445\u0430"
    ],
    "name:sco_x_preferred":[
        "A Peroxa"
    ],
    "name:spa_x_preferred":[
        "La Peroja"
    ],
    "name:tur_x_preferred":[
        "A Peroxa"
    ],
    "name:ukr_x_preferred":[
        "\u0410-\u041f\u0435\u0440\u043e\u0448\u0430"
    ],
    "name:und_x_variant":[
        "San Gin\u00e9s"
    ],
    "name:uzb_x_preferred":[
        "A Peroxa"
    ],
    "name:vie_x_preferred":[
        "A Peroxa"
    ],
    "name:war_x_preferred":[
        "A Peroxa"
    ],
    "name:zho_x_preferred":[
        "\u963f\u4f69\u7f57\u514b\u8428"
    ],
    "wof:name":"A Peroxa",
    "wof:placetype":"locality"
},
  "geometry": {"coordinates":[-7.79454,42.44132000000001],"type":"Point"}
}