{
  "type": "Feature",
  "properties": {
    "gn:admin1_code":"52",
    "gn:admin2_code":"TE",
    "gn:admin3_code":"44039",
    "gn:asciiname":"Bello",
    "gn:country_code":"ES",
    "gn:dem":1007,
    "gn:feature_class":"P",
    "gn:feature_code":"PPLA3",
    "gn:name":"Bello",
    "gn:population":346,
    "gn:timezone":"Europe/Madrid",
    "iso:country":"ES",
    "wof:name":"Bello",
    "wof:placetype":"locality",
    "wof:population":346
},
  "geometry": {"coordinates":[-1.4985,40.92266],"type":"Point"}
}