{
  "type": "Feature",
  "properties": {
    "gn:admin1_code":"52",
    "gn:admin2_code":"TE",
    "gn:admin3_code":"44039",
    "gn:asciiname":"Bello",
    "gn:country_code":"ES",
    "gn:dem":1007,
    "gn:feature_class":"P",
    "gn:feature_code":"PPLA3",
    "gn:name":"Bello",
    "gn:population":346,
    "gn:timezone":"Europe/Madrid",
    "iso:country":"ES",
    "name:ara_x_preferred":[
        "\u0628\u064a\u0644\u0648"
    ],
    "name:ben_x_preferred":[
        "\u09ac\u09c7\u09b2\u09cd\u09b2\u09cb"
    ],
    "name:ceb_x_preferred":[
        "Bello"
    ],
    "name:deu_x_preferred":[
        "Bello"
    ],
    "name:fra_x_preferred":[
        "Bello"
    ],
    "name:glg_x_preferred":[
        "Bello"
    ],
    "name:heb_x_preferred":[
        "\u05d1\u05dc\u05d5"
    ],
    "name:hin_x_preferred":[
        "\u092c\u0947\u0932\u094b"
    ],
    "name:hun_x_preferred":[
        "Bello"
    ],
    "name:ind_x_preferred":[
        "Bello"
    ],
    "name:ita_x_preferred":[
        "Bello"
    ],
    "name:kor_x_preferred":[
        "\ubca8\ub85c"
    ],
    "name:mlg_x_preferred":[
        "Bello"
    ],
    "name:msa_x_preferred":[
        "Bello"
    ],
    "name:nld_x_preferred":[
        "Bello"
    ],
    "name:pol_x_preferred":[
        "Bello"
    ],
    "name:por_x_preferred":[
        "Bello"
    ],
    "name:rus_x_preferred":[
        "\u0411\u0435\u043b\u043b\u043e"
    ],
    "name:slv_x_preferred":[
        "Bello"
    ],
    "name:spa_x_preferred":[
        "Bello"
    ],
    "name:swe_x_preferred":[
        "Bello"
    ],
    "name:tur_x_preferred":[
        "Bello"
    ],
    "name:ukr_x_preferred":[
        "\u0411\u0435\u043b\u043b\u043e"
    ],
    "name:vie_x_preferred":[
        "Bello"
    ],
    "name:war_x_preferred":[
        "Bello"
    ],
    "wof:name":"Bello",
    "wof:placetype":"locality",
    "wof:population":346
},
  "geometry": {"coordinates":[-1.4985,40.92266],"type":"Point"}
}