{
  "type": "Feature",
  "properties": {
    "gn:admin1_code":"56",
    "gn:admin2_code":"GI",
    "gn:admin3_code":"17005",
    "gn:asciiname":"l'Oliva",
    "gn:country_code":"ES",
    "gn:dem":25,
    "gn:feature_class":"P",
    "gn:feature_code":"PPL",
    "gn:name":"l'Oliva",
    "gn:population":0,
    "gn:timezone":"Europe/Madrid",
    "iso:country":"ES",
    "name:cat_x_preferred":[
        "l'Oliva"
    ],
    "wof:name":"l'Oliva",
    "wof:placetype":"locality"
},
  "geometry": {"coordinates":[2.99538,42.24677],"type":"Point"}
}