{
  "type": "Feature",
  "properties": {
    "gn:admin1_code":"34",
    "gn:admin2_code":"O",
    "gn:admin3_code":"33073",
    "gn:asciiname":"Barzana de San Facundo",
    "gn:country_code":"ES",
    "gn:dem":630,
    "gn:feature_class":"P",
    "gn:feature_code":"PPL",
    "gn:name":"B\u00e1rzana de San Facundo",
    "gn:population":0,
    "gn:timezone":"Europe/Madrid",
    "iso:country":"ES",
    "name:und_x_variant":[
        "B\u00e1rcena",
        "B\u00e1rzana de San Facundo"
    ],
    "wof:name":"Barzana de San Facundo",
    "wof:placetype":"locality"
},
  "geometry": {"coordinates":[-6.53126,43.27324],"type":"Point"}
}