{
  "type": "Feature",
  "properties": {
    "gn:gn_country":"ES",
    "gn:gn_fcode":"PPLA3",
    "gn:gn_pop":251,
    "gn:population":251,
    "iso:country":"ES",
    "name:ara_x_preferred":[
        "\u0643\u0648\u0628\u062f\u0627\u0631"
    ],
    "name:arm_x_preferred":[
        "\u053f\u0578\u0562\u0564\u0561\u0580"
    ],
    "name:baq_x_preferred":[
        "C\u00f3bdar"
    ],
    "name:cat_x_preferred":[
        "C\u00f3bdar"
    ],
    "name:chi_x_preferred":[
        "\u79d1\u592b\u8fbe\u5c14"
    ],
    "name:dut_x_preferred":[
        "C\u00f3bdar"
    ],
    "name:eng_x_preferred":[
        "C\u00f3bdar"
    ],
    "name:epo_x_preferred":[
        "C\u00f3bdar"
    ],
    "name:fre_x_preferred":[
        "C\u00f3bdar"
    ],
    "name:ger_x_preferred":[
        "C\u00f3bdar"
    ],
    "name:hat_x_preferred":[
        "C\u00f3bdar"
    ],
    "name:hun_x_preferred":[
        "C\u00f3bdar"
    ],
    "name:ina_x_preferred":[
        "C\u00f3bdar"
    ],
    "name:ita_x_preferred":[
        "C\u00f3bdar"
    ],
    "name:mac_x_preferred":[
        "\u041a\u043e\u0431\u0434\u0430\u0440"
    ],
    "name:may_x_preferred":[
        "C\u00f3bdar"
    ],
    "name:nan_x_preferred":[
        "C\u00f3bdar"
    ],
    "name:oci_x_preferred":[
        "C\u00f3bdar"
    ],
    "name:per_x_preferred":[
        "\u06a9\u0648\u0628\u062f\u0627\u0631"
    ],
    "name:pol_x_preferred":[
        "C\u00f3bdar"
    ],
    "name:por_x_preferred":[
        "C\u00f3bdar"
    ],
    "name:rum_x_preferred":[
        "C\u00f3bdar"
    ],
    "name:rus_x_preferred":[
        "\u041a\u043e\u0431\u0434\u0430\u0440"
    ],
    "name:spa_x_preferred":[
        "C\u00f3bdar"
    ],
    "name:swe_x_preferred":[
        "C\u00f3bdar"
    ],
    "name:tur_x_preferred":[
        "C\u00f3bdar"
    ],
    "name:ukr_x_preferred":[
        "\u041a\u043e\u0431\u0434\u0430\u0440"
    ],
    "name:uzb_x_preferred":[
        "C\u00f3bdar"
    ],
    "name:vie_x_preferred":[
        "C\u00f3bdar"
    ],
    "name:war_x_preferred":[
        "C\u00f3bdar"
    ],
    "qs_pg:aaroncc":"ES",
    "qs_pg:gn_country":"ES",
    "qs_pg:gn_fcode":"PPLA3",
    "qs_pg:gn_pop":251,
    "qs_pg:name":"C\u00f3bdar",
    "qs_pg:name_adm0":"Espa\u00f1a",
    "qs_pg:name_adm1":"Andaluc\u00eda",
    "qs_pg:photos_9r":0,
    "qs_pg:photos_sr":0,
    "qs_pg:pop_sr":2,
    "qs_pg:qs_pg_placetype":"locality",
    "qs_pg:qs_pg_placetype_gp":"Town",
    "qs_pg:woe_adm0":23424950,
    "woe:adm0_id":23424950,
    "woe:name_adm0":"Espa\u00f1a",
    "woe:name_adm1":"Andaluc\u00eda",
    "woe:placetype":"Town",
    "wof:name":"C\u00f3bdar",
    "wof:placetype":"locality",
    "wof:population":251
},
  "geometry": {"coordinates":[-2.21098,37.26166],"type":"Point"}
}