{
  "type": "Feature",
  "properties": {
    "gn:admin1_code":"56",
    "gn:admin2_code":"T",
    "gn:admin3_code":"43137",
    "gn:asciiname":"La Carrona",
    "gn:cc2":"ES",
    "gn:country_code":"ES",
    "gn:dem":250,
    "gn:feature_class":"P",
    "gn:feature_code":"PPL",
    "gn:name":"La Carro\u00f1a",
    "gn:population":0,
    "gn:timezone":"Europe/Madrid",
    "iso:country":"ES",
    "name:und_x_variant":[
        "Caser\u00edo Carro\u00f1a",
        "La Carro\u00f1a"
    ],
    "wof:name":"La Carrona",
    "wof:placetype":"locality"
},
  "geometry": {"coordinates":[1.56667,41.31667],"type":"Point"}
}