{
  "type": "Feature",
  "properties": {
    "gn:admin1_code":"58",
    "gn:admin2_code":"C",
    "gn:admin3_code":"15056",
    "gn:asciiname":"Albite",
    "gn:country_code":"ES",
    "gn:dem":346,
    "gn:feature_class":"P",
    "gn:feature_code":"PPL",
    "gn:name":"Albite",
    "gn:population":0,
    "gn:timezone":"Europe/Madrid",
    "iso:country":"ES",
    "name:afr_x_preferred":[
        "Albiet"
    ],
    "name:ara_x_preferred":[
        "\u0623\u0644\u0628\u064a\u062a"
    ],
    "name:aze_x_preferred":[
        "Albit"
    ],
    "name:bel_x_preferred":[
        "\u0410\u043b\u044c\u0431\u0456\u0442"
    ],
    "name:bos_x_preferred":[
        "Albit"
    ],
    "name:bul_x_preferred":[
        "\u0410\u043b\u0431\u0438\u0442"
    ],
    "name:cat_x_preferred":[
        "Albita"
    ],
    "name:ces_x_preferred":[
        "Albit"
    ],
    "name:deu_x_preferred":[
        "Albit"
    ],
    "name:ell_x_preferred":[
        "\u0391\u03bb\u03b2\u03af\u03c4\u03b7\u03c2"
    ],
    "name:epo_x_preferred":[
        "Albito"
    ],
    "name:est_x_preferred":[
        "Albiit"
    ],
    "name:eus_x_preferred":[
        "Albita"
    ],
    "name:fas_x_preferred":[
        "\u0622\u0644\u0628\u06cc\u062a"
    ],
    "name:fin_x_preferred":[
        "Albiitti"
    ],
    "name:fra_x_preferred":[
        "Albite"
    ],
    "name:glg_x_preferred":[
        "Albita"
    ],
    "name:heb_x_preferred":[
        "\u05d0\u05dc\u05d1\u05d9\u05d8"
    ],
    "name:hrv_x_preferred":[
        "Albit"
    ],
    "name:hun_x_preferred":[
        "Albit"
    ],
    "name:ita_x_preferred":[
        "Albite"
    ],
    "name:jpn_x_preferred":[
        "\u66f9\u9577\u77f3"
    ],
    "name:kat_x_preferred":[
        "\u10d0\u10da\u10d1\u10d8\u10e2\u10d8"
    ],
    "name:kaz_x_preferred":[
        "\u0410\u043b\u044c\u0431\u0438\u0442"
    ],
    "name:kir_x_preferred":[
        "\u0410\u043b\u044c\u0431\u0438\u0442"
    ],
    "name:kor_x_preferred":[
        "\uc870\uc7a5\uc11d"
    ],
    "name:lav_x_preferred":[
        "Alb\u012bts"
    ],
    "name:lit_x_preferred":[
        "Albitas"
    ],
    "name:nld_x_preferred":[
        "Albiet"
    ],
    "name:nno_x_preferred":[
        "Albitt"
    ],
    "name:nor_x_preferred":[
        "Albitt"
    ],
    "name:pol_x_preferred":[
        "Albit"
    ],
    "name:por_x_preferred":[
        "Albita"
    ],
    "name:ron_x_preferred":[
        "Albit"
    ],
    "name:rus_x_preferred":[
        "\u0410\u043b\u044c\u0431\u0438\u0442"
    ],
    "name:slk_x_preferred":[
        "Albit"
    ],
    "name:slv_x_preferred":[
        "Albit"
    ],
    "name:spa_x_preferred":[
        "Albita"
    ],
    "name:srp_x_preferred":[
        "\u0410\u043b\u0431\u0438\u0442"
    ],
    "name:swe_x_preferred":[
        "Albit"
    ],
    "name:tgk_x_preferred":[
        "\u0410\u043b\u0431\u0438\u0442"
    ],
    "name:tur_x_preferred":[
        "Albit"
    ],
    "name:ukr_x_preferred":[
        "\u0410\u043b\u044c\u0431\u0456\u0442"
    ],
    "name:uzb_x_preferred":[
        "Albit"
    ],
    "name:vie_x_preferred":[
        "Albit"
    ],
    "name:zho_x_preferred":[
        "\u94a0\u957f\u77f3"
    ],
    "wof:name":"Albite",
    "wof:placetype":"locality"
},
  "geometry": {"coordinates":[-8.87661,42.9373],"type":"Point"}
}