{
  "type": "Feature",
  "properties": {
    "iso:country":"ES",
    "name:eng_x_preferred":[
        "Camino del Colminar"
    ],
    "name:spa_x_preferred":[
        "Camino del Colminar"
    ],
    "wof:name":"Camino del Colminar",
    "wof:placetype":"neighbourhood"
},
  "geometry": {"coordinates":[-4.40939622297447,36.7431085794769],"type":"Point"}
}