{
  "type": "Feature",
  "properties": {
    "gn:admin1_code":"58",
    "gn:admin2_code":"C",
    "gn:admin3_code":"15010",
    "gn:asciiname":"Cardeiro",
    "gn:cc2":"ES",
    "gn:country_code":"ES",
    "gn:dem":403,
    "gn:feature_class":"P",
    "gn:feature_code":"PPL",
    "gn:name":"Cardeiro",
    "gn:population":0,
    "gn:timezone":"Europe/Madrid",
    "iso:country":"ES",
    "name:und_x_variant":[
        "San Pedro",
        "Cardeiro"
    ],
    "wof:name":"Cardeiro",
    "wof:placetype":"locality"
},
  "geometry": {"coordinates":[-8.15,43.01667],"type":"Point"}
}