{
  "type": "Feature",
  "properties": {
    "gn:admin1_code":"51",
    "gn:admin2_code":"GR",
    "gn:admin3_code":"18051",
    "gn:asciiname":"Casa Puerto Blanco",
    "gn:cc2":"ES",
    "gn:country_code":"ES",
    "gn:dem":942,
    "gn:feature_class":"P",
    "gn:feature_code":"PPL",
    "gn:name":"Casa Puerto Blanco",
    "gn:population":0,
    "gn:timezone":"Europe/Madrid",
    "iso:country":"ES",
    "name:und_x_variant":[
        "Caser\u00edo de Puerto Blanco",
        "Casa Puerto Blanco"
    ],
    "wof:name":"Casa Puerto Blanco",
    "wof:placetype":"locality"
},
  "geometry": {"coordinates":[-3.68333,37.38333],"type":"Point"}
}