{
  "type": "Feature",
  "properties": {
    "iso:country":"ES",
    "name:ceb_x_preferred":[
        "Alcolea"
    ],
    "name:eng_x_preferred":[
        "Alcolea"
    ],
    "name:jpn_x_preferred":[
        "\u30a2\u30eb\u30b3\u30ec\u30a2"
    ],
    "name:nld_x_preferred":[
        "Alcolea"
    ],
    "name:spa_x_preferred":[
        "Alcolea"
    ],
    "name:swe_x_preferred":[
        "Alcolea"
    ],
    "wof:name":"Alcolea",
    "wof:placetype":"neighbourhood"
},
  "geometry": {"coordinates":[-4.671761,37.931184],"type":"Point"}
}