{
  "type": "Feature",
  "properties": {
    "iso:country":"ES",
    "name:eng_x_preferred":[
        "Alcolea"
    ],
    "name:spa_x_preferred":[
        "Alcolea"
    ],
    "name:swe_x_preferred":[
        "Alcolea"
    ],
    "wof:name":"Alcolea",
    "wof:placetype":"neighbourhood"
},
  "geometry": {"coordinates":[-4.67176059243429,37.93118442563672],"type":"Point"}
}