{
  "type": "Feature",
  "properties": {
    "gn:admin1_code":"56",
    "gn:admin2_code":"B",
    "gn:admin3_code":"08060",
    "gn:admin4_code":"8060.0",
    "gn:asciiname":"Castellfollit de Riubregos",
    "gn:country_code":"ES",
    "gn:dem":548,
    "gn:feature_class":"P",
    "gn:feature_code":"PPLA3",
    "gn:name":"Castellfollit de Riubreg\u00f3s",
    "gn:population":0,
    "gn:timezone":"Europe/Madrid",
    "iso:country":"ES",
    "name:cat_x_preferred":[
        "Castellfollit de Riubreg\u00f3s"
    ],
    "name:spa_x_preferred":[
        "Castellfullit de Riubreg\u00f3s"
    ],
    "wof:name":"Castellfollit de Riubregos",
    "wof:placetype":"locality"
},
  "geometry": {"coordinates":[1.43333,41.76667],"type":"Point"}
}