{
  "type": "Feature",
  "properties": {
    "gn:admin1_code":"55",
    "gn:admin2_code":"SO",
    "gn:admin3_code":"42024",
    "gn:asciiname":"Cortos",
    "gn:country_code":"ES",
    "gn:dem":1125,
    "gn:feature_class":"P",
    "gn:feature_code":"PPL",
    "gn:name":"Cortos",
    "gn:population":0,
    "gn:timezone":"Europe/Madrid",
    "iso:country":"ES",
    "wof:name":"Cortos",
    "wof:placetype":"locality"
},
  "geometry": {"coordinates":[-2.25963,41.81082],"type":"Point"}
}