{
  "type": "Feature",
  "properties": {
    "gn:admin1_code":"58",
    "gn:admin2_code":"PO",
    "gn:admin3_code":"36047",
    "gn:asciiname":"Argozon",
    "gn:country_code":"ES",
    "gn:dem":693,
    "gn:feature_class":"P",
    "gn:feature_code":"PPL",
    "gn:name":"Argoz\u00f3n",
    "gn:population":0,
    "gn:timezone":"Europe/Madrid",
    "iso:country":"ES",
    "name:und_x_variant":[
        "San Vicente",
        "Argoz\u00f3n"
    ],
    "wof:name":"Argozon",
    "wof:placetype":"locality"
},
  "geometry": {"coordinates":[-7.86997,42.66152],"type":"Point"}
}