{
  "type": "Feature",
  "properties": {
    "gn:gn_country":"ES",
    "gn:gn_fcode":"PPLA3",
    "gn:gn_pop":61,
    "gn:population":61,
    "iso:country":"ES",
    "name:ara_x_preferred":[
        "\u0628\u0631\u0627\u062f\u0627\u0646\u0648\u0633 \u062f\u064a \u0628\u0648\u0631\u064a\u0628\u0627"
    ],
    "name:arg_x_preferred":[
        "Pr\u00e1danos de Bureba"
    ],
    "name:baq_x_preferred":[
        "Pr\u00e1danos de Bureba"
    ],
    "name:cat_x_preferred":[
        "Pr\u00e1danos de Bureba"
    ],
    "name:chi_x_preferred":[
        "\u666e\u62c9\u8fbe\u8bfa\u65af\u5fb7\u6b66\u96f7\u74e6"
    ],
    "name:dut_x_preferred":[
        "Pr\u00e1danos de Bureba"
    ],
    "name:eng_x_preferred":[
        "Pr\u00e1danos de Bureba"
    ],
    "name:fre_x_preferred":[
        "Pr\u00e1danos de Bureba"
    ],
    "name:glg_x_preferred":[
        "Pr\u00e1danos de Bureba"
    ],
    "name:haw_x_preferred":[
        "Pr\u00e1danos de Bureba"
    ],
    "name:hun_x_preferred":[
        "Pr\u00e1danos de Bureba"
    ],
    "name:ina_x_preferred":[
        "Pr\u00e1danos de Bureba"
    ],
    "name:ita_x_preferred":[
        "Pr\u00e1danos de Bureba"
    ],
    "name:may_x_preferred":[
        "Pr\u00e1danos de Bureba"
    ],
    "name:nan_x_preferred":[
        "Pr\u00e1danos de Bureba"
    ],
    "name:oci_x_preferred":[
        "Pr\u00e1danos de Bureba"
    ],
    "name:per_x_preferred":[
        "\u067e\u0631\u0627\u062f\u0644\u0648\u0626\u0646\u06af\u0648"
    ],
    "name:pol_x_preferred":[
        "Pr\u00e1danos de Bureba"
    ],
    "name:por_x_preferred":[
        "Pr\u00e1danos de Bureba"
    ],
    "name:rus_x_preferred":[
        "\u041f\u0440\u0430\u0434\u0430\u043d\u043e\u0441-\u0434\u0435-\u0411\u0443\u0440\u0435\u0431\u0430"
    ],
    "name:spa_x_preferred":[
        "Pr\u00e1danos de Bureba"
    ],
    "name:swe_x_preferred":[
        "Pr\u00e1danos de Bureba"
    ],
    "name:ukr_x_preferred":[
        "\u041f\u0440\u0430\u0434\u0430\u043d\u043e\u0441-\u0434\u0435-\u0411\u0443\u0440\u0435\u0431\u0430"
    ],
    "name:vie_x_preferred":[
        "Pr\u00e1danos de Bureba"
    ],
    "name:war_x_preferred":[
        "Pr\u00e1danos de Bureba"
    ],
    "qs_pg:aaroncc":"ES",
    "qs_pg:gn_country":"ES",
    "qs_pg:gn_fcode":"PPLA3",
    "qs_pg:gn_pop":61,
    "qs_pg:name":"Pr\u00e1danos de Bureba",
    "qs_pg:name_adm0":"Espa\u00f1a",
    "qs_pg:name_adm1":"Castilla y Le\u00f3n",
    "qs_pg:photos_9r":0,
    "qs_pg:photos_sr":0,
    "qs_pg:pop_sr":1,
    "qs_pg:qs_pg_placetype":"locality",
    "qs_pg:qs_pg_placetype_gp":"Town",
    "qs_pg:woe_adm0":23424950,
    "woe:adm0_id":23424950,
    "woe:name_adm0":"Espa\u00f1a",
    "woe:name_adm1":"Castilla y Le\u00f3n",
    "woe:placetype":"Town",
    "wof:name":"Pr\u00e1danos de Bureba",
    "wof:placetype":"locality",
    "wof:population":61
},
  "geometry": {"coordinates":[-3.34752,42.50264],"type":"Point"}
}