{
  "type": "Feature",
  "properties": {
    "gn:admin1_code":"39",
    "gn:admin2_code":"S",
    "gn:admin3_code":"39013",
    "gn:asciiname":"Lamedo",
    "gn:country_code":"ES",
    "gn:dem":831,
    "gn:feature_class":"P",
    "gn:feature_code":"PPL",
    "gn:name":"Lamedo",
    "gn:population":0,
    "gn:timezone":"Europe/Madrid",
    "iso:country":"ES",
    "wof:name":"Lamedo",
    "wof:placetype":"locality"
},
  "geometry": {"coordinates":[-4.49611,43.10872],"type":"Point"}
}