{
  "type": "Feature",
  "properties": {
    "gn:admin1_code":"59",
    "gn:admin2_code":"VI",
    "gn:admin3_code":"01054",
    "gn:asciiname":"Unza",
    "gn:country_code":"ES",
    "gn:dem":664,
    "gn:feature_class":"P",
    "gn:feature_code":"PPL",
    "gn:name":"Untzaga / Unz\u00e1",
    "gn:population":0,
    "gn:timezone":"Europe/Madrid",
    "iso:country":"ES",
    "name:eus_x_preferred":[
        "Untzaga"
    ],
    "name:spa_x_preferred":[
        "Unz\u00e1"
    ],
    "name:spa_x_variant":[
        "Unza"
    ],
    "wof:name":"Unza",
    "wof:placetype":"locality"
},
  "geometry": {"coordinates":[-2.95515,42.97589],"type":"Point"}
}