{
  "type": "Feature",
  "properties": {
    "gn:gn_country":"ES",
    "gn:gn_fcode":"PPLA3",
    "gn:gn_pop":143,
    "gn:population":143,
    "iso:country":"ES",
    "name:arg_x_preferred":[
        "Llascuarri"
    ],
    "name:arg_x_variant":[
        "Llascuarre"
    ],
    "name:cat_x_preferred":[
        "Lasquarri"
    ],
    "name:ceb_x_preferred":[
        "Lascuarre"
    ],
    "name:deu_x_preferred":[
        "Lascuarre"
    ],
    "name:eng_x_preferred":[
        "Lascuarre"
    ],
    "name:eus_x_preferred":[
        "Lascuarre"
    ],
    "name:fra_x_preferred":[
        "Lascuarre"
    ],
    "name:hak_x_preferred":[
        "Lascuarre"
    ],
    "name:hun_x_preferred":[
        "Lascuarre"
    ],
    "name:ita_x_preferred":[
        "Lascuarre"
    ],
    "name:msa_x_preferred":[
        "Lascuarre"
    ],
    "name:nan_x_preferred":[
        "Lascuarre"
    ],
    "name:nld_x_preferred":[
        "Lascuarre"
    ],
    "name:oci_x_preferred":[
        "Lascuarre"
    ],
    "name:pol_x_preferred":[
        "Lascuarre"
    ],
    "name:por_x_preferred":[
        "Lascuarre"
    ],
    "name:rus_x_preferred":[
        "\u041b\u0430\u0441\u043a\u0443\u0430\u0440\u0440\u0435"
    ],
    "name:spa_x_preferred":[
        "Lascuarre"
    ],
    "name:swe_x_preferred":[
        "Lascuarre"
    ],
    "name:ukr_x_preferred":[
        "\u041b\u0430\u0441\u043a\u0443\u0430\u0440\u0440\u0435"
    ],
    "name:unk_x_variant":[
        "Lascuarra"
    ],
    "name:uzb_x_preferred":[
        "Lascuarre"
    ],
    "name:vie_x_preferred":[
        "Lascuarre"
    ],
    "name:war_x_preferred":[
        "Lascuarre"
    ],
    "name:zho_x_preferred":[
        "\u62c9\u65af\u5938\u96f7"
    ],
    "qs_pg:aaroncc":"ES",
    "qs_pg:gn_country":"ES",
    "qs_pg:gn_fcode":"PPLA3",
    "qs_pg:gn_pop":143,
    "qs_pg:name":"Lascuarre",
    "qs_pg:name_adm0":"Espa\u00f1a",
    "qs_pg:name_adm1":"Arag\u00f3n",
    "qs_pg:photos_9r":0,
    "qs_pg:photos_sr":0,
    "qs_pg:pop_sr":1,
    "qs_pg:qs_pg_placetype":"locality",
    "qs_pg:qs_pg_placetype_gp":"Town",
    "qs_pg:woe_adm0":23424950,
    "woe:adm0_id":23424950,
    "woe:name_adm0":"Espa\u00f1a",
    "woe:name_adm1":"Arag\u00f3n",
    "woe:placetype":"Town",
    "wof:name":"Lascuarre",
    "wof:placetype":"locality",
    "wof:population":143
},
  "geometry": {"coordinates":[0.5201,42.1961],"type":"Point"}
}