{
  "type": "Feature",
  "properties": {
    "gn:admin1_code":"31",
    "gn:admin2_code":"MU",
    "gn:admin3_code":"30030",
    "gn:asciiname":"Casas de los Garcias",
    "gn:country_code":"ES",
    "gn:dem":309,
    "gn:feature_class":"P",
    "gn:feature_code":"PPL",
    "gn:name":"Casas de los Garc\u00edas",
    "gn:population":0,
    "gn:timezone":"Europe/Madrid",
    "iso:country":"ES",
    "name:und_x_variant":[
        "Casas Los Garcias",
        "Caser\u00edo Los Garc\u00edas",
        "Casas de los Garc\u00edas"
    ],
    "wof:name":"Casas de los Garcias",
    "wof:placetype":"locality"
},
  "geometry": {"coordinates":[-1.18479,37.83464],"type":"Point"}
}