{
  "type": "Feature",
  "properties": {
    "gn:admin1_code":"34",
    "gn:admin2_code":"O",
    "gn:admin3_code":"33020",
    "gn:asciiname":"Lloreda",
    "gn:country_code":"ES",
    "gn:dem":88,
    "gn:feature_class":"P",
    "gn:feature_code":"PPL",
    "gn:name":"Lloreda",
    "gn:population":0,
    "gn:timezone":"Europe/Madrid",
    "iso:country":"ES",
    "wof:name":"Lloreda",
    "wof:placetype":"locality"
},
  "geometry": {"coordinates":[-5.92948,43.52638],"type":"Point"}
}