{
  "type": "Feature",
  "properties": {
    "gn:admin1_code":"55",
    "gn:admin2_code":"LE",
    "gn:admin3_code":"24134",
    "gn:asciiname":"Puente de Alba",
    "gn:country_code":"ES",
    "gn:dem":965,
    "gn:feature_class":"P",
    "gn:feature_code":"PPL",
    "gn:name":"Puente de Alba",
    "gn:population":0,
    "gn:timezone":"Europe/Madrid",
    "iso:country":"ES",
    "wof:name":"Puente de Alba",
    "wof:placetype":"locality"
},
  "geometry": {"coordinates":[-5.62782,42.81953],"type":"Point"}
}