{
  "type": "Feature",
  "properties": {
    "iso:country":"ES",
    "name:eng_x_preferred":[
        "Perchel Norte"
    ],
    "name:spa_x_preferred":[
        "Perchel Norte"
    ],
    "wof:name":"Perchel Norte",
    "wof:placetype":"neighbourhood"
},
  "geometry": {"coordinates":[-4.4274316346961,36.7195745834518],"type":"Point"}
}