{
  "type": "Feature",
  "properties": {
    "gn:admin1_code":"51",
    "gn:admin2_code":"AL",
    "gn:admin3_code":"04053",
    "gn:asciiname":"Los Menas",
    "gn:country_code":"ES",
    "gn:dem":209,
    "gn:feature_class":"P",
    "gn:feature_code":"PPL",
    "gn:name":"Los Menas",
    "gn:population":0,
    "gn:timezone":"Europe/Madrid",
    "iso:country":"ES",
    "name:und_x_variant":[
        "Caser\u00edo Los Menas",
        "Los Menas"
    ],
    "wof:name":"Los Menas",
    "wof:placetype":"locality"
},
  "geometry": {"coordinates":[-1.99271,37.35083],"type":"Point"}
}