{
  "type": "Feature",
  "properties": {
    "gn:admin1_code":"58",
    "gn:admin2_code":"C",
    "gn:admin3_code":"15059",
    "gn:asciiname":"O Meson do Vento",
    "gn:country_code":"ES",
    "gn:dem":449,
    "gn:feature_class":"P",
    "gn:feature_code":"PPL",
    "gn:name":"O Mes\u00f3n do Vento",
    "gn:population":0,
    "gn:timezone":"Europe/Madrid",
    "iso:country":"ES",
    "wof:name":"O Meson do Vento",
    "wof:placetype":"locality"
},
  "geometry": {"coordinates":[-8.38459,43.15085],"type":"Point"}
}