{
  "type": "Feature",
  "properties": {
    "gn:admin1_code":"51",
    "gn:admin2_code":"CO",
    "gn:admin3_code":"14034",
    "gn:asciiname":"Guijo",
    "gn:country_code":"ES",
    "gn:dem":567,
    "gn:feature_class":"P",
    "gn:feature_code":"PPL",
    "gn:name":"Guijo",
    "gn:population":0,
    "gn:timezone":"Europe/Madrid",
    "iso:country":"ES",
    "name:fra_x_preferred":[
        "Guijo"
    ],
    "name:sco_x_preferred":[
        "Guijo"
    ],
    "name:spa_x_preferred":[
        "Guijo"
    ],
    "wof:name":"Guijo",
    "wof:placetype":"locality"
},
  "geometry": {"coordinates":[-4.78307,38.4964],"type":"Point"}
}