{
  "type": "Feature",
  "properties": {
    "gn:admin1_code":"55",
    "gn:admin2_code":"SA",
    "gn:admin3_code":"37149",
    "gn:asciiname":"Vilvis",
    "gn:country_code":"ES",
    "gn:dem":780,
    "gn:feature_class":"P",
    "gn:feature_code":"PPL",
    "gn:name":"Vilvis",
    "gn:population":0,
    "gn:timezone":"Europe/Madrid",
    "iso:country":"ES",
    "wof:name":"Vilvis",
    "wof:placetype":"locality"
},
  "geometry": {"coordinates":[-6.15489,40.83005],"type":"Point"}
}