{
  "type": "Feature",
  "properties": {
    "gn:admin1_code":"34",
    "gn:admin2_code":"O",
    "gn:admin3_code":"33047",
    "gn:asciiname":"Cimiano",
    "gn:country_code":"ES",
    "gn:dem":69,
    "gn:feature_class":"P",
    "gn:feature_code":"PPL",
    "gn:name":"Cimiano",
    "gn:population":0,
    "gn:timezone":"Europe/Madrid",
    "iso:country":"ES",
    "name:ita_x_preferred":[
        "Cimiano"
    ],
    "name:lmo_x_preferred":[
        "Cimian"
    ],
    "wof:name":"Cimiano",
    "wof:placetype":"locality"
},
  "geometry": {"coordinates":[-4.5752,43.32474000000001],"type":"Point"}
}