{
  "type": "Feature",
  "properties": {
    "gn:admin1_code":"51",
    "gn:admin2_code":"CA",
    "gn:admin3_code":"11020",
    "gn:asciiname":"Jerez de la Frontera",
    "gn:country_code":"ES",
    "gn:dem":53,
    "gn:feature_class":"P",
    "gn:feature_code":"PPLA3",
    "gn:name":"Jerez de la Frontera",
    "gn:population":207532,
    "gn:timezone":"Europe/Madrid",
    "iso:country":"ES",
    "name:ara_x_preferred":[
        "\u0634\u0631\u064a\u0634"
    ],
    "name:arg_x_preferred":[
        "Xerez de la Frontera"
    ],
    "name:bel_x_preferred":[
        "\u0413\u043e\u0440\u0430\u0434 \u0425\u0435\u0440\u044d\u0441-\u0434\u044d-\u043b\u0430-\u0424\u0440\u0430\u043d\u0442\u044d\u0440\u0430"
    ],
    "name:bul_x_preferred":[
        "\u0425\u0435\u0440\u0435\u0441 \u0434\u0435 \u043b\u0430 \u0424\u0440\u043e\u043d\u0442\u0435\u0440\u0430"
    ],
    "name:dan_x_preferred":[
        "Jerez de la Frontera"
    ],
    "name:deu_x_preferred":[
        "Jerez de la Frontera"
    ],
    "name:eng_x_preferred":[
        "Jerez de la Frontera"
    ],
    "name:epo_x_preferred":[
        "\u0124erezo"
    ],
    "name:epo_x_variant":[
        "Jerez de la Frontera"
    ],
    "name:fin_x_preferred":[
        "Jerez de la Frontera"
    ],
    "name:fra_x_preferred":[
        "X\u00e9r\u00e8s"
    ],
    "name:heb_x_preferred":[
        "\u05d7\u05e8\u05e1 \u05d3\u05d4 \u05dc\u05d4 \u05e4\u05e8\u05d5\u05e0\u05d8\u05e8\u05d4"
    ],
    "name:ita_x_preferred":[
        "Jerez de la Frontera"
    ],
    "name:jpn_x_preferred":[
        "\u30d8\u30ec\u30b9\u30fb\u30c7\u30fb\u30e9\u30fb\u30d5\u30ed\u30f3\u30c6\u30fc\u30e9"
    ],
    "name:kor_x_preferred":[
        "\ud5e4\ub808\uc2a4\ub370\ub77c\ud504\ub860\ud14c\ub77c"
    ],
    "name:lat_x_preferred":[
        "Xeresium"
    ],
    "name:lit_x_preferred":[
        "Cheres de la Frontera"
    ],
    "name:nld_x_preferred":[
        "Jerez de la Frontera"
    ],
    "name:nor_x_preferred":[
        "Jerez de la Frontera"
    ],
    "name:oci_x_preferred":[
        "Xer\u00e8s"
    ],
    "name:pnb_x_preferred":[
        "\u062c\u06cc\u0631\u0627\u0632 \u062f\u06cc \u0644\u0627 \u0641\u0631\u0648\u0646\u062a\u06cc\u0631\u0627"
    ],
    "name:pol_x_preferred":[
        "Jerez de la Frontera"
    ],
    "name:por_x_preferred":[
        "Jerez de la Frontera"
    ],
    "name:ron_x_preferred":[
        "Jerez de la Frontera"
    ],
    "name:rus_x_preferred":[
        "\u0425\u0435\u0440\u0435\u0441-\u0434\u0435-\u043b\u0430-\u0424\u0440\u043e\u043d\u0442\u0435\u0440\u0430"
    ],
    "name:spa_x_preferred":[
        "Jerez de la Frontera"
    ],
    "name:spa_x_variant":[
        "Jerez"
    ],
    "name:srp_x_preferred":[
        "\u0425\u0435\u0440\u0435\u0437 \u0434\u0435 \u043b\u0430 \u0424\u0440\u043e\u043d\u0442\u0435\u0440\u0430"
    ],
    "name:swe_x_preferred":[
        "Jerez de la Frontera"
    ],
    "name:tur_x_preferred":[
        "Jerez de la Frontera"
    ],
    "name:ukr_x_preferred":[
        "\u0425\u0435\u0440\u0435\u0441-\u0434\u0435-\u043b\u0430-\u0424\u0440\u043e\u043d\u0442\u0435\u0440\u0430"
    ],
    "name:und_x_variant":[
        "Jarez de la Frontera",
        "Jerez de la Frontera",
        "Jerez"
    ],
    "name:zho_x_preferred":[
        "\u8d6b\u96f7\u65af-\u5fb7\u62c9\u5f17\u9f99\u7279\u62c9"
    ],
    "wof:name":"Jerez de la Frontera",
    "wof:placetype":"locality",
    "wof:population":207532
},
  "geometry": {"coordinates":[-6.13606,36.68645],"type":"Point"}
}