{
  "type": "Feature",
  "properties": {
    "gn:country":"ES",
    "gn:fcode":"PPLA3",
    "gn:population":172,
    "iso:country":"ES",
    "name:arg_x_preferred":[
        "Villamoratiel de las Matas"
    ],
    "name:cat_x_preferred":[
        "Villamoratiel de las Matas"
    ],
    "name:eng_x_preferred":[
        "Villamoratiel de las Matas"
    ],
    "name:eus_x_preferred":[
        "Villamoratiel de las Matas"
    ],
    "name:fra_x_preferred":[
        "Villamoratiel de las Matas"
    ],
    "name:glg_x_preferred":[
        "Villamoratiel de las Matas"
    ],
    "name:haw_x_preferred":[
        "Villamoratiel de las Matas"
    ],
    "name:hun_x_preferred":[
        "Villamoratiel de las Matas"
    ],
    "name:ido_x_preferred":[
        "Villamoratiel de las Matas"
    ],
    "name:ina_x_preferred":[
        "Villamoratiel de las Matas"
    ],
    "name:ita_x_preferred":[
        "Villamoratiel de las Matas"
    ],
    "name:msa_x_preferred":[
        "Villamoratiel de las Matas"
    ],
    "name:nan_x_preferred":[
        "Villamoratiel de las Matas"
    ],
    "name:nld_x_preferred":[
        "Villamoratiel de las Matas"
    ],
    "name:oci_x_preferred":[
        "Villamoratiel de las Matas"
    ],
    "name:pol_x_preferred":[
        "Villamoratiel de las Matas"
    ],
    "name:por_x_preferred":[
        "Villamoratiel de las Matas"
    ],
    "name:rus_x_preferred":[
        "\u0412\u0438\u043b\u044c\u044f\u043c\u043e\u0440\u0430\u0442\u044c\u0435\u043b\u044c-\u0434\u0435-\u043b\u0430\u0441-\u041c\u0430\u0442\u0430\u0441"
    ],
    "name:spa_x_preferred":[
        "Villamoratiel de las Matas"
    ],
    "name:swe_x_preferred":[
        "Villamoratiel de las Matas"
    ],
    "name:tpi_x_preferred":[
        "Villamoratiel de las Matas"
    ],
    "name:ukr_x_preferred":[
        "\u0412\u0456\u043b\u044c\u044f\u043c\u043e\u0440\u0430\u0442\u044c\u0454\u043b\u044c-\u0434\u0435-\u043b\u0430\u0441-\u041c\u0430\u0442\u0430\u0441"
    ],
    "name:vie_x_preferred":[
        "Villamoratiel de las Matas"
    ],
    "name:war_x_preferred":[
        "Villamoratiel de las Matas"
    ],
    "name:zho_x_preferred":[
        "\u6bd4\u5229\u4e9a\u83ab\u62c9\u94c1\u5c14\u5fb7\u62c9\u65af\u9a6c\u5854\u65af"
    ],
    "qs_pg:aaroncc":"ES",
    "qs_pg:gn_country":"ES",
    "qs_pg:gn_fcode":"PPLA3",
    "qs_pg:gn_pop":172,
    "qs_pg:name":"Villamoratiel de Las Matas",
    "qs_pg:name_adm0":"Espa\u00f1a",
    "qs_pg:name_adm1":"Castilla y Le\u00f3n",
    "qs_pg:photos_9k":1,
    "qs_pg:photos_9r":1,
    "qs_pg:photos_all":1,
    "qs_pg:photos_sr":0,
    "qs_pg:pop_sr":1,
    "qs_pg:qs_pg_placetype":"locality",
    "qs_pg:qs_pg_placetype_gp":"Town",
    "qs_pg:woe_adm0":23424950,
    "woe:adm0_id":23424950,
    "woe:name_adm0":"Espa\u00f1a",
    "woe:name_adm1":"Castilla y Le\u00f3n",
    "woe:placetype":"Town",
    "wof:name":"Villamoratiel de Las Matas",
    "wof:placetype":"locality",
    "wof:population":172
},
  "geometry": {"coordinates":[-5.30064,42.39755],"type":"Point"}
}