{
  "type": "Feature",
  "properties": {
    "gn:admin1_code":"54",
    "gn:admin2_code":"CU",
    "gn:admin3_code":"16166",
    "gn:asciiname":"El Monte de Buenavista",
    "gn:country_code":"ES",
    "gn:dem":733,
    "gn:feature_class":"P",
    "gn:feature_code":"PPL",
    "gn:name":"El Monte de Buenavista",
    "gn:population":0,
    "gn:timezone":"Europe/Madrid",
    "iso:country":"ES",
    "name:und_x_variant":[
        "Casa de Buenavista",
        "Caser\u00edo El Monte de Buenavisva",
        "El Monte de Buenavista"
    ],
    "wof:name":"El Monte de Buenavista",
    "wof:placetype":"locality"
},
  "geometry": {"coordinates":[-2.19467,39.30208],"type":"Point"}
}