{
  "type": "Feature",
  "properties": {
    "gn:admin1_code":"58",
    "gn:admin2_code":"LU",
    "gn:admin3_code":"27063",
    "gn:asciiname":"Frejulfe",
    "gn:cc2":"ES",
    "gn:country_code":"ES",
    "gn:dem":86,
    "gn:feature_class":"P",
    "gn:feature_code":"PPL",
    "gn:name":"Frejulfe",
    "gn:population":0,
    "gn:timezone":"Europe/Madrid",
    "iso:country":"ES",
    "name:und_x_variant":[
        "Santa Eulalia",
        "Frejulfe"
    ],
    "wof:name":"Frejulfe",
    "wof:placetype":"locality"
},
  "geometry": {"coordinates":[-7.46769,43.52219],"type":"Point"}
}