{
  "type": "Feature",
  "properties": {
    "gn:admin1_code":"51",
    "gn:admin2_code":"AL",
    "gn:admin3_code":"04006",
    "gn:asciiname":"Locaiba",
    "gn:country_code":"ES",
    "gn:dem":493,
    "gn:feature_class":"P",
    "gn:feature_code":"PPL",
    "gn:name":"Locaiba",
    "gn:population":0,
    "gn:timezone":"Europe/Madrid",
    "iso:country":"ES",
    "wof:name":"Locaiba",
    "wof:placetype":"locality"
},
  "geometry": {"coordinates":[-2.15624,37.41008],"type":"Point"}
}