{
  "type": "Feature",
  "properties": {
    "gn:admin1_code":"55",
    "gn:admin2_code":"P",
    "gn:admin3_code":"34159",
    "gn:asciiname":"Amayuelas de Abajo",
    "gn:country_code":"ES",
    "gn:dem":782,
    "gn:feature_class":"P",
    "gn:feature_code":"PPL",
    "gn:name":"Amayuelas de Abajo",
    "gn:population":0,
    "gn:timezone":"Europe/Madrid",
    "iso:country":"ES",
    "wof:name":"Amayuelas de Abajo",
    "wof:placetype":"locality"
},
  "geometry": {"coordinates":[-4.49575,42.2048],"type":"Point"}
}