{
  "type": "Feature",
  "properties": {
    "gn:gn_country":"ES",
    "iso:country":"ES",
    "name:ceb_x_preferred":[
        "Giron"
    ],
    "name:deu_x_preferred":[
        "Giron"
    ],
    "name:fra_x_preferred":[
        "Giron"
    ],
    "name:nld_x_preferred":[
        "Giron"
    ],
    "name:pol_x_preferred":[
        "Giron"
    ],
    "name:ron_x_preferred":[
        "Giron"
    ],
    "name:rus_x_preferred":[
        "\u0416\u0438\u0440\u043e\u043d"
    ],
    "name:sme_x_preferred":[
        "Giron"
    ],
    "name:swe_x_preferred":[
        "Giron"
    ],
    "qs_pg:aaroncc":"ES",
    "qs_pg:gn_country":"ES",
    "qs_pg:name":"Giron",
    "qs_pg:name_adm0":"Espa\u00f1a",
    "qs_pg:name_adm1":"Andaluc\u00eda",
    "qs_pg:photos":127,
    "qs_pg:photos_1k":26,
    "qs_pg:photos_9k":1,
    "qs_pg:photos_9r":3,
    "qs_pg:photos_all":127,
    "qs_pg:photos_sr":3,
    "qs_pg:pop_sr":0,
    "qs_pg:qs_pg_placetype":"neighbourhood",
    "qs_pg:qs_pg_placetype_gp":"Suburb",
    "qs_pg:woe_adm0":23424950,
    "woe:adm0_id":23424950,
    "woe:name_adm0":"Espa\u00f1a",
    "woe:name_adm1":"Andaluc\u00eda",
    "woe:placetype":"Suburb",
    "wof:name":"Giron",
    "wof:placetype":"neighbourhood"
},
  "geometry": {"coordinates":[-4.441072,36.697156],"type":"Point"}
}