{
  "type": "Feature",
  "properties": {
    "gn:admin1_code":"58",
    "gn:admin2_code":"LU",
    "gn:admin3_code":"27005",
    "gn:asciiname":"Eiras",
    "gn:country_code":"ES",
    "gn:dem":77,
    "gn:feature_class":"P",
    "gn:feature_code":"PPL",
    "gn:name":"Eiras",
    "gn:population":0,
    "gn:timezone":"Europe/Madrid",
    "iso:country":"ES",
    "wof:name":"Eiras",
    "wof:placetype":"locality"
},
  "geometry": {"coordinates":[-7.24737,43.53642],"type":"Point"}
}