{
  "type": "Feature",
  "properties": {
    "gn:admin1_code":"58",
    "gn:admin2_code":"LU",
    "gn:admin3_code":"27015",
    "gn:asciiname":"Rioaveso",
    "gn:country_code":"ES",
    "gn:dem":425,
    "gn:feature_class":"P",
    "gn:feature_code":"PPL",
    "gn:name":"R\u00edoaveso",
    "gn:population":0,
    "gn:timezone":"Europe/Madrid",
    "iso:country":"ES",
    "name:und_x_variant":[
        "R\u00edoabeso",
        "Santa Eulalia",
        "R\u00edoaveso"
    ],
    "wof:name":"Rioaveso",
    "wof:placetype":"locality"
},
  "geometry": {"coordinates":[-7.58333,43.26667],"type":"Point"}
}