{
  "type": "Feature",
  "properties": {
    "gn:admin1_code":"55",
    "gn:admin2_code":"BU",
    "gn:admin3_code":"09427",
    "gn:asciiname":"Villanueva de Odra",
    "gn:country_code":"ES",
    "gn:dem":842,
    "gn:feature_class":"P",
    "gn:feature_code":"PPL",
    "gn:name":"Villanueva de Odra",
    "gn:population":0,
    "gn:timezone":"Europe/Madrid",
    "iso:country":"ES",
    "wof:name":"Villanueva de Odra",
    "wof:placetype":"locality"
},
  "geometry": {"coordinates":[-4.11544,42.50929],"type":"Point"}
}