{
  "type": "Feature",
  "properties": {
    "iso:country":"ES",
    "wof:name":"La Corza",
    "wof:placetype":"neighbourhood"
},
  "geometry": {"coordinates":[-5.96752145102192,37.40217092140495],"type":"Point"}
}