{
  "type": "Feature",
  "properties": {
    "gn:admin1_code":"34",
    "gn:admin2_code":"O",
    "gn:admin3_code":"33066",
    "gn:asciiname":"Paneda Vieja",
    "gn:country_code":"ES",
    "gn:dem":217,
    "gn:feature_class":"P",
    "gn:feature_code":"PPL",
    "gn:name":"Pa\u00f1eda Vieja",
    "gn:population":0,
    "gn:timezone":"Europe/Madrid",
    "iso:country":"ES",
    "name:und_x_variant":[
        "Pa\u00f1eda Vieja"
    ],
    "wof:name":"Paneda Vieja",
    "wof:placetype":"locality"
},
  "geometry": {"coordinates":[-5.71646,43.41692000000001],"type":"Point"}
}