{
  "type": "Feature",
  "properties": {
    "gn:admin1_code":"60",
    "gn:admin2_code":"V",
    "gn:admin3_code":"46249",
    "gn:asciiname":"Las Casas",
    "gn:country_code":"ES",
    "gn:dem":766,
    "gn:feature_class":"P",
    "gn:feature_code":"PPL",
    "gn:name":"Las Casas",
    "gn:population":0,
    "gn:timezone":"Europe/Madrid",
    "iso:country":"ES",
    "wof:name":"Las Casas",
    "wof:placetype":"locality"
},
  "geometry": {"coordinates":[-1.26667,39.58333],"type":"Point"}
}