{
  "type": "Feature",
  "properties": {
    "gn:country":"ES",
    "gn:fcode":"PPLA3",
    "gn:population":179,
    "iso:country":"ES",
    "name:arg_x_preferred":[
        "Bany\u00f3n"
    ],
    "name:ast_x_preferred":[
        "Ba\u00f1\u00f3n"
    ],
    "name:cat_x_preferred":[
        "Ba\u00f1\u00f3n"
    ],
    "name:ceb_x_preferred":[
        "Ba\u00f1\u00f3n"
    ],
    "name:che_x_preferred":[
        "\u0411\u0430\u043d\u044c\u043e\u043d"
    ],
    "name:eng_x_preferred":[
        "Ba\u00f1\u00f3n"
    ],
    "name:epo_x_preferred":[
        "Ba\u00f1\u00f3n"
    ],
    "name:eus_x_preferred":[
        "Ba\u00f1\u00f3n"
    ],
    "name:fas_x_preferred":[
        "\u0628\u0627\u0646\u06cc\u0646"
    ],
    "name:fra_x_preferred":[
        "Ba\u00f1\u00f3n"
    ],
    "name:hun_x_preferred":[
        "Ba\u00f1\u00f3n"
    ],
    "name:ita_x_preferred":[
        "Ba\u00f1\u00f3n"
    ],
    "name:kat_x_preferred":[
        "\u10d1\u10d0\u10dc\u10d8\u10dd\u10dc\u10d8"
    ],
    "name:kaz_x_preferred":[
        "\u0411\u0430\u043d\u044c\u043e\u043d"
    ],
    "name:lld_x_preferred":[
        "Ba\u00f1\u00f3n"
    ],
    "name:ltz_x_preferred":[
        "Ba\u00f1\u00f3n"
    ],
    "name:msa_x_preferred":[
        "Ba\u00f1\u00f3n"
    ],
    "name:nan_x_preferred":[
        "Ba\u00f1\u00f3n"
    ],
    "name:nld_x_preferred":[
        "Ba\u00f1\u00f3n"
    ],
    "name:oci_x_preferred":[
        "Ba\u00f1\u00f3n"
    ],
    "name:pol_x_preferred":[
        "Ba\u00f1\u00f3n"
    ],
    "name:por_x_preferred":[
        "Ba\u00f1\u00f3n"
    ],
    "name:rus_x_preferred":[
        "\u0411\u0430\u043d\u044c\u043e\u043d"
    ],
    "name:spa_x_preferred":[
        "Ba\u00f1\u00f3n"
    ],
    "name:swe_x_preferred":[
        "Ba\u00f1\u00f3n"
    ],
    "name:tat_x_preferred":[
        "\u0411\u0430\u043d\u044c\u043e\u043d"
    ],
    "name:ukr_x_preferred":[
        "\u0411\u0430\u043d\u044c\u0439\u043e\u043d"
    ],
    "name:uzb_x_preferred":[
        "Ba\u00f1\u00f3n"
    ],
    "name:vec_x_preferred":[
        "Ba\u00f1\u00f3n"
    ],
    "name:vie_x_preferred":[
        "Ba\u00f1\u00f3n"
    ],
    "name:war_x_preferred":[
        "Ba\u00f1\u00f3n"
    ],
    "name:zho_x_preferred":[
        "\u5df4\u5c3c\u7fc1"
    ],
    "qs_pg:aaroncc":"ES",
    "qs_pg:gn_country":"ES",
    "qs_pg:gn_fcode":"PPLA3",
    "qs_pg:gn_pop":179,
    "qs_pg:name":"Ba\u00f1\u00f3n",
    "qs_pg:name_adm0":"Espa\u00f1a",
    "qs_pg:name_adm1":"Arag\u00f3n",
    "qs_pg:photos_9k":1,
    "qs_pg:photos_9r":1,
    "qs_pg:photos_all":2,
    "qs_pg:photos_sr":0,
    "qs_pg:pop_sr":1,
    "qs_pg:qs_pg_placetype":"locality",
    "qs_pg:qs_pg_placetype_gp":"Town",
    "qs_pg:woe_adm0":23424950,
    "woe:adm0_id":23424950,
    "woe:name_adm0":"Espa\u00f1a",
    "woe:name_adm1":"Arag\u00f3n",
    "woe:placetype":"Town",
    "wof:name":"Ba\u00f1\u00f3n",
    "wof:placetype":"locality",
    "wof:population":179
},
  "geometry": {"coordinates":[-1.19091,40.83825],"type":"Point"}
}