{
  "type": "Feature",
  "properties": {
    "gn:admin1_code":"55",
    "gn:admin2_code":"SO",
    "gn:admin3_code":"42022",
    "gn:asciiname":"Peroniel del Campo",
    "gn:country_code":"ES",
    "gn:dem":1056,
    "gn:feature_class":"P",
    "gn:feature_code":"PPL",
    "gn:name":"Peroniel del Campo",
    "gn:population":0,
    "gn:timezone":"Europe/Madrid",
    "iso:country":"ES",
    "wof:name":"Peroniel del Campo",
    "wof:placetype":"locality"
},
  "geometry": {"coordinates":[-2.21991,41.71165],"type":"Point"}
}