{
  "type": "Feature",
  "properties": {
    "gn:gn_country":"ES",
    "gn:gn_fcode":"PPL",
    "gn:gn_pop":134,
    "gn:population":134,
    "iso:country":"ES",
    "name:ara_x_preferred":[
        "\u0644\u0627 \u0633\u064a\u0631\u0627\u062f\u0627"
    ],
    "name:baq_x_preferred":[
        "La Serrada"
    ],
    "name:cat_x_preferred":[
        "La Serrada"
    ],
    "name:chi_x_preferred":[
        "\u62c9\u585e\u62c9\u8fbe"
    ],
    "name:dut_x_preferred":[
        "La Serrada"
    ],
    "name:eng_x_preferred":[
        "La Serrada"
    ],
    "name:fre_x_preferred":[
        "La Serrada"
    ],
    "name:hun_x_preferred":[
        "La Serrada"
    ],
    "name:ina_x_preferred":[
        "La Serrada"
    ],
    "name:ita_x_preferred":[
        "La Serrada"
    ],
    "name:kaz_x_preferred":[
        "\u041b\u0430-\u0421\u0435\u0440\u0440\u0430\u0434\u0430"
    ],
    "name:mac_x_preferred":[
        "\u041b\u0430 \u0421\u0435\u0440\u0430\u0434\u0430"
    ],
    "name:may_x_preferred":[
        "La Serrada"
    ],
    "name:oci_x_preferred":[
        "La Serrada"
    ],
    "name:per_x_preferred":[
        "\u0644\u0627 \u0633\u0631\u0627\u062f\u0627"
    ],
    "name:pol_x_preferred":[
        "La Serrada"
    ],
    "name:por_x_preferred":[
        "La Serrada"
    ],
    "name:rus_x_preferred":[
        "\u041b\u0430-\u0421\u0435\u0440\u0440\u0430\u0434\u0430"
    ],
    "name:spa_x_preferred":[
        "La Serrada"
    ],
    "name:swe_x_preferred":[
        "La Serrada"
    ],
    "name:ukr_x_preferred":[
        "\u041b\u0430-\u0421\u0435\u0440\u0440\u0430\u0434\u0430"
    ],
    "name:uzb_x_preferred":[
        "La Serrada"
    ],
    "name:vie_x_preferred":[
        "La Serrada"
    ],
    "name:war_x_preferred":[
        "La Serrada"
    ],
    "qs_pg:aaroncc":"ES",
    "qs_pg:gn_country":"ES",
    "qs_pg:gn_fcode":"PPL",
    "qs_pg:gn_pop":134,
    "qs_pg:name":"La Serrada",
    "qs_pg:name_adm0":"Espa\u00f1a",
    "qs_pg:name_adm1":"Castilla y Le\u00f3n",
    "qs_pg:photos_9k":1,
    "qs_pg:photos_9r":1,
    "qs_pg:photos_all":1,
    "qs_pg:photos_sr":0,
    "qs_pg:pop_sr":1,
    "qs_pg:qs_pg_placetype":"locality",
    "qs_pg:qs_pg_placetype_gp":"Town",
    "qs_pg:woe_adm0":23424950,
    "woe:adm0_id":23424950,
    "woe:name_adm0":"Espa\u00f1a",
    "woe:name_adm1":"Castilla y Le\u00f3n",
    "woe:placetype":"Town",
    "wof:name":"La Serrada",
    "wof:placetype":"locality",
    "wof:population":134
},
  "geometry": {"coordinates":[-4.79284,40.63169],"type":"Point"}
}