{
  "type": "Feature",
  "properties": {
    "gn:admin1_code":"53",
    "gn:admin2_code":"TF",
    "gn:admin3_code":"38005",
    "gn:asciiname":"La Degollada",
    "gn:country_code":"ES",
    "gn:dem":472,
    "gn:feature_class":"P",
    "gn:feature_code":"PPL",
    "gn:name":"La Degollada",
    "gn:population":0,
    "gn:timezone":"Atlantic/Canary",
    "iso:country":"ES",
    "wof:name":"La Degollada",
    "wof:placetype":"locality"
},
  "geometry": {"coordinates":[-16.48838,28.18145],"type":"Point"}
}