{
  "type": "Feature",
  "properties": {
    "gn:country":"ES",
    "gn:fcode":"PPLA3",
    "gn:population":132,
    "iso:country":"ES",
    "name:arg_x_preferred":[
        "Cuelgamures"
    ],
    "name:ast_x_preferred":[
        "Cuelgamures"
    ],
    "name:cat_x_preferred":[
        "Cuelgamures"
    ],
    "name:ceb_x_preferred":[
        "Cuelgamures"
    ],
    "name:eng_x_preferred":[
        "Cuelgamures"
    ],
    "name:eus_x_preferred":[
        "Cuelgamures"
    ],
    "name:fra_x_preferred":[
        "Cuelgamures"
    ],
    "name:haw_x_preferred":[
        "Cuelgamures"
    ],
    "name:hun_x_preferred":[
        "Cuelgamures"
    ],
    "name:ile_x_preferred":[
        "Cuelgamures"
    ],
    "name:ina_x_preferred":[
        "Cuelgamures"
    ],
    "name:ita_x_preferred":[
        "Cuelgamures"
    ],
    "name:msa_x_preferred":[
        "Cuelgamures"
    ],
    "name:nan_x_preferred":[
        "Cuelgamures"
    ],
    "name:nld_x_preferred":[
        "Cuelgamures"
    ],
    "name:oci_x_preferred":[
        "Cuelgamures"
    ],
    "name:pol_x_preferred":[
        "Cuelgamures"
    ],
    "name:por_x_preferred":[
        "Cuelgamures"
    ],
    "name:rus_x_preferred":[
        "\u041a\u0443\u044d\u043b\u044c\u0433\u0430\u043c\u0443\u0440\u0435\u0441"
    ],
    "name:spa_x_preferred":[
        "Cuelgamures"
    ],
    "name:swe_x_preferred":[
        "Cuelgamures"
    ],
    "name:ukr_x_preferred":[
        "\u041a\u0443\u0435\u043b\u044c\u0433\u0430\u043c\u0443\u0440\u0435\u0441"
    ],
    "name:uzb_x_preferred":[
        "Cuelgamures"
    ],
    "name:vie_x_preferred":[
        "Cuelgamures"
    ],
    "name:war_x_preferred":[
        "Cuelgamures"
    ],
    "name:zho_x_preferred":[
        "\u5e93\u57c3\u5c14\u52a0\u7a46\u96f7\u65af"
    ],
    "qs_pg:aaroncc":"ES",
    "qs_pg:gn_country":"ES",
    "qs_pg:gn_fcode":"PPLA3",
    "qs_pg:gn_pop":132,
    "qs_pg:name":"Cuelgamures",
    "qs_pg:name_adm0":"Espa\u00f1a",
    "qs_pg:name_adm1":"Castilla y Le\u00f3n",
    "qs_pg:photos_9r":0,
    "qs_pg:photos_sr":0,
    "qs_pg:pop_sr":1,
    "qs_pg:qs_pg_placetype":"locality",
    "qs_pg:qs_pg_placetype_gp":"Town",
    "qs_pg:woe_adm0":23424950,
    "woe:adm0_id":23424950,
    "woe:name_adm0":"Espa\u00f1a",
    "woe:name_adm1":"Castilla y Le\u00f3n",
    "woe:placetype":"Town",
    "wof:name":"Cuelgamures",
    "wof:placetype":"locality",
    "wof:population":132
},
  "geometry": {"coordinates":[-5.65769,41.30738],"type":"Point"}
}