{
  "type": "Feature",
  "properties": {
    "gn:admin1_code":"52",
    "gn:admin2_code":"HU",
    "gn:admin3_code":"22150",
    "gn:asciiname":"Coscullano",
    "gn:country_code":"ES",
    "gn:dem":666,
    "gn:feature_class":"P",
    "gn:feature_code":"PPL",
    "gn:name":"Coscullano",
    "gn:population":0,
    "gn:timezone":"Europe/Madrid",
    "iso:country":"ES",
    "wof:name":"Coscullano",
    "wof:placetype":"locality"
},
  "geometry": {"coordinates":[-0.23814,42.19297],"type":"Point"}
}