{
  "type": "Feature",
  "properties": {
    "gn:gn_country":"ES",
    "gn:gn_fcode":"PPL",
    "gn:gn_pop":16023,
    "gn:population":16023,
    "iso:country":"ES",
    "name:ara_x_preferred":[
        "\u0643\u0627\u0646\u0648\u0641\u064a\u0644\u0627\u0633"
    ],
    "name:arg_x_preferred":[
        "Canovelles"
    ],
    "name:ast_x_preferred":[
        "Canovelles"
    ],
    "name:azb_x_preferred":[
        "\u06a9\u0627\u0646\u0628\u06cc\u0633"
    ],
    "name:cat_x_preferred":[
        "Canovelles"
    ],
    "name:ceb_x_preferred":[
        "Canovelles"
    ],
    "name:deu_x_preferred":[
        "Canovelles"
    ],
    "name:eng_x_preferred":[
        "Canovelles"
    ],
    "name:eus_x_preferred":[
        "Canovelles"
    ],
    "name:fas_x_preferred":[
        "\u06a9\u0627\u0646\u0628\u06cc\u0633"
    ],
    "name:fra_x_preferred":[
        "Canovelles"
    ],
    "name:glg_x_preferred":[
        "Canovelles"
    ],
    "name:hun_x_preferred":[
        "Canovelles"
    ],
    "name:hye_x_preferred":[
        "\u053f\u0561\u0576\u0578\u057e\u0565\u056c\u0575\u0561\u057d"
    ],
    "name:ita_x_preferred":[
        "Canovelles"
    ],
    "name:kaz_x_preferred":[
        "\u041a\u0430\u043d\u043e\u0432\u0435\u043b\u0435\u0441"
    ],
    "name:lat_x_preferred":[
        "Canovelles"
    ],
    "name:lit_x_preferred":[
        "Kanovelesas"
    ],
    "name:msa_x_preferred":[
        "Canovelles"
    ],
    "name:nld_x_preferred":[
        "Canovelles"
    ],
    "name:oci_x_preferred":[
        "Canovelles"
    ],
    "name:pol_x_preferred":[
        "Canovelles"
    ],
    "name:por_x_preferred":[
        "Canovelles"
    ],
    "name:ron_x_preferred":[
        "Canovelles"
    ],
    "name:rus_x_preferred":[
        "\u041a\u0430\u043d\u043e\u0432\u0435\u043b\u0435\u0441"
    ],
    "name:spa_x_preferred":[
        "Canovellas"
    ],
    "name:swe_x_preferred":[
        "Canovelles"
    ],
    "name:ukr_x_preferred":[
        "\u041a\u0430\u043d\u0443\u0431\u0435\u043b\u044f\u0441"
    ],
    "name:unk_x_variant":[
        "Canovellas"
    ],
    "name:uzb_x_preferred":[
        "Canovelles"
    ],
    "name:war_x_preferred":[
        "Canovelles"
    ],
    "name:zho_x_preferred":[
        "\u5361\u8bfa\u97e6\u5217\u65af"
    ],
    "qs_pg:aaroncc":"ES",
    "qs_pg:gn_country":"ES",
    "qs_pg:gn_fcode":"PPL",
    "qs_pg:gn_pop":16023,
    "qs_pg:name":"Canovelles",
    "qs_pg:name_adm0":"Espa\u00f1a",
    "qs_pg:name_adm1":"Catalunya",
    "qs_pg:photos":210,
    "qs_pg:photos_1k":43,
    "qs_pg:photos_9k":1,
    "qs_pg:photos_9r":4,
    "qs_pg:photos_all":210,
    "qs_pg:photos_sr":4,
    "qs_pg:pop_sr":6,
    "qs_pg:qs_pg_placetype":"locality",
    "qs_pg:qs_pg_placetype_gp":"Town",
    "qs_pg:woe_adm0":23424950,
    "woe:adm0_id":23424950,
    "woe:name_adm0":"Espa\u00f1a",
    "woe:name_adm1":"Catalunya",
    "woe:placetype":"Town",
    "wof:name":"Canovelles",
    "wof:placetype":"locality",
    "wof:population":16023
},
  "geometry": {"coordinates":[2.28333,41.61667],"type":"Point"}
}