{
  "type": "Feature",
  "properties": {
    "gn:admin1_code":"58",
    "gn:admin2_code":"OR",
    "gn:admin3_code":"32065",
    "gn:asciiname":"Villamoure",
    "gn:country_code":"ES",
    "gn:dem":344,
    "gn:feature_class":"P",
    "gn:feature_code":"PPL",
    "gn:name":"Villamoure",
    "gn:population":0,
    "gn:timezone":"Europe/Madrid",
    "iso:country":"ES",
    "wof:name":"Villamoure",
    "wof:placetype":"locality"
},
  "geometry": {"coordinates":[-8.01573,42.38804],"type":"Point"}
}