{
  "type": "Feature",
  "properties": {
    "gn:admin1_code":"55",
    "gn:admin2_code":"SG",
    "gn:admin3_code":"40162",
    "gn:asciiname":"Castroserna de Arriba",
    "gn:country_code":"ES",
    "gn:dem":1007,
    "gn:feature_class":"P",
    "gn:feature_code":"PPL",
    "gn:name":"Castroserna de Arriba",
    "gn:population":0,
    "gn:timezone":"Europe/Madrid",
    "iso:country":"ES",
    "wof:name":"Castroserna de Arriba",
    "wof:placetype":"locality"
},
  "geometry": {"coordinates":[-3.71603,41.19029000000001],"type":"Point"}
}