{
  "type": "Feature",
  "properties": {
    "gn:gn_country":"ES",
    "gn:gn_fcode":"PPLA3",
    "gn:gn_pop":312,
    "gn:population":312,
    "iso:country":"ES",
    "name:ara_x_preferred":[
        "\u0628\u0627\u0631\u0628\u0648\u0644\u064a\u0633"
    ],
    "name:arg_x_preferred":[
        "B\u00e1rbols"
    ],
    "name:cat_x_preferred":[
        "B\u00e1rboles"
    ],
    "name:eng_x_preferred":[
        "B\u00e1rboles"
    ],
    "name:eus_x_preferred":[
        "B\u00e1rboles"
    ],
    "name:fra_x_preferred":[
        "B\u00e1rboles"
    ],
    "name:hak_x_preferred":[
        "B\u00e1rboles"
    ],
    "name:hun_x_preferred":[
        "B\u00e1rboles"
    ],
    "name:hye_x_preferred":[
        "\u0532\u0561\u0580\u0562\u0578\u056c\u0565\u057d"
    ],
    "name:ita_x_preferred":[
        "B\u00e1rboles"
    ],
    "name:kaz_x_preferred":[
        "\u0411\u0430\u0440\u0431\u043e\u043b\u0435\u0441"
    ],
    "name:msa_x_preferred":[
        "B\u00e1rboles"
    ],
    "name:nan_x_preferred":[
        "B\u00e1rboles"
    ],
    "name:nld_x_preferred":[
        "B\u00e1rboles"
    ],
    "name:oci_x_preferred":[
        "B\u00e1rboles"
    ],
    "name:pol_x_preferred":[
        "B\u00e1rboles"
    ],
    "name:por_x_preferred":[
        "B\u00e1rboles"
    ],
    "name:rus_x_preferred":[
        "\u0411\u0430\u0440\u0431\u043e\u043b\u0435\u0441"
    ],
    "name:spa_x_preferred":[
        "B\u00e1rboles"
    ],
    "name:swe_x_preferred":[
        "B\u00e1rboles"
    ],
    "name:ukr_x_preferred":[
        "\u0411\u0430\u0440\u0431\u043e\u043b\u0435\u0441"
    ],
    "name:uzb_x_preferred":[
        "B\u00e1rboles"
    ],
    "name:vie_x_preferred":[
        "B\u00e1rboles"
    ],
    "name:war_x_preferred":[
        "B\u00e1rboles"
    ],
    "name:zho_x_preferred":[
        "\u5df4\u5c14\u6c83\u83b1\u65af"
    ],
    "qs_pg:aaroncc":"ES",
    "qs_pg:gn_country":"ES",
    "qs_pg:gn_fcode":"PPLA3",
    "qs_pg:gn_pop":312,
    "qs_pg:name":"B\u00e1rboles",
    "qs_pg:name_adm0":"Espa\u00f1a",
    "qs_pg:name_adm1":"Arag\u00f3n",
    "qs_pg:photos_9k":1,
    "qs_pg:photos_9r":1,
    "qs_pg:photos_all":1,
    "qs_pg:photos_sr":0,
    "qs_pg:pop_sr":2,
    "qs_pg:qs_pg_placetype":"locality",
    "qs_pg:qs_pg_placetype_gp":"Town",
    "qs_pg:woe_adm0":23424950,
    "woe:adm0_id":23424950,
    "woe:name_adm0":"Espa\u00f1a",
    "woe:name_adm1":"Arag\u00f3n",
    "woe:placetype":"Town",
    "wof:name":"B\u00e1rboles",
    "wof:placetype":"locality",
    "wof:population":312
},
  "geometry": {"coordinates":[-1.18594,41.70898],"type":"Point"}
}