{
  "type": "Feature",
  "properties": {
    "gn:admin1_code":"55",
    "gn:admin2_code":"LE",
    "gn:admin3_code":"24209",
    "gn:asciiname":"Paradina",
    "gn:country_code":"ES",
    "gn:dem":752,
    "gn:feature_class":"P",
    "gn:feature_code":"PPL",
    "gn:name":"Paradi\u00f1a",
    "gn:population":0,
    "gn:timezone":"Europe/Madrid",
    "iso:country":"ES",
    "name:und_x_variant":[
        "Paradi\u00f1a"
    ],
    "wof:name":"Paradina",
    "wof:placetype":"locality"
},
  "geometry": {"coordinates":[-6.7546,42.67902],"type":"Point"}
}