{
  "type": "Feature",
  "properties": {
    "gn:admin1_code":"52",
    "gn:admin2_code":"HU",
    "gn:admin3_code":"22130",
    "gn:asciiname":"Binue",
    "gn:country_code":"ES",
    "gn:dem":924,
    "gn:feature_class":"P",
    "gn:feature_code":"PPL",
    "gn:name":"Binu\u00e9",
    "gn:population":0,
    "gn:timezone":"Europe/Madrid",
    "iso:country":"ES",
    "wof:name":"Binue",
    "wof:placetype":"locality"
},
  "geometry": {"coordinates":[-0.45181,42.50824],"type":"Point"}
}