{
  "type": "Feature",
  "properties": {
    "gn:admin1_code":"34",
    "gn:admin2_code":"O",
    "gn:admin3_code":"33049",
    "gn:asciiname":"Tejedal",
    "gn:country_code":"ES",
    "gn:dem":457,
    "gn:feature_class":"P",
    "gn:feature_code":"PPL",
    "gn:name":"Tejedal",
    "gn:population":0,
    "gn:timezone":"Europe/Madrid",
    "iso:country":"ES",
    "wof:name":"Tejedal",
    "wof:placetype":"locality"
},
  "geometry": {"coordinates":[-5.25213,43.30323],"type":"Point"}
}