{
  "type": "Feature",
  "properties": {
    "gn:gn_country":"ES",
    "gn:gn_fcode":"PPLA3",
    "gn:gn_pop":32,
    "gn:population":32,
    "iso:country":"ES",
    "name:ara_x_preferred":[
        "\u0633\u0648\u0631\u062f\u0627\u064a\u0644\u0648\u0633"
    ],
    "name:arg_x_preferred":[
        "Sordillos"
    ],
    "name:bul_x_preferred":[
        "\u0421\u043e\u0440\u0434\u0438\u043b\u043e\u0441"
    ],
    "name:cat_x_preferred":[
        "Sordillos"
    ],
    "name:deu_x_preferred":[
        "Sordillos"
    ],
    "name:eng_x_preferred":[
        "Sordillos"
    ],
    "name:eus_x_preferred":[
        "Sordillos"
    ],
    "name:fas_x_preferred":[
        "\u0633\u0631\u062f\u06cc\u06cc\u0633"
    ],
    "name:fra_x_preferred":[
        "Sordillos"
    ],
    "name:glg_x_preferred":[
        "Sordillos"
    ],
    "name:haw_x_preferred":[
        "Sordillos"
    ],
    "name:hun_x_preferred":[
        "Sordillos"
    ],
    "name:ina_x_preferred":[
        "Sordillos"
    ],
    "name:ita_x_preferred":[
        "Sordillos"
    ],
    "name:msa_x_preferred":[
        "Sordillos"
    ],
    "name:nan_x_preferred":[
        "Sordillos"
    ],
    "name:nld_x_preferred":[
        "Sordillos"
    ],
    "name:oci_x_preferred":[
        "Sordillos"
    ],
    "name:pol_x_preferred":[
        "Sordillos"
    ],
    "name:por_x_preferred":[
        "Sordillos"
    ],
    "name:rus_x_preferred":[
        "\u0421\u043e\u0440\u0434\u0438\u043b\u044c\u043e\u0441"
    ],
    "name:spa_x_preferred":[
        "Sordillos"
    ],
    "name:swe_x_preferred":[
        "Sordillos"
    ],
    "name:ukr_x_preferred":[
        "\u0421\u043e\u0440\u0434\u0456\u043b\u044c\u0439\u043e\u0441"
    ],
    "name:vie_x_preferred":[
        "Sordillos"
    ],
    "name:war_x_preferred":[
        "Sordillos"
    ],
    "name:zho_x_preferred":[
        "\u7d22\u5c14\u8fea\u7565\u65af"
    ],
    "qs_pg:aaroncc":"ES",
    "qs_pg:gn_country":"ES",
    "qs_pg:gn_fcode":"PPLA3",
    "qs_pg:gn_pop":32,
    "qs_pg:name":"Sordillos",
    "qs_pg:name_adm0":"Espa\u00f1a",
    "qs_pg:name_adm1":"Castilla y Le\u00f3n",
    "qs_pg:photos_9k":1,
    "qs_pg:photos_9r":1,
    "qs_pg:photos_all":1,
    "qs_pg:photos_sr":0,
    "qs_pg:pop_sr":1,
    "qs_pg:qs_pg_placetype":"locality",
    "qs_pg:qs_pg_placetype_gp":"Town",
    "qs_pg:woe_adm0":23424950,
    "woe:adm0_id":23424950,
    "woe:name_adm0":"Espa\u00f1a",
    "woe:name_adm1":"Castilla y Le\u00f3n",
    "woe:placetype":"Town",
    "wof:name":"Sordillos",
    "wof:placetype":"locality",
    "wof:population":32
},
  "geometry": {"coordinates":[-4.10726,42.46197],"type":"Point"}
}