{
  "type": "Feature",
  "properties": {
    "gn:country":"ES",
    "gn:fcode":"PPLA3",
    "gn:population":72,
    "iso:country":"ES",
    "name:ara_x_preferred":[
        "\u0628\u0631\u0627\u0628\u0648\u0633"
    ],
    "name:ast_x_preferred":[
        "Brabos"
    ],
    "name:bul_x_preferred":[
        "\u0411\u0440\u0430\u0431\u043e\u0441"
    ],
    "name:cat_x_preferred":[
        "Brabos"
    ],
    "name:ceb_x_preferred":[
        "Brabos"
    ],
    "name:eng_x_preferred":[
        "Brabos"
    ],
    "name:eus_x_preferred":[
        "Brabos"
    ],
    "name:fas_x_preferred":[
        "\u0628\u0631\u0627\u0628\u0633"
    ],
    "name:fra_x_preferred":[
        "Brabos"
    ],
    "name:hun_x_preferred":[
        "Brabos"
    ],
    "name:hye_x_preferred":[
        "\u0532\u0580\u0561\u0562\u0578\u057d"
    ],
    "name:ina_x_preferred":[
        "Brabos"
    ],
    "name:ita_x_preferred":[
        "Brabos"
    ],
    "name:kaz_x_preferred":[
        "\u0411\u0440\u0430\u0431\u043e\u0441"
    ],
    "name:mkd_x_preferred":[
        "\u0411\u0440\u0430\u0431\u043e\u0441"
    ],
    "name:msa_x_preferred":[
        "Brabos"
    ],
    "name:nld_x_preferred":[
        "Brabos"
    ],
    "name:oci_x_preferred":[
        "Brabos"
    ],
    "name:pol_x_preferred":[
        "Brabos"
    ],
    "name:por_x_preferred":[
        "Brabos"
    ],
    "name:rup_x_preferred":[
        "Brabos"
    ],
    "name:rus_x_preferred":[
        "\u0411\u0440\u0430\u0431\u043e\u0441"
    ],
    "name:spa_x_preferred":[
        "Brabos"
    ],
    "name:swe_x_preferred":[
        "Brabos"
    ],
    "name:ukr_x_preferred":[
        "\u0411\u0440\u0430\u0431\u043e\u0441"
    ],
    "name:uzb_x_preferred":[
        "Brabos"
    ],
    "name:vie_x_preferred":[
        "Brabos"
    ],
    "name:war_x_preferred":[
        "Brabos"
    ],
    "name:zho_x_preferred":[
        "\u5e03\u62c9\u6c83\u65af"
    ],
    "qs_pg:aaroncc":"ES",
    "qs_pg:gn_country":"ES",
    "qs_pg:gn_fcode":"PPLA3",
    "qs_pg:gn_pop":72,
    "qs_pg:name":"Brabos",
    "qs_pg:name_adm0":"Espa\u00f1a",
    "qs_pg:name_adm1":"Castilla y Le\u00f3n",
    "qs_pg:photos_9r":0,
    "qs_pg:photos_sr":0,
    "qs_pg:pop_sr":1,
    "qs_pg:qs_pg_placetype":"locality",
    "qs_pg:qs_pg_placetype_gp":"Town",
    "qs_pg:woe_adm0":23424950,
    "woe:adm0_id":23424950,
    "woe:name_adm0":"Espa\u00f1a",
    "woe:name_adm1":"Castilla y Le\u00f3n",
    "woe:placetype":"Town",
    "wof:name":"Brabos",
    "wof:placetype":"locality",
    "wof:population":72
},
  "geometry": {"coordinates":[-4.93934,40.77846],"type":"Point"}
}