{
  "type": "Feature",
  "properties": {
    "gn:admin1_code":"54",
    "gn:admin2_code":"CU",
    "gn:admin3_code":"16157",
    "gn:asciiname":"La Pesquera",
    "gn:country_code":"ES",
    "gn:dem":813,
    "gn:feature_class":"P",
    "gn:feature_code":"PPL",
    "gn:name":"La Pesquera",
    "gn:population":0,
    "gn:timezone":"Europe/Madrid",
    "iso:country":"ES",
    "wof:name":"La Pesquera",
    "wof:placetype":"locality"
},
  "geometry": {"coordinates":[-1.56667,39.58333],"type":"Point"}
}