{
  "type": "Feature",
  "properties": {
    "gn:admin1_code":"54",
    "gn:admin2_code":"CU",
    "gn:admin3_code":"16157",
    "gn:asciiname":"La Pesquera",
    "gn:country_code":"ES",
    "gn:dem":813,
    "gn:feature_class":"P",
    "gn:feature_code":"PPL",
    "gn:name":"La Pesquera",
    "gn:population":0,
    "gn:timezone":"Europe/Madrid",
    "iso:country":"ES",
    "name:ara_x_preferred":[
        "\u0644\u0627 \u0628\u064a\u0633\u0643\u064a\u0631\u0627"
    ],
    "name:arg_x_preferred":[
        "La Pesquera"
    ],
    "name:cat_x_preferred":[
        "La Pesquera"
    ],
    "name:epo_x_preferred":[
        "La Pesquera"
    ],
    "name:eus_x_preferred":[
        "La Pesquera"
    ],
    "name:fra_x_preferred":[
        "La Pesquera"
    ],
    "name:hun_x_preferred":[
        "La Pesquera"
    ],
    "name:ita_x_preferred":[
        "La Pesquera"
    ],
    "name:kaz_x_preferred":[
        "\u041b\u0430-\u041f\u0435\u0441\u043a\u0435\u0440\u0430"
    ],
    "name:msa_x_preferred":[
        "La Pesquera"
    ],
    "name:nld_x_preferred":[
        "La Pesquera"
    ],
    "name:oci_x_preferred":[
        "La Pesquera"
    ],
    "name:pol_x_preferred":[
        "La Pesquera"
    ],
    "name:por_x_preferred":[
        "La Pesquera"
    ],
    "name:rus_x_preferred":[
        "\u041b\u0430-\u041f\u0435\u0441\u043a\u0435\u0440\u0430"
    ],
    "name:spa_x_preferred":[
        "La Pesquera"
    ],
    "name:ukr_x_preferred":[
        "\u041b\u0430-\u041f\u0435\u0441\u043a\u0435\u0440\u0430"
    ],
    "name:vie_x_preferred":[
        "La Pesquera"
    ],
    "name:war_x_preferred":[
        "La Pesquera"
    ],
    "name:zho_x_preferred":[
        "\u62c9\u4f69\u65af\u514b\u62c9"
    ],
    "wof:name":"La Pesquera",
    "wof:placetype":"locality"
},
  "geometry": {"coordinates":[-1.56667,39.58333],"type":"Point"}
}