{
  "type": "Feature",
  "properties": {
    "gn:admin1_code":"58",
    "gn:admin2_code":"OR",
    "gn:admin3_code":"32086",
    "gn:asciiname":"Punjeiro",
    "gn:country_code":"ES",
    "gn:dem":789,
    "gn:feature_class":"P",
    "gn:feature_code":"PPL",
    "gn:name":"Punjeiro",
    "gn:population":0,
    "gn:timezone":"Europe/Madrid",
    "iso:country":"ES",
    "wof:name":"Punjeiro",
    "wof:placetype":"locality"
},
  "geometry": {"coordinates":[-7.08542,42.17649],"type":"Point"}
}