{
  "type": "Feature",
  "properties": {
    "gn:country":"ES",
    "gn:fcode":"PPLA3",
    "gn:population":303,
    "iso:country":"ES",
    "name:arg_x_preferred":[
        "Aldeanueva de Figueroa"
    ],
    "name:cat_x_preferred":[
        "Aldeanueva de Figueroa"
    ],
    "name:deu_x_preferred":[
        "Aldeanueva de Figueroa"
    ],
    "name:eng_x_preferred":[
        "Aldeanueva de Figueroa"
    ],
    "name:eus_x_preferred":[
        "Aldeanueva de Figueroa"
    ],
    "name:fra_x_preferred":[
        "Aldeanueva de Figueroa"
    ],
    "name:haw_x_preferred":[
        "Aldeanueva de Figueroa"
    ],
    "name:hun_x_preferred":[
        "Aldeanueva de Figueroa"
    ],
    "name:ina_x_preferred":[
        "Aldeanueva de Figueroa"
    ],
    "name:ita_x_preferred":[
        "Aldeanueva de Figueroa"
    ],
    "name:kaz_x_preferred":[
        "\u0410\u043b\u044c\u0434\u0435\u0430\u043d\u0443\u044d\u0432\u0430-\u0434\u0435-\u0424\u0438\u0433\u0435\u0440\u043e\u0430"
    ],
    "name:msa_x_preferred":[
        "Aldeanueva de Figueroa"
    ],
    "name:nan_x_preferred":[
        "Aldeanueva de Figueroa"
    ],
    "name:nld_x_preferred":[
        "Aldeanueva de Figueroa"
    ],
    "name:oci_x_preferred":[
        "Aldeanueva de Figueroa"
    ],
    "name:pol_x_preferred":[
        "Aldeanueva de Figueroa"
    ],
    "name:por_x_preferred":[
        "Aldeanueva de Figueroa"
    ],
    "name:rup_x_preferred":[
        "Aldeanueva de Figueroa"
    ],
    "name:rus_x_preferred":[
        "\u0410\u043b\u044c\u0434\u0435\u0430\u043d\u0443\u044d\u0432\u0430-\u0434\u0435-\u0424\u0438\u0433\u0435\u0440\u043e\u0430"
    ],
    "name:spa_x_preferred":[
        "Aldeanueva de Figueroa"
    ],
    "name:swe_x_preferred":[
        "Aldeanueva de Figueroa"
    ],
    "name:ukr_x_preferred":[
        "\u0410\u043b\u044c\u0434\u0435\u0430\u043d\u0443\u0435\u0432\u0430-\u0434\u0435-\u0424\u0456\u0433\u0435\u0440\u043e\u0430"
    ],
    "name:uzb_x_preferred":[
        "Aldeanueva de Figueroa"
    ],
    "name:vie_x_preferred":[
        "Aldeanueva de Figueroa"
    ],
    "name:war_x_preferred":[
        "Aldeanueva de Figueroa"
    ],
    "name:zho_x_preferred":[
        "\u963f\u5c14\u5fb7\u4e9a\u52aa\u57c3\u74e6\u5fb7\u83f2\u683c\u7f57\u963f"
    ],
    "qs_pg:aaroncc":"ES",
    "qs_pg:gn_country":"ES",
    "qs_pg:gn_fcode":"PPLA3",
    "qs_pg:gn_pop":303,
    "qs_pg:name":"Aldeanueva de Figueroa",
    "qs_pg:photos_9r":0,
    "qs_pg:photos_sr":0,
    "qs_pg:pop_sr":2,
    "qs_pg:qs_pg_placetype":"locality",
    "wof:name":"Aldeanueva de Figueroa",
    "wof:placetype":"locality",
    "wof:population":303
},
  "geometry": {"coordinates":[-5.52404,41.14808],"type":"Point"}
}