{
  "type": "Feature",
  "properties": {
    "gn:admin1_code":"55",
    "gn:admin2_code":"P",
    "gn:admin3_code":"34049",
    "gn:asciiname":"Boedo",
    "gn:country_code":"ES",
    "gn:dem":1104,
    "gn:feature_class":"P",
    "gn:feature_code":"PPL",
    "gn:name":"Boedo",
    "gn:population":0,
    "gn:timezone":"Europe/Madrid",
    "iso:country":"ES",
    "name:ceb_x_preferred":[
        "Boedo"
    ],
    "name:deu_x_preferred":[
        "Boedo"
    ],
    "name:epo_x_preferred":[
        "Boedo"
    ],
    "name:fra_x_preferred":[
        "Boedo"
    ],
    "name:ita_x_preferred":[
        "Boedo"
    ],
    "name:jpn_x_preferred":[
        "\u30dc\u30a8\u30c9"
    ],
    "name:lat_x_preferred":[
        "Boedo"
    ],
    "name:lit_x_preferred":[
        "Boedas"
    ],
    "name:mlg_x_preferred":[
        "Boedo"
    ],
    "name:nld_x_preferred":[
        "Boedo"
    ],
    "name:por_x_preferred":[
        "Boedo"
    ],
    "name:rus_x_preferred":[
        "\u0411\u043e\u044d\u0434\u043e"
    ],
    "name:spa_x_preferred":[
        "Boedo"
    ],
    "wof:name":"Boedo",
    "wof:placetype":"locality"
},
  "geometry": {"coordinates":[-4.57088,42.79246],"type":"Point"}
}