{
  "type": "Feature",
  "properties": {
    "gn:admin1_code":"54",
    "gn:admin2_code":"AB",
    "gn:admin3_code":"02043",
    "gn:asciiname":"Casa de Berruga",
    "gn:country_code":"ES",
    "gn:dem":861,
    "gn:feature_class":"P",
    "gn:feature_code":"PPL",
    "gn:name":"Casa de Berruga",
    "gn:population":0,
    "gn:timezone":"Europe/Madrid",
    "iso:country":"ES",
    "name:und_x_variant":[
        "Caser\u00edo Casa de Berruga",
        "Casa de Berruga"
    ],
    "wof:name":"Casa de Berruga",
    "wof:placetype":"locality"
},
  "geometry": {"coordinates":[-2.27748,38.90577],"type":"Point"}
}