{
  "type": "Feature",
  "properties": {
    "gn:admin1_code":"34",
    "gn:admin2_code":"O",
    "gn:admin3_code":"33044",
    "gn:asciiname":"Sograndio de Arriba",
    "gn:country_code":"ES",
    "gn:dem":196,
    "gn:feature_class":"P",
    "gn:feature_code":"PPL",
    "gn:name":"Sograndio de Arriba",
    "gn:population":0,
    "gn:timezone":"Europe/Madrid",
    "iso:country":"ES",
    "name:ast_x_preferred":[
        "Sograndiu"
    ],
    "name:und_x_variant":[
        "Sograndio",
        "Sograndio de Arriba"
    ],
    "wof:name":"Sograndio de Arriba",
    "wof:placetype":"locality"
},
  "geometry": {"coordinates":[-5.92926,43.35072],"type":"Point"}
}