{
  "type": "Feature",
  "properties": {
    "gn:gn_country":"ES",
    "gn:gn_fcode":"PPLA3",
    "gn:gn_pop":91,
    "gn:population":91,
    "iso:country":"ES",
    "name:arg_x_preferred":[
        "Monforte de la Sierra"
    ],
    "name:baq_x_preferred":[
        "Monforte de la Sierra"
    ],
    "name:cat_x_preferred":[
        "Monforte de la Sierra"
    ],
    "name:chi_x_preferred":[
        "\u8499\u798f\u5c14\u7279\u5fb7\u62c9\u8c22\u62c9"
    ],
    "name:dut_x_preferred":[
        "Monforte de la Sierra"
    ],
    "name:eng_x_preferred":[
        "Monforte de la Sierra"
    ],
    "name:fre_x_preferred":[
        "Monforte de la Sierra"
    ],
    "name:glg_x_preferred":[
        "Monforte de la Sierra"
    ],
    "name:hun_x_preferred":[
        "Monforte de la Sierra"
    ],
    "name:ina_x_preferred":[
        "Monforte de la Sierra"
    ],
    "name:ita_x_preferred":[
        "Monforte de la Sierra"
    ],
    "name:kaz_x_preferred":[
        "\u041c\u043e\u043d\u0444\u043e\u0440\u0442\u0435-\u0434\u0435-\u043b\u0430-\u0421\u044c\u0435\u0440\u0440\u0430"
    ],
    "name:may_x_preferred":[
        "Monforte de la Sierra"
    ],
    "name:nan_x_preferred":[
        "Monforte de la Sierra"
    ],
    "name:oci_x_preferred":[
        "Monforte de la Sierra"
    ],
    "name:pol_x_preferred":[
        "Monforte de la Sierra"
    ],
    "name:por_x_preferred":[
        "Monforte de la Sierra"
    ],
    "name:rus_x_preferred":[
        "\u041c\u043e\u043d\u0444\u043e\u0440\u0442\u0435-\u0434\u0435-\u043b\u0430-\u0421\u044c\u0435\u0440\u0440\u0430"
    ],
    "name:spa_x_preferred":[
        "Monforte de la Sierra"
    ],
    "name:swe_x_preferred":[
        "Monforte de la Sierra"
    ],
    "name:ukr_x_preferred":[
        "\u041c\u043e\u043d\u0444\u043e\u0440\u0442\u0435-\u0434\u0435-\u043b\u0430-\u0421\u044c\u0454\u0440\u0440\u0430"
    ],
    "name:uzb_x_preferred":[
        "Monforte de la Sierra"
    ],
    "name:vie_x_preferred":[
        "Monforte de la Sierra"
    ],
    "name:war_x_preferred":[
        "Monforte de la Sierra"
    ],
    "qs_pg:aaroncc":"ES",
    "qs_pg:gn_country":"ES",
    "qs_pg:gn_fcode":"PPLA3",
    "qs_pg:gn_pop":91,
    "qs_pg:name":"Monforte de la Sierra",
    "qs_pg:name_adm0":"Espa\u00f1a",
    "qs_pg:name_adm1":"Castilla y Le\u00f3n",
    "qs_pg:photos_9r":0,
    "qs_pg:photos_sr":0,
    "qs_pg:pop_sr":1,
    "qs_pg:qs_pg_placetype":"locality",
    "qs_pg:qs_pg_placetype_gp":"Town",
    "qs_pg:woe_adm0":23424950,
    "woe:adm0_id":23424950,
    "woe:name_adm0":"Espa\u00f1a",
    "woe:name_adm1":"Castilla y Le\u00f3n",
    "woe:placetype":"Town",
    "wof:name":"Monforte de la Sierra",
    "wof:placetype":"locality",
    "wof:population":91
},
  "geometry": {"coordinates":[-6.05671,40.48264],"type":"Point"}
}