{
  "type": "Feature",
  "properties": {
    "gn:admin1_code":"55",
    "gn:admin2_code":"SG",
    "gn:admin3_code":"40076",
    "gn:asciiname":"Prados",
    "gn:country_code":"ES",
    "gn:dem":1172,
    "gn:feature_class":"P",
    "gn:feature_code":"PPL",
    "gn:name":"Prados",
    "gn:population":0,
    "gn:timezone":"Europe/Madrid",
    "iso:country":"ES",
    "name:und_x_variant":[
        "Caser\u00edo Prados",
        "Prados"
    ],
    "wof:name":"Prados",
    "wof:placetype":"locality"
},
  "geometry": {"coordinates":[-4.19917,40.75535],"type":"Point"}
}