{
  "type": "Feature",
  "properties": {
    "gn:admin1_code":"34",
    "gn:admin2_code":"O",
    "gn:admin3_code":"33024",
    "gn:asciiname":"Fano",
    "gn:country_code":"ES",
    "gn:dem":158,
    "gn:feature_class":"P",
    "gn:feature_code":"PPL",
    "gn:name":"Fano",
    "gn:population":0,
    "gn:timezone":"Europe/Madrid",
    "iso:country":"ES",
    "wof:name":"Fano",
    "wof:placetype":"locality"
},
  "geometry": {"coordinates":[-5.61826,43.46507],"type":"Point"}
}