{
  "type": "Feature",
  "properties": {
    "gn:admin1_code":"34",
    "gn:admin2_code":"O",
    "gn:admin3_code":"33073",
    "gn:asciiname":"Bustiello de la Cabuerna",
    "gn:country_code":"ES",
    "gn:dem":464,
    "gn:feature_class":"P",
    "gn:feature_code":"PPL",
    "gn:name":"Bustiello de la Cabuerna",
    "gn:population":0,
    "gn:timezone":"Europe/Madrid",
    "iso:country":"ES",
    "name:und_x_variant":[
        "Bustiello",
        "Bustiello de la Cabuerna"
    ],
    "wof:name":"Bustiello de la Cabuerna",
    "wof:placetype":"locality"
},
  "geometry": {"coordinates":[-6.53154,43.34624],"type":"Point"}
}