{
  "type": "Feature",
  "properties": {
    "gn:admin1_code":"55",
    "gn:admin2_code":"SO",
    "gn:admin3_code":"42113",
    "gn:asciiname":"Fuencaliente de Medina",
    "gn:country_code":"ES",
    "gn:dem":1056,
    "gn:feature_class":"P",
    "gn:feature_code":"PPL",
    "gn:name":"Fuencaliente de Medina",
    "gn:population":0,
    "gn:timezone":"Europe/Madrid",
    "iso:country":"ES",
    "name:und_x_variant":[
        "Fuencaliente",
        "Fuencaliente de Medinaceli",
        "Fuencaliente de Medina"
    ],
    "wof:name":"Fuencaliente de Medina",
    "wof:placetype":"locality"
},
  "geometry": {"coordinates":[-2.45846,41.1359],"type":"Point"}
}