{
  "type": "Feature",
  "properties": {
    "gn:admin1_code":"58",
    "gn:admin2_code":"PO",
    "gn:admin3_code":"36014",
    "gn:asciiname":"Angudes",
    "gn:cc2":"ES",
    "gn:country_code":"ES",
    "gn:dem":259,
    "gn:feature_class":"P",
    "gn:feature_code":"PPL",
    "gn:name":"Angudes",
    "gn:population":0,
    "gn:timezone":"Europe/Madrid",
    "iso:country":"ES",
    "name:und_x_variant":[
        "San Juan"
    ],
    "wof:name":"Angudes",
    "wof:placetype":"locality"
},
  "geometry": {"coordinates":[-8.18524,42.18249],"type":"Point"}
}