{
  "type": "Feature",
  "properties": {
    "gn:admin1_code":"58",
    "gn:admin2_code":"C",
    "gn:admin3_code":"15042",
    "gn:asciiname":"Berrimes",
    "gn:country_code":"ES",
    "gn:dem":92,
    "gn:feature_class":"P",
    "gn:feature_code":"PPL",
    "gn:name":"Berrimes",
    "gn:population":0,
    "gn:timezone":"Europe/Madrid",
    "iso:country":"ES",
    "wof:name":"Berrimes",
    "wof:placetype":"locality"
},
  "geometry": {"coordinates":[-8.86811,42.7715],"type":"Point"}
}