{
  "type": "Feature",
  "properties": {
    "gn:admin1_code":"27",
    "gn:admin2_code":"LO",
    "gn:admin3_code":"26065",
    "gn:asciiname":"Castilseco",
    "gn:country_code":"ES",
    "gn:dem":570,
    "gn:feature_class":"P",
    "gn:feature_code":"PPL",
    "gn:name":"Castilseco",
    "gn:population":0,
    "gn:timezone":"Europe/Madrid",
    "iso:country":"ES",
    "wof:name":"Castilseco",
    "wof:placetype":"locality"
},
  "geometry": {"coordinates":[-2.95945,42.61063],"type":"Point"}
}