{
  "type": "Feature",
  "properties": {
    "gn:admin1_code":"34",
    "gn:admin2_code":"O",
    "gn:admin3_code":"33073",
    "gn:asciiname":"Folgueras de Cornas",
    "gn:country_code":"ES",
    "gn:dem":483,
    "gn:feature_class":"P",
    "gn:feature_code":"PPL",
    "gn:name":"Folgueras de Corn\u00e1s",
    "gn:population":0,
    "gn:timezone":"Europe/Madrid",
    "iso:country":"ES",
    "name:und_x_variant":[
        "Folgueras de Corn\u00e1s"
    ],
    "wof:name":"Folgueras de Cornas",
    "wof:placetype":"locality"
},
  "geometry": {"coordinates":[-6.537,43.37095],"type":"Point"}
}