{
  "type": "Feature",
  "properties": {
    "gn:admin1_code":"34",
    "gn:admin2_code":"O",
    "gn:admin3_code":"33010",
    "gn:asciiname":"Sandiche",
    "gn:country_code":"ES",
    "gn:dem":86,
    "gn:feature_class":"P",
    "gn:feature_code":"PPL",
    "gn:name":"Sandiche",
    "gn:population":0,
    "gn:timezone":"Europe/Madrid",
    "iso:country":"ES",
    "wof:name":"Sandiche",
    "wof:placetype":"locality"
},
  "geometry": {"coordinates":[-6.06247,43.42668],"type":"Point"}
}