{
  "type": "Feature",
  "properties": {
    "gn:admin1_code":"34",
    "gn:admin2_code":"O",
    "gn:admin3_code":"33025",
    "gn:asciiname":"Susacasa",
    "gn:country_code":"ES",
    "gn:dem":64,
    "gn:feature_class":"P",
    "gn:feature_code":"PPL",
    "gn:name":"Susacasa",
    "gn:population":0,
    "gn:timezone":"Europe/Madrid",
    "iso:country":"ES",
    "wof:name":"Susacasa",
    "wof:placetype":"locality"
},
  "geometry": {"coordinates":[-5.83288,43.60793],"type":"Point"}
}