{
  "type": "Feature",
  "properties": {
    "gn:admin1_code":"29",
    "gn:admin2_code":"M",
    "gn:admin3_code":"28135",
    "gn:asciiname":"La Hoya",
    "gn:country_code":"ES",
    "gn:dem":1200,
    "gn:feature_class":"P",
    "gn:feature_code":"PPL",
    "gn:name":"La Hoya",
    "gn:population":0,
    "gn:timezone":"Europe/Madrid",
    "iso:country":"ES",
    "name:ceb_x_preferred":[
        "La Hoya"
    ],
    "name:fra_x_preferred":[
        "La Hoya"
    ],
    "name:glg_x_preferred":[
        "La Hoya"
    ],
    "name:spa_x_preferred":[
        "La Hoya"
    ],
    "name:swe_x_preferred":[
        "La Hoya"
    ],
    "wof:name":"La Hoya",
    "wof:placetype":"locality"
},
  "geometry": {"coordinates":[-4.23429,40.57002],"type":"Point"}
}