{
  "type": "Feature",
  "properties": {
    "gn:admin1_code":"52",
    "gn:admin2_code":"HU",
    "gn:admin3_code":"22150",
    "gn:asciiname":"Castilsabas",
    "gn:country_code":"ES",
    "gn:dem":711,
    "gn:feature_class":"P",
    "gn:feature_code":"PPL",
    "gn:name":"Castilsab\u00e1s",
    "gn:population":0,
    "gn:timezone":"Europe/Madrid",
    "iso:country":"ES",
    "name:und_x_variant":[
        "Castilsab\u00e1s"
    ],
    "wof:name":"Castilsabas",
    "wof:placetype":"locality"
},
  "geometry": {"coordinates":[-0.30619,42.19639],"type":"Point"}
}