{
  "type": "Feature",
  "properties": {
    "gn:gn_country":"ES",
    "gn:gn_fcode":"PPLA3",
    "gn:gn_pop":114,
    "gn:population":114,
    "iso:country":"ES",
    "name:arg_x_preferred":[
        "Villar de Samaniego"
    ],
    "name:cat_x_preferred":[
        "Villar de Samaniego"
    ],
    "name:eng_x_preferred":[
        "Villar de Samaniego"
    ],
    "name:eus_x_preferred":[
        "Villar de Samaniego"
    ],
    "name:fra_x_preferred":[
        "Villar de Samaniego"
    ],
    "name:hun_x_preferred":[
        "Villar de Samaniego"
    ],
    "name:hye_x_preferred":[
        "\u054e\u056b\u056c\u0575\u0561\u0580 \u0564\u0565 \u054d\u0561\u0574\u0561\u0576\u0565\u0563\u0578"
    ],
    "name:ina_x_preferred":[
        "Villar de Samaniego"
    ],
    "name:ita_x_preferred":[
        "Villar de Samaniego"
    ],
    "name:kaz_x_preferred":[
        "\u0412\u0438\u043b\u044c\u044f\u0440-\u0434\u0435-\u0421\u0430\u043c\u0430\u043d\u044c\u0435\u0433\u043e"
    ],
    "name:msa_x_preferred":[
        "Villar de Samaniego"
    ],
    "name:nan_x_preferred":[
        "Villar de Samaniego"
    ],
    "name:nld_x_preferred":[
        "Villar de Samaniego"
    ],
    "name:oci_x_preferred":[
        "Villar de Samaniego"
    ],
    "name:pol_x_preferred":[
        "Villar de Samaniego"
    ],
    "name:por_x_preferred":[
        "Villar de Samaniego"
    ],
    "name:rus_x_preferred":[
        "\u0412\u0438\u043b\u044c\u044f\u0440-\u0434\u0435-\u0421\u0430\u043c\u0430\u043d\u044c\u0435\u0433\u043e"
    ],
    "name:sco_x_preferred":[
        "Villar de Samaniego"
    ],
    "name:spa_x_preferred":[
        "Villar de Samaniego"
    ],
    "name:swe_x_preferred":[
        "Villar de Samaniego"
    ],
    "name:ukr_x_preferred":[
        "\u0412\u0456\u043b\u044c\u044f\u0440-\u0434\u0435-\u0421\u0430\u043c\u0430\u043d\u044c\u0454\u0433\u043e"
    ],
    "name:uzb_x_preferred":[
        "Villar de Samaniego"
    ],
    "name:vie_x_preferred":[
        "Villar de Samaniego"
    ],
    "name:war_x_preferred":[
        "Villar de Samaniego"
    ],
    "name:zho_x_preferred":[
        "\u8428\u9a6c\u6d85\u6208\u6751"
    ],
    "qs_pg:aaroncc":"ES",
    "qs_pg:gn_country":"ES",
    "qs_pg:gn_fcode":"PPLA3",
    "qs_pg:gn_pop":114,
    "qs_pg:name":"Villar de Samaniego",
    "qs_pg:name_adm0":"Espa\u00f1a",
    "qs_pg:name_adm1":"Castilla y Le\u00f3n",
    "qs_pg:photos_9r":0,
    "qs_pg:photos_sr":0,
    "qs_pg:pop_sr":1,
    "qs_pg:qs_pg_placetype":"locality",
    "qs_pg:qs_pg_placetype_gp":"Town",
    "qs_pg:woe_adm0":23424950,
    "woe:adm0_id":23424950,
    "woe:name_adm0":"Espa\u00f1a",
    "woe:name_adm1":"Castilla y Le\u00f3n",
    "woe:placetype":"Town",
    "wof:name":"Villar de Samaniego",
    "wof:placetype":"locality",
    "wof:population":114
},
  "geometry": {"coordinates":[-6.43333,41.11667],"type":"Point"}
}