{
  "type": "Feature",
  "properties": {
    "gn:admin1_code":"51",
    "gn:admin2_code":"J",
    "gn:admin3_code":"23092",
    "gn:asciiname":"Barriga",
    "gn:country_code":"ES",
    "gn:dem":469,
    "gn:feature_class":"P",
    "gn:feature_code":"PPL",
    "gn:name":"Barriga",
    "gn:population":0,
    "gn:timezone":"Europe/Madrid",
    "iso:country":"ES",
    "name:und_x_variant":[
        "Cortijo de Barriga",
        "Caser\u00edo Barriga",
        "Barriga"
    ],
    "wof:name":"Barriga",
    "wof:placetype":"locality"
},
  "geometry": {"coordinates":[-3.17119,38.02453],"type":"Point"}
}