{
  "type": "Feature",
  "properties": {
    "gn:admin1_code":"58",
    "gn:admin2_code":"LU",
    "gn:admin3_code":"27047",
    "gn:asciiname":"Castroncelos",
    "gn:country_code":"ES",
    "gn:dem":509,
    "gn:feature_class":"P",
    "gn:feature_code":"PPL",
    "gn:name":"Castroncelos",
    "gn:population":0,
    "gn:timezone":"Europe/Madrid",
    "iso:country":"ES",
    "wof:name":"Castroncelos",
    "wof:placetype":"locality"
},
  "geometry": {"coordinates":[-7.37972,42.54271],"type":"Point"}
}