{
  "type": "Feature",
  "properties": {
    "iso:country":"ES",
    "name:spa_x_preferred":[
        "Pago del Humo"
    ],
    "qs:a0":"Espa\u00f1a",
    "qs:a1":"*C\u00e1diz",
    "qs:a1r":"0Andaluc\u00eda",
    "qs:adm0":"Espa\u00f1a",
    "qs:la_lc":"*",
    "qs:level":"locality",
    "qs:loc":"Pago del Humo",
    "qs:loc_alt":"Pago del Humo",
    "qs:pop":0,
    "qs:type":"buffered point",
    "wof:lang":[
        "spa"
    ],
    "wof:name":"Pago del Humo",
    "wof:placetype":"locality"
},
  "geometry": {"coordinates":[-6.069962,36.364241],"type":"Point"}
}