{
  "type": "Feature",
  "properties": {
    "gn:admin1_code":"60",
    "gn:admin2_code":"A",
    "gn:admin3_code":"03066",
    "gn:asciiname":"Camara",
    "gn:country_code":"ES",
    "gn:dem":594,
    "gn:feature_class":"P",
    "gn:feature_code":"PPL",
    "gn:name":"C\u00e1mara",
    "gn:population":0,
    "gn:timezone":"Europe/Madrid",
    "iso:country":"ES",
    "name:und_x_variant":[
        "Casas C\u00e1mara",
        "C\u00e1mara"
    ],
    "wof:name":"Camara",
    "wof:placetype":"locality"
},
  "geometry": {"coordinates":[-0.83864,38.50501],"type":"Point"}
}