{
  "type": "Feature",
  "properties": {
    "gn:admin1_code":"60",
    "gn:admin2_code":"A",
    "gn:admin3_code":"03066",
    "gn:asciiname":"Camara",
    "gn:country_code":"ES",
    "gn:dem":594,
    "gn:feature_class":"P",
    "gn:feature_code":"PPL",
    "gn:name":"C\u00e1mara",
    "gn:population":0,
    "gn:timezone":"Europe/Madrid",
    "iso:country":"ES",
    "name:cat_x_preferred":[
        "Cambra"
    ],
    "name:deu_x_preferred":[
        "Camara"
    ],
    "name:epo_x_preferred":[
        "Camara"
    ],
    "name:fra_x_preferred":[
        "Camara"
    ],
    "name:ita_x_preferred":[
        "Camara"
    ],
    "name:jpn_x_preferred":[
        "\u30ab\u30de\u30e9"
    ],
    "name:lit_x_preferred":[
        "Camara"
    ],
    "name:nld_x_preferred":[
        "Camara"
    ],
    "name:scn_x_preferred":[
        "C\u00e0mmara"
    ],
    "name:spa_x_preferred":[
        "C\u00e1mara"
    ],
    "name:ukr_x_preferred":[
        "\u041a\u0430\u043c\u0430\u0440\u0430"
    ],
    "name:und_x_variant":[
        "Casas C\u00e1mara",
        "C\u00e1mara"
    ],
    "name:vec_x_preferred":[
        "C\u00e0mara"
    ],
    "wof:name":"Camara",
    "wof:placetype":"locality"
},
  "geometry": {"coordinates":[-0.83864,38.50501],"type":"Point"}
}