{
  "type": "Feature",
  "properties": {
    "gn:admin1_code":"51",
    "gn:admin2_code":"GR",
    "gn:admin3_code":"18185",
    "gn:asciiname":"Ochichar",
    "gn:country_code":"ES",
    "gn:dem":990,
    "gn:feature_class":"P",
    "gn:feature_code":"PPL",
    "gn:name":"Ochichar",
    "gn:population":0,
    "gn:timezone":"Europe/Madrid",
    "iso:country":"ES",
    "name:und_x_variant":[
        "Cortijo Ochichar",
        "Ochichar"
    ],
    "wof:name":"Ochichar",
    "wof:placetype":"locality"
},
  "geometry": {"coordinates":[-3.87321,37.05482],"type":"Point"}
}