{
  "type": "Feature",
  "properties": {
    "gn:admin1_code":"55",
    "gn:admin2_code":"LE",
    "gn:admin3_code":"24061",
    "gn:asciiname":"Cabanillas",
    "gn:country_code":"ES",
    "gn:dem":908,
    "gn:feature_class":"P",
    "gn:feature_code":"PPL",
    "gn:name":"Cabanillas",
    "gn:population":0,
    "gn:timezone":"Europe/Madrid",
    "iso:country":"ES",
    "name:arg_x_preferred":[
        "Cabaniellas"
    ],
    "name:bre_x_preferred":[
        "Cabanillas"
    ],
    "name:cat_x_preferred":[
        "Cabanillas"
    ],
    "name:ceb_x_preferred":[
        "Cabanillas"
    ],
    "name:eus_x_preferred":[
        "Cabanillas"
    ],
    "name:fra_x_preferred":[
        "Cabanillas"
    ],
    "name:hun_x_preferred":[
        "Cabanillas"
    ],
    "name:ita_x_preferred":[
        "Cabanillas"
    ],
    "name:msa_x_preferred":[
        "Cabanillas"
    ],
    "name:nld_x_preferred":[
        "Cabanillas"
    ],
    "name:oci_x_preferred":[
        "Cabanillas"
    ],
    "name:pol_x_preferred":[
        "Cabanillas"
    ],
    "name:por_x_preferred":[
        "Cabanillas"
    ],
    "name:rus_x_preferred":[
        "\u041a\u0430\u0431\u0430\u043d\u0438\u043b\u044c\u044f\u0441"
    ],
    "name:sco_x_preferred":[
        "Cabanillas"
    ],
    "name:spa_x_preferred":[
        "Cabanillas"
    ],
    "name:ukr_x_preferred":[
        "\u041a\u0430\u0431\u0430\u043d\u0456\u043b\u044c\u044f\u0441"
    ],
    "name:vie_x_preferred":[
        "Cabanillas"
    ],
    "name:war_x_preferred":[
        "Cabanillas"
    ],
    "name:zho_x_preferred":[
        "\u5361\u74e6\u5c3c\u5229\u4e9a\u65af"
    ],
    "wof:name":"Cabanillas",
    "wof:placetype":"locality"
},
  "geometry": {"coordinates":[-5.63191,42.72888],"type":"Point"}
}