{
  "type": "Feature",
  "properties": {
    "gn:admin1_code":"58",
    "gn:admin2_code":"LU",
    "gn:admin3_code":"27031",
    "gn:asciiname":"Penela",
    "gn:country_code":"ES",
    "gn:dem":400,
    "gn:feature_class":"P",
    "gn:feature_code":"PPL",
    "gn:name":"Penela",
    "gn:population":0,
    "gn:timezone":"Europe/Madrid",
    "iso:country":"ES",
    "name:cat_x_preferred":[
        "Penela"
    ],
    "name:ceb_x_preferred":[
        "Penela"
    ],
    "name:deu_x_preferred":[
        "Penela"
    ],
    "name:eus_x_preferred":[
        "Penela"
    ],
    "name:fra_x_preferred":[
        "Penela"
    ],
    "name:hun_x_preferred":[
        "Penela"
    ],
    "name:ita_x_preferred":[
        "Penela"
    ],
    "name:msa_x_preferred":[
        "Perbandaran Penela"
    ],
    "name:nld_x_preferred":[
        "Penela"
    ],
    "name:pol_x_preferred":[
        "Penela"
    ],
    "name:por_x_preferred":[
        "Penela"
    ],
    "name:rus_x_preferred":[
        "\u041f\u0435\u043d\u0435\u043b\u0430"
    ],
    "name:spa_x_preferred":[
        "Penela"
    ],
    "name:tur_x_preferred":[
        "Penela"
    ],
    "name:ukr_x_preferred":[
        "\u041f\u0435\u043d\u0435\u043b\u0430"
    ],
    "name:und_x_variant":[
        "Santa Mar\u00eda",
        "Penela"
    ],
    "name:vie_x_preferred":[
        "Penela"
    ],
    "name:vol_x_preferred":[
        "Penela"
    ],
    "name:war_x_preferred":[
        "Penela"
    ],
    "name:zho_x_preferred":[
        "\u4f69\u5167\u62c9"
    ],
    "wof:name":"Penela",
    "wof:placetype":"locality"
},
  "geometry": {"coordinates":[-7.48013,42.49005],"type":"Point"}
}