{
  "type": "Feature",
  "properties": {
    "gn:admin1_code":"58",
    "gn:admin2_code":"LU",
    "gn:admin3_code":"27031",
    "gn:asciiname":"Penela",
    "gn:country_code":"ES",
    "gn:dem":400,
    "gn:feature_class":"P",
    "gn:feature_code":"PPL",
    "gn:name":"Penela",
    "gn:population":0,
    "gn:timezone":"Europe/Madrid",
    "iso:country":"ES",
    "name:und_x_variant":[
        "Santa Mar\u00eda",
        "Penela"
    ],
    "wof:name":"Penela",
    "wof:placetype":"locality"
},
  "geometry": {"coordinates":[-7.48013,42.49005],"type":"Point"}
}