{
  "type": "Feature",
  "properties": {
    "gn:gn_country":"ES",
    "gn:gn_fcode":"PPLA3",
    "gn:gn_pop":102,
    "gn:population":102,
    "iso:country":"ES",
    "name:ara_x_preferred":[
        "\u0623\u0648\u0631\u062a\u0648\u0645\u0628\u0627\u0633\u0643\u0648\u0627\u0644"
    ],
    "name:cat_x_preferred":[
        "Hurtumpascual"
    ],
    "name:eng_x_preferred":[
        "Hurtumpascual"
    ],
    "name:eus_x_preferred":[
        "Hurtumpascual"
    ],
    "name:fas_x_preferred":[
        "\u0647\u0648\u0631\u062a\u0648\u0645\u067e\u0627\u0633\u06a9\u0648\u0627\u0644"
    ],
    "name:fra_x_preferred":[
        "Hurtumpascual"
    ],
    "name:hun_x_preferred":[
        "Hurtumpascual"
    ],
    "name:ina_x_preferred":[
        "Hurtumpascual"
    ],
    "name:ita_x_preferred":[
        "Hurtumpascual"
    ],
    "name:kaz_x_preferred":[
        "\u0423\u0440\u0442\u0443\u043c\u043f\u0430\u0441\u043a\u0443\u0430\u043b\u044c"
    ],
    "name:mkd_x_preferred":[
        "\u0425\u0443\u0440\u0442\u0443\u043c\u043f\u0430\u0441\u043a\u0430\u043b"
    ],
    "name:msa_x_preferred":[
        "Hurtumpascual"
    ],
    "name:nld_x_preferred":[
        "Hurtumpascual"
    ],
    "name:oci_x_preferred":[
        "Hurtumpascual"
    ],
    "name:pol_x_preferred":[
        "Hurtumpascual"
    ],
    "name:por_x_preferred":[
        "Hurtumpascual"
    ],
    "name:rus_x_preferred":[
        "\u0423\u0440\u0442\u0443\u043c\u043f\u0430\u0441\u043a\u0443\u0430\u043b\u044c"
    ],
    "name:spa_x_preferred":[
        "Hurtumpascual"
    ],
    "name:swe_x_preferred":[
        "Hurtumpascual"
    ],
    "name:ukr_x_preferred":[
        "\u0423\u0440\u0442\u0443\u043c\u043f\u0430\u0441\u043a\u0443\u0430\u043b\u044c"
    ],
    "name:uzb_x_preferred":[
        "Hurtumpascual"
    ],
    "name:vie_x_preferred":[
        "Hurtumpascual"
    ],
    "name:war_x_preferred":[
        "Hurtumpascual"
    ],
    "name:zho_x_preferred":[
        "\u4e4c\u5c14\u901a\u5e15\u65af\u5938\u5c14"
    ],
    "qs_pg:aaroncc":"ES",
    "qs_pg:gn_country":"ES",
    "qs_pg:gn_fcode":"PPLA3",
    "qs_pg:gn_pop":102,
    "qs_pg:name":"Hurtumpascual",
    "qs_pg:name_adm0":"Espa\u00f1a",
    "qs_pg:name_adm1":"Castilla y Le\u00f3n",
    "qs_pg:photos_9r":0,
    "qs_pg:photos_sr":0,
    "qs_pg:pop_sr":1,
    "qs_pg:qs_pg_placetype":"locality",
    "qs_pg:qs_pg_placetype_gp":"Town",
    "qs_pg:woe_adm0":23424950,
    "woe:adm0_id":23424950,
    "woe:name_adm0":"Espa\u00f1a",
    "woe:name_adm1":"Castilla y Le\u00f3n",
    "woe:placetype":"Town",
    "wof:name":"Hurtumpascual",
    "wof:placetype":"locality",
    "wof:population":102
},
  "geometry": {"coordinates":[-5.11379,40.692],"type":"Point"}
}