{
  "type": "Feature",
  "properties": {
    "gn:country":"ES",
    "gn:fcode":"PPLA3",
    "gn:population":54,
    "iso:country":"ES",
    "name:arg_x_preferred":[
        "Iruelos"
    ],
    "name:ast_x_preferred":[
        "Iruelos"
    ],
    "name:bul_x_preferred":[
        "\u0418\u0440\u0443\u0435\u043b\u043e\u0441"
    ],
    "name:cat_x_preferred":[
        "Iruelos"
    ],
    "name:ceb_x_preferred":[
        "Iruelos"
    ],
    "name:che_x_preferred":[
        "\u0418\u0440\u0443\u044d\u043b\u043e\u0441"
    ],
    "name:deu_x_preferred":[
        "Iruelos"
    ],
    "name:eng_x_preferred":[
        "Iruelos"
    ],
    "name:epo_x_preferred":[
        "Iruelos"
    ],
    "name:eus_x_preferred":[
        "Iruelos"
    ],
    "name:fra_x_preferred":[
        "Iruelos"
    ],
    "name:gle_x_preferred":[
        "Iruelos"
    ],
    "name:haw_x_preferred":[
        "Iruelos"
    ],
    "name:hun_x_preferred":[
        "Iruelos"
    ],
    "name:ile_x_preferred":[
        "Iruelos"
    ],
    "name:ina_x_preferred":[
        "Iruelos"
    ],
    "name:ita_x_preferred":[
        "Iruelos"
    ],
    "name:kaz_x_preferred":[
        "\u0418\u0440\u0443\u044d\u043b\u043e\u0441"
    ],
    "name:lld_x_preferred":[
        "Iruelos"
    ],
    "name:ltz_x_preferred":[
        "Iruelos"
    ],
    "name:msa_x_preferred":[
        "Iruelos"
    ],
    "name:nan_x_preferred":[
        "Iruelos"
    ],
    "name:nld_x_preferred":[
        "Iruelos"
    ],
    "name:nob_x_preferred":[
        "Iruelos"
    ],
    "name:oci_x_preferred":[
        "Iruelos"
    ],
    "name:pol_x_preferred":[
        "Iruelos"
    ],
    "name:por_x_preferred":[
        "Iruelos"
    ],
    "name:rus_x_preferred":[
        "\u0418\u0440\u0443\u044d\u043b\u043e\u0441"
    ],
    "name:spa_x_preferred":[
        "Iruelos"
    ],
    "name:swe_x_preferred":[
        "Iruelos"
    ],
    "name:tat_x_preferred":[
        "\u0418\u0440\u0443\u044d\u043b\u043e\u0441"
    ],
    "name:ukr_x_preferred":[
        "\u0406\u0440\u0443\u0435\u043b\u043e\u0441"
    ],
    "name:uzb_x_preferred":[
        "Iruelos"
    ],
    "name:vec_x_preferred":[
        "Iruelos"
    ],
    "name:vie_x_preferred":[
        "Iruelos"
    ],
    "name:war_x_preferred":[
        "Iruelos"
    ],
    "name:zho_x_preferred":[
        "\u4f0a\u9c81\u57c3\u6d1b\u65af"
    ],
    "qs_pg:aaroncc":"ES",
    "qs_pg:gn_country":"ES",
    "qs_pg:gn_fcode":"PPLA3",
    "qs_pg:gn_pop":54,
    "qs_pg:name":"Iruelos",
    "qs_pg:name_adm0":"Espa\u00f1a",
    "qs_pg:name_adm1":"Castilla y Le\u00f3n",
    "qs_pg:photos_9r":0,
    "qs_pg:photos_sr":0,
    "qs_pg:pop_sr":1,
    "qs_pg:qs_pg_placetype":"locality",
    "qs_pg:qs_pg_placetype_gp":"Town",
    "qs_pg:woe_adm0":23424950,
    "woe:adm0_id":23424950,
    "woe:name_adm0":"Espa\u00f1a",
    "woe:name_adm1":"Castilla y Le\u00f3n",
    "woe:placetype":"Town",
    "wof:name":"Iruelos",
    "wof:placetype":"locality",
    "wof:population":54
},
  "geometry": {"coordinates":[-6.32808,41.14135],"type":"Point"}
}