{
  "type": "Feature",
  "properties": {
    "gn:country":"ES",
    "gn:fcode":"PPL",
    "gn:population":0,
    "iso:country":"ES",
    "name:cat_x_preferred":[
        "Lilla"
    ],
    "name:deu_x_preferred":[
        "Lilla"
    ],
    "name:eng_x_preferred":[
        "Lilla"
    ],
    "name:fra_x_preferred":[
        "Lilla"
    ],
    "name:ita_x_preferred":[
        "Lilla"
    ],
    "name:nld_x_preferred":[
        "Lilla"
    ],
    "name:spa_x_preferred":[
        "Lilla"
    ],
    "qs_pg:aaroncc":"ES",
    "qs_pg:gn_country":"ES",
    "qs_pg:gn_fcode":"PPL",
    "qs_pg:gn_pop":0,
    "qs_pg:name":"Lilla",
    "qs_pg:name_adm0":"Espa\u00f1a",
    "qs_pg:name_adm1":"Catalunya",
    "qs_pg:photos":34,
    "qs_pg:photos_1k":7,
    "qs_pg:photos_9k":1,
    "qs_pg:photos_9r":2,
    "qs_pg:photos_all":34,
    "qs_pg:photos_sr":2,
    "qs_pg:pop_sr":0,
    "qs_pg:qs_pg_placetype":"locality",
    "qs_pg:qs_pg_placetype_gp":"Town",
    "qs_pg:woe_adm0":23424950,
    "woe:adm0_id":23424950,
    "woe:name_adm0":"Espa\u00f1a",
    "woe:name_adm1":"Catalunya",
    "woe:placetype":"Town",
    "wof:name":"Lilla",
    "wof:placetype":"locality"
},
  "geometry": {"coordinates":[1.2124,41.3485],"type":"Point"}
}