{
  "type": "Feature",
  "properties": {
    "gn:admin1_code":"54",
    "gn:admin2_code":"CU",
    "gn:admin3_code":"16239",
    "gn:asciiname":"Gregoriete",
    "gn:cc2":"ES",
    "gn:country_code":"ES",
    "gn:dem":1323,
    "gn:feature_class":"P",
    "gn:feature_code":"PPL",
    "gn:name":"Gregoriete",
    "gn:population":0,
    "gn:timezone":"Europe/Madrid",
    "iso:country":"ES",
    "name:und_x_variant":[
        "Barrio Gregoriete",
        "Gregorete",
        "Gregoriete"
    ],
    "wof:name":"Gregoriete",
    "wof:placetype":"locality"
},
  "geometry": {"coordinates":[-1.95,40.45],"type":"Point"}
}