{
  "type": "Feature",
  "properties": {
    "gn:admin1_code":"55",
    "gn:admin2_code":"SO",
    "gn:admin3_code":"42019",
    "gn:asciiname":"San Andres de Soria",
    "gn:country_code":"ES",
    "gn:dem":1154,
    "gn:feature_class":"P",
    "gn:feature_code":"PPL",
    "gn:name":"San Andr\u00e9s de Soria",
    "gn:population":0,
    "gn:timezone":"Europe/Madrid",
    "iso:country":"ES",
    "name:und_x_variant":[
        "San Andr\u00e9s de Soria"
    ],
    "wof:name":"San Andres de Soria",
    "wof:placetype":"locality"
},
  "geometry": {"coordinates":[-2.47934,41.9457],"type":"Point"}
}