{
  "type": "Feature",
  "properties": {
    "gn:admin1_code":"51",
    "gn:admin2_code":"SE",
    "gn:admin3_code":"41049",
    "gn:asciiname":"El Serrano",
    "gn:country_code":"ES",
    "gn:dem":263,
    "gn:feature_class":"P",
    "gn:feature_code":"PPL",
    "gn:name":"El Serrano",
    "gn:population":0,
    "gn:timezone":"Europe/Madrid",
    "iso:country":"ES",
    "wof:name":"El Serrano",
    "wof:placetype":"locality"
},
  "geometry": {"coordinates":[-6.07536,37.66821],"type":"Point"}
}