{
  "type": "Feature",
  "properties": {
    "gn:admin1_code":"34",
    "gn:admin2_code":"O",
    "gn:admin3_code":"33018",
    "gn:asciiname":"Sequeiro",
    "gn:country_code":"ES",
    "gn:dem":217,
    "gn:feature_class":"P",
    "gn:feature_code":"PPL",
    "gn:name":"Sequeiro",
    "gn:population":0,
    "gn:timezone":"Europe/Madrid",
    "iso:country":"ES",
    "wof:name":"Sequeiro",
    "wof:placetype":"locality"
},
  "geometry": {"coordinates":[-6.74781,43.48024],"type":"Point"}
}