{
  "type": "Feature",
  "properties": {
    "gn:admin1_code":"51",
    "gn:admin2_code":"H",
    "gn:admin3_code":"21018",
    "gn:asciiname":"La Poderosa",
    "gn:country_code":"ES",
    "gn:dem":334,
    "gn:feature_class":"P",
    "gn:feature_code":"PPL",
    "gn:name":"La Poderosa",
    "gn:population":0,
    "gn:timezone":"Europe/Madrid",
    "iso:country":"ES",
    "wof:name":"La Poderosa",
    "wof:placetype":"locality"
},
  "geometry": {"coordinates":[-6.66017,37.74800000000001],"type":"Point"}
}