{
  "type": "Feature",
  "properties": {
    "gn:admin1_code":"55",
    "gn:admin2_code":"ZA",
    "gn:admin3_code":"49062",
    "gn:asciiname":"Faramontanos de la Sierra",
    "gn:country_code":"ES",
    "gn:dem":1041,
    "gn:feature_class":"P",
    "gn:feature_code":"PPL",
    "gn:name":"Faramontanos de la Sierra",
    "gn:population":0,
    "gn:timezone":"Europe/Madrid",
    "iso:country":"ES",
    "wof:name":"Faramontanos de la Sierra",
    "wof:placetype":"locality"
},
  "geometry": {"coordinates":[-6.39425,42.13039000000001],"type":"Point"}
}