{
  "type": "Feature",
  "properties": {
    "gn:admin1_code":"31",
    "gn:admin2_code":"MU",
    "gn:admin3_code":"30015",
    "gn:asciiname":"Pinilla",
    "gn:country_code":"ES",
    "gn:dem":766,
    "gn:feature_class":"P",
    "gn:feature_code":"PPL",
    "gn:name":"Pinilla",
    "gn:population":0,
    "gn:timezone":"Europe/Madrid",
    "iso:country":"ES",
    "name:deu_x_preferred":[
        "Pinilla"
    ],
    "name:fra_x_preferred":[
        "Pinilla"
    ],
    "name:ita_x_preferred":[
        "Pinilla"
    ],
    "name:lit_x_preferred":[
        "Pinilla"
    ],
    "name:rus_x_preferred":[
        "\u041f\u0438\u043d\u0438\u043b\u044c\u044f"
    ],
    "name:spa_x_preferred":[
        "Pinilla"
    ],
    "name:und_x_variant":[
        "Caser\u00edo Pinilla",
        "Pinilla"
    ],
    "wof:name":"Pinilla",
    "wof:placetype":"locality"
},
  "geometry": {"coordinates":[-1.91737,38.02006],"type":"Point"}
}