{
  "type": "Feature",
  "properties": {
    "gn:gn_country":"ES",
    "gn:gn_fcode":"PPL",
    "gn:gn_pop":0,
    "iso:country":"ES",
    "name:ara_x_preferred":[
        "\u0633\u0627\u0646\u062a\u0627 \u0645\u0627\u0631\u064a\u0627 \u062f\u064a \u0628\u064a\u0632\u0648\u0631\u0627"
    ],
    "name:arg_x_preferred":[
        "Santa Maria de Besora"
    ],
    "name:azb_x_preferred":[
        "\u0633\u0627\u0646\u062a\u0627 \u0645\u0627\u0631\u06cc\u0627 \u062f \u0628\u0633\u0631\u0627"
    ],
    "name:bre_x_preferred":[
        "Santa Maria de Besora"
    ],
    "name:cat_x_preferred":[
        "Santa Maria de Besora"
    ],
    "name:deu_x_preferred":[
        "Santa Maria de Besora"
    ],
    "name:eng_x_preferred":[
        "Santa Maria de Besora"
    ],
    "name:eus_x_preferred":[
        "Santa Maria de Besora"
    ],
    "name:fas_x_preferred":[
        "\u0633\u0627\u0646\u062a\u0627 \u0645\u0627\u0631\u06cc\u0627 \u062f \u0628\u0633\u0631\u0627"
    ],
    "name:fra_x_preferred":[
        "Santa Maria de Besora"
    ],
    "name:gle_x_preferred":[
        "Santa Maria de Besora"
    ],
    "name:hun_x_preferred":[
        "Santa Maria de Besora"
    ],
    "name:hye_x_preferred":[
        "\u054d\u0561\u0576\u057f\u0561 \u0544\u0561\u0580\u056b\u0561 \u0564\u0565 \u0532\u0565\u057d\u0578\u0580\u0561"
    ],
    "name:ita_x_preferred":[
        "Santa Maria de Besora"
    ],
    "name:lat_x_preferred":[
        "Santa Maria de Besora"
    ],
    "name:nld_x_preferred":[
        "Santa Maria de Besora"
    ],
    "name:oci_x_preferred":[
        "Santa Maria de Besora"
    ],
    "name:pol_x_preferred":[
        "Santa Maria de Besora"
    ],
    "name:por_x_preferred":[
        "Santa Maria de Besora"
    ],
    "name:rus_x_preferred":[
        "\u0421\u0430\u043d\u0442\u0430-\u041c\u0430\u0440\u0438\u044f-\u0434\u0435-\u0411\u0435\u0441\u043e\u0440\u0430"
    ],
    "name:spa_x_preferred":[
        "Santa Mar\u00eda de Besora"
    ],
    "name:sqi_x_preferred":[
        "Santa Maria de Besora"
    ],
    "name:swe_x_preferred":[
        "Santa Maria de Besora"
    ],
    "name:uzb_x_preferred":[
        "Santa Maria de Besora"
    ],
    "name:war_x_preferred":[
        "Santa Maria de Besora"
    ],
    "name:zho_x_preferred":[
        "\u5723\u9a6c\u91cc\u4e9a\u5fb7\u97e6\u7d22\u62c9"
    ],
    "qs_pg:aaroncc":"ES",
    "qs_pg:gn_country":"ES",
    "qs_pg:gn_fcode":"PPL",
    "qs_pg:gn_pop":0,
    "qs_pg:name":"Santa Maria de Besora",
    "qs_pg:name_adm0":"Espa\u00f1a",
    "qs_pg:name_adm1":"Catalunya",
    "qs_pg:photos":178,
    "qs_pg:photos_1k":36,
    "qs_pg:photos_9k":1,
    "qs_pg:photos_9r":4,
    "qs_pg:photos_all":178,
    "qs_pg:photos_sr":4,
    "qs_pg:pop_sr":0,
    "qs_pg:qs_pg_placetype":"locality",
    "qs_pg:qs_pg_placetype_gp":"Town",
    "qs_pg:woe_adm0":23424950,
    "woe:adm0_id":23424950,
    "woe:name_adm0":"Espa\u00f1a",
    "woe:name_adm1":"Catalunya",
    "woe:placetype":"Town",
    "wof:name":"Santa Maria de Besora",
    "wof:placetype":"locality"
},
  "geometry": {"coordinates":[2.25848,42.12705],"type":"Point"}
}