{
  "type": "Feature",
  "properties": {
    "gn:gn_country":"ES",
    "gn:gn_fcode":"PPLA3",
    "gn:gn_pop":168,
    "gn:population":168,
    "iso:country":"ES",
    "name:ara_x_preferred":[
        "\u062a\u0648\u0628\u0627\u064a\u0644\u0627 \u062f\u064a\u0644 \u0644\u0627\u063a\u0648"
    ],
    "name:arg_x_preferred":[
        "Tubilla del Lago"
    ],
    "name:cat_x_preferred":[
        "Tubilla del Lago"
    ],
    "name:deu_x_preferred":[
        "Tubilla del Lago"
    ],
    "name:eng_x_preferred":[
        "Tubilla del Lago"
    ],
    "name:epo_x_preferred":[
        "Tubilla del Lago"
    ],
    "name:eus_x_preferred":[
        "Tubilla del Lago"
    ],
    "name:fas_x_preferred":[
        "\u062a\u0648\u0628\u06cc\u06cc\u0627 \u062f\u0644 \u0644\u0627\u06af\u0648"
    ],
    "name:fra_x_preferred":[
        "Tubilla del Lago"
    ],
    "name:glg_x_preferred":[
        "Tubilla del Lago"
    ],
    "name:haw_x_preferred":[
        "Tubilla del Lago"
    ],
    "name:hun_x_preferred":[
        "Tubilla del Lago"
    ],
    "name:ina_x_preferred":[
        "Tubilla del Lago"
    ],
    "name:ita_x_preferred":[
        "Tubilla del Lago"
    ],
    "name:msa_x_preferred":[
        "Tubilla del Lago"
    ],
    "name:nan_x_preferred":[
        "Tubilla del Lago"
    ],
    "name:nld_x_preferred":[
        "Tubilla del Lago"
    ],
    "name:oci_x_preferred":[
        "Tubilla del Lago"
    ],
    "name:pol_x_preferred":[
        "Tubilla del Lago"
    ],
    "name:por_x_preferred":[
        "Tubilla del Lago"
    ],
    "name:rus_x_preferred":[
        "\u0422\u0443\u0431\u0438\u043b\u044c\u044f-\u0434\u0435\u043b\u044c-\u041b\u0430\u0433\u043e"
    ],
    "name:spa_x_preferred":[
        "Tubilla del Lago"
    ],
    "name:swe_x_preferred":[
        "Tubilla del Lago"
    ],
    "name:ukr_x_preferred":[
        "\u0422\u0443\u0431\u0456\u043b\u044c\u044f-\u0434\u0435\u043b\u044c-\u041b\u0430\u0433\u043e"
    ],
    "name:urd_x_preferred":[
        "\u062a\u0648\u0628\u06cc\u0644\u0627 \u062f\u0644 \u0644\u0627\u06af\u0648"
    ],
    "name:uzb_x_preferred":[
        "Tubilla del Lago"
    ],
    "name:vie_x_preferred":[
        "Tubilla del Lago"
    ],
    "name:war_x_preferred":[
        "Tubilla del Lago"
    ],
    "name:zho_x_preferred":[
        "\u56fe\u7ef4\u5229\u4e9a\u5fb7\u5229\u4e9a\u6208"
    ],
    "qs_pg:aaroncc":"ES",
    "qs_pg:gn_country":"ES",
    "qs_pg:gn_fcode":"PPLA3",
    "qs_pg:gn_pop":168,
    "qs_pg:name":"Tubilla del Lago",
    "qs_pg:name_adm0":"Espa\u00f1a",
    "qs_pg:name_adm1":"Castilla y Le\u00f3n",
    "qs_pg:photos":114,
    "qs_pg:photos_1k":23,
    "qs_pg:photos_9k":1,
    "qs_pg:photos_9r":3,
    "qs_pg:photos_all":114,
    "qs_pg:photos_sr":3,
    "qs_pg:pop_sr":1,
    "qs_pg:qs_pg_placetype":"locality",
    "qs_pg:qs_pg_placetype_gp":"Town",
    "qs_pg:woe_adm0":23424950,
    "woe:adm0_id":23424950,
    "woe:name_adm0":"Espa\u00f1a",
    "woe:name_adm1":"Castilla y Le\u00f3n",
    "woe:placetype":"Town",
    "wof:name":"Tubilla del Lago",
    "wof:placetype":"locality",
    "wof:population":168
},
  "geometry": {"coordinates":[-3.58626,41.80154],"type":"Point"}
}