{
  "type": "Feature",
  "properties": {
    "gn:admin1_code":"34",
    "gn:admin2_code":"O",
    "gn:admin3_code":"33001",
    "gn:asciiname":"Villasonte",
    "gn:country_code":"ES",
    "gn:dem":537,
    "gn:feature_class":"P",
    "gn:feature_code":"PPL",
    "gn:name":"Villasonte",
    "gn:population":0,
    "gn:timezone":"Europe/Madrid",
    "iso:country":"ES",
    "wof:name":"Villasonte",
    "wof:placetype":"locality"
},
  "geometry": {"coordinates":[-6.76467,43.19122],"type":"Point"}
}