{
  "type": "Feature",
  "properties": {
    "gn:admin1_code":"54",
    "gn:admin2_code":"CU",
    "gn:admin3_code":"16272",
    "gn:asciiname":"Villarejo del Espartal",
    "gn:country_code":"ES",
    "gn:dem":902,
    "gn:feature_class":"P",
    "gn:feature_code":"PPL",
    "gn:name":"Villarejo del Espartal",
    "gn:population":0,
    "gn:timezone":"Europe/Madrid",
    "iso:country":"ES",
    "wof:name":"Villarejo del Espartal",
    "wof:placetype":"locality"
},
  "geometry": {"coordinates":[-2.4624,40.25795],"type":"Point"}
}