{
  "type": "Feature",
  "properties": {
    "gn:admin1_code":"52",
    "gn:admin2_code":"HU",
    "gn:admin3_code":"22090",
    "gn:asciiname":"Asque",
    "gn:country_code":"ES",
    "gn:dem":621,
    "gn:feature_class":"P",
    "gn:feature_code":"PPL",
    "gn:name":"Asque",
    "gn:population":0,
    "gn:timezone":"Europe/Madrid",
    "iso:country":"ES",
    "wof:name":"Asque",
    "wof:placetype":"locality"
},
  "geometry": {"coordinates":[0.05275,42.1753],"type":"Point"}
}