{
  "type": "Feature",
  "properties": {
    "gn:admin1_code":"60",
    "gn:admin2_code":"A",
    "gn:admin3_code":"03014",
    "gn:asciiname":"Tangel",
    "gn:country_code":"ES",
    "gn:dem":75,
    "gn:feature_class":"P",
    "gn:feature_code":"PPL",
    "gn:name":"T\u00e1ngel",
    "gn:population":0,
    "gn:timezone":"Europe/Madrid",
    "iso:country":"ES",
    "name:und_x_variant":[
        "Caser\u00edo T\u00e1ngel",
        "T\u00e1ngel"
    ],
    "wof:name":"Tangel",
    "wof:placetype":"locality"
},
  "geometry": {"coordinates":[-0.47195,38.40791],"type":"Point"}
}