{
  "type": "Feature",
  "properties": {
    "gn:country":"ES",
    "iso:country":"ES",
    "qs_pg:aaroncc":"ES",
    "qs_pg:gn_country":"ES",
    "qs_pg:name":"El Roc de Sant Gaiet\u00e0",
    "qs_pg:name_adm0":"Espa\u00f1a",
    "qs_pg:name_adm1":"Catalunya",
    "qs_pg:photos":673,
    "qs_pg:photos_1k":136,
    "qs_pg:photos_9k":3,
    "qs_pg:photos_9r":5,
    "qs_pg:photos_all":673,
    "qs_pg:photos_sr":8,
    "qs_pg:pop_sr":0,
    "qs_pg:qs_pg_placetype":"locality",
    "qs_pg:qs_pg_placetype_gp":"Town",
    "qs_pg:woe_adm0":23424950,
    "woe:adm0_id":23424950,
    "woe:name_adm0":"Espa\u00f1a",
    "woe:name_adm1":"Catalunya",
    "woe:placetype":"Town",
    "wof:name":"El Roc de Sant Gaiet\u00e0",
    "wof:placetype":"locality"
},
  "geometry": {"coordinates":[1.480536,41.169639],"type":"Point"}
}