{
  "type": "Feature",
  "properties": {
    "gn:admin1_code":"34",
    "gn:admin2_code":"O",
    "gn:admin3_code":"33002",
    "gn:asciiname":"Carrocera",
    "gn:country_code":"ES",
    "gn:dem":483,
    "gn:feature_class":"P",
    "gn:feature_code":"PPL",
    "gn:name":"Carrocera",
    "gn:population":0,
    "gn:timezone":"Europe/Madrid",
    "iso:country":"ES",
    "name:und_x_variant":[
        "Carroceta",
        "Carrocera"
    ],
    "wof:name":"Carrocera",
    "wof:placetype":"locality"
},
  "geometry": {"coordinates":[-5.68526,43.16147],"type":"Point"}
}