{
  "type": "Feature",
  "properties": {
    "gn:admin1_code":"34",
    "gn:admin2_code":"O",
    "gn:admin3_code":"33002",
    "gn:asciiname":"Carrocera",
    "gn:country_code":"ES",
    "gn:dem":483,
    "gn:feature_class":"P",
    "gn:feature_code":"PPL",
    "gn:name":"Carrocera",
    "gn:population":0,
    "gn:timezone":"Europe/Madrid",
    "iso:country":"ES",
    "name:arg_x_preferred":[
        "Carrocera"
    ],
    "name:azb_x_preferred":[
        "\u06a9\u0627\u0631\u0648\u0633\u0631\u0627"
    ],
    "name:cat_x_preferred":[
        "Carrocera"
    ],
    "name:ceb_x_preferred":[
        "Carrocera"
    ],
    "name:eus_x_preferred":[
        "Carrocera"
    ],
    "name:fas_x_preferred":[
        "\u06a9\u0627\u0631\u0648\u0633\u0631\u0627"
    ],
    "name:fra_x_preferred":[
        "Carrocera"
    ],
    "name:glg_x_preferred":[
        "Carrocera"
    ],
    "name:haw_x_preferred":[
        "Carrocera"
    ],
    "name:hun_x_preferred":[
        "Carrocera"
    ],
    "name:hye_x_preferred":[
        "\u053f\u0561\u057c\u0578\u057d\u0565\u0580\u0561"
    ],
    "name:ido_x_preferred":[
        "Carrocera"
    ],
    "name:ina_x_preferred":[
        "Carrocera"
    ],
    "name:ita_x_preferred":[
        "Carrocera"
    ],
    "name:msa_x_preferred":[
        "Carrocera"
    ],
    "name:nld_x_preferred":[
        "Carrocera"
    ],
    "name:oci_x_preferred":[
        "Carrocera"
    ],
    "name:pol_x_preferred":[
        "Carrocera"
    ],
    "name:por_x_preferred":[
        "Carrocera"
    ],
    "name:rus_x_preferred":[
        "\u041a\u0430\u0440\u0440\u043e\u0441\u0435\u0440\u0430"
    ],
    "name:spa_x_preferred":[
        "Carrocera"
    ],
    "name:swe_x_preferred":[
        "Carrocera"
    ],
    "name:tpi_x_preferred":[
        "Carrocera"
    ],
    "name:ukr_x_preferred":[
        "\u041a\u0430\u0440\u0440\u043e\u0441\u0435\u0440\u0430"
    ],
    "name:und_x_variant":[
        "Carroceta",
        "Carrocera"
    ],
    "name:vie_x_preferred":[
        "Carrocera"
    ],
    "name:war_x_preferred":[
        "Carrocera"
    ],
    "name:zho_x_preferred":[
        "\u5361\u7f57\u585e\u62c9"
    ],
    "wof:name":"Carrocera",
    "wof:placetype":"locality"
},
  "geometry": {"coordinates":[-5.68526,43.16147],"type":"Point"}
}