{
  "type": "Feature",
  "properties": {
    "gn:admin1_code":"55",
    "gn:admin2_code":"ZA",
    "gn:admin3_code":"49152",
    "gn:asciiname":"Amor",
    "gn:country_code":"ES",
    "gn:dem":728,
    "gn:feature_class":"P",
    "gn:feature_code":"PPL",
    "gn:name":"Amor",
    "gn:population":0,
    "gn:timezone":"Europe/Madrid",
    "iso:country":"ES",
    "name:ara_x_preferred":[
        "\u063a\u0631\u0627\u0645"
    ],
    "name:cat_x_preferred":[
        "Amor"
    ],
    "name:ceb_x_preferred":[
        "Amor"
    ],
    "name:deu_x_preferred":[
        "Amor"
    ],
    "name:epo_x_preferred":[
        "Amoro"
    ],
    "name:est_x_preferred":[
        "Amor"
    ],
    "name:eus_x_preferred":[
        "Amor"
    ],
    "name:fra_x_preferred":[
        "Amor"
    ],
    "name:ita_x_preferred":[
        "Amor"
    ],
    "name:jpn_x_preferred":[
        "\u30a2\u30e2\u30eb"
    ],
    "name:kor_x_preferred":[
        "\uc544\ubaa8\ub974"
    ],
    "name:lat_x_preferred":[
        "Amor"
    ],
    "name:nld_x_preferred":[
        "Amor"
    ],
    "name:pol_x_preferred":[
        "Amor"
    ],
    "name:por_x_preferred":[
        "Amor"
    ],
    "name:ron_x_preferred":[
        "Amor"
    ],
    "name:rus_x_preferred":[
        "\u0410\u043c\u043e\u0440"
    ],
    "name:slk_x_preferred":[
        "Amor"
    ],
    "name:slv_x_preferred":[
        "Amor"
    ],
    "name:spa_x_preferred":[
        "Amor"
    ],
    "name:swe_x_preferred":[
        "Amor"
    ],
    "name:und_x_variant":[
        "Casas de Amor"
    ],
    "wof:name":"Amor",
    "wof:placetype":"locality"
},
  "geometry": {"coordinates":[-5.82754,41.37853],"type":"Point"}
}