{
  "type": "Feature",
  "properties": {
    "gn:admin1_code":"55",
    "gn:admin2_code":"ZA",
    "gn:admin3_code":"49152",
    "gn:asciiname":"Amor",
    "gn:country_code":"ES",
    "gn:dem":728,
    "gn:feature_class":"P",
    "gn:feature_code":"PPL",
    "gn:name":"Amor",
    "gn:population":0,
    "gn:timezone":"Europe/Madrid",
    "iso:country":"ES",
    "name:und_x_variant":[
        "Casas de Amor",
        "Amor"
    ],
    "wof:name":"Amor",
    "wof:placetype":"locality"
},
  "geometry": {"coordinates":[-5.82754,41.37853],"type":"Point"}
}