{
  "type": "Feature",
  "properties": {
    "gn:admin1_code":"51",
    "gn:admin2_code":"CO",
    "gn:admin3_code":"14042",
    "gn:asciiname":"Jarata",
    "gn:country_code":"ES",
    "gn:dem":256,
    "gn:feature_class":"P",
    "gn:feature_code":"PPL",
    "gn:name":"Jarata",
    "gn:population":0,
    "gn:timezone":"Europe/Madrid",
    "iso:country":"ES",
    "name:und_x_variant":[
        "Caser\u00edos de Jarata",
        "Jarata"
    ],
    "wof:name":"Jarata",
    "wof:placetype":"locality"
},
  "geometry": {"coordinates":[-4.69038,37.55581],"type":"Point"}
}