{
  "type": "Feature",
  "properties": {
    "gn:admin1_code":"58",
    "gn:admin2_code":"C",
    "gn:admin3_code":"15043",
    "gn:asciiname":"Cerqueda",
    "gn:country_code":"ES",
    "gn:dem":88,
    "gn:feature_class":"P",
    "gn:feature_code":"PPL",
    "gn:name":"Cerqueda",
    "gn:population":0,
    "gn:timezone":"Europe/Madrid",
    "iso:country":"ES",
    "wof:name":"Cerqueda",
    "wof:placetype":"locality"
},
  "geometry": {"coordinates":[-8.80954,43.28334],"type":"Point"}
}