{
  "type": "Feature",
  "properties": {
    "gn:admin1_code":"56",
    "gn:admin2_code":"GI",
    "gn:admin3_code":"17012",
    "gn:asciiname":"el Mas Pau",
    "gn:country_code":"ES",
    "gn:dem":72,
    "gn:feature_class":"P",
    "gn:feature_code":"PPL",
    "gn:name":"el Mas Pau",
    "gn:population":0,
    "gn:timezone":"Europe/Madrid",
    "iso:country":"ES",
    "wof:name":"el Mas Pau",
    "wof:placetype":"locality"
},
  "geometry": {"coordinates":[2.90627,42.23903],"type":"Point"}
}