{
  "type": "Feature",
  "properties": {
    "gn:admin1_code":"34",
    "gn:admin2_code":"O",
    "gn:admin3_code":"33028",
    "gn:asciiname":"El Bao",
    "gn:country_code":"ES",
    "gn:dem":785,
    "gn:feature_class":"P",
    "gn:feature_code":"PPL",
    "gn:name":"El Bao",
    "gn:population":16,
    "gn:timezone":"Europe/Madrid",
    "iso:country":"ES",
    "wof:name":"El Bao",
    "wof:placetype":"locality",
    "wof:population":16
},
  "geometry": {"coordinates":[-6.67508,42.95462],"type":"Point"}
}