{
  "type": "Feature",
  "properties": {
    "gn:gn_country":"ES",
    "gn:gn_fcode":"PPLA3",
    "gn:gn_pop":110,
    "gn:population":110,
    "iso:country":"ES",
    "name:arg_x_preferred":[
        "Sanch\u00f3n de la Ribera"
    ],
    "name:baq_x_preferred":[
        "Sanch\u00f3n de la Ribera"
    ],
    "name:cat_x_preferred":[
        "Sanch\u00f3n de la Ribera"
    ],
    "name:chi_x_preferred":[
        "\u6851\u743c\u5fb7\u62c9\u91cc\u97e6\u62c9"
    ],
    "name:dut_x_preferred":[
        "Sanch\u00f3n de la Ribera"
    ],
    "name:eng_x_preferred":[
        "Sanch\u00f3n de la Ribera"
    ],
    "name:fre_x_preferred":[
        "Sanch\u00f3n de la Ribera"
    ],
    "name:hun_x_preferred":[
        "Sanch\u00f3n de la Ribera"
    ],
    "name:ina_x_preferred":[
        "Sanch\u00f3n de la Ribera"
    ],
    "name:ita_x_preferred":[
        "Sanch\u00f3n de la Ribera"
    ],
    "name:kaz_x_preferred":[
        "\u0421\u0430\u043d\u0447\u043e\u043d-\u0434\u0435-\u043b\u0430-\u0420\u0438\u0431\u0435\u0440\u0430"
    ],
    "name:may_x_preferred":[
        "Sanch\u00f3n de la Ribera"
    ],
    "name:nan_x_preferred":[
        "Sanch\u00f3n de la Ribera"
    ],
    "name:oci_x_preferred":[
        "Sanch\u00f3n de la Ribera"
    ],
    "name:pol_x_preferred":[
        "Sanch\u00f3n de la Ribera"
    ],
    "name:por_x_preferred":[
        "Sanch\u00f3n de la Ribera"
    ],
    "name:rus_x_preferred":[
        "\u0421\u0430\u043d\u0447\u043e\u043d-\u0434\u0435-\u043b\u0430-\u0420\u0438\u0431\u0435\u0440\u0430"
    ],
    "name:spa_x_preferred":[
        "Sanch\u00f3n de la Ribera"
    ],
    "name:swe_x_preferred":[
        "Sanch\u00f3n de la Ribera"
    ],
    "name:ukr_x_preferred":[
        "\u0421\u0430\u043d\u0447\u043e\u043d-\u0434\u0435-\u043b\u0430-\u0420\u0456\u0431\u0435\u0440\u0430"
    ],
    "name:unk_x_variant":[
        "Sanch\u00f3n de la Rivera"
    ],
    "name:uzb_x_preferred":[
        "Sanch\u00f3n de la Ribera"
    ],
    "name:vie_x_preferred":[
        "Sanch\u00f3n de la Ribera"
    ],
    "name:war_x_preferred":[
        "Sanch\u00f3n de la Ribera"
    ],
    "qs_pg:aaroncc":"ES",
    "qs_pg:gn_country":"ES",
    "qs_pg:gn_fcode":"PPLA3",
    "qs_pg:gn_pop":110,
    "qs_pg:name":"Sanch\u00f3n de la Ribera",
    "qs_pg:name_adm0":"Espa\u00f1a",
    "qs_pg:name_adm1":"Castilla y Le\u00f3n",
    "qs_pg:photos_9r":0,
    "qs_pg:photos_sr":0,
    "qs_pg:pop_sr":1,
    "qs_pg:qs_pg_placetype":"locality",
    "qs_pg:qs_pg_placetype_gp":"Town",
    "qs_pg:woe_adm0":23424950,
    "woe:adm0_id":23424950,
    "woe:name_adm0":"Espa\u00f1a",
    "woe:name_adm1":"Castilla y Le\u00f3n",
    "woe:placetype":"Town",
    "wof:name":"Sanch\u00f3n de la Ribera",
    "wof:placetype":"locality",
    "wof:population":110
},
  "geometry": {"coordinates":[-6.41314,41.08844],"type":"Point"}
}