{
  "type": "Feature",
  "properties": {
    "gn:admin1_code":"58",
    "gn:admin2_code":"LU",
    "gn:admin3_code":"27027",
    "gn:asciiname":"Lorenzana",
    "gn:cc2":"ES",
    "gn:country_code":"ES",
    "gn:dem":146,
    "gn:feature_class":"P",
    "gn:feature_code":"PPL",
    "gn:name":"Lorenzana",
    "gn:population":0,
    "gn:timezone":"Europe/Madrid",
    "iso:country":"ES",
    "name:und_x_variant":[
        "Santo Tom\u00e9",
        "Lorenzana"
    ],
    "wof:name":"Lorenzana",
    "wof:placetype":"locality"
},
  "geometry": {"coordinates":[-7.26667,43.43333],"type":"Point"}
}