{
  "type": "Feature",
  "properties": {
    "gn:admin1_code":"58",
    "gn:admin2_code":"LU",
    "gn:admin3_code":"27027",
    "gn:asciiname":"Lorenzana",
    "gn:cc2":"ES",
    "gn:country_code":"ES",
    "gn:dem":146,
    "gn:feature_class":"P",
    "gn:feature_code":"PPL",
    "gn:name":"Lorenzana",
    "gn:population":0,
    "gn:timezone":"Europe/Madrid",
    "iso:country":"ES",
    "name:azb_x_preferred":[
        "\u0644\u0648\u0631\u0646\u062a\u0632\u0627\u0646\u0627"
    ],
    "name:bcl_x_preferred":[
        "Lorenzana"
    ],
    "name:bel_x_preferred":[
        "\u041b\u0430\u0440\u044d\u043d\u0446\u0430\u043d\u0430"
    ],
    "name:bul_x_preferred":[
        "\u041b\u043e\u0440\u0435\u043d\u0446\u0430\u043d\u0430"
    ],
    "name:cat_x_preferred":[
        "Lorenzana"
    ],
    "name:ceb_x_preferred":[
        "Lorenzana"
    ],
    "name:deu_x_preferred":[
        "Lorenzana"
    ],
    "name:epo_x_preferred":[
        "Lorenzana"
    ],
    "name:eus_x_preferred":[
        "Lorenzana"
    ],
    "name:fas_x_preferred":[
        "\u0644\u0648\u0631\u0646\u062a\u0632\u0627\u0646\u0627"
    ],
    "name:fra_x_preferred":[
        "Lorenzana"
    ],
    "name:hye_x_preferred":[
        "\u053c\u0578\u0580\u0565\u0576\u0581\u0561\u0576\u0561"
    ],
    "name:ita_x_preferred":[
        "Lorenzana"
    ],
    "name:jpn_x_preferred":[
        "\u30ed\u30ec\u30f3\u30c4\u30a1\u30fc\u30ca"
    ],
    "name:kaz_x_preferred":[
        "\u041b\u043e\u0440\u0435\u043d\u0446\u0430\u043d\u0430"
    ],
    "name:lat_x_preferred":[
        "Laurentiana"
    ],
    "name:lmo_x_preferred":[
        "Lorenzana"
    ],
    "name:msa_x_preferred":[
        "Lorenzana"
    ],
    "name:nap_x_preferred":[
        "Lorenzana"
    ],
    "name:nld_x_preferred":[
        "Lorenzana"
    ],
    "name:pms_x_preferred":[
        "Lorenzana"
    ],
    "name:pol_x_preferred":[
        "Lorenzana"
    ],
    "name:por_x_preferred":[
        "Lorenzana"
    ],
    "name:ron_x_preferred":[
        "Lorenzana"
    ],
    "name:rus_x_preferred":[
        "\u041b\u043e\u0440\u0435\u043d\u0446\u0430\u043d\u0430"
    ],
    "name:scn_x_preferred":[
        "Lorenzana"
    ],
    "name:spa_x_preferred":[
        "Lorenzana"
    ],
    "name:srp_x_preferred":[
        "\u041b\u043e\u0440\u0435\u043d\u0446\u0430\u043d\u0430"
    ],
    "name:tgl_x_preferred":[
        "Lorenzana"
    ],
    "name:ukr_x_preferred":[
        "\u041b\u043e\u0440\u0435\u043d\u0446\u0430\u043d\u0430"
    ],
    "name:und_x_variant":[
        "Santo Tom\u00e9",
        "Lorenzana"
    ],
    "name:uzb_x_preferred":[
        "Lorenzana"
    ],
    "name:vie_x_preferred":[
        "Lorenzana"
    ],
    "name:vol_x_preferred":[
        "Lorenzana"
    ],
    "name:war_x_preferred":[
        "Lorenzana"
    ],
    "name:zho_x_preferred":[
        "\u6d1b\u4f26\u624e\u7eb3"
    ],
    "wof:name":"Lorenzana",
    "wof:placetype":"locality"
},
  "geometry": {"coordinates":[-7.26667,43.43333],"type":"Point"}
}