{
  "type": "Feature",
  "properties": {
    "gn:admin1_code":"58",
    "gn:admin2_code":"PO",
    "gn:admin3_code":"36052",
    "gn:asciiname":"Lamela",
    "gn:cc2":"ES",
    "gn:country_code":"ES",
    "gn:dem":280,
    "gn:feature_class":"P",
    "gn:feature_code":"PPL",
    "gn:name":"Lamela",
    "gn:population":0,
    "gn:timezone":"Europe/Madrid",
    "iso:country":"ES",
    "name:und_x_variant":[
        "San Miguel",
        "Lamela"
    ],
    "wof:name":"Lamela",
    "wof:placetype":"locality"
},
  "geometry": {"coordinates":[-8.31667,42.73333],"type":"Point"}
}