{
  "type": "Feature",
  "properties": {
    "gn:admin1_code":"34",
    "gn:admin2_code":"O",
    "gn:admin3_code":"33012",
    "gn:asciiname":"Labra",
    "gn:country_code":"ES",
    "gn:dem":178,
    "gn:feature_class":"P",
    "gn:feature_code":"PPL",
    "gn:name":"Labra",
    "gn:population":0,
    "gn:timezone":"Europe/Madrid",
    "iso:country":"ES",
    "wof:name":"Labra",
    "wof:placetype":"locality"
},
  "geometry": {"coordinates":[-5.05706,43.36113],"type":"Point"}
}