{
  "type": "Feature",
  "properties": {
    "gn:gn_country":"ES",
    "gn:gn_fcode":"PPL",
    "gn:gn_pop":43,
    "gn:population":43,
    "iso:country":"ES",
    "name:arg_x_preferred":[
        "La Bodera"
    ],
    "name:baq_x_preferred":[
        "La Bodera"
    ],
    "name:cat_x_preferred":[
        "La Bodera"
    ],
    "name:chi_x_preferred":[
        "\u62c9\u6c83\u5fb7\u62c9"
    ],
    "name:dut_x_preferred":[
        "La Bodera"
    ],
    "name:eng_x_preferred":[
        "La Bodera"
    ],
    "name:fre_x_preferred":[
        "La Bodera"
    ],
    "name:ger_x_preferred":[
        "La Bodera"
    ],
    "name:hun_x_preferred":[
        "La Bodera"
    ],
    "name:ina_x_preferred":[
        "La Bodera"
    ],
    "name:ita_x_preferred":[
        "La Bodera"
    ],
    "name:kaz_x_preferred":[
        "\u041b\u0430-\u0411\u043e\u0434\u0435\u0440\u0430"
    ],
    "name:may_x_preferred":[
        "La Bodera"
    ],
    "name:nan_x_preferred":[
        "La Bodera"
    ],
    "name:oci_x_preferred":[
        "La Bodera"
    ],
    "name:pol_x_preferred":[
        "La Bodera"
    ],
    "name:por_x_preferred":[
        "La Bodera"
    ],
    "name:rus_x_preferred":[
        "\u041b\u0430-\u0411\u043e\u0434\u0435\u0440\u0430"
    ],
    "name:spa_x_preferred":[
        "La Bodera"
    ],
    "name:ukr_x_preferred":[
        "\u041b\u0430-\u0411\u043e\u0434\u0435\u0440\u0430"
    ],
    "name:vie_x_preferred":[
        "La Bodera"
    ],
    "name:war_x_preferred":[
        "La Bodera"
    ],
    "qs_pg:aaroncc":"ES",
    "qs_pg:gn_country":"ES",
    "qs_pg:gn_fcode":"PPL",
    "qs_pg:gn_pop":43,
    "qs_pg:name":"La Bodera",
    "qs_pg:name_adm0":"Espa\u00f1a",
    "qs_pg:name_adm1":"Castilla-La Mancha",
    "qs_pg:photos_9r":0,
    "qs_pg:photos_sr":0,
    "qs_pg:pop_sr":1,
    "qs_pg:qs_pg_placetype":"locality",
    "qs_pg:qs_pg_placetype_gp":"Town",
    "qs_pg:woe_adm0":23424950,
    "woe:adm0_id":23424950,
    "woe:name_adm0":"Espa\u00f1a",
    "woe:name_adm1":"Castilla-La Mancha",
    "woe:placetype":"Town",
    "wof:name":"La Bodera",
    "wof:placetype":"locality",
    "wof:population":43
},
  "geometry": {"coordinates":[-2.88719,41.13547],"type":"Point"}
}