{
  "type": "Feature",
  "properties": {
    "gn:admin1_code":"34",
    "gn:admin2_code":"O",
    "gn:admin3_code":"33057",
    "gn:asciiname":"La Carrera",
    "gn:country_code":"ES",
    "gn:dem":426,
    "gn:feature_class":"P",
    "gn:feature_code":"PPL",
    "gn:name":"La Carrera",
    "gn:population":0,
    "gn:timezone":"Europe/Madrid",
    "iso:country":"ES",
    "wof:name":"La Carrera",
    "wof:placetype":"locality"
},
  "geometry": {"coordinates":[-5.91547,43.29396],"type":"Point"}
}