{
  "type": "Feature",
  "properties": {
    "gn:country":"ES",
    "gn:fcode":"PPL",
    "gn:population":112,
    "iso:country":"ES",
    "name:eus_x_preferred":[
        "La Serna"
    ],
    "name:spa_x_preferred":[
        "La Serna"
    ],
    "name:und_x_variant":[
        "Serna"
    ],
    "qs_pg:aaroncc":"ES",
    "qs_pg:gn_country":"ES",
    "qs_pg:gn_fcode":"PPL",
    "qs_pg:gn_pop":112,
    "qs_pg:name":"La Serna",
    "qs_pg:name_adm0":"Espa\u00f1a",
    "qs_pg:name_adm1":"Cantabria",
    "qs_pg:photos_9r":0,
    "qs_pg:photos_sr":0,
    "qs_pg:pop_sr":1,
    "qs_pg:qs_pg_placetype":"locality",
    "qs_pg:qs_pg_placetype_gp":"Town",
    "qs_pg:woe_adm0":23424950,
    "woe:adm0_id":23424950,
    "woe:name_adm0":"Espa\u00f1a",
    "woe:name_adm1":"Cantabria",
    "woe:placetype":"Town",
    "wof:name":"La Serna",
    "wof:placetype":"locality",
    "wof:population":112
},
  "geometry": {"coordinates":[-3.94873,42.88007],"type":"Point"}
}