{
  "type": "Feature",
  "properties": {
    "gn:admin1_code":"59",
    "gn:admin2_code":"BI",
    "gn:admin3_code":"48003",
    "gn:asciiname":"Agarre",
    "gn:country_code":"ES",
    "gn:dem":140,
    "gn:feature_class":"P",
    "gn:feature_code":"PPL",
    "gn:name":"Agirre",
    "gn:population":0,
    "gn:timezone":"Europe/Madrid",
    "iso:country":"ES",
    "wof:name":"Agarre",
    "wof:placetype":"locality"
},
  "geometry": {"coordinates":[-2.7506,43.23671],"type":"Point"}
}