{
  "type": "Feature",
  "properties": {
    "gn:admin1_code":"58",
    "gn:admin2_code":"OR",
    "gn:admin3_code":"32066",
    "gn:asciiname":"Mocinos",
    "gn:country_code":"ES",
    "gn:dem":546,
    "gn:feature_class":"P",
    "gn:feature_code":"PPL",
    "gn:name":"Moci\u00f1os",
    "gn:population":0,
    "gn:timezone":"Europe/Madrid",
    "iso:country":"ES",
    "name:und_x_variant":[
        "Moci\u00f1os"
    ],
    "wof:name":"Mocinos",
    "wof:placetype":"locality"
},
  "geometry": {"coordinates":[-8.10514,42.12563],"type":"Point"}
}