{
  "type": "Feature",
  "properties": {
    "gn:admin1_code":"39",
    "gn:admin2_code":"S",
    "gn:admin3_code":"39033",
    "gn:asciiname":"Cabanzon",
    "gn:country_code":"ES",
    "gn:dem":149,
    "gn:feature_class":"P",
    "gn:feature_code":"PPL",
    "gn:name":"Cabanz\u00f3n",
    "gn:population":0,
    "gn:timezone":"Europe/Madrid",
    "iso:country":"ES",
    "name:und_x_variant":[
        "Cabanz\u00f3n"
    ],
    "wof:name":"Cabanzon",
    "wof:placetype":"locality"
},
  "geometry": {"coordinates":[-4.49911,43.32162],"type":"Point"}
}