{
  "type": "Feature",
  "properties": {
    "gn:admin1_code":"58",
    "gn:admin2_code":"LU",
    "gn:admin3_code":"27063",
    "gn:asciiname":"Villacampa",
    "gn:cc2":"ES",
    "gn:country_code":"ES",
    "gn:dem":538,
    "gn:feature_class":"P",
    "gn:feature_code":"PPL",
    "gn:name":"Villacampa",
    "gn:population":0,
    "gn:timezone":"Europe/Madrid",
    "iso:country":"ES",
    "name:und_x_variant":[
        "Santa Mar\u00eda",
        "Villacampa"
    ],
    "wof:name":"Villacampa",
    "wof:placetype":"locality"
},
  "geometry": {"coordinates":[-7.51667,43.56667],"type":"Point"}
}