{
  "type": "Feature",
  "properties": {
    "gn:admin1_code":"55",
    "gn:admin2_code":"BU",
    "gn:admin3_code":"09045",
    "gn:asciiname":"La Rad",
    "gn:country_code":"ES",
    "gn:dem":979,
    "gn:feature_class":"P",
    "gn:feature_code":"PPL",
    "gn:name":"La Rad",
    "gn:population":0,
    "gn:timezone":"Europe/Madrid",
    "iso:country":"ES",
    "wof:name":"La Rad",
    "wof:placetype":"locality"
},
  "geometry": {"coordinates":[-3.9146,42.67308],"type":"Point"}
}