{
  "type": "Feature",
  "properties": {
    "gn:admin1_code":"52",
    "gn:admin2_code":"HU",
    "gn:admin3_code":"22233",
    "gn:asciiname":"Reperos",
    "gn:country_code":"ES",
    "gn:dem":976,
    "gn:feature_class":"P",
    "gn:feature_code":"PPL",
    "gn:name":"Reper\u00f3s",
    "gn:population":0,
    "gn:timezone":"Europe/Madrid",
    "iso:country":"ES",
    "wof:name":"Reperos",
    "wof:placetype":"locality"
},
  "geometry": {"coordinates":[0.52722,42.36622],"type":"Point"}
}