{
  "type": "Feature",
  "properties": {
    "gn:admin1_code":"55",
    "gn:admin2_code":"ZA",
    "gn:admin3_code":"49112",
    "gn:asciiname":"Dornillas",
    "gn:country_code":"ES",
    "gn:dem":896,
    "gn:feature_class":"P",
    "gn:feature_code":"PPL",
    "gn:name":"Dornillas",
    "gn:population":0,
    "gn:timezone":"Europe/Madrid",
    "iso:country":"ES",
    "wof:name":"Dornillas",
    "wof:placetype":"locality"
},
  "geometry": {"coordinates":[-6.3567,42.08311],"type":"Point"}
}