{
  "type": "Feature",
  "properties": {
    "gn:country":"ES",
    "gn:fcode":"PPLA3",
    "gn:population":467,
    "iso:country":"ES",
    "name:ara_x_preferred":[
        "\u0628\u064a\u0646\u0627\u064a\u0645\u0627\u0631\u0641\u0644"
    ],
    "name:arg_x_preferred":[
        "Benimarfull"
    ],
    "name:ast_x_preferred":[
        "Benimarfull"
    ],
    "name:cat_x_preferred":[
        "Benimarfull"
    ],
    "name:ceb_x_preferred":[
        "Benimarfull"
    ],
    "name:eng_x_preferred":[
        "Benimarfull"
    ],
    "name:eus_x_preferred":[
        "Benimarfull"
    ],
    "name:fas_x_preferred":[
        "\u0628\u0646\u06cc\u0645\u0627\u0631\u0641\u0648\u0644"
    ],
    "name:fra_x_preferred":[
        "Benimarfull"
    ],
    "name:hun_x_preferred":[
        "Benimarfull"
    ],
    "name:ita_x_preferred":[
        "Benimarfull"
    ],
    "name:kaz_x_preferred":[
        "\u0411\u0435\u043d\u0438\u043c\u0430\u0440\u0444\u0443\u043b\u044c"
    ],
    "name:msa_x_preferred":[
        "Benimarfull"
    ],
    "name:nan_x_preferred":[
        "Benimarfull"
    ],
    "name:nld_x_preferred":[
        "Benimarfull"
    ],
    "name:oci_x_preferred":[
        "Benimarfull"
    ],
    "name:pol_x_preferred":[
        "Benimarfull"
    ],
    "name:por_x_preferred":[
        "Benimarfull"
    ],
    "name:rus_x_preferred":[
        "\u0411\u0435\u043d\u0438\u043c\u0430\u0440\u0444\u0443\u043b\u044c"
    ],
    "name:spa_x_preferred":[
        "Benimarfull"
    ],
    "name:sqi_x_preferred":[
        "Benimarfull"
    ],
    "name:swe_x_preferred":[
        "Benimarfull"
    ],
    "name:ukr_x_preferred":[
        "\u0411\u0435\u043d\u0456\u043c\u0430\u0440\u0444\u0443\u043b\u044c"
    ],
    "name:uzb_x_preferred":[
        "Benimarfull"
    ],
    "name:war_x_preferred":[
        "Benimarfull"
    ],
    "name:zho_x_preferred":[
        "\u8d1d\u5c3c\u9a6c\u5c14\u5bcc\u5229"
    ],
    "qs_pg:aaroncc":"ES",
    "qs_pg:gn_country":"ES",
    "qs_pg:gn_fcode":"PPLA3",
    "qs_pg:gn_pop":467,
    "qs_pg:name":"Benimarfull",
    "qs_pg:name_adm0":"Espa\u00f1a",
    "qs_pg:name_adm1":"Comunitat Valenciana",
    "qs_pg:photos_9r":0,
    "qs_pg:photos_sr":0,
    "qs_pg:pop_sr":2,
    "qs_pg:qs_pg_placetype":"locality",
    "qs_pg:qs_pg_placetype_gp":"Town",
    "qs_pg:woe_adm0":23424950,
    "woe:adm0_id":23424950,
    "woe:name_adm0":"Espa\u00f1a",
    "woe:name_adm1":"Comunitat Valenciana",
    "woe:placetype":"Town",
    "wof:name":"Benimarfull",
    "wof:placetype":"locality",
    "wof:population":467
},
  "geometry": {"coordinates":[-0.39079,38.7759],"type":"Point"}
}