{
  "type": "Feature",
  "properties": {
    "gn:gn_country":"ES",
    "gn:gn_fcode":"PPL",
    "gn:gn_pop":563,
    "gn:population":563,
    "iso:country":"ES",
    "name:ara_x_preferred":[
        "\u0631\u0628\u0639"
    ],
    "name:arg_x_preferred":[
        "Arroba"
    ],
    "name:cat_x_preferred":[
        "Arrova"
    ],
    "name:ces_x_preferred":[
        "Arroba"
    ],
    "name:deu_x_preferred":[
        "Arroba"
    ],
    "name:eus_x_preferred":[
        "Arroa"
    ],
    "name:fra_x_preferred":[
        "Arroba"
    ],
    "name:jpn_x_preferred":[
        "\u30a2\u30ed\u30fc\u30d0"
    ],
    "name:pol_x_preferred":[
        "Arroba"
    ],
    "name:por_x_preferred":[
        "Arroba"
    ],
    "name:rus_x_preferred":[
        "\u0410\u0440\u0440\u043e\u0431\u0430"
    ],
    "name:ukr_x_preferred":[
        "\u0410\u0440\u0440\u043e\u0431\u0430"
    ],
    "qs_pg:aaroncc":"ES",
    "qs_pg:gn_country":"ES",
    "qs_pg:gn_fcode":"PPL",
    "qs_pg:gn_pop":563,
    "qs_pg:name":"Arroba",
    "qs_pg:photos_9r":0,
    "qs_pg:photos_sr":0,
    "qs_pg:pop_sr":2,
    "qs_pg:qs_pg_placetype":"locality",
    "wof:name":"Arroba",
    "wof:placetype":"locality",
    "wof:population":563
},
  "geometry": {"coordinates":[-4.54371,39.15401],"type":"Point"}
}