{
  "type": "Feature",
  "properties": {
    "gn:admin1_code":"58",
    "gn:admin2_code":"C",
    "gn:admin3_code":"15023",
    "gn:asciiname":"Toba de Abajo",
    "gn:country_code":"ES",
    "gn:dem":186,
    "gn:feature_class":"P",
    "gn:feature_code":"PPL",
    "gn:name":"Toba de Abajo",
    "gn:population":0,
    "gn:timezone":"Europe/Madrid",
    "iso:country":"ES",
    "wof:name":"Toba de Abajo",
    "wof:placetype":"locality"
},
  "geometry": {"coordinates":[-9.21667,42.96667],"type":"Point"}
}