{
  "type": "Feature",
  "properties": {
    "gn:admin1_code":"54",
    "gn:admin2_code":"AB",
    "gn:admin3_code":"02037",
    "gn:asciiname":"Talave",
    "gn:country_code":"ES",
    "gn:dem":629,
    "gn:feature_class":"P",
    "gn:feature_code":"PPL",
    "gn:name":"Talave",
    "gn:population":0,
    "gn:timezone":"Europe/Madrid",
    "iso:country":"ES",
    "wof:name":"Talave",
    "wof:placetype":"locality"
},
  "geometry": {"coordinates":[-1.85,38.51667],"type":"Point"}
}