{
  "type": "Feature",
  "properties": {
    "gn:admin1_code":"56",
    "gn:admin2_code":"L",
    "gn:admin3_code":"25051",
    "gn:asciiname":"Coborriu",
    "gn:country_code":"ES",
    "gn:dem":1077,
    "gn:feature_class":"P",
    "gn:feature_code":"PPL",
    "gn:name":"Coborriu",
    "gn:population":0,
    "gn:timezone":"Europe/Madrid",
    "iso:country":"ES",
    "wof:name":"Coborriu",
    "wof:placetype":"locality"
},
  "geometry": {"coordinates":[1.78034,42.35645],"type":"Point"}
}