{
  "type": "Feature",
  "properties": {
    "gn:admin1_code":"34",
    "gn:admin2_code":"O",
    "gn:admin3_code":"33066",
    "gn:asciiname":"Villanueva",
    "gn:country_code":"ES",
    "gn:dem":268,
    "gn:feature_class":"P",
    "gn:feature_code":"PPL",
    "gn:name":"Villanueva",
    "gn:population":0,
    "gn:timezone":"Europe/Madrid",
    "iso:country":"ES",
    "name:ast_x_preferred":[
        "Villanueva"
    ],
    "name:bre_x_preferred":[
        "Villanueva"
    ],
    "name:cat_x_preferred":[
        "Villanueva"
    ],
    "name:ceb_x_preferred":[
        "Villanueva"
    ],
    "name:deu_x_preferred":[
        "Villanueva"
    ],
    "name:eus_x_preferred":[
        "Villanueva"
    ],
    "name:fas_x_preferred":[
        "\u0648\u06cc\u06cc\u0627\u0646\u0648\u0626\u0648\u0627"
    ],
    "name:fra_x_preferred":[
        "Villanueva"
    ],
    "name:ita_x_preferred":[
        "Villanueva"
    ],
    "name:jpn_x_preferred":[
        "\u30d3\u30b8\u30e3\u30cc\u30a8\u30d0"
    ],
    "name:nds_x_preferred":[
        "Villanueva"
    ],
    "name:nld_x_preferred":[
        "Villanueva"
    ],
    "name:pol_x_preferred":[
        "Villanueva"
    ],
    "name:por_x_preferred":[
        "Villanueva"
    ],
    "name:rus_x_preferred":[
        "\u0412\u0438\u043b\u044c\u044f\u043d\u0443\u044d\u0432\u0430"
    ],
    "name:sco_x_preferred":[
        "Villanueva"
    ],
    "name:spa_x_preferred":[
        "Villanueva"
    ],
    "name:swe_x_preferred":[
        "Villanueva"
    ],
    "name:vie_x_preferred":[
        "Villanueva"
    ],
    "name:war_x_preferred":[
        "Villanueva"
    ],
    "wof:name":"Villanueva",
    "wof:placetype":"locality"
},
  "geometry": {"coordinates":[-5.59463,43.40646],"type":"Point"}
}