{
  "type": "Feature",
  "properties": {
    "gn:admin1_code":"34",
    "gn:admin2_code":"O",
    "gn:admin3_code":"33066",
    "gn:asciiname":"Villanueva",
    "gn:country_code":"ES",
    "gn:dem":268,
    "gn:feature_class":"P",
    "gn:feature_code":"PPL",
    "gn:name":"Villanueva",
    "gn:population":0,
    "gn:timezone":"Europe/Madrid",
    "iso:country":"ES",
    "wof:name":"Villanueva",
    "wof:placetype":"locality"
},
  "geometry": {"coordinates":[-5.59463,43.40646],"type":"Point"}
}