{
  "type": "Feature",
  "properties": {
    "iso:country":"ES",
    "wof:name":"Huerta de Santa Isabel",
    "wof:placetype":"neighbourhood"
},
  "geometry": {"coordinates":[-4.80444515871785,37.88618037873012],"type":"Point"}
}