{
  "type": "Feature",
  "properties": {
    "gn:admin1_code":"59",
    "gn:admin2_code":"BI",
    "gn:admin3_code":"48022",
    "gn:asciiname":"Santecilla",
    "gn:country_code":"ES",
    "gn:dem":308,
    "gn:feature_class":"P",
    "gn:feature_code":"PPL",
    "gn:name":"Santecilla",
    "gn:population":0,
    "gn:timezone":"Europe/Madrid",
    "iso:country":"ES",
    "wof:name":"Santecilla",
    "wof:placetype":"locality"
},
  "geometry": {"coordinates":[-3.3554,43.25929],"type":"Point"}
}