{
  "type": "Feature",
  "properties": {
    "gn:country":"ES",
    "gn:fcode":"PPLA3",
    "gn:population":75,
    "iso:country":"ES",
    "name:arg_x_preferred":[
        "Lerga"
    ],
    "name:ast_x_preferred":[
        "Lerga"
    ],
    "name:bre_x_preferred":[
        "Lerga"
    ],
    "name:bul_x_preferred":[
        "\u041b\u0435\u0440\u0433\u0430"
    ],
    "name:cat_x_preferred":[
        "Lerga"
    ],
    "name:ceb_x_preferred":[
        "Lerga"
    ],
    "name:eng_x_preferred":[
        "Lerga"
    ],
    "name:eus_x_preferred":[
        "Lerga"
    ],
    "name:fra_x_preferred":[
        "Lerga"
    ],
    "name:hun_x_preferred":[
        "Lerga"
    ],
    "name:ita_x_preferred":[
        "Lerga"
    ],
    "name:jpn_x_preferred":[
        "\u30ec\u30eb\u30ac"
    ],
    "name:msa_x_preferred":[
        "Lerga"
    ],
    "name:nan_x_preferred":[
        "Lerga"
    ],
    "name:nld_x_preferred":[
        "Lerga"
    ],
    "name:oci_x_preferred":[
        "Lerga"
    ],
    "name:pol_x_preferred":[
        "Lerga"
    ],
    "name:por_x_preferred":[
        "Lerga"
    ],
    "name:rus_x_preferred":[
        "\u041b\u0435\u0440\u0433\u0430"
    ],
    "name:spa_x_preferred":[
        "Lerga"
    ],
    "name:swe_x_preferred":[
        "Lerga"
    ],
    "name:ukr_x_preferred":[
        "\u041b\u0435\u0440\u0433\u0430"
    ],
    "name:uzb_x_preferred":[
        "Lerga"
    ],
    "name:vie_x_preferred":[
        "Lerga"
    ],
    "name:war_x_preferred":[
        "Lerga"
    ],
    "name:zho_x_preferred":[
        "\u83b1\u5c14\u52a0"
    ],
    "qs_pg:aaroncc":"ES",
    "qs_pg:gn_country":"ES",
    "qs_pg:gn_fcode":"PPLA3",
    "qs_pg:gn_pop":75,
    "qs_pg:name":"Lerga",
    "qs_pg:name_adm0":"Espa\u00f1a",
    "qs_pg:name_adm1":"Comunidad Foral de Navarra",
    "qs_pg:photos_9k":1,
    "qs_pg:photos_9r":1,
    "qs_pg:photos_all":1,
    "qs_pg:photos_sr":0,
    "qs_pg:pop_sr":1,
    "qs_pg:qs_pg_placetype":"locality",
    "qs_pg:qs_pg_placetype_gp":"Town",
    "qs_pg:woe_adm0":23424950,
    "woe:adm0_id":23424950,
    "woe:name_adm0":"Espa\u00f1a",
    "woe:name_adm1":"Comunidad Foral de Navarra",
    "woe:placetype":"Town",
    "wof:name":"Lerga",
    "wof:placetype":"locality",
    "wof:population":75
},
  "geometry": {"coordinates":[-1.5011,42.56781],"type":"Point"}
}