{
  "type": "Feature",
  "properties": {
    "gn:admin1_code":"39",
    "gn:admin2_code":"S",
    "gn:admin3_code":"39062",
    "gn:asciiname":"Omono",
    "gn:country_code":"ES",
    "gn:dem":38,
    "gn:feature_class":"P",
    "gn:feature_code":"PPL",
    "gn:name":"Omo\u00f1o",
    "gn:population":0,
    "gn:timezone":"Europe/Madrid",
    "iso:country":"ES",
    "wof:name":"Omono",
    "wof:placetype":"locality"
},
  "geometry": {"coordinates":[-3.65905,43.42724000000001],"type":"Point"}
}