{
  "type": "Feature",
  "properties": {
    "gn:admin1_code":"34",
    "gn:admin2_code":"O",
    "gn:admin3_code":"33012",
    "gn:asciiname":"Cangas de Onis",
    "gn:country_code":"ES",
    "gn:dem":60,
    "gn:feature_class":"P",
    "gn:feature_code":"PPLA3",
    "gn:name":"Cangas de On\u00eds",
    "gn:population":6623,
    "gn:timezone":"Europe/Madrid",
    "iso:country":"ES",
    "name:ara_x_preferred":[
        "\u0643\u0627\u0646\u063a\u0627\u0633 \u062f\u064a \u0623\u0648\u0646\u064a\u0633"
    ],
    "name:arg_x_preferred":[
        "Cangues dOn\u00eds"
    ],
    "name:arg_x_variant":[
        "Cangues d'On\u00eds"
    ],
    "name:ast_x_preferred":[
        "Cangues d'On\u00eds"
    ],
    "name:ast_x_variant":[
        "Cangues dOn\u00eds"
    ],
    "name:cat_x_preferred":[
        "Cangues d'On\u00eds"
    ],
    "name:cym_x_preferred":[
        "Cangues d'On\u00eds"
    ],
    "name:deu_x_preferred":[
        "Cangas de On\u00eds"
    ],
    "name:eng_x_preferred":[
        "Cangas de Onis"
    ],
    "name:fas_x_preferred":[
        "\u06a9\u0627\u0646\u06af\u0627\u0633 \u062f \u0627\u0646\u06cc\u0633"
    ],
    "name:fra_x_preferred":[
        "Cangas de On\u00eds"
    ],
    "name:glg_x_preferred":[
        "Cangues d'On\u00eds"
    ],
    "name:heb_x_preferred":[
        "\u05e7\u05e0\u05d2\u05e1 \u05d3\u05d4 \u05d0\u05d5\u05e0\u05d9\u05e1"
    ],
    "name:hye_x_preferred":[
        "\u053f\u0561\u0576\u0563\u0561\u057d \u0564\u0565 \u0555\u0576\u056b\u057d"
    ],
    "name:ita_x_preferred":[
        "Cangas de On\u00eds"
    ],
    "name:jpn_x_preferred":[
        "\u30ab\u30f3\u30ac\u30b9\u30fb\u30c7\u30fb\u30aa\u30cb\u30b9"
    ],
    "name:nld_x_preferred":[
        "Cangas de On\u00eds"
    ],
    "name:por_x_preferred":[
        "Cangas de On\u00eds"
    ],
    "name:rus_x_preferred":[
        "\u041a\u0430\u043d\u0433\u0430\u0441-\u0434\u0435-\u041e\u043d\u0438\u0441"
    ],
    "name:spa_x_preferred":[
        "Cangas de On\u00eds"
    ],
    "name:tur_x_preferred":[
        "Cangas de On\u00eds"
    ],
    "name:ukr_x_preferred":[
        "\u041a\u0430\u043d\u0433\u0430\u0441-\u0434\u0435-\u041e\u043d\u0456\u0441"
    ],
    "name:zho_x_preferred":[
        "\u574e\u52a0\u65af\u5fb7\u5965\u5c3c\u65af"
    ],
    "wof:name":"Cangas de Onis",
    "wof:placetype":"locality",
    "wof:population":6623
},
  "geometry": {"coordinates":[-5.12916,43.3514],"type":"Point"}
}