{
  "type": "Feature",
  "properties": {
    "gn:admin1_code":"59",
    "gn:admin2_code":"VI",
    "gn:admin3_code":"01058",
    "gn:asciiname":"Urbina",
    "gn:country_code":"ES",
    "gn:dem":531,
    "gn:feature_class":"P",
    "gn:feature_code":"PPL",
    "gn:name":"Urbina",
    "gn:population":0,
    "gn:timezone":"Europe/Madrid",
    "iso:country":"ES",
    "wof:name":"Urbina",
    "wof:placetype":"locality"
},
  "geometry": {"coordinates":[-2.6465,42.94436],"type":"Point"}
}