{
  "type": "Feature",
  "properties": {
    "gn:admin1_code":"58",
    "gn:admin2_code":"OR",
    "gn:admin3_code":"32063",
    "gn:asciiname":"Sobrado",
    "gn:country_code":"ES",
    "gn:dem":662,
    "gn:feature_class":"P",
    "gn:feature_code":"PPL",
    "gn:name":"Sobrado",
    "gn:population":0,
    "gn:timezone":"Europe/Madrid",
    "iso:country":"ES",
    "name:spa_x_preferred":[
        "Sobrado"
    ],
    "wof:name":"Sobrado",
    "wof:placetype":"locality"
},
  "geometry": {"coordinates":[-7.24022,42.31565],"type":"Point"}
}