{
  "type": "Feature",
  "properties": {
    "gn:admin1_code":"54",
    "gn:admin2_code":"AB",
    "gn:admin3_code":"02086",
    "gn:asciiname":"Sege",
    "gn:country_code":"ES",
    "gn:dem":959,
    "gn:feature_class":"P",
    "gn:feature_code":"PPL",
    "gn:name":"Sege",
    "gn:population":0,
    "gn:timezone":"Europe/Madrid",
    "iso:country":"ES",
    "wof:name":"Sege",
    "wof:placetype":"locality"
},
  "geometry": {"coordinates":[-2.29466,38.29583],"type":"Point"}
}