{
  "type": "Feature",
  "properties": {
    "gn:admin1_code":"53",
    "gn:admin2_code":"TF",
    "gn:admin3_code":"38049",
    "gn:asciiname":"Taguluche",
    "gn:country_code":"ES",
    "gn:dem":316,
    "gn:feature_class":"P",
    "gn:feature_code":"PPL",
    "gn:name":"Taguluche",
    "gn:population":0,
    "gn:timezone":"Atlantic/Canary",
    "iso:country":"ES",
    "wof:name":"Taguluche",
    "wof:placetype":"locality"
},
  "geometry": {"coordinates":[-17.33066,28.13529],"type":"Point"}
}