{
  "type": "Feature",
  "properties": {
    "gn:admin1_code":"56",
    "gn:admin2_code":"GI",
    "gn:admin3_code":"17088",
    "gn:asciiname":"el Pujol",
    "gn:country_code":"ES",
    "gn:dem":233,
    "gn:feature_class":"P",
    "gn:feature_code":"PPL",
    "gn:name":"el Pujol",
    "gn:population":0,
    "gn:timezone":"Europe/Madrid",
    "iso:country":"ES",
    "name:cat_x_preferred":[
        "el Pujol"
    ],
    "wof:name":"el Pujol",
    "wof:placetype":"locality"
},
  "geometry": {"coordinates":[2.80922,42.25406],"type":"Point"}
}