{
  "type": "Feature",
  "properties": {
    "gn:admin1_code":"58",
    "gn:admin2_code":"C",
    "gn:admin3_code":"15040",
    "gn:asciiname":"Coens",
    "gn:country_code":"ES",
    "gn:dem":210,
    "gn:feature_class":"P",
    "gn:feature_code":"PPL",
    "gn:name":"Coens",
    "gn:population":0,
    "gn:timezone":"Europe/Madrid",
    "iso:country":"ES",
    "wof:name":"Coens",
    "wof:placetype":"locality"
},
  "geometry": {"coordinates":[-8.99931,43.17921],"type":"Point"}
}