{
  "type": "Feature",
  "properties": {
    "gn:admin1_code":"34",
    "gn:admin2_code":"O",
    "gn:admin3_code":"33054",
    "gn:asciiname":"Grado",
    "gn:country_code":"ES",
    "gn:dem":143,
    "gn:feature_class":"P",
    "gn:feature_code":"PPL",
    "gn:name":"Grado",
    "gn:population":0,
    "gn:timezone":"Europe/Madrid",
    "iso:country":"ES",
    "name:und_x_variant":[
        "Santa Mar\u00eda",
        "Grado"
    ],
    "wof:name":"Grado",
    "wof:placetype":"locality"
},
  "geometry": {"coordinates":[-5.96849,43.38811],"type":"Point"}
}