{
  "type": "Feature",
  "properties": {
    "gn:gn_country":"ES",
    "gn:gn_fcode":"PPLA3",
    "gn:gn_pop":732,
    "gn:population":732,
    "iso:country":"ES",
    "name:ara_x_preferred":[
        "\u0646\u0627\u0641\u064a\u0633\u0648\u064a\u0644\u0627\u0633"
    ],
    "name:baq_x_preferred":[
        "Navezuelas"
    ],
    "name:cat_x_preferred":[
        "Navezuelas"
    ],
    "name:chi_x_preferred":[
        "\u7eb3\u97e6\u82cf\u57c3\u62c9\u65af"
    ],
    "name:dut_x_preferred":[
        "Navezuelas"
    ],
    "name:eng_x_preferred":[
        "Navezuelas"
    ],
    "name:epo_x_preferred":[
        "Navezuelas"
    ],
    "name:fre_x_preferred":[
        "Navezuelas"
    ],
    "name:hun_x_preferred":[
        "Navezuelas"
    ],
    "name:ina_x_preferred":[
        "Navezuelas"
    ],
    "name:ita_x_preferred":[
        "Navezuelas"
    ],
    "name:may_x_preferred":[
        "Navezuelas"
    ],
    "name:nan_x_preferred":[
        "Navezuelas"
    ],
    "name:oci_x_preferred":[
        "Navezuelas"
    ],
    "name:pol_x_preferred":[
        "Navezuelas"
    ],
    "name:por_x_preferred":[
        "Navezuelas"
    ],
    "name:rum_x_preferred":[
        "Navezuelas"
    ],
    "name:rus_x_preferred":[
        "\u041d\u0430\u0432\u0435\u0441\u0443\u044d\u043b\u0430\u0441"
    ],
    "name:spa_x_preferred":[
        "Navezuelas"
    ],
    "name:swe_x_preferred":[
        "Navezuelas"
    ],
    "name:ukr_x_preferred":[
        "\u041d\u0430\u0432\u0435\u0441\u0443\u0435\u043b\u0430\u0441"
    ],
    "name:uzb_x_preferred":[
        "Navezuelas"
    ],
    "name:vie_x_preferred":[
        "Navezuelas"
    ],
    "name:war_x_preferred":[
        "Navezuelas"
    ],
    "qs_pg:aaroncc":"ES",
    "qs_pg:gn_country":"ES",
    "qs_pg:gn_fcode":"PPLA3",
    "qs_pg:gn_pop":732,
    "qs_pg:name":"Navezuelas",
    "qs_pg:name_adm0":"Espa\u00f1a",
    "qs_pg:name_adm1":"Extremadura",
    "qs_pg:photos":31,
    "qs_pg:photos_1k":6,
    "qs_pg:photos_9k":1,
    "qs_pg:photos_9r":2,
    "qs_pg:photos_all":31,
    "qs_pg:photos_sr":2,
    "qs_pg:pop_sr":2,
    "qs_pg:qs_pg_placetype":"locality",
    "qs_pg:qs_pg_placetype_gp":"Town",
    "qs_pg:woe_adm0":23424950,
    "woe:adm0_id":23424950,
    "woe:name_adm0":"Espa\u00f1a",
    "woe:name_adm1":"Extremadura",
    "woe:placetype":"Town",
    "wof:name":"Navezuelas",
    "wof:placetype":"locality",
    "wof:population":732
},
  "geometry": {"coordinates":[-5.43766,39.50918],"type":"Point"}
}