{
  "type": "Feature",
  "properties": {
    "gn:admin1_code":"52",
    "gn:admin2_code":"HU",
    "gn:admin3_code":"22044",
    "gn:asciiname":"Paternoy",
    "gn:country_code":"ES",
    "gn:dem":745,
    "gn:feature_class":"P",
    "gn:feature_code":"PPL",
    "gn:name":"Paternoy",
    "gn:population":0,
    "gn:timezone":"Europe/Madrid",
    "iso:country":"ES",
    "wof:name":"Paternoy",
    "wof:placetype":"locality"
},
  "geometry": {"coordinates":[-0.7463,42.46734],"type":"Point"}
}