{
  "type": "Feature",
  "properties": {
    "gn:admin1_code":"58",
    "gn:admin2_code":"PO",
    "gn:admin3_code":"36902",
    "gn:asciiname":"Almofrey",
    "gn:cc2":"ES",
    "gn:country_code":"ES",
    "gn:dem":188,
    "gn:feature_class":"P",
    "gn:feature_code":"PPL",
    "gn:name":"Almofrey",
    "gn:population":0,
    "gn:timezone":"Europe/Madrid",
    "iso:country":"ES",
    "name:und_x_variant":[
        "San Lorenzo",
        "Almofrey"
    ],
    "wof:name":"Almofrey",
    "wof:placetype":"locality"
},
  "geometry": {"coordinates":[-8.55,42.43333],"type":"Point"}
}