{
  "type": "Feature",
  "properties": {
    "gn:admin1_code":"52",
    "gn:admin2_code":"HU",
    "gn:admin3_code":"22128",
    "gn:asciiname":"Permisan",
    "gn:country_code":"ES",
    "gn:dem":329,
    "gn:feature_class":"P",
    "gn:feature_code":"PPL",
    "gn:name":"Permis\u00e1n",
    "gn:population":0,
    "gn:timezone":"Europe/Madrid",
    "iso:country":"ES",
    "wof:name":"Permisan",
    "wof:placetype":"locality"
},
  "geometry": {"coordinates":[0.07336,41.97216],"type":"Point"}
}