{
  "type": "Feature",
  "properties": {
    "gn:admin1_code":"56",
    "gn:admin2_code":"GI",
    "gn:admin3_code":"17217",
    "gn:asciiname":"Palau-borrell",
    "gn:cc2":"ES",
    "gn:country_code":"ES",
    "gn:dem":55,
    "gn:feature_class":"P",
    "gn:feature_code":"PPL",
    "gn:name":"Palau-borrell",
    "gn:population":0,
    "gn:timezone":"Europe/Madrid",
    "iso:country":"ES",
    "name:cat_x_preferred":[
        "Palau-borrell"
    ],
    "wof:name":"Palau-borrell",
    "wof:placetype":"locality"
},
  "geometry": {"coordinates":[3.04433,42.13201],"type":"Point"}
}