{
  "type": "Feature",
  "properties": {
    "gn:admin1_code":"34",
    "gn:admin2_code":"O",
    "gn:admin3_code":"33009",
    "gn:asciiname":"Arriondo",
    "gn:country_code":"ES",
    "gn:dem":216,
    "gn:feature_class":"P",
    "gn:feature_code":"PPL",
    "gn:name":"Arriondo",
    "gn:population":0,
    "gn:timezone":"Europe/Madrid",
    "iso:country":"ES",
    "wof:name":"Arriondo",
    "wof:placetype":"locality"
},
  "geometry": {"coordinates":[-5.41608,43.41002],"type":"Point"}
}