{
  "type": "Feature",
  "properties": {
    "gn:admin1_code":"55",
    "gn:admin2_code":"SA",
    "gn:admin3_code":"37356",
    "gn:asciiname":"Villar de Puerco",
    "gn:country_code":"ES",
    "gn:dem":703,
    "gn:feature_class":"P",
    "gn:feature_code":"PPL",
    "gn:name":"Villar de Puerco",
    "gn:population":0,
    "gn:timezone":"Europe/Madrid",
    "iso:country":"ES",
    "wof:name":"Villar de Puerco",
    "wof:placetype":"locality"
},
  "geometry": {"coordinates":[-6.71667,40.66667],"type":"Point"}
}