{
  "type": "Feature",
  "properties": {
    "gn:admin1_code":"60",
    "gn:admin2_code":"A",
    "gn:admin3_code":"03099",
    "gn:asciiname":"Los Barrios",
    "gn:cc2":"ES",
    "gn:country_code":"ES",
    "gn:dem":96,
    "gn:feature_class":"P",
    "gn:feature_code":"PPL",
    "gn:name":"Los Barrios",
    "gn:population":0,
    "gn:timezone":"Europe/Madrid",
    "iso:country":"ES",
    "name:und_x_variant":[
        "Casa de los Barrios",
        "Cortijo Los Barrios",
        "Los Barrios"
    ],
    "wof:name":"Los Barrios",
    "wof:placetype":"locality"
},
  "geometry": {"coordinates":[-1.01667,38.15],"type":"Point"}
}