{
  "type": "Feature",
  "properties": {
    "gn:admin1_code":"51",
    "gn:admin2_code":"J",
    "gn:admin3_code":"23073",
    "gn:asciiname":"Los Rosales",
    "gn:country_code":"ES",
    "gn:dem":762,
    "gn:feature_class":"P",
    "gn:feature_code":"PPL",
    "gn:name":"Los Rosales",
    "gn:population":0,
    "gn:timezone":"Europe/Madrid",
    "iso:country":"ES",
    "name:ceb_x_preferred":[
        "Los Rosales"
    ],
    "name:spa_x_preferred":[
        "Los Rosales"
    ],
    "name:srp_x_preferred":[
        "\u041b\u043e\u0441 \u0420\u043e\u0441\u0430\u043b\u0435\u0441"
    ],
    "name:swe_x_preferred":[
        "Los Rosales"
    ],
    "name:und_x_variant":[
        "Casa Los Rosales"
    ],
    "wof:name":"Los Rosales",
    "wof:placetype":"locality"
},
  "geometry": {"coordinates":[-3.08409,37.79151],"type":"Point"}
}