{
  "type": "Feature",
  "properties": {
    "gn:admin1_code":"51",
    "gn:admin2_code":"J",
    "gn:admin3_code":"23073",
    "gn:asciiname":"Los Rosales",
    "gn:country_code":"ES",
    "gn:dem":762,
    "gn:feature_class":"P",
    "gn:feature_code":"PPL",
    "gn:name":"Los Rosales",
    "gn:population":0,
    "gn:timezone":"Europe/Madrid",
    "iso:country":"ES",
    "name:und_x_variant":[
        "Casa Los Rosales",
        "Los Rosales"
    ],
    "wof:name":"Los Rosales",
    "wof:placetype":"locality"
},
  "geometry": {"coordinates":[-3.08409,37.79151],"type":"Point"}
}