{
  "type": "Feature",
  "properties": {
    "gn:admin1_code":"58",
    "gn:admin2_code":"LU",
    "gn:admin3_code":"27037",
    "gn:asciiname":"Castelo",
    "gn:country_code":"ES",
    "gn:dem":982,
    "gn:feature_class":"P",
    "gn:feature_code":"PPL",
    "gn:name":"Castelo",
    "gn:population":0,
    "gn:timezone":"Europe/Madrid",
    "iso:country":"ES",
    "name:ceb_x_preferred":[
        "Castelo"
    ],
    "name:deu_x_preferred":[
        "Castelo"
    ],
    "name:epo_x_preferred":[
        "Castelo"
    ],
    "name:fra_x_preferred":[
        "Castelo"
    ],
    "name:glg_x_preferred":[
        "Castelo"
    ],
    "name:nld_x_preferred":[
        "Castelo"
    ],
    "name:por_x_preferred":[
        "Castelo"
    ],
    "name:rus_x_preferred":[
        "\u041a\u0430\u0448\u0442\u0435\u043b\u0443"
    ],
    "name:sco_x_preferred":[
        "Castelo"
    ],
    "name:spa_x_preferred":[
        "Castelo"
    ],
    "name:swe_x_preferred":[
        "Castelo"
    ],
    "name:ukr_x_preferred":[
        "\u041a\u0430\u0448\u0442\u0435\u043b\u0443"
    ],
    "wof:name":"Castelo",
    "wof:placetype":"locality"
},
  "geometry": {"coordinates":[-7.07421,42.77048],"type":"Point"}
}