{
  "type": "Feature",
  "properties": {
    "gn:admin1_code":"52",
    "gn:admin2_code":"HU",
    "gn:admin3_code":"22227",
    "gn:asciiname":"Lamiana",
    "gn:country_code":"ES",
    "gn:dem":1094,
    "gn:feature_class":"P",
    "gn:feature_code":"PPL",
    "gn:name":"Lamiana",
    "gn:population":0,
    "gn:timezone":"Europe/Madrid",
    "iso:country":"ES",
    "wof:name":"Lamiana",
    "wof:placetype":"locality"
},
  "geometry": {"coordinates":[0.16997,42.58393],"type":"Point"}
}