{
  "type": "Feature",
  "properties": {
    "gn:admin1_code":"54",
    "gn:admin2_code":"CU",
    "gn:admin3_code":"16211",
    "gn:asciiname":"Horcajada de la Torre",
    "gn:country_code":"ES",
    "gn:dem":926,
    "gn:feature_class":"P",
    "gn:feature_code":"PPL",
    "gn:name":"Horcajada de la Torre",
    "gn:population":0,
    "gn:timezone":"Europe/Madrid",
    "iso:country":"ES",
    "wof:name":"Horcajada de la Torre",
    "wof:placetype":"locality"
},
  "geometry": {"coordinates":[-2.56819,40.03973],"type":"Point"}
}