{
  "type": "Feature",
  "properties": {
    "gn:admin1_code":"51",
    "gn:admin2_code":"J",
    "gn:admin3_code":"23017",
    "gn:asciiname":"Estacion de Cabra",
    "gn:country_code":"ES",
    "gn:dem":1026,
    "gn:feature_class":"P",
    "gn:feature_code":"PPL",
    "gn:name":"Estaci\u00f3n de Cabra",
    "gn:population":0,
    "gn:timezone":"Europe/Madrid",
    "iso:country":"ES",
    "name:und_x_variant":[
        "Estaci\u00f3n de Cabra del Santo Cristo",
        "Estaci\u00f3n de Cabra"
    ],
    "wof:name":"Estacion de Cabra",
    "wof:placetype":"locality"
},
  "geometry": {"coordinates":[-3.26414,37.65701],"type":"Point"}
}