{
  "type": "Feature",
  "properties": {
    "gn:admin1_code":"54",
    "gn:admin2_code":"AB",
    "gn:admin3_code":"02039",
    "gn:asciiname":"Bete",
    "gn:country_code":"ES",
    "gn:dem":926,
    "gn:feature_class":"P",
    "gn:feature_code":"PPL",
    "gn:name":"Bete",
    "gn:population":0,
    "gn:timezone":"Europe/Madrid",
    "iso:country":"ES",
    "name:ceb_x_preferred":[
        "Bete"
    ],
    "name:deu_x_preferred":[
        "Bete"
    ],
    "name:fra_x_preferred":[
        "B\u00eate"
    ],
    "name:nld_x_preferred":[
        "Bete"
    ],
    "name:por_x_preferred":[
        "Bete"
    ],
    "name:swe_x_preferred":[
        "Bete"
    ],
    "name:und_x_variant":[
        "Caser\u00edo Bete"
    ],
    "wof:name":"Bete",
    "wof:placetype":"locality"
},
  "geometry": {"coordinates":[-1.41757,38.921],"type":"Point"}
}