{
  "type": "Feature",
  "properties": {
    "gn:admin1_code":"58",
    "gn:admin2_code":"C",
    "gn:admin3_code":"15902",
    "gn:asciiname":"Vivente",
    "gn:country_code":"ES",
    "gn:dem":117,
    "gn:feature_class":"P",
    "gn:feature_code":"PPL",
    "gn:name":"Vivente",
    "gn:population":0,
    "gn:timezone":"Europe/Madrid",
    "iso:country":"ES",
    "wof:name":"Vivente",
    "wof:placetype":"locality"
},
  "geometry": {"coordinates":[-8.23099,43.24347],"type":"Point"}
}