{
  "type": "Feature",
  "properties": {
    "gn:admin1_code":"58",
    "gn:admin2_code":"C",
    "gn:admin3_code":"15011",
    "gn:asciiname":"Cures",
    "gn:country_code":"ES",
    "gn:dem":152,
    "gn:feature_class":"P",
    "gn:feature_code":"PPL",
    "gn:name":"Cures",
    "gn:population":0,
    "gn:timezone":"Europe/Madrid",
    "iso:country":"ES",
    "name:cat_x_preferred":[
        "Cures"
    ],
    "name:deu_x_preferred":[
        "Cures"
    ],
    "name:fra_x_preferred":[
        "Cures Sabini"
    ],
    "name:ita_x_preferred":[
        "Cures Sabini"
    ],
    "name:por_x_preferred":[
        "Cures"
    ],
    "name:rus_x_preferred":[
        "\u041a\u0443\u0440\u0435\u0441"
    ],
    "name:spa_x_preferred":[
        "Cures"
    ],
    "name:swe_x_preferred":[
        "Cures"
    ],
    "wof:name":"Cures",
    "wof:placetype":"locality"
},
  "geometry": {"coordinates":[-8.89002,42.69885],"type":"Point"}
}