{
  "type": "Feature",
  "properties": {
    "gn:admin1_code":"58",
    "gn:admin2_code":"C",
    "gn:admin3_code":"15011",
    "gn:asciiname":"Cures",
    "gn:country_code":"ES",
    "gn:dem":152,
    "gn:feature_class":"P",
    "gn:feature_code":"PPL",
    "gn:name":"Cures",
    "gn:population":0,
    "gn:timezone":"Europe/Madrid",
    "iso:country":"ES",
    "wof:name":"Cures",
    "wof:placetype":"locality"
},
  "geometry": {"coordinates":[-8.89002,42.69885],"type":"Point"}
}