{
  "type": "Feature",
  "properties": {
    "gn:admin1_code":"55",
    "gn:admin2_code":"SA",
    "gn:admin3_code":"37344",
    "gn:asciiname":"Olmedilla",
    "gn:country_code":"ES",
    "gn:dem":904,
    "gn:feature_class":"P",
    "gn:feature_code":"PPL",
    "gn:name":"Olmedilla",
    "gn:population":0,
    "gn:timezone":"Europe/Madrid",
    "iso:country":"ES",
    "wof:name":"Olmedilla",
    "wof:placetype":"locality"
},
  "geometry": {"coordinates":[-5.85952,40.76779000000001],"type":"Point"}
}