{
  "type": "Feature",
  "properties": {
    "gn:gn_country":"ES",
    "gn:gn_fcode":"PPL",
    "gn:gn_pop":0,
    "iso:country":"ES",
    "name:cat_x_preferred":[
        "Tapis"
    ],
    "qs_pg:aaroncc":"ES",
    "qs_pg:gn_country":"ES",
    "qs_pg:gn_fcode":"PPL",
    "qs_pg:gn_pop":0,
    "qs_pg:name":"Tapis",
    "qs_pg:name_adm0":"Espa\u00f1a",
    "qs_pg:name_adm1":"Catalunya",
    "qs_pg:photos":8,
    "qs_pg:photos_1k":2,
    "qs_pg:photos_9k":1,
    "qs_pg:photos_9r":1,
    "qs_pg:photos_all":8,
    "qs_pg:photos_sr":1,
    "qs_pg:pop_sr":0,
    "qs_pg:qs_pg_placetype":"locality",
    "qs_pg:qs_pg_placetype_gp":"Town",
    "qs_pg:woe_adm0":23424950,
    "woe:adm0_id":23424950,
    "woe:name_adm0":"Espa\u00f1a",
    "woe:name_adm1":"Catalunya",
    "woe:placetype":"Town",
    "wof:name":"Tapis",
    "wof:placetype":"locality"
},
  "geometry": {"coordinates":[2.70126,42.38047],"type":"Point"}
}