{
  "type": "Feature",
  "properties": {
    "gn:admin1_code":"34",
    "gn:admin2_code":"O",
    "gn:admin3_code":"33028",
    "gn:asciiname":"Villarcebollin",
    "gn:country_code":"ES",
    "gn:dem":517,
    "gn:feature_class":"P",
    "gn:feature_code":"PPL",
    "gn:name":"Villarceboll\u00edn",
    "gn:population":0,
    "gn:timezone":"Europe/Madrid",
    "iso:country":"ES",
    "name:und_x_variant":[
        "Villarceboll\u00edn"
    ],
    "wof:name":"Villarcebollin",
    "wof:placetype":"locality"
},
  "geometry": {"coordinates":[-6.84639,43.02342],"type":"Point"}
}