{
  "type": "Feature",
  "properties": {
    "iso:country":"ES",
    "name:cat_x_preferred":[
        "Santa Isabel"
    ],
    "name:ceb_x_preferred":[
        "Santa Isabel"
    ],
    "name:deu_x_preferred":[
        "Santa Isabel"
    ],
    "name:epo_x_preferred":[
        "Santa Isabel"
    ],
    "name:est_x_preferred":[
        "Santa Isabel"
    ],
    "name:fra_x_preferred":[
        "Santa Isabel"
    ],
    "name:glg_x_preferred":[
        "Santa Isabel"
    ],
    "name:ita_x_preferred":[
        "Santa Isabel"
    ],
    "name:lit_x_preferred":[
        "Santa Isabel\u0117"
    ],
    "name:mlg_x_preferred":[
        "Santa Isabel"
    ],
    "name:nld_x_preferred":[
        "Santa Isabel"
    ],
    "name:nor_x_preferred":[
        "Santa Isabel"
    ],
    "name:pol_x_preferred":[
        "Santa Isabel"
    ],
    "name:por_x_preferred":[
        "Santa Isabel"
    ],
    "name:rus_x_preferred":[
        "\u0421\u0430\u043d\u0442\u0430-\u0418\u0441\u0430\u0431\u0435\u043b\u044c"
    ],
    "name:sco_x_preferred":[
        "Santa Isabel"
    ],
    "name:slk_x_preferred":[
        "Santa Isabel"
    ],
    "name:spa_x_preferred":[
        "Santa Isabel"
    ],
    "name:spa_x_variant":[
        "Sta Isabel",
        "Sta. Isabel"
    ],
    "name:srp_x_preferred":[
        "\u0421\u0430\u043d\u0442\u0430 \u0418\u0441\u0430\u0431\u0435\u043b"
    ],
    "name:swe_x_preferred":[
        "Santa Isabel"
    ],
    "name:ukr_x_preferred":[
        "\u0421\u0430\u043d\u0442\u0430-\u0406\u0437\u0430\u0431\u0435\u043b"
    ],
    "name:vol_x_preferred":[
        "Santa Isabel"
    ],
    "name:war_x_preferred":[
        "Santa Isabel"
    ],
    "qs:gn_adm0_cc":"ES",
    "qs:gn_local":2521978,
    "qs:gn_nam_loc":"Alicante, Alicante, Alicante, Comunitat Valenciana, ES",
    "qs:gn_namadm1":"60",
    "qs:local_max":6358,
    "qs:local_sum":21789,
    "qs:localhoods":20,
    "qs:name":"Santa Isabel",
    "qs:name_adm0":"Espa\u00f1a",
    "qs:name_adm1":"Comunitat Valenciana",
    "qs:name_adm2":"Alicante",
    "qs:name_lau":"Alicante",
    "qs:name_local":"Alicante",
    "qs:photo_max":522,
    "qs:photo_sum":918,
    "qs:placetype":"Suburb",
    "qs:quad_count":29,
    "qs:woe_adm0":23424950,
    "qs:woe_adm1":12578038,
    "qs:woe_adm2":12602137,
    "qs:woe_lau":12695279,
    "qs:woe_local":752101,
    "qs:woe_ver":"7.10.0",
    "wof:name":"Santa Isabel",
    "wof:placetype":"neighbourhood"
},
  "geometry": {"coordinates":[-0.511665,38.383811],"type":"Point"}
}