{
  "type": "Feature",
  "properties": {
    "gn:gn_country":"ES",
    "gn:gn_fcode":"ADM3",
    "gn:gn_pop":119,
    "gn:population":115,
    "iso:country":"ES",
    "name:arg_x_preferred":[
        "La Molsosa"
    ],
    "name:ast_x_preferred":[
        "La Molsosa"
    ],
    "name:cat_x_preferred":[
        "la Molsosa"
    ],
    "name:ceb_x_preferred":[
        "La Molsosa"
    ],
    "name:deu_x_preferred":[
        "La Molsosa"
    ],
    "name:eng_x_preferred":[
        "La Molsosa"
    ],
    "name:eus_x_preferred":[
        "La Molsosa"
    ],
    "name:fra_x_preferred":[
        "La Molsosa"
    ],
    "name:hun_x_preferred":[
        "La Molsosa"
    ],
    "name:hye_x_preferred":[
        "\u053c\u0561 \u0544\u0578\u056c\u057d\u0578\u057d\u0561"
    ],
    "name:ita_x_preferred":[
        "La Molsosa"
    ],
    "name:msa_x_preferred":[
        "La Molsosa"
    ],
    "name:nld_x_preferred":[
        "La Molsosa"
    ],
    "name:oci_x_preferred":[
        "La Molsosa"
    ],
    "name:pol_x_preferred":[
        "La Molsosa"
    ],
    "name:por_x_preferred":[
        "La Molsosa"
    ],
    "name:ron_x_preferred":[
        "Molsosa"
    ],
    "name:rus_x_preferred":[
        "\u041b\u0430-\u041c\u043e\u043b\u044c\u0441\u043e\u0441\u0430"
    ],
    "name:sco_x_preferred":[
        "La Molsosa"
    ],
    "name:spa_x_preferred":[
        "La Molsosa"
    ],
    "name:sqi_x_preferred":[
        "La Molsosa"
    ],
    "name:swe_x_preferred":[
        "La Molsosa"
    ],
    "name:urd_x_preferred":[
        "\u0644\u0627 \u0645\u0648\u0644\u0633\u0648\u0633\u0627"
    ],
    "name:uzb_x_preferred":[
        "La Molsosa"
    ],
    "name:vie_x_preferred":[
        "La Molsosa"
    ],
    "name:war_x_preferred":[
        "La Molsosa"
    ],
    "name:zho_x_preferred":[
        "\u62c9\u83ab\u5c14\u7d22\u8428"
    ],
    "qs_pg:aaroncc":"ES",
    "qs_pg:gn_country":"ES",
    "qs_pg:gn_fcode":"ADM3",
    "qs_pg:gn_pop":119,
    "qs_pg:name":"La Molsosa",
    "qs_pg:name_adm0":"Espa\u00f1a",
    "qs_pg:name_adm1":"Catalunya",
    "qs_pg:photos_9r":0,
    "qs_pg:photos_sr":0,
    "qs_pg:pop_sr":1,
    "qs_pg:qs_pg_placetype":"locality",
    "qs_pg:qs_pg_placetype_gp":"Town",
    "qs_pg:woe_adm0":23424950,
    "woe:adm0_id":23424950,
    "woe:name_adm0":"Espa\u00f1a",
    "woe:name_adm1":"Catalunya",
    "woe:placetype":"Town",
    "wof:name":"La Molsosa",
    "wof:placetype":"locality",
    "wof:population":115
},
  "geometry": {"coordinates":[1.52493,41.78072],"type":"Point"}
}