{
  "type": "Feature",
  "properties": {
    "gn:admin1_code":"58",
    "gn:admin2_code":"C",
    "gn:admin3_code":"15052",
    "gn:asciiname":"Pardinas",
    "gn:country_code":"ES",
    "gn:dem":109,
    "gn:feature_class":"P",
    "gn:feature_code":"PPL",
    "gn:name":"Pardi\u00f1as",
    "gn:population":0,
    "gn:timezone":"Europe/Madrid",
    "iso:country":"ES",
    "name:deu_x_preferred":[
        "Pardi\u00f1as"
    ],
    "name:glg_x_preferred":[
        "Pardi\u00f1as"
    ],
    "wof:name":"Pardinas",
    "wof:placetype":"locality"
},
  "geometry": {"coordinates":[-9.14142,43.09386],"type":"Point"}
}