{
  "type": "Feature",
  "properties": {
    "gn:admin1_code":"51",
    "gn:admin2_code":"H",
    "gn:admin3_code":"21004",
    "gn:asciiname":"Gil Marquez",
    "gn:country_code":"ES",
    "gn:dem":399,
    "gn:feature_class":"P",
    "gn:feature_code":"PPL",
    "gn:name":"Gil M\u00e1rquez",
    "gn:population":0,
    "gn:timezone":"Europe/Madrid",
    "iso:country":"ES",
    "name:und_x_variant":[
        "Gil M\u00e1rques",
        "Gil M\u00e1rquez"
    ],
    "wof:name":"Gil Marquez",
    "wof:placetype":"locality"
},
  "geometry": {"coordinates":[-6.84583,37.84915],"type":"Point"}
}