{
  "type": "Feature",
  "properties": {
    "gn:admin1_code":"58",
    "gn:admin2_code":"C",
    "gn:admin3_code":"15006",
    "gn:asciiname":"Campo",
    "gn:cc2":"ES",
    "gn:country_code":"ES",
    "gn:dem":435,
    "gn:feature_class":"P",
    "gn:feature_code":"PPL",
    "gn:name":"Campo",
    "gn:population":0,
    "gn:timezone":"Europe/Madrid",
    "iso:country":"ES",
    "name:und_x_variant":[
        "San Esteban",
        "Campo"
    ],
    "wof:name":"Campo",
    "wof:placetype":"locality"
},
  "geometry": {"coordinates":[-8.21667,42.98333],"type":"Point"}
}