{
  "type": "Feature",
  "properties": {
    "gn:admin1_code":"51",
    "gn:admin2_code":"AL",
    "gn:admin3_code":"04069",
    "gn:asciiname":"Huimayor",
    "gn:cc2":"ES",
    "gn:country_code":"ES",
    "gn:dem":514,
    "gn:feature_class":"P",
    "gn:feature_code":"PPL",
    "gn:name":"Huimayor",
    "gn:population":0,
    "gn:timezone":"Europe/Madrid",
    "iso:country":"ES",
    "name:und_x_variant":[
        "Caser\u00edo Huimayor",
        "Huimayor"
    ],
    "wof:name":"Huimayor",
    "wof:placetype":"locality"
},
  "geometry": {"coordinates":[-2.31667,37.36667],"type":"Point"}
}