{
  "type": "Feature",
  "properties": {
    "gn:admin1_code":"58",
    "gn:admin2_code":"PO",
    "gn:admin3_code":"36043",
    "gn:asciiname":"Justanes",
    "gn:cc2":"ES",
    "gn:country_code":"ES",
    "gn:dem":238,
    "gn:feature_class":"P",
    "gn:feature_code":"PPL",
    "gn:name":"Justanes",
    "gn:population":0,
    "gn:timezone":"Europe/Madrid",
    "iso:country":"ES",
    "name:und_x_variant":[
        "San Mart\u00edn",
        "Justanes"
    ],
    "wof:name":"Justanes",
    "wof:placetype":"locality"
},
  "geometry": {"coordinates":[-8.56265,42.39429000000001],"type":"Point"}
}