{
  "type": "Feature",
  "properties": {
    "gn:admin1_code":"51",
    "gn:admin2_code":"H",
    "gn:admin3_code":"21078",
    "gn:asciiname":"El Villar",
    "gn:country_code":"ES",
    "gn:dem":333,
    "gn:feature_class":"P",
    "gn:feature_code":"PPL",
    "gn:name":"El Villar",
    "gn:population":0,
    "gn:timezone":"Europe/Madrid",
    "iso:country":"ES",
    "name:ceb_x_preferred":[
        "El Villar"
    ],
    "name:spa_x_preferred":[
        "El Villar"
    ],
    "name:swe_x_preferred":[
        "El Villar"
    ],
    "wof:name":"El Villar",
    "wof:placetype":"locality"
},
  "geometry": {"coordinates":[-6.73867,37.69364],"type":"Point"}
}