{
  "type": "Feature",
  "properties": {
    "iso:country":"ES",
    "name:spa_x_preferred":[
        "Matico"
    ],
    "wof:name":"Matiko",
    "wof:placetype":"neighbourhood"
},
  "geometry": {"coordinates":[-2.92543422090851,43.26881904291093],"type":"Point"}
}