{
  "type": "Feature",
  "properties": {
    "gn:admin1_code":"27",
    "gn:admin2_code":"LO",
    "gn:admin3_code":"26047",
    "gn:asciiname":"Valdegutur",
    "gn:country_code":"ES",
    "gn:dem":564,
    "gn:feature_class":"P",
    "gn:feature_code":"PPL",
    "gn:name":"Valdegutur",
    "gn:population":0,
    "gn:timezone":"Europe/Madrid",
    "iso:country":"ES",
    "wof:name":"Valdegutur",
    "wof:placetype":"locality"
},
  "geometry": {"coordinates":[-1.90417,41.97446],"type":"Point"}
}