{
  "type": "Feature",
  "properties": {
    "gn:gn_country":"ES",
    "gn:gn_fcode":"PPLA3",
    "gn:gn_pop":174,
    "gn:population":174,
    "iso:country":"ES",
    "name:arg_x_preferred":[
        "Dios le Guarde"
    ],
    "name:ast_x_preferred":[
        "Dios le Guarde"
    ],
    "name:cat_x_preferred":[
        "Dios le Guarde"
    ],
    "name:ceb_x_preferred":[
        "Dios le Guarde"
    ],
    "name:eng_x_preferred":[
        "Dios le Guarde"
    ],
    "name:eus_x_preferred":[
        "Dios le Guarde"
    ],
    "name:fra_x_preferred":[
        "Dios le Guarde"
    ],
    "name:haw_x_preferred":[
        "Dios le Guarde"
    ],
    "name:hun_x_preferred":[
        "Dios le Guarde"
    ],
    "name:ina_x_preferred":[
        "Dios le Guarde"
    ],
    "name:ita_x_preferred":[
        "Dios le Guarde"
    ],
    "name:kaz_x_preferred":[
        "\u0414\u0438\u043e\u0441-\u043b\u0435-\u0413\u0432\u0430\u0440\u0434\u0435"
    ],
    "name:msa_x_preferred":[
        "Dios le Guarde"
    ],
    "name:nan_x_preferred":[
        "Dios le Guarde"
    ],
    "name:nld_x_preferred":[
        "Dios le Guarde"
    ],
    "name:oci_x_preferred":[
        "Dios le Guarde"
    ],
    "name:pol_x_preferred":[
        "Dios le Guarde"
    ],
    "name:por_x_preferred":[
        "Dios le Guarde"
    ],
    "name:rup_x_preferred":[
        "Dios le Guarde"
    ],
    "name:rus_x_preferred":[
        "\u0414\u0438\u043e\u0441-\u043b\u0435-\u0413\u0432\u0430\u0440\u0434\u0435"
    ],
    "name:spa_x_preferred":[
        "Dios le Guarde"
    ],
    "name:swe_x_preferred":[
        "Dios le Guarde"
    ],
    "name:ukr_x_preferred":[
        "\u0414\u0456\u043e\u0441-\u043b\u0435-\u0413\u0443\u0430\u0440\u0434\u0435"
    ],
    "name:vie_x_preferred":[
        "Dios le Guarde"
    ],
    "name:war_x_preferred":[
        "Dios le Guarde"
    ],
    "name:zho_x_preferred":[
        "\u8fea\u5965\u65af\u83b1\u74dc\u5c14\u5fb7"
    ],
    "qs_pg:aaroncc":"ES",
    "qs_pg:gn_country":"ES",
    "qs_pg:gn_fcode":"PPLA3",
    "qs_pg:gn_pop":174,
    "qs_pg:name":"Dios le Guarde",
    "qs_pg:name_adm0":"Espa\u00f1a",
    "qs_pg:name_adm1":"Castilla y Le\u00f3n",
    "qs_pg:photos_9r":0,
    "qs_pg:photos_sr":0,
    "qs_pg:pop_sr":1,
    "qs_pg:qs_pg_placetype":"locality",
    "qs_pg:qs_pg_placetype_gp":"Town",
    "qs_pg:woe_adm0":23424950,
    "woe:adm0_id":23424950,
    "woe:name_adm0":"Espa\u00f1a",
    "woe:name_adm1":"Castilla y Le\u00f3n",
    "woe:placetype":"Town",
    "wof:name":"Dios le Guarde",
    "wof:placetype":"locality",
    "wof:population":174
},
  "geometry": {"coordinates":[-6.31511,40.64283],"type":"Point"}
}