{
  "type": "Feature",
  "properties": {
    "gn:admin1_code":"58",
    "gn:admin2_code":"PO",
    "gn:admin3_code":"36022",
    "gn:asciiname":"Quinteiros",
    "gn:country_code":"ES",
    "gn:dem":37,
    "gn:feature_class":"P",
    "gn:feature_code":"PPL",
    "gn:name":"Quinteiros",
    "gn:population":0,
    "gn:timezone":"Europe/Madrid",
    "iso:country":"ES",
    "wof:name":"Quinteiros",
    "wof:placetype":"locality"
},
  "geometry": {"coordinates":[-8.91667,42.46667],"type":"Point"}
}