{
  "type": "Feature",
  "properties": {
    "gn:admin1_code":"52",
    "gn:admin2_code":"HU",
    "gn:admin3_code":"22112",
    "gn:asciiname":"Miralsot",
    "gn:country_code":"ES",
    "gn:dem":149,
    "gn:feature_class":"P",
    "gn:feature_code":"PPL",
    "gn:name":"Miralsot",
    "gn:population":0,
    "gn:timezone":"Europe/Madrid",
    "iso:country":"ES",
    "name:cat_x_preferred":[
        "Miralsot"
    ],
    "wof:name":"Miralsot",
    "wof:placetype":"locality"
},
  "geometry": {"coordinates":[0.29346,41.55343],"type":"Point"}
}