{
  "type": "Feature",
  "properties": {
    "gn:admin1_code":"58",
    "gn:admin2_code":"OR",
    "gn:admin3_code":"32013",
    "gn:asciiname":"Pazos",
    "gn:country_code":"ES",
    "gn:dem":149,
    "gn:feature_class":"P",
    "gn:feature_code":"PPL",
    "gn:name":"Pazos",
    "gn:population":0,
    "gn:timezone":"Europe/Madrid",
    "iso:country":"ES",
    "name:und_x_variant":[
        "San Salvador",
        "Pazos"
    ],
    "wof:name":"Pazos",
    "wof:placetype":"locality"
},
  "geometry": {"coordinates":[-8.15023,42.39982],"type":"Point"}
}