{
  "type": "Feature",
  "properties": {
    "gn:admin1_code":"58",
    "gn:admin2_code":"C",
    "gn:admin3_code":"15045",
    "gn:asciiname":"Gueima",
    "gn:country_code":"ES",
    "gn:dem":384,
    "gn:feature_class":"P",
    "gn:feature_code":"PPL",
    "gn:name":"Gueima",
    "gn:population":0,
    "gn:timezone":"Europe/Madrid",
    "iso:country":"ES",
    "name:und_x_variant":[
        "Gucima",
        "Gueima"
    ],
    "wof:name":"Gueima",
    "wof:placetype":"locality"
},
  "geometry": {"coordinates":[-8.95117,42.95924],"type":"Point"}
}