{
  "type": "Feature",
  "properties": {
    "gn:gn_country":"ES",
    "gn:gn_fcode":"PPLA3",
    "gn:gn_pop":124,
    "gn:population":124,
    "iso:country":"ES",
    "name:ara_x_preferred":[
        "\u0628\u0627\u0631\u062f\u0627\u064a\u0644\u0627"
    ],
    "name:arg_x_preferred":[
        "Pardilla"
    ],
    "name:baq_x_preferred":[
        "Pardilla"
    ],
    "name:cat_x_preferred":[
        "Pardilla"
    ],
    "name:chi_x_preferred":[
        "\u5e15\u5c14\u8fea\u5229\u4e9a"
    ],
    "name:dut_x_preferred":[
        "Pardilla"
    ],
    "name:eng_x_preferred":[
        "Pardilla"
    ],
    "name:epo_x_preferred":[
        "Pardilla"
    ],
    "name:fre_x_preferred":[
        "Pardilla"
    ],
    "name:glg_x_preferred":[
        "Pardilla"
    ],
    "name:haw_x_preferred":[
        "Pardilla"
    ],
    "name:hun_x_preferred":[
        "Pardilla"
    ],
    "name:ina_x_preferred":[
        "Pardilla"
    ],
    "name:ita_x_preferred":[
        "Pardilla"
    ],
    "name:may_x_preferred":[
        "Pardilla"
    ],
    "name:nan_x_preferred":[
        "Pardilla"
    ],
    "name:oci_x_preferred":[
        "Pardilla"
    ],
    "name:per_x_preferred":[
        "\u067e\u0627\u0631\u062f\u06cc\u06cc\u0627"
    ],
    "name:pol_x_preferred":[
        "Pardilla"
    ],
    "name:por_x_preferred":[
        "Pardilla"
    ],
    "name:rus_x_preferred":[
        "\u041f\u0430\u0440\u0434\u0438\u043b\u044c\u044f"
    ],
    "name:spa_x_preferred":[
        "Pardilla"
    ],
    "name:swe_x_preferred":[
        "Pardilla"
    ],
    "name:ukr_x_preferred":[
        "\u041f\u0430\u0440\u0434\u0456\u043b\u044c\u044f"
    ],
    "name:unk_x_variant":[
        "Pardillo"
    ],
    "name:vie_x_preferred":[
        "Pardilla"
    ],
    "name:war_x_preferred":[
        "Pardilla"
    ],
    "qs_pg:aaroncc":"ES",
    "qs_pg:gn_country":"ES",
    "qs_pg:gn_fcode":"PPLA3",
    "qs_pg:gn_pop":124,
    "qs_pg:name":"Pardilla",
    "qs_pg:name_adm0":"Espa\u00f1a",
    "qs_pg:name_adm1":"Castilla y Le\u00f3n",
    "qs_pg:photos_9k":1,
    "qs_pg:photos_9r":1,
    "qs_pg:photos_all":1,
    "qs_pg:photos_sr":0,
    "qs_pg:pop_sr":1,
    "qs_pg:qs_pg_placetype":"locality",
    "qs_pg:qs_pg_placetype_gp":"Town",
    "qs_pg:woe_adm0":23424950,
    "woe:adm0_id":23424950,
    "woe:name_adm0":"Espa\u00f1a",
    "woe:name_adm1":"Castilla y Le\u00f3n",
    "woe:placetype":"Town",
    "wof:name":"Pardilla",
    "wof:placetype":"locality",
    "wof:population":124
},
  "geometry": {"coordinates":[-3.71089,41.55183],"type":"Point"}
}