{
  "type": "Feature",
  "properties": {
    "gn:gn_country":"ES",
    "gn:gn_fcode":"PPLA3",
    "gn:gn_pop":415,
    "gn:population":415,
    "iso:country":"ES",
    "name:ara_x_preferred":[
        "\u0625\u064a\u0644\u0644\u0627\u0631"
    ],
    "name:cat_x_preferred":[
        "Illar"
    ],
    "name:eng_x_preferred":[
        "\u00cdllar"
    ],
    "name:epo_x_preferred":[
        "\u00cdllar"
    ],
    "name:eus_x_preferred":[
        "\u00cdllar"
    ],
    "name:fas_x_preferred":[
        "\u0627\u06cc\u06cc\u0627\u0631"
    ],
    "name:fra_x_preferred":[
        "\u00cdllar"
    ],
    "name:hat_x_preferred":[
        "Illar"
    ],
    "name:hun_x_preferred":[
        "\u00cdllar"
    ],
    "name:hye_x_preferred":[
        "\u053b\u056c\u0575\u0561\u0580"
    ],
    "name:ina_x_preferred":[
        "\u00cdllar"
    ],
    "name:ita_x_preferred":[
        "Illar"
    ],
    "name:mkd_x_preferred":[
        "\u0418\u043b\u0430\u0440"
    ],
    "name:msa_x_preferred":[
        "\u00cdllar"
    ],
    "name:nan_x_preferred":[
        "\u00cdllar"
    ],
    "name:nld_x_preferred":[
        "Illar"
    ],
    "name:oci_x_preferred":[
        "Illar"
    ],
    "name:pol_x_preferred":[
        "Illar"
    ],
    "name:por_x_preferred":[
        "\u00cdllar"
    ],
    "name:ron_x_preferred":[
        "Illar"
    ],
    "name:rus_x_preferred":[
        "\u0418\u043b\u044c\u044f\u0440"
    ],
    "name:spa_x_preferred":[
        "\u00cdllar"
    ],
    "name:swe_x_preferred":[
        "Illar"
    ],
    "name:tur_x_preferred":[
        "\u00cdllar"
    ],
    "name:ukr_x_preferred":[
        "\u0406\u043b\u044c\u044f\u0440"
    ],
    "name:uzb_x_preferred":[
        "Illar"
    ],
    "name:vie_x_preferred":[
        "Illar"
    ],
    "name:war_x_preferred":[
        "Illar"
    ],
    "name:zho_x_preferred":[
        "\u4f0a\u5229\u4e9a\u5c14"
    ],
    "qs_pg:aaroncc":"ES",
    "qs_pg:gn_country":"ES",
    "qs_pg:gn_fcode":"PPLA3",
    "qs_pg:gn_pop":415,
    "qs_pg:name":"Illar",
    "qs_pg:name_adm0":"Espa\u00f1a",
    "qs_pg:name_adm1":"Andaluc\u00eda",
    "qs_pg:photos_9r":0,
    "qs_pg:photos_sr":0,
    "qs_pg:pop_sr":2,
    "qs_pg:qs_pg_placetype":"locality",
    "qs_pg:qs_pg_placetype_gp":"Town",
    "qs_pg:woe_adm0":23424950,
    "woe:adm0_id":23424950,
    "woe:name_adm0":"Espa\u00f1a",
    "woe:name_adm1":"Andaluc\u00eda",
    "woe:placetype":"Town",
    "wof:name":"Illar",
    "wof:placetype":"locality",
    "wof:population":415
},
  "geometry": {"coordinates":[-2.63871,36.98562],"type":"Point"}
}