{
  "type": "Feature",
  "properties": {
    "gn:admin1_code":"34",
    "gn:admin2_code":"O",
    "gn:admin3_code":"33076",
    "gn:asciiname":"Cueli",
    "gn:country_code":"ES",
    "gn:dem":170,
    "gn:feature_class":"P",
    "gn:feature_code":"PPL",
    "gn:name":"Cueli",
    "gn:population":0,
    "gn:timezone":"Europe/Madrid",
    "iso:country":"ES",
    "wof:name":"Cueli",
    "wof:placetype":"locality"
},
  "geometry": {"coordinates":[-5.38176,43.48269000000001],"type":"Point"}
}