{
  "type": "Feature",
  "properties": {
    "gn:admin1_code":"55",
    "gn:admin2_code":"LE",
    "gn:admin3_code":"24019",
    "gn:asciiname":"Langre",
    "gn:country_code":"ES",
    "gn:dem":892,
    "gn:feature_class":"P",
    "gn:feature_code":"PPL",
    "gn:name":"Langre",
    "gn:population":0,
    "gn:timezone":"Europe/Madrid",
    "iso:country":"ES",
    "wof:name":"Langre",
    "wof:placetype":"locality"
},
  "geometry": {"coordinates":[-6.56573,42.73547],"type":"Point"}
}