{
  "type": "Feature",
  "properties": {
    "gn:admin1_code":"60",
    "gn:admin2_code":"A",
    "gn:admin3_code":"03132",
    "gn:asciiname":"Alcoyes",
    "gn:country_code":"ES",
    "gn:dem":843,
    "gn:feature_class":"P",
    "gn:feature_code":"PPL",
    "gn:name":"Alcoyes",
    "gn:population":0,
    "gn:timezone":"Europe/Madrid",
    "iso:country":"ES",
    "name:und_x_variant":[
        "Casa Alcoyes",
        "Alcoyes"
    ],
    "wof:name":"Alcoyes",
    "wof:placetype":"locality"
},
  "geometry": {"coordinates":[-0.40364,38.62151],"type":"Point"}
}