{
  "type": "Feature",
  "properties": {
    "gn:gn_country":"ES",
    "gn:gn_fcode":"PPL",
    "gn:gn_pop":220,
    "gn:population":220,
    "iso:country":"ES",
    "name:arg_x_preferred":[
        "Uzt\u00e1rroz"
    ],
    "name:baq_x_preferred":[
        "Uztarroze"
    ],
    "name:bre_x_preferred":[
        "Uztarroze"
    ],
    "name:cat_x_preferred":[
        "Uztarroze"
    ],
    "name:chi_x_preferred":[
        "\u4e4c\u65af\u5854\u7f57\u65af"
    ],
    "name:dut_x_preferred":[
        "Uzt\u00e1rroz"
    ],
    "name:eng_x_preferred":[
        "Uzt\u00e1rroz \u2013 Uztarrotze"
    ],
    "name:fre_x_preferred":[
        "Uzt\u00e1rroz"
    ],
    "name:hun_x_preferred":[
        "Uzt\u00e1rroz \u2013 Uztarrotze"
    ],
    "name:ita_x_preferred":[
        "Uzt\u00e1rroz"
    ],
    "name:jpn_x_preferred":[
        "\u30a6\u30b9\u30bf\u30ed\u30b9/\u30a6\u30b9\u30bf\u30ed\u30bb"
    ],
    "name:may_x_preferred":[
        "Uzt\u00e1rroz \u2013 Uztarrotze"
    ],
    "name:nan_x_preferred":[
        "Uzt\u00e1rroz \u2013 Uztarrotze"
    ],
    "name:oci_x_preferred":[
        "Uztarroze"
    ],
    "name:pol_x_preferred":[
        "Uzt\u00e1rroz"
    ],
    "name:por_x_preferred":[
        "Uzt\u00e1rroz"
    ],
    "name:rus_x_preferred":[
        "\u0423\u0441\u0442\u0430\u0440\u0440\u043e\u0441"
    ],
    "name:spa_x_preferred":[
        "Uzt\u00e1rroz"
    ],
    "name:ukr_x_preferred":[
        "\u0423\u0441\u0442\u0430\u0440\u0440\u043e\u0441"
    ],
    "name:uzb_x_preferred":[
        "Uzt\u00e1rroz"
    ],
    "name:vie_x_preferred":[
        "Uzt\u00e1rroz - Uztarrotze"
    ],
    "name:war_x_preferred":[
        "Uzt\u00e1rroz"
    ],
    "qs_pg:aaroncc":"ES",
    "qs_pg:gn_country":"ES",
    "qs_pg:gn_fcode":"PPL",
    "qs_pg:gn_pop":220,
    "qs_pg:name":"Ust\u00e1rroz",
    "qs_pg:name_adm0":"Espa\u00f1a",
    "qs_pg:name_adm1":"Comunidad Foral de Navarra",
    "qs_pg:photos_9r":0,
    "qs_pg:photos_sr":0,
    "qs_pg:pop_sr":2,
    "qs_pg:qs_pg_placetype":"locality",
    "qs_pg:qs_pg_placetype_gp":"Town",
    "qs_pg:woe_adm0":23424950,
    "woe:adm0_id":23424950,
    "woe:name_adm0":"Espa\u00f1a",
    "woe:name_adm1":"Comunidad Foral de Navarra",
    "woe:placetype":"Town",
    "wof:name":"Ust\u00e1rroz",
    "wof:placetype":"locality",
    "wof:population":220
},
  "geometry": {"coordinates":[-0.92689,42.88395],"type":"Point"}
}