{
  "type": "Feature",
  "properties": {
    "gn:admin1_code":"34",
    "gn:admin2_code":"O",
    "gn:admin3_code":"33077",
    "gn:asciiname":"Barandon",
    "gn:country_code":"ES",
    "gn:dem":557,
    "gn:feature_class":"P",
    "gn:feature_code":"PPL",
    "gn:name":"Barand\u00f3n",
    "gn:population":0,
    "gn:timezone":"Europe/Madrid",
    "iso:country":"ES",
    "name:und_x_variant":[
        "Barand\u00f3n"
    ],
    "wof:name":"Barandon",
    "wof:placetype":"locality"
},
  "geometry": {"coordinates":[-6.75538,43.34089],"type":"Point"}
}