{
  "type": "Feature",
  "properties": {
    "gn:admin1_code":"58",
    "gn:admin2_code":"LU",
    "gn:admin3_code":"27060",
    "gn:asciiname":"Gondulfe",
    "gn:country_code":"ES",
    "gn:dem":599,
    "gn:feature_class":"P",
    "gn:feature_code":"PPL",
    "gn:name":"Gondulfe",
    "gn:population":0,
    "gn:timezone":"Europe/Madrid",
    "iso:country":"ES",
    "wof:name":"Gondulfe",
    "wof:placetype":"locality"
},
  "geometry": {"coordinates":[-7.80408,42.70091],"type":"Point"}
}