{
  "type": "Feature",
  "properties": {
    "gn:admin1_code":"34",
    "gn:admin2_code":"O",
    "gn:admin3_code":"33036",
    "gn:asciiname":"Calduenin",
    "gn:country_code":"ES",
    "gn:dem":160,
    "gn:feature_class":"P",
    "gn:feature_code":"PPL",
    "gn:name":"Caldue\u00f1\u00edn",
    "gn:population":0,
    "gn:timezone":"Europe/Madrid",
    "iso:country":"ES",
    "name:und_x_variant":[
        "Caldue\u00f1\u00edn"
    ],
    "wof:name":"Calduenin",
    "wof:placetype":"locality"
},
  "geometry": {"coordinates":[-4.86642,43.37952],"type":"Point"}
}