{
  "type": "Feature",
  "properties": {
    "gn:admin1_code":"39",
    "gn:admin2_code":"S",
    "gn:admin3_code":"39096",
    "gn:asciiname":"Vada",
    "gn:country_code":"ES",
    "gn:dem":830,
    "gn:feature_class":"P",
    "gn:feature_code":"PPL",
    "gn:name":"Vada",
    "gn:population":0,
    "gn:timezone":"Europe/Madrid",
    "iso:country":"ES",
    "name:ceb_x_preferred":[
        "Vada"
    ],
    "name:deu_x_preferred":[
        "Vada"
    ],
    "name:ita_x_preferred":[
        "Vada"
    ],
    "name:nld_x_preferred":[
        "Vada"
    ],
    "name:swe_x_preferred":[
        "Vada"
    ],
    "wof:name":"Vada",
    "wof:placetype":"locality"
},
  "geometry": {"coordinates":[-4.66667,43.08333],"type":"Point"}
}