{
  "type": "Feature",
  "properties": {
    "gn:admin1_code":"51",
    "gn:admin2_code":"CA",
    "gn:admin3_code":"11030",
    "gn:asciiname":"Las Brevas",
    "gn:country_code":"ES",
    "gn:dem":57,
    "gn:feature_class":"P",
    "gn:feature_code":"PPL",
    "gn:name":"Las Brevas",
    "gn:population":0,
    "gn:timezone":"Europe/Madrid",
    "iso:country":"ES",
    "name:und_x_variant":[
        "Caser\u00edo Las Brevas",
        "Las Brevas"
    ],
    "wof:name":"Las Brevas",
    "wof:placetype":"locality"
},
  "geometry": {"coordinates":[-6.37547,36.71465],"type":"Point"}
}