{
  "type": "Feature",
  "properties": {
    "gn:admin1_code":"31",
    "gn:admin2_code":"MU",
    "gn:admin3_code":"30024",
    "gn:asciiname":"Fuente Atocha",
    "gn:country_code":"ES",
    "gn:dem":842,
    "gn:feature_class":"P",
    "gn:feature_code":"PPL",
    "gn:name":"Fuente Atocha",
    "gn:population":0,
    "gn:timezone":"Europe/Madrid",
    "iso:country":"ES",
    "name:und_x_variant":[
        "Caser\u00edo de Fuente Atocha",
        "Caser\u00edo Fuente Atocha",
        "Fuente Atocha"
    ],
    "wof:name":"Fuente Atocha",
    "wof:placetype":"locality"
},
  "geometry": {"coordinates":[-1.93982,37.89171],"type":"Point"}
}