{
  "type": "Feature",
  "properties": {
    "gn:admin1_code":"51",
    "gn:admin2_code":"SE",
    "gn:admin3_code":"41099",
    "gn:asciiname":"Alcornocalejo",
    "gn:country_code":"ES",
    "gn:dem":100,
    "gn:feature_class":"P",
    "gn:feature_code":"PPL",
    "gn:name":"Alcornocalejo",
    "gn:population":0,
    "gn:timezone":"Europe/Madrid",
    "iso:country":"ES",
    "name:und_x_variant":[
        "Caser\u00edo Alcornocalejo",
        "Alcornocalejo"
    ],
    "wof:name":"Alcornocalejo",
    "wof:placetype":"locality"
},
  "geometry": {"coordinates":[-5.77497,37.64542],"type":"Point"}
}