{
  "type": "Feature",
  "properties": {
    "gn:admin1_code":"58",
    "gn:admin2_code":"LU",
    "gn:admin3_code":"27018",
    "gn:asciiname":"Arrojo",
    "gn:cc2":"ES",
    "gn:country_code":"ES",
    "gn:dem":738,
    "gn:feature_class":"P",
    "gn:feature_code":"PPL",
    "gn:name":"Arroj\u00f3",
    "gn:population":0,
    "gn:timezone":"Europe/Madrid",
    "iso:country":"ES",
    "name:und_x_variant":[
        "San Martin",
        "Arroj\u00f3"
    ],
    "wof:name":"Arrojo",
    "wof:placetype":"locality"
},
  "geometry": {"coordinates":[-7.05,43.05],"type":"Point"}
}