{
  "type": "Feature",
  "properties": {
    "gn:admin1_code":"34",
    "gn:admin2_code":"O",
    "gn:admin3_code":"33072",
    "gn:asciiname":"Villanueva",
    "gn:country_code":"ES",
    "gn:dem":686,
    "gn:feature_class":"P",
    "gn:feature_code":"PPL",
    "gn:name":"Villanueva",
    "gn:population":0,
    "gn:timezone":"Europe/Madrid",
    "iso:country":"ES",
    "name:ast_x_preferred":[
        "Vi\u1e37\u1e37anueva"
    ],
    "name:ben_x_preferred":[
        "\u09ad\u09bf\u09b2\u09be\u09a8\u09c1\u09df\u09c7\u09ad\u09be"
    ],
    "name:deu_x_preferred":[
        "Villanueva"
    ],
    "name:ell_x_preferred":[
        "\u0392\u03b9\u03bb\u03b1\u03bd\u03bf\u03cd\u03b5\u03b2\u03b1"
    ],
    "name:fas_x_preferred":[
        "\u0648\u06cc\u0644\u0627\u0646\u0648\u0626\u0632\u0627"
    ],
    "name:heb_x_preferred":[
        "\u05d5\u05d9\u05dc\u05d0\u05e0\u05d5\u05d0\u05d1\u05d4"
    ],
    "name:hin_x_preferred":[
        "\u0935\u093f\u0932\u093e\u0928\u094d\u092f\u0942\u0935\u093e"
    ],
    "name:hun_x_preferred":[
        "Villanueva"
    ],
    "name:ind_x_preferred":[
        "Villanueva"
    ],
    "name:ita_x_preferred":[
        "Villanueva"
    ],
    "name:kor_x_preferred":[
        "\ube4c\ub77c\ub204\uc5d0\ubc14"
    ],
    "name:pol_x_preferred":[
        "Villanueva"
    ],
    "name:spa_x_preferred":[
        "Villanueva"
    ],
    "name:tur_x_preferred":[
        "Villanueva"
    ],
    "name:ukr_x_preferred":[
        "\u0412\u0456\u043b\u0430\u043d\u0443\u0435\u0432\u0430"
    ],
    "name:urd_x_preferred":[
        "\u0648\u0644\u0627\u0646\u06cc\u0648\u0627"
    ],
    "name:zho_cn_x_preferred":[
        "\u6bd4\u4e9a\u52aa\u57c3\u74e6"
    ],
    "name:zho_tw_x_preferred":[
        "\u7dad\u62c9\u7d10\u74e6"
    ],
    "wof:name":"Villanueva",
    "wof:placetype":"locality"
},
  "geometry": {"coordinates":[-6.14169,43.14917],"type":"Point"}
}