{
  "type": "Feature",
  "properties": {
    "gn:admin1_code":"34",
    "gn:admin2_code":"O",
    "gn:admin3_code":"33037.0",
    "gn:asciiname":"A Cabana",
    "gn:country_code":"ES",
    "gn:dem":649,
    "gn:feature_class":"P",
    "gn:feature_code":"PPL",
    "gn:name":"A Cabana",
    "gn:population":0,
    "gn:timezone":"Europe/Madrid",
    "iso:country":"ES",
    "wof:name":"A Cabana",
    "wof:placetype":"locality"
},
  "geometry": {"coordinates":[-5.72911,43.21984000000001],"type":"Point"}
}