{
  "type": "Feature",
  "properties": {
    "gn:gn_country":"ES",
    "gn:gn_fcode":"PPLA3",
    "gn:gn_pop":410,
    "gn:population":410,
    "iso:country":"ES",
    "name:arg_x_preferred":[
        "Bola\u00f1os de Campos"
    ],
    "name:arm_x_preferred":[
        "\u0532\u0578\u056c\u0561\u0576\u0575\u0578\u057d \u0564\u0565 \u053f\u0561\u0574\u057a\u0578\u057d"
    ],
    "name:baq_x_preferred":[
        "Bola\u00f1os de Campos"
    ],
    "name:cat_x_preferred":[
        "Bola\u00f1os de Campos"
    ],
    "name:chi_x_preferred":[
        "\u535a\u62c9\u5c3c\u5965\u65af\u5fb7\u574e\u6ce2\u65af"
    ],
    "name:dut_x_preferred":[
        "Bola\u00f1os de Campos"
    ],
    "name:eng_x_preferred":[
        "Bola\u00f1os de Campos"
    ],
    "name:fre_x_preferred":[
        "Bola\u00f1os de Campos"
    ],
    "name:hun_x_preferred":[
        "Bola\u00f1os de Campos"
    ],
    "name:ina_x_preferred":[
        "Bola\u00f1os de Campos"
    ],
    "name:ita_x_preferred":[
        "Bola\u00f1os de Campos"
    ],
    "name:may_x_preferred":[
        "Bola\u00f1os de Campos"
    ],
    "name:nan_x_preferred":[
        "Bola\u00f1os de Campos"
    ],
    "name:oci_x_preferred":[
        "Bola\u00f1os de Campos"
    ],
    "name:per_x_preferred":[
        "\u0628\u0644\u0627\u0646\u06cc\u0633 \u062f \u06a9\u0627\u0645\u067e\u0633"
    ],
    "name:pol_x_preferred":[
        "Bola\u00f1os de Campos"
    ],
    "name:por_x_preferred":[
        "Bola\u00f1os de Campos"
    ],
    "name:rus_x_preferred":[
        "\u0411\u043e\u043b\u0430\u043d\u044c\u043e\u0441-\u0434\u0435-\u041a\u0430\u043c\u043f\u043e\u0441"
    ],
    "name:spa_x_preferred":[
        "Bola\u00f1os de Campos"
    ],
    "name:swe_x_preferred":[
        "Bola\u00f1os de Campos"
    ],
    "name:ukr_x_preferred":[
        "\u0411\u043e\u043b\u0430\u043d\u044c\u0439\u043e\u0441-\u0434\u0435-\u041a\u0430\u043c\u043f\u043e\u0441"
    ],
    "name:vie_x_preferred":[
        "Bola\u00f1os de Campos"
    ],
    "name:war_x_preferred":[
        "Bola\u00f1os de Campos"
    ],
    "qs_pg:aaroncc":"ES",
    "qs_pg:gn_country":"ES",
    "qs_pg:gn_fcode":"PPLA3",
    "qs_pg:gn_pop":410,
    "qs_pg:name":"Bola\u00f1os de Campos",
    "qs_pg:name_adm0":"Espa\u00f1a",
    "qs_pg:name_adm1":"Castilla y Le\u00f3n",
    "qs_pg:photos_9k":1,
    "qs_pg:photos_9r":1,
    "qs_pg:photos_all":1,
    "qs_pg:photos_sr":0,
    "qs_pg:pop_sr":2,
    "qs_pg:qs_pg_placetype":"locality",
    "qs_pg:qs_pg_placetype_gp":"Town",
    "qs_pg:woe_adm0":23424950,
    "woe:adm0_id":23424950,
    "woe:name_adm0":"Espa\u00f1a",
    "woe:name_adm1":"Castilla y Le\u00f3n",
    "woe:placetype":"Town",
    "wof:name":"Bola\u00f1os de Campos",
    "wof:placetype":"locality",
    "wof:population":410
},
  "geometry": {"coordinates":[-5.28428,42.0068],"type":"Point"}
}