{
  "type": "Feature",
  "properties": {
    "gn:admin1_code":"55",
    "gn:admin2_code":"LE",
    "gn:admin3_code":"24198",
    "gn:asciiname":"Lindoso",
    "gn:country_code":"ES",
    "gn:dem":996,
    "gn:feature_class":"P",
    "gn:feature_code":"PPL",
    "gn:name":"Lindoso",
    "gn:population":0,
    "gn:timezone":"Europe/Madrid",
    "iso:country":"ES",
    "wof:name":"Lindoso",
    "wof:placetype":"locality"
},
  "geometry": {"coordinates":[-7.00193,42.6676],"type":"Point"}
}