{
  "type": "Feature",
  "properties": {
    "gn:admin1_code":"58",
    "gn:admin2_code":"LU",
    "gn:admin3_code":"27005",
    "gn:asciiname":"Forxan",
    "gn:country_code":"ES",
    "gn:dem":50,
    "gn:feature_class":"P",
    "gn:feature_code":"PPL",
    "gn:name":"Forx\u00e1n",
    "gn:population":0,
    "gn:timezone":"Europe/Madrid",
    "iso:country":"ES",
    "wof:name":"Forxan",
    "wof:placetype":"locality"
},
  "geometry": {"coordinates":[-7.26667,43.56667],"type":"Point"}
}