{
  "type": "Feature",
  "properties": {
    "iso:country":"ES",
    "name:spa_x_preferred":[
        "Igollo"
    ],
    "name:und_x_variant":[
        "Igollo de Camargo"
    ],
    "qs:a0":"Espa\u00f1a",
    "qs:a1":"*Cantabria",
    "qs:a1r":"0Cantabria",
    "qs:adm0":"Espa\u00f1a",
    "qs:la_lc":"*",
    "qs:level":"locality",
    "qs:loc":"Igollo",
    "qs:loc_alt":"Igollo",
    "qs:pop":0,
    "qs:type":"buffered point",
    "wof:lang":[
        "spa"
    ],
    "wof:name":"Igollo",
    "wof:placetype":"locality"
},
  "geometry": {"coordinates":[-3.88262,43.428111],"type":"Point"}
}