{
  "type": "Feature",
  "properties": {
    "gn:admin1_code":"07",
    "gn:admin2_code":"PM",
    "gn:admin3_code":"07026",
    "gn:asciiname":"Figueretes",
    "gn:country_code":"ES",
    "gn:dem":6,
    "gn:feature_class":"P",
    "gn:feature_code":"PPL",
    "gn:name":"Figueretes",
    "gn:population":0,
    "gn:timezone":"Europe/Madrid",
    "iso:country":"ES",
    "name:cat_x_preferred":[
        "Figueretes"
    ],
    "name:spa_x_preferred":[
        "Figueretes"
    ],
    "wof:name":"Figueretes",
    "wof:placetype":"locality"
},
  "geometry": {"coordinates":[1.41621,38.90105],"type":"Point"}
}