{
  "type": "Feature",
  "properties": {
    "gn:admin1_code":"55",
    "gn:admin2_code":"SO",
    "gn:admin3_code":"42162",
    "gn:asciiname":"Matanza de Soria",
    "gn:country_code":"ES",
    "gn:dem":918,
    "gn:feature_class":"P",
    "gn:feature_code":"PPL",
    "gn:name":"Matanza de Soria",
    "gn:population":0,
    "gn:timezone":"Europe/Madrid",
    "iso:country":"ES",
    "wof:name":"Matanza de Soria",
    "wof:placetype":"locality"
},
  "geometry": {"coordinates":[-3.2125,41.63542],"type":"Point"}
}