{
  "type": "Feature",
  "properties": {
    "gn:admin1_code":"59",
    "gn:admin2_code":"BI",
    "gn:admin3_code":"48053",
    "gn:asciiname":"Urresti",
    "gn:country_code":"ES",
    "gn:dem":12,
    "gn:feature_class":"P",
    "gn:feature_code":"PPL",
    "gn:name":"Urresti",
    "gn:population":0,
    "gn:timezone":"Europe/Madrid",
    "iso:country":"ES",
    "wof:name":"Urresti",
    "wof:placetype":"locality"
},
  "geometry": {"coordinates":[-2.91905,43.36343],"type":"Point"}
}