{
  "type": "Feature",
  "properties": {
    "gn:admin1_code":"58",
    "gn:admin2_code":"OR",
    "gn:admin3_code":"32076",
    "gn:asciiname":"Longos",
    "gn:country_code":"ES",
    "gn:dem":468,
    "gn:feature_class":"P",
    "gn:feature_code":"PPL",
    "gn:name":"Longos",
    "gn:population":0,
    "gn:timezone":"Europe/Madrid",
    "iso:country":"ES",
    "wof:name":"Longos",
    "wof:placetype":"locality"
},
  "geometry": {"coordinates":[-8.01384,42.47299],"type":"Point"}
}