{
  "type": "Feature",
  "properties": {
    "gn:admin1_code":"34",
    "gn:admin2_code":"O",
    "gn:admin3_code":"33033",
    "gn:asciiname":"Felgueras",
    "gn:country_code":"ES",
    "gn:dem":526,
    "gn:feature_class":"P",
    "gn:feature_code":"PPL",
    "gn:name":"Felgueras",
    "gn:population":0,
    "gn:timezone":"Europe/Madrid",
    "iso:country":"ES",
    "wof:name":"Felgueras",
    "wof:placetype":"locality"
},
  "geometry": {"coordinates":[-5.79664,43.12549],"type":"Point"}
}