{
  "type": "Feature",
  "properties": {
    "gn:country":"ES",
    "gn:fcode":"PPL",
    "gn:population":476,
    "iso:country":"ES",
    "name:arg_x_preferred":[
        "Isaba"
    ],
    "name:bre_x_preferred":[
        "Izaba"
    ],
    "name:cat_x_preferred":[
        "Izaba"
    ],
    "name:ceb_x_preferred":[
        "Isaba"
    ],
    "name:cym_x_preferred":[
        "Isaba"
    ],
    "name:eng_x_preferred":[
        "Isaba"
    ],
    "name:eus_x_preferred":[
        "Izaba"
    ],
    "name:fin_x_preferred":[
        "Izaba"
    ],
    "name:fra_x_preferred":[
        "Isaba"
    ],
    "name:hun_x_preferred":[
        "Isaba"
    ],
    "name:hye_x_preferred":[
        "\u053b\u057d\u0561\u0562\u0561"
    ],
    "name:ita_x_preferred":[
        "Isaba"
    ],
    "name:jpn_x_preferred":[
        "\u30a4\u30b5\u30d0"
    ],
    "name:msa_x_preferred":[
        "Isaba"
    ],
    "name:nan_x_preferred":[
        "Isaba"
    ],
    "name:nld_x_preferred":[
        "Isaba"
    ],
    "name:oci_x_preferred":[
        "Izaba"
    ],
    "name:pol_x_preferred":[
        "Isaba"
    ],
    "name:por_x_preferred":[
        "Isaba"
    ],
    "name:rus_x_preferred":[
        "\u0418\u0441\u0430\u0431\u0430"
    ],
    "name:spa_x_preferred":[
        "Isaba"
    ],
    "name:swe_x_preferred":[
        "Isaba"
    ],
    "name:ukr_x_preferred":[
        "\u0406\u0441\u0430\u0431\u0430"
    ],
    "name:uzb_x_preferred":[
        "Isaba"
    ],
    "name:vie_x_preferred":[
        "Isaba"
    ],
    "name:war_x_preferred":[
        "Isaba"
    ],
    "name:zho_x_preferred":[
        "\u4f0a\u8428\u74e6"
    ],
    "qs_pg:aaroncc":"ES",
    "qs_pg:gn_country":"ES",
    "qs_pg:gn_fcode":"PPL",
    "qs_pg:gn_pop":476,
    "qs_pg:name":"Isaba",
    "qs_pg:name_adm0":"Espa\u00f1a",
    "qs_pg:name_adm1":"Comunidad Foral de Navarra",
    "qs_pg:photos":602,
    "qs_pg:photos_1k":122,
    "qs_pg:photos_9k":3,
    "qs_pg:photos_9r":0,
    "qs_pg:photos_all":602,
    "qs_pg:photos_sr":0,
    "qs_pg:pop_sr":2,
    "qs_pg:qs_pg_placetype":"locality",
    "qs_pg:qs_pg_placetype_gp":"Town",
    "qs_pg:woe_adm0":23424950,
    "wof:name":"Isaba",
    "wof:placetype":"locality",
    "wof:population":476
},
  "geometry": {"coordinates":[-0.92491,42.86017],"type":"Point"}
}