{
  "type": "Feature",
  "properties": {
    "gn:admin1_code":"51",
    "gn:admin2_code":"MA",
    "gn:admin3_code":"29049",
    "gn:asciiname":"Vadofresno",
    "gn:country_code":"ES",
    "gn:dem":341,
    "gn:feature_class":"P",
    "gn:feature_code":"PPL",
    "gn:name":"Vadofresno",
    "gn:population":0,
    "gn:timezone":"Europe/Madrid",
    "iso:country":"ES",
    "wof:name":"Vadofresno",
    "wof:placetype":"locality"
},
  "geometry": {"coordinates":[-4.42573,37.28225],"type":"Point"}
}