{
  "type": "Feature",
  "properties": {
    "gn:admin1_code":"34",
    "gn:admin2_code":"O",
    "gn:admin3_code":"33076",
    "gn:asciiname":"Singla",
    "gn:country_code":"ES",
    "gn:dem":234,
    "gn:feature_class":"P",
    "gn:feature_code":"PPL",
    "gn:name":"Singla",
    "gn:population":0,
    "gn:timezone":"Europe/Madrid",
    "iso:country":"ES",
    "wof:name":"Singla",
    "wof:placetype":"locality"
},
  "geometry": {"coordinates":[-5.44433,43.44675],"type":"Point"}
}