{
  "type": "Feature",
  "properties": {
    "gn:admin1_code":"55",
    "gn:admin2_code":"LE",
    "gn:admin3_code":"24176",
    "gn:asciiname":"Azares del Paramo",
    "gn:country_code":"ES",
    "gn:dem":783,
    "gn:feature_class":"P",
    "gn:feature_code":"PPL",
    "gn:name":"Azares del P\u00e1ramo",
    "gn:population":0,
    "gn:timezone":"Europe/Madrid",
    "iso:country":"ES",
    "name:und_x_variant":[
        "Azares del P\u00e1ramo"
    ],
    "wof:name":"Azares del Paramo",
    "wof:placetype":"locality"
},
  "geometry": {"coordinates":[-5.83075,42.29201],"type":"Point"}
}