{
  "type": "Feature",
  "properties": {
    "gn:gn_country":"ES",
    "gn:gn_fcode":"PPLA3",
    "gn:gn_pop":3003,
    "gn:population":3003,
    "iso:country":"ES",
    "name:ara_x_preferred":[
        "\u0628\u0627\u0631\u0633\u064a\u0646\u0627 \u062f\u064a \u0633\u0627\u064a\u0633\u064a\u0631\u0648"
    ],
    "name:hye_x_preferred":[
        "\u0532\u0561\u0580\u057d\u0565\u0576\u0561 \u0564\u0565 \u054d\u056b\u057d\u0565\u0580\u0578"
    ],
    "name:rus_x_preferred":[
        "\u0411\u0430\u0440\u0441\u0435\u043d\u0430-\u0434\u0435-\u0421\u0438\u0441\u0435\u0440\u043e"
    ],
    "name:ukr_x_preferred":[
        "\u0411\u0430\u0440\u0441\u0435\u043d\u0430-\u0434\u0435-\u0421\u0456\u0441\u0435\u0440\u043e"
    ],
    "name:unk_x_variant":[
        "B\u00e1rcena"
    ],
    "name:zho_x_preferred":[
        "\u5df4\u5c14\u585e\u7eb3\u5fb7\u897f\u585e\u7f57"
    ],
    "qs_pg:aaroncc":"ES",
    "qs_pg:gn_country":"ES",
    "qs_pg:gn_fcode":"PPLA3",
    "qs_pg:gn_pop":3003,
    "qs_pg:name":"B\u00e1rcena de Cicero",
    "qs_pg:name_adm0":"Espa\u00f1a",
    "qs_pg:name_adm1":"Cantabria",
    "qs_pg:photos":61,
    "qs_pg:photos_1k":12,
    "qs_pg:photos_9k":1,
    "qs_pg:photos_9r":2,
    "qs_pg:photos_all":61,
    "qs_pg:photos_sr":2,
    "qs_pg:pop_sr":4,
    "qs_pg:qs_pg_placetype":"locality",
    "qs_pg:qs_pg_placetype_gp":"Town",
    "qs_pg:woe_adm0":23424950,
    "woe:adm0_id":23424950,
    "woe:name_adm0":"Espa\u00f1a",
    "woe:name_adm1":"Cantabria",
    "woe:placetype":"Town",
    "wof:name":"B\u00e1rcena de Cicero",
    "wof:placetype":"locality",
    "wof:population":3003
},
  "geometry": {"coordinates":[-3.5103,43.4216],"type":"Point"}
}