{
  "type": "Feature",
  "properties": {
    "gn:gn_country":"ES",
    "gn:gn_fcode":"PPLA3",
    "gn:gn_pop":78,
    "gn:population":78,
    "iso:country":"ES",
    "name:arg_x_preferred":[
        "Bezas"
    ],
    "name:ast_x_preferred":[
        "Bezas"
    ],
    "name:bul_x_preferred":[
        "\u0411\u0435\u0437\u0430\u0441"
    ],
    "name:cat_x_preferred":[
        "Bezas"
    ],
    "name:ceb_x_preferred":[
        "Bezas"
    ],
    "name:eng_x_preferred":[
        "Bezas"
    ],
    "name:eus_x_preferred":[
        "Bezas"
    ],
    "name:fas_x_preferred":[
        "\u0628\u0633\u0627\u0633"
    ],
    "name:fra_x_preferred":[
        "Bezas"
    ],
    "name:hun_x_preferred":[
        "Bezas"
    ],
    "name:hye_x_preferred":[
        "\u0532\u0565\u057d\u0561\u057d"
    ],
    "name:ita_x_preferred":[
        "Bezas"
    ],
    "name:kaz_x_preferred":[
        "\u0411\u0435\u0441\u0430\u0441"
    ],
    "name:msa_x_preferred":[
        "Bezas"
    ],
    "name:nan_x_preferred":[
        "Bezas"
    ],
    "name:nld_x_preferred":[
        "Bezas"
    ],
    "name:oci_x_preferred":[
        "Bezas"
    ],
    "name:pol_x_preferred":[
        "Bezas"
    ],
    "name:por_x_preferred":[
        "Bezas"
    ],
    "name:rus_x_preferred":[
        "\u0411\u0435\u0441\u0430\u0441"
    ],
    "name:spa_x_preferred":[
        "Bezas"
    ],
    "name:sqi_x_preferred":[
        "Bezas"
    ],
    "name:swe_x_preferred":[
        "Bezas"
    ],
    "name:ukr_x_preferred":[
        "\u0411\u0435\u0441\u0430\u0441"
    ],
    "name:uzb_x_preferred":[
        "Bezas"
    ],
    "name:vie_x_preferred":[
        "Bezas"
    ],
    "name:war_x_preferred":[
        "Bezas"
    ],
    "name:zho_x_preferred":[
        "\u8d1d\u8428\u65af"
    ],
    "qs_pg:aaroncc":"ES",
    "qs_pg:gn_country":"ES",
    "qs_pg:gn_fcode":"PPLA3",
    "qs_pg:gn_pop":78,
    "qs_pg:name":"Bezas",
    "qs_pg:photos_9r":0,
    "qs_pg:photos_sr":0,
    "qs_pg:pop_sr":1,
    "qs_pg:qs_pg_placetype":"locality",
    "wof:name":"Bezas",
    "wof:placetype":"locality",
    "wof:population":78
},
  "geometry": {"coordinates":[-1.32511,40.33076],"type":"Point"}
}