{
  "type": "Feature",
  "properties": {
    "gn:admin1_code":"34",
    "gn:admin2_code":"O",
    "gn:admin3_code":"33073",
    "gn:asciiname":"Escarden",
    "gn:country_code":"ES",
    "gn:dem":498,
    "gn:feature_class":"P",
    "gn:feature_code":"PPL",
    "gn:name":"Escard\u00e9n",
    "gn:population":0,
    "gn:timezone":"Europe/Madrid",
    "iso:country":"ES",
    "name:und_x_variant":[
        "Escard\u00e9n"
    ],
    "wof:name":"Escarden",
    "wof:placetype":"locality"
},
  "geometry": {"coordinates":[-6.55444,43.44529],"type":"Point"}
}