{
  "type": "Feature",
  "properties": {
    "gn:admin1_code":"34",
    "gn:admin2_code":"O",
    "gn:admin3_code":"33026",
    "gn:asciiname":"Llantrales",
    "gn:country_code":"ES",
    "gn:dem":133,
    "gn:feature_class":"P",
    "gn:feature_code":"PPL",
    "gn:name":"Llantrales",
    "gn:population":0,
    "gn:timezone":"Europe/Madrid",
    "iso:country":"ES",
    "wof:name":"Llantrales",
    "wof:placetype":"locality"
},
  "geometry": {"coordinates":[-6.06667,43.36667],"type":"Point"}
}