{
  "type": "Feature",
  "properties": {
    "gn:admin1_code":"60",
    "gn:admin2_code":"V",
    "gn:admin3_code":"46009",
    "gn:asciiname":"Mahuella",
    "gn:country_code":"ES",
    "gn:dem":20,
    "gn:feature_class":"P",
    "gn:feature_code":"PPL",
    "gn:name":"Mahuella",
    "gn:population":0,
    "gn:timezone":"Europe/Madrid",
    "iso:country":"ES",
    "wof:name":"Mahuella",
    "wof:placetype":"locality"
},
  "geometry": {"coordinates":[-0.35,39.55],"type":"Point"}
}