{
  "type": "Feature",
  "properties": {
    "gn:admin1_code":"32",
    "gn:admin3_code":"31028",
    "gn:asciiname":"Arce",
    "gn:country_code":"ES",
    "gn:dem":593,
    "gn:feature_class":"P",
    "gn:feature_code":"PPL",
    "gn:name":"Arce",
    "gn:population":0,
    "gn:timezone":"Europe/Madrid",
    "iso:country":"ES",
    "name:arg_x_preferred":[
        "Arce"
    ],
    "name:bre_x_preferred":[
        "Artzibar"
    ],
    "name:cat_x_preferred":[
        "Artzi"
    ],
    "name:eus_x_preferred":[
        "Artzibar"
    ],
    "name:fra_x_preferred":[
        "Arce-Artzi"
    ],
    "name:glg_x_preferred":[
        "Arce"
    ],
    "name:hun_x_preferred":[
        "Arce"
    ],
    "name:ita_x_preferred":[
        "Arce"
    ],
    "name:msa_x_preferred":[
        "Arce"
    ],
    "name:nld_x_preferred":[
        "Arce"
    ],
    "name:oci_x_preferred":[
        "Artzi"
    ],
    "name:oci_x_variant":[
        "Artzibar"
    ],
    "name:pol_x_preferred":[
        "Artzi"
    ],
    "name:por_x_preferred":[
        "Arce"
    ],
    "name:rus_x_preferred":[
        "\u0410\u0440\u0441\u0435"
    ],
    "name:spa_x_preferred":[
        "Arce"
    ],
    "name:ukr_x_preferred":[
        "\u0410\u0440\u0441\u0435"
    ],
    "name:uzb_x_preferred":[
        "Arce"
    ],
    "name:vie_x_preferred":[
        "Arce - Artzi"
    ],
    "name:war_x_preferred":[
        "Arce"
    ],
    "name:zho_x_preferred":[
        "\u963f\u5c14\u585e"
    ],
    "wof:name":"Arce",
    "wof:placetype":"locality"
},
  "geometry": {"coordinates":[-1.37796,42.86496],"type":"Point"}
}