{
  "type": "Feature",
  "properties": {
    "gn:admin1_code":"51",
    "gn:admin2_code":"J",
    "gn:admin3_code":"23095",
    "gn:asciiname":"El Avellano",
    "gn:cc2":"ES",
    "gn:country_code":"ES",
    "gn:dem":1109,
    "gn:feature_class":"P",
    "gn:feature_code":"PPL",
    "gn:name":"El Avellano",
    "gn:population":0,
    "gn:timezone":"Europe/Madrid",
    "iso:country":"ES",
    "name:und_x_variant":[
        "Cortijada El Avellano",
        "El Avellano"
    ],
    "wof:name":"El Avellano",
    "wof:placetype":"locality"
},
  "geometry": {"coordinates":[-2.93333,38.05],"type":"Point"}
}