{
  "type": "Feature",
  "properties": {
    "gn:gn_country":"ES",
    "gn:gn_fcode":"PPLA3",
    "gn:gn_pop":68,
    "gn:population":68,
    "iso:country":"ES",
    "name:arg_x_preferred":[
        "P\u00e1lmaces de Jadraque"
    ],
    "name:baq_x_preferred":[
        "P\u00e1lmaces de Jadraque"
    ],
    "name:cat_x_preferred":[
        "P\u00e1lmaces de Jadraque"
    ],
    "name:chi_x_preferred":[
        "\u5e15\u5c14\u9a6c\u585e\u65af\u5fb7\u54c8\u5fb7\u62c9\u514b"
    ],
    "name:dut_x_preferred":[
        "P\u00e1lmaces de Jadraque"
    ],
    "name:eng_x_preferred":[
        "P\u00e1lmaces de Jadraque"
    ],
    "name:fre_x_preferred":[
        "P\u00e1lmaces de Jadraque"
    ],
    "name:hun_x_preferred":[
        "P\u00e1lmaces de Jadraque"
    ],
    "name:ina_x_preferred":[
        "P\u00e1lmaces de Jadraque"
    ],
    "name:ita_x_preferred":[
        "P\u00e1lmaces de Jadraque"
    ],
    "name:kaz_x_preferred":[
        "\u041f\u0430\u043b\u044c\u043c\u0430\u0441\u0435\u0441-\u0434\u0435-\u0425\u0430\u0434\u0440\u0430\u043a\u0435"
    ],
    "name:may_x_preferred":[
        "P\u00e1lmaces de Jadraque"
    ],
    "name:nan_x_preferred":[
        "P\u00e1lmaces de Jadraque"
    ],
    "name:oci_x_preferred":[
        "P\u00e1lmaces de Jadraque"
    ],
    "name:pol_x_preferred":[
        "P\u00e1lmaces de Jadraque"
    ],
    "name:por_x_preferred":[
        "P\u00e1lmaces de Jadraque"
    ],
    "name:rus_x_preferred":[
        "\u041f\u0430\u043b\u044c\u043c\u0430\u0441\u0435\u0441-\u0434\u0435-\u0425\u0430\u0434\u0440\u0430\u043a\u0435"
    ],
    "name:spa_x_preferred":[
        "P\u00e1lmaces de Jadraque"
    ],
    "name:swe_x_preferred":[
        "P\u00e1lmaces de Jadraque"
    ],
    "name:ukr_x_preferred":[
        "\u041f\u0430\u043b\u044c\u043c\u0430\u0441\u0435\u0441-\u0434\u0435-\u0425\u0430\u0434\u0440\u0430\u043a\u0435"
    ],
    "name:vie_x_preferred":[
        "P\u00e1lmaces de Jadraque"
    ],
    "name:war_x_preferred":[
        "P\u00e1lmaces de Jadraque"
    ],
    "qs_pg:aaroncc":"ES",
    "qs_pg:gn_country":"ES",
    "qs_pg:gn_fcode":"PPLA3",
    "qs_pg:gn_pop":68,
    "qs_pg:name":"P\u00e1lmaces de Jadraque",
    "qs_pg:name_adm0":"Espa\u00f1a",
    "qs_pg:name_adm1":"Castilla-La Mancha",
    "qs_pg:photos":44,
    "qs_pg:photos_1k":9,
    "qs_pg:photos_9k":1,
    "qs_pg:photos_9r":2,
    "qs_pg:photos_all":44,
    "qs_pg:photos_sr":2,
    "qs_pg:pop_sr":1,
    "qs_pg:qs_pg_placetype":"locality",
    "qs_pg:qs_pg_placetype_gp":"Town",
    "qs_pg:woe_adm0":23424950,
    "woe:adm0_id":23424950,
    "woe:name_adm0":"Espa\u00f1a",
    "woe:name_adm1":"Castilla-La Mancha",
    "woe:placetype":"Town",
    "wof:name":"P\u00e1lmaces de Jadraque",
    "wof:placetype":"locality",
    "wof:population":68
},
  "geometry": {"coordinates":[-2.9106,41.0561],"type":"Point"}
}