{
  "type": "Feature",
  "properties": {
    "gn:admin1_code":"31",
    "gn:admin2_code":"MU",
    "gn:admin3_code":"30021",
    "gn:asciiname":"Corverica",
    "gn:country_code":"ES",
    "gn:dem":197,
    "gn:feature_class":"P",
    "gn:feature_code":"PPL",
    "gn:name":"Corverica",
    "gn:population":0,
    "gn:timezone":"Europe/Madrid",
    "iso:country":"ES",
    "name:und_x_variant":[
        "Casas La Corverica",
        "Cortijo Corverica",
        "Corverica"
    ],
    "wof:name":"Corverica",
    "wof:placetype":"locality"
},
  "geometry": {"coordinates":[-1.17415,37.7671],"type":"Point"}
}