{
  "type": "Feature",
  "properties": {
    "gn:admin1_code":"53",
    "gn:admin2_code":"TF",
    "gn:admin3_code":"38038",
    "gn:asciiname":"La Fortaleza",
    "gn:country_code":"ES",
    "gn:dem":261,
    "gn:feature_class":"P",
    "gn:feature_code":"PPL",
    "gn:name":"La Fortaleza",
    "gn:population":0,
    "gn:timezone":"Atlantic/Canary",
    "iso:country":"ES",
    "wof:name":"La Fortaleza",
    "wof:placetype":"locality"
},
  "geometry": {"coordinates":[-16.26002,28.50408],"type":"Point"}
}