{
  "type": "Feature",
  "properties": {
    "iso:country":"ES",
    "name:eng_x_preferred":[
        "Campos Eliseos"
    ],
    "name:spa_x_preferred":[
        "Campos Eliseos"
    ],
    "wof:name":"Campos Eliseos",
    "wof:placetype":"neighbourhood"
},
  "geometry": {"coordinates":[-4.4107518625097,36.72152387680237],"type":"Point"}
}