{
  "type": "Feature",
  "properties": {
    "gn:admin1_code":"53",
    "gn:admin2_code":"TF",
    "gn:admin3_code":"38020",
    "gn:asciiname":"El Escobonal",
    "gn:country_code":"ES",
    "gn:dem":490,
    "gn:feature_class":"P",
    "gn:feature_code":"PPL",
    "gn:name":"El Escobonal",
    "gn:population":0,
    "gn:timezone":"Atlantic/Canary",
    "iso:country":"ES",
    "wof:name":"El Escobonal",
    "wof:placetype":"locality"
},
  "geometry": {"coordinates":[-16.42975,28.26062],"type":"Point"}
}