{
  "type": "Feature",
  "properties": {
    "gn:country":"ES",
    "gn:fcode":"PPL",
    "gn:population":207,
    "iso:country":"ES",
    "name:ara_x_preferred":[
        "\u0625\u0644 \u0645\u064a\u0631\u0648\u0646"
    ],
    "name:ast_x_preferred":[
        "El Mir\u00f3n"
    ],
    "name:azb_x_preferred":[
        "\u0627\u0644 \u0645\u06cc\u0631\u0648\u0646"
    ],
    "name:bre_x_preferred":[
        "El Mir\u00f3n"
    ],
    "name:cat_x_preferred":[
        "El Mir\u00f3n"
    ],
    "name:ceb_x_preferred":[
        "El Mir\u00f3n"
    ],
    "name:deu_x_preferred":[
        "El Mir\u00f3n"
    ],
    "name:eng_x_preferred":[
        "El Mir\u00f3n"
    ],
    "name:eus_x_preferred":[
        "El Mir\u00f3n"
    ],
    "name:fas_x_preferred":[
        "\u0627\u0644 \u0645\u06cc\u0631\u0648\u0646"
    ],
    "name:fra_x_preferred":[
        "El Mir\u00f3n"
    ],
    "name:glg_x_preferred":[
        "El Mir\u00f3n"
    ],
    "name:hun_x_preferred":[
        "El Mir\u00f3n"
    ],
    "name:ina_x_preferred":[
        "El Mir\u00f3n"
    ],
    "name:ita_x_preferred":[
        "El Mir\u00f3n"
    ],
    "name:kaz_x_preferred":[
        "\u042d\u043b\u044c-\u041c\u0438\u0440\u043e\u043d"
    ],
    "name:mkd_x_preferred":[
        "\u0415\u043b \u041c\u0438\u0440\u043e\u043d"
    ],
    "name:msa_x_preferred":[
        "El Mir\u00f3n"
    ],
    "name:nld_x_preferred":[
        "El Mir\u00f3n"
    ],
    "name:oci_x_preferred":[
        "El Mir\u00f3n"
    ],
    "name:pol_x_preferred":[
        "El Mir\u00f3n"
    ],
    "name:por_x_preferred":[
        "El Mir\u00f3n"
    ],
    "name:rup_x_preferred":[
        "El Mir\u00f3n"
    ],
    "name:rus_x_preferred":[
        "\u042d\u043b\u044c-\u041c\u0438\u0440\u043e\u043d"
    ],
    "name:spa_x_preferred":[
        "El Mir\u00f3n"
    ],
    "name:sqi_x_preferred":[
        "El Mir\u00f3n"
    ],
    "name:swe_x_preferred":[
        "El Mir\u00f3n"
    ],
    "name:ukr_x_preferred":[
        "\u0415\u043b\u044c-\u041c\u0456\u0440\u043e\u043d"
    ],
    "name:uzb_x_preferred":[
        "El Mir\u00f3n"
    ],
    "name:vie_x_preferred":[
        "El Mir\u00f3n"
    ],
    "name:war_x_preferred":[
        "El Mir\u00f3n"
    ],
    "name:zho_x_preferred":[
        "\u57c3\u5c14\u7c73\u9f99"
    ],
    "qs_pg:aaroncc":"ES",
    "qs_pg:gn_country":"ES",
    "qs_pg:gn_fcode":"PPL",
    "qs_pg:gn_pop":207,
    "qs_pg:name":"El Mir\u00f3n",
    "qs_pg:name_adm0":"Espa\u00f1a",
    "qs_pg:name_adm1":"Castilla y Le\u00f3n",
    "qs_pg:photos":4,
    "qs_pg:photos_1k":1,
    "qs_pg:photos_9k":1,
    "qs_pg:photos_9r":1,
    "qs_pg:photos_all":4,
    "qs_pg:photos_sr":1,
    "qs_pg:pop_sr":2,
    "qs_pg:qs_pg_placetype":"locality",
    "qs_pg:qs_pg_placetype_gp":"Town",
    "qs_pg:woe_adm0":23424950,
    "woe:adm0_id":23424950,
    "woe:name_adm0":"Espa\u00f1a",
    "woe:name_adm1":"Castilla y Le\u00f3n",
    "woe:placetype":"Town",
    "wof:name":"El Mir\u00f3n",
    "wof:placetype":"locality",
    "wof:population":207
},
  "geometry": {"coordinates":[-5.40552,40.53322],"type":"Point"}
}