{
  "type": "Feature",
  "properties": {
    "gn:country":"ES",
    "gn:fcode":"PPLA3",
    "gn:population":719,
    "iso:country":"ES",
    "name:arg_x_preferred":[
        "B\u00e8lgida"
    ],
    "name:ast_x_preferred":[
        "B\u00e9lgida"
    ],
    "name:azb_x_preferred":[
        "\u0628\u0644\u062e\u06cc\u062f\u0627"
    ],
    "name:cat_x_preferred":[
        "B\u00e8lgida"
    ],
    "name:ceb_x_preferred":[
        "B\u00e8lgida"
    ],
    "name:dan_x_preferred":[
        "Belgida"
    ],
    "name:deu_x_preferred":[
        "B\u00e8lgida"
    ],
    "name:eng_x_preferred":[
        "B\u00e8lgida"
    ],
    "name:eus_x_preferred":[
        "B\u00e8lgida"
    ],
    "name:fas_x_preferred":[
        "\u0628\u0644\u062e\u06cc\u062f\u0627"
    ],
    "name:fra_x_preferred":[
        "B\u00e8lgida"
    ],
    "name:hun_x_preferred":[
        "B\u00e8lgida"
    ],
    "name:ita_x_preferred":[
        "B\u00e8lgida"
    ],
    "name:msa_x_preferred":[
        "B\u00e8lgida"
    ],
    "name:nan_x_preferred":[
        "B\u00e8lgida"
    ],
    "name:nld_x_preferred":[
        "B\u00e8lgida"
    ],
    "name:nob_x_preferred":[
        "B\u00e8lgida"
    ],
    "name:oci_x_preferred":[
        "B\u00e8lgida"
    ],
    "name:pol_x_preferred":[
        "B\u00e8lgida"
    ],
    "name:por_x_preferred":[
        "B\u00e8lgida"
    ],
    "name:rus_x_preferred":[
        "\u0411\u0435\u043b\u044c\u0445\u0438\u0434\u0430"
    ],
    "name:spa_x_preferred":[
        "B\u00e9lgida"
    ],
    "name:sqi_x_preferred":[
        "B\u00e8lgida"
    ],
    "name:swe_x_preferred":[
        "B\u00e8lgida"
    ],
    "name:ukr_x_preferred":[
        "\u0411\u0435\u043b\u0434\u0436\u0438\u0434\u0430"
    ],
    "name:vie_x_preferred":[
        "B\u00e8lgida"
    ],
    "name:war_x_preferred":[
        "B\u00e8lgida"
    ],
    "name:zho_x_preferred":[
        "\u8d1d\u5c14\u5e0c\u8fbe"
    ],
    "qs_pg:aaroncc":"ES",
    "qs_pg:gn_country":"ES",
    "qs_pg:gn_fcode":"PPLA3",
    "qs_pg:gn_pop":719,
    "qs_pg:name":"B\u00e9lgida",
    "qs_pg:name_adm0":"Espa\u00f1a",
    "qs_pg:name_adm1":"Comunitat Valenciana",
    "qs_pg:photos_9k":1,
    "qs_pg:photos_9r":1,
    "qs_pg:photos_all":1,
    "qs_pg:photos_sr":0,
    "qs_pg:pop_sr":2,
    "qs_pg:qs_pg_placetype":"locality",
    "qs_pg:qs_pg_placetype_gp":"Town",
    "qs_pg:woe_adm0":23424950,
    "woe:adm0_id":23424950,
    "woe:name_adm0":"Espa\u00f1a",
    "woe:name_adm1":"Comunitat Valenciana",
    "woe:placetype":"Town",
    "wof:name":"B\u00e9lgida",
    "wof:placetype":"locality",
    "wof:population":719
},
  "geometry": {"coordinates":[-0.46667,38.85],"type":"Point"}
}