{
  "type": "Feature",
  "properties": {
    "gn:admin1_code":"58",
    "gn:admin2_code":"LU",
    "gn:admin3_code":"27044",
    "gn:asciiname":"Reigosa",
    "gn:cc2":"ES",
    "gn:country_code":"ES",
    "gn:dem":431,
    "gn:feature_class":"P",
    "gn:feature_code":"PPL",
    "gn:name":"Reigosa",
    "gn:population":0,
    "gn:timezone":"Europe/Madrid",
    "iso:country":"ES",
    "name:und_x_variant":[
        "San Vicente",
        "Regueira",
        "Reigosa"
    ],
    "wof:name":"Reigosa",
    "wof:placetype":"locality"
},
  "geometry": {"coordinates":[-7.38333,43.28333],"type":"Point"}
}