{
  "type": "Feature",
  "properties": {
    "gn:admin1_code":"60",
    "gn:admin2_code":"A",
    "gn:admin3_code":"03114",
    "gn:asciiname":"La Boquera",
    "gn:country_code":"ES",
    "gn:dem":451,
    "gn:feature_class":"P",
    "gn:feature_code":"PPL",
    "gn:name":"La Boquera",
    "gn:population":0,
    "gn:timezone":"Europe/Madrid",
    "iso:country":"ES",
    "name:und_x_variant":[
        "Caser\u00edo La Boquera",
        "La Boquera"
    ],
    "wof:name":"La Boquera",
    "wof:placetype":"locality"
},
  "geometry": {"coordinates":[-0.90215,38.34684],"type":"Point"}
}