{
  "type": "Feature",
  "properties": {
    "gn:country":"ES",
    "gn:fcode":"ADM3",
    "gn:population":2322,
    "iso:country":"ES",
    "name:ara_x_preferred":[
        "\u0644\u064a\u0643\u0631\u064a\u0646"
    ],
    "name:ast_x_preferred":[
        "Lecr\u00edn"
    ],
    "name:cat_x_preferred":[
        "Lecr\u00edn"
    ],
    "name:ceb_x_preferred":[
        "Lecr\u00edn"
    ],
    "name:deu_x_preferred":[
        "Lecr\u00edn"
    ],
    "name:eng_x_preferred":[
        "Lecr\u00edn"
    ],
    "name:epo_x_preferred":[
        "Lecr\u00edn"
    ],
    "name:eus_x_preferred":[
        "Lecr\u00edn"
    ],
    "name:fra_x_preferred":[
        "Lecr\u00edn"
    ],
    "name:hun_x_preferred":[
        "Lecr\u00edn"
    ],
    "name:hye_x_preferred":[
        "\u053c\u0565\u056f\u0580\u056b\u0576"
    ],
    "name:ita_x_preferred":[
        "Lecr\u00edn"
    ],
    "name:kaz_x_preferred":[
        "\u041b\u0435\u043a\u0440\u0438\u043d"
    ],
    "name:lit_x_preferred":[
        "Lesrinas"
    ],
    "name:msa_x_preferred":[
        "Lecr\u00edn"
    ],
    "name:nan_x_preferred":[
        "Lecr\u00edn"
    ],
    "name:nld_x_preferred":[
        "Lecr\u00edn"
    ],
    "name:oci_x_preferred":[
        "Lecr\u00edn"
    ],
    "name:pol_x_preferred":[
        "Lecr\u00edn"
    ],
    "name:por_x_preferred":[
        "Lecr\u00edn"
    ],
    "name:rus_x_preferred":[
        "\u041b\u0435\u043a\u0440\u0438\u043d"
    ],
    "name:spa_x_preferred":[
        "Lecr\u00edn"
    ],
    "name:swe_x_preferred":[
        "Lecr\u00edn"
    ],
    "name:tur_x_preferred":[
        "Lecr\u00edn"
    ],
    "name:ukr_x_preferred":[
        "\u041b\u0435\u043a\u0440\u0456\u043d"
    ],
    "name:uzb_x_preferred":[
        "Lecr\u00edn"
    ],
    "name:vie_x_preferred":[
        "Lecr\u00edn"
    ],
    "name:war_x_preferred":[
        "Lecr\u00edn"
    ],
    "name:zho_x_preferred":[
        "\u83b1\u514b\u6797"
    ],
    "qs_pg:aaroncc":"ES",
    "qs_pg:gn_country":"ES",
    "qs_pg:gn_fcode":"ADM3",
    "qs_pg:gn_pop":2322,
    "qs_pg:name":"Lecr\u00edn",
    "qs_pg:name_adm0":"Espa\u00f1a",
    "qs_pg:name_adm1":"Andaluc\u00eda",
    "qs_pg:photos":273,
    "qs_pg:photos_1k":55,
    "qs_pg:photos_9k":1,
    "qs_pg:photos_9r":4,
    "qs_pg:photos_all":273,
    "qs_pg:photos_sr":5,
    "qs_pg:pop_sr":4,
    "qs_pg:qs_pg_placetype":"locality",
    "qs_pg:qs_pg_placetype_gp":"Town",
    "qs_pg:woe_adm0":23424950,
    "woe:adm0_id":23424950,
    "woe:name_adm0":"Espa\u00f1a",
    "woe:name_adm1":"Andaluc\u00eda",
    "woe:placetype":"Town",
    "wof:name":"Lecr\u00edn",
    "wof:placetype":"locality",
    "wof:population":2299
},
  "geometry": {"coordinates":[-3.53304,36.95012],"type":"Point"}
}