{
  "type": "Feature",
  "properties": {
    "gn:admin1_code":"58",
    "gn:admin2_code":"OR",
    "gn:admin3_code":"32029",
    "gn:asciiname":"Fitoiro",
    "gn:country_code":"ES",
    "gn:dem":1031,
    "gn:feature_class":"P",
    "gn:feature_code":"PPL",
    "gn:name":"Fitoiro",
    "gn:population":0,
    "gn:timezone":"Europe/Madrid",
    "iso:country":"ES",
    "name:und_x_variant":[
        "San Pelagio",
        "Fitoiro"
    ],
    "wof:name":"Fitoiro",
    "wof:placetype":"locality"
},
  "geometry": {"coordinates":[-7.38333,42.31667],"type":"Point"}
}