{
  "type": "Feature",
  "properties": {
    "gn:admin1_code":"54",
    "gn:admin2_code":"GU",
    "gn:admin3_code":"19099",
    "gn:asciiname":"Canales de Molina",
    "gn:country_code":"ES",
    "gn:dem":1138,
    "gn:feature_class":"P",
    "gn:feature_code":"PPL",
    "gn:name":"Canales de Molina",
    "gn:population":0,
    "gn:timezone":"Europe/Madrid",
    "iso:country":"ES",
    "wof:name":"Canales de Molina",
    "wof:placetype":"locality"
},
  "geometry": {"coordinates":[-1.9777,40.90161],"type":"Point"}
}