{
  "type": "Feature",
  "properties": {
    "gn:admin1_code":"51",
    "gn:admin2_code":"GR",
    "gn:admin3_code":"18039",
    "gn:asciiname":"Los Manzanos",
    "gn:country_code":"ES",
    "gn:dem":1016,
    "gn:feature_class":"P",
    "gn:feature_code":"PPL",
    "gn:name":"Los Manzanos",
    "gn:population":0,
    "gn:timezone":"Europe/Madrid",
    "iso:country":"ES",
    "name:und_x_variant":[
        "Caser\u00edo Los Manzanos",
        "Los Manzanos"
    ],
    "wof:name":"Los Manzanos",
    "wof:placetype":"locality"
},
  "geometry": {"coordinates":[-2.66542,37.38203],"type":"Point"}
}