{
  "type": "Feature",
  "properties": {
    "gn:admin1_code":"55",
    "gn:admin2_code":"SA",
    "gn:admin3_code":"37170",
    "gn:asciiname":"Pelilla",
    "gn:country_code":"ES",
    "gn:dem":777,
    "gn:feature_class":"P",
    "gn:feature_code":"PPL",
    "gn:name":"Pelilla",
    "gn:population":0,
    "gn:timezone":"Europe/Madrid",
    "iso:country":"ES",
    "wof:name":"Pelilla",
    "wof:placetype":"locality"
},
  "geometry": {"coordinates":[-6.05481,41.18381],"type":"Point"}
}