{
  "type": "Feature",
  "properties": {
    "gn:admin1_code":"58",
    "gn:admin2_code":"C",
    "gn:admin3_code":"15056",
    "gn:asciiname":"Castelan",
    "gn:country_code":"ES",
    "gn:dem":243,
    "gn:feature_class":"P",
    "gn:feature_code":"PPL",
    "gn:name":"Castel\u00e1n",
    "gn:population":0,
    "gn:timezone":"Europe/Madrid",
    "iso:country":"ES",
    "name:und_x_variant":[
        "Castel\u00e1n"
    ],
    "wof:name":"Castelan",
    "wof:placetype":"locality"
},
  "geometry": {"coordinates":[-8.87635,42.91328],"type":"Point"}
}