{
  "type": "Feature",
  "properties": {
    "gn:admin1_code":"51",
    "gn:admin2_code":"GR",
    "gn:admin3_code":"18045",
    "gn:asciiname":"Felines y Santa Catalina",
    "gn:country_code":"ES",
    "gn:dem":874,
    "gn:feature_class":"P",
    "gn:feature_code":"PPL",
    "gn:name":"Felines y Santa Catalina",
    "gn:population":0,
    "gn:timezone":"Europe/Madrid",
    "iso:country":"ES",
    "wof:name":"Felines y Santa Catalina",
    "wof:placetype":"locality"
},
  "geometry": {"coordinates":[-2.69163,37.74493],"type":"Point"}
}