{
  "type": "Feature",
  "properties": {
    "gn:admin1_code":"39",
    "gn:admin2_code":"S",
    "gn:admin3_code":"39015",
    "gn:asciiname":"La Frecha",
    "gn:country_code":"ES",
    "gn:dem":406,
    "gn:feature_class":"P",
    "gn:feature_code":"PPL",
    "gn:name":"La Frecha",
    "gn:population":0,
    "gn:timezone":"Europe/Madrid",
    "iso:country":"ES",
    "wof:name":"La Frecha",
    "wof:placetype":"locality"
},
  "geometry": {"coordinates":[-4.67661,43.15118],"type":"Point"}
}