{
  "type": "Feature",
  "properties": {
    "gn:admin1_code":"31",
    "gn:admin2_code":"MU",
    "gn:admin3_code":"30037",
    "gn:asciiname":"Los Martinez",
    "gn:cc2":"ES",
    "gn:country_code":"ES",
    "gn:dem":32,
    "gn:feature_class":"P",
    "gn:feature_code":"PPL",
    "gn:name":"Los Mart\u00ednez",
    "gn:population":0,
    "gn:timezone":"Europe/Madrid",
    "iso:country":"ES",
    "name:und_x_variant":[
        "Caser\u00edo Los Martinez",
        "Casas Los Martinez del Huerto",
        "Los Mart\u00ednez"
    ],
    "wof:name":"Los Martinez",
    "wof:placetype":"locality"
},
  "geometry": {"coordinates":[-0.93333,37.75],"type":"Point"}
}