{
  "type": "Feature",
  "properties": {
    "gn:admin1_code":"51",
    "gn:admin2_code":"GR",
    "gn:admin3_code":"18135",
    "gn:asciiname":"La Cazuela",
    "gn:country_code":"ES",
    "gn:dem":1050,
    "gn:feature_class":"P",
    "gn:feature_code":"PPL",
    "gn:name":"La Cazuela",
    "gn:population":0,
    "gn:timezone":"Europe/Madrid",
    "iso:country":"ES",
    "name:und_x_variant":[
        "Casa La Cazuela",
        "La Cazuela"
    ],
    "wof:name":"La Cazuela",
    "wof:placetype":"locality"
},
  "geometry": {"coordinates":[-3.95634,37.36126],"type":"Point"}
}