{
  "type": "Feature",
  "properties": {
    "gn:admin1_code":"52",
    "gn:admin2_code":"TE",
    "gn:admin3_code":"44050",
    "gn:asciiname":"El Villarejo",
    "gn:country_code":"ES",
    "gn:dem":1161,
    "gn:feature_class":"P",
    "gn:feature_code":"PPL",
    "gn:name":"El Villarejo",
    "gn:population":0,
    "gn:timezone":"Europe/Madrid",
    "iso:country":"ES",
    "wof:name":"El Villarejo",
    "wof:placetype":"locality"
},
  "geometry": {"coordinates":[-1.17622,40.86254],"type":"Point"}
}