{
  "type": "Feature",
  "properties": {
    "gn:admin1_code":"56",
    "gn:admin2_code":"L",
    "gn:admin3_code":"25901",
    "gn:asciiname":"Estahon",
    "gn:country_code":"ES",
    "gn:dem":1251,
    "gn:feature_class":"P",
    "gn:feature_code":"PPL",
    "gn:name":"Estah\u00f3n",
    "gn:population":0,
    "gn:timezone":"Europe/Madrid",
    "iso:country":"ES",
    "wof:name":"Estahon",
    "wof:placetype":"locality"
},
  "geometry": {"coordinates":[1.2104,42.58782],"type":"Point"}
}