{
  "type": "Feature",
  "properties": {
    "gn:admin1_code":"56",
    "gn:admin2_code":"GI",
    "gn:admin3_code":"17132",
    "gn:asciiname":"Masos de Morassac",
    "gn:country_code":"ES",
    "gn:dem":31,
    "gn:feature_class":"P",
    "gn:feature_code":"PPLL",
    "gn:name":"Masos de Morassac",
    "gn:population":0,
    "gn:timezone":"Europe/Madrid",
    "iso:country":"ES",
    "name:cat_x_preferred":[
        "Masos de Morassac"
    ],
    "wof:name":"Masos de Morassac",
    "wof:placetype":"locality"
},
  "geometry": {"coordinates":[3.00128,42.33282],"type":"Point"}
}