{
  "type": "Feature",
  "properties": {
    "gn:gn_country":"ES",
    "gn:gn_fcode":"PPLA3",
    "gn:gn_pop":503,
    "gn:population":503,
    "iso:country":"ES",
    "name:alb_x_preferred":[
        "Jorquera"
    ],
    "name:ara_x_preferred":[
        "\u062e\u0648\u0631\u0643\u064a\u0631\u0627"
    ],
    "name:arg_x_preferred":[
        "Exorquera"
    ],
    "name:baq_x_preferred":[
        "Jorquera"
    ],
    "name:cat_x_preferred":[
        "Jorquera"
    ],
    "name:chi_x_preferred":[
        "\u970d\u5c14\u514b\u62c9"
    ],
    "name:dut_x_preferred":[
        "Jorquera"
    ],
    "name:eng_x_preferred":[
        "Jorquera"
    ],
    "name:fre_x_preferred":[
        "Jorquera"
    ],
    "name:ger_x_preferred":[
        "Jorquera"
    ],
    "name:hun_x_preferred":[
        "Jorquera"
    ],
    "name:ina_x_preferred":[
        "Jorquera"
    ],
    "name:ita_x_preferred":[
        "Jorquera"
    ],
    "name:jpn_x_preferred":[
        "\u30db\u30eb\u30b1\u30fc\u30e9"
    ],
    "name:may_x_preferred":[
        "Jorquera"
    ],
    "name:nan_x_preferred":[
        "Jorquera"
    ],
    "name:oci_x_preferred":[
        "Jorquera"
    ],
    "name:per_x_preferred":[
        "\u062e\u0648\u0631\u06a9\u0631\u0627"
    ],
    "name:pol_x_preferred":[
        "Jorquera"
    ],
    "name:por_x_preferred":[
        "Jorquera"
    ],
    "name:rum_x_preferred":[
        "Jorquera"
    ],
    "name:rus_x_preferred":[
        "\u0425\u043e\u0440\u043a\u0435\u0440\u0430"
    ],
    "name:spa_x_preferred":[
        "Jorquera"
    ],
    "name:swe_x_preferred":[
        "Jorquera"
    ],
    "name:ukr_x_preferred":[
        "\u0425\u043e\u0440\u043a\u0435\u0440\u0430"
    ],
    "name:war_x_preferred":[
        "Jorquera"
    ],
    "qs_pg:aaroncc":"ES",
    "qs_pg:gn_country":"ES",
    "qs_pg:gn_fcode":"PPLA3",
    "qs_pg:gn_pop":503,
    "qs_pg:name":"Jorquera",
    "qs_pg:name_adm0":"Espa\u00f1a",
    "qs_pg:name_adm1":"Castilla-La Mancha",
    "qs_pg:photos":65,
    "qs_pg:photos_1k":13,
    "qs_pg:photos_9k":1,
    "qs_pg:photos_9r":2,
    "qs_pg:photos_all":65,
    "qs_pg:photos_sr":2,
    "qs_pg:pop_sr":2,
    "qs_pg:qs_pg_placetype":"locality",
    "qs_pg:qs_pg_placetype_gp":"Town",
    "qs_pg:woe_adm0":23424950,
    "woe:adm0_id":23424950,
    "woe:name_adm0":"Espa\u00f1a",
    "woe:name_adm1":"Castilla-La Mancha",
    "woe:placetype":"Town",
    "wof:name":"Jorquera",
    "wof:placetype":"locality",
    "wof:population":503
},
  "geometry": {"coordinates":[-1.51667,39.16667],"type":"Point"}
}