{
  "type": "Feature",
  "properties": {
    "gn:admin1_code":"34",
    "gn:admin2_code":"O",
    "gn:admin3_code":"33023",
    "gn:asciiname":"Prendones",
    "gn:country_code":"ES",
    "gn:dem":129,
    "gn:feature_class":"P",
    "gn:feature_code":"PPL",
    "gn:name":"Prendon\u00e9s",
    "gn:population":0,
    "gn:timezone":"Europe/Madrid",
    "iso:country":"ES",
    "name:ast_x_preferred":[
        "San Xuan"
    ],
    "name:deu_x_preferred":[
        "Prendones"
    ],
    "name:und_x_variant":[
        "Prendon\u00e9s"
    ],
    "wof:name":"Prendones",
    "wof:placetype":"locality"
},
  "geometry": {"coordinates":[-6.86667,43.53333],"type":"Point"}
}