{
  "type": "Feature",
  "properties": {
    "gn:admin1_code":"58",
    "gn:admin2_code":"LU",
    "gn:admin3_code":"27031",
    "gn:asciiname":"A Ferreirua",
    "gn:cc2":"ES",
    "gn:country_code":"ES",
    "gn:dem":449,
    "gn:feature_class":"P",
    "gn:feature_code":"PPL",
    "gn:name":"A Ferreir\u00faa",
    "gn:population":0,
    "gn:timezone":"Europe/Madrid",
    "iso:country":"ES",
    "name:spa_x_preferred":[
        "La Ferreira"
    ],
    "wof:name":"A Ferreirua",
    "wof:placetype":"locality"
},
  "geometry": {"coordinates":[-7.38968,42.59859],"type":"Point"}
}