{
  "type": "Feature",
  "properties": {
    "gn:admin1_code":"39",
    "gn:admin2_code":"S",
    "gn:admin3_code":"39093",
    "gn:asciiname":"Malataja",
    "gn:country_code":"ES",
    "gn:dem":990,
    "gn:feature_class":"P",
    "gn:feature_code":"PPL",
    "gn:name":"Malataja",
    "gn:population":0,
    "gn:timezone":"Europe/Madrid",
    "iso:country":"ES",
    "wof:name":"Malataja",
    "wof:placetype":"locality"
},
  "geometry": {"coordinates":[-3.99983,42.92654],"type":"Point"}
}