{
  "type": "Feature",
  "properties": {
    "gn:admin1_code":"34",
    "gn:admin2_code":"O",
    "gn:admin3_code":"33075",
    "gn:asciiname":"Cotarelo",
    "gn:country_code":"ES",
    "gn:dem":803,
    "gn:feature_class":"P",
    "gn:feature_code":"PPL",
    "gn:name":"Cotarelo",
    "gn:population":0,
    "gn:timezone":"Europe/Madrid",
    "iso:country":"ES",
    "wof:name":"Cotarelo",
    "wof:placetype":"locality"
},
  "geometry": {"coordinates":[-7.02486,43.29543],"type":"Point"}
}