{
  "type": "Feature",
  "properties": {
    "gn:admin1_code":"39",
    "gn:admin2_code":"S",
    "gn:admin3_code":"39075",
    "gn:asciiname":"Cueto",
    "gn:country_code":"ES",
    "gn:dem":68,
    "gn:feature_class":"P",
    "gn:feature_code":"PPL",
    "gn:name":"Cueto",
    "gn:population":0,
    "gn:timezone":"Europe/Madrid",
    "iso:country":"ES",
    "name:jpn_x_preferred":[
        "\u30af\u30a8\u30c8"
    ],
    "name:por_x_preferred":[
        "Cueto"
    ],
    "name:spa_x_preferred":[
        "Cueto"
    ],
    "wof:name":"Cueto",
    "wof:placetype":"locality"
},
  "geometry": {"coordinates":[-3.80049,43.48299],"type":"Point"}
}