{
  "type": "Feature",
  "properties": {
    "gn:admin1_code":"59",
    "gn:admin2_code":"VI",
    "gn:admin3_code":"01053",
    "gn:asciiname":"Zuazo",
    "gn:country_code":"ES",
    "gn:dem":586,
    "gn:feature_class":"P",
    "gn:feature_code":"PPL",
    "gn:name":"Zuhatzu Donemiliaga / Zuazo de San Mill\u00e1n",
    "gn:population":0,
    "gn:timezone":"Europe/Madrid",
    "iso:country":"ES",
    "name:eus_x_preferred":[
        "Zuhatzu Donemiliaga"
    ],
    "name:por_x_preferred":[
        "Zuazo"
    ],
    "name:spa_x_preferred":[
        "Zuazo de San Mill\u00e1n"
    ],
    "name:spa_x_variant":[
        "Zuazo"
    ],
    "wof:name":"Zuazo",
    "wof:placetype":"locality"
},
  "geometry": {"coordinates":[-2.4115,42.87118],"type":"Point"}
}