{
  "type": "Feature",
  "properties": {
    "gn:admin1_code":"27",
    "gn:admin2_code":"LO",
    "gn:admin3_code":"26047",
    "gn:asciiname":"Cabreton",
    "gn:country_code":"ES",
    "gn:dem":557,
    "gn:feature_class":"P",
    "gn:feature_code":"PPL",
    "gn:name":"Cabret\u00f3n",
    "gn:population":0,
    "gn:timezone":"Europe/Madrid",
    "iso:country":"ES",
    "name:und_x_variant":[
        "Cabret\u00f3n"
    ],
    "wof:name":"Cabreton",
    "wof:placetype":"locality"
},
  "geometry": {"coordinates":[-1.90609,41.99733],"type":"Point"}
}