{
  "type": "Feature",
  "properties": {
    "gn:country":"ES",
    "gn:fcode":"PPLA3",
    "gn:population":263,
    "iso:country":"ES",
    "name:arg_x_preferred":[
        "Milles de la Polvorosa"
    ],
    "name:azb_x_preferred":[
        "\u0645\u06cc\u0632 \u062f \u0644\u0627 \u067e\u0644\u0648\u0631\u0633\u0627"
    ],
    "name:cat_x_preferred":[
        "Milles de la Polvorosa"
    ],
    "name:eng_x_preferred":[
        "Milles de la Polvorosa"
    ],
    "name:eus_x_preferred":[
        "Milles de la Polvorosa"
    ],
    "name:fas_x_preferred":[
        "\u0645\u06cc\u0632 \u062f \u0644\u0627 \u067e\u0644\u0648\u0631\u0633\u0627"
    ],
    "name:fra_x_preferred":[
        "Milles de la Polvorosa"
    ],
    "name:haw_x_preferred":[
        "Milles de la Polvorosa"
    ],
    "name:hun_x_preferred":[
        "Milles de la Polvorosa"
    ],
    "name:ile_x_preferred":[
        "Milles de la Polvorosa"
    ],
    "name:ina_x_preferred":[
        "Milles de la Polvorosa"
    ],
    "name:ita_x_preferred":[
        "Milles de la Polvorosa"
    ],
    "name:msa_x_preferred":[
        "Milles de la Polvorosa"
    ],
    "name:nan_x_preferred":[
        "Milles de la Polvorosa"
    ],
    "name:nld_x_preferred":[
        "Milles de la Polvorosa"
    ],
    "name:oci_x_preferred":[
        "Milles de la Polvorosa"
    ],
    "name:pol_x_preferred":[
        "Milles de la Polvorosa"
    ],
    "name:por_x_preferred":[
        "Milles de la Polvorosa"
    ],
    "name:rus_x_preferred":[
        "\u041c\u0438\u043b\u044c\u0435\u0441-\u0434\u0435-\u043b\u0430-\u041f\u043e\u043b\u044c\u0432\u043e\u0440\u043e\u0441\u0430"
    ],
    "name:spa_x_preferred":[
        "Milles de la Polvorosa"
    ],
    "name:swe_x_preferred":[
        "Milles de la Polvorosa"
    ],
    "name:ukr_x_preferred":[
        "\u041c\u0456\u043b\u044c\u0454\u0441-\u0434\u0435-\u043b\u0430-\u041f\u043e\u043b\u044c\u0432\u043e\u0440\u043e\u0441\u0430"
    ],
    "name:uzb_x_preferred":[
        "Milles de la Polvorosa"
    ],
    "name:vie_x_preferred":[
        "Milles de la Polvorosa"
    ],
    "name:war_x_preferred":[
        "Milles de la Polvorosa"
    ],
    "name:zho_x_preferred":[
        "\u7c73\u5217\u65af\u5fb7\u62c9\u6ce2\u5c14\u6c83\u7f57\u8428"
    ],
    "qs_pg:aaroncc":"ES",
    "qs_pg:gn_country":"ES",
    "qs_pg:gn_fcode":"PPLA3",
    "qs_pg:gn_pop":263,
    "qs_pg:name":"Milles de la Polvorosa",
    "qs_pg:name_adm0":"Espa\u00f1a",
    "qs_pg:name_adm1":"Castilla y Le\u00f3n",
    "qs_pg:photos_9k":1,
    "qs_pg:photos_9r":1,
    "qs_pg:photos_all":1,
    "qs_pg:photos_sr":0,
    "qs_pg:pop_sr":2,
    "qs_pg:qs_pg_placetype":"locality",
    "qs_pg:qs_pg_placetype_gp":"Town",
    "qs_pg:woe_adm0":23424950,
    "woe:adm0_id":23424950,
    "woe:name_adm0":"Espa\u00f1a",
    "woe:name_adm1":"Castilla y Le\u00f3n",
    "woe:placetype":"Town",
    "wof:name":"Milles de la Polvorosa",
    "wof:placetype":"locality",
    "wof:population":263
},
  "geometry": {"coordinates":[-5.73309,41.92339],"type":"Point"}
}