{
  "type": "Feature",
  "properties": {
    "gn:country":"ES",
    "gn:fcode":"PPLA3",
    "gn:population":474,
    "iso:country":"ES",
    "name:arg_x_preferred":[
        "Oliet"
    ],
    "name:ast_x_preferred":[
        "Oliete"
    ],
    "name:azb_x_preferred":[
        "\u0627\u0644\u06cc\u062a\u0647"
    ],
    "name:cat_x_preferred":[
        "Oliete"
    ],
    "name:ceb_x_preferred":[
        "Oliete"
    ],
    "name:eng_x_preferred":[
        "Oliete"
    ],
    "name:eus_x_preferred":[
        "Oliete"
    ],
    "name:fas_x_preferred":[
        "\u0627\u0644\u06cc\u062a\u0647"
    ],
    "name:fra_x_preferred":[
        "Oliete"
    ],
    "name:glg_x_preferred":[
        "Oliete"
    ],
    "name:heb_x_preferred":[
        "\u05d0\u05d5\u05dc\u05d9\u05d9\u05d8\u05d4"
    ],
    "name:hun_x_preferred":[
        "Oliete"
    ],
    "name:ita_x_preferred":[
        "Oliete"
    ],
    "name:kaz_x_preferred":[
        "\u041e\u043b\u044c\u0435\u0442\u0435"
    ],
    "name:msa_x_preferred":[
        "Oliete"
    ],
    "name:nan_x_preferred":[
        "Oliete"
    ],
    "name:nld_x_preferred":[
        "Oliete"
    ],
    "name:oci_x_preferred":[
        "Oliete"
    ],
    "name:pol_x_preferred":[
        "Oliete"
    ],
    "name:por_x_preferred":[
        "Oliete"
    ],
    "name:rus_x_preferred":[
        "\u041e\u043b\u044c\u0435\u0442\u0435"
    ],
    "name:spa_x_preferred":[
        "Oliete"
    ],
    "name:swe_x_preferred":[
        "Oliete"
    ],
    "name:ukr_x_preferred":[
        "\u041e\u043b\u044c\u0454\u0442\u0435"
    ],
    "name:uzb_x_preferred":[
        "Oliete"
    ],
    "name:vie_x_preferred":[
        "Oliete"
    ],
    "name:war_x_preferred":[
        "Oliete"
    ],
    "name:zho_x_preferred":[
        "\u5965\u5217\u7279"
    ],
    "qs_pg:aaroncc":"ES",
    "qs_pg:gn_country":"ES",
    "qs_pg:gn_fcode":"PPLA3",
    "qs_pg:gn_pop":474,
    "qs_pg:name":"Oliete",
    "qs_pg:name_adm0":"Espa\u00f1a",
    "qs_pg:name_adm1":"Arag\u00f3n",
    "qs_pg:photos":62,
    "qs_pg:photos_1k":13,
    "qs_pg:photos_9k":1,
    "qs_pg:photos_9r":2,
    "qs_pg:photos_all":62,
    "qs_pg:photos_sr":2,
    "qs_pg:pop_sr":2,
    "qs_pg:qs_pg_placetype":"locality",
    "qs_pg:qs_pg_placetype_gp":"Town",
    "qs_pg:woe_adm0":23424950,
    "woe:adm0_id":23424950,
    "woe:name_adm0":"Espa\u00f1a",
    "woe:name_adm1":"Arag\u00f3n",
    "woe:placetype":"Town",
    "wof:name":"Oliete",
    "wof:placetype":"locality",
    "wof:population":474
},
  "geometry": {"coordinates":[-0.67429,40.99791],"type":"Point"}
}