{
  "type": "Feature",
  "properties": {
    "gn:admin1_code":"34",
    "gn:admin2_code":"O",
    "gn:admin3_code":"33074",
    "gn:asciiname":"Puente",
    "gn:country_code":"ES",
    "gn:dem":229,
    "gn:feature_class":"P",
    "gn:feature_code":"PPL",
    "gn:name":"Puente",
    "gn:population":0,
    "gn:timezone":"Europe/Madrid",
    "iso:country":"ES",
    "wof:name":"Puente",
    "wof:placetype":"locality"
},
  "geometry": {"coordinates":[-7.06667,43.45],"type":"Point"}
}