{
  "type": "Feature",
  "properties": {
    "iso:country":"ES",
    "name:ara_x_preferred":[
        "\u0627\u0644\u0628\u0637\u0631\u0648\u062c"
    ],
    "name:ceb_x_preferred":[
        "Los Pedroches"
    ],
    "name:deu_x_preferred":[
        "Los Pedroches"
    ],
    "name:ell_x_preferred":[
        "\u039b\u03bf\u03c2 \u03a0\u03b5\u03b4\u03c1\u03cc\u03c4\u03c3\u03b5\u03c2"
    ],
    "name:eng_x_preferred":[
        "Los Pedroches"
    ],
    "name:ita_x_preferred":[
        "Los Pedroches"
    ],
    "name:kaz_x_preferred":[
        "\u0412\u0430\u043b\u044c\u0435-\u0434\u0435-\u043b\u043e\u0441-\u041f\u0435\u0434\u0440\u043e\u0447\u0435\u0441"
    ],
    "name:rus_x_preferred":[
        "\u0412\u0430\u043b\u044c\u0435-\u0434\u0435-\u043b\u043e\u0441-\u041f\u0435\u0434\u0440\u043e\u0447\u0435\u0441"
    ],
    "name:sco_x_preferred":[
        "Los Pedroches"
    ],
    "name:spa_x_preferred":[
        "Pedroches"
    ],
    "name:swe_x_preferred":[
        "Los Pedroches"
    ],
    "qs:gn_adm0_cc":"ES",
    "qs:gn_local":0,
    "qs:gn_nam_loc":"C\u00f3rdoba, C\u00f3rdoba, C\u00f3rdoba, Andaluc\u00eda, ES",
    "qs:gn_namadm1":"51",
    "qs:local_max":18851,
    "qs:local_sum":52543,
    "qs:localhoods":32,
    "qs:name":"Pedroches",
    "qs:name_adm0":"Espa\u00f1a",
    "qs:name_adm1":"Andaluc\u00eda",
    "qs:name_adm2":"C\u00f3rdoba",
    "qs:name_lau":"C\u00f3rdoba",
    "qs:name_local":"C\u00f3rdoba",
    "qs:photo_max":5,
    "qs:photo_sum":19,
    "qs:placetype":"Suburb",
    "qs:quad_count":11,
    "qs:woe_adm0":23424950,
    "qs:woe_adm1":12578029,
    "qs:woe_adm2":12602098,
    "qs:woe_lau":12688792,
    "qs:woe_local":758007,
    "qs:woe_ver":"7.10.0",
    "wd:wordcount":178,
    "wof:name":"Pedroches",
    "wof:placetype":"neighbourhood"
},
  "geometry": {"coordinates":[-4.769078,37.931768],"type":"Point"}
}