{
  "type": "Feature",
  "properties": {
    "gn:country":"ES",
    "gn:fcode":"PPL",
    "gn:population":0,
    "iso:country":"ES",
    "name:ara_x_preferred":[
        "\u0628\u0627\u0644\u0627\u0648 \u0633\u0627\u0628\u0627\u0631\u062f\u064a\u0631\u0627"
    ],
    "name:arg_x_preferred":[
        "Palau-saverdera"
    ],
    "name:ast_x_preferred":[
        "Palau-saverdera"
    ],
    "name:cat_x_preferred":[
        "Palau-saverdera"
    ],
    "name:ceb_x_preferred":[
        "Palau-saverdera"
    ],
    "name:deu_x_preferred":[
        "Palau-saverdera"
    ],
    "name:eng_x_preferred":[
        "Palau-saverdera"
    ],
    "name:eus_x_preferred":[
        "Palau-saverdera"
    ],
    "name:fra_x_preferred":[
        "Palau-saverdera"
    ],
    "name:hun_x_preferred":[
        "Palau-saverdera"
    ],
    "name:hye_x_preferred":[
        "\u054a\u0561\u056c\u0561\u0578\u0582 \u054d\u0561\u0562\u0561\u0580\u0564\u0565\u0580\u0561"
    ],
    "name:ita_x_preferred":[
        "Palau-saverdera"
    ],
    "name:kaz_x_preferred":[
        "\u041f\u0430\u043b\u0430\u0443-\u0421\u0430\u0431\u0430\u0440\u0434\u0435\u0440\u0430"
    ],
    "name:lat_x_preferred":[
        "Palau-saverdera"
    ],
    "name:msa_x_preferred":[
        "Palau-saverdera"
    ],
    "name:nld_x_preferred":[
        "Palau-saverdera"
    ],
    "name:oci_x_preferred":[
        "Palau-saverdera"
    ],
    "name:pam_x_preferred":[
        "Palau-saverdera"
    ],
    "name:pol_x_preferred":[
        "Palau-saverdera"
    ],
    "name:por_x_preferred":[
        "Palau-saverdera"
    ],
    "name:rus_x_preferred":[
        "\u041f\u0430\u043b\u0430\u0443-\u0421\u0430\u0431\u0430\u0440\u0434\u0435\u0440\u0430"
    ],
    "name:spa_x_preferred":[
        "Palau Sabardera"
    ],
    "name:sqi_x_preferred":[
        "Palau-saverdera"
    ],
    "name:swe_x_preferred":[
        "Palau-saverdera"
    ],
    "name:tah_x_preferred":[
        "Palau-saverdera"
    ],
    "name:ukr_x_preferred":[
        "\u041f\u0430\u043b\u0430\u0443-\u0441\u0430\u0431\u0430\u0440\u0434\u0435\u0440\u0430"
    ],
    "name:uzb_x_preferred":[
        "Palau-saverdera"
    ],
    "name:vie_x_preferred":[
        "Palau-saverdera"
    ],
    "name:war_x_preferred":[
        "Palau-saverdera"
    ],
    "name:zho_x_preferred":[
        "\u5e15\u52b3-\u8428\u97e6\u5c14\u5fb7\u62c9"
    ],
    "qs_pg:aaroncc":"ES",
    "qs_pg:gn_country":"ES",
    "qs_pg:gn_fcode":"PPL",
    "qs_pg:gn_pop":0,
    "qs_pg:name":"Palau-Saverdera",
    "qs_pg:name_adm0":"Espa\u00f1a",
    "qs_pg:name_adm1":"Catalunya",
    "qs_pg:photos":499,
    "qs_pg:photos_1k":101,
    "qs_pg:photos_9k":2,
    "qs_pg:photos_9r":5,
    "qs_pg:photos_all":499,
    "qs_pg:photos_sr":7,
    "qs_pg:pop_sr":0,
    "qs_pg:qs_pg_placetype":"locality",
    "qs_pg:qs_pg_placetype_gp":"Town",
    "qs_pg:woe_adm0":23424950,
    "woe:adm0_id":23424950,
    "woe:name_adm0":"Espa\u00f1a",
    "woe:name_adm1":"Catalunya",
    "woe:placetype":"Town",
    "wof:name":"Palau-Saverdera",
    "wof:placetype":"locality"
},
  "geometry": {"coordinates":[3.14685,42.30778],"type":"Point"}
}