{
  "type": "Feature",
  "properties": {
    "iso:country":"ES",
    "qs_pg:aaroncc":"ES",
    "qs_pg:name":"Urbanizaci\u00f3n Cortijo Nag\u00fceles",
    "qs_pg:name_adm0":"Espa\u00f1a",
    "qs_pg:name_adm1":"Andaluc\u00eda",
    "qs_pg:photos":336,
    "qs_pg:photos_1k":68,
    "qs_pg:photos_9k":1,
    "qs_pg:photos_9r":5,
    "qs_pg:photos_all":336,
    "qs_pg:photos_sr":5,
    "qs_pg:pop_sr":0,
    "qs_pg:qs_pg_placetype":"locality",
    "qs_pg:qs_pg_placetype_gp":"Town",
    "qs_pg:woe_adm0":23424950,
    "woe:adm0_id":23424950,
    "woe:name_adm0":"Espa\u00f1a",
    "woe:name_adm1":"Andaluc\u00eda",
    "woe:placetype":"Town",
    "wof:name":"Urbanizaci\u00f3n Cortijo Nag\u00fceles",
    "wof:placetype":"locality"
},
  "geometry": {"coordinates":[-4.912111,36.518741],"type":"Point"}
}