{
  "type": "Feature",
  "properties": {
    "gn:admin1_code":"55",
    "gn:admin2_code":"SA",
    "gn:admin3_code":"37364",
    "gn:asciiname":"Zarza de Don Beltran",
    "gn:country_code":"ES",
    "gn:dem":752,
    "gn:feature_class":"P",
    "gn:feature_code":"PPL",
    "gn:name":"Zarza de Don Beltr\u00e1n",
    "gn:population":0,
    "gn:timezone":"Europe/Madrid",
    "iso:country":"ES",
    "wof:name":"Zarza de Don Beltran",
    "wof:placetype":"locality"
},
  "geometry": {"coordinates":[-6.4191,41.1732],"type":"Point"}
}