{
  "type": "Feature",
  "properties": {
    "gn:admin1_code":"56",
    "gn:admin2_code":"GI",
    "gn:admin3_code":"17141",
    "gn:admin4_code":"17069.0",
    "gn:asciiname":"Vilallovent",
    "gn:country_code":"ES",
    "gn:dem":1173,
    "gn:feature_class":"P",
    "gn:feature_code":"PPL",
    "gn:name":"Vilallovent",
    "gn:population":0,
    "gn:timezone":"Europe/Madrid",
    "iso:country":"ES",
    "name:cat_x_preferred":[
        "Vilallovent"
    ],
    "wof:name":"Vilallovent",
    "wof:placetype":"locality"
},
  "geometry": {"coordinates":[1.95264,42.40805],"type":"Point"}
}