{
  "type": "Feature",
  "properties": {
    "gn:gn_country":"ES",
    "gn:gn_fcode":"PPL",
    "gn:gn_pop":0,
    "iso:country":"ES",
    "name:baq_x_preferred":[
        "Tresponde"
    ],
    "name:dut_x_preferred":[
        "Trespuentes"
    ],
    "name:eng_x_preferred":[
        "Trespuentes"
    ],
    "name:eus_x_preferred":[
        "Trasponte"
    ],
    "name:eus_x_variant":[
        "Tresponde"
    ],
    "name:fre_x_preferred":[
        "Trespuentes"
    ],
    "name:spa_x_preferred":[
        "Trespuentes"
    ],
    "qs_pg:aaroncc":"ES",
    "qs_pg:gn_country":"ES",
    "qs_pg:gn_fcode":"PPL",
    "qs_pg:gn_pop":0,
    "qs_pg:name":"Trespuentes",
    "qs_pg:name_adm0":"Espa\u00f1a",
    "qs_pg:name_adm1":"Euskadi",
    "qs_pg:photos":65,
    "qs_pg:photos_1k":13,
    "qs_pg:photos_9k":1,
    "qs_pg:photos_9r":2,
    "qs_pg:photos_all":65,
    "qs_pg:photos_sr":2,
    "qs_pg:pop_sr":0,
    "qs_pg:qs_pg_placetype":"locality",
    "qs_pg:qs_pg_placetype_gp":"Town",
    "qs_pg:woe_adm0":23424950,
    "woe:adm0_id":23424950,
    "woe:name_adm0":"Espa\u00f1a",
    "woe:name_adm1":"Euskadi",
    "woe:placetype":"Town",
    "wof:name":"Trespuentes",
    "wof:placetype":"locality"
},
  "geometry": {"coordinates":[-2.78514,42.84705],"type":"Point"}
}