{
  "type": "Feature",
  "properties": {
    "gn:admin1_code":"58",
    "gn:admin2_code":"LU",
    "gn:admin3_code":"27042",
    "gn:asciiname":"Castro",
    "gn:country_code":"ES",
    "gn:dem":667,
    "gn:feature_class":"P",
    "gn:feature_code":"PPL",
    "gn:name":"Castro",
    "gn:population":5822,
    "gn:timezone":"Europe/Madrid",
    "iso:country":"ES",
    "wof:name":"Castro",
    "wof:placetype":"locality",
    "wof:population":5822
},
  "geometry": {"coordinates":[-7.58333,42.76667],"type":"Point"}
}