{
  "type": "Feature",
  "properties": {
    "gn:admin1_code":"54",
    "gn:admin2_code":"CU",
    "gn:admin3_code":"16908",
    "gn:asciiname":"Rubielos Bajos",
    "gn:country_code":"ES",
    "gn:dem":796,
    "gn:feature_class":"P",
    "gn:feature_code":"PPL",
    "gn:name":"Rubielos Bajos",
    "gn:population":0,
    "gn:timezone":"Europe/Madrid",
    "iso:country":"ES",
    "wof:name":"Rubielos Bajos",
    "wof:placetype":"locality"
},
  "geometry": {"coordinates":[-2.03333,39.45],"type":"Point"}
}