{
  "type": "Feature",
  "properties": {
    "gn:gn_country":"ES",
    "gn:gn_fcode":"PPLA3",
    "gn:gn_pop":2559,
    "gn:population":2559,
    "iso:country":"ES",
    "name:ara_x_preferred":[
        "\u0646\u0648\u063a\u064a\u0631\u0627 \u062f\u064a \u0631\u0627\u0645\u0648\u064a\u0646"
    ],
    "name:baq_x_preferred":[
        "Nogueira de Ramu\u00edn"
    ],
    "name:cat_x_preferred":[
        "Nogueira de Ramu\u00edn"
    ],
    "name:chi_x_preferred":[
        "\u8bfa\u76d6\u62c9\u5fb7\u62c9\u7a46\u4f0a\u6069"
    ],
    "name:dut_x_preferred":[
        "Nogueira de Ramu\u00edn"
    ],
    "name:eng_x_preferred":[
        "Nogueira de Ramu\u00edn"
    ],
    "name:fre_x_preferred":[
        "Nogueira de Ramu\u00edn"
    ],
    "name:glg_x_preferred":[
        "Nogueira de Ramu\u00edn"
    ],
    "name:hun_x_preferred":[
        "Nogueira de Ramu\u00edn"
    ],
    "name:ita_x_preferred":[
        "Nogueira de Ramu\u00edn"
    ],
    "name:jpn_x_preferred":[
        "\u30ce\u30b2\u30a4\u30e9\u30fb\u30c7\u30fb\u30e9\u30e0\u30a4\u30f3"
    ],
    "name:kaz_x_preferred":[
        "\u041d\u043e\u0433\u0435\u0439\u0440\u0430-\u0434\u0435-\u0420\u0430\u043c\u0443\u0438\u043d"
    ],
    "name:lit_x_preferred":[
        "Nogeira de Ramuinas"
    ],
    "name:lmo_x_preferred":[
        "Nogueira de Ramu\u00edn"
    ],
    "name:may_x_preferred":[
        "Nogueira de Ramu\u00edn"
    ],
    "name:nan_x_preferred":[
        "Nogueira de Ramu\u00edn"
    ],
    "name:oci_x_preferred":[
        "Nogueira de Ramu\u00edn"
    ],
    "name:pol_x_preferred":[
        "Nogueira de Ramu\u00edn"
    ],
    "name:por_x_preferred":[
        "Nogueira de Ramu\u00edn"
    ],
    "name:rus_x_preferred":[
        "\u041d\u043e\u0433\u0435\u0439\u0440\u0430-\u0434\u0435-\u0420\u0430\u043c\u0443\u0438\u043d"
    ],
    "name:sco_x_preferred":[
        "Nogueira de Ramu\u00edn"
    ],
    "name:spa_x_preferred":[
        "Nogueira de Ramu\u00edn"
    ],
    "name:swe_x_preferred":[
        "Nogueira de Ramu\u00edn"
    ],
    "name:tur_x_preferred":[
        "Nogueira de Ramu\u00edn"
    ],
    "name:ukr_x_preferred":[
        "\u041d\u043e\u0433\u0435\u0439\u0440\u0430-\u0434\u0435-\u0420\u0430\u043c\u0443\u0457\u043d"
    ],
    "name:uzb_x_preferred":[
        "Nogueira de Ramu\u00edn"
    ],
    "name:vie_x_preferred":[
        "Nogueira de Ramu\u00edn"
    ],
    "name:war_x_preferred":[
        "Nogueira de Ramu\u00edn"
    ],
    "qs_pg:aaroncc":"ES",
    "qs_pg:gn_country":"ES",
    "qs_pg:gn_fcode":"PPLA3",
    "qs_pg:gn_pop":2559,
    "qs_pg:name":"Nogueira de Ramu\u00edn",
    "qs_pg:name_adm0":"Espa\u00f1a",
    "qs_pg:name_adm1":"Galicia",
    "qs_pg:photos":29,
    "qs_pg:photos_1k":6,
    "qs_pg:photos_9k":1,
    "qs_pg:photos_9r":2,
    "qs_pg:photos_all":29,
    "qs_pg:photos_sr":2,
    "qs_pg:pop_sr":4,
    "qs_pg:qs_pg_placetype":"locality",
    "qs_pg:qs_pg_placetype_gp":"Town",
    "qs_pg:woe_adm0":23424950,
    "woe:adm0_id":23424950,
    "woe:name_adm0":"Espa\u00f1a",
    "woe:name_adm1":"Galicia",
    "woe:placetype":"Town",
    "wof:name":"Nogueira de Ramu\u00edn",
    "wof:placetype":"locality",
    "wof:population":2559
},
  "geometry": {"coordinates":[-7.74982,42.41712],"type":"Point"}
}