{
  "type": "Feature",
  "properties": {
    "gn:admin1_code":"58",
    "gn:admin2_code":"C",
    "gn:admin3_code":"15014",
    "gn:asciiname":"Brino",
    "gn:country_code":"ES",
    "gn:dem":194,
    "gn:feature_class":"P",
    "gn:feature_code":"PPL",
    "gn:name":"Bri\u00f1o",
    "gn:population":0,
    "gn:timezone":"Europe/Madrid",
    "iso:country":"ES",
    "name:und_x_variant":[
        "Bri\u00f1o"
    ],
    "wof:name":"Brino",
    "wof:placetype":"locality"
},
  "geometry": {"coordinates":[-8.96226,43.18074],"type":"Point"}
}