{
  "type": "Feature",
  "properties": {
    "gn:admin1_code":"55",
    "gn:admin2_code":"SA",
    "gn:admin3_code":"37040",
    "gn:asciiname":"Valverde de la Valmuza",
    "gn:country_code":"ES",
    "gn:dem":826,
    "gn:feature_class":"P",
    "gn:feature_code":"PPL",
    "gn:name":"Valverde de la Valmuza",
    "gn:population":0,
    "gn:timezone":"Europe/Madrid",
    "iso:country":"ES",
    "wof:name":"Valverde de la Valmuza",
    "wof:placetype":"locality"
},
  "geometry": {"coordinates":[-5.78259,40.8893],"type":"Point"}
}