{
  "type": "Feature",
  "properties": {
    "gn:admin1_code":"58",
    "gn:admin2_code":"PO",
    "gn:admin3_code":"36025",
    "gn:asciiname":"Covelo",
    "gn:cc2":"ES",
    "gn:country_code":"ES",
    "gn:dem":583,
    "gn:feature_class":"P",
    "gn:feature_code":"PPL",
    "gn:name":"Covelo",
    "gn:population":0,
    "gn:timezone":"Europe/Madrid",
    "iso:country":"ES",
    "name:ceb_x_preferred":[
        "Covelo"
    ],
    "name:deu_x_preferred":[
        "Covelo"
    ],
    "name:fra_x_preferred":[
        "Covelo"
    ],
    "name:glg_x_preferred":[
        "Covelo"
    ],
    "name:ita_x_preferred":[
        "Covelo"
    ],
    "name:nld_x_preferred":[
        "Covelo"
    ],
    "name:por_x_preferred":[
        "Covelo"
    ],
    "name:srp_x_preferred":[
        "Covelo"
    ],
    "name:swe_x_preferred":[
        "Covelo"
    ],
    "name:tur_x_preferred":[
        "Covelo"
    ],
    "name:ukr_x_preferred":[
        "\u041a\u043e\u0432\u0435\u043b\u0443"
    ],
    "name:und_x_variant":[
        "San Sebasti\u00e1n",
        "Covelo"
    ],
    "wof:name":"Covelo",
    "wof:placetype":"locality"
},
  "geometry": {"coordinates":[-8.39477,42.42784],"type":"Point"}
}