{
  "type": "Feature",
  "properties": {
    "gn:admin1_code":"58",
    "gn:admin2_code":"OR",
    "gn:admin3_code":"32084",
    "gn:asciiname":"Domes",
    "gn:cc2":"ES",
    "gn:country_code":"ES",
    "gn:dem":684,
    "gn:feature_class":"P",
    "gn:feature_code":"PPL",
    "gn:name":"Dom\u00e9s",
    "gn:population":0,
    "gn:timezone":"Europe/Madrid",
    "iso:country":"ES",
    "name:und_x_variant":[
        "San Mart\u00edn",
        "Dom\u00e9s"
    ],
    "wof:name":"Domes",
    "wof:placetype":"locality"
},
  "geometry": {"coordinates":[-7.95,42.11667],"type":"Point"}
}