{
  "type": "Feature",
  "properties": {
    "gn:gn_country":"ES",
    "gn:gn_fcode":"PPLA3",
    "gn:gn_pop":412,
    "gn:population":412,
    "iso:country":"ES",
    "name:arg_x_preferred":[
        "Berlanga del Bierzo"
    ],
    "name:cat_x_preferred":[
        "Berlanga del Bierzo"
    ],
    "name:deu_x_preferred":[
        "Berlanga del Bierzo"
    ],
    "name:eng_x_preferred":[
        "Berlanga del Bierzo"
    ],
    "name:eus_x_preferred":[
        "Berlanga del Bierzo"
    ],
    "name:fra_x_preferred":[
        "Berlanga del Bierzo"
    ],
    "name:glg_x_preferred":[
        "Berlanga del Bierzo"
    ],
    "name:haw_x_preferred":[
        "Berlanga del Bierzo"
    ],
    "name:hun_x_preferred":[
        "Berlanga del Bierzo"
    ],
    "name:ido_x_preferred":[
        "Berlanga del Bierzo"
    ],
    "name:ina_x_preferred":[
        "Berlanga del Bierzo"
    ],
    "name:ita_x_preferred":[
        "Berlanga del Bierzo"
    ],
    "name:jpn_x_preferred":[
        "\u30d9\u30eb\u30e9\u30f3\u30ac\u30fb\u30c7\u30eb\u30fb\u30d3\u30a8\u30eb\u30bd"
    ],
    "name:msa_x_preferred":[
        "Berlanga del Bierzo"
    ],
    "name:nld_x_preferred":[
        "Berlanga del Bierzo"
    ],
    "name:oci_x_preferred":[
        "Berlanga del Bierzo"
    ],
    "name:pol_x_preferred":[
        "Berlanga del Bierzo"
    ],
    "name:por_x_preferred":[
        "Berlanga del Bierzo"
    ],
    "name:rup_x_preferred":[
        "Berlanga del Bierzo"
    ],
    "name:rus_x_preferred":[
        "\u0411\u0435\u0440\u043b\u0430\u043d\u0433\u0430-\u0434\u0435\u043b\u044c-\u0411\u044c\u0435\u0440\u0441\u043e"
    ],
    "name:spa_x_preferred":[
        "Berlanga del Bierzo"
    ],
    "name:swe_x_preferred":[
        "Berlanga del Bierzo"
    ],
    "name:tpi_x_preferred":[
        "Berlanga del Bierzo"
    ],
    "name:ukr_x_preferred":[
        "\u0411\u0435\u0440\u043b\u0430\u043d\u0433\u0430-\u0434\u0435\u043b\u044c-\u0411'\u0454\u0440\u0441\u043e"
    ],
    "name:vie_x_preferred":[
        "Berlanga del Bierzo"
    ],
    "name:war_x_preferred":[
        "Berlanga del Bierzo"
    ],
    "name:zho_x_preferred":[
        "\u8d1d\u5c14\u5170\u52a0\u5fb7\u5c14\u7ef4\u8036\u5c14\u7d22"
    ],
    "qs_pg:aaroncc":"ES",
    "qs_pg:gn_country":"ES",
    "qs_pg:gn_fcode":"PPLA3",
    "qs_pg:gn_pop":412,
    "qs_pg:name":"Berlanga del Bierzo",
    "qs_pg:name_adm0":"Espa\u00f1a",
    "qs_pg:name_adm1":"Castilla y Le\u00f3n",
    "qs_pg:photos_9r":0,
    "qs_pg:photos_sr":0,
    "qs_pg:pop_sr":2,
    "qs_pg:qs_pg_placetype":"locality",
    "qs_pg:qs_pg_placetype_gp":"Town",
    "qs_pg:woe_adm0":23424950,
    "woe:adm0_id":23424950,
    "woe:name_adm0":"Espa\u00f1a",
    "woe:name_adm1":"Castilla y Le\u00f3n",
    "woe:placetype":"Town",
    "wof:name":"Berlanga del Bierzo",
    "wof:placetype":"locality",
    "wof:population":412
},
  "geometry": {"coordinates":[-6.60565,42.73104],"type":"Point"}
}