{
  "type": "Feature",
  "properties": {
    "gn:admin1_code":"56",
    "gn:admin2_code":"L",
    "gn:admin3_code":"25075",
    "gn:asciiname":"Sant Ponc",
    "gn:country_code":"ES",
    "gn:dem":519,
    "gn:feature_class":"P",
    "gn:feature_code":"PPL",
    "gn:name":"Sant Pon\u00e7",
    "gn:population":0,
    "gn:timezone":"Europe/Madrid",
    "iso:country":"ES",
    "wof:name":"Sant Ponc",
    "wof:placetype":"locality"
},
  "geometry": {"coordinates":[1.60233,41.96204],"type":"Point"}
}