{
  "type": "Feature",
  "properties": {
    "iso:country":"ES",
    "name:eng_x_preferred":[
        "Los Almendros"
    ],
    "name:spa_x_preferred":[
        "Los Almendros"
    ],
    "wof:name":"Los Almendros",
    "wof:placetype":"neighbourhood"
},
  "geometry": {"coordinates":[-4.48262414220455,36.73681509993862],"type":"Point"}
}