{
  "type": "Feature",
  "properties": {
    "gn:admin1_code":"55",
    "gn:admin2_code":"ZA",
    "gn:admin3_code":"49048",
    "gn:asciiname":"San Salvador de Palazuelo",
    "gn:country_code":"ES",
    "gn:dem":912,
    "gn:feature_class":"P",
    "gn:feature_code":"PPL",
    "gn:name":"San Salvador de Palazuelo",
    "gn:population":0,
    "gn:timezone":"Europe/Madrid",
    "iso:country":"ES",
    "wof:name":"San Salvador de Palazuelo",
    "wof:placetype":"locality"
},
  "geometry": {"coordinates":[-6.43978,42.02175],"type":"Point"}
}