{
  "type": "Feature",
  "properties": {
    "gn:admin1_code":"58",
    "gn:admin2_code":"OR",
    "gn:admin3_code":"32086",
    "gn:asciiname":"Morisca",
    "gn:country_code":"ES",
    "gn:dem":856,
    "gn:feature_class":"P",
    "gn:feature_code":"PPL",
    "gn:name":"Morisca",
    "gn:population":0,
    "gn:timezone":"Europe/Madrid",
    "iso:country":"ES",
    "wof:name":"Morisca",
    "wof:placetype":"locality"
},
  "geometry": {"coordinates":[-7.09367,42.20031],"type":"Point"}
}