{
  "type": "Feature",
  "properties": {
    "gn:gn_country":"ES",
    "gn:gn_fcode":"PPLA3",
    "gn:gn_pop":316,
    "gn:population":316,
    "iso:country":"ES",
    "name:arg_x_preferred":[
        "Mancera de Abajo"
    ],
    "name:baq_x_preferred":[
        "Mancera de Abajo"
    ],
    "name:cat_x_preferred":[
        "Mancera de Abajo"
    ],
    "name:chi_x_preferred":[
        "\u66fc\u585e\u62c9\u5fb7\u4e9a\u74e6\u970d"
    ],
    "name:dut_x_preferred":[
        "Mancera de Abajo"
    ],
    "name:eng_x_preferred":[
        "Mancera de Abajo"
    ],
    "name:fre_x_preferred":[
        "Mancera de Abajo"
    ],
    "name:hun_x_preferred":[
        "Mancera de Abajo"
    ],
    "name:ina_x_preferred":[
        "Mancera de Abajo"
    ],
    "name:ita_x_preferred":[
        "Mancera de Abajo"
    ],
    "name:kaz_x_preferred":[
        "\u041c\u0430\u043d\u0441\u0435\u0440\u0430-\u0434\u0435-\u0410\u0431\u0430\u0445\u043e"
    ],
    "name:may_x_preferred":[
        "Mancera de Abajo"
    ],
    "name:nan_x_preferred":[
        "Mancera de Abajo"
    ],
    "name:oci_x_preferred":[
        "Mancera de Abajo"
    ],
    "name:pol_x_preferred":[
        "Mancera de Abajo"
    ],
    "name:por_x_preferred":[
        "Mancera de Abajo"
    ],
    "name:rus_x_preferred":[
        "\u041c\u0430\u043d\u0441\u0435\u0440\u0430-\u0434\u0435-\u0410\u0431\u0430\u0445\u043e"
    ],
    "name:spa_x_preferred":[
        "Mancera de Abajo"
    ],
    "name:swe_x_preferred":[
        "Mancera de Abajo"
    ],
    "name:ukr_x_preferred":[
        "\u041c\u0430\u043d\u0441\u0435\u0440\u0430-\u0434\u0435-\u0410\u0431\u0430\u0445\u043e"
    ],
    "name:uzb_x_preferred":[
        "Mancera de Abajo"
    ],
    "name:vie_x_preferred":[
        "Mancera de Abajo"
    ],
    "name:war_x_preferred":[
        "Mancera de Abajo"
    ],
    "qs_pg:aaroncc":"ES",
    "qs_pg:gn_country":"ES",
    "qs_pg:gn_fcode":"PPLA3",
    "qs_pg:gn_pop":316,
    "qs_pg:name":"Mancera de Abajo",
    "qs_pg:name_adm0":"Espa\u00f1a",
    "qs_pg:name_adm1":"Castilla y Le\u00f3n",
    "qs_pg:photos_9r":0,
    "qs_pg:photos_sr":0,
    "qs_pg:pop_sr":2,
    "qs_pg:qs_pg_placetype":"locality",
    "qs_pg:qs_pg_placetype_gp":"Town",
    "qs_pg:woe_adm0":23424950,
    "woe:adm0_id":23424950,
    "woe:name_adm0":"Espa\u00f1a",
    "woe:name_adm1":"Castilla y Le\u00f3n",
    "woe:placetype":"Town",
    "wof:name":"Mancera de Abajo",
    "wof:placetype":"locality",
    "wof:population":316
},
  "geometry": {"coordinates":[-5.19933,40.83974],"type":"Point"}
}