{
  "type": "Feature",
  "properties": {
    "iso:country":"ES",
    "name:ast_x_preferred":[
        "Santa Marina"
    ],
    "name:bel_x_preferred":[
        "\u0421\u0430\u043d\u0442\u0430-\u041c\u0430\u0440\u044b\u043d\u0430"
    ],
    "name:cat_x_preferred":[
        "Santa Marina"
    ],
    "name:ceb_x_preferred":[
        "Santa Marina"
    ],
    "name:eus_x_preferred":[
        "Santa Marina"
    ],
    "name:fra_x_preferred":[
        "Santa Marina"
    ],
    "name:ita_x_preferred":[
        "Santa Marina"
    ],
    "name:nld_x_preferred":[
        "Santa Marina"
    ],
    "name:scn_x_preferred":[
        "Santa Marina"
    ],
    "name:spa_x_preferred":[
        "Santa Marina"
    ],
    "name:srp_x_preferred":[
        "\u0421\u0430\u043d\u0442\u0430 \u041c\u0430\u0440\u0438\u043d\u0430"
    ],
    "name:swe_x_preferred":[
        "Santa Marina"
    ],
    "wof:name":"Santa Marina",
    "wof:placetype":"neighbourhood"
},
  "geometry": {"coordinates":[-4.7728269677943,37.89034554711431],"type":"Point"}
}