{
  "type": "Feature",
  "properties": {
    "iso:country":"ES",
    "wof:name":"Santa Marina",
    "wof:placetype":"neighbourhood"
},
  "geometry": {"coordinates":[-4.7728269677943,37.89034554711431],"type":"Point"}
}