{
  "type": "Feature",
  "properties": {
    "gn:admin1_code":"54",
    "gn:admin2_code":"CU",
    "gn:admin3_code":"16904",
    "gn:asciiname":"Jabaga",
    "gn:country_code":"ES",
    "gn:dem":971,
    "gn:feature_class":"P",
    "gn:feature_code":"PPL",
    "gn:name":"J\u00e1baga",
    "gn:population":0,
    "gn:timezone":"Europe/Madrid",
    "iso:country":"ES",
    "name:und_x_variant":[
        "J\u00e1baga"
    ],
    "wof:name":"Jabaga",
    "wof:placetype":"locality"
},
  "geometry": {"coordinates":[-2.26338,40.08632],"type":"Point"}
}