{
  "type": "Feature",
  "properties": {
    "gn:admin1_code":"07",
    "gn:admin2_code":"PM",
    "gn:admin3_code":"7026.0",
    "gn:asciiname":"Es Viver",
    "gn:country_code":"ES",
    "gn:dem":9,
    "gn:feature_class":"P",
    "gn:feature_code":"PPL",
    "gn:name":"Es Viver",
    "gn:population":0,
    "gn:timezone":"Europe/Madrid",
    "iso:country":"ES",
    "wof:name":"Es Viver",
    "wof:placetype":"locality"
},
  "geometry": {"coordinates":[1.41329,38.89851],"type":"Point"}
}