{
  "type": "Feature",
  "properties": {
    "gn:gn_country":"ES",
    "gn:gn_fcode":"PPLA3",
    "gn:gn_pop":983,
    "gn:population":983,
    "iso:country":"ES",
    "name:arg_x_preferred":[
        "Villoruela"
    ],
    "name:cat_x_preferred":[
        "Villoruela"
    ],
    "name:deu_x_preferred":[
        "Villoruela"
    ],
    "name:eng_x_preferred":[
        "Villoruela"
    ],
    "name:eus_x_preferred":[
        "Villoruela"
    ],
    "name:fra_x_preferred":[
        "Villoruela"
    ],
    "name:hun_x_preferred":[
        "Villoruela"
    ],
    "name:ina_x_preferred":[
        "Villoruela"
    ],
    "name:ita_x_preferred":[
        "Villoruela"
    ],
    "name:kaz_x_preferred":[
        "\u0412\u0438\u043b\u044c\u043e\u0440\u0443\u044d\u043b\u0430"
    ],
    "name:msa_x_preferred":[
        "Villoruela"
    ],
    "name:nan_x_preferred":[
        "Villoruela"
    ],
    "name:nld_x_preferred":[
        "Villoruela"
    ],
    "name:oci_x_preferred":[
        "Villoruela"
    ],
    "name:pol_x_preferred":[
        "Villoruela"
    ],
    "name:por_x_preferred":[
        "Villoruela"
    ],
    "name:rus_x_preferred":[
        "\u0412\u0438\u043b\u044c\u043e\u0440\u0443\u044d\u043b\u0430"
    ],
    "name:sco_x_preferred":[
        "Villoruela"
    ],
    "name:spa_x_preferred":[
        "Villoruela"
    ],
    "name:sqi_x_preferred":[
        "Villoruela"
    ],
    "name:ukr_x_preferred":[
        "\u0412\u0456\u043b\u044c\u0439\u043e\u0440\u0443\u0435\u043b\u0430"
    ],
    "name:uzb_x_preferred":[
        "Villoruela"
    ],
    "name:war_x_preferred":[
        "Villoruela"
    ],
    "name:zho_x_preferred":[
        "\u6bd4\u7565\u9c81\u57c3\u62c9"
    ],
    "qs_pg:aaroncc":"ES",
    "qs_pg:gn_country":"ES",
    "qs_pg:gn_fcode":"PPLA3",
    "qs_pg:gn_pop":983,
    "qs_pg:name":"Villoruela",
    "qs_pg:name_adm0":"Espa\u00f1a",
    "qs_pg:name_adm1":"Castilla y Le\u00f3n",
    "qs_pg:photos_9k":1,
    "qs_pg:photos_9r":1,
    "qs_pg:photos_all":1,
    "qs_pg:photos_sr":0,
    "qs_pg:pop_sr":2,
    "qs_pg:qs_pg_placetype":"locality",
    "qs_pg:qs_pg_placetype_gp":"Town",
    "qs_pg:woe_adm0":23424950,
    "woe:adm0_id":23424950,
    "woe:name_adm0":"Espa\u00f1a",
    "woe:name_adm1":"Castilla y Le\u00f3n",
    "woe:placetype":"Town",
    "wof:name":"Villoruela",
    "wof:placetype":"locality",
    "wof:population":983
},
  "geometry": {"coordinates":[-5.3938,41.0086],"type":"Point"}
}