{
  "type": "Feature",
  "properties": {
    "gn:admin1_code":"58",
    "gn:admin2_code":"OR",
    "gn:admin3_code":"32073",
    "gn:asciiname":"Vilar de Silva",
    "gn:country_code":"ES",
    "gn:dem":673,
    "gn:feature_class":"P",
    "gn:feature_code":"PPL",
    "gn:name":"Vilar de Silva",
    "gn:population":0,
    "gn:timezone":"Europe/Madrid",
    "iso:country":"ES",
    "wof:name":"Vilar de Silva",
    "wof:placetype":"locality"
},
  "geometry": {"coordinates":[-6.83006,42.46083],"type":"Point"}
}