{
  "type": "Feature",
  "properties": {
    "gn:admin1_code":"59",
    "gn:admin2_code":"BI",
    "gn:admin3_code":"48914",
    "gn:asciiname":"Barroeta",
    "gn:country_code":"ES",
    "gn:dem":47,
    "gn:feature_class":"P",
    "gn:feature_code":"PPL",
    "gn:name":"Barroeta",
    "gn:population":0,
    "gn:timezone":"Europe/Madrid",
    "iso:country":"ES",
    "wof:name":"Barroeta",
    "wof:placetype":"locality"
},
  "geometry": {"coordinates":[-2.6419,43.31752],"type":"Point"}
}