{
  "type": "Feature",
  "properties": {
    "gn:admin1_code":"52",
    "gn:admin2_code":"TE",
    "gn:admin3_code":"44123",
    "gn:asciiname":"Cobatillas",
    "gn:country_code":"ES",
    "gn:dem":1172,
    "gn:feature_class":"P",
    "gn:feature_code":"PPL",
    "gn:name":"Cobatillas",
    "gn:population":0,
    "gn:timezone":"Europe/Madrid",
    "iso:country":"ES",
    "wof:name":"Cobatillas",
    "wof:placetype":"locality"
},
  "geometry": {"coordinates":[-0.74241,40.67158],"type":"Point"}
}