{
  "type": "Feature",
  "properties": {
    "gn:admin1_code":"51",
    "gn:admin2_code":"AL",
    "gn:admin3_code":"04093",
    "gn:asciiname":"La Canada Ancha",
    "gn:cc2":"ES",
    "gn:country_code":"ES",
    "gn:dem":134,
    "gn:feature_class":"P",
    "gn:feature_code":"PPL",
    "gn:name":"La Ca\u00f1ada Ancha",
    "gn:population":0,
    "gn:timezone":"Europe/Madrid",
    "iso:country":"ES",
    "name:und_x_variant":[
        "Caser\u00edo La Ca\u00f1ada Ancha",
        "La Ca\u00f1ada Ancha"
    ],
    "wof:name":"La Canada Ancha",
    "wof:placetype":"locality"
},
  "geometry": {"coordinates":[-1.88333,37.13333],"type":"Point"}
}