{
  "type": "Feature",
  "properties": {
    "iso:country":"ES",
    "name:cat_x_preferred":[
        "Jueria"
    ],
    "name:deu_x_preferred":[
        "J\u00fcdisches Viertel"
    ],
    "name:eng_x_preferred":[
        "Barrio de la Juderia"
    ],
    "name:eng_x_variant":[
        "Juderia"
    ],
    "name:heb_x_preferred":[
        "\u05d4\u05e8\u05d5\u05d1\u05e2 \u05d4\u05d9\u05d4\u05d5\u05d3\u05d9"
    ],
    "name:nld_x_preferred":[
        "Jodenbuurt"
    ],
    "name:rus_x_preferred":[
        "\u0415\u0432\u0440\u0435\u0439\u0441\u043a\u0438\u0439 \u043a\u0432\u0430\u0440\u0442\u0430\u043b"
    ],
    "name:slk_x_preferred":[
        "\u017didovsk\u00e1 \u0161tvr\u0165"
    ],
    "name:spa_x_preferred":[
        "Barrio de la Juderia"
    ],
    "name:spa_x_variant":[
        "Barrio de la Juder\u00eda",
        "Juder\u00eda"
    ],
    "name:unk_x_variant":[
        "Barrio de la Juderia"
    ],
    "qs:gn_adm0_cc":"ES",
    "qs:gn_local":0,
    "qs:gn_nam_loc":"C\u00f3rdoba, C\u00f3rdoba, C\u00f3rdoba, Andaluc\u00eda, ES",
    "qs:gn_namadm1":"51",
    "qs:local_max":18851,
    "qs:local_sum":52543,
    "qs:localhoods":32,
    "qs:name":"Barrio de la Juderia",
    "qs:name_adm0":"Espa\u00f1a",
    "qs:name_adm1":"Andaluc\u00eda",
    "qs:name_adm2":"C\u00f3rdoba",
    "qs:name_lau":"C\u00f3rdoba",
    "qs:name_local":"C\u00f3rdoba",
    "qs:photo_max":3754,
    "qs:photo_sum":9546,
    "qs:placetype":"Suburb",
    "qs:quad_count":36,
    "qs:woe_adm0":23424950,
    "qs:woe_adm1":12578029,
    "qs:woe_adm2":12602098,
    "qs:woe_lau":12688792,
    "qs:woe_local":758007,
    "qs:woe_ver":"7.10.0",
    "wof:lang":[
        "spa"
    ],
    "wof:name":"Jewish Quarter",
    "wof:placetype":"neighbourhood"
},
  "geometry": {"coordinates":[-4.780315,37.880707],"type":"Point"}
}