{
  "type": "Feature",
  "properties": {
    "gn:admin1_code":"58",
    "gn:admin2_code":"C",
    "gn:admin3_code":"15059",
    "gn:asciiname":"Mercurin",
    "gn:cc2":"ES",
    "gn:country_code":"ES",
    "gn:dem":328,
    "gn:feature_class":"P",
    "gn:feature_code":"PPL",
    "gn:name":"Mercur\u00edn",
    "gn:population":0,
    "gn:timezone":"Europe/Madrid",
    "iso:country":"ES",
    "name:und_x_variant":[
        "San Clemente"
    ],
    "wof:name":"Mercurin",
    "wof:placetype":"locality"
},
  "geometry": {"coordinates":[-8.42522,43.1009],"type":"Point"}
}