{
  "type": "Feature",
  "properties": {
    "gn:admin1_code":"55",
    "gn:admin2_code":"SA",
    "gn:admin3_code":"37061",
    "gn:asciiname":"Zarzoso",
    "gn:country_code":"ES",
    "gn:dem":959,
    "gn:feature_class":"P",
    "gn:feature_code":"PPL",
    "gn:name":"Zarzoso",
    "gn:population":0,
    "gn:timezone":"Europe/Madrid",
    "iso:country":"ES",
    "name:und_x_variant":[
        "Alquer\u00eda Zarzoso",
        "Zarzoso"
    ],
    "wof:name":"Zarzoso",
    "wof:placetype":"locality"
},
  "geometry": {"coordinates":[-6.12797,40.60657],"type":"Point"}
}