{
  "type": "Feature",
  "properties": {
    "gn:gn_country":"ES",
    "gn:gn_fcode":"PPL",
    "gn:gn_pop":131,
    "gn:population":131,
    "iso:country":"ES",
    "name:arg_x_preferred":[
        "Retamoso"
    ],
    "name:arm_x_preferred":[
        "\u054c\u0565\u057f\u0561\u0574\u0578\u057d\u0578 \u0564\u0565 \u056c\u0561 \u053d\u0561\u057c\u0561"
    ],
    "name:baq_x_preferred":[
        "Retamoso"
    ],
    "name:bul_x_preferred":[
        "\u0420\u0435\u0442\u0430\u043c\u043e\u0441\u043e"
    ],
    "name:cat_x_preferred":[
        "Retamoso de la Jara"
    ],
    "name:chi_x_preferred":[
        "\u96f7\u5854\u83ab\u7d22"
    ],
    "name:dut_x_preferred":[
        "Retamoso de la Jara"
    ],
    "name:eng_x_preferred":[
        "Retamoso"
    ],
    "name:epo_x_preferred":[
        "Retamoso de la Jara"
    ],
    "name:fre_x_preferred":[
        "Retamoso de la Jara"
    ],
    "name:hun_x_preferred":[
        "Retamoso"
    ],
    "name:ina_x_preferred":[
        "Retamoso"
    ],
    "name:ita_x_preferred":[
        "Retamoso de la Jara"
    ],
    "name:kaz_x_preferred":[
        "\u0420\u0435\u0442\u0430\u043c\u043e\u0441\u043e-\u0434\u0435-\u043b\u0430-\u0425\u0430\u0440\u0430"
    ],
    "name:may_x_preferred":[
        "Retamoso"
    ],
    "name:oci_x_preferred":[
        "Retamoso de la Jara"
    ],
    "name:pol_x_preferred":[
        "Retamoso de la Jara"
    ],
    "name:por_x_preferred":[
        "Retamoso"
    ],
    "name:rum_x_preferred":[
        "Retamoso"
    ],
    "name:rus_x_preferred":[
        "\u0420\u0435\u0442\u0430\u043c\u043e\u0441\u043e-\u0434\u0435-\u043b\u0430-\u0425\u0430\u0440\u0430"
    ],
    "name:spa_x_preferred":[
        "Retamoso de la Jara"
    ],
    "name:swe_x_preferred":[
        "Retamoso"
    ],
    "name:ukr_x_preferred":[
        "\u0420\u0435\u0442\u0430\u043c\u043e\u0441\u043e"
    ],
    "name:war_x_preferred":[
        "Retamoso"
    ],
    "qs_pg:aaroncc":"ES",
    "qs_pg:gn_country":"ES",
    "qs_pg:gn_fcode":"PPL",
    "qs_pg:gn_pop":131,
    "qs_pg:name":"Retamoso",
    "qs_pg:name_adm0":"Espa\u00f1a",
    "qs_pg:name_adm1":"Castilla-La Mancha",
    "qs_pg:photos_9r":0,
    "qs_pg:photos_sr":0,
    "qs_pg:pop_sr":1,
    "qs_pg:qs_pg_placetype":"locality",
    "qs_pg:qs_pg_placetype_gp":"Town",
    "qs_pg:woe_adm0":23424950,
    "woe:adm0_id":23424950,
    "woe:name_adm0":"Espa\u00f1a",
    "woe:name_adm1":"Castilla-La Mancha",
    "woe:placetype":"Town",
    "wof:name":"Retamoso",
    "wof:placetype":"locality",
    "wof:population":131
},
  "geometry": {"coordinates":[-4.75541,39.74356],"type":"Point"}
}