{
  "type": "Feature",
  "properties": {
    "gn:admin1_code":"58",
    "gn:admin2_code":"C",
    "gn:admin3_code":"15042",
    "gn:asciiname":"Argalo",
    "gn:cc2":"ES",
    "gn:country_code":"ES",
    "gn:dem":133,
    "gn:feature_class":"P",
    "gn:feature_code":"PPL",
    "gn:name":"Argalo",
    "gn:population":0,
    "gn:timezone":"Europe/Madrid",
    "iso:country":"ES",
    "name:und_x_variant":[
        "Santa Mar\u00eda",
        "Argalo"
    ],
    "wof:name":"Argalo",
    "wof:placetype":"locality"
},
  "geometry": {"coordinates":[-8.90301,42.76472],"type":"Point"}
}