{
  "type": "Feature",
  "properties": {
    "gn:gn_country":"ES",
    "gn:gn_fcode":"PPLA3",
    "gn:gn_pop":521,
    "gn:population":521,
    "iso:country":"ES",
    "name:arg_x_preferred":[
        "Pomar de Valdivia"
    ],
    "name:cat_x_preferred":[
        "Pomar de Valdivia"
    ],
    "name:deu_x_preferred":[
        "Pomar de Valdivia"
    ],
    "name:eng_x_preferred":[
        "Pomar de Valdivia"
    ],
    "name:eus_x_preferred":[
        "Pomar de Valdivia"
    ],
    "name:fas_x_preferred":[
        "\u067e\u0645\u0627\u0631 \u062f \u0628\u0627\u0644\u062f\u06cc\u0628\u06cc\u0627"
    ],
    "name:fra_x_preferred":[
        "Pomar de Valdivia"
    ],
    "name:glg_x_preferred":[
        "Pomar de Valdivia"
    ],
    "name:hun_x_preferred":[
        "Pomar de Valdivia"
    ],
    "name:hye_x_preferred":[
        "\u054a\u0578\u0574\u0561\u0580 \u0564\u0565 \u054e\u0561\u056c\u0564\u056b\u057e\u056b\u0561"
    ],
    "name:ina_x_preferred":[
        "Pomar de Valdivia"
    ],
    "name:ita_x_preferred":[
        "Pomar de Valdivia"
    ],
    "name:msa_x_preferred":[
        "Pomar de Valdivia"
    ],
    "name:nan_x_preferred":[
        "Pomar de Valdivia"
    ],
    "name:nld_x_preferred":[
        "Pomar de Valdivia"
    ],
    "name:oci_x_preferred":[
        "Pomar de Valdivia"
    ],
    "name:pol_x_preferred":[
        "Pomar de Valdivia"
    ],
    "name:por_x_preferred":[
        "Pomar de Valdivia"
    ],
    "name:rus_x_preferred":[
        "\u041f\u043e\u043c\u0430\u0440-\u0434\u0435-\u0412\u0430\u043b\u044c\u0434\u0438\u0432\u0438\u0430"
    ],
    "name:spa_x_preferred":[
        "Pomar de Valdivia"
    ],
    "name:swe_x_preferred":[
        "Pomar de Valdivia"
    ],
    "name:ukr_x_preferred":[
        "\u041f\u043e\u043c\u0430\u0440-\u0434\u0435-\u0412\u0430\u043b\u044c\u0434\u0456\u0432\u0456\u044f"
    ],
    "name:unk_x_variant":[
        "Pomar de Valdivia"
    ],
    "name:uzb_x_preferred":[
        "Pomar de Valdivia"
    ],
    "name:vie_x_preferred":[
        "Pomar de Valdivia"
    ],
    "name:war_x_preferred":[
        "Pomar de Valdivia"
    ],
    "name:zho_x_preferred":[
        "\u6ce2\u9a6c\u5c14\u5fb7\u74e6\u5c14\u8fea\u7ef4\u4e9a"
    ],
    "qs_pg:aaroncc":"ES",
    "qs_pg:gn_country":"ES",
    "qs_pg:gn_fcode":"PPLA3",
    "qs_pg:gn_pop":521,
    "qs_pg:name":"Camesa de Valdivia",
    "qs_pg:name_adm0":"Espa\u00f1a",
    "qs_pg:name_adm1":"Castilla y Le\u00f3n",
    "qs_pg:photos_9k":1,
    "qs_pg:photos_9r":1,
    "qs_pg:photos_all":5,
    "qs_pg:photos_sr":0,
    "qs_pg:pop_sr":2,
    "qs_pg:qs_pg_placetype":"locality",
    "qs_pg:qs_pg_placetype_gp":"Town",
    "qs_pg:woe_adm0":23424950,
    "woe:adm0_id":23424950,
    "woe:name_adm0":"Espa\u00f1a",
    "woe:name_adm1":"Castilla y Le\u00f3n",
    "woe:placetype":"Town",
    "wof:name":"Camesa de Valdivia",
    "wof:placetype":"locality",
    "wof:population":521
},
  "geometry": {"coordinates":[-4.16756,42.77437],"type":"Point"}
}