{
  "type": "Feature",
  "properties": {
    "gn:admin1_code":"55",
    "gn:admin2_code":"LE",
    "gn:admin3_code":"24041",
    "gn:asciiname":"El Carril",
    "gn:country_code":"ES",
    "gn:dem":402,
    "gn:feature_class":"P",
    "gn:feature_code":"PPL",
    "gn:name":"El Carril",
    "gn:population":0,
    "gn:timezone":"Europe/Madrid",
    "iso:country":"ES",
    "wof:name":"El Carril",
    "wof:placetype":"locality"
},
  "geometry": {"coordinates":[-6.83137,42.50773],"type":"Point"}
}