{
  "type": "Feature",
  "properties": {
    "gn:admin1_code":"51",
    "gn:admin2_code":"AL",
    "gn:admin3_code":"04013",
    "gn:asciiname":"La Cuesta del Gato",
    "gn:country_code":"ES",
    "gn:dem":126,
    "gn:feature_class":"P",
    "gn:feature_code":"PPL",
    "gn:name":"La Cuesta del Gato",
    "gn:population":0,
    "gn:timezone":"Europe/Madrid",
    "iso:country":"ES",
    "name:und_x_variant":[
        "Cortijada La Cuesta del Gato",
        "La Cuesta del Gato"
    ],
    "wof:name":"La Cuesta del Gato",
    "wof:placetype":"locality"
},
  "geometry": {"coordinates":[-2.48171,36.85945],"type":"Point"}
}