{
  "type": "Feature",
  "properties": {
    "gn:admin1_code":"55",
    "gn:admin2_code":"LE",
    "gn:admin3_code":"24115",
    "gn:asciiname":"Santo Tomas de las Ollas",
    "gn:country_code":"ES",
    "gn:dem":602,
    "gn:feature_class":"P",
    "gn:feature_code":"PPL",
    "gn:name":"Santo Tom\u00e1s de las Ollas",
    "gn:population":0,
    "gn:timezone":"Europe/Madrid",
    "iso:country":"ES",
    "name:und_x_variant":[
        "Santo Tom\u00e1s de las Ollas"
    ],
    "wof:name":"Santo Tomas de las Ollas",
    "wof:placetype":"locality"
},
  "geometry": {"coordinates":[-6.57819,42.55877],"type":"Point"}
}