{
  "type": "Feature",
  "properties": {
    "gn:admin1_code":"54",
    "gn:admin2_code":"AB",
    "gn:admin3_code":"02049",
    "gn:asciiname":"La Alfera",
    "gn:country_code":"ES",
    "gn:dem":913,
    "gn:feature_class":"P",
    "gn:feature_code":"PPL",
    "gn:name":"La Alfera",
    "gn:population":0,
    "gn:timezone":"Europe/Madrid",
    "iso:country":"ES",
    "name:spa_x_preferred":[
        "La Alfera"
    ],
    "wof:name":"La Alfera",
    "wof:placetype":"locality"
},
  "geometry": {"coordinates":[-2.28173,38.51215],"type":"Point"}
}