{
  "type": "Feature",
  "properties": {
    "iso:country":"ES",
    "name:eng_x_preferred":[
        "Los Girasoles"
    ],
    "name:spa_x_preferred":[
        "Los Girasoles"
    ],
    "wof:name":"Los Girasoles",
    "wof:placetype":"neighbourhood"
},
  "geometry": {"coordinates":[-4.45369918563428,36.69502890860497],"type":"Point"}
}