{
  "type": "Feature",
  "properties": {
    "gn:admin1_code":"55",
    "gn:admin2_code":"LE",
    "gn:admin3_code":"24056",
    "gn:asciiname":"Valmartino",
    "gn:country_code":"ES",
    "gn:dem":1044,
    "gn:feature_class":"P",
    "gn:feature_code":"PPL",
    "gn:name":"Valmartino",
    "gn:population":0,
    "gn:timezone":"Europe/Madrid",
    "iso:country":"ES",
    "wof:name":"Valmartino",
    "wof:placetype":"locality"
},
  "geometry": {"coordinates":[-5.10854,42.79037],"type":"Point"}
}