{
  "type": "Feature",
  "properties": {
    "gn:admin1_code":"56",
    "gn:admin2_code":"GI",
    "gn:admin3_code":"17089",
    "gn:asciiname":"Els Escuts",
    "gn:country_code":"ES",
    "gn:dem":138,
    "gn:feature_class":"P",
    "gn:feature_code":"PPL",
    "gn:name":"Els Escuts",
    "gn:population":0,
    "gn:timezone":"Europe/Madrid",
    "iso:country":"ES",
    "wof:name":"Els Escuts",
    "wof:placetype":"locality"
},
  "geometry": {"coordinates":[2.91146,41.83171],"type":"Point"}
}