{
  "type": "Feature",
  "properties": {
    "gn:admin1_code":"55",
    "gn:admin2_code":"SA",
    "gn:admin3_code":"37039",
    "gn:asciiname":"Isabela",
    "gn:country_code":"ES",
    "gn:dem":779,
    "gn:feature_class":"P",
    "gn:feature_code":"PPL",
    "gn:name":"Isabela",
    "gn:population":0,
    "gn:timezone":"Europe/Madrid",
    "iso:country":"ES",
    "name:und_x_variant":[
        "Caser\u00edo Isabela",
        "Isabela"
    ],
    "wof:name":"Isabela",
    "wof:placetype":"locality"
},
  "geometry": {"coordinates":[-6.58674,40.73801],"type":"Point"}
}