{
  "type": "Feature",
  "properties": {
    "gn:admin1_code":"55",
    "gn:admin2_code":"SA",
    "gn:admin3_code":"37039",
    "gn:asciiname":"Isabela",
    "gn:country_code":"ES",
    "gn:dem":779,
    "gn:feature_class":"P",
    "gn:feature_code":"PPL",
    "gn:name":"Isabela",
    "gn:population":0,
    "gn:timezone":"Europe/Madrid",
    "iso:country":"ES",
    "name:bre_x_preferred":[
        "Isabela"
    ],
    "name:cat_x_preferred":[
        "Isabela"
    ],
    "name:ceb_x_preferred":[
        "Isabela"
    ],
    "name:deu_x_preferred":[
        "Isabela"
    ],
    "name:ell_x_preferred":[
        "\u0399\u03b6\u03b1\u03bc\u03c0\u03ad\u03bb\u03b1"
    ],
    "name:fin_x_preferred":[
        "Isabela"
    ],
    "name:fra_x_preferred":[
        "Isabela"
    ],
    "name:hun_x_preferred":[
        "Isabela"
    ],
    "name:ind_x_preferred":[
        "Isabela"
    ],
    "name:ita_x_preferred":[
        "Isabela"
    ],
    "name:jpn_x_preferred":[
        "\u30a4\u30b6\u30d9\u30e9"
    ],
    "name:nld_x_preferred":[
        "Isabela"
    ],
    "name:pol_x_preferred":[
        "Isabela"
    ],
    "name:por_x_preferred":[
        "Isabela"
    ],
    "name:rus_x_preferred":[
        "\u0418\u0441\u0430\u0431\u0435\u043b\u0430"
    ],
    "name:spa_x_preferred":[
        "Isabela"
    ],
    "name:swe_x_preferred":[
        "Isabela"
    ],
    "name:tgl_x_preferred":[
        "Isabela"
    ],
    "name:tur_x_preferred":[
        "Isabela"
    ],
    "name:und_x_variant":[
        "Caser\u00edo Isabela"
    ],
    "name:urd_x_preferred":[
        "\u0627\u06cc\u0632\u0627\u0628\u06cc\u0644\u0627"
    ],
    "name:war_x_preferred":[
        "Isabela"
    ],
    "wof:name":"Isabela",
    "wof:placetype":"locality"
},
  "geometry": {"coordinates":[-6.58674,40.73801],"type":"Point"}
}