{
  "type": "Feature",
  "properties": {
    "gn:admin1_code":"51",
    "gn:admin2_code":"J",
    "gn:admin3_code":"23050",
    "gn:asciiname":"Puente Nuevo",
    "gn:country_code":"ES",
    "gn:dem":374,
    "gn:feature_class":"P",
    "gn:feature_code":"PPL",
    "gn:name":"Puente Nuevo",
    "gn:population":0,
    "gn:timezone":"Europe/Madrid",
    "iso:country":"ES",
    "name:und_x_variant":[
        "Caser\u00edos Puente Nuevo",
        "Puente Nuevo"
    ],
    "wof:name":"Puente Nuevo",
    "wof:placetype":"locality"
},
  "geometry": {"coordinates":[-3.74678,37.78331],"type":"Point"}
}