{
  "type": "Feature",
  "properties": {
    "gn:admin1_code":"58",
    "gn:admin2_code":"C",
    "gn:admin3_code":"15053",
    "gn:asciiname":"Creo",
    "gn:country_code":"ES",
    "gn:dem":7,
    "gn:feature_class":"P",
    "gn:feature_code":"PPL",
    "gn:name":"Creo",
    "gn:population":0,
    "gn:timezone":"Europe/Madrid",
    "iso:country":"ES",
    "wof:name":"Creo",
    "wof:placetype":"locality"
},
  "geometry": {"coordinates":[-8.97945,42.78887],"type":"Point"}
}