{
  "type": "Feature",
  "properties": {
    "gn:admin1_code":"54",
    "gn:admin2_code":"CU",
    "gn:admin3_code":"16910",
    "gn:asciiname":"Cuevas de Velasco",
    "gn:country_code":"ES",
    "gn:dem":974,
    "gn:feature_class":"P",
    "gn:feature_code":"PPL",
    "gn:name":"Cuevas de Velasco",
    "gn:population":0,
    "gn:timezone":"Europe/Madrid",
    "iso:country":"ES",
    "wof:name":"Cuevas de Velasco",
    "wof:placetype":"locality"
},
  "geometry": {"coordinates":[-2.41794,40.14964000000001],"type":"Point"}
}