{
  "type": "Feature",
  "properties": {
    "gn:admin1_code":"31",
    "gn:admin2_code":"MU",
    "gn:admin3_code":"30024",
    "gn:asciiname":"Zuniga",
    "gn:country_code":"ES",
    "gn:dem":563,
    "gn:feature_class":"P",
    "gn:feature_code":"PPL",
    "gn:name":"Z\u00fa\u00f1iga",
    "gn:population":0,
    "gn:timezone":"Europe/Madrid",
    "iso:country":"ES",
    "name:und_x_variant":[
        "Caser\u00edo Z\u00fa\u00f1iga",
        "Z\u00fa\u00f1iga"
    ],
    "wof:name":"Zuniga",
    "wof:placetype":"locality"
},
  "geometry": {"coordinates":[-1.70456,37.79887],"type":"Point"}
}