{
  "type": "Feature",
  "properties": {
    "gn:admin1_code":"31",
    "gn:admin2_code":"MU",
    "gn:admin3_code":"30024",
    "gn:asciiname":"Zuniga",
    "gn:country_code":"ES",
    "gn:dem":563,
    "gn:feature_class":"P",
    "gn:feature_code":"PPL",
    "gn:name":"Z\u00fa\u00f1iga",
    "gn:population":0,
    "gn:timezone":"Europe/Madrid",
    "iso:country":"ES",
    "name:arg_x_preferred":[
        "Estuniga"
    ],
    "name:ast_x_preferred":[
        "Zu\u00f1iga"
    ],
    "name:bre_x_preferred":[
        "Zu\u00f1iga"
    ],
    "name:cat_x_preferred":[
        "Z\u00fa\u00f1iga"
    ],
    "name:ceb_x_preferred":[
        "Z\u00fa\u00f1iga"
    ],
    "name:eus_x_preferred":[
        "Zu\u00f1iga"
    ],
    "name:fra_x_preferred":[
        "Z\u00fa\u00f1iga"
    ],
    "name:glg_x_preferred":[
        "Z\u00fa\u00f1iga"
    ],
    "name:hun_x_preferred":[
        "Z\u00fa\u00f1iga"
    ],
    "name:ita_x_preferred":[
        "Z\u00fa\u00f1iga"
    ],
    "name:msa_x_preferred":[
        "Z\u00fa\u00f1iga"
    ],
    "name:nld_x_preferred":[
        "Z\u00fa\u00f1iga"
    ],
    "name:oci_x_preferred":[
        "Zu\u00f1iga"
    ],
    "name:pol_x_preferred":[
        "Z\u00fa\u00f1iga"
    ],
    "name:por_x_preferred":[
        "Z\u00fa\u00f1iga"
    ],
    "name:rus_x_preferred":[
        "\u0421\u0443\u043d\u044c\u0438\u0433\u0430"
    ],
    "name:spa_x_preferred":[
        "Z\u00fa\u00f1iga"
    ],
    "name:swe_x_preferred":[
        "Z\u00fa\u00f1iga"
    ],
    "name:ukr_x_preferred":[
        "\u0421\u0443\u043d\u044c\u0457\u0433\u0430"
    ],
    "name:und_x_variant":[
        "Caser\u00edo Z\u00fa\u00f1iga",
        "Z\u00fa\u00f1iga"
    ],
    "name:vie_x_preferred":[
        "Z\u00fa\u00f1iga"
    ],
    "name:war_x_preferred":[
        "Z\u00fa\u00f1iga"
    ],
    "name:zho_x_preferred":[
        "\u82cf\u5c3c\u4f0a\u52a0"
    ],
    "wof:name":"Zuniga",
    "wof:placetype":"locality"
},
  "geometry": {"coordinates":[-1.70456,37.79887],"type":"Point"}
}