{
  "type": "Feature",
  "properties": {
    "gn:admin1_code":"54",
    "gn:admin2_code":"GU",
    "gn:admin3_code":"19071",
    "gn:asciiname":"Mesones",
    "gn:country_code":"ES",
    "gn:dem":815,
    "gn:feature_class":"P",
    "gn:feature_code":"PPL",
    "gn:name":"Mesones",
    "gn:population":0,
    "gn:timezone":"Europe/Madrid",
    "iso:country":"ES",
    "wof:name":"Mesones",
    "wof:placetype":"locality"
},
  "geometry": {"coordinates":[-3.41292,40.76281],"type":"Point"}
}