{
  "type": "Feature",
  "properties": {
    "gn:admin1_code":"55",
    "gn:admin2_code":"SA",
    "gn:admin3_code":"37096",
    "gn:asciiname":"Malperal",
    "gn:country_code":"ES",
    "gn:dem":706,
    "gn:feature_class":"P",
    "gn:feature_code":"PPL",
    "gn:name":"Malperal",
    "gn:population":0,
    "gn:timezone":"Europe/Madrid",
    "iso:country":"ES",
    "name:und_x_variant":[
        "Caser\u00edo Malperal",
        "Malperal"
    ],
    "wof:name":"Malperal",
    "wof:placetype":"locality"
},
  "geometry": {"coordinates":[-6.58618,40.6924],"type":"Point"}
}