{
  "type": "Feature",
  "properties": {
    "gn:admin1_code":"53",
    "gn:admin2_code":"TF",
    "gn:admin3_code":"38038",
    "gn:asciiname":"Valle Crispin",
    "gn:country_code":"ES",
    "gn:dem":251,
    "gn:feature_class":"P",
    "gn:feature_code":"PPL",
    "gn:name":"Valle Crispin",
    "gn:population":0,
    "gn:timezone":"Atlantic/Canary",
    "iso:country":"ES",
    "wof:name":"Valle Crispin",
    "wof:placetype":"locality"
},
  "geometry": {"coordinates":[-16.23758,28.51568],"type":"Point"}
}