{
  "type": "Feature",
  "properties": {
    "gn:admin1_code":"58",
    "gn:admin2_code":"OR",
    "gn:admin3_code":"32039",
    "gn:asciiname":"Trez",
    "gn:country_code":"ES",
    "gn:dem":646,
    "gn:feature_class":"P",
    "gn:feature_code":"PPL",
    "gn:name":"Trez",
    "gn:population":0,
    "gn:timezone":"Europe/Madrid",
    "iso:country":"ES",
    "wof:name":"Trez",
    "wof:placetype":"locality"
},
  "geometry": {"coordinates":[-7.41127,42.07212],"type":"Point"}
}