{
  "type": "Feature",
  "properties": {
    "gn:admin1_code":"52",
    "gn:admin2_code":"TE",
    "gn:admin3_code":"44195",
    "gn:asciiname":"Son del Puerto",
    "gn:country_code":"ES",
    "gn:dem":1301,
    "gn:feature_class":"P",
    "gn:feature_code":"PPL",
    "gn:name":"Son del Puerto",
    "gn:population":0,
    "gn:timezone":"Europe/Madrid",
    "iso:country":"ES",
    "wof:name":"Son del Puerto",
    "wof:placetype":"locality"
},
  "geometry": {"coordinates":[-0.94401,40.75987],"type":"Point"}
}