{
  "type": "Feature",
  "properties": {
    "gn:gn_country":"ES",
    "gn:gn_fcode":"PPLA3",
    "gn:gn_pop":1065,
    "gn:population":1065,
    "iso:country":"ES",
    "name:arg_x_preferred":[
        "Castrocontrigu"
    ],
    "name:ast_x_preferred":[
        "Castrocontrigu"
    ],
    "name:cat_x_preferred":[
        "Castrocontrigo"
    ],
    "name:eng_x_preferred":[
        "Castrocontrigo"
    ],
    "name:eus_x_preferred":[
        "Castrocontrigo"
    ],
    "name:fra_x_preferred":[
        "Castrocontrigo"
    ],
    "name:glg_x_preferred":[
        "Castrocontrigo"
    ],
    "name:haw_x_preferred":[
        "Castrocontrigo"
    ],
    "name:hun_x_preferred":[
        "Castrocontrigo"
    ],
    "name:ido_x_preferred":[
        "Castrocontrigo"
    ],
    "name:ina_x_preferred":[
        "Castrocontrigo"
    ],
    "name:ita_x_preferred":[
        "Castrocontrigo"
    ],
    "name:msa_x_preferred":[
        "Castrocontrigo"
    ],
    "name:nan_x_preferred":[
        "Castrocontrigo"
    ],
    "name:nld_x_preferred":[
        "Castrocontrigo"
    ],
    "name:oci_x_preferred":[
        "Castrocontrigo"
    ],
    "name:pol_x_preferred":[
        "Castrocontrigo"
    ],
    "name:por_x_preferred":[
        "Castrocontrigo"
    ],
    "name:rup_x_preferred":[
        "Castrocontrigo"
    ],
    "name:rus_x_preferred":[
        "\u041a\u0430\u0441\u0442\u0440\u043e\u043a\u043e\u043d\u0442\u0440\u0438\u0433\u043e"
    ],
    "name:spa_x_preferred":[
        "Castrocontrigo"
    ],
    "name:swe_x_preferred":[
        "Castrocontrigo"
    ],
    "name:tpi_x_preferred":[
        "Castrocontrigo"
    ],
    "name:ukr_x_preferred":[
        "\u041a\u0430\u0441\u0442\u0440\u043e\u043a\u043e\u043d\u0442\u0440\u0456\u0433\u043e"
    ],
    "name:unk_x_variant":[
        "Castrocontigo"
    ],
    "name:vie_x_preferred":[
        "Castrocontrigo"
    ],
    "name:war_x_preferred":[
        "Castrocontrigo"
    ],
    "name:zho_x_preferred":[
        "\u5361\u65af\u7279\u7f57\u5b54\u7279\u91cc\u6208"
    ],
    "qs_pg:aaroncc":"ES",
    "qs_pg:gn_country":"ES",
    "qs_pg:gn_fcode":"PPLA3",
    "qs_pg:gn_pop":1065,
    "qs_pg:name":"Castrocontrigo",
    "qs_pg:name_adm0":"Espa\u00f1a",
    "qs_pg:name_adm1":"Castilla y Le\u00f3n",
    "qs_pg:photos_9k":1,
    "qs_pg:photos_9r":1,
    "qs_pg:photos_all":4,
    "qs_pg:photos_sr":0,
    "qs_pg:pop_sr":3,
    "qs_pg:qs_pg_placetype":"locality",
    "qs_pg:qs_pg_placetype_gp":"Town",
    "qs_pg:woe_adm0":23424950,
    "woe:adm0_id":23424950,
    "woe:name_adm0":"Espa\u00f1a",
    "woe:name_adm1":"Castilla y Le\u00f3n",
    "woe:placetype":"Town",
    "wof:name":"Castrocontrigo",
    "wof:placetype":"locality",
    "wof:population":1065
},
  "geometry": {"coordinates":[-6.19022,42.18363],"type":"Point"}
}