{
  "type": "Feature",
  "properties": {
    "gn:admin1_code":"39",
    "gn:admin2_code":"S",
    "gn:admin3_code":"39078",
    "gn:asciiname":"Pando",
    "gn:country_code":"ES",
    "gn:dem":189,
    "gn:feature_class":"P",
    "gn:feature_code":"PPL",
    "gn:name":"Pando",
    "gn:population":0,
    "gn:timezone":"Europe/Madrid",
    "iso:country":"ES",
    "wof:name":"Pando",
    "wof:placetype":"locality"
},
  "geometry": {"coordinates":[-3.9322,43.2799],"type":"Point"}
}