{
  "type": "Feature",
  "properties": {
    "gn:admin1_code":"39",
    "gn:admin2_code":"S",
    "gn:admin3_code":"39078",
    "gn:asciiname":"Pando",
    "gn:country_code":"ES",
    "gn:dem":189,
    "gn:feature_class":"P",
    "gn:feature_code":"PPL",
    "gn:name":"Pando",
    "gn:population":0,
    "gn:timezone":"Europe/Madrid",
    "iso:country":"ES",
    "name:ast_x_preferred":[
        "Pando"
    ],
    "name:cat_x_preferred":[
        "Pando"
    ],
    "name:ceb_x_preferred":[
        "Pando"
    ],
    "name:deu_x_preferred":[
        "Pando"
    ],
    "name:epo_x_preferred":[
        "Pando"
    ],
    "name:eus_x_preferred":[
        "Pando"
    ],
    "name:fra_x_preferred":[
        "Pando"
    ],
    "name:glg_x_preferred":[
        "Pando"
    ],
    "name:hrv_x_preferred":[
        "Pando"
    ],
    "name:ita_x_preferred":[
        "Pando"
    ],
    "name:kor_x_preferred":[
        "\ud310\ub3c4"
    ],
    "name:nld_x_preferred":[
        "Pando"
    ],
    "name:rus_x_preferred":[
        "\u041f\u0430\u043d\u0434\u043e"
    ],
    "name:spa_x_preferred":[
        "Pando"
    ],
    "name:swe_x_preferred":[
        "Pando"
    ],
    "name:ukr_x_preferred":[
        "\u041f\u0430\u043d\u0434\u043e"
    ],
    "wof:name":"Pando",
    "wof:placetype":"locality"
},
  "geometry": {"coordinates":[-3.9322,43.2799],"type":"Point"}
}