{
  "type": "Feature",
  "properties": {
    "gn:admin1_code":"58",
    "gn:admin2_code":"LU",
    "gn:admin3_code":"27048",
    "gn:asciiname":"Eirejua",
    "gn:country_code":"ES",
    "gn:dem":317,
    "gn:feature_class":"P",
    "gn:feature_code":"PPL",
    "gn:name":"Eirej\u00faa",
    "gn:population":0,
    "gn:timezone":"Europe/Madrid",
    "iso:country":"ES",
    "wof:name":"Eirejua",
    "wof:placetype":"locality"
},
  "geometry": {"coordinates":[-7.22943,43.29536],"type":"Point"}
}