{
  "type": "Feature",
  "properties": {
    "gn:admin1_code":"31",
    "gn:admin2_code":"MU",
    "gn:admin3_code":"30024",
    "gn:asciiname":"Las Canales",
    "gn:country_code":"ES",
    "gn:dem":397,
    "gn:feature_class":"P",
    "gn:feature_code":"PPL",
    "gn:name":"Las Canales",
    "gn:population":0,
    "gn:timezone":"Europe/Madrid",
    "iso:country":"ES",
    "name:und_x_variant":[
        "Caser\u00edo Las Canales",
        "Las Canales"
    ],
    "wof:name":"Las Canales",
    "wof:placetype":"locality"
},
  "geometry": {"coordinates":[-1.76934,37.70825],"type":"Point"}
}