{
  "type": "Feature",
  "properties": {
    "gn:admin1_code":"55",
    "gn:admin2_code":"BU",
    "gn:admin3_code":"09166",
    "gn:asciiname":"Espinosilla de San Bartolome",
    "gn:country_code":"ES",
    "gn:dem":958,
    "gn:feature_class":"P",
    "gn:feature_code":"PPL",
    "gn:name":"Espinosilla de San Bartolom\u00e9",
    "gn:population":0,
    "gn:timezone":"Europe/Madrid",
    "iso:country":"ES",
    "name:und_x_variant":[
        "Espinosilla de San Bartolom\u00e9"
    ],
    "wof:name":"Espinosilla de San Bartolome",
    "wof:placetype":"locality"
},
  "geometry": {"coordinates":[-3.87044,42.53298],"type":"Point"}
}