{
  "type": "Feature",
  "properties": {
    "gn:admin1_code":"58",
    "gn:admin2_code":"C",
    "gn:admin3_code":"15071",
    "gn:asciiname":"Noal",
    "gn:country_code":"ES",
    "gn:dem":49,
    "gn:feature_class":"P",
    "gn:feature_code":"PPL",
    "gn:name":"Noal",
    "gn:population":0,
    "gn:timezone":"Europe/Madrid",
    "iso:country":"ES",
    "name:cat_x_preferred":[
        "Noal"
    ],
    "name:fra_x_preferred":[
        "Noal"
    ],
    "name:glg_x_preferred":[
        "Noal"
    ],
    "name:por_x_preferred":[
        "Noal"
    ],
    "name:spa_x_preferred":[
        "Noal"
    ],
    "wof:name":"Noal",
    "wof:placetype":"locality"
},
  "geometry": {"coordinates":[-8.9851,42.73103],"type":"Point"}
}