{
  "type": "Feature",
  "properties": {
    "gn:country":"ES",
    "gn:fcode":"PPL",
    "gn:population":0,
    "iso:country":"ES",
    "name:ara_x_preferred":[
        "\u062f\u064a\u0641\u0627"
    ],
    "name:arg_x_preferred":[
        "Deva"
    ],
    "name:ast_x_preferred":[
        "Deva"
    ],
    "name:azb_x_preferred":[
        "\u062f\u0648\u0627 \u060c"
    ],
    "name:bul_x_preferred":[
        "\u0414\u0435\u0432\u0430"
    ],
    "name:ceb_x_preferred":[
        "Deva"
    ],
    "name:cym_x_preferred":[
        "Deva"
    ],
    "name:dan_x_preferred":[
        "Deva"
    ],
    "name:deu_x_preferred":[
        "Deva"
    ],
    "name:eus_x_preferred":[
        "Deva"
    ],
    "name:fas_x_preferred":[
        "\u062f\u0648\u0627"
    ],
    "name:fra_x_preferred":[
        "Deva"
    ],
    "name:glg_x_preferred":[
        "Deva"
    ],
    "name:hrv_x_preferred":[
        "Deva"
    ],
    "name:hun_x_preferred":[
        "D\u00e9va"
    ],
    "name:ita_x_preferred":[
        "Deva"
    ],
    "name:lat_x_preferred":[
        "Deva"
    ],
    "name:lim_x_preferred":[
        "Deva"
    ],
    "name:lit_x_preferred":[
        "Deva"
    ],
    "name:min_x_preferred":[
        "Deva"
    ],
    "name:nep_x_preferred":[
        "\u0926\u0947\u0935"
    ],
    "name:new_x_preferred":[
        "\u0926\u094d\u092f"
    ],
    "name:nld_x_preferred":[
        "Deva"
    ],
    "name:nno_x_preferred":[
        "Deva"
    ],
    "name:pol_x_preferred":[
        "Deva"
    ],
    "name:por_x_preferred":[
        "Deva"
    ],
    "name:ron_x_preferred":[
        "Deva"
    ],
    "name:rus_x_preferred":[
        "\u0414\u0435\u0432\u0430"
    ],
    "name:spa_x_preferred":[
        "Deva"
    ],
    "name:sqi_x_preferred":[
        "Deva"
    ],
    "name:srp_x_preferred":[
        "\u0414\u0435\u0432\u0430"
    ],
    "name:swe_x_preferred":[
        "Deva"
    ],
    "name:tam_x_preferred":[
        "\u0ba4\u0bc7\u0bb5\u0bb0\u0bcd"
    ],
    "name:ukr_x_preferred":[
        "\u0414\u0456\u0432\u0430"
    ],
    "name:urd_x_preferred":[
        "\u062f\u06cc\u0648"
    ],
    "name:vie_x_preferred":[
        "Deva"
    ],
    "qs_pg:aaroncc":"ES",
    "qs_pg:gn_country":"ES",
    "qs_pg:gn_fcode":"PPL",
    "qs_pg:gn_pop":0,
    "qs_pg:name":"Deva",
    "qs_pg:name_adm0":"Espa\u00f1a",
    "qs_pg:name_adm1":"Galicia",
    "qs_pg:photos":28,
    "qs_pg:photos_1k":6,
    "qs_pg:photos_9k":1,
    "qs_pg:photos_9r":2,
    "qs_pg:photos_all":28,
    "qs_pg:photos_sr":2,
    "qs_pg:pop_sr":0,
    "qs_pg:qs_pg_placetype":"locality",
    "qs_pg:qs_pg_placetype_gp":"Town",
    "qs_pg:woe_adm0":23424950,
    "woe:adm0_id":23424950,
    "woe:name_adm0":"Espa\u00f1a",
    "woe:name_adm1":"Galicia",
    "woe:placetype":"Town",
    "wof:name":"Deva",
    "wof:placetype":"locality"
},
  "geometry": {"coordinates":[-6.91306,42.79685],"type":"Point"}
}