{
  "type": "Feature",
  "properties": {
    "gn:admin1_code":"55",
    "gn:admin2_code":"SA",
    "gn:admin3_code":"37188",
    "gn:asciiname":"La Maya",
    "gn:country_code":"ES",
    "gn:dem":835,
    "gn:feature_class":"P",
    "gn:feature_code":"PPL",
    "gn:name":"La Maya",
    "gn:population":256,
    "gn:timezone":"Europe/Madrid",
    "iso:country":"ES",
    "wof:name":"La Maya",
    "wof:placetype":"locality",
    "wof:population":256
},
  "geometry": {"coordinates":[-5.61307,40.68711],"type":"Point"}
}