{
  "type": "Feature",
  "properties": {
    "gn:admin1_code":"55",
    "gn:admin2_code":"SA",
    "gn:admin3_code":"37188",
    "gn:asciiname":"La Maya",
    "gn:country_code":"ES",
    "gn:dem":835,
    "gn:feature_class":"P",
    "gn:feature_code":"PPL",
    "gn:name":"La Maya",
    "gn:population":256,
    "gn:timezone":"Europe/Madrid",
    "iso:country":"ES",
    "name:arg_x_preferred":[
        "La Maya"
    ],
    "name:ast_x_preferred":[
        "La Maya"
    ],
    "name:cat_x_preferred":[
        "La Maya"
    ],
    "name:ceb_x_preferred":[
        "La Maya"
    ],
    "name:eus_x_preferred":[
        "La Maya"
    ],
    "name:fra_x_preferred":[
        "La Maya"
    ],
    "name:haw_x_preferred":[
        "La Maya"
    ],
    "name:hun_x_preferred":[
        "La Maya"
    ],
    "name:ina_x_preferred":[
        "La Maya"
    ],
    "name:ita_x_preferred":[
        "La Maya"
    ],
    "name:kaz_x_preferred":[
        "\u041b\u0430-\u041c\u0430\u0439\u044f"
    ],
    "name:msa_x_preferred":[
        "La Maya"
    ],
    "name:nld_x_preferred":[
        "La Maya"
    ],
    "name:oci_x_preferred":[
        "La Maya"
    ],
    "name:pol_x_preferred":[
        "La Maya"
    ],
    "name:por_x_preferred":[
        "La Maya"
    ],
    "name:rus_x_preferred":[
        "\u041b\u0430-\u041c\u0430\u0439\u044f"
    ],
    "name:spa_x_preferred":[
        "La Maya"
    ],
    "name:swe_x_preferred":[
        "La Maya"
    ],
    "name:ukr_x_preferred":[
        "\u041b\u0430-\u041c\u0430\u044f"
    ],
    "name:vie_x_preferred":[
        "La Maya"
    ],
    "name:war_x_preferred":[
        "La Maya"
    ],
    "name:zho_x_preferred":[
        "\u62c9\u8fc8\u963f"
    ],
    "wof:name":"La Maya",
    "wof:placetype":"locality",
    "wof:population":256
},
  "geometry": {"coordinates":[-5.61307,40.68711],"type":"Point"}
}