{
  "type": "Feature",
  "properties": {
    "gn:gn_country":"ES",
    "gn:gn_fcode":"PPL",
    "gn:gn_pop":0,
    "iso:country":"ES",
    "name:dut_x_preferred":[
        "Caleta de Sebo"
    ],
    "name:eng_x_preferred":[
        "Caleta de Sebo"
    ],
    "name:fre_x_preferred":[
        "Caleta de Sebo"
    ],
    "name:ger_x_preferred":[
        "Caleta del Sebo"
    ],
    "name:glg_x_preferred":[
        "Caleta de Sebo"
    ],
    "name:jpn_x_preferred":[
        "\u30ab\u30ec\u30fc\u30bf\u30fb\u30c7\u30fb\u30bb\u30dc"
    ],
    "name:spa_x_preferred":[
        "Caleta de Sebo"
    ],
    "name:swe_x_preferred":[
        "Caleta de Sebo"
    ],
    "qs_pg:aaroncc":"ES",
    "qs_pg:gn_country":"ES",
    "qs_pg:gn_fcode":"PPL",
    "qs_pg:gn_pop":0,
    "qs_pg:name":"Caleta de Sebo",
    "qs_pg:name_adm0":"Espa\u00f1a",
    "qs_pg:name_adm1":"Islas Canarias",
    "qs_pg:photos":1781,
    "qs_pg:photos_1k":361,
    "qs_pg:photos_9k":8,
    "qs_pg:photos_9r":8,
    "qs_pg:photos_all":1781,
    "qs_pg:photos_sr":14,
    "qs_pg:pop_sr":0,
    "qs_pg:qs_pg_placetype":"locality",
    "qs_pg:qs_pg_placetype_gp":"Town",
    "qs_pg:woe_adm0":23424950,
    "woe:adm0_id":23424950,
    "woe:name_adm0":"Espa\u00f1a",
    "woe:name_adm1":"Islas Canarias",
    "woe:placetype":"Town",
    "wof:name":"Caleta de Sebo",
    "wof:placetype":"locality"
},
  "geometry": {"coordinates":[-13.50379,29.23008],"type":"Point"}
}