{
  "type": "Feature",
  "properties": {
    "gn:country":"ES",
    "gn:fcode":"PPLA3",
    "gn:population":510,
    "iso:country":"ES",
    "name:cat_x_preferred":[
        "Santa Colomba de Somoza"
    ],
    "name:deu_x_preferred":[
        "Santa Colomba de Somoza"
    ],
    "name:eng_x_preferred":[
        "Santa Colomba de Somoza"
    ],
    "name:eus_x_preferred":[
        "Santa Colomba de Somoza"
    ],
    "name:fra_x_preferred":[
        "Santa Colomba de Somoza"
    ],
    "name:glg_x_preferred":[
        "Santa Colomba de Somoza"
    ],
    "name:haw_x_preferred":[
        "Santa Colomba de Somoza"
    ],
    "name:hun_x_preferred":[
        "Santa Colomba de Somoza"
    ],
    "name:hye_x_preferred":[
        "\u054d\u0561\u0576\u057f\u0561 \u053f\u0578\u056c\u0578\u0574\u0562\u0561 \u0564\u0565 \u054d\u0578\u0574\u0578\u057d\u0561"
    ],
    "name:ido_x_preferred":[
        "Santa Colomba de Somoza"
    ],
    "name:ina_x_preferred":[
        "Santa Colomba de Somoza"
    ],
    "name:ita_x_preferred":[
        "Santa Colomba de Somoza"
    ],
    "name:msa_x_preferred":[
        "Santa Colomba de Somoza"
    ],
    "name:nan_x_preferred":[
        "Santa Colomba de Somoza"
    ],
    "name:nld_x_preferred":[
        "Santa Colomba de Somoza"
    ],
    "name:oci_x_preferred":[
        "Santa Colomba de Somoza"
    ],
    "name:pol_x_preferred":[
        "Santa Colomba de Somoza"
    ],
    "name:por_x_preferred":[
        "Santa Colomba de Somoza"
    ],
    "name:rus_x_preferred":[
        "\u0421\u0430\u043d\u0442\u0430-\u041a\u043e\u043b\u043e\u043c\u0431\u0430-\u0434\u0435-\u0421\u043e\u043c\u043e\u0441\u0430"
    ],
    "name:spa_x_preferred":[
        "Santa Colomba de Somoza"
    ],
    "name:swe_x_preferred":[
        "Santa Colomba de Somoza"
    ],
    "name:tpi_x_preferred":[
        "Santa Colomba de Somoza"
    ],
    "name:ukr_x_preferred":[
        "\u0421\u0430\u043d\u0442\u0430-\u041a\u043e\u043b\u043e\u043c\u0431\u0430-\u0434\u0435-\u0421\u043e\u043c\u043e\u0441\u0430"
    ],
    "name:vie_x_preferred":[
        "Santa Colomba de Somoza"
    ],
    "name:war_x_preferred":[
        "Santa Colomba de Somoza"
    ],
    "name:zho_x_preferred":[
        "\u5723\u79d1\u9686\u74e6\u5fb7\u7d22\u83ab\u8428"
    ],
    "qs_pg:aaroncc":"ES",
    "qs_pg:gn_country":"ES",
    "qs_pg:gn_fcode":"PPLA3",
    "qs_pg:gn_pop":510,
    "qs_pg:name":"Santa Colomba de Somoza",
    "qs_pg:name_adm0":"Espa\u00f1a",
    "qs_pg:name_adm1":"Castilla y Le\u00f3n",
    "qs_pg:photos_9r":0,
    "qs_pg:photos_sr":0,
    "qs_pg:pop_sr":2,
    "qs_pg:qs_pg_placetype":"locality",
    "qs_pg:qs_pg_placetype_gp":"Town",
    "qs_pg:woe_adm0":23424950,
    "woe:adm0_id":23424950,
    "woe:name_adm0":"Espa\u00f1a",
    "woe:name_adm1":"Castilla y Le\u00f3n",
    "woe:placetype":"Town",
    "wof:name":"Santa Colomba de Somoza",
    "wof:placetype":"locality",
    "wof:population":510
},
  "geometry": {"coordinates":[-6.24483,42.44466],"type":"Point"}
}