{
  "type": "Feature",
  "properties": {
    "gn:admin1_code":"34",
    "gn:admin2_code":"O",
    "gn:admin3_code":"33059",
    "gn:asciiname":"Faedo",
    "gn:country_code":"ES",
    "gn:dem":509,
    "gn:feature_class":"P",
    "gn:feature_code":"PPL",
    "gn:name":"Faedo",
    "gn:population":0,
    "gn:timezone":"Europe/Madrid",
    "iso:country":"ES",
    "wof:name":"Faedo",
    "wof:placetype":"locality"
},
  "geometry": {"coordinates":[-6.33238,43.47435],"type":"Point"}
}