{
  "type": "Feature",
  "properties": {
    "gn:admin1_code":"58",
    "gn:admin2_code":"LU",
    "gn:admin3_code":"27020",
    "gn:asciiname":"Seren",
    "gn:country_code":"ES",
    "gn:dem":544,
    "gn:feature_class":"P",
    "gn:feature_code":"PPL",
    "gn:name":"Ser\u00e9n",
    "gn:population":0,
    "gn:timezone":"Europe/Madrid",
    "iso:country":"ES",
    "name:und_x_variant":[
        "Ser\u00e9n"
    ],
    "wof:name":"Seren",
    "wof:placetype":"locality"
},
  "geometry": {"coordinates":[-7.73238,43.01164],"type":"Point"}
}