{
  "type": "Feature",
  "properties": {
    "gn:admin1_code":"60",
    "gn:admin2_code":"V",
    "gn:admin3_code":"46001",
    "gn:asciiname":"Torre Alta",
    "gn:country_code":"ES",
    "gn:dem":815,
    "gn:feature_class":"P",
    "gn:feature_code":"PPL",
    "gn:name":"Torre Alta",
    "gn:population":0,
    "gn:timezone":"Europe/Madrid",
    "iso:country":"ES",
    "name:spa_x_preferred":[
        "Torre Alta"
    ],
    "wof:name":"Torre Alta",
    "wof:placetype":"locality"
},
  "geometry": {"coordinates":[-1.25,40.11667],"type":"Point"}
}