{
  "type": "Feature",
  "properties": {
    "gn:admin1_code":"34",
    "gn:admin2_code":"O",
    "gn:admin3_code":"33036",
    "gn:asciiname":"Allende",
    "gn:country_code":"ES",
    "gn:dem":187,
    "gn:feature_class":"P",
    "gn:feature_code":"PPL",
    "gn:name":"Allende",
    "gn:population":0,
    "gn:timezone":"Europe/Madrid",
    "iso:country":"ES",
    "wof:name":"Allende",
    "wof:placetype":"locality"
},
  "geometry": {"coordinates":[-4.90777,43.40767],"type":"Point"}
}