{
  "type": "Feature",
  "properties": {
    "gn:gn_country":"ES",
    "gn:gn_fcode":"PPLA3",
    "gn:gn_pop":509,
    "gn:population":509,
    "iso:country":"ES",
    "name:arg_x_preferred":[
        "Gomecello"
    ],
    "name:baq_x_preferred":[
        "Gomecello"
    ],
    "name:cat_x_preferred":[
        "Gomecello"
    ],
    "name:chi_x_preferred":[
        "\u6208\u6885\u585e\u7565"
    ],
    "name:dut_x_preferred":[
        "Gomecello"
    ],
    "name:eng_x_preferred":[
        "Gomecello"
    ],
    "name:fre_x_preferred":[
        "Gomecello"
    ],
    "name:haw_x_preferred":[
        "Gomecello"
    ],
    "name:hun_x_preferred":[
        "Gomecello"
    ],
    "name:ina_x_preferred":[
        "Gomecello"
    ],
    "name:ita_x_preferred":[
        "Gomecello"
    ],
    "name:kaz_x_preferred":[
        "\u0413\u043e\u043c\u0435\u0441\u0435\u043b\u044c\u043e"
    ],
    "name:may_x_preferred":[
        "Gomecello"
    ],
    "name:nan_x_preferred":[
        "Gomecello"
    ],
    "name:oci_x_preferred":[
        "Gomecello"
    ],
    "name:pol_x_preferred":[
        "Gomecello"
    ],
    "name:por_x_preferred":[
        "Gomecello"
    ],
    "name:rus_x_preferred":[
        "\u0413\u043e\u043c\u0435\u0441\u0435\u043b\u044c\u043e"
    ],
    "name:spa_x_preferred":[
        "Gomecello"
    ],
    "name:swe_x_preferred":[
        "Gomecello"
    ],
    "name:ukr_x_preferred":[
        "\u0413\u043e\u043c\u0435\u0441\u0435\u043b\u044c\u0439\u043e"
    ],
    "name:uzb_x_preferred":[
        "Gomecello"
    ],
    "name:vie_x_preferred":[
        "Gomecello"
    ],
    "name:war_x_preferred":[
        "Gomecello"
    ],
    "qs_pg:aaroncc":"ES",
    "qs_pg:gn_country":"ES",
    "qs_pg:gn_fcode":"PPLA3",
    "qs_pg:gn_pop":509,
    "qs_pg:name":"Gomecello",
    "qs_pg:name_adm0":"Espa\u00f1a",
    "qs_pg:name_adm1":"Castilla y Le\u00f3n",
    "qs_pg:photos":21,
    "qs_pg:photos_1k":4,
    "qs_pg:photos_9k":1,
    "qs_pg:photos_9r":1,
    "qs_pg:photos_all":21,
    "qs_pg:photos_sr":1,
    "qs_pg:pop_sr":2,
    "qs_pg:qs_pg_placetype":"locality",
    "qs_pg:qs_pg_placetype_gp":"Town",
    "qs_pg:woe_adm0":23424950,
    "woe:adm0_id":23424950,
    "woe:name_adm0":"Espa\u00f1a",
    "woe:name_adm1":"Castilla y Le\u00f3n",
    "woe:placetype":"Town",
    "wof:name":"Gomecello",
    "wof:placetype":"locality",
    "wof:population":509
},
  "geometry": {"coordinates":[-5.53585,41.0428],"type":"Point"}
}