{
  "type": "Feature",
  "properties": {
    "gn:admin1_code":"32",
    "gn:admin3_code":"31144",
    "gn:asciiname":"Oderiz",
    "gn:country_code":"ES",
    "gn:dem":766,
    "gn:feature_class":"P",
    "gn:feature_code":"PPL",
    "gn:name":"Od\u00e9riz",
    "gn:population":0,
    "gn:timezone":"Europe/Madrid",
    "iso:country":"ES",
    "wof:name":"Oderiz",
    "wof:placetype":"locality"
},
  "geometry": {"coordinates":[-1.87162,42.95077],"type":"Point"}
}