{
  "type": "Feature",
  "properties": {
    "gn:admin1_code":"55",
    "gn:admin2_code":"BU",
    "gn:admin3_code":"09306",
    "gn:asciiname":"Valtierra de Albacastro",
    "gn:country_code":"ES",
    "gn:dem":1012,
    "gn:feature_class":"P",
    "gn:feature_code":"PPL",
    "gn:name":"Valtierra de Albacastro",
    "gn:population":0,
    "gn:timezone":"Europe/Madrid",
    "iso:country":"ES",
    "wof:name":"Valtierra de Albacastro",
    "wof:placetype":"locality"
},
  "geometry": {"coordinates":[-4.16515,42.68086],"type":"Point"}
}