{
  "type": "Feature",
  "properties": {
    "gn:admin1_code":"51",
    "gn:admin2_code":"AL",
    "gn:admin3_code":"04082",
    "gn:asciiname":"Zarzales",
    "gn:country_code":"ES",
    "gn:dem":785,
    "gn:feature_class":"P",
    "gn:feature_code":"PPL",
    "gn:name":"Zarzales",
    "gn:population":0,
    "gn:timezone":"Europe/Madrid",
    "iso:country":"ES",
    "name:und_x_variant":[
        "Caser\u00edo Zarzales",
        "Zarzales"
    ],
    "wof:name":"Zarzales",
    "wof:placetype":"locality"
},
  "geometry": {"coordinates":[-2.33,37.18281],"type":"Point"}
}