{
  "type": "Feature",
  "properties": {
    "gn:gn_country":"ES",
    "gn:gn_fcode":"PPL",
    "gn:gn_pop":0,
    "iso:country":"ES",
    "name:arg_x_preferred":[
        "Peralta de la Sal"
    ],
    "name:arm_x_preferred":[
        "\u054a\u0565\u0580\u0561\u056c\u057f\u0561 \u0564\u0565 \u056c\u0561 \u054d\u0561\u056c"
    ],
    "name:cat_x_preferred":[
        "Peralta de la Sal"
    ],
    "name:eng_x_preferred":[
        "Peralta de la Sal"
    ],
    "name:fre_x_preferred":[
        "Peralta de la Sal"
    ],
    "name:ger_x_preferred":[
        "Peralta de la Sal"
    ],
    "name:ita_x_preferred":[
        "Peralta de la Sal"
    ],
    "name:rus_x_preferred":[
        "\u041f\u0435\u0440\u0430\u043b\u044c\u0442\u0430-\u0434\u0435-\u043b\u0430-\u0421\u0430\u043b"
    ],
    "name:spa_x_preferred":[
        "Peralta de la Sal"
    ],
    "qs_pg:aaroncc":"ES",
    "qs_pg:gn_country":"ES",
    "qs_pg:gn_fcode":"PPL",
    "qs_pg:gn_pop":0,
    "qs_pg:name":"Peralta de la Sal",
    "qs_pg:name_adm0":"Espa\u00f1a",
    "qs_pg:name_adm1":"Arag\u00f3n",
    "qs_pg:photos_9k":1,
    "qs_pg:photos_9r":1,
    "qs_pg:photos_all":1,
    "qs_pg:photos_sr":0,
    "qs_pg:pop_sr":0,
    "qs_pg:qs_pg_placetype":"locality",
    "qs_pg:qs_pg_placetype_gp":"Town",
    "qs_pg:woe_adm0":23424950,
    "woe:adm0_id":23424950,
    "woe:name_adm0":"Espa\u00f1a",
    "woe:name_adm1":"Arag\u00f3n",
    "woe:placetype":"Town",
    "wof:name":"Peralta de la Sal",
    "wof:placetype":"locality"
},
  "geometry": {"coordinates":[0.3862,41.99242],"type":"Point"}
}