{
  "type": "Feature",
  "properties": {
    "gn:admin1_code":"31",
    "gn:admin2_code":"MU",
    "gn:admin3_code":"30026",
    "gn:asciiname":"El Margajon",
    "gn:country_code":"ES",
    "gn:dem":309,
    "gn:feature_class":"P",
    "gn:feature_code":"PPL",
    "gn:name":"El Margaj\u00f3n",
    "gn:population":0,
    "gn:timezone":"Europe/Madrid",
    "iso:country":"ES",
    "name:und_x_variant":[
        "Caser\u00edo El Margajon",
        "El Margaj\u00f3n"
    ],
    "wof:name":"El Margajon",
    "wof:placetype":"locality"
},
  "geometry": {"coordinates":[-1.24667,37.6487],"type":"Point"}
}