{
  "type": "Feature",
  "properties": {
    "gn:admin1_code":"55",
    "gn:admin2_code":"BU",
    "gn:admin3_code":"09413",
    "gn:asciiname":"Cubillos del Rojo",
    "gn:country_code":"ES",
    "gn:dem":956,
    "gn:feature_class":"P",
    "gn:feature_code":"PPL",
    "gn:name":"Cubillos del Rojo",
    "gn:population":0,
    "gn:timezone":"Europe/Madrid",
    "iso:country":"ES",
    "wof:name":"Cubillos del Rojo",
    "wof:placetype":"locality"
},
  "geometry": {"coordinates":[-3.72324,42.93243],"type":"Point"}
}