{
  "type": "Feature",
  "properties": {
    "gn:admin1_code":"34",
    "gn:admin2_code":"O",
    "gn:admin3_code":"33075",
    "gn:asciiname":"Busdemouros",
    "gn:country_code":"ES",
    "gn:dem":632,
    "gn:feature_class":"P",
    "gn:feature_code":"PPL",
    "gn:name":"Busdemouros",
    "gn:population":0,
    "gn:timezone":"Europe/Madrid",
    "iso:country":"ES",
    "wof:name":"Busdemouros",
    "wof:placetype":"locality"
},
  "geometry": {"coordinates":[-7.01183,43.35856],"type":"Point"}
}