{
  "type": "Feature",
  "properties": {
    "gn:gn_country":"ES",
    "gn:gn_fcode":"PPLA3",
    "gn:gn_pop":243,
    "gn:population":243,
    "iso:country":"ES",
    "name:cat_x_preferred":[
        "Quintana del Puente"
    ],
    "name:eng_x_preferred":[
        "Quintana del Puente"
    ],
    "name:eus_x_preferred":[
        "Quintana del Puente"
    ],
    "name:fas_x_preferred":[
        "\u06a9\u06cc\u0646\u062a\u0627\u0646\u0627 \u062f\u0644 \u067e\u0648\u0626\u0646\u062a\u0647"
    ],
    "name:fra_x_preferred":[
        "Quintana del Puente"
    ],
    "name:glg_x_preferred":[
        "Quintana del Puente"
    ],
    "name:hun_x_preferred":[
        "Quintana del Puente"
    ],
    "name:hye_x_preferred":[
        "\u053f\u056b\u0576\u057f\u0561\u0576\u0561 \u0564\u0565\u056c \u054a\u0578\u0582\u0565\u0576\u057f\u0565"
    ],
    "name:ina_x_preferred":[
        "Quintana del Puente"
    ],
    "name:ita_x_preferred":[
        "Quintana del Puente"
    ],
    "name:msa_x_preferred":[
        "Quintana del Puente"
    ],
    "name:nan_x_preferred":[
        "Quintana del Puente"
    ],
    "name:nld_x_preferred":[
        "Quintana del Puente"
    ],
    "name:oci_x_preferred":[
        "Quintana del Puente"
    ],
    "name:pol_x_preferred":[
        "Quintana del Puente"
    ],
    "name:por_x_preferred":[
        "Quintana del Puente"
    ],
    "name:rus_x_preferred":[
        "\u041a\u0438\u043d\u0442\u0430\u043d\u0430-\u0434\u0435\u043b\u044c-\u041f\u0443\u044d\u043d\u0442\u0435"
    ],
    "name:spa_x_preferred":[
        "Quintana del Puente"
    ],
    "name:swe_x_preferred":[
        "Quintana del Puente"
    ],
    "name:ukr_x_preferred":[
        "\u041a\u0456\u043d\u0442\u0430\u043d\u0430-\u0434\u0435\u043b\u044c-\u041f\u0443\u0435\u043d\u0442\u0435"
    ],
    "name:uzb_x_preferred":[
        "Quintana del Puente"
    ],
    "name:vie_x_preferred":[
        "Quintana del Puente"
    ],
    "name:war_x_preferred":[
        "Quintana del Puente"
    ],
    "name:zho_x_preferred":[
        "\u91d1\u5854\u7eb3\u5fb7\u5c14\u84ec\u7279"
    ],
    "qs_pg:aaroncc":"ES",
    "qs_pg:gn_country":"ES",
    "qs_pg:gn_fcode":"PPLA3",
    "qs_pg:gn_pop":243,
    "qs_pg:name":"Quintana del Puente",
    "qs_pg:name_adm0":"Espa\u00f1a",
    "qs_pg:name_adm1":"Castilla y Le\u00f3n",
    "qs_pg:photos":16,
    "qs_pg:photos_1k":3,
    "qs_pg:photos_9k":1,
    "qs_pg:photos_9r":1,
    "qs_pg:photos_all":16,
    "qs_pg:photos_sr":1,
    "qs_pg:pop_sr":2,
    "qs_pg:qs_pg_placetype":"locality",
    "qs_pg:qs_pg_placetype_gp":"Town",
    "qs_pg:woe_adm0":23424950,
    "woe:adm0_id":23424950,
    "woe:name_adm0":"Espa\u00f1a",
    "woe:name_adm1":"Castilla y Le\u00f3n",
    "woe:placetype":"Town",
    "wof:name":"Quintana del Puente",
    "wof:placetype":"locality",
    "wof:population":243
},
  "geometry": {"coordinates":[-4.20649,42.08471],"type":"Point"}
}