{
  "type": "Feature",
  "properties": {
    "gn:admin1_code":"55",
    "gn:admin2_code":"LE",
    "gn:admin3_code":"24125",
    "gn:asciiname":"Tabuyuelo de Jamuz",
    "gn:country_code":"ES",
    "gn:dem":802,
    "gn:feature_class":"P",
    "gn:feature_code":"PPL",
    "gn:name":"Tabuyuelo de Jamuz",
    "gn:population":0,
    "gn:timezone":"Europe/Madrid",
    "iso:country":"ES",
    "wof:name":"Tabuyuelo de Jamuz",
    "wof:placetype":"locality"
},
  "geometry": {"coordinates":[-5.99739,42.276],"type":"Point"}
}