{
  "type": "Feature",
  "properties": {
    "gn:admin1_code":"58",
    "gn:admin2_code":"LU",
    "gn:admin3_code":"27010",
    "gn:asciiname":"Ansemar",
    "gn:cc2":"ES",
    "gn:country_code":"ES",
    "gn:dem":448,
    "gn:feature_class":"P",
    "gn:feature_code":"PPL",
    "gn:name":"Ansemar",
    "gn:population":0,
    "gn:timezone":"Europe/Madrid",
    "iso:country":"ES",
    "name:und_x_variant":[
        "El Salvador",
        "Ansemar"
    ],
    "wof:name":"Ansemar",
    "wof:placetype":"locality"
},
  "geometry": {"coordinates":[-7.41667,43.16667],"type":"Point"}
}