{
  "type": "Feature",
  "properties": {
    "gn:admin1_code":"34",
    "gn:admin2_code":"O",
    "gn:admin3_code":"33034",
    "gn:asciiname":"Longrey",
    "gn:country_code":"ES",
    "gn:dem":162,
    "gn:feature_class":"P",
    "gn:feature_code":"PPL",
    "gn:name":"Longrey",
    "gn:population":0,
    "gn:timezone":"Europe/Madrid",
    "iso:country":"ES",
    "wof:name":"Longrey",
    "wof:placetype":"locality"
},
  "geometry": {"coordinates":[-6.50135,43.45193],"type":"Point"}
}