{
  "type": "Feature",
  "properties": {
    "gn:admin1_code":"55",
    "gn:admin2_code":"ZA",
    "gn:admin3_code":"49104",
    "gn:asciiname":"Las Torres de Aliste",
    "gn:country_code":"ES",
    "gn:dem":792,
    "gn:feature_class":"P",
    "gn:feature_code":"PPL",
    "gn:name":"Las Torres de Aliste",
    "gn:population":0,
    "gn:timezone":"Europe/Madrid",
    "iso:country":"ES",
    "name:und_x_variant":[
        "Las Torres",
        "Las Torres de Aliste"
    ],
    "wof:name":"Las Torres de Aliste",
    "wof:placetype":"locality"
},
  "geometry": {"coordinates":[-6.30971,41.83929000000001],"type":"Point"}
}