{
  "type": "Feature",
  "properties": {
    "gn:admin1_code":"54",
    "gn:admin2_code":"GU",
    "gn:admin3_code":"19046",
    "gn:asciiname":"La Acequilla",
    "gn:country_code":"ES",
    "gn:dem":607,
    "gn:feature_class":"P",
    "gn:feature_code":"PPL",
    "gn:name":"La Acequilla",
    "gn:population":0,
    "gn:timezone":"Europe/Madrid",
    "iso:country":"ES",
    "name:und_x_variant":[
        "Caser\u00edo La Acequilla",
        "Casa de La Acequilla",
        "La Acequilla"
    ],
    "wof:name":"La Acequilla",
    "wof:placetype":"locality"
},
  "geometry": {"coordinates":[-3.2508,40.55255],"type":"Point"}
}