{
  "type": "Feature",
  "properties": {
    "gn:admin1_code":"60",
    "gn:admin2_code":"V",
    "gn:admin3_code":"46099",
    "gn:asciiname":"Cortes de Pallas",
    "gn:country_code":"ES",
    "gn:dem":356,
    "gn:feature_class":"P",
    "gn:feature_code":"PPLA3",
    "gn:name":"Cortes de Pall\u00e1s",
    "gn:population":999,
    "gn:timezone":"Europe/Madrid",
    "iso:country":"ES",
    "name:cat_x_preferred":[
        "Cortes de Pall\u00e1s"
    ],
    "name:rus_x_preferred":[
        "\u041a\u043e\u0440\u0442\u0435\u0441-\u0434\u0435-\u041f\u0430\u043b\u044c\u044f\u0441"
    ],
    "name:spa_x_preferred":[
        "Cortes de Pall\u00e1s"
    ],
    "name:ukr_x_preferred":[
        "\u041a\u043e\u0440\u0442\u0435\u0441-\u0434\u0435-\u041f\u0430\u043b\u044c\u044f\u0441"
    ],
    "name:und_x_variant":[
        "Cortez de Pallas",
        "Cortes de Pall\u00e1s"
    ],
    "name:zho_x_preferred":[
        "\u79d1\u5c14\u7279\u65af\u5fb7\u5e15\u5229\u4e9a\u65af"
    ],
    "wof:name":"Cortes de Pallas",
    "wof:placetype":"locality",
    "wof:population":999
},
  "geometry": {"coordinates":[-0.93333,39.25],"type":"Point"}
}