{
  "type": "Feature",
  "properties": {
    "gn:admin1_code":"60",
    "gn:admin2_code":"V",
    "gn:admin3_code":"46099",
    "gn:asciiname":"Cortes de Pallas",
    "gn:country_code":"ES",
    "gn:dem":356,
    "gn:feature_class":"P",
    "gn:feature_code":"PPLA3",
    "gn:name":"Cortes de Pall\u00e1s",
    "gn:population":999,
    "gn:timezone":"Europe/Madrid",
    "iso:country":"ES",
    "name:cat_x_preferred":[
        "Cortes de Pall\u00e1s"
    ],
    "name:spa_x_preferred":[
        "Cortes de Pall\u00e1s"
    ],
    "name:und_x_variant":[
        "Cortez de Pallas",
        "Cortes de Pall\u00e1s"
    ],
    "wof:name":"Cortes de Pallas",
    "wof:placetype":"locality",
    "wof:population":999
},
  "geometry": {"coordinates":[-0.93333,39.25],"type":"Point"}
}