{
  "type": "Feature",
  "properties": {
    "gn:admin1_code":"58",
    "gn:admin2_code":"OR",
    "gn:admin3_code":"32068",
    "gn:asciiname":"Escudeiros",
    "gn:country_code":"ES",
    "gn:dem":462,
    "gn:feature_class":"P",
    "gn:feature_code":"PPL",
    "gn:name":"Escudeiros",
    "gn:population":0,
    "gn:timezone":"Europe/Madrid",
    "iso:country":"ES",
    "wof:name":"Escudeiros",
    "wof:placetype":"locality"
},
  "geometry": {"coordinates":[-8.07753,42.20659000000001],"type":"Point"}
}