{
  "type": "Feature",
  "properties": {
    "iso:country":"ES",
    "name:ara_x_preferred":[
        "\u0628\u0627\u0644\u064a\u0646\u064a\u0627"
    ],
    "name:arg_x_preferred":[
        "Baleny\u00e0"
    ],
    "name:ast_x_preferred":[
        "Baleny\u00e0"
    ],
    "name:azb_x_preferred":[
        "\u0628\u0627\u0644\u0646\u06cc\u0627"
    ],
    "name:cat_x_preferred":[
        "Baleny\u00e0"
    ],
    "name:ceb_x_preferred":[
        "Baleny\u00e0"
    ],
    "name:che_x_preferred":[
        "\u0411\u0430\u043b\u0435\u043d\u044c\u044f"
    ],
    "name:deu_x_preferred":[
        "Baleny\u00e0"
    ],
    "name:diq_x_preferred":[
        "Baleny\u00e0"
    ],
    "name:eng_x_preferred":[
        "Baleny\u00e0"
    ],
    "name:eus_x_preferred":[
        "Baleny\u00e0"
    ],
    "name:fas_x_preferred":[
        "\u0628\u0627\u0644\u0646\u06cc\u0627"
    ],
    "name:fra_x_preferred":[
        "Baleny\u00e0"
    ],
    "name:gle_x_preferred":[
        "Baleny\u00e0"
    ],
    "name:hun_x_preferred":[
        "Baleny\u00e0"
    ],
    "name:hye_x_preferred":[
        "\u0532\u0561\u056c\u0565\u0576\u056b\u0561"
    ],
    "name:ile_x_preferred":[
        "Baleny\u00e0"
    ],
    "name:ita_x_preferred":[
        "Baleny\u00e0"
    ],
    "name:kaz_x_preferred":[
        "\u0411\u0430\u043b\u0435\u043d\u044c\u044f"
    ],
    "name:lat_x_preferred":[
        "Baleny\u00e0"
    ],
    "name:lld_x_preferred":[
        "Baleny\u00e0"
    ],
    "name:msa_x_preferred":[
        "Baleny\u00e0"
    ],
    "name:nld_x_preferred":[
        "Baleny\u00e0"
    ],
    "name:oci_x_preferred":[
        "Baleny\u00e0"
    ],
    "name:pol_x_preferred":[
        "Baleny\u00e0"
    ],
    "name:por_x_preferred":[
        "Baleny\u00e0"
    ],
    "name:ron_x_preferred":[
        "Baleny\u00e0"
    ],
    "name:rup_x_preferred":[
        "Baleny\u00e0"
    ],
    "name:rus_x_preferred":[
        "\u0411\u0430\u043b\u0435\u043d\u044c\u044f"
    ],
    "name:spa_x_preferred":[
        "Baleny\u00e1"
    ],
    "name:sqi_x_preferred":[
        "Baleny\u00e0"
    ],
    "name:swe_x_preferred":[
        "Baleny\u00e0"
    ],
    "name:tat_x_preferred":[
        "\u0411\u0430\u043b\u0435\u043d\u044c\u044f"
    ],
    "name:uzb_x_preferred":[
        "Baleny\u00e0"
    ],
    "name:vec_x_preferred":[
        "Baleny\u00e0"
    ],
    "name:war_x_preferred":[
        "Baleny\u00e0"
    ],
    "name:zho_x_preferred":[
        "\u5df4\u83b1\u5c3c\u4e9a"
    ],
    "qs_pg:aaroncc":"ES",
    "qs_pg:name":"Baleny\u00e1",
    "qs_pg:name_adm0":"Espa\u00f1a",
    "qs_pg:name_adm1":"Catalunya",
    "qs_pg:photos":187,
    "qs_pg:photos_1k":38,
    "qs_pg:photos_9k":1,
    "qs_pg:photos_9r":4,
    "qs_pg:photos_all":187,
    "qs_pg:photos_sr":4,
    "qs_pg:pop_sr":0,
    "qs_pg:qs_pg_placetype":"locality",
    "qs_pg:qs_pg_placetype_gp":"Town",
    "qs_pg:woe_adm0":23424950,
    "woe:adm0_id":23424950,
    "woe:name_adm0":"Espa\u00f1a",
    "woe:name_adm1":"Catalunya",
    "woe:placetype":"Town",
    "wof:name":"Baleny\u00e1",
    "wof:placetype":"locality"
},
  "geometry": {"coordinates":[2.234902,41.813418],"type":"Point"}
}