{
  "type": "Feature",
  "properties": {
    "gn:admin1_code":"55",
    "gn:admin2_code":"SO",
    "gn:admin3_code":"42209",
    "gn:asciiname":"Valduerteles",
    "gn:country_code":"ES",
    "gn:dem":1069,
    "gn:feature_class":"P",
    "gn:feature_code":"PPL",
    "gn:name":"Valdu\u00e9rteles",
    "gn:population":0,
    "gn:timezone":"Europe/Madrid",
    "iso:country":"ES",
    "name:und_x_variant":[
        "Valdu\u00e9rteles"
    ],
    "wof:name":"Valduerteles",
    "wof:placetype":"locality"
},
  "geometry": {"coordinates":[-2.36508,42.0541],"type":"Point"}
}