{
  "type": "Feature",
  "properties": {
    "gn:admin1_code":"34",
    "gn:admin2_code":"O",
    "gn:admin3_code":"33028",
    "gn:asciiname":"Torga",
    "gn:country_code":"ES",
    "gn:dem":820,
    "gn:feature_class":"P",
    "gn:feature_code":"PPL",
    "gn:name":"Torga",
    "gn:population":0,
    "gn:timezone":"Europe/Madrid",
    "iso:country":"ES",
    "wof:name":"Torga",
    "wof:placetype":"locality"
},
  "geometry": {"coordinates":[-6.77542,42.95814],"type":"Point"}
}