{
  "type": "Feature",
  "properties": {
    "gn:admin1_code":"58",
    "gn:admin2_code":"OR",
    "gn:admin3_code":"32056",
    "gn:asciiname":"Crespos",
    "gn:cc2":"ES",
    "gn:country_code":"ES",
    "gn:dem":273,
    "gn:feature_class":"P",
    "gn:feature_code":"PPL",
    "gn:name":"Crespos",
    "gn:population":0,
    "gn:timezone":"Europe/Madrid",
    "iso:country":"ES",
    "name:und_x_variant":[
        "San Juan",
        "Crespos"
    ],
    "wof:name":"Crespos",
    "wof:placetype":"locality"
},
  "geometry": {"coordinates":[-8.15,42.13333],"type":"Point"}
}