{
  "type": "Feature",
  "properties": {
    "gn:admin1_code":"58",
    "gn:admin2_code":"OR",
    "gn:admin3_code":"32056",
    "gn:asciiname":"Crespos",
    "gn:cc2":"ES",
    "gn:country_code":"ES",
    "gn:dem":273,
    "gn:feature_class":"P",
    "gn:feature_code":"PPL",
    "gn:name":"Crespos",
    "gn:population":0,
    "gn:timezone":"Europe/Madrid",
    "iso:country":"ES",
    "name:ara_x_preferred":[
        "\u0643\u0631\u064a\u0633\u0628\u0648\u0633"
    ],
    "name:azb_x_preferred":[
        "\u06a9\u0631\u0633\u067e\u0633"
    ],
    "name:cat_x_preferred":[
        "Crespos"
    ],
    "name:eus_x_preferred":[
        "Crespos"
    ],
    "name:fas_x_preferred":[
        "\u06a9\u0631\u0633\u067e\u0633"
    ],
    "name:fra_x_preferred":[
        "Crespos"
    ],
    "name:hun_x_preferred":[
        "Crespos"
    ],
    "name:ina_x_preferred":[
        "Crespos"
    ],
    "name:ita_x_preferred":[
        "Crespos"
    ],
    "name:kaz_x_preferred":[
        "\u041a\u0440\u0435\u0441\u043f\u043e\u0441"
    ],
    "name:mkd_x_preferred":[
        "\u041a\u0440\u0435\u0441\u043f\u043e\u0441"
    ],
    "name:msa_x_preferred":[
        "Crespos"
    ],
    "name:nld_x_preferred":[
        "Crespos"
    ],
    "name:oci_x_preferred":[
        "Crespos"
    ],
    "name:pol_x_preferred":[
        "Crespos"
    ],
    "name:por_x_preferred":[
        "Crespos"
    ],
    "name:rus_x_preferred":[
        "\u041a\u0440\u0435\u0441\u043f\u043e\u0441"
    ],
    "name:spa_x_preferred":[
        "Crespos"
    ],
    "name:ukr_x_preferred":[
        "\u041a\u0440\u0435\u0441\u043f\u043e\u0441"
    ],
    "name:und_x_variant":[
        "San Juan"
    ],
    "name:uzb_x_preferred":[
        "Crespos"
    ],
    "name:vie_x_preferred":[
        "Crespos"
    ],
    "name:war_x_preferred":[
        "Crespos"
    ],
    "name:zho_x_preferred":[
        "\u514b\u96f7\u65af\u6ce2\u65af"
    ],
    "wof:name":"Crespos",
    "wof:placetype":"locality"
},
  "geometry": {"coordinates":[-8.15,42.13333],"type":"Point"}
}