{
  "type": "Feature",
  "properties": {
    "gn:country":"ES",
    "gn:fcode":"PPL",
    "gn:population":0,
    "iso:country":"ES",
    "name:arg_x_preferred":[
        "San Emiliano"
    ],
    "name:ast_x_preferred":[
        "San Emiliano"
    ],
    "name:azb_x_preferred":[
        "\u0633\u0646 \u0627\u0645\u06cc\u0644\u06cc\u0627\u0646\u0648"
    ],
    "name:cat_x_preferred":[
        "San Emiliano"
    ],
    "name:ceb_x_preferred":[
        "San Emiliano"
    ],
    "name:eus_x_preferred":[
        "San Emiliano"
    ],
    "name:fas_x_preferred":[
        "\u0633\u0646 \u0627\u0645\u06cc\u0644\u06cc\u0627\u0646\u0648"
    ],
    "name:fra_x_preferred":[
        "San Emiliano"
    ],
    "name:glg_x_preferred":[
        "San Emiliano"
    ],
    "name:haw_x_preferred":[
        "San Emiliano"
    ],
    "name:hun_x_preferred":[
        "San Emiliano"
    ],
    "name:ido_x_preferred":[
        "San Emiliano"
    ],
    "name:ina_x_preferred":[
        "San Emiliano"
    ],
    "name:ita_x_preferred":[
        "San Emiliano"
    ],
    "name:jpn_x_preferred":[
        "\u30b5\u30f3\u30fb\u30a8\u30df\u30ea\u30a2\u30fc\u30ce"
    ],
    "name:msa_x_preferred":[
        "San Emiliano"
    ],
    "name:oci_x_preferred":[
        "San Emiliano"
    ],
    "name:pol_x_preferred":[
        "San Emiliano"
    ],
    "name:por_x_preferred":[
        "San Emiliano"
    ],
    "name:spa_x_preferred":[
        "San Emiliano"
    ],
    "name:swe_x_preferred":[
        "San Emiliano"
    ],
    "name:tpi_x_preferred":[
        "San Emiliano"
    ],
    "name:ukr_x_preferred":[
        "\u0421\u0430\u043d-\u0415\u043c\u0456\u043b\u0456\u0430\u043d\u043e"
    ],
    "name:vie_x_preferred":[
        "San Emiliano"
    ],
    "name:war_x_preferred":[
        "San Emiliano"
    ],
    "name:zho_x_preferred":[
        "\u5723\u57c3\u7c73\u5229\u4e9a\u8bfa"
    ],
    "qs_pg:aaroncc":"ES",
    "qs_pg:gn_country":"ES",
    "qs_pg:gn_fcode":"PPL",
    "qs_pg:gn_pop":0,
    "qs_pg:name":"San Emiliano",
    "qs_pg:name_adm0":"Espa\u00f1a",
    "qs_pg:name_adm1":"Principado de Asturias",
    "qs_pg:photos":9,
    "qs_pg:photos_1k":2,
    "qs_pg:photos_9k":1,
    "qs_pg:photos_9r":1,
    "qs_pg:photos_all":9,
    "qs_pg:photos_sr":1,
    "qs_pg:pop_sr":0,
    "qs_pg:qs_pg_placetype":"locality",
    "qs_pg:qs_pg_placetype_gp":"Town",
    "qs_pg:woe_adm0":23424950,
    "woe:adm0_id":23424950,
    "woe:name_adm0":"Espa\u00f1a",
    "woe:name_adm1":"Principado de Asturias",
    "woe:placetype":"Town",
    "wof:name":"San Emiliano",
    "wof:placetype":"locality"
},
  "geometry": {"coordinates":[-6.83276,43.25946],"type":"Point"}
}