{
  "type": "Feature",
  "properties": {
    "gn:country":"ES",
    "gn:fcode":"PPLA3",
    "gn:population":18,
    "iso:country":"ES",
    "name:arg_x_preferred":[
        "Villasdardo"
    ],
    "name:ast_x_preferred":[
        "Villasdardo"
    ],
    "name:bul_x_preferred":[
        "\u0412\u0438\u043b\u0430\u0441\u0434\u0430\u0440\u0434\u043e"
    ],
    "name:cat_x_preferred":[
        "Villasdardo"
    ],
    "name:ceb_x_preferred":[
        "Villasdardo"
    ],
    "name:eng_x_preferred":[
        "Villasdardo"
    ],
    "name:eus_x_preferred":[
        "Villasdardo"
    ],
    "name:fra_x_preferred":[
        "Villasdardo"
    ],
    "name:glg_x_preferred":[
        "Villasdardo"
    ],
    "name:hun_x_preferred":[
        "Villasdardo"
    ],
    "name:ina_x_preferred":[
        "Villasdardo"
    ],
    "name:ita_x_preferred":[
        "Villasdardo"
    ],
    "name:kaz_x_preferred":[
        "\u0412\u0438\u043b\u044c\u044f\u0441\u0434\u0430\u0440\u0434\u043e"
    ],
    "name:msa_x_preferred":[
        "Villasdardo"
    ],
    "name:nan_x_preferred":[
        "Villasdardo"
    ],
    "name:nld_x_preferred":[
        "Villasdardo"
    ],
    "name:oci_x_preferred":[
        "Villasdardo"
    ],
    "name:pol_x_preferred":[
        "Villasdardo"
    ],
    "name:por_x_preferred":[
        "Villasdardo"
    ],
    "name:rus_x_preferred":[
        "\u0412\u0438\u043b\u044c\u044f\u0441\u0434\u0430\u0440\u0434\u043e"
    ],
    "name:spa_x_preferred":[
        "Villasdardo"
    ],
    "name:swe_x_preferred":[
        "Villasdardo"
    ],
    "name:ukr_x_preferred":[
        "\u0412\u0456\u043b\u044c\u044f\u0441\u0434\u0430\u0440\u0434\u043e"
    ],
    "name:vie_x_preferred":[
        "Villasdardo"
    ],
    "name:war_x_preferred":[
        "Villasdardo"
    ],
    "name:zho_x_preferred":[
        "\u6bd4\u5229\u4e9a\u65af\u8fbe\u5c14\u591a"
    ],
    "qs_pg:aaroncc":"ES",
    "qs_pg:gn_country":"ES",
    "qs_pg:gn_fcode":"PPLA3",
    "qs_pg:gn_pop":18,
    "qs_pg:name":"Villasdardo",
    "qs_pg:name_adm0":"Espa\u00f1a",
    "qs_pg:name_adm1":"Castilla y Le\u00f3n",
    "qs_pg:photos_9r":0,
    "qs_pg:photos_sr":0,
    "qs_pg:pop_sr":1,
    "qs_pg:qs_pg_placetype":"locality",
    "qs_pg:qs_pg_placetype_gp":"Town",
    "qs_pg:woe_adm0":23424950,
    "woe:adm0_id":23424950,
    "woe:name_adm0":"Espa\u00f1a",
    "woe:name_adm1":"Castilla y Le\u00f3n",
    "woe:placetype":"Town",
    "wof:name":"Villasdardo",
    "wof:placetype":"locality",
    "wof:population":18
},
  "geometry": {"coordinates":[-6.16303,41.00448],"type":"Point"}
}