{
  "type": "Feature",
  "properties": {
    "gn:admin1_code":"55",
    "gn:admin2_code":"SA",
    "gn:admin3_code":"37106",
    "gn:asciiname":"El Valejo",
    "gn:country_code":"ES",
    "gn:dem":777,
    "gn:feature_class":"P",
    "gn:feature_code":"PPL",
    "gn:name":"El Valejo",
    "gn:population":0,
    "gn:timezone":"Europe/Madrid",
    "iso:country":"ES",
    "wof:name":"El Valejo",
    "wof:placetype":"locality"
},
  "geometry": {"coordinates":[-6.17808,40.96008],"type":"Point"}
}