{
  "type": "Feature",
  "properties": {
    "gn:country":"ES",
    "gn:fcode":"PPLA3",
    "gn:population":124,
    "iso:country":"ES",
    "name:arg_x_preferred":[
        "A\u00f1e"
    ],
    "name:ast_x_preferred":[
        "A\u00f1e"
    ],
    "name:cat_x_preferred":[
        "A\u00f1e"
    ],
    "name:ceb_x_preferred":[
        "A\u00f1e"
    ],
    "name:eng_x_preferred":[
        "A\u00f1e"
    ],
    "name:eus_x_preferred":[
        "A\u00f1e"
    ],
    "name:fra_x_preferred":[
        "A\u00f1e"
    ],
    "name:hun_x_preferred":[
        "A\u00f1e"
    ],
    "name:ina_x_preferred":[
        "A\u00f1e"
    ],
    "name:ita_x_preferred":[
        "A\u00f1e"
    ],
    "name:msa_x_preferred":[
        "A\u00f1e"
    ],
    "name:nan_x_preferred":[
        "A\u00f1e"
    ],
    "name:nld_x_preferred":[
        "A\u00f1e"
    ],
    "name:oci_x_preferred":[
        "A\u00f1e"
    ],
    "name:pol_x_preferred":[
        "A\u00f1e"
    ],
    "name:por_x_preferred":[
        "A\u00f1e"
    ],
    "name:rup_x_preferred":[
        "A\u00f1e"
    ],
    "name:rus_x_preferred":[
        "\u0410\u043d\u044c\u0435"
    ],
    "name:spa_x_preferred":[
        "A\u00f1e"
    ],
    "name:swe_x_preferred":[
        "A\u00f1e"
    ],
    "name:ukr_x_preferred":[
        "\u0410\u043d\u044c\u0454"
    ],
    "name:vie_x_preferred":[
        "A\u00f1e"
    ],
    "name:war_x_preferred":[
        "A\u00f1e"
    ],
    "name:zho_x_preferred":[
        "\u963f\u6d85"
    ],
    "qs_pg:aaroncc":"ES",
    "qs_pg:gn_country":"ES",
    "qs_pg:gn_fcode":"PPLA3",
    "qs_pg:gn_pop":124,
    "qs_pg:name":"A\u00f1e",
    "qs_pg:name_adm0":"Espa\u00f1a",
    "qs_pg:name_adm1":"Castilla y Le\u00f3n",
    "qs_pg:photos_9k":1,
    "qs_pg:photos_9r":1,
    "qs_pg:photos_all":2,
    "qs_pg:photos_sr":0,
    "qs_pg:pop_sr":1,
    "qs_pg:qs_pg_placetype":"locality",
    "qs_pg:qs_pg_placetype_gp":"Town",
    "qs_pg:woe_adm0":23424950,
    "woe:adm0_id":23424950,
    "woe:name_adm0":"Espa\u00f1a",
    "woe:name_adm1":"Castilla y Le\u00f3n",
    "woe:placetype":"Town",
    "wof:name":"A\u00f1e",
    "wof:placetype":"locality",
    "wof:population":124
},
  "geometry": {"coordinates":[-4.29462,41.03702],"type":"Point"}
}