{
  "type": "Feature",
  "properties": {
    "gn:admin1_code":"51",
    "gn:admin2_code":"J",
    "gn:admin3_code":"23024",
    "gn:asciiname":"Isabela",
    "gn:country_code":"ES",
    "gn:dem":527,
    "gn:feature_class":"P",
    "gn:feature_code":"PPL",
    "gn:name":"Isabela",
    "gn:population":0,
    "gn:timezone":"Europe/Madrid",
    "iso:country":"ES",
    "wof:name":"Isabela",
    "wof:placetype":"locality"
},
  "geometry": {"coordinates":[-3.58047,38.24072],"type":"Point"}
}