{
  "type": "Feature",
  "properties": {
    "gn:admin1_code":"56",
    "gn:admin2_code":"T",
    "gn:admin3_code":"43903",
    "gn:asciiname":"El lligallo del Ganguil",
    "gn:country_code":"ES",
    "gn:dem":4,
    "gn:feature_class":"P",
    "gn:feature_code":"PPL",
    "gn:name":"El lligallo del G\u00e0nguil",
    "gn:population":0,
    "gn:timezone":"Europe/Madrid",
    "iso:country":"ES",
    "wof:name":"El lligallo del Ganguil",
    "wof:placetype":"locality"
},
  "geometry": {"coordinates":[0.65214,40.75701],"type":"Point"}
}