{
  "type": "Feature",
  "properties": {
    "gn:admin1_code":"51",
    "gn:admin2_code":"AL",
    "gn:admin3_code":"04081",
    "gn:asciiname":"Las Yeseras de Galachar",
    "gn:cc2":"ES",
    "gn:country_code":"ES",
    "gn:dem":268,
    "gn:feature_class":"P",
    "gn:feature_code":"PPL",
    "gn:name":"Las Yeseras de Gal\u00e1char",
    "gn:population":0,
    "gn:timezone":"Europe/Madrid",
    "iso:country":"ES",
    "name:und_x_variant":[
        "Barriada Las Yeseras de Galachar",
        "Las Yeseras de Gal\u00e1char"
    ],
    "wof:name":"Las Yeseras de Galachar",
    "wof:placetype":"locality"
},
  "geometry": {"coordinates":[-2.53333,36.96667],"type":"Point"}
}