{
  "type": "Feature",
  "properties": {
    "gn:admin1_code":"58",
    "gn:admin2_code":"C",
    "gn:admin3_code":"15062",
    "gn:asciiname":"Casais",
    "gn:cc2":"ES",
    "gn:country_code":"ES",
    "gn:dem":157,
    "gn:feature_class":"P",
    "gn:feature_code":"PPL",
    "gn:name":"Casais",
    "gn:population":0,
    "gn:timezone":"Europe/Madrid",
    "iso:country":"ES",
    "name:und_x_variant":[
        "Casals"
    ],
    "wof:name":"Casais",
    "wof:placetype":"locality"
},
  "geometry": {"coordinates":[-8.90433,42.87169],"type":"Point"}
}