{
  "type": "Feature",
  "properties": {
    "gn:admin1_code":"58",
    "gn:admin2_code":"C",
    "gn:admin3_code":"15062",
    "gn:asciiname":"Casais",
    "gn:cc2":"ES",
    "gn:country_code":"ES",
    "gn:dem":157,
    "gn:feature_class":"P",
    "gn:feature_code":"PPL",
    "gn:name":"Casais",
    "gn:population":0,
    "gn:timezone":"Europe/Madrid",
    "iso:country":"ES",
    "name:ceb_x_preferred":[
        "Casais"
    ],
    "name:deu_x_preferred":[
        "Casais"
    ],
    "name:fra_x_preferred":[
        "Casais"
    ],
    "name:glg_x_preferred":[
        "Casais"
    ],
    "name:nld_x_preferred":[
        "Casais"
    ],
    "name:por_x_preferred":[
        "Casais"
    ],
    "name:rus_x_preferred":[
        "\u041a\u0430\u0437\u0430\u0439\u0448"
    ],
    "name:spa_x_preferred":[
        "Casais"
    ],
    "name:tur_x_preferred":[
        "Casais"
    ],
    "name:und_x_variant":[
        "Casals"
    ],
    "wof:name":"Casais",
    "wof:placetype":"locality"
},
  "geometry": {"coordinates":[-8.90433,42.87169],"type":"Point"}
}