{
  "type": "Feature",
  "properties": {
    "iso:country":"ES",
    "name:eng_x_preferred":[
        "Las Morillas"
    ],
    "name:spa_x_preferred":[
        "Las Morillas"
    ],
    "wof:name":"Las Morillas",
    "wof:placetype":"neighbourhood"
},
  "geometry": {"coordinates":[-4.46554382660371,36.7212224729206],"type":"Point"}
}