{
  "type": "Feature",
  "properties": {
    "gn:admin1_code":"58",
    "gn:admin2_code":"LU",
    "gn:admin3_code":"27012",
    "gn:asciiname":"Villaluz",
    "gn:country_code":"ES",
    "gn:dem":679,
    "gn:feature_class":"P",
    "gn:feature_code":"PPL",
    "gn:name":"Villaluz",
    "gn:population":0,
    "gn:timezone":"Europe/Madrid",
    "iso:country":"ES",
    "wof:name":"Villaluz",
    "wof:placetype":"locality"
},
  "geometry": {"coordinates":[-7.03449,42.86176],"type":"Point"}
}