{
  "type": "Feature",
  "properties": {
    "gn:admin1_code":"55",
    "gn:admin2_code":"ZA",
    "gn:admin3_code":"49087",
    "gn:asciiname":"Valer",
    "gn:country_code":"ES",
    "gn:dem":732,
    "gn:feature_class":"P",
    "gn:feature_code":"PPL",
    "gn:name":"Valer",
    "gn:population":0,
    "gn:timezone":"Europe/Madrid",
    "iso:country":"ES",
    "wof:name":"Valer",
    "wof:placetype":"locality"
},
  "geometry": {"coordinates":[-6.17967,41.76291],"type":"Point"}
}