{
  "type": "Feature",
  "properties": {
    "gn:admin1_code":"32",
    "gn:admin3_code":"31136",
    "gn:asciiname":"Oteiza",
    "gn:country_code":"ES",
    "gn:dem":499,
    "gn:feature_class":"P",
    "gn:feature_code":"PPL",
    "gn:name":"Oteiza",
    "gn:population":0,
    "gn:timezone":"Europe/Madrid",
    "iso:country":"ES",
    "wof:name":"Oteiza",
    "wof:placetype":"locality"
},
  "geometry": {"coordinates":[-1.71498,42.87118],"type":"Point"}
}