{
  "type": "Feature",
  "properties": {
    "gn:admin1_code":"32",
    "gn:admin3_code":"31136",
    "gn:asciiname":"Oteiza",
    "gn:country_code":"ES",
    "gn:dem":499,
    "gn:feature_class":"P",
    "gn:feature_code":"PPL",
    "gn:name":"Oteiza",
    "gn:population":0,
    "gn:timezone":"Europe/Madrid",
    "iso:country":"ES",
    "name:arg_x_preferred":[
        "Oteiza"
    ],
    "name:bre_x_preferred":[
        "Oteitza"
    ],
    "name:cat_x_preferred":[
        "Oteiza"
    ],
    "name:eus_x_preferred":[
        "Oteitza"
    ],
    "name:fra_x_preferred":[
        "Oteiza"
    ],
    "name:hun_x_preferred":[
        "Oteiza"
    ],
    "name:ita_x_preferred":[
        "Oteiza"
    ],
    "name:msa_x_preferred":[
        "Oteiza"
    ],
    "name:nld_x_preferred":[
        "Oteiza"
    ],
    "name:oci_x_preferred":[
        "Oteiza"
    ],
    "name:pol_x_preferred":[
        "Oteiza"
    ],
    "name:por_x_preferred":[
        "Oteiza"
    ],
    "name:rus_x_preferred":[
        "\u041e\u0442\u0435\u0439\u0441\u0430"
    ],
    "name:sco_x_preferred":[
        "Oteiza"
    ],
    "name:spa_x_preferred":[
        "Oteiza"
    ],
    "name:ukr_x_preferred":[
        "\u041e\u0442\u0435\u0439\u0441\u0430"
    ],
    "name:vie_x_preferred":[
        "Oteiza"
    ],
    "name:war_x_preferred":[
        "Oteiza"
    ],
    "name:zho_x_preferred":[
        "\u5965\u6cf0\u8428"
    ],
    "wof:name":"Oteiza",
    "wof:placetype":"locality"
},
  "geometry": {"coordinates":[-1.71498,42.87118],"type":"Point"}
}