{
  "type": "Feature",
  "properties": {
    "gn:admin1_code":"53",
    "gn:admin2_code":"GC",
    "gn:admin3_code":"35026",
    "gn:asciiname":"Gando",
    "gn:country_code":"ES",
    "gn:dem":53,
    "gn:feature_class":"P",
    "gn:feature_code":"PPL",
    "gn:name":"Gando",
    "gn:population":0,
    "gn:timezone":"Atlantic/Canary",
    "iso:country":"ES",
    "name:ceb_x_preferred":[
        "Gando"
    ],
    "name:deu_x_preferred":[
        "Gando"
    ],
    "name:fra_x_preferred":[
        "Gando"
    ],
    "name:srp_x_preferred":[
        "\u0413\u0430\u043d\u0434\u043e"
    ],
    "name:swe_x_preferred":[
        "Gando"
    ],
    "wof:name":"Gando",
    "wof:placetype":"locality"
},
  "geometry": {"coordinates":[-15.39425,27.94968],"type":"Point"}
}