{
  "type": "Feature",
  "properties": {
    "gn:admin1_code":"54",
    "gn:admin2_code":"AB",
    "gn:admin3_code":"02069",
    "gn:asciiname":"El Carmen",
    "gn:country_code":"ES",
    "gn:dem":695,
    "gn:feature_class":"P",
    "gn:feature_code":"PPL",
    "gn:name":"El Carmen",
    "gn:population":0,
    "gn:timezone":"Europe/Madrid",
    "iso:country":"ES",
    "name:bre_x_preferred":[
        "El Carmen"
    ],
    "name:ceb_x_preferred":[
        "El Carmen"
    ],
    "name:deu_x_preferred":[
        "El Carmen"
    ],
    "name:est_x_preferred":[
        "El Carmen"
    ],
    "name:fra_x_preferred":[
        "El Carmen"
    ],
    "name:ita_x_preferred":[
        "El Carmen"
    ],
    "name:nld_x_preferred":[
        "El Carmen"
    ],
    "name:pol_x_preferred":[
        "El Carmen"
    ],
    "name:por_x_preferred":[
        "El Carmen"
    ],
    "name:rus_x_preferred":[
        "\u042d\u043b\u044c-\u041a\u0430\u0440\u043c\u0435\u043d"
    ],
    "name:sco_x_preferred":[
        "El Carmen"
    ],
    "name:spa_x_preferred":[
        "El Carmen"
    ],
    "name:swe_x_preferred":[
        "El Carmen"
    ],
    "name:vie_x_preferred":[
        "El Carmen"
    ],
    "wof:name":"El Carmen",
    "wof:placetype":"locality"
},
  "geometry": {"coordinates":[-2.06667,39.26667],"type":"Point"}
}