{
  "type": "Feature",
  "properties": {
    "gn:admin1_code":"55",
    "gn:admin2_code":"AV",
    "gn:admin3_code":"05178",
    "gn:asciiname":"Tornadizos de Arevalo",
    "gn:country_code":"ES",
    "gn:dem":840,
    "gn:feature_class":"P",
    "gn:feature_code":"PPL",
    "gn:name":"Tornadizos de Ar\u00e9valo",
    "gn:population":0,
    "gn:timezone":"Europe/Madrid",
    "iso:country":"ES",
    "name:und_x_variant":[
        "Tornadizos de Ar\u00e9valo"
    ],
    "wof:name":"Tornadizos de Arevalo",
    "wof:placetype":"locality"
},
  "geometry": {"coordinates":[-4.76124,41.07919],"type":"Point"}
}