{
  "type": "Feature",
  "properties": {
    "gn:admin1_code":"34",
    "gn:admin2_code":"O",
    "gn:admin3_code":"33018",
    "gn:asciiname":"Bustabernego",
    "gn:country_code":"ES",
    "gn:dem":552,
    "gn:feature_class":"P",
    "gn:feature_code":"PPL",
    "gn:name":"Bustabernego",
    "gn:population":0,
    "gn:timezone":"Europe/Madrid",
    "iso:country":"ES",
    "name:und_x_variant":[
        "Bustaberniego",
        "Bustabarnego",
        "Bustabernego"
    ],
    "wof:name":"Bustabernego",
    "wof:placetype":"locality"
},
  "geometry": {"coordinates":[-6.75899,43.4698],"type":"Point"}
}