{
  "type": "Feature",
  "properties": {
    "gn:gn_country":"ES",
    "gn:gn_fcode":"PPLA3",
    "gn:gn_pop":43,
    "gn:population":43,
    "iso:country":"ES",
    "name:ara_x_preferred":[
        "\u0646\u0627\u0631\u0648\u0633 \u062f\u064a\u0644 \u0628\u0648\u064a\u0631\u062a\u0648"
    ],
    "name:ast_x_preferred":[
        "Narros del Puerto"
    ],
    "name:azb_x_preferred":[
        "\u0646\u0627\u0631\u0633 \u062f\u0644 \u067e\u0648\u0626\u0631\u062a\u0648"
    ],
    "name:cat_x_preferred":[
        "Narros del Puerto"
    ],
    "name:ceb_x_preferred":[
        "Narros del Puerto"
    ],
    "name:deu_x_preferred":[
        "Narros del Puerto"
    ],
    "name:eng_x_preferred":[
        "Narros del Puerto"
    ],
    "name:eus_x_preferred":[
        "Narros del Puerto"
    ],
    "name:fas_x_preferred":[
        "\u0646\u0627\u0631\u0633 \u062f\u0644 \u067e\u0648\u0626\u0631\u062a\u0648"
    ],
    "name:fra_x_preferred":[
        "Narros del Puerto"
    ],
    "name:hun_x_preferred":[
        "Narros del Puerto"
    ],
    "name:ina_x_preferred":[
        "Narros del Puerto"
    ],
    "name:ita_x_preferred":[
        "Narros del Puerto"
    ],
    "name:kaz_x_preferred":[
        "\u041d\u0430\u0440\u0440\u043e\u0441-\u0434\u0435\u043b\u044c-\u041f\u0443\u044d\u0440\u0442\u043e"
    ],
    "name:mkd_x_preferred":[
        "\u041d\u0430\u0440\u043e\u0441 \u0434\u0435\u043b \u041f\u0443\u0435\u0440\u0442\u043e"
    ],
    "name:msa_x_preferred":[
        "Narros del Puerto"
    ],
    "name:nld_x_preferred":[
        "Narros del Puerto"
    ],
    "name:oci_x_preferred":[
        "Narros del Puerto"
    ],
    "name:pol_x_preferred":[
        "Narros del Puerto"
    ],
    "name:por_x_preferred":[
        "Narros del Puerto"
    ],
    "name:rus_x_preferred":[
        "\u041d\u0430\u0440\u0440\u043e\u0441-\u0434\u0435\u043b\u044c-\u041f\u0443\u044d\u0440\u0442\u043e"
    ],
    "name:spa_x_preferred":[
        "Narros del Puerto"
    ],
    "name:swe_x_preferred":[
        "Narros del Puerto"
    ],
    "name:ukr_x_preferred":[
        "\u041d\u0430\u0440\u0440\u043e\u0441-\u0434\u0435\u043b\u044c-\u041f\u0443\u0435\u0440\u0442\u043e"
    ],
    "name:uzb_x_preferred":[
        "Narros del Puerto"
    ],
    "name:vie_x_preferred":[
        "Narros del Puerto"
    ],
    "name:war_x_preferred":[
        "Narros del Puerto"
    ],
    "name:zho_x_preferred":[
        "\u7eb3\u7f57\u65af\u5fb7\u5c14\u666e\u57c3\u5c14\u6258"
    ],
    "qs_pg:aaroncc":"ES",
    "qs_pg:gn_country":"ES",
    "qs_pg:gn_fcode":"PPLA3",
    "qs_pg:gn_pop":43,
    "qs_pg:name":"Narros del Puerto",
    "qs_pg:name_adm0":"Espa\u00f1a",
    "qs_pg:name_adm1":"Castilla y Le\u00f3n",
    "qs_pg:photos_9r":0,
    "qs_pg:photos_sr":0,
    "qs_pg:pop_sr":1,
    "qs_pg:qs_pg_placetype":"locality",
    "qs_pg:qs_pg_placetype_gp":"Town",
    "qs_pg:woe_adm0":23424950,
    "woe:adm0_id":23424950,
    "woe:name_adm0":"Espa\u00f1a",
    "woe:name_adm1":"Castilla y Le\u00f3n",
    "woe:placetype":"Town",
    "wof:name":"Narros del Puerto",
    "wof:placetype":"locality",
    "wof:population":43
},
  "geometry": {"coordinates":[-4.99292,40.54131],"type":"Point"}
}