{
  "type": "Feature",
  "properties": {
    "gn:admin1_code":"55",
    "gn:admin2_code":"BU",
    "gn:admin3_code":"09109",
    "gn:asciiname":"Golernio",
    "gn:country_code":"ES",
    "gn:dem":654,
    "gn:feature_class":"P",
    "gn:feature_code":"PPL",
    "gn:name":"Golernio",
    "gn:population":0,
    "gn:timezone":"Europe/Madrid",
    "iso:country":"ES",
    "wof:name":"Golernio",
    "wof:placetype":"locality"
},
  "geometry": {"coordinates":[-2.75568,42.76441],"type":"Point"}
}