{
  "type": "Feature",
  "properties": {
    "gn:country":"ES",
    "gn:fcode":"PPLA3",
    "gn:population":514,
    "iso:country":"ES",
    "name:ara_x_preferred":[
        "\u0628\u0627\u0631\u0627\u0643\u0648\u064a\u0648\u0633 \u062f\u064a \u062e\u064a\u0644\u0648\u0643\u0627"
    ],
    "name:arg_x_preferred":[
        "Paracuellos de Xiloca"
    ],
    "name:azb_x_preferred":[
        "\u067e\u0627\u0631\u0627\u06a9\u0648\u0626\u06cc\u0633 \u062f \u062e\u06cc\u0644\u06a9\u0627"
    ],
    "name:cat_x_preferred":[
        "Paracuellos de Jiloca"
    ],
    "name:eng_x_preferred":[
        "Paracuellos de Jiloca"
    ],
    "name:eus_x_preferred":[
        "Paracuellos de Jiloca"
    ],
    "name:fas_x_preferred":[
        "\u067e\u0627\u0631\u0627\u06a9\u0648\u0626\u06cc\u0633 \u062f \u062e\u06cc\u0644\u06a9\u0627"
    ],
    "name:fra_x_preferred":[
        "Paracuellos de Jiloca"
    ],
    "name:glg_x_preferred":[
        "Paracuellos de Jiloca"
    ],
    "name:hun_x_preferred":[
        "Paracuellos de Jiloca"
    ],
    "name:ita_x_preferred":[
        "Paracuellos de Jiloca"
    ],
    "name:kaz_x_preferred":[
        "\u041f\u0430\u0440\u0430\u043a\u0443\u044d\u043b\u044c\u043e\u0441-\u0434\u0435-\u0425\u0438\u043b\u043e\u043a\u0430"
    ],
    "name:msa_x_preferred":[
        "Paracuellos de Jiloca"
    ],
    "name:nan_x_preferred":[
        "Paracuellos de Jiloca"
    ],
    "name:nld_x_preferred":[
        "Paracuellos de Jiloca"
    ],
    "name:oci_x_preferred":[
        "Paracuellos de Jiloca"
    ],
    "name:pol_x_preferred":[
        "Paracuellos de Jiloca"
    ],
    "name:por_x_preferred":[
        "Paracuellos de Jiloca"
    ],
    "name:rus_x_preferred":[
        "\u041f\u0430\u0440\u0430\u043a\u0443\u044d\u043b\u044c\u043e\u0441-\u0434\u0435-\u0425\u0438\u043b\u043e\u043a\u0430"
    ],
    "name:spa_x_preferred":[
        "Paracuellos de Jiloca"
    ],
    "name:swe_x_preferred":[
        "Paracuellos de Jiloca"
    ],
    "name:ukr_x_preferred":[
        "\u041f\u0430\u0440\u0430\u043a\u0443\u0435\u043b\u044c\u0439\u043e\u0441-\u0434\u0435-\u0425\u0456\u043b\u043e\u043a\u0430"
    ],
    "name:uzb_x_preferred":[
        "Paracuellos de Jiloca"
    ],
    "name:vie_x_preferred":[
        "Paracuellos de Jiloca"
    ],
    "name:war_x_preferred":[
        "Paracuellos de Jiloca"
    ],
    "name:zho_x_preferred":[
        "\u5e15\u62c9\u5e93\u57c3\u7565\u65af\u5fb7\u5e0c\u6d1b\u5361"
    ],
    "qs_pg:aaroncc":"ES",
    "qs_pg:gn_country":"ES",
    "qs_pg:gn_fcode":"PPLA3",
    "qs_pg:gn_pop":514,
    "qs_pg:name":"Paracuellos de Jiloca",
    "qs_pg:name_adm0":"Espa\u00f1a",
    "qs_pg:name_adm1":"Arag\u00f3n",
    "qs_pg:photos_9r":0,
    "qs_pg:photos_sr":0,
    "qs_pg:pop_sr":2,
    "qs_pg:qs_pg_placetype":"locality",
    "qs_pg:qs_pg_placetype_gp":"Town",
    "qs_pg:woe_adm0":23424950,
    "woe:adm0_id":23424950,
    "woe:name_adm0":"Espa\u00f1a",
    "woe:name_adm1":"Arag\u00f3n",
    "woe:placetype":"Town",
    "wof:name":"Paracuellos de Jiloca",
    "wof:placetype":"locality",
    "wof:population":514
},
  "geometry": {"coordinates":[-1.64029,41.31378],"type":"Point"}
}