{
  "type": "Feature",
  "properties": {
    "iso:country":"ES",
    "name:alb_x_preferred":[
        "Amezketa"
    ],
    "name:ara_x_preferred":[
        "\u0623\u0645\u064a\u062b\u0643\u064a\u062a\u0627"
    ],
    "name:arg_x_preferred":[
        "Amezqueta"
    ],
    "name:ast_x_preferred":[
        "Amezketa"
    ],
    "name:baq_x_preferred":[
        "Amezketa"
    ],
    "name:bre_x_preferred":[
        "Amezketa"
    ],
    "name:bul_x_preferred":[
        "\u0410\u043c\u0435\u0437\u043a\u0435\u0442\u0430"
    ],
    "name:cat_x_preferred":[
        "Amezketa"
    ],
    "name:chi_x_preferred":[
        "\u963f\u6885\u65af\u514b\u5854"
    ],
    "name:dut_x_preferred":[
        "Amezketa"
    ],
    "name:eng_x_preferred":[
        "Amezketa"
    ],
    "name:fre_x_preferred":[
        "Amezketa"
    ],
    "name:glg_x_preferred":[
        "Amezketa"
    ],
    "name:hun_x_preferred":[
        "Amezketa"
    ],
    "name:ita_x_preferred":[
        "Amezketa"
    ],
    "name:jpn_x_preferred":[
        "\u30a2\u30e1\u30b9\u30b1\u30bf"
    ],
    "name:may_x_preferred":[
        "Amezketa"
    ],
    "name:oci_x_preferred":[
        "Amezketa"
    ],
    "name:per_x_preferred":[
        "\u0627\u0645\u0632\u06a9\u062a\u0627"
    ],
    "name:pol_x_preferred":[
        "Amezketa"
    ],
    "name:por_x_preferred":[
        "Amezketa"
    ],
    "name:rus_x_preferred":[
        "\u0410\u043c\u0435\u0441\u043a\u0435\u0442\u0430"
    ],
    "name:sco_x_preferred":[
        "Amezketa"
    ],
    "name:spa_x_preferred":[
        "Am\u00e9zqueta"
    ],
    "name:swe_x_preferred":[
        "Amezketa"
    ],
    "name:ukr_x_preferred":[
        "\u0410\u043c\u0435\u0441\u043a\u0435\u0442\u0430"
    ],
    "name:uzb_x_preferred":[
        "Am\u00e9zqueta"
    ],
    "name:vie_x_preferred":[
        "Amezketa"
    ],
    "name:war_x_preferred":[
        "Amezketa"
    ],
    "qs_pg:aaroncc":"ES",
    "qs_pg:name":"Amezketa",
    "qs_pg:name_adm0":"Espa\u00f1a",
    "qs_pg:name_adm1":"Euskadi",
    "qs_pg:photos":168,
    "qs_pg:photos_1k":34,
    "qs_pg:photos_9k":1,
    "qs_pg:photos_9r":4,
    "qs_pg:photos_all":168,
    "qs_pg:photos_sr":4,
    "qs_pg:pop_sr":0,
    "qs_pg:qs_pg_placetype":"locality",
    "qs_pg:qs_pg_placetype_gp":"Town",
    "qs_pg:woe_adm0":23424950,
    "woe:adm0_id":23424950,
    "woe:name_adm0":"Espa\u00f1a",
    "woe:name_adm1":"Euskadi",
    "woe:placetype":"Town",
    "wof:name":"Amezketa",
    "wof:placetype":"locality"
},
  "geometry": {"coordinates":[-2.09,43.05],"type":"Point"}
}