{
  "type": "Feature",
  "properties": {
    "iso:country":"ES",
    "name:spa_x_colloquial":[
        "Caserio Miranda"
    ],
    "name:spa_x_preferred":[
        "Miranda"
    ],
    "name:spa_x_variant":[
        "Caser\u00edo Miranda"
    ],
    "name:unk_x_variant":[
        "Caser\u00edo Miranda"
    ],
    "qs:a0":"Espa\u00f1a",
    "qs:a1":"*Murcia",
    "qs:a1r":"0Regi\u00f3n de Murcia",
    "qs:adm0":"Espa\u00f1a",
    "qs:la_lc":"*",
    "qs:level":"locality",
    "qs:loc":"Miranda",
    "qs:loc_alt":"Miranda",
    "qs:pop":0,
    "qs:type":"buffered point",
    "wof:lang":[
        "spa"
    ],
    "wof:name":"Miranda",
    "wof:placetype":"locality"
},
  "geometry": {"coordinates":[-1.024477,37.682662],"type":"Point"}
}