{
  "type": "Feature",
  "properties": {
    "gn:admin1_code":"57",
    "gn:admin2_code":"CC",
    "gn:admin3_code":"10051",
    "gn:asciiname":"Huetre",
    "gn:country_code":"ES",
    "gn:dem":699,
    "gn:feature_class":"P",
    "gn:feature_code":"PPL",
    "gn:name":"Huetre",
    "gn:population":0,
    "gn:timezone":"Europe/Madrid",
    "iso:country":"ES",
    "name:und_x_variant":[
        "Caser\u00edo Huetre",
        "Huetre"
    ],
    "wof:name":"Huetre",
    "wof:placetype":"locality"
},
  "geometry": {"coordinates":[-6.30543,40.4436],"type":"Point"}
}