{
  "type": "Feature",
  "properties": {
    "gn:admin1_code":"59",
    "gn:admin2_code":"VI",
    "gn:admin3_code":"01027",
    "gn:asciiname":"Arrieta",
    "gn:country_code":"ES",
    "gn:dem":580,
    "gn:feature_class":"P",
    "gn:feature_code":"PPL",
    "gn:name":"Arrieta",
    "gn:population":0,
    "gn:timezone":"Europe/Madrid",
    "iso:country":"ES",
    "wof:name":"Arrieta",
    "wof:placetype":"locality"
},
  "geometry": {"coordinates":[-2.47571,42.85772],"type":"Point"}
}