{
  "type": "Feature",
  "properties": {
    "gn:admin1_code":"55",
    "gn:admin2_code":"AV",
    "gn:admin3_code":"05027",
    "gn:asciiname":"El Burgo",
    "gn:country_code":"ES",
    "gn:dem":942,
    "gn:feature_class":"P",
    "gn:feature_code":"PPL",
    "gn:name":"El Burgo",
    "gn:population":0,
    "gn:timezone":"Europe/Madrid",
    "iso:country":"ES",
    "wof:name":"El Burgo",
    "wof:placetype":"locality"
},
  "geometry": {"coordinates":[-4.76335,40.80491],"type":"Point"}
}