{
  "type": "Feature",
  "properties": {
    "gn:admin1_code":"55",
    "gn:admin2_code":"AV",
    "gn:admin3_code":"05027",
    "gn:asciiname":"El Burgo",
    "gn:country_code":"ES",
    "gn:dem":942,
    "gn:feature_class":"P",
    "gn:feature_code":"PPL",
    "gn:name":"El Burgo",
    "gn:population":0,
    "gn:timezone":"Europe/Madrid",
    "iso:country":"ES",
    "name:ara_x_preferred":[
        "\u0625\u0644 \u0628\u0648\u0631\u063a\u0648"
    ],
    "name:ast_x_preferred":[
        "El Burgo"
    ],
    "name:bul_x_preferred":[
        "\u0415\u043b \u0411\u0443\u0440\u0433\u043e"
    ],
    "name:cat_x_preferred":[
        "El Burgo"
    ],
    "name:epo_x_preferred":[
        "El Burgo"
    ],
    "name:eus_x_preferred":[
        "El Burgo"
    ],
    "name:fra_x_preferred":[
        "El Burgo"
    ],
    "name:hat_x_preferred":[
        "El Burgo"
    ],
    "name:hun_x_preferred":[
        "El Burgo"
    ],
    "name:hye_x_preferred":[
        "\u0537\u056c \u0532\u0578\u0582\u0580\u0563\u0578"
    ],
    "name:ita_x_preferred":[
        "El Burgo"
    ],
    "name:kaz_x_preferred":[
        "\u042d\u043b\u044c-\u0411\u0443\u0440\u0433\u043e"
    ],
    "name:kon_x_preferred":[
        "El Burgo"
    ],
    "name:msa_x_preferred":[
        "El Burgo"
    ],
    "name:nld_x_preferred":[
        "El Burgo"
    ],
    "name:oci_x_preferred":[
        "El Burgo"
    ],
    "name:pol_x_preferred":[
        "El Burgo"
    ],
    "name:por_x_preferred":[
        "El Burgo"
    ],
    "name:rus_x_preferred":[
        "\u042d\u043b\u044c-\u0411\u0443\u0440\u0433\u043e"
    ],
    "name:spa_x_preferred":[
        "El Burgo"
    ],
    "name:ukr_x_preferred":[
        "\u0415\u043b\u044c-\u0411\u0443\u0440\u0433\u043e"
    ],
    "name:uzb_x_preferred":[
        "El Burgo"
    ],
    "name:vie_x_preferred":[
        "El Burgo"
    ],
    "name:war_x_preferred":[
        "El Burgo"
    ],
    "name:zho_x_preferred":[
        "\u57c3\u5c14\u6b66\u5c14\u6208"
    ],
    "wof:name":"El Burgo",
    "wof:placetype":"locality"
},
  "geometry": {"coordinates":[-4.76335,40.80491],"type":"Point"}
}