{
  "type": "Feature",
  "properties": {
    "gn:gn_country":"ES",
    "gn:gn_fcode":"PPLA3",
    "gn:gn_pop":0,
    "iso:country":"ES",
    "name:arg_x_preferred":[
        "Requejo de Sanabria"
    ],
    "name:cat_x_preferred":[
        "Requejo"
    ],
    "name:eng_x_preferred":[
        "Requejo"
    ],
    "name:eus_x_preferred":[
        "Requejo"
    ],
    "name:fra_x_preferred":[
        "Requejo"
    ],
    "name:glg_x_preferred":[
        "Requeixo de Seabra"
    ],
    "name:haw_x_preferred":[
        "Requejo"
    ],
    "name:hun_x_preferred":[
        "Requejo"
    ],
    "name:ile_x_preferred":[
        "Requejo"
    ],
    "name:ina_x_preferred":[
        "Requejo de Sanabria"
    ],
    "name:ita_x_preferred":[
        "Requejo"
    ],
    "name:msa_x_preferred":[
        "Requejo"
    ],
    "name:nan_x_preferred":[
        "Requejo"
    ],
    "name:nld_x_preferred":[
        "Requejo"
    ],
    "name:oci_x_preferred":[
        "Requejo"
    ],
    "name:pol_x_preferred":[
        "Requejo"
    ],
    "name:por_x_preferred":[
        "Requejo"
    ],
    "name:rus_x_preferred":[
        "\u0420\u0435\u043a\u0435\u0445\u043e"
    ],
    "name:spa_x_preferred":[
        "Requejo de Sanabria"
    ],
    "name:swe_x_preferred":[
        "Requejo"
    ],
    "name:ukr_x_preferred":[
        "\u0420\u0435\u043a\u0435\u0445\u043e"
    ],
    "name:uzb_x_preferred":[
        "Requejo"
    ],
    "name:vie_x_preferred":[
        "Requejo"
    ],
    "name:war_x_preferred":[
        "Requejo"
    ],
    "name:zho_x_preferred":[
        "\u96f7\u514b\u970d"
    ],
    "qs_pg:aaroncc":"ES",
    "qs_pg:gn_country":"ES",
    "qs_pg:gn_fcode":"PPLA3",
    "qs_pg:gn_pop":0,
    "qs_pg:name":"Requejo",
    "qs_pg:name_adm0":"Espa\u00f1a",
    "qs_pg:name_adm1":"Castilla y Le\u00f3n",
    "qs_pg:photos":48,
    "qs_pg:photos_1k":10,
    "qs_pg:photos_9k":1,
    "qs_pg:photos_9r":2,
    "qs_pg:photos_all":48,
    "qs_pg:photos_sr":2,
    "qs_pg:pop_sr":0,
    "qs_pg:qs_pg_placetype":"locality",
    "qs_pg:qs_pg_placetype_gp":"Town",
    "qs_pg:woe_adm0":23424950,
    "woe:adm0_id":23424950,
    "woe:name_adm0":"Espa\u00f1a",
    "woe:name_adm1":"Castilla y Le\u00f3n",
    "woe:placetype":"Town",
    "wof:name":"Requejo",
    "wof:placetype":"locality"
},
  "geometry": {"coordinates":[-6.74227,42.03044],"type":"Point"}
}