{
  "type": "Feature",
  "properties": {
    "gn:admin1_code":"34",
    "gn:admin2_code":"O",
    "gn:admin3_code":"33034",
    "gn:asciiname":"Sineriz",
    "gn:country_code":"ES",
    "gn:dem":435,
    "gn:feature_class":"P",
    "gn:feature_code":"PPL",
    "gn:name":"Si\u00f1eriz",
    "gn:population":0,
    "gn:timezone":"Europe/Madrid",
    "iso:country":"ES",
    "name:und_x_variant":[
        "Si\u00f1eriz"
    ],
    "wof:name":"Sineriz",
    "wof:placetype":"locality"
},
  "geometry": {"coordinates":[-6.63819,43.4526],"type":"Point"}
}