{
  "type": "Feature",
  "properties": {
    "gn:admin1_code":"52",
    "gn:admin2_code":"HU",
    "gn:admin3_code":"22109",
    "gn:asciiname":"Semolue",
    "gn:country_code":"ES",
    "gn:dem":1219,
    "gn:feature_class":"P",
    "gn:feature_code":"PPL",
    "gn:name":"Semolu\u00e9",
    "gn:population":0,
    "gn:timezone":"Europe/Madrid",
    "iso:country":"ES",
    "wof:name":"Semolue",
    "wof:placetype":"locality"
},
  "geometry": {"coordinates":[-0.04994,42.5193],"type":"Point"}
}