{
  "type": "Feature",
  "properties": {
    "gn:admin1_code":"54",
    "gn:admin2_code":"AB",
    "gn:admin3_code":"02051",
    "gn:asciiname":"Casa de los Catalinorros",
    "gn:country_code":"ES",
    "gn:dem":869,
    "gn:feature_class":"P",
    "gn:feature_code":"PPL",
    "gn:name":"Casa de los Catalinorros",
    "gn:population":0,
    "gn:timezone":"Europe/Madrid",
    "iso:country":"ES",
    "wof:name":"Casa de los Catalinorros",
    "wof:placetype":"locality"
},
  "geometry": {"coordinates":[-1.34966,38.74317],"type":"Point"}
}