{
  "type": "Feature",
  "properties": {
    "gn:admin1_code":"58",
    "gn:admin2_code":"LU",
    "gn:admin3_code":"27012",
    "gn:asciiname":"Villarnovo",
    "gn:country_code":"ES",
    "gn:dem":720,
    "gn:feature_class":"P",
    "gn:feature_code":"PPL",
    "gn:name":"Villarnovo",
    "gn:population":0,
    "gn:timezone":"Europe/Madrid",
    "iso:country":"ES",
    "wof:name":"Villarnovo",
    "wof:placetype":"locality"
},
  "geometry": {"coordinates":[-6.97177,42.89704],"type":"Point"}
}