{
  "type": "Feature",
  "properties": {
    "gn:admin1_code":"55",
    "gn:admin2_code":"BU",
    "gn:admin3_code":"09213",
    "gn:asciiname":"Almendres",
    "gn:country_code":"ES",
    "gn:dem":720,
    "gn:feature_class":"P",
    "gn:feature_code":"PPL",
    "gn:name":"Almendres",
    "gn:population":0,
    "gn:timezone":"Europe/Madrid",
    "iso:country":"ES",
    "wof:name":"Almendres",
    "wof:placetype":"locality"
},
  "geometry": {"coordinates":[-3.41365,42.89222],"type":"Point"}
}