{
  "type": "Feature",
  "properties": {
    "gn:admin1_code":"58",
    "gn:admin2_code":"LU",
    "gn:admin3_code":"27018",
    "gn:asciiname":"Xestoso dos Calvos",
    "gn:country_code":"ES",
    "gn:dem":597,
    "gn:feature_class":"P",
    "gn:feature_code":"PPL",
    "gn:name":"Xestoso dos Calvos",
    "gn:population":0,
    "gn:timezone":"Europe/Madrid",
    "iso:country":"ES",
    "wof:name":"Xestoso dos Calvos",
    "wof:placetype":"locality"
},
  "geometry": {"coordinates":[-7.05,43.16667],"type":"Point"}
}