{
  "type": "Feature",
  "properties": {
    "gn:admin1_code":"58",
    "gn:admin2_code":"PO",
    "gn:admin3_code":"36052",
    "gn:asciiname":"Abades",
    "gn:country_code":"ES",
    "gn:dem":236,
    "gn:feature_class":"P",
    "gn:feature_code":"PPL",
    "gn:name":"Abades",
    "gn:population":0,
    "gn:timezone":"Europe/Madrid",
    "iso:country":"ES",
    "name:arg_x_preferred":[
        "Abades"
    ],
    "name:cat_x_preferred":[
        "Abades"
    ],
    "name:ceb_x_preferred":[
        "Abades"
    ],
    "name:deu_x_preferred":[
        "Abades"
    ],
    "name:eus_x_preferred":[
        "Abades"
    ],
    "name:fas_x_preferred":[
        "\u0622\u0628\u0627\u062f\u0633"
    ],
    "name:fra_x_preferred":[
        "Abades"
    ],
    "name:hun_x_preferred":[
        "Abades"
    ],
    "name:ina_x_preferred":[
        "Abades"
    ],
    "name:ita_x_preferred":[
        "Abades"
    ],
    "name:msa_x_preferred":[
        "Abades"
    ],
    "name:nld_x_preferred":[
        "Abades"
    ],
    "name:oci_x_preferred":[
        "Abades"
    ],
    "name:pol_x_preferred":[
        "Abades"
    ],
    "name:por_x_preferred":[
        "Abades"
    ],
    "name:rus_x_preferred":[
        "\u0410\u0431\u0430\u0434\u0435\u0441"
    ],
    "name:spa_x_preferred":[
        "Abades"
    ],
    "name:swe_x_preferred":[
        "Abades"
    ],
    "name:ukr_x_preferred":[
        "\u0410\u0431\u0430\u0434\u0435\u0441"
    ],
    "name:vie_x_preferred":[
        "Abades"
    ],
    "name:war_x_preferred":[
        "Abades"
    ],
    "name:zho_x_preferred":[
        "\u963f\u74e6\u5fb7\u65af"
    ],
    "wof:name":"Abades",
    "wof:placetype":"locality"
},
  "geometry": {"coordinates":[-8.30455,42.74884],"type":"Point"}
}