{
  "type": "Feature",
  "properties": {
    "gn:admin1_code":"54",
    "gn:admin2_code":"CU",
    "gn:admin3_code":"16078",
    "gn:asciiname":"Embid",
    "gn:cc2":"ES",
    "gn:country_code":"ES",
    "gn:dem":946,
    "gn:feature_class":"P",
    "gn:feature_code":"PPL",
    "gn:name":"Embid",
    "gn:population":0,
    "gn:timezone":"Europe/Madrid",
    "iso:country":"ES",
    "name:und_x_variant":[
        "Caser\u00edo Embid",
        "Embid"
    ],
    "wof:name":"Embid",
    "wof:placetype":"locality"
},
  "geometry": {"coordinates":[-2.13333,40.13333],"type":"Point"}
}