{
  "type": "Feature",
  "properties": {
    "gn:admin1_code":"54",
    "gn:admin2_code":"CU",
    "gn:admin3_code":"16078",
    "gn:asciiname":"Embid",
    "gn:cc2":"ES",
    "gn:country_code":"ES",
    "gn:dem":946,
    "gn:feature_class":"P",
    "gn:feature_code":"PPL",
    "gn:name":"Embid",
    "gn:population":0,
    "gn:timezone":"Europe/Madrid",
    "iso:country":"ES",
    "name:arg_x_preferred":[
        "Embit"
    ],
    "name:ast_x_preferred":[
        "Embid"
    ],
    "name:cat_x_preferred":[
        "Embid"
    ],
    "name:ceb_x_preferred":[
        "Embid"
    ],
    "name:epo_x_preferred":[
        "Embid"
    ],
    "name:eus_x_preferred":[
        "Embid"
    ],
    "name:fra_x_preferred":[
        "Embid"
    ],
    "name:hun_x_preferred":[
        "Embid"
    ],
    "name:ina_x_preferred":[
        "Embid"
    ],
    "name:ita_x_preferred":[
        "Embid"
    ],
    "name:kaz_x_preferred":[
        "\u042d\u043c\u0431\u0438\u0434"
    ],
    "name:msa_x_preferred":[
        "Embid"
    ],
    "name:nld_x_preferred":[
        "Embid"
    ],
    "name:oci_x_preferred":[
        "Embid"
    ],
    "name:pol_x_preferred":[
        "Embid"
    ],
    "name:por_x_preferred":[
        "Embid"
    ],
    "name:rus_x_preferred":[
        "\u042d\u043c\u0431\u0438\u0434"
    ],
    "name:spa_x_preferred":[
        "Embid"
    ],
    "name:swe_x_preferred":[
        "Embid"
    ],
    "name:ukr_x_preferred":[
        "\u0415\u043c\u0431\u0456\u0434"
    ],
    "name:und_x_variant":[
        "Caser\u00edo Embid",
        "Embid"
    ],
    "name:vie_x_preferred":[
        "Embid"
    ],
    "name:war_x_preferred":[
        "Embid"
    ],
    "name:zho_x_preferred":[
        "\u6069\u7ef4\u5fb7"
    ],
    "wof:name":"Embid",
    "wof:placetype":"locality"
},
  "geometry": {"coordinates":[-2.13333,40.13333],"type":"Point"}
}