{
  "type": "Feature",
  "properties": {
    "gn:gn_country":"ES",
    "gn:gn_fcode":"PPLA3",
    "gn:gn_pop":50,
    "gn:population":50,
    "iso:country":"ES",
    "name:arg_x_preferred":[
        "Villabaruz de Campos"
    ],
    "name:azb_x_preferred":[
        "\u0628\u06cc\u06cc\u0627\u0628\u0627\u0631\u0648\u0633 \u062f \u06a9\u0627\u0645\u067e\u0633"
    ],
    "name:cat_x_preferred":[
        "Villabaruz de Campos"
    ],
    "name:deu_x_preferred":[
        "Villabaruz de Campos"
    ],
    "name:eng_x_preferred":[
        "Villabaruz de Campos"
    ],
    "name:eus_x_preferred":[
        "Villabaruz de Campos"
    ],
    "name:fas_x_preferred":[
        "\u0628\u06cc\u06cc\u0627\u0628\u0627\u0631\u0648\u0633 \u062f \u06a9\u0627\u0645\u067e\u0633"
    ],
    "name:fra_x_preferred":[
        "Villabaruz de Campos"
    ],
    "name:hun_x_preferred":[
        "Villabaruz de Campos"
    ],
    "name:hye_x_preferred":[
        "\u054e\u056b\u056c\u0575\u0561\u0562\u0561\u0580\u0578\u0582\u057d \u0564\u0565 \u053f\u0561\u0574\u057a\u0578\u057d"
    ],
    "name:ina_x_preferred":[
        "Villabaruz de Campos"
    ],
    "name:ita_x_preferred":[
        "Villabaruz de Campos"
    ],
    "name:msa_x_preferred":[
        "Villabaruz de Campos"
    ],
    "name:nan_x_preferred":[
        "Villabaruz de Campos"
    ],
    "name:nld_x_preferred":[
        "Villabaruz de Campos"
    ],
    "name:oci_x_preferred":[
        "Villabaruz de Campos"
    ],
    "name:pol_x_preferred":[
        "Villabaruz de Campos"
    ],
    "name:por_x_preferred":[
        "Villabaruz de Campos"
    ],
    "name:rus_x_preferred":[
        "\u0412\u0438\u043b\u044c\u044f\u0431\u0430\u0440\u0443\u0441-\u0434\u0435-\u041a\u0430\u043c\u043f\u043e\u0441"
    ],
    "name:spa_x_preferred":[
        "Villabaruz de Campos"
    ],
    "name:swe_x_preferred":[
        "Villabaruz de Campos"
    ],
    "name:ukr_x_preferred":[
        "\u0412\u0456\u043b\u044c\u044f\u0431\u0430\u0440\u0443\u0441-\u0434\u0435-\u041a\u0430\u043c\u043f\u043e\u0441"
    ],
    "name:unk_x_variant":[
        "Villabaruz"
    ],
    "name:vie_x_preferred":[
        "Villabaruz de Campos"
    ],
    "name:war_x_preferred":[
        "Villabaruz de Campos"
    ],
    "name:zho_x_preferred":[
        "\u6bd4\u5229\u4e9a\u74e6\u9c81\u65af\u5fb7\u574e\u6ce2\u65af"
    ],
    "qs_pg:aaroncc":"ES",
    "qs_pg:gn_country":"ES",
    "qs_pg:gn_fcode":"PPLA3",
    "qs_pg:gn_pop":50,
    "qs_pg:name":"Villabaruz de Campos",
    "qs_pg:name_adm0":"Espa\u00f1a",
    "qs_pg:name_adm1":"Castilla y Le\u00f3n",
    "qs_pg:photos_9r":0,
    "qs_pg:photos_sr":0,
    "qs_pg:pop_sr":1,
    "qs_pg:qs_pg_placetype":"locality",
    "qs_pg:qs_pg_placetype_gp":"Town",
    "qs_pg:woe_adm0":23424950,
    "woe:adm0_id":23424950,
    "woe:name_adm0":"Espa\u00f1a",
    "woe:name_adm1":"Castilla y Le\u00f3n",
    "woe:placetype":"Town",
    "wof:name":"Villabaruz de Campos",
    "wof:placetype":"locality",
    "wof:population":50
},
  "geometry": {"coordinates":[-4.99624,42.01099],"type":"Point"}
}