{
  "type": "Feature",
  "properties": {
    "gn:admin1_code":"55",
    "gn:admin2_code":"BU",
    "gn:admin3_code":"09272",
    "gn:asciiname":"Lences",
    "gn:country_code":"ES",
    "gn:dem":667,
    "gn:feature_class":"P",
    "gn:feature_code":"PPL",
    "gn:name":"Lences",
    "gn:population":0,
    "gn:timezone":"Europe/Madrid",
    "iso:country":"ES",
    "wof:name":"Lences",
    "wof:placetype":"locality"
},
  "geometry": {"coordinates":[-3.49144,42.63105],"type":"Point"}
}