{
  "type": "Feature",
  "properties": {
    "gn:admin1_code":"34",
    "gn:admin2_code":"O",
    "gn:admin3_code":"33034",
    "gn:asciiname":"Ferrera de los Gabitos",
    "gn:country_code":"ES",
    "gn:dem":227,
    "gn:feature_class":"P",
    "gn:feature_code":"PPL",
    "gn:name":"Ferrera de los Gabitos",
    "gn:population":0,
    "gn:timezone":"Europe/Madrid",
    "iso:country":"ES",
    "wof:name":"Ferrera de los Gabitos",
    "wof:placetype":"locality"
},
  "geometry": {"coordinates":[-6.36936,43.47907],"type":"Point"}
}