{
  "type": "Feature",
  "properties": {
    "gn:admin1_code":"34",
    "gn:admin2_code":"O",
    "gn:admin3_code":"33041",
    "gn:asciiname":"Salcedo",
    "gn:country_code":"ES",
    "gn:dem":70,
    "gn:feature_class":"P",
    "gn:feature_code":"PPL",
    "gn:name":"Salcedo",
    "gn:population":0,
    "gn:timezone":"Europe/Madrid",
    "iso:country":"ES",
    "name:bel_x_preferred":[
        "\u0421\u0430\u043b\u044c\u0447\u044d\u0434\u0430"
    ],
    "name:cat_x_preferred":[
        "Salcedo"
    ],
    "name:ceb_x_preferred":[
        "Salcedo"
    ],
    "name:deu_x_preferred":[
        "Salcedo"
    ],
    "name:eus_x_preferred":[
        "Salcedo"
    ],
    "name:fra_x_preferred":[
        "Salcedo"
    ],
    "name:glg_x_preferred":[
        "Salcedo"
    ],
    "name:heb_x_preferred":[
        "\u05e1\u05dc\u05e1\u05d3\u05d5"
    ],
    "name:ilo_x_preferred":[
        "Salcedo"
    ],
    "name:ita_x_preferred":[
        "Salcedo"
    ],
    "name:nld_x_preferred":[
        "Salcedo"
    ],
    "name:pms_x_preferred":[
        "Salcedo"
    ],
    "name:pol_x_preferred":[
        "Salcedo"
    ],
    "name:por_x_preferred":[
        "Salcedo"
    ],
    "name:rus_x_preferred":[
        "\u0421\u0430\u043b\u044c\u0441\u0435\u0434\u043e"
    ],
    "name:spa_x_preferred":[
        "Salcedo"
    ],
    "name:swe_x_preferred":[
        "Salcedo"
    ],
    "name:war_x_preferred":[
        "Salcedo"
    ],
    "wof:name":"Salcedo",
    "wof:placetype":"locality"
},
  "geometry": {"coordinates":[-6.70404,43.53037],"type":"Point"}
}