{
  "type": "Feature",
  "properties": {
    "gn:gn_country":"ES",
    "gn:gn_fcode":"PPLA3",
    "gn:gn_pop":192,
    "gn:population":192,
    "iso:country":"ES",
    "name:ara_x_preferred":[
        "\u0644\u064a\u062a\u0627\u063a\u0648"
    ],
    "name:arg_x_preferred":[
        "Litago"
    ],
    "name:azb_x_preferred":[
        "\u0644\u06cc\u062a\u0627\u0642\u0648"
    ],
    "name:cat_x_preferred":[
        "Litago"
    ],
    "name:ceb_x_preferred":[
        "Litago"
    ],
    "name:deu_x_preferred":[
        "Litago"
    ],
    "name:eng_x_preferred":[
        "Litago"
    ],
    "name:eus_x_preferred":[
        "Litago"
    ],
    "name:fas_x_preferred":[
        "\u0644\u06cc\u062a\u0627\u06af\u0648"
    ],
    "name:fra_x_preferred":[
        "Litago"
    ],
    "name:glg_x_preferred":[
        "Litago"
    ],
    "name:hun_x_preferred":[
        "Litago"
    ],
    "name:ita_x_preferred":[
        "Litago"
    ],
    "name:kaz_x_preferred":[
        "\u041b\u0438\u0442\u0430\u0433\u043e"
    ],
    "name:msa_x_preferred":[
        "Litago"
    ],
    "name:nan_x_preferred":[
        "Litago"
    ],
    "name:nld_x_preferred":[
        "Litago"
    ],
    "name:oci_x_preferred":[
        "Litago"
    ],
    "name:pol_x_preferred":[
        "Litago"
    ],
    "name:por_x_preferred":[
        "Litago"
    ],
    "name:rus_x_preferred":[
        "\u041b\u0438\u0442\u0430\u0433\u043e"
    ],
    "name:spa_x_preferred":[
        "Litago"
    ],
    "name:swe_x_preferred":[
        "Litago"
    ],
    "name:ukr_x_preferred":[
        "\u041b\u0456\u0442\u0430\u0433\u043e"
    ],
    "name:uzb_x_preferred":[
        "Litago"
    ],
    "name:vie_x_preferred":[
        "Litago"
    ],
    "name:war_x_preferred":[
        "Litago"
    ],
    "name:zho_x_preferred":[
        "\u5229\u5854\u6208"
    ],
    "qs_pg:aaroncc":"ES",
    "qs_pg:gn_country":"ES",
    "qs_pg:gn_fcode":"PPLA3",
    "qs_pg:gn_pop":192,
    "qs_pg:name":"Litago",
    "qs_pg:name_adm0":"Espa\u00f1a",
    "qs_pg:name_adm1":"Arag\u00f3n",
    "qs_pg:photos_9k":1,
    "qs_pg:photos_9r":1,
    "qs_pg:photos_all":1,
    "qs_pg:photos_sr":0,
    "qs_pg:pop_sr":1,
    "qs_pg:qs_pg_placetype":"locality",
    "qs_pg:qs_pg_placetype_gp":"Town",
    "qs_pg:woe_adm0":23424950,
    "woe:adm0_id":23424950,
    "woe:name_adm0":"Espa\u00f1a",
    "woe:name_adm1":"Arag\u00f3n",
    "woe:placetype":"Town",
    "wof:name":"Litago",
    "wof:placetype":"locality",
    "wof:population":192
},
  "geometry": {"coordinates":[-1.75276,41.81407],"type":"Point"}
}