{
  "type": "Feature",
  "properties": {
    "iso:country":"ES",
    "name:spa_x_preferred":[
        "Trobajo del Camino"
    ],
    "qs:a0":"Espa\u00f1a",
    "qs:a1":"*Le\u00f3n",
    "qs:a1r":"0Castilla y Le\u00f3n",
    "qs:adm0":"Espa\u00f1a",
    "qs:la_lc":"*",
    "qs:level":"locality",
    "qs:loc":"Trobajo del Camino",
    "qs:loc_alt":"Trobajo del Camino",
    "qs:pop":0,
    "qs:type":"buffered point",
    "wof:lang":[
        "spa"
    ],
    "wof:name":"Trobajo del Camino",
    "wof:placetype":"locality"
},
  "geometry": {"coordinates":[-5.607176,42.615734],"type":"Point"}
}