{
  "type": "Feature",
  "properties": {
    "gn:admin1_code":"52",
    "gn:admin2_code":"TE",
    "gn:admin3_code":"44017",
    "gn:asciiname":"Masias Santilla",
    "gn:cc2":"ES",
    "gn:country_code":"ES",
    "gn:dem":1442,
    "gn:feature_class":"P",
    "gn:feature_code":"PPL",
    "gn:name":"Mas\u00edas Santilla",
    "gn:population":0,
    "gn:timezone":"Europe/Madrid",
    "iso:country":"ES",
    "name:und_x_variant":[
        "Santilla",
        "Mas\u00edas Santilla"
    ],
    "wof:name":"Masias Santilla",
    "wof:placetype":"locality"
},
  "geometry": {"coordinates":[-0.65,40.56667],"type":"Point"}
}