{
  "type": "Feature",
  "properties": {
    "gn:admin1_code":"58",
    "gn:admin2_code":"LU",
    "gn:admin3_code":"27009",
    "gn:asciiname":"Bucinos",
    "gn:cc2":"ES",
    "gn:country_code":"ES",
    "gn:dem":636,
    "gn:feature_class":"P",
    "gn:feature_code":"PPL",
    "gn:name":"Buci\u00f1os",
    "gn:population":0,
    "gn:timezone":"Europe/Madrid",
    "iso:country":"ES",
    "name:und_x_variant":[
        "San Miguel",
        "Buei\u00f1os",
        "Buci\u00f1os"
    ],
    "wof:name":"Bucinos",
    "wof:placetype":"locality"
},
  "geometry": {"coordinates":[-7.85,42.53333],"type":"Point"}
}