{
  "type": "Feature",
  "properties": {
    "gn:gn_country":"ES",
    "gn:gn_fcode":"ADM3",
    "gn:gn_pop":2975,
    "gn:population":2879,
    "iso:country":"ES",
    "name:ara_x_preferred":[
        "\u0645\u064a\u0632\u064a\u0627"
    ],
    "name:bre_x_preferred":[
        "Mes\u00eda"
    ],
    "name:cat_x_preferred":[
        "Mes\u00eda"
    ],
    "name:deu_x_preferred":[
        "Mes\u00eda"
    ],
    "name:eng_x_preferred":[
        "Mes\u00eda"
    ],
    "name:eus_x_preferred":[
        "Mes\u00eda"
    ],
    "name:fra_x_preferred":[
        "Mes\u00eda"
    ],
    "name:glg_x_preferred":[
        "Mes\u00eda"
    ],
    "name:hun_x_preferred":[
        "Mes\u00eda"
    ],
    "name:ita_x_preferred":[
        "Mes\u00eda"
    ],
    "name:jpn_x_preferred":[
        "\u30e1\u30b7\u30fc\u30a2"
    ],
    "name:lmo_x_preferred":[
        "Mes\u00eda"
    ],
    "name:mkd_x_preferred":[
        "\u041c\u0435\u0441\u0438\u0430"
    ],
    "name:msa_x_preferred":[
        "Mes\u00eda"
    ],
    "name:nan_x_preferred":[
        "Mes\u00eda"
    ],
    "name:nld_x_preferred":[
        "Mes\u00eda"
    ],
    "name:oci_x_preferred":[
        "Mes\u00eda"
    ],
    "name:pol_x_preferred":[
        "Mes\u00eda"
    ],
    "name:por_x_preferred":[
        "Mes\u00eda"
    ],
    "name:rup_x_preferred":[
        "Mes\u00eda"
    ],
    "name:rus_x_preferred":[
        "\u041c\u0435\u0441\u0438\u0430"
    ],
    "name:spa_x_preferred":[
        "Mes\u00eda"
    ],
    "name:swe_x_preferred":[
        "Mesia"
    ],
    "name:tur_x_preferred":[
        "Mes\u00eda"
    ],
    "name:ukr_x_preferred":[
        "\u041c\u0435\u0441\u0456\u044f"
    ],
    "name:uzb_x_preferred":[
        "Mes\u00eda"
    ],
    "name:vie_x_preferred":[
        "Mes\u00eda"
    ],
    "name:war_x_preferred":[
        "Mes\u00eda"
    ],
    "name:zho_x_preferred":[
        "\u6885\u897f\u4e9a"
    ],
    "qs_pg:aaroncc":"ES",
    "qs_pg:gn_country":"ES",
    "qs_pg:gn_fcode":"ADM3",
    "qs_pg:gn_pop":2975,
    "qs_pg:name":"Mes\u00eda",
    "qs_pg:name_adm0":"Espa\u00f1a",
    "qs_pg:name_adm1":"Galicia",
    "qs_pg:photos":12,
    "qs_pg:photos_1k":2,
    "qs_pg:photos_9k":1,
    "qs_pg:photos_9r":1,
    "qs_pg:photos_all":12,
    "qs_pg:photos_sr":1,
    "qs_pg:pop_sr":4,
    "qs_pg:qs_pg_placetype":"locality",
    "qs_pg:qs_pg_placetype_gp":"Town",
    "qs_pg:woe_adm0":23424950,
    "woe:adm0_id":23424950,
    "woe:name_adm0":"Espa\u00f1a",
    "woe:name_adm1":"Galicia",
    "woe:placetype":"Town",
    "wof:name":"Mes\u00eda",
    "wof:placetype":"locality",
    "wof:population":2879
},
  "geometry": {"coordinates":[-8.24478,43.08964],"type":"Point"}
}