{
  "type": "Feature",
  "properties": {
    "gn:admin1_code":"55",
    "gn:admin2_code":"BU",
    "gn:admin3_code":"09415",
    "gn:asciiname":"Pedrosa de Valdelucio",
    "gn:country_code":"ES",
    "gn:dem":954,
    "gn:feature_class":"P",
    "gn:feature_code":"PPL",
    "gn:name":"Pedrosa de Valdelucio",
    "gn:population":0,
    "gn:timezone":"Europe/Madrid",
    "iso:country":"ES",
    "name:und_x_variant":[
        "Pedrosa de Arcellares",
        "Pedrosa de Valdelucio"
    ],
    "wof:name":"Pedrosa de Valdelucio",
    "wof:placetype":"locality"
},
  "geometry": {"coordinates":[-4.03208,42.72065],"type":"Point"}
}