{
  "type": "Feature",
  "properties": {
    "gn:admin1_code":"58",
    "gn:admin2_code":"OR",
    "gn:admin3_code":"32081",
    "gn:asciiname":"Trelle",
    "gn:country_code":"ES",
    "gn:dem":460,
    "gn:feature_class":"P",
    "gn:feature_code":"PPL",
    "gn:name":"Trelle",
    "gn:population":0,
    "gn:timezone":"Europe/Madrid",
    "iso:country":"ES",
    "wof:name":"Trelle",
    "wof:placetype":"locality"
},
  "geometry": {"coordinates":[-7.95257,42.27802],"type":"Point"}
}