{
  "type": "Feature",
  "properties": {
    "gn:population":5670,
    "iso:country":"ES",
    "name:ara_x_preferred":[
        "\u062a\u0627\u062b\u0627\u0643\u0648\u0631\u062a\u064a"
    ],
    "name:arg_x_preferred":[
        "Tazacorte"
    ],
    "name:arz_x_preferred":[
        "\u062a\u0627\u062b\u0627\u0643\u0648\u0631\u062a\u0649"
    ],
    "name:ast_x_preferred":[
        "Tazacorte"
    ],
    "name:cat_x_preferred":[
        "Tazacorte"
    ],
    "name:ceb_x_preferred":[
        "Tazacorte"
    ],
    "name:che_x_preferred":[
        "\u0422\u0430\u0441\u0430\u043a\u043e\u0440\u0442\u0435"
    ],
    "name:deu_x_preferred":[
        "Tazacorte"
    ],
    "name:eng_x_preferred":[
        "Tazacorte"
    ],
    "name:eus_x_preferred":[
        "Tazacorte"
    ],
    "name:fra_x_preferred":[
        "Tazacorte"
    ],
    "name:frr_x_preferred":[
        "Tazacorte"
    ],
    "name:gle_x_preferred":[
        "Tazacorte"
    ],
    "name:glg_x_preferred":[
        "Tazacorte"
    ],
    "name:hun_x_preferred":[
        "Tazacorte"
    ],
    "name:ita_x_preferred":[
        "Tazacorte"
    ],
    "name:kat_x_preferred":[
        "\u10e2\u10d0\u10e1\u10d0\u10d9\u10dd\u10e0\u10e2\u10d4"
    ],
    "name:lat_x_preferred":[
        "Tazacorte"
    ],
    "name:lit_x_preferred":[
        "Tasakort\u0117"
    ],
    "name:lld_x_preferred":[
        "Tazacorte"
    ],
    "name:msa_x_preferred":[
        "Tazacorte"
    ],
    "name:nld_x_preferred":[
        "Tazacorte"
    ],
    "name:nob_x_preferred":[
        "Tazacorte"
    ],
    "name:oci_x_preferred":[
        "Tazacorte"
    ],
    "name:pol_x_preferred":[
        "Tazacorte"
    ],
    "name:por_x_preferred":[
        "Tazacorte"
    ],
    "name:rus_x_preferred":[
        "\u0422\u0430\u0441\u0430\u043a\u043e\u0440\u0442\u0435"
    ],
    "name:sco_x_preferred":[
        "Tazacorte"
    ],
    "name:spa_x_preferred":[
        "Tazacorte"
    ],
    "name:sqi_x_preferred":[
        "Tazacorte"
    ],
    "name:swe_x_preferred":[
        "Tazacorte"
    ],
    "name:tat_x_preferred":[
        "\u0422\u0430\u0441\u0430\u043a\u043e\u0440\u0442\u0435"
    ],
    "name:ukr_x_preferred":[
        "\u0422\u0430\u0441\u0430\u043a\u043e\u0440\u0442\u0435"
    ],
    "name:uzb_x_preferred":[
        "Tazacorte"
    ],
    "name:vec_x_preferred":[
        "Tazacorte"
    ],
    "name:war_x_preferred":[
        "Tazacorte"
    ],
    "name:zho_x_preferred":[
        "\u5854\u8428\u79d1\u5c14\u7279"
    ],
    "qs:a0":"Espa\u00f1a",
    "qs:a1":"*Santa Cruz de Tenerife",
    "qs:a1r":"0Canarias",
    "qs:adm0":"Espa\u00f1a",
    "qs:la_lc":"*",
    "qs:level":"locality",
    "qs:loc":"Tazacorte",
    "qs:loc_alt":"Tazacorte",
    "qs:pop":0,
    "qs:type":"buffered point",
    "wd:wordcount":172,
    "wof:lang":[
        "spa"
    ],
    "wof:name":"Tazacorte",
    "wof:placetype":"locality",
    "wof:population":5670
},
  "geometry": {"coordinates":[-17.934873,28.638756],"type":"Point"}
}