{
  "type": "Feature",
  "properties": {
    "gn:admin1_code":"55",
    "gn:admin2_code":"SA",
    "gn:admin3_code":"37065",
    "gn:asciiname":"Fuentes de Masueco",
    "gn:country_code":"ES",
    "gn:dem":679,
    "gn:feature_class":"P",
    "gn:feature_code":"PPL",
    "gn:name":"Fuentes de Masueco",
    "gn:population":0,
    "gn:timezone":"Europe/Madrid",
    "iso:country":"ES",
    "wof:name":"Fuentes de Masueco",
    "wof:placetype":"locality"
},
  "geometry": {"coordinates":[-6.55145,41.16459],"type":"Point"}
}