{
  "type": "Feature",
  "properties": {
    "gn:admin1_code":"58",
    "gn:admin2_code":"LU",
    "gn:admin3_code":"27058",
    "gn:asciiname":"Sobreda",
    "gn:country_code":"ES",
    "gn:dem":619,
    "gn:feature_class":"P",
    "gn:feature_code":"PPL",
    "gn:name":"Sobreda",
    "gn:population":0,
    "gn:timezone":"Europe/Madrid",
    "iso:country":"ES",
    "name:ceb_x_preferred":[
        "Sobreda"
    ],
    "name:deu_x_preferred":[
        "Sobreda"
    ],
    "name:ita_x_preferred":[
        "Sobreda"
    ],
    "name:kaz_x_preferred":[
        "\u0421\u043e\u0431\u0440\u0435\u0434\u0430"
    ],
    "name:msa_x_preferred":[
        "Sobreda"
    ],
    "name:nld_x_preferred":[
        "Sobreda"
    ],
    "name:pol_x_preferred":[
        "Sobreda"
    ],
    "name:por_x_preferred":[
        "Sobreda"
    ],
    "name:rus_x_preferred":[
        "\u0421\u043e\u0431\u0440\u0435\u0434\u0430"
    ],
    "name:spa_x_preferred":[
        "Sobreda"
    ],
    "name:tur_x_preferred":[
        "Sobreda"
    ],
    "wof:name":"Sobreda",
    "wof:placetype":"locality"
},
  "geometry": {"coordinates":[-7.59576,42.67007],"type":"Point"}
}