{
  "type": "Feature",
  "properties": {
    "gn:admin1_code":"56",
    "gn:admin2_code":"L",
    "gn:admin3_code":"25062",
    "gn:asciiname":"Xalets de la Solana",
    "gn:country_code":"ES",
    "gn:dem":250,
    "gn:feature_class":"P",
    "gn:feature_code":"PPL",
    "gn:name":"Xalets de la Solana",
    "gn:population":0,
    "gn:timezone":"Europe/Madrid",
    "iso:country":"ES",
    "wof:name":"Xalets de la Solana",
    "wof:placetype":"locality"
},
  "geometry": {"coordinates":[0.83187,41.861],"type":"Point"}
}