{
  "type": "Feature",
  "properties": {
    "gn:gn_country":"ES",
    "gn:gn_fcode":"PPLA3",
    "gn:gn_pop":53,
    "gn:population":53,
    "iso:country":"ES",
    "name:ara_x_preferred":[
        "\u0627\u0644\u0643\u0648\u0643\u064a\u0631\u0648 \u062f\u064a \u0645\u0648\u0644\u0627"
    ],
    "name:arg_x_preferred":[
        "Alcocero de Mola"
    ],
    "name:baq_x_preferred":[
        "Alcocero de Mola"
    ],
    "name:cat_x_preferred":[
        "Alcocero de Mola"
    ],
    "name:chi_x_preferred":[
        "\u963f\u5c14\u79d1\u585e\u7f57\u5fb7\u83ab\u62c9"
    ],
    "name:dut_x_preferred":[
        "Alcocero de Mola"
    ],
    "name:eng_x_preferred":[
        "Alcocero de Mola"
    ],
    "name:fre_x_preferred":[
        "Alcocero de Mola"
    ],
    "name:ger_x_preferred":[
        "Alcocero de Mola"
    ],
    "name:glg_x_preferred":[
        "Alcocero de Mola"
    ],
    "name:haw_x_preferred":[
        "Alcocero de Mola"
    ],
    "name:hun_x_preferred":[
        "Alcocero de Mola"
    ],
    "name:ina_x_preferred":[
        "Alcocero de Mola"
    ],
    "name:ita_x_preferred":[
        "Alcocero de Mola"
    ],
    "name:lad_x_preferred":[
        "Alcocero de Mola"
    ],
    "name:may_x_preferred":[
        "Alcocero de Mola"
    ],
    "name:nan_x_preferred":[
        "Alcocero de Mola"
    ],
    "name:oci_x_preferred":[
        "Alcocero de Mola"
    ],
    "name:pam_x_preferred":[
        "Alcocero de Mola"
    ],
    "name:per_x_preferred":[
        "\u0622\u0644\u06a9\u0633\u0631\u0648 \u062f \u0645\u0644\u0627"
    ],
    "name:pol_x_preferred":[
        "Alcocero de Mola"
    ],
    "name:por_x_preferred":[
        "Alcocero de Mola"
    ],
    "name:rus_x_preferred":[
        "\u0410\u043b\u044c\u043a\u043e\u0441\u0435\u0440\u043e-\u0434\u0435-\u041c\u043e\u043b\u0430"
    ],
    "name:spa_x_preferred":[
        "Alcocero de Mola"
    ],
    "name:swe_x_preferred":[
        "Alcocero de Mola"
    ],
    "name:tah_x_preferred":[
        "Alcocero de Mola"
    ],
    "name:ukr_x_preferred":[
        "\u0410\u043b\u044c\u043a\u043e\u0441\u0435\u0440\u043e-\u0434\u0435-\u041c\u043e\u043b\u0430"
    ],
    "name:unk_x_variant":[
        "Alcocero"
    ],
    "name:vie_x_preferred":[
        "Alcocero de Mola"
    ],
    "name:war_x_preferred":[
        "Alcocero de Mola"
    ],
    "qs_pg:aaroncc":"ES",
    "qs_pg:gn_country":"ES",
    "qs_pg:gn_fcode":"PPLA3",
    "qs_pg:gn_pop":53,
    "qs_pg:name":"Alcocero de Mola",
    "qs_pg:name_adm0":"Espa\u00f1a",
    "qs_pg:name_adm1":"Castilla y Le\u00f3n",
    "qs_pg:photos_9r":0,
    "qs_pg:photos_sr":0,
    "qs_pg:pop_sr":1,
    "qs_pg:qs_pg_placetype":"locality",
    "qs_pg:qs_pg_placetype_gp":"Town",
    "qs_pg:woe_adm0":23424950,
    "woe:adm0_id":23424950,
    "woe:name_adm0":"Espa\u00f1a",
    "woe:name_adm1":"Castilla y Le\u00f3n",
    "woe:placetype":"Town",
    "wof:name":"Alcocero de Mola",
    "wof:placetype":"locality",
    "wof:population":53
},
  "geometry": {"coordinates":[-3.3579,42.47222],"type":"Point"}
}