{
  "type": "Feature",
  "properties": {
    "gn:gn_country":"ES",
    "gn:gn_fcode":"PPLA3",
    "gn:gn_pop":44,
    "gn:population":44,
    "iso:country":"ES",
    "name:ara_x_preferred":[
        "\u0643\u0627\u0633\u062a\u064a\u0644\u064a\u062e\u0648-\u0633\u0627\u064a\u0631\u0627"
    ],
    "name:arg_x_preferred":[
        "Castillejo-Sierra"
    ],
    "name:cat_x_preferred":[
        "Castillejo-Sierra"
    ],
    "name:deu_x_preferred":[
        "Castillejo-Sierra"
    ],
    "name:eng_x_preferred":[
        "Castillejo-Sierra"
    ],
    "name:eus_x_preferred":[
        "Castillejo-Sierra"
    ],
    "name:fra_x_preferred":[
        "Castillejo-Sierra"
    ],
    "name:hun_x_preferred":[
        "Castillejo-Sierra"
    ],
    "name:ita_x_preferred":[
        "Castillejo-Sierra"
    ],
    "name:kaz_x_preferred":[
        "\u041a\u0430\u0441\u0442\u0438\u043b\u044c\u0435\u0445\u043e-\u0421\u044c\u0435\u0440\u0440\u0430"
    ],
    "name:msa_x_preferred":[
        "Castillejo-Sierra"
    ],
    "name:nan_x_preferred":[
        "Castillejo-Sierra"
    ],
    "name:nld_x_preferred":[
        "Castillejo-Sierra"
    ],
    "name:oci_x_preferred":[
        "Castillejo-Sierra"
    ],
    "name:pol_x_preferred":[
        "Castillejo-Sierra"
    ],
    "name:rus_x_preferred":[
        "\u041a\u0430\u0441\u0442\u0438\u043b\u044c\u0435\u0445\u043e-\u0421\u044c\u0435\u0440\u0440\u0430"
    ],
    "name:spa_x_preferred":[
        "Castillejo-Sierra"
    ],
    "name:swe_x_preferred":[
        "Castillejo-Sierra"
    ],
    "name:ukr_x_preferred":[
        "\u041a\u0430\u0441\u0442\u0456\u043b\u044c\u0454\u0445\u043e-\u0421\u044c\u0454\u0440\u0440\u0430"
    ],
    "name:vie_x_preferred":[
        "Castillejo-Sierra"
    ],
    "name:war_x_preferred":[
        "Castillejo-Sierra"
    ],
    "name:zho_x_preferred":[
        "\u5361\u65af\u8482\u5217\u970d-\u8c22\u62c9"
    ],
    "qs_pg:aaroncc":"ES",
    "qs_pg:gn_country":"ES",
    "qs_pg:gn_fcode":"PPLA3",
    "qs_pg:gn_pop":44,
    "qs_pg:name":"Castillejo-Sierra",
    "qs_pg:name_adm0":"Espa\u00f1a",
    "qs_pg:name_adm1":"Castilla-La Mancha",
    "qs_pg:photos_9k":1,
    "qs_pg:photos_9r":1,
    "qs_pg:photos_all":1,
    "qs_pg:photos_sr":0,
    "qs_pg:pop_sr":1,
    "qs_pg:qs_pg_placetype":"locality",
    "qs_pg:qs_pg_placetype_gp":"Town",
    "qs_pg:woe_adm0":23424950,
    "woe:adm0_id":23424950,
    "woe:name_adm0":"Espa\u00f1a",
    "woe:name_adm1":"Castilla-La Mancha",
    "woe:placetype":"Town",
    "wof:name":"Castillejo-Sierra",
    "wof:placetype":"locality",
    "wof:population":44
},
  "geometry": {"coordinates":[-2.1404,40.37477],"type":"Point"}
}