{
  "type": "Feature",
  "properties": {
    "gn:admin1_code":"59",
    "gn:admin2_code":"SS",
    "gn:admin3_code":"20038",
    "gn:asciiname":"Alegria",
    "gn:country_code":"ES",
    "gn:dem":208,
    "gn:feature_class":"P",
    "gn:feature_code":"PPL",
    "gn:name":"Alegia",
    "gn:population":0,
    "gn:timezone":"Europe/Madrid",
    "iso:country":"ES",
    "name:bul_x_preferred":[
        "\u0410\u043b\u0435\u0433\u0440\u0438\u044f"
    ],
    "name:ceb_x_preferred":[
        "Alegria"
    ],
    "name:eus_x_preferred":[
        "Alegia"
    ],
    "name:ita_x_preferred":[
        "Alegria"
    ],
    "name:nld_x_preferred":[
        "Alegria"
    ],
    "name:por_x_preferred":[
        "Alegria"
    ],
    "name:rus_x_preferred":[
        "\u0410\u043b\u0435\u0433\u0440\u0438\u044f"
    ],
    "name:scn_x_preferred":[
        "Alligrizza"
    ],
    "name:spa_x_preferred":[
        "Alegr\u00eda"
    ],
    "name:swe_x_preferred":[
        "Alegria"
    ],
    "name:war_x_preferred":[
        "Alegria"
    ],
    "wof:name":"Alegria",
    "wof:placetype":"locality"
},
  "geometry": {"coordinates":[-2.26212,43.0531],"type":"Point"}
}