{
  "type": "Feature",
  "properties": {
    "gn:admin1_code":"51",
    "gn:admin2_code":"J",
    "gn:admin3_code":"23070",
    "gn:asciiname":"Cuevecillas",
    "gn:country_code":"ES",
    "gn:dem":814,
    "gn:feature_class":"P",
    "gn:feature_code":"PPL",
    "gn:name":"Cuevecillas",
    "gn:population":0,
    "gn:timezone":"Europe/Madrid",
    "iso:country":"ES",
    "name:und_x_variant":[
        "Cortijo Cuevecillas",
        "Cuevecillas"
    ],
    "wof:name":"Cuevecillas",
    "wof:placetype":"locality"
},
  "geometry": {"coordinates":[-2.99136,37.66356],"type":"Point"}
}