{
  "type": "Feature",
  "properties": {
    "gn:admin1_code":"59",
    "gn:admin2_code":"BI",
    "gn:admin3_code":"48097",
    "gn:asciiname":"Larikao",
    "gn:country_code":"ES",
    "gn:dem":153,
    "gn:feature_class":"P",
    "gn:feature_code":"PPL",
    "gn:name":"Larikao",
    "gn:population":0,
    "gn:timezone":"Europe/Madrid",
    "iso:country":"ES",
    "wof:name":"Larikao",
    "wof:placetype":"locality"
},
  "geometry": {"coordinates":[-2.86667,43.21667],"type":"Point"}
}