{
  "type": "Feature",
  "properties": {
    "gn:admin1_code":"54",
    "gn:admin2_code":"GU",
    "gn:admin3_code":"19086",
    "gn:asciiname":"Huetos",
    "gn:country_code":"ES",
    "gn:dem":878,
    "gn:feature_class":"P",
    "gn:feature_code":"PPL",
    "gn:name":"Huetos",
    "gn:population":0,
    "gn:timezone":"Europe/Madrid",
    "iso:country":"ES",
    "wof:name":"Huetos",
    "wof:placetype":"locality"
},
  "geometry": {"coordinates":[-2.53676,40.75032],"type":"Point"}
}