{
  "type": "Feature",
  "properties": {
    "gn:admin1_code":"51",
    "gn:admin2_code":"MA",
    "gn:admin3_code":"29079",
    "gn:asciiname":"Banos de Vilo",
    "gn:cc2":"ES",
    "gn:country_code":"ES",
    "gn:dem":721,
    "gn:feature_class":"P",
    "gn:feature_code":"PPL",
    "gn:name":"Ba\u00f1os de Vilo",
    "gn:population":0,
    "gn:timezone":"Europe/Madrid",
    "iso:country":"ES",
    "name:und_x_variant":[
        "Los Ba\u00f1os de Vilo"
    ],
    "wof:name":"Banos de Vilo",
    "wof:placetype":"locality"
},
  "geometry": {"coordinates":[-4.20897,36.95154],"type":"Point"}
}