{
  "type": "Feature",
  "properties": {
    "gn:admin1_code":"55",
    "gn:admin2_code":"SO",
    "gn:admin3_code":"42123",
    "gn:asciiname":"Senuela",
    "gn:country_code":"ES",
    "gn:dem":1077,
    "gn:feature_class":"P",
    "gn:feature_code":"PPL",
    "gn:name":"Se\u00f1uela",
    "gn:population":0,
    "gn:timezone":"Europe/Madrid",
    "iso:country":"ES",
    "name:und_x_variant":[
        "Sa\u00f1uela",
        "Se\u00f1uelas",
        "Se\u00f1uela"
    ],
    "wof:name":"Senuela",
    "wof:placetype":"locality"
},
  "geometry": {"coordinates":[-2.442,41.38058],"type":"Point"}
}