{
  "type": "Feature",
  "properties": {
    "gn:admin1_code":"55",
    "gn:admin2_code":"SG",
    "gn:admin3_code":"40024",
    "gn:asciiname":"Francos",
    "gn:country_code":"ES",
    "gn:dem":1055,
    "gn:feature_class":"P",
    "gn:feature_code":"PPL",
    "gn:name":"Francos",
    "gn:population":0,
    "gn:timezone":"Europe/Madrid",
    "iso:country":"ES",
    "wof:name":"Francos",
    "wof:placetype":"locality"
},
  "geometry": {"coordinates":[-3.35,41.38333],"type":"Point"}
}