{
  "type": "Feature",
  "properties": {
    "gn:gn_country":"ES",
    "gn:gn_fcode":"PPLA3",
    "gn:gn_pop":416,
    "gn:population":416,
    "iso:country":"ES",
    "name:ara_x_preferred":[
        "\u0644\u064a\u062a\u0648\u0643\u0633"
    ],
    "name:arg_x_preferred":[
        "Letuix"
    ],
    "name:baq_x_preferred":[
        "Letux"
    ],
    "name:cat_x_preferred":[
        "Letux"
    ],
    "name:chi_x_preferred":[
        "\u83b1\u56fe\u65af"
    ],
    "name:dut_x_preferred":[
        "Letux"
    ],
    "name:eng_x_preferred":[
        "Letux"
    ],
    "name:fre_x_preferred":[
        "Letux"
    ],
    "name:hun_x_preferred":[
        "Letux"
    ],
    "name:ita_x_preferred":[
        "Letux"
    ],
    "name:kaz_x_preferred":[
        "\u041b\u0435\u0442\u0443\u043a\u0441"
    ],
    "name:may_x_preferred":[
        "Letux"
    ],
    "name:nan_x_preferred":[
        "Letux"
    ],
    "name:oci_x_preferred":[
        "Letux"
    ],
    "name:pol_x_preferred":[
        "Letux"
    ],
    "name:por_x_preferred":[
        "Letux"
    ],
    "name:rus_x_preferred":[
        "\u041b\u0435\u0442\u0443\u043a\u0441"
    ],
    "name:spa_x_preferred":[
        "Letux"
    ],
    "name:swe_x_preferred":[
        "Letux"
    ],
    "name:ukr_x_preferred":[
        "\u041b\u0435\u0442\u0443\u043a\u0441"
    ],
    "name:uzb_x_preferred":[
        "Letux"
    ],
    "name:vie_x_preferred":[
        "Letux"
    ],
    "name:war_x_preferred":[
        "Letux"
    ],
    "qs_pg:aaroncc":"ES",
    "qs_pg:gn_country":"ES",
    "qs_pg:gn_fcode":"PPLA3",
    "qs_pg:gn_pop":416,
    "qs_pg:name":"Letux",
    "qs_pg:name_adm0":"Espa\u00f1a",
    "qs_pg:name_adm1":"Arag\u00f3n",
    "qs_pg:photos_9r":0,
    "qs_pg:photos_sr":0,
    "qs_pg:pop_sr":2,
    "qs_pg:qs_pg_placetype":"locality",
    "qs_pg:qs_pg_placetype_gp":"Town",
    "qs_pg:woe_adm0":23424950,
    "woe:adm0_id":23424950,
    "woe:name_adm0":"Espa\u00f1a",
    "woe:name_adm1":"Arag\u00f3n",
    "woe:placetype":"Town",
    "wof:name":"Letux",
    "wof:placetype":"locality",
    "wof:population":416
},
  "geometry": {"coordinates":[-0.80269,41.25512],"type":"Point"}
}