{
  "type": "Feature",
  "properties": {
    "gn:admin1_code":"58",
    "gn:admin2_code":"LU",
    "gn:admin3_code":"27901",
    "gn:asciiname":"Reguengo",
    "gn:country_code":"ES",
    "gn:dem":616,
    "gn:feature_class":"P",
    "gn:feature_code":"PPL",
    "gn:name":"Reguengo",
    "gn:population":0,
    "gn:timezone":"Europe/Madrid",
    "iso:country":"ES",
    "wof:name":"Reguengo",
    "wof:placetype":"locality"
},
  "geometry": {"coordinates":[-7.26667,42.91667],"type":"Point"}
}