{
  "type": "Feature",
  "properties": {
    "gn:gn_country":"ES",
    "gn:gn_fcode":"PPLA3",
    "gn:gn_pop":102,
    "gn:population":102,
    "iso:country":"ES",
    "name:ara_x_preferred":[
        "\u0628\u0627\u062f\u0627\u064a\u0644\u0627 \u062f\u064a \u0623\u0631\u0627\u064a\u0628\u0627"
    ],
    "name:arg_x_preferred":[
        "Padilla de Arriba"
    ],
    "name:cat_x_preferred":[
        "Padilla de Arriba"
    ],
    "name:eng_x_preferred":[
        "Padilla de Arriba"
    ],
    "name:eus_x_preferred":[
        "Padilla de Arriba"
    ],
    "name:fas_x_preferred":[
        "\u067e\u0627\u062f\u06cc\u06cc\u0627 \u062f \u0622\u0631\u06cc\u0628\u0627"
    ],
    "name:fra_x_preferred":[
        "Padilla de Arriba"
    ],
    "name:glg_x_preferred":[
        "Padilla de Arriba"
    ],
    "name:haw_x_preferred":[
        "Padilla de Arriba"
    ],
    "name:hun_x_preferred":[
        "Padilla de Arriba"
    ],
    "name:ina_x_preferred":[
        "Padilla de Arriba"
    ],
    "name:ita_x_preferred":[
        "Padilla de Arriba"
    ],
    "name:msa_x_preferred":[
        "Padilla de Arriba"
    ],
    "name:nan_x_preferred":[
        "Padilla de Arriba"
    ],
    "name:nld_x_preferred":[
        "Padilla de Arriba"
    ],
    "name:oci_x_preferred":[
        "Padilla de Arriba"
    ],
    "name:pol_x_preferred":[
        "Padilla de Arriba"
    ],
    "name:por_x_preferred":[
        "Padilla de Arriba"
    ],
    "name:rus_x_preferred":[
        "\u041f\u0430\u0434\u0438\u043b\u044c\u044f-\u0434\u0435-\u0410\u0440\u0440\u0438\u0431\u0430"
    ],
    "name:spa_x_preferred":[
        "Padilla de Arriba"
    ],
    "name:swe_x_preferred":[
        "Padilla de Arriba"
    ],
    "name:ukr_x_preferred":[
        "\u041f\u0430\u0434\u0456\u043b\u044c\u044f-\u0434\u0435-\u0410\u0440\u0440\u0456\u0431\u0430"
    ],
    "name:vie_x_preferred":[
        "Padilla de Arriba"
    ],
    "name:war_x_preferred":[
        "Padilla de Arriba"
    ],
    "name:zho_x_preferred":[
        "\u5e15\u8fea\u5229\u4e9a\u5fb7\u4e9a\u91cc\u74e6"
    ],
    "qs_pg:aaroncc":"ES",
    "qs_pg:gn_country":"ES",
    "qs_pg:gn_fcode":"PPLA3",
    "qs_pg:gn_pop":102,
    "qs_pg:name":"Padilla de Arriba",
    "qs_pg:name_adm0":"Espa\u00f1a",
    "qs_pg:name_adm1":"Castilla y Le\u00f3n",
    "qs_pg:photos_9k":1,
    "qs_pg:photos_9r":1,
    "qs_pg:photos_all":1,
    "qs_pg:photos_sr":0,
    "qs_pg:pop_sr":1,
    "qs_pg:qs_pg_placetype":"locality",
    "qs_pg:qs_pg_placetype_gp":"Town",
    "qs_pg:woe_adm0":23424950,
    "woe:adm0_id":23424950,
    "woe:name_adm0":"Espa\u00f1a",
    "woe:name_adm1":"Castilla y Le\u00f3n",
    "woe:placetype":"Town",
    "wof:name":"Padilla de Arriba",
    "wof:placetype":"locality",
    "wof:population":102
},
  "geometry": {"coordinates":[-4.19094,42.43803],"type":"Point"}
}