{
  "type": "Feature",
  "properties": {
    "gn:admin1_code":"39",
    "gn:admin2_code":"S",
    "gn:admin3_code":"39002",
    "gn:asciiname":"Bernales",
    "gn:country_code":"ES",
    "gn:dem":27,
    "gn:feature_class":"P",
    "gn:feature_code":"PPL",
    "gn:name":"Bernales",
    "gn:population":0,
    "gn:timezone":"Europe/Madrid",
    "iso:country":"ES",
    "wof:name":"Bernales",
    "wof:placetype":"locality"
},
  "geometry": {"coordinates":[-3.4083,43.33631],"type":"Point"}
}