{
  "type": "Feature",
  "properties": {
    "gn:gn_country":"ES",
    "gn:gn_fcode":"PPLA3",
    "gn:gn_pop":88,
    "gn:population":88,
    "iso:country":"ES",
    "name:arg_x_preferred":[
        "Cazurra"
    ],
    "name:arm_x_preferred":[
        "\u053f\u0561\u057d\u0578\u0582\u057c\u0561"
    ],
    "name:ast_x_preferred":[
        "Cazurra"
    ],
    "name:baq_x_preferred":[
        "Cazurra"
    ],
    "name:cat_x_preferred":[
        "Cazurra"
    ],
    "name:chi_x_preferred":[
        "\u5361\u82cf\u62c9"
    ],
    "name:dut_x_preferred":[
        "Cazurra"
    ],
    "name:eng_x_preferred":[
        "Cazurra"
    ],
    "name:fre_x_preferred":[
        "Cazurra"
    ],
    "name:haw_x_preferred":[
        "Cazurra"
    ],
    "name:hun_x_preferred":[
        "Cazurra"
    ],
    "name:ile_x_preferred":[
        "Cazurra"
    ],
    "name:ina_x_preferred":[
        "Cazurra"
    ],
    "name:ita_x_preferred":[
        "Cazurra"
    ],
    "name:may_x_preferred":[
        "Cazurra"
    ],
    "name:nan_x_preferred":[
        "Cazurra"
    ],
    "name:oci_x_preferred":[
        "Cazurra"
    ],
    "name:pol_x_preferred":[
        "Cazurra"
    ],
    "name:por_x_preferred":[
        "Cazurra"
    ],
    "name:rus_x_preferred":[
        "\u041a\u0430\u0441\u0443\u0440\u0440\u0430"
    ],
    "name:spa_x_preferred":[
        "Cazurra"
    ],
    "name:swe_x_preferred":[
        "Cazurra"
    ],
    "name:ukr_x_preferred":[
        "\u041a\u0430\u0441\u0443\u0440\u0440\u0430"
    ],
    "name:uzb_x_preferred":[
        "Cazurra"
    ],
    "name:vie_x_preferred":[
        "Cazurra"
    ],
    "name:war_x_preferred":[
        "Cazurra"
    ],
    "qs_pg:aaroncc":"ES",
    "qs_pg:gn_country":"ES",
    "qs_pg:gn_fcode":"PPLA3",
    "qs_pg:gn_pop":88,
    "qs_pg:name":"Cazurra",
    "qs_pg:name_adm0":"Espa\u00f1a",
    "qs_pg:name_adm1":"Castilla y Le\u00f3n",
    "qs_pg:photos_9r":0,
    "qs_pg:photos_sr":0,
    "qs_pg:pop_sr":1,
    "qs_pg:qs_pg_placetype":"locality",
    "qs_pg:qs_pg_placetype_gp":"Town",
    "qs_pg:woe_adm0":23424950,
    "woe:adm0_id":23424950,
    "woe:name_adm0":"Espa\u00f1a",
    "woe:name_adm1":"Castilla y Le\u00f3n",
    "woe:placetype":"Town",
    "wof:name":"Cazurra",
    "wof:placetype":"locality",
    "wof:population":88
},
  "geometry": {"coordinates":[-5.70454,41.41583],"type":"Point"}
}