{
  "type": "Feature",
  "properties": {
    "gn:admin1_code":"56",
    "gn:admin2_code":"L",
    "gn:admin3_code":"25185",
    "gn:asciiname":"Gramos",
    "gn:country_code":"ES",
    "gn:dem":901,
    "gn:feature_class":"P",
    "gn:feature_code":"PPL",
    "gn:name":"Gram\u00f3s",
    "gn:population":0,
    "gn:timezone":"Europe/Madrid",
    "iso:country":"ES",
    "name:bul_x_preferred":[
        "\u0413\u0440\u0430\u043c\u043e\u0441"
    ],
    "name:ceb_x_preferred":[
        "Gr\u00e1mos \u00d3ros"
    ],
    "name:ces_x_preferred":[
        "Grammos"
    ],
    "name:deu_x_preferred":[
        "Grammos"
    ],
    "name:ell_x_preferred":[
        "\u0393\u03c1\u03ac\u03bc\u03bc\u03bf\u03c2"
    ],
    "name:fin_x_preferred":[
        "Gr\u00e1mmos"
    ],
    "name:fra_x_preferred":[
        "Gramos"
    ],
    "name:hrv_x_preferred":[
        "Gramos"
    ],
    "name:lit_x_preferred":[
        "Gramas"
    ],
    "name:mkd_x_preferred":[
        "\u0413\u0440\u0430\u043c\u0443\u0448\u0442\u0430"
    ],
    "name:nno_x_preferred":[
        "Gr\u00e1mmos"
    ],
    "name:rus_x_preferred":[
        "\u0413\u0440\u0430\u043c\u043e\u0441"
    ],
    "name:spa_x_preferred":[
        "Grammos"
    ],
    "name:srp_x_preferred":[
        "\u0413\u0440\u0430\u043c\u043e\u0441"
    ],
    "name:swe_x_preferred":[
        "Gr\u00e1mos \u00d3ros"
    ],
    "name:zho_x_preferred":[
        "\u683c\u62c9\u83ab\u65af\u5c71\u8108"
    ],
    "wof:name":"Gramos",
    "wof:placetype":"locality"
},
  "geometry": {"coordinates":[1.33621,42.31873],"type":"Point"}
}