{
  "type": "Feature",
  "properties": {
    "gn:admin1_code":"56",
    "gn:admin2_code":"L",
    "gn:admin3_code":"25185",
    "gn:asciiname":"Gramos",
    "gn:country_code":"ES",
    "gn:dem":901,
    "gn:feature_class":"P",
    "gn:feature_code":"PPL",
    "gn:name":"Gram\u00f3s",
    "gn:population":0,
    "gn:timezone":"Europe/Madrid",
    "iso:country":"ES",
    "wof:name":"Gramos",
    "wof:placetype":"locality"
},
  "geometry": {"coordinates":[1.33621,42.31873],"type":"Point"}
}