{
  "type": "Feature",
  "properties": {
    "iso:country":"ES",
    "name:eng_x_preferred":[
        "La Asuncion"
    ],
    "name:spa_x_preferred":[
        "La Asunci\u00f3n"
    ],
    "wof:name":"La Asuncion",
    "wof:placetype":"neighbourhood"
},
  "geometry": {"coordinates":[-4.44591719929687,36.71019107049601],"type":"Point"}
}