{
  "type": "Feature",
  "properties": {
    "gn:gn_country":"ES",
    "gn:gn_fcode":"PPLA3",
    "gn:gn_pop":282,
    "gn:population":282,
    "iso:country":"ES",
    "name:arg_x_preferred":[
        "Sanchotello"
    ],
    "name:ast_x_preferred":[
        "Sanchotello"
    ],
    "name:cat_x_preferred":[
        "Sanchotello"
    ],
    "name:ceb_x_preferred":[
        "Sanchotello"
    ],
    "name:eng_x_preferred":[
        "Sanchotello"
    ],
    "name:eus_x_preferred":[
        "Sanchotello"
    ],
    "name:fra_x_preferred":[
        "Sanchotello"
    ],
    "name:hun_x_preferred":[
        "Sanchotello"
    ],
    "name:ina_x_preferred":[
        "Sanchotello"
    ],
    "name:ita_x_preferred":[
        "Sanchotello"
    ],
    "name:kaz_x_preferred":[
        "\u0421\u0430\u043d\u0447\u043e\u0442\u0435\u043b\u044c\u043e"
    ],
    "name:msa_x_preferred":[
        "Sanchotello"
    ],
    "name:nan_x_preferred":[
        "Sanchotello"
    ],
    "name:nld_x_preferred":[
        "Sanchotello"
    ],
    "name:oci_x_preferred":[
        "Sanchotello"
    ],
    "name:pol_x_preferred":[
        "Sanchotello"
    ],
    "name:por_x_preferred":[
        "Sanchotello"
    ],
    "name:rus_x_preferred":[
        "\u0421\u0430\u043d\u0447\u043e\u0442\u0435\u043b\u044c\u043e"
    ],
    "name:spa_x_preferred":[
        "Sanchotello"
    ],
    "name:swe_x_preferred":[
        "Sanchotello"
    ],
    "name:ukr_x_preferred":[
        "\u0421\u0430\u043d\u0447\u043e\u0442\u0435\u043b\u044c\u0439\u043e"
    ],
    "name:vie_x_preferred":[
        "Sanchotello"
    ],
    "name:war_x_preferred":[
        "Sanchotello"
    ],
    "name:zho_x_preferred":[
        "\u6851\u4e54\u7279\u7565"
    ],
    "qs_pg:aaroncc":"ES",
    "qs_pg:gn_country":"ES",
    "qs_pg:gn_fcode":"PPLA3",
    "qs_pg:gn_pop":282,
    "qs_pg:name":"Sanchotello",
    "qs_pg:name_adm0":"Espa\u00f1a",
    "qs_pg:name_adm1":"Castilla y Le\u00f3n",
    "qs_pg:photos_9r":0,
    "qs_pg:photos_sr":0,
    "qs_pg:pop_sr":2,
    "qs_pg:qs_pg_placetype":"locality",
    "qs_pg:qs_pg_placetype_gp":"Town",
    "qs_pg:woe_adm0":23424950,
    "woe:adm0_id":23424950,
    "woe:name_adm0":"Espa\u00f1a",
    "woe:name_adm1":"Castilla y Le\u00f3n",
    "woe:placetype":"Town",
    "wof:name":"Sanchotello",
    "wof:placetype":"locality",
    "wof:population":282
},
  "geometry": {"coordinates":[-5.75394,40.43812],"type":"Point"}
}