{
  "type": "Feature",
  "properties": {
    "gn:gn_country":"ES",
    "gn:gn_fcode":"PPL",
    "gn:gn_pop":0,
    "iso:country":"ES",
    "name:bul_x_preferred":[
        "\u041f\u043e\u0440\u0442\u043e\u043f\u0435\u0442\u0440\u043e"
    ],
    "name:cat_x_preferred":[
        "Portopetro"
    ],
    "name:deu_x_preferred":[
        "Portopetro"
    ],
    "name:dut_x_preferred":[
        "Portopetro"
    ],
    "name:eng_x_preferred":[
        "Portopetro"
    ],
    "name:ger_x_preferred":[
        "Portopetro"
    ],
    "name:spa_x_preferred":[
        "Portopetro"
    ],
    "name:swe_x_preferred":[
        "Portopetro"
    ],
    "qs_pg:aaroncc":"ES",
    "qs_pg:gn_country":"ES",
    "qs_pg:gn_fcode":"PPL",
    "qs_pg:gn_pop":0,
    "qs_pg:name":"Porto Petro",
    "qs_pg:name_adm0":"Espa\u00f1a",
    "qs_pg:name_adm1":"Illes Balears",
    "qs_pg:photos":632,
    "qs_pg:photos_1k":128,
    "qs_pg:photos_9k":3,
    "qs_pg:photos_9r":5,
    "qs_pg:photos_all":632,
    "qs_pg:photos_sr":8,
    "qs_pg:pop_sr":0,
    "qs_pg:qs_pg_placetype":"locality",
    "qs_pg:qs_pg_placetype_gp":"Town",
    "qs_pg:woe_adm0":23424950,
    "woe:adm0_id":23424950,
    "woe:name_adm0":"Espa\u00f1a",
    "woe:name_adm1":"Illes Balears",
    "woe:placetype":"Town",
    "wof:name":"Porto Petro",
    "wof:placetype":"locality"
},
  "geometry": {"coordinates":[3.21005,39.36169],"type":"Point"}
}