{
  "type": "Feature",
  "properties": {
    "gn:admin1_code":"55",
    "gn:admin2_code":"P",
    "gn:admin3_code":"34902",
    "gn:asciiname":"Villatoquite",
    "gn:country_code":"ES",
    "gn:dem":785,
    "gn:feature_class":"P",
    "gn:feature_code":"PPL",
    "gn:name":"Villatoquite",
    "gn:population":0,
    "gn:timezone":"Europe/Madrid",
    "iso:country":"ES",
    "wof:name":"Villatoquite",
    "wof:placetype":"locality"
},
  "geometry": {"coordinates":[-4.77828,42.20739],"type":"Point"}
}