{
  "type": "Feature",
  "properties": {
    "gn:admin1_code":"58",
    "gn:admin2_code":"LU",
    "gn:admin3_code":"27018",
    "gn:asciiname":"Vilafrime",
    "gn:country_code":"ES",
    "gn:dem":634,
    "gn:feature_class":"P",
    "gn:feature_code":"PPL",
    "gn:name":"Vilafrime",
    "gn:population":0,
    "gn:timezone":"Europe/Madrid",
    "iso:country":"ES",
    "wof:name":"Vilafrime",
    "wof:placetype":"locality"
},
  "geometry": {"coordinates":[-7.10562,43.07299],"type":"Point"}
}