{
  "type": "Feature",
  "properties": {
    "gn:admin1_code":"51",
    "gn:admin2_code":"AL",
    "gn:admin3_code":"04032",
    "gn:asciiname":"El Barranco de Garcia",
    "gn:country_code":"ES",
    "gn:dem":260,
    "gn:feature_class":"P",
    "gn:feature_code":"PPL",
    "gn:name":"El Barranco de Garc\u00eda",
    "gn:population":0,
    "gn:timezone":"Europe/Madrid",
    "iso:country":"ES",
    "name:und_x_variant":[
        "Ca\u00f1ada El Barranco de Garc\u00eda",
        "El Barranco de Garc\u00eda"
    ],
    "wof:name":"El Barranco de Garcia",
    "wof:placetype":"locality"
},
  "geometry": {"coordinates":[-1.93623,37.0491],"type":"Point"}
}