{
  "type": "Feature",
  "properties": {
    "gn:admin1_code":"31",
    "gn:admin2_code":"MU",
    "gn:admin3_code":"30007",
    "gn:asciiname":"Las Pullas",
    "gn:country_code":"ES",
    "gn:dem":91,
    "gn:feature_class":"P",
    "gn:feature_code":"PPL",
    "gn:name":"Las Pullas",
    "gn:population":0,
    "gn:timezone":"Europe/Madrid",
    "iso:country":"ES",
    "name:und_x_variant":[
        "Caser\u00edo Las Pullas",
        "Las Pullas"
    ],
    "wof:name":"Las Pullas",
    "wof:placetype":"locality"
},
  "geometry": {"coordinates":[-1.25827,38.06748],"type":"Point"}
}