{
  "type": "Feature",
  "properties": {
    "gn:gn_country":"ES",
    "gn:gn_fcode":"PPLA3",
    "gn:gn_pop":148,
    "gn:population":148,
    "iso:country":"ES",
    "name:ara_x_preferred":[
        "\u063a\u0627\u064a\u0648\u0643\u0627\u0646\u062a\u0627"
    ],
    "name:arg_x_preferred":[
        "Gallocanta"
    ],
    "name:ast_x_preferred":[
        "Gallocanta"
    ],
    "name:cat_x_preferred":[
        "Gallocanta"
    ],
    "name:ceb_x_preferred":[
        "Gallocanta"
    ],
    "name:deu_x_preferred":[
        "Gallocanta"
    ],
    "name:eng_x_preferred":[
        "Gallocanta"
    ],
    "name:eus_x_preferred":[
        "Gallocanta"
    ],
    "name:fas_x_preferred":[
        "\u06af\u0627\u06cc\u06a9\u0627\u0646\u062a\u0627"
    ],
    "name:fra_x_preferred":[
        "Gallocanta"
    ],
    "name:hak_x_preferred":[
        "Gallocanta"
    ],
    "name:hun_x_preferred":[
        "Gallocanta"
    ],
    "name:ita_x_preferred":[
        "Gallocanta"
    ],
    "name:kaz_x_preferred":[
        "\u0413\u0430\u043b\u044c\u043e\u043a\u0430\u043d\u0442\u0430"
    ],
    "name:msa_x_preferred":[
        "Gallocanta"
    ],
    "name:nan_x_preferred":[
        "Gallocanta"
    ],
    "name:nld_x_preferred":[
        "Gallocanta"
    ],
    "name:oci_x_preferred":[
        "Gallocanta"
    ],
    "name:pol_x_preferred":[
        "Gallocanta"
    ],
    "name:por_x_preferred":[
        "Gallocanta"
    ],
    "name:rus_x_preferred":[
        "\u0413\u0430\u043b\u044c\u043e\u043a\u0430\u043d\u0442\u0430"
    ],
    "name:spa_x_preferred":[
        "Gallocanta"
    ],
    "name:swe_x_preferred":[
        "Gallocanta"
    ],
    "name:ukr_x_preferred":[
        "\u0413\u0430\u043b\u044c\u0439\u043e\u043a\u0430\u043d\u0442\u0430"
    ],
    "name:uzb_x_preferred":[
        "Gallocanta"
    ],
    "name:vie_x_preferred":[
        "Gallocanta"
    ],
    "name:war_x_preferred":[
        "Gallocanta"
    ],
    "name:zho_x_preferred":[
        "\u52a0\u7565\u574e\u5854"
    ],
    "qs_pg:aaroncc":"ES",
    "qs_pg:gn_country":"ES",
    "qs_pg:gn_fcode":"PPLA3",
    "qs_pg:gn_pop":148,
    "qs_pg:name":"Gallocanta",
    "qs_pg:name_adm0":"Espa\u00f1a",
    "qs_pg:name_adm1":"Arag\u00f3n",
    "qs_pg:photos":164,
    "qs_pg:photos_1k":33,
    "qs_pg:photos_9k":1,
    "qs_pg:photos_9r":4,
    "qs_pg:photos_all":164,
    "qs_pg:photos_sr":4,
    "qs_pg:pop_sr":1,
    "qs_pg:qs_pg_placetype":"locality",
    "qs_pg:qs_pg_placetype_gp":"Town",
    "qs_pg:woe_adm0":23424950,
    "woe:adm0_id":23424950,
    "woe:name_adm0":"Espa\u00f1a",
    "woe:name_adm1":"Arag\u00f3n",
    "woe:placetype":"Town",
    "wof:name":"Gallocanta",
    "wof:placetype":"locality",
    "wof:population":148
},
  "geometry": {"coordinates":[-1.50774,40.99624],"type":"Point"}
}