{
  "type": "Feature",
  "properties": {
    "gn:admin1_code":"51",
    "gn:admin2_code":"AL",
    "gn:admin3_code":"04053",
    "gn:asciiname":"Los Pinares",
    "gn:country_code":"ES",
    "gn:dem":273,
    "gn:feature_class":"P",
    "gn:feature_code":"PPL",
    "gn:name":"Los Pinares",
    "gn:population":0,
    "gn:timezone":"Europe/Madrid",
    "iso:country":"ES",
    "name:und_x_variant":[
        "Caser\u00edo Los Pinares",
        "Los Pinares"
    ],
    "wof:name":"Los Pinares",
    "wof:placetype":"locality"
},
  "geometry": {"coordinates":[-1.81331,37.43075],"type":"Point"}
}