{
  "type": "Feature",
  "properties": {
    "gn:admin1_code":"55",
    "gn:admin2_code":"LE",
    "gn:admin3_code":"24038",
    "gn:asciiname":"Peon de Abajo",
    "gn:cc2":"ES",
    "gn:country_code":"ES",
    "gn:dem":431,
    "gn:feature_class":"P",
    "gn:feature_code":"PPL",
    "gn:name":"Pe\u00f3n de Abajo",
    "gn:population":0,
    "gn:timezone":"Europe/Madrid",
    "iso:country":"ES",
    "name:und_x_variant":[
        "Caser\u00edo Pe\u00f3n de Abajo",
        "Pe\u00f3n de Abajo"
    ],
    "wof:name":"Peon de Abajo",
    "wof:placetype":"locality"
},
  "geometry": {"coordinates":[-6.76667,42.53333],"type":"Point"}
}