{
  "type": "Feature",
  "properties": {
    "gn:admin1_code":"58",
    "gn:admin2_code":"LU",
    "gn:admin3_code":"27024",
    "gn:asciiname":"Trascastro",
    "gn:country_code":"ES",
    "gn:dem":625,
    "gn:feature_class":"P",
    "gn:feature_code":"PPL",
    "gn:name":"Trascastro",
    "gn:population":0,
    "gn:timezone":"Europe/Madrid",
    "iso:country":"ES",
    "name:und_x_variant":[
        "Tracastro",
        "Trascastro"
    ],
    "wof:name":"Trascastro",
    "wof:placetype":"locality"
},
  "geometry": {"coordinates":[-7.33097,42.64459],"type":"Point"}
}