{
  "type": "Feature",
  "properties": {
    "gn:gn_country":"ES",
    "gn:gn_fcode":"PPLA3",
    "gn:gn_pop":129,
    "gn:population":129,
    "iso:country":"ES",
    "name:arg_x_preferred":[
        "Sesu\u00e9"
    ],
    "name:ast_x_preferred":[
        "Sesu\u00e9"
    ],
    "name:azb_x_preferred":[
        "\u0633\u0647\u200c\u0633\u0648\u0626\u0647"
    ],
    "name:cat_x_preferred":[
        "Sessu\u00e9"
    ],
    "name:ceb_x_preferred":[
        "Sesu\u00e9"
    ],
    "name:deu_x_preferred":[
        "Sesu\u00e9"
    ],
    "name:eng_x_preferred":[
        "Sesu\u00e9"
    ],
    "name:eus_x_preferred":[
        "Sesu\u00e9"
    ],
    "name:fas_x_preferred":[
        "\u0633\u0647\u200c\u0633\u0648\u0626\u0647"
    ],
    "name:fra_x_preferred":[
        "Sesu\u00e9"
    ],
    "name:glg_x_preferred":[
        "Sesu\u00e9"
    ],
    "name:hak_x_preferred":[
        "Sesu\u00e9"
    ],
    "name:hun_x_preferred":[
        "Sesu\u00e9"
    ],
    "name:ita_x_preferred":[
        "Sesu\u00e9"
    ],
    "name:jpn_x_preferred":[
        "\u30bb\u30b9\u30a8"
    ],
    "name:msa_x_preferred":[
        "Sesu\u00e9"
    ],
    "name:nan_x_preferred":[
        "Sesu\u00e9"
    ],
    "name:nld_x_preferred":[
        "Sesu\u00e9"
    ],
    "name:oci_x_preferred":[
        "Sesu\u00e9"
    ],
    "name:pol_x_preferred":[
        "Sesu\u00e9"
    ],
    "name:por_x_preferred":[
        "Sesu\u00e9"
    ],
    "name:rus_x_preferred":[
        "\u0421\u0435\u0441\u0443\u044d"
    ],
    "name:spa_x_preferred":[
        "Sesu\u00e9"
    ],
    "name:swe_x_preferred":[
        "Sesu\u00e9"
    ],
    "name:ukr_x_preferred":[
        "\u0421\u0435\u0441\u0443\u0435"
    ],
    "name:uzb_x_preferred":[
        "Sesu\u00e9"
    ],
    "name:vie_x_preferred":[
        "Sesu\u00e9"
    ],
    "name:war_x_preferred":[
        "Sesu\u00e9"
    ],
    "name:zho_x_preferred":[
        "\u585e\u82cf\u57c3"
    ],
    "qs_pg:aaroncc":"ES",
    "qs_pg:gn_country":"ES",
    "qs_pg:gn_fcode":"PPLA3",
    "qs_pg:gn_pop":129,
    "qs_pg:name":"Sesu\u00e9",
    "qs_pg:name_adm0":"Espa\u00f1a",
    "qs_pg:name_adm1":"Arag\u00f3n",
    "qs_pg:photos_9r":0,
    "qs_pg:photos_sr":0,
    "qs_pg:pop_sr":1,
    "qs_pg:qs_pg_placetype":"locality",
    "qs_pg:qs_pg_placetype_gp":"Town",
    "qs_pg:woe_adm0":23424950,
    "woe:adm0_id":23424950,
    "woe:name_adm0":"Espa\u00f1a",
    "woe:name_adm1":"Arag\u00f3n",
    "woe:placetype":"Town",
    "wof:name":"Sesu\u00e9",
    "wof:placetype":"locality",
    "wof:population":129
},
  "geometry": {"coordinates":[0.47212,42.55131],"type":"Point"}
}