{
  "type": "Feature",
  "properties": {
    "gn:admin1_code":"55",
    "gn:admin2_code":"LE",
    "gn:admin3_code":"24185",
    "gn:asciiname":"Val de San Roman",
    "gn:country_code":"ES",
    "gn:dem":891,
    "gn:feature_class":"P",
    "gn:feature_code":"PPL",
    "gn:name":"Val de San Rom\u00e1n",
    "gn:population":0,
    "gn:timezone":"Europe/Madrid",
    "iso:country":"ES",
    "name:und_x_variant":[
        "Val de San Rom\u00e1n"
    ],
    "wof:name":"Val de San Roman",
    "wof:placetype":"locality"
},
  "geometry": {"coordinates":[-6.13386,42.42787],"type":"Point"}
}