{
  "type": "Feature",
  "properties": {
    "gn:admin1_code":"56",
    "gn:admin2_code":"GI",
    "gn:admin3_code":"17140",
    "gn:asciiname":"sa Perafita",
    "gn:country_code":"ES",
    "gn:dem":288,
    "gn:feature_class":"P",
    "gn:feature_code":"PPLL",
    "gn:name":"sa Perafita",
    "gn:population":0,
    "gn:timezone":"Europe/Madrid",
    "iso:country":"ES",
    "name:cat_x_preferred":[
        "sa Perafita"
    ],
    "wof:name":"sa Perafita",
    "wof:placetype":"locality"
},
  "geometry": {"coordinates":[3.2374,42.29918],"type":"Point"}
}