{
  "type": "Feature",
  "properties": {
    "gn:admin1_code":"31",
    "gn:admin2_code":"MU",
    "gn:admin3_code":"30043",
    "gn:asciiname":"Carche",
    "gn:cc2":"ES",
    "gn:country_code":"ES",
    "gn:dem":614,
    "gn:feature_class":"P",
    "gn:feature_code":"PPL",
    "gn:name":"Carche",
    "gn:population":0,
    "gn:timezone":"Europe/Madrid",
    "iso:country":"ES",
    "name:cat_x_preferred":[
        "El Carxe"
    ],
    "name:ceb_x_preferred":[
        "Carche"
    ],
    "name:epo_x_preferred":[
        "El Carche"
    ],
    "name:eus_x_preferred":[
        "El Carxe"
    ],
    "name:fra_x_preferred":[
        "El Carche"
    ],
    "name:frp_x_preferred":[
        "Lo Carjo"
    ],
    "name:glg_x_preferred":[
        "El Carche"
    ],
    "name:ita_x_preferred":[
        "El Carche"
    ],
    "name:nld_x_preferred":[
        "El Carche"
    ],
    "name:nor_x_preferred":[
        "El Carxe"
    ],
    "name:oci_x_preferred":[
        "Carxe"
    ],
    "name:pol_x_preferred":[
        "Carche"
    ],
    "name:por_x_preferred":[
        "El Carche"
    ],
    "name:rus_x_preferred":[
        "\u042d\u043b\u044c-\u041a\u0430\u0440\u0447\u0435"
    ],
    "name:spa_x_preferred":[
        "El Carche"
    ],
    "name:swe_x_preferred":[
        "El Carche"
    ],
    "name:ukr_x_preferred":[
        "\u0410\u043b-\u041a\u0430\u0440\u0448\u0430"
    ],
    "name:und_x_variant":[
        "Boquera del Carche",
        "Caser\u00edo Boquera del Carche",
        "Carche"
    ],
    "wof:name":"Carche",
    "wof:placetype":"locality"
},
  "geometry": {"coordinates":[-1.13333,38.48333],"type":"Point"}
}