{
  "type": "Feature",
  "properties": {
    "gn:admin1_code":"31",
    "gn:admin2_code":"MU",
    "gn:admin3_code":"30043",
    "gn:asciiname":"Carche",
    "gn:cc2":"ES",
    "gn:country_code":"ES",
    "gn:dem":614,
    "gn:feature_class":"P",
    "gn:feature_code":"PPL",
    "gn:name":"Carche",
    "gn:population":0,
    "gn:timezone":"Europe/Madrid",
    "iso:country":"ES",
    "name:und_x_variant":[
        "Boquera del Carche",
        "Caser\u00edo Boquera del Carche",
        "Carche"
    ],
    "wof:name":"Carche",
    "wof:placetype":"locality"
},
  "geometry": {"coordinates":[-1.13333,38.48333],"type":"Point"}
}