{
  "type": "Feature",
  "properties": {
    "gn:gn_country":"ES",
    "gn:gn_fcode":"PPL",
    "gn:gn_pop":0,
    "gn:population":3656,
    "iso:country":"ES",
    "name:cat_x_preferred":[
        "El Pardo"
    ],
    "name:chi_x_preferred":[
        "\u827e\u6d3e\u5ea6\u7687\u5bae"
    ],
    "name:cze_x_preferred":[
        "El Pardo"
    ],
    "name:dut_x_preferred":[
        "El Pardo"
    ],
    "name:eng_x_preferred":[
        "El Pardo"
    ],
    "name:epo_x_preferred":[
        "Pardo"
    ],
    "name:fre_x_preferred":[
        "El Pardo"
    ],
    "name:ger_x_preferred":[
        "El Pardo"
    ],
    "name:heb_x_preferred":[
        "\u05d0\u05dc \u05e4\u05e8\u05d3\u05d5"
    ],
    "name:jpn_x_preferred":[
        "\u30a8\u30eb\u30fb\u30d1\u30eb\u30c9\u5893\u5730"
    ],
    "name:por_x_preferred":[
        "El Pardo"
    ],
    "name:rus_x_preferred":[
        "\u042d\u043b\u044c-\u041f\u0430\u0440\u0434\u043e"
    ],
    "name:spa_x_preferred":[
        "El Pardo"
    ],
    "name:swe_x_preferred":[
        "El Pardo"
    ],
    "name:unk_x_variant":[
        "El Pardo"
    ],
    "qs_pg:aaroncc":"ES",
    "qs_pg:gn_country":"ES",
    "qs_pg:gn_fcode":"PPL",
    "qs_pg:gn_pop":0,
    "qs_pg:name":"El Vado",
    "qs_pg:name_adm0":"Espa\u00f1a",
    "qs_pg:name_adm1":"Castilla-La Mancha",
    "qs_pg:photos":73,
    "qs_pg:photos_1k":15,
    "qs_pg:photos_9k":1,
    "qs_pg:photos_9r":2,
    "qs_pg:photos_all":73,
    "qs_pg:photos_sr":2,
    "qs_pg:pop_sr":0,
    "qs_pg:qs_pg_placetype":"locality",
    "qs_pg:qs_pg_placetype_gp":"Town",
    "qs_pg:woe_adm0":23424950,
    "woe:adm0_id":23424950,
    "woe:name_adm0":"Espa\u00f1a",
    "woe:name_adm1":"Castilla-La Mancha",
    "woe:placetype":"Town",
    "wof:name":"El Vado",
    "wof:placetype":"locality",
    "wof:population":3656
},
  "geometry": {"coordinates":[-3.77253,40.51454],"type":"Point"}
}