{
  "type": "Feature",
  "properties": {
    "gn:admin1_code":"56",
    "gn:admin2_code":"L",
    "gn:admin3_code":"25096",
    "gn:asciiname":"Boldu",
    "gn:country_code":"ES",
    "gn:dem":271,
    "gn:feature_class":"P",
    "gn:feature_code":"PPL",
    "gn:name":"Bold\u00fa",
    "gn:population":0,
    "gn:timezone":"Europe/Madrid",
    "iso:country":"ES",
    "name:und_x_variant":[
        "Bold\u00fa"
    ],
    "wof:name":"Boldu",
    "wof:placetype":"locality"
},
  "geometry": {"coordinates":[1.00478,41.7194],"type":"Point"}
}