{
  "type": "Feature",
  "properties": {
    "gn:admin1_code":"56",
    "gn:admin2_code":"L",
    "gn:admin3_code":"25096",
    "gn:asciiname":"Boldu",
    "gn:country_code":"ES",
    "gn:dem":271,
    "gn:feature_class":"P",
    "gn:feature_code":"PPL",
    "gn:name":"Bold\u00fa",
    "gn:population":0,
    "gn:timezone":"Europe/Madrid",
    "iso:country":"ES",
    "name:ceb_x_preferred":[
        "Boldu"
    ],
    "name:ita_x_preferred":[
        "Boldu"
    ],
    "name:msa_x_preferred":[
        "Boldu"
    ],
    "name:nld_x_preferred":[
        "Boldu"
    ],
    "name:por_x_preferred":[
        "Boldu"
    ],
    "name:ron_x_preferred":[
        "Boldu"
    ],
    "name:srp_x_preferred":[
        "\u041e\u043f\u0448\u0442\u0438\u043d\u0430 \u0411\u043e\u043b\u0434\u0443"
    ],
    "name:ukr_x_preferred":[
        "\u0411\u043e\u043b\u0434\u0443"
    ],
    "name:und_x_variant":[
        "Bold\u00fa"
    ],
    "name:vie_x_preferred":[
        "Boldu"
    ],
    "name:vol_x_preferred":[
        "Boldu"
    ],
    "name:zho_x_preferred":[
        "\u535a\u723e\u675c\u9109"
    ],
    "wof:name":"Boldu",
    "wof:placetype":"locality"
},
  "geometry": {"coordinates":[1.00478,41.7194],"type":"Point"}
}