{
  "type": "Feature",
  "properties": {
    "gn:admin1_code":"55",
    "gn:admin2_code":"P",
    "gn:admin3_code":"34158",
    "gn:asciiname":"San Mames de Zalima",
    "gn:country_code":"ES",
    "gn:dem":964,
    "gn:feature_class":"P",
    "gn:feature_code":"PPL",
    "gn:name":"San Mam\u00e9s de Zalima",
    "gn:population":0,
    "gn:timezone":"Europe/Madrid",
    "iso:country":"ES",
    "name:und_x_variant":[
        "San Mam\u00e9s de Zalima"
    ],
    "wof:name":"San Mames de Zalima",
    "wof:placetype":"locality"
},
  "geometry": {"coordinates":[-4.3566,42.83909],"type":"Point"}
}