{
  "type": "Feature",
  "properties": {
    "gn:admin1_code":"54",
    "gn:admin2_code":"CR",
    "gn:admin3_code":"13055",
    "gn:asciiname":"El Hoyo",
    "gn:country_code":"ES",
    "gn:dem":494,
    "gn:feature_class":"P",
    "gn:feature_code":"PPL",
    "gn:name":"El Hoyo",
    "gn:population":0,
    "gn:timezone":"Europe/Madrid",
    "iso:country":"ES",
    "name:ita_x_preferred":[
        "El Hoyo"
    ],
    "name:spa_x_preferred":[
        "El Hoyo"
    ],
    "wof:name":"El Hoyo",
    "wof:placetype":"locality"
},
  "geometry": {"coordinates":[-3.92016,38.40847],"type":"Point"}
}