{
  "type": "Feature",
  "properties": {
    "gn:admin1_code":"60",
    "gn:admin2_code":"A",
    "gn:admin3_code":"03063",
    "gn:asciiname":"Torrecarrals",
    "gn:cc2":"ES",
    "gn:country_code":"ES",
    "gn:dem":10,
    "gn:feature_class":"P",
    "gn:feature_code":"PPL",
    "gn:name":"Torrecarrals",
    "gn:population":0,
    "gn:timezone":"Europe/Madrid",
    "iso:country":"ES",
    "name:und_x_variant":[
        "Caser\u00edo Torre Carrals",
        "Torrecarrals"
    ],
    "wof:name":"Torrecarrals",
    "wof:placetype":"locality"
},
  "geometry": {"coordinates":[0.05,38.85],"type":"Point"}
}