{
  "type": "Feature",
  "properties": {
    "gn:gn_country":"ES",
    "gn:gn_fcode":"PPLA3",
    "gn:gn_pop":980,
    "gn:population":980,
    "iso:country":"ES",
    "name:arg_x_preferred":[
        "Soto y Am\u00edo"
    ],
    "name:azb_x_preferred":[
        "\u0633\u0648\u062a\u0648 \u0627\u06cc \u0627\u0645\u06cc\u0648"
    ],
    "name:cat_x_preferred":[
        "Soto y Am\u00edo"
    ],
    "name:ceb_x_preferred":[
        "Soto y Am\u00edo"
    ],
    "name:deu_x_preferred":[
        "Soto y Am\u00edo"
    ],
    "name:eng_x_preferred":[
        "Soto y Am\u00edo"
    ],
    "name:eus_x_preferred":[
        "Soto y Am\u00edo"
    ],
    "name:fas_x_preferred":[
        "\u0633\u0648\u062a\u0648 \u0627\u06cc \u0627\u0645\u06cc\u0648"
    ],
    "name:fra_x_preferred":[
        "Soto y Am\u00edo"
    ],
    "name:glg_x_preferred":[
        "Soto y Am\u00edo"
    ],
    "name:haw_x_preferred":[
        "Soto y Am\u00edo"
    ],
    "name:hun_x_preferred":[
        "Soto y Am\u00edo"
    ],
    "name:hye_x_preferred":[
        "\u054d\u0578\u057f\u0578 \u056b \u0531\u0574\u056b\u0578"
    ],
    "name:ido_x_preferred":[
        "Soto y Am\u00edo"
    ],
    "name:ina_x_preferred":[
        "Soto y Am\u00edo"
    ],
    "name:ita_x_preferred":[
        "Soto y Am\u00edo"
    ],
    "name:msa_x_preferred":[
        "Soto y Am\u00edo"
    ],
    "name:nan_x_preferred":[
        "Soto y Am\u00edo"
    ],
    "name:nld_x_preferred":[
        "Soto y Am\u00edo"
    ],
    "name:oci_x_preferred":[
        "Soto y Am\u00edo"
    ],
    "name:pol_x_preferred":[
        "Soto y Am\u00edo"
    ],
    "name:por_x_preferred":[
        "Soto y Am\u00edo"
    ],
    "name:rus_x_preferred":[
        "\u0421\u043e\u0442\u043e-\u0438-\u0410\u043c\u0438\u043e"
    ],
    "name:spa_x_preferred":[
        "Soto y Am\u00edo"
    ],
    "name:swe_x_preferred":[
        "Soto y Am\u00edo"
    ],
    "name:tpi_x_preferred":[
        "Soto y Am\u00edo"
    ],
    "name:ukr_x_preferred":[
        "\u0421\u043e\u0442\u043e-\u0456-\u0410\u043c\u0456\u043e"
    ],
    "name:vie_x_preferred":[
        "Soto y Am\u00edo"
    ],
    "name:war_x_preferred":[
        "Soto y Am\u00edo"
    ],
    "name:zho_x_preferred":[
        "\u7d22\u6258\u4e9a\u7c73\u5965"
    ],
    "qs_pg:aaroncc":"ES",
    "qs_pg:gn_country":"ES",
    "qs_pg:gn_fcode":"PPLA3",
    "qs_pg:gn_pop":980,
    "qs_pg:name":"Soto y Am\u00edo",
    "qs_pg:name_adm0":"Espa\u00f1a",
    "qs_pg:name_adm1":"Castilla y Le\u00f3n",
    "qs_pg:photos_9k":1,
    "qs_pg:photos_9r":1,
    "qs_pg:photos_all":1,
    "qs_pg:photos_sr":0,
    "qs_pg:pop_sr":2,
    "qs_pg:qs_pg_placetype":"locality",
    "qs_pg:qs_pg_placetype_gp":"Town",
    "qs_pg:woe_adm0":23424950,
    "woe:adm0_id":23424950,
    "woe:name_adm0":"Espa\u00f1a",
    "woe:name_adm1":"Castilla y Le\u00f3n",
    "woe:placetype":"Town",
    "wof:name":"Soto y Am\u00edo",
    "wof:placetype":"locality",
    "wof:population":980
},
  "geometry": {"coordinates":[-5.88693,42.77477],"type":"Point"}
}