{
  "type": "Feature",
  "properties": {
    "gn:admin1_code":"59",
    "gn:admin2_code":"SS",
    "gn:admin3_code":"20016",
    "gn:asciiname":"Santiago Errioa",
    "gn:country_code":"ES",
    "gn:dem":10,
    "gn:feature_class":"P",
    "gn:feature_code":"PPL",
    "gn:name":"Santio Erreka",
    "gn:population":0,
    "gn:timezone":"Europe/Madrid",
    "iso:country":"ES",
    "name:eus_x_preferred":[
        "Santiago Errioa"
    ],
    "name:eus_x_variant":[
        "Santio-erreka",
        "Santiago-erreka",
        "Santiagoerreka"
    ],
    "name:spa_x_preferred":[
        "R\u00eda"
    ],
    "wof:name":"Santiago Errioa",
    "wof:placetype":"locality"
},
  "geometry": {"coordinates":[-2.11899,43.26702],"type":"Point"}
}