{
  "type": "Feature",
  "properties": {
    "gn:gn_country":"ES",
    "gn:gn_fcode":"PPLA3",
    "gn:gn_pop":371,
    "gn:population":371,
    "iso:country":"ES",
    "name:ara_x_preferred":[
        "\u0623\u0631\u063a\u064a\u0644\u0627\u063a\u064a\u0631"
    ],
    "name:arg_x_preferred":[
        "Argelaguer"
    ],
    "name:ast_x_preferred":[
        "Argelaguer"
    ],
    "name:cat_x_preferred":[
        "Argelaguer"
    ],
    "name:ceb_x_preferred":[
        "Argelaguer"
    ],
    "name:deu_x_preferred":[
        "Argelaguer"
    ],
    "name:eng_x_preferred":[
        "Argelaguer"
    ],
    "name:eus_x_preferred":[
        "Argelaguer"
    ],
    "name:fra_x_preferred":[
        "Argelaguer"
    ],
    "name:glg_x_preferred":[
        "Argelaguer"
    ],
    "name:hun_x_preferred":[
        "Argelaguer"
    ],
    "name:hye_x_preferred":[
        "\u0531\u0580\u056a\u0565\u056c\u0561\u0563\u0565\u0580"
    ],
    "name:ita_x_preferred":[
        "Argelaguer"
    ],
    "name:kaz_x_preferred":[
        "\u0410\u0440\u0436\u0435\u043b\u0430\u0433\u0435\u0440"
    ],
    "name:lat_x_preferred":[
        "Argelaguer"
    ],
    "name:msa_x_preferred":[
        "Argelaguer"
    ],
    "name:nld_x_preferred":[
        "Argelaguer"
    ],
    "name:oci_x_preferred":[
        "Argelaguer"
    ],
    "name:pol_x_preferred":[
        "Argelaguer"
    ],
    "name:por_x_preferred":[
        "Argelaguer"
    ],
    "name:ron_x_preferred":[
        "Argelaguer"
    ],
    "name:rus_x_preferred":[
        "\u0410\u0440\u0436\u0435\u043b\u0430\u0433\u0435\u0440"
    ],
    "name:spa_x_preferred":[
        "Argelaguer"
    ],
    "name:sqi_x_preferred":[
        "Argelaguer"
    ],
    "name:swe_x_preferred":[
        "Argelaguer"
    ],
    "name:tah_x_preferred":[
        "Argelaguer"
    ],
    "name:uzb_x_preferred":[
        "Argelaguer"
    ],
    "name:war_x_preferred":[
        "Argelaguer"
    ],
    "name:zho_x_preferred":[
        "\u963f\u5c14\u8d6b\u62c9\u683c\u5c14"
    ],
    "qs_pg:aaroncc":"ES",
    "qs_pg:gn_country":"ES",
    "qs_pg:gn_fcode":"PPLA3",
    "qs_pg:gn_pop":371,
    "qs_pg:name":"Argelaguer",
    "qs_pg:name_adm0":"Espa\u00f1a",
    "qs_pg:name_adm1":"Catalunya",
    "qs_pg:photos_9k":1,
    "qs_pg:photos_9r":1,
    "qs_pg:photos_all":1,
    "qs_pg:photos_sr":0,
    "qs_pg:pop_sr":2,
    "qs_pg:qs_pg_placetype":"locality",
    "qs_pg:qs_pg_placetype_gp":"Town",
    "qs_pg:woe_adm0":23424950,
    "woe:adm0_id":23424950,
    "woe:name_adm0":"Espa\u00f1a",
    "woe:name_adm1":"Catalunya",
    "woe:placetype":"Town",
    "wof:name":"Argelaguer",
    "wof:placetype":"locality",
    "wof:population":371
},
  "geometry": {"coordinates":[2.64193,42.21563],"type":"Point"}
}