{
  "type": "Feature",
  "properties": {
    "iso:country":"ES",
    "qs_pg:aaroncc":"ES",
    "qs_pg:name":"Santuario de Bel\u00e9n",
    "qs_pg:name_adm0":"Espa\u00f1a",
    "qs_pg:name_adm1":"Castilla-La Mancha",
    "qs_pg:photos":23,
    "qs_pg:photos_1k":5,
    "qs_pg:photos_9k":1,
    "qs_pg:photos_9r":1,
    "qs_pg:photos_all":23,
    "qs_pg:photos_sr":1,
    "qs_pg:pop_sr":0,
    "qs_pg:qs_pg_placetype":"locality",
    "qs_pg:qs_pg_placetype_gp":"Town",
    "qs_pg:woe_adm0":23424950,
    "woe:adm0_id":23424950,
    "woe:name_adm0":"Espa\u00f1a",
    "woe:name_adm1":"Castilla-La Mancha",
    "woe:placetype":"Town",
    "wof:name":"Santuario de Bel\u00e9n",
    "wof:placetype":"locality"
},
  "geometry": {"coordinates":[-1.201758,38.861448],"type":"Point"}
}