{
  "type": "Feature",
  "properties": {
    "gn:admin1_code":"56",
    "gn:admin2_code":"B",
    "gn:admin3_code":"08273",
    "gn:asciiname":"Can Cartro",
    "gn:country_code":"ES",
    "gn:dem":185,
    "gn:feature_class":"P",
    "gn:feature_code":"PPL",
    "gn:name":"Can Cartr\u00f3",
    "gn:population":0,
    "gn:timezone":"Europe/Madrid",
    "iso:country":"ES",
    "wof:name":"Can Cartro",
    "wof:placetype":"locality"
},
  "geometry": {"coordinates":[1.73824,41.39606],"type":"Point"}
}