{
  "type": "Feature",
  "properties": {
    "gn:population":2196,
    "iso:country":"ES",
    "name:ara_x_preferred":[
        "\u0642\u0631\u0628"
    ],
    "name:arg_x_preferred":[
        "Gurb"
    ],
    "name:cat_x_preferred":[
        "Gurb"
    ],
    "name:ceb_x_preferred":[
        "Gurb"
    ],
    "name:deu_x_preferred":[
        "Gurb"
    ],
    "name:eng_x_preferred":[
        "Gurb"
    ],
    "name:eus_x_preferred":[
        "Gurb"
    ],
    "name:fas_x_preferred":[
        "\u06af\u0648\u0631\u0628"
    ],
    "name:fra_x_preferred":[
        "Gurb"
    ],
    "name:glg_x_preferred":[
        "Gurb"
    ],
    "name:hun_x_preferred":[
        "Gurb"
    ],
    "name:hye_x_preferred":[
        "\u0533\u0578\u0582\u0580\u0562"
    ],
    "name:ita_x_preferred":[
        "Gurb"
    ],
    "name:kaz_x_preferred":[
        "\u0413\u0443\u0440\u0431"
    ],
    "name:lat_x_preferred":[
        "Gurb"
    ],
    "name:nld_x_preferred":[
        "Gurb"
    ],
    "name:oci_x_preferred":[
        "Gurb"
    ],
    "name:pol_x_preferred":[
        "Gurb"
    ],
    "name:por_x_preferred":[
        "Gurb"
    ],
    "name:ron_x_preferred":[
        "Gurb"
    ],
    "name:rus_x_preferred":[
        "\u0413\u0443\u0440\u0431"
    ],
    "name:spa_x_preferred":[
        "Gurb"
    ],
    "name:spa_x_variant":[
        "El Gurb"
    ],
    "name:sqi_x_preferred":[
        "Gurb"
    ],
    "name:swe_x_preferred":[
        "Gurb"
    ],
    "name:uzb_x_preferred":[
        "Gurb"
    ],
    "name:war_x_preferred":[
        "Gurb"
    ],
    "name:zho_x_preferred":[
        "\u53e4\u5c14\u5e03"
    ],
    "qs:a0":"Espa\u00f1a",
    "qs:a1":"*Barcelona",
    "qs:a1r":"0Catalu\u00f1a",
    "qs:adm0":"Espa\u00f1a",
    "qs:la_lc":"*",
    "qs:level":"locality",
    "qs:loc":"Gurb",
    "qs:loc_alt":"Gurb",
    "qs:pop":0,
    "qs:type":"buffered point",
    "wd:wordcount":68,
    "wof:lang":[
        "spa"
    ],
    "wof:name":"Gurb",
    "wof:placetype":"locality",
    "wof:population":2196
},
  "geometry": {"coordinates":[2.232554,41.956196],"type":"Point"}
}