{
  "type": "Feature",
  "properties": {
    "gn:admin1_code":"55",
    "gn:admin2_code":"ZA",
    "gn:admin3_code":"49181",
    "gn:asciiname":"Santiago de la Requejada",
    "gn:country_code":"ES",
    "gn:dem":1078,
    "gn:feature_class":"P",
    "gn:feature_code":"PPL",
    "gn:name":"Santiago de la Requejada",
    "gn:population":0,
    "gn:timezone":"Europe/Madrid",
    "iso:country":"ES",
    "wof:name":"Santiago de la Requejada",
    "wof:placetype":"locality"
},
  "geometry": {"coordinates":[-6.55652,42.10166],"type":"Point"}
}