{
  "type": "Feature",
  "properties": {
    "gn:country":"ES",
    "gn:fcode":"PPLA3",
    "gn:population":916,
    "iso:country":"ES",
    "name:arg_x_preferred":[
        "Camarasa"
    ],
    "name:ast_x_preferred":[
        "Camarasa"
    ],
    "name:cat_x_preferred":[
        "Camarasa"
    ],
    "name:cat_x_variant":[
        "Camarassa"
    ],
    "name:ceb_x_preferred":[
        "Camarasa"
    ],
    "name:deu_x_preferred":[
        "Camarasa"
    ],
    "name:eng_x_preferred":[
        "Camarassa"
    ],
    "name:eng_x_variant":[
        "Camarasa"
    ],
    "name:eus_x_preferred":[
        "Camarassa"
    ],
    "name:eus_x_variant":[
        "Camarasa"
    ],
    "name:fra_x_preferred":[
        "Camarasa"
    ],
    "name:hun_x_preferred":[
        "Camarasa"
    ],
    "name:hye_x_preferred":[
        "\u053f\u0561\u0574\u0561\u0580\u0561\u057d\u0561"
    ],
    "name:ita_x_preferred":[
        "Camarasa"
    ],
    "name:msa_x_preferred":[
        "Camarasa"
    ],
    "name:nld_x_preferred":[
        "Camarasa"
    ],
    "name:oci_x_preferred":[
        "Camarassa"
    ],
    "name:oci_x_variant":[
        "Camarasa"
    ],
    "name:pol_x_preferred":[
        "Camarasa"
    ],
    "name:por_x_preferred":[
        "Camarasa"
    ],
    "name:ron_x_preferred":[
        "Camarasa"
    ],
    "name:rus_x_preferred":[
        "\u041a\u0430\u043c\u0430\u0440\u0430\u0441\u0430"
    ],
    "name:sco_x_preferred":[
        "Camarasa"
    ],
    "name:spa_x_preferred":[
        "Camarasa"
    ],
    "name:sqi_x_preferred":[
        "Camarasa"
    ],
    "name:swe_x_preferred":[
        "Camarasa"
    ],
    "name:uzb_x_preferred":[
        "Camarasa"
    ],
    "name:vie_x_preferred":[
        "Camarasa"
    ],
    "name:war_x_preferred":[
        "Camarasa"
    ],
    "name:zho_x_preferred":[
        "\u5361\u9a6c\u62c9\u8428"
    ],
    "qs_pg:aaroncc":"ES",
    "qs_pg:gn_country":"ES",
    "qs_pg:gn_fcode":"PPLA3",
    "qs_pg:gn_pop":916,
    "qs_pg:name":"Camarasa",
    "qs_pg:name_adm0":"Espa\u00f1a",
    "qs_pg:name_adm1":"Catalunya",
    "qs_pg:photos":331,
    "qs_pg:photos_1k":67,
    "qs_pg:photos_9k":1,
    "qs_pg:photos_9r":5,
    "qs_pg:photos_all":331,
    "qs_pg:photos_sr":5,
    "qs_pg:pop_sr":2,
    "qs_pg:qs_pg_placetype":"locality",
    "qs_pg:qs_pg_placetype_gp":"Town",
    "qs_pg:woe_adm0":23424950,
    "woe:adm0_id":23424950,
    "woe:name_adm0":"Espa\u00f1a",
    "woe:name_adm1":"Catalunya",
    "woe:placetype":"Town",
    "wof:name":"Camarasa",
    "wof:placetype":"locality",
    "wof:population":916
},
  "geometry": {"coordinates":[0.87814,41.87486],"type":"Point"}
}