{
  "type": "Feature",
  "properties": {
    "gn:admin1_code":"55",
    "gn:admin2_code":"SO",
    "gn:admin3_code":"42162",
    "gn:asciiname":"Velilla de San Esteban",
    "gn:country_code":"ES",
    "gn:dem":860,
    "gn:feature_class":"P",
    "gn:feature_code":"PPL",
    "gn:name":"Velilla de San Esteban",
    "gn:population":0,
    "gn:timezone":"Europe/Madrid",
    "iso:country":"ES",
    "wof:name":"Velilla de San Esteban",
    "wof:placetype":"locality"
},
  "geometry": {"coordinates":[-3.30393,41.59127],"type":"Point"}
}