{
  "type": "Feature",
  "properties": {
    "gn:admin1_code":"58",
    "gn:admin2_code":"OR",
    "gn:admin3_code":"32007",
    "gn:asciiname":"Alvite",
    "gn:country_code":"ES",
    "gn:dem":552,
    "gn:feature_class":"P",
    "gn:feature_code":"PPL",
    "gn:name":"Alvite",
    "gn:population":0,
    "gn:timezone":"Europe/Madrid",
    "iso:country":"ES",
    "wof:name":"Alvite",
    "wof:placetype":"locality"
},
  "geometry": {"coordinates":[-7.68067,42.24853],"type":"Point"}
}