{
  "type": "Feature",
  "properties": {
    "gn:admin1_code":"58",
    "gn:admin2_code":"OR",
    "gn:admin3_code":"32007",
    "gn:asciiname":"Alvite",
    "gn:country_code":"ES",
    "gn:dem":552,
    "gn:feature_class":"P",
    "gn:feature_code":"PPL",
    "gn:name":"Alvite",
    "gn:population":0,
    "gn:timezone":"Europe/Madrid",
    "iso:country":"ES",
    "name:ceb_x_preferred":[
        "Alvite"
    ],
    "name:deu_x_preferred":[
        "Alvite"
    ],
    "name:fra_x_preferred":[
        "Alvite"
    ],
    "name:glg_x_preferred":[
        "Alvite"
    ],
    "name:por_x_preferred":[
        "Alvite"
    ],
    "name:rus_x_preferred":[
        "\u0410\u043b\u0432\u0438\u0442\u0435"
    ],
    "name:ukr_x_preferred":[
        "\u0410\u043b\u0432\u0456\u0442\u0435"
    ],
    "wof:name":"Alvite",
    "wof:placetype":"locality"
},
  "geometry": {"coordinates":[-7.68067,42.24853],"type":"Point"}
}