{
  "type": "Feature",
  "properties": {
    "gn:admin1_code":"54",
    "gn:admin2_code":"AB",
    "gn:admin3_code":"02019",
    "gn:asciiname":"Sotuelamos",
    "gn:country_code":"ES",
    "gn:dem":860,
    "gn:feature_class":"P",
    "gn:feature_code":"PPL",
    "gn:name":"Sotu\u00e9lamos",
    "gn:population":0,
    "gn:timezone":"Europe/Madrid",
    "iso:country":"ES",
    "name:und_x_variant":[
        "Caser\u00edo Sotu\u00e9lamos",
        "Sotu\u00e9lamos"
    ],
    "wof:name":"Sotuelamos",
    "wof:placetype":"locality"
},
  "geometry": {"coordinates":[-2.57439,39.04018],"type":"Point"}
}