{
  "type": "Feature",
  "properties": {
    "gn:admin1_code":"55",
    "gn:admin2_code":"BU",
    "gn:admin3_code":"09059",
    "gn:asciiname":"Villalonquejar",
    "gn:country_code":"ES",
    "gn:dem":832,
    "gn:feature_class":"P",
    "gn:feature_code":"PPL",
    "gn:name":"Villalonqu\u00e9jar",
    "gn:population":0,
    "gn:timezone":"Europe/Madrid",
    "iso:country":"ES",
    "wof:name":"Villalonquejar",
    "wof:placetype":"locality"
},
  "geometry": {"coordinates":[-3.77277,42.36102],"type":"Point"}
}