{
  "type": "Feature",
  "properties": {
    "gn:admin1_code":"07",
    "gn:admin2_code":"PM",
    "gn:admin3_code":"07015",
    "gn:asciiname":"Urbanitzacio Tamarinda",
    "gn:country_code":"ES",
    "gn:dem":6,
    "gn:feature_class":"P",
    "gn:feature_code":"PPL",
    "gn:name":"Urbanitzaci\u00f3 Tamarinda",
    "gn:population":0,
    "gn:timezone":"Europe/Madrid",
    "iso:country":"ES",
    "wof:name":"Urbanitzacio Tamarinda",
    "wof:placetype":"locality"
},
  "geometry": {"coordinates":[3.82419,39.92356],"type":"Point"}
}