{
  "type": "Feature",
  "properties": {
    "gn:gn_country":"ES",
    "gn:gn_fcode":"PPLA3",
    "gn:gn_pop":72,
    "gn:population":72,
    "iso:country":"ES",
    "name:arg_x_preferred":[
        "Brieva de Cameros"
    ],
    "name:cat_x_preferred":[
        "Brieva de Cameros"
    ],
    "name:eng_x_preferred":[
        "Brieva de Cameros"
    ],
    "name:eus_x_preferred":[
        "Brieva de Cameros"
    ],
    "name:fra_x_preferred":[
        "Brieva de Cameros"
    ],
    "name:hun_x_preferred":[
        "Brieva de Cameros"
    ],
    "name:hye_x_preferred":[
        "\u0532\u0580\u056b\u0587\u0561 \u0564\u0565 \u053f\u0561\u0574\u0565\u0580\u0578\u057d"
    ],
    "name:ita_x_preferred":[
        "Brieva de Cameros"
    ],
    "name:kaz_x_preferred":[
        "\u0411\u0440\u044c\u0435\u0432\u0430-\u0434\u0435-\u041a\u0430\u043c\u0435\u0440\u043e\u0441"
    ],
    "name:ltz_x_preferred":[
        "Brieva de Cameros"
    ],
    "name:msa_x_preferred":[
        "Brieva de Cameros"
    ],
    "name:nan_x_preferred":[
        "Brieva de Cameros"
    ],
    "name:nld_x_preferred":[
        "Brieva de Cameros"
    ],
    "name:oci_x_preferred":[
        "Brieva de Cameros"
    ],
    "name:pol_x_preferred":[
        "Brieva de Cameros"
    ],
    "name:por_x_preferred":[
        "Brieva de Cameros"
    ],
    "name:rup_x_preferred":[
        "Brieva de Cameros"
    ],
    "name:rus_x_preferred":[
        "\u0411\u0440\u044c\u0435\u0432\u0430-\u0434\u0435-\u041a\u0430\u043c\u0435\u0440\u043e\u0441"
    ],
    "name:spa_x_preferred":[
        "Brieva de Cameros"
    ],
    "name:swe_x_preferred":[
        "Brieva de Cameros"
    ],
    "name:ukr_x_preferred":[
        "\u0411\u0440\u0456\u0454\u0432\u0430-\u0434\u0435-\u041a\u0430\u043c\u0435\u0440\u043e\u0441"
    ],
    "name:uzb_x_preferred":[
        "Brieva de Cameros"
    ],
    "name:vie_x_preferred":[
        "Brieva de Cameros"
    ],
    "name:war_x_preferred":[
        "Brieva de Cameros"
    ],
    "name:zho_x_preferred":[
        "\u5e03\u5217\u74e6\u5fb7\u5361\u6885\u7f57\u65af"
    ],
    "qs_pg:aaroncc":"ES",
    "qs_pg:gn_country":"ES",
    "qs_pg:gn_fcode":"PPLA3",
    "qs_pg:gn_pop":72,
    "qs_pg:name":"Brieva de Cameros",
    "qs_pg:name_adm0":"Espa\u00f1a",
    "qs_pg:name_adm1":"La Rioja",
    "qs_pg:photos_9k":1,
    "qs_pg:photos_9r":1,
    "qs_pg:photos_all":7,
    "qs_pg:photos_sr":0,
    "qs_pg:pop_sr":1,
    "qs_pg:qs_pg_placetype":"locality",
    "qs_pg:qs_pg_placetype_gp":"Town",
    "qs_pg:woe_adm0":23424950,
    "woe:adm0_id":23424950,
    "woe:name_adm0":"Espa\u00f1a",
    "woe:name_adm1":"La Rioja",
    "woe:placetype":"Town",
    "wof:name":"Brieva de Cameros",
    "wof:placetype":"locality",
    "wof:population":72
},
  "geometry": {"coordinates":[-2.7945,42.16462],"type":"Point"}
}