{
  "type": "Feature",
  "properties": {
    "gn:admin1_code":"59",
    "gn:admin2_code":"VI",
    "gn:admin3_code":"01059",
    "gn:asciiname":"Arangiz",
    "gn:country_code":"ES",
    "gn:dem":510,
    "gn:feature_class":"P",
    "gn:feature_code":"PPL",
    "gn:name":"Arangiz",
    "gn:population":0,
    "gn:timezone":"Europe/Madrid",
    "iso:country":"ES",
    "name:eus_x_preferred":[
        "Arangiz"
    ],
    "name:spa_x_preferred":[
        "Aranguiz"
    ],
    "name:spa_x_variant":[
        "Ar\u00e1nguiz"
    ],
    "wof:name":"Arangiz",
    "wof:placetype":"locality"
},
  "geometry": {"coordinates":[-2.69979,42.88838],"type":"Point"}
}