{
  "type": "Feature",
  "properties": {
    "gn:admin1_code":"34",
    "gn:admin2_code":"O",
    "gn:admin3_code":"33004",
    "gn:asciiname":"Heros",
    "gn:country_code":"ES",
    "gn:dem":35,
    "gn:feature_class":"P",
    "gn:feature_code":"PPL",
    "gn:name":"Heros",
    "gn:population":0,
    "gn:timezone":"Europe/Madrid",
    "iso:country":"ES",
    "name:bul_x_preferred":[
        "\u0425\u0435\u0440\u043e\u0441"
    ],
    "name:deu_x_preferred":[
        "Heros"
    ],
    "name:nld_x_preferred":[
        "Heros"
    ],
    "name:nor_x_preferred":[
        "Heros"
    ],
    "name:pol_x_preferred":[
        "Heros"
    ],
    "wof:name":"Heros",
    "wof:placetype":"locality"
},
  "geometry": {"coordinates":[-5.93333,43.55],"type":"Point"}
}