{
  "type": "Feature",
  "properties": {
    "gn:admin1_code":"58",
    "gn:admin2_code":"LU",
    "gn:admin3_code":"27031",
    "gn:asciiname":"Valverde",
    "gn:country_code":"ES",
    "gn:dem":369,
    "gn:feature_class":"P",
    "gn:feature_code":"PPL",
    "gn:name":"Valverde",
    "gn:population":0,
    "gn:timezone":"Europe/Madrid",
    "iso:country":"ES",
    "wof:name":"Valverde",
    "wof:placetype":"locality"
},
  "geometry": {"coordinates":[-7.48401,42.5722],"type":"Point"}
}