{
  "type": "Feature",
  "properties": {
    "gn:admin1_code":"51",
    "gn:admin2_code":"AL",
    "gn:admin3_code":"04088",
    "gn:asciiname":"Marchante",
    "gn:country_code":"ES",
    "gn:dem":595,
    "gn:feature_class":"P",
    "gn:feature_code":"PPL",
    "gn:name":"Marchante",
    "gn:population":0,
    "gn:timezone":"Europe/Madrid",
    "iso:country":"ES",
    "name:und_x_variant":[
        "Caser\u00edo Marchante",
        "Marchante"
    ],
    "wof:name":"Marchante",
    "wof:placetype":"locality"
},
  "geometry": {"coordinates":[-2.3429,37.02866],"type":"Point"}
}