{
  "type": "Feature",
  "properties": {
    "gn:country":"ES",
    "gn:fcode":"PPL",
    "gn:population":0,
    "iso:country":"ES",
    "name:ara_x_preferred":[
        "\u0644\u0627\u0633 \u0645\u062f\u0648\u0644\u0627\u0633"
    ],
    "name:ast_x_preferred":[
        "Las M\u00e9dulas"
    ],
    "name:cat_x_preferred":[
        "Les M\u00e8dules"
    ],
    "name:ces_x_preferred":[
        "Las M\u00e9dulas"
    ],
    "name:dan_x_preferred":[
        "Las M\u00e9dulas"
    ],
    "name:deu_x_preferred":[
        "Las M\u00e9dulas"
    ],
    "name:ell_x_preferred":[
        "\u039b\u03b1\u03c2 \u039c\u03ad\u03b4\u03bf\u03c5\u03bb\u03b1\u03c2"
    ],
    "name:epo_x_preferred":[
        "Las M\u00e9dulas"
    ],
    "name:eus_x_preferred":[
        "Las M\u00e9dulas"
    ],
    "name:fas_x_preferred":[
        "\u0644\u0627\u0633 \u0645\u062f\u0648\u0644\u0627\u0633"
    ],
    "name:fin_x_preferred":[
        "Las M\u00e9dulas"
    ],
    "name:fra_x_preferred":[
        "Las M\u00e9dulas"
    ],
    "name:glg_x_preferred":[
        "As M\u00e9dulas"
    ],
    "name:hrv_x_preferred":[
        "Las M\u00e9dulas"
    ],
    "name:hun_x_preferred":[
        "Las M\u00e9dulas"
    ],
    "name:hye_x_preferred":[
        "\u053c\u0561\u057d \u0544\u0565\u0564\u0578\u0582\u056c\u0561\u057d"
    ],
    "name:ita_x_preferred":[
        "Las M\u00e9dulas"
    ],
    "name:jpn_x_preferred":[
        "\u30e9\u30b9\u30fb\u30e1\u30c9\u30a5\u30e9\u30b9"
    ],
    "name:kat_x_preferred":[
        "\u10da\u10d0\u10e1-\u10db\u10d4\u10d3\u10e3\u10da\u10d0\u10e1\u10d8"
    ],
    "name:lit_x_preferred":[
        "Las M\u00e9dulas"
    ],
    "name:ltz_x_preferred":[
        "Las M\u00e9dulas"
    ],
    "name:mal_x_preferred":[
        "\u0d32\u0d3e\u0d38\u0d4d \u0d2e\u0d46\u0d21\u0d41\u0d32\u0d3e\u0d38\u0d4d"
    ],
    "name:nld_x_preferred":[
        "Las M\u00e9dulas"
    ],
    "name:pol_x_preferred":[
        "Las M\u00e9dulas"
    ],
    "name:por_x_preferred":[
        "Las M\u00e9dulas"
    ],
    "name:rus_x_preferred":[
        "\u041b\u0430\u0441-\u041c\u0435\u0434\u0443\u043b\u0430\u0441"
    ],
    "name:slk_x_preferred":[
        "Las M\u00e9dulas"
    ],
    "name:spa_x_preferred":[
        "Las M\u00e9dulas"
    ],
    "name:swe_x_preferred":[
        "Las M\u00e9dulas"
    ],
    "name:tur_x_preferred":[
        "Las M\u00e9dulas"
    ],
    "name:vie_x_preferred":[
        "Las M\u00e9dulas"
    ],
    "name:zho_x_preferred":[
        "\u62c9\u65af\u6885\u5fb7\u62c9\u65af"
    ],
    "qs_pg:aaroncc":"ES",
    "qs_pg:gn_country":"ES",
    "qs_pg:gn_fcode":"PPL",
    "qs_pg:gn_pop":0,
    "qs_pg:name":"Las M\u00e9dulas",
    "qs_pg:name_adm0":"Espa\u00f1a",
    "qs_pg:name_adm1":"Castilla y Le\u00f3n",
    "qs_pg:photos":1151,
    "qs_pg:photos_1k":233,
    "qs_pg:photos_9k":5,
    "qs_pg:photos_9r":7,
    "qs_pg:photos_all":1151,
    "qs_pg:photos_sr":11,
    "qs_pg:pop_sr":0,
    "qs_pg:qs_pg_placetype":"locality",
    "qs_pg:qs_pg_placetype_gp":"Town",
    "qs_pg:woe_adm0":23424950,
    "woe:adm0_id":23424950,
    "woe:name_adm0":"Espa\u00f1a",
    "woe:name_adm1":"Castilla y Le\u00f3n",
    "woe:placetype":"Town",
    "wof:name":"Las M\u00e9dulas",
    "wof:placetype":"locality"
},
  "geometry": {"coordinates":[-6.76844,42.45842],"type":"Point"}
}