{
  "type": "Feature",
  "properties": {
    "gn:admin1_code":"58",
    "gn:admin2_code":"LU",
    "gn:admin3_code":"27034",
    "gn:asciiname":"Faquis",
    "gn:country_code":"ES",
    "gn:dem":799,
    "gn:feature_class":"P",
    "gn:feature_code":"PPL",
    "gn:name":"Faqu\u00eds",
    "gn:population":0,
    "gn:timezone":"Europe/Madrid",
    "iso:country":"ES",
    "wof:name":"Faquis",
    "wof:placetype":"locality"
},
  "geometry": {"coordinates":[-6.88333,42.95],"type":"Point"}
}