{
  "type": "Feature",
  "properties": {
    "iso:country":"ES",
    "name:eng_x_preferred":[
        "Industrial Alcade Diaz Zafra"
    ],
    "name:spa_x_preferred":[
        "Industrial Alcade Diaz Zafra"
    ],
    "wof:name":"Industrial Alcade Diaz Zafra",
    "wof:placetype":"neighbourhood"
},
  "geometry": {"coordinates":[-4.45058066905054,36.70780569413726],"type":"Point"}
}