{
  "type": "Feature",
  "properties": {
    "gn:admin1_code":"34",
    "gn:admin2_code":"O",
    "gn:admin3_code":"33073",
    "gn:asciiname":"Penafolgueros",
    "gn:country_code":"ES",
    "gn:dem":682,
    "gn:feature_class":"P",
    "gn:feature_code":"PPL",
    "gn:name":"Pe\u00f1afolgueros",
    "gn:population":0,
    "gn:timezone":"Europe/Madrid",
    "iso:country":"ES",
    "name:und_x_variant":[
        "Pe\u00f1afolgueros"
    ],
    "wof:name":"Penafolgueros",
    "wof:placetype":"locality"
},
  "geometry": {"coordinates":[-6.43523,43.39788],"type":"Point"}
}