{
  "type": "Feature",
  "properties": {
    "gn:admin1_code":"56",
    "gn:admin2_code":"L",
    "gn:admin3_code":"25089",
    "gn:asciiname":"Mallolis",
    "gn:country_code":"ES",
    "gn:dem":1276,
    "gn:feature_class":"P",
    "gn:feature_code":"PPL",
    "gn:name":"Mallol\u00eds",
    "gn:population":0,
    "gn:timezone":"Europe/Madrid",
    "iso:country":"ES",
    "name:und_x_variant":[
        "Mallol\u00eds"
    ],
    "wof:name":"Mallolis",
    "wof:placetype":"locality"
},
  "geometry": {"coordinates":[1.25785,42.49497],"type":"Point"}
}