{
  "type": "Feature",
  "properties": {
    "gn:admin1_code":"51",
    "gn:admin2_code":"J",
    "gn:admin3_code":"23041",
    "gn:asciiname":"Higuera de Calatrava",
    "gn:country_code":"ES",
    "gn:dem":356,
    "gn:feature_class":"P",
    "gn:feature_code":"PPLA3",
    "gn:name":"Higuera de Calatrava",
    "gn:population":709,
    "gn:timezone":"Europe/Madrid",
    "iso:country":"ES",
    "name:ara_x_preferred":[
        "\u0625\u063a\u064a\u0631\u0627 \u062f\u064a \u0643\u0627\u0644\u0627\u062a\u0631\u0627\u0641\u0627"
    ],
    "name:hye_x_preferred":[
        "\u053b\u0563\u0565\u0580\u0561 \u0564\u0565 \u053f\u0561\u056c\u0561\u057f\u0580\u0561\u057e\u0561"
    ],
    "name:rus_x_preferred":[
        "\u0418\u0433\u0435\u0440\u0430-\u0434\u0435-\u041a\u0430\u043b\u0430\u0442\u0440\u0430\u0432\u0430"
    ],
    "name:ukr_x_preferred":[
        "\u0406\u0433\u0435\u0440\u0430-\u0434\u0435-\u041a\u0430\u043b\u0430\u0442\u0440\u0430\u0432\u0430"
    ],
    "name:zho_x_preferred":[
        "\u4f0a\u683c\u62c9\u5fb7\u5361\u62c9\u7279\u62c9\u74e6"
    ],
    "wof:name":"Higuera de Calatrava",
    "wof:placetype":"locality",
    "wof:population":709
},
  "geometry": {"coordinates":[-4.15737,37.79848],"type":"Point"}
}