{
  "type": "Feature",
  "properties": {
    "gn:admin1_code":"51",
    "gn:admin2_code":"J",
    "gn:admin3_code":"23041",
    "gn:asciiname":"Higuera de Calatrava",
    "gn:country_code":"ES",
    "gn:dem":356,
    "gn:feature_class":"P",
    "gn:feature_code":"PPLA3",
    "gn:name":"Higuera de Calatrava",
    "gn:population":709,
    "gn:timezone":"Europe/Madrid",
    "iso:country":"ES",
    "wof:name":"Higuera de Calatrava",
    "wof:placetype":"locality",
    "wof:population":709
},
  "geometry": {"coordinates":[-4.15737,37.79848],"type":"Point"}
}