{
  "type": "Feature",
  "properties": {
    "gn:admin1_code":"55",
    "gn:admin2_code":"BU",
    "gn:admin3_code":"09041",
    "gn:asciiname":"Barrio de Muno",
    "gn:country_code":"ES",
    "gn:dem":775,
    "gn:feature_class":"P",
    "gn:feature_code":"PPLA3",
    "gn:name":"Barrio de Mu\u00f1\u00f3",
    "gn:population":32,
    "gn:timezone":"Europe/Madrid",
    "iso:country":"ES",
    "name:ara_x_preferred":[
        "\u0628\u0627\u0631\u0627\u064a\u0648 \u062f\u064a \u0645\u0648\u0646\u064a\u0648"
    ],
    "name:fas_x_preferred":[
        "\u0628\u0627\u0631\u06cc\u0648 \u062f \u0645\u0648\u0646\u06cc\u0648"
    ],
    "name:rus_x_preferred":[
        "\u0411\u0430\u0440\u0440\u0438\u043e-\u0434\u0435-\u041c\u0443\u043d\u044c\u043e"
    ],
    "name:ukr_x_preferred":[
        "\u0411\u0430\u0440\u0440\u0456\u043e-\u0434\u0435-\u041c\u0443\u043d\u044c\u0439\u043e"
    ],
    "name:und_x_variant":[
        "Barrio de Mu\u00f1\u00f3"
    ],
    "name:zho_x_preferred":[
        "\u5df4\u91cc\u5965\u5fb7\u7a46\u5c3c\u5965"
    ],
    "wof:name":"Barrio de Muno",
    "wof:placetype":"locality",
    "wof:population":32
},
  "geometry": {"coordinates":[-4.00715,42.17584],"type":"Point"}
}