{
  "type": "Feature",
  "properties": {
    "gn:country":"ES",
    "gn:fcode":"PPL",
    "gn:population":0,
    "iso:country":"ES",
    "name:ara_x_preferred":[
        "\u062c\u0627\u0648\u064a\u0627"
    ],
    "name:aym_x_preferred":[
        "Xauxa"
    ],
    "name:ben_x_preferred":[
        "\u099c\u09be\u0989\u099c\u09be"
    ],
    "name:ceb_x_preferred":[
        "Jauja"
    ],
    "name:deu_x_preferred":[
        "Jauja"
    ],
    "name:ell_x_preferred":[
        "\u03a7\u03ac\u03bf\u03c5\u03c7\u03b1"
    ],
    "name:epo_x_preferred":[
        "Jauja"
    ],
    "name:fas_x_preferred":[
        "\u062e\u0627\u0648\u062e\u0627"
    ],
    "name:fra_x_preferred":[
        "Jauja"
    ],
    "name:hin_x_preferred":[
        "\u0939\u0941\u0906\u091c\u093e"
    ],
    "name:hun_x_preferred":[
        "Jauja"
    ],
    "name:ind_x_preferred":[
        "Jauja"
    ],
    "name:ita_x_preferred":[
        "Jauja"
    ],
    "name:kor_x_preferred":[
        "\ud558\uc6b0\ud558"
    ],
    "name:lit_x_preferred":[
        "Chaucha"
    ],
    "name:nor_x_preferred":[
        "Jauja"
    ],
    "name:pol_x_preferred":[
        "Jauja"
    ],
    "name:por_x_preferred":[
        "Jauja"
    ],
    "name:que_x_preferred":[
        "Shawsha"
    ],
    "name:rus_x_preferred":[
        "\u0425\u0430\u0443\u0445\u0430"
    ],
    "name:sco_x_preferred":[
        "Jauja"
    ],
    "name:spa_x_preferred":[
        "Jauja"
    ],
    "name:swe_x_preferred":[
        "Jauja"
    ],
    "name:tur_x_preferred":[
        "Jauja"
    ],
    "name:ukr_x_preferred":[
        "\u0425\u0430\u0443\u0445\u0430"
    ],
    "name:urd_x_preferred":[
        "\u062c\u0627\u0648\u062c\u0627"
    ],
    "name:vie_x_preferred":[
        "Jauja"
    ],
    "name:war_x_preferred":[
        "Jauja"
    ],
    "qs_pg:aaroncc":"ES",
    "qs_pg:gn_country":"ES",
    "qs_pg:gn_fcode":"PPL",
    "qs_pg:gn_pop":0,
    "qs_pg:name":"Jauja",
    "qs_pg:name_adm0":"Espa\u00f1a",
    "qs_pg:name_adm1":"Andaluc\u00eda",
    "qs_pg:photos":26,
    "qs_pg:photos_1k":5,
    "qs_pg:photos_9k":1,
    "qs_pg:photos_9r":2,
    "qs_pg:photos_all":26,
    "qs_pg:photos_sr":2,
    "qs_pg:pop_sr":0,
    "qs_pg:qs_pg_placetype":"locality",
    "qs_pg:qs_pg_placetype_gp":"Town",
    "qs_pg:woe_adm0":23424950,
    "woe:adm0_id":23424950,
    "woe:name_adm0":"Espa\u00f1a",
    "woe:name_adm1":"Andaluc\u00eda",
    "woe:placetype":"Town",
    "wof:name":"Jauja",
    "wof:placetype":"locality"
},
  "geometry": {"coordinates":[-4.65564,37.30295],"type":"Point"}
}