{
  "type": "Feature",
  "properties": {
    "gn:admin1_code":"51",
    "gn:admin2_code":"SE",
    "gn:admin3_code":"41095",
    "gn:asciiname":"El Torviscal",
    "gn:country_code":"ES",
    "gn:dem":18,
    "gn:feature_class":"P",
    "gn:feature_code":"PPL",
    "gn:name":"El Torviscal",
    "gn:population":0,
    "gn:timezone":"Europe/Madrid",
    "iso:country":"ES",
    "wof:name":"El Torviscal",
    "wof:placetype":"locality"
},
  "geometry": {"coordinates":[-5.85628,37.08419],"type":"Point"}
}