{
  "type": "Feature",
  "properties": {
    "gn:admin1_code":"55",
    "gn:admin2_code":"LE",
    "gn:admin3_code":"24038",
    "gn:asciiname":"Villadepalos",
    "gn:country_code":"ES",
    "gn:dem":443,
    "gn:feature_class":"P",
    "gn:feature_code":"PPL",
    "gn:name":"Villadepalos",
    "gn:population":0,
    "gn:timezone":"Europe/Madrid",
    "iso:country":"ES",
    "wof:name":"Villadepalos",
    "wof:placetype":"locality"
},
  "geometry": {"coordinates":[-6.74966,42.53984000000001],"type":"Point"}
}