{
  "type": "Feature",
  "properties": {
    "gn:admin1_code":"55",
    "gn:admin2_code":"SG",
    "gn:admin3_code":"40024",
    "gn:asciiname":"Saldana de Ayllon",
    "gn:country_code":"ES",
    "gn:dem":1000,
    "gn:feature_class":"P",
    "gn:feature_code":"PPL",
    "gn:name":"Salda\u00f1a de Ayll\u00f3n",
    "gn:population":0,
    "gn:timezone":"Europe/Madrid",
    "iso:country":"ES",
    "name:und_x_variant":[
        "Salda\u00f1a de Ayll\u00f3n"
    ],
    "wof:name":"Saldana de Ayllon",
    "wof:placetype":"locality"
},
  "geometry": {"coordinates":[-3.4231,41.38528],"type":"Point"}
}