{
  "type": "Feature",
  "properties": {
    "gn:admin1_code":"58",
    "gn:admin2_code":"LU",
    "gn:admin3_code":"27039",
    "gn:asciiname":"Vilela",
    "gn:cc2":"ES",
    "gn:country_code":"ES",
    "gn:dem":409,
    "gn:feature_class":"P",
    "gn:feature_code":"PPL",
    "gn:name":"Vilela",
    "gn:population":0,
    "gn:timezone":"Europe/Madrid",
    "iso:country":"ES",
    "name:und_x_variant":[
        "Santiago",
        "Vilella",
        "Vilela"
    ],
    "wof:name":"Vilela",
    "wof:placetype":"locality"
},
  "geometry": {"coordinates":[-7.55,43.13333],"type":"Point"}
}