{
  "type": "Feature",
  "properties": {
    "gn:admin1_code":"55",
    "gn:admin2_code":"BU",
    "gn:admin3_code":"09030",
    "gn:asciiname":"Sopena",
    "gn:country_code":"ES",
    "gn:dem":914,
    "gn:feature_class":"P",
    "gn:feature_code":"PPL",
    "gn:name":"Sope\u00f1a",
    "gn:population":0,
    "gn:timezone":"Europe/Madrid",
    "iso:country":"ES",
    "wof:name":"Sopena",
    "wof:placetype":"locality"
},
  "geometry": {"coordinates":[-3.58332,42.22978],"type":"Point"}
}