{
  "type": "Feature",
  "properties": {
    "gn:admin1_code":"39",
    "gn:admin2_code":"S",
    "gn:admin3_code":"39015",
    "gn:asciiname":"Mieses",
    "gn:country_code":"ES",
    "gn:dem":416,
    "gn:feature_class":"P",
    "gn:feature_code":"PPL",
    "gn:name":"Mieses",
    "gn:population":0,
    "gn:timezone":"Europe/Madrid",
    "iso:country":"ES",
    "wof:name":"Mieses",
    "wof:placetype":"locality"
},
  "geometry": {"coordinates":[-4.64063,43.1519],"type":"Point"}
}