{
  "type": "Feature",
  "properties": {
    "gn:country":"ES",
    "gn:fcode":"PPL",
    "gn:population":105,
    "iso:country":"ES",
    "name:cat_x_preferred":[
        "Sant Pere Despuig"
    ],
    "name:ceb_x_preferred":[
        "Sant Pere Despuig"
    ],
    "name:eng_x_preferred":[
        "Sant Pere Despuig"
    ],
    "name:fra_x_preferred":[
        "Sant Pere Despuig"
    ],
    "name:oci_x_preferred":[
        "Sant Pere Despuig"
    ],
    "name:spa_x_preferred":[
        "Sant Pere Despuig"
    ],
    "name:swe_x_preferred":[
        "Sant Pere Despuig"
    ],
    "name:tah_x_preferred":[
        "Sant Pere Despuig"
    ],
    "qs_pg:aaroncc":"ES",
    "qs_pg:gn_country":"ES",
    "qs_pg:gn_fcode":"PPL",
    "qs_pg:gn_pop":105,
    "qs_pg:name":"Sant Pere Despuig",
    "qs_pg:name_adm0":"Espa\u00f1a",
    "qs_pg:name_adm1":"Catalunya",
    "qs_pg:photos":12,
    "qs_pg:photos_1k":2,
    "qs_pg:photos_9k":1,
    "qs_pg:photos_9r":1,
    "qs_pg:photos_all":12,
    "qs_pg:photos_sr":1,
    "qs_pg:pop_sr":1,
    "qs_pg:qs_pg_placetype":"locality",
    "qs_pg:qs_pg_placetype_gp":"Town",
    "qs_pg:woe_adm0":23424950,
    "woe:adm0_id":23424950,
    "woe:name_adm0":"Espa\u00f1a",
    "woe:name_adm1":"Catalunya",
    "woe:placetype":"Town",
    "wof:name":"Sant Pere Despuig",
    "wof:placetype":"locality",
    "wof:population":105
},
  "geometry": {"coordinates":[2.43333,42.21667],"type":"Point"}
}