{
  "type": "Feature",
  "properties": {
    "gn:admin1_code":"34",
    "gn:admin2_code":"O",
    "gn:admin3_code":"33022",
    "gn:asciiname":"Fondovegas",
    "gn:country_code":"ES",
    "gn:dem":750,
    "gn:feature_class":"P",
    "gn:feature_code":"PPL",
    "gn:name":"Fondovegas",
    "gn:population":0,
    "gn:timezone":"Europe/Madrid",
    "iso:country":"ES",
    "wof:name":"Fondovegas",
    "wof:placetype":"locality"
},
  "geometry": {"coordinates":[-6.61485,42.95406],"type":"Point"}
}