{
  "type": "Feature",
  "properties": {
    "gn:admin1_code":"60",
    "gn:admin2_code":"V",
    "gn:admin3_code":"46213",
    "gn:asciiname":"Los Ochandos",
    "gn:cc2":"ES",
    "gn:country_code":"ES",
    "gn:dem":692,
    "gn:feature_class":"P",
    "gn:feature_code":"PPL",
    "gn:name":"Los Ochandos",
    "gn:population":0,
    "gn:timezone":"Europe/Madrid",
    "iso:country":"ES",
    "name:und_x_variant":[
        "Caser\u00edo Los Ochandos",
        "Los Ochandos"
    ],
    "wof:name":"Los Ochandos",
    "wof:placetype":"locality"
},
  "geometry": {"coordinates":[-1.15,39.51667],"type":"Point"}
}