{
  "type": "Feature",
  "properties": {
    "gn:admin1_code":"55",
    "gn:admin2_code":"BU",
    "gn:admin3_code":"09048",
    "gn:asciiname":"Loranquillo",
    "gn:country_code":"ES",
    "gn:dem":754,
    "gn:feature_class":"P",
    "gn:feature_code":"PPL",
    "gn:name":"Loranquillo",
    "gn:population":0,
    "gn:timezone":"Europe/Madrid",
    "iso:country":"ES",
    "name:und_x_variant":[
        "Loranguillo",
        "Loranquillo"
    ],
    "wof:name":"Loranquillo",
    "wof:placetype":"locality"
},
  "geometry": {"coordinates":[-3.19971,42.48049],"type":"Point"}
}