{
  "type": "Feature",
  "properties": {
    "gn:admin1_code":"51",
    "gn:admin2_code":"CO",
    "gn:admin3_code":"14029",
    "gn:asciiname":"Piconcillo",
    "gn:country_code":"ES",
    "gn:dem":588,
    "gn:feature_class":"P",
    "gn:feature_code":"PPL",
    "gn:name":"Piconcillo",
    "gn:population":0,
    "gn:timezone":"Europe/Madrid",
    "iso:country":"ES",
    "wof:name":"Piconcillo",
    "wof:placetype":"locality"
},
  "geometry": {"coordinates":[-5.46626,38.17727],"type":"Point"}
}