{
  "type": "Feature",
  "properties": {
    "gn:admin1_code":"55",
    "gn:admin2_code":"AV",
    "gn:admin3_code":"05064",
    "gn:asciiname":"Jaraices",
    "gn:country_code":"ES",
    "gn:dem":892,
    "gn:feature_class":"P",
    "gn:feature_code":"PPL",
    "gn:name":"Jaraices",
    "gn:population":0,
    "gn:timezone":"Europe/Madrid",
    "iso:country":"ES",
    "wof:name":"Jaraices",
    "wof:placetype":"locality"
},
  "geometry": {"coordinates":[-4.90476,40.94052],"type":"Point"}
}