{
  "type": "Feature",
  "properties": {
    "iso:country":"ES",
    "qs:a0":"Espa\u00f1a",
    "qs:a1":"*Gipuzkoa",
    "qs:a1r":"0Pa\u00eds Vasco",
    "qs:adm0":"Espa\u00f1a",
    "qs:la_lc":"*",
    "qs:level":"locality",
    "qs:loc":"San Martin",
    "qs:loc_alt":"San Martin",
    "qs:pop":0,
    "qs:type":"buffered point",
    "wof:name":"San Martin",
    "wof:placetype":"locality"
},
  "geometry": {"coordinates":[-2.17781,43.006809],"type":"Point"}
}