{
  "type": "Feature",
  "properties": {
    "iso:country":"ES",
    "name:eng_x_preferred":[
        "San Francisco"
    ],
    "name:spa_x_preferred":[
        "San Francisco"
    ],
    "wof:name":"San Francisco",
    "wof:placetype":"neighbourhood"
},
  "geometry": {"coordinates":[-4.36776881064023,36.728914812135],"type":"Point"}
}