{
  "type": "Feature",
  "properties": {
    "gn:country":"ES",
    "gn:fcode":"PPLA3",
    "gn:population":286,
    "iso:country":"ES",
    "name:arg_x_preferred":[
        "Vega de Tirados"
    ],
    "name:azb_x_preferred":[
        "\u0648\u0642\u0627 \u062f\u0648 \u062a\u06cc\u0631\u062f\u0633"
    ],
    "name:cat_x_preferred":[
        "Vega de Tirados"
    ],
    "name:eng_x_preferred":[
        "Vega de Tirados"
    ],
    "name:eus_x_preferred":[
        "Vega de Tirados"
    ],
    "name:fas_x_preferred":[
        "\u0648\u06af\u0627 \u062f\u0648 \u062a\u06cc\u0631\u062f\u0633"
    ],
    "name:fra_x_preferred":[
        "Vega de Tirados"
    ],
    "name:hun_x_preferred":[
        "Vega de Tirados"
    ],
    "name:ina_x_preferred":[
        "Vega de Tirados"
    ],
    "name:ita_x_preferred":[
        "Vega de Tirados"
    ],
    "name:kaz_x_preferred":[
        "\u0412\u0435\u0433\u0430-\u0434\u0435-\u0422\u0438\u0440\u0430\u0434\u043e\u0441"
    ],
    "name:msa_x_preferred":[
        "Vega de Tirados"
    ],
    "name:nan_x_preferred":[
        "Vega de Tirados"
    ],
    "name:nld_x_preferred":[
        "Vega de Tirados"
    ],
    "name:oci_x_preferred":[
        "Vega de Tirados"
    ],
    "name:pol_x_preferred":[
        "Vega de Tirados"
    ],
    "name:por_x_preferred":[
        "Vega de Tirados"
    ],
    "name:rus_x_preferred":[
        "\u0412\u0435\u0433\u0430-\u0434\u0435-\u0422\u0438\u0440\u0430\u0434\u043e\u0441"
    ],
    "name:spa_x_preferred":[
        "Vega de Tirados"
    ],
    "name:swe_x_preferred":[
        "Vega de Tirados"
    ],
    "name:ukr_x_preferred":[
        "\u0412\u0435\u0433\u0430-\u0434\u0435-\u0422\u0456\u0440\u0430\u0434\u043e\u0441"
    ],
    "name:vie_x_preferred":[
        "Vega de Tirados"
    ],
    "name:war_x_preferred":[
        "Vega de Tirados"
    ],
    "name:zho_x_preferred":[
        "\u8d1d\u52a0\u5fb7\u8482\u62c9\u591a\u65af"
    ],
    "qs_pg:aaroncc":"ES",
    "qs_pg:gn_country":"ES",
    "qs_pg:gn_fcode":"PPLA3",
    "qs_pg:gn_pop":286,
    "qs_pg:name":"Vega de Tirados",
    "qs_pg:name_adm0":"Espa\u00f1a",
    "qs_pg:name_adm1":"Castilla y Le\u00f3n",
    "qs_pg:photos_9r":0,
    "qs_pg:photos_sr":0,
    "qs_pg:pop_sr":2,
    "qs_pg:qs_pg_placetype":"locality",
    "qs_pg:qs_pg_placetype_gp":"Town",
    "qs_pg:woe_adm0":23424950,
    "woe:adm0_id":23424950,
    "woe:name_adm0":"Espa\u00f1a",
    "woe:name_adm1":"Castilla y Le\u00f3n",
    "woe:placetype":"Town",
    "wof:name":"Vega de Tirados",
    "wof:placetype":"locality",
    "wof:population":286
},
  "geometry": {"coordinates":[-5.88667,41.02543],"type":"Point"}
}