{
  "type": "Feature",
  "properties": {
    "gn:admin1_code":"54",
    "gn:admin2_code":"GU",
    "gn:admin3_code":"19086",
    "gn:asciiname":"Moranchel",
    "gn:country_code":"ES",
    "gn:dem":909,
    "gn:feature_class":"P",
    "gn:feature_code":"PPL",
    "gn:name":"Moranchel",
    "gn:population":0,
    "gn:timezone":"Europe/Madrid",
    "iso:country":"ES",
    "wof:name":"Moranchel",
    "wof:placetype":"locality"
},
  "geometry": {"coordinates":[-2.6672,40.81817],"type":"Point"}
}