{
  "type": "Feature",
  "properties": {
    "iso:country":"ES",
    "name:cat_x_preferred":[
        "Sant Jordi de ses Salines"
    ],
    "name:dut_x_preferred":[
        "Sant Jordi de ses Salines"
    ],
    "name:eng_x_preferred":[
        "Sant Jordi de ses Salines"
    ],
    "name:fre_x_preferred":[
        "Sant Jordi de ses Salines"
    ],
    "name:ger_x_preferred":[
        "Sant Jordi de ses Salines"
    ],
    "qs_pg:aaroncc":"ES",
    "qs_pg:name":"Sant Jordi de Ses Salines",
    "qs_pg:name_adm0":"Espa\u00f1a",
    "qs_pg:name_adm1":"Illes Balears",
    "qs_pg:photos":250,
    "qs_pg:photos_1k":51,
    "qs_pg:photos_9k":1,
    "qs_pg:photos_9r":4,
    "qs_pg:photos_all":250,
    "qs_pg:photos_sr":4,
    "qs_pg:pop_sr":0,
    "qs_pg:qs_pg_placetype":"locality",
    "qs_pg:qs_pg_placetype_gp":"Town",
    "qs_pg:woe_adm0":23424950,
    "woe:adm0_id":23424950,
    "woe:name_adm0":"Espa\u00f1a",
    "woe:name_adm1":"Illes Balears",
    "woe:placetype":"Town",
    "wof:name":"Sant Jordi de Ses Salines",
    "wof:placetype":"locality"
},
  "geometry": {"coordinates":[1.393053,38.887976],"type":"Point"}
}