{
  "type": "Feature",
  "properties": {
    "gn:admin1_code":"51",
    "gn:admin2_code":"J",
    "gn:admin3_code":"23066",
    "gn:asciiname":"Guadiana",
    "gn:country_code":"ES",
    "gn:dem":364,
    "gn:feature_class":"P",
    "gn:feature_code":"PPL",
    "gn:name":"Guadiana",
    "gn:population":0,
    "gn:timezone":"Europe/Madrid",
    "iso:country":"ES",
    "name:und_x_variant":[
        "Cortijo de Guadiana",
        "Cortijada Guadiana",
        "Guadiana"
    ],
    "wof:name":"Guadiana",
    "wof:placetype":"locality"
},
  "geometry": {"coordinates":[-3.22043,37.90826],"type":"Point"}
}