{
  "type": "Feature",
  "properties": {
    "gn:admin1_code":"56",
    "gn:admin2_code":"B",
    "gn:admin3_code":"08058",
    "gn:asciiname":"Cornudella de Montsant",
    "gn:country_code":"ES",
    "gn:dem":542,
    "gn:elevation":"542.0",
    "gn:feature_class":"P",
    "gn:feature_code":"PPL",
    "gn:name":"Cornudella de Montsant",
    "gn:population":981,
    "gn:timezone":"Europe/Madrid",
    "iso:country":"ES",
    "name:cat_x_preferred":[
        "Cornudella de Montsant"
    ],
    "name:fas_x_preferred":[
        "\u06a9\u0631\u0646\u0648\u062f\u06cc\u0627 \u062f \u0645\u0646\u062a\u0633\u0627\u0646\u062a"
    ],
    "name:hye_x_preferred":[
        "\u053f\u0578\u0580\u0576\u0578\u0582\u0564\u0565\u056c\u0575\u0561 \u0564\u0565 \u0544\u0578\u0576\u057d\u0561\u0576"
    ],
    "name:rus_x_preferred":[
        "\u041a\u043e\u0440\u043d\u0443\u0434\u0435\u043b\u044c\u044f-\u0434\u0435-\u041c\u043e\u043d\u0441\u0430\u043d"
    ],
    "name:spa_x_preferred":[
        "Cornudella"
    ],
    "name:zho_x_preferred":[
        "\u79d1\u5c14\u52aa\u5fb7\u5229\u4e9a\u5fb7\u8499\u7279\u6851\u7279"
    ],
    "wof:name":"Cornudella de Montsant",
    "wof:placetype":"locality",
    "wof:population":981
},
  "geometry": {"coordinates":[0.9052,41.26558],"type":"Point"}
}