{
  "type": "Feature",
  "properties": {
    "gn:admin1_code":"56",
    "gn:admin2_code":"B",
    "gn:admin3_code":"08058",
    "gn:asciiname":"Cornudella de Montsant",
    "gn:country_code":"ES",
    "gn:dem":542,
    "gn:elevation":"542.0",
    "gn:feature_class":"P",
    "gn:feature_code":"PPL",
    "gn:name":"Cornudella de Montsant",
    "gn:population":981,
    "gn:timezone":"Europe/Madrid",
    "iso:country":"ES",
    "name:cat_x_preferred":[
        "Cornudella de Montsant"
    ],
    "name:spa_x_preferred":[
        "Cornudella"
    ],
    "name:und_x_variant":[
        "Cornudella"
    ],
    "wof:name":"Cornudella de Montsant",
    "wof:placetype":"locality",
    "wof:population":981
},
  "geometry": {"coordinates":[0.9052,41.26558],"type":"Point"}
}