{
  "type": "Feature",
  "properties": {
    "gn:admin1_code":"54",
    "gn:admin2_code":"CR",
    "gn:admin3_code":"13015",
    "gn:asciiname":"Navacerrada",
    "gn:country_code":"ES",
    "gn:dem":664,
    "gn:feature_class":"P",
    "gn:feature_code":"PPL",
    "gn:name":"Navacerrada",
    "gn:population":0,
    "gn:timezone":"Europe/Madrid",
    "iso:country":"ES",
    "name:ara_x_preferred":[
        "\u0646\u0627\u0641\u0627\u0633\u064a\u0631\u0627\u062f\u0627"
    ],
    "name:cat_x_preferred":[
        "Navacerrada"
    ],
    "name:ceb_x_preferred":[
        "Navacerrada"
    ],
    "name:epo_x_preferred":[
        "Navacerrada"
    ],
    "name:eus_x_preferred":[
        "Navacerrada"
    ],
    "name:fra_x_preferred":[
        "Navacerrada"
    ],
    "name:hun_x_preferred":[
        "Navacerrada"
    ],
    "name:hye_x_preferred":[
        "\u0546\u0561\u057e\u0561\u057d\u0565\u057c\u0561\u0564\u0561"
    ],
    "name:ita_x_preferred":[
        "Navacerrada"
    ],
    "name:ltz_x_preferred":[
        "Navacerrada"
    ],
    "name:msa_x_preferred":[
        "Navacerrada"
    ],
    "name:nld_x_preferred":[
        "Navacerrada"
    ],
    "name:oci_x_preferred":[
        "Navacerrada"
    ],
    "name:pol_x_preferred":[
        "Navacerrada"
    ],
    "name:por_x_preferred":[
        "Navacerrada"
    ],
    "name:rus_x_preferred":[
        "\u041d\u0430\u0432\u0430\u0441\u0435\u0440\u0440\u0430\u0434\u0430"
    ],
    "name:spa_x_preferred":[
        "Navacerrada"
    ],
    "name:swe_x_preferred":[
        "Navacerrada"
    ],
    "name:ukr_x_preferred":[
        "\u041d\u0430\u0432\u0430\u0441\u0435\u0440\u0440\u0430\u0434\u0430"
    ],
    "name:uzb_x_preferred":[
        "Navacerrada"
    ],
    "name:vie_x_preferred":[
        "Navacerrada"
    ],
    "name:war_x_preferred":[
        "Navacerrada"
    ],
    "name:zho_x_preferred":[
        "\u7eb3\u74e6\u585e\u62c9\u8fbe"
    ],
    "wof:name":"Navacerrada",
    "wof:placetype":"locality"
},
  "geometry": {"coordinates":[-4.40061,38.79749],"type":"Point"}
}