{
  "type": "Feature",
  "properties": {
    "gn:admin1_code":"54",
    "gn:admin2_code":"CR",
    "gn:admin3_code":"13015",
    "gn:asciiname":"Navacerrada",
    "gn:country_code":"ES",
    "gn:dem":664,
    "gn:feature_class":"P",
    "gn:feature_code":"PPL",
    "gn:name":"Navacerrada",
    "gn:population":0,
    "gn:timezone":"Europe/Madrid",
    "iso:country":"ES",
    "wof:name":"Navacerrada",
    "wof:placetype":"locality"
},
  "geometry": {"coordinates":[-4.40061,38.79749],"type":"Point"}
}