{
  "type": "Feature",
  "properties": {
    "gn:admin1_code":"34",
    "gn:admin2_code":"O",
    "gn:admin3_code":"33044",
    "gn:asciiname":"Pintoria",
    "gn:country_code":"ES",
    "gn:dem":220,
    "gn:feature_class":"P",
    "gn:feature_code":"PPL",
    "gn:name":"Pintoria",
    "gn:population":0,
    "gn:timezone":"Europe/Madrid",
    "iso:country":"ES",
    "name:und_x_variant":[
        "Santa Mar\u00eda",
        "Pintoria"
    ],
    "wof:name":"Pintoria",
    "wof:placetype":"locality"
},
  "geometry": {"coordinates":[-5.9488,43.34268],"type":"Point"}
}