{
  "type": "Feature",
  "properties": {
    "gn:population":1462,
    "iso:country":"ES",
    "name:ara_x_preferred":[
        "\u0623\u062a\u0632\u064a\u0646\u064a\u062a\u0627 \u062f\u064a\u0644 \u0645\u0627\u064a\u0633\u062a\u0631\u0627\u062a"
    ],
    "name:arg_x_preferred":[
        "Adzaneta"
    ],
    "name:cat_x_preferred":[
        "Atzeneta del Maestrat"
    ],
    "name:cat_x_variant":[
        "Atzaneta del Maestrat"
    ],
    "name:ceb_x_preferred":[
        "Atzeneta del Maestrat"
    ],
    "name:eng_x_preferred":[
        "Atzeneta del Maestrat"
    ],
    "name:eus_x_preferred":[
        "Atzeneta del Maestrat"
    ],
    "name:fra_x_preferred":[
        "Atzeneta del Maestrat"
    ],
    "name:hun_x_preferred":[
        "Atzeneta del Maestrat"
    ],
    "name:ita_x_preferred":[
        "Atzeneta del Maestrat"
    ],
    "name:msa_x_preferred":[
        "Atzeneta del Maestrat"
    ],
    "name:nld_x_preferred":[
        "Atzeneta del Maestrat"
    ],
    "name:oci_x_preferred":[
        "Atzeneta del Maestrat"
    ],
    "name:pam_x_preferred":[
        "Atzeneta del Maestrat"
    ],
    "name:pol_x_preferred":[
        "Atzeneta del Maestrat"
    ],
    "name:por_x_preferred":[
        "Atzeneta del Maestrat"
    ],
    "name:rus_x_preferred":[
        "\u0410\u0434\u0437\u0430\u043d\u0435\u0442\u0430"
    ],
    "name:spa_x_preferred":[
        "Adzaneta"
    ],
    "name:sqi_x_preferred":[
        "Atzeneta del Maestrat"
    ],
    "name:swe_x_preferred":[
        "Atzeneta del Maestrat"
    ],
    "name:ukr_x_preferred":[
        "\u0410\u0434\u0437\u0435\u043d\u0435\u0442\u0430-\u0434\u0435\u043b-\u041c\u0430\u0435\u0441\u0442\u0440\u0430\u0442"
    ],
    "name:unk_x_variant":[
        "Adzaneta"
    ],
    "name:uzb_x_preferred":[
        "Adzaneta"
    ],
    "name:vie_x_preferred":[
        "Atzeneta del Maestrat"
    ],
    "name:war_x_preferred":[
        "Atzeneta del Maestrat"
    ],
    "name:zho_x_preferred":[
        "\u963f\u7279\u585e\u5185\u5854\u5fb7\u5c14\u8fc8\u65af\u7279\u62c9\u7279"
    ],
    "qs:a0":"Espa\u00f1a",
    "qs:a1":"*Castell\u00f3n/Castell\u00f3",
    "qs:a1r":"0Comunidad Valenciana",
    "qs:adm0":"Espa\u00f1a",
    "qs:la_lc":"*",
    "qs:level":"locality",
    "qs:loc":"Atzeneta del Maestrat",
    "qs:loc_alt":"Atzeneta del Maestrat",
    "qs:pop":0,
    "qs:type":"buffered point",
    "wd:wordcount":13,
    "wof:name":"Atzeneta del Maestrat",
    "wof:placetype":"locality",
    "wof:population":1462
},
  "geometry": {"coordinates":[-0.170998,40.216194],"type":"Point"}
}