{
  "type": "Feature",
  "properties": {
    "gn:admin1_code":"52",
    "gn:admin2_code":"HU",
    "gn:admin3_code":"22116.0",
    "gn:asciiname":"Montesusin",
    "gn:country_code":"ES",
    "gn:dem":351,
    "gn:elevation":"332.0",
    "gn:feature_class":"P",
    "gn:feature_code":"PPLL",
    "gn:name":"Montesusin",
    "gn:population":241,
    "gn:timezone":"Europe/Madrid",
    "iso:country":"ES",
    "wof:name":"Montesusin",
    "wof:placetype":"locality",
    "wof:population":241
},
  "geometry": {"coordinates":[-0.3928,41.88528],"type":"Point"}
}