{
  "type": "Feature",
  "properties": {
    "gn:admin1_code":"52",
    "gn:admin2_code":"HU",
    "gn:admin3_code":"22906",
    "gn:asciiname":"Huerta de Vero",
    "gn:country_code":"ES",
    "gn:dem":439,
    "gn:feature_class":"P",
    "gn:feature_code":"PPL",
    "gn:name":"Huerta de Vero",
    "gn:population":0,
    "gn:timezone":"Europe/Madrid",
    "iso:country":"ES",
    "name:spa_x_preferred":[
        "Huerta de Vero"
    ],
    "name:spa_x_variant":[
        "Huerta del Vero"
    ],
    "wof:name":"Huerta de Vero",
    "wof:placetype":"locality"
},
  "geometry": {"coordinates":[0.01468,42.11499],"type":"Point"}
}