{
  "type": "Feature",
  "properties": {
    "gn:admin1_code":"54",
    "gn:admin2_code":"GU",
    "gn:admin3_code":"19282",
    "gn:asciiname":"La Fuensavinan",
    "gn:country_code":"ES",
    "gn:dem":1114,
    "gn:feature_class":"P",
    "gn:feature_code":"PPL",
    "gn:name":"La Fuensavi\u00f1\u00e1n",
    "gn:population":0,
    "gn:timezone":"Europe/Madrid",
    "iso:country":"ES",
    "name:und_x_variant":[
        "La Fuensavi\u00f1\u00e1n"
    ],
    "wof:name":"La Fuensavinan",
    "wof:placetype":"locality"
},
  "geometry": {"coordinates":[-2.58387,40.96495],"type":"Point"}
}