{
  "type": "Feature",
  "properties": {
    "gn:admin1_code":"58",
    "gn:admin2_code":"OR",
    "gn:admin3_code":"32023",
    "gn:asciiname":"Castrelo",
    "gn:cc2":"ES",
    "gn:country_code":"ES",
    "gn:dem":758,
    "gn:feature_class":"P",
    "gn:feature_code":"PPL",
    "gn:name":"Castrelo",
    "gn:population":0,
    "gn:timezone":"Europe/Madrid",
    "iso:country":"ES",
    "name:und_x_variant":[
        "Santa Mar\u00eda",
        "Castrelo"
    ],
    "wof:name":"Castrelo",
    "wof:placetype":"locality"
},
  "geometry": {"coordinates":[-7.35,42.36667],"type":"Point"}
}