{
  "type": "Feature",
  "properties": {
    "gn:admin1_code":"07",
    "gn:admin2_code":"PM",
    "gn:admin3_code":"07046",
    "gn:asciiname":"Sant Rafel de Forca",
    "gn:country_code":"ES",
    "gn:dem":125,
    "gn:feature_class":"P",
    "gn:feature_code":"PPLL",
    "gn:name":"Sant Rafel de Forca",
    "gn:population":0,
    "gn:timezone":"Europe/Madrid",
    "iso:country":"ES",
    "name:und_x_variant":[
        "Sant Rafel de sa Creu"
    ],
    "wof:name":"Sant Rafel de Forca",
    "wof:placetype":"locality"
},
  "geometry": {"coordinates":[1.39966,38.96173],"type":"Point"}
}