{
  "type": "Feature",
  "properties": {
    "gn:admin1_code":"34",
    "gn:admin2_code":"O",
    "gn:admin3_code":"33072",
    "gn:asciiname":"Taja",
    "gn:country_code":"ES",
    "gn:dem":986,
    "gn:feature_class":"P",
    "gn:feature_code":"PPL",
    "gn:name":"Taja",
    "gn:population":0,
    "gn:timezone":"Europe/Madrid",
    "iso:country":"ES",
    "name:ast_x_preferred":[
        "Taxa"
    ],
    "name:spa_x_preferred":[
        "Taja"
    ],
    "wof:name":"Taja",
    "wof:placetype":"locality"
},
  "geometry": {"coordinates":[-6.17278,43.17053],"type":"Point"}
}