{
  "type": "Feature",
  "properties": {
    "gn:admin1_code":"58",
    "gn:admin2_code":"C",
    "gn:admin3_code":"15074",
    "gn:asciiname":"Sisto",
    "gn:country_code":"ES",
    "gn:dem":26,
    "gn:feature_class":"P",
    "gn:feature_code":"PPL",
    "gn:name":"Sisto",
    "gn:population":0,
    "gn:timezone":"Europe/Madrid",
    "iso:country":"ES",
    "wof:name":"Sisto",
    "wof:placetype":"locality"
},
  "geometry": {"coordinates":[-8.64405,42.80768],"type":"Point"}
}