{
  "type": "Feature",
  "properties": {
    "gn:admin1_code":"55",
    "gn:admin2_code":"LE",
    "gn:admin3_code":"24151",
    "gn:asciiname":"Barrio de Nuestra Senora",
    "gn:country_code":"ES",
    "gn:dem":881,
    "gn:feature_class":"P",
    "gn:feature_code":"PPL",
    "gn:name":"Barrio de Nuestra Se\u00f1ora",
    "gn:population":0,
    "gn:timezone":"Europe/Madrid",
    "iso:country":"ES",
    "name:und_x_variant":[
        "Barrio de Nuestra Se\u00f1ora"
    ],
    "wof:name":"Barrio de Nuestra Senora",
    "wof:placetype":"locality"
},
  "geometry": {"coordinates":[-5.37803,42.70843],"type":"Point"}
}