{
  "type": "Feature",
  "properties": {
    "gn:admin1_code":"39",
    "gn:admin2_code":"S",
    "gn:admin3_code":"39032",
    "gn:asciiname":"Entrambasaguas",
    "gn:country_code":"ES",
    "gn:dem":1035,
    "gn:feature_class":"P",
    "gn:feature_code":"PPL",
    "gn:name":"Entrambasaguas",
    "gn:population":0,
    "gn:timezone":"Europe/Madrid",
    "iso:country":"ES",
    "wof:name":"Entrambasaguas",
    "wof:placetype":"locality"
},
  "geometry": {"coordinates":[-4.27999,43.00926],"type":"Point"}
}