{
  "type": "Feature",
  "properties": {
    "gn:admin1_code":"39",
    "gn:admin2_code":"S",
    "gn:admin3_code":"39032",
    "gn:asciiname":"Entrambasaguas",
    "gn:country_code":"ES",
    "gn:dem":1035,
    "gn:feature_class":"P",
    "gn:feature_code":"PPL",
    "gn:name":"Entrambasaguas",
    "gn:population":0,
    "gn:timezone":"Europe/Madrid",
    "iso:country":"ES",
    "name:ara_x_preferred":[
        "\u0625\u064a\u0646\u062a\u0631\u0627\u0645\u0628\u0627\u0633\u0627\u063a\u0648\u0627\u0633"
    ],
    "name:arg_x_preferred":[
        "Entrambasaguas"
    ],
    "name:cat_x_preferred":[
        "Entrambasaguas"
    ],
    "name:ceb_x_preferred":[
        "Entrambasaguas"
    ],
    "name:eus_x_preferred":[
        "Entrambasaguas"
    ],
    "name:fra_x_preferred":[
        "Entrambasaguas"
    ],
    "name:glg_x_preferred":[
        "Entrambasaguas"
    ],
    "name:hun_x_preferred":[
        "Entrambasaguas"
    ],
    "name:hye_x_preferred":[
        "\u0537\u0576\u057f\u0580\u0561\u0574\u0562\u0561\u057d\u0561\u0563\u0578\u0582\u0561\u057d"
    ],
    "name:ina_x_preferred":[
        "Entrambasaguas"
    ],
    "name:ita_x_preferred":[
        "Entrambasaguas"
    ],
    "name:msa_x_preferred":[
        "Entrambasaguas"
    ],
    "name:nld_x_preferred":[
        "Entrambasaguas"
    ],
    "name:oci_x_preferred":[
        "Entrambasaguas"
    ],
    "name:pam_x_preferred":[
        "Entrambasaguas"
    ],
    "name:pol_x_preferred":[
        "Entrambasaguas"
    ],
    "name:por_x_preferred":[
        "Entrambasaguas"
    ],
    "name:rus_x_preferred":[
        "\u042d\u043d\u0442\u0440\u0430\u043c\u0431\u0430\u0441\u0430\u0433\u0443\u0430\u0441"
    ],
    "name:spa_x_preferred":[
        "Entrambasaguas"
    ],
    "name:sqi_x_preferred":[
        "Entrambasaguas"
    ],
    "name:swe_x_preferred":[
        "Entrambasaguas"
    ],
    "name:tur_x_preferred":[
        "Entrambasaguas"
    ],
    "name:ukr_x_preferred":[
        "\u0415\u043d\u0442\u0440\u0430\u043c\u0431\u0430\u0441\u0430\u0433\u0443\u0430\u0441"
    ],
    "name:uzb_x_preferred":[
        "Entrambasaguas"
    ],
    "name:vie_x_preferred":[
        "Entrambasaguas"
    ],
    "name:war_x_preferred":[
        "Entrambasaguas"
    ],
    "name:zho_x_preferred":[
        "\u6069\u7279\u5170\u74e6\u8428\u74dc\u65af"
    ],
    "wof:name":"Entrambasaguas",
    "wof:placetype":"locality"
},
  "geometry": {"coordinates":[-4.27999,43.00926],"type":"Point"}
}