{
  "type": "Feature",
  "properties": {
    "gn:admin1_code":"52",
    "gn:admin2_code":"TE",
    "gn:admin3_code":"44168",
    "gn:asciiname":"Odon",
    "gn:country_code":"ES",
    "gn:dem":1091,
    "gn:feature_class":"P",
    "gn:feature_code":"PPLA3",
    "gn:name":"Od\u00f3n",
    "gn:population":257,
    "gn:timezone":"Europe/Madrid",
    "iso:country":"ES",
    "name:bre_x_preferred":[
        "Odon"
    ],
    "name:cat_x_preferred":[
        "Od\u00f3"
    ],
    "name:ceb_x_preferred":[
        "Odon"
    ],
    "name:fra_x_preferred":[
        "Odon"
    ],
    "name:ita_x_preferred":[
        "Odon"
    ],
    "name:jpn_x_preferred":[
        "\u30aa\u30c9\u30f3"
    ],
    "name:nld_x_preferred":[
        "Odon"
    ],
    "name:pol_x_preferred":[
        "Odon"
    ],
    "name:rus_x_preferred":[
        "\u041e\u0434\u043e\u043d"
    ],
    "name:spa_x_preferred":[
        "Od\u00f3n"
    ],
    "name:swe_x_preferred":[
        "Od\u00f3n"
    ],
    "name:und_x_variant":[
        "Od\u00f3n"
    ],
    "wof:name":"Odon",
    "wof:placetype":"locality",
    "wof:population":257
},
  "geometry": {"coordinates":[-1.56792,40.88417000000001],"type":"Point"}
}