{
  "type": "Feature",
  "properties": {
    "gn:admin1_code":"58",
    "gn:admin2_code":"PO",
    "gn:admin3_code":"36015",
    "gn:asciiname":"Couselo",
    "gn:country_code":"ES",
    "gn:dem":263,
    "gn:feature_class":"P",
    "gn:feature_code":"PPL",
    "gn:name":"Couselo",
    "gn:population":0,
    "gn:timezone":"Europe/Madrid",
    "iso:country":"ES",
    "name:und_x_variant":[
        "Conselo",
        "Couselo"
    ],
    "wof:name":"Couselo",
    "wof:placetype":"locality"
},
  "geometry": {"coordinates":[-8.56553,42.6733],"type":"Point"}
}