{
  "type": "Feature",
  "properties": {
    "gn:admin1_code":"34",
    "gn:admin2_code":"O",
    "gn:admin3_code":"33034",
    "gn:asciiname":"Gallinero de Arcallana",
    "gn:country_code":"ES",
    "gn:dem":282,
    "gn:feature_class":"P",
    "gn:feature_code":"PPL",
    "gn:name":"Gallinero de Arcallana",
    "gn:population":0,
    "gn:timezone":"Europe/Madrid",
    "iso:country":"ES",
    "name:und_x_variant":[
        "Gallinero",
        "Gallinero de Arcallana"
    ],
    "wof:name":"Gallinero de Arcallana",
    "wof:placetype":"locality"
},
  "geometry": {"coordinates":[-6.34135,43.54025],"type":"Point"}
}