{
  "type": "Feature",
  "properties": {
    "gn:admin1_code":"52",
    "gn:admin2_code":"HU",
    "gn:admin3_code":"22069",
    "gn:asciiname":"Bergua",
    "gn:country_code":"ES",
    "gn:dem":1066,
    "gn:feature_class":"P",
    "gn:feature_code":"PPL",
    "gn:name":"Bergua",
    "gn:population":0,
    "gn:timezone":"Europe/Madrid",
    "iso:country":"ES",
    "wof:name":"Bergua",
    "wof:placetype":"locality"
},
  "geometry": {"coordinates":[-0.17023,42.53373],"type":"Point"}
}