{
  "type": "Feature",
  "properties": {
    "gn:admin1_code":"59",
    "gn:admin2_code":"SS",
    "gn:admin3_code":"20016",
    "gn:asciiname":"Urdaneta",
    "gn:country_code":"ES",
    "gn:dem":349,
    "gn:feature_class":"P",
    "gn:feature_code":"PPL",
    "gn:name":"Urdaneta",
    "gn:population":0,
    "gn:timezone":"Europe/Madrid",
    "iso:country":"ES",
    "name:ceb_x_preferred":[
        "Urdaneta"
    ],
    "name:deu_x_preferred":[
        "Urdaneta"
    ],
    "name:eus_x_preferred":[
        "Urdaneta"
    ],
    "name:fra_x_preferred":[
        "Urdaneta"
    ],
    "name:ita_x_preferred":[
        "Urdaneta"
    ],
    "name:nds_x_preferred":[
        "Urdaneta"
    ],
    "name:nld_x_preferred":[
        "Urdaneta"
    ],
    "name:por_x_preferred":[
        "Urdaneta"
    ],
    "name:rus_x_preferred":[
        "\u0423\u0440\u0434\u0430\u043d\u0435\u0442\u0430"
    ],
    "name:sco_x_preferred":[
        "Urdaneta"
    ],
    "name:spa_x_preferred":[
        "Urdaneta"
    ],
    "wof:name":"Urdaneta",
    "wof:placetype":"locality"
},
  "geometry": {"coordinates":[-2.19768,43.24803],"type":"Point"}
}