{
  "type": "Feature",
  "properties": {
    "gn:admin1_code":"39",
    "gn:admin2_code":"S",
    "gn:admin3_code":"39014",
    "gn:asciiname":"Teran",
    "gn:country_code":"ES",
    "gn:dem":272,
    "gn:feature_class":"P",
    "gn:feature_code":"PPL",
    "gn:name":"Ter\u00e1n",
    "gn:population":0,
    "gn:timezone":"Europe/Madrid",
    "iso:country":"ES",
    "name:deu_x_preferred":[
        "Teran"
    ],
    "name:lfn_x_preferred":[
        "Teran"
    ],
    "name:srp_x_preferred":[
        "\u0422\u0435\u0440\u0430\u043d"
    ],
    "wof:name":"Teran",
    "wof:placetype":"locality"
},
  "geometry": {"coordinates":[-4.30295,43.22103],"type":"Point"}
}