{
  "type": "Feature",
  "properties": {
    "gn:admin1_code":"34",
    "gn:admin2_code":"O",
    "gn:admin3_code":"33065",
    "gn:asciiname":"San Roman",
    "gn:country_code":"ES",
    "gn:dem":335,
    "gn:feature_class":"P",
    "gn:feature_code":"PPL",
    "gn:name":"San Rom\u00e1n",
    "gn:population":0,
    "gn:timezone":"Europe/Madrid",
    "iso:country":"ES",
    "wof:name":"San Roman",
    "wof:placetype":"locality"
},
  "geometry": {"coordinates":[-5.50827,43.41191],"type":"Point"}
}