{
  "type": "Feature",
  "properties": {
    "iso:country":"ES",
    "wof:name":"Pedro Salvador",
    "wof:placetype":"neighbourhood"
},
  "geometry": {"coordinates":[-5.97732469918638,37.35468052972224],"type":"Point"}
}