{
  "type": "Feature",
  "properties": {
    "iso:country":"ES",
    "name:eng_x_preferred":[
        "Capuchinos"
    ],
    "name:spa_x_preferred":[
        "Capuchinos"
    ],
    "wof:name":"Capuchinos",
    "wof:placetype":"neighbourhood"
},
  "geometry": {"coordinates":[-4.42145209372362,36.72948106703946],"type":"Point"}
}