{
  "type": "Feature",
  "properties": {
    "gn:admin1_code":"55",
    "gn:admin2_code":"BU",
    "gn:admin3_code":"09410",
    "gn:asciiname":"Taranco",
    "gn:country_code":"ES",
    "gn:dem":429,
    "gn:feature_class":"P",
    "gn:feature_code":"PPL",
    "gn:name":"Taranco",
    "gn:population":0,
    "gn:timezone":"Europe/Madrid",
    "iso:country":"ES",
    "wof:name":"Taranco",
    "wof:placetype":"locality"
},
  "geometry": {"coordinates":[-3.32731,43.10863],"type":"Point"}
}