{
  "type": "Feature",
  "properties": {
    "gn:admin1_code":"60",
    "gn:admin2_code":"V",
    "gn:admin3_code":"46153",
    "gn:asciiname":"Llocnou de Sant Jeroni",
    "gn:country_code":"ES",
    "gn:dem":136,
    "gn:feature_class":"P",
    "gn:feature_code":"PPLA3",
    "gn:name":"Llocnou de Sant Jeroni",
    "gn:population":568,
    "gn:timezone":"Europe/Madrid",
    "iso:country":"ES",
    "name:cat_x_preferred":[
        "Llocnou de Sant Jeroni"
    ],
    "name:spa_x_preferred":[
        "Lugar Nuevo de San Jer\u00f3nimo"
    ],
    "name:und_x_variant":[
        "Lugar Nuevo de San Jer\u00f3nimo"
    ],
    "wof:name":"Llocnou de Sant Jeroni",
    "wof:placetype":"locality",
    "wof:population":568
},
  "geometry": {"coordinates":[-0.28333,38.91667],"type":"Point"}
}