{
  "type": "Feature",
  "properties": {
    "gn:admin1_code":"55",
    "gn:admin2_code":"SO",
    "gn:admin3_code":"42205",
    "gn:asciiname":"Villaciervitos",
    "gn:country_code":"ES",
    "gn:dem":1171,
    "gn:feature_class":"P",
    "gn:feature_code":"PPL",
    "gn:name":"Villaciervitos",
    "gn:population":0,
    "gn:timezone":"Europe/Madrid",
    "iso:country":"ES",
    "wof:name":"Villaciervitos",
    "wof:placetype":"locality"
},
  "geometry": {"coordinates":[-2.63946,41.75279000000001],"type":"Point"}
}