{
  "type": "Feature",
  "properties": {
    "gn:admin1_code":"56",
    "gn:admin2_code":"GI",
    "gn:admin3_code":"17096",
    "gn:asciiname":"Viladonja",
    "gn:country_code":"ES",
    "gn:dem":991,
    "gn:elevation":"1168.0",
    "gn:feature_class":"P",
    "gn:feature_code":"PPL",
    "gn:name":"Viladonja",
    "gn:population":0,
    "gn:timezone":"Europe/Madrid",
    "iso:country":"ES",
    "name:cat_x_preferred":[
        "Viladonja"
    ],
    "name:eng_x_preferred":[
        "Viladonja"
    ],
    "name:eus_x_preferred":[
        "Viladonja"
    ],
    "name:oci_x_preferred":[
        "Viladonja"
    ],
    "name:und_x_variant":[
        "Viladonia",
        "Viladonja"
    ],
    "wof:name":"Viladonja",
    "wof:placetype":"locality"
},
  "geometry": {"coordinates":[2.06781,42.16524],"type":"Point"}
}