{
  "type": "Feature",
  "properties": {
    "gn:admin1_code":"55",
    "gn:admin2_code":"SO",
    "gn:admin3_code":"42013",
    "gn:asciiname":"Canos",
    "gn:country_code":"ES",
    "gn:dem":1075,
    "gn:feature_class":"P",
    "gn:feature_code":"PPL",
    "gn:name":"Canos",
    "gn:population":0,
    "gn:timezone":"Europe/Madrid",
    "iso:country":"ES",
    "wof:name":"Canos",
    "wof:placetype":"locality"
},
  "geometry": {"coordinates":[-2.31725,41.82827],"type":"Point"}
}