{
  "type": "Feature",
  "properties": {
    "gn:country":"ES",
    "gn:fcode":"PPLA3",
    "gn:population":389,
    "iso:country":"ES",
    "name:arg_x_preferred":[
        "Castromonte"
    ],
    "name:ast_x_preferred":[
        "Castromonte"
    ],
    "name:azb_x_preferred":[
        "\u06a9\u0627\u0633\u062a\u0631\u0645\u0646\u062a\u0647"
    ],
    "name:cat_x_preferred":[
        "Castromonte"
    ],
    "name:ceb_x_preferred":[
        "Castromonte"
    ],
    "name:eng_x_preferred":[
        "Castromonte"
    ],
    "name:eus_x_preferred":[
        "Castromonte"
    ],
    "name:fas_x_preferred":[
        "\u06a9\u0627\u0633\u062a\u0631\u0645\u0646\u062a\u0647"
    ],
    "name:fra_x_preferred":[
        "Castromonte"
    ],
    "name:hun_x_preferred":[
        "Castromonte"
    ],
    "name:hye_x_preferred":[
        "\u053f\u0561\u057d\u057f\u0580\u0578\u0574\u0578\u0576\u057f\u0565"
    ],
    "name:ina_x_preferred":[
        "Castromonte"
    ],
    "name:ita_x_preferred":[
        "Castromonte"
    ],
    "name:msa_x_preferred":[
        "Castromonte"
    ],
    "name:nan_x_preferred":[
        "Castromonte"
    ],
    "name:nld_x_preferred":[
        "Castromonte"
    ],
    "name:oci_x_preferred":[
        "Castromonte"
    ],
    "name:pol_x_preferred":[
        "Castromonte"
    ],
    "name:por_x_preferred":[
        "Castromonte"
    ],
    "name:rus_x_preferred":[
        "\u041a\u0430\u0441\u0442\u0440\u043e\u043c\u043e\u043d\u0442\u0435"
    ],
    "name:spa_x_preferred":[
        "Castromonte"
    ],
    "name:swe_x_preferred":[
        "Castromonte"
    ],
    "name:ukr_x_preferred":[
        "\u041a\u0430\u0441\u0442\u0440\u043e\u043c\u043e\u043d\u0442\u0435"
    ],
    "name:uzb_x_preferred":[
        "Castromonte"
    ],
    "name:vie_x_preferred":[
        "Castromonte"
    ],
    "name:war_x_preferred":[
        "Castromonte"
    ],
    "name:zho_x_preferred":[
        "\u5361\u65af\u7279\u7f57\u8499\u7279"
    ],
    "qs_pg:aaroncc":"ES",
    "qs_pg:gn_country":"ES",
    "qs_pg:gn_fcode":"PPLA3",
    "qs_pg:gn_pop":389,
    "qs_pg:name":"Castromonte",
    "qs_pg:name_adm0":"Espa\u00f1a",
    "qs_pg:name_adm1":"Castilla y Le\u00f3n",
    "qs_pg:photos":147,
    "qs_pg:photos_1k":30,
    "qs_pg:photos_9k":1,
    "qs_pg:photos_9r":3,
    "qs_pg:photos_all":147,
    "qs_pg:photos_sr":3,
    "qs_pg:pop_sr":2,
    "qs_pg:qs_pg_placetype":"locality",
    "qs_pg:qs_pg_placetype_gp":"Town",
    "qs_pg:woe_adm0":23424950,
    "woe:adm0_id":23424950,
    "woe:name_adm0":"Espa\u00f1a",
    "woe:name_adm1":"Castilla y Le\u00f3n",
    "woe:placetype":"Town",
    "wof:name":"Castromonte",
    "wof:placetype":"locality",
    "wof:population":389
},
  "geometry": {"coordinates":[-5.03909,41.77355],"type":"Point"}
}