{
  "type": "Feature",
  "properties": {
    "gn:country":"ES",
    "gn:fcode":"PPLA3",
    "gn:population":129,
    "iso:country":"ES",
    "name:arg_x_preferred":[
        "Estollo"
    ],
    "name:ast_x_preferred":[
        "Estollo"
    ],
    "name:cat_x_preferred":[
        "Estollo"
    ],
    "name:ceb_x_preferred":[
        "Estollo"
    ],
    "name:eng_x_preferred":[
        "Estollo"
    ],
    "name:eus_x_preferred":[
        "Estollo"
    ],
    "name:fra_x_preferred":[
        "Estollo"
    ],
    "name:hun_x_preferred":[
        "Estollo"
    ],
    "name:hye_x_preferred":[
        "\u0537\u057d\u057f\u0578\u056c\u056b\u0578"
    ],
    "name:ita_x_preferred":[
        "Estollo"
    ],
    "name:kaz_x_preferred":[
        "\u042d\u0441\u0442\u043e\u043b\u044c\u043e"
    ],
    "name:msa_x_preferred":[
        "Estollo"
    ],
    "name:nan_x_preferred":[
        "Estollo"
    ],
    "name:nld_x_preferred":[
        "Estollo"
    ],
    "name:oci_x_preferred":[
        "Estollo"
    ],
    "name:pol_x_preferred":[
        "Estollo"
    ],
    "name:por_x_preferred":[
        "Estollo"
    ],
    "name:rup_x_preferred":[
        "Estollo"
    ],
    "name:rus_x_preferred":[
        "\u042d\u0441\u0442\u043e\u043b\u044c\u043e"
    ],
    "name:spa_x_preferred":[
        "Estollo"
    ],
    "name:swe_x_preferred":[
        "Estollo"
    ],
    "name:ukr_x_preferred":[
        "\u0415\u0441\u0442\u043e\u043b\u044c\u0439\u043e"
    ],
    "name:uzb_x_preferred":[
        "Estollo"
    ],
    "name:vie_x_preferred":[
        "Estollo"
    ],
    "name:war_x_preferred":[
        "Estollo"
    ],
    "name:zho_x_preferred":[
        "\u57c3\u65af\u6258\u7565"
    ],
    "qs_pg:aaroncc":"ES",
    "qs_pg:gn_country":"ES",
    "qs_pg:gn_fcode":"PPLA3",
    "qs_pg:gn_pop":129,
    "qs_pg:name":"Estollo",
    "qs_pg:name_adm0":"Espa\u00f1a",
    "qs_pg:name_adm1":"La Rioja",
    "qs_pg:photos":12,
    "qs_pg:photos_1k":2,
    "qs_pg:photos_9k":1,
    "qs_pg:photos_9r":1,
    "qs_pg:photos_all":12,
    "qs_pg:photos_sr":1,
    "qs_pg:pop_sr":1,
    "qs_pg:qs_pg_placetype":"locality",
    "qs_pg:qs_pg_placetype_gp":"Town",
    "qs_pg:woe_adm0":23424950,
    "woe:adm0_id":23424950,
    "woe:name_adm0":"Espa\u00f1a",
    "woe:name_adm1":"La Rioja",
    "woe:placetype":"Town",
    "wof:name":"Estollo",
    "wof:placetype":"locality",
    "wof:population":129
},
  "geometry": {"coordinates":[-2.85092,42.32953],"type":"Point"}
}