{
  "type": "Feature",
  "properties": {
    "gn:admin1_code":"39",
    "gn:admin2_code":"S",
    "gn:admin3_code":"39093",
    "gn:asciiname":"Barrio de Arriba",
    "gn:country_code":"ES",
    "gn:dem":962,
    "gn:feature_class":"P",
    "gn:feature_code":"PPL",
    "gn:name":"Barrio de Arriba",
    "gn:population":0,
    "gn:timezone":"Europe/Madrid",
    "iso:country":"ES",
    "wof:name":"Barrio de Arriba",
    "wof:placetype":"locality"
},
  "geometry": {"coordinates":[-4.05265,42.88018],"type":"Point"}
}