{
  "type": "Feature",
  "properties": {
    "gn:gn_country":"ES",
    "gn:gn_fcode":"PPLA3",
    "gn:gn_pop":432,
    "gn:population":432,
    "iso:country":"ES",
    "name:ara_x_preferred":[
        "\u0625\u0631\u0644\u0627\u060c \u0633\u0631\u0642\u0633\u0637\u0629"
    ],
    "name:ara_x_variant":[
        "\u0625\u0631\u0644\u0627"
    ],
    "name:arg_x_preferred":[
        "Erla"
    ],
    "name:ast_x_preferred":[
        "Erla"
    ],
    "name:azb_x_preferred":[
        "\u0627\u0631\u0644\u0627"
    ],
    "name:cat_x_preferred":[
        "Erla"
    ],
    "name:ceb_x_preferred":[
        "Erla"
    ],
    "name:eng_x_preferred":[
        "Erla"
    ],
    "name:eus_x_preferred":[
        "Erla"
    ],
    "name:fas_x_preferred":[
        "\u0627\u0631\u0644\u0627"
    ],
    "name:fra_x_preferred":[
        "Erla"
    ],
    "name:hak_x_preferred":[
        "Erla"
    ],
    "name:hun_x_preferred":[
        "Erla"
    ],
    "name:hye_x_preferred":[
        "\u0537\u0580\u056c\u0561"
    ],
    "name:ita_x_preferred":[
        "Erla"
    ],
    "name:msa_x_preferred":[
        "Erla"
    ],
    "name:nan_x_preferred":[
        "Erla"
    ],
    "name:nld_x_preferred":[
        "Erla"
    ],
    "name:oci_x_preferred":[
        "Erla"
    ],
    "name:pol_x_preferred":[
        "Erla"
    ],
    "name:por_x_preferred":[
        "Erla"
    ],
    "name:rus_x_preferred":[
        "\u042d\u0440\u043b\u0430"
    ],
    "name:spa_x_preferred":[
        "Erla"
    ],
    "name:swe_x_preferred":[
        "Erla"
    ],
    "name:ukr_x_preferred":[
        "\u0415\u0440\u043b\u0430"
    ],
    "name:uzb_x_preferred":[
        "Erla"
    ],
    "name:vie_x_preferred":[
        "Erla"
    ],
    "name:war_x_preferred":[
        "Erla"
    ],
    "name:zho_x_preferred":[
        "\u57c3\u5c14\u62c9"
    ],
    "qs_pg:aaroncc":"ES",
    "qs_pg:gn_country":"ES",
    "qs_pg:gn_fcode":"PPLA3",
    "qs_pg:gn_pop":432,
    "qs_pg:name":"Erla",
    "qs_pg:name_adm0":"Espa\u00f1a",
    "qs_pg:name_adm1":"Arag\u00f3n",
    "qs_pg:photos_9k":1,
    "qs_pg:photos_9r":1,
    "qs_pg:photos_all":1,
    "qs_pg:photos_sr":0,
    "qs_pg:pop_sr":2,
    "qs_pg:qs_pg_placetype":"locality",
    "qs_pg:qs_pg_placetype_gp":"Town",
    "qs_pg:woe_adm0":23424950,
    "woe:adm0_id":23424950,
    "woe:name_adm0":"Espa\u00f1a",
    "woe:name_adm1":"Arag\u00f3n",
    "woe:placetype":"Town",
    "wof:name":"Erla",
    "wof:placetype":"locality",
    "wof:population":432
},
  "geometry": {"coordinates":[-0.95019,42.11732],"type":"Point"}
}