{
  "type": "Feature",
  "properties": {
    "gn:admin1_code":"58",
    "gn:admin2_code":"LU",
    "gn:admin3_code":"27018",
    "gn:asciiname":"San Martin de Suarna",
    "gn:country_code":"ES",
    "gn:dem":551,
    "gn:feature_class":"P",
    "gn:feature_code":"PPL",
    "gn:name":"San Mart\u00edn de Suarna",
    "gn:population":0,
    "gn:timezone":"Europe/Madrid",
    "iso:country":"ES",
    "name:und_x_variant":[
        "San Mart\u00edn de Suarna"
    ],
    "wof:name":"San Martin de Suarna",
    "wof:placetype":"locality"
},
  "geometry": {"coordinates":[-7.0365,43.11806],"type":"Point"}
}