{
  "type": "Feature",
  "properties": {
    "gn:admin1_code":"32",
    "gn:admin3_code":"31262",
    "gn:asciiname":"Ubani",
    "gn:country_code":"ES",
    "gn:dem":467,
    "gn:feature_class":"P",
    "gn:feature_code":"PPL",
    "gn:name":"Ubani",
    "gn:population":0,
    "gn:timezone":"Europe/Madrid",
    "iso:country":"ES",
    "wof:name":"Ubani",
    "wof:placetype":"locality"
},
  "geometry": {"coordinates":[-1.78413,42.77258],"type":"Point"}
}