{
  "type": "Feature",
  "properties": {
    "gn:admin1_code":"58",
    "gn:admin2_code":"LU",
    "gn:admin3_code":"27051",
    "gn:asciiname":"Vilaosende",
    "gn:country_code":"ES",
    "gn:dem":95,
    "gn:feature_class":"P",
    "gn:feature_code":"PPL",
    "gn:name":"Vilaosende",
    "gn:population":0,
    "gn:timezone":"Europe/Madrid",
    "iso:country":"ES",
    "name:und_x_variant":[
        "Santa Eulalia",
        "Vilaosende"
    ],
    "wof:name":"Vilaosende",
    "wof:placetype":"locality"
},
  "geometry": {"coordinates":[-7.06751,43.48476],"type":"Point"}
}