{
  "type": "Feature",
  "properties": {
    "gn:admin1_code":"32",
    "gn:admin3_code":"31171",
    "gn:asciiname":"Vergalijo",
    "gn:country_code":"ES",
    "gn:dem":305,
    "gn:feature_class":"P",
    "gn:feature_code":"PPL",
    "gn:name":"Vergalijo",
    "gn:population":0,
    "gn:timezone":"Europe/Madrid",
    "iso:country":"ES",
    "wof:name":"Vergalijo",
    "wof:placetype":"locality"
},
  "geometry": {"coordinates":[-1.80478,42.47225],"type":"Point"}
}