{
  "type": "Feature",
  "properties": {
    "gn:admin1_code":"55",
    "gn:admin2_code":"AV",
    "gn:admin3_code":"05227",
    "gn:asciiname":"Escarabajosa",
    "gn:country_code":"ES",
    "gn:dem":695,
    "gn:feature_class":"P",
    "gn:feature_code":"PPL",
    "gn:name":"Escarabajosa",
    "gn:population":0,
    "gn:timezone":"Europe/Madrid",
    "iso:country":"ES",
    "wof:name":"Escarabajosa",
    "wof:placetype":"locality"
},
  "geometry": {"coordinates":[-4.55411,40.30337],"type":"Point"}
}