{
  "type": "Feature",
  "properties": {
    "gn:admin1_code":"58",
    "gn:admin2_code":"C",
    "gn:admin3_code":"15016",
    "gn:asciiname":"Buria e Camarinas",
    "gn:country_code":"ES",
    "gn:dem":18,
    "gn:feature_class":"P",
    "gn:feature_code":"PPL",
    "gn:name":"Buria e Camari\u00f1as",
    "gn:population":0,
    "gn:timezone":"Europe/Madrid",
    "iso:country":"ES",
    "wof:name":"Buria e Camarinas",
    "wof:placetype":"locality"
},
  "geometry": {"coordinates":[-9.18333,43.13333],"type":"Point"}
}