{
  "type": "Feature",
  "properties": {
    "gn:gn_country":"ES",
    "gn:gn_fcode":"PPLA3",
    "gn:gn_pop":152,
    "gn:population":152,
    "iso:country":"ES",
    "name:ara_x_preferred":[
        "\u0623\u0628\u0627\u0646\u062a\u0648"
    ],
    "name:arg_x_preferred":[
        "Abanto"
    ],
    "name:baq_x_preferred":[
        "Abanto"
    ],
    "name:cat_x_preferred":[
        "Abanto"
    ],
    "name:chi_x_preferred":[
        "\u963f\u4e07\u6258"
    ],
    "name:dut_x_preferred":[
        "Abanto"
    ],
    "name:eng_x_preferred":[
        "Abanto"
    ],
    "name:fre_x_preferred":[
        "Abanto"
    ],
    "name:glg_x_preferred":[
        "Abanto"
    ],
    "name:hak_x_preferred":[
        "Abanto"
    ],
    "name:hun_x_preferred":[
        "Abanto"
    ],
    "name:ita_x_preferred":[
        "Abanto"
    ],
    "name:jpn_x_preferred":[
        "\u30a2\u30d0\u30f3\u30c8"
    ],
    "name:kaz_x_preferred":[
        "\u0410\u0431\u0430\u043d\u0442\u043e"
    ],
    "name:may_x_preferred":[
        "Abanto"
    ],
    "name:nan_x_preferred":[
        "Abanto"
    ],
    "name:oci_x_preferred":[
        "Abanto"
    ],
    "name:per_x_preferred":[
        "\u0622\u0628\u0627\u0646\u062a\u0648"
    ],
    "name:pol_x_preferred":[
        "Abanto"
    ],
    "name:por_x_preferred":[
        "Abanto"
    ],
    "name:rus_x_preferred":[
        "\u0410\u0431\u0430\u043d\u0442\u043e"
    ],
    "name:spa_x_preferred":[
        "Abanto"
    ],
    "name:swe_x_preferred":[
        "Abanto"
    ],
    "name:ukr_x_preferred":[
        "\u0410\u0431\u0430\u043d\u0442\u043e"
    ],
    "name:uzb_x_preferred":[
        "Abanto"
    ],
    "name:vie_x_preferred":[
        "Abanto"
    ],
    "name:war_x_preferred":[
        "Abanto"
    ],
    "qs_pg:aaroncc":"ES",
    "qs_pg:gn_country":"ES",
    "qs_pg:gn_fcode":"PPLA3",
    "qs_pg:gn_pop":152,
    "qs_pg:name":"Abanto",
    "qs_pg:photos_9r":0,
    "qs_pg:photos_sr":0,
    "qs_pg:pop_sr":1,
    "qs_pg:qs_pg_placetype":"locality",
    "wof:name":"Abanto",
    "wof:placetype":"locality",
    "wof:population":152
},
  "geometry": {"coordinates":[-1.69818,41.13751],"type":"Point"}
}