{
  "type": "Feature",
  "properties": {
    "gn:admin1_code":"51",
    "gn:admin2_code":"CO",
    "gn:admin3_code":"14017",
    "gn:asciiname":"Barriaga",
    "gn:country_code":"ES",
    "gn:dem":184,
    "gn:feature_class":"P",
    "gn:feature_code":"PPL",
    "gn:name":"Barriaga",
    "gn:population":0,
    "gn:timezone":"Europe/Madrid",
    "iso:country":"ES",
    "wof:name":"Barriaga",
    "wof:placetype":"locality"
},
  "geometry": {"coordinates":[-4.9436,37.71444],"type":"Point"}
}