{
  "type": "Feature",
  "properties": {
    "gn:admin1_code":"55",
    "gn:admin2_code":"AV",
    "gn:admin3_code":"05103",
    "gn:asciiname":"La Carrera",
    "gn:country_code":"ES",
    "gn:dem":1016,
    "gn:feature_class":"P",
    "gn:feature_code":"PPL",
    "gn:name":"La Carrera",
    "gn:population":0,
    "gn:timezone":"Europe/Madrid",
    "iso:country":"ES",
    "wof:name":"La Carrera",
    "wof:placetype":"locality"
},
  "geometry": {"coordinates":[-5.42654,40.45594000000001],"type":"Point"}
}