{
  "type": "Feature",
  "properties": {
    "gn:admin1_code":"55",
    "gn:admin2_code":"AV",
    "gn:admin3_code":"05103",
    "gn:asciiname":"La Carrera",
    "gn:country_code":"ES",
    "gn:dem":1016,
    "gn:feature_class":"P",
    "gn:feature_code":"PPL",
    "gn:name":"La Carrera",
    "gn:population":0,
    "gn:timezone":"Europe/Madrid",
    "iso:country":"ES",
    "name:ara_x_preferred":[
        "\u0644\u0627 \u0643\u0627\u0631\u064a\u0631\u0627"
    ],
    "name:azb_x_preferred":[
        "\u0644\u0627 \u06a9\u0627\u0631\u0631\u0627"
    ],
    "name:cat_x_preferred":[
        "La Carrera"
    ],
    "name:eus_x_preferred":[
        "La Carrera"
    ],
    "name:fas_x_preferred":[
        "\u0644\u0627 \u06a9\u0627\u0631\u0631\u0627"
    ],
    "name:fra_x_preferred":[
        "La Carrera"
    ],
    "name:hun_x_preferred":[
        "La Carrera"
    ],
    "name:ina_x_preferred":[
        "La Carrera"
    ],
    "name:ita_x_preferred":[
        "La Carrera"
    ],
    "name:mkd_x_preferred":[
        "\u041b\u0430 \u041a\u0430\u0440\u0435\u0440\u0430"
    ],
    "name:msa_x_preferred":[
        "La Carrera"
    ],
    "name:nld_x_preferred":[
        "La Carrera"
    ],
    "name:oci_x_preferred":[
        "La Carrera"
    ],
    "name:pol_x_preferred":[
        "La Carrera"
    ],
    "name:por_x_preferred":[
        "La Carrera"
    ],
    "name:spa_x_preferred":[
        "La Carrera"
    ],
    "name:ukr_x_preferred":[
        "\u041b\u0430-\u041a\u0430\u0440\u0440\u0435\u0440\u0430"
    ],
    "name:vie_x_preferred":[
        "La Carrera"
    ],
    "name:war_x_preferred":[
        "La Carrera"
    ],
    "name:zho_x_preferred":[
        "\u62c9\u5361\u96f7\u62c9"
    ],
    "wof:name":"La Carrera",
    "wof:placetype":"locality"
},
  "geometry": {"coordinates":[-5.42654,40.45594000000001],"type":"Point"}
}