{
  "type": "Feature",
  "properties": {
    "iso:country":"ES",
    "wof:name":"Continente",
    "wof:placetype":"neighbourhood"
},
  "geometry": {"coordinates":[-5.94167209566957,37.40703449940546],"type":"Point"}
}