{
  "type": "Feature",
  "properties": {
    "gn:admin1_code":"58",
    "gn:admin2_code":"OR",
    "gn:admin3_code":"32001",
    "gn:asciiname":"Requejo de Valverde",
    "gn:country_code":"ES",
    "gn:dem":505,
    "gn:feature_class":"P",
    "gn:feature_code":"PPL",
    "gn:name":"Requejo de Valverde",
    "gn:population":0,
    "gn:timezone":"Europe/Madrid",
    "iso:country":"ES",
    "name:und_x_variant":[
        "Requejo",
        "Requejo de Valverde"
    ],
    "wof:name":"Requejo de Valverde",
    "wof:placetype":"locality"
},
  "geometry": {"coordinates":[-7.76583,42.18978],"type":"Point"}
}