{
  "type": "Feature",
  "properties": {
    "gn:admin1_code":"52",
    "gn:admin2_code":"HU",
    "gn:admin3_code":"22130",
    "gn:asciiname":"Bergosa",
    "gn:country_code":"ES",
    "gn:dem":1119,
    "gn:feature_class":"P",
    "gn:feature_code":"PPL",
    "gn:name":"Bergosa",
    "gn:population":0,
    "gn:timezone":"Europe/Madrid",
    "iso:country":"ES",
    "wof:name":"Bergosa",
    "wof:placetype":"locality"
},
  "geometry": {"coordinates":[-0.53683,42.61469],"type":"Point"}
}