{
  "type": "Feature",
  "properties": {
    "gn:admin1_code":"55",
    "gn:admin2_code":"SA",
    "gn:admin3_code":"37036",
    "gn:asciiname":"Arroyomuerto",
    "gn:country_code":"ES",
    "gn:dem":1013,
    "gn:feature_class":"P",
    "gn:feature_code":"PPL",
    "gn:name":"Arroyomuerto",
    "gn:population":0,
    "gn:timezone":"Europe/Madrid",
    "iso:country":"ES",
    "wof:name":"Arroyomuerto",
    "wof:placetype":"locality"
},
  "geometry": {"coordinates":[-6.04596,40.53655],"type":"Point"}
}