{
  "type": "Feature",
  "properties": {
    "gn:admin1_code":"55",
    "gn:admin2_code":"SO",
    "gn:admin3_code":"42155",
    "gn:asciiname":"Sauquillo de Paredes",
    "gn:country_code":"ES",
    "gn:dem":1199,
    "gn:feature_class":"P",
    "gn:feature_code":"PPL",
    "gn:name":"Sauquillo de Paredes",
    "gn:population":0,
    "gn:timezone":"Europe/Madrid",
    "iso:country":"ES",
    "wof:name":"Sauquillo de Paredes",
    "wof:placetype":"locality"
},
  "geometry": {"coordinates":[-2.97696,41.36757],"type":"Point"}
}