{
  "type": "Feature",
  "properties": {
    "gn:admin1_code":"56",
    "gn:admin2_code":"L",
    "gn:admin3_code":"25161",
    "gn:asciiname":"Ortoneda",
    "gn:country_code":"ES",
    "gn:dem":992,
    "gn:feature_class":"P",
    "gn:feature_code":"PPL",
    "gn:name":"Ortoneda",
    "gn:population":0,
    "gn:timezone":"Europe/Madrid",
    "iso:country":"ES",
    "wof:name":"Ortoneda",
    "wof:placetype":"locality"
},
  "geometry": {"coordinates":[1.04259,42.24557],"type":"Point"}
}