{
  "type": "Feature",
  "properties": {
    "gn:admin1_code":"31",
    "gn:admin2_code":"MU",
    "gn:admin3_code":"30024",
    "gn:asciiname":"Santa Quiteria",
    "gn:country_code":"ES",
    "gn:dem":327,
    "gn:feature_class":"P",
    "gn:feature_code":"PPL",
    "gn:name":"Santa Quiteria",
    "gn:population":0,
    "gn:timezone":"Europe/Madrid",
    "iso:country":"ES",
    "name:ceb_x_preferred":[
        "Santa Quiteria"
    ],
    "name:swe_x_preferred":[
        "Santa Quiteria"
    ],
    "name:und_x_variant":[
        "Caser\u00edo Santa Quiteria",
        "Santa Quiteria"
    ],
    "wof:name":"Santa Quiteria",
    "wof:placetype":"locality"
},
  "geometry": {"coordinates":[-1.6924,37.6739],"type":"Point"}
}