{
  "type": "Feature",
  "properties": {
    "gn:admin1_code":"55",
    "gn:admin2_code":"AV",
    "gn:admin3_code":"05249",
    "gn:asciiname":"Venta de las Veguillas",
    "gn:country_code":"ES",
    "gn:dem":1077,
    "gn:feature_class":"P",
    "gn:feature_code":"PPL",
    "gn:name":"Venta de las Veguillas",
    "gn:population":0,
    "gn:timezone":"Europe/Madrid",
    "iso:country":"ES",
    "name:und_x_variant":[
        "Barrio Venta de las Veguillas",
        "Venta de las Veguillas"
    ],
    "wof:name":"Venta de las Veguillas",
    "wof:placetype":"locality"
},
  "geometry": {"coordinates":[-5.58115,40.31882],"type":"Point"}
}