{
  "type": "Feature",
  "properties": {
    "gn:admin1_code":"58",
    "gn:admin2_code":"LU",
    "gn:admin3_code":"27015",
    "gn:asciiname":"Goa",
    "gn:country_code":"ES",
    "gn:dem":409,
    "gn:feature_class":"P",
    "gn:feature_code":"PPL",
    "gn:name":"Go\u00e1",
    "gn:population":0,
    "gn:timezone":"Europe/Madrid",
    "iso:country":"ES",
    "name:und_x_variant":[
        "Goas",
        "Go\u00e1"
    ],
    "wof:name":"Goa",
    "wof:placetype":"locality"
},
  "geometry": {"coordinates":[-7.51667,43.26667],"type":"Point"}
}