{
  "type": "Feature",
  "properties": {
    "gn:gn_country":"ES",
    "gn:gn_fcode":"PPLA3",
    "gn:gn_pop":45,
    "gn:population":45,
    "iso:country":"ES",
    "name:arg_x_preferred":[
        "Viniegra de Arriba"
    ],
    "name:arm_x_preferred":[
        "\u054e\u056b\u0576\u056b\u0565\u0563\u0580\u0561 \u0564\u0565 \u0531\u057c\u056b\u0562\u0561"
    ],
    "name:baq_x_preferred":[
        "Viniegra de Arriba"
    ],
    "name:cat_x_preferred":[
        "Viniegra de Arriba"
    ],
    "name:chi_x_preferred":[
        "\u6bd4\u6d85\u683c\u62c9\u5fb7\u4e9a\u91cc\u74e6"
    ],
    "name:dut_x_preferred":[
        "Viniegra de Arriba"
    ],
    "name:eng_x_preferred":[
        "Viniegra de Arriba"
    ],
    "name:fre_x_preferred":[
        "Viniegra de Arriba"
    ],
    "name:ger_x_preferred":[
        "Viniegra de Arriba"
    ],
    "name:hun_x_preferred":[
        "Viniegra de Arriba"
    ],
    "name:ita_x_preferred":[
        "Viniegra de Arriba"
    ],
    "name:kaz_x_preferred":[
        "\u0412\u0438\u043d\u044c\u0435\u0433\u0440\u0430-\u0434\u0435-\u0410\u0440\u0440\u0438\u0431\u0430"
    ],
    "name:may_x_preferred":[
        "Viniegra de Arriba"
    ],
    "name:nan_x_preferred":[
        "Viniegra de Arriba"
    ],
    "name:oci_x_preferred":[
        "Viniegra de Arriba"
    ],
    "name:pol_x_preferred":[
        "Viniegra de Arriba"
    ],
    "name:por_x_preferred":[
        "Viniegra de Arriba"
    ],
    "name:rup_x_preferred":[
        "Viniegra de Arriba"
    ],
    "name:rus_x_preferred":[
        "\u0412\u0438\u043d\u044c\u0435\u0433\u0440\u0430-\u0434\u0435-\u0410\u0440\u0440\u0438\u0431\u0430"
    ],
    "name:spa_x_preferred":[
        "Viniegra de Arriba"
    ],
    "name:swe_x_preferred":[
        "Viniegra de Arriba"
    ],
    "name:ukr_x_preferred":[
        "\u0412\u0456\u043d\u044c\u0454\u0433\u0440\u0430-\u0434\u0435-\u0410\u0440\u0440\u0456\u0431\u0430"
    ],
    "name:uzb_x_preferred":[
        "Viniegra de Arriba"
    ],
    "name:vie_x_preferred":[
        "Viniegra de Arriba"
    ],
    "name:war_x_preferred":[
        "Viniegra de Arriba"
    ],
    "qs_pg:aaroncc":"ES",
    "qs_pg:gn_country":"ES",
    "qs_pg:gn_fcode":"PPLA3",
    "qs_pg:gn_pop":45,
    "qs_pg:name":"Viniegra de Arriba",
    "qs_pg:name_adm0":"Espa\u00f1a",
    "qs_pg:name_adm1":"La Rioja",
    "qs_pg:photos_9k":1,
    "qs_pg:photos_9r":1,
    "qs_pg:photos_all":8,
    "qs_pg:photos_sr":0,
    "qs_pg:pop_sr":1,
    "qs_pg:qs_pg_placetype":"locality",
    "qs_pg:qs_pg_placetype_gp":"Town",
    "qs_pg:woe_adm0":23424950,
    "woe:adm0_id":23424950,
    "woe:name_adm0":"Espa\u00f1a",
    "woe:name_adm1":"La Rioja",
    "woe:placetype":"Town",
    "wof:name":"Viniegra de Arriba",
    "wof:placetype":"locality",
    "wof:population":45
},
  "geometry": {"coordinates":[-2.83304,42.09513],"type":"Point"}
}