{
  "type": "Feature",
  "properties": {
    "gn:gn_country":"ES",
    "gn:gn_fcode":"PPL",
    "gn:gn_pop":0,
    "iso:country":"ES",
    "name:arg_x_preferred":[
        "Amaiur"
    ],
    "name:bre_x_preferred":[
        "Amaiur"
    ],
    "name:cat_x_preferred":[
        "Amaiur"
    ],
    "name:eng_x_preferred":[
        "Amaiur o Maya"
    ],
    "name:eng_x_variant":[
        "Amaiur-Maya"
    ],
    "name:eus_x_preferred":[
        "Amaiur"
    ],
    "name:fra_x_preferred":[
        "Amaiur"
    ],
    "name:nld_x_preferred":[
        "Amaiur o Maya"
    ],
    "name:spa_x_preferred":[
        "Maya"
    ],
    "name:unk_x_variant":[
        "Maya"
    ],
    "qs_pg:aaroncc":"ES",
    "qs_pg:gn_country":"ES",
    "qs_pg:gn_fcode":"PPL",
    "qs_pg:gn_pop":0,
    "qs_pg:name":"Maya del Bazt\u00e1n",
    "qs_pg:name_adm0":"Espa\u00f1a",
    "qs_pg:name_adm1":"Comunidad Foral de Navarra",
    "qs_pg:photos":296,
    "qs_pg:photos_1k":60,
    "qs_pg:photos_9k":1,
    "qs_pg:photos_9r":4,
    "qs_pg:photos_all":296,
    "qs_pg:photos_sr":5,
    "qs_pg:pop_sr":0,
    "qs_pg:qs_pg_placetype":"locality",
    "qs_pg:qs_pg_placetype_gp":"Town",
    "qs_pg:woe_adm0":23424950,
    "woe:adm0_id":23424950,
    "woe:name_adm0":"Espa\u00f1a",
    "woe:name_adm1":"Comunidad Foral de Navarra",
    "woe:placetype":"Town",
    "wof:name":"Maya del Bazt\u00e1n",
    "wof:placetype":"locality"
},
  "geometry": {"coordinates":[-1.47849,43.20184],"type":"Point"}
}