{
  "type": "Feature",
  "properties": {
    "gn:admin1_code":"57",
    "gn:admin2_code":"CC",
    "gn:admin3_code":"10216",
    "gn:asciiname":"Zarza de Granadilla",
    "gn:country_code":"ES",
    "gn:dem":394,
    "gn:feature_class":"P",
    "gn:feature_code":"PPLA3",
    "gn:name":"Zarza de Granadilla",
    "gn:population":1744,
    "gn:timezone":"Europe/Madrid",
    "iso:country":"ES",
    "name:ara_x_preferred":[
        "\u0632\u0631\u0632\u0627 \u062f\u064a \u063a\u0631\u0627\u0646\u0627\u062f\u0627\u064a\u0644\u0627"
    ],
    "name:rus_x_preferred":[
        "\u0421\u0430\u0440\u0441\u0430-\u0434\u0435-\u0413\u0440\u0430\u043d\u0430\u0434\u0438\u043b\u044c\u044f"
    ],
    "name:ukr_x_preferred":[
        "\u0421\u0430\u0440\u0441\u0430-\u0434\u0435-\u0413\u0440\u0430\u043d\u0430\u0434\u0456\u043b\u044c\u044f"
    ],
    "name:zho_x_preferred":[
        "\u8428\u5c14\u8428\u5fb7\u683c\u62c9\u7eb3\u8fea\u5229\u4e9a"
    ],
    "wof:name":"Zarza de Granadilla",
    "wof:placetype":"locality",
    "wof:population":1744
},
  "geometry": {"coordinates":[-6.0485,40.23723],"type":"Point"}
}