{
  "type": "Feature",
  "properties": {
    "gn:admin1_code":"57",
    "gn:admin2_code":"CC",
    "gn:admin3_code":"10216",
    "gn:asciiname":"Zarza de Granadilla",
    "gn:country_code":"ES",
    "gn:dem":394,
    "gn:feature_class":"P",
    "gn:feature_code":"PPLA3",
    "gn:name":"Zarza de Granadilla",
    "gn:population":1744,
    "gn:timezone":"Europe/Madrid",
    "iso:country":"ES",
    "wof:name":"Zarza de Granadilla",
    "wof:placetype":"locality",
    "wof:population":1744
},
  "geometry": {"coordinates":[-6.0485,40.23723],"type":"Point"}
}