{
  "type": "Feature",
  "properties": {
    "gn:admin1_code":"54",
    "gn:admin2_code":"CU",
    "gn:admin3_code":"16211",
    "gn:asciiname":"Villarejo-Sobrehuerta",
    "gn:country_code":"ES",
    "gn:dem":949,
    "gn:feature_class":"P",
    "gn:feature_code":"PPL",
    "gn:name":"Villarejo-Sobrehuerta",
    "gn:population":0,
    "gn:timezone":"Europe/Madrid",
    "iso:country":"ES",
    "wof:name":"Villarejo-Sobrehuerta",
    "wof:placetype":"locality"
},
  "geometry": {"coordinates":[-2.48681,40.01907],"type":"Point"}
}