{
  "type": "Feature",
  "properties": {
    "gn:gn_country":"ES",
    "gn:gn_fcode":"PPLA3",
    "gn:gn_pop":34,
    "gn:population":34,
    "iso:country":"ES",
    "name:arg_x_preferred":[
        "Moraleja de las Panaderas"
    ],
    "name:arm_x_preferred":[
        "\u0544\u0578\u0580\u0561\u056c\u0565\u056d\u0561 \u0564\u0565 \u056c\u0561\u057d \u054a\u0561\u0576\u0561\u0564\u0565\u0580\u0561\u057d"
    ],
    "name:baq_x_preferred":[
        "Moraleja de las Panaderas"
    ],
    "name:cat_x_preferred":[
        "Moraleja de las Panaderas"
    ],
    "name:chi_x_preferred":[
        "\u83ab\u62c9\u83b1\u54c8\u5fb7\u62c9\u65af\u5e15\u7eb3\u5fb7\u62c9\u65af"
    ],
    "name:dut_x_preferred":[
        "Moraleja de las Panaderas"
    ],
    "name:eng_x_preferred":[
        "Moraleja de las Panaderas"
    ],
    "name:fre_x_preferred":[
        "Moraleja de las Panaderas"
    ],
    "name:ger_x_preferred":[
        "Moraleja de las Panaderas"
    ],
    "name:hun_x_preferred":[
        "Moraleja de las Panaderas"
    ],
    "name:ina_x_preferred":[
        "Moraleja de las Panaderas"
    ],
    "name:ita_x_preferred":[
        "Moraleja de las Panaderas"
    ],
    "name:may_x_preferred":[
        "Moraleja de las Panaderas"
    ],
    "name:nan_x_preferred":[
        "Moraleja de las Panaderas"
    ],
    "name:oci_x_preferred":[
        "Moraleja de las Panaderas"
    ],
    "name:per_x_preferred":[
        "\u0645\u0631\u0627\u0644\u062e\u0627 \u062f \u0644\u0627\u0633 \u067e\u0627\u0646\u0627\u062f\u0631\u0627\u0633"
    ],
    "name:pol_x_preferred":[
        "Moraleja de las Panaderas"
    ],
    "name:por_x_preferred":[
        "Moraleja de las Panaderas"
    ],
    "name:rus_x_preferred":[
        "\u041c\u043e\u0440\u0430\u043b\u0435\u0445\u0430-\u0434\u0435-\u043b\u0430\u0441-\u041f\u0430\u043d\u0430\u0434\u0435\u0440\u0430\u0441"
    ],
    "name:spa_x_preferred":[
        "Moraleja de las Panaderas"
    ],
    "name:swe_x_preferred":[
        "Moraleja de las Panaderas"
    ],
    "name:ukr_x_preferred":[
        "\u041c\u043e\u0440\u0430\u043b\u0435\u0445\u0430-\u0434\u0435-\u043b\u0430\u0441-\u041f\u0430\u043d\u0430\u0434\u0435\u0440\u0430\u0441"
    ],
    "name:unk_x_variant":[
        "Moraleja de las Panaderas"
    ],
    "name:uzb_x_preferred":[
        "Moraleja de las Panaderas"
    ],
    "name:vie_x_preferred":[
        "Moraleja de las Panaderas"
    ],
    "name:war_x_preferred":[
        "Moraleja de las Panaderas"
    ],
    "qs_pg:aaroncc":"ES",
    "qs_pg:gn_country":"ES",
    "qs_pg:gn_fcode":"PPLA3",
    "qs_pg:gn_pop":34,
    "qs_pg:name":"Moraleja de Las Panaderas",
    "qs_pg:name_adm0":"Espa\u00f1a",
    "qs_pg:name_adm1":"Castilla y Le\u00f3n",
    "qs_pg:photos_9r":0,
    "qs_pg:photos_sr":0,
    "qs_pg:pop_sr":1,
    "qs_pg:qs_pg_placetype":"locality",
    "qs_pg:qs_pg_placetype_gp":"Town",
    "qs_pg:woe_adm0":23424950,
    "woe:adm0_id":23424950,
    "woe:name_adm0":"Espa\u00f1a",
    "woe:name_adm1":"Castilla y Le\u00f3n",
    "woe:placetype":"Town",
    "wof:name":"Moraleja de Las Panaderas",
    "wof:placetype":"locality",
    "wof:population":34
},
  "geometry": {"coordinates":[-4.82521,41.27636],"type":"Point"}
}