{
  "type": "Feature",
  "properties": {
    "gn:admin1_code":"58",
    "gn:admin2_code":"LU",
    "gn:admin3_code":"27061",
    "gn:asciiname":"Abaira",
    "gn:country_code":"ES",
    "gn:dem":271,
    "gn:feature_class":"P",
    "gn:feature_code":"PPL",
    "gn:name":"Abaira",
    "gn:population":0,
    "gn:timezone":"Europe/Madrid",
    "iso:country":"ES",
    "wof:name":"Abaira",
    "wof:placetype":"locality"
},
  "geometry": {"coordinates":[-7.17423,43.45665],"type":"Point"}
}