{
  "type": "Feature",
  "properties": {
    "iso:country":"ES",
    "name:ceb_x_preferred":[
        "Bami"
    ],
    "name:swe_x_preferred":[
        "Bami"
    ],
    "wof:name":"Bami",
    "wof:placetype":"neighbourhood"
},
  "geometry": {"coordinates":[-5.97777531052761,37.3600332686008],"type":"Point"}
}