{
  "type": "Feature",
  "properties": {
    "iso:country":"ES",
    "name:eng_x_preferred":[
        "Hacienda Paredes"
    ],
    "name:spa_x_preferred":[
        "Hacienda Paredes"
    ],
    "wof:name":"Hacienda Paredes",
    "wof:placetype":"neighbourhood"
},
  "geometry": {"coordinates":[-4.3758399831749,36.72924275264584],"type":"Point"}
}