{
  "type": "Feature",
  "properties": {
    "gn:country":"ES",
    "gn:fcode":"PPLA3",
    "gn:population":182,
    "iso:country":"ES",
    "name:arg_x_preferred":[
        "La Morera de Montsant"
    ],
    "name:cat_x_preferred":[
        "la Morera de Montsant"
    ],
    "name:cat_x_variant":[
        "la Morera"
    ],
    "name:eng_x_preferred":[
        "La Morera de Montsant"
    ],
    "name:eus_x_preferred":[
        "La Morera de Montsant"
    ],
    "name:fin_x_preferred":[
        "La Morera de Montsant"
    ],
    "name:fra_x_preferred":[
        "La Morera de Montsant"
    ],
    "name:glg_x_preferred":[
        "La Morera de Montsant"
    ],
    "name:hun_x_preferred":[
        "La Morera de Montsant"
    ],
    "name:hye_x_preferred":[
        "\u053c\u0561 \u0544\u0578\u0580\u0565\u0580\u0561 \u0564\u0565 \u0544\u0578\u0576\u057d\u0561\u0576"
    ],
    "name:ita_x_preferred":[
        "La Morera de Montsant"
    ],
    "name:lat_x_preferred":[
        "La Morera de Montsant"
    ],
    "name:nld_x_preferred":[
        "La Morera de Montsant"
    ],
    "name:oci_x_preferred":[
        "La Morera de Montsant"
    ],
    "name:pol_x_preferred":[
        "El Morera de Montsant"
    ],
    "name:por_x_preferred":[
        "La Morera de Montsant"
    ],
    "name:rus_x_preferred":[
        "\u041b\u0430-\u041c\u043e\u0440\u0435\u0440\u0430-\u0434\u0435-\u041c\u043e\u043d\u0441\u0430\u043d"
    ],
    "name:spa_x_preferred":[
        "La Morera de Montsant"
    ],
    "name:sqi_x_preferred":[
        "La Morera de Montsant"
    ],
    "name:swe_x_preferred":[
        "La Morera de Montsant"
    ],
    "name:uzb_x_preferred":[
        "La Morera de Montsant"
    ],
    "name:vie_x_preferred":[
        "La Morera de Montsant"
    ],
    "name:war_x_preferred":[
        "La Morera de Montsant"
    ],
    "name:zho_x_preferred":[
        "\u62c9\u83ab\u96f7\u62c9\u5fb7\u8499\u7279\u6851\u7279"
    ],
    "qs_pg:aaroncc":"ES",
    "qs_pg:gn_country":"ES",
    "qs_pg:gn_fcode":"PPLA3",
    "qs_pg:gn_pop":182,
    "qs_pg:name":"La Morera de Montsant",
    "qs_pg:name_adm0":"Espa\u00f1a",
    "qs_pg:name_adm1":"Catalunya",
    "qs_pg:photos":414,
    "qs_pg:photos_1k":84,
    "qs_pg:photos_9k":2,
    "qs_pg:photos_9r":5,
    "qs_pg:photos_all":414,
    "qs_pg:photos_sr":6,
    "qs_pg:pop_sr":1,
    "qs_pg:qs_pg_placetype":"locality",
    "qs_pg:qs_pg_placetype_gp":"Town",
    "qs_pg:woe_adm0":23424950,
    "woe:adm0_id":23424950,
    "woe:name_adm0":"Espa\u00f1a",
    "woe:name_adm1":"Catalunya",
    "woe:placetype":"Town",
    "wof:name":"La Morera de Montsant",
    "wof:placetype":"locality",
    "wof:population":160
},
  "geometry": {"coordinates":[0.84157,41.26529],"type":"Point"}
}