{
  "type": "Feature",
  "properties": {
    "gn:country":"ES",
    "gn:fcode":"PPLA3",
    "gn:population":1368,
    "iso:country":"ES",
    "name:arg_x_preferred":[
        "Galar"
    ],
    "name:bre_x_preferred":[
        "Galar Zendea"
    ],
    "name:cat_x_preferred":[
        "Galar"
    ],
    "name:ceb_x_preferred":[
        "Galar"
    ],
    "name:eus_x_preferred":[
        "Galar"
    ],
    "name:eus_x_variant":[
        "Galar Zendea"
    ],
    "name:fra_x_preferred":[
        "Cendea de Galar"
    ],
    "name:hun_x_preferred":[
        "Galar"
    ],
    "name:hye_x_preferred":[
        "\u0533\u0561\u056c\u0561\u0580"
    ],
    "name:ita_x_preferred":[
        "Galar"
    ],
    "name:msa_x_preferred":[
        "Galar"
    ],
    "name:nld_x_preferred":[
        "Galar"
    ],
    "name:oci_x_preferred":[
        "Galar Zendea"
    ],
    "name:oci_x_variant":[
        "Galar"
    ],
    "name:pol_x_preferred":[
        "Galar"
    ],
    "name:por_x_preferred":[
        "Cendea de Galar"
    ],
    "name:rus_x_preferred":[
        "\u0413\u0430\u043b\u0430\u0440"
    ],
    "name:sco_x_preferred":[
        "Galar"
    ],
    "name:spa_x_preferred":[
        "Galar"
    ],
    "name:swe_x_preferred":[
        "Galar"
    ],
    "name:ukr_x_preferred":[
        "\u0413\u0430\u043b\u0430\u0440"
    ],
    "name:uzb_x_preferred":[
        "Galar"
    ],
    "name:vie_x_preferred":[
        "Galar"
    ],
    "name:war_x_preferred":[
        "Galar"
    ],
    "name:zho_x_preferred":[
        "\u52a0\u62c9\u5c14"
    ],
    "qs_pg:aaroncc":"ES",
    "qs_pg:gn_country":"ES",
    "qs_pg:gn_fcode":"PPLA3",
    "qs_pg:gn_pop":1368,
    "qs_pg:name":"Galar",
    "qs_pg:name_adm0":"Espa\u00f1a",
    "qs_pg:name_adm1":"Comunidad Foral de Navarra",
    "qs_pg:photos":30,
    "qs_pg:photos_1k":6,
    "qs_pg:photos_9k":1,
    "qs_pg:photos_9r":2,
    "qs_pg:photos_all":30,
    "qs_pg:photos_sr":2,
    "qs_pg:pop_sr":3,
    "qs_pg:qs_pg_placetype":"locality",
    "qs_pg:qs_pg_placetype_gp":"Town",
    "qs_pg:woe_adm0":23424950,
    "woe:adm0_id":23424950,
    "woe:name_adm0":"Espa\u00f1a",
    "woe:name_adm1":"Comunidad Foral de Navarra",
    "woe:placetype":"Town",
    "wof:name":"Galar",
    "wof:placetype":"locality",
    "wof:population":1368
},
  "geometry": {"coordinates":[-1.69881,42.76147],"type":"Point"}
}