{
  "type": "Feature",
  "properties": {
    "gn:admin1_code":"58",
    "gn:admin2_code":"LU",
    "gn:admin3_code":"27012",
    "gn:asciiname":"Santalla",
    "gn:country_code":"ES",
    "gn:dem":756,
    "gn:feature_class":"P",
    "gn:feature_code":"PPL",
    "gn:name":"Santalla",
    "gn:population":0,
    "gn:timezone":"Europe/Madrid",
    "iso:country":"ES",
    "wof:name":"Santalla",
    "wof:placetype":"locality"
},
  "geometry": {"coordinates":[-6.99585,42.87605],"type":"Point"}
}