{
  "type": "Feature",
  "properties": {
    "gn:admin1_code":"58",
    "gn:admin2_code":"LU",
    "gn:admin3_code":"27020",
    "gn:asciiname":"Roimil",
    "gn:cc2":"ES",
    "gn:country_code":"ES",
    "gn:dem":542,
    "gn:feature_class":"P",
    "gn:feature_code":"PPL",
    "gn:name":"Roimil",
    "gn:population":0,
    "gn:timezone":"Europe/Madrid",
    "iso:country":"ES",
    "name:und_x_variant":[
        "Raimil",
        "San Juli\u00e1n",
        "Roimil"
    ],
    "wof:name":"Roimil",
    "wof:placetype":"locality"
},
  "geometry": {"coordinates":[-7.83333,43.06667],"type":"Point"}
}