{
  "type": "Feature",
  "properties": {
    "gn:country":"ES",
    "gn:fcode":"PPLA3",
    "gn:population":217,
    "iso:country":"ES",
    "name:arg_x_preferred":[
        "Serradilla del Llano"
    ],
    "name:ast_x_preferred":[
        "Serradilla del Llano"
    ],
    "name:cat_x_preferred":[
        "Serradilla del Llano"
    ],
    "name:ceb_x_preferred":[
        "Serradilla del Llano"
    ],
    "name:eng_x_preferred":[
        "Serradilla del Llano"
    ],
    "name:eus_x_preferred":[
        "Serradilla del Llano"
    ],
    "name:fra_x_preferred":[
        "Serradilla del Llano"
    ],
    "name:hun_x_preferred":[
        "Serradilla del Llano"
    ],
    "name:ina_x_preferred":[
        "Serradilla del Llano"
    ],
    "name:ita_x_preferred":[
        "Serradilla del Llano"
    ],
    "name:kaz_x_preferred":[
        "\u0421\u0435\u0440\u0440\u0430\u0434\u0438\u043b\u044c\u044f-\u0434\u0435\u043b\u044c-\u041b\u044c\u044f\u043d\u043e"
    ],
    "name:msa_x_preferred":[
        "Serradilla del Llano"
    ],
    "name:nan_x_preferred":[
        "Serradilla del Llano"
    ],
    "name:nld_x_preferred":[
        "Serradilla del Llano"
    ],
    "name:oci_x_preferred":[
        "Serradilla del Llano"
    ],
    "name:pol_x_preferred":[
        "Serradilla del Llano"
    ],
    "name:por_x_preferred":[
        "Serradilla del Llano"
    ],
    "name:rus_x_preferred":[
        "\u0421\u0435\u0440\u0440\u0430\u0434\u0438\u043b\u044c\u044f-\u0434\u0435\u043b\u044c-\u041b\u044c\u044f\u043d\u043e"
    ],
    "name:spa_x_preferred":[
        "Serradilla del Llano"
    ],
    "name:swe_x_preferred":[
        "Serradilla del Llano"
    ],
    "name:ukr_x_preferred":[
        "\u0421\u0435\u0440\u0440\u0430\u0434\u0456\u043b\u044c\u044f-\u0434\u0435\u043b\u044c-\u041b\u044c\u044f\u043d\u043e"
    ],
    "name:vie_x_preferred":[
        "Serradilla del Llano"
    ],
    "name:war_x_preferred":[
        "Serradilla del Llano"
    ],
    "name:zho_x_preferred":[
        "\u585e\u62c9\u8fea\u5229\u4e9a\u5fb7\u5229\u62c9\u8bfa"
    ],
    "qs_pg:aaroncc":"ES",
    "qs_pg:gn_country":"ES",
    "qs_pg:gn_fcode":"PPLA3",
    "qs_pg:gn_pop":217,
    "qs_pg:name":"Serradilla del Llano",
    "qs_pg:name_adm0":"Espa\u00f1a",
    "qs_pg:name_adm1":"Castilla y Le\u00f3n",
    "qs_pg:photos_9r":0,
    "qs_pg:photos_sr":0,
    "qs_pg:pop_sr":2,
    "qs_pg:qs_pg_placetype":"locality",
    "qs_pg:qs_pg_placetype_gp":"Town",
    "qs_pg:woe_adm0":23424950,
    "woe:adm0_id":23424950,
    "woe:name_adm0":"Espa\u00f1a",
    "woe:name_adm1":"Castilla y Le\u00f3n",
    "woe:placetype":"Town",
    "wof:name":"Serradilla del Llano",
    "wof:placetype":"locality",
    "wof:population":217
},
  "geometry": {"coordinates":[-6.35701,40.49996],"type":"Point"}
}