{
  "type": "Feature",
  "properties": {
    "gn:admin1_code":"51",
    "gn:admin2_code":"CO",
    "gn:admin3_code":"14055",
    "gn:asciiname":"Castil de Campos",
    "gn:country_code":"ES",
    "gn:dem":674,
    "gn:feature_class":"P",
    "gn:feature_code":"PPL",
    "gn:name":"Castil de Campos",
    "gn:population":0,
    "gn:timezone":"Europe/Madrid",
    "iso:country":"ES",
    "wof:name":"Castil de Campos",
    "wof:placetype":"locality"
},
  "geometry": {"coordinates":[-4.14356,37.49189000000001],"type":"Point"}
}