{
  "type": "Feature",
  "properties": {
    "gn:gn_country":"ES",
    "gn:gn_fcode":"PPLA3",
    "gn:gn_pop":411,
    "gn:population":411,
    "iso:country":"ES",
    "name:ara_x_preferred":[
        "\u0646\u0627\u0641\u0627\u0631\u064a\u0641\u064a\u0633\u0643\u0627"
    ],
    "name:baq_x_preferred":[
        "Navarrevisca"
    ],
    "name:cat_x_preferred":[
        "Navarrevisca"
    ],
    "name:chi_x_preferred":[
        "\u7eb3\u74e6\u96f7\u7ef4\u65af\u5361"
    ],
    "name:dut_x_preferred":[
        "Navarrevisca"
    ],
    "name:eng_x_preferred":[
        "Navarrevisca"
    ],
    "name:fre_x_preferred":[
        "Navarrevisca"
    ],
    "name:hun_x_preferred":[
        "Navarrevisca"
    ],
    "name:ina_x_preferred":[
        "Navarrevisca"
    ],
    "name:ita_x_preferred":[
        "Navarrevisca"
    ],
    "name:kaz_x_preferred":[
        "\u041d\u0430\u0432\u0430\u0440\u0440\u0435\u0432\u0438\u0441\u043a\u0430"
    ],
    "name:mac_x_preferred":[
        "\u041d\u0430\u0432\u0430\u0440\u0435\u0432\u0438\u0441\u043a\u0430"
    ],
    "name:may_x_preferred":[
        "Navarrevisca"
    ],
    "name:oci_x_preferred":[
        "Navarrevisca"
    ],
    "name:per_x_preferred":[
        "\u0646\u0627\u0628\u0627\u0631\u0628\u06cc\u0633\u06a9\u0627"
    ],
    "name:pol_x_preferred":[
        "Navarrevisca"
    ],
    "name:por_x_preferred":[
        "Navarrevisca"
    ],
    "name:rus_x_preferred":[
        "\u041d\u0430\u0432\u0430\u0440\u0440\u0435\u0432\u0438\u0441\u043a\u0430"
    ],
    "name:spa_x_preferred":[
        "Navarrevisca"
    ],
    "name:swe_x_preferred":[
        "Navarrevisca"
    ],
    "name:ukr_x_preferred":[
        "\u041d\u0430\u0432\u0430\u0440\u0440\u0435\u0432\u0456\u0441\u043a\u0430"
    ],
    "name:uzb_x_preferred":[
        "Navarrevisca"
    ],
    "name:vie_x_preferred":[
        "Navarrevisca"
    ],
    "name:war_x_preferred":[
        "Navarrevisca"
    ],
    "qs_pg:aaroncc":"ES",
    "qs_pg:gn_country":"ES",
    "qs_pg:gn_fcode":"PPLA3",
    "qs_pg:gn_pop":411,
    "qs_pg:name":"Navarrevisca",
    "qs_pg:name_adm0":"Espa\u00f1a",
    "qs_pg:name_adm1":"Castilla y Le\u00f3n",
    "qs_pg:photos":17,
    "qs_pg:photos_1k":3,
    "qs_pg:photos_9k":1,
    "qs_pg:photos_9r":1,
    "qs_pg:photos_all":17,
    "qs_pg:photos_sr":1,
    "qs_pg:pop_sr":2,
    "qs_pg:qs_pg_placetype":"locality",
    "qs_pg:qs_pg_placetype_gp":"Town",
    "qs_pg:woe_adm0":23424950,
    "woe:adm0_id":23424950,
    "woe:name_adm0":"Espa\u00f1a",
    "woe:name_adm1":"Castilla y Le\u00f3n",
    "woe:placetype":"Town",
    "wof:name":"Navarrevisca",
    "wof:placetype":"locality",
    "wof:population":411
},
  "geometry": {"coordinates":[-4.89352,40.36417],"type":"Point"}
}