{
  "type": "Feature",
  "properties": {
    "gn:admin1_code":"55",
    "gn:admin2_code":"BU",
    "gn:admin3_code":"09174",
    "gn:asciiname":"Hinojar del Rey",
    "gn:country_code":"ES",
    "gn:dem":946,
    "gn:feature_class":"P",
    "gn:feature_code":"PPL",
    "gn:name":"Hinojar del Rey",
    "gn:population":0,
    "gn:timezone":"Europe/Madrid",
    "iso:country":"ES",
    "wof:name":"Hinojar del Rey",
    "wof:placetype":"locality"
},
  "geometry": {"coordinates":[-3.32981,41.76836],"type":"Point"}
}