{
  "type": "Feature",
  "properties": {
    "gn:admin1_code":"58",
    "gn:admin2_code":"OR",
    "gn:admin3_code":"32083",
    "gn:asciiname":"Banos",
    "gn:country_code":"ES",
    "gn:dem":873,
    "gn:feature_class":"P",
    "gn:feature_code":"PPL",
    "gn:name":"Ba\u00f1os",
    "gn:population":0,
    "gn:timezone":"Europe/Madrid",
    "iso:country":"ES",
    "name:ceb_x_preferred":[
        "Banos"
    ],
    "name:deu_x_preferred":[
        "Banos"
    ],
    "name:nld_x_preferred":[
        "Banos"
    ],
    "wof:name":"Banos",
    "wof:placetype":"locality"
},
  "geometry": {"coordinates":[-7.00952,42.2335],"type":"Point"}
}