{
  "type": "Feature",
  "properties": {
    "gn:admin1_code":"34",
    "gn:admin2_code":"O",
    "gn:admin3_code":"33011",
    "gn:asciiname":"Noceda",
    "gn:country_code":"ES",
    "gn:dem":833,
    "gn:feature_class":"P",
    "gn:feature_code":"PPL",
    "gn:name":"Noceda",
    "gn:population":0,
    "gn:timezone":"Europe/Madrid",
    "iso:country":"ES",
    "wof:name":"Noceda",
    "wof:placetype":"locality"
},
  "geometry": {"coordinates":[-6.58418,43.04944],"type":"Point"}
}