{
  "type": "Feature",
  "properties": {
    "gn:admin1_code":"55",
    "gn:admin2_code":"ZA",
    "gn:admin3_code":"49206",
    "gn:asciiname":"Bercianos de Vidriales",
    "gn:country_code":"ES",
    "gn:dem":729,
    "gn:feature_class":"P",
    "gn:feature_code":"PPL",
    "gn:name":"Bercianos de Vidriales",
    "gn:population":0,
    "gn:timezone":"Europe/Madrid",
    "iso:country":"ES",
    "wof:name":"Bercianos de Vidriales",
    "wof:placetype":"locality"
},
  "geometry": {"coordinates":[-5.96334,42.0743],"type":"Point"}
}