{
  "type": "Feature",
  "properties": {
    "gn:gn_country":"ES",
    "gn:gn_fcode":"PPLA3",
    "gn:gn_pop":660,
    "gn:population":660,
    "iso:country":"ES",
    "name:arg_x_preferred":[
        "Pereruela"
    ],
    "name:baq_x_preferred":[
        "Pereruela"
    ],
    "name:cat_x_preferred":[
        "Pereruela"
    ],
    "name:chi_x_preferred":[
        "\u4f69\u96f7\u9c81\u57c3\u62c9"
    ],
    "name:dut_x_preferred":[
        "Pereruela"
    ],
    "name:eng_x_preferred":[
        "Pereruela"
    ],
    "name:fre_x_preferred":[
        "Pereruela"
    ],
    "name:haw_x_preferred":[
        "Pereruela"
    ],
    "name:hun_x_preferred":[
        "Pereruela"
    ],
    "name:ile_x_preferred":[
        "Pereruela"
    ],
    "name:ina_x_preferred":[
        "Pereruela"
    ],
    "name:ita_x_preferred":[
        "Pereruela"
    ],
    "name:may_x_preferred":[
        "Pereruela"
    ],
    "name:nan_x_preferred":[
        "Pereruela"
    ],
    "name:oci_x_preferred":[
        "Pereruela"
    ],
    "name:pol_x_preferred":[
        "Pereruela"
    ],
    "name:por_x_preferred":[
        "Pereruela"
    ],
    "name:rus_x_preferred":[
        "\u041f\u0435\u0440\u0435\u0440\u0443\u044d\u043b\u0430"
    ],
    "name:spa_x_preferred":[
        "Pereruela"
    ],
    "name:swe_x_preferred":[
        "Pereruela"
    ],
    "name:ukr_x_preferred":[
        "\u041f\u0435\u0440\u0435\u0440\u0443\u0435\u043b\u0430"
    ],
    "name:vie_x_preferred":[
        "Pereruela"
    ],
    "name:war_x_preferred":[
        "Pereruela"
    ],
    "name:zho_x_preferred":[
        "\u4f69\u96f7\u9c81\u57c3\u62c9"
    ],
    "qs_pg:aaroncc":"ES",
    "qs_pg:gn_country":"ES",
    "qs_pg:gn_fcode":"PPLA3",
    "qs_pg:gn_pop":660,
    "qs_pg:name":"Pereruela",
    "qs_pg:name_adm0":"Espa\u00f1a",
    "qs_pg:name_adm1":"Castilla y Le\u00f3n",
    "qs_pg:photos":43,
    "qs_pg:photos_1k":9,
    "qs_pg:photos_9k":1,
    "qs_pg:photos_9r":2,
    "qs_pg:photos_all":43,
    "qs_pg:photos_sr":2,
    "qs_pg:pop_sr":2,
    "qs_pg:qs_pg_placetype":"locality",
    "qs_pg:qs_pg_placetype_gp":"Town",
    "qs_pg:woe_adm0":23424950,
    "woe:adm0_id":23424950,
    "woe:name_adm0":"Espa\u00f1a",
    "woe:name_adm1":"Castilla y Le\u00f3n",
    "woe:placetype":"Town",
    "wof:name":"Pereruela",
    "wof:placetype":"locality",
    "wof:population":660
},
  "geometry": {"coordinates":[-5.87812,41.4165],"type":"Point"}
}