{
  "type": "Feature",
  "properties": {
    "gn:country":"ES",
    "gn:fcode":"PPLA3",
    "gn:population":129,
    "iso:country":"ES",
    "name:ara_x_preferred":[
        "\u0627\u0644\u0645\u0646\u064a\u0629"
    ],
    "name:arg_x_preferred":[
        "Armu\u00f1a de Taju\u00f1a"
    ],
    "name:cat_x_preferred":[
        "Armu\u00f1a de Taju\u00f1a"
    ],
    "name:che_x_preferred":[
        "\u0410\u0440\u043c\u0443\u043d\u044c\u044f-\u0434\u0435-\u0422\u0430\u0445\u0443\u043d\u044c\u044f"
    ],
    "name:deu_x_preferred":[
        "Armu\u00f1a de Taju\u00f1a"
    ],
    "name:eng_x_preferred":[
        "Armu\u00f1a de Taju\u00f1a"
    ],
    "name:eus_x_preferred":[
        "Armu\u00f1a de Taju\u00f1a"
    ],
    "name:fra_x_preferred":[
        "Armu\u00f1a de Taju\u00f1a"
    ],
    "name:hun_x_preferred":[
        "Armu\u00f1a de Taju\u00f1a"
    ],
    "name:ina_x_preferred":[
        "Armu\u00f1a de Taju\u00f1a"
    ],
    "name:ita_x_preferred":[
        "Armu\u00f1a de Taju\u00f1a"
    ],
    "name:kaz_x_preferred":[
        "\u0410\u0440\u043c\u0443\u043d\u0438\u044f-\u0434\u0435-\u0422\u0430\u0445\u0443\u043d\u0438\u044f"
    ],
    "name:msa_x_preferred":[
        "Armu\u00f1a de Taju\u00f1a"
    ],
    "name:nan_x_preferred":[
        "Armu\u00f1a de Taju\u00f1a"
    ],
    "name:nld_x_preferred":[
        "Armu\u00f1a de Taju\u00f1a"
    ],
    "name:oci_x_preferred":[
        "Armu\u00f1a de Taju\u00f1a"
    ],
    "name:pol_x_preferred":[
        "Armu\u00f1a de Taju\u00f1a"
    ],
    "name:por_x_preferred":[
        "Armu\u00f1a de Taju\u00f1a"
    ],
    "name:rus_x_preferred":[
        "\u0410\u0440\u043c\u0443\u043d\u0438\u044f-\u0434\u0435-\u0422\u0430\u0445\u0443\u043d\u0438\u044f"
    ],
    "name:spa_x_preferred":[
        "Armu\u00f1a de Taju\u00f1a"
    ],
    "name:swe_x_preferred":[
        "Armu\u00f1a de Taju\u00f1a"
    ],
    "name:tat_x_preferred":[
        "\u0410\u0440\u043c\u0443\u043d\u044c\u044f-\u0434\u0435-\u0422\u0430\u0445\u0443\u043d\u044c\u044f"
    ],
    "name:ukr_x_preferred":[
        "\u0410\u0440\u043c\u0443\u043d\u044c\u044f-\u0434\u0435-\u0422\u0430\u0445\u0443\u043d\u044c\u044f"
    ],
    "name:vie_x_preferred":[
        "Armu\u00f1a de Taju\u00f1a"
    ],
    "name:war_x_preferred":[
        "Armu\u00f1a de Taju\u00f1a"
    ],
    "name:zho_x_preferred":[
        "\u963f\u5c14\u7a46\u5c3c\u4e9a\u5fb7\u5854\u80e1\u5c3c\u4e9a"
    ],
    "qs_pg:aaroncc":"ES",
    "qs_pg:gn_country":"ES",
    "qs_pg:gn_fcode":"PPLA3",
    "qs_pg:gn_pop":129,
    "qs_pg:name":"Armu\u00f1a de Taju\u00f1a",
    "qs_pg:name_adm0":"Espa\u00f1a",
    "qs_pg:name_adm1":"Castilla-La Mancha",
    "qs_pg:photos_9r":0,
    "qs_pg:photos_sr":0,
    "qs_pg:pop_sr":1,
    "qs_pg:qs_pg_placetype":"locality",
    "qs_pg:qs_pg_placetype_gp":"Town",
    "qs_pg:woe_adm0":23424950,
    "woe:adm0_id":23424950,
    "woe:name_adm0":"Espa\u00f1a",
    "woe:name_adm1":"Castilla-La Mancha",
    "woe:placetype":"Town",
    "wof:name":"Armu\u00f1a de Taju\u00f1a",
    "wof:placetype":"locality",
    "wof:population":129
},
  "geometry": {"coordinates":[-3.02819,40.52884],"type":"Point"}
}