{
  "type": "Feature",
  "properties": {
    "gn:gn_country":"ES",
    "gn:gn_fcode":"PPLA3",
    "gn:gn_pop":518,
    "gn:population":518,
    "iso:country":"ES",
    "name:arg_x_preferred":[
        "Murla"
    ],
    "name:azb_x_preferred":[
        "\u0645\u0648\u0631\u0644\u0627"
    ],
    "name:cat_x_preferred":[
        "Murla"
    ],
    "name:ceb_x_preferred":[
        "Murla"
    ],
    "name:eng_x_preferred":[
        "Murla"
    ],
    "name:eus_x_preferred":[
        "Murla"
    ],
    "name:fas_x_preferred":[
        "\u0645\u0648\u0631\u0644\u0627"
    ],
    "name:fra_x_preferred":[
        "Murla"
    ],
    "name:hun_x_preferred":[
        "Murla"
    ],
    "name:ita_x_preferred":[
        "Murla"
    ],
    "name:kaz_x_preferred":[
        "\u041c\u0443\u0440\u043b\u0430"
    ],
    "name:msa_x_preferred":[
        "Murla"
    ],
    "name:nld_x_preferred":[
        "Murla"
    ],
    "name:oci_x_preferred":[
        "Murla"
    ],
    "name:pol_x_preferred":[
        "Murla"
    ],
    "name:por_x_preferred":[
        "Murla"
    ],
    "name:rus_x_preferred":[
        "\u041c\u0443\u0440\u043b\u0430"
    ],
    "name:spa_x_preferred":[
        "Murla"
    ],
    "name:swe_x_preferred":[
        "Murla"
    ],
    "name:ukr_x_preferred":[
        "\u041c\u0443\u0440\u043b\u0430"
    ],
    "name:uzb_x_preferred":[
        "Murla"
    ],
    "name:war_x_preferred":[
        "Murla"
    ],
    "name:zho_x_preferred":[
        "\u7a46\u5c14\u62c9"
    ],
    "qs_pg:aaroncc":"ES",
    "qs_pg:gn_country":"ES",
    "qs_pg:gn_fcode":"PPLA3",
    "qs_pg:gn_pop":518,
    "qs_pg:name":"Murla",
    "qs_pg:name_adm0":"Espa\u00f1a",
    "qs_pg:name_adm1":"Comunitat Valenciana",
    "qs_pg:photos":18,
    "qs_pg:photos_1k":4,
    "qs_pg:photos_9k":1,
    "qs_pg:photos_9r":1,
    "qs_pg:photos_all":18,
    "qs_pg:photos_sr":1,
    "qs_pg:pop_sr":2,
    "qs_pg:qs_pg_placetype":"locality",
    "qs_pg:qs_pg_placetype_gp":"Town",
    "qs_pg:woe_adm0":23424950,
    "woe:adm0_id":23424950,
    "woe:name_adm0":"Espa\u00f1a",
    "woe:name_adm1":"Comunitat Valenciana",
    "woe:placetype":"Town",
    "wof:name":"Murla",
    "wof:placetype":"locality",
    "wof:population":518
},
  "geometry": {"coordinates":[-0.08208,38.76037],"type":"Point"}
}