{
  "type": "Feature",
  "properties": {
    "gn:admin1_code":"54",
    "gn:admin2_code":"TO",
    "gn:admin3_code":"45025",
    "gn:asciiname":"Cabanas de la Sagra",
    "gn:country_code":"ES",
    "gn:dem":551,
    "gn:feature_class":"P",
    "gn:feature_code":"PPLA3",
    "gn:name":"Caba\u00f1as de la Sagra",
    "gn:population":1767,
    "gn:timezone":"Europe/Madrid",
    "iso:country":"ES",
    "name:azb_x_preferred":[
        "\u06a9\u0627\u0628\u0627\u0646\u06cc\u0627\u0633 \u062f \u0644\u0627 \u0633\u0627\u0642\u0631\u0627"
    ],
    "name:fas_x_preferred":[
        "\u06a9\u0627\u0628\u0627\u0646\u06cc\u0627\u0633 \u062f \u0644\u0627 \u0633\u0627\u06af\u0631\u0627"
    ],
    "name:hye_x_preferred":[
        "\u053f\u0561\u0562\u0561\u0576\u056b\u0561\u057d \u0564\u0565 \u056c\u0561 \u054d\u0561\u0563\u0580\u0561"
    ],
    "name:und_x_variant":[
        "Caba\u00f1as de la Sagra"
    ],
    "wof:name":"Cabanas de la Sagra",
    "wof:placetype":"locality",
    "wof:population":1767
},
  "geometry": {"coordinates":[-3.9456,40.0061],"type":"Point"}
}