{
  "type": "Feature",
  "properties": {
    "gn:admin1_code":"54",
    "gn:admin2_code":"TO",
    "gn:admin3_code":"45025",
    "gn:asciiname":"Cabanas de la Sagra",
    "gn:country_code":"ES",
    "gn:dem":551,
    "gn:feature_class":"P",
    "gn:feature_code":"PPLA3",
    "gn:name":"Caba\u00f1as de la Sagra",
    "gn:population":1767,
    "gn:timezone":"Europe/Madrid",
    "iso:country":"ES",
    "name:und_x_variant":[
        "Caba\u00f1as de la Sagra"
    ],
    "wof:name":"Cabanas de la Sagra",
    "wof:placetype":"locality",
    "wof:population":1767
},
  "geometry": {"coordinates":[-3.9456,40.0061],"type":"Point"}
}