{
  "type": "Feature",
  "properties": {
    "gn:admin1_code":"54",
    "gn:admin2_code":"CU",
    "gn:admin3_code":"16902",
    "gn:asciiname":"Tortola",
    "gn:country_code":"ES",
    "gn:dem":992,
    "gn:feature_class":"P",
    "gn:feature_code":"PPL",
    "gn:name":"T\u00f3rtola",
    "gn:population":0,
    "gn:timezone":"Europe/Madrid",
    "iso:country":"ES",
    "name:ara_x_preferred":[
        "\u062a\u0648\u0631\u062a\u0648\u0644\u0627"
    ],
    "name:cat_x_preferred":[
        "T\u00f3rtola"
    ],
    "name:ceb_x_preferred":[
        "Tortola"
    ],
    "name:che_x_preferred":[
        "\u0422\u043e\u0440\u0442\u043e\u043b\u0430"
    ],
    "name:dan_x_preferred":[
        "Tortola"
    ],
    "name:deu_x_preferred":[
        "Tortola"
    ],
    "name:ell_x_preferred":[
        "\u03a4\u03bf\u03c1\u03c4\u03cc\u03bb\u03b1"
    ],
    "name:fas_x_preferred":[
        "\u062a\u0648\u0631\u062a\u0648\u0644\u0627"
    ],
    "name:fin_x_preferred":[
        "Tortola"
    ],
    "name:fra_x_preferred":[
        "Tortola"
    ],
    "name:glg_x_preferred":[
        "T\u00f3rtola"
    ],
    "name:heb_x_preferred":[
        "\u05d8\u05d5\u05e8\u05d8\u05d5\u05dc\u05d4"
    ],
    "name:hrv_x_preferred":[
        "Tortola"
    ],
    "name:hun_x_preferred":[
        "Tortola"
    ],
    "name:hye_x_preferred":[
        "\u054f\u0578\u0580\u057f\u0578\u056c\u0561"
    ],
    "name:ita_x_preferred":[
        "Tortola"
    ],
    "name:jpn_x_preferred":[
        "\u30c8\u30eb\u30c8\u30e9\u5cf6"
    ],
    "name:kor_x_preferred":[
        "\ud1a0\ub974\ud1a8\ub77c\uc12c"
    ],
    "name:lat_x_preferred":[
        "Tortola"
    ],
    "name:lit_x_preferred":[
        "Tortola"
    ],
    "name:nld_x_preferred":[
        "Tortola"
    ],
    "name:nor_x_preferred":[
        "Tortola"
    ],
    "name:pol_x_preferred":[
        "Tortola"
    ],
    "name:por_x_preferred":[
        "Tortola"
    ],
    "name:rus_x_preferred":[
        "\u0422\u043e\u0440\u0442\u043e\u043b\u0430"
    ],
    "name:spa_x_preferred":[
        "T\u00f3rtola"
    ],
    "name:srp_x_preferred":[
        "\u0422\u043e\u0440\u0442\u043e\u043b\u0430"
    ],
    "name:swe_x_preferred":[
        "Tortola"
    ],
    "name:ukr_x_preferred":[
        "\u0422\u043e\u0440\u0442\u043e\u043b\u0430"
    ],
    "name:vie_x_preferred":[
        "Tortola"
    ],
    "name:zho_x_preferred":[
        "\u6258\u5c14\u6258\u62c9\u5c9b"
    ],
    "wof:name":"Tortola",
    "wof:placetype":"locality"
},
  "geometry": {"coordinates":[-2.13333,39.91667],"type":"Point"}
}