{
  "type": "Feature",
  "properties": {
    "gn:admin1_code":"54",
    "gn:admin2_code":"CU",
    "gn:admin3_code":"16902",
    "gn:asciiname":"Tortola",
    "gn:country_code":"ES",
    "gn:dem":992,
    "gn:feature_class":"P",
    "gn:feature_code":"PPL",
    "gn:name":"T\u00f3rtola",
    "gn:population":0,
    "gn:timezone":"Europe/Madrid",
    "iso:country":"ES",
    "name:und_x_variant":[
        "T\u00f3rtola"
    ],
    "wof:name":"Tortola",
    "wof:placetype":"locality"
},
  "geometry": {"coordinates":[-2.13333,39.91667],"type":"Point"}
}