{
  "type": "Feature",
  "properties": {
    "gn:admin1_code":"55",
    "gn:admin2_code":"SO",
    "gn:admin3_code":"42209",
    "gn:asciiname":"Montaves",
    "gn:country_code":"ES",
    "gn:dem":1320,
    "gn:feature_class":"P",
    "gn:feature_code":"PPL",
    "gn:name":"Montaves",
    "gn:population":0,
    "gn:timezone":"Europe/Madrid",
    "iso:country":"ES",
    "wof:name":"Montaves",
    "wof:placetype":"locality"
},
  "geometry": {"coordinates":[-2.30501,42.00467],"type":"Point"}
}