{
  "type": "Feature",
  "properties": {
    "gn:admin1_code":"55",
    "gn:admin2_code":"SG",
    "gn:admin3_code":"40195",
    "gn:asciiname":"Vellosillo",
    "gn:country_code":"ES",
    "gn:dem":1000,
    "gn:feature_class":"P",
    "gn:feature_code":"PPL",
    "gn:name":"Vellosillo",
    "gn:population":0,
    "gn:timezone":"Europe/Madrid",
    "iso:country":"ES",
    "wof:name":"Vellosillo",
    "wof:placetype":"locality"
},
  "geometry": {"coordinates":[-3.70623,41.26703],"type":"Point"}
}