{
  "type": "Feature",
  "properties": {
    "iso:country":"ES",
    "wof:name":"La Llum",
    "wof:placetype":"neighbourhood"
},
  "geometry": {"coordinates":[-0.41107300478783,39.46786016282771],"type":"Point"}
}