{
  "type": "Feature",
  "properties": {
    "gn:admin1_code":"31",
    "gn:admin2_code":"MU",
    "gn:admin3_code":"30024",
    "gn:asciiname":"Turbinto",
    "gn:country_code":"ES",
    "gn:dem":354,
    "gn:feature_class":"P",
    "gn:feature_code":"PPL",
    "gn:name":"Turbinto",
    "gn:population":0,
    "gn:timezone":"Europe/Madrid",
    "iso:country":"ES",
    "name:und_x_variant":[
        "Caser\u00edo Turvinto",
        "Turvinto",
        "Turbinto"
    ],
    "wof:name":"Turbinto",
    "wof:placetype":"locality"
},
  "geometry": {"coordinates":[-1.74618,37.53817],"type":"Point"}
}