{
  "type": "Feature",
  "properties": {
    "gn:admin1_code":"57",
    "gn:admin2_code":"CC",
    "gn:admin3_code":"10136",
    "gn:asciiname":"Las Berrozanas",
    "gn:country_code":"ES",
    "gn:dem":293,
    "gn:feature_class":"P",
    "gn:feature_code":"PPL",
    "gn:name":"Las Berrozanas",
    "gn:population":0,
    "gn:timezone":"Europe/Madrid",
    "iso:country":"ES",
    "name:und_x_variant":[
        "Caser\u00edo Las Berrozanas",
        "Las Berrozanas"
    ],
    "wof:name":"Las Berrozanas",
    "wof:placetype":"locality"
},
  "geometry": {"coordinates":[-6.12331,40.07143],"type":"Point"}
}