{
  "type": "Feature",
  "properties": {
    "gn:gn_country":"ES",
    "gn:gn_fcode":"PPLA3",
    "gn:gn_pop":294,
    "gn:population":294,
    "iso:country":"ES",
    "name:ara_x_preferred":[
        "\u0641\u0627\u0644\u0641\u0631\u062f\u0648\u0646"
    ],
    "name:arg_x_preferred":[
        "Valverd\u00f3n"
    ],
    "name:ast_x_preferred":[
        "Valverd\u00f3n"
    ],
    "name:cat_x_preferred":[
        "Valverd\u00f3n"
    ],
    "name:ceb_x_preferred":[
        "Valverd\u00f3n"
    ],
    "name:deu_x_preferred":[
        "Valverd\u00f3n"
    ],
    "name:eng_x_preferred":[
        "Valverd\u00f3n"
    ],
    "name:eus_x_preferred":[
        "Valverd\u00f3n"
    ],
    "name:fra_x_preferred":[
        "Valverd\u00f3n"
    ],
    "name:hun_x_preferred":[
        "Valverd\u00f3n"
    ],
    "name:ina_x_preferred":[
        "Valverd\u00f3n"
    ],
    "name:ita_x_preferred":[
        "Valverd\u00f3n"
    ],
    "name:kaz_x_preferred":[
        "\u0412\u0430\u043b\u044c\u0432\u0435\u0440\u0434\u043e\u043d"
    ],
    "name:msa_x_preferred":[
        "Valverd\u00f3n"
    ],
    "name:nan_x_preferred":[
        "Valverd\u00f3n"
    ],
    "name:nld_x_preferred":[
        "Valverd\u00f3n"
    ],
    "name:oci_x_preferred":[
        "Valverd\u00f3n"
    ],
    "name:pol_x_preferred":[
        "Valverd\u00f3n"
    ],
    "name:por_x_preferred":[
        "Valverd\u00f3n"
    ],
    "name:rus_x_preferred":[
        "\u0412\u0430\u043b\u044c\u0432\u0435\u0440\u0434\u043e\u043d"
    ],
    "name:spa_x_preferred":[
        "Valverd\u00f3n"
    ],
    "name:swe_x_preferred":[
        "Valverd\u00f3n"
    ],
    "name:ukr_x_preferred":[
        "\u0412\u0430\u043b\u044c\u0432\u0435\u0440\u0434\u043e\u043d"
    ],
    "name:uzb_x_preferred":[
        "Valverd\u00f3n"
    ],
    "name:vie_x_preferred":[
        "Valverd\u00f3n"
    ],
    "name:war_x_preferred":[
        "Valverd\u00f3n"
    ],
    "name:zho_x_preferred":[
        "\u5df4\u5c14\u97e6\u5c14\u4e1c"
    ],
    "qs_pg:aaroncc":"ES",
    "qs_pg:gn_country":"ES",
    "qs_pg:gn_fcode":"PPLA3",
    "qs_pg:gn_pop":294,
    "qs_pg:name":"Valverd\u00f3n",
    "qs_pg:photos_9r":0,
    "qs_pg:photos_sr":0,
    "qs_pg:pop_sr":2,
    "qs_pg:qs_pg_placetype":"locality",
    "wof:name":"Valverd\u00f3n",
    "wof:placetype":"locality",
    "wof:population":294
},
  "geometry": {"coordinates":[-5.76955,41.04691],"type":"Point"}
}