{
  "type": "Feature",
  "properties": {
    "gn:admin1_code":"55",
    "gn:admin2_code":"P",
    "gn:admin3_code":"34056",
    "gn:asciiname":"Colmenares",
    "gn:country_code":"ES",
    "gn:dem":1027,
    "gn:feature_class":"P",
    "gn:feature_code":"PPL",
    "gn:name":"Colmenares",
    "gn:population":0,
    "gn:timezone":"Europe/Madrid",
    "iso:country":"ES",
    "wof:name":"Colmenares",
    "wof:placetype":"locality"
},
  "geometry": {"coordinates":[-4.5216,42.79502],"type":"Point"}
}