{
  "type": "Feature",
  "properties": {
    "gn:admin1_code":"55",
    "gn:admin2_code":"SO",
    "gn:admin3_code":"42149",
    "gn:asciiname":"Los Rabanos",
    "gn:country_code":"ES",
    "gn:dem":1042,
    "gn:feature_class":"P",
    "gn:feature_code":"PPL",
    "gn:name":"Los R\u00e1banos",
    "gn:population":488,
    "gn:timezone":"Europe/Madrid",
    "iso:country":"ES",
    "name:und_x_variant":[
        "Los R\u00e1banos"
    ],
    "wof:name":"Los Rabanos",
    "wof:placetype":"locality",
    "wof:population":488
},
  "geometry": {"coordinates":[-2.47647,41.71803],"type":"Point"}
}