{
  "type": "Feature",
  "properties": {
    "gn:admin1_code":"39",
    "gn:admin2_code":"S",
    "gn:admin3_code":"39097",
    "gn:asciiname":"Candolias",
    "gn:country_code":"ES",
    "gn:dem":328,
    "gn:feature_class":"P",
    "gn:feature_code":"PPL",
    "gn:name":"Candolias",
    "gn:population":0,
    "gn:timezone":"Europe/Madrid",
    "iso:country":"ES",
    "name:und_x_variant":[
        "Candolia",
        "Candolias"
    ],
    "wof:name":"Candolias",
    "wof:placetype":"locality"
},
  "geometry": {"coordinates":[-3.79824,43.15753],"type":"Point"}
}