{
  "type": "Feature",
  "properties": {
    "gn:admin1_code":"56",
    "gn:admin2_code":"GI",
    "gn:admin3_code":"17089",
    "gn:asciiname":"Veinat de Sant Llorenc",
    "gn:country_code":"ES",
    "gn:dem":133,
    "gn:feature_class":"P",
    "gn:feature_code":"PPL",
    "gn:name":"Ve\u00efnat de Sant Lloren\u00e7",
    "gn:population":0,
    "gn:timezone":"Europe/Madrid",
    "iso:country":"ES",
    "name:und_x_variant":[
        "Caser\u00edo Vehinat de San Lorenzo",
        "San Lorenzo"
    ],
    "wof:name":"Veinat de Sant Llorenc",
    "wof:placetype":"locality"
},
  "geometry": {"coordinates":[2.89464,41.82353],"type":"Point"}
}