{
  "type": "Feature",
  "properties": {
    "gn:admin1_code":"39",
    "gn:admin2_code":"S",
    "gn:admin3_code":"39080",
    "gn:asciiname":"Abano",
    "gn:country_code":"ES",
    "gn:dem":25,
    "gn:feature_class":"P",
    "gn:feature_code":"PPL",
    "gn:name":"Aba\u00f1o",
    "gn:population":0,
    "gn:timezone":"Europe/Madrid",
    "iso:country":"ES",
    "name:und_x_variant":[
        "Aba\u00f1o"
    ],
    "wof:name":"Abano",
    "wof:placetype":"locality"
},
  "geometry": {"coordinates":[-4.39146,43.3625],"type":"Point"}
}