{
  "type": "Feature",
  "properties": {
    "gn:admin1_code":"39",
    "gn:admin2_code":"S",
    "gn:admin3_code":"39080",
    "gn:asciiname":"Abano",
    "gn:country_code":"ES",
    "gn:dem":25,
    "gn:feature_class":"P",
    "gn:feature_code":"PPL",
    "gn:name":"Aba\u00f1o",
    "gn:population":0,
    "gn:timezone":"Europe/Madrid",
    "iso:country":"ES",
    "name:ces_x_preferred":[
        "Abano"
    ],
    "name:deu_x_preferred":[
        "Abano"
    ],
    "name:fas_x_preferred":[
        "\u0622\u0628\u0627\u0646\u0648"
    ],
    "name:kat_x_preferred":[
        "\u10d0\u10d1\u10d0\u10dc\u10dd"
    ],
    "name:oss_x_preferred":[
        "\u0410\u0431\u0430\u043d\u0430"
    ],
    "name:por_x_preferred":[
        "Abano"
    ],
    "name:rus_x_preferred":[
        "\u0410\u0431\u0430\u043d\u043e"
    ],
    "name:sco_x_preferred":[
        "Abano"
    ],
    "name:ukr_x_preferred":[
        "\u0410\u0431\u0430\u043d\u043e"
    ],
    "name:und_x_variant":[
        "Aba\u00f1o"
    ],
    "wof:name":"Abano",
    "wof:placetype":"locality"
},
  "geometry": {"coordinates":[-4.39146,43.3625],"type":"Point"}
}