{
  "type": "Feature",
  "properties": {
    "gn:admin1_code":"31",
    "gn:admin2_code":"MU",
    "gn:admin3_code":"30028",
    "gn:asciiname":"Calar de la Santa",
    "gn:country_code":"ES",
    "gn:dem":1244,
    "gn:feature_class":"P",
    "gn:feature_code":"PPL",
    "gn:name":"Calar de la Santa",
    "gn:population":0,
    "gn:timezone":"Europe/Madrid",
    "iso:country":"ES",
    "name:und_x_variant":[
        "Caser\u00edo Calar de la Santa",
        "Calar de la Santa"
    ],
    "wof:name":"Calar de la Santa",
    "wof:placetype":"locality"
},
  "geometry": {"coordinates":[-2.1707,38.17935],"type":"Point"}
}