{
  "type": "Feature",
  "properties": {
    "gn:admin1_code":"34",
    "gn:admin2_code":"O",
    "gn:admin3_code":"33059",
    "gn:asciiname":"Socolina",
    "gn:country_code":"ES",
    "gn:dem":560,
    "gn:feature_class":"P",
    "gn:feature_code":"PPL",
    "gn:name":"Socolina",
    "gn:population":0,
    "gn:timezone":"Europe/Madrid",
    "iso:country":"ES",
    "wof:name":"Socolina",
    "wof:placetype":"locality"
},
  "geometry": {"coordinates":[-6.32957,43.44388],"type":"Point"}
}