{
  "type": "Feature",
  "properties": {
    "gn:admin1_code":"34",
    "gn:admin2_code":"O",
    "gn:admin3_code":"33034",
    "gn:asciiname":"El Pueblo",
    "gn:country_code":"ES",
    "gn:dem":240,
    "gn:feature_class":"P",
    "gn:feature_code":"PPL",
    "gn:name":"El Pueblo",
    "gn:population":0,
    "gn:timezone":"Europe/Madrid",
    "iso:country":"ES",
    "name:cat_x_preferred":[
        "El Pueblo"
    ],
    "name:ceb_x_preferred":[
        "El Pueblo"
    ],
    "name:deu_x_preferred":[
        "El Pueblo"
    ],
    "name:glg_x_preferred":[
        "El Pueblo"
    ],
    "name:spa_x_preferred":[
        "El pueblo"
    ],
    "name:swe_x_preferred":[
        "El Pueblo"
    ],
    "wof:name":"El Pueblo",
    "wof:placetype":"locality"
},
  "geometry": {"coordinates":[-6.31667,43.51667],"type":"Point"}
}