{
  "type": "Feature",
  "properties": {
    "gn:admin1_code":"31",
    "gn:admin2_code":"MU",
    "gn:admin3_code":"30030",
    "gn:asciiname":"Avileses",
    "gn:country_code":"ES",
    "gn:dem":126,
    "gn:feature_class":"P",
    "gn:feature_code":"PPL",
    "gn:name":"Avileses",
    "gn:population":0,
    "gn:timezone":"Europe/Madrid",
    "iso:country":"ES",
    "name:und_x_variant":[
        "Caser\u00edo Avileses",
        "Avileses"
    ],
    "wof:name":"Avileses",
    "wof:placetype":"locality"
},
  "geometry": {"coordinates":[-0.94336,37.84873],"type":"Point"}
}