{
  "type": "Feature",
  "properties": {
    "gn:admin1_code":"55",
    "gn:admin2_code":"VA",
    "gn:admin3_code":"47091",
    "gn:asciiname":"Rinconada",
    "gn:country_code":"ES",
    "gn:dem":761,
    "gn:feature_class":"P",
    "gn:feature_code":"PPL",
    "gn:name":"Rinconada",
    "gn:population":0,
    "gn:timezone":"Europe/Madrid",
    "iso:country":"ES",
    "name:und_x_variant":[
        "Casa de Cuesta",
        "Caser\u00edo Rinconada",
        "Rinconada"
    ],
    "wof:name":"Rinconada",
    "wof:placetype":"locality"
},
  "geometry": {"coordinates":[-5.18436,42.23328],"type":"Point"}
}