{
  "type": "Feature",
  "properties": {
    "gn:admin1_code":"51",
    "gn:admin2_code":"SE",
    "gn:admin3_code":"41039",
    "gn:asciiname":"Villar",
    "gn:country_code":"ES",
    "gn:dem":190,
    "gn:feature_class":"P",
    "gn:feature_code":"PPL",
    "gn:name":"Villar",
    "gn:population":0,
    "gn:timezone":"Europe/Madrid",
    "iso:country":"ES",
    "wof:name":"Villar",
    "wof:placetype":"locality"
},
  "geometry": {"coordinates":[-5.04638,37.62868],"type":"Point"}
}