{
  "type": "Feature",
  "properties": {
    "gn:admin1_code":"56",
    "gn:admin2_code":"L",
    "gn:admin3_code":"25008",
    "gn:asciiname":"la Portella",
    "gn:country_code":"ES",
    "gn:dem":260,
    "gn:feature_class":"P",
    "gn:feature_code":"PPL",
    "gn:name":"la Portella",
    "gn:population":0,
    "gn:timezone":"Europe/Madrid",
    "iso:country":"ES",
    "name:cat_x_preferred":[
        "la Portella"
    ],
    "name:eng_x_preferred":[
        "la Portella"
    ],
    "name:eus_x_preferred":[
        "la Portella"
    ],
    "name:oci_x_preferred":[
        "la Portella"
    ],
    "wof:name":"la Portella",
    "wof:placetype":"locality"
},
  "geometry": {"coordinates":[0.65,41.73333],"type":"Point"}
}