{
  "type": "Feature",
  "properties": {
    "gn:admin1_code":"56",
    "gn:admin2_code":"L",
    "gn:admin3_code":"25008",
    "gn:asciiname":"la Portella",
    "gn:country_code":"ES",
    "gn:dem":260,
    "gn:feature_class":"P",
    "gn:feature_code":"PPL",
    "gn:name":"la Portella",
    "gn:population":0,
    "gn:timezone":"Europe/Madrid",
    "iso:country":"ES",
    "name:arg_x_preferred":[
        "La Portella"
    ],
    "name:ast_x_preferred":[
        "La Portella"
    ],
    "name:cat_x_preferred":[
        "la Portella"
    ],
    "name:cat_x_variant":[
        "La Portella"
    ],
    "name:ceb_x_preferred":[
        "La Portella"
    ],
    "name:eng_x_preferred":[
        "la Portella"
    ],
    "name:eus_x_preferred":[
        "la Portella"
    ],
    "name:eus_x_variant":[
        "La Portella"
    ],
    "name:fra_x_preferred":[
        "La Portella"
    ],
    "name:hun_x_preferred":[
        "La Portella"
    ],
    "name:hye_x_preferred":[
        "\u054a\u0578\u057f\u0565\u056c\u0575\u0561"
    ],
    "name:ita_x_preferred":[
        "La Portella"
    ],
    "name:msa_x_preferred":[
        "La Portella"
    ],
    "name:oci_x_preferred":[
        "la Portella"
    ],
    "name:oci_x_variant":[
        "La Portella"
    ],
    "name:pol_x_preferred":[
        "La Portella"
    ],
    "name:por_x_preferred":[
        "La Portella"
    ],
    "name:ron_x_preferred":[
        "La Portella"
    ],
    "name:rus_x_preferred":[
        "\u041f\u043e\u0440\u0442\u0435\u043b\u044c\u044f"
    ],
    "name:spa_x_preferred":[
        "Portella"
    ],
    "name:sqi_x_preferred":[
        "La Portella"
    ],
    "name:swe_x_preferred":[
        "La Portella"
    ],
    "name:urd_x_preferred":[
        "\u0644\u0627 \u067e\u0648\u0631\u0679\u06cc\u0644\u0627"
    ],
    "name:uzb_x_preferred":[
        "La Portella"
    ],
    "name:vie_x_preferred":[
        "La Portella"
    ],
    "name:war_x_preferred":[
        "La Portella"
    ],
    "name:zho_x_preferred":[
        "\u6ce2\u5c14\u7279\u5229\u4e9a"
    ],
    "wof:name":"la Portella",
    "wof:placetype":"locality"
},
  "geometry": {"coordinates":[0.65,41.73333],"type":"Point"}
}