{
  "type": "Feature",
  "properties": {
    "gn:gn_country":"ES",
    "gn:gn_fcode":"PPL",
    "gn:gn_pop":0,
    "iso:country":"ES",
    "name:dut_x_preferred":[
        "Los Escullos"
    ],
    "name:eng_x_preferred":[
        "Los Escullos"
    ],
    "name:ger_x_preferred":[
        "Los Escullos"
    ],
    "name:ita_x_preferred":[
        "Los Escullos"
    ],
    "name:spa_x_preferred":[
        "Los Escullos"
    ],
    "name:unk_x_variant":[
        "Caser\u00edo Los Escullos"
    ],
    "qs_pg:aaroncc":"ES",
    "qs_pg:gn_country":"ES",
    "qs_pg:gn_fcode":"PPL",
    "qs_pg:gn_pop":0,
    "qs_pg:name":"Los Escullos",
    "qs_pg:name_adm0":"Espa\u00f1a",
    "qs_pg:name_adm1":"Andaluc\u00eda",
    "qs_pg:photos":872,
    "qs_pg:photos_1k":177,
    "qs_pg:photos_9k":4,
    "qs_pg:photos_9r":6,
    "qs_pg:photos_all":872,
    "qs_pg:photos_sr":10,
    "qs_pg:pop_sr":0,
    "qs_pg:qs_pg_placetype":"locality",
    "qs_pg:qs_pg_placetype_gp":"Town",
    "qs_pg:woe_adm0":23424950,
    "woe:adm0_id":23424950,
    "woe:name_adm0":"Espa\u00f1a",
    "woe:name_adm1":"Andaluc\u00eda",
    "woe:placetype":"Town",
    "wof:name":"Los Escullos",
    "wof:placetype":"locality"
},
  "geometry": {"coordinates":[-2.06339,36.80359],"type":"Point"}
}