{
  "type": "Feature",
  "properties": {
    "gn:admin1_code":"27",
    "gn:admin2_code":"LO",
    "gn:admin3_code":"26110",
    "gn:asciiname":"Ulizarna",
    "gn:country_code":"ES",
    "gn:dem":949,
    "gn:feature_class":"P",
    "gn:feature_code":"PPL",
    "gn:name":"Ulizarna",
    "gn:population":0,
    "gn:timezone":"Europe/Madrid",
    "iso:country":"ES",
    "wof:name":"Ulizarna",
    "wof:placetype":"locality"
},
  "geometry": {"coordinates":[-2.98159,42.34856],"type":"Point"}
}