{
  "type": "Feature",
  "properties": {
    "gn:admin1_code":"51",
    "gn:admin2_code":"AL",
    "gn:admin3_code":"04031",
    "gn:asciiname":"Arroyo Albanchez",
    "gn:country_code":"ES",
    "gn:dem":351,
    "gn:feature_class":"P",
    "gn:feature_code":"PPL",
    "gn:name":"Arroyo Albanchez",
    "gn:population":0,
    "gn:timezone":"Europe/Madrid",
    "iso:country":"ES",
    "name:eng_x_preferred":[
        "El Arroyo Albanchez"
    ],
    "wof:name":"Arroyo Albanchez",
    "wof:placetype":"locality"
},
  "geometry": {"coordinates":[-2.14431,37.32471],"type":"Point"}
}