{
  "type": "Feature",
  "properties": {
    "iso:country":"ES",
    "name:eng_x_preferred":[
        "El Ejido"
    ],
    "name:spa_x_preferred":[
        "El Ejido"
    ],
    "wof:name":"El Ejido",
    "wof:placetype":"neighbourhood"
},
  "geometry": {"coordinates":[-4.41790442348157,36.72831161814074],"type":"Point"}
}