{
  "type": "Feature",
  "properties": {
    "gn:admin1_code":"34",
    "gn:admin2_code":"O",
    "gn:admin3_code":"33011",
    "gn:asciiname":"Laron",
    "gn:country_code":"ES",
    "gn:dem":815,
    "gn:feature_class":"P",
    "gn:feature_code":"PPL",
    "gn:name":"Lar\u00f3n",
    "gn:population":0,
    "gn:timezone":"Europe/Madrid",
    "iso:country":"ES",
    "name:ast_x_preferred":[
        "\u1e36\u1e37ar\u00f3n"
    ],
    "name:spa_x_preferred":[
        "Lar\u00f3n"
    ],
    "name:und_x_variant":[
        "Lar\u00f3n"
    ],
    "wof:name":"Laron",
    "wof:placetype":"locality"
},
  "geometry": {"coordinates":[-6.63036,42.98634000000001],"type":"Point"}
}