{
  "type": "Feature",
  "properties": {
    "gn:admin1_code":"56",
    "gn:admin2_code":"GI",
    "gn:admin3_code":"17051",
    "gn:asciiname":"Nuestra Senora de Vida",
    "gn:country_code":"ES",
    "gn:dem":163,
    "gn:feature_class":"P",
    "gn:feature_code":"PPL",
    "gn:name":"Nuestra Se\u00f1ora de Vida",
    "gn:population":0,
    "gn:timezone":"Europe/Madrid",
    "iso:country":"ES",
    "wof:name":"Nuestra Senora de Vida",
    "wof:placetype":"locality"
},
  "geometry": {"coordinates":[2.83972,42.26431],"type":"Point"}
}