{
  "type": "Feature",
  "properties": {
    "iso:country":"ES",
    "name:eng_x_preferred":[
        "La Palma"
    ],
    "name:spa_x_preferred":[
        "La Palma"
    ],
    "wof:name":"La Palma",
    "wof:placetype":"neighbourhood"
},
  "geometry": {"coordinates":[-4.47109421391788,36.72197924703654],"type":"Point"}
}