{
  "type": "Feature",
  "properties": {
    "iso:country":"ES",
    "name:ben_x_preferred":[
        "\u09b2\u09be \u09aa\u09be\u09b2\u09ae\u09be"
    ],
    "name:ell_x_preferred":[
        "\u039b\u03b1 \u03a0\u03ac\u03bb\u03bc\u03b1"
    ],
    "name:eng_x_preferred":[
        "La Palma"
    ],
    "name:fas_x_preferred":[
        "\u0644\u0627 \u067e\u0627\u0644\u0645\u0627"
    ],
    "name:heb_x_preferred":[
        "\u05dc\u05d4 \u05e4\u05dc\u05de\u05d4"
    ],
    "name:hin_x_preferred":[
        "\u0932\u093e \u092a\u093e\u0932\u094d\u092e\u093e"
    ],
    "name:hun_x_preferred":[
        "La Palma"
    ],
    "name:ind_x_preferred":[
        "La Palma"
    ],
    "name:spa_x_preferred":[
        "La Palma"
    ],
    "name:swe_x_preferred":[
        "La Palma"
    ],
    "name:tur_x_preferred":[
        "La Palma"
    ],
    "name:ukr_x_preferred":[
        "\u041b\u0430-\u041f\u0430\u043b\u044c\u043c\u0430"
    ],
    "name:urd_x_preferred":[
        "\u0644\u0627 \u067e\u0627\u0644\u0645\u0627"
    ],
    "name:vie_x_preferred":[
        "La Palma"
    ],
    "wof:name":"La Palma",
    "wof:placetype":"neighbourhood"
},
  "geometry": {"coordinates":[-4.471094,36.721979],"type":"Point"}
}