{
  "type": "Feature",
  "properties": {
    "gn:gn_country":"ES",
    "gn:gn_fcode":"PPLA3",
    "gn:gn_pop":146,
    "gn:population":146,
    "iso:country":"ES",
    "name:arg_x_preferred":[
        "Pajares de la Laguna"
    ],
    "name:baq_x_preferred":[
        "Pajares de la Laguna"
    ],
    "name:cat_x_preferred":[
        "Pajares de la Laguna"
    ],
    "name:chi_x_preferred":[
        "\u5e15\u54c8\u96f7\u65af\u5fb7\u62c9\u62c9\u53e4\u7eb3"
    ],
    "name:dut_x_preferred":[
        "Pajares de la Laguna"
    ],
    "name:eng_x_preferred":[
        "Pajares de la Laguna"
    ],
    "name:fre_x_preferred":[
        "Pajares de la Laguna"
    ],
    "name:hun_x_preferred":[
        "Pajares de la Laguna"
    ],
    "name:ina_x_preferred":[
        "Pajares de la Laguna"
    ],
    "name:ita_x_preferred":[
        "Pajares de la Laguna"
    ],
    "name:kaz_x_preferred":[
        "\u041f\u0430\u0445\u0430\u0440\u0435\u0441-\u0434\u0435-\u043b\u0430-\u041b\u0430\u0433\u0443\u043d\u0430"
    ],
    "name:may_x_preferred":[
        "Pajares de la Laguna"
    ],
    "name:nan_x_preferred":[
        "Pajares de la Laguna"
    ],
    "name:oci_x_preferred":[
        "Pajares de la Laguna"
    ],
    "name:pol_x_preferred":[
        "Pajares de la Laguna"
    ],
    "name:por_x_preferred":[
        "Pajares de la Laguna"
    ],
    "name:rus_x_preferred":[
        "\u041f\u0430\u0445\u0430\u0440\u0435\u0441-\u0434\u0435-\u043b\u0430-\u041b\u0430\u0433\u0443\u043d\u0430"
    ],
    "name:spa_x_preferred":[
        "Pajares de la Laguna"
    ],
    "name:swe_x_preferred":[
        "Pajares de la Laguna"
    ],
    "name:ukr_x_preferred":[
        "\u041f\u0430\u0445\u0430\u0440\u0435\u0441-\u0434\u0435-\u043b\u0430-\u041b\u0430\u0433\u0443\u043d\u0430"
    ],
    "name:uzb_x_preferred":[
        "Pajares de la Laguna"
    ],
    "name:vie_x_preferred":[
        "Pajares de la Laguna"
    ],
    "name:war_x_preferred":[
        "Pajares de la Laguna"
    ],
    "qs_pg:aaroncc":"ES",
    "qs_pg:gn_country":"ES",
    "qs_pg:gn_fcode":"PPLA3",
    "qs_pg:gn_pop":146,
    "qs_pg:name":"Pajares de la Laguna",
    "qs_pg:name_adm0":"Espa\u00f1a",
    "qs_pg:name_adm1":"Castilla y Le\u00f3n",
    "qs_pg:photos_9r":0,
    "qs_pg:photos_sr":0,
    "qs_pg:pop_sr":1,
    "qs_pg:qs_pg_placetype":"locality",
    "qs_pg:qs_pg_placetype_gp":"Town",
    "qs_pg:woe_adm0":23424950,
    "woe:adm0_id":23424950,
    "woe:name_adm0":"Espa\u00f1a",
    "woe:name_adm1":"Castilla y Le\u00f3n",
    "woe:placetype":"Town",
    "wof:name":"Pajares de la Laguna",
    "wof:placetype":"locality",
    "wof:population":146
},
  "geometry": {"coordinates":[-5.50888,41.08754],"type":"Point"}
}