{
  "type": "Feature",
  "properties": {
    "iso:country":"ES",
    "name:ara_x_preferred":[
        "\u0623\u0628\u0627\u0644\u062b\u064a\u0633\u0643\u064a\u062a\u0627"
    ],
    "name:arg_x_preferred":[
        "Abaltzisketa"
    ],
    "name:ast_x_preferred":[
        "Abalcisqueta"
    ],
    "name:ast_x_variant":[
        "Abaltzisketa"
    ],
    "name:azb_x_preferred":[
        "\u0622\u0628\u0627\u0644\u062a\u0632\u06cc\u0633\u06a9\u062a\u0627"
    ],
    "name:bre_x_preferred":[
        "Abaltzisketa"
    ],
    "name:bul_x_preferred":[
        "\u0410\u0431\u0430\u043b\u0442\u0437\u0438\u0441\u043a\u0435\u0442\u0430"
    ],
    "name:cat_x_preferred":[
        "Abaltzisketa"
    ],
    "name:ceb_x_preferred":[
        "Abaltzisketa"
    ],
    "name:eng_x_preferred":[
        "Abaltzisketa"
    ],
    "name:eus_x_preferred":[
        "Abaltzisketa"
    ],
    "name:fas_x_preferred":[
        "\u0622\u0628\u0627\u0644\u062a\u0632\u06cc\u0633\u06a9\u062a\u0627"
    ],
    "name:fra_x_preferred":[
        "Abaltzisketa"
    ],
    "name:glg_x_preferred":[
        "Abaltzisketa"
    ],
    "name:hun_x_preferred":[
        "Abaltzisketa"
    ],
    "name:ita_x_preferred":[
        "Abaltzisketa"
    ],
    "name:jpn_x_preferred":[
        "\u30a2\u30d0\u30eb\u30c4\u30a3\u30b9\u30b1\u30bf"
    ],
    "name:msa_x_preferred":[
        "Abaltzisketa"
    ],
    "name:nld_x_preferred":[
        "Abaltzisketa"
    ],
    "name:oci_x_preferred":[
        "Abaltzisketa"
    ],
    "name:pol_x_preferred":[
        "Abaltzisketa"
    ],
    "name:por_x_preferred":[
        "Abaltzisketa"
    ],
    "name:rup_x_preferred":[
        "Abalcisqueta"
    ],
    "name:rus_x_preferred":[
        "\u0410\u0431\u0430\u043b\u044c\u0441\u0438\u0441\u043a\u0435\u0442\u0430"
    ],
    "name:sco_x_preferred":[
        "Abaltzisketa"
    ],
    "name:spa_x_preferred":[
        "Abalcisqueta"
    ],
    "name:swe_x_preferred":[
        "Abaltzisketa"
    ],
    "name:ukr_x_preferred":[
        "\u0410\u0431\u0430\u043b\u044c\u0446\u0438\u0441\u043a\u0435\u0442\u0430"
    ],
    "name:uzb_x_preferred":[
        "Abalcisqueta"
    ],
    "name:vie_x_preferred":[
        "Abaltzisketa"
    ],
    "name:war_x_preferred":[
        "Abaltzisketa"
    ],
    "name:zho_x_preferred":[
        "\u963f\u74e6\u5c14\u7279\u897f\u65af\u514b\u5854"
    ],
    "qs_pg:aaroncc":"ES",
    "qs_pg:name":"Abaltzisketa",
    "qs_pg:name_adm0":"Espa\u00f1a",
    "qs_pg:name_adm1":"Euskadi",
    "qs_pg:photos":60,
    "qs_pg:photos_1k":12,
    "qs_pg:photos_9k":1,
    "qs_pg:photos_9r":2,
    "qs_pg:photos_all":60,
    "qs_pg:photos_sr":2,
    "qs_pg:pop_sr":0,
    "qs_pg:qs_pg_placetype":"locality",
    "qs_pg:qs_pg_placetype_gp":"Town",
    "qs_pg:woe_adm0":23424950,
    "woe:adm0_id":23424950,
    "woe:name_adm0":"Espa\u00f1a",
    "woe:name_adm1":"Euskadi",
    "woe:placetype":"Town",
    "wof:name":"Abaltzisketa",
    "wof:placetype":"locality"
},
  "geometry": {"coordinates":[-2.105744,43.0346735],"type":"Point"}
}