{
  "type": "Feature",
  "properties": {
    "gn:admin1_code":"54",
    "gn:admin2_code":"AB",
    "gn:admin3_code":"02072",
    "gn:asciiname":"Casas del Rio",
    "gn:cc2":"ES",
    "gn:country_code":"ES",
    "gn:dem":400,
    "gn:feature_class":"P",
    "gn:feature_code":"PPL",
    "gn:name":"Casas del R\u00edo",
    "gn:population":0,
    "gn:timezone":"Europe/Madrid",
    "iso:country":"ES",
    "name:und_x_variant":[
        "Caser\u00edo Casas del R\u00edo",
        "Casas del R\u00edo"
    ],
    "wof:name":"Casas del Rio",
    "wof:placetype":"locality"
},
  "geometry": {"coordinates":[-1.81667,38.36667],"type":"Point"}
}