{
  "type": "Feature",
  "properties": {
    "gn:admin1_code":"34",
    "gn:admin2_code":"O",
    "gn:admin3_code":"33021",
    "gn:asciiname":"Corollos",
    "gn:country_code":"ES",
    "gn:dem":251,
    "gn:feature_class":"P",
    "gn:feature_code":"PPL",
    "gn:name":"Corollos",
    "gn:population":0,
    "gn:timezone":"Europe/Madrid",
    "iso:country":"ES",
    "wof:name":"Corollos",
    "wof:placetype":"locality"
},
  "geometry": {"coordinates":[-6.18728,43.52643],"type":"Point"}
}