{
  "type": "Feature",
  "properties": {
    "gn:admin1_code":"58",
    "gn:admin2_code":"LU",
    "gn:admin3_code":"27055",
    "gn:asciiname":"Reiriz",
    "gn:country_code":"ES",
    "gn:dem":517,
    "gn:feature_class":"P",
    "gn:feature_code":"PPL",
    "gn:name":"Reiriz",
    "gn:population":0,
    "gn:timezone":"Europe/Madrid",
    "iso:country":"ES",
    "wof:name":"Reiriz",
    "wof:placetype":"locality"
},
  "geometry": {"coordinates":[-7.35,42.75],"type":"Point"}
}