{
  "type": "Feature",
  "properties": {
    "gn:admin1_code":"55",
    "gn:admin2_code":"AV",
    "gn:admin3_code":"05152",
    "gn:asciiname":"Noharre",
    "gn:country_code":"ES",
    "gn:dem":862,
    "gn:feature_class":"P",
    "gn:feature_code":"PPL",
    "gn:name":"Noharre",
    "gn:population":0,
    "gn:timezone":"Europe/Madrid",
    "iso:country":"ES",
    "name:und_x_variant":[
        "Nobarre",
        "Noharre"
    ],
    "wof:name":"Noharre",
    "wof:placetype":"locality"
},
  "geometry": {"coordinates":[-4.78856,41.00159],"type":"Point"}
}