{
  "type": "Feature",
  "properties": {
    "gn:admin1_code":"58",
    "gn:admin2_code":"LU",
    "gn:admin3_code":"27050",
    "gn:asciiname":"Bustelo de Fisteus",
    "gn:country_code":"ES",
    "gn:dem":673,
    "gn:feature_class":"P",
    "gn:feature_code":"PPL",
    "gn:name":"Bustelo de Fist\u00e9us",
    "gn:population":0,
    "gn:timezone":"Europe/Madrid",
    "iso:country":"ES",
    "name:und_x_variant":[
        "Bustelo de Fist\u00e9us"
    ],
    "wof:name":"Bustelo de Fisteus",
    "wof:placetype":"locality"
},
  "geometry": {"coordinates":[-7.18708,42.50644000000001],"type":"Point"}
}