{
  "type": "Feature",
  "properties": {
    "gn:admin1_code":"60",
    "gn:admin2_code":"V",
    "gn:admin3_code":"46245",
    "gn:asciiname":"Torres-Torres",
    "gn:country_code":"ES",
    "gn:dem":163,
    "gn:feature_class":"P",
    "gn:feature_code":"PPL",
    "gn:name":"Torres-Torres",
    "gn:population":0,
    "gn:timezone":"Europe/Madrid",
    "iso:country":"ES",
    "wof:name":"Torres-Torres",
    "wof:placetype":"locality"
},
  "geometry": {"coordinates":[-0.35,39.73333],"type":"Point"}
}