{
  "type": "Feature",
  "properties": {
    "gn:admin1_code":"32",
    "gn:admin3_code":"31017",
    "gn:asciiname":"Aritzu",
    "gn:country_code":"ES",
    "gn:dem":626,
    "gn:feature_class":"P",
    "gn:feature_code":"PPL",
    "gn:name":"Aritzu",
    "gn:population":0,
    "gn:timezone":"Europe/Madrid",
    "iso:country":"ES",
    "name:eus_x_preferred":[
        "Aritzu"
    ],
    "name:spa_x_preferred":[
        "Arizu"
    ],
    "name:und_x_variant":[
        "Arizu"
    ],
    "wof:name":"Aritzu",
    "wof:placetype":"locality"
},
  "geometry": {"coordinates":[-1.61667,42.98333],"type":"Point"}
}