{
  "type": "Feature",
  "properties": {
    "iso:country":"ES",
    "name:eng_x_preferred":[
        "Explanada de la Estacion"
    ],
    "name:spa_x_preferred":[
        "Explanada de la Estaci\u00f3n"
    ],
    "wof:name":"Explanada de la Estacion",
    "wof:placetype":"neighbourhood"
},
  "geometry": {"coordinates":[-4.43109709296315,36.71313828420852],"type":"Point"}
}