{
  "type": "Feature",
  "properties": {
    "gn:admin1_code":"58",
    "gn:admin2_code":"LU",
    "gn:admin3_code":"27029",
    "gn:asciiname":"Leiras",
    "gn:country_code":"ES",
    "gn:dem":582,
    "gn:feature_class":"P",
    "gn:feature_code":"PPL",
    "gn:name":"Leiras",
    "gn:population":0,
    "gn:timezone":"Europe/Madrid",
    "iso:country":"ES",
    "wof:name":"Leiras",
    "wof:placetype":"locality"
},
  "geometry": {"coordinates":[-7.27375,43.23518],"type":"Point"}
}