{
  "type": "Feature",
  "properties": {
    "gn:admin1_code":"51",
    "gn:admin2_code":"AL",
    "gn:admin3_code":"04059",
    "gn:asciiname":"Los Jarales",
    "gn:country_code":"ES",
    "gn:dem":817,
    "gn:feature_class":"P",
    "gn:feature_code":"PPL",
    "gn:name":"Los Jarales",
    "gn:population":0,
    "gn:timezone":"Europe/Madrid",
    "iso:country":"ES",
    "name:und_x_variant":[
        "Cortijada Los Jarales",
        "Los Jarales"
    ],
    "wof:name":"Los Jarales",
    "wof:placetype":"locality"
},
  "geometry": {"coordinates":[-2.12964,37.22386],"type":"Point"}
}