{
  "type": "Feature",
  "properties": {
    "gn:admin1_code":"55",
    "gn:admin2_code":"BU",
    "gn:admin3_code":"09274",
    "gn:asciiname":"Garganchon",
    "gn:country_code":"ES",
    "gn:dem":928,
    "gn:feature_class":"P",
    "gn:feature_code":"PPL",
    "gn:name":"Garganch\u00f3n",
    "gn:population":0,
    "gn:timezone":"Europe/Madrid",
    "iso:country":"ES",
    "name:und_x_variant":[
        "Carganch\u00f3n",
        "Garganch\u00f3n"
    ],
    "wof:name":"Garganchon",
    "wof:placetype":"locality"
},
  "geometry": {"coordinates":[-3.22696,42.32689],"type":"Point"}
}