{
  "type": "Feature",
  "properties": {
    "gn:admin1_code":"58",
    "gn:admin2_code":"PO",
    "gn:admin3_code":"36059",
    "gn:asciiname":"Beigondo",
    "gn:cc2":"ES",
    "gn:country_code":"ES",
    "gn:dem":295,
    "gn:feature_class":"P",
    "gn:feature_code":"PPL",
    "gn:name":"Beigondo",
    "gn:population":0,
    "gn:timezone":"Europe/Madrid",
    "iso:country":"ES",
    "name:und_x_variant":[
        "San Cosme",
        "Beigonde",
        "Beigondo"
    ],
    "wof:name":"Beigondo",
    "wof:placetype":"locality"
},
  "geometry": {"coordinates":[-8.13333,42.85],"type":"Point"}
}