{
  "type": "Feature",
  "properties": {
    "gn:admin1_code":"58",
    "gn:admin2_code":"PO",
    "gn:admin3_code":"36047",
    "gn:asciiname":"Senra",
    "gn:country_code":"ES",
    "gn:dem":801,
    "gn:feature_class":"P",
    "gn:feature_code":"PPL",
    "gn:name":"Senra",
    "gn:population":0,
    "gn:timezone":"Europe/Madrid",
    "iso:country":"ES",
    "name:nld_x_preferred":[
        "Senra"
    ],
    "name:por_x_preferred":[
        "Senra"
    ],
    "name:spa_x_preferred":[
        "Senra"
    ],
    "name:und_x_variant":[
        "San Pelayo",
        "Senra"
    ],
    "wof:name":"Senra",
    "wof:placetype":"locality"
},
  "geometry": {"coordinates":[-7.93698,42.62069],"type":"Point"}
}