{
  "type": "Feature",
  "properties": {
    "gn:admin1_code":"34",
    "gn:admin2_code":"O",
    "gn:admin3_code":"33040",
    "gn:asciiname":"Monga",
    "gn:country_code":"ES",
    "gn:dem":260,
    "gn:feature_class":"P",
    "gn:feature_code":"PPL",
    "gn:name":"Monga",
    "gn:population":0,
    "gn:timezone":"Europe/Madrid",
    "iso:country":"ES",
    "name:ceb_x_preferred":[
        "Monga"
    ],
    "name:rus_x_preferred":[
        "\u041c\u043e\u043d\u0433\u0430"
    ],
    "name:swa_x_preferred":[
        "Mto Monga"
    ],
    "name:swe_x_preferred":[
        "Monga"
    ],
    "wof:name":"Monga",
    "wof:placetype":"locality"
},
  "geometry": {"coordinates":[-5.48859,43.36822],"type":"Point"}
}