{
  "type": "Feature",
  "properties": {
    "gn:admin1_code":"34",
    "gn:admin2_code":"O",
    "gn:admin3_code":"33040",
    "gn:asciiname":"Monga",
    "gn:country_code":"ES",
    "gn:dem":260,
    "gn:feature_class":"P",
    "gn:feature_code":"PPL",
    "gn:name":"Monga",
    "gn:population":0,
    "gn:timezone":"Europe/Madrid",
    "iso:country":"ES",
    "wof:name":"Monga",
    "wof:placetype":"locality"
},
  "geometry": {"coordinates":[-5.48859,43.36822],"type":"Point"}
}