{
  "type": "Feature",
  "properties": {
    "gn:admin1_code":"51",
    "gn:admin2_code":"SE",
    "gn:admin3_code":"41087",
    "gn:asciiname":"La Estacion de Benacazon",
    "gn:country_code":"ES",
    "gn:dem":123,
    "gn:feature_class":"P",
    "gn:feature_code":"PPL",
    "gn:name":"La Estaci\u00f3n de Benacaz\u00f3n",
    "gn:population":0,
    "gn:timezone":"Europe/Madrid",
    "iso:country":"ES",
    "wof:name":"La Estacion de Benacazon",
    "wof:placetype":"locality"
},
  "geometry": {"coordinates":[-6.19142,37.36368],"type":"Point"}
}