{
  "type": "Feature",
  "properties": {
    "gn:admin1_code":"59",
    "gn:admin2_code":"SS",
    "gn:admin3_code":"20064",
    "gn:asciiname":"Pasajes de San Juan",
    "gn:country_code":"ES",
    "gn:dem":42,
    "gn:feature_class":"P",
    "gn:feature_code":"PPL",
    "gn:name":"Pasai Donibane",
    "gn:population":0,
    "gn:timezone":"Europe/Madrid",
    "iso:country":"ES",
    "name:eus_x_preferred":[
        "Pasai Donibane"
    ],
    "name:oci_x_preferred":[
        "Passatjes"
    ],
    "name:spa_x_preferred":[
        "Pasajes"
    ],
    "name:spa_x_variant":[
        "Pasajes San Juan",
        "Pasajes de San Juan"
    ],
    "name:und_x_variant":[
        "San Juan"
    ],
    "wof:name":"Pasajes de San Juan",
    "wof:placetype":"locality"
},
  "geometry": {"coordinates":[-1.91601,43.32504],"type":"Point"}
}