{
  "type": "Feature",
  "properties": {
    "gn:admin1_code":"31",
    "gn:admin2_code":"MU",
    "gn:admin3_code":"30021",
    "gn:asciiname":"Casas de Egea",
    "gn:country_code":"ES",
    "gn:dem":160,
    "gn:feature_class":"P",
    "gn:feature_code":"PPL",
    "gn:name":"Casas de Egea",
    "gn:population":0,
    "gn:timezone":"Europe/Madrid",
    "iso:country":"ES",
    "name:und_x_variant":[
        "Caser\u00edo Casa de Egea",
        "Casas de Egea"
    ],
    "wof:name":"Casas de Egea",
    "wof:placetype":"locality"
},
  "geometry": {"coordinates":[-1.21153,37.69847],"type":"Point"}
}