{
  "type": "Feature",
  "properties": {
    "gn:country":"ES",
    "gn:fcode":"PPL",
    "gn:population":0,
    "iso:country":"ES",
    "name:cat_x_preferred":[
        "Cala'n Bosch"
    ],
    "name:cat_x_variant":[
        "Cala en Bosch"
    ],
    "name:ceb_x_preferred":[
        "Cala'n Bosch"
    ],
    "name:deu_x_preferred":[
        "Cala en Bosch"
    ],
    "name:eng_x_preferred":[
        "Cala en Bosch"
    ],
    "name:nld_x_preferred":[
        "Cala en Bosch"
    ],
    "name:spa_x_preferred":[
        "Cala en Bosch"
    ],
    "name:swe_x_preferred":[
        "Cala en Bosch"
    ],
    "name:swe_x_variant":[
        "Cala'n Bosch"
    ],
    "qs_pg:aaroncc":"ES",
    "qs_pg:gn_country":"ES",
    "qs_pg:gn_fcode":"PPL",
    "qs_pg:gn_pop":0,
    "qs_pg:name":"Cala en Bosc",
    "qs_pg:name_adm0":"Espa\u00f1a",
    "qs_pg:name_adm1":"Illes Balears",
    "qs_pg:photos":209,
    "qs_pg:photos_1k":42,
    "qs_pg:photos_9k":1,
    "qs_pg:photos_9r":4,
    "qs_pg:photos_all":209,
    "qs_pg:photos_sr":4,
    "qs_pg:pop_sr":0,
    "qs_pg:qs_pg_placetype":"locality",
    "qs_pg:qs_pg_placetype_gp":"Town",
    "qs_pg:woe_adm0":23424950,
    "woe:adm0_id":23424950,
    "woe:name_adm0":"Espa\u00f1a",
    "woe:name_adm1":"Illes Balears",
    "woe:placetype":"Town",
    "wof:name":"Cala en Bosc",
    "wof:placetype":"locality"
},
  "geometry": {"coordinates":[3.832,39.92659],"type":"Point"}
}