{
  "type": "Feature",
  "properties": {
    "gn:admin1_code":"31",
    "gn:admin2_code":"MU",
    "gn:admin3_code":"30030",
    "gn:asciiname":"Las Penicas",
    "gn:country_code":"ES",
    "gn:dem":35,
    "gn:feature_class":"P",
    "gn:feature_code":"PPL",
    "gn:name":"Las Pe\u00f1icas",
    "gn:population":0,
    "gn:timezone":"Europe/Madrid",
    "iso:country":"ES",
    "name:und_x_variant":[
        "Caser\u00edo Las Pe\u00f1icas",
        "Las Pe\u00f1icas"
    ],
    "wof:name":"Las Penicas",
    "wof:placetype":"locality"
},
  "geometry": {"coordinates":[-1.07391,38.05404],"type":"Point"}
}