{
  "type": "Feature",
  "properties": {
    "gn:admin1_code":"58",
    "gn:admin2_code":"C",
    "gn:admin3_code":"15049",
    "gn:asciiname":"Labacengos",
    "gn:cc2":"ES",
    "gn:country_code":"ES",
    "gn:dem":291,
    "gn:feature_class":"P",
    "gn:feature_code":"PPL",
    "gn:name":"Labacengos",
    "gn:population":0,
    "gn:timezone":"Europe/Madrid",
    "iso:country":"ES",
    "name:und_x_variant":[
        "Santa Mar\u00eda",
        "Labacengos"
    ],
    "wof:name":"Labacengos",
    "wof:placetype":"locality"
},
  "geometry": {"coordinates":[-7.96667,43.56667],"type":"Point"}
}