{
  "type": "Feature",
  "properties": {
    "gn:admin1_code":"57",
    "gn:admin2_code":"BA",
    "gn:admin3_code":"06060",
    "gn:asciiname":"Valdearenales",
    "gn:country_code":"ES",
    "gn:dem":358,
    "gn:feature_class":"P",
    "gn:feature_code":"PPL",
    "gn:name":"Valdearenales",
    "gn:population":0,
    "gn:timezone":"Europe/Madrid",
    "iso:country":"ES",
    "name:und_x_variant":[
        "Casas Valdearenales",
        "Valdearenales"
    ],
    "wof:name":"Valdearenales",
    "wof:placetype":"locality"
},
  "geometry": {"coordinates":[-6.05131,38.80829],"type":"Point"}
}