{
  "type": "Feature",
  "properties": {
    "gn:admin1_code":"34",
    "gn:admin2_code":"O",
    "gn:admin3_code":"33026",
    "gn:asciiname":"Penaflor",
    "gn:country_code":"ES",
    "gn:dem":48,
    "gn:feature_class":"P",
    "gn:feature_code":"PPL",
    "gn:name":"Pe\u00f1aflor",
    "gn:population":261,
    "gn:timezone":"Europe/Madrid",
    "iso:country":"ES",
    "name:ast_x_preferred":[
        "Pe\u00f1aflor"
    ],
    "name:deu_x_preferred":[
        "Pe\u00f1aflor"
    ],
    "name:spa_x_preferred":[
        "Pe\u00f1aflor"
    ],
    "wof:name":"Penaflor",
    "wof:placetype":"locality",
    "wof:population":261
},
  "geometry": {"coordinates":[-6.04609,43.4023],"type":"Point"}
}