{
  "type": "Feature",
  "properties": {
    "gn:admin1_code":"27",
    "gn:admin2_code":"LO",
    "gn:admin3_code":"26050",
    "gn:asciiname":"Cirinuela",
    "gn:country_code":"ES",
    "gn:dem":717,
    "gn:feature_class":"P",
    "gn:feature_code":"PPL",
    "gn:name":"Ciri\u00f1uela",
    "gn:population":0,
    "gn:timezone":"Europe/Madrid",
    "iso:country":"ES",
    "name:und_x_variant":[
        "Ciri\u00f1uela"
    ],
    "wof:name":"Cirinuela",
    "wof:placetype":"locality"
},
  "geometry": {"coordinates":[-2.89261,42.42249],"type":"Point"}
}