{
  "type": "Feature",
  "properties": {
    "gn:admin1_code":"56",
    "gn:admin2_code":"T",
    "gn:admin3_code":"43012",
    "gn:asciiname":"la Riera de Gaia",
    "gn:country_code":"ES",
    "gn:dem":25,
    "gn:feature_class":"P",
    "gn:feature_code":"PPL",
    "gn:name":"la Riera de Gai\u00e0",
    "gn:population":0,
    "gn:timezone":"Europe/Madrid",
    "iso:country":"ES",
    "name:cat_x_preferred":[
        "la Riera de Gai\u00e0"
    ],
    "name:spa_x_preferred":[
        "la Riera"
    ],
    "name:und_x_variant":[
        "La Riera"
    ],
    "wof:name":"la Riera de Gaia",
    "wof:placetype":"locality"
},
  "geometry": {"coordinates":[1.36667,41.16667],"type":"Point"}
}