{
  "type": "Feature",
  "properties": {
    "gn:admin1_code":"34",
    "gn:admin2_code":"O",
    "gn:admin3_code":"33009",
    "gn:asciiname":"La Puerta",
    "gn:country_code":"ES",
    "gn:dem":329,
    "gn:feature_class":"P",
    "gn:feature_code":"PPL",
    "gn:name":"La Puerta",
    "gn:population":0,
    "gn:timezone":"Europe/Madrid",
    "iso:country":"ES",
    "name:ceb_x_preferred":[
        "La Puerta"
    ],
    "name:deu_x_preferred":[
        "La Puerta"
    ],
    "name:fra_x_preferred":[
        "La Puerta"
    ],
    "name:ita_x_preferred":[
        "La Puerta"
    ],
    "name:por_x_preferred":[
        "La Puerta"
    ],
    "name:spa_x_preferred":[
        "La Puerta"
    ],
    "name:swe_x_preferred":[
        "La Puerta"
    ],
    "name:zho_x_preferred":[
        "\u62c9\u666e\u57c3\u723e\u5854"
    ],
    "wof:name":"La Puerta",
    "wof:placetype":"locality"
},
  "geometry": {"coordinates":[-5.43111,43.42007],"type":"Point"}
}