{
  "type": "Feature",
  "properties": {
    "gn:country":"ES",
    "gn:fcode":"PPL",
    "gn:population":0,
    "iso:country":"ES",
    "name:ara_x_preferred":[
        "\u0628\u0646\u0627\u0621 \u0645\u062d\u0645\u062f"
    ],
    "name:bul_x_preferred":[
        "\u0411\u0435\u043d\u0430\u043c\u0430\u0445\u043e\u043c\u0430"
    ],
    "name:ceb_x_preferred":[
        "Benamahoma"
    ],
    "name:eng_x_preferred":[
        "Benamahoma"
    ],
    "name:epo_x_preferred":[
        "Benamahoma"
    ],
    "name:fra_x_preferred":[
        "Benamahoma"
    ],
    "name:hun_x_preferred":[
        "Benamahoma"
    ],
    "name:nld_x_preferred":[
        "Benamahoma"
    ],
    "name:spa_x_preferred":[
        "Benamahoma"
    ],
    "name:swe_x_preferred":[
        "Benamahoma"
    ],
    "qs_pg:aaroncc":"ES",
    "qs_pg:gn_country":"ES",
    "qs_pg:gn_fcode":"PPL",
    "qs_pg:gn_pop":0,
    "qs_pg:name":"Benamahoma",
    "qs_pg:name_adm0":"Espa\u00f1a",
    "qs_pg:name_adm1":"Andaluc\u00eda",
    "qs_pg:photos":444,
    "qs_pg:photos_1k":90,
    "qs_pg:photos_9k":2,
    "qs_pg:photos_9r":5,
    "qs_pg:photos_all":444,
    "qs_pg:photos_sr":6,
    "qs_pg:pop_sr":0,
    "qs_pg:qs_pg_placetype":"locality",
    "qs_pg:qs_pg_placetype_gp":"Town",
    "qs_pg:woe_adm0":23424950,
    "woe:adm0_id":23424950,
    "woe:name_adm0":"Espa\u00f1a",
    "woe:name_adm1":"Andaluc\u00eda",
    "woe:placetype":"Town",
    "wof:name":"Benamahoma",
    "wof:placetype":"locality"
},
  "geometry": {"coordinates":[-5.46656,36.76505],"type":"Point"}
}