{
  "type": "Feature",
  "properties": {
    "gn:admin1_code":"32",
    "gn:admin3_code":"31139",
    "gn:asciiname":"Narcue",
    "gn:country_code":"ES",
    "gn:dem":693,
    "gn:feature_class":"P",
    "gn:feature_code":"PPL",
    "gn:name":"Narcu\u00e9",
    "gn:population":0,
    "gn:timezone":"Europe/Madrid",
    "iso:country":"ES",
    "name:und_x_variant":[
        "Narcu\u00e9"
    ],
    "wof:name":"Narcue",
    "wof:placetype":"locality"
},
  "geometry": {"coordinates":[-2.25744,42.72483],"type":"Point"}
}