{
  "type": "Feature",
  "properties": {
    "gn:admin1_code":"59",
    "gn:admin2_code":"BI",
    "gn:admin3_code":"48909",
    "gn:asciiname":"Icazurietas",
    "gn:country_code":"ES",
    "gn:dem":329,
    "gn:feature_class":"P",
    "gn:feature_code":"PPL",
    "gn:name":"Ikazurieta",
    "gn:population":0,
    "gn:timezone":"Europe/Madrid",
    "iso:country":"ES",
    "wof:name":"Icazurietas",
    "wof:placetype":"locality"
},
  "geometry": {"coordinates":[-2.59077,43.33181],"type":"Point"}
}