{
  "type": "Feature",
  "properties": {
    "gn:admin1_code":"58",
    "gn:admin2_code":"OR",
    "gn:admin3_code":"32048",
    "gn:asciiname":"Castromil",
    "gn:country_code":"ES",
    "gn:dem":1035,
    "gn:feature_class":"P",
    "gn:feature_code":"PPL",
    "gn:name":"Castromil",
    "gn:population":0,
    "gn:timezone":"Europe/Madrid",
    "iso:country":"ES",
    "name:und_x_variant":[
        "Nuestra Se\u00f1ora de la Encarnaci\u00f3n de Castromil",
        "Castromil"
    ],
    "wof:name":"Castromil",
    "wof:placetype":"locality"
},
  "geometry": {"coordinates":[-6.97593,42.00268],"type":"Point"}
}