{
  "type": "Feature",
  "properties": {
    "gn:admin1_code":"55",
    "gn:admin2_code":"BU",
    "gn:admin3_code":"09416",
    "gn:asciiname":"Gallejones",
    "gn:country_code":"ES",
    "gn:dem":659,
    "gn:feature_class":"P",
    "gn:feature_code":"PPL",
    "gn:name":"Gallejones",
    "gn:population":0,
    "gn:timezone":"Europe/Madrid",
    "iso:country":"ES",
    "name:und_x_variant":[
        "Callejones",
        "Gallejones"
    ],
    "wof:name":"Gallejones",
    "wof:placetype":"locality"
},
  "geometry": {"coordinates":[-3.75678,42.85133],"type":"Point"}
}