{
  "type": "Feature",
  "properties": {
    "gn:admin1_code":"51",
    "gn:admin2_code":"AL",
    "gn:admin3_code":"04018",
    "gn:asciiname":"El Canalito",
    "gn:country_code":"ES",
    "gn:dem":633,
    "gn:feature_class":"P",
    "gn:feature_code":"PPL",
    "gn:name":"El Canalito",
    "gn:population":0,
    "gn:timezone":"Europe/Madrid",
    "iso:country":"ES",
    "name:und_x_variant":[
        "Cortijada El Canalito",
        "El Canalito"
    ],
    "wof:name":"El Canalito",
    "wof:placetype":"locality"
},
  "geometry": {"coordinates":[-2.42209,37.36651],"type":"Point"}
}