{
  "type": "Feature",
  "properties": {
    "gn:admin1_code":"55",
    "gn:admin2_code":"LE",
    "gn:admin3_code":"24109",
    "gn:asciiname":"Salientes",
    "gn:country_code":"ES",
    "gn:dem":1230,
    "gn:feature_class":"P",
    "gn:feature_code":"PPL",
    "gn:name":"Salientes",
    "gn:population":0,
    "gn:timezone":"Europe/Madrid",
    "iso:country":"ES",
    "wof:name":"Salientes",
    "wof:placetype":"locality"
},
  "geometry": {"coordinates":[-6.31388,42.84942],"type":"Point"}
}