{
  "type": "Feature",
  "properties": {
    "gn:admin1_code":"58",
    "gn:admin2_code":"LU",
    "gn:admin3_code":"27046",
    "gn:asciiname":"Lua",
    "gn:country_code":"ES",
    "gn:dem":481,
    "gn:feature_class":"P",
    "gn:feature_code":"PPL",
    "gn:name":"L\u00faa",
    "gn:population":0,
    "gn:timezone":"Europe/Madrid",
    "iso:country":"ES",
    "name:ceb_x_preferred":[
        "Lua"
    ],
    "name:dan_x_preferred":[
        "Lua"
    ],
    "name:deu_x_preferred":[
        "Lua"
    ],
    "name:eus_x_preferred":[
        "Lua"
    ],
    "name:fra_x_preferred":[
        "Lua"
    ],
    "name:gle_x_preferred":[
        "Luas"
    ],
    "name:glg_x_preferred":[
        "L\u00faa"
    ],
    "name:hun_x_preferred":[
        "Lua"
    ],
    "name:ind_x_preferred":[
        "Lua"
    ],
    "name:lat_x_preferred":[
        "Lua"
    ],
    "name:nld_x_preferred":[
        "Lua"
    ],
    "name:por_x_preferred":[
        "Lua"
    ],
    "name:ron_x_preferred":[
        "Lua"
    ],
    "name:srp_x_preferred":[
        "Lua"
    ],
    "name:swe_x_preferred":[
        "Lua"
    ],
    "name:tha_x_preferred":[
        "\u0e25\u0e39\u0e2d\u0e32"
    ],
    "name:und_x_variant":[
        "San Mart\u00edn"
    ],
    "wof:name":"Lua",
    "wof:placetype":"locality"
},
  "geometry": {"coordinates":[-7.24885,43.16569000000001],"type":"Point"}
}