{
  "type": "Feature",
  "properties": {
    "gn:admin1_code":"58",
    "gn:admin2_code":"LU",
    "gn:admin3_code":"27046",
    "gn:asciiname":"Lua",
    "gn:country_code":"ES",
    "gn:dem":481,
    "gn:feature_class":"P",
    "gn:feature_code":"PPL",
    "gn:name":"L\u00faa",
    "gn:population":0,
    "gn:timezone":"Europe/Madrid",
    "iso:country":"ES",
    "name:und_x_variant":[
        "San Mart\u00edn",
        "L\u00faa"
    ],
    "wof:name":"Lua",
    "wof:placetype":"locality"
},
  "geometry": {"coordinates":[-7.24885,43.16569000000001],"type":"Point"}
}