{
  "type": "Feature",
  "properties": {
    "gn:admin1_code":"58",
    "gn:admin2_code":"LU",
    "gn:admin3_code":"27046",
    "gn:asciiname":"Lua",
    "gn:country_code":"ES",
    "gn:dem":481,
    "gn:feature_class":"P",
    "gn:feature_code":"PPL",
    "gn:name":"L\u00faa",
    "gn:population":0,
    "gn:timezone":"Europe/Madrid",
    "iso:country":"ES",
    "name:ara_x_preferred":[
        "\u0644\u0648\u0627"
    ],
    "name:ben_x_preferred":[
        "\u09b2\u09c1\u09df\u09be"
    ],
    "name:ceb_x_preferred":[
        "Lua"
    ],
    "name:dan_x_preferred":[
        "Lua"
    ],
    "name:deu_x_preferred":[
        "Lua"
    ],
    "name:ell_x_preferred":[
        "\u039b\u03bf\u03c5\u03b1"
    ],
    "name:eng_x_preferred":[
        "Lua Tributary"
    ],
    "name:eus_x_preferred":[
        "Lua"
    ],
    "name:fas_x_preferred":[
        "\u0644\u0648\u0627"
    ],
    "name:fra_x_preferred":[
        "Lua"
    ],
    "name:gle_x_preferred":[
        "Luas"
    ],
    "name:glg_x_preferred":[
        "L\u00faa"
    ],
    "name:heb_x_preferred":[
        "\u05dc\u05d5\u05d0\u05df"
    ],
    "name:hin_x_preferred":[
        "\u0932\u0941\u0906"
    ],
    "name:hun_x_preferred":[
        "Lua"
    ],
    "name:ind_x_preferred":[
        "Lua"
    ],
    "name:ita_x_preferred":[
        "Lua"
    ],
    "name:jpn_x_preferred":[
        "\u30eb\u30a2\u5ddd"
    ],
    "name:kor_x_preferred":[
        "\ub8e8\uc544"
    ],
    "name:lat_x_preferred":[
        "Lua"
    ],
    "name:nld_x_preferred":[
        "Lua"
    ],
    "name:pol_x_preferred":[
        "Lua"
    ],
    "name:por_x_preferred":[
        "Lua"
    ],
    "name:ron_x_preferred":[
        "Lua"
    ],
    "name:rus_x_preferred":[
        "\u0440\u0435\u043a\u0430 \u041b\u0443\u0430"
    ],
    "name:spa_x_preferred":[
        "Lua"
    ],
    "name:srp_x_preferred":[
        "Lua"
    ],
    "name:swe_x_preferred":[
        "Lua"
    ],
    "name:tha_x_preferred":[
        "\u0e25\u0e39\u0e2d\u0e32"
    ],
    "name:tur_x_preferred":[
        "Lua"
    ],
    "name:ukr_x_preferred":[
        "\u041b\u0443\u0430"
    ],
    "name:und_x_variant":[
        "San Mart\u00edn"
    ],
    "name:urd_x_preferred":[
        "\u0644\u0648\u0627"
    ],
    "name:vie_x_preferred":[
        "S\u00f4ng Lua"
    ],
    "name:zho_cn_x_preferred":[
        "\u5362\u963f\u6cb3"
    ],
    "name:zho_tw_x_preferred":[
        "\u8def\u4e9e\u6cb3"
    ],
    "wof:name":"Lua",
    "wof:placetype":"locality"
},
  "geometry": {"coordinates":[-7.24885,43.16569],"type":"Point"}
}