{
  "type": "Feature",
  "properties": {
    "gn:admin1_code":"31",
    "gn:admin2_code":"MU",
    "gn:admin3_code":"30024",
    "gn:asciiname":"El Molinillo",
    "gn:country_code":"ES",
    "gn:dem":310,
    "gn:feature_class":"P",
    "gn:feature_code":"PPL",
    "gn:name":"El Molinillo",
    "gn:population":0,
    "gn:timezone":"Europe/Madrid",
    "iso:country":"ES",
    "name:und_x_variant":[
        "Caser\u00edo El Molinillo",
        "El Molinillo"
    ],
    "wof:name":"El Molinillo",
    "wof:placetype":"locality"
},
  "geometry": {"coordinates":[-1.66972,37.66042],"type":"Point"}
}