{
  "type": "Feature",
  "properties": {
    "iso:country":"ES",
    "name:ara_x_preferred":[
        "\u062b\u064a\u063a\u0627\u0645\u0627"
    ],
    "name:arg_x_preferred":[
        "Zegama"
    ],
    "name:ast_x_preferred":[
        "Zegama"
    ],
    "name:bre_x_preferred":[
        "Zegama"
    ],
    "name:bul_x_preferred":[
        "\u0417\u0435\u0433\u0430\u043c\u0430"
    ],
    "name:cat_x_preferred":[
        "Zegama"
    ],
    "name:ceb_x_preferred":[
        "Zegama"
    ],
    "name:dan_x_preferred":[
        "Zegama"
    ],
    "name:deu_x_preferred":[
        "Zegama"
    ],
    "name:eng_x_preferred":[
        "Zegama"
    ],
    "name:eus_x_preferred":[
        "Zegama"
    ],
    "name:fao_x_preferred":[
        "Zegama"
    ],
    "name:fra_x_preferred":[
        "Zegama"
    ],
    "name:glg_x_preferred":[
        "Zegama"
    ],
    "name:hun_x_preferred":[
        "Zegama"
    ],
    "name:ind_x_preferred":[
        "Zegama"
    ],
    "name:ind_x_variant":[
        "Cegama"
    ],
    "name:ita_x_preferred":[
        "Zegama"
    ],
    "name:jpn_x_preferred":[
        "\u30bb\u30ac\u30de"
    ],
    "name:kal_x_preferred":[
        "Zegama"
    ],
    "name:msa_x_preferred":[
        "Zegama"
    ],
    "name:nld_x_preferred":[
        "Zegama"
    ],
    "name:nno_x_preferred":[
        "Zegama"
    ],
    "name:nob_x_preferred":[
        "Zegama"
    ],
    "name:oci_x_preferred":[
        "Zegama"
    ],
    "name:pol_x_preferred":[
        "Zegama"
    ],
    "name:por_x_preferred":[
        "Zegama"
    ],
    "name:rus_x_preferred":[
        "\u0421\u0435\u0433\u0430\u043c\u0430"
    ],
    "name:sco_x_preferred":[
        "Zegama"
    ],
    "name:spa_x_preferred":[
        "Cegama"
    ],
    "name:sqi_x_preferred":[
        "Zegama"
    ],
    "name:swe_x_preferred":[
        "Zegama"
    ],
    "name:ukr_x_preferred":[
        "\u0421\u0435\u0433\u0430\u043c\u0430"
    ],
    "name:uzb_x_preferred":[
        "Zegama"
    ],
    "name:uzb_x_variant":[
        "Cegama"
    ],
    "name:vie_x_preferred":[
        "Zegama"
    ],
    "name:war_x_preferred":[
        "Zegama"
    ],
    "name:zho_x_preferred":[
        "\u585e\u52a0\u9a6c"
    ],
    "qs:a0":"Espa\u00f1a",
    "qs:a1":"*Gipuzkoa",
    "qs:a1r":"0Pa\u00eds Vasco",
    "qs:adm0":"Espa\u00f1a",
    "qs:la_lc":"*",
    "qs:level":"locality",
    "qs:loc":"Zegama",
    "qs:loc_alt":"Zegama",
    "qs:pop":0,
    "qs:type":"buffered point",
    "wd:wordcount":404,
    "wof:name":"Zegama",
    "wof:placetype":"locality"
},
  "geometry": {"coordinates":[-2.290066,42.975952],"type":"Point"}
}