{
  "type": "Feature",
  "properties": {
    "gn:admin1_code":"58",
    "gn:admin2_code":"LU",
    "gn:admin3_code":"27034",
    "gn:asciiname":"Vallo",
    "gn:country_code":"ES",
    "gn:dem":654,
    "gn:feature_class":"P",
    "gn:feature_code":"PPL",
    "gn:name":"Vallo",
    "gn:population":0,
    "gn:timezone":"Europe/Madrid",
    "iso:country":"ES",
    "name:ceb_x_preferred":[
        "Vallo"
    ],
    "name:deu_x_preferred":[
        "Vallo"
    ],
    "name:fra_x_preferred":[
        "Vallo"
    ],
    "name:glg_x_preferred":[
        "Vallo"
    ],
    "name:ita_x_preferred":[
        "Vallo"
    ],
    "name:por_x_preferred":[
        "Vallo"
    ],
    "name:rus_x_preferred":[
        "\u0412\u0430\u043b\u043b\u043e"
    ],
    "name:spa_x_preferred":[
        "Vallo"
    ],
    "name:srp_x_preferred":[
        "Valo"
    ],
    "name:swe_x_preferred":[
        "Vallo"
    ],
    "wof:name":"Vallo",
    "wof:placetype":"locality"
},
  "geometry": {"coordinates":[-6.98735,42.89873],"type":"Point"}
}