{
  "type": "Feature",
  "properties": {
    "gn:admin1_code":"34",
    "gn:admin2_code":"O",
    "gn:admin3_code":"33028",
    "gn:asciiname":"Cecos",
    "gn:country_code":"ES",
    "gn:dem":349,
    "gn:feature_class":"P",
    "gn:feature_code":"PPL",
    "gn:name":"Cecos",
    "gn:population":0,
    "gn:timezone":"Europe/Madrid",
    "iso:country":"ES",
    "wof:name":"Cecos",
    "wof:placetype":"locality"
},
  "geometry": {"coordinates":[-6.85876,43.02058],"type":"Point"}
}