{
  "type": "Feature",
  "properties": {
    "gn:population":1243,
    "iso:country":"ES",
    "name:ara_x_preferred":[
        "\u0628\u064a\u062f\u0631\u0648 \u0628\u064a\u0631\u0646\u0627\u0631\u062f\u0648"
    ],
    "name:arg_x_preferred":[
        "Pedro Bernardo"
    ],
    "name:cat_x_preferred":[
        "Pedro Bernardo"
    ],
    "name:eng_x_preferred":[
        "Pedro Bernardo"
    ],
    "name:eus_x_preferred":[
        "Pedro Bernardo"
    ],
    "name:fas_x_preferred":[
        "\u067e\u062f\u0631\u0648 \u0628\u0631\u0646\u0627\u0631\u062f\u0648"
    ],
    "name:fra_x_preferred":[
        "Pedro Bernardo"
    ],
    "name:hun_x_preferred":[
        "Pedro Bernardo"
    ],
    "name:hye_x_preferred":[
        "\u054a\u0565\u0564\u0580\u0578 \u0532\u0565\u0580\u0576\u0561\u0580\u0564\u0578"
    ],
    "name:hye_x_variant":[
        "\u0532\u0561\u0580\u0562\u0561\u0564\u056b\u056c\u0575\u0578 \u0564\u0565 \u0537\u057c\u0565\u0580\u0578\u057d"
    ],
    "name:ina_x_preferred":[
        "Pedro Bernardo"
    ],
    "name:ita_x_preferred":[
        "Pedro Bernardo"
    ],
    "name:kaz_x_preferred":[
        "\u041f\u0435\u0434\u0440\u043e-\u0411\u0435\u0440\u043d\u0430\u0440\u0434\u043e"
    ],
    "name:mkd_x_preferred":[
        "\u041f\u0435\u0434\u0440\u043e \u0411\u0435\u0440\u043d\u0430\u0440\u0434\u043e"
    ],
    "name:msa_x_preferred":[
        "Pedro Bernardo"
    ],
    "name:nld_x_preferred":[
        "Pedro Bernardo"
    ],
    "name:oci_x_preferred":[
        "Pedro Bernardo"
    ],
    "name:pol_x_preferred":[
        "Pedro Bernardo"
    ],
    "name:por_x_preferred":[
        "Pedro Bernardo"
    ],
    "name:rus_x_preferred":[
        "\u041f\u0435\u0434\u0440\u043e-\u0411\u0435\u0440\u043d\u0430\u0440\u0434\u043e"
    ],
    "name:spa_x_preferred":[
        "Pedro Bernardo"
    ],
    "name:swe_x_preferred":[
        "Pedro Bernardo"
    ],
    "name:ukr_x_preferred":[
        "\u041f\u0435\u0434\u0440\u043e-\u0411\u0435\u0440\u043d\u0430\u0440\u0434\u043e"
    ],
    "name:unk_x_variant":[
        "Bernardos"
    ],
    "name:uzb_x_preferred":[
        "Pedro Bernardo"
    ],
    "name:vie_x_preferred":[
        "Pedro Bernardo"
    ],
    "name:war_x_preferred":[
        "Pedro Bernardo"
    ],
    "name:zho_x_preferred":[
        "\u4f69\u5fb7\u7f57\u97e6\u5c14\u7eb3\u5c14\u591a"
    ],
    "qs:a0":"Espa\u00f1a",
    "qs:a1":"*Avila",
    "qs:a1r":"0Castilla y Le\u00f3n",
    "qs:adm0":"Espa\u00f1a",
    "qs:la_lc":"*",
    "qs:level":"locality",
    "qs:loc":"Pedro Bernardo",
    "qs:loc_alt":"Pedro Bernardo",
    "qs:pop":0,
    "qs:type":"buffered point",
    "wd:wordcount":46,
    "wof:lang":[
        "spa"
    ],
    "wof:name":"Pedro Bernardo",
    "wof:placetype":"locality",
    "wof:population":1243
},
  "geometry": {"coordinates":[-4.911729,40.243187],"type":"Point"}
}