{
  "type": "Feature",
  "properties": {
    "gn:admin1_code":"58",
    "gn:admin2_code":"LU",
    "gn:admin3_code":"27046",
    "gn:asciiname":"Gondel",
    "gn:cc2":"ES",
    "gn:country_code":"ES",
    "gn:dem":659,
    "gn:feature_class":"P",
    "gn:feature_code":"PPL",
    "gn:name":"Gondel",
    "gn:population":0,
    "gn:timezone":"Europe/Madrid",
    "iso:country":"ES",
    "name:und_x_variant":[
        "San Cosme",
        "Gondel"
    ],
    "wof:name":"Gondel",
    "wof:placetype":"locality"
},
  "geometry": {"coordinates":[-7.31667,43.11667],"type":"Point"}
}