{
  "type": "Feature",
  "properties": {
    "gn:country":"ES",
    "gn:fcode":"PPLA3",
    "gn:population":111,
    "iso:country":"ES",
    "name:arg_x_preferred":[
        "Nava de B\u00e9jar"
    ],
    "name:cat_x_preferred":[
        "Nava de B\u00e9jar"
    ],
    "name:che_x_preferred":[
        "\u041d\u0430\u0432\u0430-\u0434\u0435-\u0411\u0435\u0445\u0430\u0440"
    ],
    "name:ell_x_preferred":[
        "\u039d\u03ac\u03b2\u03b1 \u03bd\u03c4\u03b5 \u039c\u03c0\u03ad\u03c7\u03b1\u03c1"
    ],
    "name:eng_x_preferred":[
        "Nava de B\u00e9jar"
    ],
    "name:eus_x_preferred":[
        "Nava de B\u00e9jar"
    ],
    "name:fra_x_preferred":[
        "Nava de B\u00e9jar"
    ],
    "name:haw_x_preferred":[
        "Nava de B\u00e9jar"
    ],
    "name:hun_x_preferred":[
        "Nava de B\u00e9jar"
    ],
    "name:ina_x_preferred":[
        "Nava de B\u00e9jar"
    ],
    "name:ita_x_preferred":[
        "Nava de B\u00e9jar"
    ],
    "name:kaz_x_preferred":[
        "\u041d\u0430\u0432\u0430-\u0434\u0435-\u0411\u0435\u0445\u0430\u0440"
    ],
    "name:msa_x_preferred":[
        "Nava de B\u00e9jar"
    ],
    "name:nan_x_preferred":[
        "Nava de B\u00e9jar"
    ],
    "name:nld_x_preferred":[
        "Nava de B\u00e9jar"
    ],
    "name:oci_x_preferred":[
        "Nava de B\u00e9jar"
    ],
    "name:pol_x_preferred":[
        "Nava de B\u00e9jar"
    ],
    "name:por_x_preferred":[
        "Nava de B\u00e9jar"
    ],
    "name:rus_x_preferred":[
        "\u041d\u0430\u0432\u0430-\u0434\u0435-\u0411\u0435\u0445\u0430\u0440"
    ],
    "name:spa_x_preferred":[
        "Nava de B\u00e9jar"
    ],
    "name:swe_x_preferred":[
        "Nava de B\u00e9jar"
    ],
    "name:tat_x_preferred":[
        "\u041d\u0430\u0432\u0430-\u0434\u0435-\u0411\u0435\u0445\u0430\u0440"
    ],
    "name:ukr_x_preferred":[
        "\u041d\u0430\u0432\u0430-\u0434\u0435-\u0411\u0435\u0445\u0430\u0440"
    ],
    "name:vie_x_preferred":[
        "Nava de B\u00e9jar"
    ],
    "name:war_x_preferred":[
        "Nava de B\u00e9jar"
    ],
    "name:zho_x_preferred":[
        "\u7eb3\u74e6\u5fb7\u97e6\u54c8\u5c14"
    ],
    "qs_pg:aaroncc":"ES",
    "qs_pg:gn_country":"ES",
    "qs_pg:gn_fcode":"PPLA3",
    "qs_pg:gn_pop":111,
    "qs_pg:name":"Nava de B\u00e9jar",
    "qs_pg:name_adm0":"Espa\u00f1a",
    "qs_pg:name_adm1":"Castilla y Le\u00f3n",
    "qs_pg:photos_9r":0,
    "qs_pg:photos_sr":0,
    "qs_pg:pop_sr":1,
    "qs_pg:qs_pg_placetype":"locality",
    "qs_pg:qs_pg_placetype_gp":"Town",
    "qs_pg:woe_adm0":23424950,
    "woe:adm0_id":23424950,
    "woe:name_adm0":"Espa\u00f1a",
    "woe:name_adm1":"Castilla y Le\u00f3n",
    "woe:placetype":"Town",
    "wof:name":"Nava de B\u00e9jar",
    "wof:placetype":"locality",
    "wof:population":111
},
  "geometry": {"coordinates":[-5.67856,40.47518],"type":"Point"}
}