{
  "type": "Feature",
  "properties": {
    "iso:country":"ES",
    "wof:name":"Valdezorras",
    "wof:placetype":"neighbourhood"
},
  "geometry": {"coordinates":[-5.92582202055591,37.42899621198455],"type":"Point"}
}