{
  "type": "Feature",
  "properties": {
    "iso:country":"ES",
    "name:eng_x_preferred":[
        "Zurbano"
    ],
    "name:eus_x_preferred":[
        "Zurbao"
    ],
    "name:fra_x_preferred":[
        "Zurbano"
    ],
    "name:nld_x_preferred":[
        "Zurbano"
    ],
    "name:spa_x_preferred":[
        "Zurbano"
    ],
    "name:swe_x_preferred":[
        "Zurbao / Zurbano"
    ],
    "qs_pg:aaroncc":"ES",
    "qs_pg:name":"Zurbano",
    "qs_pg:name_adm0":"Espa\u00f1a",
    "qs_pg:name_adm1":"Euskadi",
    "qs_pg:photos":180,
    "qs_pg:photos_1k":36,
    "qs_pg:photos_9k":1,
    "qs_pg:photos_9r":4,
    "qs_pg:photos_all":180,
    "qs_pg:photos_sr":4,
    "qs_pg:pop_sr":0,
    "qs_pg:qs_pg_placetype":"locality",
    "qs_pg:qs_pg_placetype_gp":"Town",
    "qs_pg:woe_adm0":23424950,
    "woe:adm0_id":23424950,
    "woe:name_adm0":"Espa\u00f1a",
    "woe:name_adm1":"Euskadi",
    "woe:placetype":"Town",
    "wof:name":"Zurbano",
    "wof:placetype":"locality"
},
  "geometry": {"coordinates":[-2.621334,42.865394],"type":"Point"}
}