{
  "type": "Feature",
  "properties": {
    "gn:country":"ES",
    "iso:country":"ES",
    "qs_pg:aaroncc":"ES",
    "qs_pg:gn_country":"ES",
    "qs_pg:name":"Cala Comte",
    "qs_pg:name_adm0":"Espa\u00f1a",
    "qs_pg:name_adm1":"Illes Balears",
    "qs_pg:photos":1334,
    "qs_pg:photos_1k":270,
    "qs_pg:photos_9k":6,
    "qs_pg:photos_9r":7,
    "qs_pg:photos_all":1334,
    "qs_pg:photos_sr":12,
    "qs_pg:pop_sr":0,
    "qs_pg:qs_pg_placetype":"locality",
    "qs_pg:qs_pg_placetype_gp":"Town",
    "qs_pg:woe_adm0":23424950,
    "woe:adm0_id":23424950,
    "woe:name_adm0":"Espa\u00f1a",
    "woe:name_adm1":"Illes Balears",
    "woe:placetype":"Town",
    "wof:name":"Cala Comte",
    "wof:placetype":"locality"
},
  "geometry": {"coordinates":[1.220254,38.962729],"type":"Point"}
}