{
  "type": "Feature",
  "properties": {
    "gn:country":"ES",
    "gn:fcode":"PPLA3",
    "gn:population":182,
    "iso:country":"ES",
    "name:arg_x_preferred":[
        "Algodre"
    ],
    "name:ast_x_preferred":[
        "Algodre"
    ],
    "name:cat_x_preferred":[
        "Algodre"
    ],
    "name:ceb_x_preferred":[
        "Algodre"
    ],
    "name:deu_x_preferred":[
        "Algodre"
    ],
    "name:eng_x_preferred":[
        "Algodre"
    ],
    "name:eus_x_preferred":[
        "Algodre"
    ],
    "name:fas_x_preferred":[
        "\u0627\u0644\u06af\u0627\u062f\u0631"
    ],
    "name:fra_x_preferred":[
        "Algodre"
    ],
    "name:glg_x_preferred":[
        "Algodre"
    ],
    "name:haw_x_preferred":[
        "Algodre"
    ],
    "name:hun_x_preferred":[
        "Algodre"
    ],
    "name:ile_x_preferred":[
        "Algodre"
    ],
    "name:ina_x_preferred":[
        "Algodre"
    ],
    "name:ita_x_preferred":[
        "Algodre"
    ],
    "name:msa_x_preferred":[
        "Algodre"
    ],
    "name:nan_x_preferred":[
        "Algodre"
    ],
    "name:nld_x_preferred":[
        "Algodre"
    ],
    "name:oci_x_preferred":[
        "Algodre"
    ],
    "name:pol_x_preferred":[
        "Algodre"
    ],
    "name:por_x_preferred":[
        "Algodre"
    ],
    "name:rus_x_preferred":[
        "\u0410\u043b\u044c\u0433\u043e\u0434\u0440\u0435"
    ],
    "name:spa_x_preferred":[
        "Algodre"
    ],
    "name:swe_x_preferred":[
        "Algodre"
    ],
    "name:ukr_x_preferred":[
        "\u0410\u043b\u044c\u0433\u043e\u0434\u0440\u0435"
    ],
    "name:uzb_x_preferred":[
        "Algodre"
    ],
    "name:vie_x_preferred":[
        "Algodre"
    ],
    "name:war_x_preferred":[
        "Algodre"
    ],
    "name:zho_x_preferred":[
        "\u963f\u5c14\u6208\u5fb7\u96f7"
    ],
    "qs_pg:aaroncc":"ES",
    "qs_pg:gn_country":"ES",
    "qs_pg:gn_fcode":"PPLA3",
    "qs_pg:gn_pop":182,
    "qs_pg:name":"Algodre",
    "qs_pg:name_adm0":"Espa\u00f1a",
    "qs_pg:name_adm1":"Castilla y Le\u00f3n",
    "qs_pg:photos":39,
    "qs_pg:photos_1k":8,
    "qs_pg:photos_9k":1,
    "qs_pg:photos_9r":2,
    "qs_pg:photos_all":39,
    "qs_pg:photos_sr":2,
    "qs_pg:pop_sr":1,
    "qs_pg:qs_pg_placetype":"locality",
    "qs_pg:qs_pg_placetype_gp":"Town",
    "qs_pg:woe_adm0":23424950,
    "woe:adm0_id":23424950,
    "woe:name_adm0":"Espa\u00f1a",
    "woe:name_adm1":"Castilla y Le\u00f3n",
    "woe:placetype":"Town",
    "wof:name":"Algodre",
    "wof:placetype":"locality",
    "wof:population":182
},
  "geometry": {"coordinates":[-5.60406,41.56631],"type":"Point"}
}