{
  "type": "Feature",
  "properties": {
    "gn:admin1_code":"52",
    "gn:admin2_code":"Z",
    "gn:admin3_code":"50232",
    "gn:asciiname":"Lorbes",
    "gn:country_code":"ES",
    "gn:dem":820,
    "gn:feature_class":"P",
    "gn:feature_code":"PPL",
    "gn:name":"Lorb\u00e9s",
    "gn:population":0,
    "gn:timezone":"Europe/Madrid",
    "iso:country":"ES",
    "wof:name":"Lorbes",
    "wof:placetype":"locality"
},
  "geometry": {"coordinates":[-0.90878,42.67638],"type":"Point"}
}