{
  "type": "Feature",
  "properties": {
    "gn:country":"ES",
    "gn:fcode":"PPLA3",
    "gn:population":0,
    "iso:country":"ES",
    "name:ara_x_preferred":[
        "\u0625\u062a\u064a\u0643\u0633\u0628\u0627\u0631\u0631\u064a\u0627"
    ],
    "name:arg_x_preferred":[
        "Etxebarria"
    ],
    "name:bre_x_preferred":[
        "Etxebarria"
    ],
    "name:cat_x_preferred":[
        "Etxebarria"
    ],
    "name:ceb_x_preferred":[
        "Etxebarria"
    ],
    "name:eus_x_preferred":[
        "Etxebarria"
    ],
    "name:fra_x_preferred":[
        "Etxebarria"
    ],
    "name:glg_x_preferred":[
        "Etxebarria"
    ],
    "name:hun_x_preferred":[
        "Etxebarria"
    ],
    "name:ita_x_preferred":[
        "Etxebarria"
    ],
    "name:lat_x_preferred":[
        "Echevarr\u00eda"
    ],
    "name:msa_x_preferred":[
        "Etxebarria"
    ],
    "name:nld_x_preferred":[
        "Etxebarria"
    ],
    "name:oci_x_preferred":[
        "Etxebarria"
    ],
    "name:pol_x_preferred":[
        "Etxebarria"
    ],
    "name:por_x_preferred":[
        "Echevarr\u00eda"
    ],
    "name:rus_x_preferred":[
        "\u042d\u0447\u0435\u0432\u0430\u0440\u0440\u0438\u044f"
    ],
    "name:sco_x_preferred":[
        "Etxebarria"
    ],
    "name:spa_x_preferred":[
        "Echevarr\u00eda"
    ],
    "name:swe_x_preferred":[
        "Etxebarria"
    ],
    "name:ukr_x_preferred":[
        "\u0415\u0447\u0435\u0431\u0430\u0440\u0440\u0456\u044f"
    ],
    "name:uzb_x_preferred":[
        "Echevarr\u00eda"
    ],
    "name:war_x_preferred":[
        "Etxebarria"
    ],
    "name:zho_x_preferred":[
        "\u57c3\u7279\u514b\u585e\u74e6\u91cc\u4e9a"
    ],
    "qs_pg:aaroncc":"ES",
    "qs_pg:gn_country":"ES",
    "qs_pg:gn_fcode":"PPLA3",
    "qs_pg:gn_pop":0,
    "qs_pg:name":"Etxebarria",
    "qs_pg:name_adm0":"Espa\u00f1a",
    "qs_pg:name_adm1":"Euskadi",
    "qs_pg:photos":8,
    "qs_pg:photos_1k":2,
    "qs_pg:photos_9k":1,
    "qs_pg:photos_9r":1,
    "qs_pg:photos_all":8,
    "qs_pg:photos_sr":1,
    "qs_pg:pop_sr":0,
    "qs_pg:qs_pg_placetype":"locality",
    "qs_pg:qs_pg_placetype_gp":"Town",
    "qs_pg:woe_adm0":23424950,
    "woe:adm0_id":23424950,
    "woe:name_adm0":"Espa\u00f1a",
    "woe:name_adm1":"Euskadi",
    "woe:placetype":"Town",
    "wof:name":"Etxebarria",
    "wof:placetype":"locality"
},
  "geometry": {"coordinates":[-2.47776,43.25414],"type":"Point"}
}