{
  "type": "Feature",
  "properties": {
    "gn:admin1_code":"59",
    "gn:admin2_code":"SS",
    "gn:admin3_code":"20014",
    "gn:asciiname":"Goialdea",
    "gn:country_code":"ES",
    "gn:dem":115,
    "gn:feature_class":"P",
    "gn:feature_code":"PPL",
    "gn:name":"Goialdea",
    "gn:population":0,
    "gn:timezone":"Europe/Madrid",
    "iso:country":"ES",
    "name:eus_x_preferred":[
        "Goialdea"
    ],
    "wof:name":"Goialdea",
    "wof:placetype":"locality"
},
  "geometry": {"coordinates":[-2.0742,43.19917],"type":"Point"}
}