{
  "type": "Feature",
  "properties": {
    "gn:gn_country":"ES",
    "gn:gn_fcode":"PPLA3",
    "gn:gn_pop":197,
    "gn:population":197,
    "iso:country":"ES",
    "name:arg_x_preferred":[
        "Tormantos"
    ],
    "name:cat_x_preferred":[
        "Tormantos"
    ],
    "name:deu_x_preferred":[
        "Tormantos"
    ],
    "name:eng_x_preferred":[
        "Tormantos"
    ],
    "name:eus_x_preferred":[
        "Tormantos"
    ],
    "name:fra_x_preferred":[
        "Tormantos"
    ],
    "name:hun_x_preferred":[
        "Tormantos"
    ],
    "name:hye_x_preferred":[
        "\u054f\u0578\u0580\u0574\u0561\u0576\u057f\u0578\u057d"
    ],
    "name:ita_x_preferred":[
        "Tormantos"
    ],
    "name:kaz_x_preferred":[
        "\u0422\u043e\u0440\u043c\u0430\u043d\u0442\u043e\u0441"
    ],
    "name:msa_x_preferred":[
        "Tormantos"
    ],
    "name:nan_x_preferred":[
        "Tormantos"
    ],
    "name:nld_x_preferred":[
        "Tormantos"
    ],
    "name:oci_x_preferred":[
        "Tormantos"
    ],
    "name:pol_x_preferred":[
        "Tormantos"
    ],
    "name:por_x_preferred":[
        "Tormantos"
    ],
    "name:rup_x_preferred":[
        "Tormantos"
    ],
    "name:rus_x_preferred":[
        "\u0422\u043e\u0440\u043c\u0430\u043d\u0442\u043e\u0441"
    ],
    "name:spa_x_preferred":[
        "Tormantos"
    ],
    "name:swe_x_preferred":[
        "Tormantos"
    ],
    "name:ukr_x_preferred":[
        "\u0422\u043e\u0440\u043c\u0430\u043d\u0442\u043e\u0441"
    ],
    "name:uzb_x_preferred":[
        "Tormantos"
    ],
    "name:vie_x_preferred":[
        "Tormantos"
    ],
    "name:war_x_preferred":[
        "Tormantos"
    ],
    "name:zho_x_preferred":[
        "\u6258\u5c14\u66fc\u6258\u65af"
    ],
    "qs_pg:aaroncc":"ES",
    "qs_pg:gn_country":"ES",
    "qs_pg:gn_fcode":"PPLA3",
    "qs_pg:gn_pop":197,
    "qs_pg:name":"Tormantos",
    "qs_pg:name_adm0":"Espa\u00f1a",
    "qs_pg:name_adm1":"La Rioja",
    "qs_pg:photos_9k":1,
    "qs_pg:photos_9r":3,
    "qs_pg:photos_all":121,
    "qs_pg:photos_sr":0,
    "qs_pg:pop_sr":1,
    "qs_pg:qs_pg_placetype":"locality",
    "qs_pg:qs_pg_placetype_gp":"Town",
    "qs_pg:woe_adm0":23424950,
    "woe:adm0_id":23424950,
    "woe:name_adm0":"Espa\u00f1a",
    "woe:name_adm1":"La Rioja",
    "woe:placetype":"Town",
    "wof:name":"Tormantos",
    "wof:placetype":"locality",
    "wof:population":197
},
  "geometry": {"coordinates":[-3.07446,42.49431],"type":"Point"}
}