{
  "type": "Feature",
  "properties": {
    "iso:country":"ES",
    "name:spa_x_preferred":[
        "Plaza de Toros"
    ],
    "qs:gn_adm0_cc":"ES",
    "qs:gn_local":2512989,
    "qs:gn_nam_loc":"Palma de Mallorca, Palma, Illes Balears, Baleares, ES",
    "qs:gn_namadm1":"07",
    "qs:local_max":12450,
    "qs:local_sum":37995,
    "qs:localhoods":16,
    "qs:name":"Plaza de Toros",
    "qs:name_adm0":"Espa\u00f1a",
    "qs:name_adm1":"Illes Balears",
    "qs:name_adm2":"Baleares",
    "qs:name_lau":"Palma de Mallorca",
    "qs:name_local":"Palma",
    "qs:photo_max":298,
    "qs:photo_sum":1732,
    "qs:placetype":"Suburb",
    "qs:quad_count":69,
    "qs:woe_adm0":23424950,
    "qs:woe_adm1":12578039,
    "qs:woe_adm2":12602088,
    "qs:woe_lau":12687747,
    "qs:woe_local":769293,
    "qs:woe_ver":"7.10.0",
    "wof:lang":[
        "spa"
    ],
    "wof:name":"Plaza de Toros",
    "wof:placetype":"neighbourhood"
},
  "geometry": {"coordinates":[2.659372,39.593324],"type":"Point"}
}