{
  "type": "Feature",
  "properties": {
    "gn:admin1_code":"54",
    "gn:admin2_code":"AB",
    "gn:admin3_code":"02030",
    "gn:asciiname":"Gallego",
    "gn:country_code":"ES",
    "gn:dem":479,
    "gn:feature_class":"P",
    "gn:feature_code":"PPL",
    "gn:name":"Gallego",
    "gn:population":0,
    "gn:timezone":"Europe/Madrid",
    "iso:country":"ES",
    "name:deu_x_preferred":[
        "Gallego"
    ],
    "name:fra_x_preferred":[
        "Gallego"
    ],
    "name:glg_x_preferred":[
        "Gallego"
    ],
    "name:ita_x_preferred":[
        "Gallego"
    ],
    "name:nno_x_preferred":[
        "Gallego"
    ],
    "name:pol_x_preferred":[
        "Gallego"
    ],
    "name:rus_x_preferred":[
        "\u0413\u0430\u043b\u044c\u0435\u0433\u043e"
    ],
    "name:spa_x_preferred":[
        "Gallego"
    ],
    "name:ukr_x_preferred":[
        "\u0413\u0430\u043b\u044c\u0454\u0433\u043e"
    ],
    "name:und_x_variant":[
        "Caser\u00edo Gallego",
        "Gallego"
    ],
    "wof:name":"Gallego",
    "wof:placetype":"locality"
},
  "geometry": {"coordinates":[-2.01042,38.41284],"type":"Point"}
}