{
  "type": "Feature",
  "properties": {
    "gn:country":"ES",
    "gn:fcode":"PPL",
    "gn:population":0,
    "iso:country":"ES",
    "name:rus_x_preferred":[
        "\u041f\u0443\u044d\u0440\u0442\u043e \u041d\u0430\u043e\u0441"
    ],
    "qs_pg:aaroncc":"ES",
    "qs_pg:gn_country":"ES",
    "qs_pg:gn_fcode":"PPL",
    "qs_pg:gn_pop":0,
    "qs_pg:name":"Puerto Naos",
    "qs_pg:name_adm0":"Espa\u00f1a",
    "qs_pg:name_adm1":"Islas Canarias",
    "qs_pg:photos":1014,
    "qs_pg:photos_1k":205,
    "qs_pg:photos_9k":4,
    "qs_pg:photos_9r":7,
    "qs_pg:photos_all":1014,
    "qs_pg:photos_sr":11,
    "qs_pg:pop_sr":0,
    "qs_pg:qs_pg_placetype":"locality",
    "qs_pg:qs_pg_placetype_gp":"Town",
    "qs_pg:woe_adm0":23424950,
    "woe:adm0_id":23424950,
    "woe:name_adm0":"Espa\u00f1a",
    "woe:name_adm1":"Islas Canarias",
    "woe:placetype":"Town",
    "wof:name":"Puerto Naos",
    "wof:placetype":"locality",
    "wof:population":979
},
  "geometry": {"coordinates":[-17.90969,28.58626],"type":"Point"}
}