{
  "type": "Feature",
  "properties": {
    "gn:admin1_code":"34",
    "gn:admin2_code":"O",
    "gn:admin3_code":"33070",
    "gn:asciiname":"El Viso",
    "gn:country_code":"ES",
    "gn:dem":25,
    "gn:feature_class":"P",
    "gn:feature_code":"PPL",
    "gn:name":"El Viso",
    "gn:population":0,
    "gn:timezone":"Europe/Madrid",
    "iso:country":"ES",
    "wof:name":"El Viso",
    "wof:placetype":"locality"
},
  "geometry": {"coordinates":[-6.94293,43.56323],"type":"Point"}
}