{
  "type": "Feature",
  "properties": {
    "gn:admin1_code":"34",
    "gn:admin2_code":"O",
    "gn:admin3_code":"33023",
    "gn:asciiname":"Ferreira",
    "gn:country_code":"ES",
    "gn:dem":130,
    "gn:feature_class":"P",
    "gn:feature_code":"PPL",
    "gn:name":"Ferreira",
    "gn:population":0,
    "gn:timezone":"Europe/Madrid",
    "iso:country":"ES",
    "wof:name":"Ferreira",
    "wof:placetype":"locality"
},
  "geometry": {"coordinates":[-6.82181,43.52664],"type":"Point"}
}