{
  "type": "Feature",
  "properties": {
    "gn:country":"ES",
    "gn:fcode":"PPLA3",
    "gn:population":115,
    "iso:country":"ES",
    "name:ara_x_preferred":[
        "\u0628\u0627\u0631\u0627\u062a\u0634\u064a\u0646 \u062f\u064a\u0644 \u0647\u0648\u064a\u0648"
    ],
    "name:arg_x_preferred":[
        "Barch\u00edn del Hoyo"
    ],
    "name:ast_x_preferred":[
        "Barch\u00edn del Hoyo"
    ],
    "name:cat_x_preferred":[
        "Barch\u00edn del Hoyo"
    ],
    "name:ceb_x_preferred":[
        "Barch\u00edn del Hoyo"
    ],
    "name:eng_x_preferred":[
        "Barch\u00edn del Hoyo"
    ],
    "name:epo_x_preferred":[
        "Barch\u00edn del Hoyo"
    ],
    "name:eus_x_preferred":[
        "Barch\u00edn del Hoyo"
    ],
    "name:fra_x_preferred":[
        "Barch\u00edn del Hoyo"
    ],
    "name:hun_x_preferred":[
        "Barch\u00edn del Hoyo"
    ],
    "name:ita_x_preferred":[
        "Barch\u00edn del Hoyo"
    ],
    "name:kaz_x_preferred":[
        "\u0411\u0430\u0440\u0447\u0438\u043d-\u0434\u0435\u043b\u044c-\u041e\u0439\u043e"
    ],
    "name:msa_x_preferred":[
        "Barch\u00edn del Hoyo"
    ],
    "name:nan_x_preferred":[
        "Barch\u00edn del Hoyo"
    ],
    "name:nld_x_preferred":[
        "Barch\u00edn del Hoyo"
    ],
    "name:oci_x_preferred":[
        "Barch\u00edn del Hoyo"
    ],
    "name:pol_x_preferred":[
        "Barch\u00edn del Hoyo"
    ],
    "name:por_x_preferred":[
        "Barch\u00edn del Hoyo"
    ],
    "name:rus_x_preferred":[
        "\u0411\u0430\u0440\u0447\u0438\u043d-\u0434\u0435\u043b\u044c-\u041e\u0439\u043e"
    ],
    "name:spa_x_preferred":[
        "Barch\u00edn del Hoyo"
    ],
    "name:swe_x_preferred":[
        "Barch\u00edn del Hoyo"
    ],
    "name:ukr_x_preferred":[
        "\u0411\u0430\u0440\u0447\u0438\u043d-\u0434\u0435\u043b\u044c-\u041e\u0439\u043e"
    ],
    "name:vie_x_preferred":[
        "Barch\u00edn del Hoyo"
    ],
    "name:war_x_preferred":[
        "Barch\u00edn del Hoyo"
    ],
    "name:zho_x_preferred":[
        "\u5df4\u5c14\u94a6\u5fb7\u5c14\u5965\u7ea6"
    ],
    "qs_pg:aaroncc":"ES",
    "qs_pg:gn_country":"ES",
    "qs_pg:gn_fcode":"PPLA3",
    "qs_pg:gn_pop":115,
    "qs_pg:name":"Barch\u00edn del Hoyo",
    "qs_pg:name_adm0":"Espa\u00f1a",
    "qs_pg:name_adm1":"Castilla-La Mancha",
    "qs_pg:photos_9k":1,
    "qs_pg:photos_9r":1,
    "qs_pg:photos_all":3,
    "qs_pg:photos_sr":0,
    "qs_pg:pop_sr":1,
    "qs_pg:qs_pg_placetype":"locality",
    "qs_pg:qs_pg_placetype_gp":"Town",
    "qs_pg:woe_adm0":23424950,
    "woe:adm0_id":23424950,
    "woe:name_adm0":"Espa\u00f1a",
    "woe:name_adm1":"Castilla-La Mancha",
    "woe:placetype":"Town",
    "wof:name":"Barch\u00edn del Hoyo",
    "wof:placetype":"locality",
    "wof:population":115
},
  "geometry": {"coordinates":[-2.06667,39.66667],"type":"Point"}
}