{
  "type": "Feature",
  "properties": {
    "iso:country":"ES",
    "name:eng_x_preferred":[
        "El Lagarillo"
    ],
    "name:spa_x_preferred":[
        "El Lagarillo"
    ],
    "wof:name":"El Lagarillo",
    "wof:placetype":"neighbourhood"
},
  "geometry": {"coordinates":[-4.36479334527593,36.73391346900227],"type":"Point"}
}