{
  "type": "Feature",
  "properties": {
    "gn:admin1_code":"58",
    "gn:admin2_code":"LU",
    "gn:admin3_code":"27050",
    "gn:asciiname":"Pena de Folenche",
    "gn:cc2":"ES",
    "gn:country_code":"ES",
    "gn:dem":641,
    "gn:feature_class":"P",
    "gn:feature_code":"PPL",
    "gn:name":"Pena de Folenche",
    "gn:population":0,
    "gn:timezone":"Europe/Madrid",
    "iso:country":"ES",
    "name:und_x_variant":[
        "Pe\u00f1a Folenche"
    ],
    "wof:name":"Pena de Folenche",
    "wof:placetype":"locality"
},
  "geometry": {"coordinates":[-7.28333,42.36667],"type":"Point"}
}