{
  "type": "Feature",
  "properties": {
    "gn:admin1_code":"58",
    "gn:admin2_code":"OR",
    "gn:admin3_code":"32015",
    "gn:asciiname":"Chao de Castro",
    "gn:country_code":"ES",
    "gn:dem":812,
    "gn:feature_class":"P",
    "gn:feature_code":"PPL",
    "gn:name":"Chao de Castro",
    "gn:population":0,
    "gn:timezone":"Europe/Madrid",
    "iso:country":"ES",
    "wof:name":"Chao de Castro",
    "wof:placetype":"locality"
},
  "geometry": {"coordinates":[-7.10335,42.27556],"type":"Point"}
}