{
  "type": "Feature",
  "properties": {
    "iso:country":"ES",
    "name:spa_x_colloquial":[
        "Caserio Las Balsicas"
    ],
    "name:spa_x_preferred":[
        "Las Balsicas"
    ],
    "name:spa_x_variant":[
        "Caser\u00edo Las Balsicas"
    ],
    "qs:a0":"Espa\u00f1a",
    "qs:a1":"*Murcia",
    "qs:a1r":"0Regi\u00f3n de Murcia",
    "qs:adm0":"Espa\u00f1a",
    "qs:la_lc":"*",
    "qs:level":"locality",
    "qs:loc":"Balsicas,Las",
    "qs:loc_alt":"Balsicas,Las",
    "qs:pop":0,
    "qs:type":"buffered point",
    "wof:name":"Balsicas,Las",
    "wof:placetype":"locality"
},
  "geometry": {"coordinates":[-1.250948,37.598538],"type":"Point"}
}