{
  "type": "Feature",
  "properties": {
    "gn:admin1_code":"59",
    "gn:admin2_code":"BI",
    "gn:admin3_code":"48042",
    "gn:asciiname":"Zaldu",
    "gn:country_code":"ES",
    "gn:dem":97,
    "gn:feature_class":"P",
    "gn:feature_code":"PPL",
    "gn:name":"Zaldu",
    "gn:population":0,
    "gn:timezone":"Europe/Madrid",
    "iso:country":"ES",
    "name:eus_x_preferred":[
        "Zaldu"
    ],
    "name:spa_x_preferred":[
        "Llano de Zaldu"
    ],
    "wof:name":"Zaldu",
    "wof:placetype":"locality"
},
  "geometry": {"coordinates":[-3.03118,43.17727],"type":"Point"}
}