{
  "type": "Feature",
  "properties": {
    "gn:admin1_code":"58",
    "gn:admin2_code":"OR",
    "gn:admin3_code":"32059",
    "gn:asciiname":"Souto",
    "gn:cc2":"ES",
    "gn:country_code":"ES",
    "gn:dem":372,
    "gn:feature_class":"P",
    "gn:feature_code":"PPL",
    "gn:name":"Souto",
    "gn:population":0,
    "gn:timezone":"Europe/Madrid",
    "iso:country":"ES",
    "name:ceb_x_preferred":[
        "Souto"
    ],
    "name:deu_x_preferred":[
        "Souto"
    ],
    "name:fra_x_preferred":[
        "Souto"
    ],
    "name:glg_x_preferred":[
        "Souto"
    ],
    "name:nld_x_preferred":[
        "Souto"
    ],
    "name:por_x_preferred":[
        "Souto"
    ],
    "name:rus_x_preferred":[
        "\u0421\u043e\u0442\u0443"
    ],
    "name:spa_x_preferred":[
        "Souto"
    ],
    "name:tur_x_preferred":[
        "Souto"
    ],
    "name:ukr_x_preferred":[
        "\u0421\u043e\u0442\u0443"
    ],
    "name:und_x_variant":[
        "San Crist\u00f3bal"
    ],
    "wof:name":"Souto",
    "wof:placetype":"locality"
},
  "geometry": {"coordinates":[-7.75,42.48333],"type":"Point"}
}