{
  "type": "Feature",
  "properties": {
    "gn:admin1_code":"29",
    "gn:admin2_code":"M",
    "gn:admin3_code":"28901",
    "gn:asciiname":"Las Navas de Buitrago",
    "gn:country_code":"ES",
    "gn:dem":994,
    "gn:feature_class":"P",
    "gn:feature_code":"PPL",
    "gn:name":"Las Navas de Buitrago",
    "gn:population":0,
    "gn:timezone":"Europe/Madrid",
    "iso:country":"ES",
    "wof:name":"Las Navas de Buitrago",
    "wof:placetype":"locality"
},
  "geometry": {"coordinates":[-3.59454,40.93365],"type":"Point"}
}