{
  "type": "Feature",
  "properties": {
    "gn:admin1_code":"58",
    "gn:admin2_code":"C",
    "gn:admin3_code":"15032",
    "gn:asciiname":"Curtis",
    "gn:cc2":"ES",
    "gn:country_code":"ES",
    "gn:dem":534,
    "gn:feature_class":"P",
    "gn:feature_code":"PPLA3",
    "gn:name":"Curtis",
    "gn:population":0,
    "gn:timezone":"Europe/Madrid",
    "iso:country":"ES",
    "name:und_x_variant":[
        "Santa Eulalia",
        "Curtis"
    ],
    "wof:name":"Curtis",
    "wof:placetype":"locality"
},
  "geometry": {"coordinates":[-8.14818,43.12374000000001],"type":"Point"}
}