{
  "type": "Feature",
  "properties": {
    "gn:admin1_code":"58",
    "gn:admin2_code":"C",
    "gn:admin3_code":"15057",
    "gn:asciiname":"Agrelo",
    "gn:cc2":"ES",
    "gn:country_code":"ES",
    "gn:dem":59,
    "gn:feature_class":"P",
    "gn:feature_code":"PPL",
    "gn:name":"Agrelo",
    "gn:population":0,
    "gn:timezone":"Europe/Madrid",
    "iso:country":"ES",
    "name:und_x_variant":[
        "Agrela",
        "Agrelo"
    ],
    "wof:name":"Agrelo",
    "wof:placetype":"locality"
},
  "geometry": {"coordinates":[-8.88333,42.81667],"type":"Point"}
}