{
  "type": "Feature",
  "properties": {
    "gn:gn_country":"ES",
    "gn:gn_fcode":"PPL",
    "gn:gn_pop":0,
    "gn:population":150,
    "iso:country":"ES",
    "name:cat_x_preferred":[
        "La Matilla"
    ],
    "name:ceb_x_preferred":[
        "La Matilla"
    ],
    "name:eus_x_preferred":[
        "La Matilla"
    ],
    "name:fra_x_preferred":[
        "La Matilla"
    ],
    "name:hun_x_preferred":[
        "La Matilla"
    ],
    "name:ina_x_preferred":[
        "La Matilla"
    ],
    "name:ita_x_preferred":[
        "La Matilla"
    ],
    "name:msa_x_preferred":[
        "La Matilla"
    ],
    "name:nld_x_preferred":[
        "La Matilla"
    ],
    "name:oci_x_preferred":[
        "La Matilla"
    ],
    "name:pol_x_preferred":[
        "La Matilla"
    ],
    "name:por_x_preferred":[
        "La Matilla"
    ],
    "name:rus_x_preferred":[
        "\u041b\u0430-\u041c\u0430\u0442\u0438\u043b\u044c\u044f"
    ],
    "name:spa_x_preferred":[
        "La Matilla"
    ],
    "name:ukr_x_preferred":[
        "\u041b\u0430-\u041c\u0430\u0442\u0456\u043b\u044c\u044f"
    ],
    "name:vie_x_preferred":[
        "La Matilla"
    ],
    "name:war_x_preferred":[
        "La Matilla"
    ],
    "name:zho_x_preferred":[
        "\u62c9\u9a6c\u8482\u5229\u4e9a"
    ],
    "qs_pg:aaroncc":"ES",
    "qs_pg:gn_country":"ES",
    "qs_pg:gn_fcode":"PPL",
    "qs_pg:gn_pop":0,
    "qs_pg:name":"La Matilla",
    "qs_pg:name_adm0":"Espa\u00f1a",
    "qs_pg:name_adm1":"Islas Canarias",
    "qs_pg:photos":78,
    "qs_pg:photos_1k":16,
    "qs_pg:photos_9k":1,
    "qs_pg:photos_9r":3,
    "qs_pg:photos_all":78,
    "qs_pg:photos_sr":3,
    "qs_pg:pop_sr":0,
    "qs_pg:qs_pg_placetype":"locality",
    "qs_pg:qs_pg_placetype_gp":"Town",
    "qs_pg:woe_adm0":23424950,
    "woe:adm0_id":23424950,
    "woe:name_adm0":"Espa\u00f1a",
    "woe:name_adm1":"Islas Canarias",
    "woe:placetype":"Town",
    "wof:name":"La Matilla",
    "wof:placetype":"locality",
    "wof:population":150
},
  "geometry": {"coordinates":[-13.95497,28.55686],"type":"Point"}
}