{
  "type": "Feature",
  "properties": {
    "gn:admin1_code":"58",
    "gn:admin2_code":"LU",
    "gn:admin3_code":"27020",
    "gn:asciiname":"Devesa",
    "gn:cc2":"ES",
    "gn:country_code":"ES",
    "gn:dem":470,
    "gn:feature_class":"P",
    "gn:feature_code":"PPL",
    "gn:name":"Devesa",
    "gn:population":0,
    "gn:timezone":"Europe/Madrid",
    "iso:country":"ES",
    "name:und_x_variant":[
        "Santa Eulalia",
        "Debesa",
        "Devesa"
    ],
    "wof:name":"Devesa",
    "wof:placetype":"locality"
},
  "geometry": {"coordinates":[-7.75,43.03333],"type":"Point"}
}