{
  "type": "Feature",
  "properties": {
    "gn:country":"ES",
    "gn:fcode":"PPL",
    "gn:population":0,
    "iso:country":"ES",
    "name:ceb_x_preferred":[
        "El Cuervo"
    ],
    "name:deu_x_preferred":[
        "El Cuervo"
    ],
    "name:spa_x_preferred":[
        "El cuervo"
    ],
    "name:swe_x_preferred":[
        "El Cuervo"
    ],
    "name:und_x_variant":[
        "Caser\u00edo El Cuervo"
    ],
    "qs_pg:aaroncc":"ES",
    "qs_pg:gn_country":"ES",
    "qs_pg:gn_fcode":"PPL",
    "qs_pg:gn_pop":0,
    "qs_pg:name":"El Cuervo",
    "qs_pg:name_adm0":"Espa\u00f1a",
    "qs_pg:name_adm1":"Andaluc\u00eda",
    "qs_pg:photos_9k":1,
    "qs_pg:photos_9r":1,
    "qs_pg:photos_all":1,
    "qs_pg:photos_sr":0,
    "qs_pg:pop_sr":0,
    "qs_pg:qs_pg_placetype":"locality",
    "qs_pg:qs_pg_placetype_gp":"Town",
    "qs_pg:woe_adm0":23424950,
    "woe:adm0_id":23424950,
    "woe:name_adm0":"Espa\u00f1a",
    "woe:name_adm1":"Andaluc\u00eda",
    "woe:placetype":"Town",
    "wof:name":"El Cuervo",
    "wof:placetype":"locality"
},
  "geometry": {"coordinates":[-6.03785,36.85298],"type":"Point"}
}