{
  "type": "Feature",
  "properties": {
    "gn:admin1_code":"55",
    "gn:admin2_code":"BU",
    "gn:admin3_code":"09902",
    "gn:asciiname":"Minon",
    "gn:country_code":"ES",
    "gn:dem":862,
    "gn:feature_class":"P",
    "gn:feature_code":"PPL",
    "gn:name":"Mi\u00f1\u00f3n",
    "gn:population":0,
    "gn:timezone":"Europe/Madrid",
    "iso:country":"ES",
    "name:ara_x_preferred":[
        "\u0645\u064a\u0646\u0648\u0646"
    ],
    "name:mal_x_preferred":[
        "\u0d2e\u0d3f\u0d28\u0d4b\u0d7a"
    ],
    "name:und_x_variant":[
        "Mi\u00f1\u00f3n"
    ],
    "wof:name":"Minon",
    "wof:placetype":"locality"
},
  "geometry": {"coordinates":[-3.79794,42.46404],"type":"Point"}
}