{
  "type": "Feature",
  "properties": {
    "gn:admin1_code":"59",
    "gn:admin2_code":"SS",
    "gn:admin3_code":"20069",
    "gn:asciiname":"Santiago",
    "gn:country_code":"ES",
    "gn:dem":117,
    "gn:feature_class":"P",
    "gn:feature_code":"PPL",
    "gn:name":"Santiago",
    "gn:population":0,
    "gn:timezone":"Europe/Madrid",
    "iso:country":"ES",
    "name:eus_x_preferred":[
        "Santiago"
    ],
    "wof:name":"Santiago",
    "wof:placetype":"locality"
},
  "geometry": {"coordinates":[-1.94448,43.27831],"type":"Point"}
}