{
  "type": "Feature",
  "properties": {
    "gn:admin1_code":"34",
    "gn:admin2_code":"O",
    "gn:admin3_code":"33007",
    "gn:asciiname":"Coba",
    "gn:country_code":"ES",
    "gn:dem":475,
    "gn:feature_class":"P",
    "gn:feature_code":"PPL",
    "gn:name":"Coba",
    "gn:population":0,
    "gn:timezone":"Europe/Madrid",
    "iso:country":"ES",
    "name:und_x_variant":[
        "Lebredo",
        "Coba"
    ],
    "wof:name":"Coba",
    "wof:placetype":"locality"
},
  "geometry": {"coordinates":[-6.80268,43.46513],"type":"Point"}
}