{
  "type": "Feature",
  "properties": {
    "gn:admin1_code":"34",
    "gn:admin2_code":"O",
    "gn:admin3_code":"33007",
    "gn:asciiname":"Coba",
    "gn:country_code":"ES",
    "gn:dem":475,
    "gn:feature_class":"P",
    "gn:feature_code":"PPL",
    "gn:name":"Coba",
    "gn:population":0,
    "gn:timezone":"Europe/Madrid",
    "iso:country":"ES",
    "name:ara_x_preferred":[
        "\u0643\u0648\u0628\u0627"
    ],
    "name:bel_x_preferred":[
        "\u041a\u0430\u0431\u0430"
    ],
    "name:cat_x_preferred":[
        "Cob\u00e1"
    ],
    "name:deu_x_preferred":[
        "Cob\u00e1"
    ],
    "name:epo_x_preferred":[
        "Coba"
    ],
    "name:fra_x_preferred":[
        "Cob\u00e1"
    ],
    "name:hun_x_preferred":[
        "Cob\u00e1"
    ],
    "name:ind_x_preferred":[
        "Coba"
    ],
    "name:ita_x_preferred":[
        "Cob\u00e1"
    ],
    "name:jpn_x_preferred":[
        "\u30b3\u30d0\u30fc"
    ],
    "name:kat_x_preferred":[
        "\u10d9\u10dd\u10d1\u10d0"
    ],
    "name:lit_x_preferred":[
        "Koba"
    ],
    "name:mkd_x_preferred":[
        "\u041a\u043e\u0431\u0430"
    ],
    "name:nld_x_preferred":[
        "Cob\u00e1"
    ],
    "name:nor_x_preferred":[
        "Cob\u00e1"
    ],
    "name:pol_x_preferred":[
        "Cob\u00e1"
    ],
    "name:por_x_preferred":[
        "Cob\u00e1"
    ],
    "name:rus_x_preferred":[
        "\u041a\u043e\u0431\u0430"
    ],
    "name:spa_x_preferred":[
        "Cob\u00e1"
    ],
    "name:srp_x_preferred":[
        "\u041a\u043e\u0431\u0430"
    ],
    "name:swe_x_preferred":[
        "Coba"
    ],
    "name:ukr_x_preferred":[
        "\u041a\u043e\u0431\u0430"
    ],
    "name:und_x_variant":[
        "Lebredo"
    ],
    "wof:name":"Coba",
    "wof:placetype":"locality"
},
  "geometry": {"coordinates":[-6.80268,43.46513],"type":"Point"}
}