{
  "type": "Feature",
  "properties": {
    "gn:admin1_code":"55",
    "gn:admin2_code":"AV",
    "gn:admin3_code":"05131",
    "gn:asciiname":"Miruena",
    "gn:country_code":"ES",
    "gn:dem":1132,
    "gn:feature_class":"P",
    "gn:feature_code":"PPL",
    "gn:name":"Mirue\u00f1a",
    "gn:population":0,
    "gn:timezone":"Europe/Madrid",
    "iso:country":"ES",
    "wof:name":"Miruena",
    "wof:placetype":"locality"
},
  "geometry": {"coordinates":[-5.09111,40.73724],"type":"Point"}
}