{
  "type": "Feature",
  "properties": {
    "gn:admin1_code":"55",
    "gn:admin2_code":"SG",
    "gn:admin3_code":"40039",
    "gn:asciiname":"Fuentemizarra",
    "gn:country_code":"ES",
    "gn:dem":993,
    "gn:feature_class":"P",
    "gn:feature_code":"PPL",
    "gn:name":"Fuentemizarra",
    "gn:population":0,
    "gn:timezone":"Europe/Madrid",
    "iso:country":"ES",
    "wof:name":"Fuentemizarra",
    "wof:placetype":"locality"
},
  "geometry": {"coordinates":[-3.56194,41.45816],"type":"Point"}
}