{
  "type": "Feature",
  "properties": {
    "gn:admin1_code":"54",
    "gn:admin2_code":"AB",
    "gn:admin3_code":"02059",
    "gn:asciiname":"Batanes",
    "gn:country_code":"ES",
    "gn:dem":1066,
    "gn:feature_class":"P",
    "gn:feature_code":"PPL",
    "gn:name":"Batanes",
    "gn:population":0,
    "gn:timezone":"Europe/Madrid",
    "iso:country":"ES",
    "name:und_x_variant":[
        "Caser\u00edo Batanes",
        "Batanes"
    ],
    "wof:name":"Batanes",
    "wof:placetype":"locality"
},
  "geometry": {"coordinates":[-2.23704,38.69117],"type":"Point"}
}