{
  "type": "Feature",
  "properties": {
    "gn:admin1_code":"54",
    "gn:admin2_code":"AB",
    "gn:admin3_code":"02065",
    "gn:asciiname":"La Zarza",
    "gn:country_code":"ES",
    "gn:dem":900,
    "gn:feature_class":"P",
    "gn:feature_code":"PPL",
    "gn:name":"La Zarza",
    "gn:population":0,
    "gn:timezone":"Europe/Madrid",
    "iso:country":"ES",
    "wof:name":"La Zarza",
    "wof:placetype":"locality"
},
  "geometry": {"coordinates":[-2.06833,38.78215],"type":"Point"}
}