{
  "type": "Feature",
  "properties": {
    "gn:admin1_code":"58",
    "gn:admin2_code":"LU",
    "gn:admin3_code":"27028",
    "gn:asciiname":"Piugos",
    "gn:country_code":"ES",
    "gn:dem":453,
    "gn:feature_class":"P",
    "gn:feature_code":"PPL",
    "gn:name":"Piugos",
    "gn:population":0,
    "gn:timezone":"Europe/Madrid",
    "iso:country":"ES",
    "name:und_x_variant":[
        "Puigos",
        "Piugos"
    ],
    "wof:name":"Piugos",
    "wof:placetype":"locality"
},
  "geometry": {"coordinates":[-7.57076,42.98855],"type":"Point"}
}