{
  "type": "Feature",
  "properties": {
    "gn:gn_country":"ES",
    "gn:gn_fcode":"PPL",
    "gn:gn_pop":92,
    "gn:population":92,
    "iso:country":"ES",
    "name:arg_x_preferred":[
        "Barbarin"
    ],
    "name:bre_x_preferred":[
        "Barbarin"
    ],
    "name:bul_x_preferred":[
        "\u0411\u0430\u0440\u0431\u0430\u0440\u0438\u043d"
    ],
    "name:cat_x_preferred":[
        "Barbarin"
    ],
    "name:eng_x_preferred":[
        "Barbarin"
    ],
    "name:eus_x_preferred":[
        "Barbarin"
    ],
    "name:fra_x_preferred":[
        "Barbarin"
    ],
    "name:hun_x_preferred":[
        "Barbarin"
    ],
    "name:ita_x_preferred":[
        "Barbarin"
    ],
    "name:jpn_x_preferred":[
        "\u30d0\u30eb\u30d0\u30ea\u30f3"
    ],
    "name:msa_x_preferred":[
        "Barbarin"
    ],
    "name:nan_x_preferred":[
        "Barbarin"
    ],
    "name:nld_x_preferred":[
        "Barbarin"
    ],
    "name:oci_x_preferred":[
        "Barbarin"
    ],
    "name:pol_x_preferred":[
        "Barbarin"
    ],
    "name:por_x_preferred":[
        "Barbarin"
    ],
    "name:rup_x_preferred":[
        "Barbarin"
    ],
    "name:rus_x_preferred":[
        "\u0411\u0430\u0440\u0431\u0430\u0440\u0438\u043d"
    ],
    "name:spa_x_preferred":[
        "Barbarin"
    ],
    "name:swe_x_preferred":[
        "Barbarin"
    ],
    "name:ukr_x_preferred":[
        "\u0411\u0430\u0440\u0431\u0430\u0440\u0456\u043d"
    ],
    "name:unk_x_variant":[
        "Barbar\u00edn"
    ],
    "name:vie_x_preferred":[
        "Barbarin"
    ],
    "name:war_x_preferred":[
        "Barbarin"
    ],
    "name:zho_x_preferred":[
        "\u5df4\u5c14\u74e6\u6797"
    ],
    "qs_pg:aaroncc":"ES",
    "qs_pg:gn_country":"ES",
    "qs_pg:gn_fcode":"PPL",
    "qs_pg:gn_pop":92,
    "qs_pg:name":"Barbarin",
    "qs_pg:name_adm0":"Espa\u00f1a",
    "qs_pg:name_adm1":"Comunidad Foral de Navarra",
    "qs_pg:photos_9r":0,
    "qs_pg:photos_sr":0,
    "qs_pg:pop_sr":1,
    "qs_pg:qs_pg_placetype":"locality",
    "qs_pg:qs_pg_placetype_gp":"Town",
    "qs_pg:woe_adm0":23424950,
    "woe:adm0_id":23424950,
    "woe:name_adm0":"Espa\u00f1a",
    "woe:name_adm1":"Comunidad Foral de Navarra",
    "woe:placetype":"Town",
    "wof:name":"Barbarin",
    "wof:placetype":"locality",
    "wof:population":92
},
  "geometry": {"coordinates":[-2.10203,42.60197],"type":"Point"}
}