{
  "type": "Feature",
  "properties": {
    "gn:admin1_code":"55",
    "gn:admin2_code":"VA",
    "gn:admin3_code":"47077",
    "gn:asciiname":"Granja de San Mames",
    "gn:country_code":"ES",
    "gn:dem":839,
    "gn:feature_class":"P",
    "gn:feature_code":"PPL",
    "gn:name":"Granja de San Mam\u00e9s",
    "gn:population":0,
    "gn:timezone":"Europe/Madrid",
    "iso:country":"ES",
    "name:und_x_variant":[
        "Caser\u00edo de Granja de San Mam\u00e9s",
        "Granja de San Mam\u00e9s"
    ],
    "wof:name":"Granja de San Mames",
    "wof:placetype":"locality"
},
  "geometry": {"coordinates":[-4.25529,41.54927],"type":"Point"}
}