{
  "type": "Feature",
  "properties": {
    "gn:admin1_code":"34",
    "gn:admin2_code":"O",
    "gn:admin3_code":"33068",
    "gn:asciiname":"Gua",
    "gn:country_code":"ES",
    "gn:dem":884,
    "gn:feature_class":"P",
    "gn:feature_code":"PPL",
    "gn:name":"G\u00faa",
    "gn:population":0,
    "gn:timezone":"Europe/Madrid",
    "iso:country":"ES",
    "name:spa_x_preferred":[
        "G\u00faa"
    ],
    "name:und_x_variant":[
        "G\u00faa"
    ],
    "wof:name":"Gua",
    "wof:placetype":"locality"
},
  "geometry": {"coordinates":[-6.26068,43.08038],"type":"Point"}
}